{
  "type": "Feature",
  "properties": {
    "gn:admin1_code":"11.0",
    "gn:admin2_code":"2006.0",
    "gn:asciiname":"Maqrudah",
    "gn:country_code":"YE",
    "gn:dem":1256,
    "gn:feature_class":"P",
    "gn:feature_code":"PPL",
    "gn:name":"Maqr\u016b\u1e11ah",
    "gn:population":0,
    "gn:timezone":"Asia/Aden",
    "iso:country":"YE",
    "name:und_x_variant":[
        "Maqr\u016b\u1e11ah"
    ],
    "wof:name":"Maqrudah",
    "wof:placetype":"locality"
},
  "geometry": {"coordinates":[43.73962,14.33071],"type":"Point"}
}