{
  "type": "Feature",
  "properties": {
    "gn:country":"YE",
    "gn:fcode":"PPL",
    "gn:pop":7,
    "iso:country":"YE",
    "name:ara_x_preferred":[
        "\u0646\u064a\u062f \u0627\u0644\u063a\u0645\u064a\u0631"
    ],
    "name:eng_x_preferred":[
        "Nayd Al Ghamir"
    ],
    "name:eng_x_variant":[
        "Al Muwayrah"
    ],
    "qs:name":"Nayd al Gham\u012br",
    "qs:photos_9r":0,
    "qs:photos_sr":0,
    "qs:pop_sr":"1",
    "wof:name":"Nayd al Gham\u012br",
    "wof:placetype":"locality",
    "wof:population":7
},
  "geometry": {"coordinates":[43.36774,17.11256],"type":"Point"}
}