{
  "type": "Feature",
  "properties": {
    "gn:admin1_code":"23.0",
    "gn:admin2_code":"1109.0",
    "gn:asciiname":"Hadid",
    "gn:country_code":"YE",
    "gn:dem":1914,
    "gn:feature_class":"P",
    "gn:feature_code":"PPL",
    "gn:name":"\u1e28ad\u012bd",
    "gn:population":0,
    "gn:timezone":"Asia/Aden",
    "iso:country":"YE",
    "name:ara_x_preferred":[
        "\u062d\u062f\u064a\u062f"
    ],
    "name:und_x_variant":[
        "\u1e28ad\u012bd"
    ],
    "wof:name":"Hadid",
    "wof:placetype":"locality"
},
  "geometry": {"coordinates":[43.98392,14.0234],"type":"Point"}
}