{
  "type": "Feature",
  "properties": {
    "gn:admin1_code":"20.0",
    "gn:asciiname":"Mi`mar",
    "gn:country_code":"YE",
    "gn:dem":2435,
    "gn:feature_class":"P",
    "gn:feature_code":"PPL",
    "gn:name":"Mi\u2018m\u0101r",
    "gn:population":0,
    "gn:timezone":"Asia/Aden",
    "iso:country":"YE",
    "name:ara_x_preferred":[
        "\u0645\u0639\u0645\u0627\u0631"
    ],
    "name:und_x_variant":[
        "Mi\u2018m\u0101r"
    ],
    "wof:name":"Mi`mar",
    "wof:placetype":"locality"
},
  "geometry": {"coordinates":[44.46164,14.32753],"type":"Point"}
}