{
  "type": "Feature",
  "properties": {
    "gn:admin1_code":"11.0",
    "gn:admin2_code":"2004.0",
    "gn:asciiname":"Bani `Ufayr",
    "gn:country_code":"YE",
    "gn:dem":2340,
    "gn:feature_class":"P",
    "gn:feature_code":"PPL",
    "gn:name":"Ban\u012b \u2018Ufayr",
    "gn:population":0,
    "gn:timezone":"Asia/Aden",
    "iso:country":"YE",
    "name:und_x_variant":[
        "Ban\u012b \u2018Ufayr"
    ],
    "wof:name":"Bani `Ufayr",
    "wof:placetype":"locality"
},
  "geometry": {"coordinates":[44.11667,14.53333],"type":"Point"}
}