{
  "type": "Feature",
  "properties": {
    "gn:country":"YE",
    "gn:fcode":"PPLL",
    "gn:population":12,
    "iso:country":"YE",
    "name:ara_x_preferred":[
        "\u0627\u0644\u062d\u0638\u064a\u0631\u0629"
    ],
    "name:eng_x_preferred":[
        "Al Huzayrah"
    ],
    "name:nno_x_preferred":[
        "Ad Dahrah"
    ],
    "qs:name":"Al \u1e28uz\u0327ayrah",
    "qs:photos_9r":0,
    "qs:photos_sr":0,
    "qs:pop_sr":"1",
    "wof:name":"Al \u1e28uz\u0327ayrah",
    "wof:placetype":"locality",
    "wof:population":12
},
  "geometry": {"coordinates":[43.78577,17.19751],"type":"Point"}
}