{
  "type": "Feature",
  "properties": {
    "gn:country":"YE",
    "gn:fcode":"PPLX",
    "gn:pop":56,
    "iso:country":"YE",
    "name:ara_x_preferred":[
        "\u062d\u0627\u0631\u0629 \u0627\u0644\u0633\u0648\u0642 \u0627\u0644\u062c\u062f\u064a\u062f"
    ],
    "name:ara_x_variant":[
        "\u062d\u0627\u0631\u0629 \u0627\u0644\u0633\u0648\u0642"
    ],
    "name:unk_x_variant":[
        "\u1e28\u0101rat as S\u016bq"
    ],
    "qs:name":"\u1e28\u0101rat as S\u016bq al Jad\u012bd",
    "qs:photos_9r":0,
    "qs:photos_sr":0,
    "qs:pop_sr":"1",
    "wof:name":"\u1e28\u0101rat as S\u016bq al Jad\u012bd",
    "wof:placetype":"neighbourhood",
    "wof:population":56
},
  "geometry": {"coordinates":[44.29064,16.5534],"type":"Point"}
}