{
  "type": "Feature",
  "properties": {
    "gn:admin1_code":"14.0",
    "gn:admin2_code":"2607.0",
    "gn:asciiname":"Ya`arah",
    "gn:country_code":"YE",
    "gn:dem":1209,
    "gn:feature_class":"P",
    "gn:feature_code":"PPL",
    "gn:name":"Ya\u2018arah",
    "gn:population":0,
    "gn:timezone":"Asia/Aden",
    "iso:country":"YE",
    "name:ara_x_preferred":[
        "\u064a\u0639\u0631\u0629"
    ],
    "name:und_x_variant":[
        "Ya\u2018arah"
    ],
    "wof:name":"Ya`arah",
    "wof:placetype":"locality"
},
  "geometry": {"coordinates":[45.24344,15.17166],"type":"Point"}
}