{
  "type": "Feature",
  "properties": {
    "gn:admin1_code":"23.0",
    "gn:admin2_code":"1120.0",
    "gn:asciiname":"Al Masha`ibah",
    "gn:country_code":"YE",
    "gn:dem":1908,
    "gn:feature_class":"P",
    "gn:feature_code":"PPL",
    "gn:name":"Al Mash\u0101\u2018ibah",
    "gn:population":0,
    "gn:timezone":"Asia/Aden",
    "iso:country":"YE",
    "name:und_x_variant":[
        "Al Mush\u0101\u2018ibah",
        "Al Mash\u0101\u2018ibah"
    ],
    "wof:name":"Al Masha`ibah",
    "wof:placetype":"locality"
},
  "geometry": {"coordinates":[44.19832,13.93308],"type":"Point"}
}