{
  "type": "Feature",
  "properties": {
    "gn:country":"YE",
    "gn:fcode":"PPL",
    "gn:pop":4,
    "iso:country":"YE",
    "name:ara_x_preferred":[
        "\u0627\u0644 \u062c\u062f\u064a\u0644\u0627\u0646"
    ],
    "name:eng_x_preferred":[
        "Al Judaylan"
    ],
    "name:eng_x_variant":[
        "Al Mawdiqah"
    ],
    "qs:name":"\u0100l Judayl\u0101n",
    "qs:photos_9r":0,
    "qs:photos_sr":0,
    "qs:pop_sr":"1",
    "wof:name":"\u0100l Judayl\u0101n",
    "wof:placetype":"locality",
    "wof:population":4
},
  "geometry": {"coordinates":[45.40812,15.4297],"type":"Point"}
}