{
  "type": "Feature",
  "properties": {
    "gn:admin1_code":"22.0",
    "gn:admin2_code":"1701.0",
    "gn:asciiname":"Bay`ar",
    "gn:country_code":"YE",
    "gn:dem":416,
    "gn:feature_class":"P",
    "gn:feature_code":"PPL",
    "gn:name":"Bay\u2018ar",
    "gn:population":0,
    "gn:timezone":"Asia/Aden",
    "iso:country":"YE",
    "name:ara_x_preferred":[
        "\u0628\u064a\u0639\u0631"
    ],
    "name:und_x_variant":[
        "Bay\u2018ar"
    ],
    "wof:name":"Bay`ar",
    "wof:placetype":"locality"
},
  "geometry": {"coordinates":[43.28754,16.5599],"type":"Point"}
}