{
  "type": "Feature",
  "properties": {
    "gn:admin1_code":"22.0",
    "gn:admin2_code":"1724.0",
    "gn:asciiname":"Az Zahir",
    "gn:cc2":"YE",
    "gn:country_code":"YE",
    "gn:dem":351,
    "gn:feature_class":"P",
    "gn:feature_code":"PPL",
    "gn:name":"Az\u0327 Z\u0327\u0101hir",
    "gn:population":0,
    "gn:timezone":"Asia/Aden",
    "iso:country":"YE",
    "name:ara_x_preferred":[
        "Az\u0327 Z\u0327\u0101hir"
    ],
    "name:und_x_variant":[
        "Al Drahir"
    ],
    "wof:name":"Az Zahir",
    "wof:placetype":"locality"
},
  "geometry": {"coordinates":[43.31667,15.53333],"type":"Point"}
}