{
  "type": "Feature",
  "properties": {
    "gn:admin1_code":"10.0",
    "gn:admin2_code":"2709.0",
    "gn:asciiname":"Al Qal`ah",
    "gn:country_code":"YE",
    "gn:dem":1809,
    "gn:feature_class":"P",
    "gn:feature_code":"PPL",
    "gn:name":"Al Qal\u2018ah",
    "gn:population":0,
    "gn:timezone":"Asia/Aden",
    "iso:country":"YE",
    "name:und_x_variant":[
        "Al Qal\u2018ah"
    ],
    "wof:name":"Al Qal`ah",
    "wof:placetype":"locality"
},
  "geometry": {"coordinates":[43.52528,15.46115],"type":"Point"}
}