{
  "type": "Feature",
  "properties": {
    "gn:country":"YE",
    "gn:fcode":"PPL",
    "gn:population":3,
    "iso:country":"YE",
    "name:ara_x_preferred":[
        "\u0633\u0631 \u0639\u0637\u064a\u0641\u0629"
    ],
    "name:eng_x_preferred":[
        "Sirr 'Atifah"
    ],
    "name:eng_x_variant":[
        "Al Jul\u0101\u1e29\u012bt"
    ],
    "name:und_x_variant":[
        "Sirr \u2018U\u0163ayfah"
    ],
    "qs:name":"Sirr \u2018A\u0163\u012bfah",
    "qs:photos_9r":0,
    "qs:photos_sr":0,
    "qs:pop_sr":"1",
    "wof:name":"Sirr \u2018A\u0163\u012bfah",
    "wof:placetype":"locality",
    "wof:population":3
},
  "geometry": {"coordinates":[43.29866,16.67106],"type":"Point"}
}