{
  "type": "Feature",
  "properties": {
    "gn:admin1_code":"11.0",
    "gn:admin2_code":"2006.0",
    "gn:asciiname":"Al Magharib",
    "gn:country_code":"YE",
    "gn:dem":1611,
    "gn:feature_class":"P",
    "gn:feature_code":"PPL",
    "gn:name":"Al Magh\u0101rib",
    "gn:population":0,
    "gn:timezone":"Asia/Aden",
    "iso:country":"YE",
    "name:und_x_variant":[
        "Al Magh\u0101rib"
    ],
    "wof:name":"Al Magharib",
    "wof:placetype":"locality"
},
  "geometry": {"coordinates":[43.74659000000001,14.39874],"type":"Point"}
}