{
  "type": "Feature",
  "properties": {
    "gn:admin1_code":"26.0",
    "gn:admin2_code":"1310.0",
    "gn:asciiname":"Maragh",
    "gn:country_code":"YE",
    "gn:dem":2184,
    "gn:feature_class":"P",
    "gn:feature_code":"PPL",
    "gn:name":"Mar\u0101gh",
    "gn:population":0,
    "gn:timezone":"Asia/Aden",
    "iso:country":"YE",
    "name:ara_x_preferred":[
        "\u0645\u0631\u0627\u063a"
    ],
    "name:und_x_variant":[
        "Mar\u0101gh"
    ],
    "wof:name":"Maragh",
    "wof:placetype":"locality"
},
  "geometry": {"coordinates":[44.35152,15.56047],"type":"Point"}
}