{
  "type": "Feature",
  "properties": {
    "gn:admin1_code":"16.0",
    "gn:admin2_code":"2303.0",
    "gn:asciiname":"Al Hamdah",
    "gn:country_code":"YE",
    "gn:dem":2119,
    "gn:feature_class":"P",
    "gn:feature_code":"PPL",
    "gn:name":"Al \u1e28amdah",
    "gn:population":0,
    "gn:timezone":"Asia/Aden",
    "iso:country":"YE",
    "name:ara_x_preferred":[
        "\u0627\u0644\u062d\u0645\u062f\u0629"
    ],
    "name:und_x_variant":[
        "Al \u1e28amdah"
    ],
    "wof:name":"Al Hamdah",
    "wof:placetype":"locality"
},
  "geometry": {"coordinates":[44.59351,15.70651],"type":"Point"}
}