{
  "type": "Feature",
  "properties": {
    "gn:admin1_code":"22.0",
    "gn:admin2_code":"1731.0",
    "gn:asciiname":"Jabah",
    "gn:country_code":"YE",
    "gn:dem":975,
    "gn:feature_class":"P",
    "gn:feature_code":"PPL",
    "gn:name":"J\u0101bah",
    "gn:population":0,
    "gn:timezone":"Asia/Aden",
    "iso:country":"YE",
    "name:ara_x_preferred":[
        "\u062c\u0627\u0628\u0629"
    ],
    "name:ara_x_variant":[
        "\u062c\u0628\u0627"
    ],
    "name:fas_x_preferred":[
        "\u062c\u0628\u0627"
    ],
    "name:pol_x_preferred":[
        "D\u017caba"
    ],
    "name:und_x_variant":[
        "J\u0101bah"
    ],
    "name:vie_x_preferred":[
        "Jabah"
    ],
    "wof:name":"Jabah",
    "wof:placetype":"locality"
},
  "geometry": {"coordinates":[43.44381,16.27849],"type":"Point"}
}