{
  "type": "Feature",
  "properties": {
    "gn:country":"YE",
    "gn:fcode":"PPL",
    "gn:population":2,
    "iso:country":"YE",
    "name:ara_x_preferred":[
        "Al B\u0101rik"
    ],
    "name:ara_x_variant":[
        "\u0627\u0644\u0628\u0627\u0631\u0643"
    ],
    "qs:name":"Al B\u0101rik",
    "qs:photos_9r":0,
    "qs:photos_sr":0,
    "qs:pop_sr":"1",
    "wof:name":"Al B\u0101rik",
    "wof:placetype":"locality",
    "wof:population":2
},
  "geometry": {"coordinates":[43.26594,17.38578],"type":"Point"}
}