{
  "type": "Feature",
  "properties": {
    "gn:country":"YE",
    "gn:fcode":"PPLX",
    "gn:population":1,
    "iso:country":"YE",
    "name:ara_x_preferred":[
        "\u015eif\u0101"
    ],
    "name:ara_x_variant":[
        "\u0635\u0641\u0627"
    ],
    "qs:name":"\u015eif\u0101",
    "qs:photos_9r":0,
    "qs:photos_sr":0,
    "qs:pop_sr":"1",
    "wof:name":"\u015eif\u0101",
    "wof:placetype":"neighbourhood",
    "wof:population":1
},
  "geometry": {"coordinates":[43.63514,16.18733],"type":"Point"}
}