{
  "type": "Feature",
  "properties": {
    "gn:country":"YE",
    "gn:fcode":"PPL",
    "gn:pop":3,
    "iso:country":"YE",
    "name:ara_x_preferred":[
        "Mi\u1e11y\u0101f"
    ],
    "name:ara_x_variant":[
        "\u0645\u0636\u064a\u0627\u0641"
    ],
    "name:eng_x_preferred":[
        "Miuyaf"
    ],
    "name:eng_x_variant":[
        "\u1e28a\u015fib Shams\u0101n"
    ],
    "qs:name":"Mi\u1e11y\u0101f",
    "qs:photos_9r":0,
    "qs:photos_sr":0,
    "qs:pop_sr":"1",
    "wof:name":"Mi\u1e11y\u0101f",
    "wof:placetype":"locality",
    "wof:population":3
},
  "geometry": {"coordinates":[45.8861,14.21316],"type":"Point"}
}