{
  "type": "Feature",
  "properties": {
    "gn:admin1_code":"22.0",
    "gn:admin2_code":"1724.0",
    "gn:asciiname":"Mahall al Kharab",
    "gn:country_code":"YE",
    "gn:dem":402,
    "gn:feature_class":"P",
    "gn:feature_code":"PPL",
    "gn:name":"Ma\u1e29all al Khar\u0101b",
    "gn:population":0,
    "gn:timezone":"Asia/Aden",
    "iso:country":"YE",
    "name:und_x_variant":[
        "Ma\u1e29all al Khar\u0101b"
    ],
    "wof:name":"Mahall al Kharab",
    "wof:placetype":"locality"
},
  "geometry": {"coordinates":[43.41535,15.65476],"type":"Point"}
}