{
  "type": "Feature",
  "properties": {
    "gn:country":"YE",
    "gn:fcode":"PPL",
    "gn:pop":9,
    "iso:country":"YE",
    "name:ara_x_preferred":[
        "\u0627\u0644\u0645\u062d\u0637"
    ],
    "name:eng_x_preferred":[
        "Al Mahatt"
    ],
    "name:eng_x_variant":[
        "Ash Sha\u0163ibah"
    ],
    "qs:name":"Al Ma\u1e29a\u0163\u0163",
    "qs:photos_9r":0,
    "qs:photos_sr":0,
    "qs:pop_sr":"1",
    "wof:name":"Al Ma\u1e29a\u0163\u0163",
    "wof:placetype":"locality",
    "wof:population":9
},
  "geometry": {"coordinates":[43.31868,16.74676],"type":"Point"}
}