{
  "type": "Feature",
  "properties": {
    "gn:country":"YE",
    "gn:fcode":"PPL",
    "gn:population":79,
    "iso:country":"YE",
    "name:ara_x_preferred":[
        "\u0627\u0644\u0645\u0644\u062a\u0642\u064a"
    ],
    "name:eng_x_preferred":[
        "Miltaqi"
    ],
    "name:eng_x_variant":[
        "Shams\u0101n"
    ],
    "qs:name":"Miltaq\u012b",
    "qs:photos_9r":0,
    "qs:photos_sr":0,
    "qs:pop_sr":"1",
    "wof:name":"Miltaq\u012b",
    "wof:placetype":"locality",
    "wof:population":79
},
  "geometry": {"coordinates":[44.3801,16.75112],"type":"Point"}
}