{
  "type": "Feature",
  "properties": {
    "gn:country":"YE",
    "gn:fcode":"PPL",
    "gn:pop":2,
    "iso:country":"YE",
    "name:ara_x_preferred":[
        "\u0627\u0644\u0633\u0644\u0628"
    ],
    "name:eng_x_preferred":[
        "As Salb"
    ],
    "name:eng_x_variant":[
        "Dhir\u0101\u2018 al Mu\u1e29ayb"
    ],
    "qs:name":"As Salb",
    "qs:photos_9r":0,
    "qs:photos_sr":0,
    "qs:pop_sr":"1",
    "wof:name":"As Salb",
    "wof:placetype":"locality",
    "wof:population":2
},
  "geometry": {"coordinates":[43.30638,16.66307],"type":"Point"}
}