{
  "type": "Feature",
  "properties": {
    "gn:admin1_code":"23.0",
    "gn:admin2_code":"1101.0",
    "gn:asciiname":"Al Hassah",
    "gn:country_code":"YE",
    "gn:dem":1509,
    "gn:feature_class":"P",
    "gn:feature_code":"PPL",
    "gn:name":"Al \u1e28a\u015f\u015fah",
    "gn:population":0,
    "gn:timezone":"Asia/Aden",
    "iso:country":"YE",
    "name:ara_x_preferred":[
        "\u0627\u0644\u062d\u0635\u0629"
    ],
    "name:und_x_variant":[
        "Al \u1e28a\u015f\u015fah"
    ],
    "wof:name":"Al Hassah",
    "wof:placetype":"locality"
},
  "geometry": {"coordinates":[44.11238,14.29383],"type":"Point"}
}