{
  "type": "Feature",
  "properties": {
    "gn:country":"YE",
    "gn:fcode":"PPL",
    "gn:population":17,
    "iso:country":"YE",
    "name:ara_x_preferred":[
        "Al \u2018A\u0163if"
    ],
    "name:ara_x_variant":[
        "\u0627\u0644\u0639\u0637\u0641"
    ],
    "qs:name":"Al \u2018A\u0163if",
    "qs:photos_9r":0,
    "qs:photos_sr":0,
    "qs:pop_sr":"1",
    "wof:name":"Al \u2018A\u0163if",
    "wof:placetype":"locality",
    "wof:population":17
},
  "geometry": {"coordinates":[44.3826,16.51674],"type":"Point"}
}