{
  "type": "Feature",
  "properties": {
    "gn:admin1_code":"20.0",
    "gn:admin2_code":"1419.0",
    "gn:asciiname":"Kharabat Sha`ban",
    "gn:country_code":"YE",
    "gn:dem":1997,
    "gn:feature_class":"P",
    "gn:feature_code":"PPL",
    "gn:name":"Khar\u0101bat Sha\u2018b\u0101n",
    "gn:population":0,
    "gn:timezone":"Asia/Aden",
    "iso:country":"YE",
    "name:und_x_variant":[
        "Khar\u0101bat Sha\u2018b\u0101n"
    ],
    "wof:name":"Kharabat Sha`ban",
    "wof:placetype":"locality"
},
  "geometry": {"coordinates":[45.00342,14.33481],"type":"Point"}
}