{
  "type": "Feature",
  "properties": {
    "gn:country":"YE",
    "gn:fcode":"PPL",
    "gn:population":7,
    "iso:country":"YE",
    "name:ara_x_preferred":[
        "\u0642\u0645\u0644\u0627\u0646"
    ],
    "name:eng_x_preferred":[
        "Qamlan"
    ],
    "name:eng_x_variant":[
        "Qabr Sinn\u0101n"
    ],
    "qs:name":"Qaml\u0101n",
    "qs:photos_9r":0,
    "qs:photos_sr":0,
    "qs:pop_sr":"1",
    "wof:name":"Qaml\u0101n",
    "wof:placetype":"locality",
    "wof:population":7
},
  "geometry": {"coordinates":[43.40184,16.81199],"type":"Point"}
}