{
  "type": "Feature",
  "properties": {
    "gn:admin1_code":"22.0",
    "gn:admin2_code":"1706.0",
    "gn:asciiname":"Bani al A`ma'",
    "gn:country_code":"YE",
    "gn:dem":219,
    "gn:feature_class":"P",
    "gn:feature_code":"PPL",
    "gn:name":"Ban\u012b al A\u2018m\u0101\u2019",
    "gn:population":0,
    "gn:timezone":"Asia/Aden",
    "iso:country":"YE",
    "name:und_x_variant":[
        "Ban\u012b al A\u2018m\u0101\u2019"
    ],
    "wof:name":"Bani al A`ma'",
    "wof:placetype":"locality"
},
  "geometry": {"coordinates":[43.21667,16.23333],"type":"Point"}
}