{
  "type": "Feature",
  "properties": {
    "gn:admin1_code":"8.0",
    "gn:admin2_code":"1810.0",
    "gn:asciiname":"Al 'Ali",
    "gn:country_code":"YE",
    "gn:dem":235,
    "gn:feature_class":"P",
    "gn:feature_code":"PPL",
    "gn:name":"Al \u2018Al\u012b",
    "gn:population":0,
    "gn:timezone":"Asia/Aden",
    "iso:country":"YE",
    "name:ara_x_preferred":[
        "\u0627\u0644\u0639\u0644\u064a"
    ],
    "name:und_x_variant":[
        "Al \u2018Al\u012b"
    ],
    "wof:name":"Al 'Ali",
    "wof:placetype":"locality"
},
  "geometry": {"coordinates":[43.31923,15.10063],"type":"Point"}
}