{
  "type": "Feature",
  "properties": {
    "gn:admin1_code":"18.0",
    "gn:admin2_code":"3009.0",
    "gn:asciiname":"Qaryat Marwas",
    "gn:country_code":"YE",
    "gn:dem":1628,
    "gn:feature_class":"P",
    "gn:feature_code":"PPL",
    "gn:name":"Qaryat Marwas",
    "gn:population":0,
    "gn:timezone":"Asia/Aden",
    "iso:country":"YE",
    "wof:name":"Qaryat Marwas",
    "wof:placetype":"locality"
},
  "geometry": {"coordinates":[44.45785,13.68868],"type":"Point"}
}