{
  "type": "Feature",
  "properties": {
    "gn:admin1_code":"14.0",
    "gn:admin2_code":"2612.0",
    "gn:asciiname":"Al Mahtam",
    "gn:country_code":"YE",
    "gn:dem":1090,
    "gn:feature_class":"P",
    "gn:feature_code":"PPL",
    "gn:name":"\u0100l Mahtam",
    "gn:population":0,
    "gn:timezone":"Asia/Aden",
    "iso:country":"YE",
    "name:ara_x_preferred":[
        "\u0622\u0644 \u0645\u0647\u062a\u0645"
    ],
    "name:und_x_variant":[
        "\u0100l Mahtam"
    ],
    "wof:name":"Al Mahtam",
    "wof:placetype":"locality"
},
  "geometry": {"coordinates":[45.3712,15.4379],"type":"Point"}
}