{
  "type": "Feature",
  "properties": {
    "gn:admin1_code":"22.0",
    "gn:admin2_code":"1727.0",
    "gn:asciiname":"Bayt Musa as Sayidi",
    "gn:country_code":"YE",
    "gn:dem":1016,
    "gn:feature_class":"P",
    "gn:feature_code":"PPL",
    "gn:name":"Bayt M\u016bs\u00e1 a\u015f \u015e\u0101yid\u012b",
    "gn:population":0,
    "gn:timezone":"Asia/Aden",
    "iso:country":"YE",
    "name:ara_x_preferred":[
        "\u0628\u064a\u062a \u0645\u0648\u0633\u0649 \u0627\u0644\u0635\u0627\u064a\u062f\u064a"
    ],
    "name:und_x_variant":[
        "Bayt M\u016bs\u00e1 a\u015f \u015e\u0101yid\u012b"
    ],
    "wof:name":"Bayt Musa as Sayidi",
    "wof:placetype":"locality"
},
  "geometry": {"coordinates":[43.62494,15.54547],"type":"Point"}
}