{
  "type": "Feature",
  "properties": {
    "gn:admin1_code":"16.0",
    "gn:admin2_code":"2305.0",
    "gn:asciiname":"Dar Salm",
    "gn:country_code":"YE",
    "gn:dem":2312,
    "gn:feature_class":"P",
    "gn:feature_code":"PPL",
    "gn:name":"D\u0101r Salm",
    "gn:population":0,
    "gn:timezone":"Asia/Aden",
    "iso:country":"YE",
    "name:ara_x_preferred":[
        "\u062f\u0627\u0631 \u0633\u0644\u0645"
    ],
    "name:und_x_variant":[
        "D\u0101r Salam",
        "D\u0101r Salm"
    ],
    "wof:name":"Dar Salm",
    "wof:placetype":"locality"
},
  "geometry": {"coordinates":[44.25741,15.28067],"type":"Point"}
}