{
  "type": "Feature",
  "properties": {
    "gn:admin1_code":"15.0",
    "gn:admin2_code":"2212.0",
    "gn:asciiname":"Shatt `Awsan",
    "gn:country_code":"YE",
    "gn:dem":1640,
    "gn:feature_class":"P",
    "gn:feature_code":"PPL",
    "gn:name":"Sha\u0163\u0163 \u2018Aws\u0101n",
    "gn:population":0,
    "gn:timezone":"Asia/Aden",
    "iso:country":"YE",
    "name:ara_x_preferred":[
        "\u0634\u0637 \u0639\u0648\u0635\u0627\u0646"
    ],
    "name:und_x_variant":[
        "Sha\u0163\u0163 \u2018Aws\u0101",
        "Sha\u0163\u0163 \u2018Aws\u0101n"
    ],
    "wof:name":"Shatt `Awsan",
    "wof:placetype":"locality"
},
  "geometry": {"coordinates":[43.92261,16.71854],"type":"Point"}
}