{
  "type": "Feature",
  "properties": {
    "gn:admin1_code":"16.0",
    "gn:admin2_code":"2303.0",
    "gn:asciiname":"Al Jarabat",
    "gn:country_code":"YE",
    "gn:dem":1773,
    "gn:feature_class":"P",
    "gn:feature_code":"PPL",
    "gn:name":"Al Jarab\u0101t",
    "gn:population":0,
    "gn:timezone":"Asia/Aden",
    "iso:country":"YE",
    "name:ara_x_preferred":[
        "\u0627\u0644\u062c\u0631\u0628\u0627\u062a"
    ],
    "name:und_x_variant":[
        "Al Jarab\u0101t"
    ],
    "wof:name":"Al Jarabat",
    "wof:placetype":"locality"
},
  "geometry": {"coordinates":[44.59469,15.52248],"type":"Point"}
}