{
  "type": "Feature",
  "properties": {
    "gn:country":"YE",
    "gn:fcode":"PPL",
    "gn:pop":3,
    "iso:country":"YE",
    "name:ara_x_preferred":[
        "\u0645\u062c\u0644\u062d"
    ],
    "name:eng_x_preferred":[
        "Majlih"
    ],
    "name:eng_x_variant":[
        "Al \u2018Ashshah"
    ],
    "qs:name":"Majli\u1e29",
    "qs:photos_9r":0,
    "qs:photos_sr":0,
    "qs:pop_sr":"1",
    "wof:name":"Majli\u1e29",
    "wof:placetype":"locality",
    "wof:population":3
},
  "geometry": {"coordinates":[43.38047,16.32581],"type":"Point"}
}