{
  "type": "Feature",
  "properties": {
    "gn:admin1_code":"8.0",
    "gn:admin2_code":"1824.0",
    "gn:asciiname":"At Turaybah",
    "gn:country_code":"YE",
    "gn:dem":149,
    "gn:feature_class":"P",
    "gn:feature_code":"PPL",
    "gn:name":"At Turaybah",
    "gn:population":0,
    "gn:timezone":"Asia/Aden",
    "iso:country":"YE",
    "name:und_x_variant":[
        "At Taribah",
        "Tarabe",
        "At Turaybah"
    ],
    "wof:name":"At Turaybah",
    "wof:placetype":"locality"
},
  "geometry": {"coordinates":[43.37894,14.22869],"type":"Point"}
}