{
  "type": "Feature",
  "properties": {
    "gn:admin1_code":"23.0",
    "gn:admin2_code":"1116.0",
    "gn:asciiname":"Dar al Jami`",
    "gn:country_code":"YE",
    "gn:dem":1747,
    "gn:feature_class":"P",
    "gn:feature_code":"PPL",
    "gn:name":"D\u0101r al J\u0101mi\u2018",
    "gn:population":0,
    "gn:timezone":"Asia/Aden",
    "iso:country":"YE",
    "name:und_x_variant":[
        "D\u0101r al J\u0101mi\u2018"
    ],
    "wof:name":"Dar al Jami`",
    "wof:placetype":"locality"
},
  "geometry": {"coordinates":[44.1165,13.8056],"type":"Point"}
}