{
  "type": "Feature",
  "properties": {
    "gn:admin1_code":"15.0",
    "gn:admin2_code":"2210.0",
    "gn:asciiname":"Takhyah",
    "gn:country_code":"YE",
    "gn:dem":1923,
    "gn:feature_class":"P",
    "gn:feature_code":"PPL",
    "gn:name":"\u0162akhyah",
    "gn:population":0,
    "gn:timezone":"Asia/Aden",
    "iso:country":"YE",
    "name:ara_x_preferred":[
        "\u0637\u062e\u064a\u0629"
    ],
    "name:und_x_variant":[
        "\u0162akhyah"
    ],
    "wof:name":"Takhyah",
    "wof:placetype":"locality"
},
  "geometry": {"coordinates":[43.59099000000001,17.15399],"type":"Point"}
}