{
  "type": "Feature",
  "properties": {
    "gn:admin1_code":"22.0",
    "gn:admin2_code":"1716.0",
    "gn:asciiname":"Al Wa`liyah",
    "gn:country_code":"YE",
    "gn:dem":2004,
    "gn:feature_class":"P",
    "gn:feature_code":"PPL",
    "gn:name":"Al Wa\u2018l\u012byah",
    "gn:population":0,
    "gn:timezone":"Asia/Aden",
    "iso:country":"YE",
    "name:und_x_variant":[
        "Al Wa\u2018l\u012byah",
        "Al Wu\u2018l\u012byah"
    ],
    "wof:name":"Al Wa`liyah",
    "wof:placetype":"locality"
},
  "geometry": {"coordinates":[43.46481,15.95577],"type":"Point"}
}