{
  "type": "Feature",
  "properties": {
    "gn:admin1_code":"8.0",
    "gn:admin2_code":"1818.0",
    "gn:asciiname":"Markaz al Marir",
    "gn:country_code":"YE",
    "gn:dem":328,
    "gn:feature_class":"P",
    "gn:feature_code":"PPLA2",
    "gn:name":"Markaz al Mar\u012br",
    "gn:population":0,
    "gn:timezone":"Asia/Aden",
    "iso:country":"YE",
    "name:ara_x_preferred":[
        "\u0645\u0631\u0643\u0632 \u0627\u0644\u0645\u0631\u064a\u0631"
    ],
    "name:und_x_variant":[
        "Marir",
        "El-Mar\u012br",
        "Markaz al Mar\u012br",
        "Al Mar\u012br"
    ],
    "wof:name":"Markaz al Marir",
    "wof:placetype":"locality"
},
  "geometry": {"coordinates":[43.59547,13.98178],"type":"Point"}
}