{
  "type": "Feature",
  "properties": {
    "gn:admin1_code":"25.0",
    "gn:admin2_code":"1513.0",
    "gn:asciiname":"Al Mikhlafiyah",
    "gn:country_code":"YE",
    "gn:dem":1044,
    "gn:feature_class":"P",
    "gn:feature_code":"PPL",
    "gn:name":"Al Mikhl\u0101f\u012byah",
    "gn:population":0,
    "gn:timezone":"Asia/Aden",
    "iso:country":"YE",
    "name:und_x_variant":[
        "Al Mikhl\u0101f\u012byah"
    ],
    "wof:name":"Al Mikhlafiyah",
    "wof:placetype":"locality"
},
  "geometry": {"coordinates":[44.23545,13.51348],"type":"Point"}
}