{
  "type": "Feature",
  "properties": {
    "gn:admin1_code":"23.0",
    "gn:admin2_code":"1115.0",
    "gn:asciiname":"Khuba'ah",
    "gn:country_code":"YE",
    "gn:dem":1618,
    "gn:feature_class":"P",
    "gn:feature_code":"PPL",
    "gn:name":"Kh\u016bb\u0101\u2019ah",
    "gn:population":0,
    "gn:timezone":"Asia/Aden",
    "iso:country":"YE",
    "name:und_x_variant":[
        "Kh\u016bb\u0101\u2019ah"
    ],
    "wof:name":"Khuba'ah",
    "wof:placetype":"locality"
},
  "geometry": {"coordinates":[44.21211,13.76227],"type":"Point"}
}