{
  "type": "Feature",
  "properties": {
    "gn:admin1_code":"5.0",
    "gn:admin2_code":"2110.0",
    "gn:asciiname":"Zaqrah",
    "gn:country_code":"YE",
    "gn:dem":1139,
    "gn:feature_class":"P",
    "gn:feature_code":"PPL",
    "gn:name":"Zaqrah",
    "gn:population":0,
    "gn:timezone":"Asia/Aden",
    "iso:country":"YE",
    "wof:name":"Zaqrah",
    "wof:placetype":"locality"
},
  "geometry": {"coordinates":[46.45186,14.41116],"type":"Point"}
}