{
  "type": "Feature",
  "properties": {
    "gn:country":"YE",
    "gn:fcode":"PPL",
    "gn:population":2,
    "iso:country":"YE",
    "name:ara_x_preferred":[
        "\u0627\u0644\u0631\u062f\u0629"
    ],
    "name:eng_x_preferred":[
        "Ar Raddah"
    ],
    "name:eng_x_variant":[
        "Al Marz\u016bqah"
    ],
    "qs:name":"Ar Raddah",
    "qs:photos_9r":0,
    "qs:photos_sr":0,
    "qs:pop_sr":"1",
    "wof:name":"Ar Raddah",
    "wof:placetype":"locality",
    "wof:population":2
},
  "geometry": {"coordinates":[43.81007,13.33087],"type":"Point"}
}