{
  "type": "Feature",
  "properties": {
    "gn:admin1_code":"28.0",
    "gn:admin2_code":"1926.0",
    "gn:asciiname":"Bajubi",
    "gn:country_code":"YE",
    "gn:dem":337,
    "gn:feature_class":"P",
    "gn:feature_code":"PPL",
    "gn:name":"B\u0101j\u016bb\u012b",
    "gn:population":0,
    "gn:timezone":"Asia/Aden",
    "iso:country":"YE",
    "wof:name":"Bajubi",
    "wof:placetype":"locality"
},
  "geometry": {"coordinates":[54.29669000000001,12.52616],"type":"Point"}
}