{
  "type": "Feature",
  "properties": {
    "gn:admin1_code":"8.0",
    "gn:admin2_code":"1809.0",
    "gn:asciiname":"Yahya Qasim",
    "gn:country_code":"YE",
    "gn:dem":115,
    "gn:feature_class":"P",
    "gn:feature_code":"PPL",
    "gn:name":"Ya\u1e29y\u00e1 Q\u0101sim",
    "gn:population":0,
    "gn:timezone":"Asia/Aden",
    "iso:country":"YE",
    "name:ara_x_preferred":[
        "\u064a\u062d\u064a\u0649 \u0642\u0627\u0633\u0645"
    ],
    "name:und_x_variant":[
        "Ya\u1e29y\u00e1 Q\u0101sim"
    ],
    "wof:name":"Yahya Qasim",
    "wof:placetype":"locality"
},
  "geometry": {"coordinates":[43.14827,15.19443],"type":"Point"}
}