{
  "type": "Feature",
  "properties": {
    "gn:admin1_code":"22.0",
    "gn:admin2_code":"1709.0",
    "gn:asciiname":"Al Madnifah",
    "gn:country_code":"YE",
    "gn:dem":1215,
    "gn:feature_class":"P",
    "gn:feature_code":"PPL",
    "gn:name":"Al Madnifah",
    "gn:population":0,
    "gn:timezone":"Asia/Aden",
    "iso:country":"YE",
    "name:ara_x_preferred":[
        "\u0627\u0644\u0645\u062f\u0646\u0641\u0629"
    ],
    "wof:name":"Al Madnifah",
    "wof:placetype":"locality"
},
  "geometry": {"coordinates":[43.44647,16.01936],"type":"Point"}
}