{
  "type": "Feature",
  "properties": {
    "gn:admin1_code":"14.0",
    "gn:admin2_code":"2607.0",
    "gn:asciiname":"Khudayr",
    "gn:country_code":"YE",
    "gn:dem":2319,
    "gn:feature_class":"P",
    "gn:feature_code":"PPL",
    "gn:name":"Khu\u1e11ayr",
    "gn:population":0,
    "gn:timezone":"Asia/Aden",
    "iso:country":"YE",
    "name:und_x_variant":[
        "Khu\u1e11ayr"
    ],
    "wof:name":"Khudayr",
    "wof:placetype":"locality"
},
  "geometry": {"coordinates":[45.18953,15.14726],"type":"Point"}
}