{
  "type": "Feature",
  "properties": {
    "gn:admin1_code":"25.0",
    "gn:admin2_code":"1521.0",
    "gn:asciiname":"Al `Akab",
    "gn:country_code":"YE",
    "gn:dem":1445,
    "gn:feature_class":"P",
    "gn:feature_code":"PPL",
    "gn:name":"Al \u2018Akab",
    "gn:population":0,
    "gn:timezone":"Asia/Aden",
    "iso:country":"YE",
    "name:und_x_variant":[
        "Al \u2018Akab"
    ],
    "wof:name":"Al `Akab",
    "wof:placetype":"locality"
},
  "geometry": {"coordinates":[44.00331,13.39177],"type":"Point"}
}