{
  "type": "Feature",
  "properties": {
    "gn:country":"YE",
    "gn:fcode":"PPLX",
    "gn:population":40,
    "iso:country":"YE",
    "name:ara_x_preferred":[
        "\u062d\u0627\u0631\u0629 \u0627\u0644 \u0625\u0633\u0645\u0627\u0639\u064a\u0644"
    ],
    "qs:name":"\u1e28\u0101rat \u0100l Ism\u0101\u2018\u012bl",
    "qs:photos_9r":0,
    "qs:photos_sr":0,
    "qs:pop_sr":"1",
    "wof:name":"\u1e28\u0101rat \u0100l Ism\u0101\u2018\u012bl",
    "wof:placetype":"neighbourhood",
    "wof:population":40
},
  "geometry": {"coordinates":[44.28916,16.55507],"type":"Point"}
}