{
  "type": "Feature",
  "properties": {
    "gn:country":"YE",
    "gn:fcode":"PPL",
    "gn:pop":22,
    "iso:country":"YE",
    "name:ara_x_preferred":[
        "\u0627\u0644\u0631\u062c\u0627\u0626\u0632"
    ],
    "name:eng_x_preferred":[
        "Ar Rajaiz"
    ],
    "name:unk_x_variant":[
        "Ar Raj\u0101\u2019iz"
    ],
    "qs:name":"Ar Raj\u0101i\u2019z",
    "qs:photos_9r":0,
    "qs:photos_sr":0,
    "qs:pop_sr":"1",
    "wof:name":"Ar Raj\u0101i\u2019z",
    "wof:placetype":"locality",
    "wof:population":22
},
  "geometry": {"coordinates":[44.51252,17.19574],"type":"Point"}
}