{
  "type": "Feature",
  "properties": {
    "gn:admin1_code":"20.0",
    "gn:admin2_code":"1419.0",
    "gn:asciiname":"Kharabat Al Sirhan",
    "gn:country_code":"YE",
    "gn:dem":1933,
    "gn:feature_class":"P",
    "gn:feature_code":"PPL",
    "gn:name":"Khar\u0101bat \u0100l Sir\u1e29\u0101n",
    "gn:population":0,
    "gn:timezone":"Asia/Aden",
    "iso:country":"YE",
    "name:ara_x_preferred":[
        "\u0627\u0644\u062e\u0631\u0627\u0628\u0629"
    ],
    "name:und_x_variant":[
        "Khar\u0101bat \u0100l Sir\u1e29\u0101n",
        "Al Khar\u0101bah"
    ],
    "wof:name":"Kharabat Al Sirhan",
    "wof:placetype":"locality"
},
  "geometry": {"coordinates":[45.04271,14.30218],"type":"Point"}
}