{
  "type": "Feature",
  "properties": {
    "gn:admin1_code":"23.0",
    "gn:admin2_code":"1114.0",
    "gn:asciiname":"Qaryat adh Dhira`",
    "gn:country_code":"YE",
    "gn:dem":1903,
    "gn:feature_class":"P",
    "gn:feature_code":"PPL",
    "gn:name":"Qaryat adh Dhir\u0101\u2018",
    "gn:population":0,
    "gn:timezone":"Asia/Aden",
    "iso:country":"YE",
    "name:und_x_variant":[
        "Qaryat adh Dhir\u0101\u2018"
    ],
    "wof:name":"Qaryat adh Dhira`",
    "wof:placetype":"locality"
},
  "geometry": {"coordinates":[44.33921,13.74741],"type":"Point"}
}