{
  "type": "Feature",
  "properties": {
    "gn:country":"YE",
    "gn:fcode":"PPL",
    "gn:pop":44,
    "iso:country":"YE",
    "name:ara_x_preferred":[
        "\u0627\u0644\u0642\u0644\u064a\u0639\u0629"
    ],
    "name:eng_x_preferred":[
        "Al Qulay'ah"
    ],
    "qs:name":"Al Qulay\u2018ah",
    "qs:photos_9r":0,
    "qs:photos_sr":0,
    "qs:pop_sr":"1",
    "wof:name":"Al Qulay\u2018ah",
    "wof:placetype":"locality",
    "wof:population":44
},
  "geometry": {"coordinates":[43.7436,13.32107],"type":"Point"}
}