{
  "type": "Feature",
  "properties": {
    "gn:admin1_code":"1.0",
    "gn:admin2_code":"1208.0",
    "gn:asciiname":"Sakin Ahl Mahathith",
    "gn:country_code":"YE",
    "gn:dem":934,
    "gn:feature_class":"P",
    "gn:feature_code":"PPL",
    "gn:name":"S\u0101kin Ahl Mah\u0101th\u012bth",
    "gn:population":0,
    "gn:timezone":"Asia/Aden",
    "iso:country":"YE",
    "name:nno_x_preferred":[
        "Sakin Ahl Mahathith"
    ],
    "name:und_x_variant":[
        "S\u0101kin Ahl Mah\u0101th\u012bth"
    ],
    "wof:name":"Sakin Ahl Mahathith",
    "wof:placetype":"locality"
},
  "geometry": {"coordinates":[45.88556,13.72389],"type":"Point"}
}