{
  "type": "Feature",
  "properties": {
    "gn:admin1_code":"16.0",
    "gn:admin2_code":"2308.0",
    "gn:asciiname":"Rakhdah",
    "gn:country_code":"YE",
    "gn:dem":1426,
    "gn:feature_class":"P",
    "gn:feature_code":"PPL",
    "gn:name":"Rakhdah",
    "gn:population":0,
    "gn:timezone":"Asia/Aden",
    "iso:country":"YE",
    "wof:name":"Rakhdah",
    "wof:placetype":"locality"
},
  "geometry": {"coordinates":[43.85446,15.20941],"type":"Point"}
}