{
  "type": "Feature",
  "properties": {
    "gn:country":"YE",
    "gn:fcode":"PPL",
    "gn:pop":3,
    "iso:country":"YE",
    "name:ara_x_preferred":[
        "Sh\u0101fi\u2018"
    ],
    "name:ara_x_variant":[
        "\u0634\u0627\u0641\u0639"
    ],
    "name:eng_x_preferred":[
        "Shafi'"
    ],
    "name:eng_x_variant":[
        "A\u015f \u015eal\u0101bah"
    ],
    "qs:name":"Sh\u0101fi\u2018",
    "qs:photos_9r":0,
    "qs:photos_sr":0,
    "qs:pop_sr":"1",
    "wof:name":"Sh\u0101fi\u2018",
    "wof:placetype":"locality",
    "wof:population":3
},
  "geometry": {"coordinates":[43.40659,16.30791],"type":"Point"}
}