{
  "type": "Feature",
  "properties": {
    "gn:admin1_code":"11.0",
    "gn:admin2_code":"2011.0",
    "gn:asciiname":"Al Maqatihah",
    "gn:country_code":"YE",
    "gn:dem":2228,
    "gn:feature_class":"P",
    "gn:feature_code":"PPL",
    "gn:name":"Al Maq\u0101\u0163i\u1e29ah",
    "gn:population":0,
    "gn:timezone":"Asia/Aden",
    "iso:country":"YE",
    "name:und_x_variant":[
        "Al Maq\u0101\u0163i\u1e29ah"
    ],
    "wof:name":"Al Maqatihah",
    "wof:placetype":"locality"
},
  "geometry": {"coordinates":[44.19389,14.74603],"type":"Point"}
}