{
  "type": "Feature",
  "properties": {
    "gn:admin1_code":"14.0",
    "gn:admin2_code":"2611.0",
    "gn:asciiname":"Al Ashbal",
    "gn:country_code":"YE",
    "gn:dem":2051,
    "gn:feature_class":"P",
    "gn:feature_code":"PPL",
    "gn:name":"Al Ashb\u0101l",
    "gn:population":0,
    "gn:timezone":"Asia/Aden",
    "iso:country":"YE",
    "name:ara_x_preferred":[
        "Al Ashb\u0101l"
    ],
    "name:ara_x_variant":[
        "\u0627\u0644\u0623\u0634\u0628\u0627\u0644"
    ],
    "wof:name":"Al Ashbal",
    "wof:placetype":"locality"
},
  "geometry": {"coordinates":[45.40933,14.72834],"type":"Point"}
}