{
  "type": "Feature",
  "properties": {
    "gn:country":"YE",
    "gn:fcode":"EST",
    "gn:pop":4,
    "iso:country":"YE",
    "name:ara_x_preferred":[
        "\u0627\u0644\u0633\u064a\u0627\u062f\u0629"
    ],
    "qs:name":"As Siy\u0101dah",
    "qs:photos_9r":0,
    "qs:photos_sr":0,
    "qs:pop_sr":"1",
    "wof:name":"As Siy\u0101dah",
    "wof:placetype":"locality",
    "wof:population":4
},
  "geometry": {"coordinates":[43.71873,16.93948],"type":"Point"}
}