{
  "type": "Feature",
  "properties": {
    "gn:admin1_code":"16.0",
    "gn:admin2_code":"2305.0",
    "gn:asciiname":"Ad Dirm",
    "gn:country_code":"YE",
    "gn:dem":2678,
    "gn:feature_class":"P",
    "gn:feature_code":"PPL",
    "gn:name":"Ad Dirm",
    "gn:population":0,
    "gn:timezone":"Asia/Aden",
    "iso:country":"YE",
    "wof:name":"Ad Dirm",
    "wof:placetype":"locality"
},
  "geometry": {"coordinates":[44.38256,15.10386],"type":"Point"}
}