{
  "type": "Feature",
  "properties": {
    "gn:admin1_code":"20.0",
    "gn:admin2_code":"1406.0",
    "gn:asciiname":"Ash Shazibi",
    "gn:country_code":"YE",
    "gn:dem":1962,
    "gn:feature_class":"P",
    "gn:feature_code":"PPL",
    "gn:name":"Ash Sh\u0101zib\u012b",
    "gn:population":0,
    "gn:timezone":"Asia/Aden",
    "iso:country":"YE",
    "name:ara_x_preferred":[
        "Ash Sh\u0101zib\u012b"
    ],
    "name:ara_x_variant":[
        "\u0627\u0644\u0634\u0627\u0632\u0628\u064a"
    ],
    "name:und_x_variant":[
        "Ma\u1e29all ash Sh\u0101dhib\u012b"
    ],
    "wof:name":"Ash Shazibi",
    "wof:placetype":"locality"
},
  "geometry": {"coordinates":[45.43363,14.09487],"type":"Point"}
}