{
  "type": "Feature",
  "properties": {
    "gn:admin1_code":"11.0",
    "gn:admin2_code":"2002.0",
    "gn:asciiname":"San`ah",
    "gn:country_code":"YE",
    "gn:dem":2423,
    "gn:feature_class":"P",
    "gn:feature_code":"PPL",
    "gn:name":"\u015ean\u2018ah",
    "gn:population":0,
    "gn:timezone":"Asia/Aden",
    "iso:country":"YE",
    "name:und_x_variant":[
        "\u015ean\u2018ah"
    ],
    "wof:name":"San`ah",
    "wof:placetype":"locality"
},
  "geometry": {"coordinates":[44.30663,14.58599],"type":"Point"}
}