{
  "type": "Feature",
  "properties": {
    "gn:country":"YE",
    "gn:fcode":"PPL",
    "gn:pop":3,
    "iso:country":"YE",
    "name:ara_x_preferred":[
        "\u0634\u0639\u0628 \u0627\u0644\u0633\u0631"
    ],
    "name:eng_x_preferred":[
        "Sha'b As Sirr"
    ],
    "qs:name":"Sha\u2018b as Sirr",
    "qs:photos_9r":0,
    "qs:photos_sr":0,
    "qs:pop_sr":"1",
    "wof:name":"Sha\u2018b as Sirr",
    "wof:placetype":"locality",
    "wof:population":3
},
  "geometry": {"coordinates":[43.27336,17.02571],"type":"Point"}
}