{
  "type": "Feature",
  "properties": {
    "gn:admin1_code":"10.0",
    "gn:admin2_code":"2704.0",
    "gn:asciiname":"Al Ghaliyah",
    "gn:country_code":"YE",
    "gn:dem":803,
    "gn:feature_class":"P",
    "gn:feature_code":"PPL",
    "gn:name":"Al Ghal\u012byah",
    "gn:population":0,
    "gn:timezone":"Asia/Aden",
    "iso:country":"YE",
    "name:und_x_variant":[
        "Al Ghal\u012byah"
    ],
    "wof:name":"Al Ghaliyah",
    "wof:placetype":"locality"
},
  "geometry": {"coordinates":[43.28086,15.50588],"type":"Point"}
}