{
  "type": "Feature",
  "properties": {
    "gn:admin1_code":"16.0",
    "gn:admin2_code":"2307.0",
    "gn:asciiname":"Mahall Rayd",
    "gn:country_code":"YE",
    "gn:dem":2661,
    "gn:feature_class":"P",
    "gn:feature_code":"PPL",
    "gn:name":"Ma\u1e29all Rayd",
    "gn:population":0,
    "gn:timezone":"Asia/Aden",
    "iso:country":"YE",
    "name:ara_x_preferred":[
        "\u0645\u062d\u0644 \u0631\u064a\u062f"
    ],
    "name:nno_x_preferred":[
        "Mahall Rayd"
    ],
    "name:und_x_variant":[
        "Ma\u1e29all Rayd"
    ],
    "wof:name":"Mahall Rayd",
    "wof:placetype":"locality"
},
  "geometry": {"coordinates":[44.12352,15.32174],"type":"Point"}
}