{
  "type": "Feature",
  "properties": {
    "gn:admin1_code":"23.0",
    "gn:admin2_code":"1106.0",
    "gn:asciiname":"Al Manzil",
    "gn:country_code":"YE",
    "gn:dem":2276,
    "gn:feature_class":"P",
    "gn:feature_code":"PPL",
    "gn:name":"Al Manzil",
    "gn:population":0,
    "gn:timezone":"Asia/Aden",
    "iso:country":"YE",
    "wof:name":"Al Manzil",
    "wof:placetype":"locality"
},
  "geometry": {"coordinates":[44.40153,14.11638],"type":"Point"}
}