{
  "type": "Feature",
  "properties": {
    "gn:admin1_code":"16.0",
    "gn:admin2_code":"2308.0",
    "gn:asciiname":"Bayt as Sayd `Abdah",
    "gn:country_code":"YE",
    "gn:dem":1409,
    "gn:feature_class":"P",
    "gn:feature_code":"PPL",
    "gn:name":"Bayt as Sayd \u2018Abdah",
    "gn:population":0,
    "gn:timezone":"Asia/Aden",
    "iso:country":"YE",
    "name:und_x_variant":[
        "Bayt as Sayd \u2018Abdah"
    ],
    "wof:name":"Bayt as Sayd `Abdah",
    "wof:placetype":"locality"
},
  "geometry": {"coordinates":[43.81365,15.2088],"type":"Point"}
}