{
  "type": "Feature",
  "properties": {
    "gn:admin1_code":"5.0",
    "gn:admin2_code":"2111.0",
    "gn:asciiname":"Mahraq",
    "gn:country_code":"YE",
    "gn:dem":1468,
    "gn:feature_class":"P",
    "gn:feature_code":"PPL",
    "gn:name":"Ma\u1e29raq",
    "gn:population":0,
    "gn:timezone":"Asia/Aden",
    "iso:country":"YE",
    "name:und_x_variant":[
        "Ma\u1e29raq"
    ],
    "wof:name":"Mahraq",
    "wof:placetype":"locality"
},
  "geometry": {"coordinates":[46.45,14.23333],"type":"Point"}
}