{
  "type": "Feature",
  "properties": {
    "gn:admin1_code":"23.0",
    "gn:admin2_code":"1111.0",
    "gn:asciiname":"Rummadah",
    "gn:country_code":"YE",
    "gn:dem":1553,
    "gn:feature_class":"P",
    "gn:feature_code":"PPL",
    "gn:name":"Rumm\u0101\u1e11ah",
    "gn:population":0,
    "gn:timezone":"Asia/Aden",
    "iso:country":"YE",
    "name:und_x_variant":[
        "Rumm\u0101\u1e11ah"
    ],
    "wof:name":"Rummadah",
    "wof:placetype":"locality"
},
  "geometry": {"coordinates":[43.88489000000001,13.91535],"type":"Point"}
}