{
  "type": "Feature",
  "properties": {
    "gn:admin1_code":"8.0",
    "gn:admin2_code":"1814.0",
    "gn:asciiname":"Al Hiddah",
    "gn:country_code":"YE",
    "gn:dem":13,
    "gn:feature_class":"P",
    "gn:feature_code":"PPL",
    "gn:name":"Al Hiddah",
    "gn:population":0,
    "gn:timezone":"Asia/Aden",
    "iso:country":"YE",
    "name:ara_x_preferred":[
        "\u0627\u0644\u0647\u062f\u0629"
    ],
    "name:und_x_variant":[
        "Shuraim",
        "Shuraym",
        "Al Hiddah"
    ],
    "wof:name":"Al Hiddah",
    "wof:placetype":"locality"
},
  "geometry": {"coordinates":[43.01837,14.61074],"type":"Point"}
}