{
  "type": "Feature",
  "properties": {
    "gn:admin1_code":"23.0",
    "gn:admin2_code":"1115.0",
    "gn:asciiname":"Al Maqtah",
    "gn:country_code":"YE",
    "gn:dem":2075,
    "gn:feature_class":"P",
    "gn:feature_code":"PPL",
    "gn:name":"Al Maq\u0163a\u1e29",
    "gn:population":0,
    "gn:timezone":"Asia/Aden",
    "iso:country":"YE",
    "name:und_x_variant":[
        "Al Maq\u0163a\u1e29"
    ],
    "wof:name":"Al Maqtah",
    "wof:placetype":"locality"
},
  "geometry": {"coordinates":[44.20656,13.88795],"type":"Point"}
}