{
  "type": "Feature",
  "properties": {
    "gn:admin1_code":"22.0",
    "gn:admin2_code":"1704.0",
    "gn:asciiname":"Bitah",
    "gn:country_code":"YE",
    "gn:dem":66,
    "gn:feature_class":"P",
    "gn:feature_code":"PPL",
    "gn:name":"Bi\u0163\u0101\u1e29",
    "gn:population":0,
    "gn:timezone":"Asia/Aden",
    "iso:country":"YE",
    "name:ara_x_preferred":[
        "Bi\u0163\u0101\u1e29"
    ],
    "wof:name":"Bitah",
    "wof:placetype":"locality"
},
  "geometry": {"coordinates":[42.98333,16.03333],"type":"Point"}
}