{
  "type": "Feature",
  "properties": {
    "gn:admin1_code":"19.0",
    "gn:admin2_code":"2901.0",
    "gn:asciiname":"Riyam",
    "gn:cc2":"YE",
    "gn:country_code":"YE",
    "gn:dem":1432,
    "gn:feature_class":"P",
    "gn:feature_code":"PPL",
    "gn:name":"Riy\u0101m",
    "gn:population":0,
    "gn:timezone":"Asia/Aden",
    "iso:country":"YE",
    "name:ara_x_preferred":[
        "Riy\u0101m"
    ],
    "name:und_x_variant":[
        "Ri\u00e2m"
    ],
    "wof:name":"Riyam",
    "wof:placetype":"locality"
},
  "geometry": {"coordinates":[44.31667,16.03333],"type":"Point"}
}