{
  "type": "Feature",
  "properties": {
    "gn:country":"YE",
    "gn:fcode":"PPL",
    "gn:pop":5,
    "iso:country":"YE",
    "name:ara_x_preferred":[
        "\u0627\u0644\u0638\u0647\u0631"
    ],
    "name:eng_x_preferred":[
        "Az Zahar"
    ],
    "qs:name":"Az\u0327 Z\u0327ahar",
    "qs:photos_9r":0,
    "qs:photos_sr":0,
    "qs:pop_sr":"1",
    "wof:name":"Az\u0327 Z\u0327ahar",
    "wof:placetype":"locality",
    "wof:population":5
},
  "geometry": {"coordinates":[45.82504,14.21088],"type":"Point"}
}