{
  "type": "Feature",
  "properties": {
    "gn:country":"YE",
    "gn:fcode":"PPL",
    "gn:pop":2,
    "iso:country":"YE",
    "name:ara_x_preferred":[
        "Al Ikhw\u0101\u1e11"
    ],
    "name:ara_x_variant":[
        "\u0627\u0644\u0625\u062e\u0648\u0627\u0636"
    ],
    "name:eng_x_preferred":[
        "Al Ikhwau"
    ],
    "name:eng_x_variant":[
        "A\u015f \u015eir\u0101b"
    ],
    "qs:name":"Al Ikhw\u0101\u1e11",
    "qs:photos_9r":0,
    "qs:photos_sr":0,
    "qs:pop_sr":"1",
    "wof:name":"Al Ikhw\u0101\u1e11",
    "wof:placetype":"locality",
    "wof:population":2
},
  "geometry": {"coordinates":[43.417,16.03103],"type":"Point"}
}