{
  "type": "Feature",
  "properties": {
    "gn:admin1_code":"8.0",
    "gn:admin2_code":"1815.0",
    "gn:asciiname":"Al Kawkab",
    "gn:country_code":"YE",
    "gn:dem":301,
    "gn:feature_class":"P",
    "gn:feature_code":"PPL",
    "gn:name":"Al Kawkab",
    "gn:population":0,
    "gn:timezone":"Asia/Aden",
    "iso:country":"YE",
    "name:ara_x_preferred":[
        "\u0627\u0644\u0643\u0648\u0643\u0628"
    ],
    "wof:name":"Al Kawkab",
    "wof:placetype":"locality"
},
  "geometry": {"coordinates":[43.4541,14.81594],"type":"Point"}
}