{
  "type": "Feature",
  "properties": {
    "gn:admin1_code":"11.0",
    "gn:admin2_code":"2001.0",
    "gn:asciiname":"Al Jaharinah",
    "gn:country_code":"YE",
    "gn:dem":2444,
    "gn:feature_class":"P",
    "gn:feature_code":"PPL",
    "gn:name":"Al Jah\u0101rinah",
    "gn:population":0,
    "gn:timezone":"Asia/Aden",
    "iso:country":"YE",
    "name:und_x_variant":[
        "Al Jah\u0101rinah"
    ],
    "wof:name":"Al Jaharinah",
    "wof:placetype":"locality"
},
  "geometry": {"coordinates":[44.36846,14.96931],"type":"Point"}
}