{
  "type": "Feature",
  "properties": {
    "gn:admin1_code":"11.0",
    "gn:admin2_code":"2011.0",
    "gn:asciiname":"Sayban",
    "gn:country_code":"YE",
    "gn:dem":1163,
    "gn:feature_class":"P",
    "gn:feature_code":"PPL",
    "gn:name":"Sayb\u0101n",
    "gn:population":0,
    "gn:timezone":"Asia/Aden",
    "iso:country":"YE",
    "name:und_x_variant":[
        "Sayb\u0101n"
    ],
    "wof:name":"Sayban",
    "wof:placetype":"locality"
},
  "geometry": {"coordinates":[43.91195,14.84867],"type":"Point"}
}