{
  "type": "Feature",
  "properties": {
    "gn:country":"YE",
    "gn:fcode":"PPLX",
    "gn:pop":116,
    "iso:country":"YE",
    "name:ara_x_preferred":[
        "\u0627\u0644\u0645\u0631\u0629 \u0627\u0644\u0633\u0641\u0644\u0649"
    ],
    "qs:name":"Al Murrah as Sufl\u00e1",
    "qs:photos_9r":0,
    "qs:photos_sr":0,
    "qs:pop_sr":"1",
    "wof:name":"Al Murrah as Sufl\u00e1",
    "wof:placetype":"neighbourhood",
    "wof:population":116
},
  "geometry": {"coordinates":[43.55586,13.49926],"type":"Point"}
}