{
  "type": "Feature",
  "properties": {
    "gn:admin1_code":"19.0",
    "gn:admin2_code":"2903.0",
    "gn:asciiname":"Abu Hajar",
    "gn:country_code":"YE",
    "gn:dem":1134,
    "gn:feature_class":"P",
    "gn:feature_code":"PPL",
    "gn:name":"Ab\u016b Haj\u0101r",
    "gn:population":0,
    "gn:timezone":"Asia/Aden",
    "iso:country":"YE",
    "name:ara_x_preferred":[
        "\u0623\u0628\u0648 \u0647\u062c\u0627\u0631"
    ],
    "name:und_x_variant":[
        "Ab\u016b Haj\u0101r"
    ],
    "wof:name":"Abu Hajar",
    "wof:placetype":"locality"
},
  "geometry": {"coordinates":[43.81111,16.18998],"type":"Point"}
}