{
  "type": "Feature",
  "properties": {
    "gn:country":"YE",
    "gn:fcode":"PPL",
    "gn:population":2,
    "iso:country":"YE",
    "name:ara_x_preferred":[
        "\u0627\u0644\u0631\u0627\u0642\u0629"
    ],
    "qs:name":"Ar R\u0101qah",
    "qs:photos_9r":0,
    "qs:photos_sr":0,
    "qs:pop_sr":"1",
    "wof:name":"Ar R\u0101qah",
    "wof:placetype":"locality",
    "wof:population":2
},
  "geometry": {"coordinates":[44.48905,16.68828],"type":"Point"}
}