{
  "type": "Feature",
  "properties": {
    "gn:admin1_code":"11.0",
    "gn:admin2_code":"2011.0",
    "gn:asciiname":"Al Harf",
    "gn:country_code":"YE",
    "gn:dem":1509,
    "gn:feature_class":"P",
    "gn:feature_code":"PPL",
    "gn:name":"Al \u1e28arf",
    "gn:population":0,
    "gn:timezone":"Asia/Aden",
    "iso:country":"YE",
    "name:und_x_variant":[
        "Al \u1e28arf"
    ],
    "wof:name":"Al Harf",
    "wof:placetype":"locality"
},
  "geometry": {"coordinates":[43.99269,14.81612],"type":"Point"}
}