{
  "type": "Feature",
  "properties": {
    "gn:admin1_code":"18.0",
    "gn:admin2_code":"3007.0",
    "gn:asciiname":"Qarnah",
    "gn:country_code":"YE",
    "gn:dem":2083,
    "gn:feature_class":"P",
    "gn:feature_code":"PPL",
    "gn:name":"Qarnah",
    "gn:population":0,
    "gn:timezone":"Asia/Aden",
    "iso:country":"YE",
    "name:und_x_variant":[
        "Karna",
        "Qarnah"
    ],
    "wof:name":"Qarnah",
    "wof:placetype":"locality"
},
  "geometry": {"coordinates":[44.68923,13.74321],"type":"Point"}
}