{
  "type": "Feature",
  "properties": {
    "gn:admin1_code":"25.0",
    "gn:admin2_code":"1515.0",
    "gn:asciiname":"Shuba`ah",
    "gn:country_code":"YE",
    "gn:dem":1383,
    "gn:feature_class":"P",
    "gn:feature_code":"PPL",
    "gn:name":"Shub\u0101\u2018ah",
    "gn:population":0,
    "gn:timezone":"Asia/Aden",
    "iso:country":"YE",
    "name:und_x_variant":[
        "Shub\u0101\u2018ah"
    ],
    "wof:name":"Shuba`ah",
    "wof:placetype":"locality"
},
  "geometry": {"coordinates":[44.04723,13.18404],"type":"Point"}
}