{
  "type": "Feature",
  "properties": {
    "gn:admin1_code":"16.0",
    "gn:admin2_code":"2307.0",
    "gn:asciiname":"Al Ashraf",
    "gn:country_code":"YE",
    "gn:dem":2682,
    "gn:feature_class":"P",
    "gn:feature_code":"PPL",
    "gn:name":"Al Ashr\u0101f",
    "gn:population":0,
    "gn:timezone":"Asia/Aden",
    "iso:country":"YE",
    "name:ara_x_preferred":[
        "Al Ashr\u0101f"
    ],
    "wof:name":"Al Ashraf",
    "wof:placetype":"locality"
},
  "geometry": {"coordinates":[44.01008,15.22767],"type":"Point"}
}