{
  "type": "Feature",
  "properties": {
    "gn:admin1_code":"22.0",
    "gn:admin2_code":"1715.0",
    "gn:asciiname":"Al Qadd",
    "gn:country_code":"YE",
    "gn:dem":1566,
    "gn:feature_class":"P",
    "gn:feature_code":"PPL",
    "gn:name":"Al Qadd",
    "gn:population":0,
    "gn:timezone":"Asia/Aden",
    "iso:country":"YE",
    "wof:name":"Al Qadd",
    "wof:placetype":"locality"
},
  "geometry": {"coordinates":[43.44128,15.96375],"type":"Point"}
}