{
  "type": "Feature",
  "properties": {
    "gn:admin1_code":"20.0",
    "gn:admin2_code":"1417.0",
    "gn:asciiname":"Farghan",
    "gn:country_code":"YE",
    "gn:dem":2553,
    "gn:feature_class":"P",
    "gn:feature_code":"PPL",
    "gn:name":"Fargh\u0101n",
    "gn:population":0,
    "gn:timezone":"Asia/Aden",
    "iso:country":"YE",
    "name:und_x_variant":[
        "Fargh\u0101n"
    ],
    "wof:name":"Farghan",
    "wof:placetype":"locality"
},
  "geometry": {"coordinates":[44.67302,14.23474],"type":"Point"}
}