{
  "type": "Feature",
  "properties": {
    "gn:admin1_code":"11.0",
    "gn:asciiname":"Al Maryamah",
    "gn:country_code":"YE",
    "gn:dem":2439,
    "gn:feature_class":"P",
    "gn:feature_code":"PPL",
    "gn:name":"Al Maryamah",
    "gn:population":0,
    "gn:timezone":"Asia/Aden",
    "iso:country":"YE",
    "name:ara_x_preferred":[
        "\u0627\u0644\u0645\u0631\u064a\u0645\u0629"
    ],
    "wof:name":"Al Maryamah",
    "wof:placetype":"locality"
},
  "geometry": {"coordinates":[44.45589,14.28971],"type":"Point"}
}