{
  "type": "Feature",
  "properties": {
    "gn:admin1_code":"14.0",
    "gn:admin2_code":"1403.0",
    "gn:asciiname":"Shay`an",
    "gn:country_code":"YE",
    "gn:dem":1780,
    "gn:feature_class":"P",
    "gn:feature_code":"PPL",
    "gn:name":"Shay`\u0101n",
    "gn:population":0,
    "gn:timezone":"Asia/Aden",
    "iso:country":"YE",
    "wof:name":"Shay`an",
    "wof:placetype":"locality"
},
  "geometry": {"coordinates":[45.66667,14.375],"type":"Point"}
}