{
  "type": "Feature",
  "properties": {
    "gn:admin1_code":"8.0",
    "gn:admin2_code":"1807.0",
    "gn:asciiname":"Miftah",
    "gn:country_code":"YE",
    "gn:dem":100,
    "gn:feature_class":"P",
    "gn:feature_code":"PPL",
    "gn:name":"Mift\u0101\u1e29",
    "gn:population":0,
    "gn:timezone":"Asia/Aden",
    "iso:country":"YE",
    "name:ara_x_preferred":[
        "Mift\u0101\u1e29"
    ],
    "wof:name":"Miftah",
    "wof:placetype":"locality"
},
  "geometry": {"coordinates":[43.15593,15.42297],"type":"Point"}
}