{
  "type": "Feature",
  "properties": {
    "gn:admin1_code":"25.0",
    "gn:admin2_code":"1505.0",
    "gn:asciiname":"Sahaban",
    "gn:country_code":"YE",
    "gn:dem":757,
    "gn:feature_class":"P",
    "gn:feature_code":"PPL",
    "gn:name":"Sahaban",
    "gn:population":0,
    "gn:timezone":"Asia/Aden",
    "iso:country":"YE",
    "wof:name":"Sahaban",
    "wof:placetype":"locality"
},
  "geometry": {"coordinates":[43.70748,13.7284],"type":"Point"}
}