{
  "type": "Feature",
  "properties": {
    "gn:admin1_code":"5.0",
    "gn:admin2_code":"2106.0",
    "gn:asciiname":"Shaqir",
    "gn:country_code":"YE",
    "gn:dem":1163,
    "gn:elevation":"2.0",
    "gn:feature_class":"P",
    "gn:feature_code":"PPL",
    "gn:name":"Shaq\u012br",
    "gn:population":0,
    "gn:timezone":"Asia/Aden",
    "iso:country":"YE",
    "name:und_x_variant":[
        "Shaq\u012br"
    ],
    "wof:name":"Shaqir",
    "wof:placetype":"locality"
},
  "geometry": {"coordinates":[45.51975,14.93077],"type":"Point"}
}