{
  "type": "Feature",
  "properties": {
    "gn:country":"YE",
    "gn:fcode":"PPLX",
    "gn:pop":9,
    "iso:country":"YE",
    "name:ara_x_preferred":[
        "Dh\u016b F\u0101yin"
    ],
    "name:ara_x_variant":[
        "\u0630\u0648 \u0641\u0627\u064a\u0646"
    ],
    "qs:name":"Dh\u016b F\u0101yin",
    "qs:photos_9r":0,
    "qs:photos_sr":0,
    "qs:pop_sr":"1",
    "wof:name":"Dh\u016b F\u0101yin",
    "wof:placetype":"neighbourhood",
    "wof:population":9
},
  "geometry": {"coordinates":[43.84246,16.80779],"type":"Point"}
}