{
  "type": "Feature",
  "properties": {
    "gn:country":"YE",
    "gn:fcode":"PPL",
    "gn:pop":2,
    "iso:country":"YE",
    "name:ara_x_preferred":[
        "\u0639\u062c\u0645\u0629 \u0627\u0644\u0642\u0641\u0644\u0629"
    ],
    "name:eng_x_preferred":[
        "Ajmat Al Quflah"
    ],
    "name:eng_x_variant":[
        "Al Mad\u0101rah",
        "'Ajmat Al Quflah"
    ],
    "qs:name":"\u2018Ajmat al Quflah",
    "qs:photos_9r":0,
    "qs:photos_sr":0,
    "qs:pop_sr":"1",
    "wof:name":"\u2018Ajmat al Quflah",
    "wof:placetype":"locality",
    "wof:population":2
},
  "geometry": {"coordinates":[45.46889,14.838],"type":"Point"}
}