{
  "type": "Feature",
  "properties": {
    "gn:admin1_code":"23.0",
    "gn:admin2_code":"1113.0",
    "gn:asciiname":"Haql",
    "gn:country_code":"YE",
    "gn:dem":2419,
    "gn:feature_class":"P",
    "gn:feature_code":"PPL",
    "gn:name":"\u1e28aql",
    "gn:population":0,
    "gn:timezone":"Asia/Aden",
    "iso:country":"YE",
    "name:ara_x_preferred":[
        "\u062d\u0642\u0644"
    ],
    "name:und_x_variant":[
        "\u1e28aql"
    ],
    "wof:name":"Haql",
    "wof:placetype":"locality"
},
  "geometry": {"coordinates":[44.25592,14.0484],"type":"Point"}
}