{
  "type": "Feature",
  "properties": {
    "gn:admin1_code":"23.0",
    "gn:admin2_code":"1113.0",
    "gn:asciiname":"Haql",
    "gn:country_code":"YE",
    "gn:dem":2419,
    "gn:feature_class":"P",
    "gn:feature_code":"PPL",
    "gn:name":"\u1e28aql",
    "gn:population":0,
    "gn:timezone":"Asia/Aden",
    "iso:country":"YE",
    "name:ara_x_preferred":[
        "\u062d\u0642\u0644"
    ],
    "name:ara_x_variant":[
        "\u0645\u062d\u0627\u0641\u0638\u0629 \u062d\u0642\u0644"
    ],
    "name:fas_x_preferred":[
        "\u062d\u0642\u0644"
    ],
    "name:heb_x_preferred":[
        "\u05d7\u05e7\u05dc"
    ],
    "name:nld_x_preferred":[
        "Haql"
    ],
    "name:nno_x_preferred":[
        "Haql"
    ],
    "name:pol_x_preferred":[
        "Hakl"
    ],
    "name:rus_x_preferred":[
        "\u0425\u0430\u043a\u043b\u044c"
    ],
    "name:spa_x_preferred":[
        "Haql"
    ],
    "name:tgl_x_preferred":[
        "Haql"
    ],
    "name:tur_x_preferred":[
        "Hakl"
    ],
    "name:und_x_variant":[
        "\u1e28aql"
    ],
    "name:urd_x_preferred":[
        "\u062d\u0642\u0644"
    ],
    "wof:name":"Haql",
    "wof:placetype":"locality"
},
  "geometry": {"coordinates":[44.25592,14.0484],"type":"Point"}
}