{
  "type": "Feature",
  "properties": {
    "gn:admin1_code":"19.0",
    "gn:admin2_code":"2908.0",
    "gn:asciiname":"Mahall Abu Hijar",
    "gn:country_code":"YE",
    "gn:dem":1006,
    "gn:feature_class":"P",
    "gn:feature_code":"PPL",
    "gn:name":"Ma\u1e29all Ab\u016b Hij\u0101r",
    "gn:population":0,
    "gn:timezone":"Asia/Aden",
    "iso:country":"YE",
    "name:und_x_variant":[
        "Ma\u1e29all Ab\u016b Hij\u0101r"
    ],
    "wof:name":"Mahall Abu Hijar",
    "wof:placetype":"locality"
},
  "geometry": {"coordinates":[43.7525,16.05544],"type":"Point"}
}