{
  "type": "Feature",
  "properties": {
    "gn:country":"YE",
    "gn:fcode":"PPL",
    "gn:pop":20,
    "iso:country":"YE",
    "name:ara_x_preferred":[
        "\u0627\u0644 \u0634\u0645\u064a\u0644\u0629"
    ],
    "name:eng_x_preferred":[
        "Al Shamilah"
    ],
    "qs:name":"\u0100l Sham\u012blah",
    "qs:photos_9r":0,
    "qs:photos_sr":0,
    "qs:pop_sr":"1",
    "wof:name":"\u0100l Sham\u012blah",
    "wof:placetype":"locality",
    "wof:population":20
},
  "geometry": {"coordinates":[43.49273,16.88631],"type":"Point"}
}