{
  "type": "Feature",
  "properties": {
    "gn:admin1_code":"23.0",
    "gn:admin2_code":"1106.0",
    "gn:asciiname":"Hawrah",
    "gn:country_code":"YE",
    "gn:dem":2611,
    "gn:feature_class":"P",
    "gn:feature_code":"PPL",
    "gn:name":"\u1e28awrah",
    "gn:population":0,
    "gn:timezone":"Asia/Aden",
    "iso:country":"YE",
    "name:ara_x_preferred":[
        "\u062d\u0648\u0631\u0629"
    ],
    "name:und_x_variant":[
        "\u1e28awrah"
    ],
    "wof:name":"Hawrah",
    "wof:placetype":"locality"
},
  "geometry": {"coordinates":[44.38705,14.16125],"type":"Point"}
}