{
  "type": "Feature",
  "properties": {
    "gn:admin1_code":"23.0",
    "gn:admin2_code":"1105.0",
    "gn:asciiname":"Al `Umqi",
    "gn:country_code":"YE",
    "gn:dem":2628,
    "gn:feature_class":"P",
    "gn:feature_code":"PPL",
    "gn:name":"Al \u2018Umq\u012b",
    "gn:population":0,
    "gn:timezone":"Asia/Aden",
    "iso:country":"YE",
    "name:ara_x_preferred":[
        "\u0627\u0644\u0639\u0645\u0642\u064a"
    ],
    "name:und_x_variant":[
        "Al \u2018Umaq\u012b",
        "Al \u2018Umq\u012b"
    ],
    "wof:name":"Al `Umqi",
    "wof:placetype":"locality"
},
  "geometry": {"coordinates":[44.38488,14.07862],"type":"Point"}
}