{
  "type": "Feature",
  "properties": {
    "gn:admin1_code":"16.0",
    "gn:admin2_code":"2307.0",
    "gn:asciiname":"Yazil",
    "gn:country_code":"YE",
    "gn:dem":2841,
    "gn:feature_class":"P",
    "gn:feature_code":"PPL",
    "gn:name":"Y\u0101zil",
    "gn:population":0,
    "gn:timezone":"Asia/Aden",
    "iso:country":"YE",
    "name:ara_x_preferred":[
        "Y\u0101zil"
    ],
    "wof:name":"Yazil",
    "wof:placetype":"locality"
},
  "geometry": {"coordinates":[43.99097,15.23344],"type":"Point"}
}