{
  "type": "Feature",
  "properties": {
    "gn:admin1_code":"15.0",
    "gn:admin2_code":"2202.0",
    "gn:asciiname":"Ath Thahir",
    "gn:country_code":"YE",
    "gn:dem":1655,
    "gn:feature_class":"P",
    "gn:feature_code":"PPL",
    "gn:name":"Ath Th\u0101hir",
    "gn:population":0,
    "gn:timezone":"Asia/Aden",
    "iso:country":"YE",
    "name:ara_x_preferred":[
        "Ath Th\u0101hir"
    ],
    "name:ara_x_variant":[
        "\u0627\u0644\u062b\u0627\u0647\u0631"
    ],
    "wof:name":"Ath Thahir",
    "wof:placetype":"locality"
},
  "geometry": {"coordinates":[43.30048,17.37232],"type":"Point"}
}