{
  "type": "Feature",
  "properties": {
    "gn:admin1_code":"11.0",
    "gn:admin2_code":"2004.0",
    "gn:asciiname":"Ahjar",
    "gn:country_code":"YE",
    "gn:dem":2341,
    "gn:feature_class":"P",
    "gn:feature_code":"PPL",
    "gn:name":"A\u1e29jar",
    "gn:population":0,
    "gn:timezone":"Asia/Aden",
    "iso:country":"YE",
    "name:und_x_variant":[
        "A\u1e29jar"
    ],
    "wof:name":"Ahjar",
    "wof:placetype":"locality"
},
  "geometry": {"coordinates":[44.17415,14.55446],"type":"Point"}
}