{
  "type": "Feature",
  "properties": {
    "gn:admin1_code":"23.0",
    "gn:admin2_code":"1108.0",
    "gn:asciiname":"`Akab",
    "gn:country_code":"YE",
    "gn:dem":2410,
    "gn:feature_class":"P",
    "gn:feature_code":"PPL",
    "gn:name":"\u2018Akab",
    "gn:population":0,
    "gn:timezone":"Asia/Aden",
    "iso:country":"YE",
    "name:ara_x_preferred":[
        "\u0639\u0643\u0628"
    ],
    "name:und_x_variant":[
        "\u2018Akab"
    ],
    "wof:name":"`Akab",
    "wof:placetype":"locality"
},
  "geometry": {"coordinates":[44.08638,14.04413],"type":"Point"}
}