{
  "type": "Feature",
  "properties": {
    "gn:admin1_code":"15.0",
    "gn:admin2_code":"2214.0",
    "gn:asciiname":"Al `Ushash",
    "gn:country_code":"YE",
    "gn:dem":2005,
    "gn:feature_class":"P",
    "gn:feature_code":"PPL",
    "gn:name":"Al \u2018Ush\u0101sh",
    "gn:population":0,
    "gn:timezone":"Asia/Aden",
    "iso:country":"YE",
    "name:ara_x_preferred":[
        "Al \u2018Ush\u0101sh"
    ],
    "name:ara_x_variant":[
        "\u0627\u0644\u0639\u0634\u0627\u0634"
    ],
    "wof:name":"Al `Ushash",
    "wof:placetype":"locality"
},
  "geometry": {"coordinates":[43.97857,17.03313],"type":"Point"}
}