{
  "type": "Feature",
  "properties": {
    "gn:admin1_code":"4.0",
    "gn:admin2_code":"1919.0",
    "gn:asciiname":"Hisn Duwid",
    "gn:cc2":"YE",
    "gn:country_code":"YE",
    "gn:dem":707,
    "gn:feature_class":"P",
    "gn:feature_code":"PPL",
    "gn:name":"\u1e28i\u015fn D\u016bwid",
    "gn:population":0,
    "gn:timezone":"Asia/Aden",
    "iso:country":"YE",
    "name:ara_x_preferred":[
        "\u1e28i\u015fn D\u016bwid"
    ],
    "name:und_x_variant":[
        "\u1e24u\u1e63n \u0100l-Duw\u012bl",
        "\u1e24u\u1e63n D\u016bwid"
    ],
    "wof:name":"Hisn Duwid",
    "wof:placetype":"locality"
},
  "geometry": {"coordinates":[48.13333,15.73333],"type":"Point"}
}