{
  "type": "Feature",
  "properties": {
    "gn:admin1_code":"15.0",
    "gn:admin2_code":"2212.0",
    "gn:asciiname":"Khidran",
    "gn:country_code":"YE",
    "gn:dem":1602,
    "gn:feature_class":"P",
    "gn:feature_code":"PPL",
    "gn:name":"Khidr\u0101n",
    "gn:population":0,
    "gn:timezone":"Asia/Aden",
    "iso:country":"YE",
    "name:ara_x_preferred":[
        "Khidr\u0101n"
    ],
    "wof:name":"Khidran",
    "wof:placetype":"locality"
},
  "geometry": {"coordinates":[43.98423,16.7131],"type":"Point"}
}