{
  "type": "Feature",
  "properties": {
    "gn:admin1_code":"10.0",
    "gn:admin2_code":"2709.0",
    "gn:asciiname":"Bayt ar Razzaq",
    "gn:country_code":"YE",
    "gn:dem":1244,
    "gn:feature_class":"P",
    "gn:feature_code":"PPL",
    "gn:name":"Bayt ar Razz\u0101q",
    "gn:population":0,
    "gn:timezone":"Asia/Aden",
    "iso:country":"YE",
    "name:und_x_variant":[
        "Bayt ar Razz\u0101q"
    ],
    "wof:name":"Bayt ar Razzaq",
    "wof:placetype":"locality"
},
  "geometry": {"coordinates":[43.57734,15.39019],"type":"Point"}
}