{
  "type": "Feature",
  "properties": {
    "gn:admin1_code":"15.0",
    "gn:admin2_code":"2205.0",
    "gn:asciiname":"Al 'Aydan",
    "gn:country_code":"YE",
    "gn:dem":1489,
    "gn:feature_class":"P",
    "gn:feature_code":"PPL",
    "gn:name":"\u0100l \u2018Ayd\u0101n",
    "gn:population":0,
    "gn:timezone":"Asia/Aden",
    "iso:country":"YE",
    "name:ara_x_preferred":[
        "\u0100l \u2018Ayd\u0101n"
    ],
    "name:ara_x_variant":[
        "\u0627\u0644 \u0639\u064a\u062f\u0627\u0646"
    ],
    "wof:name":"Al 'Aydan",
    "wof:placetype":"locality"
},
  "geometry": {"coordinates":[43.24453,16.91194],"type":"Point"}
}