{
  "type": "Feature",
  "properties": {
    "gn:country":"YE",
    "gn:fcode":"PPL",
    "gn:pop":2,
    "iso:country":"YE",
    "name:ara_x_preferred":[
        "\u0627\u0644\u0645\u0633\u0644\u062e"
    ],
    "name:eng_x_preferred":[
        "Al Maslakh"
    ],
    "name:eng_x_variant":[
        "Al Quma\u2018"
    ],
    "qs:name":"Al Maslakh",
    "qs:photos_9r":0,
    "qs:photos_sr":0,
    "qs:pop_sr":"1",
    "wof:name":"Al Maslakh",
    "wof:placetype":"locality",
    "wof:population":2
},
  "geometry": {"coordinates":[43.67757,16.14398],"type":"Point"}
}