{
  "type": "Feature",
  "properties": {
    "gn:admin1_code":"25.0",
    "gn:admin2_code":"1505.0",
    "gn:asciiname":"Al Wa`aylah Qarhah",
    "gn:country_code":"YE",
    "gn:dem":657,
    "gn:feature_class":"P",
    "gn:feature_code":"PPL",
    "gn:name":"Al Wa\u2018aylah Qar\u1e29ah",
    "gn:population":0,
    "gn:timezone":"Asia/Aden",
    "iso:country":"YE",
    "name:und_x_variant":[
        "Al Wa\u2018aylah Qar\u1e29ah"
    ],
    "wof:name":"Al Wa`aylah Qarhah",
    "wof:placetype":"locality"
},
  "geometry": {"coordinates":[43.66162,13.57635],"type":"Point"}
}