{
  "type": "Feature",
  "properties": {
    "gn:country":"YE",
    "gn:fcode":"PPL",
    "gn:pop":8,
    "iso:country":"YE",
    "name:ara_x_preferred":[
        "Al Mu\u1e29\u0101jin"
    ],
    "name:ara_x_variant":[
        "\u0627\u0644\u0645\u062d\u0627\u062c\u0646"
    ],
    "name:eng_x_preferred":[
        "Al Muhajin"
    ],
    "qs:name":"Al Mu\u1e29\u0101jin",
    "qs:photos_9r":0,
    "qs:photos_sr":0,
    "qs:pop_sr":"1",
    "wof:name":"Al Mu\u1e29\u0101jin",
    "wof:placetype":"locality",
    "wof:population":8
},
  "geometry": {"coordinates":[43.69671,16.13701],"type":"Point"}
}