{
  "type": "Feature",
  "properties": {
    "gn:gn_country":"YE",
    "gn:gn_fcode":"PPL",
    "gn:gn_pop":1,
    "gn:population":1,
    "iso:country":"YE",
    "name:ara_x_preferred":[
        "\u062d\u0635\u064a\u0628 \u064a\u0627\u0633\u064a\u0646"
    ],
    "name:eng_x_preferred":[
        "Hasib Yasin"
    ],
    "qs_pg:aaroncc":"YE",
    "qs_pg:gn_country":"YE",
    "qs_pg:gn_fcode":"PPL",
    "qs_pg:gn_pop":1,
    "qs_pg:name":"\u1e28a\u015f\u012bb Y\u0101s\u012bn",
    "qs_pg:photos_9r":0,
    "qs_pg:photos_sr":0,
    "qs_pg:pop_sr":1,
    "qs_pg:qs_pg_placetype":"locality",
    "wof:name":"\u1e28a\u015f\u012bb Y\u0101s\u012bn",
    "wof:placetype":"locality",
    "wof:population":1
},
  "geometry": {"coordinates":[43.78114,13.48626],"type":"Point"}
}