{
  "type": "Feature",
  "properties": {
    "gn:admin1_code":"22.0",
    "gn:admin2_code":"1720.0",
    "gn:asciiname":"Az Zafir",
    "gn:country_code":"YE",
    "gn:dem":1949,
    "gn:feature_class":"P",
    "gn:feature_code":"PPL",
    "gn:name":"Az\u0327 Z\u0327af\u012br",
    "gn:population":0,
    "gn:timezone":"Asia/Aden",
    "iso:country":"YE",
    "name:nno_x_preferred":[
        "Az Zafir"
    ],
    "name:und_x_variant":[
        "Az\u0327 Z\u0327af\u012br"
    ],
    "wof:name":"Az Zafir",
    "wof:placetype":"locality"
},
  "geometry": {"coordinates":[43.59745,15.76336],"type":"Point"}
}