{
  "type": "Feature",
  "properties": {
    "gn:country":"YE",
    "gn:fcode":"PPL",
    "gn:pop":1,
    "iso:country":"YE",
    "name:ara_x_preferred":[
        "\u063a\u0627\u0631\u0628 \u0627\u0644\u0628\u0631\u0648\u064a\u0640\u0629"
    ],
    "name:ara_x_variant":[
        "\u063a\u0627\u0631\u0628 \u0627\u0644\u0628\u0631\u0648\u064a\u0629"
    ],
    "name:eng_x_preferred":[
        "Gharib Al Birwiyah"
    ],
    "name:eng_x_variant":[
        "\u1e28ab\u0163\u0101\u2019"
    ],
    "qs:name":"Gh\u0101rib al Birw\u012byah",
    "qs:photos_9r":0,
    "qs:photos_sr":0,
    "qs:pop_sr":"1",
    "wof:name":"Gh\u0101rib al Birw\u012byah",
    "wof:placetype":"locality",
    "wof:population":1
},
  "geometry": {"coordinates":[43.43611,16.42006],"type":"Point"}
}