{
  "type": "Feature",
  "properties": {
    "gn:admin1_code":"25.0",
    "gn:admin2_code":"1502.0",
    "gn:asciiname":"Al Alwah",
    "gn:country_code":"YE",
    "gn:dem":1091,
    "gn:feature_class":"P",
    "gn:feature_code":"PPL",
    "gn:name":"Al Alw\u0101\u1e29",
    "gn:population":0,
    "gn:timezone":"Asia/Aden",
    "iso:country":"YE",
    "name:ara_x_preferred":[
        "Al Alw\u0101\u1e29"
    ],
    "wof:name":"Al Alwah",
    "wof:placetype":"locality"
},
  "geometry": {"coordinates":[43.93666,13.57965],"type":"Point"}
}