{
  "type": "Feature",
  "properties": {
    "gn:admin1_code":"8.0",
    "gn:admin2_code":"1808.0",
    "gn:asciiname":"Mahall ar Rayh",
    "gn:country_code":"YE",
    "gn:dem":117,
    "gn:feature_class":"P",
    "gn:feature_code":"PPL",
    "gn:name":"Ma\u1e29all ar Ray\u1e29",
    "gn:population":0,
    "gn:timezone":"Asia/Aden",
    "iso:country":"YE",
    "name:und_x_variant":[
        "Ma\u1e29all ar Ray\u1e29"
    ],
    "wof:name":"Mahall ar Rayh",
    "wof:placetype":"locality"
},
  "geometry": {"coordinates":[43.1475,15.26274],"type":"Point"}
}