{
  "type": "Feature",
  "properties": {
    "gn:admin1_code":"16.0",
    "gn:admin2_code":"2305.0",
    "gn:asciiname":"Bayt al `Ansi",
    "gn:country_code":"YE",
    "gn:dem":2321,
    "gn:feature_class":"P",
    "gn:feature_code":"PPL",
    "gn:name":"Bayt al \u2018Ans\u012b",
    "gn:population":0,
    "gn:timezone":"Asia/Aden",
    "iso:country":"YE",
    "name:und_x_variant":[
        "Bayt al \u2018Ans\u012b"
    ],
    "wof:name":"Bayt al `Ansi",
    "wof:placetype":"locality"
},
  "geometry": {"coordinates":[44.24108,15.13357],"type":"Point"}
}