{
  "type": "Feature",
  "properties": {
    "gn:country":"YE",
    "gn:fcode":"PPL",
    "gn:population":8,
    "iso:country":"YE",
    "name:ara_x_preferred":[
        "\u0627\u0644 \u0631\u064a\u062d\u0627\u0646"
    ],
    "name:eng_x_preferred":[
        "Al Rayhan"
    ],
    "name:eng_x_variant":[
        "Midh\u0101f\u012b"
    ],
    "qs:name":"\u0100l Ray\u1e29\u0101n",
    "qs:photos_9r":0,
    "qs:photos_sr":0,
    "qs:pop_sr":"1",
    "wof:name":"\u0100l Ray\u1e29\u0101n",
    "wof:placetype":"locality",
    "wof:population":8
},
  "geometry": {"coordinates":[44.47711,16.63368],"type":"Point"}
}