{
  "type": "Feature",
  "properties": {
    "gn:admin1_code":"16.0",
    "gn:admin2_code":"2312.0",
    "gn:asciiname":"An Nijad",
    "gn:country_code":"YE",
    "gn:dem":1702,
    "gn:feature_class":"P",
    "gn:feature_code":"PPL",
    "gn:name":"An Nij\u0101d",
    "gn:population":0,
    "gn:timezone":"Asia/Aden",
    "iso:country":"YE",
    "name:ara_x_preferred":[
        "\u0627\u0644\u0646\u062c\u0627\u062f"
    ],
    "name:und_x_variant":[
        "An Nij\u0101d"
    ],
    "wof:name":"An Nijad",
    "wof:placetype":"locality"
},
  "geometry": {"coordinates":[44.87089,15.32734],"type":"Point"}
}