{
  "type": "Feature",
  "properties": {
    "gn:admin1_code":"19.0",
    "gn:admin2_code":"2903.0",
    "gn:asciiname":"Al Maflaq",
    "gn:country_code":"YE",
    "gn:dem":1267,
    "gn:feature_class":"P",
    "gn:feature_code":"PPL",
    "gn:name":"Al Maflaq",
    "gn:population":0,
    "gn:timezone":"Asia/Aden",
    "iso:country":"YE",
    "name:ara_x_preferred":[
        "\u0627\u0644\u0645\u0641\u0644\u0642"
    ],
    "wof:name":"Al Maflaq",
    "wof:placetype":"locality"
},
  "geometry": {"coordinates":[43.79299,16.31622999999999],"type":"Point"}
}