{
  "type": "Feature",
  "properties": {
    "gn:admin1_code":"24.0",
    "gn:admin2_code":"2512.0",
    "gn:asciiname":"Bayt Su'ad",
    "gn:country_code":"YE",
    "gn:dem":1300,
    "gn:feature_class":"P",
    "gn:feature_code":"PPL",
    "gn:name":"Bayt Su\u2018\u0101d",
    "gn:population":0,
    "gn:timezone":"Asia/Aden",
    "iso:country":"YE",
    "name:ara_x_preferred":[
        "\u0628\u064a\u062a \u0633\u0639\u0627\u062f"
    ],
    "name:und_x_variant":[
        "Bayt Su\u2018\u0101d"
    ],
    "wof:name":"Bayt Su'ad",
    "wof:placetype":"locality"
},
  "geometry": {"coordinates":[44.20022,13.16597],"type":"Point"}
}