{
  "type": "Feature",
  "properties": {
    "gn:admin1_code":"4.0",
    "gn:admin2_code":"1910.0",
    "gn:asciiname":"Dahamah",
    "gn:country_code":"YE",
    "gn:dem":636,
    "gn:feature_class":"P",
    "gn:feature_code":"PPL",
    "gn:name":"Da\u1e29\u0101mah",
    "gn:population":0,
    "gn:timezone":"Asia/Aden",
    "iso:country":"YE",
    "name:und_x_variant":[
        "Da\u1e29\u0101mah"
    ],
    "wof:name":"Dahamah",
    "wof:placetype":"locality"
},
  "geometry": {"coordinates":[48.85278,16.01306],"type":"Point"}
}