{
  "type": "Feature",
  "properties": {
    "gn:country":"YE",
    "gn:fcode":"PPL",
    "gn:pop":5,
    "iso:country":"YE",
    "name:ara_x_preferred":[
        "\u0627\u0644\u0645\u0642\u0646\u0639"
    ],
    "name:eng_x_preferred":[
        "Al Maqna'"
    ],
    "qs:name":"Al Maqna\u2018",
    "qs:photos_9r":0,
    "qs:photos_sr":0,
    "qs:pop_sr":"1",
    "wof:name":"Al Maqna\u2018",
    "wof:placetype":"locality",
    "wof:population":5
},
  "geometry": {"coordinates":[45.38862,14.32518],"type":"Point"}
}