{
  "type": "Feature",
  "properties": {
    "gn:admin1_code":"11.0",
    "gn:admin2_code":"2005.0",
    "gn:asciiname":"Tilmid Dayn",
    "gn:country_code":"YE",
    "gn:dem":2100,
    "gn:feature_class":"P",
    "gn:feature_code":"PPL",
    "gn:name":"Tilmid Dayn",
    "gn:population":0,
    "gn:timezone":"Asia/Aden",
    "iso:country":"YE",
    "wof:name":"Tilmid Dayn",
    "wof:placetype":"locality"
},
  "geometry": {"coordinates":[44.02283,14.49924],"type":"Point"}
}