{
  "type": "Feature",
  "properties": {
    "gn:admin1_code":"8.0",
    "gn:admin2_code":"1812.0",
    "gn:asciiname":"Ar Ramah",
    "gn:country_code":"YE",
    "gn:dem":1069,
    "gn:feature_class":"P",
    "gn:feature_code":"PPLL",
    "gn:name":"Ar R\u0101mah",
    "gn:population":0,
    "gn:timezone":"Asia/Aden",
    "iso:country":"YE",
    "name:ara_x_preferred":[
        "\u0627\u0644\u0631\u0627\u0645\u0629"
    ],
    "name:und_x_variant":[
        "Ar R\u0101mah"
    ],
    "wof:name":"Ar Ramah",
    "wof:placetype":"locality"
},
  "geometry": {"coordinates":[43.43626,14.92342],"type":"Point"}
}