{
  "type": "Feature",
  "properties": {
    "gn:admin1_code":"22.0",
    "gn:admin2_code":"1727.0",
    "gn:asciiname":"Bayt al Hijrah",
    "gn:country_code":"YE",
    "gn:dem":1134,
    "gn:feature_class":"P",
    "gn:feature_code":"PPL",
    "gn:name":"Bayt al Hijrah",
    "gn:population":0,
    "gn:timezone":"Asia/Aden",
    "iso:country":"YE",
    "name:ara_x_preferred":[
        "\u0628\u064a\u062a \u0627\u0644\u0647\u062c\u0631\u0629"
    ],
    "wof:name":"Bayt al Hijrah",
    "wof:placetype":"locality"
},
  "geometry": {"coordinates":[43.56275,15.56828],"type":"Point"}
}