{
  "type": "Feature",
  "properties": {
    "gn:admin1_code":"11.0",
    "gn:admin2_code":"2007.0",
    "gn:asciiname":"Dindiwan",
    "gn:country_code":"YE",
    "gn:dem":1409,
    "gn:feature_class":"P",
    "gn:feature_code":"PPL",
    "gn:name":"Dindiw\u0101n",
    "gn:population":0,
    "gn:timezone":"Asia/Aden",
    "iso:country":"YE",
    "name:ara_x_preferred":[
        "Dindiw\u0101n"
    ],
    "wof:name":"Dindiwan",
    "wof:placetype":"locality"
},
  "geometry": {"coordinates":[43.62176,14.24163],"type":"Point"}
}