{
  "type": "Feature",
  "properties": {
    "gn:country":"YE",
    "gn:fcode":"PPL",
    "gn:pop":1,
    "iso:country":"YE",
    "name:ara_x_preferred":[
        "\u0627\u0644\u0631\u0648\u0628\u0629"
    ],
    "name:eng_x_preferred":[
        "Ar Rawbah"
    ],
    "name:eng_x_variant":[
        "Bi\u2019r Shir\u1e29\u016bj"
    ],
    "qs:name":"Ar Rawbah",
    "qs:photos_9r":0,
    "qs:photos_sr":0,
    "qs:pop_sr":"1",
    "wof:name":"Ar Rawbah",
    "wof:placetype":"locality",
    "wof:population":1
},
  "geometry": {"coordinates":[43.31878,16.72737],"type":"Point"}
}