{
  "type": "Feature",
  "properties": {
    "gn:admin1_code":"25.0",
    "gn:admin2_code":"1504.0",
    "gn:asciiname":"Suq al Hariyah",
    "gn:country_code":"YE",
    "gn:dem":809,
    "gn:feature_class":"P",
    "gn:feature_code":"PPL",
    "gn:name":"S\u016bq al \u1e28ar\u012byah",
    "gn:population":0,
    "gn:timezone":"Asia/Aden",
    "iso:country":"YE",
    "name:ara_x_preferred":[
        "\u0633\u0648\u0642 \u0627\u0644\u062d\u0631\u064a\u0629"
    ],
    "name:und_x_variant":[
        "S\u016bq al \u1e28ar\u012byah",
        "S\u016bq al \u1e28urr\u012byah"
    ],
    "wof:name":"Suq al Hariyah",
    "wof:placetype":"locality"
},
  "geometry": {"coordinates":[43.79735,13.84211],"type":"Point"}
}