{
  "type": "Feature",
  "properties": {
    "gn:admin1_code":"23.0",
    "gn:admin2_code":"1120.0",
    "gn:asciiname":"Jabat",
    "gn:country_code":"YE",
    "gn:dem":2425,
    "gn:feature_class":"P",
    "gn:feature_code":"PPL",
    "gn:name":"Jab\u0101t",
    "gn:population":0,
    "gn:timezone":"Asia/Aden",
    "iso:country":"YE",
    "name:und_x_variant":[
        "Jab\u0101t"
    ],
    "wof:name":"Jabat",
    "wof:placetype":"locality"
},
  "geometry": {"coordinates":[44.2082,13.95117],"type":"Point"}
}