{
  "type": "Feature",
  "properties": {
    "gn:admin1_code":"16.0",
    "gn:admin2_code":"2310.0",
    "gn:asciiname":"`Adan",
    "gn:country_code":"YE",
    "gn:dem":2183,
    "gn:feature_class":"P",
    "gn:feature_code":"PPL",
    "gn:name":"\u2018Adan",
    "gn:population":0,
    "gn:timezone":"Asia/Aden",
    "iso:country":"YE",
    "name:und_x_variant":[
        "\u2018Adan"
    ],
    "wof:name":"`Adan",
    "wof:placetype":"locality"
},
  "geometry": {"coordinates":[43.74126,15.01925],"type":"Point"}
}