{
  "type": "Feature",
  "properties": {
    "gn:admin1_code":"15.0",
    "gn:admin2_code":"2205.0",
    "gn:asciiname":"Al Ma'taq",
    "gn:country_code":"YE",
    "gn:dem":2080,
    "gn:feature_class":"P",
    "gn:feature_code":"PPL",
    "gn:name":"Al Ma\u2018taq",
    "gn:population":0,
    "gn:timezone":"Asia/Aden",
    "iso:country":"YE",
    "name:ara_x_preferred":[
        "\u0627\u0644\u0645\u0639\u062a\u0642"
    ],
    "name:und_x_variant":[
        "Al Ma\u2018taq"
    ],
    "wof:name":"Al Ma'taq",
    "wof:placetype":"locality"
},
  "geometry": {"coordinates":[43.2983,16.98022000000001],"type":"Point"}
}