{
  "type": "Feature",
  "properties": {
    "gn:admin1_code":"23.0",
    "gn:admin2_code":"3003.0",
    "gn:asciiname":"Ubalah",
    "gn:country_code":"YE",
    "gn:dem":1703,
    "gn:feature_class":"P",
    "gn:feature_code":"PPL",
    "gn:name":"Ub\u0101lah",
    "gn:population":0,
    "gn:timezone":"Asia/Aden",
    "iso:country":"YE",
    "name:und_x_variant":[
        "Ub\u0101la",
        "Ub\u0101lah"
    ],
    "wof:name":"Ubalah",
    "wof:placetype":"locality"
},
  "geometry": {"coordinates":[44.43924000000001,13.8949],"type":"Point"}
}