{
  "type": "Feature",
  "properties": {
    "gn:admin1_code":"8.0",
    "gn:admin2_code":"1824.0",
    "gn:asciiname":"Nawbat `Amir Mukaynis",
    "gn:country_code":"YE",
    "gn:dem":144,
    "gn:feature_class":"P",
    "gn:feature_code":"PPL",
    "gn:name":"Nawbat \u2018\u0100mir Mukaynis",
    "gn:population":0,
    "gn:timezone":"Asia/Aden",
    "iso:country":"YE",
    "name:und_x_variant":[
        "Nawbat \u2018\u0100mir Mukaynis"
    ],
    "wof:name":"Nawbat `Amir Mukaynis",
    "wof:placetype":"locality"
},
  "geometry": {"coordinates":[43.34941,14.33941],"type":"Point"}
}