{
  "type": "Feature",
  "properties": {
    "gn:admin1_code":"11.0",
    "gn:admin2_code":"2007.0",
    "gn:asciiname":"Zahmum",
    "gn:country_code":"YE",
    "gn:dem":428,
    "gn:feature_class":"P",
    "gn:feature_code":"PPL",
    "gn:name":"Za\u1e29m\u016bm",
    "gn:population":0,
    "gn:timezone":"Asia/Aden",
    "iso:country":"YE",
    "name:und_x_variant":[
        "Za\u1e29m\u016bm"
    ],
    "wof:name":"Zahmum",
    "wof:placetype":"locality"
},
  "geometry": {"coordinates":[43.58533,14.38934],"type":"Point"}
}