{
  "type": "Feature",
  "properties": {
    "gn:admin1_code":"19.0",
    "gn:admin2_code":"2919.0",
    "gn:asciiname":"Ath Thaylat",
    "gn:country_code":"YE",
    "gn:dem":2557,
    "gn:feature_class":"P",
    "gn:feature_code":"PPL",
    "gn:name":"Ath Thayl\u0101t",
    "gn:population":0,
    "gn:timezone":"Asia/Aden",
    "iso:country":"YE",
    "name:und_x_variant":[
        "Ath Thayl\u0101t"
    ],
    "wof:name":"Ath Thaylat",
    "wof:placetype":"locality"
},
  "geometry": {"coordinates":[44.03383,15.98865],"type":"Point"}
}