{
  "type": "Feature",
  "properties": {
    "gn:country":"YE",
    "gn:fcode":"PPL",
    "gn:pop":2,
    "iso:country":"YE",
    "name:ara_x_preferred":[
        "Al \u2018Afl\u0101\u2019"
    ],
    "name:ara_x_variant":[
        "\u0627\u0644\u0639\u0641\u0644\u0627\u0621"
    ],
    "name:eng_x_preferred":[
        "Al 'Afla"
    ],
    "name:eng_x_variant":[
        "Al Ghurzah"
    ],
    "qs:name":"Al \u2018Afl\u0101\u2019",
    "qs:photos_9r":0,
    "qs:photos_sr":0,
    "qs:pop_sr":"1",
    "wof:name":"Al \u2018Afl\u0101\u2019",
    "wof:placetype":"locality",
    "wof:population":2
},
  "geometry": {"coordinates":[43.31767,16.65926],"type":"Point"}
}