{
  "type": "Feature",
  "properties": {
    "gn:country":"YE",
    "gn:fcode":"PPL",
    "gn:pop":6,
    "iso:country":"YE",
    "name:ara_x_preferred":[
        "\u0627\u0644\u0632\u062e\u0645\u0629"
    ],
    "name:eng_x_preferred":[
        "Az Zukhmah"
    ],
    "name:eng_x_variant":[
        "Al \u2018Adbah"
    ],
    "qs:name":"Az Zukhmah",
    "qs:photos_9r":0,
    "qs:photos_sr":0,
    "qs:pop_sr":"1",
    "wof:name":"Az Zukhmah",
    "wof:placetype":"locality",
    "wof:population":6
},
  "geometry": {"coordinates":[45.02091,14.30638],"type":"Point"}
}