{
  "type": "Feature",
  "properties": {
    "gn:admin1_code":"19.0",
    "gn:admin2_code":"2911.0",
    "gn:asciiname":"Bayt Faraj",
    "gn:country_code":"YE",
    "gn:dem":2393,
    "gn:feature_class":"P",
    "gn:feature_code":"PPL",
    "gn:name":"Bayt Faraj",
    "gn:population":0,
    "gn:timezone":"Asia/Aden",
    "iso:country":"YE",
    "name:ara_x_preferred":[
        "\u0628\u064a\u062a \u0641\u0631\u062c"
    ],
    "wof:name":"Bayt Faraj",
    "wof:placetype":"locality"
},
  "geometry": {"coordinates":[44.0108,15.88727],"type":"Point"}
}