{
  "type": "Feature",
  "properties": {
    "gn:admin1_code":"22.0",
    "gn:admin2_code":"1719.0",
    "gn:asciiname":"Qal`at al Faysali",
    "gn:country_code":"YE",
    "gn:dem":1846,
    "gn:feature_class":"P",
    "gn:feature_code":"PPL",
    "gn:name":"Qal\u2018at al Fay\u015fal\u012b",
    "gn:population":0,
    "gn:timezone":"Asia/Aden",
    "iso:country":"YE",
    "name:und_x_variant":[
        "Qal\u2018at al Fay\u015fal\u012b"
    ],
    "wof:name":"Qal`at al Faysali",
    "wof:placetype":"locality"
},
  "geometry": {"coordinates":[43.69323,15.68966],"type":"Point"}
}