{
  "type": "Feature",
  "properties": {
    "gn:admin1_code":"14.0",
    "gn:admin2_code":"2607.0",
    "gn:asciiname":"Jaww Hudayr",
    "gn:country_code":"YE",
    "gn:dem":1246,
    "gn:feature_class":"P",
    "gn:feature_code":"PPL",
    "gn:name":"Jaww \u1e28u\u1e11ayr",
    "gn:population":0,
    "gn:timezone":"Asia/Aden",
    "iso:country":"YE",
    "name:ara_x_preferred":[
        "\u062c\u0648 \u062d\u0636\u064a\u0631"
    ],
    "name:und_x_variant":[
        "Jaww \u1e28u\u1e11ayr"
    ],
    "wof:name":"Jaww Hudayr",
    "wof:placetype":"locality"
},
  "geometry": {"coordinates":[45.28761,15.08613],"type":"Point"}
}