{
  "type": "Feature",
  "properties": {
    "gn:admin1_code":"25.0",
    "gn:admin2_code":"1516.0",
    "gn:asciiname":"Az Zaribah",
    "gn:country_code":"YE",
    "gn:dem":686,
    "gn:feature_class":"P",
    "gn:feature_code":"PPL",
    "gn:name":"Az Zar\u012bbah",
    "gn:population":0,
    "gn:timezone":"Asia/Aden",
    "iso:country":"YE",
    "name:ara_x_preferred":[
        "\u0627\u0644\u0632\u0631\u064a\u0628\u0629"
    ],
    "name:und_x_variant":[
        "Az Zar\u012bbah"
    ],
    "wof:name":"Az Zaribah",
    "wof:placetype":"locality"
},
  "geometry": {"coordinates":[43.85728,13.14621],"type":"Point"}
}