{
  "type": "Feature",
  "properties": {
    "gn:country":"YE",
    "gn:fcode":"PPL",
    "gn:pop":1,
    "iso:country":"YE",
    "name:ara_x_preferred":[
        "Al Muth\u0101mil"
    ],
    "name:ara_x_variant":[
        "\u0627\u0644\u0645\u062b\u0627\u0645\u0644"
    ],
    "name:eng_x_preferred":[
        "Al Muthamil"
    ],
    "name:eng_x_variant":[
        "\u0100l a\u0163 \u0162irla\u1e29ij"
    ],
    "qs:name":"Al Muth\u0101mil",
    "qs:photos_9r":0,
    "qs:photos_sr":0,
    "qs:pop_sr":"1",
    "wof:name":"Al Muth\u0101mil",
    "wof:placetype":"locality",
    "wof:population":1
},
  "geometry": {"coordinates":[43.30985,16.65058],"type":"Point"}
}