{
  "type": "Feature",
  "properties": {
    "gn:admin1_code":"10.0",
    "gn:admin2_code":"2705.0",
    "gn:asciiname":"As Sahari",
    "gn:country_code":"YE",
    "gn:dem":1469,
    "gn:feature_class":"P",
    "gn:feature_code":"PPL",
    "gn:name":"A\u015f \u015eah\u0101r\u012b",
    "gn:population":0,
    "gn:timezone":"Asia/Aden",
    "iso:country":"YE",
    "name:und_x_variant":[
        "A\u015f \u015eah\u0101r\u012b"
    ],
    "wof:name":"As Sahari",
    "wof:placetype":"locality"
},
  "geometry": {"coordinates":[43.3473,15.40741],"type":"Point"}
}