{
  "type": "Feature",
  "properties": {
    "gn:admin1_code":"24.0",
    "gn:admin2_code":"2512.0",
    "gn:asciiname":"Al Qa'mah",
    "gn:country_code":"YE",
    "gn:dem":849,
    "gn:feature_class":"P",
    "gn:feature_code":"PPL",
    "gn:name":"Al Qa\u2018mah",
    "gn:population":0,
    "gn:timezone":"Asia/Aden",
    "iso:country":"YE",
    "name:ara_x_preferred":[
        "\u0627\u0644\u0642\u0639\u0645\u0629"
    ],
    "name:und_x_variant":[
        "Al Qa\u2018mah"
    ],
    "wof:name":"Al Qa'mah",
    "wof:placetype":"locality"
},
  "geometry": {"coordinates":[44.22779,13.15514],"type":"Point"}
}