{
  "type": "Feature",
  "properties": {
    "gn:admin1_code":"8.0",
    "gn:admin2_code":"1813.0",
    "gn:asciiname":"Mahall Ibrahim Rayyis",
    "gn:country_code":"YE",
    "gn:dem":237,
    "gn:feature_class":"P",
    "gn:feature_code":"PPL",
    "gn:name":"Ma\u1e29all Ibr\u0101h\u012bm Rayyis",
    "gn:population":0,
    "gn:timezone":"Asia/Aden",
    "iso:country":"YE",
    "name:und_x_variant":[
        "Ma\u1e29all Ibr\u0101h\u012bm Rayyis"
    ],
    "wof:name":"Mahall Ibrahim Rayyis",
    "wof:placetype":"locality"
},
  "geometry": {"coordinates":[43.38068,14.93696],"type":"Point"}
}