{
  "type": "Feature",
  "properties": {
    "gn:country":"YE",
    "gn:fcode":"PPLX",
    "gn:pop":3,
    "iso:country":"YE",
    "name:ara_x_preferred":[
        "\u0627\u0644\u0631\u0648\u064a\u0646"
    ],
    "qs:name":"Ar Ruwayn",
    "qs:photos_9r":0,
    "qs:photos_sr":0,
    "qs:pop_sr":"1",
    "wof:name":"Ar Ruwayn",
    "wof:placetype":"neighbourhood",
    "wof:population":3
},
  "geometry": {"coordinates":[43.40501,17.23066],"type":"Point"}
}