{
  "type": "Feature",
  "properties": {
    "gn:admin1_code":"16.0",
    "gn:admin2_code":"2309.0",
    "gn:asciiname":"Al Hasib",
    "gn:country_code":"YE",
    "gn:dem":1251,
    "gn:feature_class":"P",
    "gn:feature_code":"PPL",
    "gn:name":"Al \u1e28\u0101sib",
    "gn:population":0,
    "gn:timezone":"Asia/Aden",
    "iso:country":"YE",
    "name:ara_x_preferred":[
        "Al \u1e28\u0101sib"
    ],
    "wof:name":"Al Hasib",
    "wof:placetype":"locality"
},
  "geometry": {"coordinates":[43.86363,14.9335],"type":"Point"}
}