{
  "type": "Feature",
  "properties": {
    "gn:admin1_code":"25.0",
    "gn:admin2_code":"1504.0",
    "gn:asciiname":"Al Jabzi",
    "gn:country_code":"YE",
    "gn:dem":1261,
    "gn:feature_class":"P",
    "gn:feature_code":"PPL",
    "gn:name":"Al Jabz\u012b",
    "gn:population":0,
    "gn:timezone":"Asia/Aden",
    "iso:country":"YE",
    "name:ara_x_preferred":[
        "\u0627\u0644\u062c\u0628\u0632\u064a"
    ],
    "name:und_x_variant":[
        "Al Jabz\u012b",
        "Al Jibz\u012b"
    ],
    "wof:name":"Al Jabzi",
    "wof:placetype":"locality"
},
  "geometry": {"coordinates":[43.77649,13.74957],"type":"Point"}
}