{
  "type": "Feature",
  "properties": {
    "gn:admin1_code":"23.0",
    "gn:admin2_code":"1104.0",
    "gn:asciiname":"Salyah",
    "gn:country_code":"YE",
    "gn:dem":2815,
    "gn:feature_class":"P",
    "gn:feature_code":"PPL",
    "gn:name":"Salyah",
    "gn:population":0,
    "gn:timezone":"Asia/Aden",
    "iso:country":"YE",
    "wof:name":"Salyah",
    "wof:placetype":"locality"
},
  "geometry": {"coordinates":[44.492,14.15709],"type":"Point"}
}