{
  "type": "Feature",
  "properties": {
    "gn:admin1_code":"8.0",
    "gn:admin2_code":"1805.0",
    "gn:asciiname":"Mahall al Mu'adhdhin",
    "gn:country_code":"YE",
    "gn:dem":43,
    "gn:feature_class":"P",
    "gn:feature_code":"PPL",
    "gn:name":"Ma\u1e29all al Mu\u2019adhdhin",
    "gn:population":0,
    "gn:timezone":"Asia/Aden",
    "iso:country":"YE",
    "name:ara_x_preferred":[
        "\u0645\u062d\u0644 \u0627\u0644\u0645\u0624\u0630\u0646"
    ],
    "name:und_x_variant":[
        "Ma\u1e29all al \u1e28an\u012bnah",
        "Ma\u1e29all al Mu\u2019adhdhin"
    ],
    "wof:name":"Mahall al Mu'adhdhin",
    "wof:placetype":"locality"
},
  "geometry": {"coordinates":[42.96543,15.36899],"type":"Point"}
}