{
  "type": "Feature",
  "properties": {
    "gn:country":"YE",
    "gn:fcode":"PPL",
    "gn:population":4,
    "iso:country":"YE",
    "name:ara_x_preferred":[
        "\u0627\u0644\u0628\u062f\u062d"
    ],
    "name:und_x_variant":[
        "Al Bad\u1e29"
    ],
    "qs:name":"Al Bid\u1e29",
    "qs:photos_9r":0,
    "qs:photos_sr":0,
    "qs:pop_sr":"1",
    "wof:name":"Al Bid\u1e29",
    "wof:placetype":"locality",
    "wof:population":4
},
  "geometry": {"coordinates":[43.37792,16.21301],"type":"Point"}
}