{
  "type": "Feature",
  "properties": {
    "gn:admin1_code":"23.0",
    "gn:admin2_code":"1105.0",
    "gn:asciiname":"Al Qarayn",
    "gn:country_code":"YE",
    "gn:dem":3011,
    "gn:feature_class":"P",
    "gn:feature_code":"PPL",
    "gn:name":"Al Qarayn",
    "gn:population":0,
    "gn:timezone":"Asia/Aden",
    "iso:country":"YE",
    "wof:name":"Al Qarayn",
    "wof:placetype":"locality"
},
  "geometry": {"coordinates":[44.33017,14.05386],"type":"Point"}
}