{
  "type": "Feature",
  "properties": {
    "gn:admin1_code":"4.0",
    "gn:admin2_code":"1924.0",
    "gn:asciiname":"Al Hawtah",
    "gn:cc2":"YE",
    "gn:country_code":"YE",
    "gn:dem":388,
    "gn:feature_class":"P",
    "gn:feature_code":"PPL",
    "gn:name":"Al \u1e28aw\u0163ah",
    "gn:population":0,
    "gn:timezone":"Asia/Aden",
    "iso:country":"YE",
    "name:und_x_variant":[
        "Al-Hautah",
        "Al Hauta",
        "Al \u1e28aw\u0163ah"
    ],
    "wof:name":"Al Hawtah",
    "wof:placetype":"locality"
},
  "geometry": {"coordinates":[48.21083,14.48889],"type":"Point"}
}