{
  "type": "Feature",
  "properties": {
    "gn:admin1_code":"8.0",
    "gn:admin2_code":"1809.0",
    "gn:asciiname":"Ash Shubayli",
    "gn:country_code":"YE",
    "gn:dem":308,
    "gn:feature_class":"P",
    "gn:feature_code":"PPL",
    "gn:name":"Ash Shubayl\u012b",
    "gn:population":0,
    "gn:timezone":"Asia/Aden",
    "iso:country":"YE",
    "name:ara_x_preferred":[
        "\u0627\u0644\u0634\u0628\u064a\u0644\u064a"
    ],
    "name:und_x_variant":[
        "Ma\u1e29all ash Shubayl\u012b",
        "Ash Shubayl\u012b"
    ],
    "wof:name":"Ash Shubayli",
    "wof:placetype":"locality"
},
  "geometry": {"coordinates":[43.31963,15.23296],"type":"Point"}
}