{
  "type": "Feature",
  "properties": {
    "gn:admin1_code":"23.0",
    "gn:admin2_code":"1108.0",
    "gn:asciiname":"Al Mifsas",
    "gn:country_code":"YE",
    "gn:dem":1993,
    "gn:feature_class":"P",
    "gn:feature_code":"PPL",
    "gn:name":"Al Mif\u015f\u0101\u015f",
    "gn:population":0,
    "gn:timezone":"Asia/Aden",
    "iso:country":"YE",
    "name:ara_x_preferred":[
        "Al Mif\u015f\u0101\u015f"
    ],
    "name:ara_x_variant":[
        "\u0627\u0644\u0645\u0642\u0635\u0627\u0635"
    ],
    "name:und_x_variant":[
        "Al Miq\u015f\u0101\u015f"
    ],
    "wof:name":"Al Mifsas",
    "wof:placetype":"locality"
},
  "geometry": {"coordinates":[44.11119,14.09446],"type":"Point"}
}