{
  "type": "Feature",
  "properties": {
    "gn:admin1_code":"25.0",
    "gn:admin2_code":"1515.0",
    "gn:asciiname":"Al Lakimah",
    "gn:country_code":"YE",
    "gn:dem":1155,
    "gn:feature_class":"P",
    "gn:feature_code":"PPL",
    "gn:name":"Al Lak\u012bmah",
    "gn:population":0,
    "gn:timezone":"Asia/Aden",
    "iso:country":"YE",
    "name:ara_x_preferred":[
        "\u0627\u0644\u0644\u0643\u064a\u0645\u0629"
    ],
    "name:und_x_variant":[
        "Al Lak\u012bmah"
    ],
    "wof:name":"Al Lakimah",
    "wof:placetype":"locality"
},
  "geometry": {"coordinates":[43.96099,13.19659],"type":"Point"}
}