{
  "type": "Feature",
  "properties": {
    "gn:admin1_code":"23.0",
    "gn:admin2_code":"1109.0",
    "gn:asciiname":"Shiraykhud",
    "gn:country_code":"YE",
    "gn:dem":1804,
    "gn:feature_class":"P",
    "gn:feature_code":"PPL",
    "gn:name":"Shiraykh\u016b\u1e11",
    "gn:population":0,
    "gn:timezone":"Asia/Aden",
    "iso:country":"YE",
    "name:ara_x_preferred":[
        "\u0634\u0631\u064a \u064a\u062e\u0648\u0636"
    ],
    "name:und_x_variant":[
        "Shiraykh\u016b\u1e11",
        "Shar\u012b Yakhwa\u1e11"
    ],
    "wof:name":"Shiraykhud",
    "wof:placetype":"locality"
},
  "geometry": {"coordinates":[44.01339,14.04739],"type":"Point"}
}