{
  "type": "Feature",
  "properties": {
    "gn:admin1_code":"18.0",
    "gn:admin2_code":"3003.0",
    "gn:asciiname":"`Izzan",
    "gn:country_code":"YE",
    "gn:dem":2301,
    "gn:feature_class":"P",
    "gn:feature_code":"PPL",
    "gn:name":"\u2018Izz\u0101n",
    "gn:population":0,
    "gn:timezone":"Asia/Aden",
    "iso:country":"YE",
    "name:ara_x_preferred":[
        "\u2018Izz\u0101n"
    ],
    "wof:name":"`Izzan",
    "wof:placetype":"locality"
},
  "geometry": {"coordinates":[44.8051,14.0056],"type":"Point"}
}