{
  "type": "Feature",
  "properties": {
    "gn:country":"YE",
    "gn:fcode":"FRMS",
    "gn:population":7,
    "iso:country":"YE",
    "name:ara_x_preferred":[
        "Sib\u0101\u1e29"
    ],
    "name:ara_x_variant":[
        "\u0633\u0628\u0627\u062d",
        "\u0645\u062f\u064a\u0631\u064a\u0629 \u0633\u0628\u0627\u062d"
    ],
    "name:bul_x_preferred":[
        "\u0421\u0438\u0431\u0430\u0445"
    ],
    "name:ceb_x_preferred":[
        "Sibah"
    ],
    "name:eng_x_preferred":[
        "Sibah District"
    ],
    "name:fas_x_preferred":[
        "\u0646\u0627\u062d\u06cc\u0647 \u0633\u0628\u0627\u062d"
    ],
    "name:fra_x_preferred":[
        "Sibah"
    ],
    "name:nan_x_preferred":[
        "Sibah Ko\u0101n"
    ],
    "name:nno_x_preferred":[
        "Sibah-distriktet"
    ],
    "name:tha_x_preferred":[
        "\u0e2d\u0e33\u0e40\u0e20\u0e2d\u0e0b\u0e34\u0e1a\u0e32\u0e2b\u0e4c"
    ],
    "name:urd_x_preferred":[
        "\u0633\u0628\u0627\u062d \u0636\u0644\u0639"
    ],
    "name:vie_x_preferred":[
        "Sibah"
    ],
    "qs:name":"Sib\u0101\u1e29",
    "qs:photos_9r":0,
    "qs:photos_sr":0,
    "qs:pop_sr":"1",
    "wd:wordcount":46,
    "wof:name":"Sib\u0101\u1e29",
    "wof:placetype":"locality",
    "wof:population":7
},
  "geometry": {"coordinates":[43.52118,16.8731],"type":"Point"}
}