{
  "type": "Feature",
  "properties": {
    "gn:country":"YE",
    "gn:fcode":"FRMS",
    "gn:pop":7,
    "iso:country":"YE",
    "name:ara_x_preferred":[
        "Sib\u0101\u1e29"
    ],
    "name:ara_x_variant":[
        "\u0633\u0628\u0627\u062d"
    ],
    "qs:name":"Sib\u0101\u1e29",
    "qs:photos_9r":0,
    "qs:photos_sr":0,
    "qs:pop_sr":"1",
    "wd:wordcount":46,
    "wof:name":"Sib\u0101\u1e29",
    "wof:placetype":"locality",
    "wof:population":7
},
  "geometry": {"coordinates":[43.52118,16.8731],"type":"Point"}
}