{
  "type": "Feature",
  "properties": {
    "gn:admin1_code":"16.0",
    "gn:admin2_code":"2310.0",
    "gn:asciiname":"Hisn Bani al Qulayd",
    "gn:country_code":"YE",
    "gn:dem":1239,
    "gn:feature_class":"P",
    "gn:feature_code":"PPL",
    "gn:name":"\u1e28i\u015fn Ban\u012b al Qulayd",
    "gn:population":0,
    "gn:timezone":"Asia/Aden",
    "iso:country":"YE",
    "name:und_x_variant":[
        "\u1e28i\u015fn Ban\u012b al Qulayd"
    ],
    "wof:name":"Hisn Bani al Qulayd",
    "wof:placetype":"locality"
},
  "geometry": {"coordinates":[43.69101,15.11537],"type":"Point"}
}