{
  "type": "Feature",
  "properties": {
    "gn:admin1_code":"10.0",
    "gn:admin2_code":"2704.0",
    "gn:asciiname":"Al Khumayri",
    "gn:country_code":"YE",
    "gn:dem":280,
    "gn:feature_class":"P",
    "gn:feature_code":"PPL",
    "gn:name":"Al Khumayr\u012b",
    "gn:population":0,
    "gn:timezone":"Asia/Aden",
    "iso:country":"YE",
    "name:und_x_variant":[
        "Al Khumayr\u012b"
    ],
    "wof:name":"Al Khumayri",
    "wof:placetype":"locality"
},
  "geometry": {"coordinates":[43.27236,15.46902],"type":"Point"}
}