{
  "type": "Feature",
  "properties": {
    "gn:admin1_code":"11.0",
    "gn:admin2_code":"2011.0",
    "gn:asciiname":"Jarf at Tahir",
    "gn:country_code":"YE",
    "gn:dem":2303,
    "gn:feature_class":"P",
    "gn:feature_code":"PPL",
    "gn:name":"Jarf a\u0163 \u0162\u0101hir",
    "gn:population":0,
    "gn:timezone":"Asia/Aden",
    "iso:country":"YE",
    "name:und_x_variant":[
        "Jarf a\u0163 \u0162\u0101hir"
    ],
    "wof:name":"Jarf at Tahir",
    "wof:placetype":"locality"
},
  "geometry": {"coordinates":[44.11023,14.80536],"type":"Point"}
}