{
  "type": "Feature",
  "properties": {
    "gn:country":"YE",
    "gn:fcode":"PPL",
    "gn:population":2,
    "iso:country":"YE",
    "name:ara_x_preferred":[
        "\u0627\u0644\u0645\u062f\u0631\u062c"
    ],
    "name:eng_x_preferred":[
        "Al Madraj"
    ],
    "name:eng_x_variant":[
        "Ar Riqraw\u0101sh"
    ],
    "qs:name":"Al Madraj",
    "qs:photos_9r":0,
    "qs:photos_sr":0,
    "qs:pop_sr":"1",
    "wof:name":"Al Madraj",
    "wof:placetype":"locality",
    "wof:population":2
},
  "geometry": {"coordinates":[43.31246,16.6632],"type":"Point"}
}