{
  "type": "Feature",
  "properties": {
    "gn:admin1_code":"22.0",
    "gn:admin2_code":"1725.0",
    "gn:asciiname":"Bayt Ghurbah",
    "gn:country_code":"YE",
    "gn:dem":1098,
    "gn:feature_class":"P",
    "gn:feature_code":"PPL",
    "gn:name":"Bayt Ghurbah",
    "gn:population":0,
    "gn:timezone":"Asia/Aden",
    "iso:country":"YE",
    "name:ara_x_preferred":[
        "\u0628\u064a\u062a \u063a\u0631\u0628\u0629"
    ],
    "wof:name":"Bayt Ghurbah",
    "wof:placetype":"locality"
},
  "geometry": {"coordinates":[43.56695,15.59347],"type":"Point"}
}