{
  "type": "Feature",
  "properties": {
    "gn:admin1_code":"23.0",
    "gn:admin2_code":"1102.0",
    "gn:asciiname":"Dhi Arwah",
    "gn:country_code":"YE",
    "gn:dem":2843,
    "gn:feature_class":"P",
    "gn:feature_code":"PPL",
    "gn:name":"Dh\u012b Arwa\u1e29",
    "gn:population":0,
    "gn:timezone":"Asia/Aden",
    "iso:country":"YE",
    "name:und_x_variant":[
        "Dh\u012b Arwa\u1e29"
    ],
    "wof:name":"Dhi Arwah",
    "wof:placetype":"locality"
},
  "geometry": {"coordinates":[44.27006,14.15662],"type":"Point"}
}