{
  "type": "Feature",
  "properties": {
    "gn:country":"YE",
    "gn:fcode":"PPL",
    "gn:pop":14,
    "iso:country":"YE",
    "name:ara_x_preferred":[
        "Al Minz\u0101f"
    ],
    "name:ara_x_variant":[
        "\u0627\u0644\u0645\u0646\u0632\u0627\u0641"
    ],
    "name:eng_x_preferred":[
        "Al Minzaf"
    ],
    "name:eng_x_variant":[
        "Zab\u012byah"
    ],
    "qs:name":"Al Minz\u0101f",
    "qs:photos_9r":0,
    "qs:photos_sr":0,
    "qs:pop_sr":"1",
    "wof:name":"Al Minz\u0101f",
    "wof:placetype":"locality",
    "wof:population":14
},
  "geometry": {"coordinates":[45.28773,14.32621],"type":"Point"}
}