{
  "type": "Feature",
  "properties": {
    "gn:admin1_code":"16.0",
    "gn:admin2_code":"2302.0",
    "gn:asciiname":"Al Makarib",
    "gn:country_code":"YE",
    "gn:dem":2237,
    "gn:feature_class":"P",
    "gn:feature_code":"PPL",
    "gn:name":"Al Mak\u0101r\u012bb",
    "gn:population":0,
    "gn:timezone":"Asia/Aden",
    "iso:country":"YE",
    "name:und_x_variant":[
        "Al Mak\u0101r\u012bb"
    ],
    "wof:name":"Al Makarib",
    "wof:placetype":"locality"
},
  "geometry": {"coordinates":[44.21767,15.64892],"type":"Point"}
}