{
  "type": "Feature",
  "properties": {
    "gn:admin1_code":"23.0",
    "gn:admin2_code":"1104.0",
    "gn:asciiname":"Al Kastabah",
    "gn:country_code":"YE",
    "gn:dem":2101,
    "gn:feature_class":"P",
    "gn:feature_code":"PPL",
    "gn:name":"Al Kastabah",
    "gn:population":0,
    "gn:timezone":"Asia/Aden",
    "iso:country":"YE",
    "name:ara_x_preferred":[
        "\u0627\u0644\u0643\u0633\u062a\u0628\u0629"
    ],
    "name:und_x_variant":[
        "Al Kushtubah",
        "Al Kastabah"
    ],
    "wof:name":"Al Kastabah",
    "wof:placetype":"locality"
},
  "geometry": {"coordinates":[44.48724,14.08752],"type":"Point"}
}