{
  "type": "Feature",
  "properties": {
    "gn:admin1_code":"8.0",
    "gn:admin2_code":"1818.0",
    "gn:asciiname":"Al Mudhayfir",
    "gn:country_code":"YE",
    "gn:dem":274,
    "gn:feature_class":"P",
    "gn:feature_code":"PPL",
    "gn:name":"Al Mudhayfir",
    "gn:population":0,
    "gn:timezone":"Asia/Aden",
    "iso:country":"YE",
    "wof:name":"Al Mudhayfir",
    "wof:placetype":"locality"
},
  "geometry": {"coordinates":[43.55401,13.99487],"type":"Point"}
}