{
  "type": "Feature",
  "properties": {
    "gn:country":"YE",
    "gn:fcode":"PPL",
    "gn:population":8,
    "iso:country":"YE",
    "name:ara_x_preferred":[
        "\u0642\u0627\u0639 \u0627\u0644\u0645\u062f\u0627\u0646"
    ],
    "qs:name":"Q\u0101\u2018 al Mad\u0101n",
    "qs:photos_9r":0,
    "qs:photos_sr":0,
    "qs:pop_sr":"1",
    "wof:name":"Q\u0101\u2018 al Mad\u0101n",
    "wof:placetype":"locality",
    "wof:population":8
},
  "geometry": {"coordinates":[43.63015,16.16342],"type":"Point"}
}