{
  "type": "Feature",
  "properties": {
    "gn:admin1_code":"8.0",
    "gn:admin2_code":"1815.0",
    "gn:asciiname":"Al Mirmadah",
    "gn:country_code":"YE",
    "gn:dem":215,
    "gn:feature_class":"P",
    "gn:feature_code":"PPL",
    "gn:name":"Al Mirm\u0101dah",
    "gn:population":0,
    "gn:timezone":"Asia/Aden",
    "iso:country":"YE",
    "name:ara_x_preferred":[
        "\u0627\u0644\u0645\u0631\u0645\u0627\u062f\u0629"
    ],
    "name:und_x_variant":[
        "Al Mirm\u0101dah"
    ],
    "wof:name":"Al Mirmadah",
    "wof:placetype":"locality"
},
  "geometry": {"coordinates":[43.42753,14.77828],"type":"Point"}
}