{
  "type": "Feature",
  "properties": {
    "gn:admin1_code":"27.0",
    "gn:admin2_code":"3105.0",
    "gn:asciiname":"Shi`b al Ghayl",
    "gn:country_code":"YE",
    "gn:dem":676,
    "gn:feature_class":"P",
    "gn:feature_code":"PPL",
    "gn:name":"Shi\u2018b al Ghayl",
    "gn:population":0,
    "gn:timezone":"Asia/Aden",
    "iso:country":"YE",
    "name:und_x_variant":[
        "Shi\u2018b al Ghayl"
    ],
    "wof:name":"Shi`b al Ghayl",
    "wof:placetype":"locality"
},
  "geometry": {"coordinates":[43.55291,14.3853],"type":"Point"}
}