{
  "type": "Feature",
  "properties": {
    "gn:admin1_code":"22.0",
    "gn:admin2_code":"1725.0",
    "gn:asciiname":"Bayt al Mahan",
    "gn:country_code":"YE",
    "gn:dem":726,
    "gn:feature_class":"P",
    "gn:feature_code":"PPL",
    "gn:name":"Bayt al Ma\u1e29an",
    "gn:population":0,
    "gn:timezone":"Asia/Aden",
    "iso:country":"YE",
    "name:ara_x_preferred":[
        "\u0628\u064a\u062a \u0627\u0644\u0645\u062d\u0646"
    ],
    "name:und_x_variant":[
        "Bayt al Ma\u1e29an"
    ],
    "wof:name":"Bayt al Mahan",
    "wof:placetype":"locality"
},
  "geometry": {"coordinates":[43.5268,15.56317],"type":"Point"}
}