{
  "type": "Feature",
  "properties": {
    "gn:country":"YE",
    "gn:fcode":"PPLX",
    "gn:population":74,
    "iso:country":"YE",
    "name:ara_x_preferred":[
        "\u0627\u0644\u0634\u0648\u0627\u062d\u0637"
    ],
    "qs:name":"Ash Shaw\u0101\u1e29i\u0163",
    "qs:photos_9r":0,
    "qs:photos_sr":0,
    "qs:pop_sr":"1",
    "wof:name":"Ash Shaw\u0101\u1e29i\u0163",
    "wof:placetype":"neighbourhood",
    "wof:population":74
},
  "geometry": {"coordinates":[43.39798,16.15866],"type":"Point"}
}