{
  "type": "Feature",
  "properties": {
    "gn:admin1_code":"20.0",
    "gn:admin2_code":"1406.0",
    "gn:asciiname":"Al Qashib",
    "gn:country_code":"YE",
    "gn:dem":2013,
    "gn:feature_class":"P",
    "gn:feature_code":"PPL",
    "gn:name":"Al Qash\u012bb",
    "gn:population":0,
    "gn:timezone":"Asia/Aden",
    "iso:country":"YE",
    "name:und_x_variant":[
        "Al Qash\u012bb"
    ],
    "wof:name":"Al Qashib",
    "wof:placetype":"locality"
},
  "geometry": {"coordinates":[45.44404,14.05977],"type":"Point"}
}