{
  "type": "Feature",
  "properties": {
    "gn:admin1_code":"8.0",
    "gn:admin2_code":"1801.0",
    "gn:asciiname":"Mahall Mirin",
    "gn:country_code":"YE",
    "gn:dem":49,
    "gn:feature_class":"P",
    "gn:feature_code":"PPL",
    "gn:name":"Ma\u1e29all M\u012br\u012bn",
    "gn:population":0,
    "gn:timezone":"Asia/Aden",
    "iso:country":"YE",
    "name:ara_x_preferred":[
        "\u0645\u062d\u0644 \u0645\u064a\u0631\u064a\u0646"
    ],
    "name:und_x_variant":[
        "Ma\u1e29all M\u012br\u012bn"
    ],
    "wof:name":"Mahall Mirin",
    "wof:placetype":"locality"
},
  "geometry": {"coordinates":[42.95227,15.77295],"type":"Point"}
}