{
  "type": "Feature",
  "properties": {
    "gn:admin1_code":"16.0",
    "gn:admin2_code":"2302.0",
    "gn:asciiname":"Al Bukwal",
    "gn:country_code":"YE",
    "gn:dem":2296,
    "gn:feature_class":"P",
    "gn:feature_code":"PPL",
    "gn:name":"Al Bukwal",
    "gn:population":0,
    "gn:timezone":"Asia/Aden",
    "iso:country":"YE",
    "name:ara_x_preferred":[
        "\u0627\u0644\u0628\u0643\u0648\u0644"
    ],
    "wof:name":"Al Bukwal",
    "wof:placetype":"locality"
},
  "geometry": {"coordinates":[44.16676,15.59514],"type":"Point"}
}