{
  "type": "Feature",
  "properties": {
    "gn:gn_country":"YE",
    "gn:gn_fcode":"PPL",
    "gn:gn_pop":3,
    "gn:population":3,
    "iso:country":"YE",
    "name:ara_x_preferred":[
        "\u0639\u0628\u0627\u062f \u0645\u0642\u0628\u0644"
    ],
    "name:eng_x_preferred":[
        "Abbad Maqbal"
    ],
    "name:eng_x_variant":[
        "Al \u2018Aqq\u0101m",
        "'Abbad Maqbal"
    ],
    "qs_pg:aaroncc":"YE",
    "qs_pg:gn_country":"YE",
    "qs_pg:gn_fcode":"PPL",
    "qs_pg:gn_pop":3,
    "qs_pg:name":"\u2018Abb\u0101d Maqbal",
    "qs_pg:photos_9r":0,
    "qs_pg:photos_sr":0,
    "qs_pg:pop_sr":1,
    "qs_pg:qs_pg_placetype":"locality",
    "wof:name":"\u2018Abb\u0101d Maqbal",
    "wof:placetype":"locality",
    "wof:population":3
},
  "geometry": {"coordinates":[45.45424,14.831],"type":"Point"}
}