{
  "type": "Feature",
  "properties": {
    "gn:admin1_code":"16.0",
    "gn:admin2_code":"2308.0",
    "gn:asciiname":"Hajar",
    "gn:country_code":"YE",
    "gn:dem":1388,
    "gn:feature_class":"P",
    "gn:feature_code":"PPL",
    "gn:name":"\u1e28aj\u0101r",
    "gn:population":0,
    "gn:timezone":"Asia/Aden",
    "iso:country":"YE",
    "name:aze_x_preferred":[
        "H\u0259c\u0259r"
    ],
    "name:ceb_x_preferred":[
        "Hajar"
    ],
    "name:rus_x_preferred":[
        "\u0425\u0430\u0434\u0436\u0430\u0440"
    ],
    "name:und_x_variant":[
        "\u1e28aj\u0101r"
    ],
    "wof:name":"Hajar",
    "wof:placetype":"locality"
},
  "geometry": {"coordinates":[43.86541,15.20276],"type":"Point"}
}