{
  "type": "Feature",
  "properties": {
    "gn:admin1_code":"20.0",
    "gn:admin2_code":"1418.0",
    "gn:asciiname":"Buyut Al Salamah",
    "gn:country_code":"YE",
    "gn:dem":2068,
    "gn:feature_class":"P",
    "gn:feature_code":"PPL",
    "gn:name":"Buy\u016bt \u0100l Sal\u0101mah",
    "gn:population":0,
    "gn:timezone":"Asia/Aden",
    "iso:country":"YE",
    "name:und_x_variant":[
        "Buy\u016bt \u0100l Sal\u0101mah"
    ],
    "wof:name":"Buyut Al Salamah",
    "wof:placetype":"locality"
},
  "geometry": {"coordinates":[44.84672,14.24767],"type":"Point"}
}