{
  "type": "Feature",
  "properties": {
    "gn:country":"YE",
    "gn:fcode":"PPL",
    "gn:pop":1,
    "iso:country":"YE",
    "name:ara_x_preferred":[
        "\u0627\u0644 \u0644\u0643\u0633\u0631"
    ],
    "name:eng_x_preferred":[
        "Al Laksir"
    ],
    "name:eng_x_variant":[
        "\u0100l Zubayr\u012b"
    ],
    "qs:name":"\u0100l Laksir",
    "qs:photos_9r":0,
    "qs:photos_sr":0,
    "qs:pop_sr":"1",
    "wof:name":"\u0100l Laksir",
    "wof:placetype":"locality",
    "wof:population":1
},
  "geometry": {"coordinates":[45.49796,14.9871],"type":"Point"}
}