{
  "type": "Feature",
  "properties": {
    "gn:admin1_code":"11.0",
    "gn:admin2_code":"2007.0",
    "gn:asciiname":"Al Hasib al `Ali",
    "gn:country_code":"YE",
    "gn:dem":561,
    "gn:feature_class":"P",
    "gn:feature_code":"PPL",
    "gn:name":"Al \u1e28a\u015fib al \u2018\u0100l\u012b",
    "gn:population":0,
    "gn:timezone":"Asia/Aden",
    "iso:country":"YE",
    "name:und_x_variant":[
        "Al \u1e28a\u015fib al \u2018\u0100l\u012b"
    ],
    "wof:name":"Al Hasib al `Ali",
    "wof:placetype":"locality"
},
  "geometry": {"coordinates":[43.64952,14.16845],"type":"Point"}
}