{
  "type": "Feature",
  "properties": {
    "gn:country":"YE",
    "gn:fcode":"PPL",
    "gn:pop":25,
    "iso:country":"YE",
    "name:ara_x_preferred":[
        "\u0627\u0644\u0642\u0639\u0648\u0629"
    ],
    "qs:name":"Al Qa\u2018wah",
    "qs:photos_9r":0,
    "qs:photos_sr":0,
    "qs:pop_sr":"1",
    "wof:name":"Al Qa\u2018wah",
    "wof:placetype":"locality",
    "wof:population":25
},
  "geometry": {"coordinates":[43.38692,16.72256],"type":"Point"}
}