{
  "type": "Feature",
  "properties": {
    "gn:country":"YE",
    "gn:fcode":"PPL",
    "gn:pop":4,
    "iso:country":"YE",
    "name:ara_x_preferred":[
        "\u062e\u0644\u0628\u0627\u0646\u0629"
    ],
    "name:eng_x_preferred":[
        "Khilbanah"
    ],
    "name:unk_x_variant":[
        "Ma\u1e29all Khilb\u0101n"
    ],
    "qs:name":"Khilb\u0101nah",
    "qs:photos_9r":0,
    "qs:photos_sr":0,
    "qs:pop_sr":"1",
    "wof:name":"Khilb\u0101nah",
    "wof:placetype":"locality",
    "wof:population":4
},
  "geometry": {"coordinates":[43.51837,16.94438],"type":"Point"}
}