{
  "type": "Feature",
  "properties": {
    "gn:country":"YE",
    "gn:fcode":"FRMS",
    "gn:pop":3,
    "iso:country":"YE",
    "name:ara_x_preferred":[
        "Al \u2018Aws\u0101j"
    ],
    "name:ara_x_variant":[
        "\u0627\u0644\u0639\u0648\u0633\u0627\u062c"
    ],
    "qs:name":"Al \u2018Aws\u0101j",
    "qs:photos_9r":0,
    "qs:photos_sr":0,
    "qs:pop_sr":"1",
    "wof:name":"Al \u2018Aws\u0101j",
    "wof:placetype":"locality",
    "wof:population":3
},
  "geometry": {"coordinates":[44.26444,15.42413],"type":"Point"}
}