{
  "type": "Feature",
  "properties": {
    "gn:admin1_code":"11.0",
    "gn:admin2_code":"2002.0",
    "gn:asciiname":"Afk",
    "gn:country_code":"YE",
    "gn:dem":2415,
    "gn:feature_class":"P",
    "gn:feature_code":"PPL",
    "gn:name":"Afk",
    "gn:population":0,
    "gn:timezone":"Asia/Aden",
    "iso:country":"YE",
    "wof:name":"Afk",
    "wof:placetype":"locality"
},
  "geometry": {"coordinates":[44.28722,14.62069],"type":"Point"}
}