{
  "type": "Feature",
  "properties": {
    "gn:admin1_code":"11.0",
    "gn:admin2_code":"2001.0",
    "gn:asciiname":"Quraynah",
    "gn:country_code":"YE",
    "gn:dem":2215,
    "gn:feature_class":"P",
    "gn:feature_code":"PPL",
    "gn:name":"Quraynah",
    "gn:population":0,
    "gn:timezone":"Asia/Aden",
    "iso:country":"YE",
    "wof:name":"Quraynah",
    "wof:placetype":"locality"
},
  "geometry": {"coordinates":[44.44303,14.91192],"type":"Point"}
}