{
  "type": "Feature",
  "properties": {
    "gn:country":"YE",
    "gn:fcode":"PPL",
    "gn:pop":7,
    "iso:country":"YE",
    "name:ara_x_preferred":[
        "\u0642\u0644\u0627\u0639 \u0627\u0644\u0646\u0639\u062a\u0627\u0621"
    ],
    "name:eng_x_preferred":[
        "Qala' An Na'ta"
    ],
    "name:unk_x_variant":[
        "Qil\u0101\u2018 an Na\u2018t\u0101\u2019"
    ],
    "qs:name":"Qal\u0101\u2018 an Na\u2018t\u0101\u2019",
    "qs:photos_9r":0,
    "qs:photos_sr":0,
    "qs:pop_sr":"1",
    "wof:name":"Qal\u0101\u2018 an Na\u2018t\u0101\u2019",
    "wof:placetype":"locality",
    "wof:population":7
},
  "geometry": {"coordinates":[43.32372,16.33723],"type":"Point"}
}