{
  "type": "Feature",
  "properties": {
    "gn:admin1_code":"11.0",
    "gn:admin2_code":"2008.0",
    "gn:asciiname":"Shomahi",
    "gn:country_code":"YE",
    "gn:dem":2406,
    "gn:feature_class":"P",
    "gn:feature_code":"PPL",
    "gn:name":"Shomahi",
    "gn:population":0,
    "gn:timezone":"Asia/Aden",
    "iso:country":"YE",
    "wof:name":"Shomahi",
    "wof:placetype":"locality"
},
  "geometry": {"coordinates":[44.35,14.61667],"type":"Point"}
}