{
  "type": "Feature",
  "properties": {
    "gn:admin1_code":"14.0",
    "gn:admin2_code":"2614.0",
    "gn:asciiname":"Al Badi'",
    "gn:country_code":"YE",
    "gn:dem":1900,
    "gn:feature_class":"P",
    "gn:feature_code":"PPL",
    "gn:name":"Al Bad\u012b\u2018",
    "gn:population":0,
    "gn:timezone":"Asia/Aden",
    "iso:country":"YE",
    "name:ara_x_preferred":[
        "\u0627\u0644\u0628\u062f\u064a\u0639"
    ],
    "name:ara_x_variant":[
        "\u0627\u0644\u0628\u062f\u064a\u0639 \u0648\u0627\u0644\u0642\u0631\u0641\u064a"
    ],
    "name:fas_x_preferred":[
        "\u0627\u0644\u0628\u0627\u062f\u06cc"
    ],
    "name:nno_x_preferred":[
        "Al Badi'"
    ],
    "name:und_x_variant":[
        "Al Bad\u012b\u2018"
    ],
    "wof:name":"Al Badi'",
    "wof:placetype":"locality"
},
  "geometry": {"coordinates":[45.20785,15.00568],"type":"Point"}
}