{
  "type": "Feature",
  "properties": {
    "gn:admin1_code":"4.0",
    "gn:admin2_code":"1930.0",
    "gn:asciiname":"Hasar",
    "gn:country_code":"YE",
    "gn:dem":1788,
    "gn:feature_class":"P",
    "gn:feature_code":"PPL",
    "gn:name":"Hasar",
    "gn:population":0,
    "gn:timezone":"Asia/Aden",
    "iso:country":"YE",
    "name:und_x_variant":[
        "Al \u1e28a\u015f\u00e1"
    ],
    "wof:name":"Hasar",
    "wof:placetype":"locality"
},
  "geometry": {"coordinates":[48.58333,14.83333],"type":"Point"}
}