{
  "type": "Feature",
  "properties": {
    "gn:admin1_code":"20.0",
    "gn:admin2_code":"1419.0",
    "gn:asciiname":"Al Munqati'",
    "gn:country_code":"YE",
    "gn:dem":1918,
    "gn:feature_class":"P",
    "gn:feature_code":"PPL",
    "gn:name":"Al Munqa\u0163i\u2018",
    "gn:population":3,
    "gn:timezone":"Asia/Aden",
    "iso:country":"YE",
    "name:ara_x_preferred":[
        "\u0627\u0644\u0645\u0646\u0642\u0637\u0639"
    ],
    "name:und_x_variant":[
        "Al Munqa\u0163i\u2018"
    ],
    "wof:name":"Al Munqati'",
    "wof:placetype":"locality",
    "wof:population":3
},
  "geometry": {"coordinates":[45.11254,14.34014],"type":"Point"}
}