{
  "type": "Feature",
  "properties": {
    "gn:admin1_code":"1.0",
    "gn:admin2_code":"1204.0",
    "gn:asciiname":"Am Qa`",
    "gn:country_code":"YE",
    "gn:dem":1069,
    "gn:feature_class":"P",
    "gn:feature_code":"PPL",
    "gn:name":"Am Q\u0101\u2018",
    "gn:population":0,
    "gn:timezone":"Asia/Aden",
    "iso:country":"YE",
    "name:ara_x_preferred":[
        "Al Q\u0101\u2018"
    ],
    "name:ara_x_variant":[
        "Am Q\u0101\u2018"
    ],
    "wof:name":"Am Qa`",
    "wof:placetype":"locality"
},
  "geometry": {"coordinates":[45.92883,13.96768],"type":"Point"}
}