{
  "type": "Feature",
  "properties": {
    "gn:country":"YE",
    "gn:fcode":"PPL",
    "gn:population":1,
    "iso:country":"YE",
    "name:ara_x_preferred":[
        "\u062d\u0635\u0646 \u0627\u0644\u0628\u0631\u0642\u0629"
    ],
    "name:eng_x_preferred":[
        "Hisn Al Bariqah"
    ],
    "name:eng_x_variant":[
        "Al \u1e28alwah"
    ],
    "qs:name":"\u1e28i\u015fn al Bariqah",
    "qs:photos_9r":0,
    "qs:photos_sr":0,
    "qs:pop_sr":"1",
    "wof:name":"\u1e28i\u015fn al Bariqah",
    "wof:placetype":"locality",
    "wof:population":1
},
  "geometry": {"coordinates":[43.29585,16.56671],"type":"Point"}
}