{
  "type": "Feature",
  "properties": {
    "gn:admin1_code":"25.0",
    "gn:admin2_code":"1508.0",
    "gn:asciiname":"Mawza`",
    "gn:country_code":"YE",
    "gn:dem":202,
    "gn:feature_class":"P",
    "gn:feature_code":"PPLA2",
    "gn:name":"Mawza\u2018",
    "gn:population":0,
    "gn:timezone":"Asia/Aden",
    "iso:country":"YE",
    "name:ara_x_preferred":[
        "\u0645\u0648\u0632\u0639"
    ],
    "name:und_x_variant":[
        "Mawdha\u2018",
        "M\u016bs\u00e1",
        "Mawz\u2018ah",
        "Muse",
        "Mawza\u2018",
        "Mawza\u2018ah"
    ],
    "wof:name":"Mawza`",
    "wof:placetype":"locality"
},
  "geometry": {"coordinates":[43.50993,13.26831],"type":"Point"}
}