{
  "type": "Feature",
  "properties": {
    "gn:country":"YE",
    "gn:fcode":"PPLF",
    "gn:pop":2,
    "iso:country":"YE",
    "name:ara_x_preferred":[
        "\u0627\u0644\u0648\u0642\u064a\u0631\u0629"
    ],
    "qs:name":"Al Waq\u012brah",
    "qs:photos_9r":0,
    "qs:photos_sr":0,
    "qs:pop_sr":"1",
    "wof:name":"Al Waq\u012brah",
    "wof:placetype":"locality",
    "wof:population":2
},
  "geometry": {"coordinates":[43.41648,16.43038],"type":"Point"}
}