{
  "type": "Feature",
  "properties": {
    "gn:admin1_code":"21.0",
    "gn:admin2_code":"1604.0",
    "gn:asciiname":"Al Khuzay'",
    "gn:country_code":"YE",
    "gn:dem":1209,
    "gn:feature_class":"P",
    "gn:feature_code":"PPLL",
    "gn:name":"\u0100l Khuzay\u2018",
    "gn:population":0,
    "gn:timezone":"Asia/Aden",
    "iso:country":"YE",
    "name:ara_x_preferred":[
        "\u0622\u0644 \u062e\u0632\u064a\u0639"
    ],
    "name:und_x_variant":[
        "\u0100l Khuzay\u2018"
    ],
    "wof:name":"Al Khuzay'",
    "wof:placetype":"locality"
},
  "geometry": {"coordinates":[44.4535,16.32623],"type":"Point"}
}