{
  "type": "Feature",
  "properties": {
    "gn:admin1_code":"23.0",
    "gn:admin2_code":"1114.0",
    "gn:asciiname":"An Najdayn",
    "gn:country_code":"YE",
    "gn:dem":1645,
    "gn:feature_class":"P",
    "gn:feature_code":"PPL",
    "gn:name":"An Najdayn",
    "gn:population":0,
    "gn:timezone":"Asia/Aden",
    "iso:country":"YE",
    "wof:name":"An Najdayn",
    "wof:placetype":"locality"
},
  "geometry": {"coordinates":[44.36443,13.76994],"type":"Point"}
}