{
  "type": "Feature",
  "properties": {
    "gn:admin1_code":"19.0",
    "gn:admin2_code":"2901.0",
    "gn:asciiname":"Al Gharas",
    "gn:country_code":"YE",
    "gn:dem":1866,
    "gn:feature_class":"P",
    "gn:feature_code":"PPLL",
    "gn:name":"Al Ghar\u0101s",
    "gn:population":0,
    "gn:timezone":"Asia/Aden",
    "iso:country":"YE",
    "name:ara_x_preferred":[
        "\u0627\u0644\u063a\u0631\u0627\u0633"
    ],
    "name:und_x_variant":[
        "Al Ghar\u0101s"
    ],
    "wof:name":"Al Gharas",
    "wof:placetype":"locality"
},
  "geometry": {"coordinates":[44.01909000000001,16.39021],"type":"Point"}
}