{
  "type": "Feature",
  "properties": {
    "gn:admin1_code":"27.0",
    "gn:admin2_code":"2007.0",
    "gn:asciiname":"Shi`b Habis",
    "gn:country_code":"YE",
    "gn:dem":670,
    "gn:feature_class":"P",
    "gn:feature_code":"PPL",
    "gn:name":"Shi\u2018b \u1e28\u0101bis",
    "gn:population":0,
    "gn:timezone":"Asia/Aden",
    "iso:country":"YE",
    "name:ara_x_preferred":[
        "Shi\u2018b \u1e28\u0101bis"
    ],
    "name:ara_x_variant":[
        "\u0634\u0639\u0628 \u062d\u0627\u0628\u0633"
    ],
    "wof:name":"Shi`b Habis",
    "wof:placetype":"locality"
},
  "geometry": {"coordinates":[43.54749,14.49667],"type":"Point"}
}