{
  "type": "Feature",
  "properties": {
    "gn:country":"YE",
    "gn:fcode":"CMP",
    "gn:population":12,
    "iso:country":"YE",
    "name:ara_x_preferred":[
        "\u0628\u062f\u0648 \u0623\u062a\u064a\u0633"
    ],
    "qs:name":"Badw At\u012bs",
    "qs:photos_9r":0,
    "qs:photos_sr":0,
    "qs:pop_sr":"1",
    "wof:name":"Badw At\u012bs",
    "wof:placetype":"locality",
    "wof:population":12
},
  "geometry": {"coordinates":[44.5331,17.19157],"type":"Point"}
}