{
  "type": "Feature",
  "properties": {
    "gn:country":"YE",
    "gn:fcode":"PPL",
    "gn:population":23,
    "iso:country":"YE",
    "name:ara_x_preferred":[
        "\u0627\u0644\u062b\u0647\u0631\u0629"
    ],
    "qs:name":"Ath Thahrah",
    "qs:photos_9r":0,
    "qs:photos_sr":0,
    "qs:pop_sr":"1",
    "wof:name":"Ath Thahrah",
    "wof:placetype":"locality",
    "wof:population":23
},
  "geometry": {"coordinates":[43.44548,16.14961],"type":"Point"}
}