{
  "type": "Feature",
  "properties": {
    "gn:admin1_code":"15.0",
    "gn:admin2_code":"2207.0",
    "gn:asciiname":"Al Markabah",
    "gn:country_code":"YE",
    "gn:dem":479,
    "gn:feature_class":"P",
    "gn:feature_code":"PPL",
    "gn:name":"Al Mark\u0101bah",
    "gn:population":7,
    "gn:timezone":"Asia/Aden",
    "iso:country":"YE",
    "name:ara_x_preferred":[
        "\u0627\u0644\u0645\u0631\u0643\u0627\u0628\u0629"
    ],
    "name:und_x_variant":[
        "Al Mark\u0101bah"
    ],
    "wof:name":"Al Markabah",
    "wof:placetype":"locality",
    "wof:population":7
},
  "geometry": {"coordinates":[43.29395,16.80106],"type":"Point"}
}