{
  "type": "Feature",
  "properties": {
    "gn:admin1_code":"23.0",
    "gn:admin2_code":"1109.0",
    "gn:asciiname":"As Suhaybi",
    "gn:country_code":"YE",
    "gn:dem":922,
    "gn:feature_class":"P",
    "gn:feature_code":"PPL",
    "gn:name":"A\u015f \u015euhayb\u012b",
    "gn:population":0,
    "gn:timezone":"Asia/Aden",
    "iso:country":"YE",
    "name:ara_x_preferred":[
        "\u0627\u0644\u0635\u0647\u064a\u0628\u064a"
    ],
    "name:und_x_variant":[
        "Qaryat a\u015f \u015eahayb\u012b",
        "A\u015f \u015euhayb\u012b"
    ],
    "wof:name":"As Suhaybi",
    "wof:placetype":"locality"
},
  "geometry": {"coordinates":[43.8871,14.14634],"type":"Point"}
}