{
  "type": "Feature",
  "properties": {
    "gn:country":"YE",
    "gn:fcode":"PPLX",
    "gn:population":28,
    "iso:country":"YE",
    "name:ara_x_preferred":[
        "\u0627\u0644\u0642\u0633\u0648\u064a"
    ],
    "qs:name":"Al Qasaw\u012b",
    "qs:photos_9r":0,
    "qs:photos_sr":0,
    "qs:pop_sr":"1",
    "wof:name":"Al Qasaw\u012b",
    "wof:placetype":"neighbourhood",
    "wof:population":28
},
  "geometry": {"coordinates":[43.3765,16.0306],"type":"Point"}
}