{
  "type": "Feature",
  "properties": {
    "gn:admin1_code":"10.0",
    "gn:admin2_code":"2709.0",
    "gn:asciiname":"Jida`ah",
    "gn:country_code":"YE",
    "gn:dem":1239,
    "gn:feature_class":"P",
    "gn:feature_code":"PPL",
    "gn:name":"Jid\u0101\u2018ah",
    "gn:population":0,
    "gn:timezone":"Asia/Aden",
    "iso:country":"YE",
    "name:und_x_variant":[
        "Jid\u0101\u2018ah"
    ],
    "wof:name":"Jida`ah",
    "wof:placetype":"locality"
},
  "geometry": {"coordinates":[43.56983,15.39487],"type":"Point"}
}