{
  "type": "Feature",
  "properties": {
    "gn:admin1_code":"14.0",
    "gn:admin2_code":"2608.0",
    "gn:asciiname":"Ar Ra`am",
    "gn:country_code":"YE",
    "gn:dem":2048,
    "gn:feature_class":"P",
    "gn:feature_code":"PPL",
    "gn:name":"Ar Ra\u2018am",
    "gn:population":0,
    "gn:timezone":"Asia/Aden",
    "iso:country":"YE",
    "name:ara_x_preferred":[
        "\u0627\u0644\u0631\u0639\u0645"
    ],
    "name:und_x_variant":[
        "Ar Ra\u2018am"
    ],
    "wof:name":"Ar Ra`am",
    "wof:placetype":"locality"
},
  "geometry": {"coordinates":[45.13028,15.03701],"type":"Point"}
}