{
  "type": "Feature",
  "properties": {
    "gn:admin1_code":"22.0",
    "gn:admin2_code":"1709.0",
    "gn:asciiname":"Ad Dahiyah",
    "gn:country_code":"YE",
    "gn:dem":1347,
    "gn:feature_class":"P",
    "gn:feature_code":"PPL",
    "gn:name":"A\u1e11 \u1e10\u0101\u1e29\u012byah",
    "gn:population":0,
    "gn:timezone":"Asia/Aden",
    "iso:country":"YE",
    "name:ara_x_preferred":[
        "\u0627\u0644\u0636\u0627\u062d\u064a\u0629"
    ],
    "name:und_x_variant":[
        "A\u1e11 \u1e10\u0101\u1e29\u012byah"
    ],
    "wof:name":"Ad Dahiyah",
    "wof:placetype":"locality"
},
  "geometry": {"coordinates":[43.44826,16.03254],"type":"Point"}
}