{
  "type": "Feature",
  "properties": {
    "gn:country":"YE",
    "gn:fcode":"PPL",
    "gn:pop":49,
    "iso:country":"YE",
    "name:ara_x_preferred":[
        "\u0632\u0645\u0647\u0631"
    ],
    "name:eng_x_preferred":[
        "Zimhar"
    ],
    "name:eng_x_variant":[
        "Al Lujj"
    ],
    "qs:name":"Zimhar",
    "qs:photos_9r":0,
    "qs:photos_sr":0,
    "qs:pop_sr":"1",
    "wof:name":"Zimhar",
    "wof:placetype":"locality",
    "wof:population":49
},
  "geometry": {"coordinates":[45.47232,14.14876],"type":"Point"}
}