{
  "type": "Feature",
  "properties": {
    "gn:admin1_code":"8.0",
    "gn:admin2_code":"1802.0",
    "gn:asciiname":"Sabarit",
    "gn:country_code":"YE",
    "gn:dem":18,
    "gn:feature_class":"P",
    "gn:feature_code":"PPL",
    "gn:name":"Sab\u0101r\u012bt",
    "gn:population":0,
    "gn:timezone":"Asia/Aden",
    "iso:country":"YE",
    "name:ara_x_preferred":[
        "\u0633\u0628\u0627\u0631\u064a\u062a"
    ],
    "name:und_x_variant":[
        "Sab\u0101r\u012bt"
    ],
    "wof:name":"Sabarit",
    "wof:placetype":"locality"
},
  "geometry": {"coordinates":[42.80875,15.53962],"type":"Point"}
}