{
  "type": "Feature",
  "properties": {
    "gn:admin1_code":"23.0",
    "gn:admin2_code":"1103.0",
    "gn:asciiname":"Hazi",
    "gn:country_code":"YE",
    "gn:dem":2454,
    "gn:feature_class":"P",
    "gn:feature_code":"PPL",
    "gn:name":"\u1e28az\u0327\u012b",
    "gn:population":0,
    "gn:timezone":"Asia/Aden",
    "iso:country":"YE",
    "name:ara_x_preferred":[
        "\u062d\u0638\u064a"
    ],
    "name:und_x_variant":[
        "\u1e28u\u1e11ayy",
        "\u1e28uz\u0327ayy"
    ],
    "wof:name":"Hazi",
    "wof:placetype":"locality"
},
  "geometry": {"coordinates":[44.5095,14.22818],"type":"Point"}
}