{
  "type": "Feature",
  "properties": {
    "gn:admin1_code":"24.0",
    "gn:admin2_code":"2515.0",
    "gn:asciiname":"Dar al `Anad",
    "gn:country_code":"YE",
    "gn:dem":295,
    "gn:feature_class":"P",
    "gn:feature_code":"PPL",
    "gn:name":"D\u0101r al \u2018Anad",
    "gn:population":0,
    "gn:timezone":"Asia/Aden",
    "iso:country":"YE",
    "name:und_x_variant":[
        "D\u0101r al \u2018Anad"
    ],
    "wof:name":"Dar al `Anad",
    "wof:placetype":"locality"
},
  "geometry": {"coordinates":[44.77861,13.20528],"type":"Point"}
}