{
  "type": "Feature",
  "properties": {
    "gn:admin1_code":"11.0",
    "gn:admin2_code":"2011.0",
    "gn:asciiname":"Al Gap",
    "gn:cc2":"YE",
    "gn:country_code":"YE",
    "gn:dem":1750,
    "gn:feature_class":"P",
    "gn:feature_code":"PPL",
    "gn:name":"Al Gap",
    "gn:population":0,
    "gn:timezone":"Asia/Aden",
    "iso:country":"YE",
    "name:und_x_variant":[
        "El Gap",
        "Al Gap"
    ],
    "wof:name":"Al Gap",
    "wof:placetype":"locality"
},
  "geometry": {"coordinates":[44.15,14.91667],"type":"Point"}
}