{
  "type": "Feature",
  "properties": {
    "gn:country":"YE",
    "gn:fcode":"PPL",
    "gn:pop":1,
    "iso:country":"YE",
    "name:ara_x_preferred":[
        "Al \u1e28ir\u0101q\u012b"
    ],
    "name:ara_x_variant":[
        "\u0627\u0644\u062d\u0631\u0627\u0642\u0649"
    ],
    "name:eng_x_preferred":[
        "Al Hiraqi"
    ],
    "name:eng_x_variant":[
        "Dh\u016b N\u0101j\u012b"
    ],
    "qs:name":"Al \u1e28ir\u0101q\u012b",
    "qs:photos_9r":0,
    "qs:photos_sr":0,
    "qs:pop_sr":"1",
    "wof:name":"Al \u1e28ir\u0101q\u012b",
    "wof:placetype":"locality",
    "wof:population":1
},
  "geometry": {"coordinates":[43.74583,16.01396],"type":"Point"}
}