{
  "type": "Feature",
  "properties": {
    "gn:admin1_code":"5.0",
    "gn:admin2_code":"2107.0",
    "gn:asciiname":"Jalis",
    "gn:country_code":"YE",
    "gn:dem":1175,
    "gn:elevation":"2.0",
    "gn:feature_class":"P",
    "gn:feature_code":"PPL",
    "gn:name":"J\u0101lis",
    "gn:population":0,
    "gn:timezone":"Asia/Aden",
    "iso:country":"YE",
    "name:ara_x_preferred":[
        "J\u0101lis"
    ],
    "wof:name":"Jalis",
    "wof:placetype":"locality"
},
  "geometry": {"coordinates":[45.67687,14.7708],"type":"Point"}
}