{
  "type": "Feature",
  "properties": {
    "gn:admin1_code":"22.0",
    "gn:admin2_code":"1702.0",
    "gn:asciiname":"Bani `Uwayd",
    "gn:country_code":"YE",
    "gn:dem":75,
    "gn:feature_class":"P",
    "gn:feature_code":"PPL",
    "gn:name":"Ban\u012b \u2018Uwayd",
    "gn:population":0,
    "gn:timezone":"Asia/Aden",
    "iso:country":"YE",
    "name:und_x_variant":[
        "Ban\u012b \u2018Uwayd"
    ],
    "wof:name":"Bani `Uwayd",
    "wof:placetype":"locality"
},
  "geometry": {"coordinates":[43.01707,16.36683],"type":"Point"}
}