{
  "type": "Feature",
  "properties": {
    "gn:admin1_code":"25.0",
    "gn:admin2_code":"1504.0",
    "gn:asciiname":"Al `Arish",
    "gn:country_code":"YE",
    "gn:dem":1092,
    "gn:feature_class":"P",
    "gn:feature_code":"PPL",
    "gn:name":"Al \u2018Ar\u012bsh",
    "gn:population":0,
    "gn:timezone":"Asia/Aden",
    "iso:country":"YE",
    "name:ara_x_preferred":[
        "Al \u2018Ar\u012bsh"
    ],
    "name:ara_x_variant":[
        "\u0627\u0644\u0639\u0631\u064a\u0634"
    ],
    "name:gle_x_preferred":[
        "Al `Arish"
    ],
    "name:nno_x_preferred":[
        "Al `Arish"
    ],
    "wof:name":"Al `Arish",
    "wof:placetype":"locality"
},
  "geometry": {"coordinates":[43.70943,13.79516],"type":"Point"}
}