{
  "type": "Feature",
  "properties": {
    "gn:admin1_code":"8.0",
    "gn:admin2_code":"1807.0",
    "gn:asciiname":"Makhduf",
    "gn:country_code":"YE",
    "gn:dem":143,
    "gn:feature_class":"P",
    "gn:feature_code":"PPL",
    "gn:name":"Makhd\u016bf",
    "gn:population":0,
    "gn:timezone":"Asia/Aden",
    "iso:country":"YE",
    "name:ara_x_preferred":[
        "\u0645\u062e\u062f\u0648\u0641"
    ],
    "name:und_x_variant":[
        "Makhd\u016bf"
    ],
    "wof:name":"Makhduf",
    "wof:placetype":"locality"
},
  "geometry": {"coordinates":[43.23088,15.37758],"type":"Point"}
}