{
  "type": "Feature",
  "properties": {
    "gn:admin1_code":"14.0",
    "gn:admin2_code":"2607.0",
    "gn:asciiname":"Sukhaybir",
    "gn:country_code":"YE",
    "gn:dem":1217,
    "gn:feature_class":"P",
    "gn:feature_code":"PPLL",
    "gn:name":"\u015eukhaybir",
    "gn:population":0,
    "gn:timezone":"Asia/Aden",
    "iso:country":"YE",
    "name:ara_x_preferred":[
        "\u0635\u062e\u064a\u0628\u0631"
    ],
    "name:und_x_variant":[
        "\u015eukhaybir"
    ],
    "wof:name":"Sukhaybir",
    "wof:placetype":"locality"
},
  "geometry": {"coordinates":[45.21751,15.18381],"type":"Point"}
}