{
  "type": "Feature",
  "properties": {
    "gn:admin1_code":"22.0",
    "gn:admin2_code":"1711.0",
    "gn:asciiname":"Ad Dahaysh",
    "gn:country_code":"YE",
    "gn:dem":471,
    "gn:feature_class":"P",
    "gn:feature_code":"PPL",
    "gn:name":"Ad Dahaysh",
    "gn:population":0,
    "gn:timezone":"Asia/Aden",
    "iso:country":"YE",
    "name:ara_x_preferred":[
        "\u0627\u0644\u062f\u0647\u064a\u0634"
    ],
    "wof:name":"Ad Dahaysh",
    "wof:placetype":"locality"
},
  "geometry": {"coordinates":[43.37687,16.00902],"type":"Point"}
}