{
  "type": "Feature",
  "properties": {
    "gn:admin1_code":"14.0",
    "gn:admin2_code":"2605.0",
    "gn:asciiname":"Al Qusara'",
    "gn:country_code":"YE",
    "gn:dem":1669,
    "gn:feature_class":"P",
    "gn:feature_code":"PPL",
    "gn:name":"Al Qu\u015far\u0101\u2019",
    "gn:population":0,
    "gn:timezone":"Asia/Aden",
    "iso:country":"YE",
    "name:und_x_variant":[
        "Al Qu\u015far\u0101\u2019"
    ],
    "wof:name":"Al Qusara'",
    "wof:placetype":"locality"
},
  "geometry": {"coordinates":[44.80061,15.34509],"type":"Point"}
}