{
  "type": "Feature",
  "properties": {
    "gn:admin1_code":"23.0",
    "gn:admin2_code":"1110.0",
    "gn:asciiname":"As Sal`a'",
    "gn:country_code":"YE",
    "gn:dem":620,
    "gn:feature_class":"P",
    "gn:feature_code":"PPL",
    "gn:name":"A\u015f \u015eal\u2018\u0101\u2019",
    "gn:population":0,
    "gn:timezone":"Asia/Aden",
    "iso:country":"YE",
    "name:ara_x_preferred":[
        "\u0627\u0644\u0635\u0644\u0639\u0627\u0621"
    ],
    "name:und_x_variant":[
        "A\u015f \u015eal\u2018\u0101\u2019"
    ],
    "wof:name":"As Sal`a'",
    "wof:placetype":"locality"
},
  "geometry": {"coordinates":[43.68328,13.98225],"type":"Point"}
}