{
  "type": "Feature",
  "properties": {
    "gn:admin1_code":"5.0",
    "gn:admin2_code":"2114.0",
    "gn:asciiname":"Haynun",
    "gn:cc2":"YE",
    "gn:country_code":"YE",
    "gn:dem":986,
    "gn:feature_class":"P",
    "gn:feature_code":"PPL",
    "gn:name":"Hayn\u016bn",
    "gn:population":0,
    "gn:timezone":"Asia/Aden",
    "iso:country":"YE",
    "name:und_x_variant":[
        "Hain\u016bn",
        "Hayn\u016bn"
    ],
    "wof:name":"Haynun",
    "wof:placetype":"locality"
},
  "geometry": {"coordinates":[47.11667,14.38333],"type":"Point"}
}