{
  "type": "Feature",
  "properties": {
    "gn:admin1_code":"19.0",
    "gn:admin2_code":"2909.0",
    "gn:asciiname":"Ash Shawabiyah",
    "gn:country_code":"YE",
    "gn:dem":1541,
    "gn:feature_class":"P",
    "gn:feature_code":"PPL",
    "gn:name":"Ash Shaw\u0101b\u012byah",
    "gn:population":0,
    "gn:timezone":"Asia/Aden",
    "iso:country":"YE",
    "name:ara_x_preferred":[
        "\u0627\u0644\u0634\u0648\u0627\u0628\u064a\u0629"
    ],
    "name:und_x_variant":[
        "Ash Shaw\u0101b\u012byah"
    ],
    "wof:name":"Ash Shawabiyah",
    "wof:placetype":"locality"
},
  "geometry": {"coordinates":[44.24802,16.01721],"type":"Point"}
}