{
  "type": "Feature",
  "properties": {
    "gn:admin1_code":"8.0",
    "gn:admin2_code":"1825.0",
    "gn:asciiname":"Bilad al Musawah",
    "gn:country_code":"YE",
    "gn:dem":149,
    "gn:feature_class":"P",
    "gn:feature_code":"PPL",
    "gn:name":"Bil\u0101d al Mus\u0101w\u0101h",
    "gn:population":0,
    "gn:timezone":"Asia/Aden",
    "iso:country":"YE",
    "name:und_x_variant":[
        "Bil\u0101d al Mus\u0101w\u0101h"
    ],
    "wof:name":"Bilad al Musawah",
    "wof:placetype":"locality"
},
  "geometry": {"coordinates":[43.37626,14.12639],"type":"Point"}
}