{
  "type": "Feature",
  "properties": {
    "gn:admin1_code":"8.0",
    "gn:admin2_code":"1807.0",
    "gn:asciiname":"Yahya Hasan Madani",
    "gn:country_code":"YE",
    "gn:dem":57,
    "gn:feature_class":"P",
    "gn:feature_code":"PPL",
    "gn:name":"Ya\u1e29y\u00e1 \u1e28asan Madan\u012b",
    "gn:population":0,
    "gn:timezone":"Asia/Aden",
    "iso:country":"YE",
    "name:ara_x_preferred":[
        "\u064a\u062d\u064a\u0649 \u062d\u0633\u0646 \u0645\u062f\u0646\u064a"
    ],
    "name:und_x_variant":[
        "Ya\u1e29y\u00e1 \u1e28asan Madan\u012b"
    ],
    "wof:name":"Yahya Hasan Madani",
    "wof:placetype":"locality"
},
  "geometry": {"coordinates":[43.01835,15.21404],"type":"Point"}
}