{
  "type": "Feature",
  "properties": {
    "gn:admin1_code":"19.0",
    "gn:admin2_code":"2919.0",
    "gn:asciiname":"Ar Rus",
    "gn:country_code":"YE",
    "gn:dem":1984,
    "gn:feature_class":"P",
    "gn:feature_code":"PPL",
    "gn:name":"Ar R\u016bs",
    "gn:population":0,
    "gn:timezone":"Asia/Aden",
    "iso:country":"YE",
    "name:ara_x_preferred":[
        "Ar R\u016bs"
    ],
    "name:ara_x_variant":[
        "\u0627\u0644\u0631\u0648\u0633"
    ],
    "wof:name":"Ar Rus",
    "wof:placetype":"locality"
},
  "geometry": {"coordinates":[43.83946,16.03421],"type":"Point"}
}