{
  "type": "Feature",
  "properties": {
    "gn:admin1_code":"16.0",
    "gn:admin2_code":"2303.0",
    "gn:asciiname":"Bani 'Aytah",
    "gn:country_code":"YE",
    "gn:dem":2163,
    "gn:feature_class":"P",
    "gn:feature_code":"PPL",
    "gn:name":"Ban\u012b \u2018Ay\u0163ah",
    "gn:population":0,
    "gn:timezone":"Asia/Aden",
    "iso:country":"YE",
    "name:ara_x_preferred":[
        "\u0628\u0646\u064a \u0639\u064a\u0637\u0629"
    ],
    "name:und_x_variant":[
        "Ban\u012b \u2018Ay\u0163ah"
    ],
    "wof:name":"Bani 'Aytah",
    "wof:placetype":"locality"
},
  "geometry": {"coordinates":[44.52761,15.74194],"type":"Point"}
}