{
  "type": "Feature",
  "properties": {
    "gn:admin1_code":"11.0",
    "gn:admin2_code":"2005.0",
    "gn:asciiname":"Al Jumayhah",
    "gn:country_code":"YE",
    "gn:dem":1213,
    "gn:feature_class":"P",
    "gn:feature_code":"PPL",
    "gn:name":"Al Jumay\u1e29ah",
    "gn:population":0,
    "gn:timezone":"Asia/Aden",
    "iso:country":"YE",
    "name:und_x_variant":[
        "Al Jumay\u1e29ah"
    ],
    "wof:name":"Al Jumayhah",
    "wof:placetype":"locality"
},
  "geometry": {"coordinates":[43.95012,14.59948],"type":"Point"}
}