{
  "type": "Feature",
  "properties": {
    "gn:country":"YE",
    "gn:fcode":"PPLX",
    "gn:pop":5,
    "iso:country":"YE",
    "name:ara_x_preferred":[
        "\u0639\u0641\u0627\u0631\u0629 \u0627\u0644\u0639\u0644\u064a\u0627"
    ],
    "qs:name":"\u2018Af\u0101rat al \u2018Uly\u0101",
    "qs:photos_9r":0,
    "qs:photos_sr":0,
    "qs:pop_sr":"1",
    "wof:name":"\u2018Af\u0101rat al \u2018Uly\u0101",
    "wof:placetype":"neighbourhood",
    "wof:population":5
},
  "geometry": {"coordinates":[45.77881,14.10312],"type":"Point"}
}