{
  "type": "Feature",
  "properties": {
    "gn:admin1_code":"8.0",
    "gn:admin2_code":"1813.0",
    "gn:asciiname":"Dayr ash Shura`i",
    "gn:country_code":"YE",
    "gn:dem":127,
    "gn:feature_class":"P",
    "gn:feature_code":"PPL",
    "gn:name":"Dayr ash Shur\u0101\u2018\u012b",
    "gn:population":0,
    "gn:timezone":"Asia/Aden",
    "iso:country":"YE",
    "name:und_x_variant":[
        "Dayr ash Shur\u0101\u2018\u012b"
    ],
    "wof:name":"Dayr ash Shura`i",
    "wof:placetype":"locality"
},
  "geometry": {"coordinates":[43.2226,14.93018],"type":"Point"}
}