{
  "type": "Feature",
  "properties": {
    "gn:admin1_code":"23.0",
    "gn:admin2_code":"1101.0",
    "gn:asciiname":"Al Fiddiyah",
    "gn:country_code":"YE",
    "gn:dem":1347,
    "gn:feature_class":"P",
    "gn:feature_code":"PPL",
    "gn:name":"Al Fi\u1e11\u1e11\u012byah",
    "gn:population":0,
    "gn:timezone":"Asia/Aden",
    "iso:country":"YE",
    "name:ara_x_preferred":[
        "\u0627\u0644\u0641\u0636\u064a\u0629"
    ],
    "name:und_x_variant":[
        "Al Fi\u1e11\u1e11\u012byah"
    ],
    "wof:name":"Al Fiddiyah",
    "wof:placetype":"locality"
},
  "geometry": {"coordinates":[44.09924,14.34583],"type":"Point"}
}