{
  "type": "Feature",
  "properties": {
    "gn:admin1_code":"25.0",
    "gn:admin2_code":"1521.0",
    "gn:asciiname":"Al Jurjur",
    "gn:country_code":"YE",
    "gn:dem":1236,
    "gn:feature_class":"P",
    "gn:feature_code":"PPL",
    "gn:name":"Al Jurj\u016br",
    "gn:population":0,
    "gn:timezone":"Asia/Aden",
    "iso:country":"YE",
    "name:ara_x_preferred":[
        "Al Jurj\u016br"
    ],
    "wof:name":"Al Jurjur",
    "wof:placetype":"locality"
},
  "geometry": {"coordinates":[43.99785,13.44384],"type":"Point"}
}