{
  "type": "Feature",
  "properties": {
    "gn:admin1_code":"24.0",
    "gn:admin2_code":"2510.0",
    "gn:asciiname":"Dar Salim Bin Salih",
    "gn:country_code":"YE",
    "gn:dem":527,
    "gn:feature_class":"P",
    "gn:feature_code":"PPL",
    "gn:name":"D\u0101r S\u0101lim Bin \u015e\u0101li\u1e29",
    "gn:population":0,
    "gn:timezone":"Asia/Aden",
    "iso:country":"YE",
    "name:ara_x_preferred":[
        "D\u0101r S\u0101lim Bin \u015e\u0101li\u1e29"
    ],
    "wof:name":"Dar Salim Bin Salih",
    "wof:placetype":"locality"
},
  "geometry": {"coordinates":[44.55861,13.25833],"type":"Point"}
}