{
  "type": "Feature",
  "properties": {
    "gn:country":"YE",
    "gn:fcode":"PPL",
    "gn:population":20,
    "iso:country":"YE",
    "name:ara_x_preferred":[
        "\u0627\u0644 \u0645\u062d\u0645\u062f"
    ],
    "name:eng_x_preferred":[
        "Al Muhammad"
    ],
    "name:nno_x_preferred":[
        "Ar Rahwah"
    ],
    "qs:name":"\u0100l Mu\u1e29ammad",
    "qs:photos_9r":0,
    "qs:photos_sr":0,
    "qs:pop_sr":"1",
    "wof:name":"\u0100l Mu\u1e29ammad",
    "wof:placetype":"locality",
    "wof:population":20
},
  "geometry": {"coordinates":[45.35178,14.50878],"type":"Point"}
}