{
  "type": "Feature",
  "properties": {
    "gn:admin1_code":"14.0",
    "gn:admin2_code":"2606.0",
    "gn:asciiname":"Qaryat as Sadah",
    "gn:country_code":"YE",
    "gn:dem":1890,
    "gn:feature_class":"P",
    "gn:feature_code":"PPL",
    "gn:name":"Qaryat as S\u0101dah",
    "gn:population":0,
    "gn:timezone":"Asia/Aden",
    "iso:country":"YE",
    "name:und_x_variant":[
        "Qaryat as S\u0101dah"
    ],
    "wof:name":"Qaryat as Sadah",
    "wof:placetype":"locality"
},
  "geometry": {"coordinates":[45.07323,15.50347],"type":"Point"}
}