{
  "type": "Feature",
  "properties": {
    "gn:admin1_code":"25.0",
    "gn:admin2_code":"1512.0",
    "gn:asciiname":"Buraykat",
    "gn:country_code":"YE",
    "gn:dem":1603,
    "gn:feature_class":"P",
    "gn:feature_code":"PPL",
    "gn:name":"Burayk\u0101t",
    "gn:population":0,
    "gn:timezone":"Asia/Aden",
    "iso:country":"YE",
    "name:und_x_variant":[
        "Burayk\u0101t"
    ],
    "wof:name":"Buraykat",
    "wof:placetype":"locality"
},
  "geometry": {"coordinates":[44.08941,13.51977],"type":"Point"}
}