{
  "type": "Feature",
  "properties": {
    "gn:admin1_code":"25.0",
    "gn:admin2_code":"1516.0",
    "gn:asciiname":"Al Mahjam",
    "gn:country_code":"YE",
    "gn:dem":643,
    "gn:feature_class":"P",
    "gn:feature_code":"PPL",
    "gn:name":"Al Mahjam",
    "gn:population":0,
    "gn:timezone":"Asia/Aden",
    "iso:country":"YE",
    "name:ara_x_preferred":[
        "\u0627\u0644\u0645\u0647\u062c\u0645"
    ],
    "wof:name":"Al Mahjam",
    "wof:placetype":"locality"
},
  "geometry": {"coordinates":[43.81045,13.17031],"type":"Point"}
}