{
  "type": "Feature",
  "properties": {
    "gn:admin1_code":"20.0",
    "gn:admin2_code":"1417.0",
    "gn:asciiname":"Qarn Qasim",
    "gn:country_code":"YE",
    "gn:dem":2523,
    "gn:feature_class":"P",
    "gn:feature_code":"PPL",
    "gn:name":"Qarn Q\u0101sim",
    "gn:population":0,
    "gn:timezone":"Asia/Aden",
    "iso:country":"YE",
    "name:und_x_variant":[
        "Qarn Q\u0101sim"
    ],
    "wof:name":"Qarn Qasim",
    "wof:placetype":"locality"
},
  "geometry": {"coordinates":[44.7046,14.24354],"type":"Point"}
}