{
  "type": "Feature",
  "properties": {
    "gn:country":"YE",
    "gn:fcode":"PPL",
    "gn:population":1,
    "iso:country":"YE",
    "name:ara_x_preferred":[
        "\u0627\u0644\u0631\u0623\u0633"
    ],
    "qs:name":"Al Ra\u2019s",
    "qs:photos_9r":0,
    "qs:photos_sr":0,
    "qs:pop_sr":"1",
    "wof:name":"Al Ra\u2019s",
    "wof:placetype":"locality",
    "wof:population":1
},
  "geometry": {"coordinates":[44.42425,16.70764],"type":"Point"}
}