{
  "type": "Feature",
  "properties": {
    "gn:admin1_code":"19.0",
    "gn:admin2_code":"2914.0",
    "gn:asciiname":"Bayt al Bawni",
    "gn:country_code":"YE",
    "gn:dem":2115,
    "gn:feature_class":"P",
    "gn:feature_code":"PPL",
    "gn:name":"Bayt al Bawn\u012b",
    "gn:population":0,
    "gn:timezone":"Asia/Aden",
    "iso:country":"YE",
    "name:und_x_variant":[
        "Bayt al Bawn\u012b"
    ],
    "wof:name":"Bayt al Bawni",
    "wof:placetype":"locality"
},
  "geometry": {"coordinates":[43.77618,15.7751],"type":"Point"}
}