{
  "type": "Feature",
  "properties": {
    "gn:country":"YE",
    "gn:fcode":"PPL",
    "gn:population":1,
    "iso:country":"YE",
    "name:ara_x_preferred":[
        "\u0627\u0644\u062d\u0630\u0641\u064a\u0629"
    ],
    "name:eng_x_preferred":[
        "Al Hadhifiyah"
    ],
    "name:eng_x_variant":[
        "Alt Sh\u0101kir"
    ],
    "qs:name":"Al \u1e28adhif\u012byah",
    "qs:photos_9r":0,
    "qs:photos_sr":0,
    "qs:pop_sr":"1",
    "wof:name":"Al \u1e28adhif\u012byah",
    "wof:placetype":"locality",
    "wof:population":1
},
  "geometry": {"coordinates":[43.28464,17.26578],"type":"Point"}
}