{
  "type": "Feature",
  "properties": {
    "gn:country":"YE",
    "gn:fcode":"PPL",
    "gn:population":1,
    "iso:country":"YE",
    "name:ara_x_preferred":[
        "\u0627\u0644\u062f\u064a\u0631"
    ],
    "name:eng_x_preferred":[
        "Ad Dayr"
    ],
    "name:eng_x_variant":[
        "Bayt \u2018Am\u012br"
    ],
    "qs:name":"Ad Dayr",
    "qs:photos_9r":0,
    "qs:photos_sr":0,
    "qs:pop_sr":"1",
    "wof:name":"Ad Dayr",
    "wof:placetype":"locality",
    "wof:population":1
},
  "geometry": {"coordinates":[43.47282,16.31658],"type":"Point"}
}