{
  "type": "Feature",
  "properties": {
    "gn:admin1_code":"5.0",
    "gn:admin2_code":"2115.0",
    "gn:asciiname":"Qarn al Aswad",
    "gn:country_code":"YE",
    "gn:dem":1069,
    "gn:feature_class":"P",
    "gn:feature_code":"PPL",
    "gn:name":"Qarn al Aswad",
    "gn:population":0,
    "gn:timezone":"Asia/Aden",
    "iso:country":"YE",
    "wof:name":"Qarn al Aswad",
    "wof:placetype":"locality"
},
  "geometry": {"coordinates":[47.08351,14.57678],"type":"Point"}
}