{
  "type": "Feature",
  "properties": {
    "gn:admin1_code":"19.0",
    "gn:admin2_code":"2908.0",
    "gn:asciiname":"Sharqiyat Zabi",
    "gn:country_code":"YE",
    "gn:dem":1386,
    "gn:feature_class":"P",
    "gn:feature_code":"PPLL",
    "gn:name":"Sharq\u012byat Z\u0327ab\u012b",
    "gn:population":0,
    "gn:timezone":"Asia/Aden",
    "iso:country":"YE",
    "name:ara_x_preferred":[
        "\u0634\u0631\u0642\u064a\u0629 \u0638\u0628\u064a"
    ],
    "name:und_x_variant":[
        "Sharq\u012byat Z\u0327ab\u012b"
    ],
    "wof:name":"Sharqiyat Zabi",
    "wof:placetype":"locality"
},
  "geometry": {"coordinates":[43.75355,16.12631],"type":"Point"}
}