{
  "type": "Feature",
  "properties": {
    "gn:admin1_code":"19.0",
    "gn:admin2_code":"2903.0",
    "gn:asciiname":"As Salbah",
    "gn:country_code":"YE",
    "gn:dem":1184,
    "gn:feature_class":"P",
    "gn:feature_code":"PPLL",
    "gn:name":"A\u015f \u015ealbah",
    "gn:population":0,
    "gn:timezone":"Asia/Aden",
    "iso:country":"YE",
    "name:ara_x_preferred":[
        "\u0627\u0644\u0635\u0644\u0628\u0629"
    ],
    "name:und_x_variant":[
        "A\u015f \u015ealbah"
    ],
    "wof:name":"As Salbah",
    "wof:placetype":"locality"
},
  "geometry": {"coordinates":[43.81667,16.14974],"type":"Point"}
}