{
  "type": "Feature",
  "properties": {
    "gn:country":"YE",
    "gn:fcode":"PPL",
    "gn:pop":5,
    "iso:country":"YE",
    "name:ara_x_preferred":[
        "\u063a\u0627\u0631\u0628 \u0635\u0631\u062d\u0629"
    ],
    "name:eng_x_preferred":[
        "Gharib Sarhah"
    ],
    "name:eng_x_variant":[
        "Gh\u0101rib Qays"
    ],
    "qs:name":"Gh\u0101rib \u015ear\u1e29ah",
    "qs:photos_9r":0,
    "qs:photos_sr":0,
    "qs:pop_sr":"1",
    "wof:name":"Gh\u0101rib \u015ear\u1e29ah",
    "wof:placetype":"locality",
    "wof:population":5
},
  "geometry": {"coordinates":[43.3186,16.19689],"type":"Point"}
}