{
  "type": "Feature",
  "properties": {
    "gn:admin1_code":"8.0",
    "gn:admin2_code":"1817.0",
    "gn:asciiname":"Al Qubay`",
    "gn:country_code":"YE",
    "gn:dem":79,
    "gn:feature_class":"P",
    "gn:feature_code":"PPL",
    "gn:name":"Al Qubay\u2018",
    "gn:population":0,
    "gn:timezone":"Asia/Aden",
    "iso:country":"YE",
    "name:und_x_variant":[
        "Al Qubay\u2018"
    ],
    "wof:name":"Al Qubay`",
    "wof:placetype":"locality"
},
  "geometry": {"coordinates":[43.23633,14.36226],"type":"Point"}
}