{
  "type": "Feature",
  "properties": {
    "gn:admin1_code":"16.0",
    "gn:admin2_code":"2316.0",
    "gn:asciiname":"As Sartahah",
    "gn:country_code":"YE",
    "gn:dem":2318,
    "gn:feature_class":"P",
    "gn:feature_code":"PPL",
    "gn:name":"A\u015f \u015ear\u0163a\u1e29ah",
    "gn:population":0,
    "gn:timezone":"Asia/Aden",
    "iso:country":"YE",
    "name:ara_x_preferred":[
        "\u0627\u0644\u0635\u0631\u0637\u062d\u0629"
    ],
    "name:und_x_variant":[
        "A\u015f \u015ear\u0163a\u1e29ah"
    ],
    "wof:name":"As Sartahah",
    "wof:placetype":"locality"
},
  "geometry": {"coordinates":[44.5395,15.27972],"type":"Point"}
}