{
  "type": "Feature",
  "properties": {
    "gn:admin1_code":"14.0",
    "gn:admin2_code":"2605.0",
    "gn:asciiname":"Al 'Utayfah",
    "gn:country_code":"YE",
    "gn:dem":2047,
    "gn:feature_class":"P",
    "gn:feature_code":"PPL",
    "gn:name":"Al \u2018U\u0163ayfah",
    "gn:population":0,
    "gn:timezone":"Asia/Aden",
    "iso:country":"YE",
    "name:ara_x_preferred":[
        "\u0627\u0644\u0639\u0637\u064a\u0641\u0629"
    ],
    "name:und_x_variant":[
        "Al \u2018U\u0163ayfah"
    ],
    "wof:name":"Al 'Utayfah",
    "wof:placetype":"locality"
},
  "geometry": {"coordinates":[44.7255,15.40296],"type":"Point"}
}