{
  "type": "Feature",
  "properties": {
    "gn:admin1_code":"14.0",
    "gn:admin2_code":"2609.0",
    "gn:asciiname":"Hilwah",
    "gn:country_code":"YE",
    "gn:dem":1143,
    "gn:elevation":"3.0",
    "gn:feature_class":"P",
    "gn:feature_code":"PPL",
    "gn:name":"\u1e28ilwah",
    "gn:population":0,
    "gn:timezone":"Asia/Aden",
    "iso:country":"YE",
    "name:ara_x_preferred":[
        "\u062d\u0644\u0648\u0629"
    ],
    "name:und_x_variant":[
        "\u1e28ilwah"
    ],
    "wof:name":"Hilwah",
    "wof:placetype":"locality"
},
  "geometry": {"coordinates":[45.50968,14.97048],"type":"Point"}
}