{
  "type": "Feature",
  "properties": {
    "gn:admin1_code":"18.0",
    "gn:admin2_code":"3008.0",
    "gn:asciiname":"Zakhmumah",
    "gn:country_code":"YE",
    "gn:dem":970,
    "gn:feature_class":"P",
    "gn:feature_code":"PPL",
    "gn:name":"Zakhm\u016bmah",
    "gn:population":0,
    "gn:timezone":"Asia/Aden",
    "iso:country":"YE",
    "name:und_x_variant":[
        "Zakhmuma",
        "Zakhm\u016bmah",
        "Zakhm\u016bm"
    ],
    "wof:name":"Zakhmumah",
    "wof:placetype":"locality"
},
  "geometry": {"coordinates":[44.59106,13.64119],"type":"Point"}
}