{
  "type": "Feature",
  "properties": {
    "gn:admin1_code":"19.0",
    "gn:admin2_code":"2912.0",
    "gn:asciiname":"Al Khadarah",
    "gn:country_code":"YE",
    "gn:dem":2685,
    "gn:feature_class":"P",
    "gn:feature_code":"PPL",
    "gn:name":"Al Khadarah",
    "gn:population":0,
    "gn:timezone":"Asia/Aden",
    "iso:country":"YE",
    "wof:name":"Al Khadarah",
    "wof:placetype":"locality"
},
  "geometry": {"coordinates":[43.8735,15.74389],"type":"Point"}
}