{
  "type": "Feature",
  "properties": {
    "gn:country":"YE",
    "gn:fcode":"PPLF",
    "gn:population":1,
    "iso:country":"YE",
    "name:ara_x_preferred":[
        "\u0645\u062c\u0647\u0631"
    ],
    "name:eng_x_preferred":[
        "Majhar"
    ],
    "name:eng_x_variant":[
        "Bayt Fal\u0101\u1e29"
    ],
    "qs:name":"Majhar",
    "qs:photos_9r":0,
    "qs:photos_sr":0,
    "qs:pop_sr":"1",
    "wof:name":"Majhar",
    "wof:placetype":"locality",
    "wof:population":1
},
  "geometry": {"coordinates":[43.45115,16.37757],"type":"Point"}
}