{
  "type": "Feature",
  "properties": {
    "gn:country":"YE",
    "gn:fcode":"PPL",
    "gn:pop":2,
    "iso:country":"YE",
    "name:ara_x_preferred":[
        "Al Mid\u0101h\u012b"
    ],
    "name:ara_x_variant":[
        "\u0627\u0644\u0645\u062f\u0627\u0647\u064a"
    ],
    "name:eng_x_preferred":[
        "Al Midahi"
    ],
    "qs:name":"Al Mid\u0101h\u012b",
    "qs:photos_9r":0,
    "qs:photos_sr":0,
    "qs:pop_sr":"1",
    "wof:name":"Al Mid\u0101h\u012b",
    "wof:placetype":"locality",
    "wof:population":2
},
  "geometry": {"coordinates":[43.40857,16.14767],"type":"Point"}
}