{
  "type": "Feature",
  "properties": {
    "gn:gn_country":"YE",
    "gn:gn_fcode":"PPL",
    "gn:gn_pop":3,
    "gn:population":3,
    "iso:country":"YE",
    "name:ara_x_preferred":[
        "\u0627\u0644\u0631\u0627\u0642\u0628\u064a\u0629"
    ],
    "name:eng_x_preferred":[
        "Ar Raqibiyah"
    ],
    "name:eng_x_variant":[
        "\u1e28ab\u012bl al M\u0101jin"
    ],
    "qs_pg:aaroncc":"YE",
    "qs_pg:gn_country":"YE",
    "qs_pg:gn_fcode":"PPL",
    "qs_pg:gn_pop":3,
    "qs_pg:name":"Ar R\u0101qib\u012byah",
    "qs_pg:photos_9r":0,
    "qs_pg:photos_sr":0,
    "qs_pg:pop_sr":1,
    "qs_pg:qs_pg_placetype":"locality",
    "wof:name":"Ar R\u0101qib\u012byah",
    "wof:placetype":"locality",
    "wof:population":3
},
  "geometry": {"coordinates":[43.31041,16.14918],"type":"Point"}
}