{
  "type": "Feature",
  "properties": {
    "gn:admin1_code":"25.0",
    "gn:admin2_code":"1506.0",
    "gn:asciiname":"Hasy Salim",
    "gn:country_code":"YE",
    "gn:dem":10,
    "gn:feature_class":"P",
    "gn:feature_code":"PPL",
    "gn:name":"\u1e28asy S\u0101lim",
    "gn:population":0,
    "gn:timezone":"Asia/Aden",
    "iso:country":"YE",
    "name:und_x_variant":[
        "\u1e28asy S\u0101lim"
    ],
    "wof:name":"Hasy Salim",
    "wof:placetype":"locality"
},
  "geometry": {"coordinates":[43.31161,13.63169],"type":"Point"}
}