{
  "type": "Feature",
  "properties": {
    "gn:admin1_code":"24.0",
    "gn:admin2_code":"2512.0",
    "gn:asciiname":"Umm al Khayr",
    "gn:country_code":"YE",
    "gn:dem":831,
    "gn:feature_class":"P",
    "gn:feature_code":"PPL",
    "gn:name":"Umm al Khayr",
    "gn:population":0,
    "gn:timezone":"Asia/Aden",
    "iso:country":"YE",
    "name:ara_x_preferred":[
        "\u0623\u0645 \u0627\u0644\u062e\u064a\u0631"
    ],
    "wof:name":"Umm al Khayr",
    "wof:placetype":"locality"
},
  "geometry": {"coordinates":[44.1764,13.12272],"type":"Point"}
}