{
  "type": "Feature",
  "properties": {
    "gn:admin1_code":"11.0",
    "gn:admin2_code":"2010.0",
    "gn:asciiname":"Ash Shaqb",
    "gn:country_code":"YE",
    "gn:dem":2544,
    "gn:feature_class":"P",
    "gn:feature_code":"PPL",
    "gn:name":"Ash Shaqb",
    "gn:population":0,
    "gn:timezone":"Asia/Aden",
    "iso:country":"YE",
    "wof:name":"Ash Shaqb",
    "wof:placetype":"locality"
},
  "geometry": {"coordinates":[44.47825,14.36287],"type":"Point"}
}