{
  "type": "Feature",
  "properties": {
    "gn:admin1_code":"8.0",
    "gn:admin2_code":"1806.0",
    "gn:asciiname":"Otaia",
    "gn:cc2":"YE",
    "gn:country_code":"YE",
    "gn:dem":119,
    "gn:feature_class":"P",
    "gn:feature_code":"PPL",
    "gn:name":"Otaia",
    "gn:population":0,
    "gn:timezone":"Asia/Aden",
    "iso:country":"YE",
    "name:und_x_variant":[
        "Otala",
        "Otaia"
    ],
    "wof:name":"Otaia",
    "wof:placetype":"locality"
},
  "geometry": {"coordinates":[43.18333,15.53333],"type":"Point"}
}