{
  "type": "Feature",
  "properties": {
    "gn:admin1_code":"11.0",
    "gn:admin2_code":"2007.0",
    "gn:asciiname":"Wadi al Qaryah",
    "gn:country_code":"YE",
    "gn:dem":988,
    "gn:feature_class":"P",
    "gn:feature_code":"PPL",
    "gn:name":"W\u0101d\u012b al Qaryah",
    "gn:population":0,
    "gn:timezone":"Asia/Aden",
    "iso:country":"YE",
    "name:und_x_variant":[
        "W\u0101d\u012b al Qaryah"
    ],
    "wof:name":"Wadi al Qaryah",
    "wof:placetype":"locality"
},
  "geometry": {"coordinates":[43.68798,14.28436],"type":"Point"}
}