{
  "type": "Feature",
  "properties": {
    "gn:admin1_code":"5.0",
    "gn:admin2_code":"2108.0",
    "gn:asciiname":"Matrah al Quwwah",
    "gn:country_code":"YE",
    "gn:dem":1352,
    "gn:feature_class":"P",
    "gn:feature_code":"PPL",
    "gn:name":"Ma\u0163ra\u1e29 al Quwwah",
    "gn:population":0,
    "gn:timezone":"Asia/Aden",
    "iso:country":"YE",
    "name:und_x_variant":[
        "Al Quwwah",
        "Ma\u0163ra\u1e29 al Quwwah",
        "Al Q\u016bwah"
    ],
    "wof:name":"Matrah al Quwwah",
    "wof:placetype":"locality"
},
  "geometry": {"coordinates":[45.90817,14.45303],"type":"Point"}
}