{
  "type": "Feature",
  "properties": {
    "gn:admin1_code":"25.0",
    "gn:admin2_code":"1501.0",
    "gn:asciiname":"Al `Aduf",
    "gn:country_code":"YE",
    "gn:dem":1257,
    "gn:feature_class":"P",
    "gn:feature_code":"PPL",
    "gn:name":"Al \u2018Ad\u016bf",
    "gn:population":0,
    "gn:timezone":"Asia/Aden",
    "iso:country":"YE",
    "name:ara_x_preferred":[
        "Al \u2018Ad\u016bf"
    ],
    "wof:name":"Al `Aduf",
    "wof:placetype":"locality"
},
  "geometry": {"coordinates":[44.36524,13.56761],"type":"Point"}
}