{
  "type": "Feature",
  "properties": {
    "gn:admin1_code":"15.0",
    "gn:admin2_code":"2215.0",
    "gn:asciiname":"An Nayd",
    "gn:country":"YE",
    "gn:country_code":"YE",
    "gn:dem":1891,
    "gn:fcode":"PPL",
    "gn:feature_class":"P",
    "gn:feature_code":"PPL",
    "gn:name":"An Nayd",
    "gn:population":36,
    "gn:timezone":"Asia/Aden",
    "iso:country":"YE",
    "name:ara_x_preferred":[
        "\u0627\u0644\u0646\u064a\u062f"
    ],
    "qs:name":"An Nayd",
    "qs:photos_9r":0,
    "qs:photos_sr":0,
    "qs:pop_sr":"1",
    "wof:name":"An Nayd",
    "wof:placetype":"locality",
    "wof:population":36
},
  "geometry": {"coordinates":[43.77544,16.90966],"type":"Point"}
}