{
  "type": "Feature",
  "properties": {
    "gn:country":"YE",
    "gn:fcode":"PPL",
    "gn:pop":36,
    "iso:country":"YE",
    "name:ara_x_preferred":[
        "\u0627\u0644\u0646\u064a\u062f"
    ],
    "qs:name":"An Nayd",
    "qs:photos_9r":0,
    "qs:photos_sr":0,
    "qs:pop_sr":"1",
    "wof:name":"An Nayd",
    "wof:placetype":"locality",
    "wof:population":36
},
  "geometry": {"coordinates":[43.77544,16.90966],"type":"Point"}
}