{
  "type": "Feature",
  "properties": {
    "gn:admin1_code":"25.0",
    "gn:admin2_code":"1515.0",
    "gn:asciiname":"`Ukhaynah",
    "gn:country_code":"YE",
    "gn:dem":1068,
    "gn:feature_class":"P",
    "gn:feature_code":"PPL",
    "gn:name":"\u2018Ukhaynah",
    "gn:population":0,
    "gn:timezone":"Asia/Aden",
    "iso:country":"YE",
    "name:und_x_variant":[
        "\u2018Ukhaynah"
    ],
    "wof:name":"`Ukhaynah",
    "wof:placetype":"locality"
},
  "geometry": {"coordinates":[44.02254,13.13364],"type":"Point"}
}