{
  "type": "Feature",
  "properties": {
    "gn:country":"YE",
    "gn:fcode":"PPLX",
    "gn:population":18,
    "iso:country":"YE",
    "name:ara_x_preferred":[
        "A\u1e11 \u1e10il\u0101\u2018"
    ],
    "name:ara_x_variant":[
        "\u0627\u0644\u0636\u0644\u0627\u0639"
    ],
    "qs:name":"A\u1e11 \u1e10il\u0101\u2018",
    "qs:photos_9r":0,
    "qs:photos_sr":0,
    "qs:pop_sr":"1",
    "wof:name":"A\u1e11 \u1e10il\u0101\u2018",
    "wof:placetype":"neighbourhood",
    "wof:population":18
},
  "geometry": {"coordinates":[43.64596,16.22448],"type":"Point"}
}