{
  "type": "Feature",
  "properties": {
    "gn:country":"YE",
    "gn:fcode":"PPL",
    "gn:population":21,
    "iso:country":"YE",
    "name:ara_x_preferred":[
        "\u0627\u0644\u0645\u0639\u0635\u064a\u062f"
    ],
    "name:eng_x_preferred":[
        "Al Mu'sayd"
    ],
    "name:eng_x_variant":[
        "Gh\u0101rib Mashjan"
    ],
    "qs:name":"Al Mu\u2018\u015fayd",
    "qs:photos_9r":0,
    "qs:photos_sr":0,
    "qs:pop_sr":"1",
    "wof:name":"Al Mu\u2018\u015fayd",
    "wof:placetype":"locality",
    "wof:population":21
},
  "geometry": {"coordinates":[43.41225,16.32846],"type":"Point"}
}