{
  "type": "Feature",
  "properties": {
    "gn:country":"YE",
    "gn:fcode":"PPL",
    "gn:pop":4,
    "iso:country":"YE",
    "name:ara_x_preferred":[
        "\u0627\u0644\u0645\u0644\u062d\u0629 \u0627\u0644\u0633\u0641\u0644\u0649"
    ],
    "name:eng_x_preferred":[
        "Al Milhah As Sufla"
    ],
    "qs:name":"Al Mil\u1e29ah as Sufl\u00e1",
    "qs:photos_9r":0,
    "qs:photos_sr":0,
    "qs:pop_sr":"1",
    "wof:name":"Al Mil\u1e29ah as Sufl\u00e1",
    "wof:placetype":"locality",
    "wof:population":4
},
  "geometry": {"coordinates":[43.94234,16.74269],"type":"Point"}
}