{
  "type": "Feature",
  "properties": {
    "gn:country":"YE",
    "gn:fcode":"PPL",
    "gn:pop":2,
    "iso:country":"YE",
    "name:ara_x_preferred":[
        "\u0627\u0644\u0645\u062d\u062a\u062c\u0641"
    ],
    "name:eng_x_preferred":[
        "Al Muhtajaf"
    ],
    "qs:name":"Al Mu\u1e29tajaf",
    "qs:photos_9r":0,
    "qs:photos_sr":0,
    "qs:pop_sr":"1",
    "wof:name":"Al Mu\u1e29tajaf",
    "wof:placetype":"locality",
    "wof:population":2
},
  "geometry": {"coordinates":[43.35566,17.37605],"type":"Point"}
}