{
  "type": "Feature",
  "properties": {
    "gn:country":"YE",
    "gn:fcode":"PPL",
    "gn:pop":1,
    "iso:country":"YE",
    "name:ara_x_preferred":[
        "\u0627\u0644\u0635\u0648\u0645\u0644\u0629"
    ],
    "name:eng_x_preferred":[
        "As Sawmilah"
    ],
    "name:eng_x_variant":[
        "Hayr"
    ],
    "qs:name":"A\u015f \u015eawmilah",
    "qs:photos_9r":0,
    "qs:photos_sr":0,
    "qs:pop_sr":"1",
    "wof:name":"A\u015f \u015eawmilah",
    "wof:placetype":"locality",
    "wof:population":1
},
  "geometry": {"coordinates":[43.32668,17.50379],"type":"Point"}
}