{
  "type": "Feature",
  "properties": {
    "gn:admin1_code":"22.0",
    "gn:admin2_code":"1707.0",
    "gn:asciiname":"Ad Damnah",
    "gn:country_code":"YE",
    "gn:dem":1284,
    "gn:feature_class":"P",
    "gn:feature_code":"PPL",
    "gn:name":"Ad Damnah",
    "gn:population":6,
    "gn:timezone":"Asia/Aden",
    "iso:country":"YE",
    "name:ara_x_preferred":[
        "\u0627\u0644\u062f\u0645\u0646\u0629"
    ],
    "wof:name":"Ad Damnah",
    "wof:placetype":"locality",
    "wof:population":6
},
  "geometry": {"coordinates":[43.41871,16.09225],"type":"Point"}
}