{
  "type": "Feature",
  "properties": {
    "gn:admin1_code":"19.0",
    "gn:admin2_code":"2912.0",
    "gn:asciiname":"Mahall Nafwah",
    "gn:country_code":"YE",
    "gn:dem":2591,
    "gn:feature_class":"P",
    "gn:feature_code":"PPL",
    "gn:name":"Ma\u1e29all Nafwah",
    "gn:population":0,
    "gn:timezone":"Asia/Aden",
    "iso:country":"YE",
    "name:und_x_variant":[
        "Ma\u1e29all Nafwah"
    ],
    "wof:name":"Mahall Nafwah",
    "wof:placetype":"locality"
},
  "geometry": {"coordinates":[43.82043,15.7512],"type":"Point"}
}