{
  "type": "Feature",
  "properties": {
    "gn:admin1_code":"10.0",
    "gn:admin2_code":"2706.0",
    "gn:asciiname":"Tinab",
    "gn:country_code":"YE",
    "gn:dem":1689,
    "gn:feature_class":"P",
    "gn:feature_code":"PPL",
    "gn:name":"\u0162in\u0101b",
    "gn:population":0,
    "gn:timezone":"Asia/Aden",
    "iso:country":"YE",
    "name:ara_x_preferred":[
        "\u0162in\u0101b"
    ],
    "wof:name":"Tinab",
    "wof:placetype":"locality"
},
  "geometry": {"coordinates":[43.43817,15.40988],"type":"Point"}
}