{
  "type": "Feature",
  "properties": {
    "gn:admin1_code":"23.0",
    "gn:admin2_code":"1103.0",
    "gn:asciiname":"Hujayl",
    "gn:country_code":"YE",
    "gn:dem":2762,
    "gn:feature_class":"P",
    "gn:feature_code":"PPL",
    "gn:name":"\u1e28ujayl",
    "gn:population":0,
    "gn:timezone":"Asia/Aden",
    "iso:country":"YE",
    "name:und_x_variant":[
        "\u1e28ujayl"
    ],
    "wof:name":"Hujayl",
    "wof:placetype":"locality"
},
  "geometry": {"coordinates":[44.57065,14.15428],"type":"Point"}
}