{
  "type": "Feature",
  "properties": {
    "gn:admin1_code":"25.0",
    "gn:admin2_code":"1501.0",
    "gn:asciiname":"Zaribah",
    "gn:country_code":"YE",
    "gn:dem":1295,
    "gn:feature_class":"P",
    "gn:feature_code":"PPL",
    "gn:name":"Zar\u012bbah",
    "gn:population":0,
    "gn:timezone":"Asia/Aden",
    "iso:country":"YE",
    "name:und_x_variant":[
        "Zar\u012bbah"
    ],
    "wof:name":"Zaribah",
    "wof:placetype":"locality"
},
  "geometry": {"coordinates":[44.34385,13.63352],"type":"Point"}
}