{
  "type": "Feature",
  "properties": {
    "gn:admin1_code":"14.0",
    "gn:admin2_code":"2614.0",
    "gn:asciiname":"At Talhah",
    "gn:country_code":"YE",
    "gn:dem":1941,
    "gn:feature_class":"P",
    "gn:feature_code":"PPL",
    "gn:name":"A\u0163 \u0162al\u1e29ah",
    "gn:population":0,
    "gn:timezone":"Asia/Aden",
    "iso:country":"YE",
    "name:und_x_variant":[
        "A\u0163 \u0162al\u1e29ah"
    ],
    "wof:name":"At Talhah",
    "wof:placetype":"locality"
},
  "geometry": {"coordinates":[45.15763,15.08821],"type":"Point"}
}