{
  "type": "Feature",
  "properties": {
    "gn:admin1_code":"22.0",
    "gn:admin2_code":"1704.0",
    "gn:asciiname":"Al Bidah",
    "gn:country_code":"YE",
    "gn:dem":121,
    "gn:feature_class":"P",
    "gn:feature_code":"PPL",
    "gn:name":"Al Bid\u0101\u1e29",
    "gn:population":0,
    "gn:timezone":"Asia/Aden",
    "iso:country":"YE",
    "name:ara_x_preferred":[
        "Al Bid\u0101\u1e29"
    ],
    "name:und_x_variant":[
        "Al Bid\u0101\u2018"
    ],
    "wof:name":"Al Bidah",
    "wof:placetype":"locality"
},
  "geometry": {"coordinates":[43.12028,16.1148],"type":"Point"}
}