{
  "type": "Feature",
  "properties": {
    "gn:admin1_code":"25.0",
    "gn:admin2_code":"1517.0",
    "gn:asciiname":"`Amuq",
    "gn:country_code":"YE",
    "gn:dem":1383,
    "gn:feature_class":"P",
    "gn:feature_code":"PPL",
    "gn:name":"\u2018Am\u016bq",
    "gn:population":0,
    "gn:timezone":"Asia/Aden",
    "iso:country":"YE",
    "name:ara_x_preferred":[
        "\u2018Am\u016bq"
    ],
    "wof:name":"`Amuq",
    "wof:placetype":"locality"
},
  "geometry": {"coordinates":[44.28556,13.29028],"type":"Point"}
}