{
  "type": "Feature",
  "properties": {
    "gn:admin1_code":"15.0",
    "gn:admin2_code":"2212.0",
    "gn:asciiname":"Al Hudayrah",
    "gn:country_code":"YE",
    "gn:dem":1963,
    "gn:feature_class":"P",
    "gn:feature_code":"PPL",
    "gn:name":"Al \u1e28u\u1e11ayrah",
    "gn:population":0,
    "gn:timezone":"Asia/Aden",
    "iso:country":"YE",
    "name:ara_x_preferred":[
        "\u0627\u0644\u062d\u0636\u064a\u0631\u0629"
    ],
    "name:und_x_variant":[
        "Al \u1e28u\u1e11ayrah"
    ],
    "wof:name":"Al Hudayrah",
    "wof:placetype":"locality"
},
  "geometry": {"coordinates":[43.80104,16.80138],"type":"Point"}
}