{
  "type": "Feature",
  "properties": {
    "gn:admin1_code":"15.0",
    "gn:admin2_code":"2208.0",
    "gn:asciiname":"Al al Hallah",
    "gn:country_code":"YE",
    "gn:dem":1756,
    "gn:feature_class":"P",
    "gn:feature_code":"PPL",
    "gn:name":"\u0100l al Hallah",
    "gn:population":0,
    "gn:timezone":"Asia/Aden",
    "iso:country":"YE",
    "name:ara_x_preferred":[
        "\u0627\u0644 \u0627\u0644\u0647\u0644\u0629"
    ],
    "name:und_x_variant":[
        "Al Hallah",
        "\u0100l al Hallah"
    ],
    "wof:name":"Al al Hallah",
    "wof:placetype":"locality"
},
  "geometry": {"coordinates":[43.38048,16.82996],"type":"Point"}
}