{
  "type": "Feature",
  "properties": {
    "gn:admin1_code":"22.0",
    "gn:admin2_code":"1725.0",
    "gn:asciiname":"Al Qu'ad",
    "gn:country_code":"YE",
    "gn:dem":806,
    "gn:feature_class":"P",
    "gn:feature_code":"PPL",
    "gn:name":"Al Qu\u2018\u0101d",
    "gn:population":0,
    "gn:timezone":"Asia/Aden",
    "iso:country":"YE",
    "name:ara_x_preferred":[
        "\u0627\u0644\u0642\u0639\u0627\u062f"
    ],
    "name:und_x_variant":[
        "Al Qu\u2018\u0101d"
    ],
    "wof:name":"Al Qu'ad",
    "wof:placetype":"locality"
},
  "geometry": {"coordinates":[43.52393,15.57787],"type":"Point"}
}