{
  "type": "Feature",
  "properties": {
    "gn:admin1_code":"20.0",
    "gn:asciiname":"Al Majarin",
    "gn:country_code":"YE",
    "gn:dem":2198,
    "gn:feature_class":"P",
    "gn:feature_code":"PPL",
    "gn:name":"Al Maj\u0101r\u012bn",
    "gn:population":0,
    "gn:timezone":"Asia/Aden",
    "iso:country":"YE",
    "name:ara_x_preferred":[
        "\u0627\u0644\u0645\u062c\u0627\u0631\u064a\u0646"
    ],
    "name:und_x_variant":[
        "Al Maj\u0101r\u012bn"
    ],
    "wof:name":"Al Majarin",
    "wof:placetype":"locality"
},
  "geometry": {"coordinates":[44.37612,14.41957],"type":"Point"}
}