{
  "type": "Feature",
  "properties": {
    "gn:admin1_code":"19.0",
    "gn:admin2_code":"2916.0",
    "gn:asciiname":"Qaylab",
    "gn:country_code":"YE",
    "gn:dem":1708,
    "gn:feature_class":"P",
    "gn:feature_code":"PPL",
    "gn:name":"Qayl\u0101b",
    "gn:population":0,
    "gn:timezone":"Asia/Aden",
    "iso:country":"YE",
    "name:und_x_variant":[
        "Qayl\u0101b"
    ],
    "wof:name":"Qaylab",
    "wof:placetype":"locality"
},
  "geometry": {"coordinates":[43.71368,15.64937],"type":"Point"}
}