{
  "type": "Feature",
  "properties": {
    "gn:admin1_code":"11.0",
    "gn:admin2_code":"2005.0",
    "gn:asciiname":"Markaz `Utmah",
    "gn:country_code":"YE",
    "gn:dem":2042,
    "gn:feature_class":"P",
    "gn:feature_code":"PPL",
    "gn:name":"Markaz \u2018Utmah",
    "gn:population":0,
    "gn:timezone":"Asia/Aden",
    "iso:country":"YE",
    "name:und_x_variant":[
        "Markaz \u2018Utmah"
    ],
    "wof:name":"Markaz `Utmah",
    "wof:placetype":"locality"
},
  "geometry": {"coordinates":[44.01422,14.50361],"type":"Point"}
}