{
  "type": "Feature",
  "properties": {
    "gn:admin1_code":"11.0",
    "gn:admin2_code":"2011.0",
    "gn:asciiname":"Dhi Haywan",
    "gn:country_code":"YE",
    "gn:dem":1937,
    "gn:feature_class":"P",
    "gn:feature_code":"PPL",
    "gn:name":"Dh\u012b \u1e28ayw\u0101n",
    "gn:population":0,
    "gn:timezone":"Asia/Aden",
    "iso:country":"YE",
    "name:und_x_variant":[
        "Dh\u012b \u1e28ayw\u0101n"
    ],
    "wof:name":"Dhi Haywan",
    "wof:placetype":"locality"
},
  "geometry": {"coordinates":[44.04105,14.81691],"type":"Point"}
}