{
  "type": "Feature",
  "properties": {
    "gn:country":"YE",
    "gn:fcode":"PPL",
    "gn:pop":1,
    "iso:country":"YE",
    "name:ara_x_preferred":[
        "\u0627\u0644\u0642\u0631\u064a\u0629 \u0627\u0644\u0633\u0641\u0644\u0649"
    ],
    "name:eng_x_preferred":[
        "Al Qaryah As Sufla"
    ],
    "qs:name":"Al Qaryah as Sufl\u00e1",
    "qs:photos_9r":0,
    "qs:photos_sr":0,
    "qs:pop_sr":"1",
    "wof:name":"Al Qaryah as Sufl\u00e1",
    "wof:placetype":"locality",
    "wof:population":1
},
  "geometry": {"coordinates":[43.96352,13.13015],"type":"Point"}
}