{
  "type": "Feature",
  "properties": {
    "gn:admin1_code":"22.0",
    "gn:admin2_code":"1707.0",
    "gn:asciiname":"Al Marjam",
    "gn:country_code":"YE",
    "gn:dem":995,
    "gn:feature_class":"P",
    "gn:feature_code":"PPL",
    "gn:name":"Al Marjam",
    "gn:population":0,
    "gn:timezone":"Asia/Aden",
    "iso:country":"YE",
    "name:ara_x_preferred":[
        "\u0627\u0644\u0645\u0631\u062c\u0645"
    ],
    "wof:name":"Al Marjam",
    "wof:placetype":"locality"
},
  "geometry": {"coordinates":[43.4366,16.19971],"type":"Point"}
}