{
  "type": "Feature",
  "properties": {
    "gn:admin1_code":"19.0",
    "gn:admin2_code":"2907.0",
    "gn:asciiname":"Qayfan",
    "gn:country_code":"YE",
    "gn:dem":1170,
    "gn:feature_class":"P",
    "gn:feature_code":"PPL",
    "gn:name":"Qayf\u0101n",
    "gn:population":0,
    "gn:timezone":"Asia/Aden",
    "iso:country":"YE",
    "name:ara_x_preferred":[
        "\u0642\u064a\u0641\u0627\u0646"
    ],
    "name:und_x_variant":[
        "Qayf\u0101n"
    ],
    "wof:name":"Qayfan",
    "wof:placetype":"locality"
},
  "geometry": {"coordinates":[43.62923,16.09761],"type":"Point"}
}