{
  "type": "Feature",
  "properties": {
    "gn:country":"YE",
    "gn:fcode":"PPL",
    "gn:population":5,
    "iso:country":"YE",
    "name:ara_x_preferred":[
        "\u0627\u0644\u0639\u0642\u0644\u0629 \u0627\u0644\u0646\u0633\u0645\u0629"
    ],
    "name:eng_x_preferred":[
        "Al 'Uqlah An Nismah"
    ],
    "name:eng_x_variant":[
        "Al \u2018U\u0163fah"
    ],
    "qs:name":"Al \u2018Uqlah an Nismah",
    "qs:photos_9r":0,
    "qs:photos_sr":0,
    "qs:pop_sr":"1",
    "wof:name":"Al \u2018Uqlah an Nismah",
    "wof:placetype":"locality",
    "wof:population":5
},
  "geometry": {"coordinates":[45.36797,14.46165],"type":"Point"}
}