{
  "type": "Feature",
  "properties": {
    "gn:admin1_code":"22.0",
    "gn:admin2_code":"1706.0",
    "gn:asciiname":"Al hamra'",
    "gn:country_code":"YE",
    "gn:dem":165,
    "gn:feature_class":"P",
    "gn:feature_code":"PPL",
    "gn:name":"Al \u1e29amr\u0101\u2019",
    "gn:population":0,
    "gn:timezone":"Asia/Aden",
    "iso:country":"YE",
    "name:ara_x_preferred":[
        "\u0627\u0644\u062d\u0645\u0631\u0627\u0621"
    ],
    "name:und_x_variant":[
        "Al \u1e29amr\u0101\u2019"
    ],
    "wof:name":"Al hamra'",
    "wof:placetype":"locality"
},
  "geometry": {"coordinates":[43.16273,16.24004],"type":"Point"}
}