{
  "type": "Feature",
  "properties": {
    "gn:admin1_code":"23.0",
    "gn:admin2_code":"1101.0",
    "gn:asciiname":"Rajab",
    "gn:country_code":"YE",
    "gn:dem":1646,
    "gn:feature_class":"P",
    "gn:feature_code":"PPL",
    "gn:name":"Rajab",
    "gn:population":0,
    "gn:timezone":"Asia/Aden",
    "iso:country":"YE",
    "name:ara_x_preferred":[
        "\u0631\u062c\u0628"
    ],
    "wof:name":"Rajab",
    "wof:placetype":"locality"
},
  "geometry": {"coordinates":[44.16391,14.26561],"type":"Point"}
}