{
  "type": "Feature",
  "properties": {
    "gn:admin1_code":"23.0",
    "gn:admin2_code":"1101.0",
    "gn:asciiname":"Rajab",
    "gn:country_code":"YE",
    "gn:dem":1646,
    "gn:feature_class":"P",
    "gn:feature_code":"PPL",
    "gn:name":"Rajab",
    "gn:population":0,
    "gn:timezone":"Asia/Aden",
    "iso:country":"YE",
    "name:ace_x_preferred":[
        "Rajab"
    ],
    "name:ara_x_preferred":[
        "\u0631\u062c\u0628"
    ],
    "name:ava_x_preferred":[
        "\u0420\u0430\u0436\u0430\u0431"
    ],
    "name:aze_x_preferred":[
        "R\u0259c\u0259b"
    ],
    "name:bak_x_preferred":[
        "\u0420\u04d9\u0436\u04d9\u0431"
    ],
    "name:ben_x_preferred":[
        "\u09b0\u099c\u09ac"
    ],
    "name:bos_x_preferred":[
        "Red\u017eeb"
    ],
    "name:cat_x_preferred":[
        "R\u00e0jab"
    ],
    "name:che_x_preferred":[
        "\u0420\u0430\u0434\u0436\u0430\u0431"
    ],
    "name:ckb_x_preferred":[
        "\u0695\u06d5\u062c\u06d5\u0628"
    ],
    "name:dan_x_preferred":[
        "Rajab"
    ],
    "name:deu_x_preferred":[
        "Radschab"
    ],
    "name:diq_x_preferred":[
        "Receb"
    ],
    "name:eus_x_preferred":[
        "Rajab"
    ],
    "name:fas_x_preferred":[
        "\u0631\u062c\u0628"
    ],
    "name:fra_x_preferred":[
        "Rajab"
    ],
    "name:hau_x_preferred":[
        "Rajab"
    ],
    "name:heb_x_preferred":[
        "\u05e8\u05d2'\u05d1"
    ],
    "name:hin_x_preferred":[
        "\u0930\u091c\u094d\u091c\u092c"
    ],
    "name:ind_x_preferred":[
        "Rajab"
    ],
    "name:ita_x_preferred":[
        "Rajab"
    ],
    "name:jav_x_preferred":[
        "Rejeb"
    ],
    "name:kaz_x_preferred":[
        "\u0420\u0430\u0434\u0436\u0430\u0431"
    ],
    "name:kor_x_preferred":[
        "\ub77c\uc790\ube0c"
    ],
    "name:kur_x_preferred":[
        "Receb"
    ],
    "name:lbe_x_preferred":[
        "\u0420\u0430\u0434\u0436\u0430\u0431 \u0431\u0430\u0440\u0437"
    ],
    "name:mal_x_preferred":[
        "\u0d31\u0d1c\u0d2c\u0d4d"
    ],
    "name:msa_x_preferred":[
        "Rejab"
    ],
    "name:nld_x_preferred":[
        "Rajab"
    ],
    "name:pnb_x_preferred":[
        "\u0631\u062c\u0628"
    ],
    "name:pol_x_preferred":[
        "Rad\u017cab"
    ],
    "name:por_x_preferred":[
        "Rajabe"
    ],
    "name:rus_x_preferred":[
        "\u0420\u0430\u0434\u0436\u0430\u0431"
    ],
    "name:sco_x_preferred":[
        "Rajab"
    ],
    "name:snd_x_preferred":[
        "\u0631\u062c\u0628"
    ],
    "name:som_x_preferred":[
        "Rajab"
    ],
    "name:spa_x_preferred":[
        "Rayab"
    ],
    "name:sqi_x_preferred":[
        "Rexheb"
    ],
    "name:sun_x_preferred":[
        "Rojab"
    ],
    "name:swe_x_preferred":[
        "Rajab"
    ],
    "name:tam_x_preferred":[
        "\u0bb0\u0b9c\u0baa\u0bcd"
    ],
    "name:tat_x_preferred":[
        "\u0420\u04d9\u0497\u04d9\u043f"
    ],
    "name:tgk_x_preferred":[
        "\u0420\u0430\u04b7\u0430\u0431"
    ],
    "name:tha_x_preferred":[
        "\u0e40\u0e23\u0e32\u0e30\u0e0d\u0e31\u0e1a"
    ],
    "name:tur_x_preferred":[
        "Recep"
    ],
    "name:ukr_x_preferred":[
        "\u0420\u0430\u0434\u0436\u0430\u0431"
    ],
    "name:urd_x_preferred":[
        "\u0631\u062c\u0628"
    ],
    "name:uzb_x_preferred":[
        "Rajab oyi"
    ],
    "name:wol_x_preferred":[
        "Ndeyi-koor"
    ],
    "name:zho_x_preferred":[
        "\u8d56\u54f2\u535c\u6708"
    ],
    "wof:name":"Rajab",
    "wof:placetype":"locality"
},
  "geometry": {"coordinates":[44.16391,14.26561],"type":"Point"}
}