{
  "type": "Feature",
  "properties": {
    "gn:admin1_code":"23.0",
    "gn:admin2_code":"1106.0",
    "gn:asciiname":"Bayt al Juhaynah",
    "gn:country_code":"YE",
    "gn:dem":2724,
    "gn:feature_class":"P",
    "gn:feature_code":"PPL",
    "gn:name":"Bayt al Ju\u1e29aynah",
    "gn:population":0,
    "gn:timezone":"Asia/Aden",
    "iso:country":"YE",
    "name:ara_x_preferred":[
        "\u0628\u064a\u062a \u0627\u0644\u062c\u062d\u064a\u0646\u0629"
    ],
    "name:und_x_variant":[
        "Bayt al Ju\u1e29aynah"
    ],
    "wof:name":"Bayt al Juhaynah",
    "wof:placetype":"locality"
},
  "geometry": {"coordinates":[44.3905,14.18281],"type":"Point"}
}