{
  "type": "Feature",
  "properties": {
    "gn:admin1_code":"15.0",
    "gn:admin2_code":"2208.0",
    "gn:asciiname":"Al Ma'zab",
    "gn:country_code":"YE",
    "gn:dem":1291,
    "gn:feature_class":"P",
    "gn:feature_code":"PPL",
    "gn:name":"Al Ma\u2018zab",
    "gn:population":3,
    "gn:timezone":"Asia/Aden",
    "iso:country":"YE",
    "name:ara_x_preferred":[
        "\u0627\u0644\u0645\u0639\u0632\u0628"
    ],
    "name:und_x_variant":[
        "Al Ma\u2018zab"
    ],
    "wof:name":"Al Ma'zab",
    "wof:placetype":"locality",
    "wof:population":3
},
  "geometry": {"coordinates":[43.36976,16.68262],"type":"Point"}
}