{
  "type": "Feature",
  "properties": {
    "gn:admin1_code":"16.0",
    "gn:admin2_code":"2304.0",
    "gn:asciiname":"Ash Sha'b",
    "gn:country_code":"YE",
    "gn:dem":2339,
    "gn:feature_class":"P",
    "gn:feature_code":"PPL",
    "gn:name":"Ash Sha\u2018b",
    "gn:population":0,
    "gn:timezone":"Asia/Aden",
    "iso:country":"YE",
    "name:ara_x_preferred":[
        "\u0627\u0644\u0634\u0639\u0628"
    ],
    "name:und_x_variant":[
        "Ash Sha\u2018b"
    ],
    "wof:name":"Ash Sha'b",
    "wof:placetype":"locality"
},
  "geometry": {"coordinates":[44.42068,15.52195],"type":"Point"}
}