{
  "type": "Feature",
  "properties": {
    "gn:admin1_code":"5.0",
    "gn:admin2_code":"2109.0",
    "gn:asciiname":"Dhat al Jar",
    "gn:country_code":"YE",
    "gn:dem":995,
    "gn:feature_class":"P",
    "gn:feature_code":"PPL",
    "gn:name":"Dh\u0101t al J\u0101r",
    "gn:population":0,
    "gn:timezone":"Asia/Aden",
    "iso:country":"YE",
    "name:ara_x_preferred":[
        "\u0630\u0627\u062a \u0627\u0644\u062c\u0627\u0631"
    ],
    "name:und_x_variant":[
        "Dh\u0101t al J\u0101r"
    ],
    "wof:name":"Dhat al Jar",
    "wof:placetype":"locality"
},
  "geometry": {"coordinates":[46.43731,14.73255],"type":"Point"}
}