{
  "type": "Feature",
  "properties": {
    "gn:admin1_code":"8.0",
    "gn:admin2_code":"1810.0",
    "gn:asciiname":"Al Khadra'",
    "gn:country_code":"YE",
    "gn:dem":70,
    "gn:feature_class":"P",
    "gn:feature_code":"PPL",
    "gn:name":"Al Kha\u1e11r\u0101\u2019",
    "gn:population":0,
    "gn:timezone":"Asia/Aden",
    "iso:country":"YE",
    "name:und_x_variant":[
        "Al Kha\u1e11r\u0101\u2019"
    ],
    "wof:name":"Al Khadra'",
    "wof:placetype":"locality"
},
  "geometry": {"coordinates":[43.05551,15.04592],"type":"Point"}
}