{
  "type": "Feature",
  "properties": {
    "gn:admin1_code":"18.0",
    "gn:admin2_code":"3001.0",
    "gn:asciiname":"As Salamah",
    "gn:cc2":"YE",
    "gn:country_code":"YE",
    "gn:dem":1801,
    "gn:feature_class":"P",
    "gn:feature_code":"PPL",
    "gn:name":"As Sal\u0101mah",
    "gn:population":0,
    "gn:timezone":"Asia/Aden",
    "iso:country":"YE",
    "name:und_x_variant":[
        "Al Salamah",
        "As Sal\u0101mah"
    ],
    "wof:name":"As Salamah",
    "wof:placetype":"locality"
},
  "geometry": {"coordinates":[44.96667,14.15],"type":"Point"}
}