{
  "type": "Feature",
  "properties": {
    "gn:admin1_code":"19.0",
    "gn:admin2_code":"2905.0",
    "gn:asciiname":"Kharab ash Shami",
    "gn:country_code":"YE",
    "gn:dem":1318,
    "gn:feature_class":"P",
    "gn:feature_code":"PPL",
    "gn:name":"Khar\u0101b ash Sh\u0101m\u012b",
    "gn:population":0,
    "gn:timezone":"Asia/Aden",
    "iso:country":"YE",
    "name:und_x_variant":[
        "Khar\u0101b ash Sh\u0101m\u012b"
    ],
    "wof:name":"Kharab ash Shami",
    "wof:placetype":"locality"
},
  "geometry": {"coordinates":[43.74203,16.21106],"type":"Point"}
}