{
  "type": "Feature",
  "properties": {
    "gn:country":"YE",
    "gn:fcode":"PPL",
    "gn:pop":3,
    "iso:country":"YE",
    "name:ara_x_preferred":[
        "\u0627\u0644\u062b\u0648\u0639\u0629"
    ],
    "qs:name":"Ath Th\u016b\u2018ah",
    "qs:photos_9r":0,
    "qs:photos_sr":0,
    "qs:pop_sr":"1",
    "wof:name":"Ath Th\u016b\u2018ah",
    "wof:placetype":"locality",
    "wof:population":3
},
  "geometry": {"coordinates":[43.27314,17.16717],"type":"Point"}
}