{
  "type": "Feature",
  "properties": {
    "gn:admin1_code":"24.0",
    "gn:admin2_code":"2504.0",
    "gn:asciiname":"As Suwayda",
    "gn:country_code":"YE",
    "gn:dem":1529,
    "gn:feature_class":"P",
    "gn:feature_code":"PPLA2",
    "gn:name":"As Suwayd\u0101",
    "gn:population":0,
    "gn:timezone":"Asia/Aden",
    "iso:country":"YE",
    "name:ara_x_preferred":[
        "\u0627\u0644\u0633\u0648\u064a\u062f\u0627\u0621"
    ],
    "name:ara_x_variant":[
        "\u0627\u0644\u0633\u0648\u064a\u062f\u0627"
    ],
    "name:hun_x_preferred":[
        "As Suwayda"
    ],
    "name:und_x_variant":[
        "As Suwayd\u0101\u2019",
        "As Suwayd\u0101",
        "Suwayd\u0101"
    ],
    "wof:name":"As Suwayda",
    "wof:placetype":"locality"
},
  "geometry": {"coordinates":[45.2304,13.78694],"type":"Point"}
}