{
  "type": "Feature",
  "properties": {
    "gn:country":"YE",
    "gn:fcode":"HSE",
    "gn:pop":1,
    "iso:country":"YE",
    "name:ara_x_preferred":[
        "\u0628\u0646\u064a \u064a\u0645\u0627\u0646\u064a"
    ],
    "name:eng_x_preferred":[
        "Bani Yamani"
    ],
    "name:eng_x_variant":[
        "\u0100l Sh\u0101\u2019i\u2018"
    ],
    "name:unk_x_variant":[
        "\u0628\u0646\u064a \u064a\u0645\u0627\u0646\u064a"
    ],
    "qs:name":"Ban\u012b Yam\u0101n\u012b",
    "qs:photos_9r":0,
    "qs:photos_sr":0,
    "qs:pop_sr":"1",
    "wof:name":"Ban\u012b Yam\u0101n\u012b",
    "wof:placetype":"locality",
    "wof:population":1
},
  "geometry": {"coordinates":[42.90931,16.10906],"type":"Point"}
}