{
  "type": "Feature",
  "properties": {
    "gn:country":"YE",
    "gn:fcode":"PPL",
    "gn:population":6,
    "iso:country":"YE",
    "name:ara_x_preferred":[
        "\u0642\u0644\u0629 \u0627\u0644\u0633\u0631\u0648"
    ],
    "name:eng_x_preferred":[
        "Qullat As Sarw"
    ],
    "name:eng_x_variant":[
        "Al \u1e28\u0101\u0163"
    ],
    "qs:name":"Qullat as Sarw",
    "qs:photos_9r":0,
    "qs:photos_sr":0,
    "qs:pop_sr":"1",
    "wof:name":"Qullat as Sarw",
    "wof:placetype":"locality",
    "wof:population":6
},
  "geometry": {"coordinates":[43.40068,16.82986],"type":"Point"}
}