{
  "type": "Feature",
  "properties": {
    "gn:admin1_code":"22.0",
    "gn:admin2_code":"1716.0",
    "gn:asciiname":"Mashru` al Jabar",
    "gn:country_code":"YE",
    "gn:dem":1745,
    "gn:feature_class":"P",
    "gn:feature_code":"PPL",
    "gn:name":"Mashr\u016b\u2018 al Jabar",
    "gn:population":0,
    "gn:timezone":"Asia/Aden",
    "iso:country":"YE",
    "name:und_x_variant":[
        "Mashr\u016b\u2018 al Jabar"
    ],
    "wof:name":"Mashru` al Jabar",
    "wof:placetype":"locality"
},
  "geometry": {"coordinates":[43.47857,15.9731],"type":"Point"}
}