{
  "type": "Feature",
  "properties": {
    "gn:country":"YE",
    "gn:fcode":"PPL",
    "gn:pop":8,
    "iso:country":"YE",
    "name:ara_x_preferred":[
        "\u0627\u0644\u0642\u0645\u0627\u0645\u0629"
    ],
    "qs:name":"Al Qam\u0101mah",
    "qs:photos_9r":0,
    "qs:photos_sr":0,
    "qs:pop_sr":"1",
    "wof:name":"Al Qam\u0101mah",
    "wof:placetype":"locality",
    "wof:population":8
},
  "geometry": {"coordinates":[43.33634,16.30128],"type":"Point"}
}