{
  "type": "Feature",
  "properties": {
    "gn:admin1_code":"4.0",
    "gn:admin2_code":"1922.0",
    "gn:asciiname":"Hisn Dughaym",
    "gn:cc2":"YE",
    "gn:country_code":"YE",
    "gn:dem":1458,
    "gn:feature_class":"P",
    "gn:feature_code":"PPL",
    "gn:name":"\u1e28i\u015fn Dughaym",
    "gn:population":0,
    "gn:timezone":"Asia/Aden",
    "iso:country":"YE",
    "name:und_x_variant":[
        "Husn Dugham",
        "\u1e28u\u015fn Dughaym",
        "\u1e24u\u1e63n Dughaim",
        "\u1e28i\u015fn Dughaym"
    ],
    "wof:name":"Hisn Dughaym",
    "wof:placetype":"locality"
},
  "geometry": {"coordinates":[47.95,14.98333],"type":"Point"}
}