{
  "type": "Feature",
  "properties": {
    "gn:admin1_code":"19.0",
    "gn:admin2_code":"2913.0",
    "gn:asciiname":"Mahall Darqam",
    "gn:country_code":"YE",
    "gn:dem":1348,
    "gn:feature_class":"P",
    "gn:feature_code":"PPL",
    "gn:name":"Ma\u1e29all Darqam",
    "gn:population":0,
    "gn:timezone":"Asia/Aden",
    "iso:country":"YE",
    "name:und_x_variant":[
        "Ma\u1e29all Darqam"
    ],
    "wof:name":"Mahall Darqam",
    "wof:placetype":"locality"
},
  "geometry": {"coordinates":[43.73317,15.97529],"type":"Point"}
}