{
  "type": "Feature",
  "properties": {
    "gn:admin1_code":"4.0",
    "gn:admin2_code":"1907.0",
    "gn:asciiname":"Hazm Haynan",
    "gn:cc2":"YE",
    "gn:country_code":"YE",
    "gn:dem":699,
    "gn:feature_class":"P",
    "gn:feature_code":"PPL",
    "gn:name":"\u1e28azm Haynan",
    "gn:population":0,
    "gn:timezone":"Asia/Aden",
    "iso:country":"YE",
    "name:nno_x_preferred":[
        "Hazm Haynan"
    ],
    "name:und_x_variant":[
        "\u1e28azm Haynin",
        "\u1e28azm Haynan"
    ],
    "wof:name":"Hazm Haynan",
    "wof:placetype":"locality"
},
  "geometry": {"coordinates":[48.30806,15.82778],"type":"Point"}
}