{
  "type": "Feature",
  "properties": {
    "gn:admin1_code":"15.0",
    "gn:admin2_code":"2204.0",
    "gn:asciiname":"Jida`",
    "gn:country_code":"YE",
    "gn:dem":1557,
    "gn:feature_class":"P",
    "gn:feature_code":"PPL",
    "gn:name":"Jid\u0101\u2018",
    "gn:population":0,
    "gn:timezone":"Asia/Aden",
    "iso:country":"YE",
    "name:ara_x_preferred":[
        "Jid\u0101\u2018"
    ],
    "wof:name":"Jida`",
    "wof:placetype":"locality"
},
  "geometry": {"coordinates":[43.31129,17.02132000000001],"type":"Point"}
}