{
  "type": "Feature",
  "properties": {
    "gn:admin1_code":"22.0",
    "gn:admin2_code":"1721.0",
    "gn:asciiname":"Bayt Jabbar",
    "gn:country_code":"YE",
    "gn:dem":1203,
    "gn:feature_class":"P",
    "gn:feature_code":"PPL",
    "gn:name":"Bayt Jabb\u0101r",
    "gn:population":0,
    "gn:timezone":"Asia/Aden",
    "iso:country":"YE",
    "name:und_x_variant":[
        "Bayt Jabb\u0101r"
    ],
    "wof:name":"Bayt Jabbar",
    "wof:placetype":"locality"
},
  "geometry": {"coordinates":[43.47742,15.86692],"type":"Point"}
}