{
  "type": "Feature",
  "properties": {
    "gn:admin1_code":"25.0",
    "gn:admin2_code":"1502.0",
    "gn:asciiname":"Al Batra'",
    "gn:country_code":"YE",
    "gn:dem":1366,
    "gn:feature_class":"P",
    "gn:feature_code":"PPL",
    "gn:name":"Al Batr\u0101\u2019",
    "gn:population":0,
    "gn:timezone":"Asia/Aden",
    "iso:country":"YE",
    "name:und_x_variant":[
        "Al Batr\u0101\u2019"
    ],
    "wof:name":"Al Batra'",
    "wof:placetype":"locality"
},
  "geometry": {"coordinates":[44.06542,13.60962],"type":"Point"}
}