{
  "type": "Feature",
  "properties": {
    "gn:admin1_code":"16.0",
    "gn:admin2_code":"2302.0",
    "gn:asciiname":"Bayt `Asta",
    "gn:country_code":"YE",
    "gn:dem":2345,
    "gn:feature_class":"P",
    "gn:feature_code":"PPL",
    "gn:name":"Bayt \u2018A\u015f\u0163\u0101",
    "gn:population":0,
    "gn:timezone":"Asia/Aden",
    "iso:country":"YE",
    "name:und_x_variant":[
        "Bayt \u2018A\u015f\u0163\u0101"
    ],
    "wof:name":"Bayt `Asta",
    "wof:placetype":"locality"
},
  "geometry": {"coordinates":[44.32539000000001,15.76757],"type":"Point"}
}