{
  "type": "Feature",
  "properties": {
    "gn:admin1_code":"19.0",
    "gn:admin2_code":"2904.0",
    "gn:asciiname":"Qarn Ghadhiyah",
    "gn:country_code":"YE",
    "gn:dem":1165,
    "gn:feature_class":"P",
    "gn:feature_code":"PPL",
    "gn:name":"Qarn Gh\u0101dh\u012byah",
    "gn:population":0,
    "gn:timezone":"Asia/Aden",
    "iso:country":"YE",
    "name:ara_x_preferred":[
        "\u0642\u0631\u0646 \u063a\u0627\u0630\u064a\u0629"
    ],
    "name:und_x_variant":[
        "Qarn Gh\u0101dh\u012byah"
    ],
    "wof:name":"Qarn Ghadhiyah",
    "wof:placetype":"locality"
},
  "geometry": {"coordinates":[43.7988,16.19932],"type":"Point"}
}