{
  "type": "Feature",
  "properties": {
    "gn:admin1_code":"22.0",
    "gn:admin2_code":"1727.0",
    "gn:asciiname":"Bayt al Khamasi",
    "gn:country_code":"YE",
    "gn:dem":1167,
    "gn:feature_class":"P",
    "gn:feature_code":"PPL",
    "gn:name":"Bayt al Kham\u0101s\u012b",
    "gn:population":0,
    "gn:timezone":"Asia/Aden",
    "iso:country":"YE",
    "name:ara_x_preferred":[
        "\u0628\u064a\u062a \u0627\u0644\u062e\u0645\u0627\u0633\u064a"
    ],
    "name:und_x_variant":[
        "Bayt al Kham\u0101s\u012b"
    ],
    "wof:name":"Bayt al Khamasi",
    "wof:placetype":"locality"
},
  "geometry": {"coordinates":[43.56051,15.5705],"type":"Point"}
}