{
  "type": "Feature",
  "properties": {
    "gn:country":"YE",
    "gn:fcode":"PPL",
    "gn:pop":7,
    "iso:country":"YE",
    "name:ara_x_preferred":[
        "\u0627\u0644 \u062c\u0639\u064a\u0631"
    ],
    "name:eng_x_preferred":[
        "Al Ju'ayr"
    ],
    "name:eng_x_variant":[
        "Al Waq\u0101\u2019ir"
    ],
    "qs:name":"Al Ju\u2018ayr",
    "qs:photos_9r":0,
    "qs:photos_sr":0,
    "qs:pop_sr":"1",
    "wof:name":"Al Ju\u2018ayr",
    "wof:placetype":"locality",
    "wof:population":7
},
  "geometry": {"coordinates":[45.32686,15.44641],"type":"Point"}
}