{
  "type": "Feature",
  "properties": {
    "gn:admin1_code":"16.0",
    "gn:admin2_code":"2303.0",
    "gn:asciiname":"Al 'Arqub",
    "gn:country_code":"YE",
    "gn:dem":2151,
    "gn:feature_class":"P",
    "gn:feature_code":"PPL",
    "gn:name":"Al \u2018Arq\u016bb",
    "gn:population":0,
    "gn:timezone":"Asia/Aden",
    "iso:country":"YE",
    "name:ara_x_preferred":[
        "\u0627\u0644\u0639\u0631\u0642\u0648\u0628"
    ],
    "name:und_x_variant":[
        "Al \u2018Arq\u016bb"
    ],
    "wof:name":"Al 'Arqub",
    "wof:placetype":"locality"
},
  "geometry": {"coordinates":[44.58711,15.68876],"type":"Point"}
}