{
  "type": "Feature",
  "properties": {
    "gn:admin1_code":"27.0",
    "gn:admin2_code":"3102.0",
    "gn:asciiname":"Al Marbu`",
    "gn:country_code":"YE",
    "gn:dem":443,
    "gn:feature_class":"P",
    "gn:feature_code":"PPL",
    "gn:name":"Al Marb\u016b\u2018",
    "gn:population":0,
    "gn:timezone":"Asia/Aden",
    "iso:country":"YE",
    "name:und_x_variant":[
        "Al Marb\u016b\u2018"
    ],
    "wof:name":"Al Marbu`",
    "wof:placetype":"locality"
},
  "geometry": {"coordinates":[43.51999,14.67009],"type":"Point"}
}