{
  "type": "Feature",
  "properties": {
    "gn:admin1_code":"22.0",
    "gn:admin2_code":"1722.0",
    "gn:asciiname":"As Sudah",
    "gn:country_code":"YE",
    "gn:dem":274,
    "gn:feature_class":"P",
    "gn:feature_code":"PPL",
    "gn:name":"As S\u016bdah",
    "gn:population":0,
    "gn:timezone":"Asia/Aden",
    "iso:country":"YE",
    "name:und_x_variant":[
        "As S\u016bdah"
    ],
    "wof:name":"As Sudah",
    "wof:placetype":"locality"
},
  "geometry": {"coordinates":[43.26703,15.92336],"type":"Point"}
}