{
  "type": "Feature",
  "properties": {
    "gn:admin1_code":"8.0",
    "gn:admin2_code":"1813.0",
    "gn:asciiname":"Mahall al `Aqarah",
    "gn:country_code":"YE",
    "gn:dem":170,
    "gn:feature_class":"P",
    "gn:feature_code":"PPL",
    "gn:name":"Ma\u1e29all al \u2018Aq\u0101rah",
    "gn:population":0,
    "gn:timezone":"Asia/Aden",
    "iso:country":"YE",
    "name:und_x_variant":[
        "Ma\u1e29all al \u2018Aq\u0101rah"
    ],
    "wof:name":"Mahall al `Aqarah",
    "wof:placetype":"locality"
},
  "geometry": {"coordinates":[43.34445,14.91057],"type":"Point"}
}