{
  "type": "Feature",
  "properties": {
    "gn:country":"YE",
    "gn:fcode":"PPL",
    "gn:population":12,
    "iso:country":"YE",
    "name:ara_x_preferred":[
        "\u0646\u0634\u0648\u0627\u0646"
    ],
    "name:eng_x_preferred":[
        "Nashwan"
    ],
    "name:fra_x_preferred":[
        "Nashwan"
    ],
    "name:jpn_x_preferred":[
        "\u30ca\u30b7\u30e5\u30ef\u30f3"
    ],
    "name:spa_x_preferred":[
        "Nashwan"
    ],
    "qs:name":"Nashw\u0101n",
    "qs:photos_9r":0,
    "qs:photos_sr":0,
    "qs:pop_sr":"1",
    "wd:wordcount":1347,
    "wof:name":"Nashw\u0101n",
    "wof:placetype":"locality",
    "wof:population":12
},
  "geometry": {"coordinates":[43.43705,16.79346],"type":"Point"}
}