{
  "type": "Feature",
  "properties": {
    "gn:admin1_code":"19.0",
    "gn:admin2_code":"2919.0",
    "gn:asciiname":"Az Za'la",
    "gn:country_code":"YE",
    "gn:dem":2307,
    "gn:feature_class":"P",
    "gn:feature_code":"PPL",
    "gn:name":"Az Za\u2018l\u0101",
    "gn:population":0,
    "gn:timezone":"Asia/Aden",
    "iso:country":"YE",
    "name:ara_x_preferred":[
        "\u0627\u0644\u0632\u0639\u0644\u0627"
    ],
    "name:und_x_variant":[
        "Az Za\u2018l\u0101"
    ],
    "wof:name":"Az Za'la",
    "wof:placetype":"locality"
},
  "geometry": {"coordinates":[43.92342,16.04088],"type":"Point"}
}