{
  "type": "Feature",
  "properties": {
    "gn:country":"YE",
    "gn:fcode":"PPLX",
    "gn:pop":25,
    "iso:country":"YE",
    "name:ara_x_preferred":[
        "\u0622\u0644 \u0634\u0648\u064a\u0637"
    ],
    "qs:name":"\u0100l Shuway\u0163",
    "qs:photos_9r":0,
    "qs:photos_sr":0,
    "qs:pop_sr":"1",
    "wof:name":"\u0100l Shuway\u0163",
    "wof:placetype":"neighbourhood",
    "wof:population":25
},
  "geometry": {"coordinates":[43.75304,16.75854],"type":"Point"}
}