{
  "type": "Feature",
  "properties": {
    "gn:admin1_code":"20.0",
    "gn:asciiname":"Al Mi`mar",
    "gn:country_code":"YE",
    "gn:dem":2066,
    "gn:feature_class":"P",
    "gn:feature_code":"PPL",
    "gn:name":"Al Mi\u2018m\u0101r",
    "gn:population":0,
    "gn:timezone":"Asia/Aden",
    "iso:country":"YE",
    "name:ara_x_preferred":[
        "\u0627\u0644\u0645\u0639\u0645\u0627\u0631"
    ],
    "name:und_x_variant":[
        "Al Mi\u2018m\u0101r"
    ],
    "wof:name":"Al Mi`mar",
    "wof:placetype":"locality"
},
  "geometry": {"coordinates":[44.29498,14.41354],"type":"Point"}
}