{
  "type": "Feature",
  "properties": {
    "gn:country":"YE",
    "gn:fcode":"PPL",
    "gn:population":7,
    "iso:country":"YE",
    "name:ara_x_preferred":[
        "\u0627\u0644\u0645\u0641\u0644\u0637\u062d"
    ],
    "qs_pg:aaroncc":"YE",
    "qs_pg:gn_country":"YE",
    "qs_pg:gn_fcode":"PPL",
    "qs_pg:gn_pop":7,
    "qs_pg:name":"Al Mufal\u0163a\u1e29",
    "qs_pg:photos_9r":0,
    "qs_pg:photos_sr":0,
    "qs_pg:pop_sr":1,
    "qs_pg:qs_pg_placetype":"locality",
    "wof:name":"Al Mufal\u0163a\u1e29",
    "wof:placetype":"locality",
    "wof:population":7
},
  "geometry": {"coordinates":[43.33871,16.24543],"type":"Point"}
}