{
  "type": "Feature",
  "properties": {
    "gn:admin1_code":"16.0",
    "gn:admin2_code":"2310.0",
    "gn:asciiname":"Lakamat al Kuruf",
    "gn:country_code":"YE",
    "gn:dem":1715,
    "gn:feature_class":"P",
    "gn:feature_code":"PPL",
    "gn:name":"Lakamat al Kur\u016bf",
    "gn:population":0,
    "gn:timezone":"Asia/Aden",
    "iso:country":"YE",
    "name:und_x_variant":[
        "Lakamat al Kur\u016bf"
    ],
    "wof:name":"Lakamat al Kuruf",
    "wof:placetype":"locality"
},
  "geometry": {"coordinates":[43.78487,15.06512],"type":"Point"}
}