{
  "type": "Feature",
  "properties": {
    "gn:country":"YE",
    "gn:fcode":"PPL",
    "gn:pop":1,
    "iso:country":"YE",
    "name:ara_x_preferred":[
        "Al Ju\u1e29f\u0101\u2019"
    ],
    "name:ara_x_variant":[
        "\u0627\u0644\u062c\u062d\u0641\u0627\u0621"
    ],
    "name:eng_x_preferred":[
        "Al Juhfa"
    ],
    "qs:name":"Al Ju\u1e29f\u0101\u2019",
    "qs:photos_9r":0,
    "qs:photos_sr":0,
    "qs:pop_sr":"1",
    "wof:name":"Al Ju\u1e29f\u0101\u2019",
    "wof:placetype":"locality",
    "wof:population":1
},
  "geometry": {"coordinates":[43.3249,17.50367],"type":"Point"}
}