{
  "type": "Feature",
  "properties": {
    "gn:country":"YE",
    "gn:fcode":"PPL",
    "gn:population":1,
    "iso:country":"YE",
    "name:ara_x_preferred":[
        "\u0645\u0648\u0627\u0644 \u0634\u0648\u0639\u064a"
    ],
    "name:eng_x_preferred":[
        "Mawal Shawa'i"
    ],
    "name:eng_x_variant":[
        "Al Qaz\u016b\u2018"
    ],
    "qs:name":"Maw\u0101l Shawa\u2018\u012b",
    "qs:photos_9r":0,
    "qs:photos_sr":0,
    "qs:pop_sr":"1",
    "wof:name":"Maw\u0101l Shawa\u2018\u012b",
    "wof:placetype":"locality",
    "wof:population":1
},
  "geometry": {"coordinates":[43.31319,16.63938],"type":"Point"}
}