{
  "type": "Feature",
  "properties": {
    "gn:admin1_code":"22.0",
    "gn:admin2_code":"1701.0",
    "gn:asciiname":"As Sirr",
    "gn:country_code":"YE",
    "gn:dem":413,
    "gn:feature_class":"P",
    "gn:feature_code":"PPL",
    "gn:name":"As Sirr",
    "gn:population":0,
    "gn:timezone":"Asia/Aden",
    "iso:country":"YE",
    "name:ara_x_preferred":[
        "\u0627\u0644\u0633\u0631"
    ],
    "wof:name":"As Sirr",
    "wof:placetype":"locality"
},
  "geometry": {"coordinates":[43.31679000000001,16.50999],"type":"Point"}
}