{
  "type": "Feature",
  "properties": {
    "gn:admin1_code":"23.0",
    "gn:admin2_code":"1101.0",
    "gn:asciiname":"Al Ma'aridi",
    "gn:country_code":"YE",
    "gn:dem":1428,
    "gn:feature_class":"P",
    "gn:feature_code":"PPL",
    "gn:name":"Al Ma\u2018\u0101r\u012b\u1e11\u012b",
    "gn:population":0,
    "gn:timezone":"Asia/Aden",
    "iso:country":"YE",
    "name:ara_x_preferred":[
        "\u0627\u0644\u0645\u0639\u0627\u0631\u064a\u0636\u064a"
    ],
    "name:und_x_variant":[
        "Al Ma\u2018\u0101r\u012b\u1e11\u012b"
    ],
    "wof:name":"Al Ma'aridi",
    "wof:placetype":"locality"
},
  "geometry": {"coordinates":[44.12006,14.29718],"type":"Point"}
}