{
  "type": "Feature",
  "properties": {
    "gn:country":"YE",
    "gn:fcode":"PPL",
    "gn:pop":4,
    "iso:country":"YE",
    "name:ara_x_preferred":[
        "\u0627\u0644\u0645\u0634\u0631\u0641\u0629"
    ],
    "name:eng_x_preferred":[
        "Al Mashrifah"
    ],
    "name:eng_x_variant":[
        "Shawk\u0101n"
    ],
    "qs:name":"Al Mashrifah",
    "qs:photos_9r":0,
    "qs:photos_sr":0,
    "qs:pop_sr":"1",
    "wof:name":"Al Mashrifah",
    "wof:placetype":"locality",
    "wof:population":4
},
  "geometry": {"coordinates":[45.14445,14.69802],"type":"Point"}
}