{
  "type": "Feature",
  "properties": {
    "gn:admin1_code":"25.0",
    "gn:admin2_code":"1505.0",
    "gn:asciiname":"Al Marnuf",
    "gn:country_code":"YE",
    "gn:dem":364,
    "gn:feature_class":"P",
    "gn:feature_code":"PPL",
    "gn:name":"Al Marn\u016bf",
    "gn:population":0,
    "gn:timezone":"Asia/Aden",
    "iso:country":"YE",
    "name:und_x_variant":[
        "Al Marn\u016bf"
    ],
    "wof:name":"Al Marnuf",
    "wof:placetype":"locality"
},
  "geometry": {"coordinates":[43.59178,13.85384],"type":"Point"}
}