{
  "type": "Feature",
  "properties": {
    "gn:admin1_code":"8.0",
    "gn:admin2_code":"1817.0",
    "gn:asciiname":"Ash Shatt",
    "gn:country_code":"YE",
    "gn:dem":207,
    "gn:feature_class":"P",
    "gn:feature_code":"PPL",
    "gn:name":"Ash Sha\u0163\u0163",
    "gn:population":0,
    "gn:timezone":"Asia/Aden",
    "iso:country":"YE",
    "name:und_x_variant":[
        "Ash Sha\u0163\u0163"
    ],
    "wof:name":"Ash Shatt",
    "wof:placetype":"locality"
},
  "geometry": {"coordinates":[43.44677,14.59907],"type":"Point"}
}