{
  "type": "Feature",
  "properties": {
    "gn:admin1_code":"23.0",
    "gn:admin2_code":"1101.0",
    "gn:asciiname":"Al Asbal",
    "gn:country_code":"YE",
    "gn:dem":1457,
    "gn:feature_class":"P",
    "gn:feature_code":"PPL",
    "gn:name":"Al Asb\u0101l",
    "gn:population":0,
    "gn:timezone":"Asia/Aden",
    "iso:country":"YE",
    "name:ara_x_preferred":[
        "\u0627\u0644\u0623\u0633\u0628\u0627\u0644"
    ],
    "name:und_x_variant":[
        "Al Asb\u0101l"
    ],
    "wof:name":"Al Asbal",
    "wof:placetype":"locality"
},
  "geometry": {"coordinates":[44.11165,14.29127],"type":"Point"}
}