{
  "type": "Feature",
  "properties": {
    "gn:country":"YE",
    "gn:fcode":"PPLX",
    "gn:population":64,
    "iso:country":"YE",
    "name:ara_x_preferred":[
        "\u0648\u0631\u062f\u0629"
    ],
    "qs:name":"Waridah",
    "qs:photos_9r":0,
    "qs:photos_sr":0,
    "qs:pop_sr":"1",
    "wof:name":"Waridah",
    "wof:placetype":"neighbourhood",
    "wof:population":64
},
  "geometry": {"coordinates":[44.36307,16.73359],"type":"Point"}
}