{
  "type": "Feature",
  "properties": {
    "gn:country":"YE",
    "gn:fcode":"PPL",
    "gn:pop":4,
    "iso:country":"YE",
    "name:ara_x_preferred":[
        "\u0627\u0644\u0635\u062f\u0627\u0631\u0629"
    ],
    "name:eng_x_preferred":[
        "As Sidarah"
    ],
    "name:eng_x_variant":[
        "Bi\u2019r Barak\u0101t"
    ],
    "qs:name":"A\u015f \u015eid\u0101rah",
    "qs:photos_9r":0,
    "qs:photos_sr":0,
    "qs:pop_sr":"1",
    "wof:name":"A\u015f \u015eid\u0101rah",
    "wof:placetype":"locality",
    "wof:population":4
},
  "geometry": {"coordinates":[43.43183,16.09531],"type":"Point"}
}