{
  "type": "Feature",
  "properties": {
    "gn:admin1_code":"8.0",
    "gn:admin2_code":"1814.0",
    "gn:asciiname":"Buyut an Naharin",
    "gn:country_code":"YE",
    "gn:dem":89,
    "gn:feature_class":"P",
    "gn:feature_code":"PPL",
    "gn:name":"Buy\u016bt an Nah\u0101r\u012bn",
    "gn:population":0,
    "gn:timezone":"Asia/Aden",
    "iso:country":"YE",
    "name:und_x_variant":[
        "Buy\u016bt an Nah\u0101r\u012bn"
    ],
    "wof:name":"Buyut an Naharin",
    "wof:placetype":"locality"
},
  "geometry": {"coordinates":[43.24573,14.65528],"type":"Point"}
}