{
  "type": "Feature",
  "properties": {
    "gn:admin1_code":"24.0",
    "gn:admin2_code":"2510.0",
    "gn:asciiname":"Al Ka`thal",
    "gn:country_code":"YE",
    "gn:dem":1289,
    "gn:feature_class":"P",
    "gn:feature_code":"PPL",
    "gn:name":"Al Ka\u2018thal",
    "gn:population":0,
    "gn:timezone":"Asia/Aden",
    "iso:country":"YE",
    "name:und_x_variant":[
        "Al Ka\u2018thal"
    ],
    "wof:name":"Al Ka`thal",
    "wof:placetype":"locality"
},
  "geometry": {"coordinates":[44.43234,13.23984],"type":"Point"}
}