{
  "type": "Feature",
  "properties": {
    "gn:admin1_code":"8.0",
    "gn:admin2_code":"1807.0",
    "gn:asciiname":"Muhammad 'Abd Allah Madani",
    "gn:country_code":"YE",
    "gn:dem":54,
    "gn:feature_class":"P",
    "gn:feature_code":"PPL",
    "gn:name":"Mu\u1e29ammad \u2018Abd All\u0101h Madan\u012b",
    "gn:population":0,
    "gn:timezone":"Asia/Aden",
    "iso:country":"YE",
    "name:ara_x_preferred":[
        "\u0645\u062d\u0645\u062f \u0639\u0628\u062f \u0627\u0644\u0644\u0647 \u0645\u062f\u0646\u064a"
    ],
    "name:und_x_variant":[
        "Mu\u1e29ammad \u2018Abd All\u0101h Madan\u012b"
    ],
    "wof:name":"Muhammad 'Abd Allah Madani",
    "wof:placetype":"locality"
},
  "geometry": {"coordinates":[43.00424,15.23899],"type":"Point"}
}