{
  "type": "Feature",
  "properties": {
    "gn:admin1_code":"23.0",
    "gn:admin2_code":"1101.0",
    "gn:asciiname":"Sha'b al Hujjaj",
    "gn:country_code":"YE",
    "gn:dem":1268,
    "gn:feature_class":"P",
    "gn:feature_code":"PPL",
    "gn:name":"Sha\u2018b al \u1e28ujj\u0101j",
    "gn:population":0,
    "gn:timezone":"Asia/Aden",
    "iso:country":"YE",
    "name:ara_x_preferred":[
        "\u0634\u0639\u0628 \u0627\u0644\u062d\u062c\u0627\u062c"
    ],
    "name:und_x_variant":[
        "Sha\u2018b al \u1e28ujj\u0101j"
    ],
    "wof:name":"Sha'b al Hujjaj",
    "wof:placetype":"locality"
},
  "geometry": {"coordinates":[44.07619,14.31159],"type":"Point"}
}