{
  "type": "Feature",
  "properties": {
    "gn:admin1_code":"16.0",
    "gn:admin2_code":"2316.0",
    "gn:asciiname":"Bayt al Huduri",
    "gn:country_code":"YE",
    "gn:dem":2301,
    "gn:feature_class":"P",
    "gn:feature_code":"PPL",
    "gn:name":"Bayt al \u1e28u\u1e11\u016br\u012b",
    "gn:population":0,
    "gn:timezone":"Asia/Aden",
    "iso:country":"YE",
    "name:ara_x_preferred":[
        "\u0628\u064a\u062a \u0627\u0644\u062d\u0636\u0648\u0631\u064a"
    ],
    "name:und_x_variant":[
        "Bayt al \u1e28u\u1e11\u016br\u012b"
    ],
    "wof:name":"Bayt al Huduri",
    "wof:placetype":"locality"
},
  "geometry": {"coordinates":[44.53936,15.27331],"type":"Point"}
}