{
  "type": "Feature",
  "properties": {
    "gn:admin1_code":"25.0",
    "gn:admin2_code":"1508.0",
    "gn:asciiname":"Al Hajir",
    "gn:country_code":"YE",
    "gn:dem":272,
    "gn:feature_class":"P",
    "gn:feature_code":"PPL",
    "gn:name":"Al \u1e28aj\u012br",
    "gn:population":0,
    "gn:timezone":"Asia/Aden",
    "iso:country":"YE",
    "name:ara_x_preferred":[
        "\u0627\u0644\u062d\u062c\u064a\u0631"
    ],
    "name:und_x_variant":[
        "Al \u1e28aj\u012br"
    ],
    "wof:name":"Al Hajir",
    "wof:placetype":"locality"
},
  "geometry": {"coordinates":[43.5688,13.31005],"type":"Point"}
}