{
  "type": "Feature",
  "properties": {
    "gn:admin1_code":"19.0",
    "gn:admin2_code":"2914.0",
    "gn:asciiname":"Ma`mar Waththab",
    "gn:country_code":"YE",
    "gn:dem":1931,
    "gn:feature_class":"P",
    "gn:feature_code":"PPL",
    "gn:name":"Ma\u2018mar Wathth\u0101b",
    "gn:population":0,
    "gn:timezone":"Asia/Aden",
    "iso:country":"YE",
    "name:und_x_variant":[
        "Ma\u2018mar Wathth\u0101b"
    ],
    "wof:name":"Ma`mar Waththab",
    "wof:placetype":"locality"
},
  "geometry": {"coordinates":[43.76739,15.77067],"type":"Point"}
}