{
  "type": "Feature",
  "properties": {
    "gn:country":"YE",
    "gn:fcode":"PPL",
    "gn:pop":17,
    "iso:country":"YE",
    "name:ara_x_preferred":[
        "\u0627\u0644 \u0645\u0647\u062f\u064a\u0629"
    ],
    "name:eng_x_preferred":[
        "Al Mahdiyah"
    ],
    "qs:name":"Al Mahd\u012byah",
    "qs:photos_9r":0,
    "qs:photos_sr":0,
    "qs:pop_sr":"1",
    "wof:name":"Al Mahd\u012byah",
    "wof:placetype":"locality",
    "wof:population":17
},
  "geometry": {"coordinates":[43.24012,17.1043],"type":"Point"}
}