{
  "type": "Feature",
  "properties": {
    "gn:admin1_code":"11.0",
    "gn:admin2_code":"1102.0",
    "gn:asciiname":"Al Qahirah",
    "gn:country_code":"YE",
    "gn:dem":2719,
    "gn:feature_class":"P",
    "gn:feature_code":"PPL",
    "gn:name":"Al Q\u0101hirah",
    "gn:population":0,
    "gn:timezone":"Asia/Aden",
    "iso:country":"YE",
    "name:ara_x_preferred":[
        "\u0627\u0644\u0642\u0627\u0647\u0631\u0629"
    ],
    "name:und_x_variant":[
        "Al Q\u0101hirah"
    ],
    "wof:name":"Al Qahirah",
    "wof:placetype":"locality"
},
  "geometry": {"coordinates":[44.38956,14.26634],"type":"Point"}
}