{
  "type": "Feature",
  "properties": {
    "gn:admin1_code":"8.0",
    "gn:admin2_code":"1815.0",
    "gn:asciiname":"Al Maqabil",
    "gn:country_code":"YE",
    "gn:dem":112,
    "gn:feature_class":"P",
    "gn:feature_code":"PPL",
    "gn:name":"Al Maq\u0101b\u012bl",
    "gn:population":0,
    "gn:timezone":"Asia/Aden",
    "iso:country":"YE",
    "name:ara_x_preferred":[
        "\u0627\u0644\u0645\u0642\u0627\u0628\u064a\u0644"
    ],
    "name:und_x_variant":[
        "Al Maq\u0101b\u012bl"
    ],
    "wof:name":"Al Maqabil",
    "wof:placetype":"locality"
},
  "geometry": {"coordinates":[43.24116,14.70715],"type":"Point"}
}