{
  "type": "Feature",
  "properties": {
    "gn:country":"YE",
    "gn:fcode":"PPL",
    "gn:population":3,
    "iso:country":"YE",
    "name:ara_x_preferred":[
        "\u0627\u0644\u062a\u0631\u0628\u0629"
    ],
    "name:eng_x_preferred":[
        "At Turbah"
    ],
    "name:eng_x_variant":[
        "\u0100l R\u0101shid"
    ],
    "qs:name":"At Turbah",
    "qs:photos_9r":0,
    "qs:photos_sr":0,
    "qs:pop_sr":"1",
    "wd:wordcount":73,
    "wof:name":"At Turbah",
    "wof:placetype":"locality",
    "wof:population":3
},
  "geometry": {"coordinates":[43.31375,16.66142],"type":"Point"}
}