{
  "type": "Feature",
  "properties": {
    "gn:country":"YE",
    "gn:fcode":"PPL",
    "gn:population":8,
    "iso:country":"YE",
    "name:ara_x_preferred":[
        "\u0627\u0644\u062f\u0648\u064a\u0631\u064a\u0629"
    ],
    "name:eng_x_preferred":[
        "Ad Diwayriyah"
    ],
    "name:eng_x_variant":[
        "\u1e10aw\u0101\u1e29\u012b al Qaryah"
    ],
    "qs:name":"Ad Diwayr\u012byah",
    "qs:photos_9r":0,
    "qs:photos_sr":0,
    "qs:pop_sr":"1",
    "wof:name":"Ad Diwayr\u012byah",
    "wof:placetype":"locality",
    "wof:population":8
},
  "geometry": {"coordinates":[43.43889,16.19544],"type":"Point"}
}