{
  "type": "Feature",
  "properties": {
    "gn:country":"YE",
    "gn:fcode":"PPL",
    "gn:pop":2,
    "iso:country":"YE",
    "name:ara_x_preferred":[
        "\u0100l Q\u0101sim"
    ],
    "name:ara_x_variant":[
        "\u0627\u0644 \u0642\u0627\u0633\u0645"
    ],
    "name:eng_x_preferred":[
        "Al Qasim"
    ],
    "qs:name":"\u0100l Q\u0101sim",
    "qs:photos_9r":0,
    "qs:photos_sr":0,
    "qs:pop_sr":"1",
    "wof:name":"\u0100l Q\u0101sim",
    "wof:placetype":"locality",
    "wof:population":2
},
  "geometry": {"coordinates":[45.42799,14.96929],"type":"Point"}
}