{
  "type": "Feature",
  "properties": {
    "gn:admin1_code":"23.0",
    "gn:admin2_code":"1105.0",
    "gn:asciiname":"As Sarat",
    "gn:country_code":"YE",
    "gn:dem":2826,
    "gn:feature_class":"P",
    "gn:feature_code":"PPL",
    "gn:name":"As Sar\u0101t",
    "gn:population":0,
    "gn:timezone":"Asia/Aden",
    "iso:country":"YE",
    "name:ara_x_preferred":[
        "As Sir\u0101t"
    ],
    "name:ara_x_variant":[
        "\u0627\u0644\u0633\u0631\u0627\u062a"
    ],
    "name:und_x_variant":[
        "As Sar\u0101t"
    ],
    "wof:name":"As Sarat",
    "wof:placetype":"locality"
},
  "geometry": {"coordinates":[44.33348,14.08462],"type":"Point"}
}