{
  "type": "Feature",
  "properties": {
    "gn:admin1_code":"25.0",
    "gn:admin2_code":"1517.0",
    "gn:asciiname":"Al Kabbah",
    "gn:country_code":"YE",
    "gn:dem":1142,
    "gn:feature_class":"P",
    "gn:feature_code":"PPL",
    "gn:name":"Al Kabbah",
    "gn:population":0,
    "gn:timezone":"Asia/Aden",
    "iso:country":"YE",
    "wof:name":"Al Kabbah",
    "wof:placetype":"locality"
},
  "geometry": {"coordinates":[44.33195,13.27574],"type":"Point"}
}