{
  "type": "Feature",
  "properties": {
    "gn:admin1_code":"14.0",
    "gn:admin2_code":"2607.0",
    "gn:asciiname":"Shi'ab al 'Abd",
    "gn:country_code":"YE",
    "gn:dem":1257,
    "gn:feature_class":"P",
    "gn:feature_code":"PPLL",
    "gn:name":"Shi\u2018\u0101b al \u2018Abd",
    "gn:population":0,
    "gn:timezone":"Asia/Aden",
    "iso:country":"YE",
    "name:ara_x_preferred":[
        "\u0634\u0639\u0627\u0628 \u0627\u0644\u0639\u0628\u062f"
    ],
    "name:und_x_variant":[
        "Shi\u2018\u0101b al \u2018Abd"
    ],
    "wof:name":"Shi'ab al 'Abd",
    "wof:placetype":"locality"
},
  "geometry": {"coordinates":[45.3366,15.09883],"type":"Point"}
}