{
  "type": "Feature",
  "properties": {
    "gn:admin1_code":"11.0",
    "gn:admin2_code":"2007.0",
    "gn:asciiname":"Ad Darah",
    "gn:country_code":"YE",
    "gn:dem":915,
    "gn:feature_class":"P",
    "gn:feature_code":"PPL",
    "gn:name":"Ad D\u0101rah",
    "gn:population":0,
    "gn:timezone":"Asia/Aden",
    "iso:country":"YE",
    "name:und_x_variant":[
        "Ad D\u0101rah"
    ],
    "wof:name":"Ad Darah",
    "wof:placetype":"locality"
},
  "geometry": {"coordinates":[43.68622,14.25974],"type":"Point"}
}