{
  "type": "Feature",
  "properties": {
    "gn:admin1_code":"15.0",
    "gn:admin2_code":"2205.0",
    "gn:asciiname":"Az Zaharah",
    "gn:country_code":"YE",
    "gn:dem":1803,
    "gn:feature_class":"P",
    "gn:feature_code":"PPL",
    "gn:name":"Az\u0327 Z\u0327aharah",
    "gn:population":0,
    "gn:timezone":"Asia/Aden",
    "iso:country":"YE",
    "name:und_x_variant":[
        "Az\u0327 Z\u0327aharah"
    ],
    "wof:name":"Az Zaharah",
    "wof:placetype":"locality"
},
  "geometry": {"coordinates":[43.21661,16.99391],"type":"Point"}
}