{
  "type": "Feature",
  "properties": {
    "gn:admin1_code":"14.0",
    "gn:asciiname":"Aba al Jabir",
    "gn:country_code":"YE",
    "gn:dem":1648,
    "gn:feature_class":"P",
    "gn:feature_code":"PPL",
    "gn:name":"Ab\u0101 al J\u0101bir",
    "gn:population":0,
    "gn:timezone":"Asia/Aden",
    "iso:country":"YE",
    "name:ara_x_preferred":[
        "\u0623\u0628\u0627 \u0627\u0644\u062c\u0627\u0628\u0631"
    ],
    "name:und_x_variant":[
        "Ab\u0101 al J\u0101bir"
    ],
    "wof:name":"Aba al Jabir",
    "wof:placetype":"locality"
},
  "geometry": {"coordinates":[44.80295,16.49768],"type":"Point"}
}