{
  "type": "Feature",
  "properties": {
    "gn:admin1_code":"22.0",
    "gn:admin2_code":"1716.0",
    "gn:asciiname":"Bayt al `Arudi",
    "gn:country_code":"YE",
    "gn:dem":1959,
    "gn:feature_class":"P",
    "gn:feature_code":"PPL",
    "gn:name":"Bayt al \u2018Ar\u016b\u1e11\u012b",
    "gn:population":0,
    "gn:timezone":"Asia/Aden",
    "iso:country":"YE",
    "name:und_x_variant":[
        "Bayt al \u2018Ar\u016b\u1e11\u012b"
    ],
    "wof:name":"Bayt al `Arudi",
    "wof:placetype":"locality"
},
  "geometry": {"coordinates":[43.4598,15.96325],"type":"Point"}
}