{
  "type": "Feature",
  "properties": {
    "gn:country":"YE",
    "gn:fcode":"PPL",
    "gn:pop":6,
    "iso:country":"YE",
    "name:ara_x_preferred":[
        "\u0627\u0644\u0645\u0633\u0644\u0645"
    ],
    "qs:name":"Al Maslam",
    "qs:photos_9r":0,
    "qs:photos_sr":0,
    "qs:pop_sr":"1",
    "wof:name":"Al Maslam",
    "wof:placetype":"locality",
    "wof:population":6
},
  "geometry": {"coordinates":[43.33002,16.20194],"type":"Point"}
}