{
  "type": "Feature",
  "properties": {
    "gn:country":"YE",
    "gn:fcode":"PPL",
    "gn:pop":7,
    "iso:country":"YE",
    "name:ara_x_preferred":[
        "\u0643\u0648\u0644\u0629 \u0628\u0646 \u062c\u0627\u0628\u0631"
    ],
    "name:eng_x_preferred":[
        "Kawlat Bin Jabir"
    ],
    "name:eng_x_variant":[
        "\u0100l ad Dawlah"
    ],
    "qs:name":"Kawlat Bin J\u0101bir",
    "qs:photos_9r":0,
    "qs:photos_sr":0,
    "qs:pop_sr":"1",
    "wof:name":"Kawlat Bin J\u0101bir",
    "wof:placetype":"locality",
    "wof:population":7
},
  "geometry": {"coordinates":[43.41782,16.0519],"type":"Point"}
}