{
  "type": "Feature",
  "properties": {
    "gn:country":"YE",
    "gn:fcode":"PPL",
    "gn:pop":14,
    "iso:country":"YE",
    "name:ara_x_preferred":[
        "\u0627\u0644\u062f\u0631\u064a\u0634"
    ],
    "name:eng_x_preferred":[
        "Ad Duraysh"
    ],
    "name:eng_x_variant":[
        "Gh\u0101rib al Mijr\u0101b"
    ],
    "name:unk_x_variant":[
        "\u0627\u0644\u062f\u0631\u064a\u0634"
    ],
    "qs:name":"Ad Duraysh",
    "qs:photos_9r":0,
    "qs:photos_sr":0,
    "qs:pop_sr":"1",
    "wof:name":"Ad Duraysh",
    "wof:placetype":"locality",
    "wof:population":14
},
  "geometry": {"coordinates":[43.00043,16.38728],"type":"Point"}
}