{
  "type": "Feature",
  "properties": {
    "gn:admin1_code":"16.0",
    "gn:admin2_code":"2304.0",
    "gn:asciiname":"Bayt al Malahi",
    "gn:country_code":"YE",
    "gn:dem":2331,
    "gn:feature_class":"P",
    "gn:feature_code":"PPL",
    "gn:name":"Bayt al Mal\u0101\u1e29\u012b",
    "gn:population":0,
    "gn:timezone":"Asia/Aden",
    "iso:country":"YE",
    "name:und_x_variant":[
        "Bayt al Mal\u0101\u1e29\u012b"
    ],
    "wof:name":"Bayt al Malahi",
    "wof:placetype":"locality"
},
  "geometry": {"coordinates":[44.45396,15.49154],"type":"Point"}
}