{
  "type": "Feature",
  "properties": {
    "gn:country":"YE",
    "gn:fcode":"PPL",
    "gn:pop":6,
    "iso:country":"YE",
    "name:ara_x_preferred":[
        "\u0627\u0644\u062b\u0631\u0628\u0629"
    ],
    "name:eng_x_preferred":[
        "Ath Tharibah"
    ],
    "name:eng_x_variant":[
        "Qar\u00e1 Zayd"
    ],
    "qs:name":"Ath Tharibah",
    "qs:photos_9r":0,
    "qs:photos_sr":0,
    "qs:pop_sr":"1",
    "wof:name":"Ath Tharibah",
    "wof:placetype":"locality",
    "wof:population":6
},
  "geometry": {"coordinates":[43.27668,17.08346],"type":"Point"}
}