{
  "type": "Feature",
  "properties": {
    "gn:country":"YE",
    "gn:fcode":"PPL",
    "gn:population":8,
    "iso:country":"YE",
    "name:ara_x_preferred":[
        "\u0627\u0644\u062e\u062f\u0631\u0627\u0621"
    ],
    "qs:name":"Al Khadr\u0101\u2019",
    "qs:photos_9r":0,
    "qs:photos_sr":0,
    "qs:pop_sr":"1",
    "wof:name":"Al Khadr\u0101\u2019",
    "wof:placetype":"locality",
    "wof:population":8
},
  "geometry": {"coordinates":[43.3891,16.40235],"type":"Point"}
}