{
  "type": "Feature",
  "properties": {
    "gn:admin1_code":"20.0",
    "gn:admin2_code":"1416.0",
    "gn:asciiname":"As Surm",
    "gn:country_code":"YE",
    "gn:dem":2145,
    "gn:feature_class":"P",
    "gn:feature_code":"PPL",
    "gn:name":"A\u015f \u015eurm",
    "gn:population":0,
    "gn:timezone":"Asia/Aden",
    "iso:country":"YE",
    "name:ara_x_preferred":[
        "A\u015f \u015eurm"
    ],
    "wof:name":"As Surm",
    "wof:placetype":"locality"
},
  "geometry": {"coordinates":[44.82865,14.3839],"type":"Point"}
}