{
  "type": "Feature",
  "properties": {
    "gn:country":"YE",
    "gn:fcode":"PPL",
    "gn:pop":3,
    "iso:country":"YE",
    "name:ara_x_preferred":[
        "\u0627\u0644\u0631\u0627\u062a\u0628\u064a\u0629"
    ],
    "name:eng_x_preferred":[
        "Ar Ratibiyah"
    ],
    "qs:name":"Ar R\u0101tib\u012byah",
    "qs:photos_9r":0,
    "qs:photos_sr":0,
    "qs:pop_sr":"1",
    "wof:name":"Ar R\u0101tib\u012byah",
    "wof:placetype":"locality",
    "wof:population":3
},
  "geometry": {"coordinates":[44.34044,17.0381],"type":"Point"}
}