{
  "type": "Feature",
  "properties": {
    "gn:admin1_code":"14.0",
    "gn:admin2_code":"2602.0",
    "gn:asciiname":"Asdas",
    "gn:country_code":"YE",
    "gn:dem":1102,
    "gn:feature_class":"P",
    "gn:feature_code":"PPLA2",
    "gn:name":"Asd\u0101s",
    "gn:population":0,
    "gn:timezone":"Asia/Aden",
    "iso:country":"YE",
    "name:ara_x_preferred":[
        "Asd\u0101s"
    ],
    "name:ara_x_variant":[
        "\u0623\u0633\u062f\u0627\u0633"
    ],
    "name:fas_x_preferred":[
        "\u0627\u0633\u062f\u0627\u0633"
    ],
    "name:nno_x_preferred":[
        "Asdas"
    ],
    "wof:name":"Asdas",
    "wof:placetype":"locality"
},
  "geometry": {"coordinates":[45.08151,15.76601],"type":"Point"}
}