{
  "type": "Feature",
  "properties": {
    "gn:country":"YE",
    "gn:fcode":"TRB",
    "gn:pop":18,
    "iso:country":"YE",
    "name:ara_x_preferred":[
        "\u0628\u062f\u0648 \u0645\u0633\u0648\u062f\u0629"
    ],
    "qs:name":"Badw Mas\u016bdah",
    "qs:photos_9r":0,
    "qs:photos_sr":0,
    "qs:pop_sr":"1",
    "wof:name":"Badw Mas\u016bdah",
    "wof:placetype":"locality",
    "wof:population":18
},
  "geometry": {"coordinates":[43.7651,17.26024],"type":"Point"}
}