{
  "type": "Feature",
  "properties": {
    "gn:admin1_code":"15.0",
    "gn:admin2_code":"2211.0",
    "gn:asciiname":"As Surar",
    "gn:country_code":"YE",
    "gn:dem":1867,
    "gn:feature_class":"P",
    "gn:feature_code":"PPL",
    "gn:name":"As Sur\u0101r",
    "gn:population":0,
    "gn:timezone":"Asia/Aden",
    "iso:country":"YE",
    "name:ara_x_preferred":[
        "As Sur\u0101r"
    ],
    "wof:name":"As Surar",
    "wof:placetype":"locality"
},
  "geometry": {"coordinates":[43.74626,17.00606],"type":"Point"}
}