{
  "type": "Feature",
  "properties": {
    "gn:admin1_code":"22.0",
    "gn:admin2_code":"1724.0",
    "gn:asciiname":"Al Qub`iyah",
    "gn:country_code":"YE",
    "gn:dem":251,
    "gn:feature_class":"P",
    "gn:feature_code":"PPL",
    "gn:name":"Al Qub\u2018\u012byah",
    "gn:population":0,
    "gn:timezone":"Asia/Aden",
    "iso:country":"YE",
    "name:und_x_variant":[
        "Al Qub\u2018\u012byah"
    ],
    "wof:name":"Al Qub`iyah",
    "wof:placetype":"locality"
},
  "geometry": {"coordinates":[43.26706,15.55905],"type":"Point"}
}