{
  "type": "Feature",
  "properties": {
    "gn:admin1_code":"8.0",
    "gn:admin2_code":"1802.0",
    "gn:asciiname":"Khamir",
    "gn:country_code":"YE",
    "gn:dem":62,
    "gn:feature_class":"P",
    "gn:feature_code":"PPL",
    "gn:name":"Khamir",
    "gn:population":0,
    "gn:timezone":"Asia/Aden",
    "iso:country":"YE",
    "name:ceb_x_preferred":[
        "Khamir"
    ],
    "name:swe_x_preferred":[
        "Khamir"
    ],
    "wof:name":"Khamir",
    "wof:placetype":"locality"
},
  "geometry": {"coordinates":[42.96572000000001,15.63066],"type":"Point"}
}