{
  "type": "Feature",
  "properties": {
    "gn:admin1_code":"22.0",
    "gn:admin2_code":"1725.0",
    "gn:asciiname":"Nuha al Barmikah",
    "gn:country_code":"YE",
    "gn:dem":713,
    "gn:feature_class":"P",
    "gn:feature_code":"PPL",
    "gn:name":"Nuh\u0101 al Barmikah",
    "gn:population":0,
    "gn:timezone":"Asia/Aden",
    "iso:country":"YE",
    "name:ara_x_preferred":[
        "\u0646\u0647\u0627 \u0627\u0644\u0628\u0631\u0645\u0643\u0629"
    ],
    "name:und_x_variant":[
        "Nuh\u0101 al Barmikah"
    ],
    "wof:name":"Nuha al Barmikah",
    "wof:placetype":"locality"
},
  "geometry": {"coordinates":[43.52915,15.56827],"type":"Point"}
}