{
  "type": "Feature",
  "properties": {
    "gn:admin1_code":"11.0",
    "gn:admin2_code":"2007.0",
    "gn:asciiname":"Al Ahad",
    "gn:country_code":"YE",
    "gn:dem":1240,
    "gn:feature_class":"P",
    "gn:feature_code":"PPLA2",
    "gn:name":"Al A\u1e29ad",
    "gn:population":0,
    "gn:timezone":"Asia/Aden",
    "iso:country":"YE",
    "name:ara_x_preferred":[
        "\u0627\u0644\u0623\u062d\u062f"
    ],
    "name:und_x_variant":[
        "Al A\u1e29ad"
    ],
    "wof:name":"Al Ahad",
    "wof:placetype":"locality"
},
  "geometry": {"coordinates":[43.64167,14.25833],"type":"Point"}
}