{
  "type": "Feature",
  "properties": {
    "gn:admin1_code":"22.0",
    "gn:admin2_code":"1730.0",
    "gn:asciiname":"Al Mawdinah",
    "gn:country_code":"YE",
    "gn:dem":690,
    "gn:feature_class":"P",
    "gn:feature_code":"PPL",
    "gn:name":"Al Mawdinah",
    "gn:population":2,
    "gn:timezone":"Asia/Aden",
    "iso:country":"YE",
    "name:ara_x_preferred":[
        "\u0627\u0644\u0645\u0648\u062f\u0646\u0629"
    ],
    "wof:name":"Al Mawdinah",
    "wof:placetype":"locality",
    "wof:population":2
},
  "geometry": {"coordinates":[43.37576,16.35148],"type":"Point"}
}