{
  "type": "Feature",
  "properties": {
    "gn:admin1_code":"4.0",
    "gn:admin2_code":"1925.0",
    "gn:asciiname":"Sharj Bin Talib",
    "gn:country_code":"YE",
    "gn:dem":7,
    "gn:feature_class":"P",
    "gn:feature_code":"PPL",
    "gn:name":"Sharj Bin \u0162\u0101lib",
    "gn:population":0,
    "gn:timezone":"Asia/Aden",
    "iso:country":"YE",
    "name:und_x_variant":[
        "Sharj Bin \u0162\u0101lib"
    ],
    "wof:name":"Sharj Bin Talib",
    "wof:placetype":"locality"
},
  "geometry": {"coordinates":[48.68333,14.08333],"type":"Point"}
}