{
  "type": "Feature",
  "properties": {
    "gn:country":"YE",
    "gn:fcode":"PPLX",
    "gn:population":8,
    "iso:country":"YE",
    "name:ara_x_preferred":[
        "\u0634\u0639\u0628 \u062d\u0627\u062c\u0628"
    ],
    "qs:name":"Sha\u2018b \u1e28\u0101jib",
    "qs:photos_9r":0,
    "qs:photos_sr":0,
    "qs:pop_sr":"1",
    "wof:name":"Sha\u2018b \u1e28\u0101jib",
    "wof:placetype":"neighbourhood",
    "wof:population":8
},
  "geometry": {"coordinates":[43.71067,16.17351],"type":"Point"}
}