{
  "type": "Feature",
  "properties": {
    "gn:country":"YE",
    "gn:fcode":"PPL",
    "gn:pop":3,
    "iso:country":"YE",
    "name:ara_x_preferred":[
        "\u0623\u0648\u0634\u0639 \u0627\u0644\u0633\u0644\u0645"
    ],
    "name:eng_x_preferred":[
        "Awsha' As Salim"
    ],
    "name:eng_x_variant":[
        "Mawf al Mayd\u0101n"
    ],
    "qs:name":"Awsha\u2018 as Salim",
    "qs:photos_9r":0,
    "qs:photos_sr":0,
    "qs:pop_sr":"1",
    "wof:name":"Awsha\u2018 as Salim",
    "wof:placetype":"locality",
    "wof:population":3
},
  "geometry": {"coordinates":[45.19981,14.8674],"type":"Point"}
}