{
  "type": "Feature",
  "properties": {
    "gn:admin1_code":"23.0",
    "gn:admin2_code":"1106.0",
    "gn:asciiname":"Al Aghbari",
    "gn:country_code":"YE",
    "gn:dem":2365,
    "gn:feature_class":"P",
    "gn:feature_code":"PPL",
    "gn:name":"Al Aghbar\u012b",
    "gn:population":0,
    "gn:timezone":"Asia/Aden",
    "iso:country":"YE",
    "name:ara_x_preferred":[
        "\u0627\u0644\u0623\u063a\u0628\u0631\u064a"
    ],
    "name:und_x_variant":[
        "Al Aghbar\u012b"
    ],
    "wof:name":"Al Aghbari",
    "wof:placetype":"locality"
},
  "geometry": {"coordinates":[44.42748,14.10919],"type":"Point"}
}