{
  "type": "Feature",
  "properties": {
    "gn:country":"YE",
    "gn:fcode":"PPL",
    "gn:pop":15,
    "iso:country":"YE",
    "name:ara_x_preferred":[
        "\u0630\u0648 \u0647\u0630\u064a\u0644"
    ],
    "name:eng_x_preferred":[
        "DhU Hudhayl"
    ],
    "name:eng_x_variant":[
        "Ar Rawgh"
    ],
    "qs:name":"Dh\u016b Hudhayl",
    "qs:photos_9r":0,
    "qs:photos_sr":0,
    "qs:pop_sr":"1",
    "wof:name":"Dh\u016b Hudhayl",
    "wof:placetype":"locality",
    "wof:population":15
},
  "geometry": {"coordinates":[43.8108,16.78301],"type":"Point"}
}