{
  "type": "Feature",
  "properties": {
    "gn:admin1_code":"11.0",
    "gn:admin2_code":"2011.0",
    "gn:asciiname":"Qaryat al Ghuwarah",
    "gn:country_code":"YE",
    "gn:dem":2474,
    "gn:feature_class":"P",
    "gn:feature_code":"PPL",
    "gn:name":"Qaryat al Ghuw\u0101rah",
    "gn:population":0,
    "gn:timezone":"Asia/Aden",
    "iso:country":"YE",
    "name:und_x_variant":[
        "Qaryat al Ghuw\u0101rah"
    ],
    "wof:name":"Qaryat al Ghuwarah",
    "wof:placetype":"locality"
},
  "geometry": {"coordinates":[44.18751,14.96121],"type":"Point"}
}