{
  "type": "Feature",
  "properties": {
    "gn:admin1_code":"20.0",
    "gn:admin2_code":"1407.0",
    "gn:asciiname":"Al Hadidah",
    "gn:country_code":"YE",
    "gn:dem":1574,
    "gn:feature_class":"P",
    "gn:feature_code":"PPL",
    "gn:name":"Al \u1e28ad\u012bdah",
    "gn:population":0,
    "gn:timezone":"Asia/Aden",
    "iso:country":"YE",
    "name:und_x_variant":[
        "Al \u1e28ad\u012bdah"
    ],
    "wof:name":"Al Hadidah",
    "wof:placetype":"locality"
},
  "geometry": {"coordinates":[45.28143,14.05142],"type":"Point"}
}