{
  "type": "Feature",
  "properties": {
    "gn:country":"YE",
    "gn:fcode":"PPL",
    "gn:pop":25,
    "iso:country":"YE",
    "name:unk_x_variant":[
        "\u0627\u0644\u0634\u0639\u0628\u0629"
    ],
    "qs:name":"Ash Sha\u2018bah",
    "qs:photos_9r":0,
    "qs:photos_sr":0,
    "qs:pop_sr":"1",
    "wd:wordcount":24,
    "wof:name":"Ash Sha\u2018bah",
    "wof:placetype":"locality",
    "wof:population":25
},
  "geometry": {"coordinates":[42.99188,16.26406],"type":"Point"}
}