{
  "type": "Feature",
  "properties": {
    "gn:admin1_code":"8.0",
    "gn:admin2_code":"1810.0",
    "gn:asciiname":"Al Khubaytiyah",
    "gn:country_code":"YE",
    "gn:dem":75,
    "gn:feature_class":"P",
    "gn:feature_code":"PPL",
    "gn:name":"Al Khubayt\u012byah",
    "gn:population":0,
    "gn:timezone":"Asia/Aden",
    "iso:country":"YE",
    "name:und_x_variant":[
        "Al Khubayt\u012byah"
    ],
    "wof:name":"Al Khubaytiyah",
    "wof:placetype":"locality"
},
  "geometry": {"coordinates":[43.07868,15.05709],"type":"Point"}
}