{
  "type": "Feature",
  "properties": {
    "gn:country":"YE",
    "gn:fcode":"PPL",
    "gn:population":2,
    "iso:country":"YE",
    "name:ara_x_preferred":[
        "\u0645\u0639\u0645\u0631 \u0627\u0644 \u0645\u0647\u062f\u064a"
    ],
    "name:eng_x_preferred":[
        "Mu'ammar Al Mahdi"
    ],
    "name:eng_x_variant":[
        "Al Hudaysh\u012byah"
    ],
    "qs:name":"Mu\u2018ammar \u0100l Mahd\u012b",
    "qs:photos_9r":0,
    "qs:photos_sr":0,
    "qs:pop_sr":"1",
    "wof:name":"Mu\u2018ammar \u0100l Mahd\u012b",
    "wof:placetype":"locality",
    "wof:population":2
},
  "geometry": {"coordinates":[44.32496,17.02664],"type":"Point"}
}