{
  "type": "Feature",
  "properties": {
    "gn:admin1_code":"22.0",
    "gn:admin2_code":"1725.0",
    "gn:asciiname":"Dawas",
    "gn:country_code":"YE",
    "gn:dem":1087,
    "gn:feature_class":"P",
    "gn:feature_code":"PPL",
    "gn:name":"Daw\u0101s",
    "gn:population":0,
    "gn:timezone":"Asia/Aden",
    "iso:country":"YE",
    "name:und_x_variant":[
        "Daw\u0101s"
    ],
    "wof:name":"Dawas",
    "wof:placetype":"locality"
},
  "geometry": {"coordinates":[43.51667,15.63333],"type":"Point"}
}