{
  "type": "Feature",
  "properties": {
    "gn:admin1_code":"10.0",
    "gn:admin2_code":"2704.0",
    "gn:asciiname":"Qufash",
    "gn:country_code":"YE",
    "gn:dem":444,
    "gn:feature_class":"P",
    "gn:feature_code":"PPL",
    "gn:name":"Q\u016bfash",
    "gn:population":0,
    "gn:timezone":"Asia/Aden",
    "iso:country":"YE",
    "name:und_x_variant":[
        "Q\u016bfash"
    ],
    "wof:name":"Qufash",
    "wof:placetype":"locality"
},
  "geometry": {"coordinates":[43.34323,15.49532],"type":"Point"}
}