{
  "type": "Feature",
  "properties": {
    "gn:country":"YE",
    "gn:fcode":"PPL",
    "gn:population":25,
    "iso:country":"YE",
    "name:ara_x_preferred":[
        "\u063a\u0627\u0631\u0628 \u0628\u062c\u064a\u062f\u0629"
    ],
    "name:eng_x_preferred":[
        "Gharib Buhaydah"
    ],
    "name:eng_x_variant":[
        "A\u015f \u015e\u0101gh\u012b"
    ],
    "qs:name":"Gh\u0101rib Bu\u1e29aydah",
    "qs:photos_9r":0,
    "qs:photos_sr":0,
    "qs:pop_sr":"1",
    "wof:name":"Gh\u0101rib Bu\u1e29aydah",
    "wof:placetype":"locality",
    "wof:population":25
},
  "geometry": {"coordinates":[43.45542,16.195],"type":"Point"}
}