{
  "type": "Feature",
  "properties": {
    "gn:admin1_code":"23.0",
    "gn:admin2_code":"1111.0",
    "gn:asciiname":"Al Jazi`ah",
    "gn:country_code":"YE",
    "gn:dem":1946,
    "gn:feature_class":"P",
    "gn:feature_code":"PPL",
    "gn:name":"Al J\u0101zi\u2018ah",
    "gn:population":0,
    "gn:timezone":"Asia/Aden",
    "iso:country":"YE",
    "name:und_x_variant":[
        "Al J\u0101zi\u2018ah"
    ],
    "wof:name":"Al Jazi`ah",
    "wof:placetype":"locality"
},
  "geometry": {"coordinates":[43.89581,13.89524],"type":"Point"}
}