{
  "type": "Feature",
  "properties": {
    "gn:country":"YE",
    "gn:fcode":"PPL",
    "gn:population":12,
    "iso:country":"YE",
    "name:ara_x_preferred":[
        "\u0627\u0644\u0635\u062f\u0631\u0629"
    ],
    "qs:name":"A\u015f \u015eudrah",
    "qs:photos_9r":0,
    "qs:photos_sr":0,
    "qs:pop_sr":"1",
    "wof:name":"A\u015f \u015eudrah",
    "wof:placetype":"locality",
    "wof:population":12
},
  "geometry": {"coordinates":[44.21275,16.90788],"type":"Point"}
}