{
  "type": "Feature",
  "properties": {
    "gn:admin1_code":"15.0",
    "gn:admin2_code":"2207.0",
    "gn:asciiname":"Adh Dhira'",
    "gn:country_code":"YE",
    "gn:dem":768,
    "gn:feature_class":"P",
    "gn:feature_code":"PPL",
    "gn:name":"Adh Dhir\u0101\u2018",
    "gn:population":3,
    "gn:timezone":"Asia/Aden",
    "iso:country":"YE",
    "name:ara_x_preferred":[
        "Adh Dhir\u0101\u2018"
    ],
    "name:ara_x_variant":[
        "\u0627\u0644\u0630\u0631\u0627\u0639"
    ],
    "wof:name":"Adh Dhira'",
    "wof:placetype":"locality",
    "wof:population":3
},
  "geometry": {"coordinates":[43.29747,16.67281],"type":"Point"}
}