{
  "type": "Feature",
  "properties": {
    "gn:admin1_code":"20.0",
    "gn:admin2_code":"1404.0",
    "gn:asciiname":"Al Dahmah",
    "gn:country_code":"YE",
    "gn:dem":2056,
    "gn:feature_class":"P",
    "gn:feature_code":"PPL",
    "gn:name":"\u0100l Dahmah",
    "gn:population":0,
    "gn:timezone":"Asia/Aden",
    "iso:country":"YE",
    "name:ara_x_preferred":[
        "\u0627\u0644 \u062f\u0647\u0645\u0629"
    ],
    "name:und_x_variant":[
        "\u0100l Dahmah"
    ],
    "wof:name":"Al Dahmah",
    "wof:placetype":"locality"
},
  "geometry": {"coordinates":[45.77824,14.08782],"type":"Point"}
}