{
  "type": "Feature",
  "properties": {
    "gn:admin1_code":"8.0",
    "gn:admin2_code":"1801.0",
    "gn:asciiname":"Ad Duman",
    "gn:country_code":"YE",
    "gn:dem":189,
    "gn:feature_class":"P",
    "gn:feature_code":"PPL",
    "gn:name":"Ad Duman",
    "gn:population":0,
    "gn:timezone":"Asia/Aden",
    "iso:country":"YE",
    "wof:name":"Ad Duman",
    "wof:placetype":"locality"
},
  "geometry": {"coordinates":[43.21636,15.8679],"type":"Point"}
}