{
  "type": "Feature",
  "properties": {
    "gn:admin1_code":"20.0",
    "gn:admin2_code":"1405.0",
    "gn:asciiname":"Jahur",
    "gn:country_code":"YE",
    "gn:dem":2045,
    "gn:feature_class":"P",
    "gn:feature_code":"PPL",
    "gn:name":"J\u0101\u1e29\u016br",
    "gn:population":0,
    "gn:timezone":"Asia/Aden",
    "iso:country":"YE",
    "name:ara_x_preferred":[
        "J\u0101\u1e29\u016br"
    ],
    "wof:name":"Jahur",
    "wof:placetype":"locality"
},
  "geometry": {"coordinates":[45.40066,14.00461],"type":"Point"}
}