{
  "type": "Feature",
  "properties": {
    "gn:country":"YE",
    "gn:fcode":"PPL",
    "gn:population":6,
    "iso:country":"YE",
    "name:ara_x_preferred":[
        "\u0642\u064a\u0645\u0629 \u0627\u0644\u062c\u0641\u0645\u064a"
    ],
    "name:eng_x_preferred":[
        "Qimat Al Jafami"
    ],
    "name:eng_x_variant":[
        "\u0100l al \u2018Aw\u0101d\u012b"
    ],
    "qs:name":"Q\u012bmat al Jafam\u012b",
    "qs:photos_9r":0,
    "qs:photos_sr":0,
    "qs:pop_sr":"1",
    "wof:name":"Q\u012bmat al Jafam\u012b",
    "wof:placetype":"locality",
    "wof:population":6
},
  "geometry": {"coordinates":[43.38115,16.32484],"type":"Point"}
}