{
  "type": "Feature",
  "properties": {
    "gn:country":"YE",
    "gn:fcode":"PPL",
    "gn:population":2,
    "iso:country":"YE",
    "name:ara_x_preferred":[
        "\u062d\u0628\u064a\u0644 \u0627\u0644\u0631\u0648\u064a\u0633"
    ],
    "name:eng_x_preferred":[
        "Habil Ar Ruways"
    ],
    "name:eng_x_variant":[
        "\u1e28ar\u012bs"
    ],
    "qs:name":"\u1e28ab\u012bl ar Ruways",
    "qs:photos_9r":0,
    "qs:photos_sr":0,
    "qs:pop_sr":"1",
    "wof:name":"\u1e28ab\u012bl ar Ruways",
    "wof:placetype":"locality",
    "wof:population":2
},
  "geometry": {"coordinates":[43.27222,17.08881],"type":"Point"}
}