{
  "type": "Feature",
  "properties": {
    "gn:country":"YE",
    "gn:fcode":"PPL",
    "gn:population":8,
    "iso:country":"YE",
    "name:ara_x_preferred":[
        "Ath Thuw\u0101\u2018"
    ],
    "name:ara_x_variant":[
        "\u0627\u0644\u062b\u0648\u0627\u0639"
    ],
    "name:eng_x_preferred":[
        "Ath Thuwa'"
    ],
    "name:eng_x_variant":[
        "Al \u1e28i\u0163\u0101wir"
    ],
    "qs:name":"Ath Thuw\u0101\u2018",
    "qs:photos_9r":0,
    "qs:photos_sr":0,
    "qs:pop_sr":"1",
    "wof:name":"Ath Thuw\u0101\u2018",
    "wof:placetype":"locality",
    "wof:population":8
},
  "geometry": {"coordinates":[43.21474,17.17102],"type":"Point"}
}