{
  "type": "Feature",
  "properties": {
    "gn:country":"YE",
    "gn:fcode":"PPL",
    "gn:pop":2,
    "iso:country":"YE",
    "name:ara_x_preferred":[
        "Al L\u0101l"
    ],
    "name:ara_x_variant":[
        "\u0627\u0644\u0644\u0627\u0644"
    ],
    "name:eng_x_preferred":[
        "Al Lal"
    ],
    "name:eng_x_variant":[
        "Ash Sharw"
    ],
    "qs:name":"Al L\u0101l",
    "qs:photos_9r":0,
    "qs:photos_sr":0,
    "qs:pop_sr":"1",
    "wof:name":"Al L\u0101l",
    "wof:placetype":"locality",
    "wof:population":2
},
  "geometry": {"coordinates":[45.03028,14.99005],"type":"Point"}
}