{
  "type": "Feature",
  "properties": {
    "gn:admin1_code":"16.0",
    "gn:admin2_code":"2304.0",
    "gn:asciiname":"Saraf",
    "gn:country_code":"YE",
    "gn:dem":2279,
    "gn:feature_class":"P",
    "gn:feature_code":"PPL",
    "gn:name":"\u015earaf",
    "gn:population":0,
    "gn:timezone":"Asia/Aden",
    "iso:country":"YE",
    "name:ara_x_preferred":[
        "\u0635\u0631\u0641"
    ],
    "name:und_x_variant":[
        "\u015earf",
        "\u015earaf"
    ],
    "wof:name":"Saraf",
    "wof:placetype":"locality"
},
  "geometry": {"coordinates":[44.26929000000001,15.42876],"type":"Point"}
}