{
  "type": "Feature",
  "properties": {
    "gn:country":"YE",
    "gn:fcode":"PPL",
    "gn:pop":8,
    "iso:country":"YE",
    "name:ara_x_preferred":[
        "\u0645\u0644\u062d\u0627\u0646"
    ],
    "qs:name":"Mal\u1e29\u0101n",
    "qs:photos_9r":0,
    "qs:photos_sr":0,
    "qs:pop_sr":"1",
    "wof:name":"Mal\u1e29\u0101n",
    "wof:placetype":"locality",
    "wof:population":8
},
  "geometry": {"coordinates":[43.72472,16.07522],"type":"Point"}
}