{
  "type": "Feature",
  "properties": {
    "gn:admin1_code":"4.0",
    "gn:admin2_code":"1908.0",
    "gn:asciiname":"Hawtat as Sadah",
    "gn:cc2":"YE",
    "gn:country_code":"YE",
    "gn:dem":680,
    "gn:feature_class":"P",
    "gn:feature_code":"PPL",
    "gn:name":"\u1e28aw\u0163at as S\u0101dah",
    "gn:population":0,
    "gn:timezone":"Asia/Aden",
    "iso:country":"YE",
    "name:nno_x_preferred":[
        "Hawtat As Sadah"
    ],
    "name:und_x_variant":[
        "Hautat al-S\u0101dah",
        "\u1e28aw\u0163at as S\u0101dah"
    ],
    "wof:name":"Hawtat as Sadah",
    "wof:placetype":"locality"
},
  "geometry": {"coordinates":[48.67,15.90333],"type":"Point"}
}