{
  "type": "Feature",
  "properties": {
    "gn:admin1_code":"11.0",
    "gn:admin2_code":"2010.0",
    "gn:asciiname":"Al Jubbah",
    "gn:country_code":"YE",
    "gn:dem":2283,
    "gn:feature_class":"P",
    "gn:feature_code":"PPL",
    "gn:name":"Al Jubbah",
    "gn:population":0,
    "gn:timezone":"Asia/Aden",
    "iso:country":"YE",
    "wof:name":"Al Jubbah",
    "wof:placetype":"locality"
},
  "geometry": {"coordinates":[44.26445,14.53417],"type":"Point"}
}