{
  "type": "Feature",
  "properties": {
    "gn:admin1_code":"24.0",
    "gn:admin2_code":"2511.0",
    "gn:asciiname":"Am Daymah",
    "gn:country_code":"YE",
    "gn:dem":595,
    "gn:feature_class":"P",
    "gn:feature_code":"PPL",
    "gn:name":"Am Daymah",
    "gn:population":0,
    "gn:timezone":"Asia/Aden",
    "iso:country":"YE",
    "wof:name":"Am Daymah",
    "wof:placetype":"locality"
},
  "geometry": {"coordinates":[44.32573,13.16419],"type":"Point"}
}