{
  "type": "Feature",
  "properties": {
    "gn:country":"YE",
    "gn:fcode":"PPL",
    "gn:pop":2,
    "iso:country":"YE",
    "name:ara_x_preferred":[
        "\u0642\u0635\u0628\u0629 \u0627\u0644\u0639\u062f\u0627\u0626\u0646"
    ],
    "name:eng_x_preferred":[
        "Qasabat Al 'Adain"
    ],
    "name:eng_x_variant":[
        "Al Qaz\u2018\u00e1"
    ],
    "qs:name":"Qa\u015fabat al \u2018Ad\u0101\u2019in",
    "qs:photos_9r":0,
    "qs:photos_sr":0,
    "qs:pop_sr":"1",
    "wof:name":"Qa\u015fabat al \u2018Ad\u0101\u2019in",
    "wof:placetype":"locality",
    "wof:population":2
},
  "geometry": {"coordinates":[43.621,16.00489],"type":"Point"}
}