{
  "type": "Feature",
  "properties": {
    "gn:admin1_code":"15.0",
    "gn:admin2_code":"2203.0",
    "gn:asciiname":"Al Mabda'",
    "gn:country_code":"YE",
    "gn:dem":1849,
    "gn:feature_class":"P",
    "gn:feature_code":"PPL",
    "gn:name":"Al Mabd\u0101\u2019",
    "gn:population":0,
    "gn:timezone":"Asia/Aden",
    "iso:country":"YE",
    "name:ara_x_preferred":[
        "\u0627\u0644\u0645\u0628\u062f\u0627\u0621"
    ],
    "name:und_x_variant":[
        "Al Mabd\u0101\u2019"
    ],
    "wof:name":"Al Mabda'",
    "wof:placetype":"locality"
},
  "geometry": {"coordinates":[43.28178,17.21826],"type":"Point"}
}