{
  "type": "Feature",
  "properties": {
    "gn:admin1_code":"22.0",
    "gn:admin2_code":"1704.0",
    "gn:asciiname":"Hiwwal",
    "gn:country_code":"YE",
    "gn:dem":133,
    "gn:feature_class":"P",
    "gn:feature_code":"PPL",
    "gn:name":"\u1e28iwwal",
    "gn:population":0,
    "gn:timezone":"Asia/Aden",
    "iso:country":"YE",
    "name:und_x_variant":[
        "\u1e28iwwal"
    ],
    "wof:name":"Hiwwal",
    "wof:placetype":"locality"
},
  "geometry": {"coordinates":[43.10135,15.91629],"type":"Point"}
}