{
  "type": "Feature",
  "properties": {
    "gn:admin1_code":"16.0",
    "gn:admin2_code":"2312.0",
    "gn:asciiname":"Al Madid",
    "gn:country_code":"YE",
    "gn:dem":2119,
    "gn:feature_class":"P",
    "gn:feature_code":"PPL",
    "gn:name":"Al Mad\u012bd",
    "gn:population":0,
    "gn:timezone":"Asia/Aden",
    "iso:country":"YE",
    "name:ara_x_preferred":[
        "\u0627\u0644\u0645\u062f\u064a\u062f"
    ],
    "name:und_x_variant":[
        "Al Mad\u012bd"
    ],
    "wof:name":"Al Madid",
    "wof:placetype":"locality"
},
  "geometry": {"coordinates":[44.73344,15.28814],"type":"Point"}
}