{
  "type": "Feature",
  "properties": {
    "gn:country":"YE",
    "gn:fcode":"PPL",
    "gn:pop":1,
    "iso:country":"YE",
    "name:ara_x_preferred":[
        "\u0627\u0644\u0637\u0648\u0627\u0626\u0644"
    ],
    "name:eng_x_preferred":[
        "At Tawail"
    ],
    "qs:name":"A\u0163 \u0162aw\u0101\u2019il",
    "qs:photos_9r":0,
    "qs:photos_sr":0,
    "qs:pop_sr":"1",
    "wof:name":"A\u0163 \u0162aw\u0101\u2019il",
    "wof:placetype":"locality",
    "wof:population":1
},
  "geometry": {"coordinates":[43.39128,16.67366],"type":"Point"}
}