{
  "type": "Feature",
  "properties": {
    "gn:admin1_code":"22.0",
    "gn:admin2_code":"1704.0",
    "gn:asciiname":"Al Muharraqah",
    "gn:country_code":"YE",
    "gn:dem":163,
    "gn:feature_class":"P",
    "gn:feature_code":"PPL",
    "gn:name":"Al Mu\u1e29arraqah",
    "gn:population":0,
    "gn:timezone":"Asia/Aden",
    "iso:country":"YE",
    "name:und_x_variant":[
        "Al Mu\u1e29arraqah",
        "Al \u2018Ash\u0101b\u012byah",
        "Al Mu\u1e29raqah"
    ],
    "wof:name":"Al Muharraqah",
    "wof:placetype":"locality"
},
  "geometry": {"coordinates":[43.19252,15.91851],"type":"Point"}
}