{
  "type": "Feature",
  "properties": {
    "gn:admin1_code":"23.0",
    "gn:admin2_code":"1101.0",
    "gn:asciiname":"Najd al Ahmar",
    "gn:country_code":"YE",
    "gn:dem":1205,
    "gn:feature_class":"P",
    "gn:feature_code":"PPL",
    "gn:name":"Najd al A\u1e29mar",
    "gn:population":0,
    "gn:timezone":"Asia/Aden",
    "iso:country":"YE",
    "name:ara_x_preferred":[
        "\u0646\u062c\u062f \u0627\u0644\u0623\u062d\u0645\u0631"
    ],
    "name:und_x_variant":[
        "Najd al A\u1e29mar"
    ],
    "wof:name":"Najd al Ahmar",
    "wof:placetype":"locality"
},
  "geometry": {"coordinates":[44.04867,14.29314],"type":"Point"}
}