{
  "type": "Feature",
  "properties": {
    "gn:country":"YE",
    "gn:fcode":"PPL",
    "gn:pop":4,
    "iso:country":"YE",
    "name:ara_x_preferred":[
        "\u063a\u0627\u0631\u0628 \u0631\u062c\u062d"
    ],
    "name:eng_x_preferred":[
        "Gharib Rajih"
    ],
    "qs:name":"Gh\u0101rib Raji\u1e29",
    "qs:photos_9r":0,
    "qs:photos_sr":0,
    "qs:pop_sr":"1",
    "wof:name":"Gh\u0101rib Raji\u1e29",
    "wof:placetype":"locality",
    "wof:population":4
},
  "geometry": {"coordinates":[43.7265,16.26694],"type":"Point"}
}