{
  "type": "Feature",
  "properties": {
    "gn:admin1_code":"27.0",
    "gn:admin2_code":"3102.0",
    "gn:asciiname":"Al Khadar",
    "gn:country_code":"YE",
    "gn:dem":292,
    "gn:feature_class":"P",
    "gn:feature_code":"PPL",
    "gn:name":"Al Kha\u1e11\u0101r",
    "gn:population":0,
    "gn:timezone":"Asia/Aden",
    "iso:country":"YE",
    "name:und_x_variant":[
        "Al Kha\u1e11\u0101r"
    ],
    "wof:name":"Al Khadar",
    "wof:placetype":"locality"
},
  "geometry": {"coordinates":[43.46997,14.69479],"type":"Point"}
}