{
  "type": "Feature",
  "properties": {
    "gn:admin1_code":"11.0",
    "gn:admin2_code":"2005.0",
    "gn:asciiname":"Kammat al Jahawir",
    "gn:country_code":"YE",
    "gn:dem":1774,
    "gn:feature_class":"P",
    "gn:feature_code":"PPL",
    "gn:name":"Kammat al Jah\u0101wir",
    "gn:population":0,
    "gn:timezone":"Asia/Aden",
    "iso:country":"YE",
    "name:und_x_variant":[
        "Kammat al Jah\u0101wir"
    ],
    "wof:name":"Kammat al Jahawir",
    "wof:placetype":"locality"
},
  "geometry": {"coordinates":[44.03035,14.52108],"type":"Point"}
}