{
  "type": "Feature",
  "properties": {
    "gn:admin1_code":"22.0",
    "gn:admin2_code":"1717.0",
    "gn:asciiname":"Al `Ashiri",
    "gn:country_code":"YE",
    "gn:dem":728,
    "gn:feature_class":"P",
    "gn:feature_code":"PPL",
    "gn:name":"Al \u2018\u0100shir\u012b",
    "gn:population":0,
    "gn:timezone":"Asia/Aden",
    "iso:country":"YE",
    "name:ara_x_preferred":[
        "Al \u2018\u0100shir\u012b"
    ],
    "wof:name":"Al `Ashiri",
    "wof:placetype":"locality"
},
  "geometry": {"coordinates":[43.58881,15.83436],"type":"Point"}
}