{
  "type": "Feature",
  "properties": {
    "gn:admin1_code":"16.0",
    "gn:admin2_code":"2302.0",
    "gn:asciiname":"Bayt as Subayhi",
    "gn:country_code":"YE",
    "gn:dem":1630,
    "gn:feature_class":"P",
    "gn:feature_code":"PPL",
    "gn:name":"Bayt a\u015f \u015eubay\u1e29\u012b",
    "gn:population":0,
    "gn:timezone":"Asia/Aden",
    "iso:country":"YE",
    "name:ara_x_preferred":[
        "\u0628\u064a\u062a \u0627\u0644\u0635\u0628\u064a\u062d\u064a"
    ],
    "name:und_x_variant":[
        "Bayt a\u015f \u015eubay\u1e29\u012b"
    ],
    "wof:name":"Bayt as Subayhi",
    "wof:placetype":"locality"
},
  "geometry": {"coordinates":[44.19849,15.98829],"type":"Point"}
}