{
  "type": "Feature",
  "properties": {
    "gn:admin1_code":"22.0",
    "gn:admin2_code":"1711.0",
    "gn:asciiname":"Al Marajim",
    "gn:country_code":"YE",
    "gn:dem":485,
    "gn:feature_class":"P",
    "gn:feature_code":"PPL",
    "gn:name":"Al Mar\u0101jim",
    "gn:population":0,
    "gn:timezone":"Asia/Aden",
    "iso:country":"YE",
    "name:und_x_variant":[
        "Al Mar\u0101jim"
    ],
    "wof:name":"Al Marajim",
    "wof:placetype":"locality"
},
  "geometry": {"coordinates":[43.38081,16.00445],"type":"Point"}
}