{
  "type": "Feature",
  "properties": {
    "gn:admin1_code":"23.0",
    "gn:admin2_code":"1101.0",
    "gn:asciiname":"Ash Sha'fa'",
    "gn:country_code":"YE",
    "gn:dem":1353,
    "gn:feature_class":"P",
    "gn:feature_code":"PPL",
    "gn:name":"Ash Sha\u2018f\u0101\u2019",
    "gn:population":0,
    "gn:timezone":"Asia/Aden",
    "iso:country":"YE",
    "name:ara_x_preferred":[
        "\u0627\u0644\u0634\u0639\u0641\u0627\u0621"
    ],
    "name:und_x_variant":[
        "Ash Sha\u2018f\u0101\u2019"
    ],
    "wof:name":"Ash Sha'fa'",
    "wof:placetype":"locality"
},
  "geometry": {"coordinates":[44.09199,14.33968],"type":"Point"}
}