{
  "type": "Feature",
  "properties": {
    "gn:admin1_code":"24.0",
    "gn:admin2_code":"2512.0",
    "gn:asciiname":"Duqm Salih",
    "gn:country_code":"YE",
    "gn:dem":1300,
    "gn:feature_class":"P",
    "gn:feature_code":"PPL",
    "gn:name":"Duqm \u015e\u0101li\u1e29",
    "gn:population":0,
    "gn:timezone":"Asia/Aden",
    "iso:country":"YE",
    "name:ara_x_preferred":[
        "\u062f\u0642\u0645 \u0635\u0627\u0644\u062d"
    ],
    "name:und_x_variant":[
        "Duqm \u015e\u0101li\u1e29"
    ],
    "wof:name":"Duqm Salih",
    "wof:placetype":"locality"
},
  "geometry": {"coordinates":[44.19508,13.20376],"type":"Point"}
}