{
  "type": "Feature",
  "properties": {
    "gn:admin1_code":"5.0",
    "gn:admin2_code":"2108.0",
    "gn:asciiname":"An Nab",
    "gn:country_code":"YE",
    "gn:dem":1146,
    "gn:feature_class":"P",
    "gn:feature_code":"PPL",
    "gn:name":"An N\u0101b",
    "gn:population":0,
    "gn:timezone":"Asia/Aden",
    "iso:country":"YE",
    "name:ara_x_preferred":[
        "\u0627\u0644\u0646\u0627\u0628"
    ],
    "name:und_x_variant":[
        "Hajar am-N\u0101b",
        "Hajar en-N\u0101b",
        "Hajar an N\u0101b",
        "An N\u0101b"
    ],
    "wof:name":"An Nab",
    "wof:placetype":"locality"
},
  "geometry": {"coordinates":[46.04047,14.57612],"type":"Point"}
}