{
  "type": "Feature",
  "properties": {
    "gn:admin1_code":"8.0",
    "gn:admin2_code":"1810.0",
    "gn:asciiname":"Al Qarn",
    "gn:country_code":"YE",
    "gn:dem":349,
    "gn:feature_class":"P",
    "gn:feature_code":"PPL",
    "gn:name":"Al Qarn",
    "gn:population":0,
    "gn:timezone":"Asia/Aden",
    "iso:country":"YE",
    "wof:name":"Al Qarn",
    "wof:placetype":"locality"
},
  "geometry": {"coordinates":[43.39735,15.04077],"type":"Point"}
}