{
  "type": "Feature",
  "properties": {
    "gn:country":"YE",
    "gn:fcode":"PPL",
    "gn:pop":11,
    "iso:country":"YE",
    "name:ara_x_preferred":[
        "\u0627\u0644\u0645\u062d\u062a\u062f"
    ],
    "name:eng_x_preferred":[
        "Al Mahtad"
    ],
    "qs:name":"Al Ma\u1e29tad",
    "qs:photos_9r":0,
    "qs:photos_sr":0,
    "qs:pop_sr":"1",
    "wof:name":"Al Ma\u1e29tad",
    "wof:placetype":"locality",
    "wof:population":11
},
  "geometry": {"coordinates":[45.4676,14.14359],"type":"Point"}
}