{
  "type": "Feature",
  "properties": {
    "gn:admin1_code":"15.0",
    "gn:admin2_code":"2210.0",
    "gn:asciiname":"As Saqat",
    "gn:country_code":"YE",
    "gn:dem":2535,
    "gn:feature_class":"P",
    "gn:feature_code":"PPL",
    "gn:name":"As S\u0101q\u0101t",
    "gn:population":0,
    "gn:timezone":"Asia/Aden",
    "iso:country":"YE",
    "name:ara_x_preferred":[
        "As S\u0101q\u0101t"
    ],
    "name:ara_x_variant":[
        "\u0627\u0644\u0633\u0627\u0642\u0627\u062a"
    ],
    "wof:name":"As Saqat",
    "wof:placetype":"locality"
},
  "geometry": {"coordinates":[43.40031,17.19008],"type":"Point"}
}