{
  "type": "Feature",
  "properties": {
    "gn:admin1_code":"22.0",
    "gn:admin2_code":"1725.0",
    "gn:asciiname":"Mabyan",
    "gn:country_code":"YE",
    "gn:dem":1035,
    "gn:feature_class":"P",
    "gn:feature_code":"PPL",
    "gn:name":"Mabyan",
    "gn:population":0,
    "gn:timezone":"Asia/Aden",
    "iso:country":"YE",
    "name:ara_x_preferred":[
        "\u0645\u0628\u064a\u0646"
    ],
    "wof:name":"Mabyan",
    "wof:placetype":"locality"
},
  "geometry": {"coordinates":[43.54008,15.56067],"type":"Point"}
}