{
  "type": "Feature",
  "properties": {
    "gn:admin1_code":"14.0",
    "gn:admin2_code":"2613.0",
    "gn:asciiname":"Al Uraydan",
    "gn:country_code":"YE",
    "gn:dem":1065,
    "gn:feature_class":"P",
    "gn:feature_code":"PPL",
    "gn:name":"\u0100l Urayd\u0101n",
    "gn:population":0,
    "gn:timezone":"Asia/Aden",
    "iso:country":"YE",
    "name:ara_x_preferred":[
        "\u0622\u0644 \u0648\u0631\u064a\u062f\u0627\u0646"
    ],
    "name:und_x_variant":[
        "\u0100l Wurayd\u0101n",
        "\u0100l Urayd\u0101n"
    ],
    "wof:name":"Al Uraydan",
    "wof:placetype":"locality"
},
  "geometry": {"coordinates":[45.42077000000001,15.44202],"type":"Point"}
}