{
  "type": "Feature",
  "properties": {
    "gn:admin1_code":"25.0",
    "gn:admin2_code":"1515.0",
    "gn:asciiname":"Al Kuddahi",
    "gn:country_code":"YE",
    "gn:dem":1037,
    "gn:feature_class":"P",
    "gn:feature_code":"PPL",
    "gn:name":"Al Kudd\u0101\u1e29\u012b",
    "gn:population":0,
    "gn:timezone":"Asia/Aden",
    "iso:country":"YE",
    "name:ara_x_preferred":[
        "Al Kudd\u0101\u1e29\u012b"
    ],
    "name:ara_x_variant":[
        "\u0627\u0644\u0643\u062f\u0627\u062d\u064a"
    ],
    "wof:name":"Al Kuddahi",
    "wof:placetype":"locality"
},
  "geometry": {"coordinates":[43.94885,13.15919],"type":"Point"}
}