{
  "type": "Feature",
  "properties": {
    "gn:admin1_code":"20.0",
    "gn:admin2_code":"1414.0",
    "gn:asciiname":"Ar Radhah",
    "gn:country_code":"YE",
    "gn:dem":2026,
    "gn:feature_class":"P",
    "gn:feature_code":"PPL",
    "gn:name":"Ar Rad\u1e29ah",
    "gn:population":0,
    "gn:timezone":"Asia/Aden",
    "iso:country":"YE",
    "name:und_x_variant":[
        "Ar Rad\u1e29ah"
    ],
    "wof:name":"Ar Radhah",
    "wof:placetype":"locality"
},
  "geometry": {"coordinates":[44.98132,14.51312],"type":"Point"}
}