{
  "type": "Feature",
  "properties": {
    "gn:country":"YE",
    "gn:fcode":"PPL",
    "gn:pop":6,
    "iso:country":"YE",
    "name:ara_x_preferred":[
        "\u0627\u0644\u0634\u0639\u0628\u064a\u0646"
    ],
    "name:eng_x_preferred":[
        "Ash Sha'bin"
    ],
    "qs:name":"Ash Sha\u2018b\u012bn",
    "qs:photos_9r":0,
    "qs:photos_sr":0,
    "qs:pop_sr":"1",
    "wof:name":"Ash Sha\u2018b\u012bn",
    "wof:placetype":"locality",
    "wof:population":6
},
  "geometry": {"coordinates":[44.31958,17.0327],"type":"Point"}
}