{
  "type": "Feature",
  "properties": {
    "gn:admin1_code":"24.0",
    "gn:admin2_code":"2502.0",
    "gn:asciiname":"Madinat Lab`us",
    "gn:country_code":"YE",
    "gn:dem":2281,
    "gn:feature_class":"P",
    "gn:feature_code":"PPLA2",
    "gn:name":"Mad\u012bnat Lab\u2018\u016bs",
    "gn:population":0,
    "gn:timezone":"Asia/Aden",
    "iso:country":"YE",
    "name:ara_x_preferred":[
        "\u0645\u062f\u064a\u0646\u0629 \u0644\u0628\u0639\u0648\u0633"
    ],
    "name:und_x_variant":[
        "Hajar al Ab\u2018\u016bs",
        "Mad\u012bnat Lab\u2018\u016bs"
    ],
    "wof:name":"Madinat Lab`us",
    "wof:placetype":"locality"
},
  "geometry": {"coordinates":[45.25,13.86667],"type":"Point"}
}