{
  "type": "Feature",
  "properties": {
    "gn:admin1_code":"15.0",
    "gn:admin2_code":"2208.0",
    "gn:asciiname":"Mahnakah",
    "gn:country_code":"YE",
    "gn:dem":2128,
    "gn:feature_class":"P",
    "gn:feature_code":"PPL",
    "gn:name":"Ma\u1e29nakah",
    "gn:population":0,
    "gn:timezone":"Asia/Aden",
    "iso:country":"YE",
    "name:ara_x_preferred":[
        "\u0645\u062d\u0646\u0643\u0629"
    ],
    "name:und_x_variant":[
        "Ma\u1e29nakah"
    ],
    "wof:name":"Mahnakah",
    "wof:placetype":"locality"
},
  "geometry": {"coordinates":[43.44844000000001,16.76787],"type":"Point"}
}