{
  "type": "Feature",
  "properties": {
    "gn:admin1_code":"1.0",
    "gn:admin2_code":"1211.0",
    "gn:asciiname":"Khuban",
    "gn:cc2":"YE",
    "gn:country_code":"YE",
    "gn:dem":17,
    "gn:feature_class":"P",
    "gn:feature_code":"PPL",
    "gn:name":"Khub\u0101n",
    "gn:population":0,
    "gn:timezone":"Asia/Aden",
    "iso:country":"YE",
    "name:ara_x_preferred":[
        "Khub\u0101n"
    ],
    "name:und_x_variant":[
        "Kanad\u00e1"
    ],
    "wof:name":"Khuban",
    "wof:placetype":"locality"
},
  "geometry": {"coordinates":[45.44611,13.18806],"type":"Point"}
}