{
  "type": "Feature",
  "properties": {
    "gn:gn_country":"YE",
    "gn:gn_fcode":"PPL",
    "gn:gn_pop":2,
    "gn:population":2,
    "iso:country":"YE",
    "name:ara_x_preferred":[
        "\u062f\u0645\u0646\u0629 \u0627\u0644\u0637\u0648\u0631"
    ],
    "name:eng_x_preferred":[
        "Dimnat At Tawr"
    ],
    "name:eng_x_variant":[
        "Al Muraysh"
    ],
    "qs_pg:aaroncc":"YE",
    "qs_pg:gn_country":"YE",
    "qs_pg:gn_fcode":"PPL",
    "qs_pg:gn_pop":2,
    "qs_pg:name":"Dimnat a\u0163 \u0162awr",
    "qs_pg:photos_9r":0,
    "qs_pg:photos_sr":0,
    "qs_pg:pop_sr":1,
    "qs_pg:qs_pg_placetype":"locality",
    "wof:name":"Dimnat a\u0163 \u0162awr",
    "wof:placetype":"locality",
    "wof:population":2
},
  "geometry": {"coordinates":[43.31583,16.65108],"type":"Point"}
}