{
  "type": "Feature",
  "properties": {
    "gn:country":"YE",
    "gn:fcode":"PPL",
    "gn:pop":7,
    "iso:country":"YE",
    "name:ara_x_preferred":[
        "\u0634\u0639\u0628 \u0627\u0644\u0642\u062d\u0637\u0627\u0646\u064a"
    ],
    "name:eng_x_preferred":[
        "Sha'b Al Qahtani"
    ],
    "qs:name":"Sha\u2018b al Qa\u1e29\u0163\u0101n\u012b",
    "qs:photos_9r":0,
    "qs:photos_sr":0,
    "qs:pop_sr":"1",
    "wof:name":"Sha\u2018b al Qa\u1e29\u0163\u0101n\u012b",
    "wof:placetype":"locality",
    "wof:population":7
},
  "geometry": {"coordinates":[43.71123,16.09323],"type":"Point"}
}