{
  "type": "Feature",
  "properties": {
    "gn:country":"YE",
    "gn:fcode":"PPL",
    "gn:pop":3,
    "iso:country":"YE",
    "name:ara_x_preferred":[
        "\u0645\u0646\u064a\u0646 \u0627\u0644\u0623\u0634\u0631\u0627\u0641"
    ],
    "name:ara_x_variant":[
        "\u0645\u0646\u064a\u0646 \u0627\u0644\u0627\u0634\u0631\u0627\u0641"
    ],
    "name:eng_x_preferred":[
        "Manin Al Ashraf"
    ],
    "qs:name":"Man\u012bn al Ashr\u0101f",
    "qs:photos_9r":0,
    "qs:photos_sr":0,
    "qs:pop_sr":"1",
    "wof:name":"Man\u012bn al Ashr\u0101f",
    "wof:placetype":"locality",
    "wof:population":3
},
  "geometry": {"coordinates":[45.30039,15.40307],"type":"Point"}
}