{
  "type": "Feature",
  "properties": {
    "gn:admin1_code":"22.0",
    "gn:admin2_code":"1716.0",
    "gn:asciiname":"Bayt Sulan",
    "gn:country_code":"YE",
    "gn:dem":1804,
    "gn:feature_class":"P",
    "gn:feature_code":"PPL",
    "gn:name":"Bayt \u015e\u016bl\u0101n",
    "gn:population":0,
    "gn:timezone":"Asia/Aden",
    "iso:country":"YE",
    "name:und_x_variant":[
        "Bayt \u015e\u016bl\u0101n"
    ],
    "wof:name":"Bayt Sulan",
    "wof:placetype":"locality"
},
  "geometry": {"coordinates":[43.45999000000001,15.98907],"type":"Point"}
}