{
  "type": "Feature",
  "properties": {
    "gn:admin1_code":"23.0",
    "gn:admin2_code":"1117.0",
    "gn:asciiname":"Al Gharbi",
    "gn:country_code":"YE",
    "gn:dem":1402,
    "gn:feature_class":"P",
    "gn:feature_code":"PPL",
    "gn:name":"Al Gharb\u012b",
    "gn:population":0,
    "gn:timezone":"Asia/Aden",
    "iso:country":"YE",
    "name:ara_x_preferred":[
        "\u0627\u0644\u063a\u0631\u0628\u064a"
    ],
    "name:und_x_variant":[
        "Al Gharb\u012b"
    ],
    "wof:name":"Al Gharbi",
    "wof:placetype":"locality"
},
  "geometry": {"coordinates":[43.94246,13.80561],"type":"Point"}
}