{
  "type": "Feature",
  "properties": {
    "gn:admin1_code":"5.0",
    "gn:admin2_code":"2102.0",
    "gn:asciiname":"Rashshah",
    "gn:country_code":"YE",
    "gn:dem":1491,
    "gn:feature_class":"P",
    "gn:feature_code":"PPL",
    "gn:name":"Rashshah",
    "gn:population":0,
    "gn:timezone":"Asia/Aden",
    "iso:country":"YE",
    "wof:name":"Rashshah",
    "wof:placetype":"locality"
},
  "geometry": {"coordinates":[47.4706,15.23937],"type":"Point"}
}