{
  "type": "Feature",
  "properties": {
    "gn:admin1_code":"22.0",
    "gn:admin2_code":"1720.0",
    "gn:asciiname":"Ar Rahabah",
    "gn:country_code":"YE",
    "gn:dem":660,
    "gn:feature_class":"P",
    "gn:feature_code":"PPL",
    "gn:name":"Ar Ra\u1e29abah",
    "gn:population":0,
    "gn:timezone":"Asia/Aden",
    "iso:country":"YE",
    "name:nno_x_preferred":[
        "Ar Rahabah"
    ],
    "name:und_x_variant":[
        "Ar Ra\u1e29abah"
    ],
    "wof:name":"Ar Rahabah",
    "wof:placetype":"locality"
},
  "geometry": {"coordinates":[43.50216,15.75323],"type":"Point"}
}