{
  "type": "Feature",
  "properties": {
    "gn:admin1_code":"15.0",
    "gn:admin2_code":"2211.0",
    "gn:asciiname":"Jildan",
    "gn:country_code":"YE",
    "gn:dem":1921,
    "gn:feature_class":"P",
    "gn:feature_code":"PPL",
    "gn:name":"Jild\u0101n",
    "gn:population":0,
    "gn:timezone":"Asia/Aden",
    "iso:country":"YE",
    "name:ara_x_preferred":[
        "Jild\u0101n"
    ],
    "name:ara_x_variant":[
        "\u062c\u0644\u062f\u0627\u0646"
    ],
    "wof:name":"Jildan",
    "wof:placetype":"locality"
},
  "geometry": {"coordinates":[43.68398,17.01063],"type":"Point"}
}