{
  "type": "Feature",
  "properties": {
    "gn:admin1_code":"19.0",
    "gn:admin2_code":"2919.0",
    "gn:asciiname":"Al Mahanah",
    "gn:country_code":"YE",
    "gn:dem":2003,
    "gn:feature_class":"P",
    "gn:feature_code":"PPL",
    "gn:name":"Al Ma\u1e29\u0101nah",
    "gn:population":0,
    "gn:timezone":"Asia/Aden",
    "iso:country":"YE",
    "name:ara_x_preferred":[
        "\u0627\u0644\u0645\u062d\u0627\u0646\u0629"
    ],
    "name:und_x_variant":[
        "Al Ma\u1e29\u0101nah"
    ],
    "wof:name":"Al Mahanah",
    "wof:placetype":"locality"
},
  "geometry": {"coordinates":[43.85231,16.02968],"type":"Point"}
}