{
  "type": "Feature",
  "properties": {
    "gn:admin1_code":"8.0",
    "gn:admin2_code":"1808.0",
    "gn:asciiname":"Mahall Shawqi",
    "gn:country_code":"YE",
    "gn:dem":115,
    "gn:feature_class":"P",
    "gn:feature_code":"PPL",
    "gn:name":"Ma\u1e29all Shawq\u012b",
    "gn:population":0,
    "gn:timezone":"Asia/Aden",
    "iso:country":"YE",
    "name:ara_x_preferred":[
        "\u0645\u062d\u0644 \u0634\u0648\u0642\u064a"
    ],
    "name:und_x_variant":[
        "Ma\u1e29all Shawq\u012b"
    ],
    "wof:name":"Mahall Shawqi",
    "wof:placetype":"locality"
},
  "geometry": {"coordinates":[43.15229,15.28113],"type":"Point"}
}