{
  "type": "Feature",
  "properties": {
    "gn:admin1_code":"21.0",
    "gn:admin2_code":"1610.0",
    "gn:asciiname":"Al Qa`",
    "gn:country_code":"YE",
    "gn:dem":2048,
    "gn:feature_class":"P",
    "gn:feature_code":"PPL",
    "gn:name":"Al Q\u0101\u2018",
    "gn:population":0,
    "gn:timezone":"Asia/Aden",
    "iso:country":"YE",
    "name:ara_x_preferred":[
        "Al Q\u0101\u2018"
    ],
    "name:ara_x_variant":[
        "\u0627\u0644\u0642\u0627\u0639"
    ],
    "name:und_x_variant":[
        "Ma\u1e29all al Q\u0101\u2018"
    ],
    "wof:name":"Al Qa`",
    "wof:placetype":"locality"
},
  "geometry": {"coordinates":[44.41559,16.76613],"type":"Point"}
}