{
  "type": "Feature",
  "properties": {
    "gn:admin1_code":"4.0",
    "gn:admin2_code":"1928.0",
    "gn:asciiname":"Shamikh Bin Musallam",
    "gn:cc2":"YE",
    "gn:country_code":"YE",
    "gn:dem":800,
    "gn:feature_class":"P",
    "gn:feature_code":"PPL",
    "gn:name":"Sh\u0101mikh Bin Musallam",
    "gn:population":0,
    "gn:timezone":"Asia/Aden",
    "iso:country":"YE",
    "name:und_x_variant":[
        "\u1e28. Ya\u1e29annas",
        "Sh\u0101mikh",
        "Sh\u0101mikh Bin Musallam"
    ],
    "wof:name":"Shamikh Bin Musallam",
    "wof:placetype":"locality"
},
  "geometry": {"coordinates":[48.06667,15.51667],"type":"Point"}
}