{
  "type": "Feature",
  "properties": {
    "gn:admin1_code":"22.0",
    "gn:admin2_code":"1724.0",
    "gn:asciiname":"Al Ma`aynah",
    "gn:country_code":"YE",
    "gn:dem":240,
    "gn:feature_class":"P",
    "gn:feature_code":"PPL",
    "gn:name":"Al Ma\u2018aynah",
    "gn:population":0,
    "gn:timezone":"Asia/Aden",
    "iso:country":"YE",
    "name:und_x_variant":[
        "Al Ma\u2018aynah",
        "Al Mu\u2018aynah"
    ],
    "wof:name":"Al Ma`aynah",
    "wof:placetype":"locality"
},
  "geometry": {"coordinates":[43.274,15.67881],"type":"Point"}
}