{
  "type": "Feature",
  "properties": {
    "gn:country":"YE",
    "gn:fcode":"PPL",
    "gn:population":3,
    "iso:country":"YE",
    "name:ara_x_preferred":[
        "\u0627\u0644\u0646\u0634\u064a\u0641"
    ],
    "name:eng_x_preferred":[
        "An Nushayf"
    ],
    "name:eng_x_variant":[
        "Badw Naq\u2018ah"
    ],
    "qs:name":"An Nushayf",
    "qs:photos_9r":0,
    "qs:photos_sr":0,
    "qs:pop_sr":"1",
    "wof:name":"An Nushayf",
    "wof:placetype":"locality",
    "wof:population":3
},
  "geometry": {"coordinates":[43.36952,16.34917],"type":"Point"}
}