{
  "type": "Feature",
  "properties": {
    "gn:country":"YE",
    "gn:fcode":"PPL",
    "gn:pop":42,
    "iso:country":"YE",
    "name:ara_x_preferred":[
        "\u0637\u0648\u0631\u0629"
    ],
    "name:eng_x_preferred":[
        "Tawrah"
    ],
    "qs:name":"\u0162awrah",
    "qs:photos_9r":0,
    "qs:photos_sr":0,
    "qs:pop_sr":"1",
    "wof:name":"\u0162awrah",
    "wof:placetype":"locality",
    "wof:population":42
},
  "geometry": {"coordinates":[43.80791,13.16485],"type":"Point"}
}