{
  "type": "Feature",
  "properties": {
    "gn:country":"YE",
    "gn:fcode":"PPL",
    "gn:population":5,
    "iso:country":"YE",
    "name:ara_x_preferred":[
        "\u0627\u0644\u0645\u062c\u0632\u0639\u0629"
    ],
    "name:eng_x_preferred":[
        "Al Majzi'ah"
    ],
    "name:eng_x_variant":[
        "Al \u1e28im\u0101\u2019"
    ],
    "qs_pg:aaroncc":"YE",
    "qs_pg:gn_country":"YE",
    "qs_pg:gn_fcode":"PPL",
    "qs_pg:gn_pop":5,
    "qs_pg:name":"Al Majzi\u2018ah",
    "qs_pg:photos_9r":0,
    "qs_pg:photos_sr":0,
    "qs_pg:pop_sr":1,
    "qs_pg:qs_pg_placetype":"locality",
    "wof:name":"Al Majzi\u2018ah",
    "wof:placetype":"locality",
    "wof:population":5
},
  "geometry": {"coordinates":[43.37955,17.09379],"type":"Point"}
}