{
  "type": "Feature",
  "properties": {
    "gn:admin1_code":"19.0",
    "gn:admin2_code":"2919.0",
    "gn:asciiname":"Ghulah",
    "gn:cc2":"YE",
    "gn:country_code":"YE",
    "gn:dem":2376,
    "gn:feature_class":"P",
    "gn:feature_code":"PPL",
    "gn:name":"Gh\u016blah",
    "gn:population":0,
    "gn:timezone":"Asia/Aden",
    "iso:country":"YE",
    "name:und_x_variant":[
        "G\u00fble",
        "Ghule",
        "Gh\u016blah"
    ],
    "wof:name":"Ghulah",
    "wof:placetype":"locality"
},
  "geometry": {"coordinates":[44.01667,16.05],"type":"Point"}
}