{
  "type": "Feature",
  "properties": {
    "gn:admin1_code":"16.0",
    "gn:admin2_code":"2309.0",
    "gn:asciiname":"Bani Rubayh",
    "gn:country_code":"YE",
    "gn:dem":1548,
    "gn:feature_class":"P",
    "gn:feature_code":"PPL",
    "gn:name":"Ban\u012b Rubay\u1e29",
    "gn:population":0,
    "gn:timezone":"Asia/Aden",
    "iso:country":"YE",
    "name:und_x_variant":[
        "Ban\u012b Rubay\u1e29"
    ],
    "wof:name":"Bani Rubayh",
    "wof:placetype":"locality"
},
  "geometry": {"coordinates":[43.86742,15.07975],"type":"Point"}
}