{
  "type": "Feature",
  "properties": {
    "gn:country":"YE",
    "gn:fcode":"PPL",
    "gn:pop":25,
    "iso:country":"YE",
    "name:ara_x_preferred":[
        "\u0627\u0644 \u0623\u0628\u0648 \u062d\u0627\u0633\u0631\u0629"
    ],
    "name:eng_x_preferred":[
        "Al AbU Hasirah"
    ],
    "name:eng_x_variant":[
        "Mal\u1e29at al \u2018Uly\u0101"
    ],
    "qs:name":"\u0100l Ab\u016b \u1e28\u0101sirah",
    "qs:photos_9r":0,
    "qs:photos_sr":0,
    "qs:pop_sr":"1",
    "wof:name":"\u0100l Ab\u016b \u1e28\u0101sirah",
    "wof:placetype":"locality",
    "wof:population":25
},
  "geometry": {"coordinates":[43.80246,17.05124],"type":"Point"}
}