{
  "type": "Feature",
  "properties": {
    "gn:admin1_code":"25.0",
    "gn:admin2_code":"1501.0",
    "gn:asciiname":"Hujfah",
    "gn:country_code":"YE",
    "gn:dem":1118,
    "gn:feature_class":"P",
    "gn:feature_code":"PPL",
    "gn:name":"\u1e28ujfah",
    "gn:population":0,
    "gn:timezone":"Asia/Aden",
    "iso:country":"YE",
    "name:und_x_variant":[
        "\u1e28ujfah"
    ],
    "wof:name":"Hujfah",
    "wof:placetype":"locality"
},
  "geometry": {"coordinates":[44.26727,13.58496],"type":"Point"}
}