{
  "type": "Feature",
  "properties": {
    "gn:admin1_code":"23.0",
    "gn:admin2_code":"1101.0",
    "gn:asciiname":"Az Zanimah",
    "gn:country_code":"YE",
    "gn:dem":1676,
    "gn:feature_class":"P",
    "gn:feature_code":"PPL",
    "gn:name":"Az\u0327 Z\u0327an\u012bmah",
    "gn:population":0,
    "gn:timezone":"Asia/Aden",
    "iso:country":"YE",
    "name:ara_x_preferred":[
        "\u0627\u0644\u0638\u0646\u064a\u0645\u0629"
    ],
    "name:und_x_variant":[
        "Az\u0327 Z\u0327an\u012bmah"
    ],
    "wof:name":"Az Zanimah",
    "wof:placetype":"locality"
},
  "geometry": {"coordinates":[44.15142,14.33907],"type":"Point"}
}