{
  "type": "Feature",
  "properties": {
    "gn:country":"YE",
    "gn:fcode":"PPL",
    "gn:pop":17,
    "iso:country":"YE",
    "name:ara_x_preferred":[
        "\u0628\u0646\u064a \u0642\u0631\u0627\u0635"
    ],
    "name:eng_x_preferred":[
        "Bani Qiras"
    ],
    "name:unk_x_variant":[
        "\u0628\u0646\u064a \u0642\u0631\u0627\u0635"
    ],
    "qs:name":"Ban\u012b Qir\u0101\u015f",
    "qs:photos_9r":0,
    "qs:photos_sr":0,
    "qs:pop_sr":"1",
    "wof:name":"Ban\u012b Qir\u0101\u015f",
    "wof:placetype":"locality",
    "wof:population":17
},
  "geometry": {"coordinates":[42.989,16.38966],"type":"Point"}
}