{
  "type": "Feature",
  "properties": {
    "gn:admin1_code":"23.0",
    "gn:admin2_code":"1113.0",
    "gn:asciiname":"Bayt al Jadid",
    "gn:country_code":"YE",
    "gn:dem":2474,
    "gn:feature_class":"P",
    "gn:feature_code":"PPL",
    "gn:name":"Bayt al Jad\u012bd",
    "gn:population":0,
    "gn:timezone":"Asia/Aden",
    "iso:country":"YE",
    "name:und_x_variant":[
        "Bayt al Jad\u012bd"
    ],
    "wof:name":"Bayt al Jadid",
    "wof:placetype":"locality"
},
  "geometry": {"coordinates":[44.24139,13.99632],"type":"Point"}
}