{
  "type": "Feature",
  "properties": {
    "gn:admin1_code":"15.0",
    "gn:admin2_code":"2214.0",
    "gn:asciiname":"Al `Id",
    "gn:country_code":"YE",
    "gn:dem":1862,
    "gn:feature_class":"P",
    "gn:feature_code":"PPL",
    "gn:name":"\u0100l \u2018\u012ad",
    "gn:population":0,
    "gn:timezone":"Asia/Aden",
    "iso:country":"YE",
    "name:ara_x_preferred":[
        "\u0100l \u2018\u012ad"
    ],
    "wof:name":"Al `Id",
    "wof:placetype":"locality"
},
  "geometry": {"coordinates":[44.09945,17.09225],"type":"Point"}
}