{
  "type": "Feature",
  "properties": {
    "gn:admin1_code":"10.0",
    "gn:admin2_code":"2702.0",
    "gn:asciiname":"Sawwan",
    "gn:country_code":"YE",
    "gn:dem":2337,
    "gn:feature_class":"P",
    "gn:feature_code":"PPL",
    "gn:name":"\u015eaww\u0101n",
    "gn:population":0,
    "gn:timezone":"Asia/Aden",
    "iso:country":"YE",
    "name:und_x_variant":[
        "\u015eaww\u0101n"
    ],
    "wof:name":"Sawwan",
    "wof:placetype":"locality"
},
  "geometry": {"coordinates":[43.75628,15.52015],"type":"Point"}
}