{
  "type": "Feature",
  "properties": {
    "gn:admin1_code":"14.0",
    "gn:admin2_code":"2609.0",
    "gn:asciiname":"Thayb",
    "gn:country_code":"YE",
    "gn:dem":1217,
    "gn:feature_class":"P",
    "gn:feature_code":"PPL",
    "gn:name":"Thayb",
    "gn:population":0,
    "gn:timezone":"Asia/Aden",
    "iso:country":"YE",
    "name:ara_x_preferred":[
        "\u062b\u064a\u0628"
    ],
    "wof:name":"Thayb",
    "wof:placetype":"locality"
},
  "geometry": {"coordinates":[45.43409000000001,14.90251],"type":"Point"}
}