{
  "type": "Feature",
  "properties": {
    "gn:admin1_code":"11.0",
    "gn:admin2_code":"2006.0",
    "gn:asciiname":"Zulaf",
    "gn:country_code":"YE",
    "gn:dem":1367,
    "gn:feature_class":"P",
    "gn:feature_code":"PPL",
    "gn:name":"Z\u0327ul\u0101f",
    "gn:population":0,
    "gn:timezone":"Asia/Aden",
    "iso:country":"YE",
    "name:ara_x_preferred":[
        "Z\u0327ul\u0101f"
    ],
    "wof:name":"Zulaf",
    "wof:placetype":"locality"
},
  "geometry": {"coordinates":[43.83369,14.33016],"type":"Point"}
}