{
  "type": "Feature",
  "properties": {
    "gn:admin1_code":"8.0",
    "gn:admin2_code":"1810.0",
    "gn:asciiname":"Dayr as Sahil",
    "gn:country_code":"YE",
    "gn:dem":91,
    "gn:feature_class":"P",
    "gn:feature_code":"PPL",
    "gn:name":"Dayr as Sah\u012bl",
    "gn:population":0,
    "gn:timezone":"Asia/Aden",
    "iso:country":"YE",
    "name:und_x_variant":[
        "Dayr as Sah\u012bl"
    ],
    "wof:name":"Dayr as Sahil",
    "wof:placetype":"locality"
},
  "geometry": {"coordinates":[43.13333,15.01667],"type":"Point"}
}