{
  "type": "Feature",
  "properties": {
    "gn:admin1_code":"22.0",
    "gn:admin2_code":"1708.0",
    "gn:asciiname":"Gharib Sulayman",
    "gn:country_code":"YE",
    "gn:dem":909,
    "gn:feature_class":"P",
    "gn:feature_code":"PPL",
    "gn:name":"Gh\u0101rib Sulaym\u0101n",
    "gn:population":0,
    "gn:timezone":"Asia/Aden",
    "iso:country":"YE",
    "name:und_x_variant":[
        "Gh\u0101rib Sulaym\u0101n",
        "Gh\u0101rib a\u1e11 \u1e10ubbah"
    ],
    "wof:name":"Gharib Sulayman",
    "wof:placetype":"locality"
},
  "geometry": {"coordinates":[43.59017,15.98527],"type":"Point"}
}