{
  "type": "Feature",
  "properties": {
    "gn:admin1_code":"22.0",
    "gn:admin2_code":"1725.0",
    "gn:asciiname":"Al Hadib",
    "gn:country_code":"YE",
    "gn:dem":646,
    "gn:feature_class":"P",
    "gn:feature_code":"PPL",
    "gn:name":"Al \u1e28\u0101\u1e11ib",
    "gn:population":0,
    "gn:timezone":"Asia/Aden",
    "iso:country":"YE",
    "name:ara_x_preferred":[
        "Al \u1e28\u0101\u1e11ib"
    ],
    "wof:name":"Al Hadib",
    "wof:placetype":"locality"
},
  "geometry": {"coordinates":[43.47285,15.57471],"type":"Point"}
}