{
  "type": "Feature",
  "properties": {
    "gn:admin1_code":"24.0",
    "gn:admin2_code":"2512.0",
    "gn:asciiname":"Hajiyu",
    "gn:country_code":"YE",
    "gn:dem":949,
    "gn:feature_class":"P",
    "gn:feature_code":"PPLL",
    "gn:name":"Haj\u012by\u016b",
    "gn:population":0,
    "gn:timezone":"Asia/Aden",
    "iso:country":"YE",
    "name:ara_x_preferred":[
        "\u0647\u062c\u064a\u0648"
    ],
    "name:und_x_variant":[
        "Haj\u012by\u016b"
    ],
    "wof:name":"Hajiyu",
    "wof:placetype":"locality"
},
  "geometry": {"coordinates":[44.15454,13.08388],"type":"Point"}
}