{
  "type": "Feature",
  "properties": {
    "gn:admin1_code":"19.0",
    "gn:admin2_code":"2910.0",
    "gn:asciiname":"Mahm al Kalbiyin",
    "gn:country_code":"YE",
    "gn:dem":2541,
    "gn:feature_class":"P",
    "gn:feature_code":"PPL",
    "gn:name":"Ma\u1e29m al Kalb\u012by\u012bn",
    "gn:population":0,
    "gn:timezone":"Asia/Aden",
    "iso:country":"YE",
    "name:und_x_variant":[
        "Ma\u1e29m al Kalb\u012by\u012bn"
    ],
    "wof:name":"Mahm al Kalbiyin",
    "wof:placetype":"locality"
},
  "geometry": {"coordinates":[44.05847,15.88757],"type":"Point"}
}