{
  "type": "Feature",
  "properties": {
    "gn:gn_country":"YE",
    "gn:gn_fcode":"PPL",
    "gn:gn_pop":4,
    "gn:population":4,
    "iso:country":"YE",
    "name:ara_x_preferred":[
        "\u0627\u0644\u062f\u0648\u0627\u062d\u0645\u0640\u0629"
    ],
    "name:eng_x_preferred":[
        "Ad Diwahimah"
    ],
    "name:eng_x_variant":[
        "Al \u2018Ay\u0101b"
    ],
    "qs_pg:aaroncc":"YE",
    "qs_pg:gn_country":"YE",
    "qs_pg:gn_fcode":"PPL",
    "qs_pg:gn_pop":4,
    "qs_pg:name":"Ad Diw\u0101\u1e29imah",
    "qs_pg:photos_9r":0,
    "qs_pg:photos_sr":0,
    "qs_pg:pop_sr":1,
    "qs_pg:qs_pg_placetype":"locality",
    "wof:name":"Ad Diw\u0101\u1e29imah",
    "wof:placetype":"locality",
    "wof:population":4
},
  "geometry": {"coordinates":[43.32344,16.12611],"type":"Point"}
}