{
  "type": "Feature",
  "properties": {
    "gn:country":"YE",
    "gn:fcode":"PPL",
    "gn:population":39,
    "iso:country":"YE",
    "name:ara_x_preferred":[
        "\u0628\u0626\u0631 \u064a\u0639\u0642\u0648\u0628"
    ],
    "name:eng_x_preferred":[
        "Bir Ya'qUb"
    ],
    "name:eng_x_variant":[
        "\u0100l al Mahdhir\u012byah"
    ],
    "qs:name":"Bi\u2019r Ya\u2018q\u016bb",
    "qs:photos_9r":0,
    "qs:photos_sr":0,
    "qs:pop_sr":"1",
    "wof:name":"Bi\u2019r Ya\u2018q\u016bb",
    "wof:placetype":"locality",
    "wof:population":39
},
  "geometry": {"coordinates":[43.76971,16.91409],"type":"Point"}
}