{
  "type": "Feature",
  "properties": {
    "gn:admin1_code":"11.0",
    "gn:admin2_code":"1101.0",
    "gn:asciiname":"Hawjam",
    "gn:country_code":"YE",
    "gn:dem":2500,
    "gn:feature_class":"P",
    "gn:feature_code":"PPL",
    "gn:name":"\u1e28awjam",
    "gn:population":0,
    "gn:timezone":"Asia/Aden",
    "iso:country":"YE",
    "name:ara_x_preferred":[
        "\u062d\u0648\u062c\u0645"
    ],
    "name:und_x_variant":[
        "\u1e28awjam"
    ],
    "wof:name":"Hawjam",
    "wof:placetype":"locality"
},
  "geometry": {"coordinates":[44.26835,14.31905],"type":"Point"}
}