{
  "type": "Feature",
  "properties": {
    "gn:admin1_code":"19.0",
    "gn:admin2_code":"2913.0",
    "gn:asciiname":"Bani Ghawi",
    "gn:country_code":"YE",
    "gn:dem":1018,
    "gn:feature_class":"P",
    "gn:feature_code":"PPL",
    "gn:name":"Ban\u012b Gh\u0101w\u012b",
    "gn:population":0,
    "gn:timezone":"Asia/Aden",
    "iso:country":"YE",
    "name:und_x_variant":[
        "Ban\u012b Gh\u0101w\u012b"
    ],
    "wof:name":"Bani Ghawi",
    "wof:placetype":"locality"
},
  "geometry": {"coordinates":[43.72231,15.88316],"type":"Point"}
}