{
  "type": "Feature",
  "properties": {
    "gn:admin1_code":"25.0",
    "gn:admin2_code":"1515.0",
    "gn:asciiname":"As Saqha'",
    "gn:country_code":"YE",
    "gn:dem":2022,
    "gn:feature_class":"P",
    "gn:feature_code":"PPL",
    "gn:name":"As Saq\u1e29\u0101\u2019",
    "gn:population":0,
    "gn:timezone":"Asia/Aden",
    "iso:country":"YE",
    "name:ara_x_preferred":[
        "\u0627\u0644\u0633\u0642\u062d\u0627\u0621"
    ],
    "name:und_x_variant":[
        "As Saq\u1e29\u0101\u2019"
    ],
    "wof:name":"As Saqha'",
    "wof:placetype":"locality"
},
  "geometry": {"coordinates":[44.16752,13.24701],"type":"Point"}
}