{
  "type": "Feature",
  "properties": {
    "gn:country":"YE",
    "gn:fcode":"PPL",
    "gn:pop":2,
    "iso:country":"YE",
    "name:ara_x_preferred":[
        "\u0642\u0644\u0648\u0627\u0639 \u0633\u0627\u0631\u0649"
    ],
    "name:eng_x_preferred":[
        "Qalwa' Sari"
    ],
    "qs:name":"Qalw\u0101\u2018 S\u0101r\u012b",
    "qs:photos_9r":0,
    "qs:photos_sr":0,
    "qs:pop_sr":"1",
    "wof:name":"Qalw\u0101\u2018 S\u0101r\u012b",
    "wof:placetype":"locality",
    "wof:population":2
},
  "geometry": {"coordinates":[43.39953,16.2808],"type":"Point"}
}