{
  "type": "Feature",
  "properties": {
    "gn:admin1_code":"8.0",
    "gn:admin2_code":"1810.0",
    "gn:asciiname":"Al Wajihiyah",
    "gn:country_code":"YE",
    "gn:dem":24,
    "gn:feature_class":"P",
    "gn:feature_code":"PPL",
    "gn:name":"Al Waj\u012bh\u012byah",
    "gn:population":0,
    "gn:timezone":"Asia/Aden",
    "iso:country":"YE",
    "name:ara_x_preferred":[
        "\u0627\u0644\u0648\u062c\u064a\u0647\u064a\u0629"
    ],
    "name:und_x_variant":[
        "Al Waj\u012bh\u012byah"
    ],
    "wof:name":"Al Wajihiyah",
    "wof:placetype":"locality"
},
  "geometry": {"coordinates":[42.92918,15.05667],"type":"Point"}
}