{
  "type": "Feature",
  "properties": {
    "gn:admin1_code":"25.0",
    "gn:admin2_code":"1515.0",
    "gn:asciiname":"Qaryat al Jami`",
    "gn:country_code":"YE",
    "gn:dem":1590,
    "gn:feature_class":"P",
    "gn:feature_code":"PPL",
    "gn:name":"Qaryat al J\u0101mi\u2018",
    "gn:population":0,
    "gn:timezone":"Asia/Aden",
    "iso:country":"YE",
    "name:und_x_variant":[
        "Qaryat al J\u0101mi\u2018"
    ],
    "wof:name":"Qaryat al Jami`",
    "wof:placetype":"locality"
},
  "geometry": {"coordinates":[44.06364,13.2323],"type":"Point"}
}