{
  "type": "Feature",
  "properties": {
    "gn:country":"YE",
    "gn:fcode":"PPL",
    "gn:population":5,
    "iso:country":"YE",
    "name:ara_x_preferred":[
        "\u0627\u0644\u0645\u0644\u0627\u062d\u064a\u0627\u062a"
    ],
    "name:eng_x_preferred":[
        "Al Malahiyat"
    ],
    "name:eng_x_variant":[
        "\u015eal\u0101\u1e29"
    ],
    "qs:name":"Al Mal\u0101\u1e29iy\u0101t",
    "qs:photos_9r":0,
    "qs:photos_sr":0,
    "qs:pop_sr":"1",
    "wof:name":"Al Mal\u0101\u1e29iy\u0101t",
    "wof:placetype":"locality",
    "wof:population":5
},
  "geometry": {"coordinates":[43.34153,16.59767],"type":"Point"}
}