{
  "type": "Feature",
  "properties": {
    "gn:admin1_code":"23.0",
    "gn:admin2_code":"1101.0",
    "gn:asciiname":"Dhi `Adin",
    "gn:country_code":"YE",
    "gn:dem":2381,
    "gn:feature_class":"P",
    "gn:feature_code":"PPL",
    "gn:name":"Dh\u012b \u2018Ad\u012bn",
    "gn:population":0,
    "gn:timezone":"Asia/Aden",
    "iso:country":"YE",
    "name:ara_x_preferred":[
        "Dh\u012b \u2018Ad\u012bn"
    ],
    "wof:name":"Dhi `Adin",
    "wof:placetype":"locality"
},
  "geometry": {"coordinates":[44.23278,14.29059],"type":"Point"}
}