{
  "type": "Feature",
  "properties": {
    "gn:country":"YE",
    "gn:fcode":"PPL",
    "gn:population":2,
    "iso:country":"YE",
    "name:ara_x_preferred":[
        "\u063a\u0627\u0644\u0628 \u0627\u0644\u0646\u0648\u0631"
    ],
    "name:eng_x_preferred":[
        "Ghalib An NUr"
    ],
    "name:eng_x_variant":[
        "\u0100l M\u012br\u0101n"
    ],
    "qs:name":"Gh\u0101lib an N\u016br",
    "qs:photos_9r":0,
    "qs:photos_sr":0,
    "qs:pop_sr":"1",
    "wof:name":"Gh\u0101lib an N\u016br",
    "wof:placetype":"locality",
    "wof:population":2
},
  "geometry": {"coordinates":[43.3306,16.51596],"type":"Point"}
}