{
  "type": "Feature",
  "properties": {
    "gn:admin1_code":"23.0",
    "gn:admin2_code":"1102.0",
    "gn:asciiname":"Al Uksud",
    "gn:country_code":"YE",
    "gn:dem":2656,
    "gn:feature_class":"P",
    "gn:feature_code":"PPL",
    "gn:name":"Al Uks\u016bd",
    "gn:population":0,
    "gn:timezone":"Asia/Aden",
    "iso:country":"YE",
    "name:ara_x_preferred":[
        "Al Aks\u016bd"
    ],
    "name:ara_x_variant":[
        "\u0627\u0644\u0623\u0643\u0633\u0648\u062f"
    ],
    "name:und_x_variant":[
        "Al Uks\u016bd"
    ],
    "wof:name":"Al Uksud",
    "wof:placetype":"locality"
},
  "geometry": {"coordinates":[44.38072,14.213],"type":"Point"}
}