{
  "type": "Feature",
  "properties": {
    "gn:admin1_code":"22.0",
    "gn:admin2_code":"1723.0",
    "gn:asciiname":"Mahall al Hinak",
    "gn:country_code":"YE",
    "gn:dem":873,
    "gn:feature_class":"P",
    "gn:feature_code":"PPL",
    "gn:name":"Ma\u1e29all al \u1e28in\u0101k",
    "gn:population":0,
    "gn:timezone":"Asia/Aden",
    "iso:country":"YE",
    "name:und_x_variant":[
        "Ma\u1e29all al \u1e28in\u0101k"
    ],
    "wof:name":"Mahall al Hinak",
    "wof:placetype":"locality"
},
  "geometry": {"coordinates":[43.48646,15.71741],"type":"Point"}
}