{
  "type": "Feature",
  "properties": {
    "gn:admin1_code":"25.0",
    "gn:admin2_code":"1517.0",
    "gn:asciiname":"Hawb al Jamil",
    "gn:country_code":"YE",
    "gn:dem":1620,
    "gn:feature_class":"P",
    "gn:feature_code":"PPL",
    "gn:name":"Hawb al Jam\u012bl",
    "gn:population":0,
    "gn:timezone":"Asia/Aden",
    "iso:country":"YE",
    "name:ara_x_preferred":[
        "\u0647\u0648\u0628 \u0627\u0644\u062c\u0645\u064a\u0644"
    ],
    "name:und_x_variant":[
        "Hawb al Jam\u012bl"
    ],
    "wof:name":"Hawb al Jamil",
    "wof:placetype":"locality"
},
  "geometry": {"coordinates":[44.1949,13.2237],"type":"Point"}
}