{
  "type": "Feature",
  "properties": {
    "gn:admin1_code":"25.0",
    "gn:admin2_code":"1515.0",
    "gn:asciiname":"Sardaf",
    "gn:country_code":"YE",
    "gn:dem":1674,
    "gn:feature_class":"P",
    "gn:feature_code":"PPL",
    "gn:name":"\u015eardaf",
    "gn:population":0,
    "gn:timezone":"Asia/Aden",
    "iso:country":"YE",
    "name:und_x_variant":[
        "\u015eardaf"
    ],
    "wof:name":"Sardaf",
    "wof:placetype":"locality"
},
  "geometry": {"coordinates":[44.08431,13.20918],"type":"Point"}
}