{
  "type": "Feature",
  "properties": {
    "gn:admin1_code":"24.0",
    "gn:admin2_code":"2512.0",
    "gn:asciiname":"Hawl Jabir",
    "gn:country_code":"YE",
    "gn:dem":1472,
    "gn:feature_class":"P",
    "gn:feature_code":"PPL",
    "gn:name":"\u1e28awl J\u0101bir",
    "gn:population":0,
    "gn:timezone":"Asia/Aden",
    "iso:country":"YE",
    "name:ara_x_preferred":[
        "\u062d\u0648\u0644 \u062c\u0627\u0628\u0631"
    ],
    "name:und_x_variant":[
        "\u1e28awl J\u0101bir"
    ],
    "wof:name":"Hawl Jabir",
    "wof:placetype":"locality"
},
  "geometry": {"coordinates":[44.18315,13.22015],"type":"Point"}
}