{
  "type": "Feature",
  "properties": {
    "gn:admin1_code":"23.0",
    "gn:admin2_code":"1108.0",
    "gn:asciiname":"Qaryat al `Ard",
    "gn:country_code":"YE",
    "gn:dem":2108,
    "gn:feature_class":"P",
    "gn:feature_code":"PPL",
    "gn:name":"Qaryat al \u2018Ar\u1e11",
    "gn:population":0,
    "gn:timezone":"Asia/Aden",
    "iso:country":"YE",
    "name:ara_x_preferred":[
        "\u0627\u0644\u0639\u0631\u0636"
    ],
    "name:und_x_variant":[
        "Qaryat al \u2018Ar\u1e11",
        "Al \u2018Ar\u1e11"
    ],
    "wof:name":"Qaryat al `Ard",
    "wof:placetype":"locality"
},
  "geometry": {"coordinates":[44.09947,14.10634],"type":"Point"}
}