{
  "type": "Feature",
  "properties": {
    "gn:admin1_code":"1.0",
    "gn:admin2_code":"1204.0",
    "gn:asciiname":"Sakin am Zuhur",
    "gn:country_code":"YE",
    "gn:dem":1045,
    "gn:feature_class":"P",
    "gn:feature_code":"PPL",
    "gn:name":"S\u0101kin am Zuh\u016br",
    "gn:population":0,
    "gn:timezone":"Asia/Aden",
    "iso:country":"YE",
    "name:und_x_variant":[
        "S\u0101kin am Zuh\u016br"
    ],
    "wof:name":"Sakin am Zuhur",
    "wof:placetype":"locality"
},
  "geometry": {"coordinates":[45.86955,13.92605],"type":"Point"}
}