{
  "type": "Feature",
  "properties": {
    "gn:admin1_code":"8.0",
    "gn:admin2_code":"1812.0",
    "gn:asciiname":"Ash Sharaqi",
    "gn:country_code":"YE",
    "gn:dem":746,
    "gn:feature_class":"P",
    "gn:feature_code":"PPL",
    "gn:name":"Ash Shar\u0101q\u012b",
    "gn:population":0,
    "gn:timezone":"Asia/Aden",
    "iso:country":"YE",
    "name:ara_x_preferred":[
        "\u0627\u0644\u0634\u0631\u0627\u0642\u064a"
    ],
    "name:und_x_variant":[
        "Ash Shar\u0101q\u012b"
    ],
    "wof:name":"Ash Sharaqi",
    "wof:placetype":"locality"
},
  "geometry": {"coordinates":[43.43433,14.93322],"type":"Point"}
}