{
  "type": "Feature",
  "properties": {
    "gn:country":"YE",
    "gn:fcode":"PPL",
    "gn:population":3,
    "iso:country":"YE",
    "name:ara_x_preferred":[
        "\u0627\u0644\u062e\u0645\u0627\u0631\u064a\u0629"
    ],
    "name:eng_x_preferred":[
        "Al Khimariyah"
    ],
    "name:sqi_x_preferred":[
        "Al Muq\u0163a\u2018"
    ],
    "qs:name":"Al Khim\u0101r\u012byah",
    "qs:photos_9r":0,
    "qs:photos_sr":0,
    "qs:pop_sr":"1",
    "wof:name":"Al Khim\u0101r\u012byah",
    "wof:placetype":"locality",
    "wof:population":3
},
  "geometry": {"coordinates":[43.81635,13.40942],"type":"Point"}
}