{
  "type": "Feature",
  "properties": {
    "gn:country":"YE",
    "gn:fcode":"PPL",
    "gn:pop":17,
    "iso:country":"YE",
    "name:ara_x_preferred":[
        "\u0628\u0646 \u0627\u0644\u062e\u0631\u0627\u0628"
    ],
    "name:eng_x_preferred":[
        "Bin Al Kharab"
    ],
    "qs:name":"Bin al Khar\u0101b",
    "qs:photos_9r":0,
    "qs:photos_sr":0,
    "qs:pop_sr":"1",
    "wd:wordcount":956,
    "wof:name":"Bin al Khar\u0101b",
    "wof:placetype":"locality",
    "wof:population":17
},
  "geometry": {"coordinates":[43.67613,16.19702],"type":"Point"}
}