{
  "type": "Feature",
  "properties": {
    "gn:country":"YE",
    "gn:fcode":"PPL",
    "gn:population":21,
    "iso:country":"YE",
    "name:ara_x_preferred":[
        "\u0627\u0644\u0628\u0631\u0634"
    ],
    "name:eng_x_preferred":[
        "Al Bursh"
    ],
    "name:eng_x_variant":[
        "Al Ja\u2018milah"
    ],
    "qs:name":"Al Bursh",
    "qs:photos_9r":0,
    "qs:photos_sr":0,
    "qs:pop_sr":"1",
    "wof:name":"Al Bursh",
    "wof:placetype":"locality",
    "wof:population":21
},
  "geometry": {"coordinates":[43.3683,16.06838],"type":"Point"}
}