{
  "type": "Feature",
  "properties": {
    "gn:admin1_code":"22.0",
    "gn:admin2_code":"1714.0",
    "gn:asciiname":"Hirran",
    "gn:country_code":"YE",
    "gn:dem":635,
    "gn:feature_class":"P",
    "gn:feature_code":"PPL",
    "gn:name":"Hirr\u0101n",
    "gn:population":0,
    "gn:timezone":"Asia/Aden",
    "iso:country":"YE",
    "name:ara_x_preferred":[
        "Hirr\u0101n"
    ],
    "wof:name":"Hirran",
    "wof:placetype":"locality"
},
  "geometry": {"coordinates":[43.41325,15.98345],"type":"Point"}
}