{
  "type": "Feature",
  "properties": {
    "gn:admin1_code":"15.0",
    "gn:admin2_code":"2214.0",
    "gn:asciiname":"As Sadah",
    "gn:country_code":"YE",
    "gn:dem":1716,
    "gn:feature_class":"P",
    "gn:feature_code":"PPLF",
    "gn:name":"As S\u0101dah",
    "gn:population":0,
    "gn:timezone":"Asia/Aden",
    "iso:country":"YE",
    "name:ara_x_preferred":[
        "\u0627\u0644\u0633\u0627\u062f\u0629"
    ],
    "name:und_x_variant":[
        "As S\u0101dah"
    ],
    "wof:name":"As Sadah",
    "wof:placetype":"locality"
},
  "geometry": {"coordinates":[44.18753,16.92205],"type":"Point"}
}