{
  "type": "Feature",
  "properties": {
    "gn:admin1_code":"10.0",
    "gn:admin2_code":"2707.0",
    "gn:asciiname":"Al Nubiyah",
    "gn:country_code":"YE",
    "gn:dem":1102,
    "gn:feature_class":"P",
    "gn:feature_code":"PPL",
    "gn:name":"Al N\u016bbiyah",
    "gn:population":0,
    "gn:timezone":"Asia/Aden",
    "iso:country":"YE",
    "name:und_x_variant":[
        "Al N\u016bbiyah"
    ],
    "wof:name":"Al Nubiyah",
    "wof:placetype":"locality"
},
  "geometry": {"coordinates":[43.50816,15.38341],"type":"Point"}
}