{
  "type": "Feature",
  "properties": {
    "gn:country":"YE",
    "gn:fcode":"PPL",
    "gn:population":7,
    "iso:country":"YE",
    "name:ara_x_preferred":[
        "\u0627\u0644\u063a\u0640\u0631\u0631"
    ],
    "name:ara_x_variant":[
        "\u0627\u0644\u063a\u0631\u0631"
    ],
    "name:eng_x_preferred":[
        "Al Gharar"
    ],
    "name:eng_x_variant":[
        "Al Mujaw\u0101z"
    ],
    "qs:name":"Al Gharar",
    "qs:photos_9r":0,
    "qs:photos_sr":0,
    "qs:pop_sr":"1",
    "wof:name":"Al Gharar",
    "wof:placetype":"locality",
    "wof:population":7
},
  "geometry": {"coordinates":[43.46665,16.16405],"type":"Point"}
}