{
  "type": "Feature",
  "properties": {
    "gn:admin1_code":"8.0",
    "gn:admin2_code":"1810.0",
    "gn:asciiname":"Al Miqdamiyah",
    "gn:country_code":"YE",
    "gn:dem":152,
    "gn:feature_class":"P",
    "gn:feature_code":"PPL",
    "gn:name":"Al Miqd\u0101m\u012byah",
    "gn:population":0,
    "gn:timezone":"Asia/Aden",
    "iso:country":"YE",
    "name:und_x_variant":[
        "Al Miqd\u0101m\u012byah"
    ],
    "wof:name":"Al Miqdamiyah",
    "wof:placetype":"locality"
},
  "geometry": {"coordinates":[43.22458,15.07784],"type":"Point"}
}