{
  "type": "Feature",
  "properties": {
    "gn:admin1_code":"8.0",
    "gn:admin2_code":"1816.0",
    "gn:asciiname":"Qaryat al Kawaziyah",
    "gn:country_code":"YE",
    "gn:dem":123,
    "gn:feature_class":"P",
    "gn:feature_code":"PPL",
    "gn:name":"Qaryat al Kaw\u0101z\u012byah",
    "gn:population":0,
    "gn:timezone":"Asia/Aden",
    "iso:country":"YE",
    "name:und_x_variant":[
        "Qaryat al Kaw\u0101z\u012byah"
    ],
    "wof:name":"Qaryat al Kawaziyah",
    "wof:placetype":"locality"
},
  "geometry": {"coordinates":[43.35251,14.66893],"type":"Point"}
}