{
  "type": "Feature",
  "properties": {
    "gn:admin1_code":"15.0",
    "gn:admin2_code":"2208.0",
    "gn:asciiname":"As Sabi`",
    "gn:country_code":"YE",
    "gn:dem":1863,
    "gn:feature_class":"P",
    "gn:feature_code":"PPL",
    "gn:name":"As Sab\u012b\u2018",
    "gn:population":0,
    "gn:timezone":"Asia/Aden",
    "iso:country":"YE",
    "name:ara_x_preferred":[
        "\u0627\u0644\u0633\u0628\u064a\u0639"
    ],
    "name:und_x_variant":[
        "Qarn as Sab\u012b\u2018",
        "As Sab\u012b\u2018"
    ],
    "wof:name":"As Sabi`",
    "wof:placetype":"locality"
},
  "geometry": {"coordinates":[43.37987,16.76546],"type":"Point"}
}