{
  "type": "Feature",
  "properties": {
    "gn:admin1_code":"19.0",
    "gn:admin2_code":"2911.0",
    "gn:asciiname":"Kawlat as Suqayyah",
    "gn:country_code":"YE",
    "gn:dem":2638,
    "gn:feature_class":"P",
    "gn:feature_code":"PPL",
    "gn:name":"Kawlat as Suqayyah",
    "gn:population":0,
    "gn:timezone":"Asia/Aden",
    "iso:country":"YE",
    "wof:name":"Kawlat as Suqayyah",
    "wof:placetype":"locality"
},
  "geometry": {"coordinates":[44.08266,15.72755],"type":"Point"}
}