{
  "type": "Feature",
  "properties": {
    "gn:admin1_code":"19.0",
    "gn:admin2_code":"2919.0",
    "gn:asciiname":"Ar Rajanah",
    "gn:country_code":"YE",
    "gn:dem":1973,
    "gn:feature_class":"P",
    "gn:feature_code":"PPLL",
    "gn:name":"Ar Raj\u0101nah",
    "gn:population":0,
    "gn:timezone":"Asia/Aden",
    "iso:country":"YE",
    "name:ara_x_preferred":[
        "\u0627\u0644\u0631\u062c\u0627\u0646\u0629"
    ],
    "name:und_x_variant":[
        "Ar Raj\u0101nah"
    ],
    "wof:name":"Ar Rajanah",
    "wof:placetype":"locality"
},
  "geometry": {"coordinates":[43.84262,16.03322],"type":"Point"}
}