{
  "type": "Feature",
  "properties": {
    "gn:country":"YE",
    "gn:fcode":"PPL",
    "gn:pop":1,
    "iso:country":"YE",
    "name:ara_x_preferred":[
        "\u0639\u0634\u0631\u0629"
    ],
    "name:eng_x_preferred":[
        "Asharah"
    ],
    "qs:name":"\u2018Asharah",
    "qs:photos_9r":0,
    "qs:photos_sr":0,
    "qs:pop_sr":"1",
    "wd:wordcount":498,
    "wof:name":"\u2018Asharah",
    "wof:placetype":"locality",
    "wof:population":1
},
  "geometry": {"coordinates":[45.42796,14.92414],"type":"Point"}
}