{
  "type": "Feature",
  "properties": {
    "gn:admin1_code":"22.0",
    "gn:admin2_code":"1725.0",
    "gn:asciiname":"Bayt at Tanubi",
    "gn:country_code":"YE",
    "gn:dem":1050,
    "gn:feature_class":"P",
    "gn:feature_code":"PPL",
    "gn:name":"Bayt at Tan\u016bb\u012b",
    "gn:population":0,
    "gn:timezone":"Asia/Aden",
    "iso:country":"YE",
    "name:ara_x_preferred":[
        "\u0628\u064a\u062a \u0627\u0644\u062a\u0646\u0648\u0628\u064a"
    ],
    "name:und_x_variant":[
        "Bayt at Tan\u016bb\u012b"
    ],
    "wof:name":"Bayt at Tanubi",
    "wof:placetype":"locality"
},
  "geometry": {"coordinates":[43.55361,15.5923],"type":"Point"}
}