{
  "type": "Feature",
  "properties": {
    "gn:admin1_code":"23.0",
    "gn:admin2_code":"1101.0",
    "gn:asciiname":"Ash Shurf",
    "gn:country_code":"YE",
    "gn:dem":2442,
    "gn:feature_class":"P",
    "gn:feature_code":"PPL",
    "gn:name":"Ash Shurf",
    "gn:population":0,
    "gn:timezone":"Asia/Aden",
    "iso:country":"YE",
    "name:ara_x_preferred":[
        "\u0627\u0644\u0634\u0631\u0641"
    ],
    "wof:name":"Ash Shurf",
    "wof:placetype":"locality"
},
  "geometry": {"coordinates":[44.22008,14.27558],"type":"Point"}
}