{
  "type": "Feature",
  "properties": {
    "gn:country":"YE",
    "gn:fcode":"PPL",
    "gn:population":13,
    "iso:country":"YE",
    "name:ara_x_preferred":[
        "\u0627\u0644\u0642\u0644\u0639\u0629"
    ],
    "qs:name":"Al Qal\u2018ah",
    "qs:photos_9r":0,
    "qs:photos_sr":0,
    "qs:pop_sr":"1",
    "wof:name":"Al Qal\u2018ah",
    "wof:placetype":"locality",
    "wof:population":13
},
  "geometry": {"coordinates":[43.45453,16.33431],"type":"Point"}
}