{
  "type": "Feature",
  "properties": {
    "gn:admin1_code":"11.0",
    "gn:admin2_code":"2005.0",
    "gn:asciiname":"Al Jizzah",
    "gn:country_code":"YE",
    "gn:dem":2486,
    "gn:feature_class":"P",
    "gn:feature_code":"PPL",
    "gn:name":"Al Jizz\u0101\u1e29",
    "gn:population":0,
    "gn:timezone":"Asia/Aden",
    "iso:country":"YE",
    "name:ara_x_preferred":[
        "Al Jizz\u0101\u1e29"
    ],
    "wof:name":"Al Jizzah",
    "wof:placetype":"locality"
},
  "geometry": {"coordinates":[43.92092,14.47542],"type":"Point"}
}