{
  "type": "Feature",
  "properties": {
    "gn:admin1_code":"15.0",
    "gn:admin2_code":"2210.0",
    "gn:asciiname":"Lahj Sa`d",
    "gn:country_code":"YE",
    "gn:dem":1464,
    "gn:feature_class":"P",
    "gn:feature_code":"PPL",
    "gn:name":"La\u1e29j Sa\u2018d",
    "gn:population":0,
    "gn:timezone":"Asia/Aden",
    "iso:country":"YE",
    "name:ara_x_preferred":[
        "\u0644\u062d\u062c \u0633\u0639\u062f"
    ],
    "name:und_x_variant":[
        "La\u1e29j Sa\u2018d"
    ],
    "wof:name":"Lahj Sa`d",
    "wof:placetype":"locality"
},
  "geometry": {"coordinates":[43.33869,17.17816],"type":"Point"}
}