{
  "type": "Feature",
  "properties": {
    "gn:admin1_code":"8.0",
    "gn:admin2_code":"1812.0",
    "gn:asciiname":"Sharim",
    "gn:country_code":"YE",
    "gn:dem":493,
    "gn:feature_class":"P",
    "gn:feature_code":"PPL",
    "gn:name":"Shar\u012bm",
    "gn:population":0,
    "gn:timezone":"Asia/Aden",
    "iso:country":"YE",
    "name:und_x_variant":[
        "Shar\u012bm"
    ],
    "wof:name":"Sharim",
    "wof:placetype":"locality"
},
  "geometry": {"coordinates":[43.44469,14.93952],"type":"Point"}
}