{
  "type": "Feature",
  "properties": {
    "gn:country":"YE",
    "gn:fcode":"PPL",
    "gn:pop":4,
    "iso:country":"YE",
    "name:ara_x_preferred":[
        "\u0630\u0648 \u0635\u0648\u0627\u0628"
    ],
    "name:eng_x_preferred":[
        "DhU Sawab"
    ],
    "qs:name":"Dh\u016b \u015eaw\u0101b",
    "qs:photos_9r":0,
    "qs:photos_sr":0,
    "qs:pop_sr":"1",
    "wof:name":"Dh\u016b \u015eaw\u0101b",
    "wof:placetype":"locality",
    "wof:population":4
},
  "geometry": {"coordinates":[44.09328,16.84823],"type":"Point"}
}