{
  "type": "Feature",
  "properties": {
    "gn:country":"YE",
    "gn:fcode":"PPL",
    "gn:population":1,
    "iso:country":"YE",
    "name:ara_x_preferred":[
        "\u0627\u0644\u0636\u064a\u0641\u0629 \u0627\u0644\u0623\u0633\u0641\u0644"
    ],
    "name:eng_x_preferred":[
        "Au Dayqah Al Asfal"
    ],
    "name:eng_x_variant":[
        "Qullat as Sarw"
    ],
    "qs:name":"A\u1e11 \u1e10ayqah al Asfal",
    "qs:photos_9r":0,
    "qs:photos_sr":0,
    "qs:pop_sr":"1",
    "wof:name":"A\u1e11 \u1e10ayqah al Asfal",
    "wof:placetype":"locality",
    "wof:population":1
},
  "geometry": {"coordinates":[44.4384,16.91192],"type":"Point"}
}