{
  "type": "Feature",
  "properties": {
    "gn:admin1_code":"25.0",
    "gn:admin2_code":"1515.0",
    "gn:asciiname":"Muqarimah",
    "gn:country_code":"YE",
    "gn:dem":1523,
    "gn:feature_class":"P",
    "gn:feature_code":"PPL",
    "gn:name":"Muq\u0101rimah",
    "gn:population":0,
    "gn:timezone":"Asia/Aden",
    "iso:country":"YE",
    "name:und_x_variant":[
        "Muq\u0101rimah"
    ],
    "wof:name":"Muqarimah",
    "wof:placetype":"locality"
},
  "geometry": {"coordinates":[44.06,13.13528],"type":"Point"}
}