{
  "type": "Feature",
  "properties": {
    "gn:country":"YE",
    "gn:fcode":"PPL",
    "gn:population":1,
    "iso:country":"YE",
    "name:ara_x_preferred":[
        "\u0627\u0644\u0623\u0643\u0645\u0629"
    ],
    "name:und_x_variant":[
        "Al Akamah"
    ],
    "qs:name":"Al Akimah",
    "qs:photos_9r":0,
    "qs:photos_sr":0,
    "qs:pop_sr":"1",
    "wof:name":"Al Akimah",
    "wof:placetype":"locality",
    "wof:population":1
},
  "geometry": {"coordinates":[43.78514,13.4511],"type":"Point"}
}