{
  "type": "Feature",
  "properties": {
    "gn:admin1_code":"19.0",
    "gn:admin2_code":"2911.0",
    "gn:asciiname":"Bayt al Qatar",
    "gn:country_code":"YE",
    "gn:dem":2244,
    "gn:feature_class":"P",
    "gn:feature_code":"PPL",
    "gn:name":"Bayt al Qatar",
    "gn:population":0,
    "gn:timezone":"Asia/Aden",
    "iso:country":"YE",
    "wof:name":"Bayt al Qatar",
    "wof:placetype":"locality"
},
  "geometry": {"coordinates":[43.97393,15.84408],"type":"Point"}
}