{
  "type": "Feature",
  "properties": {
    "gn:admin1_code":"10.0",
    "gn:admin2_code":"2706.0",
    "gn:asciiname":"Rawud",
    "gn:country_code":"YE",
    "gn:dem":1597,
    "gn:feature_class":"P",
    "gn:feature_code":"PPL",
    "gn:name":"R\u0101wud",
    "gn:population":0,
    "gn:timezone":"Asia/Aden",
    "iso:country":"YE",
    "name:ara_x_preferred":[
        "R\u0101wud"
    ],
    "wof:name":"Rawud",
    "wof:placetype":"locality"
},
  "geometry": {"coordinates":[43.40543,15.34919],"type":"Point"}
}