{
  "type": "Feature",
  "properties": {
    "gn:country":"YE",
    "gn:fcode":"PPL",
    "gn:pop":14,
    "iso:country":"YE",
    "name:ara_x_preferred":[
        "\u0628\u0648\u0642\u0629"
    ],
    "name:eng_x_preferred":[
        "BUqah\""
    ],
    "name:eng_x_variant":[
        "Bayt Ja\u2018w\u0101n"
    ],
    "qs:name":"B\u016bqah",
    "qs:photos_9r":0,
    "qs:photos_sr":0,
    "qs:pop_sr":"1",
    "wof:name":"B\u016bqah",
    "wof:placetype":"locality",
    "wof:population":14
},
  "geometry": {"coordinates":[45.38062,14.29882],"type":"Point"}
}