{
  "type": "Feature",
  "properties": {
    "gn:admin1_code":"25.0",
    "gn:admin2_code":"1505.0",
    "gn:asciiname":"Rifa`",
    "gn:country_code":"YE",
    "gn:dem":764,
    "gn:feature_class":"P",
    "gn:feature_code":"PPL",
    "gn:name":"Rif\u0101\u2018",
    "gn:population":0,
    "gn:timezone":"Asia/Aden",
    "iso:country":"YE",
    "name:ara_x_preferred":[
        "Rif\u0101\u2018"
    ],
    "wof:name":"Rifa`",
    "wof:placetype":"locality"
},
  "geometry": {"coordinates":[43.71773,13.70939],"type":"Point"}
}