{
  "type": "Feature",
  "properties": {
    "gn:admin1_code":"18.0",
    "gn:admin2_code":"3009.0",
    "gn:asciiname":"Dimnah",
    "gn:country_code":"YE",
    "gn:dem":1501,
    "gn:feature_class":"P",
    "gn:feature_code":"PPL",
    "gn:name":"Dimnah",
    "gn:population":0,
    "gn:timezone":"Asia/Aden",
    "iso:country":"YE",
    "wof:name":"Dimnah",
    "wof:placetype":"locality"
},
  "geometry": {"coordinates":[44.44496,13.71588],"type":"Point"}
}