{
  "type": "Feature",
  "properties": {
    "gn:country":"YE",
    "gn:fcode":"PPLX",
    "gn:population":5,
    "iso:country":"YE",
    "name:ara_x_preferred":[
        "\u0628\u064a\u062a \u0642\u0645\u0627\u0634"
    ],
    "qs:name":"Bayt Qim\u0101sh",
    "qs:photos_9r":0,
    "qs:photos_sr":0,
    "qs:pop_sr":"1",
    "wof:name":"Bayt Qim\u0101sh",
    "wof:placetype":"neighbourhood",
    "wof:population":5
},
  "geometry": {"coordinates":[43.64247,16.2272],"type":"Point"}
}