{
  "type": "Feature",
  "properties": {
    "gn:admin1_code":"20.0",
    "gn:admin2_code":"1414.0",
    "gn:asciiname":"Nawbat `Isa",
    "gn:country_code":"YE",
    "gn:dem":2117,
    "gn:feature_class":"P",
    "gn:feature_code":"PPL",
    "gn:name":"Nawbat \u2018\u012as\u00e1",
    "gn:population":0,
    "gn:timezone":"Asia/Aden",
    "iso:country":"YE",
    "name:und_x_variant":[
        "Nawbat \u2018\u012as\u00e1"
    ],
    "wof:name":"Nawbat `Isa",
    "wof:placetype":"locality"
},
  "geometry": {"coordinates":[44.87413,14.44037],"type":"Point"}
}