{
  "type": "Feature",
  "properties": {
    "gn:country":"YE",
    "gn:fcode":"PPL",
    "gn:population":3,
    "iso:country":"YE",
    "name:ara_x_preferred":[
        "\u0627\u0644\u062d\u0646\u0628\u0629"
    ],
    "name:eng_x_preferred":[
        "Al Hanibah"
    ],
    "name:eng_x_variant":[
        "Gh\u0101rib at Tuw\u0101b"
    ],
    "qs:name":"Al \u1e28anibah",
    "qs:photos_9r":0,
    "qs:photos_sr":0,
    "qs:pop_sr":"1",
    "wof:name":"Al \u1e28anibah",
    "wof:placetype":"locality",
    "wof:population":3
},
  "geometry": {"coordinates":[43.27127,17.257],"type":"Point"}
}