{
  "type": "Feature",
  "properties": {
    "gn:country":"YE",
    "gn:fcode":"PPL",
    "gn:pop":8,
    "iso:country":"YE",
    "name:ara_x_preferred":[
        "Sh\u0101\u0163i\u2019 \u2018Akk\u0101sh"
    ],
    "name:ara_x_variant":[
        "\u0634\u0627\u0637\u0626 \u0639\u0643\u0627\u0634"
    ],
    "name:eng_x_preferred":[
        "Shati 'Akkash"
    ],
    "qs:name":"Sh\u0101\u0163i\u2019 \u2018Akk\u0101sh",
    "qs:photos_9r":0,
    "qs:photos_sr":0,
    "qs:pop_sr":"1",
    "wof:name":"Sh\u0101\u0163i\u2019 \u2018Akk\u0101sh",
    "wof:placetype":"locality",
    "wof:population":8
},
  "geometry": {"coordinates":[43.32004,16.35277],"type":"Point"}
}