{
  "type": "Feature",
  "properties": {
    "gn:admin1_code":"22.0",
    "gn:admin2_code":"1720.0",
    "gn:asciiname":"Al Mashab",
    "gn:country_code":"YE",
    "gn:dem":1109,
    "gn:feature_class":"P",
    "gn:feature_code":"PPL",
    "gn:name":"Al Mas\u1e29ab",
    "gn:population":0,
    "gn:timezone":"Asia/Aden",
    "iso:country":"YE",
    "name:und_x_variant":[
        "Al Mas\u1e29ab"
    ],
    "wof:name":"Al Mashab",
    "wof:placetype":"locality"
},
  "geometry": {"coordinates":[43.54351,15.70461],"type":"Point"}
}