{
  "type": "Feature",
  "properties": {
    "gn:admin1_code":"15.0",
    "gn:admin2_code":"2203.0",
    "gn:asciiname":"Al Quway'ah",
    "gn:country_code":"YE",
    "gn:dem":1599,
    "gn:feature_class":"P",
    "gn:feature_code":"PPL",
    "gn:name":"Al Quway\u2018ah",
    "gn:population":0,
    "gn:timezone":"Asia/Aden",
    "iso:country":"YE",
    "name:ara_x_preferred":[
        "\u0627\u0644\u0642\u0648\u064a\u0639\u0629"
    ],
    "name:und_x_variant":[
        "Al Quway\u2018ah"
    ],
    "wof:name":"Al Quway'ah",
    "wof:placetype":"locality"
},
  "geometry": {"coordinates":[43.27642,17.18226],"type":"Point"}
}