{
  "type": "Feature",
  "properties": {
    "gn:country":"YE",
    "gn:fcode":"PPL",
    "gn:population":3,
    "iso:country":"YE",
    "name:ara_x_preferred":[
        "\u0627\u0644\u0645\u0642\u0628\u0635"
    ],
    "qs:name":"Al Maqba\u015f",
    "qs:photos_9r":0,
    "qs:photos_sr":0,
    "qs:pop_sr":"1",
    "wof:name":"Al Maqba\u015f",
    "wof:placetype":"locality",
    "wof:population":3
},
  "geometry": {"coordinates":[43.30515,16.64984],"type":"Point"}
}