{
  "type": "Feature",
  "properties": {
    "gn:admin1_code":"15.0",
    "gn:admin2_code":"2208.0",
    "gn:asciiname":"Ahwar",
    "gn:country_code":"YE",
    "gn:dem":1961,
    "gn:feature_class":"P",
    "gn:feature_code":"PPL",
    "gn:name":"A\u1e29war",
    "gn:population":0,
    "gn:timezone":"Asia/Aden",
    "iso:country":"YE",
    "name:ara_x_preferred":[
        "\u0623\u062d\u0648\u0631"
    ],
    "name:ceb_x_preferred":[
        "A\u1e29war"
    ],
    "name:fas_x_preferred":[
        "\u0627\u062d\u0648\u0631"
    ],
    "name:hrv_x_preferred":[
        "Ahwar"
    ],
    "name:ita_x_preferred":[
        "Ahwar"
    ],
    "name:nno_x_preferred":[
        "Ahwar"
    ],
    "name:rus_x_preferred":[
        "\u0410\u0445\u0432\u0430\u0440"
    ],
    "name:swe_x_preferred":[
        "Ahwar"
    ],
    "name:ukr_x_preferred":[
        "\u0410\u0445\u0432\u0430\u0440"
    ],
    "name:und_x_variant":[
        "A\u1e29war"
    ],
    "wof:name":"Ahwar",
    "wof:placetype":"locality"
},
  "geometry": {"coordinates":[43.60651,16.68678],"type":"Point"}
}