{
  "type": "Feature",
  "properties": {
    "gn:admin1_code":"25.0",
    "gn:admin2_code":"1511.0",
    "gn:asciiname":"Firayzimah",
    "gn:country_code":"YE",
    "gn:dem":1256,
    "gn:feature_class":"P",
    "gn:feature_code":"PPL",
    "gn:name":"Firayzimah",
    "gn:population":0,
    "gn:timezone":"Asia/Aden",
    "iso:country":"YE",
    "name:ara_x_preferred":[
        "\u0641\u0631\u064a\u0632\u0645"
    ],
    "name:und_x_variant":[
        "Furayzimah",
        "Furayzim"
    ],
    "wof:name":"Firayzimah",
    "wof:placetype":"locality"
},
  "geometry": {"coordinates":[43.95907,13.54021],"type":"Point"}
}