{
  "type": "Feature",
  "properties": {
    "gn:admin1_code":"24.0",
    "gn:admin2_code":"2503.0",
    "gn:asciiname":"Al Jurbah",
    "gn:country_code":"YE",
    "gn:dem":2260,
    "gn:feature_class":"P",
    "gn:feature_code":"PPLA2",
    "gn:name":"Al Jurbah",
    "gn:population":0,
    "gn:timezone":"Asia/Aden",
    "iso:country":"YE",
    "name:ara_x_preferred":[
        "\u0627\u0644\u062c\u0631\u0628\u0629"
    ],
    "name:und_x_variant":[
        "Jurba",
        "Al Jurbah"
    ],
    "wof:name":"Al Jurbah",
    "wof:placetype":"locality"
},
  "geometry": {"coordinates":[45.15894,13.7915],"type":"Point"}
}