{
  "type": "Feature",
  "properties": {
    "gn:admin1_code":"15.0",
    "gn:admin2_code":"2209.0",
    "gn:asciiname":"Ash Sharaf",
    "gn:country_code":"YE",
    "gn:dem":1793,
    "gn:feature_class":"P",
    "gn:feature_code":"PPL",
    "gn:name":"Ash Sharaf",
    "gn:population":0,
    "gn:timezone":"Asia/Aden",
    "iso:country":"YE",
    "wof:name":"Ash Sharaf",
    "wof:placetype":"locality"
},
  "geometry": {"coordinates":[43.34997,16.87052000000001],"type":"Point"}
}