{
  "type": "Feature",
  "properties": {
    "gn:admin1_code":"14.0",
    "gn:admin2_code":"2603.0",
    "gn:asciiname":"Al Manamah",
    "gn:country_code":"YE",
    "gn:dem":1413,
    "gn:feature_class":"P",
    "gn:feature_code":"PPL",
    "gn:name":"Al Man\u0101mah",
    "gn:population":0,
    "gn:timezone":"Asia/Aden",
    "iso:country":"YE",
    "name:ara_x_preferred":[
        "\u0627\u0644\u0645\u0646\u0627\u0645\u0629"
    ],
    "name:und_x_variant":[
        "Al Man\u0101mah"
    ],
    "wof:name":"Al Manamah",
    "wof:placetype":"locality"
},
  "geometry": {"coordinates":[44.87694000000001,15.58944],"type":"Point"}
}