{
  "type": "Feature",
  "properties": {
    "gn:admin1_code":"25.0",
    "gn:admin2_code":"1504.0",
    "gn:asciiname":"Hasid",
    "gn:country_code":"YE",
    "gn:dem":809,
    "gn:feature_class":"P",
    "gn:feature_code":"PPL",
    "gn:name":"\u1e28as\u012bd",
    "gn:population":0,
    "gn:timezone":"Asia/Aden",
    "iso:country":"YE",
    "name:und_x_variant":[
        "\u1e28as\u012bd"
    ],
    "wof:name":"Hasid",
    "wof:placetype":"locality"
},
  "geometry": {"coordinates":[43.75453,13.87946],"type":"Point"}
}