{
  "type": "Feature",
  "properties": {
    "gn:admin1_code":"8.0",
    "gn:admin2_code":"1810.0",
    "gn:asciiname":"As Sayyid as Sulayman",
    "gn:country_code":"YE",
    "gn:dem":406,
    "gn:feature_class":"P",
    "gn:feature_code":"PPL",
    "gn:name":"As Sayyid as Sulaym\u0101n",
    "gn:population":0,
    "gn:timezone":"Asia/Aden",
    "iso:country":"YE",
    "name:ara_x_preferred":[
        "\u0627\u0644\u0633\u064a\u062f \u0633\u0644\u064a\u0645\u0627\u0646"
    ],
    "name:und_x_variant":[
        "As Sayyid as Sulaym\u0101n"
    ],
    "wof:name":"As Sayyid as Sulayman",
    "wof:placetype":"locality"
},
  "geometry": {"coordinates":[43.46544,15.00735],"type":"Point"}
}