{
  "type": "Feature",
  "properties": {
    "gn:admin1_code":"23.0",
    "gn:admin2_code":"1101.0",
    "gn:asciiname":"Majhat",
    "gn:country_code":"YE",
    "gn:dem":1535,
    "gn:feature_class":"P",
    "gn:feature_code":"PPL",
    "gn:name":"Maj\u1e29at",
    "gn:population":0,
    "gn:timezone":"Asia/Aden",
    "iso:country":"YE",
    "name:ara_x_preferred":[
        "\u0645\u062c\u062d\u062a"
    ],
    "name:und_x_variant":[
        "Maj\u1e29at"
    ],
    "wof:name":"Majhat",
    "wof:placetype":"locality"
},
  "geometry": {"coordinates":[44.1495,14.36787],"type":"Point"}
}