{
  "type": "Feature",
  "properties": {
    "gn:admin1_code":"8.0",
    "gn:admin2_code":"1801.0",
    "gn:asciiname":"Kidf ad Da`ayshi",
    "gn:country_code":"YE",
    "gn:dem":137,
    "gn:feature_class":"P",
    "gn:feature_code":"PPL",
    "gn:name":"Kidf ad Da\u2018aysh\u012b",
    "gn:population":0,
    "gn:timezone":"Asia/Aden",
    "iso:country":"YE",
    "name:und_x_variant":[
        "Kadaf ad Da\u2018\u012bsh",
        "Kidaf ad Da\u2018\u012bsh",
        "Kidf ad Da\u2018aysh\u012b",
        "Kidf ad Da\u2018\u012bsh"
    ],
    "wof:name":"Kidf ad Da`ayshi",
    "wof:placetype":"locality"
},
  "geometry": {"coordinates":[43.15812,15.75583],"type":"Point"}
}