{
  "type": "Feature",
  "properties": {
    "gn:admin1_code":"14.0",
    "gn:admin2_code":"2614.0",
    "gn:asciiname":"Al `Utbah",
    "gn:country_code":"YE",
    "gn:dem":1962,
    "gn:feature_class":"P",
    "gn:feature_code":"PPL",
    "gn:name":"Al \u2018U\u0163bah",
    "gn:population":0,
    "gn:timezone":"Asia/Aden",
    "iso:country":"YE",
    "name:ara_x_preferred":[
        "\u0627\u0644\u0639\u0637\u0628\u0629"
    ],
    "name:und_x_variant":[
        "Al \u2018U\u0163bah al \u1e28adad",
        "Al \u2018U\u0163bah"
    ],
    "wof:name":"Al `Utbah",
    "wof:placetype":"locality"
},
  "geometry": {"coordinates":[45.1744,15.01205],"type":"Point"}
}