{
  "type": "Feature",
  "properties": {
    "gn:admin1_code":"16.0",
    "gn:admin2_code":"2316.0",
    "gn:asciiname":"Mahall al Lima`",
    "gn:country_code":"YE",
    "gn:dem":2372,
    "gn:feature_class":"P",
    "gn:feature_code":"PPL",
    "gn:name":"Ma\u1e29all al Lim\u0101\u2018",
    "gn:population":0,
    "gn:timezone":"Asia/Aden",
    "iso:country":"YE",
    "name:und_x_variant":[
        "Ma\u1e29all al Lim\u0101\u2018"
    ],
    "wof:name":"Mahall al Lima`",
    "wof:placetype":"locality"
},
  "geometry": {"coordinates":[44.40281,15.15698],"type":"Point"}
}