{
  "type": "Feature",
  "properties": {
    "gn:country":"YE",
    "gn:fcode":"PPL",
    "gn:pop":4,
    "iso:country":"YE",
    "name:ara_x_preferred":[
        "\u0628\u064a\u062a \u0627\u0644\u0639\u0645\u0631\u064a"
    ],
    "name:eng_x_preferred":[
        "Bayt Al 'Umri"
    ],
    "name:unk_x_variant":[
        "Bayt al \u2018Umar\u012b"
    ],
    "qs:name":"Bayt al \u2018Umr\u012b",
    "qs:photos_9r":0,
    "qs:photos_sr":0,
    "qs:pop_sr":"1",
    "wof:name":"Bayt al \u2018Umr\u012b",
    "wof:placetype":"locality",
    "wof:population":4
},
  "geometry": {"coordinates":[43.37666,16.19619],"type":"Point"}
}