{
  "type": "Feature",
  "properties": {
    "gn:country":"YE",
    "gn:fcode":"PPL",
    "gn:population":8,
    "iso:country":"YE",
    "name:ara_x_preferred":[
        "Kh\u0101lif"
    ],
    "name:ara_x_variant":[
        "\u062e\u0627\u0644\u0641"
    ],
    "name:eng_x_preferred":[
        "Khalif"
    ],
    "qs:name":"Kh\u0101lif",
    "qs:photos_9r":0,
    "qs:photos_sr":0,
    "qs:pop_sr":"1",
    "wof:name":"Kh\u0101lif",
    "wof:placetype":"locality",
    "wof:population":8
},
  "geometry": {"coordinates":[45.27648,14.04387],"type":"Point"}
}