{
  "type": "Feature",
  "properties": {
    "gn:country":"YE",
    "gn:fcode":"PPL",
    "gn:pop":4,
    "iso:country":"YE",
    "name:ara_x_preferred":[
        "\u0627\u0644\u0645\u062d\u062b\u0628\u0649"
    ],
    "name:eng_x_preferred":[
        "Al Mahthabi"
    ],
    "qs:name":"Al Ma\u1e29thab\u012b",
    "qs:photos_9r":0,
    "qs:photos_sr":0,
    "qs:pop_sr":"1",
    "wof:name":"Al Ma\u1e29thab\u012b",
    "wof:placetype":"locality",
    "wof:population":4
},
  "geometry": {"coordinates":[43.32628,16.6552],"type":"Point"}
}