{
  "type": "Feature",
  "properties": {
    "gn:admin1_code":"22.0",
    "gn:admin2_code":"1724.0",
    "gn:asciiname":"Bani Kuhayl",
    "gn:country_code":"YE",
    "gn:dem":415,
    "gn:feature_class":"P",
    "gn:feature_code":"PPL",
    "gn:name":"Ban\u012b Ku\u1e29ayl",
    "gn:population":0,
    "gn:timezone":"Asia/Aden",
    "iso:country":"YE",
    "name:und_x_variant":[
        "Ban\u012b Ku\u1e29ayl"
    ],
    "wof:name":"Bani Kuhayl",
    "wof:placetype":"locality"
},
  "geometry": {"coordinates":[43.42375,15.66703],"type":"Point"}
}