{
  "type": "Feature",
  "properties": {
    "gn:country":"YE",
    "gn:fcode":"PPL",
    "gn:population":1,
    "iso:country":"YE",
    "name:ara_x_preferred":[
        "\u0627\u0644\u0641\u0642\u064a\u0648\u0629"
    ],
    "name:eng_x_preferred":[
        "Al Fuqaywah"
    ],
    "name:eng_x_variant":[
        "Mat\u00e1"
    ],
    "qs:name":"Al Fuqaywah",
    "qs:photos_9r":0,
    "qs:photos_sr":0,
    "qs:pop_sr":"1",
    "wof:name":"Al Fuqaywah",
    "wof:placetype":"locality",
    "wof:population":1
},
  "geometry": {"coordinates":[43.95882,13.11978],"type":"Point"}
}