{
  "type": "Feature",
  "properties": {
    "gn:admin1_code":"8.0",
    "gn:admin2_code":"1825.0",
    "gn:asciiname":"Al Mushay`il",
    "gn:country_code":"YE",
    "gn:dem":283,
    "gn:feature_class":"P",
    "gn:feature_code":"PPL",
    "gn:name":"Al Mushay\u2018il",
    "gn:population":0,
    "gn:timezone":"Asia/Aden",
    "iso:country":"YE",
    "name:und_x_variant":[
        "Al Mushay\u2018il"
    ],
    "wof:name":"Al Mushay`il",
    "wof:placetype":"locality"
},
  "geometry": {"coordinates":[43.49639000000001,14.16351],"type":"Point"}
}