{
  "type": "Feature",
  "properties": {
    "gn:country":"YE",
    "gn:fcode":"PPL",
    "gn:pop":1,
    "iso:country":"YE",
    "name:ara_x_preferred":[
        "\u062d\u064a\u0627\u0641 \u0627\u0644\u062d\u0628\u064a\u0644"
    ],
    "name:eng_x_preferred":[
        "Hiyaf Al Habil"
    ],
    "qs:name":"\u1e28iy\u0101f al \u1e28ab\u012bl",
    "qs:photos_9r":0,
    "qs:photos_sr":0,
    "qs:pop_sr":"1",
    "wof:name":"\u1e28iy\u0101f al \u1e28ab\u012bl",
    "wof:placetype":"locality",
    "wof:population":1
},
  "geometry": {"coordinates":[43.26644,17.10765],"type":"Point"}
}