{
  "type": "Feature",
  "properties": {
    "gn:admin1_code":"8.0",
    "gn:admin2_code":"1801.0",
    "gn:asciiname":"Dayr al Muzayyin",
    "gn:country_code":"YE",
    "gn:dem":118,
    "gn:feature_class":"P",
    "gn:feature_code":"PPL",
    "gn:name":"Dayr al Muzayyin",
    "gn:population":0,
    "gn:timezone":"Asia/Aden",
    "iso:country":"YE",
    "wof:name":"Dayr al Muzayyin",
    "wof:placetype":"locality"
},
  "geometry": {"coordinates":[43.11435,15.84116],"type":"Point"}
}