{
  "type": "Feature",
  "properties": {
    "gn:admin1_code":"10.0",
    "gn:admin2_code":"2703.0",
    "gn:asciiname":"`Alhan",
    "gn:country_code":"YE",
    "gn:dem":2198,
    "gn:feature_class":"P",
    "gn:feature_code":"PPL",
    "gn:name":"\u2018Alh\u0101n",
    "gn:population":0,
    "gn:timezone":"Asia/Aden",
    "iso:country":"YE",
    "name:ara_x_preferred":[
        "\u2018Alh\u0101n"
    ],
    "wof:name":"`Alhan",
    "wof:placetype":"locality"
},
  "geometry": {"coordinates":[43.69686,15.47131],"type":"Point"}
}