{
  "type": "Feature",
  "properties": {
    "gn:country":"YE",
    "gn:fcode":"PPL",
    "gn:population":5,
    "iso:country":"YE",
    "name:ara_x_preferred":[
        "\u0634\u0639\u0628 \u0627\u0644\u062d\u064a\u0629"
    ],
    "name:eng_x_preferred":[
        "Sha'b Al Hiyah"
    ],
    "name:eng_x_variant":[
        "Adh Dhir\u0101\u2018"
    ],
    "qs:name":"Sha\u2018b al \u1e28\u012byah",
    "qs:photos_9r":0,
    "qs:photos_sr":0,
    "qs:pop_sr":"1",
    "wof:name":"Sha\u2018b al \u1e28\u012byah",
    "wof:placetype":"locality",
    "wof:population":5
},
  "geometry": {"coordinates":[43.40571,16.14538],"type":"Point"}
}