{
  "type": "Feature",
  "properties": {
    "gn:admin1_code":"8.0",
    "gn:admin2_code":"1802.0",
    "gn:asciiname":"Al Jubayriyah",
    "gn:country_code":"YE",
    "gn:dem":76,
    "gn:feature_class":"P",
    "gn:feature_code":"PPL",
    "gn:name":"Al Jubayr\u012byah",
    "gn:population":0,
    "gn:timezone":"Asia/Aden",
    "iso:country":"YE",
    "name:und_x_variant":[
        "Al Jubayr\u012byah",
        "Dayr Jubayr\u012byah"
    ],
    "wof:name":"Al Jubayriyah",
    "wof:placetype":"locality"
},
  "geometry": {"coordinates":[43.03714,15.59287],"type":"Point"}
}