{
  "type": "Feature",
  "properties": {
    "gn:admin1_code":"8.0",
    "gn:admin2_code":"1802.0",
    "gn:asciiname":"Az Zawiyah",
    "gn:country_code":"YE",
    "gn:dem":51,
    "gn:feature_class":"P",
    "gn:feature_code":"PPL",
    "gn:name":"Az Z\u0101wiyah",
    "gn:population":0,
    "gn:timezone":"Asia/Aden",
    "iso:country":"YE",
    "name:heb_x_preferred":[
        "\u05d0\u05d6 \u05d6\u05d0\u05d5\u05d5\u05d9\u05d4"
    ],
    "name:und_x_variant":[
        "Az Z\u0101wiyah"
    ],
    "wof:name":"Az Zawiyah",
    "wof:placetype":"locality"
},
  "geometry": {"coordinates":[42.94876,15.57877],"type":"Point"}
}