{
  "type": "Feature",
  "properties": {
    "gn:admin1_code":"23.0",
    "gn:admin2_code":"1110.0",
    "gn:asciiname":"Ath Thulth",
    "gn:country_code":"YE",
    "gn:dem":1460,
    "gn:feature_class":"P",
    "gn:feature_code":"PPL",
    "gn:name":"Ath Thulth",
    "gn:population":0,
    "gn:timezone":"Asia/Aden",
    "iso:country":"YE",
    "wof:name":"Ath Thulth",
    "wof:placetype":"locality"
},
  "geometry": {"coordinates":[43.81001,13.9054],"type":"Point"}
}