{
  "type": "Feature",
  "properties": {
    "gn:admin1_code":"22.0",
    "gn:admin2_code":"1730.0",
    "gn:asciiname":"Al Hayjah",
    "gn:country_code":"YE",
    "gn:dem":1064,
    "gn:feature_class":"P",
    "gn:feature_code":"PPL",
    "gn:name":"Al Hayjah",
    "gn:population":0,
    "gn:timezone":"Asia/Aden",
    "iso:country":"YE",
    "name:ara_x_preferred":[
        "\u0627\u0644\u0647\u064a\u062c\u0629"
    ],
    "wof:name":"Al Hayjah",
    "wof:placetype":"locality"
},
  "geometry": {"coordinates":[43.38808,16.34561],"type":"Point"}
}