{
  "type": "Feature",
  "properties": {
    "gn:country":"YE",
    "gn:fcode":"PPL",
    "gn:pop":5,
    "iso:country":"YE",
    "name:ara_x_preferred":[
        "Si\u1e29\u0101r"
    ],
    "name:ara_x_variant":[
        "\u0633\u062d\u0627\u0631"
    ],
    "name:eng_x_preferred":[
        "Sihar"
    ],
    "qs:name":"Si\u1e29\u0101r",
    "qs:photos_9r":0,
    "qs:photos_sr":0,
    "qs:pop_sr":"1",
    "wof:name":"Si\u1e29\u0101r",
    "wof:placetype":"locality",
    "wof:population":5
},
  "geometry": {"coordinates":[43.36255,16.76181],"type":"Point"}
}