{
  "type": "Feature",
  "properties": {
    "gn:country":"YE",
    "gn:fcode":"PPLF",
    "gn:population":6,
    "iso:country":"YE",
    "name:ara_x_preferred":[
        "\u0627\u0644\u062f\u0648\u0627\u064a\u0631"
    ],
    "qs:name":"Ad Daw\u0101yir",
    "qs:photos_9r":0,
    "qs:photos_sr":0,
    "qs:pop_sr":"1",
    "wof:name":"Ad Daw\u0101yir",
    "wof:placetype":"locality",
    "wof:population":6
},
  "geometry": {"coordinates":[43.52837,16.85716],"type":"Point"}
}