{
  "type": "Feature",
  "properties": {
    "gn:admin1_code":"10.0",
    "gn:admin2_code":"2701.0",
    "gn:asciiname":"Al Ma` yan",
    "gn:country_code":"YE",
    "gn:dem":2299,
    "gn:feature_class":"P",
    "gn:feature_code":"PPL",
    "gn:name":"Al Ma\u2018 yan",
    "gn:population":0,
    "gn:timezone":"Asia/Aden",
    "iso:country":"YE",
    "name:und_x_variant":[
        "Al Ma\u2018 yan"
    ],
    "wof:name":"Al Ma` yan",
    "wof:placetype":"locality"
},
  "geometry": {"coordinates":[43.89021,15.45997],"type":"Point"}
}