{
  "type": "Feature",
  "properties": {
    "gn:admin1_code":"18.0",
    "gn:admin2_code":"3001.0",
    "gn:asciiname":"Jabubah",
    "gn:cc2":"YE",
    "gn:country_code":"YE",
    "gn:dem":1953,
    "gn:feature_class":"P",
    "gn:feature_code":"PPL",
    "gn:name":"Jab\u016bbah",
    "gn:population":0,
    "gn:timezone":"Asia/Aden",
    "iso:country":"YE",
    "name:und_x_variant":[
        "Jabuba",
        "Jab\u016bbah"
    ],
    "wof:name":"Jabubah",
    "wof:placetype":"locality"
},
  "geometry": {"coordinates":[44.93333,14.03333],"type":"Point"}
}