{
  "type": "Feature",
  "properties": {
    "gn:admin1_code":"4.0",
    "gn:admin2_code":"1907.0",
    "gn:asciiname":"Bayt Qishn",
    "gn:cc2":"YE",
    "gn:country_code":"YE",
    "gn:dem":712,
    "gn:feature_class":"P",
    "gn:feature_code":"PPL",
    "gn:name":"Bayt Qishn",
    "gn:population":0,
    "gn:timezone":"Asia/Aden",
    "iso:country":"YE",
    "name:und_x_variant":[
        "Bit \u2018Ishin",
        "Bayt Qishin",
        "Bait Qishin",
        "Bayt Qishn"
    ],
    "wof:name":"Bayt Qishn",
    "wof:placetype":"locality"
},
  "geometry": {"coordinates":[48.27222,15.86333],"type":"Point"}
}