{
  "type": "Feature",
  "properties": {
    "gn:country":"YE",
    "gn:fcode":"PPL",
    "gn:population":4,
    "iso:country":"YE",
    "name:ara_x_preferred":[
        "\u0627\u0644\u0647\u0636\u0628\u0629"
    ],
    "qs:name":"Al Ha\u1e11bah",
    "qs:photos_9r":0,
    "qs:photos_sr":0,
    "qs:pop_sr":"1",
    "wof:name":"Al Ha\u1e11bah",
    "wof:placetype":"locality",
    "wof:population":4
},
  "geometry": {"coordinates":[45.45484,14.10836],"type":"Point"}
}