{
  "type": "Feature",
  "properties": {
    "gn:admin1_code":"16.0",
    "gn:admin2_code":"2303.0",
    "gn:asciiname":"Al Malahi",
    "gn:country_code":"YE",
    "gn:dem":2063,
    "gn:feature_class":"P",
    "gn:feature_code":"PPL",
    "gn:name":"Al Mal\u0101\u1e29\u012b",
    "gn:population":0,
    "gn:timezone":"Asia/Aden",
    "iso:country":"YE",
    "name:ara_x_preferred":[
        "\u0627\u0644\u0645\u0644\u0627\u062d\u064a"
    ],
    "name:und_x_variant":[
        "Al Mal\u0101\u1e29\u012b"
    ],
    "wof:name":"Al Malahi",
    "wof:placetype":"locality"
},
  "geometry": {"coordinates":[44.45578,15.65622],"type":"Point"}
}