{
  "type": "Feature",
  "properties": {
    "gn:admin1_code":"22.0",
    "gn:admin2_code":"1724.0",
    "gn:asciiname":"Al Jar",
    "gn:country_code":"YE",
    "gn:dem":254,
    "gn:feature_class":"P",
    "gn:feature_code":"PPL",
    "gn:name":"Al J\u0101r",
    "gn:population":0,
    "gn:timezone":"Asia/Aden",
    "iso:country":"YE",
    "name:ara_x_preferred":[
        "Al J\u0101r"
    ],
    "wof:name":"Al Jar",
    "wof:placetype":"locality"
},
  "geometry": {"coordinates":[43.29825,15.651],"type":"Point"}
}