{
  "type": "Feature",
  "properties": {
    "gn:country":"YE",
    "gn:fcode":"PPL",
    "gn:pop":21,
    "iso:country":"YE",
    "name:ara_x_preferred":[
        "\u062e\u0631\u0627\u0628\u0629 \u0627\u0644\u0631\u064a\u0648\u062f"
    ],
    "name:eng_x_preferred":[
        "Kharabat Ar RiyUd"
    ],
    "qs:name":"Khar\u0101bat ar Riy\u016bd",
    "qs:photos_9r":0,
    "qs:photos_sr":0,
    "qs:pop_sr":"1",
    "wof:name":"Khar\u0101bat ar Riy\u016bd",
    "wof:placetype":"locality",
    "wof:population":21
},
  "geometry": {"coordinates":[45.11221,14.21383],"type":"Point"}
}