{
  "type": "Feature",
  "properties": {
    "gn:admin1_code":"25.0",
    "gn:admin2_code":"1509.0",
    "gn:asciiname":"`Asab",
    "gn:country_code":"YE",
    "gn:dem":1426,
    "gn:feature_class":"P",
    "gn:feature_code":"PPL",
    "gn:name":"\u2018As\u0101b",
    "gn:population":0,
    "gn:timezone":"Asia/Aden",
    "iso:country":"YE",
    "name:ara_x_preferred":[
        "\u2018As\u0101b"
    ],
    "wof:name":"`Asab",
    "wof:placetype":"locality"
},
  "geometry": {"coordinates":[43.93333,13.53333],"type":"Point"}
}