{
  "type": "Feature",
  "properties": {
    "gn:admin1_code":"23.0",
    "gn:admin2_code":"1101.0",
    "gn:asciiname":"'Adan Rakhmin",
    "gn:country_code":"YE",
    "gn:dem":1661,
    "gn:feature_class":"P",
    "gn:feature_code":"PPL",
    "gn:name":"\u2018Adan Rakhm\u012bn",
    "gn:population":0,
    "gn:timezone":"Asia/Aden",
    "iso:country":"YE",
    "name:ara_x_preferred":[
        "\u0639\u062f\u0646 \u0631\u062e\u0645\u064a\u0646"
    ],
    "name:und_x_variant":[
        "\u2018Adan Rakhm\u012bn"
    ],
    "wof:name":"'Adan Rakhmin",
    "wof:placetype":"locality"
},
  "geometry": {"coordinates":[44.14722,14.31743],"type":"Point"}
}