{
  "type": "Feature",
  "properties": {
    "gn:admin1_code":"8.0",
    "gn:admin2_code":"1816.0",
    "gn:asciiname":"Buyut al Kurush",
    "gn:country_code":"YE",
    "gn:dem":119,
    "gn:feature_class":"P",
    "gn:feature_code":"PPL",
    "gn:name":"Buy\u016bt al Kur\u016bsh",
    "gn:population":0,
    "gn:timezone":"Asia/Aden",
    "iso:country":"YE",
    "name:ara_x_preferred":[
        "\u0628\u064a\u0648\u062a \u0627\u0644\u0643\u0631\u0648\u0634"
    ],
    "name:und_x_variant":[
        "Buy\u016bt al Kur\u016bsh"
    ],
    "wof:name":"Buyut al Kurush",
    "wof:placetype":"locality"
},
  "geometry": {"coordinates":[43.26513,14.71453],"type":"Point"}
}