{
  "type": "Feature",
  "properties": {
    "gn:admin1_code":"11.0",
    "gn:admin2_code":"2010.0",
    "gn:asciiname":"Al Hijrah",
    "gn:country_code":"YE",
    "gn:dem":2229,
    "gn:feature_class":"P",
    "gn:feature_code":"PPL",
    "gn:name":"Al Hijrah",
    "gn:population":0,
    "gn:timezone":"Asia/Aden",
    "iso:country":"YE",
    "wof:name":"Al Hijrah",
    "wof:placetype":"locality"
},
  "geometry": {"coordinates":[44.20147,14.56564],"type":"Point"}
}