{
  "type": "Feature",
  "properties": {
    "gn:gn_country":"YE",
    "gn:gn_fcode":"PPL",
    "gn:gn_pop":2,
    "gn:population":2,
    "iso:country":"YE",
    "name:ara_x_preferred":[
        "\u0639\u0634\u0629 \u0627\u0644\u0633\u0648\u062f\u0646"
    ],
    "name:eng_x_preferred":[
        "Ashshat As Sawdin"
    ],
    "qs_pg:aaroncc":"YE",
    "qs_pg:gn_country":"YE",
    "qs_pg:gn_fcode":"PPL",
    "qs_pg:gn_pop":2,
    "qs_pg:name":"\u2018Ashshat as Sawdin",
    "qs_pg:photos_9r":0,
    "qs_pg:photos_sr":0,
    "qs_pg:pop_sr":1,
    "qs_pg:qs_pg_placetype":"locality",
    "wof:name":"\u2018Ashshat as Sawdin",
    "wof:placetype":"locality",
    "wof:population":2
},
  "geometry": {"coordinates":[43.285,16.58295],"type":"Point"}
}