{
  "type": "Feature",
  "properties": {
    "gn:admin1_code":"23.0",
    "gn:admin2_code":"1101.0",
    "gn:asciiname":"Sayhan",
    "gn:country_code":"YE",
    "gn:dem":1552,
    "gn:feature_class":"P",
    "gn:feature_code":"PPL",
    "gn:name":"\u015eay\u1e29\u0101n",
    "gn:population":0,
    "gn:timezone":"Asia/Aden",
    "iso:country":"YE",
    "name:nno_x_preferred":[
        "Sayhan"
    ],
    "name:und_x_variant":[
        "\u015eay\u1e29\u0101n"
    ],
    "wof:name":"Sayhan",
    "wof:placetype":"locality"
},
  "geometry": {"coordinates":[44.14896,14.33528],"type":"Point"}
}