{
  "type": "Feature",
  "properties": {
    "gn:country":"YE",
    "gn:fcode":"PPL",
    "gn:pop":1,
    "iso:country":"YE",
    "name:ara_x_preferred":[
        "\u0627\u0644\u0645\u062d\u0631\u0633"
    ],
    "qs:name":"Al Ma\u1e29ras",
    "qs:photos_9r":0,
    "qs:photos_sr":0,
    "qs:pop_sr":"1",
    "wof:name":"Al Ma\u1e29ras",
    "wof:placetype":"locality",
    "wof:population":1
},
  "geometry": {"coordinates":[45.0618,14.99878],"type":"Point"}
}