{
  "type": "Feature",
  "properties": {
    "gn:admin1_code":"22.0",
    "gn:admin2_code":"1724.0",
    "gn:asciiname":"Mahall Bani Husayn",
    "gn:country_code":"YE",
    "gn:dem":359,
    "gn:feature_class":"P",
    "gn:feature_code":"PPL",
    "gn:name":"Ma\u1e29all Ban\u012b \u1e28usayn",
    "gn:population":0,
    "gn:timezone":"Asia/Aden",
    "iso:country":"YE",
    "name:und_x_variant":[
        "Ma\u1e29all Ban\u012b \u1e28usayn"
    ],
    "wof:name":"Mahall Bani Husayn",
    "wof:placetype":"locality"
},
  "geometry": {"coordinates":[43.34584,15.55941],"type":"Point"}
}