{
  "type": "Feature",
  "properties": {
    "gn:admin1_code":"23.0",
    "gn:admin2_code":"1108.0",
    "gn:asciiname":"Qaryat Marwahah",
    "gn:country_code":"YE",
    "gn:dem":2322,
    "gn:feature_class":"P",
    "gn:feature_code":"PPL",
    "gn:name":"Qaryat Marwa\u1e29ah",
    "gn:population":0,
    "gn:timezone":"Asia/Aden",
    "iso:country":"YE",
    "name:ara_x_preferred":[
        "\u0645\u0631\u0648\u062d\u0629"
    ],
    "name:und_x_variant":[
        "Qaryat Marwa\u1e29ah",
        "Marwa\u1e29ah"
    ],
    "wof:name":"Qaryat Marwahah",
    "wof:placetype":"locality"
},
  "geometry": {"coordinates":[44.05783,14.03096],"type":"Point"}
}