{
  "type": "Feature",
  "properties": {
    "gn:admin1_code":"23.0",
    "gn:admin2_code":"1112.0",
    "gn:asciiname":"Jiblah",
    "gn:country_code":"YE",
    "gn:dem":2003,
    "gn:feature_class":"P",
    "gn:feature_code":"PPLA2",
    "gn:name":"Jiblah",
    "gn:population":0,
    "gn:timezone":"Asia/Aden",
    "iso:country":"YE",
    "name:ara_x_preferred":[
        "\u062c\u0628\u0644\u0629"
    ],
    "name:und_x_variant":[
        "Jibla",
        "Jible",
        "J\u012blah",
        "Jiblah"
    ],
    "wof:name":"Jiblah",
    "wof:placetype":"locality"
},
  "geometry": {"coordinates":[44.14668,13.92162],"type":"Point"}
}