{
  "type": "Feature",
  "properties": {
    "gn:admin1_code":"19.0",
    "gn:admin2_code":"2920.0",
    "gn:asciiname":"Bayt ash Sham",
    "gn:country_code":"YE",
    "gn:dem":2234,
    "gn:feature_class":"P",
    "gn:feature_code":"PPL",
    "gn:name":"Bayt ash Sh\u0101m",
    "gn:population":0,
    "gn:timezone":"Asia/Aden",
    "iso:country":"YE",
    "name:ara_x_preferred":[
        "\u0628\u064a\u062a \u0627\u0644\u0634\u0627\u0645"
    ],
    "name:und_x_variant":[
        "Bayt ash Sh\u0101m"
    ],
    "wof:name":"Bayt ash Sham",
    "wof:placetype":"locality"
},
  "geometry": {"coordinates":[43.96347,16.1443],"type":"Point"}
}