{
  "type": "Feature",
  "properties": {
    "gn:country":"YE",
    "gn:fcode":"PPL",
    "gn:pop":9,
    "iso:country":"YE",
    "name:ara_x_preferred":[
        "\u0634\u0627\u0637\u0626 \u0627\u0644\u0628\u062f\u0639\u0640\u0640\u0629"
    ],
    "name:eng_x_preferred":[
        "Shati Al Bid'ah"
    ],
    "qs:name":"Sh\u0101\u0163i\u2019 al Bid\u2018ah",
    "qs:photos_9r":0,
    "qs:photos_sr":0,
    "qs:pop_sr":"1",
    "wof:name":"Sh\u0101\u0163i\u2019 al Bid\u2018ah",
    "wof:placetype":"locality",
    "wof:population":9
},
  "geometry": {"coordinates":[43.6459,16.47545],"type":"Point"}
}