{
  "type": "Feature",
  "properties": {
    "gn:admin1_code":"23.0",
    "gn:admin2_code":"1120.0",
    "gn:asciiname":"Az Zabbah",
    "gn:country_code":"YE",
    "gn:dem":1693,
    "gn:feature_class":"P",
    "gn:feature_code":"PPL",
    "gn:name":"Az\u0327 Z\u0327abbah",
    "gn:population":0,
    "gn:timezone":"Asia/Aden",
    "iso:country":"YE",
    "name:ara_x_preferred":[
        "\u0627\u0644\u0636\u0628\u0629"
    ],
    "name:und_x_variant":[
        "Az\u0327 Z\u0327abbah",
        "A\u1e11 \u1e10abbah"
    ],
    "wof:name":"Az Zabbah",
    "wof:placetype":"locality"
},
  "geometry": {"coordinates":[44.16977,14.01654],"type":"Point"}
}