{
  "type": "Feature",
  "properties": {
    "gn:admin1_code":"14.0",
    "gn:admin2_code":"2606.0",
    "gn:asciiname":"Al Hamam",
    "gn:country_code":"YE",
    "gn:dem":1893,
    "gn:feature_class":"P",
    "gn:feature_code":"PPL",
    "gn:name":"Al \u1e28amam",
    "gn:population":0,
    "gn:timezone":"Asia/Aden",
    "iso:country":"YE",
    "name:ara_x_preferred":[
        "\u0627\u0644\u062d\u0645\u0645"
    ],
    "name:fas_x_preferred":[
        "\u0627\u0644\u062d\u0645\u0627\u0645"
    ],
    "name:nno_x_preferred":[
        "Al Hamam"
    ],
    "name:und_x_variant":[
        "Al \u1e28amam"
    ],
    "wof:name":"Al Hamam",
    "wof:placetype":"locality"
},
  "geometry": {"coordinates":[45.07545,15.50516],"type":"Point"}
}