{
  "type": "Feature",
  "properties": {
    "gn:country":"YE",
    "gn:fcode":"PPL",
    "gn:pop":3,
    "iso:country":"YE",
    "name:ara_x_preferred":[
        "\u0628\u064a\u062a \u0627\u0644\u0637\u0648\u064a\u0644\u0629"
    ],
    "name:eng_x_preferred":[
        "Bayt At Tawilah"
    ],
    "qs:name":"Bayt a\u0163 \u0162aw\u012blah",
    "qs:photos_9r":0,
    "qs:photos_sr":0,
    "qs:pop_sr":"1",
    "wof:name":"Bayt a\u0163 \u0162aw\u012blah",
    "wof:placetype":"locality",
    "wof:population":3
},
  "geometry": {"coordinates":[43.38825,16.07579],"type":"Point"}
}