{
  "type": "Feature",
  "properties": {
    "gn:admin1_code":"22.0",
    "gn:admin2_code":"1704.0",
    "gn:asciiname":"Al Ma`sarah",
    "gn:country_code":"YE",
    "gn:dem":151,
    "gn:feature_class":"P",
    "gn:feature_code":"PPL",
    "gn:name":"Al Ma\u2018\u015farah",
    "gn:population":0,
    "gn:timezone":"Asia/Aden",
    "iso:country":"YE",
    "name:und_x_variant":[
        "Al Ma\u2018\u015farah",
        "Al Ma\u2018\u015far"
    ],
    "wof:name":"Al Ma`sarah",
    "wof:placetype":"locality"
},
  "geometry": {"coordinates":[43.18713,16.15681],"type":"Point"}
}