{
  "type": "Feature",
  "properties": {
    "gn:country":"YE",
    "gn:fcode":"PPL",
    "gn:population":13,
    "iso:country":"YE",
    "name:ara_x_preferred":[
        "\u0627\u0644\u062d\u062c\u0631\u064a\u0646"
    ],
    "name:eng_x_preferred":[
        "Al Hajirin"
    ],
    "name:eng_x_variant":[
        "Rawwah"
    ],
    "qs:name":"Al \u1e28ajir\u012bn",
    "qs:photos_9r":0,
    "qs:photos_sr":0,
    "qs:pop_sr":"1",
    "wof:name":"Al \u1e28ajir\u012bn",
    "wof:placetype":"locality",
    "wof:population":13
},
  "geometry": {"coordinates":[43.82508,16.8838],"type":"Point"}
}