{
  "type": "Feature",
  "properties": {
    "gn:admin1_code":"16.0",
    "gn:admin2_code":"2307.0",
    "gn:asciiname":"Bayt al Qaramani",
    "gn:country_code":"YE",
    "gn:dem":2774,
    "gn:feature_class":"P",
    "gn:feature_code":"PPL",
    "gn:name":"Bayt al Qaram\u0101n\u012b",
    "gn:population":0,
    "gn:timezone":"Asia/Aden",
    "iso:country":"YE",
    "name:und_x_variant":[
        "Bayt al Qaram\u0101n\u012b"
    ],
    "wof:name":"Bayt al Qaramani",
    "wof:placetype":"locality"
},
  "geometry": {"coordinates":[43.995,15.21262],"type":"Point"}
}