{
  "type": "Feature",
  "properties": {
    "gn:country":"YE",
    "gn:fcode":"PPL",
    "gn:pop":2,
    "iso:country":"YE",
    "name:ara_x_preferred":[
        "\u062d\u0628\u0637\u0627\u0621"
    ],
    "name:eng_x_preferred":[
        "Habta"
    ],
    "name:eng_x_variant":[
        "Al \u1e28urayb"
    ],
    "qs:name":"\u1e28ab\u0163\u0101\u2019",
    "qs:photos_9r":0,
    "qs:photos_sr":0,
    "qs:pop_sr":"1",
    "wof:name":"\u1e28ab\u0163\u0101\u2019",
    "wof:placetype":"locality",
    "wof:population":2
},
  "geometry": {"coordinates":[43.38162,16.37782],"type":"Point"}
}