{
  "type": "Feature",
  "properties": {
    "gn:admin1_code":"15.0",
    "gn:admin2_code":"2204.0",
    "gn:asciiname":"Al Jumaymah",
    "gn:country_code":"YE",
    "gn:dem":1436,
    "gn:feature_class":"P",
    "gn:feature_code":"PPL",
    "gn:name":"Al Jumaymah",
    "gn:population":7,
    "gn:timezone":"Asia/Aden",
    "iso:country":"YE",
    "name:ara_x_preferred":[
        "\u0627\u0644\u062c\u0645\u064a\u0645\u0629"
    ],
    "wof:name":"Al Jumaymah",
    "wof:placetype":"locality",
    "wof:population":7
},
  "geometry": {"coordinates":[43.26657,17.02273],"type":"Point"}
}