{
  "type": "Feature",
  "properties": {
    "gn:admin1_code":"19.0",
    "gn:admin2_code":"2914.0",
    "gn:asciiname":"An Nasirah",
    "gn:country_code":"YE",
    "gn:dem":2327,
    "gn:feature_class":"P",
    "gn:feature_code":"PPLA2",
    "gn:name":"An N\u0101\u015firah",
    "gn:population":0,
    "gn:timezone":"Asia/Aden",
    "iso:country":"YE",
    "name:ara_x_preferred":[
        "\u0627\u0644\u0646\u0627\u0635\u0631\u0629"
    ],
    "name:und_x_variant":[
        "An N\u0101\u015firah"
    ],
    "wof:name":"An Nasirah",
    "wof:placetype":"locality"
},
  "geometry": {"coordinates":[43.80902,15.77277],"type":"Point"}
}