{
  "type": "Feature",
  "properties": {
    "gn:admin1_code":"18.0",
    "gn:admin2_code":"3002.0",
    "gn:asciiname":"Mahqan",
    "gn:country_code":"YE",
    "gn:dem":2094,
    "gn:feature_class":"P",
    "gn:feature_code":"PPL",
    "gn:name":"Ma\u1e29qan",
    "gn:population":0,
    "gn:timezone":"Asia/Aden",
    "iso:country":"YE",
    "name:und_x_variant":[
        "Ma\u1e29qan"
    ],
    "wof:name":"Mahqan",
    "wof:placetype":"locality"
},
  "geometry": {"coordinates":[44.69312,14.0274],"type":"Point"}
}