{
  "type": "Feature",
  "properties": {
    "gn:admin1_code":"15.0",
    "gn:admin2_code":"2211.0",
    "gn:asciiname":"As Sawh",
    "gn:country_code":"YE",
    "gn:dem":2113,
    "gn:feature_class":"P",
    "gn:feature_code":"PPL",
    "gn:name":"A\u015f \u015eaw\u1e29",
    "gn:population":0,
    "gn:timezone":"Asia/Aden",
    "iso:country":"YE",
    "name:ara_x_preferred":[
        "\u0627\u0644\u0635\u0648\u062d"
    ],
    "name:und_x_variant":[
        "A\u015f \u015eaw\u1e29"
    ],
    "wof:name":"As Sawh",
    "wof:placetype":"locality"
},
  "geometry": {"coordinates":[43.74224,16.74235],"type":"Point"}
}