{
  "type": "Feature",
  "properties": {
    "gn:admin1_code":"25.0",
    "gn:admin2_code":"1502.0",
    "gn:asciiname":"AL Lasbah",
    "gn:country_code":"YE",
    "gn:dem":1110,
    "gn:feature_class":"P",
    "gn:feature_code":"PPL",
    "gn:name":"AL La\u015fbah",
    "gn:population":0,
    "gn:timezone":"Asia/Aden",
    "iso:country":"YE",
    "name:und_x_variant":[
        "AL La\u015fbah"
    ],
    "wof:name":"AL Lasbah",
    "wof:placetype":"locality"
},
  "geometry": {"coordinates":[43.88333,13.68333],"type":"Point"}
}