{
  "type": "Feature",
  "properties": {
    "gn:admin1_code":"25.0",
    "gn:admin2_code":"1511.0",
    "gn:asciiname":"Al `Irkab",
    "gn:country_code":"YE",
    "gn:dem":1606,
    "gn:feature_class":"P",
    "gn:feature_code":"PPL",
    "gn:name":"Al \u2018Irk\u0101b",
    "gn:population":0,
    "gn:timezone":"Asia/Aden",
    "iso:country":"YE",
    "name:ara_x_preferred":[
        "Al \u2018Irk\u0101b"
    ],
    "wof:name":"Al `Irkab",
    "wof:placetype":"locality"
},
  "geometry": {"coordinates":[44.08895,13.5698],"type":"Point"}
}