{
  "type": "Feature",
  "properties": {
    "gn:admin1_code":"14.0",
    "gn:asciiname":"Lubb as Sawda'",
    "gn:country_code":"YE",
    "gn:dem":1142,
    "gn:feature_class":"P",
    "gn:feature_code":"PPLL",
    "gn:name":"Lubb as Sawd\u0101\u2019",
    "gn:population":0,
    "gn:timezone":"Asia/Aden",
    "iso:country":"YE",
    "name:ara_x_preferred":[
        "\u0644\u0628 \u0627\u0644\u0633\u0648\u062f\u0627\u0621"
    ],
    "name:und_x_variant":[
        "Lubb as Sawd\u0101\u2019"
    ],
    "wof:name":"Lubb as Sawda'",
    "wof:placetype":"locality"
},
  "geometry": {"coordinates":[44.62496,16.16933],"type":"Point"}
}