{
  "type": "Feature",
  "properties": {
    "gn:admin1_code":"15.0",
    "gn:admin2_code":"2208.0",
    "gn:asciiname":"Ash Sharqi",
    "gn:country_code":"YE",
    "gn:dem":1240,
    "gn:feature_class":"P",
    "gn:feature_code":"PPL",
    "gn:name":"Ash Sharq\u012b",
    "gn:population":0,
    "gn:timezone":"Asia/Aden",
    "iso:country":"YE",
    "name:und_x_variant":[
        "Ash Sharq\u012b"
    ],
    "wof:name":"Ash Sharqi",
    "wof:placetype":"locality"
},
  "geometry": {"coordinates":[43.34889,16.80278],"type":"Point"}
}