{
  "type": "Feature",
  "properties": {
    "gn:admin1_code":"22.0",
    "gn:admin2_code":"1722.0",
    "gn:asciiname":"Hulbubah",
    "gn:country_code":"YE",
    "gn:dem":566,
    "gn:feature_class":"P",
    "gn:feature_code":"PPL",
    "gn:name":"\u1e28ulb\u016bbah",
    "gn:population":0,
    "gn:timezone":"Asia/Aden",
    "iso:country":"YE",
    "name:und_x_variant":[
        "\u1e28ulb\u016bbah"
    ],
    "wof:name":"Hulbubah",
    "wof:placetype":"locality"
},
  "geometry": {"coordinates":[43.393,15.79196],"type":"Point"}
}