{
  "type": "Feature",
  "properties": {
    "gn:admin1_code":"25.0",
    "gn:admin2_code":"1514.0",
    "gn:asciiname":"Ar Rafsah",
    "gn:country_code":"YE",
    "gn:dem":1501,
    "gn:feature_class":"P",
    "gn:feature_code":"PPL",
    "gn:name":"Ar Raf\u015fah",
    "gn:population":0,
    "gn:timezone":"Asia/Aden",
    "iso:country":"YE",
    "name:und_x_variant":[
        "Ar Raf\u015fah"
    ],
    "wof:name":"Ar Rafsah",
    "wof:placetype":"locality"
},
  "geometry": {"coordinates":[44.19317,13.38725],"type":"Point"}
}