{
  "type": "Feature",
  "properties": {
    "gn:admin1_code":"20.0",
    "gn:admin2_code":"1409.0",
    "gn:asciiname":"Al Maqfal",
    "gn:country_code":"YE",
    "gn:dem":1980,
    "gn:feature_class":"P",
    "gn:feature_code":"PPL",
    "gn:name":"Al Maqfal",
    "gn:population":0,
    "gn:timezone":"Asia/Aden",
    "iso:country":"YE",
    "name:und_x_variant":[
        "Al Mugfil",
        "Al Maqfal",
        "Al Muqfil"
    ],
    "wof:name":"Al Maqfal",
    "wof:placetype":"locality"
},
  "geometry": {"coordinates":[45.57182,13.99993],"type":"Point"}
}