{
  "type": "Feature",
  "properties": {
    "gn:admin1_code":"14.0",
    "gn:admin2_code":"2606.0",
    "gn:asciiname":"Diwar",
    "gn:country_code":"YE",
    "gn:dem":1484,
    "gn:feature_class":"P",
    "gn:feature_code":"PPL",
    "gn:name":"\u1e10iwar",
    "gn:population":0,
    "gn:timezone":"Asia/Aden",
    "iso:country":"YE",
    "name:und_x_variant":[
        "\u1e10iwar"
    ],
    "wof:name":"Diwar",
    "wof:placetype":"locality"
},
  "geometry": {"coordinates":[44.95,15.45833],"type":"Point"}
}