{
  "type": "Feature",
  "properties": {
    "gn:admin1_code":"15.0",
    "gn:admin2_code":"2210.0",
    "gn:asciiname":"Mashham",
    "gn:country_code":"YE",
    "gn:dem":1980,
    "gn:feature_class":"P",
    "gn:feature_code":"PPL",
    "gn:name":"Mash\u1e29am",
    "gn:population":0,
    "gn:timezone":"Asia/Aden",
    "iso:country":"YE",
    "name:und_x_variant":[
        "Mash\u1e29am"
    ],
    "wof:name":"Mashham",
    "wof:placetype":"locality"
},
  "geometry": {"coordinates":[43.61978,17.08586],"type":"Point"}
}