{
  "type": "Feature",
  "properties": {
    "gn:admin1_code":"15.0",
    "gn:admin2_code":"2203.0",
    "gn:asciiname":"Ash Shabliyah",
    "gn:country_code":"YE",
    "gn:dem":1872,
    "gn:feature_class":"P",
    "gn:feature_code":"PPL",
    "gn:name":"Ash Shabl\u012byah",
    "gn:population":0,
    "gn:timezone":"Asia/Aden",
    "iso:country":"YE",
    "name:ara_x_preferred":[
        "\u0627\u0644\u0634\u0628\u0644\u064a\u0629"
    ],
    "name:und_x_variant":[
        "Ash Shabl\u012byah"
    ],
    "wof:name":"Ash Shabliyah",
    "wof:placetype":"locality"
},
  "geometry": {"coordinates":[43.2794,17.17602999999999],"type":"Point"}
}