{
  "type": "Feature",
  "properties": {
    "gn:admin1_code":"19.0",
    "gn:admin2_code":"2917.0",
    "gn:asciiname":"Al Hayyarah",
    "gn:country_code":"YE",
    "gn:dem":3102,
    "gn:feature_class":"P",
    "gn:feature_code":"PPL",
    "gn:name":"Al \u1e28ayy\u0101rah",
    "gn:population":0,
    "gn:timezone":"Asia/Aden",
    "iso:country":"YE",
    "name:und_x_variant":[
        "Al \u1e28ayy\u0101rah"
    ],
    "wof:name":"Al Hayyarah",
    "wof:placetype":"locality"
},
  "geometry": {"coordinates":[43.809,15.61192],"type":"Point"}
}