{
  "type": "Feature",
  "properties": {
    "gn:admin1_code":"21.0",
    "gn:admin2_code":"1608.0",
    "gn:asciiname":"As Salamat",
    "gn:country_code":"YE",
    "gn:dem":1118,
    "gn:feature_class":"P",
    "gn:feature_code":"PPL",
    "gn:name":"As Salam\u0101t",
    "gn:population":0,
    "gn:timezone":"Asia/Aden",
    "iso:country":"YE",
    "name:ara_x_preferred":[
        "\u0627\u0644\u0633\u0644\u0645\u0627\u062a"
    ],
    "name:und_x_variant":[
        "As Salam\u0101t"
    ],
    "wof:name":"As Salamat",
    "wof:placetype":"locality"
},
  "geometry": {"coordinates":[44.73716,16.1129],"type":"Point"}
}