{
  "type": "Feature",
  "properties": {
    "gn:admin1_code":"22.0",
    "gn:admin2_code":"1706.0",
    "gn:asciiname":"Al `Uwayriyan",
    "gn:country_code":"YE",
    "gn:dem":259,
    "gn:feature_class":"P",
    "gn:feature_code":"PPL",
    "gn:name":"Al \u2018Uwayriy\u0101n",
    "gn:population":0,
    "gn:timezone":"Asia/Aden",
    "iso:country":"YE",
    "name:und_x_variant":[
        "Al \u2018Uwayriy\u0101n"
    ],
    "wof:name":"Al `Uwayriyan",
    "wof:placetype":"locality"
},
  "geometry": {"coordinates":[43.24436,16.24225],"type":"Point"}
}