{
  "type": "Feature",
  "properties": {
    "gn:admin1_code":"4.0",
    "gn:admin2_code":"1905.0",
    "gn:asciiname":"An Nughsh",
    "gn:cc2":"YE",
    "gn:country_code":"YE",
    "gn:dem":1132,
    "gn:feature_class":"P",
    "gn:feature_code":"PPL",
    "gn:name":"An Nughsh",
    "gn:population":0,
    "gn:timezone":"Asia/Aden",
    "iso:country":"YE",
    "name:und_x_variant":[
        "Al-Nughsh",
        "An Nughsh"
    ],
    "wof:name":"An Nughsh",
    "wof:placetype":"locality"
},
  "geometry": {"coordinates":[48.08333,16.18333],"type":"Point"}
}