{
  "type": "Feature",
  "properties": {
    "gn:country":"YE",
    "gn:fcode":"PPL",
    "gn:pop":34,
    "iso:country":"YE",
    "name:ara_x_preferred":[
        "\u062d\u0635\u0628 \u0623\u0633\u0648\u062f"
    ],
    "name:eng_x_preferred":[
        "Hasab Aswad"
    ],
    "qs:name":"\u1e28a\u015fab Aswad",
    "qs:photos_9r":0,
    "qs:photos_sr":0,
    "qs:pop_sr":"1",
    "wof:name":"\u1e28a\u015fab Aswad",
    "wof:placetype":"locality",
    "wof:population":34
},
  "geometry": {"coordinates":[43.78616,13.13787],"type":"Point"}
}