{
  "type": "Feature",
  "properties": {
    "gn:admin1_code":"22.0",
    "gn:admin2_code":"1709.0",
    "gn:asciiname":"Sa`dan",
    "gn:country_code":"YE",
    "gn:dem":1551,
    "gn:feature_class":"P",
    "gn:feature_code":"PPL",
    "gn:name":"Sa\u2018d\u0101n",
    "gn:population":0,
    "gn:timezone":"Asia/Aden",
    "iso:country":"YE",
    "name:und_x_variant":[
        "Sa\u2018d\u0101n"
    ],
    "wof:name":"Sa`dan",
    "wof:placetype":"locality"
},
  "geometry": {"coordinates":[43.50361,15.99464],"type":"Point"}
}