{
  "type": "Feature",
  "properties": {
    "gn:country":"YE",
    "gn:fcode":"PPL",
    "gn:population":4,
    "iso:country":"YE",
    "name:ara_x_preferred":[
        "\u0627\u0644\u0638\u0644\u0627\u0645\u064a"
    ],
    "qs:name":"Az\u0327 Z\u0327al\u0101m\u012b",
    "qs:photos_9r":0,
    "qs:photos_sr":0,
    "qs:pop_sr":"1",
    "wof:name":"Az\u0327 Z\u0327al\u0101m\u012b",
    "wof:placetype":"locality",
    "wof:population":4
},
  "geometry": {"coordinates":[43.26988,17.12386],"type":"Point"}
}