{
  "type": "Feature",
  "properties": {
    "gn:admin1_code":"25.0",
    "gn:admin2_code":"1503.0",
    "gn:asciiname":"`Azban",
    "gn:country_code":"YE",
    "gn:dem":1529,
    "gn:feature_class":"P",
    "gn:feature_code":"PPL",
    "gn:name":"\u2018Azb\u0101n",
    "gn:population":0,
    "gn:timezone":"Asia/Aden",
    "iso:country":"YE",
    "name:ara_x_preferred":[
        "\u2018Azb\u0101n"
    ],
    "wof:name":"`Azban",
    "wof:placetype":"locality"
},
  "geometry": {"coordinates":[43.85925,13.75167],"type":"Point"}
}