{
  "type": "Feature",
  "properties": {
    "gn:admin1_code":"19.0",
    "gn:admin2_code":"2920.0",
    "gn:asciiname":"Bayt al Jahshari",
    "gn:country_code":"YE",
    "gn:dem":2082,
    "gn:feature_class":"P",
    "gn:feature_code":"PPL",
    "gn:name":"Bayt al Ja\u1e29shar\u012b",
    "gn:population":0,
    "gn:timezone":"Asia/Aden",
    "iso:country":"YE",
    "name:ara_x_preferred":[
        "\u0628\u064a\u062a \u0627\u0644\u062c\u062d\u0634\u0631\u064a"
    ],
    "name:und_x_variant":[
        "Al Mas\u0101jid",
        "Bayt al Ja\u1e29shar\u012b"
    ],
    "wof:name":"Bayt al Jahshari",
    "wof:placetype":"locality"
},
  "geometry": {"coordinates":[43.92788,16.12978],"type":"Point"}
}