{
  "type": "Feature",
  "properties": {
    "gn:admin1_code":"19.0",
    "gn:admin2_code":"2919.0",
    "gn:asciiname":"Aqsam `Abbas",
    "gn:country_code":"YE",
    "gn:dem":1781,
    "gn:feature_class":"P",
    "gn:feature_code":"PPL",
    "gn:name":"Aqs\u0101m \u2018Abb\u0101s",
    "gn:population":0,
    "gn:timezone":"Asia/Aden",
    "iso:country":"YE",
    "name:ara_x_preferred":[
        "Aqs\u0101m \u2018Abb\u0101s"
    ],
    "name:ara_x_variant":[
        "\u0623\u0642\u0633\u0627\u0645 \u0639\u0628\u0627\u0633"
    ],
    "wof:name":"Aqsam `Abbas",
    "wof:placetype":"locality"
},
  "geometry": {"coordinates":[43.86124,16.06254],"type":"Point"}
}