{
  "type": "Feature",
  "properties": {
    "gn:admin1_code":"19.0",
    "gn:admin2_code":"2909.0",
    "gn:asciiname":"Hijrat Mirhibah",
    "gn:country_code":"YE",
    "gn:dem":2240,
    "gn:feature_class":"P",
    "gn:feature_code":"PPL",
    "gn:name":"Hijrat Mirhibah",
    "gn:population":0,
    "gn:timezone":"Asia/Aden",
    "iso:country":"YE",
    "wof:name":"Hijrat Mirhibah",
    "wof:placetype":"locality"
},
  "geometry": {"coordinates":[44.09299,16.02765],"type":"Point"}
}