{
  "type": "Feature",
  "properties": {
    "gn:admin1_code":"22.0",
    "gn:admin2_code":"1727.0",
    "gn:asciiname":"Bayt al Juhrah",
    "gn:country_code":"YE",
    "gn:dem":1035,
    "gn:feature_class":"P",
    "gn:feature_code":"PPL",
    "gn:name":"Bayt al Ju\u1e29rah",
    "gn:population":0,
    "gn:timezone":"Asia/Aden",
    "iso:country":"YE",
    "name:ara_x_preferred":[
        "\u0628\u064a\u062a \u0627\u0644\u062c\u062d\u0631\u0629"
    ],
    "name:und_x_variant":[
        "Bayt al Ju\u1e29rah"
    ],
    "wof:name":"Bayt al Juhrah",
    "wof:placetype":"locality"
},
  "geometry": {"coordinates":[43.5651,15.55622],"type":"Point"}
}