{
  "type": "Feature",
  "properties": {
    "gn:admin1_code":"19.0",
    "gn:admin2_code":"2910.0",
    "gn:asciiname":"Suwat",
    "gn:country_code":"YE",
    "gn:dem":2074,
    "gn:feature_class":"P",
    "gn:feature_code":"PPL",
    "gn:name":"Suw\u0101t",
    "gn:population":0,
    "gn:timezone":"Asia/Aden",
    "iso:country":"YE",
    "name:ara_x_preferred":[
        "Suw\u0101t"
    ],
    "wof:name":"Suwat",
    "wof:placetype":"locality"
},
  "geometry": {"coordinates":[44.13345,15.90087],"type":"Point"}
}