{
  "type": "Feature",
  "properties": {
    "gn:country":"YE",
    "gn:fcode":"PPL",
    "gn:population":4,
    "iso:country":"YE",
    "name:ara_x_preferred":[
        "\u0639\u0643\u0631\u0645\u0629"
    ],
    "name:eng_x_preferred":[
        "Akramah"
    ],
    "name:eng_x_variant":[
        "\u0100l Markab",
        "'Akramah"
    ],
    "qs:name":"\u2018Akramah",
    "qs:photos_9r":0,
    "qs:photos_sr":0,
    "qs:pop_sr":"1",
    "wof:name":"\u2018Akramah",
    "wof:placetype":"locality",
    "wof:population":4
},
  "geometry": {"coordinates":[43.4104,16.30628],"type":"Point"}
}