{
  "type": "Feature",
  "properties": {
    "gn:admin1_code":"20.0",
    "gn:admin2_code":"1419.0",
    "gn:asciiname":"Safa'",
    "gn:country_code":"YE",
    "gn:dem":1968,
    "gn:feature_class":"P",
    "gn:feature_code":"PPL",
    "gn:name":"\u015eaf\u0101\u2019",
    "gn:population":0,
    "gn:timezone":"Asia/Aden",
    "iso:country":"YE",
    "name:und_x_variant":[
        "\u015eaf\u0101\u2019"
    ],
    "wof:name":"Safa'",
    "wof:placetype":"locality"
},
  "geometry": {"coordinates":[45.21797,14.29411],"type":"Point"}
}