{
  "type": "Feature",
  "properties": {
    "gn:admin1_code":"22.0",
    "gn:admin2_code":"1717.0",
    "gn:asciiname":"Ru`ayn",
    "gn:country_code":"YE",
    "gn:dem":1531,
    "gn:feature_class":"P",
    "gn:feature_code":"PPL",
    "gn:name":"Ru\u2018ayn",
    "gn:population":0,
    "gn:timezone":"Asia/Aden",
    "iso:country":"YE",
    "name:und_x_variant":[
        "Ru\u2018ayn"
    ],
    "wof:name":"Ru`ayn",
    "wof:placetype":"locality"
},
  "geometry": {"coordinates":[43.66531,15.86783],"type":"Point"}
}