{
  "type": "Feature",
  "properties": {
    "gn:admin1_code":"16.0",
    "gn:admin2_code":"2309.0",
    "gn:asciiname":"Suq al Jum`ah",
    "gn:country_code":"YE",
    "gn:dem":1374,
    "gn:feature_class":"P",
    "gn:feature_code":"PPL",
    "gn:name":"S\u016bq al Jum\u2018ah",
    "gn:population":0,
    "gn:timezone":"Asia/Aden",
    "iso:country":"YE",
    "name:und_x_variant":[
        "S\u016bq al Jum\u2018ah"
    ],
    "wof:name":"Suq al Jum`ah",
    "wof:placetype":"locality"
},
  "geometry": {"coordinates":[43.83461,15.13109],"type":"Point"}
}