{
  "type": "Feature",
  "properties": {
    "gn:admin1_code":"5.0",
    "gn:admin2_code":"2101.0",
    "gn:asciiname":"Matarah",
    "gn:country_code":"YE",
    "gn:dem":838,
    "gn:feature_class":"P",
    "gn:feature_code":"PPLA2",
    "gn:name":"Ma\u0163arah",
    "gn:population":0,
    "gn:timezone":"Asia/Aden",
    "iso:country":"YE",
    "name:ara_x_preferred":[
        "\u0645\u0637\u0631\u0629"
    ],
    "name:und_x_variant":[
        "Ma\u0163arah"
    ],
    "wof:name":"Matarah",
    "wof:placetype":"locality"
},
  "geometry": {"coordinates":[47.63339000000001,15.52591],"type":"Point"}
}