{
  "type": "Feature",
  "properties": {
    "gn:admin1_code":"8.0",
    "gn:admin2_code":"1807.0",
    "gn:asciiname":"Dayr `Asalah",
    "gn:country_code":"YE",
    "gn:dem":75,
    "gn:feature_class":"P",
    "gn:feature_code":"PPL",
    "gn:name":"Dayr `Asalah",
    "gn:population":0,
    "gn:timezone":"Asia/Aden",
    "iso:country":"YE",
    "wof:name":"Dayr `Asalah",
    "wof:placetype":"locality"
},
  "geometry": {"coordinates":[43.05972,15.29611],"type":"Point"}
}