{
  "type": "Feature",
  "properties": {
    "gn:admin1_code":"23.0",
    "gn:admin2_code":"1108.0",
    "gn:asciiname":"Qaryat ash Sharaf",
    "gn:country_code":"YE",
    "gn:dem":1878,
    "gn:feature_class":"P",
    "gn:feature_code":"PPL",
    "gn:name":"Qaryat ash Sharaf",
    "gn:population":0,
    "gn:timezone":"Asia/Aden",
    "iso:country":"YE",
    "name:ara_x_preferred":[
        "\u0627\u0644\u0634\u0631\u0641"
    ],
    "name:und_x_variant":[
        "Ash Shurf"
    ],
    "wof:name":"Qaryat ash Sharaf",
    "wof:placetype":"locality"
},
  "geometry": {"coordinates":[44.10843,14.13457],"type":"Point"}
}