{
  "type": "Feature",
  "properties": {
    "gn:admin1_code":"10.0",
    "gn:admin2_code":"2702.0",
    "gn:asciiname":"`Afit",
    "gn:country_code":"YE",
    "gn:dem":2949,
    "gn:feature_class":"P",
    "gn:feature_code":"PPL",
    "gn:name":"\u2018Afi\u0163",
    "gn:population":0,
    "gn:timezone":"Asia/Aden",
    "iso:country":"YE",
    "name:ara_x_preferred":[
        "\u2018Afi\u0163"
    ],
    "wof:name":"`Afit",
    "wof:placetype":"locality"
},
  "geometry": {"coordinates":[43.78174,15.56337],"type":"Point"}
}