{
  "type": "Feature",
  "properties": {
    "gn:admin1_code":"23.0",
    "gn:admin2_code":"1112.0",
    "gn:asciiname":"Jabal Humayd",
    "gn:country_code":"YE",
    "gn:dem":2190,
    "gn:feature_class":"P",
    "gn:feature_code":"PPL",
    "gn:name":"Jabal \u1e28umayd",
    "gn:population":0,
    "gn:timezone":"Asia/Aden",
    "iso:country":"YE",
    "name:und_x_variant":[
        "Jabal \u1e28umayd"
    ],
    "wof:name":"Jabal Humayd",
    "wof:placetype":"locality"
},
  "geometry": {"coordinates":[44.16005,13.9103],"type":"Point"}
}