{
  "type": "Feature",
  "properties": {
    "gn:country":"YE",
    "gn:fcode":"PPL",
    "gn:population":1,
    "iso:country":"YE",
    "name:ara_x_preferred":[
        "\u0627\u0644\u0642\u0631\u062d\u064a\u0627\u0646"
    ],
    "name:eng_x_preferred":[
        "Al Qarhiyan"
    ],
    "name:eng_x_variant":[
        "Al Qim\u2018ah"
    ],
    "qs:name":"Al Qar\u1e29iy\u0101n",
    "qs:photos_9r":0,
    "qs:photos_sr":0,
    "qs:pop_sr":"1",
    "wof:name":"Al Qar\u1e29iy\u0101n",
    "wof:placetype":"locality",
    "wof:population":1
},
  "geometry": {"coordinates":[43.93054,13.14096],"type":"Point"}
}