{
  "type": "Feature",
  "properties": {
    "gn:country":"YE",
    "gn:fcode":"PPL",
    "gn:population":50,
    "iso:country":"YE",
    "name:ara_x_preferred":[
        "\u0627\u0644\u0646\u0642\u0627\u062d\u0629"
    ],
    "name:eng_x_preferred":[
        "An Naqahah"
    ],
    "name:eng_x_variant":[
        "Al Ja\u2018\u0101d\u012byah"
    ],
    "qs:name":"An Naq\u0101\u1e29ah",
    "qs:photos_9r":0,
    "qs:photos_sr":0,
    "qs:pop_sr":"1",
    "wof:name":"An Naq\u0101\u1e29ah",
    "wof:placetype":"locality",
    "wof:population":50
},
  "geometry": {"coordinates":[43.7202,13.08689],"type":"Point"}
}