{
  "type": "Feature",
  "properties": {
    "gn:admin1_code":"16.0",
    "gn:admin2_code":"2312.0",
    "gn:asciiname":"An Naqqub",
    "gn:country_code":"YE",
    "gn:dem":2029,
    "gn:feature_class":"P",
    "gn:feature_code":"PPL",
    "gn:name":"An Naqq\u016bb",
    "gn:population":0,
    "gn:timezone":"Asia/Aden",
    "iso:country":"YE",
    "name:ara_x_preferred":[
        "\u0627\u0644\u0646\u0642\u0648\u0628"
    ],
    "name:und_x_variant":[
        "An Naqq\u016bb"
    ],
    "wof:name":"An Naqqub",
    "wof:placetype":"locality"
},
  "geometry": {"coordinates":[44.74532,15.22161],"type":"Point"}
}