{
  "type": "Feature",
  "properties": {
    "gn:country":"YE",
    "gn:fcode":"PPL",
    "gn:population":6,
    "iso:country":"YE",
    "name:ara_x_preferred":[
        "\u0634\u0639\u0628 \u0627\u0644\u062c\u062f\u064a"
    ],
    "qs:name":"Sha\u2018b al Jad\u012b",
    "qs:photos_9r":0,
    "qs:photos_sr":0,
    "qs:pop_sr":"1",
    "wof:name":"Sha\u2018b al Jad\u012b",
    "wof:placetype":"locality",
    "wof:population":6
},
  "geometry": {"coordinates":[43.47689,16.1195],"type":"Point"}
}