{
  "type": "Feature",
  "properties": {
    "gn:admin1_code":"23.0",
    "gn:admin2_code":"1110.0",
    "gn:asciiname":"Al Hubayl",
    "gn:country_code":"YE",
    "gn:dem":782,
    "gn:feature_class":"P",
    "gn:feature_code":"PPL",
    "gn:name":"Al \u1e28ubayl",
    "gn:population":0,
    "gn:timezone":"Asia/Aden",
    "iso:country":"YE",
    "name:ara_x_preferred":[
        "\u0627\u0644\u062d\u0628\u064a\u0644"
    ],
    "name:und_x_variant":[
        "Al \u1e28ab\u012bl",
        "Al \u1e28ubayl"
    ],
    "wof:name":"Al Hubayl",
    "wof:placetype":"locality"
},
  "geometry": {"coordinates":[43.80292,14.01948],"type":"Point"}
}