{
  "type": "Feature",
  "properties": {
    "gn:admin1_code":"14.0",
    "gn:admin2_code":"2606.0",
    "gn:asciiname":"Haqibah",
    "gn:country_code":"YE",
    "gn:dem":1503,
    "gn:feature_class":"P",
    "gn:feature_code":"PPL",
    "gn:name":"\u1e28aq\u012bbah",
    "gn:population":0,
    "gn:timezone":"Asia/Aden",
    "iso:country":"YE",
    "name:ara_x_preferred":[
        "\u062d\u0642\u064a\u0628\u0629"
    ],
    "name:und_x_variant":[
        "\u1e28aq\u012bbah"
    ],
    "wof:name":"Haqibah",
    "wof:placetype":"locality"
},
  "geometry": {"coordinates":[44.77896,15.50811],"type":"Point"}
}