{
  "type": "Feature",
  "properties": {
    "gn:admin1_code":"22.0",
    "gn:admin2_code":"1729.0",
    "gn:asciiname":"Bayt al Qasi",
    "gn:country_code":"YE",
    "gn:dem":1395,
    "gn:feature_class":"P",
    "gn:feature_code":"PPL",
    "gn:name":"Bayt al Q\u0101s\u012b",
    "gn:population":0,
    "gn:timezone":"Asia/Aden",
    "iso:country":"YE",
    "name:und_x_variant":[
        "Bayt al Q\u0101s\u012b"
    ],
    "wof:name":"Bayt al Qasi",
    "wof:placetype":"locality"
},
  "geometry": {"coordinates":[43.63201,15.68048],"type":"Point"}
}