{
  "type": "Feature",
  "properties": {
    "gn:admin1_code":"10.0",
    "gn:admin2_code":"2702.0",
    "gn:asciiname":"Az Zahrah",
    "gn:country_code":"YE",
    "gn:dem":2136,
    "gn:feature_class":"P",
    "gn:feature_code":"PPL",
    "gn:name":"Az\u0327 Z\u0327ahrah",
    "gn:population":0,
    "gn:timezone":"Asia/Aden",
    "iso:country":"YE",
    "name:und_x_variant":[
        "Az\u0327 Z\u0327ahrah"
    ],
    "wof:name":"Az Zahrah",
    "wof:placetype":"locality"
},
  "geometry": {"coordinates":[43.70798,15.48096],"type":"Point"}
}