{
  "type": "Feature",
  "properties": {
    "gn:admin1_code":"24.0",
    "gn:admin2_code":"2512.0",
    "gn:asciiname":"Hayjat Baqi'",
    "gn:country_code":"YE",
    "gn:dem":1477,
    "gn:feature_class":"P",
    "gn:feature_code":"PPL",
    "gn:name":"Hayjat Baq\u012b\u2018",
    "gn:population":0,
    "gn:timezone":"Asia/Aden",
    "iso:country":"YE",
    "name:ara_x_preferred":[
        "\u0647\u064a\u062c\u0629 \u0628\u0642\u064a\u0639"
    ],
    "name:und_x_variant":[
        "Hayjat Baq\u012b\u2018"
    ],
    "wof:name":"Hayjat Baqi'",
    "wof:placetype":"locality"
},
  "geometry": {"coordinates":[44.17437,13.19489],"type":"Point"}
}