{
  "type": "Feature",
  "properties": {
    "gn:country":"YE",
    "gn:fcode":"PPL",
    "gn:pop":12,
    "iso:country":"YE",
    "name:ara_x_preferred":[
        "Al \u2018Ayl\u0101t"
    ],
    "name:ara_x_variant":[
        "\u0627\u0644\u0639\u064a\u0644\u0627\u062a"
    ],
    "name:eng_x_preferred":[
        "Al 'Aylat"
    ],
    "name:eng_x_variant":[
        "Nayd al Khariqah"
    ],
    "qs:name":"Al \u2018Ayl\u0101t",
    "qs:photos_9r":0,
    "qs:photos_sr":0,
    "qs:pop_sr":"1",
    "wof:name":"Al \u2018Ayl\u0101t",
    "wof:placetype":"locality",
    "wof:population":12
},
  "geometry": {"coordinates":[45.04963,14.32503],"type":"Point"}
}