{
  "type": "Feature",
  "properties": {
    "gn:admin1_code":"8.0",
    "gn:admin2_code":"1817.0",
    "gn:asciiname":"Ad Dabarah",
    "gn:country_code":"YE",
    "gn:dem":140,
    "gn:feature_class":"P",
    "gn:feature_code":"PPL",
    "gn:name":"A\u1e11 \u1e10abarah",
    "gn:population":0,
    "gn:timezone":"Asia/Aden",
    "iso:country":"YE",
    "name:und_x_variant":[
        "A\u1e11 \u1e10abarah"
    ],
    "wof:name":"Ad Dabarah",
    "wof:placetype":"locality"
},
  "geometry": {"coordinates":[43.39951,14.5598],"type":"Point"}
}