{
  "type": "Feature",
  "properties": {
    "gn:admin1_code":"8.0",
    "gn:admin2_code":"1817.0",
    "gn:asciiname":"Mahall ad Da`aysh",
    "gn:country_code":"YE",
    "gn:dem":66,
    "gn:feature_class":"P",
    "gn:feature_code":"PPL",
    "gn:name":"Ma\u1e29all ad Da\u2018aysh",
    "gn:population":0,
    "gn:timezone":"Asia/Aden",
    "iso:country":"YE",
    "name:und_x_variant":[
        "Ma\u1e29all ad Da\u2018aysh"
    ],
    "wof:name":"Mahall ad Da`aysh",
    "wof:placetype":"locality"
},
  "geometry": {"coordinates":[43.2486,14.61446],"type":"Point"}
}