{
  "type": "Feature",
  "properties": {
    "gn:admin1_code":"20.0",
    "gn:admin2_code":"1410.0",
    "gn:asciiname":"Mash`abah",
    "gn:country_code":"YE",
    "gn:dem":1946,
    "gn:feature_class":"P",
    "gn:feature_code":"PPL",
    "gn:name":"Mash\u2018abah",
    "gn:population":0,
    "gn:timezone":"Asia/Aden",
    "iso:country":"YE",
    "name:und_x_variant":[
        "Mash\u2018abah"
    ],
    "wof:name":"Mash`abah",
    "wof:placetype":"locality"
},
  "geometry": {"coordinates":[45.56,14.04477],"type":"Point"}
}