{
  "type": "Feature",
  "properties": {
    "gn:admin1_code":"23.0",
    "gn:admin2_code":"1115.0",
    "gn:asciiname":"Janad",
    "gn:country_code":"YE",
    "gn:dem":2257,
    "gn:feature_class":"P",
    "gn:feature_code":"PPL",
    "gn:name":"Jan\u0101d",
    "gn:population":0,
    "gn:timezone":"Asia/Aden",
    "iso:country":"YE",
    "name:und_x_variant":[
        "Jan\u0101d"
    ],
    "wof:name":"Janad",
    "wof:placetype":"locality"
},
  "geometry": {"coordinates":[44.16218,13.85811],"type":"Point"}
}