{
  "type": "Feature",
  "properties": {
    "gn:admin1_code":"25.0",
    "gn:admin2_code":"1505.0",
    "gn:asciiname":"Qaryat at Tawahir",
    "gn:country_code":"YE",
    "gn:dem":329,
    "gn:feature_class":"P",
    "gn:feature_code":"PPL",
    "gn:name":"Qaryat a\u0163 \u0162aw\u0101hir",
    "gn:population":0,
    "gn:timezone":"Asia/Aden",
    "iso:country":"YE",
    "name:ara_x_preferred":[
        "\u0627\u0644\u0637\u0648\u0627\u0647\u0631"
    ],
    "name:und_x_variant":[
        "Qaryat a\u0163 \u0162aw\u0101hir",
        "A\u0163 \u0162aw\u0101hir"
    ],
    "wof:name":"Qaryat at Tawahir",
    "wof:placetype":"locality"
},
  "geometry": {"coordinates":[43.50775,13.81939],"type":"Point"}
}