{
  "type": "Feature",
  "properties": {
    "gn:admin1_code":"16.0",
    "gn:admin2_code":"2307.0",
    "gn:asciiname":"Bayt al `Uwa'",
    "gn:country_code":"YE",
    "gn:dem":2449,
    "gn:feature_class":"P",
    "gn:feature_code":"PPL",
    "gn:name":"Bayt al \u2018Uw\u0101\u2019",
    "gn:population":0,
    "gn:timezone":"Asia/Aden",
    "iso:country":"YE",
    "name:und_x_variant":[
        "Bayt al \u2018Uw\u0101\u2019"
    ],
    "wof:name":"Bayt al `Uwa'",
    "wof:placetype":"locality"
},
  "geometry": {"coordinates":[44.04115,15.19209],"type":"Point"}
}