{
  "type": "Feature",
  "properties": {
    "gn:admin1_code":"18.0",
    "gn:admin2_code":"3001.0",
    "gn:asciiname":"Al Khaniq",
    "gn:country_code":"YE",
    "gn:dem":1815,
    "gn:feature_class":"P",
    "gn:feature_code":"PPL",
    "gn:name":"Al Kh\u0101niq",
    "gn:population":0,
    "gn:timezone":"Asia/Aden",
    "iso:country":"YE",
    "name:ara_x_preferred":[
        "Al Kh\u0101niq"
    ],
    "wof:name":"Al Khaniq",
    "wof:placetype":"locality"
},
  "geometry": {"coordinates":[45.02434,14.04636],"type":"Point"}
}