{
  "type": "Feature",
  "properties": {
    "gn:admin1_code":"19.0",
    "gn:admin2_code":"2920.0",
    "gn:asciiname":"Bayt Qatran",
    "gn:country_code":"YE",
    "gn:dem":2027,
    "gn:feature_class":"P",
    "gn:feature_code":"PPL",
    "gn:name":"Bayt Qa\u0163r\u0101n",
    "gn:population":0,
    "gn:timezone":"Asia/Aden",
    "iso:country":"YE",
    "name:ara_x_preferred":[
        "\u0628\u064a\u062a \u0642\u0637\u0631\u0627\u0646"
    ],
    "name:und_x_variant":[
        "Bayt Qa\u0163r\u0101n"
    ],
    "wof:name":"Bayt Qatran",
    "wof:placetype":"locality"
},
  "geometry": {"coordinates":[43.92855,16.16986],"type":"Point"}
}