{
  "type": "Feature",
  "properties": {
    "gn:admin1_code":"19.0",
    "gn:admin2_code":"2909.0",
    "gn:asciiname":"Al Qadah",
    "gn:country_code":"YE",
    "gn:dem":1759,
    "gn:feature_class":"P",
    "gn:feature_code":"PPL",
    "gn:name":"Al Qa\u1e11\u0101h",
    "gn:population":0,
    "gn:timezone":"Asia/Aden",
    "iso:country":"YE",
    "name:ara_x_preferred":[
        "\u0627\u0644\u0642\u0636\u0627\u0629"
    ],
    "name:und_x_variant":[
        "Al Qa\u1e11\u0101h"
    ],
    "wof:name":"Al Qadah",
    "wof:placetype":"locality"
},
  "geometry": {"coordinates":[44.15991,16.00784],"type":"Point"}
}