{
  "type": "Feature",
  "properties": {
    "gn:admin1_code":"15.0",
    "gn:admin2_code":"2205.0",
    "gn:asciiname":"Arhab",
    "gn:country_code":"YE",
    "gn:dem":1642,
    "gn:feature_class":"P",
    "gn:feature_code":"PPL",
    "gn:name":"Ar\u1e29ab",
    "gn:population":0,
    "gn:timezone":"Asia/Aden",
    "iso:country":"YE",
    "name:ara_x_preferred":[
        "\u0623\u0631\u062d\u0628"
    ],
    "name:und_x_variant":[
        "Ar\u1e29ab"
    ],
    "wof:name":"Arhab",
    "wof:placetype":"locality"
},
  "geometry": {"coordinates":[43.26115,16.92501],"type":"Point"}
}