{
  "type": "Feature",
  "properties": {
    "gn:admin1_code":"21.0",
    "gn:admin2_code":"1612.0",
    "gn:asciiname":"Dahinah",
    "gn:country_code":"YE",
    "gn:dem":1447,
    "gn:feature_class":"P",
    "gn:feature_code":"PPL",
    "gn:name":"D\u0101\u1e29inah",
    "gn:population":0,
    "gn:timezone":"Asia/Aden",
    "iso:country":"YE",
    "name:ara_x_preferred":[
        "\u062f\u0627\u062d\u0646\u0629"
    ],
    "name:und_x_variant":[
        "D\u0101\u1e29inah"
    ],
    "wof:name":"Dahinah",
    "wof:placetype":"locality"
},
  "geometry": {"coordinates":[44.25138,16.58583],"type":"Point"}
}