{
  "type": "Feature",
  "properties": {
    "gn:admin1_code":"18.0",
    "gn:admin2_code":"3006.0",
    "gn:asciiname":"Al Maryah",
    "gn:country_code":"YE",
    "gn:dem":1120,
    "gn:feature_class":"P",
    "gn:feature_code":"PPL",
    "gn:name":"Al Mary\u0101\u1e29",
    "gn:population":0,
    "gn:timezone":"Asia/Aden",
    "iso:country":"YE",
    "name:und_x_variant":[
        "El Maria",
        "Al Miryah",
        "Al Mary\u0101\u1e29"
    ],
    "wof:name":"Al Maryah",
    "wof:placetype":"locality"
},
  "geometry": {"coordinates":[44.58641,13.77656],"type":"Point"}
}