{
  "type": "Feature",
  "properties": {
    "gn:admin1_code":"16.0",
    "gn:admin2_code":"2310.0",
    "gn:asciiname":"`Azzan",
    "gn:country_code":"YE",
    "gn:dem":2101,
    "gn:feature_class":"P",
    "gn:feature_code":"PPL",
    "gn:name":"\u2018Azz\u0101n",
    "gn:population":0,
    "gn:timezone":"Asia/Aden",
    "iso:country":"YE",
    "name:ara_x_preferred":[
        "\u2018Azz\u0101n"
    ],
    "wof:name":"`Azzan",
    "wof:placetype":"locality"
},
  "geometry": {"coordinates":[43.78485,15.0454],"type":"Point"}
}