{
  "type": "Feature",
  "properties": {
    "gn:country":"YE",
    "gn:fcode":"PPL",
    "gn:pop":12,
    "iso:country":"YE",
    "name:ara_x_preferred":[
        "\u063a\u0648\u0644 \u0627\u0644\u062d\u0644\u0627\u0644"
    ],
    "name:eng_x_preferred":[
        "Ghawl Al Hilal"
    ],
    "qs:name":"Ghawl al \u1e28il\u0101l",
    "qs:photos_9r":0,
    "qs:photos_sr":0,
    "qs:pop_sr":"1",
    "wof:name":"Ghawl al \u1e28il\u0101l",
    "wof:placetype":"locality",
    "wof:population":12
},
  "geometry": {"coordinates":[45.99099,14.53071],"type":"Point"}
}