{
  "type": "Feature",
  "properties": {
    "gn:admin1_code":"22.0",
    "gn:admin2_code":"1728.0",
    "gn:asciiname":"Ghurban",
    "gn:country_code":"YE",
    "gn:dem":1248,
    "gn:feature_class":"P",
    "gn:feature_code":"PPL",
    "gn:name":"Ghurb\u0101n",
    "gn:population":0,
    "gn:timezone":"Asia/Aden",
    "iso:country":"YE",
    "name:ara_x_preferred":[
        "Ghurb\u0101n"
    ],
    "wof:name":"Ghurban",
    "wof:placetype":"locality"
},
  "geometry": {"coordinates":[43.60132,15.67688],"type":"Point"}
}