{
  "type": "Feature",
  "properties": {
    "gn:admin1_code":"23.0",
    "gn:admin2_code":"1110.0",
    "gn:asciiname":"Al Mizhanah",
    "gn:country_code":"YE",
    "gn:dem":1418,
    "gn:feature_class":"P",
    "gn:feature_code":"PPL",
    "gn:name":"Al Miz\u1e29\u0101nah",
    "gn:population":0,
    "gn:timezone":"Asia/Aden",
    "iso:country":"YE",
    "name:und_x_variant":[
        "Al Miz\u1e29\u0101nah"
    ],
    "wof:name":"Al Mizhanah",
    "wof:placetype":"locality"
},
  "geometry": {"coordinates":[43.82453,13.90794],"type":"Point"}
}