{
  "type": "Feature",
  "properties": {
    "gn:admin1_code":"19.0",
    "gn:admin2_code":"2913.0",
    "gn:asciiname":"Dhubayl",
    "gn:country_code":"YE",
    "gn:dem":2047,
    "gn:feature_class":"P",
    "gn:feature_code":"PPL",
    "gn:name":"Dhubayl",
    "gn:population":0,
    "gn:timezone":"Asia/Aden",
    "iso:country":"YE",
    "wof:name":"Dhubayl",
    "wof:placetype":"locality"
},
  "geometry": {"coordinates":[43.81867,15.9589],"type":"Point"}
}