{
  "type": "Feature",
  "properties": {
    "gn:admin1_code":"19.0",
    "gn:admin2_code":"2903.0",
    "gn:asciiname":"As Suwaydah",
    "gn:country_code":"YE",
    "gn:dem":1178,
    "gn:feature_class":"P",
    "gn:feature_code":"PPL",
    "gn:name":"As Suwaydah",
    "gn:population":0,
    "gn:timezone":"Asia/Aden",
    "iso:country":"YE",
    "wof:name":"As Suwaydah",
    "wof:placetype":"locality"
},
  "geometry": {"coordinates":[43.81624,16.2258],"type":"Point"}
}