{
  "type": "Feature",
  "properties": {
    "gn:admin1_code":"19.0",
    "gn:admin2_code":"2904.0",
    "gn:asciiname":"Al Jawashi`ah",
    "gn:country_code":"YE",
    "gn:dem":1391,
    "gn:feature_class":"P",
    "gn:feature_code":"PPL",
    "gn:name":"Al Jaw\u0101shi\u2018ah",
    "gn:population":0,
    "gn:timezone":"Asia/Aden",
    "iso:country":"YE",
    "name:ara_x_preferred":[
        "\u0627\u0644\u062c\u0648\u0627\u0634\u0639\u0629"
    ],
    "name:und_x_variant":[
        "Ma\u1e29all al Jaw\u0101shi\u2018ah",
        "Al Jaw\u0101shi\u2018ah"
    ],
    "wof:name":"Al Jawashi`ah",
    "wof:placetype":"locality"
},
  "geometry": {"coordinates":[43.71336,16.28609],"type":"Point"}
}