{
  "type": "Feature",
  "properties": {
    "gn:admin1_code":"22.0",
    "gn:admin2_code":"1707.0",
    "gn:asciiname":"Baghit",
    "gn:country_code":"YE",
    "gn:dem":1067,
    "gn:feature_class":"P",
    "gn:feature_code":"PPL",
    "gn:name":"B\u0101ghit",
    "gn:population":0,
    "gn:timezone":"Asia/Aden",
    "iso:country":"YE",
    "name:ara_x_preferred":[
        "B\u0101ghit"
    ],
    "name:ara_x_variant":[
        "\u0628\u0627\u063a\u062a"
    ],
    "wof:name":"Baghit",
    "wof:placetype":"locality"
},
  "geometry": {"coordinates":[43.44598,16.23031],"type":"Point"}
}