{
  "type": "Feature",
  "properties": {
    "gn:admin1_code":"22.0",
    "gn:admin2_code":"1707.0",
    "gn:asciiname":"Al 'Arish",
    "gn:country_code":"YE",
    "gn:dem":1043,
    "gn:feature_class":"P",
    "gn:feature_code":"PPL",
    "gn:name":"Al \u2018Ar\u012bsh",
    "gn:population":0,
    "gn:timezone":"Asia/Aden",
    "iso:country":"YE",
    "name:ara_x_preferred":[
        "Al \u2018Ar\u012bsh"
    ],
    "name:ara_x_variant":[
        "\u0627\u0644\u0639\u0631\u064a\u0634"
    ],
    "wof:name":"Al 'Arish",
    "wof:placetype":"locality"
},
  "geometry": {"coordinates":[43.40671,16.17818],"type":"Point"}
}