{
  "type": "Feature",
  "properties": {
    "gn:admin1_code":"11.0",
    "gn:admin2_code":"2012.0",
    "gn:asciiname":"Bayt Jurhum",
    "gn:country_code":"YE",
    "gn:dem":1955,
    "gn:feature_class":"P",
    "gn:feature_code":"PPL",
    "gn:name":"Bayt Jurhum",
    "gn:population":0,
    "gn:timezone":"Asia/Aden",
    "iso:country":"YE",
    "wof:name":"Bayt Jurhum",
    "wof:placetype":"locality"
},
  "geometry": {"coordinates":[44.13169,14.69149],"type":"Point"}
}