{
  "type": "Feature",
  "properties": {
    "gn:admin1_code":"25.0",
    "gn:admin2_code":"1523.0",
    "gn:asciiname":"Al Habilayn",
    "gn:country_code":"YE",
    "gn:dem":1913,
    "gn:feature_class":"P",
    "gn:feature_code":"PPL",
    "gn:name":"Al \u1e28ab\u012blayn",
    "gn:population":0,
    "gn:timezone":"Asia/Aden",
    "iso:country":"YE",
    "name:und_x_variant":[
        "Al \u1e28ab\u012blayn"
    ],
    "wof:name":"Al Habilayn",
    "wof:placetype":"locality"
},
  "geometry": {"coordinates":[44.06819,13.40374],"type":"Point"}
}