{
  "type": "Feature",
  "properties": {
    "gn:admin1_code":"25.0",
    "gn:admin2_code":"1508.0",
    "gn:asciiname":"Qaryat al Qama`irah",
    "gn:country_code":"YE",
    "gn:dem":334,
    "gn:feature_class":"P",
    "gn:feature_code":"PPL",
    "gn:name":"Qaryat al Qam\u0101\u2018irah",
    "gn:population":0,
    "gn:timezone":"Asia/Aden",
    "iso:country":"YE",
    "name:und_x_variant":[
        "Qaryat al Qam\u0101\u2018irah"
    ],
    "wof:name":"Qaryat al Qama`irah",
    "wof:placetype":"locality"
},
  "geometry": {"coordinates":[43.63655,13.25241],"type":"Point"}
}