{
  "type": "Feature",
  "properties": {
    "gn:admin1_code":"14.0",
    "gn:admin2_code":"2606.0",
    "gn:asciiname":"Al Suwaylih",
    "gn:country_code":"YE",
    "gn:dem":1488,
    "gn:feature_class":"P",
    "gn:feature_code":"PPL",
    "gn:name":"\u0100l \u015euwayli\u1e29",
    "gn:population":0,
    "gn:timezone":"Asia/Aden",
    "iso:country":"YE",
    "name:ara_x_preferred":[
        "\u0622\u0644 \u0635\u0648\u064a\u0644\u062d"
    ],
    "name:und_x_variant":[
        "\u0100l \u015euwayli\u1e29",
        "\u0100l \u015euwayla\u1e29"
    ],
    "wof:name":"Al Suwaylih",
    "wof:placetype":"locality"
},
  "geometry": {"coordinates":[44.99937,15.47139],"type":"Point"}
}