{
  "type": "Feature",
  "properties": {
    "gn:admin1_code":"23.0",
    "gn:admin2_code":"1113.0",
    "gn:asciiname":"Bayt Muhanna",
    "gn:country_code":"YE",
    "gn:dem":2139,
    "gn:feature_class":"P",
    "gn:feature_code":"PPL",
    "gn:name":"Bayt Muhann\u0101",
    "gn:population":0,
    "gn:timezone":"Asia/Aden",
    "iso:country":"YE",
    "name:und_x_variant":[
        "Bayt Muhann\u0101"
    ],
    "wof:name":"Bayt Muhanna",
    "wof:placetype":"locality"
},
  "geometry": {"coordinates":[44.30477,13.99486],"type":"Point"}
}