{
  "type": "Feature",
  "properties": {
    "gn:admin1_code":"11.0",
    "gn:asciiname":"Jabayib ad Dab`",
    "gn:country_code":"YE",
    "gn:dem":2489,
    "gn:feature_class":"P",
    "gn:feature_code":"PPL",
    "gn:name":"Jab\u0101yib a\u1e11 \u1e10ab\u2018",
    "gn:population":0,
    "gn:timezone":"Asia/Aden",
    "iso:country":"YE",
    "name:ara_x_preferred":[
        "\u062c\u0628\u0627\u064a\u0628 \u0627\u0644\u0636\u0628\u0639"
    ],
    "name:und_x_variant":[
        "Jab\u0101yib a\u1e11 \u1e10ab\u2018"
    ],
    "wof:name":"Jabayib ad Dab`",
    "wof:placetype":"locality"
},
  "geometry": {"coordinates":[44.4458,14.28697],"type":"Point"}
}