{
  "type": "Feature",
  "properties": {
    "gn:admin1_code":"19.0",
    "gn:admin2_code":"2914.0",
    "gn:asciiname":"Sali",
    "gn:country_code":"YE",
    "gn:dem":1425,
    "gn:feature_class":"P",
    "gn:feature_code":"PPL",
    "gn:name":"Sali",
    "gn:population":0,
    "gn:timezone":"Asia/Aden",
    "iso:country":"YE",
    "name:ara_x_preferred":[
        "A\u015f \u015e\u0101f\u012b"
    ],
    "name:und_x_variant":[
        "E\u1e63-\u1e62\u00e2fi",
        "Fahbi"
    ],
    "wof:name":"Sali",
    "wof:placetype":"locality"
},
  "geometry": {"coordinates":[43.73333,15.76667],"type":"Point"}
}