{
  "type": "Feature",
  "properties": {
    "gn:admin1_code":"16.0",
    "gn:admin2_code":"2301.0",
    "gn:asciiname":"Al Hawiri",
    "gn:country_code":"YE",
    "gn:dem":2251,
    "gn:feature_class":"P",
    "gn:feature_code":"PPL",
    "gn:name":"Al \u1e28\u0101wir\u012b",
    "gn:population":0,
    "gn:timezone":"Asia/Aden",
    "iso:country":"YE",
    "name:fas_x_preferred":[
        "\u0627\u0644\u062d\u0648\u06cc\u0631\u06cc"
    ],
    "name:nno_x_preferred":[
        "Al Hawiri"
    ],
    "name:und_x_variant":[
        "Al \u1e28\u0101wir\u012b"
    ],
    "wof:name":"Al Hawiri",
    "wof:placetype":"locality"
},
  "geometry": {"coordinates":[44.13333,15.52083],"type":"Point"}
}