{
  "type": "Feature",
  "properties": {
    "gn:admin1_code":"23.0",
    "gn:admin2_code":"1117.0",
    "gn:asciiname":"Ash Shuhaym",
    "gn:country_code":"YE",
    "gn:dem":1597,
    "gn:feature_class":"P",
    "gn:feature_code":"PPL",
    "gn:name":"Ash Shu\u1e29aym",
    "gn:population":0,
    "gn:timezone":"Asia/Aden",
    "iso:country":"YE",
    "name:und_x_variant":[
        "Ash Shu\u1e29aym"
    ],
    "wof:name":"Ash Shuhaym",
    "wof:placetype":"locality"
},
  "geometry": {"coordinates":[43.94791,13.89648],"type":"Point"}
}