{
  "type": "Feature",
  "properties": {
    "gn:admin1_code":"23.0",
    "gn:admin2_code":"1101.0",
    "gn:asciiname":"Al Bir",
    "gn:country_code":"YE",
    "gn:dem":1270,
    "gn:feature_class":"P",
    "gn:feature_code":"PPL",
    "gn:name":"Al B\u012br",
    "gn:population":0,
    "gn:timezone":"Asia/Aden",
    "iso:country":"YE",
    "name:ara_x_preferred":[
        "\u0627\u0644\u0628\u064a\u0631"
    ],
    "name:fas_x_preferred":[
        "\u0627\u0644\u0628\u06cc\u0631"
    ],
    "name:nno_x_preferred":[
        "Al Bir"
    ],
    "name:und_x_variant":[
        "Al B\u012br"
    ],
    "name:urd_x_preferred":[
        "\u0627\u0644\u0628\u06cc\u0631"
    ],
    "wof:name":"Al Bir",
    "wof:placetype":"locality"
},
  "geometry": {"coordinates":[44.07487,14.32118],"type":"Point"}
}