{
  "type": "Feature",
  "properties": {
    "gn:admin1_code":"18.0",
    "gn:admin2_code":"3006.0",
    "gn:asciiname":"Ad Dubiyat",
    "gn:country_code":"YE",
    "gn:dem":1672,
    "gn:feature_class":"P",
    "gn:feature_code":"PPL",
    "gn:name":"Ad Dubiyat",
    "gn:population":0,
    "gn:timezone":"Asia/Aden",
    "iso:country":"YE",
    "name:und_x_variant":[
        "A\u1e11 \u1e10ubayy\u0101t"
    ],
    "wof:name":"Ad Dubiyat",
    "wof:placetype":"locality"
},
  "geometry": {"coordinates":[44.77335,13.61255],"type":"Point"}
}