{
  "type": "Feature",
  "properties": {
    "gn:admin1_code":"22.0",
    "gn:admin2_code":"1725.0",
    "gn:asciiname":"Al Qasabah",
    "gn:country_code":"YE",
    "gn:dem":534,
    "gn:feature_class":"P",
    "gn:feature_code":"PPL",
    "gn:name":"Al Qa\u015fabah",
    "gn:population":0,
    "gn:timezone":"Asia/Aden",
    "iso:country":"YE",
    "name:und_x_variant":[
        "Al Qa\u015fabah"
    ],
    "wof:name":"Al Qasabah",
    "wof:placetype":"locality"
},
  "geometry": {"coordinates":[43.45575,15.60083],"type":"Point"}
}