{
  "type": "Feature",
  "properties": {
    "gn:admin1_code":"11.0",
    "gn:admin2_code":"2005.0",
    "gn:asciiname":"Suq ash Sharm",
    "gn:country_code":"YE",
    "gn:dem":1571,
    "gn:feature_class":"P",
    "gn:feature_code":"PPL",
    "gn:name":"S\u016bq ash Sharm",
    "gn:population":0,
    "gn:timezone":"Asia/Aden",
    "iso:country":"YE",
    "name:und_x_variant":[
        "S\u016bq ash Sharm"
    ],
    "wof:name":"Suq ash Sharm",
    "wof:placetype":"locality"
},
  "geometry": {"coordinates":[43.96237,14.40561],"type":"Point"}
}