{
  "type": "Feature",
  "properties": {
    "gn:admin1_code":"8.0",
    "gn:admin2_code":"1806.0",
    "gn:asciiname":"Mahall al Bahhari",
    "gn:country_code":"YE",
    "gn:dem":85,
    "gn:feature_class":"P",
    "gn:feature_code":"PPL",
    "gn:name":"Ma\u1e29all al Ba\u1e29\u1e29\u0101r\u012b",
    "gn:population":0,
    "gn:timezone":"Asia/Aden",
    "iso:country":"YE",
    "name:ara_x_preferred":[
        "\u0645\u062d\u0644 \u0642\u0637\u0646"
    ],
    "name:und_x_variant":[
        "Ma\u1e29all al Ba\u1e29\u1e29\u0101r\u012b",
        "Ma\u1e29all Qu\u0163n"
    ],
    "wof:name":"Mahall al Bahhari",
    "wof:placetype":"locality"
},
  "geometry": {"coordinates":[43.11946,15.43117],"type":"Point"}
}