{
  "type": "Feature",
  "properties": {
    "gn:admin1_code":"11.0",
    "gn:admin2_code":"2006.0",
    "gn:asciiname":"Dhi Fadalah",
    "gn:country_code":"YE",
    "gn:dem":1248,
    "gn:feature_class":"P",
    "gn:feature_code":"PPL",
    "gn:name":"Dh\u012b Fa\u1e11\u0101lah",
    "gn:population":0,
    "gn:timezone":"Asia/Aden",
    "iso:country":"YE",
    "name:und_x_variant":[
        "Dh\u012b Fa\u1e11\u0101lah"
    ],
    "wof:name":"Dhi Fadalah",
    "wof:placetype":"locality"
},
  "geometry": {"coordinates":[43.78135,14.34987],"type":"Point"}
}