{
  "type": "Feature",
  "properties": {
    "gn:admin1_code":"25.0",
    "gn:admin2_code":"1501.0",
    "gn:asciiname":"Al Ma'ana",
    "gn:country_code":"YE",
    "gn:dem":1086,
    "gn:feature_class":"P",
    "gn:feature_code":"PPL",
    "gn:name":"Al Ma\u2019ana",
    "gn:population":0,
    "gn:timezone":"Asia/Aden",
    "iso:country":"YE",
    "name:und_x_variant":[
        "Al Ma\u2019ana"
    ],
    "wof:name":"Al Ma'ana",
    "wof:placetype":"locality"
},
  "geometry": {"coordinates":[44.31667,13.51667],"type":"Point"}
}