{
  "type": "Feature",
  "properties": {
    "gn:admin1_code":"23.0",
    "gn:admin2_code":"1111.0",
    "gn:asciiname":"Hujanah Bani `Imran",
    "gn:country_code":"YE",
    "gn:dem":1070,
    "gn:feature_class":"P",
    "gn:feature_code":"PPL",
    "gn:name":"Huj\u0101nah Ban\u012b \u2018Imr\u0101n",
    "gn:population":0,
    "gn:timezone":"Asia/Aden",
    "iso:country":"YE",
    "name:und_x_variant":[
        "Huj\u0101nah Ban\u012b \u2018Imr\u0101n"
    ],
    "wof:name":"Hujanah Bani `Imran",
    "wof:placetype":"locality"
},
  "geometry": {"coordinates":[43.87307,14.07358],"type":"Point"}
}