{
  "type": "Feature",
  "properties": {
    "gn:admin1_code":"23.0",
    "gn:admin2_code":"1105.0",
    "gn:asciiname":"Ribat as Sarimah",
    "gn:country_code":"YE",
    "gn:dem":3127,
    "gn:feature_class":"P",
    "gn:feature_code":"PPL",
    "gn:name":"Rib\u0101\u0163 as Sar\u012bmah",
    "gn:population":0,
    "gn:timezone":"Asia/Aden",
    "iso:country":"YE",
    "name:ara_x_preferred":[
        "\u0631\u0628\u0627\u0637 \u0627\u0644\u0633\u0631\u064a\u0645\u0629"
    ],
    "name:und_x_variant":[
        "Rib\u0101\u0163 as Saryamah",
        "Rib\u0101\u0163 as Sar\u012bmah"
    ],
    "wof:name":"Ribat as Sarimah",
    "wof:placetype":"locality"
},
  "geometry": {"coordinates":[44.33127,14.06523],"type":"Point"}
}