{
  "type": "Feature",
  "properties": {
    "gn:country":"YE",
    "gn:fcode":"PPL",
    "gn:population":8,
    "iso:country":"YE",
    "name:ara_x_preferred":[
        "Al Jiz\u0101r"
    ],
    "name:ara_x_variant":[
        "\u0627\u0644\u062c\u0632\u0627\u0631"
    ],
    "name:eng_x_preferred":[
        "Al Jizar"
    ],
    "name:eng_x_variant":[
        "Al Mashri\u1e29ah"
    ],
    "qs:name":"Al Jiz\u0101r",
    "qs:photos_9r":0,
    "qs:photos_sr":0,
    "qs:pop_sr":"1",
    "wof:name":"Al Jiz\u0101r",
    "wof:placetype":"locality",
    "wof:population":8
},
  "geometry": {"coordinates":[45.2491,14.06166],"type":"Point"}
}