{
  "type": "Feature",
  "properties": {
    "gn:admin1_code":"19.0",
    "gn:admin2_code":"2904.0",
    "gn:asciiname":"Al Hijab",
    "gn:country_code":"YE",
    "gn:dem":1346,
    "gn:feature_class":"P",
    "gn:feature_code":"PPL",
    "gn:name":"Al \u1e28ij\u0101b",
    "gn:population":0,
    "gn:timezone":"Asia/Aden",
    "iso:country":"YE",
    "name:ara_x_preferred":[
        "Al \u1e28ij\u0101b"
    ],
    "name:ara_x_variant":[
        "\u0627\u0644\u062d\u062c\u0627\u0628"
    ],
    "wof:name":"Al Hijab",
    "wof:placetype":"locality"
},
  "geometry": {"coordinates":[43.72098,16.33661],"type":"Point"}
}