{
  "type": "Feature",
  "properties": {
    "gn:admin1_code":"5.0",
    "gn:admin2_code":"2113.0",
    "gn:asciiname":"Qawban",
    "gn:country_code":"YE",
    "gn:dem":1213,
    "gn:feature_class":"P",
    "gn:feature_code":"PPL",
    "gn:name":"Qawb\u0101n",
    "gn:population":0,
    "gn:timezone":"Asia/Aden",
    "iso:country":"YE",
    "name:ara_x_preferred":[
        "\u0642\u0648\u0628\u0627\u0646"
    ],
    "name:und_x_variant":[
        "Qauban",
        "Qawb\u0101n"
    ],
    "wof:name":"Qawban",
    "wof:placetype":"locality"
},
  "geometry": {"coordinates":[46.82001,14.44714],"type":"Point"}
}