{
  "type": "Feature",
  "properties": {
    "gn:admin1_code":"23.0",
    "gn:admin2_code":"1107.0",
    "gn:asciiname":"Hisn Ghundil",
    "gn:country_code":"YE",
    "gn:dem":2410,
    "gn:feature_class":"P",
    "gn:feature_code":"PPL",
    "gn:name":"\u1e28i\u015fn Ghundil",
    "gn:population":0,
    "gn:timezone":"Asia/Aden",
    "iso:country":"YE",
    "name:ara_x_preferred":[
        "\u1e28i\u015fn Ghundil"
    ],
    "name:ara_x_variant":[
        "\u062d\u0635\u0646 \u063a\u0646\u062f\u0644"
    ],
    "name:und_x_variant":[
        "\u1e28i\u015fn Ghandal"
    ],
    "wof:name":"Hisn Ghundil",
    "wof:placetype":"locality"
},
  "geometry": {"coordinates":[44.21421,14.05903],"type":"Point"}
}