{
  "type": "Feature",
  "properties": {
    "gn:admin1_code":"19.0",
    "gn:admin2_code":"2912.0",
    "gn:asciiname":"Bayt al `Urri",
    "gn:country_code":"YE",
    "gn:dem":1520,
    "gn:feature_class":"P",
    "gn:feature_code":"PPL",
    "gn:name":"Bayt al \u2018Urr\u012b",
    "gn:population":0,
    "gn:timezone":"Asia/Aden",
    "iso:country":"YE",
    "name:und_x_variant":[
        "Bayt al \u2018Urr\u012b"
    ],
    "wof:name":"Bayt al `Urri",
    "wof:placetype":"locality"
},
  "geometry": {"coordinates":[43.79906,15.88421],"type":"Point"}
}