{
  "type": "Feature",
  "properties": {
    "gn:admin1_code":"10.0",
    "gn:admin2_code":"2709.0",
    "gn:asciiname":"Hubaysh",
    "gn:country_code":"YE",
    "gn:dem":1586,
    "gn:feature_class":"P",
    "gn:feature_code":"PPL",
    "gn:name":"\u1e28ubaysh",
    "gn:population":0,
    "gn:timezone":"Asia/Aden",
    "iso:country":"YE",
    "name:und_x_variant":[
        "\u1e28ubaysh"
    ],
    "wof:name":"Hubaysh",
    "wof:placetype":"locality"
},
  "geometry": {"coordinates":[43.50792,15.46438],"type":"Point"}
}