{
  "type": "Feature",
  "properties": {
    "gn:country":"YE",
    "gn:fcode":"PPL",
    "gn:population":20,
    "iso:country":"YE",
    "name:ara_x_preferred":[
        "\u0627\u0644\u062d\u0642\u0644\u064a\u0646"
    ],
    "name:eng_x_preferred":[
        "Al Haqlayn"
    ],
    "name:eng_x_variant":[
        "Al Kar\u0101nah"
    ],
    "qs:name":"Al \u1e28aqlayn",
    "qs:photos_9r":0,
    "qs:photos_sr":0,
    "qs:pop_sr":"1",
    "wof:name":"Al \u1e28aqlayn",
    "wof:placetype":"locality",
    "wof:population":20
},
  "geometry": {"coordinates":[43.3786,17.28792],"type":"Point"}
}