{
  "type": "Feature",
  "properties": {
    "gn:admin1_code":"25.0",
    "gn:admin2_code":"1513.0",
    "gn:asciiname":"Masaliq",
    "gn:country_code":"YE",
    "gn:dem":1330,
    "gn:feature_class":"P",
    "gn:feature_code":"PPL",
    "gn:name":"Mas\u0101liq",
    "gn:population":0,
    "gn:timezone":"Asia/Aden",
    "iso:country":"YE",
    "name:und_x_variant":[
        "Mas\u0101liq"
    ],
    "wof:name":"Masaliq",
    "wof:placetype":"locality"
},
  "geometry": {"coordinates":[44.15054,13.51656],"type":"Point"}
}