{
  "type": "Feature",
  "properties": {
    "gn:admin1_code":"22.0",
    "gn:admin2_code":"1703.0",
    "gn:asciiname":"Bani al Khal",
    "gn:country_code":"YE",
    "gn:dem":27,
    "gn:feature_class":"P",
    "gn:feature_code":"PPL",
    "gn:name":"Ban\u012b al Kh\u0101l",
    "gn:population":0,
    "gn:timezone":"Asia/Aden",
    "iso:country":"YE",
    "name:ara_x_preferred":[
        "\u0628\u0646\u064a \u0627\u0644\u062e\u0627\u0644"
    ],
    "name:und_x_variant":[
        "Ban\u012b al Kh\u0101l"
    ],
    "wof:name":"Bani al Khal",
    "wof:placetype":"locality"
},
  "geometry": {"coordinates":[42.90477,15.97603],"type":"Point"}
}