{
  "type": "Feature",
  "properties": {
    "gn:admin1_code":"22.0",
    "gn:admin2_code":"1711.0",
    "gn:asciiname":"Dayr az Zubri",
    "gn:country_code":"YE",
    "gn:dem":409,
    "gn:feature_class":"P",
    "gn:feature_code":"PPL",
    "gn:name":"Dayr az\u0327 Z\u0327ubr\u012b",
    "gn:population":0,
    "gn:timezone":"Asia/Aden",
    "iso:country":"YE",
    "name:und_x_variant":[
        "Dayr az\u0327 Z\u0327ubr\u012b"
    ],
    "wof:name":"Dayr az Zubri",
    "wof:placetype":"locality"
},
  "geometry": {"coordinates":[43.36257,15.98237],"type":"Point"}
}