{
  "type": "Feature",
  "properties": {
    "gn:country":"YE",
    "gn:fcode":"PPL",
    "gn:pop":11,
    "iso:country":"YE",
    "name:ara_x_preferred":[
        "\u062c\u0648\u064a\u0641\u0627\u0646"
    ],
    "name:eng_x_preferred":[
        "Juwayfan"
    ],
    "name:eng_x_variant":[
        "\u0100l Riss\u0101m"
    ],
    "qs:name":"Juwayf\u0101n",
    "qs:photos_9r":0,
    "qs:photos_sr":0,
    "qs:pop_sr":"1",
    "wof:name":"Juwayf\u0101n",
    "wof:placetype":"locality",
    "wof:population":11
},
  "geometry": {"coordinates":[46.28272,16.63398],"type":"Point"}
}