{
  "type": "Feature",
  "properties": {
    "gn:country":"YE",
    "gn:fcode":"PPLX",
    "gn:pop":15,
    "iso:country":"YE",
    "name:ara_x_preferred":[
        "Ar R\u016bs"
    ],
    "name:ara_x_variant":[
        "\u0627\u0644\u0631\u0648\u0633"
    ],
    "qs:name":"Ar R\u016bs",
    "qs:photos_9r":0,
    "qs:photos_sr":0,
    "qs:pop_sr":"1",
    "wd:wordcount":58,
    "wof:name":"Ar R\u016bs",
    "wof:placetype":"neighbourhood",
    "wof:population":15
},
  "geometry": {"coordinates":[43.64539,16.22539],"type":"Point"}
}