{
  "type": "Feature",
  "properties": {
    "gn:country":"YE",
    "gn:fcode":"PPLX",
    "gn:pop":15,
    "iso:country":"YE",
    "name:ara_x_preferred":[
        "Ar R\u016bs"
    ],
    "name:ara_x_variant":[
        "\u0627\u0644\u0631\u0648\u0633",
        "\u0645\u062f\u064a\u0631\u064a\u0629 \u0628\u0644\u0627\u062f \u0627\u0644\u0631\u0648\u0633"
    ],
    "name:ceb_x_preferred":[
        "Bilad Ar Rus"
    ],
    "name:eng_x_preferred":[
        "Bilad Ar Rus District"
    ],
    "name:fra_x_preferred":[
        "Bilad Ar Rus"
    ],
    "name:nan_x_preferred":[
        "Bilad Ar Rus Ko\u0101n"
    ],
    "name:urd_x_preferred":[
        "\u0628\u0644\u0627\u062f \u0627\u0644\u0631\u0648\u0633 \u0636\u0644\u0639"
    ],
    "name:vie_x_preferred":[
        "Bilad Ar Rus"
    ],
    "qs:name":"Ar R\u016bs",
    "qs:photos_9r":0,
    "qs:photos_sr":0,
    "qs:pop_sr":"1",
    "wd:wordcount":58,
    "wof:name":"Ar R\u016bs",
    "wof:placetype":"neighbourhood",
    "wof:population":15
},
  "geometry": {"coordinates":[43.64539,16.22539],"type":"Point"}
}