{
  "type": "Feature",
  "properties": {
    "gn:admin1_code":"8.0",
    "gn:admin2_code":"1810.0",
    "gn:asciiname":"Dayr Qaml ash Sharq",
    "gn:country_code":"YE",
    "gn:dem":140,
    "gn:feature_class":"P",
    "gn:feature_code":"PPL",
    "gn:name":"Dayr Qaml ash Sharq",
    "gn:population":0,
    "gn:timezone":"Asia/Aden",
    "iso:country":"YE",
    "name:ara_x_preferred":[
        "\u062f\u064a\u0631 \u0642\u0645\u0644 \u0627\u0644\u0634\u0631\u0642"
    ],
    "name:und_x_variant":[
        "Dayr Qaml",
        "Dayr Qaml ash Sharq",
        "Dayr Qummal"
    ],
    "wof:name":"Dayr Qaml ash Sharq",
    "wof:placetype":"locality"
},
  "geometry": {"coordinates":[43.20844,15.06331],"type":"Point"}
}