{
  "type": "Feature",
  "properties": {
    "gn:admin1_code":"19.0",
    "gn:admin2_code":"2920.0",
    "gn:asciiname":"Bayt Zimam",
    "gn:country_code":"YE",
    "gn:dem":2223,
    "gn:feature_class":"P",
    "gn:feature_code":"PPL",
    "gn:name":"Bayt Zim\u0101m",
    "gn:population":0,
    "gn:timezone":"Asia/Aden",
    "iso:country":"YE",
    "name:ara_x_preferred":[
        "\u0628\u064a\u062a \u0632\u0645\u0627\u0645"
    ],
    "name:und_x_variant":[
        "Bayt Zim\u0101m"
    ],
    "wof:name":"Bayt Zimam",
    "wof:placetype":"locality"
},
  "geometry": {"coordinates":[44.01925,16.07518],"type":"Point"}
}