{
  "type": "Feature",
  "properties": {
    "gn:admin1_code":"22.0",
    "gn:admin2_code":"1725.0",
    "gn:asciiname":"Qufasah",
    "gn:country_code":"YE",
    "gn:dem":830,
    "gn:feature_class":"P",
    "gn:feature_code":"PPL",
    "gn:name":"Quf\u0101\u015fah",
    "gn:population":0,
    "gn:timezone":"Asia/Aden",
    "iso:country":"YE",
    "name:ara_x_preferred":[
        "\u0642\u0641\u0627\u0635\u0629"
    ],
    "name:und_x_variant":[
        "Quf\u0101\u015fah"
    ],
    "wof:name":"Qufasah",
    "wof:placetype":"locality"
},
  "geometry": {"coordinates":[43.52057,15.574],"type":"Point"}
}