{
  "type": "Feature",
  "properties": {
    "gn:country":"YE",
    "gn:fcode":"PPL",
    "gn:pop":6,
    "iso:country":"YE",
    "name:ara_x_preferred":[
        "\u0630\u0648 \u0628\u064a\u062d\u0627\u0646"
    ],
    "name:eng_x_preferred":[
        "DhU Bayhan"
    ],
    "qs:name":"Dh\u016b Bay\u1e29\u0101n",
    "qs:photos_9r":0,
    "qs:photos_sr":0,
    "qs:pop_sr":"1",
    "wof:name":"Dh\u016b Bay\u1e29\u0101n",
    "wof:placetype":"locality",
    "wof:population":6
},
  "geometry": {"coordinates":[43.67969,16.48361],"type":"Point"}
}