{
  "type": "Feature",
  "properties": {
    "gn:admin1_code":"8.0",
    "gn:admin2_code":"1818.0",
    "gn:asciiname":"Kadawih al Asha`ir",
    "gn:country_code":"YE",
    "gn:dem":574,
    "gn:feature_class":"P",
    "gn:feature_code":"PPL",
    "gn:name":"Kadawi\u1e29 al Ash\u0101\u2018ir",
    "gn:population":0,
    "gn:timezone":"Asia/Aden",
    "iso:country":"YE",
    "name:und_x_variant":[
        "Kadawi\u1e29 al Ash\u0101\u2018ir"
    ],
    "wof:name":"Kadawih al Asha`ir",
    "wof:placetype":"locality"
},
  "geometry": {"coordinates":[43.71141,14.00758],"type":"Point"}
}