{
  "type": "Feature",
  "properties": {
    "gn:admin1_code":"8.0",
    "gn:admin2_code":"1801.0",
    "gn:asciiname":"Al Khazawimah",
    "gn:country_code":"YE",
    "gn:dem":166,
    "gn:feature_class":"P",
    "gn:feature_code":"PPL",
    "gn:name":"Al Khaz\u0101wimah",
    "gn:population":0,
    "gn:timezone":"Asia/Aden",
    "iso:country":"YE",
    "name:und_x_variant":[
        "Al Khaz\u0101wimah"
    ],
    "wof:name":"Al Khazawimah",
    "wof:placetype":"locality"
},
  "geometry": {"coordinates":[43.21339,15.75588],"type":"Point"}
}