{
  "type": "Feature",
  "properties": {
    "gn:country":"YE",
    "gn:fcode":"PPL",
    "gn:pop":9,
    "iso:country":"YE",
    "name:ara_x_preferred":[
        "\u0648\u0627\u062f\u064a \u0627\u0644\u0641\u0644\u062c"
    ],
    "name:eng_x_preferred":[
        "Wadi Al Falaj"
    ],
    "name:eng_x_variant":[
        "Qullat as Sidd\u0101d"
    ],
    "qs:name":"W\u0101d\u012b al Falaj",
    "qs:photos_9r":0,
    "qs:photos_sr":0,
    "qs:pop_sr":"1",
    "wof:name":"W\u0101d\u012b al Falaj",
    "wof:placetype":"locality",
    "wof:population":9
},
  "geometry": {"coordinates":[43.25848,17.15557],"type":"Point"}
}