{
  "type": "Feature",
  "properties": {
    "gn:country":"YE",
    "gn:fcode":"PPL",
    "gn:population":3,
    "iso:country":"YE",
    "name:ara_x_preferred":[
        "Dh\u016b N\u0101j\u012b"
    ],
    "name:ara_x_variant":[
        "\u0630\u0648 \u0646\u0627\u062c\u064a"
    ],
    "name:eng_x_preferred":[
        "DhU Naji"
    ],
    "name:eng_x_variant":[
        "Al Marq\u012b"
    ],
    "qs:name":"Dh\u016b N\u0101j\u012b",
    "qs:photos_9r":0,
    "qs:photos_sr":0,
    "qs:pop_sr":"1",
    "wof:name":"Dh\u016b N\u0101j\u012b",
    "wof:placetype":"locality",
    "wof:population":3
},
  "geometry": {"coordinates":[43.67779,16.25976],"type":"Point"}
}