{
  "type": "Feature",
  "properties": {
    "gn:admin1_code":"19.0",
    "gn:admin2_code":"2908.0",
    "gn:asciiname":"Mahall Jamil",
    "gn:country_code":"YE",
    "gn:dem":875,
    "gn:feature_class":"P",
    "gn:feature_code":"PPL",
    "gn:name":"Ma\u1e29all Jam\u012bl",
    "gn:population":0,
    "gn:timezone":"Asia/Aden",
    "iso:country":"YE",
    "name:und_x_variant":[
        "Ma\u1e29all Jam\u012bl"
    ],
    "wof:name":"Mahall Jamil",
    "wof:placetype":"locality"
},
  "geometry": {"coordinates":[43.69144,15.98701],"type":"Point"}
}