{
  "type": "Feature",
  "properties": {
    "gn:admin1_code":"24.0",
    "gn:admin2_code":"2510.0",
    "gn:asciiname":"Al Mad-hur",
    "gn:country_code":"YE",
    "gn:dem":1318,
    "gn:feature_class":"P",
    "gn:feature_code":"PPL",
    "gn:name":"Al Mad-h\u016br",
    "gn:population":0,
    "gn:timezone":"Asia/Aden",
    "iso:country":"YE",
    "name:und_x_variant":[
        "Al Mad-h\u016br"
    ],
    "wof:name":"Al Mad-hur",
    "wof:placetype":"locality"
},
  "geometry": {"coordinates":[44.34447,13.29434],"type":"Point"}
}