{
  "type": "Feature",
  "properties": {
    "gn:admin1_code":"8.0",
    "gn:admin2_code":"1807.0",
    "gn:asciiname":"Barkhal as Saghir",
    "gn:country_code":"YE",
    "gn:dem":86,
    "gn:feature_class":"P",
    "gn:feature_code":"PPL",
    "gn:name":"Barkhal a\u015f \u015eagh\u012br",
    "gn:population":0,
    "gn:timezone":"Asia/Aden",
    "iso:country":"YE",
    "name:ara_x_preferred":[
        "\u0628\u0631\u062e\u0644 \u0627\u0644\u0635\u063a\u064a\u0631"
    ],
    "name:und_x_variant":[
        "Barkhal a\u015f \u015eagh\u012br"
    ],
    "wof:name":"Barkhal as Saghir",
    "wof:placetype":"locality"
},
  "geometry": {"coordinates":[43.09046,15.30135],"type":"Point"}
}