{
  "type": "Feature",
  "properties": {
    "gn:admin1_code":"1.0",
    "gn:admin2_code":"1211.0",
    "gn:asciiname":"Umm Sawad",
    "gn:country_code":"YE",
    "gn:dem":417,
    "gn:feature_class":"P",
    "gn:feature_code":"PPL",
    "gn:name":"Umm Saw\u0101d",
    "gn:population":0,
    "gn:timezone":"Asia/Aden",
    "iso:country":"YE",
    "name:ara_x_preferred":[
        "\u0623\u0645 \u0633\u0648\u0627\u062f"
    ],
    "name:und_x_variant":[
        "Am Saw\u0101d",
        "Al Sawad Husen",
        "As Saw\u0101d",
        "Umm Saw\u0101d"
    ],
    "wof:name":"Umm Sawad",
    "wof:placetype":"locality"
},
  "geometry": {"coordinates":[45.56206,13.48388],"type":"Point"}
}