{
  "type": "Feature",
  "properties": {
    "gn:admin1_code":"19.0",
    "gn:admin2_code":"2919.0",
    "gn:asciiname":"Darbayn",
    "gn:country_code":"YE",
    "gn:dem":2648,
    "gn:feature_class":"P",
    "gn:feature_code":"PPL",
    "gn:name":"Darbayn",
    "gn:population":0,
    "gn:timezone":"Asia/Aden",
    "iso:country":"YE",
    "wof:name":"Darbayn",
    "wof:placetype":"locality"
},
  "geometry": {"coordinates":[43.96227,15.89389],"type":"Point"}
}