{
  "type": "Feature",
  "properties": {
    "gn:admin1_code":"19.0",
    "gn:admin2_code":"2919.0",
    "gn:asciiname":"Al Malahah",
    "gn:country_code":"YE",
    "gn:dem":2148,
    "gn:feature_class":"P",
    "gn:feature_code":"PPL",
    "gn:name":"Al Mal\u0101\u1e29ah",
    "gn:population":0,
    "gn:timezone":"Asia/Aden",
    "iso:country":"YE",
    "name:ara_x_preferred":[
        "\u0627\u0644\u0645\u0644\u0627\u062d\u0629"
    ],
    "name:und_x_variant":[
        "Al Mal\u0101\u1e29ah"
    ],
    "wof:name":"Al Malahah",
    "wof:placetype":"locality"
},
  "geometry": {"coordinates":[43.90506,16.00999],"type":"Point"}
}