{
  "type": "Feature",
  "properties": {
    "gn:admin1_code":"19.0",
    "gn:admin2_code":"2903.0",
    "gn:asciiname":"Ash Shurtah",
    "gn:country_code":"YE",
    "gn:dem":1184,
    "gn:feature_class":"P",
    "gn:feature_code":"PPL",
    "gn:name":"Ash Shur\u0163ah",
    "gn:population":0,
    "gn:timezone":"Asia/Aden",
    "iso:country":"YE",
    "name:ara_x_preferred":[
        "\u0627\u0644\u0634\u0631\u0637\u0629"
    ],
    "name:und_x_variant":[
        "Ash Shur\u0163ah"
    ],
    "wof:name":"Ash Shurtah",
    "wof:placetype":"locality"
},
  "geometry": {"coordinates":[43.84548,16.22039],"type":"Point"}
}