{
  "type": "Feature",
  "properties": {
    "gn:admin1_code":"18.0",
    "gn:admin2_code":"3009.0",
    "gn:asciiname":"`Atabah",
    "gn:country_code":"YE",
    "gn:dem":1865,
    "gn:feature_class":"P",
    "gn:feature_code":"PPL",
    "gn:name":"\u2018At\u0101bah",
    "gn:population":0,
    "gn:timezone":"Asia/Aden",
    "iso:country":"YE",
    "name:und_x_variant":[
        "Al Atabah",
        "Ataba",
        "\u2018At\u0101bah",
        "\u2018Atabah"
    ],
    "wof:name":"`Atabah",
    "wof:placetype":"locality"
},
  "geometry": {"coordinates":[44.48328,13.68154],"type":"Point"}
}