{
  "type": "Feature",
  "properties": {
    "gn:country":"YE",
    "gn:fcode":"PPL",
    "gn:population":6,
    "iso:country":"YE",
    "name:ara_x_preferred":[
        "\u0630\u0647\u0628\u0629"
    ],
    "name:eng_x_preferred":[
        "Dhibah"
    ],
    "name:vie_x_preferred":[
        "Sa'adah"
    ],
    "qs:name":"Dhibah",
    "qs:photos_9r":0,
    "qs:photos_sr":0,
    "qs:pop_sr":"1",
    "wof:name":"Dhibah",
    "wof:placetype":"locality",
    "wof:population":6
},
  "geometry": {"coordinates":[44.06464,17.04],"type":"Point"}
}