{
  "type": "Feature",
  "properties": {
    "gn:admin1_code":"10.0",
    "gn:admin2_code":"2707.0",
    "gn:asciiname":"Al Qari",
    "gn:country_code":"YE",
    "gn:dem":1063,
    "gn:feature_class":"P",
    "gn:feature_code":"PPL",
    "gn:name":"Al Q\u0101r\u012b",
    "gn:population":0,
    "gn:timezone":"Asia/Aden",
    "iso:country":"YE",
    "name:ara_x_preferred":[
        "Al Q\u0101r\u012b"
    ],
    "wof:name":"Al Qari",
    "wof:placetype":"locality"
},
  "geometry": {"coordinates":[43.47968,15.12152],"type":"Point"}
}