{
  "type": "Feature",
  "properties": {
    "gn:admin1_code":"23.0",
    "gn:admin2_code":"1101.0",
    "gn:asciiname":"Qashurah",
    "gn:country_code":"YE",
    "gn:dem":1227,
    "gn:feature_class":"P",
    "gn:feature_code":"PPL",
    "gn:name":"Q\u0101sh\u016brah",
    "gn:population":0,
    "gn:timezone":"Asia/Aden",
    "iso:country":"YE",
    "name:ara_x_preferred":[
        "\u0642\u0627\u0634\u0648\u0631\u0629"
    ],
    "name:und_x_variant":[
        "Q\u0101sh\u016brah"
    ],
    "wof:name":"Qashurah",
    "wof:placetype":"locality"
},
  "geometry": {"coordinates":[44.04361,14.37435],"type":"Point"}
}