{
  "type": "Feature",
  "properties": {
    "gn:admin1_code":"24.0",
    "gn:admin2_code":"2513.0",
    "gn:asciiname":"Al Fassayah",
    "gn:country_code":"YE",
    "gn:dem":198,
    "gn:feature_class":"P",
    "gn:feature_code":"PPL",
    "gn:name":"Al Fass\u0101yah",
    "gn:population":0,
    "gn:timezone":"Asia/Aden",
    "iso:country":"YE",
    "name:und_x_variant":[
        "Al Fass\u0101yah"
    ],
    "wof:name":"Al Fassayah",
    "wof:placetype":"locality"
},
  "geometry": {"coordinates":[44.05093,12.85198],"type":"Point"}
}