{
  "type": "Feature",
  "properties": {
    "gn:country":"YE",
    "gn:fcode":"PPL",
    "gn:population":3,
    "iso:country":"YE",
    "name:ara_x_preferred":[
        "\u063a\u0627\u0631\u0628 \u0627\u0644\u0637\u0648\u064a\u0644"
    ],
    "name:eng_x_preferred":[
        "Gharib At Tawil"
    ],
    "name:eng_x_variant":[
        "Ad Dib\u0101y\u0101t"
    ],
    "qs:name":"Gh\u0101rib a\u0163 \u0162aw\u012bl",
    "qs:photos_9r":0,
    "qs:photos_sr":0,
    "qs:pop_sr":"1",
    "wof:name":"Gh\u0101rib a\u0163 \u0162aw\u012bl",
    "wof:placetype":"locality",
    "wof:population":3
},
  "geometry": {"coordinates":[43.30759,16.64234],"type":"Point"}
}