{
  "type": "Feature",
  "properties": {
    "gn:country":"YE",
    "gn:fcode":"PPL",
    "gn:pop":5,
    "iso:country":"YE",
    "name:ara_x_preferred":[
        "\u0642\u0634\u0639 \u0627\u0644\u0645\u0648\u0633\u0637\u0629"
    ],
    "name:ara_x_variant":[
        "\u0627\u0644\u0642\u0634\u0639"
    ],
    "name:unk_x_variant":[
        "Al Qash\u2018"
    ],
    "qs:name":"Qash\u2018 al Mawsi\u0163ah",
    "qs:photos_9r":0,
    "qs:photos_sr":0,
    "qs:pop_sr":"1",
    "wof:name":"Qash\u2018 al Mawsi\u0163ah",
    "wof:placetype":"locality",
    "wof:population":5
},
  "geometry": {"coordinates":[45.49707,14.98466],"type":"Point"}
}