{
  "type": "Feature",
  "properties": {
    "gn:admin1_code":"23.0",
    "gn:admin2_code":"1108.0",
    "gn:asciiname":"Al Khadharif",
    "gn:country_code":"YE",
    "gn:dem":1784,
    "gn:feature_class":"P",
    "gn:feature_code":"PPL",
    "gn:name":"Al Khadh\u0101rif",
    "gn:population":0,
    "gn:timezone":"Asia/Aden",
    "iso:country":"YE",
    "name:ara_x_preferred":[
        "\u0627\u0644\u062e\u0630\u0627\u0631\u0641"
    ],
    "name:und_x_variant":[
        "Al Khadh\u0101rif"
    ],
    "wof:name":"Al Khadharif",
    "wof:placetype":"locality"
},
  "geometry": {"coordinates":[44.13013,14.08827],"type":"Point"}
}