{
  "type": "Feature",
  "properties": {
    "gn:country":"YE",
    "gn:fcode":"PPL",
    "gn:population":2,
    "iso:country":"YE",
    "name:ara_x_preferred":[
        "Al Mut\u0101rris"
    ],
    "name:ara_x_variant":[
        "\u0627\u0644\u0645\u062a\u0627\u0631\u0633"
    ],
    "qs:name":"Al Mut\u0101rris",
    "qs:photos_9r":0,
    "qs:photos_sr":0,
    "qs:pop_sr":"1",
    "wof:name":"Al Mut\u0101rris",
    "wof:placetype":"locality",
    "wof:population":2
},
  "geometry": {"coordinates":[43.31127,16.74233],"type":"Point"}
}