{
  "type": "Feature",
  "properties": {
    "gn:admin1_code":"23.0",
    "gn:admin2_code":"1106.0",
    "gn:asciiname":"Al Jaramiz",
    "gn:country_code":"YE",
    "gn:dem":2595,
    "gn:feature_class":"P",
    "gn:feature_code":"PPL",
    "gn:name":"Al Jar\u0101miz",
    "gn:population":0,
    "gn:timezone":"Asia/Aden",
    "iso:country":"YE",
    "name:ara_x_preferred":[
        "\u0627\u0644\u062c\u0631\u0627\u0645\u0632"
    ],
    "name:und_x_variant":[
        "Al Jar\u0101m\u012bz",
        "Al Jar\u0101miz"
    ],
    "wof:name":"Al Jaramiz",
    "wof:placetype":"locality"
},
  "geometry": {"coordinates":[44.35734,14.16559],"type":"Point"}
}