{
  "type": "Feature",
  "properties": {
    "gn:country":"YE",
    "gn:fcode":"PPL",
    "gn:population":4,
    "iso:country":"YE",
    "name:ara_x_preferred":[
        "\u0627\u0644\u0645\u0633\u0627\u0647\u0631\u0629"
    ],
    "name:eng_x_preferred":[
        "Al Misahirah"
    ],
    "name:eng_x_variant":[
        "Al Jalb\u016bb"
    ],
    "qs:name":"Al Mis\u0101hirah",
    "qs:photos_9r":0,
    "qs:photos_sr":0,
    "qs:pop_sr":"1",
    "wof:name":"Al Mis\u0101hirah",
    "wof:placetype":"locality",
    "wof:population":4
},
  "geometry": {"coordinates":[43.32912,16.08581],"type":"Point"}
}