{
  "type": "Feature",
  "properties": {
    "gn:admin1_code":"11.0",
    "gn:admin2_code":"2007.0",
    "gn:asciiname":"Shi`b Ruman",
    "gn:country_code":"YE",
    "gn:dem":1044,
    "gn:feature_class":"P",
    "gn:feature_code":"PPL",
    "gn:name":"Shi\u2018b Rum\u0101n",
    "gn:population":0,
    "gn:timezone":"Asia/Aden",
    "iso:country":"YE",
    "name:ara_x_preferred":[
        "Shi\u2018b Rum\u0101n"
    ],
    "wof:name":"Shi`b Ruman",
    "wof:placetype":"locality"
},
  "geometry": {"coordinates":[43.60961,14.2519],"type":"Point"}
}