{
  "type": "Feature",
  "properties": {
    "gn:admin1_code":"16.0",
    "gn:admin2_code":"2316.0",
    "gn:asciiname":"Al Khaw`ah",
    "gn:country_code":"YE",
    "gn:dem":2264,
    "gn:feature_class":"P",
    "gn:feature_code":"PPL",
    "gn:name":"Al Khaw\u2018ah",
    "gn:population":0,
    "gn:timezone":"Asia/Aden",
    "iso:country":"YE",
    "name:und_x_variant":[
        "Al Khaw\u2018ah"
    ],
    "wof:name":"Al Khaw`ah",
    "wof:placetype":"locality"
},
  "geometry": {"coordinates":[44.46061,15.11805],"type":"Point"}
}