{
  "type": "Feature",
  "properties": {
    "gn:admin1_code":"14.0",
    "gn:asciiname":"Al `Irq",
    "gn:country_code":"YE",
    "gn:dem":1762,
    "gn:feature_class":"P",
    "gn:feature_code":"PPL",
    "gn:name":"Al \u2018Irq",
    "gn:population":0,
    "gn:timezone":"Asia/Aden",
    "iso:country":"YE",
    "name:ara_x_preferred":[
        "\u0627\u0644\u0639\u0631\u0642"
    ],
    "name:und_x_variant":[
        "Al \u2018Irq"
    ],
    "wof:name":"Al `Irq",
    "wof:placetype":"locality"
},
  "geometry": {"coordinates":[44.70414,16.44593],"type":"Point"}
}