{
  "type": "Feature",
  "properties": {
    "gn:admin1_code":"16.0",
    "gn:admin2_code":"2316.0",
    "gn:asciiname":"Bani Ghunaym",
    "gn:country_code":"YE",
    "gn:dem":2178,
    "gn:feature_class":"P",
    "gn:feature_code":"PPL",
    "gn:name":"Ban\u012b Ghunaym",
    "gn:population":0,
    "gn:timezone":"Asia/Aden",
    "iso:country":"YE",
    "name:und_x_variant":[
        "Ban\u012b Ghunaym"
    ],
    "wof:name":"Bani Ghunaym",
    "wof:placetype":"locality"
},
  "geometry": {"coordinates":[44.52814,15.18743],"type":"Point"}
}