{
  "type": "Feature",
  "properties": {
    "gn:admin1_code":"15.0",
    "gn:admin2_code":"2209.0",
    "gn:asciiname":"Al `Arabah",
    "gn:country_code":"YE",
    "gn:dem":2127,
    "gn:feature_class":"P",
    "gn:feature_code":"PPL",
    "gn:name":"Al \u2018Ar\u0101bah",
    "gn:population":0,
    "gn:timezone":"Asia/Aden",
    "iso:country":"YE",
    "name:ara_x_preferred":[
        "\u0627\u0644\u0639\u0631\u0627\u0628\u0629"
    ],
    "name:und_x_variant":[
        "Al \u2018Ar\u0101bah"
    ],
    "wof:name":"Al `Arabah",
    "wof:placetype":"locality"
},
  "geometry": {"coordinates":[43.43756,16.90581],"type":"Point"}
}