{
  "type": "Feature",
  "properties": {
    "gn:admin1_code":"25.0",
    "gn:admin2_code":"1502.0",
    "gn:asciiname":"Al Khums",
    "gn:country_code":"YE",
    "gn:dem":1533,
    "gn:feature_class":"P",
    "gn:feature_code":"PPL",
    "gn:name":"Al Khums",
    "gn:population":0,
    "gn:timezone":"Asia/Aden",
    "iso:country":"YE",
    "name:ara_x_preferred":[
        "\u0627\u0644\u062e\u0645\u0633"
    ],
    "name:bel_x_preferred":[
        "\u0410\u043b\u044c-\u0425\u0443\u043c\u0441"
    ],
    "name:bul_x_preferred":[
        "\u0425\u0443\u043c\u0441"
    ],
    "name:cat_x_preferred":[
        "Homs"
    ],
    "name:ceb_x_preferred":[
        "Al Khums"
    ],
    "name:deu_x_preferred":[
        "Al-Chums"
    ],
    "name:epo_x_preferred":[
        "Al \u0124ums"
    ],
    "name:eus_x_preferred":[
        "Khums"
    ],
    "name:fas_x_preferred":[
        "\u0627\u0644\u062e\u0645\u0633"
    ],
    "name:fin_x_preferred":[
        "Al Khums"
    ],
    "name:fra_x_preferred":[
        "Khoms"
    ],
    "name:heb_x_preferred":[
        "\u05d0\u05dc-\u05d7'\u05d5\u05de\u05e1"
    ],
    "name:ind_x_preferred":[
        "Al Khums"
    ],
    "name:ita_x_preferred":[
        "Homs"
    ],
    "name:jpn_x_preferred":[
        "\u30d5\u30e0\u30b9"
    ],
    "name:kat_x_preferred":[
        "\u10d4\u10da-\u10ee\u10e3\u10db\u10e1\u10d8"
    ],
    "name:lit_x_preferred":[
        "Humsas"
    ],
    "name:nld_x_preferred":[
        "Al Khums"
    ],
    "name:oci_x_preferred":[
        "Khoms"
    ],
    "name:pol_x_preferred":[
        "Al-Chums"
    ],
    "name:por_x_preferred":[
        "Homs"
    ],
    "name:ron_x_preferred":[
        "Al Khums"
    ],
    "name:rus_x_preferred":[
        "\u0425\u043e\u043c\u0441"
    ],
    "name:sco_x_preferred":[
        "Al Khums"
    ],
    "name:spa_x_preferred":[
        "Al Khoms"
    ],
    "name:srd_x_preferred":[
        "Homs"
    ],
    "name:swe_x_preferred":[
        "Al-Khums"
    ],
    "name:ukr_x_preferred":[
        "\u0425\u043e\u043c\u0441"
    ],
    "name:urd_x_preferred":[
        "\u062e\u0645\u0633"
    ],
    "name:vie_x_preferred":[
        "Al Khums"
    ],
    "name:vol_x_preferred":[
        "Kums"
    ],
    "name:war_x_preferred":[
        "Homs"
    ],
    "name:zho_x_preferred":[
        "\u80e1\u59c6\u65af"
    ],
    "wof:name":"Al Khums",
    "wof:placetype":"locality"
},
  "geometry": {"coordinates":[44.07557,13.73653],"type":"Point"}
}