{
  "type": "Feature",
  "properties": {
    "gn:admin1_code":"25.0",
    "gn:admin2_code":"1502.0",
    "gn:asciiname":"Al Khums",
    "gn:country_code":"YE",
    "gn:dem":1533,
    "gn:feature_class":"P",
    "gn:feature_code":"PPL",
    "gn:name":"Al Khums",
    "gn:population":0,
    "gn:timezone":"Asia/Aden",
    "iso:country":"YE",
    "wof:name":"Al Khums",
    "wof:placetype":"locality"
},
  "geometry": {"coordinates":[44.07557,13.73653],"type":"Point"}
}