{
  "type": "Feature",
  "properties": {
    "gn:admin1_code":"23.0",
    "gn:admin2_code":"1112.0",
    "gn:asciiname":"Ra`awi",
    "gn:country_code":"YE",
    "gn:dem":2156,
    "gn:feature_class":"P",
    "gn:feature_code":"PPL",
    "gn:name":"Ra\u2018aw\u012b",
    "gn:population":0,
    "gn:timezone":"Asia/Aden",
    "iso:country":"YE",
    "name:und_x_variant":[
        "Ra\u2018aw\u012b"
    ],
    "wof:name":"Ra`awi",
    "wof:placetype":"locality"
},
  "geometry": {"coordinates":[44.06202,13.90775],"type":"Point"}
}