{
  "type": "Feature",
  "properties": {
    "gn:admin1_code":"15.0",
    "gn:admin2_code":"2212.0",
    "gn:asciiname":"Maqam Dhu Zahir",
    "gn:country_code":"YE",
    "gn:dem":1655,
    "gn:feature_class":"P",
    "gn:feature_code":"PPL",
    "gn:name":"Maq\u0101m Dh\u016b Z\u0101hir",
    "gn:population":0,
    "gn:timezone":"Asia/Aden",
    "iso:country":"YE",
    "name:ara_x_preferred":[
        "\u0645\u0642\u0627\u0645 \u0630\u0648 \u0632\u0627\u0647\u0631"
    ],
    "name:und_x_variant":[
        "Maq\u0101m Dh\u016b Z\u0101hir"
    ],
    "wof:name":"Maqam Dhu Zahir",
    "wof:placetype":"locality"
},
  "geometry": {"coordinates":[43.91186,16.7266],"type":"Point"}
}