{
  "type": "Feature",
  "properties": {
    "gn:admin1_code":"1.0",
    "gn:admin2_code":"1204.0",
    "gn:asciiname":"Mahmar",
    "gn:country_code":"YE",
    "gn:dem":1963,
    "gn:feature_class":"P",
    "gn:feature_code":"PPL",
    "gn:name":"Mahmar",
    "gn:population":0,
    "gn:timezone":"Asia/Aden",
    "iso:country":"YE",
    "wof:name":"Mahmar",
    "wof:placetype":"locality"
},
  "geometry": {"coordinates":[46.06667,14.05],"type":"Point"}
}