{
  "type": "Feature",
  "properties": {
    "gn:country":"YE",
    "gn:fcode":"PPL",
    "gn:pop":4,
    "iso:country":"YE",
    "name:ara_x_preferred":[
        "\u0642\u0644\u0629 \u0627\u0644\u0623\u062c\u0628\u0627\u0631"
    ],
    "name:eng_x_preferred":[
        "Qullat Al Ajbar"
    ],
    "name:eng_x_variant":[
        "Bayt ash Shu\u2018ayb\u012b"
    ],
    "qs:name":"Qullat al Ajb\u0101r",
    "qs:photos_9r":0,
    "qs:photos_sr":0,
    "qs:pop_sr":"1",
    "wof:name":"Qullat al Ajb\u0101r",
    "wof:placetype":"locality",
    "wof:population":4
},
  "geometry": {"coordinates":[43.27459,16.82745],"type":"Point"}
}