{
  "type": "Feature",
  "properties": {
    "gn:admin1_code":"16.0",
    "gn:admin2_code":"2302.0",
    "gn:asciiname":"Bani Shirran",
    "gn:country_code":"YE",
    "gn:dem":1566,
    "gn:feature_class":"P",
    "gn:feature_code":"PPL",
    "gn:name":"Ban\u012b Shirr\u0101n",
    "gn:population":0,
    "gn:timezone":"Asia/Aden",
    "iso:country":"YE",
    "name:und_x_variant":[
        "Ban\u012b Shirr\u0101n"
    ],
    "wof:name":"Bani Shirran",
    "wof:placetype":"locality"
},
  "geometry": {"coordinates":[44.25064,16.00703],"type":"Point"}
}