{
  "type": "Feature",
  "properties": {
    "gn:admin1_code":"28.0",
    "gn:admin2_code":"1926.0",
    "gn:asciiname":"Muq'ayuh",
    "gn:country_code":"YE",
    "gn:dem":194,
    "gn:feature_class":"P",
    "gn:feature_code":"PPL",
    "gn:name":"Muq\u2018\u0101y\u016bh",
    "gn:population":0,
    "gn:timezone":"Asia/Aden",
    "iso:country":"YE",
    "wof:name":"Muq'ayuh",
    "wof:placetype":"locality"
},
  "geometry": {"coordinates":[54.07496,12.51351],"type":"Point"}
}