{
  "type": "Feature",
  "properties": {
    "gn:gn_country":"YE",
    "gn:gn_fcode":"PPL",
    "gn:gn_pop":37,
    "gn:population":37,
    "iso:country":"YE",
    "name:ara_x_preferred":[
        "\u0634\u0639\u0628\u0629 \u0627\u0644\u062d\u0646\u0627\u064a\u0629"
    ],
    "name:eng_x_preferred":[
        "Sha'bat Al Hunayah"
    ],
    "qs_pg:aaroncc":"YE",
    "qs_pg:gn_country":"YE",
    "qs_pg:gn_fcode":"PPL",
    "qs_pg:gn_pop":37,
    "qs_pg:name":"Sha\u2018bat al \u1e28un\u0101yah",
    "qs_pg:photos_9r":0,
    "qs_pg:photos_sr":0,
    "qs_pg:pop_sr":1,
    "qs_pg:qs_pg_placetype":"locality",
    "wof:name":"Sha\u2018bat al \u1e28un\u0101yah",
    "wof:placetype":"locality",
    "wof:population":37
},
  "geometry": {"coordinates":[43.13389,16.57062],"type":"Point"}
}