{
  "type": "Feature",
  "properties": {
    "gn:admin1_code":"15.0",
    "gn:admin2_code":"2201.0",
    "gn:asciiname":"Ar Rawh",
    "gn:country_code":"YE",
    "gn:dem":2163,
    "gn:feature_class":"P",
    "gn:feature_code":"PPL",
    "gn:name":"Ar Raw\u1e29",
    "gn:population":0,
    "gn:timezone":"Asia/Aden",
    "iso:country":"YE",
    "name:ara_x_preferred":[
        "\u0100l Zimm\u0101\u1e29"
    ],
    "name:ara_x_variant":[
        "\u0627\u0644\u0631\u0648\u062d"
    ],
    "name:und_x_variant":[
        "Ar Raw\u1e29"
    ],
    "wof:name":"Ar Rawh",
    "wof:placetype":"locality"
},
  "geometry": {"coordinates":[43.44098,17.43368],"type":"Point"}
}