{
  "type": "Feature",
  "properties": {
    "gn:country":"YE",
    "gn:fcode":"PPL",
    "gn:pop":6,
    "iso:country":"YE",
    "name:ara_x_preferred":[
        "Al Muh\u012bd"
    ],
    "name:ara_x_variant":[
        "\u0627\u0644\u0645\u0647\u064a\u062f"
    ],
    "qs:name":"Al Muh\u012bd",
    "qs:photos_9r":0,
    "qs:photos_sr":0,
    "qs:pop_sr":"1",
    "wof:name":"Al Muh\u012bd",
    "wof:placetype":"locality",
    "wof:population":6
},
  "geometry": {"coordinates":[43.27233,17.20502],"type":"Point"}
}