{
  "type": "Feature",
  "properties": {
    "gn:admin1_code":"25.0",
    "gn:admin2_code":"1517.0",
    "gn:asciiname":"An Nuwas",
    "gn:country_code":"YE",
    "gn:dem":1160,
    "gn:feature_class":"P",
    "gn:feature_code":"PPL",
    "gn:name":"An Nuw\u0101s",
    "gn:population":0,
    "gn:timezone":"Asia/Aden",
    "iso:country":"YE",
    "name:ara_x_preferred":[
        "\u0627\u0644\u0646\u0648\u0627\u0633"
    ],
    "name:ara_x_variant":[
        "\u0646\u0648\u0627\u0633"
    ],
    "name:und_x_variant":[
        "An Nuw\u0101s",
        "Nuw\u0101s"
    ],
    "wof:name":"An Nuwas",
    "wof:placetype":"locality"
},
  "geometry": {"coordinates":[44.24334,13.22543],"type":"Point"}
}