{
  "type": "Feature",
  "properties": {
    "gn:admin1_code":"10.0",
    "gn:admin2_code":"2709.0",
    "gn:asciiname":"Al Jama'im",
    "gn:country_code":"YE",
    "gn:dem":1116,
    "gn:feature_class":"P",
    "gn:feature_code":"PPL",
    "gn:name":"Al Jam\u0101\u2019im",
    "gn:population":0,
    "gn:timezone":"Asia/Aden",
    "iso:country":"YE",
    "name:und_x_variant":[
        "Al Jam\u0101\u2019im"
    ],
    "wof:name":"Al Jama'im",
    "wof:placetype":"locality"
},
  "geometry": {"coordinates":[43.48914,15.49002],"type":"Point"}
}