{
  "type": "Feature",
  "properties": {
    "gn:country":"YE",
    "gn:fcode":"PPL",
    "gn:pop":15,
    "iso:country":"YE",
    "name:ara_x_preferred":[
        "\u0642\u0635\u0628\u0629 \u062f\u0647\u0634\u0648\u0634"
    ],
    "name:eng_x_preferred":[
        "Qasabat DahshUsh"
    ],
    "qs:name":"Qa\u015fabat Dahsh\u016bsh",
    "qs:photos_9r":0,
    "qs:photos_sr":0,
    "qs:pop_sr":"1",
    "wof:name":"Qa\u015fabat Dahsh\u016bsh",
    "wof:placetype":"locality",
    "wof:population":15
},
  "geometry": {"coordinates":[43.60188,16.02887],"type":"Point"}
}