{
  "type": "Feature",
  "properties": {
    "gn:country":"YE",
    "gn:fcode":"PPL",
    "gn:population":18,
    "iso:country":"YE",
    "name:ara_x_preferred":[
        "Al \u2018Aql"
    ],
    "name:ara_x_variant":[
        "\u0627\u0644\u0639\u0642\u0644"
    ],
    "qs:name":"Al \u2018Aql",
    "qs:photos_9r":0,
    "qs:photos_sr":0,
    "qs:pop_sr":"1",
    "wof:name":"Al \u2018Aql",
    "wof:placetype":"locality",
    "wof:population":18
},
  "geometry": {"coordinates":[44.15869,17.12282],"type":"Point"}
}