{
  "type": "Feature",
  "properties": {
    "gn:admin1_code":"8.0",
    "gn:admin2_code":"1824.0",
    "gn:asciiname":"Al Madaniyah",
    "gn:country_code":"YE",
    "gn:dem":57,
    "gn:feature_class":"P",
    "gn:feature_code":"PPL",
    "gn:name":"Al Madan\u012byah",
    "gn:population":0,
    "gn:timezone":"Asia/Aden",
    "iso:country":"YE",
    "name:und_x_variant":[
        "Al Madna\u012byah",
        "Al Madan\u012bah",
        "Al Madniyyah",
        "Al Madan\u012byah"
    ],
    "wof:name":"Al Madaniyah",
    "wof:placetype":"locality"
},
  "geometry": {"coordinates":[43.17695,14.28472],"type":"Point"}
}