{
  "type": "Feature",
  "properties": {
    "gn:admin1_code":"8.0",
    "gn:admin2_code":"1808.0",
    "gn:asciiname":"Ar Rafi`i",
    "gn:country_code":"YE",
    "gn:dem":144,
    "gn:feature_class":"P",
    "gn:feature_code":"PPL",
    "gn:name":"Ar R\u0101fi`\u012b",
    "gn:population":0,
    "gn:timezone":"Asia/Aden",
    "iso:country":"YE",
    "wof:name":"Ar Rafi`i",
    "wof:placetype":"locality"
},
  "geometry": {"coordinates":[43.22028,15.31167],"type":"Point"}
}