{
  "type": "Feature",
  "properties": {
    "gn:admin1_code":"24.0",
    "gn:admin2_code":"2513.0",
    "gn:asciiname":"Al Qa`idah",
    "gn:country_code":"YE",
    "gn:dem":578,
    "gn:feature_class":"P",
    "gn:feature_code":"PPL",
    "gn:name":"Al Q\u0101\u2018idah",
    "gn:population":0,
    "gn:timezone":"Asia/Aden",
    "iso:country":"YE",
    "name:und_x_variant":[
        "Al Q\u0101\u2018idah"
    ],
    "wof:name":"Al Qa`idah",
    "wof:placetype":"locality"
},
  "geometry": {"coordinates":[43.88611,13.04],"type":"Point"}
}