{
  "type": "Feature",
  "properties": {
    "gn:admin1_code":"19.0",
    "gn:admin2_code":"2908.0",
    "gn:asciiname":"Nimran",
    "gn:country_code":"YE",
    "gn:dem":1389,
    "gn:feature_class":"P",
    "gn:feature_code":"PPL",
    "gn:name":"Nimr\u0101n",
    "gn:population":0,
    "gn:timezone":"Asia/Aden",
    "iso:country":"YE",
    "name:ara_x_preferred":[
        "Nimr\u0101n"
    ],
    "name:ara_x_variant":[
        "\u0646\u0645\u0631\u0627\u0646"
    ],
    "wof:name":"Nimran",
    "wof:placetype":"locality"
},
  "geometry": {"coordinates":[43.73262,16.10904],"type":"Point"}
}