{
  "type": "Feature",
  "properties": {
    "gn:admin1_code":"8.0",
    "gn:admin2_code":"1802.0",
    "gn:asciiname":"As Suq al Qadim",
    "gn:country_code":"YE",
    "gn:dem":92,
    "gn:feature_class":"P",
    "gn:feature_code":"PPL",
    "gn:name":"As S\u016bq al Qad\u012bm",
    "gn:population":0,
    "gn:timezone":"Asia/Aden",
    "iso:country":"YE",
    "name:und_x_variant":[
        "As S\u016bq al Qad\u012bm"
    ],
    "wof:name":"As Suq al Qadim",
    "wof:placetype":"locality"
},
  "geometry": {"coordinates":[43.07188,15.63203],"type":"Point"}
}