{
  "type": "Feature",
  "properties": {
    "gn:admin1_code":"20.0",
    "gn:admin2_code":"1408.0",
    "gn:asciiname":"Sakin Ahl Wuhaysh",
    "gn:country_code":"YE",
    "gn:dem":1934,
    "gn:feature_class":"P",
    "gn:feature_code":"PPL",
    "gn:name":"S\u0101kin Ahl Wu\u1e29aysh",
    "gn:population":0,
    "gn:timezone":"Asia/Aden",
    "iso:country":"YE",
    "name:nno_x_preferred":[
        "Sakin Ahl Wuhaysh"
    ],
    "name:und_x_variant":[
        "S\u0101kin Wu\u1e29aysh\u012b",
        "Sakin Waishisi",
        "Sakin Ahl Wuhaish",
        "S\u0101kin Wu\u1e25aish\u012b",
        "S\u0101kin Ahl Wu\u1e29aysh"
    ],
    "wof:name":"Sakin Ahl Wuhaysh",
    "wof:placetype":"locality"
},
  "geometry": {"coordinates":[45.89583,14.14028],"type":"Point"}
}