{
  "type": "Feature",
  "properties": {
    "gn:admin1_code":"16.0",
    "gn:admin2_code":"2303.0",
    "gn:asciiname":"Mahall Fil",
    "gn:country_code":"YE",
    "gn:dem":2383,
    "gn:feature_class":"P",
    "gn:feature_code":"PPL",
    "gn:name":"Ma\u1e29all F\u012bl",
    "gn:population":0,
    "gn:timezone":"Asia/Aden",
    "iso:country":"YE",
    "name:ara_x_preferred":[
        "\u0645\u062d\u0644 \u0641\u064a\u0644"
    ],
    "name:und_x_variant":[
        "Ma\u1e29all F\u012bl"
    ],
    "wof:name":"Mahall Fil",
    "wof:placetype":"locality"
},
  "geometry": {"coordinates":[44.51294,15.58823],"type":"Point"}
}