{
  "type": "Feature",
  "properties": {
    "gn:admin1_code":"5.0",
    "gn:admin2_code":"2107.0",
    "gn:asciiname":"Ar Rukbah",
    "gn:country_code":"YE",
    "gn:dem":1103,
    "gn:elevation":"2.0",
    "gn:feature_class":"P",
    "gn:feature_code":"PPL",
    "gn:name":"Ar Rukbah",
    "gn:population":0,
    "gn:timezone":"Asia/Aden",
    "iso:country":"YE",
    "wof:name":"Ar Rukbah",
    "wof:placetype":"locality"
},
  "geometry": {"coordinates":[45.73507,14.89279],"type":"Point"}
}