{
  "type": "Feature",
  "properties": {
    "gn:admin1_code":"22.0",
    "gn:admin2_code":"1725.0",
    "gn:asciiname":"Sahl 'Amir",
    "gn:country_code":"YE",
    "gn:dem":871,
    "gn:feature_class":"P",
    "gn:feature_code":"PPL",
    "gn:name":"Sahl \u2018\u0100mir",
    "gn:population":0,
    "gn:timezone":"Asia/Aden",
    "iso:country":"YE",
    "name:ara_x_preferred":[
        "\u0633\u0647\u0644 \u0639\u0627\u0645\u0631"
    ],
    "name:und_x_variant":[
        "Sahl \u2018\u0100mir"
    ],
    "wof:name":"Sahl 'Amir",
    "wof:placetype":"locality"
},
  "geometry": {"coordinates":[43.52558,15.57558],"type":"Point"}
}