{
  "type": "Feature",
  "properties": {
    "gn:admin1_code":"16.0",
    "gn:admin2_code":"2301.0",
    "gn:asciiname":"Bayt Mirrah",
    "gn:country_code":"YE",
    "gn:dem":2359,
    "gn:feature_class":"P",
    "gn:feature_code":"PPL",
    "gn:name":"Bayt Mirrah",
    "gn:population":0,
    "gn:timezone":"Asia/Aden",
    "iso:country":"YE",
    "wof:name":"Bayt Mirrah",
    "wof:placetype":"locality"
},
  "geometry": {"coordinates":[44.08902,15.44116],"type":"Point"}
}