{
  "type": "Feature",
  "properties": {
    "gn:country":"YE",
    "gn:fcode":"PPL",
    "gn:pop":13,
    "iso:country":"YE",
    "name:ara_x_preferred":[
        "\u0627\u0644\u0642\u0627\u0647\u0631\u0629"
    ],
    "qs:name":"Al Q\u0101hirah",
    "qs:photos_9r":0,
    "qs:photos_sr":0,
    "qs:pop_sr":"1",
    "wof:name":"Al Q\u0101hirah",
    "wof:placetype":"locality",
    "wof:population":13
},
  "geometry": {"coordinates":[43.40258,16.15506],"type":"Point"}
}