{
  "type": "Feature",
  "properties": {
    "gn:country":"YE",
    "gn:fcode":"PPL",
    "gn:population":5,
    "iso:country":"YE",
    "name:ara_x_preferred":[
        "\u0642\u0644\u0639\u0629 \u0627\u0644\u0645\u0634\u0631\u0628\u0629"
    ],
    "name:eng_x_preferred":[
        "Qal'at Al Mashribah"
    ],
    "name:eng_x_variant":[
        "Qarn al \u2018Amiy\u0101\u2019"
    ],
    "qs:name":"Qal\u2018at al Mashribah",
    "qs:photos_9r":0,
    "qs:photos_sr":0,
    "qs:pop_sr":"1",
    "wof:name":"Qal\u2018at al Mashribah",
    "wof:placetype":"locality",
    "wof:population":5
},
  "geometry": {"coordinates":[43.32995,16.3305],"type":"Point"}
}