{
  "type": "Feature",
  "properties": {
    "gn:admin1_code":"19.0",
    "gn:admin2_code":"2909.0",
    "gn:asciiname":"Al Kassad",
    "gn:country_code":"YE",
    "gn:dem":2300,
    "gn:feature_class":"P",
    "gn:feature_code":"PPL",
    "gn:name":"Al Kass\u0101d",
    "gn:population":0,
    "gn:timezone":"Asia/Aden",
    "iso:country":"YE",
    "name:und_x_variant":[
        "Al Kass\u0101d"
    ],
    "wof:name":"Al Kassad",
    "wof:placetype":"locality"
},
  "geometry": {"coordinates":[44.10991,16.02132000000001],"type":"Point"}
}