{
  "type": "Feature",
  "properties": {
    "gn:admin1_code":"25.0",
    "gn:admin2_code":"1502.0",
    "gn:asciiname":"Al Beke",
    "gn:cc2":"YE",
    "gn:country_code":"YE",
    "gn:dem":1420,
    "gn:feature_class":"P",
    "gn:feature_code":"PPL",
    "gn:name":"Al Beke",
    "gn:population":0,
    "gn:timezone":"Asia/Aden",
    "iso:country":"YE",
    "name:und_x_variant":[
        "El Beke",
        "Al Beke"
    ],
    "wof:name":"Al Beke",
    "wof:placetype":"locality"
},
  "geometry": {"coordinates":[44.13333,13.66667],"type":"Point"}
}