{
  "type": "Feature",
  "properties": {
    "gn:country":"YE",
    "gn:fcode":"PPL",
    "gn:pop":11,
    "iso:country":"YE",
    "name:ara_x_preferred":[
        "\u0628\u064a\u062a \u0627\u0644\u0641\u0636\u0644\u064a"
    ],
    "name:eng_x_preferred":[
        "Bayt Al Fauuali"
    ],
    "qs:name":"Bayt al Fa\u1e11\u1e11al\u012b",
    "qs:photos_9r":0,
    "qs:photos_sr":0,
    "qs:pop_sr":"1",
    "wof:name":"Bayt al Fa\u1e11\u1e11al\u012b",
    "wof:placetype":"locality",
    "wof:population":11
},
  "geometry": {"coordinates":[43.7294,16.17136],"type":"Point"}
}