{
  "type": "Feature",
  "properties": {
    "gn:admin1_code":"10.0",
    "gn:admin2_code":"2702.0",
    "gn:asciiname":"Zubayrat al Ma`iz",
    "gn:country_code":"YE",
    "gn:dem":2157,
    "gn:feature_class":"P",
    "gn:feature_code":"PPL",
    "gn:name":"Zubayr\u0101t al M\u0101\u2018iz",
    "gn:population":0,
    "gn:timezone":"Asia/Aden",
    "iso:country":"YE",
    "name:und_x_variant":[
        "Zubayr\u0101t al M\u0101\u2018iz"
    ],
    "wof:name":"Zubayrat al Ma`iz",
    "wof:placetype":"locality"
},
  "geometry": {"coordinates":[43.81498,15.41874],"type":"Point"}
}