{
  "type": "Feature",
  "properties": {
    "gn:admin1_code":"1.0",
    "gn:admin2_code":"1208.0",
    "gn:asciiname":"Am Sa'id",
    "gn:country_code":"YE",
    "gn:dem":848,
    "gn:feature_class":"P",
    "gn:feature_code":"PPL",
    "gn:name":"Am \u015ea\u2018\u012bd",
    "gn:population":0,
    "gn:timezone":"Asia/Aden",
    "iso:country":"YE",
    "name:und_x_variant":[
        "Am \u015ea\u2018\u012bd"
    ],
    "wof:name":"Am Sa'id",
    "wof:placetype":"locality"
},
  "geometry": {"coordinates":[45.94127,13.73802],"type":"Point"}
}