{
  "type": "Feature",
  "properties": {
    "gn:admin1_code":"16.0",
    "gn:admin2_code":"2302.0",
    "gn:asciiname":"Al Qunnah",
    "gn:country_code":"YE",
    "gn:dem":2354,
    "gn:feature_class":"P",
    "gn:feature_code":"PPL",
    "gn:name":"Al Qunnah",
    "gn:population":0,
    "gn:timezone":"Asia/Aden",
    "iso:country":"YE",
    "name:ara_x_preferred":[
        "\u0627\u0644\u0642\u0646\u0629"
    ],
    "wof:name":"Al Qunnah",
    "wof:placetype":"locality"
},
  "geometry": {"coordinates":[44.23385,15.85266],"type":"Point"}
}