{
  "type": "Feature",
  "properties": {
    "gn:admin1_code":"22.0",
    "gn:admin2_code":"1722.0",
    "gn:asciiname":"Zahr al Masjid",
    "gn:country_code":"YE",
    "gn:dem":191,
    "gn:feature_class":"P",
    "gn:feature_code":"PPL",
    "gn:name":"Z\u0327ahr al Masjid",
    "gn:population":0,
    "gn:timezone":"Asia/Aden",
    "iso:country":"YE",
    "name:und_x_variant":[
        "Z\u0327ahr al Masjid"
    ],
    "wof:name":"Zahr al Masjid",
    "wof:placetype":"locality"
},
  "geometry": {"coordinates":[43.23792,15.72241],"type":"Point"}
}