{
  "type": "Feature",
  "properties": {
    "gn:country":"YE",
    "gn:fcode":"PPL",
    "gn:population":2,
    "iso:country":"YE",
    "name:ara_x_preferred":[
        "\u0628\u064a\u062a \u0643\u0646\u062f\u0634"
    ],
    "name:eng_x_preferred":[
        "Bayt Kandush"
    ],
    "name:eng_x_variant":[
        "Hir\u0101n"
    ],
    "qs:name":"Bayt Kandush",
    "qs:photos_9r":0,
    "qs:photos_sr":0,
    "qs:pop_sr":"1",
    "wof:name":"Bayt Kandush",
    "wof:placetype":"locality",
    "wof:population":2
},
  "geometry": {"coordinates":[44.25444,16.54027],"type":"Point"}
}