{
  "type": "Feature",
  "properties": {
    "gn:admin1_code":"14.0",
    "gn:asciiname":"Buraysh",
    "gn:country_code":"YE",
    "gn:dem":1176,
    "gn:feature_class":"P",
    "gn:feature_code":"PPLL",
    "gn:name":"Buraysh",
    "gn:population":0,
    "gn:timezone":"Asia/Aden",
    "iso:country":"YE",
    "name:ara_x_preferred":[
        "\u0628\u0631\u064a\u0634"
    ],
    "wof:name":"Buraysh",
    "wof:placetype":"locality"
},
  "geometry": {"coordinates":[44.51877,16.17317],"type":"Point"}
}