{
  "type": "Feature",
  "properties": {
    "gn:admin1_code":"25.0",
    "gn:admin2_code":"1502.0",
    "gn:asciiname":"Samsarah",
    "gn:country_code":"YE",
    "gn:dem":1218,
    "gn:feature_class":"P",
    "gn:feature_code":"PPL",
    "gn:name":"Samsarah",
    "gn:population":0,
    "gn:timezone":"Asia/Aden",
    "iso:country":"YE",
    "wof:name":"Samsarah",
    "wof:placetype":"locality"
},
  "geometry": {"coordinates":[44.03162,13.67112],"type":"Point"}
}