{
  "type": "Feature",
  "properties": {
    "gn:country":"YE",
    "gn:fcode":"PPL",
    "gn:population":1,
    "iso:country":"YE",
    "name:ara_x_preferred":[
        "Az Zuq\u0101q"
    ],
    "name:ara_x_variant":[
        "\u0627\u0644\u0632\u0642\u0627\u0642"
    ],
    "qs:name":"Az Zuq\u0101q",
    "qs:photos_9r":0,
    "qs:photos_sr":0,
    "qs:pop_sr":"1",
    "wof:name":"Az Zuq\u0101q",
    "wof:placetype":"locality",
    "wof:population":1
},
  "geometry": {"coordinates":[43.40583,16.30539],"type":"Point"}
}