{
  "type": "Feature",
  "properties": {
    "gn:country":"YE",
    "gn:fcode":"PPL",
    "gn:pop":2,
    "iso:country":"YE",
    "name:ara_x_preferred":[
        "Al \u2018A\u015fil"
    ],
    "name:ara_x_variant":[
        "\u0627\u0644\u0639\u0635\u0644"
    ],
    "name:eng_x_preferred":[
        "Al 'Asil"
    ],
    "qs:name":"Al \u2018A\u015fil",
    "qs:photos_9r":0,
    "qs:photos_sr":0,
    "qs:pop_sr":"1",
    "wof:name":"Al \u2018A\u015fil",
    "wof:placetype":"locality",
    "wof:population":2
},
  "geometry": {"coordinates":[44.79336,15.97705],"type":"Point"}
}