{
  "type": "Feature",
  "properties": {
    "gn:admin1_code":"24.0",
    "gn:admin2_code":"2507.0",
    "gn:asciiname":"Al Milahah",
    "gn:country_code":"YE",
    "gn:dem":706,
    "gn:feature_class":"P",
    "gn:feature_code":"PPL",
    "gn:name":"Al Mil\u0101\u1e29ah",
    "gn:population":0,
    "gn:timezone":"Asia/Aden",
    "iso:country":"YE",
    "name:und_x_variant":[
        "Al Mil\u0101\u1e29ah"
    ],
    "wof:name":"Al Milahah",
    "wof:placetype":"locality"
},
  "geometry": {"coordinates":[44.8897,13.51899],"type":"Point"}
}