{
  "type": "Feature",
  "properties": {
    "gn:admin1_code":"16.0",
    "gn:admin2_code":"2312.0",
    "gn:asciiname":"Maswar",
    "gn:cc2":"YE",
    "gn:country_code":"YE",
    "gn:dem":2181,
    "gn:feature_class":"P",
    "gn:feature_code":"PPL",
    "gn:name":"Maswar",
    "gn:population":0,
    "gn:timezone":"Asia/Aden",
    "iso:country":"YE",
    "name:und_x_variant":[
        "Miswar",
        "Maswar"
    ],
    "wof:name":"Maswar",
    "wof:placetype":"locality"
},
  "geometry": {"coordinates":[44.65,15.26667],"type":"Point"}
}