{
  "type": "Feature",
  "properties": {
    "gn:admin1_code":"15.0",
    "gn:admin2_code":"2212.0",
    "gn:asciiname":"Al Mukafat",
    "gn:country_code":"YE",
    "gn:dem":1571,
    "gn:feature_class":"P",
    "gn:feature_code":"PPL",
    "gn:name":"Al Mukafat",
    "gn:population":0,
    "gn:timezone":"Asia/Aden",
    "iso:country":"YE",
    "name:ara_x_preferred":[
        "\u0627\u0644\u0645\u0643\u0641\u062a"
    ],
    "wof:name":"Al Mukafat",
    "wof:placetype":"locality"
},
  "geometry": {"coordinates":[44.02075,16.68473],"type":"Point"}
}