{
  "type": "Feature",
  "properties": {
    "gn:country":"YE",
    "gn:fcode":"PPL",
    "gn:pop":8,
    "iso:country":"YE",
    "name:ara_x_preferred":[
        "\u0627\u0644 \u064a\u0632\u064a\u062f \u0627\u0644\u063a\u0631\u0648\u0633"
    ],
    "name:eng_x_preferred":[
        "Al Yazid Al GharUs"
    ],
    "name:eng_x_variant":[
        "B\u016bs\u0101n al Asfal"
    ],
    "qs:name":"\u0100l Yaz\u012bd al Ghar\u016bs",
    "qs:photos_9r":0,
    "qs:photos_sr":0,
    "qs:pop_sr":"1",
    "wof:name":"\u0100l Yaz\u012bd al Ghar\u016bs",
    "wof:placetype":"locality",
    "wof:population":8
},
  "geometry": {"coordinates":[45.06224,14.2837],"type":"Point"}
}