{
  "type": "Feature",
  "properties": {
    "gn:admin1_code":"22.0",
    "gn:admin2_code":"1706.0",
    "gn:asciiname":"Mahall Hammam",
    "gn:country_code":"YE",
    "gn:dem":164,
    "gn:feature_class":"P",
    "gn:feature_code":"PPL",
    "gn:name":"Ma\u1e29all \u1e28amm\u0101m",
    "gn:population":0,
    "gn:timezone":"Asia/Aden",
    "iso:country":"YE",
    "name:und_x_variant":[
        "Ma\u1e29all \u1e28amm\u0101m"
    ],
    "wof:name":"Mahall Hammam",
    "wof:placetype":"locality"
},
  "geometry": {"coordinates":[43.16667,16.23333],"type":"Point"}
}