{
  "type": "Feature",
  "properties": {
    "gn:admin1_code":"22.0",
    "gn:admin2_code":"1709.0",
    "gn:asciiname":"Bayt as Sifa",
    "gn:country_code":"YE",
    "gn:dem":1658,
    "gn:feature_class":"P",
    "gn:feature_code":"PPL",
    "gn:name":"Bayt a\u015f \u015eif\u0101",
    "gn:population":0,
    "gn:timezone":"Asia/Aden",
    "iso:country":"YE",
    "name:ara_x_preferred":[
        "\u0628\u064a\u062a \u0627\u0644\u0635\u0641\u0627"
    ],
    "name:und_x_variant":[
        "Bayt a\u015f \u015eif\u0101"
    ],
    "wof:name":"Bayt as Sifa",
    "wof:placetype":"locality"
},
  "geometry": {"coordinates":[43.49088,16.0318],"type":"Point"}
}