{
  "type": "Feature",
  "properties": {
    "gn:admin1_code":"15.0",
    "gn:admin2_code":"2214.0",
    "gn:asciiname":"Al Naji`",
    "gn:country_code":"YE",
    "gn:dem":1914,
    "gn:feature_class":"P",
    "gn:feature_code":"PPL",
    "gn:name":"\u0100l N\u0101ji\u2018",
    "gn:population":0,
    "gn:timezone":"Asia/Aden",
    "iso:country":"YE",
    "name:ara_x_preferred":[
        "\u0100l N\u0101ji\u2018"
    ],
    "name:ara_x_variant":[
        "\u0627\u0644 \u0646\u0627\u062c\u0639"
    ],
    "wof:name":"Al Naji`",
    "wof:placetype":"locality"
},
  "geometry": {"coordinates":[44.06426,17.06814],"type":"Point"}
}