{
  "type": "Feature",
  "properties": {
    "gn:country":"YE",
    "gn:fcode":"PPL",
    "gn:pop":2,
    "iso:country":"YE",
    "name:ara_x_preferred":[
        "\u0627\u0644\u062a\u0648\u0627\u062b\u064a \u0627\u0644\u0623\u0633\u0641\u0644"
    ],
    "name:eng_x_preferred":[
        "At Tuwathi Al Asfal"
    ],
    "qs:name":"At Tuw\u0101th\u012b al Asfal",
    "qs:photos_9r":0,
    "qs:photos_sr":0,
    "qs:pop_sr":"1",
    "wof:name":"At Tuw\u0101th\u012b al Asfal",
    "wof:placetype":"locality",
    "wof:population":2
},
  "geometry": {"coordinates":[43.25,16.23767],"type":"Point"}
}