{
  "type": "Feature",
  "properties": {
    "gn:admin1_code":"19.0",
    "gn:admin2_code":"2920.0",
    "gn:asciiname":"Bayt Jitam",
    "gn:country_code":"YE",
    "gn:dem":1934,
    "gn:feature_class":"P",
    "gn:feature_code":"PPL",
    "gn:name":"Bayt Jit\u0101m",
    "gn:population":0,
    "gn:timezone":"Asia/Aden",
    "iso:country":"YE",
    "name:ara_x_preferred":[
        "\u0628\u064a\u062a \u062c\u062a\u0627\u0645"
    ],
    "name:und_x_variant":[
        "Bayt Jit\u0101m"
    ],
    "wof:name":"Bayt Jitam",
    "wof:placetype":"locality"
},
  "geometry": {"coordinates":[43.91091,16.17893],"type":"Point"}
}