{
  "type": "Feature",
  "properties": {
    "gn:country":"YE",
    "gn:fcode":"PPL",
    "gn:population":8,
    "iso:country":"YE",
    "name:ara_x_preferred":[
        "\u0628\u064a\u0636\u0627\u0646"
    ],
    "name:eng_x_preferred":[
        "Bayuan"
    ],
    "name:eng_x_variant":[
        "Ath Tha\u2018bil\u012byah"
    ],
    "qs:name":"Bay\u1e11\u0101n",
    "qs:photos_9r":0,
    "qs:photos_sr":0,
    "qs:pop_sr":"1",
    "wof:name":"Bay\u1e11\u0101n",
    "wof:placetype":"locality",
    "wof:population":8
},
  "geometry": {"coordinates":[43.46748,16.18713],"type":"Point"}
}