{
  "type": "Feature",
  "properties": {
    "gn:admin1_code":"15.0",
    "gn:admin2_code":"2203.0",
    "gn:asciiname":"Ath Thahirah",
    "gn:country_code":"YE",
    "gn:dem":1719,
    "gn:feature_class":"P",
    "gn:feature_code":"PPL",
    "gn:name":"Ath T\u1e29\u0101hirah",
    "gn:population":0,
    "gn:timezone":"Asia/Aden",
    "iso:country":"YE",
    "name:ara_x_preferred":[
        "\u0627\u0644\u062b\u0627\u0647\u0631\u0629"
    ],
    "name:und_x_variant":[
        "Az\u0327 Z\u0327\u0101hirah",
        "Ath T\u1e29\u0101hirah"
    ],
    "wof:name":"Ath Thahirah",
    "wof:placetype":"locality"
},
  "geometry": {"coordinates":[43.28100000000001,17.16126],"type":"Point"}
}