{
  "type": "Feature",
  "properties": {
    "gn:country":"YE",
    "gn:fcode":"PPL",
    "gn:pop":3,
    "iso:country":"YE",
    "name:ara_x_preferred":[
        "\u0627\u0644\u062f\u0648\u064a\u062f\u0629"
    ],
    "name:eng_x_preferred":[
        "Ad Duwaydah"
    ],
    "name:eng_x_variant":[
        "Al Q\u0101\u2018"
    ],
    "qs:name":"Ad Duwaydah",
    "qs:photos_9r":0,
    "qs:photos_sr":0,
    "qs:pop_sr":"1",
    "wof:name":"Ad Duwaydah",
    "wof:placetype":"locality",
    "wof:population":3
},
  "geometry": {"coordinates":[43.52841,13.44714],"type":"Point"}
}