{
  "type": "Feature",
  "properties": {
    "gn:country":"YE",
    "gn:fcode":"PPL",
    "gn:population":2,
    "iso:country":"YE",
    "name:ara_x_preferred":[
        "\u0645\u062b\u0628\u0631"
    ],
    "name:eng_x_preferred":[
        "Mathbir"
    ],
    "qs:name":"Mathbir",
    "qs:photos_9r":0,
    "qs:photos_sr":0,
    "qs:pop_sr":"1",
    "wof:name":"Mathbir",
    "wof:placetype":"locality",
    "wof:population":2
},
  "geometry": {"coordinates":[43.37088,16.78483],"type":"Point"}
}