{
  "type": "Feature",
  "properties": {
    "gn:admin1_code":"16.0",
    "gn:admin2_code":"2306.0",
    "gn:asciiname":"Al Aysar",
    "gn:country_code":"YE",
    "gn:dem":1775,
    "gn:feature_class":"P",
    "gn:feature_code":"PPL",
    "gn:name":"Al Aysar",
    "gn:population":0,
    "gn:timezone":"Asia/Aden",
    "iso:country":"YE",
    "wof:name":"Al Aysar",
    "wof:placetype":"locality"
},
  "geometry": {"coordinates":[44.21233,15.04238],"type":"Point"}
}