{
  "type": "Feature",
  "properties": {
    "gn:admin1_code":"8.0",
    "gn:admin2_code":"1808.0",
    "gn:asciiname":"Mazra'at ash Shaykh",
    "gn:country_code":"YE",
    "gn:dem":101,
    "gn:feature_class":"P",
    "gn:feature_code":"PPL",
    "gn:name":"Mazra\u2018at ash Shaykh",
    "gn:population":0,
    "gn:timezone":"Asia/Aden",
    "iso:country":"YE",
    "name:ara_x_preferred":[
        "\u0645\u0632\u0631\u0639\u0629 \u0627\u0644\u0634\u064a\u062e"
    ],
    "name:und_x_variant":[
        "Mazra\u2018at ash Shaykh"
    ],
    "wof:name":"Mazra'at ash Shaykh",
    "wof:placetype":"locality"
},
  "geometry": {"coordinates":[43.14495,15.34786],"type":"Point"}
}