{
  "type": "Feature",
  "properties": {
    "gn:admin1_code":"11.0",
    "gn:admin2_code":"2007.0",
    "gn:asciiname":"Miqranah",
    "gn:country_code":"YE",
    "gn:dem":814,
    "gn:feature_class":"P",
    "gn:feature_code":"PPL",
    "gn:name":"Miqr\u0101nah",
    "gn:population":0,
    "gn:timezone":"Asia/Aden",
    "iso:country":"YE",
    "name:und_x_variant":[
        "Miqr\u0101nah"
    ],
    "wof:name":"Miqranah",
    "wof:placetype":"locality"
},
  "geometry": {"coordinates":[43.5998,14.23573],"type":"Point"}
}