{
  "type": "Feature",
  "properties": {
    "gn:admin1_code":"15.0",
    "gn:admin2_code":"2211.0",
    "gn:asciiname":"Al Murari",
    "gn:country_code":"YE",
    "gn:dem":1863,
    "gn:feature_class":"P",
    "gn:feature_code":"PPL",
    "gn:name":"\u0100l Mur\u0101r\u012b",
    "gn:population":0,
    "gn:timezone":"Asia/Aden",
    "iso:country":"YE",
    "name:ara_x_preferred":[
        "\u0100l Mur\u0101r\u012b"
    ],
    "wof:name":"Al Murari",
    "wof:placetype":"locality"
},
  "geometry": {"coordinates":[43.75196,17.02313],"type":"Point"}
}