{
  "type": "Feature",
  "properties": {
    "gn:admin1_code":"19.0",
    "gn:admin2_code":"2920.0",
    "gn:asciiname":"Bayt Ahmad al Hajj",
    "gn:country_code":"YE",
    "gn:dem":2188,
    "gn:feature_class":"P",
    "gn:feature_code":"PPL",
    "gn:name":"Bayt A\u1e29mad al \u1e28\u0101jj",
    "gn:population":0,
    "gn:timezone":"Asia/Aden",
    "iso:country":"YE",
    "name:ara_x_preferred":[
        "\u0628\u064a\u062a \u0623\u062d\u0645\u062f \u0627\u0644\u062d\u0627\u062c"
    ],
    "name:und_x_variant":[
        "Bayt A\u1e29mad al \u1e28\u0101jj"
    ],
    "wof:name":"Bayt Ahmad al Hajj",
    "wof:placetype":"locality"
},
  "geometry": {"coordinates":[43.98954000000001,16.13376],"type":"Point"}
}