{
  "type": "Feature",
  "properties": {
    "gn:country":"YE",
    "gn:fcode":"PPL",
    "gn:pop":4,
    "iso:country":"YE",
    "name:ara_x_preferred":[
        "Al Mi\u1e29z\u0101m"
    ],
    "name:ara_x_variant":[
        "\u0627\u0644\u0645\u062d\u0632\u0627\u0645"
    ],
    "name:eng_x_preferred":[
        "Al Mihzam"
    ],
    "qs:name":"Al Mi\u1e29z\u0101m",
    "qs:photos_9r":0,
    "qs:photos_sr":0,
    "qs:pop_sr":"1",
    "wof:name":"Al Mi\u1e29z\u0101m",
    "wof:placetype":"locality",
    "wof:population":4
},
  "geometry": {"coordinates":[44.7841,16.1673],"type":"Point"}
}