{
  "type": "Feature",
  "properties": {
    "gn:admin1_code":"22.0",
    "gn:admin2_code":"1707.0",
    "gn:asciiname":"Dhim Nashim",
    "gn:country_code":"YE",
    "gn:dem":1247,
    "gn:feature_class":"P",
    "gn:feature_code":"PPL",
    "gn:name":"Dhim Nashim",
    "gn:population":0,
    "gn:timezone":"Asia/Aden",
    "iso:country":"YE",
    "name:ara_x_preferred":[
        "\u0630\u0645 \u0646\u0634\u0645"
    ],
    "wof:name":"Dhim Nashim",
    "wof:placetype":"locality"
},
  "geometry": {"coordinates":[43.47497,16.12475],"type":"Point"}
}