{
  "type": "Feature",
  "properties": {
    "gn:admin1_code":"16.0",
    "gn:admin2_code":"2308.0",
    "gn:asciiname":"Dir`ah",
    "gn:country_code":"YE",
    "gn:dem":2933,
    "gn:feature_class":"P",
    "gn:feature_code":"PPL",
    "gn:name":"Dir\u2018ah",
    "gn:population":0,
    "gn:timezone":"Asia/Aden",
    "iso:country":"YE",
    "name:und_x_variant":[
        "Dir\u2018ah"
    ],
    "wof:name":"Dir`ah",
    "wof:placetype":"locality"
},
  "geometry": {"coordinates":[43.94536,15.32096],"type":"Point"}
}