{
  "type": "Feature",
  "properties": {
    "gn:country":"YE",
    "gn:fcode":"PPLF",
    "gn:pop":3,
    "iso:country":"YE",
    "name:ara_x_preferred":[
        "Q\u0101yim \u0162\u0101lib"
    ],
    "name:ara_x_variant":[
        "\u0642\u0627\u064a\u0645 \u0637\u0627\u0644\u0628"
    ],
    "name:eng_x_preferred":[
        "Qayim Talib"
    ],
    "name:eng_x_variant":[
        "Rad\u1e29at al \u2018Ar\u0101j\u012b"
    ],
    "qs:name":"Q\u0101yim \u0162\u0101lib",
    "qs:photos_9r":0,
    "qs:photos_sr":0,
    "qs:pop_sr":"1",
    "wof:name":"Q\u0101yim \u0162\u0101lib",
    "wof:placetype":"locality",
    "wof:population":3
},
  "geometry": {"coordinates":[43.32232,16.55812],"type":"Point"}
}