{
  "type": "Feature",
  "properties": {
    "gn:admin1_code":"24.0",
    "gn:admin2_code":"2514.0",
    "gn:asciiname":"Sufyan",
    "gn:country_code":"YE",
    "gn:dem":143,
    "gn:feature_class":"P",
    "gn:feature_code":"PPL",
    "gn:name":"Sufy\u0101n",
    "gn:population":0,
    "gn:timezone":"Asia/Aden",
    "iso:country":"YE",
    "name:ara_x_preferred":[
        "Sufy\u0101n"
    ],
    "wof:name":"Sufyan",
    "wof:placetype":"locality"
},
  "geometry": {"coordinates":[44.88778,13.07222],"type":"Point"}
}