{
  "type": "Feature",
  "properties": {
    "gn:admin1_code":"19.0",
    "gn:admin2_code":"2919.0",
    "gn:asciiname":"Bashir",
    "gn:country_code":"YE",
    "gn:dem":2317,
    "gn:feature_class":"P",
    "gn:feature_code":"PPL",
    "gn:name":"B\u0101shir",
    "gn:population":0,
    "gn:timezone":"Asia/Aden",
    "iso:country":"YE",
    "name:ara_x_preferred":[
        "B\u0101shir"
    ],
    "name:ara_x_variant":[
        "\u0628\u0627\u0634\u0631"
    ],
    "name:cat_x_preferred":[
        "Baixir"
    ],
    "name:deu_x_preferred":[
        "Baschir"
    ],
    "name:fra_x_preferred":[
        "B\u00e9chir"
    ],
    "name:rus_x_preferred":[
        "\u0411\u0430\u0448\u0438\u0440"
    ],
    "wof:name":"Bashir",
    "wof:placetype":"locality"
},
  "geometry": {"coordinates":[43.92409,16.0371],"type":"Point"}
}