{
  "type": "Feature",
  "properties": {
    "gn:country":"YE",
    "gn:fcode":"PPL",
    "gn:pop":1,
    "iso:country":"YE",
    "name:ara_x_preferred":[
        "\u0627\u0644\u0642\u0631\u064a\u0629"
    ],
    "qs:name":"Al Qaryah",
    "qs:photos_9r":0,
    "qs:photos_sr":0,
    "qs:pop_sr":"1",
    "wof:name":"Al Qaryah",
    "wof:placetype":"locality",
    "wof:population":1
},
  "geometry": {"coordinates":[43.45837,16.15818],"type":"Point"}
}