{
  "type": "Feature",
  "properties": {
    "gn:admin1_code":"24.0",
    "gn:admin2_code":"2504.0",
    "gn:asciiname":"Daral",
    "gn:country_code":"YE",
    "gn:dem":1643,
    "gn:feature_class":"P",
    "gn:feature_code":"PPL",
    "gn:name":"Daral",
    "gn:population":0,
    "gn:timezone":"Asia/Aden",
    "iso:country":"YE",
    "wof:name":"Daral",
    "wof:placetype":"locality"
},
  "geometry": {"coordinates":[45.23983,13.79894],"type":"Point"}
}