{
  "type": "Feature",
  "properties": {
    "gn:admin1_code":"8.0",
    "gn:admin2_code":"1826.0",
    "gn:asciiname":"Al Jilab",
    "gn:country_code":"YE",
    "gn:dem":13,
    "gn:feature_class":"P",
    "gn:feature_code":"PPL",
    "gn:name":"Al Jil\u0101b",
    "gn:population":0,
    "gn:timezone":"Asia/Aden",
    "iso:country":"YE",
    "name:ara_x_preferred":[
        "Al Jil\u0101b"
    ],
    "wof:name":"Al Jilab",
    "wof:placetype":"locality"
},
  "geometry": {"coordinates":[43.20544,13.90926],"type":"Point"}
}