{
  "type": "Feature",
  "properties": {
    "gn:admin1_code":"19.0",
    "gn:admin2_code":"2915.0",
    "gn:asciiname":"Az Zubr",
    "gn:country_code":"YE",
    "gn:dem":2228,
    "gn:feature_class":"P",
    "gn:feature_code":"PPL",
    "gn:name":"Az\u0327 Z\u0327ubr",
    "gn:population":0,
    "gn:timezone":"Asia/Aden",
    "iso:country":"YE",
    "name:ara_x_preferred":[
        "Az\u0327 Z\u0327ubr"
    ],
    "wof:name":"Az Zubr",
    "wof:placetype":"locality"
},
  "geometry": {"coordinates":[43.95705,15.70721],"type":"Point"}
}