{
  "type": "Feature",
  "properties": {
    "gn:admin1_code":"25.0",
    "gn:admin2_code":"1505.0",
    "gn:asciiname":"Su`aydah",
    "gn:country_code":"YE",
    "gn:dem":850,
    "gn:feature_class":"P",
    "gn:feature_code":"PPL",
    "gn:name":"Su\u2018aydah",
    "gn:population":0,
    "gn:timezone":"Asia/Aden",
    "iso:country":"YE",
    "name:und_x_variant":[
        "Su\u2018aydah"
    ],
    "wof:name":"Su`aydah",
    "wof:placetype":"locality"
},
  "geometry": {"coordinates":[43.62548,13.66784],"type":"Point"}
}