{
  "type": "Feature",
  "properties": {
    "gn:admin1_code":"15.0",
    "gn:admin2_code":"2209.0",
    "gn:asciiname":"Tighil",
    "gn:country_code":"YE",
    "gn:dem":2262,
    "gn:feature_class":"P",
    "gn:feature_code":"PPL",
    "gn:name":"Tigh\u012bl",
    "gn:population":0,
    "gn:timezone":"Asia/Aden",
    "iso:country":"YE",
    "name:ara_x_preferred":[
        "Tigh\u012bl"
    ],
    "name:ara_x_variant":[
        "\u062a\u063a\u064a\u0644"
    ],
    "wof:name":"Tighil",
    "wof:placetype":"locality"
},
  "geometry": {"coordinates":[43.493,16.80061],"type":"Point"}
}