{
  "type": "Feature",
  "properties": {
    "gn:admin1_code":"25.0",
    "gn:admin2_code":"1512.0",
    "gn:asciiname":"Anbiyan",
    "gn:country_code":"YE",
    "gn:dem":2032,
    "gn:feature_class":"P",
    "gn:feature_code":"PPL",
    "gn:name":"Anbiy\u0101n",
    "gn:population":0,
    "gn:timezone":"Asia/Aden",
    "iso:country":"YE",
    "name:ara_x_preferred":[
        "Anbiy\u0101n"
    ],
    "wof:name":"Anbiyan",
    "wof:placetype":"locality"
},
  "geometry": {"coordinates":[44.01393,13.51128],"type":"Point"}
}