{
  "type": "Feature",
  "properties": {
    "gn:admin1_code":"23.0",
    "gn:admin2_code":"1103.0",
    "gn:asciiname":"Hamah",
    "gn:country_code":"YE",
    "gn:dem":2405,
    "gn:feature_class":"P",
    "gn:feature_code":"PPL",
    "gn:name":"H\u0101mah",
    "gn:population":0,
    "gn:timezone":"Asia/Aden",
    "iso:country":"YE",
    "name:ara_x_preferred":[
        "\u0647\u0627\u0645\u0629"
    ],
    "name:und_x_variant":[
        "H\u0101mah"
    ],
    "wof:name":"Hamah",
    "wof:placetype":"locality"
},
  "geometry": {"coordinates":[44.54608,14.19785],"type":"Point"}
}