{
  "type": "Feature",
  "properties": {
    "gn:admin1_code":"22.0",
    "gn:admin2_code":"1710.0",
    "gn:asciiname":"Qawdah",
    "gn:country_code":"YE",
    "gn:dem":1065,
    "gn:feature_class":"P",
    "gn:feature_code":"PPL",
    "gn:name":"Qawdah",
    "gn:population":0,
    "gn:timezone":"Asia/Aden",
    "iso:country":"YE",
    "name:ara_x_preferred":[
        "\u0642\u0648\u062f\u0629"
    ],
    "wof:name":"Qawdah",
    "wof:placetype":"locality"
},
  "geometry": {"coordinates":[43.40916,16.0506],"type":"Point"}
}