{
  "type": "Feature",
  "properties": {
    "gn:admin1_code":"19.0",
    "gn:admin2_code":"2919.0",
    "gn:asciiname":"Al Mihjali",
    "gn:country_code":"YE",
    "gn:dem":1737,
    "gn:feature_class":"P",
    "gn:feature_code":"PPL",
    "gn:name":"Al Mi\u1e29j\u0101l\u012b",
    "gn:population":0,
    "gn:timezone":"Asia/Aden",
    "iso:country":"YE",
    "name:ara_x_preferred":[
        "Al Mi\u1e29j\u0101l\u012b"
    ],
    "name:ara_x_variant":[
        "\u0627\u0644\u0645\u062d\u062c\u0627\u0644\u064a"
    ],
    "wof:name":"Al Mihjali",
    "wof:placetype":"locality"
},
  "geometry": {"coordinates":[43.8096,16.02171],"type":"Point"}
}