{
  "type": "Feature",
  "properties": {
    "gn:admin1_code":"25.0",
    "gn:admin2_code":"1504.0",
    "gn:asciiname":"Ad Duwaymah",
    "gn:country_code":"YE",
    "gn:dem":488,
    "gn:feature_class":"P",
    "gn:feature_code":"PPL",
    "gn:name":"Ad Duwaymah",
    "gn:population":0,
    "gn:timezone":"Asia/Aden",
    "iso:country":"YE",
    "wof:name":"Ad Duwaymah",
    "wof:placetype":"locality"
},
  "geometry": {"coordinates":[43.67687,13.84811],"type":"Point"}
}