{
  "type": "Feature",
  "properties": {
    "gn:admin1_code":"24.0",
    "gn:admin2_code":"2512.0",
    "gn:asciiname":"Al 'Ishsh",
    "gn:country_code":"YE",
    "gn:dem":901,
    "gn:feature_class":"P",
    "gn:feature_code":"PPL",
    "gn:name":"Al \u2018Ishsh",
    "gn:population":0,
    "gn:timezone":"Asia/Aden",
    "iso:country":"YE",
    "name:ara_x_preferred":[
        "\u0627\u0644\u0639\u0634"
    ],
    "name:und_x_variant":[
        "Al \u2018Ishsh"
    ],
    "wof:name":"Al 'Ishsh",
    "wof:placetype":"locality"
},
  "geometry": {"coordinates":[44.22151,13.16313],"type":"Point"}
}