{
  "type": "Feature",
  "properties": {
    "gn:admin1_code":"8.0",
    "gn:admin2_code":"1801.0",
    "gn:asciiname":"Buyut al Maghafir",
    "gn:country_code":"YE",
    "gn:dem":69,
    "gn:feature_class":"P",
    "gn:feature_code":"PPL",
    "gn:name":"Buy\u016bt al Magh\u0101f\u012br",
    "gn:population":0,
    "gn:timezone":"Asia/Aden",
    "iso:country":"YE",
    "name:ara_x_preferred":[
        "\u0628\u064a\u0648\u062a \u0627\u0644\u0645\u063a\u0627\u0641\u064a\u0631"
    ],
    "name:und_x_variant":[
        "Buy\u016bt al Magh\u0101f\u012br"
    ],
    "wof:name":"Buyut al Maghafir",
    "wof:placetype":"locality"
},
  "geometry": {"coordinates":[42.992,15.70734],"type":"Point"}
}