{
  "type": "Feature",
  "properties": {
    "gn:admin1_code":"22.0",
    "gn:admin2_code":"1725.0",
    "gn:asciiname":"Dabbiyah",
    "gn:country_code":"YE",
    "gn:dem":667,
    "gn:feature_class":"P",
    "gn:feature_code":"PPL",
    "gn:name":"Dabb\u012byah",
    "gn:population":0,
    "gn:timezone":"Asia/Aden",
    "iso:country":"YE",
    "name:ara_x_preferred":[
        "\u062f\u0628\u064a\u0629"
    ],
    "name:und_x_variant":[
        "Dabb\u012byah"
    ],
    "wof:name":"Dabbiyah",
    "wof:placetype":"locality"
},
  "geometry": {"coordinates":[43.50552,15.56994],"type":"Point"}
}