{
  "type": "Feature",
  "properties": {
    "gn:admin1_code":"15.0",
    "gn:admin2_code":"2215.0",
    "gn:asciiname":"Qawbarah",
    "gn:country_code":"YE",
    "gn:dem":1879,
    "gn:feature_class":"P",
    "gn:feature_code":"PPL",
    "gn:name":"Qawbarah",
    "gn:population":0,
    "gn:timezone":"Asia/Aden",
    "iso:country":"YE",
    "name:ara_x_preferred":[
        "\u0642\u0648\u0628\u0631\u0629"
    ],
    "wof:name":"Qawbarah",
    "wof:placetype":"locality"
},
  "geometry": {"coordinates":[43.76543,16.92386],"type":"Point"}
}