{
  "type": "Feature",
  "properties": {
    "gn:admin1_code":"10.0",
    "gn:admin2_code":"2702.0",
    "gn:asciiname":"Bayt Shahm",
    "gn:country_code":"YE",
    "gn:dem":2655,
    "gn:feature_class":"P",
    "gn:feature_code":"PPL",
    "gn:name":"Bayt Shahm",
    "gn:population":0,
    "gn:timezone":"Asia/Aden",
    "iso:country":"YE",
    "wof:name":"Bayt Shahm",
    "wof:placetype":"locality"
},
  "geometry": {"coordinates":[43.7676,15.47688],"type":"Point"}
}