{
  "type": "Feature",
  "properties": {
    "gn:admin1_code":"16.0",
    "gn:admin2_code":"2316.0",
    "gn:asciiname":"Mahall Bayt Wahhab",
    "gn:country_code":"YE",
    "gn:dem":2323,
    "gn:feature_class":"P",
    "gn:feature_code":"PPL",
    "gn:name":"Ma\u1e29all Bayt Wahhab",
    "gn:population":0,
    "gn:timezone":"Asia/Aden",
    "iso:country":"YE",
    "name:und_x_variant":[
        "Ma\u1e29all Bayt Wahhab"
    ],
    "wof:name":"Mahall Bayt Wahhab",
    "wof:placetype":"locality"
},
  "geometry": {"coordinates":[44.44785,15.1769],"type":"Point"}
}