{
  "type": "Feature",
  "properties": {
    "gn:admin1_code":"15.0",
    "gn:admin2_code":"2212.0",
    "gn:asciiname":"Al Khaniq",
    "gn:country_code":"YE",
    "gn:dem":1896,
    "gn:feature_class":"P",
    "gn:feature_code":"PPL",
    "gn:name":"Al Kh\u0101niq",
    "gn:population":0,
    "gn:timezone":"Asia/Aden",
    "iso:country":"YE",
    "name:ara_x_preferred":[
        "Al Kh\u0101niq"
    ],
    "name:ara_x_variant":[
        "\u0627\u0644\u062e\u0627\u0646\u0642"
    ],
    "wof:name":"Al Khaniq",
    "wof:placetype":"locality"
},
  "geometry": {"coordinates":[43.78425,16.89725],"type":"Point"}
}