{
  "type": "Feature",
  "properties": {
    "gn:admin1_code":"22.0",
    "gn:admin2_code":"1702.0",
    "gn:asciiname":"Qabr al `Abd",
    "gn:country_code":"YE",
    "gn:dem":158,
    "gn:feature_class":"P",
    "gn:feature_code":"PPL",
    "gn:name":"Qabr al \u2018Abd",
    "gn:population":0,
    "gn:timezone":"Asia/Aden",
    "iso:country":"YE",
    "name:ara_x_preferred":[
        "\u0642\u0628\u0631 \u0627\u0644\u0639\u0628\u062f"
    ],
    "name:und_x_variant":[
        "Qabr al \u2018Abd"
    ],
    "wof:name":"Qabr al `Abd",
    "wof:placetype":"locality"
},
  "geometry": {"coordinates":[43.16271,16.53584],"type":"Point"}
}