{
  "type": "Feature",
  "properties": {
    "gn:admin1_code":"5.0",
    "gn:asciiname":"`Awid",
    "gn:country_code":"YE",
    "gn:dem":1206,
    "gn:feature_class":"P",
    "gn:feature_code":"PPL",
    "gn:name":"\u2018\u0100wid",
    "gn:population":0,
    "gn:timezone":"Asia/Aden",
    "iso:country":"YE",
    "name:ara_x_preferred":[
        "\u0639\u0627\u0648\u062f"
    ],
    "name:und_x_variant":[
        "\u2018\u0100wid"
    ],
    "wof:name":"`Awid",
    "wof:placetype":"locality"
},
  "geometry": {"coordinates":[45.8958,14.56869],"type":"Point"}
}