{
  "type": "Feature",
  "properties": {
    "gn:gn_country":"YE",
    "gn:gn_fcode":"PPL",
    "gn:gn_pop":5,
    "gn:population":5,
    "iso:country":"YE",
    "name:ara_x_preferred":[
        "\u0627\u0644\u062a \u0627\u0644\u0637\u0644\u064a"
    ],
    "name:eng_x_preferred":[
        "Alt At Tilli"
    ],
    "name:eng_x_variant":[
        "Umm at Tur\u0101b as Sufl\u00e1"
    ],
    "qs_pg:aaroncc":"YE",
    "qs_pg:gn_country":"YE",
    "qs_pg:gn_fcode":"PPL",
    "qs_pg:gn_pop":5,
    "qs_pg:name":"Alt a\u0163 \u0162ill\u012b",
    "qs_pg:photos_9r":0,
    "qs_pg:photos_sr":0,
    "qs_pg:pop_sr":1,
    "qs_pg:qs_pg_placetype":"locality",
    "wof:name":"Alt a\u0163 \u0162ill\u012b",
    "wof:placetype":"locality",
    "wof:population":5
},
  "geometry": {"coordinates":[43.49298,16.86482],"type":"Point"}
}