{
  "type": "Feature",
  "properties": {
    "gn:admin1_code":"22.0",
    "gn:admin2_code":"1730.0",
    "gn:asciiname":"Hasan al Qal'ah",
    "gn:country_code":"YE",
    "gn:dem":1207,
    "gn:feature_class":"P",
    "gn:feature_code":"PPL",
    "gn:name":"\u1e28a\u015fan al Qal\u2018ah",
    "gn:population":0,
    "gn:timezone":"Asia/Aden",
    "iso:country":"YE",
    "name:ara_x_preferred":[
        "\u062d\u0635\u0646 \u0627\u0644\u0642\u0644\u0639\u0629"
    ],
    "name:und_x_variant":[
        "\u1e28a\u015fan al Qal\u2018ah"
    ],
    "wof:name":"Hasan al Qal'ah",
    "wof:placetype":"locality"
},
  "geometry": {"coordinates":[43.39776,16.29285],"type":"Point"}
}