{
  "type": "Feature",
  "properties": {
    "gn:admin1_code":"11.0",
    "gn:admin2_code":"2001.0",
    "gn:asciiname":"Bayt al Juhaynah",
    "gn:country_code":"YE",
    "gn:dem":2329,
    "gn:feature_class":"P",
    "gn:feature_code":"PPL",
    "gn:name":"Bayt al Ju\u1e29aynah",
    "gn:population":0,
    "gn:timezone":"Asia/Aden",
    "iso:country":"YE",
    "name:und_x_variant":[
        "Bayt al Ju\u1e29aynah"
    ],
    "wof:name":"Bayt al Juhaynah",
    "wof:placetype":"locality"
},
  "geometry": {"coordinates":[44.40358,14.93539],"type":"Point"}
}