{
  "type": "Feature",
  "properties": {
    "gn:admin1_code":"11.0",
    "gn:admin2_code":"2012.0",
    "gn:asciiname":"`Ashrus",
    "gn:country_code":"YE",
    "gn:dem":1918,
    "gn:feature_class":"P",
    "gn:feature_code":"PPL",
    "gn:name":"\u2018Ashr\u016bs",
    "gn:population":0,
    "gn:timezone":"Asia/Aden",
    "iso:country":"YE",
    "name:ara_x_preferred":[
        "\u2018Ashr\u016bs"
    ],
    "wof:name":"`Ashrus",
    "wof:placetype":"locality"
},
  "geometry": {"coordinates":[44.18234,14.65507],"type":"Point"}
}