{
  "type": "Feature",
  "properties": {
    "gn:admin1_code":"25.0",
    "gn:admin2_code":"1515.0",
    "gn:asciiname":"Hadad",
    "gn:country_code":"YE",
    "gn:dem":1425,
    "gn:feature_class":"P",
    "gn:feature_code":"PPL",
    "gn:name":"Had\u0101d",
    "gn:population":0,
    "gn:timezone":"Asia/Aden",
    "iso:country":"YE",
    "name:ara_x_preferred":[
        "\u0647\u062f\u062f"
    ],
    "name:azb_x_preferred":[
        "\u0627\u06cc\u0634\u06a9\u0648\u0631"
    ],
    "name:ben_x_preferred":[
        "\u09b9\u09be\u09a6\u09be\u09a6"
    ],
    "name:deu_x_preferred":[
        "Hadad"
    ],
    "name:heb_x_preferred":[
        "\u05d4\u05d3\u05d3"
    ],
    "name:hrv_x_preferred":[
        "Hadad"
    ],
    "name:hun_x_preferred":[
        "Hadad"
    ],
    "name:ind_x_preferred":[
        "Hadad"
    ],
    "name:ita_x_preferred":[
        "Hadad"
    ],
    "name:nld_x_preferred":[
        "Hadad"
    ],
    "name:por_x_preferred":[
        "Adade"
    ],
    "name:rus_x_preferred":[
        "\u0411\u0430\u0430\u043b-\u0425\u0430\u0434\u0430\u0434"
    ],
    "name:sco_x_preferred":[
        "Hadad"
    ],
    "name:snd_x_preferred":[
        "\u0627\u062f\u0627\u062f"
    ],
    "name:spa_x_preferred":[
        "Hadad"
    ],
    "name:swe_x_preferred":[
        "Hadad"
    ],
    "name:tam_x_preferred":[
        "\u0b86\u0ba4\u0bbe\u0ba4\u0bcd"
    ],
    "name:tgl_x_preferred":[
        "Hadad"
    ],
    "name:tur_x_preferred":[
        "Hadad"
    ],
    "name:und_x_variant":[
        "Had\u0101d"
    ],
    "wof:name":"Hadad",
    "wof:placetype":"locality"
},
  "geometry": {"coordinates":[44.02658,13.25245],"type":"Point"}
}