{
  "type": "Feature",
  "properties": {
    "gn:admin1_code":"25.0",
    "gn:admin2_code":"1515.0",
    "gn:asciiname":"Hadad",
    "gn:country_code":"YE",
    "gn:dem":1425,
    "gn:feature_class":"P",
    "gn:feature_code":"PPL",
    "gn:name":"Had\u0101d",
    "gn:population":0,
    "gn:timezone":"Asia/Aden",
    "iso:country":"YE",
    "name:und_x_variant":[
        "Had\u0101d"
    ],
    "wof:name":"Hadad",
    "wof:placetype":"locality"
},
  "geometry": {"coordinates":[44.02658,13.25245],"type":"Point"}
}