{
  "type": "Feature",
  "properties": {
    "gn:admin1_code":"23.0",
    "gn:admin2_code":"1101.0",
    "gn:asciiname":"Di Hilf",
    "gn:country_code":"YE",
    "gn:dem":2486,
    "gn:feature_class":"P",
    "gn:feature_code":"PPL",
    "gn:name":"D\u012b \u1e28ilf",
    "gn:population":0,
    "gn:timezone":"Asia/Aden",
    "iso:country":"YE",
    "name:ara_x_preferred":[
        "\u062f\u064a \u062d\u0644\u0641"
    ],
    "name:und_x_variant":[
        "D\u012b \u1e28ilf"
    ],
    "wof:name":"Di Hilf",
    "wof:placetype":"locality"
},
  "geometry": {"coordinates":[44.23552,14.28335],"type":"Point"}
}