{
  "type": "Feature",
  "properties": {
    "gn:admin1_code":"14.0",
    "gn:admin2_code":"2608.0",
    "gn:asciiname":"Khubayzan",
    "gn:country_code":"YE",
    "gn:dem":1500,
    "gn:feature_class":"P",
    "gn:feature_code":"PPL",
    "gn:name":"Khubayz\u0101n",
    "gn:population":0,
    "gn:timezone":"Asia/Aden",
    "iso:country":"YE",
    "name:ara_x_preferred":[
        "\u062e\u0628\u064a\u0632\u0627\u0646"
    ],
    "name:und_x_variant":[
        "Kawlat Khubayz\u0101n",
        "Khubayz\u0101n"
    ],
    "wof:name":"Khubayzan",
    "wof:placetype":"locality"
},
  "geometry": {"coordinates":[45.08571,15.07992],"type":"Point"}
}