{
  "type": "Feature",
  "properties": {
    "gn:gn_country":"YE",
    "gn:gn_fcode":"PPL",
    "gn:gn_pop":5,
    "gn:population":5,
    "iso:country":"YE",
    "name:ara_x_preferred":[
        "Al Mukhkhi\u015f"
    ],
    "name:ara_x_variant":[
        "\u0627\u0644\u0645\u062e\u0635"
    ],
    "name:eng_x_preferred":[
        "Al Mukhkhis"
    ],
    "name:eng_x_variant":[
        "Al \u1e28\u0101zah al Qa\u015f\u0101\u2018\u012b"
    ],
    "qs_pg:aaroncc":"YE",
    "qs_pg:gn_country":"YE",
    "qs_pg:gn_fcode":"PPL",
    "qs_pg:gn_pop":5,
    "qs_pg:name":"Al Mukhkhi\u015f",
    "qs_pg:photos_9r":0,
    "qs_pg:photos_sr":0,
    "qs_pg:pop_sr":1,
    "qs_pg:qs_pg_placetype":"locality",
    "wof:name":"Al Mukhkhi\u015f",
    "wof:placetype":"locality",
    "wof:population":5
},
  "geometry": {"coordinates":[43.31338,16.11235],"type":"Point"}
}