{
  "type": "Feature",
  "properties": {
    "gn:country":"YE",
    "gn:fcode":"PPL",
    "gn:pop":3,
    "iso:country":"YE",
    "name:ara_x_preferred":[
        "\u062e\u0636\u064a\u0631\u0645\u064a\u0629"
    ],
    "name:eng_x_preferred":[
        "Khuuayrmiyah"
    ],
    "name:eng_x_variant":[
        "B\u0101\u1e29ishw\u0101n"
    ],
    "qs:name":"Khu\u1e11ayrm\u012byah",
    "qs:photos_9r":0,
    "qs:photos_sr":0,
    "qs:pop_sr":"1",
    "wof:name":"Khu\u1e11ayrm\u012byah",
    "wof:placetype":"locality",
    "wof:population":3
},
  "geometry": {"coordinates":[43.74028,17.10955],"type":"Point"}
}