{
  "type": "Feature",
  "properties": {
    "gn:admin1_code":"18.0",
    "gn:admin2_code":"3003.0",
    "gn:asciiname":"Atta",
    "gn:country_code":"YE",
    "gn:dem":2237,
    "gn:feature_class":"P",
    "gn:feature_code":"PPL",
    "gn:name":"Atta",
    "gn:population":0,
    "gn:timezone":"Asia/Aden",
    "iso:country":"YE",
    "name:cat_x_preferred":[
        "Atta"
    ],
    "name:ceb_x_preferred":[
        "Atta"
    ],
    "name:deu_x_preferred":[
        "Atta"
    ],
    "name:fra_x_preferred":[
        "Atta"
    ],
    "name:ita_x_preferred":[
        "Atta"
    ],
    "name:kor_x_preferred":[
        "\uc544\ud0c0"
    ],
    "name:mal_x_preferred":[
        "\u0d06\u0d1f\u0d4d\u0d1f"
    ],
    "name:nld_x_preferred":[
        "Atta"
    ],
    "name:pol_x_preferred":[
        "Atta"
    ],
    "name:rus_x_preferred":[
        "\u0410\u0442\u0442\u0430"
    ],
    "name:spa_x_preferred":[
        "Atta"
    ],
    "name:swe_x_preferred":[
        "Atta"
    ],
    "name:und_x_variant":[
        "\u2018A\u0163\u0163ah",
        "Atta"
    ],
    "wof:name":"Atta",
    "wof:placetype":"locality"
},
  "geometry": {"coordinates":[44.76463,13.96804],"type":"Point"}
}