{
  "type": "Feature",
  "properties": {
    "gn:country":"YE",
    "gn:fcode":"PPL",
    "gn:pop":4,
    "iso:country":"YE",
    "name:ara_x_preferred":[
        "\u0628\u064a\u062a \u0627\u0644\u0639\u0648\u062c\u0627\u0621"
    ],
    "name:eng_x_preferred":[
        "Bayt Al 'Awja"
    ],
    "name:eng_x_variant":[
        "D\u0101r ash Sh\u0101m\u012byah"
    ],
    "qs:name":"Bayt al \u2018Awj\u0101\u2019",
    "qs:photos_9r":0,
    "qs:photos_sr":0,
    "qs:pop_sr":"1",
    "wof:name":"Bayt al \u2018Awj\u0101\u2019",
    "wof:placetype":"locality",
    "wof:population":4
},
  "geometry": {"coordinates":[43.42203,16.07848],"type":"Point"}
}