{
  "type": "Feature",
  "properties": {
    "gn:admin1_code":"23.0",
    "gn:admin2_code":"1101.0",
    "gn:asciiname":"Hatabah",
    "gn:country_code":"YE",
    "gn:dem":1534,
    "gn:feature_class":"P",
    "gn:feature_code":"PPL",
    "gn:name":"\u1e28a\u0163\u0101bah",
    "gn:population":0,
    "gn:timezone":"Asia/Aden",
    "iso:country":"YE",
    "name:ara_x_preferred":[
        "\u062d\u0637\u0627\u0628\u0629"
    ],
    "name:und_x_variant":[
        "\u1e28a\u0163\u0101bah"
    ],
    "wof:name":"Hatabah",
    "wof:placetype":"locality"
},
  "geometry": {"coordinates":[44.18433,14.28171],"type":"Point"}
}