{
  "type": "Feature",
  "properties": {
    "gn:admin1_code":"28.0",
    "gn:admin2_code":"1926.0",
    "gn:asciiname":"Zafiq",
    "gn:country_code":"YE",
    "gn:dem":476,
    "gn:feature_class":"P",
    "gn:feature_code":"PPL",
    "gn:name":"Z\u0101fiq",
    "gn:population":0,
    "gn:timezone":"Asia/Aden",
    "iso:country":"YE",
    "wof:name":"Zafiq",
    "wof:placetype":"locality"
},
  "geometry": {"coordinates":[54.34656999999999,12.53747],"type":"Point"}
}