{
  "type": "Feature",
  "properties": {
    "gn:admin1_code":"14.0",
    "gn:admin2_code":"2601.0",
    "gn:asciiname":"Al Mawdin",
    "gn:country_code":"YE",
    "gn:dem":1202,
    "gn:feature_class":"P",
    "gn:feature_code":"PPL",
    "gn:name":"Al Mawdin",
    "gn:population":0,
    "gn:timezone":"Asia/Aden",
    "iso:country":"YE",
    "name:ara_x_preferred":[
        "\u0627\u0644\u0645\u0648\u062f\u0646"
    ],
    "wof:name":"Al Mawdin",
    "wof:placetype":"locality"
},
  "geometry": {"coordinates":[44.76908,15.89161],"type":"Point"}
}