{
  "type": "Feature",
  "properties": {
    "gn:admin1_code":"18.0",
    "gn:admin2_code":"3002.0",
    "gn:asciiname":"Kawlat az Zaqri",
    "gn:country_code":"YE",
    "gn:dem":2105,
    "gn:feature_class":"P",
    "gn:feature_code":"PPL",
    "gn:name":"Kawlat az Zaqr\u012b",
    "gn:population":0,
    "gn:timezone":"Asia/Aden",
    "iso:country":"YE",
    "name:und_x_variant":[
        "Kawlat az Zaqr\u012b"
    ],
    "wof:name":"Kawlat az Zaqri",
    "wof:placetype":"locality"
},
  "geometry": {"coordinates":[44.635,14.07587],"type":"Point"}
}