{
  "type": "Feature",
  "properties": {
    "gn:country":"YE",
    "gn:fcode":"PPL",
    "gn:pop":110,
    "iso:country":"YE",
    "name:ara_x_preferred":[
        "\u0633\u0648\u062f\u0627\u0646"
    ],
    "qs:name":"Sawd\u0101n",
    "qs:photos_9r":0,
    "qs:photos_sr":0,
    "qs:pop_sr":"1",
    "wof:name":"Sawd\u0101n",
    "wof:placetype":"locality",
    "wof:population":110
},
  "geometry": {"coordinates":[43.66402,16.94309],"type":"Point"}
}