{
  "type": "Feature",
  "properties": {
    "gn:country":"YE",
    "gn:fcode":"PPL",
    "gn:pop":8,
    "iso:country":"YE",
    "name:ara_x_preferred":[
        "\u0627\u0644\u062d\u062c\u064a\u062c"
    ],
    "name:eng_x_preferred":[
        "Al Hujayh"
    ],
    "qs:name":"Al \u1e28ujay\u1e29",
    "qs:photos_9r":0,
    "qs:photos_sr":0,
    "qs:pop_sr":"1",
    "wof:name":"Al \u1e28ujay\u1e29",
    "wof:placetype":"locality",
    "wof:population":8
},
  "geometry": {"coordinates":[43.77598,13.43783],"type":"Point"}
}