{
  "type": "Feature",
  "properties": {
    "gn:country":"YE",
    "gn:fcode":"PPLX",
    "gn:population":12,
    "iso:country":"YE",
    "name:ara_x_preferred":[
        "\u0627\u0644\u062a \u062d\u064a\u0648\u0627\u0646"
    ],
    "qs_pg:aaroncc":"YE",
    "qs_pg:gn_country":"YE",
    "qs_pg:gn_fcode":"PPLX",
    "qs_pg:gn_pop":12,
    "qs_pg:name":"Alt \u1e28ayw\u0101n",
    "qs_pg:photos_9r":0,
    "qs_pg:photos_sr":0,
    "qs_pg:pop_sr":1,
    "qs_pg:qs_pg_placetype":"neighbourhood",
    "wof:name":"Alt \u1e28ayw\u0101n",
    "wof:placetype":"neighbourhood",
    "wof:population":12
},
  "geometry": {"coordinates":[43.49653,16.83941],"type":"Point"}
}