{
  "type": "Feature",
  "properties": {
    "gn:country":"YE",
    "gn:fcode":"PPL",
    "gn:pop":1,
    "iso:country":"YE",
    "name:ara_x_preferred":[
        "\u0628\u0644\u0627\u062f \u064a\u0645\u0627\u0646"
    ],
    "name:eng_x_preferred":[
        "Bilad Yaman"
    ],
    "qs:name":"Bil\u0101d Yam\u0101n",
    "qs:photos_9r":0,
    "qs:photos_sr":0,
    "qs:pop_sr":"1",
    "wof:name":"Bil\u0101d Yam\u0101n",
    "wof:placetype":"locality",
    "wof:population":1
},
  "geometry": {"coordinates":[45.5206,14.9852],"type":"Point"}
}