{
  "type": "Feature",
  "properties": {
    "gn:admin1_code":"8.0",
    "gn:admin2_code":"1807.0",
    "gn:asciiname":"Mahall al Mash`af",
    "gn:country_code":"YE",
    "gn:dem":68,
    "gn:feature_class":"P",
    "gn:feature_code":"PPL",
    "gn:name":"Ma\u1e29all al Mash\u2018af",
    "gn:population":0,
    "gn:timezone":"Asia/Aden",
    "iso:country":"YE",
    "name:und_x_variant":[
        "Ma\u1e29all al Mash\u2018af"
    ],
    "wof:name":"Mahall al Mash`af",
    "wof:placetype":"locality"
},
  "geometry": {"coordinates":[43.03565,15.30418],"type":"Point"}
}