{
  "type": "Feature",
  "properties": {
    "gn:admin1_code":"15.0",
    "gn:admin2_code":"2201.0",
    "gn:asciiname":"Baqim",
    "gn:country_code":"YE",
    "gn:dem":2013,
    "gn:feature_class":"P",
    "gn:feature_code":"PPL",
    "gn:name":"B\u0101qim",
    "gn:population":0,
    "gn:timezone":"Asia/Aden",
    "iso:country":"YE",
    "name:ara_x_preferred":[
        "B\u0101qim"
    ],
    "wof:name":"Baqim",
    "wof:placetype":"locality"
},
  "geometry": {"coordinates":[43.53333,17.31667],"type":"Point"}
}