{
  "type": "Feature",
  "properties": {
    "gn:admin1_code":"10.0",
    "gn:admin2_code":"2702.0",
    "gn:asciiname":"Maqbal",
    "gn:country_code":"YE",
    "gn:dem":2583,
    "gn:feature_class":"P",
    "gn:feature_code":"PPL",
    "gn:name":"Maqbal",
    "gn:population":0,
    "gn:timezone":"Asia/Aden",
    "iso:country":"YE",
    "wof:name":"Maqbal",
    "wof:placetype":"locality"
},
  "geometry": {"coordinates":[43.72869,15.49456],"type":"Point"}
}