{
  "type": "Feature",
  "properties": {
    "gn:admin1_code":"22.0",
    "gn:admin2_code":"1727.0",
    "gn:asciiname":"Bayt al Harawi",
    "gn:country_code":"YE",
    "gn:dem":1570,
    "gn:feature_class":"P",
    "gn:feature_code":"PPL",
    "gn:name":"Bayt al \u1e28ar\u0101w\u012b",
    "gn:population":0,
    "gn:timezone":"Asia/Aden",
    "iso:country":"YE",
    "name:ara_x_preferred":[
        "\u0628\u064a\u062a \u0627\u0644\u062d\u0631\u0627\u0648\u064a"
    ],
    "name:und_x_variant":[
        "Bayt al \u1e28ar\u0101w\u012b"
    ],
    "wof:name":"Bayt al Harawi",
    "wof:placetype":"locality"
},
  "geometry": {"coordinates":[43.57433,15.57332],"type":"Point"}
}