{
  "type": "Feature",
  "properties": {
    "gn:admin1_code":"8.0",
    "gn:admin2_code":"1817.0",
    "gn:asciiname":"Al Marawigh",
    "gn:country_code":"YE",
    "gn:dem":170,
    "gn:feature_class":"P",
    "gn:feature_code":"PPL",
    "gn:name":"Al Mar\u0101wigh",
    "gn:population":0,
    "gn:timezone":"Asia/Aden",
    "iso:country":"YE",
    "name:und_x_variant":[
        "Al Mar\u0101wigh"
    ],
    "wof:name":"Al Marawigh",
    "wof:placetype":"locality"
},
  "geometry": {"coordinates":[43.43584,14.56258],"type":"Point"}
}