{
  "type": "Feature",
  "properties": {
    "gn:admin1_code":"19.0",
    "gn:admin2_code":"2919.0",
    "gn:asciiname":"Fashayish",
    "gn:country_code":"YE",
    "gn:dem":2109,
    "gn:feature_class":"P",
    "gn:feature_code":"PPL",
    "gn:name":"Fash\u0101yish",
    "gn:population":0,
    "gn:timezone":"Asia/Aden",
    "iso:country":"YE",
    "name:ara_x_preferred":[
        "\u0641\u0634\u0627\u064a\u0634"
    ],
    "name:und_x_variant":[
        "Fash\u0101yish"
    ],
    "wof:name":"Fashayish",
    "wof:placetype":"locality"
},
  "geometry": {"coordinates":[43.88583,16.03955],"type":"Point"}
}