{
  "type": "Feature",
  "properties": {
    "gn:admin1_code":"15.0",
    "gn:admin2_code":"2205.0",
    "gn:asciiname":"As Suflayn",
    "gn:country_code":"YE",
    "gn:dem":1495,
    "gn:feature_class":"P",
    "gn:feature_code":"PPL",
    "gn:name":"As Suflayn",
    "gn:population":0,
    "gn:timezone":"Asia/Aden",
    "iso:country":"YE",
    "name:ara_x_preferred":[
        "\u0627\u0644\u0633\u0641\u0644\u064a\u0646"
    ],
    "wof:name":"As Suflayn",
    "wof:placetype":"locality"
},
  "geometry": {"coordinates":[43.24466,16.90939],"type":"Point"}
}