{
  "type": "Feature",
  "properties": {
    "gn:admin1_code":"8.0",
    "gn:admin2_code":"1814.0",
    "gn:asciiname":"Al Kurd",
    "gn:country_code":"YE",
    "gn:dem":53,
    "gn:feature_class":"P",
    "gn:feature_code":"PPL",
    "gn:name":"Al Kurd",
    "gn:population":0,
    "gn:timezone":"Asia/Aden",
    "iso:country":"YE",
    "wof:name":"Al Kurd",
    "wof:placetype":"locality"
},
  "geometry": {"coordinates":[43.18294,14.6213],"type":"Point"}
}