{
  "type": "Feature",
  "properties": {
    "gn:admin1_code":"15.0",
    "gn:admin2_code":"2208.0",
    "gn:asciiname":"Quhafah",
    "gn:country_code":"YE",
    "gn:dem":2359,
    "gn:feature_class":"P",
    "gn:feature_code":"PPL",
    "gn:name":"Qu\u1e29afah",
    "gn:population":0,
    "gn:timezone":"Asia/Aden",
    "iso:country":"YE",
    "name:ara_x_preferred":[
        "\u0642\u062d\u0641\u0629"
    ],
    "name:und_x_variant":[
        "Qu\u1e29afah"
    ],
    "wof:name":"Quhafah",
    "wof:placetype":"locality"
},
  "geometry": {"coordinates":[43.44826,16.68052999999999],"type":"Point"}
}