{
  "type": "Feature",
  "properties": {
    "gn:admin1_code":"16.0",
    "gn:admin2_code":"2313.0",
    "gn:asciiname":"Bayn Nashwan",
    "gn:country_code":"YE",
    "gn:dem":2392,
    "gn:feature_class":"P",
    "gn:feature_code":"PPL",
    "gn:name":"Bayn Nashw\u0101n",
    "gn:population":0,
    "gn:timezone":"Asia/Aden",
    "iso:country":"YE",
    "name:ara_x_preferred":[
        "\u0628\u064a\u0646 \u0646\u0634\u0648\u0627\u0646"
    ],
    "name:und_x_variant":[
        "Bayn Nashw\u0101n"
    ],
    "wof:name":"Bayn Nashwan",
    "wof:placetype":"locality"
},
  "geometry": {"coordinates":[44.58538,15.35281],"type":"Point"}
}