{
  "type": "Feature",
  "properties": {
    "gn:admin1_code":"14.0",
    "gn:admin2_code":"2605.0",
    "gn:asciiname":"Adh Dhira'",
    "gn:country_code":"YE",
    "gn:dem":1746,
    "gn:feature_class":"P",
    "gn:feature_code":"PPL",
    "gn:name":"Adh Dhir\u0101\u2018",
    "gn:population":0,
    "gn:timezone":"Asia/Aden",
    "iso:country":"YE",
    "name:ara_x_preferred":[
        "\u0627\u0644\u0630\u0631\u0627\u0639"
    ],
    "name:und_x_variant":[
        "Adh Dhir\u0101\u2018"
    ],
    "wof:name":"Adh Dhira'",
    "wof:placetype":"locality"
},
  "geometry": {"coordinates":[44.77484000000001,15.34054],"type":"Point"}
}