{
  "type": "Feature",
  "properties": {
    "gn:admin1_code":"16.0",
    "gn:admin2_code":"2304.0",
    "gn:asciiname":"Al Hinami",
    "gn:country_code":"YE",
    "gn:dem":2293,
    "gn:feature_class":"P",
    "gn:feature_code":"PPL",
    "gn:name":"Al \u1e28inam\u012b",
    "gn:population":0,
    "gn:timezone":"Asia/Aden",
    "iso:country":"YE",
    "name:und_x_variant":[
        "Al \u1e28inam\u012b",
        "Bayt al \u1e28anam\u012b"
    ],
    "wof:name":"Al Hinami",
    "wof:placetype":"locality"
},
  "geometry": {"coordinates":[44.33779000000001,15.45256],"type":"Point"}
}