{
  "type": "Feature",
  "properties": {
    "gn:admin1_code":"8.0",
    "gn:admin2_code":"1810.0",
    "gn:asciiname":"Al Mihsam",
    "gn:country_code":"YE",
    "gn:dem":133,
    "gn:feature_class":"P",
    "gn:feature_code":"PPL",
    "gn:name":"Al Mi\u1e29\u015f\u0101m",
    "gn:population":0,
    "gn:timezone":"Asia/Aden",
    "iso:country":"YE",
    "name:ara_x_preferred":[
        "Al Mi\u1e29s\u0101m"
    ],
    "name:ara_x_variant":[
        "\u0627\u0644\u0645\u062d\u0635\u0627\u0645"
    ],
    "name:und_x_variant":[
        "Al Mi\u1e29\u015f\u0101m"
    ],
    "wof:name":"Al Mihsam",
    "wof:placetype":"locality"
},
  "geometry": {"coordinates":[43.19600000000001,15.08873],"type":"Point"}
}