{
  "type": "Feature",
  "properties": {
    "gn:admin1_code":"25.0",
    "gn:admin2_code":"1505.0",
    "gn:asciiname":"Qaryat al Bitnah",
    "gn:country_code":"YE",
    "gn:dem":870,
    "gn:feature_class":"P",
    "gn:feature_code":"PPL",
    "gn:name":"Qaryat al Bi\u0163nah",
    "gn:population":0,
    "gn:timezone":"Asia/Aden",
    "iso:country":"YE",
    "name:und_x_variant":[
        "Qaryat al Bi\u0163nah"
    ],
    "wof:name":"Qaryat al Bitnah",
    "wof:placetype":"locality"
},
  "geometry": {"coordinates":[43.66149,13.65999],"type":"Point"}
}