{
  "type": "Feature",
  "properties": {
    "gn:country":"YE",
    "gn:fcode":"PPL",
    "gn:population":2,
    "iso:country":"YE",
    "name:ara_x_preferred":[
        "\u0627\u0644\u0639\u062c\u0641"
    ],
    "name:eng_x_preferred":[
        "Al 'Ujaf"
    ],
    "name:eng_x_variant":[
        "Al Manbahah"
    ],
    "qs_pg:aaroncc":"YE",
    "qs_pg:gn_country":"YE",
    "qs_pg:gn_fcode":"PPL",
    "qs_pg:gn_pop":2,
    "qs_pg:name":"Al \u2018Ujaf",
    "qs_pg:photos_9r":0,
    "qs_pg:photos_sr":0,
    "qs_pg:pop_sr":1,
    "qs_pg:qs_pg_placetype":"locality",
    "wof:name":"Al \u2018Ujaf",
    "wof:placetype":"locality",
    "wof:population":2
},
  "geometry": {"coordinates":[43.86976,13.3591],"type":"Point"}
}