{
  "type": "Feature",
  "properties": {
    "gn:admin1_code":"24.0",
    "gn:admin2_code":"2513.0",
    "gn:asciiname":"Ash Shatt",
    "gn:country_code":"YE",
    "gn:dem":237,
    "gn:feature_class":"P",
    "gn:feature_code":"PPLA2",
    "gn:name":"Ash Sha\u0163\u0163",
    "gn:population":0,
    "gn:timezone":"Asia/Aden",
    "iso:country":"YE",
    "name:ara_x_preferred":[
        "\u0623\u0645 \u0634\u0637"
    ],
    "name:ara_x_variant":[
        "\u0627\u0644\u0634\u0637"
    ],
    "name:und_x_variant":[
        "Am Shat",
        "Am Sha\u0163\u0163",
        "Ash Sha\u0163\u0163"
    ],
    "wof:name":"Ash Shatt",
    "wof:placetype":"locality"
},
  "geometry": {"coordinates":[44.03571,12.89357],"type":"Point"}
}