{
  "type": "Feature",
  "properties": {
    "gn:admin1_code":"15.0",
    "gn:admin2_code":"2206.0",
    "gn:asciiname":"As Sawdah",
    "gn:country_code":"YE",
    "gn:dem":277,
    "gn:feature_class":"P",
    "gn:feature_code":"PPL",
    "gn:name":"As Sawdah",
    "gn:population":0,
    "gn:timezone":"Asia/Aden",
    "iso:country":"YE",
    "name:ara_x_preferred":[
        "\u0627\u0644\u0633\u0648\u062f\u0629"
    ],
    "wof:name":"As Sawdah",
    "wof:placetype":"locality"
},
  "geometry": {"coordinates":[43.14009,16.90399],"type":"Point"}
}