{
  "type": "Feature",
  "properties": {
    "gn:admin1_code":"22.0",
    "gn:admin2_code":"1711.0",
    "gn:asciiname":"Al Hanakah",
    "gn:country_code":"YE",
    "gn:dem":658,
    "gn:feature_class":"P",
    "gn:feature_code":"PPL",
    "gn:name":"Al \u1e28anakah",
    "gn:population":12,
    "gn:timezone":"Asia/Aden",
    "iso:country":"YE",
    "name:ara_x_preferred":[
        "\u0627\u0644\u062d\u0646\u0643\u0629"
    ],
    "name:fas_x_preferred":[
        "\u0627\u0644\u062d\u0646\u062e\u0647"
    ],
    "name:nno_x_preferred":[
        "Al Hanakah"
    ],
    "name:und_x_variant":[
        "Al \u1e28anakah"
    ],
    "wof:name":"Al Hanakah",
    "wof:placetype":"locality",
    "wof:population":12
},
  "geometry": {"coordinates":[43.36523,16.10547],"type":"Point"}
}