{
  "type": "Feature",
  "properties": {
    "gn:admin1_code":"22.0",
    "gn:admin2_code":"1724.0",
    "gn:asciiname":"Gharb al Fasi`",
    "gn:country_code":"YE",
    "gn:dem":380,
    "gn:feature_class":"P",
    "gn:feature_code":"PPL",
    "gn:name":"Gharb al Fas\u012b\u2018",
    "gn:population":0,
    "gn:timezone":"Asia/Aden",
    "iso:country":"YE",
    "name:und_x_variant":[
        "Gharb al Fas\u012b\u2018"
    ],
    "wof:name":"Gharb al Fasi`",
    "wof:placetype":"locality"
},
  "geometry": {"coordinates":[43.4019,15.71628],"type":"Point"}
}