{
  "type": "Feature",
  "properties": {
    "gn:country":"YE",
    "gn:fcode":"PPL",
    "gn:pop":3,
    "iso:country":"YE",
    "name:ara_x_preferred":[
        "\u0633\u0647\u0644\u0629"
    ],
    "qs:name":"Sahilah",
    "qs:photos_9r":0,
    "qs:photos_sr":0,
    "qs:pop_sr":"1",
    "wof:name":"Sahilah",
    "wof:placetype":"locality",
    "wof:population":3
},
  "geometry": {"coordinates":[44.04871,17.05821],"type":"Point"}
}