{
  "type": "Feature",
  "properties": {
    "gn:country":"YE",
    "gn:fcode":"PPLX",
    "gn:population":22,
    "iso:country":"YE",
    "name:ara_x_preferred":[
        "\u0627\u0644\u0631\u0642\u064a\u0628"
    ],
    "qs:name":"Ar Ruqayb",
    "qs:photos_9r":0,
    "qs:photos_sr":0,
    "qs:pop_sr":"1",
    "wof:name":"Ar Ruqayb",
    "wof:placetype":"neighbourhood",
    "wof:population":22
},
  "geometry": {"coordinates":[44.3809,16.74752],"type":"Point"}
}