{
  "type": "Feature",
  "properties": {
    "gn:admin1_code":"19.0",
    "gn:admin2_code":"2904.0",
    "gn:asciiname":"Hadabat Abu Sawadi",
    "gn:country_code":"YE",
    "gn:dem":1151,
    "gn:feature_class":"P",
    "gn:feature_code":"PPLL",
    "gn:name":"\u1e28adabat Ab\u016b Saw\u0101d\u012b",
    "gn:population":0,
    "gn:timezone":"Asia/Aden",
    "iso:country":"YE",
    "name:ara_x_preferred":[
        "\u062d\u062f\u0628\u0629 \u0623\u0628\u0648 \u0633\u0648\u0627\u062f\u064a"
    ],
    "name:und_x_variant":[
        "\u1e28adabat Ab\u016b Saw\u0101d\u012b"
    ],
    "wof:name":"Hadabat Abu Sawadi",
    "wof:placetype":"locality"
},
  "geometry": {"coordinates":[43.7741,16.16795],"type":"Point"}
}