{
  "type": "Feature",
  "properties": {
    "gn:country":"YE",
    "gn:fcode":"PPL",
    "gn:pop":4,
    "iso:country":"YE",
    "name:ara_x_preferred":[
        "B\u0101b M\u0101li\u015f"
    ],
    "name:ara_x_variant":[
        "\u0628\u0627\u0628 \u0645\u0627\u0644\u0635"
    ],
    "name:eng_x_preferred":[
        "Bab Malis"
    ],
    "name:eng_x_variant":[
        "\u2018\u0100qil Wabrah"
    ],
    "qs:name":"B\u0101b M\u0101li\u015f",
    "qs:photos_9r":0,
    "qs:photos_sr":0,
    "qs:pop_sr":"1",
    "wof:name":"B\u0101b M\u0101li\u015f",
    "wof:placetype":"locality",
    "wof:population":4
},
  "geometry": {"coordinates":[43.5591,16.00127],"type":"Point"}
}