{
  "type": "Feature",
  "properties": {
    "gn:admin1_code":"23.0",
    "gn:admin2_code":"1103.0",
    "gn:asciiname":"Hamdan",
    "gn:country_code":"YE",
    "gn:dem":2459,
    "gn:feature_class":"P",
    "gn:feature_code":"PPL",
    "gn:name":"Hamd\u0101n",
    "gn:population":0,
    "gn:timezone":"Asia/Aden",
    "iso:country":"YE",
    "name:ara_x_preferred":[
        "\u0647\u0645\u062f\u0627\u0646"
    ],
    "name:und_x_variant":[
        "Hamd\u0101n"
    ],
    "wof:name":"Hamdan",
    "wof:placetype":"locality"
},
  "geometry": {"coordinates":[44.5071,14.26713],"type":"Point"}
}