{
  "type": "Feature",
  "properties": {
    "gn:admin1_code":"22.0",
    "gn:admin2_code":"1722.0",
    "gn:asciiname":"Muhafa",
    "gn:cc2":"YE",
    "gn:country_code":"YE",
    "gn:dem":340,
    "gn:feature_class":"P",
    "gn:feature_code":"PPL",
    "gn:name":"Muhafa",
    "gn:population":0,
    "gn:timezone":"Asia/Aden",
    "iso:country":"YE",
    "name:und_x_variant":[
        "Mahfa",
        "Muhafa"
    ],
    "wof:name":"Muhafa",
    "wof:placetype":"locality"
},
  "geometry": {"coordinates":[43.25,15.88333],"type":"Point"}
}