{
  "type": "Feature",
  "properties": {
    "gn:admin1_code":"28.0",
    "gn:admin2_code":"1926.0",
    "gn:asciiname":"Dinihuh",
    "gn:country_code":"YE",
    "gn:dem":316,
    "gn:feature_class":"P",
    "gn:feature_code":"PPL",
    "gn:name":"D\u012bnih\u016bh",
    "gn:population":0,
    "gn:timezone":"Asia/Aden",
    "iso:country":"YE",
    "wof:name":"Dinihuh",
    "wof:placetype":"locality"
},
  "geometry": {"coordinates":[54.2989,12.51686],"type":"Point"}
}