{
  "type": "Feature",
  "properties": {
    "gn:admin1_code":"20.0",
    "gn:admin2_code":"1420.0",
    "gn:asciiname":"Ar Radah",
    "gn:country_code":"YE",
    "gn:dem":2020,
    "gn:feature_class":"P",
    "gn:feature_code":"PPL",
    "gn:name":"Ar Rad\u0101h",
    "gn:population":0,
    "gn:timezone":"Asia/Aden",
    "iso:country":"YE",
    "name:und_x_variant":[
        "Ar Rad\u0101h"
    ],
    "wof:name":"Ar Radah",
    "wof:placetype":"locality"
},
  "geometry": {"coordinates":[45.33986,14.25877],"type":"Point"}
}