{
  "type": "Feature",
  "properties": {
    "gn:admin1_code":"19.0",
    "gn:admin2_code":"2919.0",
    "gn:asciiname":"Bani Hadasah",
    "gn:country_code":"YE",
    "gn:dem":2077,
    "gn:feature_class":"P",
    "gn:feature_code":"PPL",
    "gn:name":"Ban\u012b Hadasah",
    "gn:population":0,
    "gn:timezone":"Asia/Aden",
    "iso:country":"YE",
    "name:und_x_variant":[
        "Ban\u012b Hadasah"
    ],
    "wof:name":"Bani Hadasah",
    "wof:placetype":"locality"
},
  "geometry": {"coordinates":[43.87106,16.04567999999999],"type":"Point"}
}