{
  "type": "Feature",
  "properties": {
    "gn:admin1_code":"25.0",
    "gn:admin2_code":"1514.0",
    "gn:asciiname":"Ad Dawmalah",
    "gn:country_code":"YE",
    "gn:dem":1570,
    "gn:feature_class":"P",
    "gn:feature_code":"PPL",
    "gn:name":"Ad Dawmalah",
    "gn:population":0,
    "gn:timezone":"Asia/Aden",
    "iso:country":"YE",
    "wof:name":"Ad Dawmalah",
    "wof:placetype":"locality"
},
  "geometry": {"coordinates":[44.17568,13.3843],"type":"Point"}
}