{
  "type": "Feature",
  "properties": {
    "gn:country":"YE",
    "gn:fcode":"PPL",
    "gn:pop":12,
    "iso:country":"YE",
    "name:ara_x_preferred":[
        "Al \u1e28ij\u0101\u2019ir"
    ],
    "name:ara_x_variant":[
        "\u0627\u0644\u062d\u062c\u0627\u0626\u0631"
    ],
    "name:eng_x_preferred":[
        "Al Hijair"
    ],
    "name:eng_x_variant":[
        "Al Lujm"
    ],
    "qs:name":"Al \u1e28ij\u0101\u2019ir",
    "qs:photos_9r":0,
    "qs:photos_sr":0,
    "qs:pop_sr":"1",
    "wof:name":"Al \u1e28ij\u0101\u2019ir",
    "wof:placetype":"locality",
    "wof:population":12
},
  "geometry": {"coordinates":[44.27627,16.72251],"type":"Point"}
}