{
  "type": "Feature",
  "properties": {
    "gn:country":"YE",
    "gn:fcode":"PPL",
    "gn:population":6,
    "iso:country":"YE",
    "name:ara_x_preferred":[
        "\u062e\u064a\u0629"
    ],
    "name:eng_x_preferred":[
        "Khiyah"
    ],
    "name:nno_x_preferred":[
        "An Najd"
    ],
    "qs:name":"Khiyah",
    "qs:photos_9r":0,
    "qs:photos_sr":0,
    "qs:pop_sr":"1",
    "wof:name":"Khiyah",
    "wof:placetype":"locality",
    "wof:population":6
},
  "geometry": {"coordinates":[44.16615,17.26223],"type":"Point"}
}