{
  "type": "Feature",
  "properties": {
    "gn:country":"YE",
    "gn:fcode":"PPL",
    "gn:population":18,
    "iso:country":"YE",
    "name:ara_x_preferred":[
        "\u0627\u0644\u0628\u0631\u062d\u0629"
    ],
    "name:eng_x_preferred":[
        "Al Barhah"
    ],
    "name:eng_x_variant":[
        "W\u0101si\u0163"
    ],
    "qs:name":"Al Bar\u1e29ah",
    "qs:photos_9r":0,
    "qs:photos_sr":0,
    "qs:pop_sr":"1",
    "wof:name":"Al Bar\u1e29ah",
    "wof:placetype":"locality",
    "wof:population":18
},
  "geometry": {"coordinates":[43.83231,13.12627],"type":"Point"}
}