{
  "type": "Feature",
  "properties": {
    "gn:admin1_code":"23.0",
    "gn:admin2_code":"1110.0",
    "gn:asciiname":"Qaryat Ghurabah",
    "gn:country_code":"YE",
    "gn:dem":908,
    "gn:feature_class":"P",
    "gn:feature_code":"PPL",
    "gn:name":"Qaryat Ghur\u0101bah",
    "gn:population":0,
    "gn:timezone":"Asia/Aden",
    "iso:country":"YE",
    "name:ara_x_preferred":[
        "\u063a\u0631\u0627\u0628\u0629"
    ],
    "name:und_x_variant":[
        "Qaryat Ghur\u0101bah",
        "Ghur\u0101bah"
    ],
    "wof:name":"Qaryat Ghurabah",
    "wof:placetype":"locality"
},
  "geometry": {"coordinates":[43.81717,13.99615],"type":"Point"}
}