{
  "type": "Feature",
  "properties": {
    "gn:admin1_code":"21.0",
    "gn:admin2_code":"1612.0",
    "gn:asciiname":"Al `Atf",
    "gn:country_code":"YE",
    "gn:dem":1373,
    "gn:feature_class":"P",
    "gn:feature_code":"PPL",
    "gn:name":"Al \u2018A\u0163f",
    "gn:population":0,
    "gn:timezone":"Asia/Aden",
    "iso:country":"YE",
    "name:ara_x_preferred":[
        "Al \u2018A\u0163f"
    ],
    "wof:name":"Al `Atf",
    "wof:placetype":"locality"
},
  "geometry": {"coordinates":[44.26807,16.54441],"type":"Point"}
}