{
  "type": "Feature",
  "properties": {
    "gn:admin1_code":"25.0",
    "gn:admin2_code":"1503.0",
    "gn:asciiname":"As Sidri",
    "gn:country_code":"YE",
    "gn:dem":1150,
    "gn:feature_class":"P",
    "gn:feature_code":"PPL",
    "gn:name":"As Sidr\u012b",
    "gn:population":0,
    "gn:timezone":"Asia/Aden",
    "iso:country":"YE",
    "name:ara_x_preferred":[
        "As Sidr\u012b"
    ],
    "name:ara_x_variant":[
        "\u0627\u0644\u0633\u062f\u0631\u064a"
    ],
    "wof:name":"As Sidri",
    "wof:placetype":"locality"
},
  "geometry": {"coordinates":[43.95677,13.68842],"type":"Point"}
}