{
  "type": "Feature",
  "properties": {
    "gn:country":"YE",
    "gn:fcode":"PPL",
    "gn:pop":1,
    "iso:country":"YE",
    "name:ara_x_preferred":[
        "Qurd\u016b\u2018"
    ],
    "name:ara_x_variant":[
        "\u0642\u0631\u062f\u0648\u0639"
    ],
    "name:eng_x_preferred":[
        "QurdU'"
    ],
    "name:eng_x_variant":[
        "Ib\u0101l"
    ],
    "qs:name":"Qurd\u016b\u2018",
    "qs:photos_9r":0,
    "qs:photos_sr":0,
    "qs:pop_sr":"1",
    "wof:name":"Qurd\u016b\u2018",
    "wof:placetype":"locality",
    "wof:population":1
},
  "geometry": {"coordinates":[43.73874,16.27866],"type":"Point"}
}