{
  "type": "Feature",
  "properties": {
    "gn:admin1_code":"8.0",
    "gn:admin2_code":"1810.0",
    "gn:asciiname":"Dayr ad Damh",
    "gn:country_code":"YE",
    "gn:dem":98,
    "gn:feature_class":"P",
    "gn:feature_code":"PPL",
    "gn:name":"Dayr ad Dam\u1e29",
    "gn:population":0,
    "gn:timezone":"Asia/Aden",
    "iso:country":"YE",
    "name:und_x_variant":[
        "Dayr ad Dam\u1e29"
    ],
    "wof:name":"Dayr ad Damh",
    "wof:placetype":"locality"
},
  "geometry": {"coordinates":[43.14286,14.95893],"type":"Point"}
}