{
  "type": "Feature",
  "properties": {
    "gn:admin1_code":"16.0",
    "gn:admin2_code":"2302.0",
    "gn:asciiname":"Bayt Hazib",
    "gn:country_code":"YE",
    "gn:dem":2276,
    "gn:feature_class":"P",
    "gn:feature_code":"PPL",
    "gn:name":"Bayt \u1e28\u0101zib",
    "gn:population":0,
    "gn:timezone":"Asia/Aden",
    "iso:country":"YE",
    "name:und_x_variant":[
        "Bayt \u1e28\u0101zib"
    ],
    "wof:name":"Bayt Hazib",
    "wof:placetype":"locality"
},
  "geometry": {"coordinates":[44.26937,15.71005],"type":"Point"}
}