{
  "type": "Feature",
  "properties": {
    "gn:admin1_code":"28.0",
    "gn:admin2_code":"1926.0",
    "gn:asciiname":"Sha'b",
    "gn:country_code":"YE",
    "gn:dem":261,
    "gn:feature_class":"P",
    "gn:feature_code":"PPL",
    "gn:name":"Sha\u2018b",
    "gn:population":0,
    "gn:timezone":"Asia/Aden",
    "iso:country":"YE",
    "wof:name":"Sha'b",
    "wof:placetype":"locality"
},
  "geometry": {"coordinates":[54.25781,12.50647],"type":"Point"}
}