{
  "type": "Feature",
  "properties": {
    "gn:admin1_code":"23.0",
    "gn:admin2_code":"1116.0",
    "gn:asciiname":"Luba' al Ashraf",
    "gn:country_code":"YE",
    "gn:dem":2236,
    "gn:feature_class":"P",
    "gn:feature_code":"PPL",
    "gn:name":"L\u016bb\u0101\u2019 al Ashr\u0101f",
    "gn:population":0,
    "gn:timezone":"Asia/Aden",
    "iso:country":"YE",
    "name:und_x_variant":[
        "L\u016bb\u0101\u2019 al Ashr\u0101f"
    ],
    "wof:name":"Luba' al Ashraf",
    "wof:placetype":"locality"
},
  "geometry": {"coordinates":[44.06911,13.82797],"type":"Point"}
}