{
  "type": "Feature",
  "properties": {
    "gn:admin1_code":"25.0",
    "gn:admin2_code":"1507.0",
    "gn:asciiname":"Ad Dawsh",
    "gn:country_code":"YE",
    "gn:dem":202,
    "gn:feature_class":"P",
    "gn:feature_code":"PPL",
    "gn:name":"Ad Dawsh",
    "gn:population":0,
    "gn:timezone":"Asia/Aden",
    "iso:country":"YE",
    "name:ara_x_preferred":[
        "\u0627\u0644\u062f\u0648\u0634"
    ],
    "wof:name":"Ad Dawsh",
    "wof:placetype":"locality"
},
  "geometry": {"coordinates":[43.52052,13.25308],"type":"Point"}
}