{
  "type": "Feature",
  "properties": {
    "gn:country":"YE",
    "gn:fcode":"PPL",
    "gn:pop":1,
    "iso:country":"YE",
    "name:ara_x_preferred":[
        "\u0627\u0644\u062f\u0645\u0646"
    ],
    "qs:name":"Ad Diman",
    "qs:photos_9r":0,
    "qs:photos_sr":0,
    "qs:pop_sr":"1",
    "wof:name":"Ad Diman",
    "wof:placetype":"locality",
    "wof:population":1
},
  "geometry": {"coordinates":[43.29818,16.63298],"type":"Point"}
}