{
  "type": "Feature",
  "properties": {
    "gn:country":"YE",
    "gn:fcode":"PPL",
    "gn:pop":14,
    "iso:country":"YE",
    "name:ara_x_preferred":[
        "\u0643\u062f\u0641 \u0627\u0644\u0634\u0639\u0628\u0629"
    ],
    "name:eng_x_preferred":[
        "Kadaf Ash Sha'bah"
    ],
    "name:eng_x_variant":[
        "Ban\u012b Ma\u015fla\u1e29"
    ],
    "name:unk_x_variant":[
        "Kadaf ash Sha\u2018bah"
    ],
    "qs:name":"Kadaf Ash Sha\u2018bah",
    "qs:photos_9r":0,
    "qs:photos_sr":0,
    "qs:pop_sr":"1",
    "wof:name":"Kadaf Ash Sha\u2018bah",
    "wof:placetype":"locality",
    "wof:population":14
},
  "geometry": {"coordinates":[43.01763,16.22816],"type":"Point"}
}