{
  "type": "Feature",
  "properties": {
    "gn:admin1_code":"23.0",
    "gn:admin2_code":"1102.0",
    "gn:asciiname":"Al `Uduf",
    "gn:country_code":"YE",
    "gn:dem":2086,
    "gn:feature_class":"P",
    "gn:feature_code":"PPL",
    "gn:name":"Al \u2018Ud\u016bf",
    "gn:population":0,
    "gn:timezone":"Asia/Aden",
    "iso:country":"YE",
    "name:ara_x_preferred":[
        "Al \u2018Ad\u016bf"
    ],
    "name:ara_x_variant":[
        "\u0627\u0644\u0639\u062f\u0648\u0641"
    ],
    "name:und_x_variant":[
        "Al \u2018Ud\u016bf"
    ],
    "wof:name":"Al `Uduf",
    "wof:placetype":"locality"
},
  "geometry": {"coordinates":[44.21325,14.3848],"type":"Point"}
}