{
  "type": "Feature",
  "properties": {
    "gn:admin1_code":"25.0",
    "gn:admin2_code":"1501.0",
    "gn:asciiname":"Al Kawlah",
    "gn:country_code":"YE",
    "gn:dem":1181,
    "gn:feature_class":"P",
    "gn:feature_code":"PPL",
    "gn:name":"Al Kawlah",
    "gn:population":0,
    "gn:timezone":"Asia/Aden",
    "iso:country":"YE",
    "name:und_x_variant":[
        "Al Kola"
    ],
    "wof:name":"Al Kawlah",
    "wof:placetype":"locality"
},
  "geometry": {"coordinates":[44.27307,13.61172],"type":"Point"}
}