{
  "type": "Feature",
  "properties": {
    "gn:admin1_code":"23.0",
    "gn:admin2_code":"1101.0",
    "gn:asciiname":"Al Hublah",
    "gn:country_code":"YE",
    "gn:dem":2055,
    "gn:feature_class":"P",
    "gn:feature_code":"PPL",
    "gn:name":"Al \u1e28ublah",
    "gn:population":0,
    "gn:timezone":"Asia/Aden",
    "iso:country":"YE",
    "name:ara_x_preferred":[
        "\u0627\u0644\u062d\u0628\u0644\u0629"
    ],
    "name:und_x_variant":[
        "Al \u1e28ablah",
        "Al \u1e28ublah"
    ],
    "wof:name":"Al Hublah",
    "wof:placetype":"locality"
},
  "geometry": {"coordinates":[44.22749,14.3023],"type":"Point"}
}