{
  "type": "Feature",
  "properties": {
    "gn:admin1_code":"14.0",
    "gn:admin2_code":"2610.0",
    "gn:asciiname":"Ibrahim",
    "gn:country_code":"YE",
    "gn:dem":2079,
    "gn:feature_class":"P",
    "gn:feature_code":"PPL",
    "gn:name":"Ibr\u0101h\u012bm",
    "gn:population":0,
    "gn:timezone":"Asia/Aden",
    "iso:country":"YE",
    "name:ara_x_preferred":[
        "Ibr\u0101h\u012bm"
    ],
    "name:ara_x_variant":[
        "\u0625\u0628\u0631\u0627\u0647\u064a\u0645"
    ],
    "wof:name":"Ibrahim",
    "wof:placetype":"locality"
},
  "geometry": {"coordinates":[45.29539000000001,14.5546],"type":"Point"}
}