{
  "type": "Feature",
  "properties": {
    "gn:admin1_code":"23.0",
    "gn:admin2_code":"1101.0",
    "gn:asciiname":"Az Zabidi",
    "gn:country_code":"YE",
    "gn:dem":1107,
    "gn:feature_class":"P",
    "gn:feature_code":"PPL",
    "gn:name":"Az Zab\u012bd\u012b",
    "gn:population":0,
    "gn:timezone":"Asia/Aden",
    "iso:country":"YE",
    "name:und_x_variant":[
        "Az Zab\u012bd\u012b"
    ],
    "wof:name":"Az Zabidi",
    "wof:placetype":"locality"
},
  "geometry": {"coordinates":[44.06352,14.22785],"type":"Point"}
}