{
  "type": "Feature",
  "properties": {
    "gn:gn_country":"YE",
    "gn:gn_fcode":"PPL",
    "gn:gn_pop":2,
    "gn:population":2,
    "iso:country":"YE",
    "name:ara_x_preferred":[
        "\u0638\u0627\u0647\u0631 \u0627\u0644\u0634\u0648\u0643"
    ],
    "name:eng_x_preferred":[
        "Zahir Ash Shawk"
    ],
    "qs_pg:aaroncc":"YE",
    "qs_pg:gn_country":"YE",
    "qs_pg:gn_fcode":"PPL",
    "qs_pg:gn_pop":2,
    "qs_pg:name":"Z\u0327\u0101hir ash Shawk",
    "qs_pg:photos_9r":0,
    "qs_pg:photos_sr":0,
    "qs_pg:pop_sr":1,
    "qs_pg:qs_pg_placetype":"locality",
    "wof:name":"Z\u0327\u0101hir ash Shawk",
    "wof:placetype":"locality",
    "wof:population":2
},
  "geometry": {"coordinates":[43.35377,16.67488],"type":"Point"}
}