{
  "type": "Feature",
  "properties": {
    "gn:admin1_code":"20.0",
    "gn:admin2_code":"1411.0",
    "gn:asciiname":"Rahban",
    "gn:country_code":"YE",
    "gn:dem":1987,
    "gn:feature_class":"P",
    "gn:feature_code":"PPL",
    "gn:name":"Rahb\u0101n",
    "gn:population":0,
    "gn:timezone":"Asia/Aden",
    "iso:country":"YE",
    "name:ara_x_preferred":[
        "\u0631\u0647\u0628\u0627\u0646"
    ],
    "name:und_x_variant":[
        "Rahb\u0101n"
    ],
    "wof:name":"Rahban",
    "wof:placetype":"locality"
},
  "geometry": {"coordinates":[45.27916,14.33462],"type":"Point"}
}