{
  "type": "Feature",
  "properties": {
    "gn:admin1_code":"24.0",
    "gn:admin2_code":"2515.0",
    "gn:asciiname":"Al Khudad",
    "gn:country_code":"YE",
    "gn:dem":203,
    "gn:feature_class":"P",
    "gn:feature_code":"PPL",
    "gn:name":"Al Khud\u0101d",
    "gn:population":0,
    "gn:timezone":"Asia/Aden",
    "iso:country":"YE",
    "name:ara_x_preferred":[
        "Al Khud\u0101d"
    ],
    "name:und_x_variant":[
        "Al Khadd\u0101d",
        "Al Khid\u0101d"
    ],
    "wof:name":"Al Khudad",
    "wof:placetype":"locality"
},
  "geometry": {"coordinates":[44.85139,13.11972],"type":"Point"}
}