{
  "type": "Feature",
  "properties": {
    "gn:admin1_code":"25.0",
    "gn:admin2_code":"1521.0",
    "gn:asciiname":"Al Har",
    "gn:country_code":"YE",
    "gn:dem":1542,
    "gn:feature_class":"P",
    "gn:feature_code":"PPL",
    "gn:name":"Al \u1e28\u0101r",
    "gn:population":0,
    "gn:timezone":"Asia/Aden",
    "iso:country":"YE",
    "name:ara_x_preferred":[
        "Al \u1e28\u0101r"
    ],
    "wof:name":"Al Har",
    "wof:placetype":"locality"
},
  "geometry": {"coordinates":[44.00904,13.42678],"type":"Point"}
}