{
  "type": "Feature",
  "properties": {
    "gn:admin1_code":"15.0",
    "gn:admin2_code":"2213.0",
    "gn:asciiname":"Al Jufrah",
    "gn:country_code":"YE",
    "gn:dem":1489,
    "gn:feature_class":"P",
    "gn:feature_code":"PPL",
    "gn:name":"Al Jufrah",
    "gn:population":0,
    "gn:timezone":"Asia/Aden",
    "iso:country":"YE",
    "wof:name":"Al Jufrah",
    "wof:placetype":"locality"
},
  "geometry": {"coordinates":[44.308,16.93994],"type":"Point"}
}