{
  "type": "Feature",
  "properties": {
    "gn:country":"YE",
    "gn:fcode":"PPL",
    "gn:population":1,
    "iso:country":"YE",
    "name:ara_x_preferred":[
        "\u0627\u0644\u0645\u0628\u0631\u0627\u062f\u0629"
    ],
    "name:eng_x_preferred":[
        "Al Mabradah"
    ],
    "name:eng_x_variant":[
        "Bi\u2019r al Qiz\u2018\u0101n"
    ],
    "qs_pg:aaroncc":"YE",
    "qs_pg:gn_country":"YE",
    "qs_pg:gn_fcode":"PPL",
    "qs_pg:gn_pop":1,
    "qs_pg:name":"Al Mabr\u0101dah",
    "qs_pg:photos_9r":0,
    "qs_pg:photos_sr":0,
    "qs_pg:pop_sr":1,
    "qs_pg:qs_pg_placetype":"locality",
    "wof:name":"Al Mabr\u0101dah",
    "wof:placetype":"locality",
    "wof:population":1
},
  "geometry": {"coordinates":[44.20132,17.3303],"type":"Point"}
}