{
  "type": "Feature",
  "properties": {
    "gn:country":"YE",
    "gn:fcode":"PPL",
    "gn:pop":9,
    "iso:country":"YE",
    "name:ara_x_preferred":[
        "\u0627\u0644\u0647\u064a\u0644\u0629"
    ],
    "name:eng_x_preferred":[
        "Al Haylah"
    ],
    "name:eng_x_variant":[
        "\u1e28i\u015fn"
    ],
    "qs:name":"Al Haylah",
    "qs:photos_9r":0,
    "qs:photos_sr":0,
    "qs:pop_sr":"1",
    "wd:wordcount":40,
    "wof:name":"Al Haylah",
    "wof:placetype":"locality",
    "wof:population":9
},
  "geometry": {"coordinates":[45.09694,14.96318],"type":"Point"}
}