{
  "type": "Feature",
  "properties": {
    "gn:country":"YE",
    "gn:fcode":"PPL",
    "gn:population":3,
    "iso:country":"YE",
    "name:ara_x_preferred":[
        "\u063a\u0627\u0631\u0628 \u0627\u0644\u0645\u0637\u0631\u0632\u064a \u0627\u0644\u0641\u064a\u0644"
    ],
    "name:eng_x_preferred":[
        "Gharib Al Matrizi Al Fil"
    ],
    "qs:name":"Gh\u0101rib al Ma\u0163riz\u012b al F\u012bl",
    "qs:photos_9r":0,
    "qs:photos_sr":0,
    "qs:pop_sr":"1",
    "wof:name":"Gh\u0101rib al Ma\u0163riz\u012b al F\u012bl",
    "wof:placetype":"locality",
    "wof:population":3
},
  "geometry": {"coordinates":[43.45139,16.18997],"type":"Point"}
}