{
  "type": "Feature",
  "properties": {
    "gn:admin1_code":"23.0",
    "gn:admin2_code":"1119.0",
    "gn:asciiname":"Mu`ayin al Ghaythi",
    "gn:country_code":"YE",
    "gn:dem":1947,
    "gn:feature_class":"P",
    "gn:feature_code":"PPL",
    "gn:name":"Mu\u2018\u0101yin al Ghayth\u012b",
    "gn:population":0,
    "gn:timezone":"Asia/Aden",
    "iso:country":"YE",
    "name:und_x_variant":[
        "Mu\u2018\u0101yin al Ghayth\u012b"
    ],
    "wof:name":"Mu`ayin al Ghaythi",
    "wof:placetype":"locality"
},
  "geometry": {"coordinates":[44.1611,13.97978],"type":"Point"}
}