{
  "type": "Feature",
  "properties": {
    "gn:admin1_code":"16.0",
    "gn:admin2_code":"2306.0",
    "gn:asciiname":"Sa`dan",
    "gn:country_code":"YE",
    "gn:dem":2638,
    "gn:feature_class":"P",
    "gn:feature_code":"PPL",
    "gn:name":"Sa\u2018d\u0101n",
    "gn:population":0,
    "gn:timezone":"Asia/Aden",
    "iso:country":"YE",
    "name:und_x_variant":[
        "Sa\u2018d\u0101n"
    ],
    "wof:name":"Sa`dan",
    "wof:placetype":"locality"
},
  "geometry": {"coordinates":[44.31998,15.05011],"type":"Point"}
}