{
  "type": "Feature",
  "properties": {
    "gn:admin1_code":"22.0",
    "gn:admin2_code":"1730.0",
    "gn:asciiname":"Al 'Usaydah",
    "gn:country_code":"YE",
    "gn:dem":556,
    "gn:feature_class":"P",
    "gn:feature_code":"PPL",
    "gn:name":"Al \u2018U\u015faydah",
    "gn:population":0,
    "gn:timezone":"Asia/Aden",
    "iso:country":"YE",
    "name:ara_x_preferred":[
        "\u0627\u0644\u0639\u0635\u064a\u062f\u0629"
    ],
    "name:und_x_variant":[
        "Al \u2018U\u015faydah"
    ],
    "wof:name":"Al 'Usaydah",
    "wof:placetype":"locality"
},
  "geometry": {"coordinates":[43.39161,16.23537],"type":"Point"}
}