{
  "type": "Feature",
  "properties": {
    "gn:admin1_code":"11.0",
    "gn:admin2_code":"2007.0",
    "gn:asciiname":"Al Quhaf",
    "gn:country_code":"YE",
    "gn:dem":936,
    "gn:feature_class":"P",
    "gn:feature_code":"PPL",
    "gn:name":"Al Qu\u1e29\u0101f",
    "gn:population":0,
    "gn:timezone":"Asia/Aden",
    "iso:country":"YE",
    "name:ara_x_preferred":[
        "Al Qu\u1e29\u0101f"
    ],
    "wof:name":"Al Quhaf",
    "wof:placetype":"locality"
},
  "geometry": {"coordinates":[43.68956,14.24602],"type":"Point"}
}