{
  "type": "Feature",
  "properties": {
    "gn:admin1_code":"27.0",
    "gn:admin2_code":"3103.0",
    "gn:asciiname":"Majrad",
    "gn:country_code":"YE",
    "gn:dem":2250,
    "gn:feature_class":"P",
    "gn:feature_code":"PPL",
    "gn:name":"Majrad",
    "gn:population":0,
    "gn:timezone":"Asia/Aden",
    "iso:country":"YE",
    "wof:name":"Majrad",
    "wof:placetype":"locality"
},
  "geometry": {"coordinates":[43.76873,14.70647],"type":"Point"}
}