{
  "type": "Feature",
  "properties": {
    "gn:admin1_code":"14.0",
    "gn:admin2_code":"2602.0",
    "gn:asciiname":"Mahall Shi`fan",
    "gn:country_code":"YE",
    "gn:dem":1101,
    "gn:feature_class":"P",
    "gn:feature_code":"PPL",
    "gn:name":"Ma\u1e29all Shi\u2018f\u0101n",
    "gn:population":0,
    "gn:timezone":"Asia/Aden",
    "iso:country":"YE",
    "name:und_x_variant":[
        "Ma\u1e29all Shi\u2018f\u0101n"
    ],
    "wof:name":"Mahall Shi`fan",
    "wof:placetype":"locality"
},
  "geometry": {"coordinates":[45.06317,15.7671],"type":"Point"}
}