{
  "type": "Feature",
  "properties": {
    "gn:country":"YE",
    "gn:fcode":"PPL",
    "gn:population":4,
    "iso:country":"YE",
    "name:ara_x_preferred":[
        "\u0627\u0644\u0642\u0631\u064a\u0639"
    ],
    "name:eng_x_preferred":[
        "Al Quray'"
    ],
    "name:eng_x_variant":[
        "Al Jihda\u2018ah"
    ],
    "qs:name":"Al Quray\u2018",
    "qs:photos_9r":0,
    "qs:photos_sr":0,
    "qs:pop_sr":"1",
    "wof:name":"Al Quray\u2018",
    "wof:placetype":"locality",
    "wof:population":4
},
  "geometry": {"coordinates":[45.11022,14.20884],"type":"Point"}
}