{
  "type": "Feature",
  "properties": {
    "gn:admin1_code":"19.0",
    "gn:admin2_code":"2901.0",
    "gn:asciiname":"Dhu Saydah",
    "gn:country_code":"YE",
    "gn:dem":1664,
    "gn:feature_class":"P",
    "gn:feature_code":"PPL",
    "gn:name":"Dh\u016b Saydah",
    "gn:population":0,
    "gn:timezone":"Asia/Aden",
    "iso:country":"YE",
    "name:und_x_variant":[
        "Dh\u016b Saydah"
    ],
    "wof:name":"Dhu Saydah",
    "wof:placetype":"locality"
},
  "geometry": {"coordinates":[44.05101,16.50119],"type":"Point"}
}