{
  "type": "Feature",
  "properties": {
    "gn:country":"YE",
    "gn:fcode":"PPL",
    "gn:population":2,
    "iso:country":"YE",
    "name:ara_x_preferred":[
        "\u0632\u0647\u0631\u0627\u062a"
    ],
    "name:eng_x_preferred":[
        "Zahrat"
    ],
    "name:eng_x_variant":[
        "W\u0101d\u012b Liyah"
    ],
    "qs:name":"Zahr\u0101t",
    "qs:photos_9r":0,
    "qs:photos_sr":0,
    "qs:pop_sr":"1",
    "wof:name":"Zahr\u0101t",
    "wof:placetype":"locality",
    "wof:population":2
},
  "geometry": {"coordinates":[43.61033,16.11908],"type":"Point"}
}