{
  "type": "Feature",
  "properties": {
    "gn:country":"YE",
    "gn:fcode":"PPL",
    "gn:pop":2,
    "iso:country":"YE",
    "name:ara_x_preferred":[
        "\u0627\u0644\u0645\u062d\u0645\u064a \u0627\u0644\u0623\u0633\u0641\u0644"
    ],
    "name:eng_x_preferred":[
        "Al Muhami Al Asfal"
    ],
    "name:eng_x_variant":[
        "Jib\u016bb Bin \u1e28ash\u1e29ash"
    ],
    "qs:name":"Al Mu\u1e29am\u012b al Asfal",
    "qs:photos_9r":0,
    "qs:photos_sr":0,
    "qs:pop_sr":"1",
    "wof:name":"Al Mu\u1e29am\u012b al Asfal",
    "wof:placetype":"locality",
    "wof:population":2
},
  "geometry": {"coordinates":[43.39597,16.0537],"type":"Point"}
}