{
  "type": "Feature",
  "properties": {
    "gn:admin1_code":"8.0",
    "gn:admin2_code":"1813.0",
    "gn:asciiname":"Al Maqsu'",
    "gn:country_code":"YE",
    "gn:dem":284,
    "gn:feature_class":"P",
    "gn:feature_code":"PPL",
    "gn:name":"Al Maq\u015f\u016b\u2018",
    "gn:population":0,
    "gn:timezone":"Asia/Aden",
    "iso:country":"YE",
    "name:ara_x_preferred":[
        "\u0627\u0644\u0645\u0642\u0635\u0648\u0639"
    ],
    "name:und_x_variant":[
        "Al Maq\u015f\u016b\u2018"
    ],
    "wof:name":"Al Maqsu'",
    "wof:placetype":"locality"
},
  "geometry": {"coordinates":[43.39956,14.95298],"type":"Point"}
}