{
  "type": "Feature",
  "properties": {
    "gn:admin1_code":"14.0",
    "gn:admin2_code":"2609.0",
    "gn:asciiname":"As Sawar",
    "gn:country_code":"YE",
    "gn:dem":1951,
    "gn:feature_class":"P",
    "gn:feature_code":"PPL",
    "gn:name":"As Saw\u0101r",
    "gn:population":8,
    "gn:timezone":"Asia/Aden",
    "iso:country":"YE",
    "name:ara_x_preferred":[
        "\u0627\u0644\u0633\u0648\u0627\u0631"
    ],
    "name:und_x_variant":[
        "As Saw\u0101r"
    ],
    "wof:name":"As Sawar",
    "wof:placetype":"locality",
    "wof:population":8
},
  "geometry": {"coordinates":[45.21775,14.88941],"type":"Point"}
}