{
  "type": "Feature",
  "properties": {
    "gn:admin1_code":"16.0",
    "gn:admin2_code":"2316.0",
    "gn:asciiname":"At Tu`aymah",
    "gn:country_code":"YE",
    "gn:dem":2260,
    "gn:feature_class":"P",
    "gn:feature_code":"PPL",
    "gn:name":"At Tu\u2018aymah",
    "gn:population":0,
    "gn:timezone":"Asia/Aden",
    "iso:country":"YE",
    "name:und_x_variant":[
        "At Tu\u2018aymah"
    ],
    "wof:name":"At Tu`aymah",
    "wof:placetype":"locality"
},
  "geometry": {"coordinates":[44.48816,15.15282],"type":"Point"}
}