{
  "type": "Feature",
  "properties": {
    "gn:admin1_code":"22.0",
    "gn:admin2_code":"1731.0",
    "gn:asciiname":"Al Kawlah",
    "gn:country_code":"YE",
    "gn:dem":1714,
    "gn:feature_class":"P",
    "gn:feature_code":"PPL",
    "gn:name":"Al Kawlah",
    "gn:population":0,
    "gn:timezone":"Asia/Aden",
    "iso:country":"YE",
    "name:ara_x_preferred":[
        "\u0627\u0644\u0643\u0648\u0644\u0629"
    ],
    "wof:name":"Al Kawlah",
    "wof:placetype":"locality"
},
  "geometry": {"coordinates":[43.47121,16.34423],"type":"Point"}
}