{
  "type": "Feature",
  "properties": {
    "gn:country":"YE",
    "gn:fcode":"PPL",
    "gn:pop":8,
    "iso:country":"YE",
    "name:ara_x_preferred":[
        "\u0645\u0642\u0627\u062d\u0644\u0629"
    ],
    "name:eng_x_preferred":[
        "Maqahilah"
    ],
    "name:eng_x_variant":[
        "Al \u2018Uwayrah"
    ],
    "qs:name":"Maq\u0101\u1e29ilah",
    "qs:photos_9r":0,
    "qs:photos_sr":0,
    "qs:pop_sr":"1",
    "wof:name":"Maq\u0101\u1e29ilah",
    "wof:placetype":"locality",
    "wof:population":8
},
  "geometry": {"coordinates":[43.2831,16.34828],"type":"Point"}
}