{
  "type": "Feature",
  "properties": {
    "gn:country":"YE",
    "gn:fcode":"PPL",
    "gn:population":4,
    "iso:country":"YE",
    "name:ara_x_preferred":[
        "\u0648\u0627\u062f\u064a \u0628\u0646\u064a \u0639\u064a\u0640\u0634"
    ],
    "name:ara_x_variant":[
        "\u0648\u0627\u062f\u064a \u0628\u0646\u064a \u0639\u064a\u0634"
    ],
    "name:eng_x_preferred":[
        "Wadi Bani 'Aysh"
    ],
    "name:eng_x_variant":[
        "Ad Dafinah"
    ],
    "qs:name":"W\u0101d\u012b Ban\u012b \u2018Aysh",
    "qs:photos_9r":0,
    "qs:photos_sr":0,
    "qs:pop_sr":"1",
    "wof:name":"W\u0101d\u012b Ban\u012b \u2018Aysh",
    "wof:placetype":"locality",
    "wof:population":4
},
  "geometry": {"coordinates":[43.4675,16.16506],"type":"Point"}
}