{
  "type": "Feature",
  "properties": {
    "gn:admin1_code":"23.0",
    "gn:admin2_code":"1102.0",
    "gn:asciiname":"Mughni",
    "gn:country_code":"YE",
    "gn:dem":2620,
    "gn:feature_class":"P",
    "gn:feature_code":"PPL",
    "gn:name":"Mughn\u012b",
    "gn:population":0,
    "gn:timezone":"Asia/Aden",
    "iso:country":"YE",
    "name:ara_x_preferred":[
        "Mughn\u012b"
    ],
    "wof:name":"Mughni",
    "wof:placetype":"locality"
},
  "geometry": {"coordinates":[44.42874000000001,14.25946],"type":"Point"}
}