{
  "type": "Feature",
  "properties": {
    "gn:admin1_code":"23.0",
    "gn:admin2_code":"1102.0",
    "gn:asciiname":"Mughni",
    "gn:country_code":"YE",
    "gn:dem":2620,
    "gn:feature_class":"P",
    "gn:feature_code":"PPL",
    "gn:name":"Mughn\u012b",
    "gn:population":0,
    "gn:timezone":"Asia/Aden",
    "iso:country":"YE",
    "name:ara_x_preferred":[
        "Mughn\u012b"
    ],
    "name:ceb_x_preferred":[
        "Mughni"
    ],
    "name:deu_x_preferred":[
        "Mughni"
    ],
    "name:fas_x_preferred":[
        "\u0645\u0648\u063a\u0646\u06cc"
    ],
    "name:hye_x_preferred":[
        "\u0544\u0578\u0582\u0572\u0576\u056b"
    ],
    "name:kat_x_preferred":[
        "\u10db\u10e3\u10e6\u10dc\u10d8"
    ],
    "name:por_x_preferred":[
        "Mughni"
    ],
    "name:rus_x_preferred":[
        "\u041c\u0443\u0433\u043d\u0438"
    ],
    "name:spa_x_preferred":[
        "Mughni"
    ],
    "name:swe_x_preferred":[
        "Mughni"
    ],
    "name:ukr_x_preferred":[
        "\u041c\u0443\u0433\u043d\u0456"
    ],
    "wof:name":"Mughni",
    "wof:placetype":"locality"
},
  "geometry": {"coordinates":[44.42874000000001,14.25946],"type":"Point"}
}