{
  "type": "Feature",
  "properties": {
    "gn:admin1_code":"20.0",
    "gn:admin2_code":"1410.0",
    "gn:asciiname":"Himim",
    "gn:country_code":"YE",
    "gn:dem":2025,
    "gn:feature_class":"P",
    "gn:feature_code":"PPL",
    "gn:name":"\u1e28imim",
    "gn:population":0,
    "gn:timezone":"Asia/Aden",
    "iso:country":"YE",
    "name:ara_x_preferred":[
        "\u1e28imim"
    ],
    "wof:name":"Himim",
    "wof:placetype":"locality"
},
  "geometry": {"coordinates":[45.61042,14.05111],"type":"Point"}
}