{
  "type": "Feature",
  "properties": {
    "gn:country":"YE",
    "gn:fcode":"LCTY",
    "gn:pop":62,
    "iso:country":"YE",
    "name:ara_x_preferred":[
        "\u0627\u0644\u0628\u0631\u064a\u062f"
    ],
    "name:ara_x_variant":[
        "\u0627\u0644\u0628\u0627\u0631\u062f"
    ],
    "name:fas_x_preferred":[
        "\u0627\u0644\u0628\u0627\u0631\u062f"
    ],
    "name:pol_x_preferred":[
        "Al-Barid"
    ],
    "name:vie_x_preferred":[
        "Al-Barid"
    ],
    "qs:name":"Al Bar\u012bd",
    "qs:photos_9r":0,
    "qs:photos_sr":0,
    "qs:pop_sr":"1",
    "wd:wordcount":76,
    "wof:name":"Al Bar\u012bd",
    "wof:placetype":"locality",
    "wof:population":62
},
  "geometry": {"coordinates":[43.58393,16.18742],"type":"Point"}
}