{
  "type": "Feature",
  "properties": {
    "gn:admin1_code":"16.0",
    "gn:admin2_code":"2310.0",
    "gn:asciiname":"Ad Dahrah",
    "gn:country_code":"YE",
    "gn:dem":1843,
    "gn:feature_class":"P",
    "gn:feature_code":"PPL",
    "gn:name":"A\u1e11 \u1e10ahrah",
    "gn:population":0,
    "gn:timezone":"Asia/Aden",
    "iso:country":"YE",
    "name:fas_x_preferred":[
        "\u0627\u0644\u062f\u0647\u0631\u0647"
    ],
    "name:nno_x_preferred":[
        "Ad Dahrah"
    ],
    "name:und_x_variant":[
        "\u2018Att\u0101rah",
        "Al \u2018At\u0101rah",
        "Attara",
        "Al \u2018Att\u0101rah",
        "A\u1e11 \u1e10ahrah"
    ],
    "wof:name":"Ad Dahrah",
    "wof:placetype":"locality"
},
  "geometry": {"coordinates":[43.68929,15.05352],"type":"Point"}
}