{
  "type": "Feature",
  "properties": {
    "gn:admin1_code":"8.0",
    "gn:admin2_code":"1807.0",
    "gn:asciiname":"Ash Sharaf",
    "gn:country_code":"YE",
    "gn:dem":108,
    "gn:feature_class":"P",
    "gn:feature_code":"PPL",
    "gn:name":"Ash Sharaf",
    "gn:population":0,
    "gn:timezone":"Asia/Aden",
    "iso:country":"YE",
    "name:und_x_variant":[
        "Esh Sheraf",
        "Ash Sharaf"
    ],
    "wof:name":"Ash Sharaf",
    "wof:placetype":"locality"
},
  "geometry": {"coordinates":[43.18516,15.39879],"type":"Point"}
}