{
  "type": "Feature",
  "properties": {
    "gn:admin1_code":"11.0",
    "gn:admin2_code":"2001.0",
    "gn:asciiname":"As Sarm",
    "gn:country_code":"YE",
    "gn:dem":2476,
    "gn:feature_class":"P",
    "gn:feature_code":"PPL",
    "gn:name":"A\u015f \u015earm",
    "gn:population":0,
    "gn:timezone":"Asia/Aden",
    "iso:country":"YE",
    "name:ara_x_preferred":[
        "A\u015f \u015eurm"
    ],
    "name:ara_x_variant":[
        "\u0627\u0644\u0635\u0631\u0645"
    ],
    "name:und_x_variant":[
        "A\u015f \u015earm"
    ],
    "wof:name":"As Sarm",
    "wof:placetype":"locality"
},
  "geometry": {"coordinates":[44.54727000000001,14.64829],"type":"Point"}
}