{
  "type": "Feature",
  "properties": {
    "gn:country":"YE",
    "gn:fcode":"PPL",
    "gn:pop":8,
    "iso:country":"YE",
    "name:ara_x_preferred":[
        "\u0634\u0639\u0628 \u064a\u062d\u064a\u0649"
    ],
    "name:eng_x_preferred":[
        "Sha'b Yahya"
    ],
    "qs:name":"Sha\u2018b Ya\u1e29y\u00e1",
    "qs:photos_9r":0,
    "qs:photos_sr":0,
    "qs:pop_sr":"1",
    "wof:name":"Sha\u2018b Ya\u1e29y\u00e1",
    "wof:placetype":"locality",
    "wof:population":8
},
  "geometry": {"coordinates":[43.43146,16.05865],"type":"Point"}
}