{
  "type": "Feature",
  "properties": {
    "gn:admin1_code":"19.0",
    "gn:admin2_code":"2904.0",
    "gn:asciiname":"Dhu Sa'ninah",
    "gn:country_code":"YE",
    "gn:dem":1177,
    "gn:feature_class":"P",
    "gn:feature_code":"PPL",
    "gn:name":"Dh\u016b Sa\u2018ninah",
    "gn:population":0,
    "gn:timezone":"Asia/Aden",
    "iso:country":"YE",
    "name:ara_x_preferred":[
        "\u0630\u0648 \u0633\u0639\u0646\u0646\u0629"
    ],
    "name:und_x_variant":[
        "Dh\u016b Sa\u2018ninah"
    ],
    "wof:name":"Dhu Sa'ninah",
    "wof:placetype":"locality"
},
  "geometry": {"coordinates":[43.76523,16.17605],"type":"Point"}
}