{
  "type": "Feature",
  "properties": {
    "gn:admin1_code":"14.0",
    "gn:admin2_code":"2609.0",
    "gn:asciiname":"Jalb Sa`id",
    "gn:country_code":"YE",
    "gn:dem":1145,
    "gn:feature_class":"P",
    "gn:feature_code":"PPL",
    "gn:name":"Jalb Sa\u2018\u012bd",
    "gn:population":0,
    "gn:timezone":"Asia/Aden",
    "iso:country":"YE",
    "name:und_x_variant":[
        "Jalb Sa\u2018\u012bd"
    ],
    "wof:name":"Jalb Sa`id",
    "wof:placetype":"locality"
},
  "geometry": {"coordinates":[45.52292,14.97257],"type":"Point"}
}