{
  "type": "Feature",
  "properties": {
    "gn:admin1_code":"22.0",
    "gn:admin2_code":"1718.0",
    "gn:asciiname":"Bani at Turubi",
    "gn:country_code":"YE",
    "gn:dem":1456,
    "gn:feature_class":"P",
    "gn:feature_code":"PPL",
    "gn:name":"Ban\u012b a\u0163 \u0162urub\u012b",
    "gn:population":0,
    "gn:timezone":"Asia/Aden",
    "iso:country":"YE",
    "name:und_x_variant":[
        "Ban\u012b a\u0163 \u0162urub\u012b"
    ],
    "wof:name":"Bani at Turubi",
    "wof:placetype":"locality"
},
  "geometry": {"coordinates":[43.69843,15.66197],"type":"Point"}
}