{
  "type": "Feature",
  "properties": {
    "gn:admin1_code":"19.0",
    "gn:admin2_code":"2906.0",
    "gn:asciiname":"Ad Da'ir",
    "gn:country_code":"YE",
    "gn:dem":1439,
    "gn:feature_class":"P",
    "gn:feature_code":"PPL",
    "gn:name":"Ad D\u0101\u2019ir",
    "gn:population":0,
    "gn:timezone":"Asia/Aden",
    "iso:country":"YE",
    "name:ara_x_preferred":[
        "Ad D\u0101\u2019ir"
    ],
    "name:fas_x_preferred":[
        "\u0627\u0644\u062f\u0627\u06cc\u0631"
    ],
    "name:nno_x_preferred":[
        "Ad Da'ir"
    ],
    "wof:name":"Ad Da'ir",
    "wof:placetype":"locality"
},
  "geometry": {"coordinates":[43.64657,16.25067],"type":"Point"}
}