{
  "type": "Feature",
  "properties": {
    "gn:country":"YE",
    "gn:fcode":"PPL",
    "gn:pop":15,
    "iso:country":"YE",
    "name:ara_x_preferred":[
        "\u063a\u0627\u0631\u0628 \u0627\u0644\u0645\u062c\u0631\u0627\u0628"
    ],
    "name:eng_x_preferred":[
        "Gharib Al Mijrab"
    ],
    "qs:name":"Gh\u0101rib al Mijr\u0101b",
    "qs:photos_9r":0,
    "qs:photos_sr":0,
    "qs:pop_sr":"1",
    "wof:name":"Gh\u0101rib al Mijr\u0101b",
    "wof:placetype":"locality",
    "wof:population":15
},
  "geometry": {"coordinates":[43.3588,16.16231],"type":"Point"}
}