{
  "type": "Feature",
  "properties": {
    "gn:admin1_code":"23.0",
    "gn:admin2_code":"1112.0",
    "gn:asciiname":"Al `Aqa'ir",
    "gn:country_code":"YE",
    "gn:dem":2350,
    "gn:feature_class":"P",
    "gn:feature_code":"PPL",
    "gn:name":"Al \u2018Aq\u0101\u2019ir",
    "gn:population":0,
    "gn:timezone":"Asia/Aden",
    "iso:country":"YE",
    "name:ara_x_preferred":[
        "Al \u2018Aq\u0101\u2019ir"
    ],
    "wof:name":"Al `Aqa'ir",
    "wof:placetype":"locality"
},
  "geometry": {"coordinates":[44.11656,13.95063],"type":"Point"}
}