{
  "type": "Feature",
  "properties": {
    "gn:admin1_code":"19.0",
    "gn:admin2_code":"2904.0",
    "gn:asciiname":"Al Mu`ayrijah",
    "gn:country_code":"YE",
    "gn:dem":1228,
    "gn:feature_class":"P",
    "gn:feature_code":"PPL",
    "gn:name":"Al Mu\u2018ayrijah",
    "gn:population":0,
    "gn:timezone":"Asia/Aden",
    "iso:country":"YE",
    "name:und_x_variant":[
        "Al Mu\u2018ayrijah"
    ],
    "wof:name":"Al Mu`ayrijah",
    "wof:placetype":"locality"
},
  "geometry": {"coordinates":[43.81249,16.2558],"type":"Point"}
}