{
  "type": "Feature",
  "properties": {
    "gn:admin1_code":"8.0",
    "gn:admin2_code":"1813.0",
    "gn:asciiname":"Dayr al Mudawwar",
    "gn:country_code":"YE",
    "gn:dem":138,
    "gn:feature_class":"P",
    "gn:feature_code":"PPL",
    "gn:name":"Dayr al Mudawwar",
    "gn:population":0,
    "gn:timezone":"Asia/Aden",
    "iso:country":"YE",
    "wof:name":"Dayr al Mudawwar",
    "wof:placetype":"locality"
},
  "geometry": {"coordinates":[43.23611,14.96944],"type":"Point"}
}