{
  "type": "Feature",
  "properties": {
    "gn:admin1_code":"19.0",
    "gn:admin2_code":"2903.0",
    "gn:asciiname":"Shaw'an",
    "gn:country_code":"YE",
    "gn:dem":1419,
    "gn:feature_class":"P",
    "gn:feature_code":"PPL",
    "gn:name":"Shaw\u2018\u0101n",
    "gn:population":0,
    "gn:timezone":"Asia/Aden",
    "iso:country":"YE",
    "name:ara_x_preferred":[
        "\u0634\u0648\u0639\u0627\u0646"
    ],
    "name:und_x_variant":[
        "Shaw\u2018\u0101n"
    ],
    "wof:name":"Shaw'an",
    "wof:placetype":"locality"
},
  "geometry": {"coordinates":[43.85751,16.33589],"type":"Point"}
}