{
  "type": "Feature",
  "properties": {
    "gn:country":"YE",
    "gn:fcode":"PPL",
    "gn:population":6,
    "iso:country":"YE",
    "name:ara_x_preferred":[
        "\u0627\u0644\u0648\u0639\u0631"
    ],
    "name:eng_x_preferred":[
        "Al Wa'r"
    ],
    "name:eng_x_variant":[
        "Buy\u016bt al W\u0101d\u012b"
    ],
    "qs:name":"Al Wa\u2018r",
    "qs:photos_9r":0,
    "qs:photos_sr":0,
    "qs:pop_sr":"1",
    "wof:name":"Al Wa\u2018r",
    "wof:placetype":"locality",
    "wof:population":6
},
  "geometry": {"coordinates":[43.22391,17.15281],"type":"Point"}
}