{
  "type": "Feature",
  "properties": {
    "gn:country":"YE",
    "gn:fcode":"PPL",
    "gn:population":20,
    "iso:country":"YE",
    "name:ara_x_preferred":[
        "\u0622\u0644 \u0642\u0637\u0627\u0645"
    ],
    "name:eng_x_preferred":[
        "Al Qatam"
    ],
    "name:eng_x_variant":[
        "Al Jufaynah"
    ],
    "qs:name":"\u0100l Qa\u0163\u0101m",
    "qs:photos_9r":0,
    "qs:photos_sr":0,
    "qs:pop_sr":"1",
    "wof:name":"\u0100l Qa\u0163\u0101m",
    "wof:placetype":"locality",
    "wof:population":20
},
  "geometry": {"coordinates":[44.17213,16.91863],"type":"Point"}
}