{
  "type": "Feature",
  "properties": {
    "gn:admin1_code":"4.0",
    "gn:admin2_code":"1910.0",
    "gn:asciiname":"Al Marabid",
    "gn:country_code":"YE",
    "gn:dem":643,
    "gn:feature_class":"P",
    "gn:feature_code":"PPL",
    "gn:name":"Al Mar\u0101bid",
    "gn:population":0,
    "gn:timezone":"Asia/Aden",
    "iso:country":"YE",
    "name:und_x_variant":[
        "Al Mar\u0101bid"
    ],
    "wof:name":"Al Marabid",
    "wof:placetype":"locality"
},
  "geometry": {"coordinates":[48.88333,16.03333],"type":"Point"}
}