{
  "type": "Feature",
  "properties": {
    "gn:admin1_code":"22.0",
    "gn:admin2_code":"1725.0",
    "gn:asciiname":"Al Hamra'",
    "gn:country_code":"YE",
    "gn:dem":869,
    "gn:feature_class":"P",
    "gn:feature_code":"PPL",
    "gn:name":"Al \u1e28amr\u0101\u2019",
    "gn:population":0,
    "gn:timezone":"Asia/Aden",
    "iso:country":"YE",
    "name:ara_x_preferred":[
        "\u0627\u0644\u062d\u0645\u0631\u0627\u0621"
    ],
    "name:und_x_variant":[
        "Al \u1e28amr\u0101\u2019"
    ],
    "wof:name":"Al Hamra'",
    "wof:placetype":"locality"
},
  "geometry": {"coordinates":[43.50746,15.58064],"type":"Point"}
}