{
  "type": "Feature",
  "properties": {
    "gn:admin1_code":"23.0",
    "gn:admin2_code":"1115.0",
    "gn:asciiname":"Diras as Sufla",
    "gn:country_code":"YE",
    "gn:dem":1886,
    "gn:feature_class":"P",
    "gn:feature_code":"PPL",
    "gn:name":"\u1e10ir\u0101\u015f as Sufl\u00e1",
    "gn:population":0,
    "gn:timezone":"Asia/Aden",
    "iso:country":"YE",
    "name:und_x_variant":[
        "\u1e10ir\u0101\u015f as Sufl\u00e1"
    ],
    "wof:name":"Diras as Sufla",
    "wof:placetype":"locality"
},
  "geometry": {"coordinates":[44.15295,13.83452],"type":"Point"}
}