{
  "type": "Feature",
  "properties": {
    "gn:admin1_code":"23.0",
    "gn:admin2_code":"1117.0",
    "gn:asciiname":"Ash Shakhs",
    "gn:country_code":"YE",
    "gn:dem":2077,
    "gn:feature_class":"P",
    "gn:feature_code":"PPL",
    "gn:name":"Ash Shakh\u015f",
    "gn:population":0,
    "gn:timezone":"Asia/Aden",
    "iso:country":"YE",
    "name:und_x_variant":[
        "Ash Shakh\u015f"
    ],
    "wof:name":"Ash Shakhs",
    "wof:placetype":"locality"
},
  "geometry": {"coordinates":[43.94115,13.83372],"type":"Point"}
}