{
  "type": "Feature",
  "properties": {
    "gn:admin1_code":"16.0",
    "gn:admin2_code":"2308.0",
    "gn:asciiname":"Al `Urr",
    "gn:country_code":"YE",
    "gn:dem":2019,
    "gn:feature_class":"P",
    "gn:feature_code":"PPLA2",
    "gn:name":"Al \u2018Urr",
    "gn:population":0,
    "gn:timezone":"Asia/Aden",
    "iso:country":"YE",
    "name:ara_x_preferred":[
        "Al \u2018Urr"
    ],
    "name:ara_x_variant":[
        "\u0627\u0644\u0639\u0631"
    ],
    "name:fas_x_preferred":[
        "\u0627\u0644\u06cc\u0648\u0631"
    ],
    "name:nno_x_preferred":[
        "Al `Urr"
    ],
    "wof:name":"Al `Urr",
    "wof:placetype":"locality"
},
  "geometry": {"coordinates":[43.88836,15.24648],"type":"Point"}
}