{
  "type": "Feature",
  "properties": {
    "gn:country":"YE",
    "gn:fcode":"PPL",
    "gn:pop":5,
    "iso:country":"YE",
    "name:ara_x_preferred":[
        "Al Mu\u015fl\u00e1"
    ],
    "name:ara_x_variant":[
        "\u0627\u0644\u0645\u0635\u0644\u0649"
    ],
    "qs:name":"Al Mu\u015fl\u00e1",
    "qs:photos_9r":0,
    "qs:photos_sr":0,
    "qs:pop_sr":"1",
    "wof:name":"Al Mu\u015fl\u00e1",
    "wof:placetype":"locality",
    "wof:population":5
},
  "geometry": {"coordinates":[43.72658,16.1011],"type":"Point"}
}