{
  "type": "Feature",
  "properties": {
    "gn:admin1_code":"19.0",
    "gn:admin2_code":"2901.0",
    "gn:asciiname":"Al Jawwah",
    "gn:country_code":"YE",
    "gn:dem":1688,
    "gn:feature_class":"P",
    "gn:feature_code":"PPL",
    "gn:name":"Al Jawwah",
    "gn:population":0,
    "gn:timezone":"Asia/Aden",
    "iso:country":"YE",
    "wof:name":"Al Jawwah",
    "wof:placetype":"locality"
},
  "geometry": {"coordinates":[44.03493,16.49736],"type":"Point"}
}