{
  "type": "Feature",
  "properties": {
    "gn:admin1_code":"11.0",
    "gn:admin2_code":"2007.0",
    "gn:asciiname":"`Arjud",
    "gn:country_code":"YE",
    "gn:dem":436,
    "gn:feature_class":"P",
    "gn:feature_code":"PPL",
    "gn:name":"\u2018Arj\u016bd",
    "gn:population":0,
    "gn:timezone":"Asia/Aden",
    "iso:country":"YE",
    "name:ara_x_preferred":[
        "\u2018Arj\u016bd"
    ],
    "name:und_x_variant":[
        "Arjub"
    ],
    "wof:name":"`Arjud",
    "wof:placetype":"locality"
},
  "geometry": {"coordinates":[43.53333,14.33333],"type":"Point"}
}