{
  "type": "Feature",
  "properties": {
    "gn:admin1_code":"23.0",
    "gn:admin2_code":"1105.0",
    "gn:asciiname":"`Adan al Mahaqirah",
    "gn:country_code":"YE",
    "gn:dem":2299,
    "gn:feature_class":"P",
    "gn:feature_code":"PPL",
    "gn:name":"\u2018Adan al Ma\u1e29\u0101qirah",
    "gn:population":0,
    "gn:timezone":"Asia/Aden",
    "iso:country":"YE",
    "name:ara_x_preferred":[
        "\u0639\u062f\u0646 \u0627\u0644\u0645\u062d\u0627\u0642\u0631\u0629"
    ],
    "name:und_x_variant":[
        "Al Ma\u1e29\u0101qirah",
        "\u2018Adan al Ma\u1e29\u0101qirah"
    ],
    "wof:name":"`Adan al Mahaqirah",
    "wof:placetype":"locality"
},
  "geometry": {"coordinates":[44.34381,14.00991],"type":"Point"}
}