{
  "type": "Feature",
  "properties": {
    "gn:admin1_code":"19.0",
    "gn:admin2_code":"2905.0",
    "gn:asciiname":"Sawar",
    "gn:country_code":"YE",
    "gn:dem":1345,
    "gn:feature_class":"P",
    "gn:feature_code":"PPL",
    "gn:name":"\u015eawar",
    "gn:population":0,
    "gn:timezone":"Asia/Aden",
    "iso:country":"YE",
    "name:und_x_variant":[
        "\u015eawar"
    ],
    "wof:name":"Sawar",
    "wof:placetype":"locality"
},
  "geometry": {"coordinates":[43.7377,16.19572],"type":"Point"}
}