{
  "type": "Feature",
  "properties": {
    "gn:admin1_code":"15.0",
    "gn:admin2_code":"2206.0",
    "gn:asciiname":"Ma'tiq al 'Araji",
    "gn:country_code":"YE",
    "gn:dem":987,
    "gn:feature_class":"P",
    "gn:feature_code":"PPL",
    "gn:name":"Ma\u2018tiq al \u2018Araj\u012b",
    "gn:population":0,
    "gn:timezone":"Asia/Aden",
    "iso:country":"YE",
    "name:ara_x_preferred":[
        "\u0645\u0639\u062a\u0642 \u0627\u0644\u0639\u0631\u062c\u064a"
    ],
    "name:und_x_variant":[
        "Ma\u2018tiq al \u2018Araj\u012b"
    ],
    "wof:name":"Ma'tiq al 'Araji",
    "wof:placetype":"locality"
},
  "geometry": {"coordinates":[43.17303,16.90065],"type":"Point"}
}