{
  "type": "Feature",
  "properties": {
    "gn:admin1_code":"15.0",
    "gn:admin2_code":"2209.0",
    "gn:asciiname":"Alt Satir",
    "gn:country_code":"YE",
    "gn:dem":2537,
    "gn:feature_class":"P",
    "gn:feature_code":"PPL",
    "gn:name":"Alt S\u0101tir",
    "gn:population":0,
    "gn:timezone":"Asia/Aden",
    "iso:country":"YE",
    "name:ara_x_preferred":[
        "Alt S\u0101tir"
    ],
    "wof:name":"Alt Satir",
    "wof:placetype":"locality"
},
  "geometry": {"coordinates":[43.387,16.88802],"type":"Point"}
}