{
  "type": "Feature",
  "properties": {
    "gn:admin1_code":"22.0",
    "gn:admin2_code":"1722.0",
    "gn:asciiname":"Al Wa`rah",
    "gn:country_code":"YE",
    "gn:dem":592,
    "gn:feature_class":"P",
    "gn:feature_code":"PPL",
    "gn:name":"Al Wa\u2018rah",
    "gn:population":0,
    "gn:timezone":"Asia/Aden",
    "iso:country":"YE",
    "name:und_x_variant":[
        "Al Wa\u2018rah"
    ],
    "wof:name":"Al Wa`rah",
    "wof:placetype":"locality"
},
  "geometry": {"coordinates":[43.3798,15.77696],"type":"Point"}
}