{
  "type": "Feature",
  "properties": {
    "gn:country":"YE",
    "gn:fcode":"PPL",
    "gn:population":23,
    "iso:country":"YE",
    "name:ara_x_preferred":[
        "\u0627\u0644\u0645\u064a\u062c\u0627\u0646\u0629"
    ],
    "name:eng_x_preferred":[
        "Al Mayjanah"
    ],
    "name:eng_x_variant":[
        "Bayt Zuhayr"
    ],
    "qs:name":"Al Mayj\u0101nah",
    "qs:photos_9r":0,
    "qs:photos_sr":0,
    "qs:pop_sr":"1",
    "wof:name":"Al Mayj\u0101nah",
    "wof:placetype":"locality",
    "wof:population":23
},
  "geometry": {"coordinates":[43.40939,16.08104],"type":"Point"}
}