{
  "type": "Feature",
  "properties": {
    "gn:admin1_code":"19.0",
    "gn:admin2_code":"2919.0",
    "gn:asciiname":"Al Qaradi'",
    "gn:country_code":"YE",
    "gn:dem":1642,
    "gn:feature_class":"P",
    "gn:feature_code":"PPL",
    "gn:name":"Al Qar\u0101d\u012b\u2018",
    "gn:population":0,
    "gn:timezone":"Asia/Aden",
    "iso:country":"YE",
    "name:ara_x_preferred":[
        "\u0627\u0644\u0642\u0631\u0627\u062f\u064a\u0639"
    ],
    "name:und_x_variant":[
        "Al Qar\u0101d\u012b\u2018"
    ],
    "wof:name":"Al Qaradi'",
    "wof:placetype":"locality"
},
  "geometry": {"coordinates":[43.80822,16.04237],"type":"Point"}
}