{
  "type": "Feature",
  "properties": {
    "gn:admin1_code":"27.0",
    "gn:admin2_code":"3103.0",
    "gn:asciiname":"Al Maswal",
    "gn:country_code":"YE",
    "gn:dem":2019,
    "gn:feature_class":"P",
    "gn:feature_code":"PPL",
    "gn:name":"Al Ma\u015fwal",
    "gn:population":0,
    "gn:timezone":"Asia/Aden",
    "iso:country":"YE",
    "name:und_x_variant":[
        "Al Ma\u015fwal"
    ],
    "wof:name":"Al Maswal",
    "wof:placetype":"locality"
},
  "geometry": {"coordinates":[43.84371,14.63637],"type":"Point"}
}