{
  "type": "Feature",
  "properties": {
    "gn:admin1_code":"23.0",
    "gn:admin2_code":"1116.0",
    "gn:asciiname":"Al Wahs",
    "gn:country_code":"YE",
    "gn:dem":1963,
    "gn:feature_class":"P",
    "gn:feature_code":"PPL",
    "gn:name":"Al Wa\u1e29\u015f",
    "gn:population":0,
    "gn:timezone":"Asia/Aden",
    "iso:country":"YE",
    "name:und_x_variant":[
        "Al Wa\u1e29\u015f"
    ],
    "wof:name":"Al Wahs",
    "wof:placetype":"locality"
},
  "geometry": {"coordinates":[44.07924000000001,13.82543],"type":"Point"}
}