{
  "type": "Feature",
  "properties": {
    "gn:admin1_code":"25.0",
    "gn:admin2_code":"1516.0",
    "gn:asciiname":"Dhi `Ayyan",
    "gn:country_code":"YE",
    "gn:dem":567,
    "gn:feature_class":"P",
    "gn:feature_code":"PPL",
    "gn:name":"Dh\u012b \u2018Ayy\u0101n",
    "gn:population":0,
    "gn:timezone":"Asia/Aden",
    "iso:country":"YE",
    "name:ara_x_preferred":[
        "Dh\u012b \u2018Ayy\u0101n"
    ],
    "name:ara_x_variant":[
        "\u0630\u064a \u0639\u064a\u0627\u0646"
    ],
    "wof:name":"Dhi `Ayyan",
    "wof:placetype":"locality"
},
  "geometry": {"coordinates":[43.77203,13.198],"type":"Point"}
}