{
  "type": "Feature",
  "properties": {
    "gn:admin1_code":"22.0",
    "gn:admin2_code":"1730.0",
    "gn:asciiname":"Al Bad'ah",
    "gn:country_code":"YE",
    "gn:dem":1348,
    "gn:feature_class":"P",
    "gn:feature_code":"PPL",
    "gn:name":"Al Bad\u2018ah",
    "gn:population":0,
    "gn:timezone":"Asia/Aden",
    "iso:country":"YE",
    "name:ara_x_preferred":[
        "\u0627\u0644\u0628\u062f\u0639\u0629"
    ],
    "name:und_x_variant":[
        "Al Bad\u2018ah"
    ],
    "wof:name":"Al Bad'ah",
    "wof:placetype":"locality"
},
  "geometry": {"coordinates":[43.40069,16.2957],"type":"Point"}
}