{
  "type": "Feature",
  "properties": {
    "gn:country":"YE",
    "gn:fcode":"PPL",
    "gn:pop":3,
    "iso:country":"YE",
    "name:ara_x_preferred":[
        "\u0627\u0644\u0645\u062d\u064a\u0635\u0628"
    ],
    "name:eng_x_preferred":[
        "Al Muhaysib"
    ],
    "qs:name":"Al Mu\u1e29ay\u015fib",
    "qs:photos_9r":0,
    "qs:photos_sr":0,
    "qs:pop_sr":"1",
    "wof:name":"Al Mu\u1e29ay\u015fib",
    "wof:placetype":"locality",
    "wof:population":3
},
  "geometry": {"coordinates":[43.77533,13.48211],"type":"Point"}
}