{
  "type": "Feature",
  "properties": {
    "gn:admin1_code":"25.0",
    "gn:admin2_code":"1521.0",
    "gn:asciiname":"`Ubad",
    "gn:country_code":"YE",
    "gn:dem":1270,
    "gn:feature_class":"P",
    "gn:feature_code":"PPL",
    "gn:name":"\u2018Ub\u0101d",
    "gn:population":0,
    "gn:timezone":"Asia/Aden",
    "iso:country":"YE",
    "name:ara_x_preferred":[
        "\u2018Ub\u0101d"
    ],
    "name:und_x_variant":[
        "\u2018Ib\u0101d"
    ],
    "wof:name":"`Ubad",
    "wof:placetype":"locality"
},
  "geometry": {"coordinates":[44.03622,13.35961],"type":"Point"}
}