{
  "type": "Feature",
  "properties": {
    "gn:admin1_code":"16.0",
    "gn:admin2_code":"2316.0",
    "gn:asciiname":"Al Hisn al Amir",
    "gn:country_code":"YE",
    "gn:dem":2197,
    "gn:feature_class":"P",
    "gn:feature_code":"PPL",
    "gn:name":"Al \u1e28i\u015fn al Am\u012br",
    "gn:population":0,
    "gn:timezone":"Asia/Aden",
    "iso:country":"YE",
    "name:und_x_variant":[
        "Al \u1e28i\u015fn al Am\u012br"
    ],
    "wof:name":"Al Hisn al Amir",
    "wof:placetype":"locality"
},
  "geometry": {"coordinates":[44.56667,15.21667],"type":"Point"}
}