{
  "type": "Feature",
  "properties": {
    "gn:admin1_code":"20.0",
    "gn:asciiname":"Dhira` al Majnunah",
    "gn:country_code":"YE",
    "gn:dem":2209,
    "gn:feature_class":"P",
    "gn:feature_code":"PPL",
    "gn:name":"Dhir\u0101\u2018 al Majn\u016bnah",
    "gn:population":0,
    "gn:timezone":"Asia/Aden",
    "iso:country":"YE",
    "name:ara_x_preferred":[
        "\u0630\u0631\u0627\u0639 \u0627\u0644\u0645\u062c\u0646\u0648\u0646\u0629"
    ],
    "name:und_x_variant":[
        "Dhir\u0101\u2018 al Majn\u016bnah"
    ],
    "wof:name":"Dhira` al Majnunah",
    "wof:placetype":"locality"
},
  "geometry": {"coordinates":[44.37488,14.4263],"type":"Point"}
}