{
  "type": "Feature",
  "properties": {
    "gn:admin1_code":"22.0",
    "gn:admin2_code":"1725.0",
    "gn:asciiname":"An Nasirah",
    "gn:country_code":"YE",
    "gn:dem":743,
    "gn:feature_class":"P",
    "gn:feature_code":"PPL",
    "gn:name":"An N\u0101\u015firah",
    "gn:population":0,
    "gn:timezone":"Asia/Aden",
    "iso:country":"YE",
    "name:und_x_variant":[
        "An N\u0101\u015firah"
    ],
    "wof:name":"An Nasirah",
    "wof:placetype":"locality"
},
  "geometry": {"coordinates":[43.46626,15.59254],"type":"Point"}
}