{
  "type": "Feature",
  "properties": {
    "gn:country":"YE",
    "gn:fcode":"PPL",
    "gn:pop":1,
    "iso:country":"YE",
    "name:ara_x_preferred":[
        "\u0627\u0644\u0639\u062f\u0646\u0629"
    ],
    "name:eng_x_preferred":[
        "Al 'Udnah"
    ],
    "qs:name":"Al \u2018Udnah",
    "qs:photos_9r":0,
    "qs:photos_sr":0,
    "qs:pop_sr":"1",
    "wof:name":"Al \u2018Udnah",
    "wof:placetype":"locality",
    "wof:population":1
},
  "geometry": {"coordinates":[43.23978,17.24164],"type":"Point"}
}