{
  "type": "Feature",
  "properties": {
    "gn:country":"YE",
    "gn:fcode":"PPL",
    "gn:pop":10,
    "iso:country":"YE",
    "name:ara_x_preferred":[
        "\u0643\u0648\u0644\u0629 \u0627\u0644\u0645\u062d\u0631\u0627\u0646"
    ],
    "name:eng_x_preferred":[
        "Kawlat Al Mahrab"
    ],
    "qs:name":"Kawlat al Ma\u1e29r\u0101b",
    "qs:photos_9r":0,
    "qs:photos_sr":0,
    "qs:pop_sr":"1",
    "wof:name":"Kawlat al Ma\u1e29r\u0101b",
    "wof:placetype":"locality",
    "wof:population":10
},
  "geometry": {"coordinates":[43.42719,16.0769],"type":"Point"}
}