{
  "type": "Feature",
  "properties": {
    "gn:admin1_code":"22.0",
    "gn:admin2_code":"1730.0",
    "gn:asciiname":"Al Qimah",
    "gn:country_code":"YE",
    "gn:dem":1080,
    "gn:feature_class":"P",
    "gn:feature_code":"PPL",
    "gn:name":"Al Q\u012bmah",
    "gn:population":5,
    "gn:timezone":"Asia/Aden",
    "iso:country":"YE",
    "name:ara_x_preferred":[
        "\u0627\u0644\u0642\u064a\u0645\u0629"
    ],
    "name:und_x_variant":[
        "Al Q\u012bmah"
    ],
    "wof:name":"Al Qimah",
    "wof:placetype":"locality",
    "wof:population":5
},
  "geometry": {"coordinates":[43.40314,16.36337],"type":"Point"}
}