{
  "type": "Feature",
  "properties": {
    "gn:admin1_code":"25.0",
    "gn:admin2_code":"1505.0",
    "gn:asciiname":"Bani Hajjaj",
    "gn:country_code":"YE",
    "gn:dem":1152,
    "gn:feature_class":"P",
    "gn:feature_code":"PPL",
    "gn:name":"Ban\u012b \u1e28ajj\u0101j",
    "gn:population":0,
    "gn:timezone":"Asia/Aden",
    "iso:country":"YE",
    "name:und_x_variant":[
        "Ban\u012b \u1e28ajj\u0101j"
    ],
    "wof:name":"Bani Hajjaj",
    "wof:placetype":"locality"
},
  "geometry": {"coordinates":[43.81461,13.47099],"type":"Point"}
}