{
  "type": "Feature",
  "properties": {
    "gn:admin1_code":"15.0",
    "gn:admin2_code":"2210.0",
    "gn:asciiname":"Rughafah",
    "gn:country_code":"YE",
    "gn:dem":1949,
    "gn:feature_class":"P",
    "gn:feature_code":"PPL",
    "gn:name":"Rugh\u0101fah",
    "gn:population":0,
    "gn:timezone":"Asia/Aden",
    "iso:country":"YE",
    "name:ara_x_preferred":[
        "\u0631\u063a\u0627\u0641\u0629"
    ],
    "name:und_x_variant":[
        "Rugh\u0101fah"
    ],
    "wof:name":"Rughafah",
    "wof:placetype":"locality"
},
  "geometry": {"coordinates":[43.50334,17.21027],"type":"Point"}
}