{
  "type": "Feature",
  "properties": {
    "gn:admin1_code":"8.0",
    "gn:admin2_code":"1802.0",
    "gn:asciiname":"Dayr al Hadi",
    "gn:country_code":"YE",
    "gn:dem":81,
    "gn:feature_class":"P",
    "gn:feature_code":"PPL",
    "gn:name":"Dayr al H\u0101d\u012b",
    "gn:population":0,
    "gn:timezone":"Asia/Aden",
    "iso:country":"YE",
    "name:und_x_variant":[
        "Dayr al H\u0101d\u012b",
        "Dayr H\u0101d\u012b"
    ],
    "wof:name":"Dayr al Hadi",
    "wof:placetype":"locality"
},
  "geometry": {"coordinates":[43.02761,15.59577],"type":"Point"}
}