{
  "type": "Feature",
  "properties": {
    "gn:admin1_code":"23.0",
    "gn:admin2_code":"1102.0",
    "gn:asciiname":"Al Khirbah",
    "gn:country_code":"YE",
    "gn:dem":2765,
    "gn:feature_class":"P",
    "gn:feature_code":"PPL",
    "gn:name":"Al Khirbah",
    "gn:population":0,
    "gn:timezone":"Asia/Aden",
    "iso:country":"YE",
    "name:ara_x_preferred":[
        "\u0627\u0644\u062e\u0631\u0628\u0629"
    ],
    "name:und_x_variant":[
        "Al Kharbah",
        "Al Khirbah"
    ],
    "wof:name":"Al Khirbah",
    "wof:placetype":"locality"
},
  "geometry": {"coordinates":[44.30404,14.17482],"type":"Point"}
}