{
  "type": "Feature",
  "properties": {
    "gn:admin1_code":"23.0",
    "gn:admin2_code":"1109.0",
    "gn:asciiname":"Al Kasr",
    "gn:country_code":"YE",
    "gn:dem":1132,
    "gn:feature_class":"P",
    "gn:feature_code":"PPL",
    "gn:name":"Al Kasr",
    "gn:population":0,
    "gn:timezone":"Asia/Aden",
    "iso:country":"YE",
    "name:ara_x_preferred":[
        "\u0627\u0644\u0643\u0633\u0631"
    ],
    "name:und_x_variant":[
        "Al Kusr",
        "Al Kasr"
    ],
    "wof:name":"Al Kasr",
    "wof:placetype":"locality"
},
  "geometry": {"coordinates":[43.86415,14.07558],"type":"Point"}
}