{
  "type": "Feature",
  "properties": {
    "gn:admin1_code":"8.0",
    "gn:admin2_code":"1812.0",
    "gn:asciiname":"Al Mahrur",
    "gn:country_code":"YE",
    "gn:dem":2002,
    "gn:feature_class":"P",
    "gn:feature_code":"PPL",
    "gn:name":"Al Ma\u1e29r\u016br",
    "gn:population":0,
    "gn:timezone":"Asia/Aden",
    "iso:country":"YE",
    "name:ara_x_preferred":[
        "\u0627\u0644\u0645\u062d\u0631\u0648\u0631"
    ],
    "name:und_x_variant":[
        "Al Ma\u1e29r\u016br"
    ],
    "wof:name":"Al Mahrur",
    "wof:placetype":"locality"
},
  "geometry": {"coordinates":[43.4994,14.89508],"type":"Point"}
}