{
  "type": "Feature",
  "properties": {
    "gn:admin1_code":"8.0",
    "gn:admin2_code":"1801.0",
    "gn:asciiname":"Dayr al Musayyir",
    "gn:country_code":"YE",
    "gn:dem":201,
    "gn:feature_class":"P",
    "gn:feature_code":"PPL",
    "gn:name":"Dayr al Musayyir",
    "gn:population":0,
    "gn:timezone":"Asia/Aden",
    "iso:country":"YE",
    "wof:name":"Dayr al Musayyir",
    "wof:placetype":"locality"
},
  "geometry": {"coordinates":[43.22702,15.81352],"type":"Point"}
}