{
  "type": "Feature",
  "properties": {
    "gn:country":"YE",
    "gn:fcode":"PPL",
    "gn:population":6,
    "iso:country":"YE",
    "name:ara_x_preferred":[
        "\u0627\u0644\u0643\u0644\u064a\u0643\u0644\u0629"
    ],
    "name:eng_x_preferred":[
        "Al Kulaykilah"
    ],
    "name:eng_x_variant":[
        "Khiyah"
    ],
    "qs:name":"Al Kulaykilah",
    "qs:photos_9r":0,
    "qs:photos_sr":0,
    "qs:pop_sr":"1",
    "wof:name":"Al Kulaykilah",
    "wof:placetype":"locality",
    "wof:population":6
},
  "geometry": {"coordinates":[43.25703,17.10801],"type":"Point"}
}