{
  "type": "Feature",
  "properties": {
    "gn:admin1_code":"22.0",
    "gn:admin2_code":"1731.0",
    "gn:asciiname":"Maswar",
    "gn:country_code":"YE",
    "gn:dem":1765,
    "gn:feature_class":"P",
    "gn:feature_code":"PPL",
    "gn:name":"Ma\u015fwar",
    "gn:population":0,
    "gn:timezone":"Asia/Aden",
    "iso:country":"YE",
    "name:ara_x_preferred":[
        "\u0645\u0635\u0648\u0631"
    ],
    "name:und_x_variant":[
        "Ma\u015fwar"
    ],
    "wof:name":"Maswar",
    "wof:placetype":"locality"
},
  "geometry": {"coordinates":[43.46767,16.33167000000001],"type":"Point"}
}