{
  "type": "Feature",
  "properties": {
    "gn:admin1_code":"24.0",
    "gn:admin2_code":"2512.0",
    "gn:asciiname":"Al 'Azmaq",
    "gn:country_code":"YE",
    "gn:dem":757,
    "gn:feature_class":"P",
    "gn:feature_code":"PPL",
    "gn:name":"Al \u2018Azmaq",
    "gn:population":0,
    "gn:timezone":"Asia/Aden",
    "iso:country":"YE",
    "name:ara_x_preferred":[
        "\u0627\u0644\u0639\u0632\u0645\u0642"
    ],
    "name:und_x_variant":[
        "Al \u2018Azmaq"
    ],
    "wof:name":"Al 'Azmaq",
    "wof:placetype":"locality"
},
  "geometry": {"coordinates":[44.1738,13.11383],"type":"Point"}
}