{
  "type": "Feature",
  "properties": {
    "gn:admin1_code":"24.0",
    "gn:admin2_code":"2510.0",
    "gn:asciiname":"Ash Shaji",
    "gn:country_code":"YE",
    "gn:dem":1257,
    "gn:feature_class":"P",
    "gn:feature_code":"PPL",
    "gn:name":"Ash Sh\u0101j\u012b",
    "gn:population":0,
    "gn:timezone":"Asia/Aden",
    "iso:country":"YE",
    "name:ara_x_preferred":[
        "Ash Sh\u0101j\u012b"
    ],
    "wof:name":"Ash Shaji",
    "wof:placetype":"locality"
},
  "geometry": {"coordinates":[44.36104,13.24026],"type":"Point"}
}