{
  "type": "Feature",
  "properties": {
    "gn:admin1_code":"11.0",
    "gn:admin2_code":"2003.0",
    "gn:asciiname":"Mahall Sahwah",
    "gn:country_code":"YE",
    "gn:dem":1586,
    "gn:feature_class":"P",
    "gn:feature_code":"PPL",
    "gn:name":"Ma\u1e29all Sahwah",
    "gn:population":0,
    "gn:timezone":"Asia/Aden",
    "iso:country":"YE",
    "name:und_x_variant":[
        "Ma\u1e29all Sahwah"
    ],
    "wof:name":"Mahall Sahwah",
    "wof:placetype":"locality"
},
  "geometry": {"coordinates":[44.03825,14.66315],"type":"Point"}
}