{
  "type": "Feature",
  "properties": {
    "gn:admin1_code":"11.0",
    "gn:admin2_code":"1102.0",
    "gn:asciiname":"As Sari",
    "gn:country_code":"YE",
    "gn:dem":2699,
    "gn:feature_class":"P",
    "gn:feature_code":"PPL",
    "gn:name":"As S\u0101r\u012b",
    "gn:population":0,
    "gn:timezone":"Asia/Aden",
    "iso:country":"YE",
    "name:ara_x_preferred":[
        "As S\u0101r\u012b"
    ],
    "name:ara_x_variant":[
        "\u0627\u0644\u0633\u0627\u0631\u064a"
    ],
    "wof:name":"As Sari",
    "wof:placetype":"locality"
},
  "geometry": {"coordinates":[44.32819,14.3091],"type":"Point"}
}