{
  "type": "Feature",
  "properties": {
    "gn:admin1_code":"8.0",
    "gn:admin2_code":"1817.0",
    "gn:asciiname":"Al Hasaniyah",
    "gn:country_code":"YE",
    "gn:dem":121,
    "gn:feature_class":"P",
    "gn:feature_code":"PPL",
    "gn:name":"Al \u1e28asan\u012byah",
    "gn:population":0,
    "gn:timezone":"Asia/Aden",
    "iso:country":"YE",
    "name:und_x_variant":[
        "Al \u1e28asan\u012byah"
    ],
    "wof:name":"Al Hasaniyah",
    "wof:placetype":"locality"
},
  "geometry": {"coordinates":[43.30266,14.42735],"type":"Point"}
}