{
  "type": "Feature",
  "properties": {
    "gn:admin1_code":"8.0",
    "gn:admin2_code":"1815.0",
    "gn:asciiname":"Dayf `Abduh Yahya",
    "gn:country_code":"YE",
    "gn:dem":209,
    "gn:feature_class":"P",
    "gn:feature_code":"PPL",
    "gn:name":"\u1e10ayf \u2018Abduh Ya\u1e29y\u00e1",
    "gn:population":0,
    "gn:timezone":"Asia/Aden",
    "iso:country":"YE",
    "name:ara_x_preferred":[
        "\u0636\u064a\u0641 \u0639\u0628\u062f\u0647 \u064a\u062d\u064a\u0649"
    ],
    "name:und_x_variant":[
        "\u015eanif \u2018Abdah Ya\u1e29y\u00e1 Qushaymah",
        "\u1e10ayf \u2018Abduh Ya\u1e29y\u00e1"
    ],
    "wof:name":"Dayf `Abduh Yahya",
    "wof:placetype":"locality"
},
  "geometry": {"coordinates":[43.40931,14.81448],"type":"Point"}
}