{
  "type": "Feature",
  "properties": {
    "gn:admin1_code":"2.0",
    "gn:admin2_code":"2404.0",
    "gn:asciiname":"Bi'r Rubak",
    "gn:country_code":"YE",
    "gn:dem":9,
    "gn:feature_class":"P",
    "gn:feature_code":"PPL",
    "gn:name":"Bi\u2019r Rub\u0101k",
    "gn:population":0,
    "gn:timezone":"Asia/Aden",
    "iso:country":"YE",
    "name:ara_x_preferred":[
        "Bi\u2019r Rub\u0101k"
    ],
    "name:und_x_variant":[
        "Bi\u2019r Rib\u0101q",
        "Bir Rubaq"
    ],
    "wof:name":"Bi'r Rubak",
    "wof:placetype":"locality"
},
  "geometry": {"coordinates":[44.92083,12.83167],"type":"Point"}
}