{
  "type": "Feature",
  "properties": {
    "gn:admin1_code":"23.0",
    "gn:admin2_code":"1117.0",
    "gn:asciiname":"Hisn Halyan",
    "gn:country_code":"YE",
    "gn:dem":1454,
    "gn:feature_class":"P",
    "gn:feature_code":"PPL",
    "gn:name":"\u1e28i\u015fn \u1e28aly\u0101n",
    "gn:population":0,
    "gn:timezone":"Asia/Aden",
    "iso:country":"YE",
    "name:und_x_variant":[
        "\u1e28i\u015fn \u1e28aly\u0101n"
    ],
    "wof:name":"Hisn Halyan",
    "wof:placetype":"locality"
},
  "geometry": {"coordinates":[44.01012,13.89682],"type":"Point"}
}