{
  "type": "Feature",
  "properties": {
    "gn:admin1_code":"24.0",
    "gn:admin2_code":"2508.0",
    "gn:asciiname":"Al `Alawi",
    "gn:country_code":"YE",
    "gn:dem":702,
    "gn:feature_class":"P",
    "gn:feature_code":"PPL",
    "gn:name":"Al \u2018Alaw\u012b",
    "gn:population":0,
    "gn:timezone":"Asia/Aden",
    "iso:country":"YE",
    "name:und_x_variant":[
        "Al \u2018Alaw\u012b"
    ],
    "wof:name":"Al `Alawi",
    "wof:placetype":"locality"
},
  "geometry": {"coordinates":[44.90528,13.46167],"type":"Point"}
}