{
  "type": "Feature",
  "properties": {
    "gn:admin1_code":"8.0",
    "gn:admin2_code":"1807.0",
    "gn:asciiname":"'Umar Hasan",
    "gn:country_code":"YE",
    "gn:dem":98,
    "gn:feature_class":"P",
    "gn:feature_code":"PPL",
    "gn:name":"\u2018Umar \u1e28asan",
    "gn:population":0,
    "gn:timezone":"Asia/Aden",
    "iso:country":"YE",
    "name:ara_x_preferred":[
        "\u0639\u0645\u0631 \u062d\u0633\u0646"
    ],
    "name:und_x_variant":[
        "\u2018Umar \u1e28asan"
    ],
    "wof:name":"'Umar Hasan",
    "wof:placetype":"locality"
},
  "geometry": {"coordinates":[43.15947,15.38839],"type":"Point"}
}