{
  "type": "Feature",
  "properties": {
    "gn:admin1_code":"24.0",
    "gn:admin2_code":"2512.0",
    "gn:asciiname":"Al Ki'ab",
    "gn:country_code":"YE",
    "gn:dem":844,
    "gn:feature_class":"P",
    "gn:feature_code":"PPL",
    "gn:name":"Al Ki\u2018\u0101b",
    "gn:population":0,
    "gn:timezone":"Asia/Aden",
    "iso:country":"YE",
    "name:ara_x_preferred":[
        "\u0627\u0644\u0643\u0639\u0627\u0628"
    ],
    "name:und_x_variant":[
        "Al Ki\u2018\u0101b"
    ],
    "wof:name":"Al Ki'ab",
    "wof:placetype":"locality"
},
  "geometry": {"coordinates":[44.17574000000001,13.12667],"type":"Point"}
}