{
  "type": "Feature",
  "properties": {
    "gn:country":"YE",
    "gn:fcode":"PPL",
    "gn:pop":29,
    "iso:country":"YE",
    "name:ara_x_preferred":[
        "Ad D\u0101shin"
    ],
    "name:ara_x_variant":[
        "\u0627\u0644\u062f\u0627\u0634\u0646"
    ],
    "name:eng_x_preferred":[
        "Ad Dashin"
    ],
    "name:eng_x_variant":[
        "Ma\u1e29\u016b\u0163\u016b"
    ],
    "qs:name":"Ad D\u0101shin",
    "qs:photos_9r":0,
    "qs:photos_sr":0,
    "qs:pop_sr":"1",
    "wof:name":"Ad D\u0101shin",
    "wof:placetype":"locality",
    "wof:population":29
},
  "geometry": {"coordinates":[43.84251,13.35693],"type":"Point"}
}