{
  "type": "Feature",
  "properties": {
    "gn:admin1_code":"19.0",
    "gn:admin2_code":"2909.0",
    "gn:asciiname":"Bayt Mirka`",
    "gn:country_code":"YE",
    "gn:dem":2064,
    "gn:feature_class":"P",
    "gn:feature_code":"PPL",
    "gn:name":"Bayt Mirk\u0101\u2018",
    "gn:population":0,
    "gn:timezone":"Asia/Aden",
    "iso:country":"YE",
    "name:ara_x_preferred":[
        "\u0628\u064a\u062a \u0645\u0631\u0643\u0627\u0639"
    ],
    "name:und_x_variant":[
        "Bayt Mirk\u0101\u2018"
    ],
    "wof:name":"Bayt Mirka`",
    "wof:placetype":"locality"
},
  "geometry": {"coordinates":[44.09346,16.06086],"type":"Point"}
}