{
  "type": "Feature",
  "properties": {
    "gn:country":"YE",
    "gn:fcode":"PPL",
    "gn:pop":25,
    "iso:country":"YE",
    "name:ara_x_preferred":[
        "\u0627\u0644\u0642\u0637\u0639\u0629"
    ],
    "qs:name":"Al Qa\u0163\u2018ah",
    "qs:photos_9r":0,
    "qs:photos_sr":0,
    "qs:pop_sr":"1",
    "wof:name":"Al Qa\u0163\u2018ah",
    "wof:placetype":"locality",
    "wof:population":25
},
  "geometry": {"coordinates":[45.11082,14.33828],"type":"Point"}
}