{
  "type": "Feature",
  "properties": {
    "gn:country":"YE",
    "gn:fcode":"PPL",
    "gn:pop":6,
    "iso:country":"YE",
    "name:ara_x_preferred":[
        "\u0627\u0644\u0645\u062d\u0631\u0627\u0642"
    ],
    "qs:name":"Al Ma\u1e29r\u0101q",
    "qs:photos_9r":0,
    "qs:photos_sr":0,
    "qs:pop_sr":"1",
    "wof:name":"Al Ma\u1e29r\u0101q",
    "wof:placetype":"locality",
    "wof:population":6
},
  "geometry": {"coordinates":[43.38459,16.19745],"type":"Point"}
}