{
  "type": "Feature",
  "properties": {
    "gn:admin1_code":"19.0",
    "gn:admin2_code":"2901.0",
    "gn:asciiname":"Bijja`ah",
    "gn:country_code":"YE",
    "gn:dem":1179,
    "gn:feature_class":"P",
    "gn:feature_code":"PPL",
    "gn:name":"Bijja\u2018ah",
    "gn:population":0,
    "gn:timezone":"Asia/Aden",
    "iso:country":"YE",
    "name:ara_x_preferred":[
        "\u0628\u062c\u0639\u0629"
    ],
    "name:und_x_variant":[
        "Bijja\u2018ah"
    ],
    "wof:name":"Bijja`ah",
    "wof:placetype":"locality"
},
  "geometry": {"coordinates":[43.5428,16.35239],"type":"Point"}
}