{
  "type": "Feature",
  "properties": {
    "gn:country":"YE",
    "gn:fcode":"PPLF",
    "gn:pop":7,
    "iso:country":"YE",
    "name:ara_x_preferred":[
        "\u0630\u0648 \u0642\u0631\u064a\u062d"
    ],
    "name:eng_x_preferred":[
        "DhU Qurayh"
    ],
    "name:eng_x_variant":[
        "Sha\u2018b a\u015f \u015eubb\u012b"
    ],
    "qs:name":"Dh\u016b Quray\u1e29",
    "qs:photos_9r":0,
    "qs:photos_sr":0,
    "qs:pop_sr":"1",
    "wof:name":"Dh\u016b Quray\u1e29",
    "wof:placetype":"locality",
    "wof:population":7
},
  "geometry": {"coordinates":[44.02458,16.89129],"type":"Point"}
}