{
  "type": "Feature",
  "properties": {
    "gn:admin1_code":"22.0",
    "gn:admin2_code":"1724.0",
    "gn:asciiname":"Mahall Bani Amir al hawatim",
    "gn:country_code":"YE",
    "gn:dem":250,
    "gn:feature_class":"P",
    "gn:feature_code":"PPL",
    "gn:name":"Ma\u1e29all Ban\u012b \u0100mir al \u1e29aw\u0101tim",
    "gn:population":0,
    "gn:timezone":"Asia/Aden",
    "iso:country":"YE",
    "name:und_x_variant":[
        "Ma\u1e29all Ban\u012b \u0100mir al \u1e29aw\u0101tim"
    ],
    "wof:name":"Mahall Bani Amir al hawatim",
    "wof:placetype":"locality"
},
  "geometry": {"coordinates":[43.28055,15.65933],"type":"Point"}
}