{
  "type": "Feature",
  "properties": {
    "gn:admin1_code":"21.0",
    "gn:admin2_code":"1604.0",
    "gn:asciiname":"Badw al Jabal al Ahmar",
    "gn:country_code":"YE",
    "gn:dem":1248,
    "gn:feature_class":"P",
    "gn:feature_code":"PPLL",
    "gn:name":"Badw al Jabal al A\u1e29mar",
    "gn:population":0,
    "gn:timezone":"Asia/Aden",
    "iso:country":"YE",
    "name:ara_x_preferred":[
        "\u0628\u062f\u0648 \u0627\u0644\u062c\u0628\u0644 \u0627\u0644\u0623\u062d\u0645\u0631"
    ],
    "name:und_x_variant":[
        "Badw al Jabal al A\u1e29mar"
    ],
    "wof:name":"Badw al Jabal al Ahmar",
    "wof:placetype":"locality"
},
  "geometry": {"coordinates":[44.45919,16.3706],"type":"Point"}
}