{
  "type": "Feature",
  "properties": {
    "gn:country":"YE",
    "gn:fcode":"PPL",
    "gn:pop":25,
    "iso:country":"YE",
    "name:ara_x_preferred":[
        "\u0627\u0644\u0631\u062d\u0628\u0629"
    ],
    "name:eng_x_preferred":[
        "Ar Rahabah"
    ],
    "name:eng_x_variant":[
        "Al Murrah al \u2018Uly\u0101"
    ],
    "qs:name":"Ar Ra\u1e29abah",
    "qs:photos_9r":0,
    "qs:photos_sr":0,
    "qs:pop_sr":"1",
    "wd:wordcount":23,
    "wof:name":"Ar Ra\u1e29abah",
    "wof:placetype":"locality",
    "wof:population":25
},
  "geometry": {"coordinates":[43.71149,16.05002],"type":"Point"}
}