{
  "type": "Feature",
  "properties": {
    "gn:admin1_code":"11.0",
    "gn:asciiname":"Al Maydan",
    "gn:country_code":"YE",
    "gn:dem":2521,
    "gn:feature_class":"P",
    "gn:feature_code":"PPL",
    "gn:name":"Al Mayd\u0101n",
    "gn:population":0,
    "gn:timezone":"Asia/Aden",
    "iso:country":"YE",
    "name:ara_x_preferred":[
        "\u0627\u0644\u0645\u064a\u062f\u0627\u0646"
    ],
    "name:und_x_variant":[
        "Al Mayd\u0101n"
    ],
    "wof:name":"Al Maydan",
    "wof:placetype":"locality"
},
  "geometry": {"coordinates":[44.4517,14.28175],"type":"Point"}
}