{
  "type": "Feature",
  "properties": {
    "gn:admin1_code":"21.0",
    "gn:admin2_code":"1602.0",
    "gn:asciiname":"Al Hafrah",
    "gn:country_code":"YE",
    "gn:dem":1269,
    "gn:feature_class":"P",
    "gn:feature_code":"PPL",
    "gn:name":"Al \u1e28afrah",
    "gn:population":0,
    "gn:timezone":"Asia/Aden",
    "iso:country":"YE",
    "name:ara_x_preferred":[
        "\u0627\u0644\u062d\u0641\u0631\u0629"
    ],
    "name:und_x_variant":[
        "Al \u1e28afrah"
    ],
    "wof:name":"Al Hafrah",
    "wof:placetype":"locality"
},
  "geometry": {"coordinates":[44.38234,16.42133],"type":"Point"}
}