{
  "type": "Feature",
  "properties": {
    "gn:admin1_code":"16.0",
    "gn:admin2_code":"2307.0",
    "gn:asciiname":"Bayt Sa`d",
    "gn:country_code":"YE",
    "gn:dem":2755,
    "gn:feature_class":"P",
    "gn:feature_code":"PPL",
    "gn:name":"Bayt Sa\u2018d",
    "gn:population":0,
    "gn:timezone":"Asia/Aden",
    "iso:country":"YE",
    "name:und_x_variant":[
        "Bayt Sa\u2018d"
    ],
    "wof:name":"Bayt Sa`d",
    "wof:placetype":"locality"
},
  "geometry": {"coordinates":[43.96614,15.39923],"type":"Point"}
}