{
  "type": "Feature",
  "properties": {
    "gn:country":"YE",
    "gn:fcode":"PPL",
    "gn:population":16,
    "iso:country":"YE",
    "name:ara_x_preferred":[
        "\u062c\u0628\u0644 \u0627\u0644\u062a\u0645\u0627\u0631"
    ],
    "name:eng_x_preferred":[
        "Jabal At Timar"
    ],
    "name:eng_x_variant":[
        "Al \u2018Art\u016bb"
    ],
    "qs:name":"Jabal at Tim\u0101r",
    "qs:photos_9r":0,
    "qs:photos_sr":0,
    "qs:pop_sr":"1",
    "wof:name":"Jabal at Tim\u0101r",
    "wof:placetype":"locality",
    "wof:population":16
},
  "geometry": {"coordinates":[43.29157,16.33754],"type":"Point"}
}