{
  "type": "Feature",
  "properties": {
    "gn:admin1_code":"23.0",
    "gn:admin2_code":"1107.0",
    "gn:asciiname":"Turmanah",
    "gn:cc2":"YE",
    "gn:country_code":"YE",
    "gn:dem":2353,
    "gn:feature_class":"P",
    "gn:feature_code":"PPL",
    "gn:name":"Turm\u0101nah",
    "gn:population":0,
    "gn:timezone":"Asia/Aden",
    "iso:country":"YE",
    "name:und_x_variant":[
        "Turmana",
        "Turm\u0101nah"
    ],
    "wof:name":"Turmanah",
    "wof:placetype":"locality"
},
  "geometry": {"coordinates":[44.21667,14.08333],"type":"Point"}
}