{
  "type": "Feature",
  "properties": {
    "gn:admin1_code":"8.0",
    "gn:admin2_code":"1812.0",
    "gn:asciiname":"As Sufla",
    "gn:country_code":"YE",
    "gn:dem":1867,
    "gn:feature_class":"P",
    "gn:feature_code":"PPL",
    "gn:name":"As Sufl\u00e1",
    "gn:population":0,
    "gn:timezone":"Asia/Aden",
    "iso:country":"YE",
    "name:ara_x_preferred":[
        "\u0627\u0644\u0633\u0641\u0644\u0649"
    ],
    "name:und_x_variant":[
        "As Sufl\u00e1"
    ],
    "wof:name":"As Sufla",
    "wof:placetype":"locality"
},
  "geometry": {"coordinates":[43.49741,14.89046],"type":"Point"}
}