{
  "type": "Feature",
  "properties": {
    "gn:country":"YE",
    "gn:fcode":"PPL",
    "gn:pop":11,
    "iso:country":"YE",
    "name:ara_x_preferred":[
        "Az\u0327 Z\u0327ih\u0101r"
    ],
    "name:ara_x_variant":[
        "\u0627\u0644\u0638\u0647\u0627\u0631"
    ],
    "qs:name":"Az\u0327 Z\u0327ih\u0101r",
    "qs:photos_9r":0,
    "qs:photos_sr":0,
    "qs:pop_sr":"1",
    "wof:name":"Az\u0327 Z\u0327ih\u0101r",
    "wof:placetype":"locality",
    "wof:population":11
},
  "geometry": {"coordinates":[43.6294,16.37671],"type":"Point"}
}