{
  "type": "Feature",
  "properties": {
    "gn:admin1_code":"22.0",
    "gn:admin2_code":"1727.0",
    "gn:asciiname":"Bayt al Waqf",
    "gn:country_code":"YE",
    "gn:dem":809,
    "gn:feature_class":"P",
    "gn:feature_code":"PPL",
    "gn:name":"Bayt al Waqf",
    "gn:population":0,
    "gn:timezone":"Asia/Aden",
    "iso:country":"YE",
    "name:ara_x_preferred":[
        "\u0628\u064a\u062a \u0627\u0644\u0648\u0642\u0641"
    ],
    "wof:name":"Bayt al Waqf",
    "wof:placetype":"locality"
},
  "geometry": {"coordinates":[43.59092,15.54093],"type":"Point"}
}