{
  "type": "Feature",
  "properties": {
    "gn:admin1_code":"14.0",
    "gn:asciiname":"Umm ad Dawwar",
    "gn:country_code":"YE",
    "gn:dem":1199,
    "gn:feature_class":"P",
    "gn:feature_code":"PPL",
    "gn:name":"Umm ad Daww\u0101r",
    "gn:population":0,
    "gn:timezone":"Asia/Aden",
    "iso:country":"YE",
    "name:ara_x_preferred":[
        "\u0623\u0645 \u0627\u0644\u062f\u0648\u0627\u0631"
    ],
    "name:und_x_variant":[
        "Umm ad Daww\u0101r"
    ],
    "wof:name":"Umm ad Dawwar",
    "wof:placetype":"locality"
},
  "geometry": {"coordinates":[44.50459,16.30934],"type":"Point"}
}