{
  "type": "Feature",
  "properties": {
    "gn:admin1_code":"19.0",
    "gn:admin2_code":"2901.0",
    "gn:asciiname":"Al `Aqib",
    "gn:country_code":"YE",
    "gn:dem":1561,
    "gn:feature_class":"P",
    "gn:feature_code":"PPL",
    "gn:name":"Al \u2018Aqib",
    "gn:population":0,
    "gn:timezone":"Asia/Aden",
    "iso:country":"YE",
    "name:ara_x_preferred":[
        "Al \u2018Aqib"
    ],
    "name:ara_x_variant":[
        "\u0627\u0644\u0639\u0642\u0628"
    ],
    "wof:name":"Al `Aqib",
    "wof:placetype":"locality"
},
  "geometry": {"coordinates":[44.27608,16.04259],"type":"Point"}
}