{
  "type": "Feature",
  "properties": {
    "gn:admin1_code":"25.0",
    "gn:admin2_code":"1513.0",
    "gn:asciiname":"Qaryat al Qurayyah",
    "gn:country_code":"YE",
    "gn:dem":1066,
    "gn:feature_class":"P",
    "gn:feature_code":"PPL",
    "gn:name":"Qaryat al Qurayyah",
    "gn:population":0,
    "gn:timezone":"Asia/Aden",
    "iso:country":"YE",
    "wof:name":"Qaryat al Qurayyah",
    "wof:placetype":"locality"
},
  "geometry": {"coordinates":[44.27485,13.51853],"type":"Point"}
}