{
  "type": "Feature",
  "properties": {
    "gn:admin1_code":"8.0",
    "gn:admin2_code":"1808.0",
    "gn:asciiname":"Warshat al Khatib",
    "gn:country_code":"YE",
    "gn:dem":99,
    "gn:feature_class":"P",
    "gn:feature_code":"PPL",
    "gn:name":"Warshat al Kha\u0163\u012bb",
    "gn:population":0,
    "gn:timezone":"Asia/Aden",
    "iso:country":"YE",
    "name:ara_x_preferred":[
        "\u0648\u0631\u0634\u0629 \u0627\u0644\u062e\u0637\u064a\u0628"
    ],
    "name:und_x_variant":[
        "Warshat al Kha\u0163\u012bb"
    ],
    "wof:name":"Warshat al Khatib",
    "wof:placetype":"locality"
},
  "geometry": {"coordinates":[43.13991,15.32973],"type":"Point"}
}