{
  "type": "Feature",
  "properties": {
    "gn:admin1_code":"25.0",
    "gn:admin2_code":"1502.0",
    "gn:asciiname":"Ruba`",
    "gn:country_code":"YE",
    "gn:dem":1182,
    "gn:feature_class":"P",
    "gn:feature_code":"PPL",
    "gn:name":"R\u016bba\u2018",
    "gn:population":0,
    "gn:timezone":"Asia/Aden",
    "iso:country":"YE",
    "name:und_x_variant":[
        "R\u016bba\u2018"
    ],
    "wof:name":"Ruba`",
    "wof:placetype":"locality"
},
  "geometry": {"coordinates":[43.9063,13.71383],"type":"Point"}
}