{
  "type": "Feature",
  "properties": {
    "gn:country":"YE",
    "gn:fcode":"PPL",
    "gn:population":7,
    "iso:country":"YE",
    "name:ara_x_preferred":[
        "\u0627\u0644 \u0648\u0642\u0627\u0631"
    ],
    "name:eng_x_preferred":[
        "Al Waqqar"
    ],
    "name:eng_x_variant":[
        "\u2018Aq\u0101ris"
    ],
    "qs:name":"\u0100l Waqq\u0101r",
    "qs:photos_9r":0,
    "qs:photos_sr":0,
    "qs:pop_sr":"1",
    "wof:name":"\u0100l Waqq\u0101r",
    "wof:placetype":"locality",
    "wof:population":7
},
  "geometry": {"coordinates":[43.39547,17.16298],"type":"Point"}
}