{
  "type": "Feature",
  "properties": {
    "gn:admin1_code":"20.0",
    "gn:admin2_code":"1417.0",
    "gn:asciiname":"Al Hajar",
    "gn:country_code":"YE",
    "gn:dem":2626,
    "gn:feature_class":"P",
    "gn:feature_code":"PPL",
    "gn:name":"Al Hajar",
    "gn:population":0,
    "gn:timezone":"Asia/Aden",
    "iso:country":"YE",
    "wof:name":"Al Hajar",
    "wof:placetype":"locality"
},
  "geometry": {"coordinates":[44.6729,14.31519],"type":"Point"}
}