{
  "type": "Feature",
  "properties": {
    "gn:admin1_code":"4.0",
    "gn:admin2_code":"1924.0",
    "gn:asciiname":"Ba`ba`",
    "gn:country_code":"YE",
    "gn:dem":425,
    "gn:feature_class":"P",
    "gn:feature_code":"PPL",
    "gn:name":"Ba\u2018b\u0101\u2018",
    "gn:population":0,
    "gn:timezone":"Asia/Aden",
    "iso:country":"YE",
    "name:und_x_variant":[
        "Ba\u2018b\u0101\u2018"
    ],
    "wof:name":"Ba`ba`",
    "wof:placetype":"locality"
},
  "geometry": {"coordinates":[48.11667,14.46667],"type":"Point"}
}