{
  "type": "Feature",
  "properties": {
    "gn:admin1_code":"23.0",
    "gn:admin2_code":"1111.0",
    "gn:asciiname":"Al Hadani",
    "gn:country_code":"YE",
    "gn:dem":1722,
    "gn:feature_class":"P",
    "gn:feature_code":"PPL",
    "gn:name":"Al \u1e28ad\u0101n\u012b",
    "gn:population":0,
    "gn:timezone":"Asia/Aden",
    "iso:country":"YE",
    "name:und_x_variant":[
        "Al \u1e28ad\u0101n\u012b"
    ],
    "wof:name":"Al Hadani",
    "wof:placetype":"locality"
},
  "geometry": {"coordinates":[44.06384,13.95576],"type":"Point"}
}