{
  "type": "Feature",
  "properties": {
    "gn:country":"YE",
    "gn:fcode":"PPL",
    "gn:population":5,
    "iso:country":"YE",
    "name:ara_x_preferred":[
        "\u0642\u062b\u064a\u062f"
    ],
    "name:eng_x_preferred":[
        "Quthayd"
    ],
    "name:eng_x_variant":[
        "Al Mazrib"
    ],
    "qs:name":"Quthayd",
    "qs:photos_9r":0,
    "qs:photos_sr":0,
    "qs:pop_sr":"1",
    "wof:name":"Quthayd",
    "wof:placetype":"locality",
    "wof:population":5
},
  "geometry": {"coordinates":[45.21935,14.71651],"type":"Point"}
}