{
  "type": "Feature",
  "properties": {
    "gn:admin1_code":"20.0",
    "gn:admin2_code":"1410.0",
    "gn:asciiname":"Am Hajar",
    "gn:country_code":"YE",
    "gn:dem":2045,
    "gn:feature_class":"P",
    "gn:feature_code":"PPL",
    "gn:name":"Am Hajar",
    "gn:population":0,
    "gn:timezone":"Asia/Aden",
    "iso:country":"YE",
    "name:ara_x_preferred":[
        "\u0642\u0631\u064a\u0629 \u0627\u0644\u0645\u0634\u0631\u0639"
    ],
    "name:und_x_variant":[
        "Al Hajar",
        "Qaryat al Mashra\u2018"
    ],
    "wof:name":"Am Hajar",
    "wof:placetype":"locality"
},
  "geometry": {"coordinates":[45.60605,13.9827],"type":"Point"}
}