{
  "type": "Feature",
  "properties": {
    "gn:admin1_code":"5.0",
    "gn:admin2_code":"2111.0",
    "gn:asciiname":"Hisn Bin Ja`far",
    "gn:country_code":"YE",
    "gn:dem":1440,
    "gn:feature_class":"P",
    "gn:feature_code":"PPL",
    "gn:name":"\u1e28i\u015fn Bin Ja\u2018far",
    "gn:population":0,
    "gn:timezone":"Asia/Aden",
    "iso:country":"YE",
    "name:und_x_variant":[
        "Husn Bin Jaafir",
        "\u1e28ayd Bin Ja\u2018far",
        "\u1e28i\u015fn Bin Ja\u2018far"
    ],
    "wof:name":"Hisn Bin Ja`far",
    "wof:placetype":"locality"
},
  "geometry": {"coordinates":[46.44401,14.25042],"type":"Point"}
}