{
  "type": "Feature",
  "properties": {
    "gn:admin1_code":"5.0",
    "gn:admin2_code":"2105.0",
    "gn:asciiname":"Ad Dar",
    "gn:country_code":"YE",
    "gn:dem":1053,
    "gn:feature_class":"P",
    "gn:feature_code":"PPL",
    "gn:name":"Ad D\u0101r",
    "gn:population":0,
    "gn:timezone":"Asia/Aden",
    "iso:country":"YE",
    "name:ara_x_preferred":[
        "Ad D\u0101r"
    ],
    "name:und_x_variant":[
        "Al-D\u0101r"
    ],
    "wof:name":"Ad Dar",
    "wof:placetype":"locality"
},
  "geometry": {"coordinates":[45.79665,14.97775],"type":"Point"}
}