{
  "type": "Feature",
  "properties": {
    "gn:admin1_code":"14.0",
    "gn:admin2_code":"2602.0",
    "gn:asciiname":"Hazmat Badi",
    "gn:country_code":"YE",
    "gn:dem":1109,
    "gn:feature_class":"P",
    "gn:feature_code":"PPL",
    "gn:name":"\u1e28azmat B\u0101d\u012b",
    "gn:population":0,
    "gn:timezone":"Asia/Aden",
    "iso:country":"YE",
    "name:ara_x_preferred":[
        "\u062d\u0632\u0645\u062a \u0628\u0627\u062f\u064a"
    ],
    "name:und_x_variant":[
        "\u1e28azmat B\u0101d\u012b"
    ],
    "wof:name":"Hazmat Badi",
    "wof:placetype":"locality"
},
  "geometry": {"coordinates":[45.06275,15.74346],"type":"Point"}
}