{
  "type": "Feature",
  "properties": {
    "gn:admin1_code":"18.0",
    "gn:admin2_code":"3003.0",
    "gn:asciiname":"Habil Rahah",
    "gn:country_code":"YE",
    "gn:dem":1226,
    "gn:feature_class":"P",
    "gn:feature_code":"PPL",
    "gn:name":"\u1e28ab\u012bl R\u0101\u1e29ah",
    "gn:population":0,
    "gn:timezone":"Asia/Aden",
    "iso:country":"YE",
    "name:und_x_variant":[
        "\u1e28ab\u012bl R\u0101\u1e29ah"
    ],
    "wof:name":"Habil Rahah",
    "wof:placetype":"locality"
},
  "geometry": {"coordinates":[44.63333,13.83333],"type":"Point"}
}