{
  "type": "Feature",
  "properties": {
    "gn:admin1_code":"19.0",
    "gn:admin2_code":"2919.0",
    "gn:asciiname":"Bayt Shilal",
    "gn:country_code":"YE",
    "gn:dem":2353,
    "gn:feature_class":"P",
    "gn:feature_code":"PPL",
    "gn:name":"Bayt Shil\u0101l",
    "gn:population":0,
    "gn:timezone":"Asia/Aden",
    "iso:country":"YE",
    "name:ara_x_preferred":[
        "\u0628\u064a\u062a \u0634\u0644\u0627\u0644"
    ],
    "name:und_x_variant":[
        "Bayt Shil\u0101l"
    ],
    "wof:name":"Bayt Shilal",
    "wof:placetype":"locality"
},
  "geometry": {"coordinates":[43.91505,16.00871],"type":"Point"}
}