{
  "type": "Feature",
  "properties": {
    "gn:admin1_code":"14.0",
    "gn:admin2_code":"2606.0",
    "gn:asciiname":"Sarbat al Marakhat",
    "gn:country_code":"YE",
    "gn:dem":1537,
    "gn:feature_class":"P",
    "gn:feature_code":"PPL",
    "gn:name":"\u015earbat al Marakh\u0101t",
    "gn:population":0,
    "gn:timezone":"Asia/Aden",
    "iso:country":"YE",
    "name:ara_x_preferred":[
        "\u0635\u0631\u0628\u0629 \u0627\u0644\u0645\u0631\u062e\u0627\u062a"
    ],
    "name:und_x_variant":[
        "Sarbat al Marakh\u0101t",
        "\u015earbat al Marakh\u0101t"
    ],
    "wof:name":"Sarbat al Marakhat",
    "wof:placetype":"locality"
},
  "geometry": {"coordinates":[45.05864,15.48012],"type":"Point"}
}