{
  "type": "Feature",
  "properties": {
    "gn:admin1_code":"19.0",
    "gn:admin2_code":"2906.0",
    "gn:asciiname":"Kharab ash Sharafah",
    "gn:country_code":"YE",
    "gn:dem":1319,
    "gn:feature_class":"P",
    "gn:feature_code":"PPL",
    "gn:name":"Khar\u0101b ash Sharafah",
    "gn:population":0,
    "gn:timezone":"Asia/Aden",
    "iso:country":"YE",
    "name:ara_x_preferred":[
        "\u062e\u0631\u0627\u0628 \u0627\u0644\u0634\u0631\u0641\u0629"
    ],
    "name:und_x_variant":[
        "Khar\u0101b ash Shir\u0101fah",
        "Khar\u0101b ash Sharafah"
    ],
    "wof:name":"Kharab ash Sharafah",
    "wof:placetype":"locality"
},
  "geometry": {"coordinates":[43.61667,16.25726],"type":"Point"}
}