{
  "type": "Feature",
  "properties": {
    "gn:admin1_code":"22.0",
    "gn:admin2_code":"1726.0",
    "gn:asciiname":"Bayt as Salamah",
    "gn:country_code":"YE",
    "gn:dem":969,
    "gn:feature_class":"P",
    "gn:feature_code":"PPL",
    "gn:name":"Bayt as Sal\u0101mah",
    "gn:population":0,
    "gn:timezone":"Asia/Aden",
    "iso:country":"YE",
    "name:und_x_variant":[
        "Bayt as Sal\u0101mah"
    ],
    "wof:name":"Bayt as Salamah",
    "wof:placetype":"locality"
},
  "geometry": {"coordinates":[43.52868,15.64432],"type":"Point"}
}