{
  "type": "Feature",
  "properties": {
    "gn:country":"YE",
    "gn:fcode":"PPL",
    "gn:population":2,
    "iso:country":"YE",
    "name:ara_x_preferred":[
        "\u0627\u0644\u0645\u062e\u062a\u0628\u064a\u0629"
    ],
    "name:eng_x_preferred":[
        "Al Mukhtaybah"
    ],
    "name:eng_x_variant":[
        "Al Makhqah"
    ],
    "qs:name":"Al Mukhtaybah",
    "qs:photos_9r":0,
    "qs:photos_sr":0,
    "qs:pop_sr":"1",
    "wof:name":"Al Mukhtaybah",
    "wof:placetype":"locality",
    "wof:population":2
},
  "geometry": {"coordinates":[44.43728,16.77064],"type":"Point"}
}