{
  "type": "Feature",
  "properties": {
    "gn:admin1_code":"24.0",
    "gn:admin2_code":"2512.0",
    "gn:asciiname":"Az Zanah",
    "gn:country_code":"YE",
    "gn:dem":1015,
    "gn:feature_class":"P",
    "gn:feature_code":"PPL",
    "gn:name":"Az Zan\u0101\u1e29",
    "gn:population":0,
    "gn:timezone":"Asia/Aden",
    "iso:country":"YE",
    "name:ara_x_preferred":[
        "\u0627\u0644\u0632\u0646\u0627\u062d"
    ],
    "name:und_x_variant":[
        "Az Zan\u0101\u1e29"
    ],
    "wof:name":"Az Zanah",
    "wof:placetype":"locality"
},
  "geometry": {"coordinates":[44.12600000000001,13.11741],"type":"Point"}
}