{
  "type": "Feature",
  "properties": {
    "gn:admin1_code":"16.0",
    "gn:admin2_code":"2307.0",
    "gn:asciiname":"Bayt Shami",
    "gn:country_code":"YE",
    "gn:dem":2583,
    "gn:feature_class":"P",
    "gn:feature_code":"PPL",
    "gn:name":"Bayt Sh\u0101m\u012b",
    "gn:population":0,
    "gn:timezone":"Asia/Aden",
    "iso:country":"YE",
    "name:und_x_variant":[
        "Bayt Sh\u0101m\u012b"
    ],
    "wof:name":"Bayt Shami",
    "wof:placetype":"locality"
},
  "geometry": {"coordinates":[44.12435,15.19433],"type":"Point"}
}