{
  "type": "Feature",
  "properties": {
    "gn:admin1_code":"23.0",
    "gn:admin2_code":"1102.0",
    "gn:asciiname":"Al Kharbah",
    "gn:country_code":"YE",
    "gn:dem":1842,
    "gn:feature_class":"P",
    "gn:feature_code":"PPL",
    "gn:name":"Al Kharbah",
    "gn:population":0,
    "gn:timezone":"Asia/Aden",
    "iso:country":"YE",
    "wof:name":"Al Kharbah",
    "wof:placetype":"locality"
},
  "geometry": {"coordinates":[44.22388,14.15014],"type":"Point"}
}