{
  "type": "Feature",
  "properties": {
    "gn:admin1_code":"8.0",
    "gn:admin2_code":"1817.0",
    "gn:asciiname":"Al Kudayf",
    "gn:country_code":"YE",
    "gn:dem":117,
    "gn:feature_class":"P",
    "gn:feature_code":"PPL",
    "gn:name":"Al Kudayf",
    "gn:population":0,
    "gn:timezone":"Asia/Aden",
    "iso:country":"YE",
    "wof:name":"Al Kudayf",
    "wof:placetype":"locality"
},
  "geometry": {"coordinates":[43.31793,14.34076],"type":"Point"}
}