{
  "type": "Feature",
  "properties": {
    "gn:admin1_code":"15.0",
    "gn:admin2_code":"2214.0",
    "gn:asciiname":"Al Hadirah",
    "gn:country_code":"YE",
    "gn:dem":1568,
    "gn:feature_class":"P",
    "gn:feature_code":"PPL",
    "gn:name":"Al \u1e28a\u1e11\u012brah",
    "gn:population":0,
    "gn:timezone":"Asia/Aden",
    "iso:country":"YE",
    "name:ara_x_preferred":[
        "\u0627\u0644\u062d\u0638\u064a\u0631\u0629"
    ],
    "name:und_x_variant":[
        "Al \u1e28a\u1e11\u012brah",
        "Al \u1e28az\u0327\u012brah"
    ],
    "wof:name":"Al Hadirah",
    "wof:placetype":"locality"
},
  "geometry": {"coordinates":[44.17708,17.29285],"type":"Point"}
}