{
  "type": "Feature",
  "properties": {
    "gn:admin1_code":"18.0",
    "gn:admin2_code":"3005.0",
    "gn:asciiname":"Arhab",
    "gn:country_code":"YE",
    "gn:dem":1663,
    "gn:feature_class":"P",
    "gn:feature_code":"PPL",
    "gn:name":"Arhab",
    "gn:population":0,
    "gn:timezone":"Asia/Aden",
    "iso:country":"YE",
    "wof:name":"Arhab",
    "wof:placetype":"locality"
},
  "geometry": {"coordinates":[44.85,13.78333],"type":"Point"}
}