{
  "type": "Feature",
  "properties": {
    "gn:admin1_code":"5.0",
    "gn:admin2_code":"2113.0",
    "gn:asciiname":"Hashasah",
    "gn:country_code":"YE",
    "gn:dem":1266,
    "gn:feature_class":"P",
    "gn:feature_code":"PPL",
    "gn:name":"\u1e28as\u1e29asah",
    "gn:population":0,
    "gn:timezone":"Asia/Aden",
    "iso:country":"YE",
    "name:und_x_variant":[
        "\u1e28as\u1e29asah"
    ],
    "wof:name":"Hashasah",
    "wof:placetype":"locality"
},
  "geometry": {"coordinates":[46.94763,14.39762],"type":"Point"}
}