{
  "type": "Feature",
  "properties": {
    "gn:country":"YE",
    "gn:fcode":"PPL",
    "gn:pop":1,
    "iso:country":"YE",
    "name:ara_x_preferred":[
        "\u0627\u0644\u0645\u0643\u064a\u0645\u0646"
    ],
    "name:eng_x_preferred":[
        "Al Mukaymin"
    ],
    "qs:name":"Al Mukaymin",
    "qs:photos_9r":0,
    "qs:photos_sr":0,
    "qs:pop_sr":"1",
    "wof:name":"Al Mukaymin",
    "wof:placetype":"locality",
    "wof:population":1
},
  "geometry": {"coordinates":[43.98103,13.08863],"type":"Point"}
}