{
  "type": "Feature",
  "properties": {
    "gn:admin1_code":"20.0",
    "gn:asciiname":"Ghawl Allah",
    "gn:country_code":"YE",
    "gn:dem":2519,
    "gn:feature_class":"P",
    "gn:feature_code":"PPL",
    "gn:name":"Ghawl All\u0101h",
    "gn:population":0,
    "gn:timezone":"Asia/Aden",
    "iso:country":"YE",
    "name:ara_x_preferred":[
        "\u063a\u0648\u0644 \u0627\u0644\u0644\u0647"
    ],
    "name:und_x_variant":[
        "Ghawl All\u0101h"
    ],
    "wof:name":"Ghawl Allah",
    "wof:placetype":"locality"
},
  "geometry": {"coordinates":[44.42132,14.38765],"type":"Point"}
}