{
  "type": "Feature",
  "properties": {
    "gn:admin1_code":"20.0",
    "gn:admin2_code":"1414.0",
    "gn:asciiname":"Al Janbah",
    "gn:country_code":"YE",
    "gn:dem":2089,
    "gn:feature_class":"P",
    "gn:feature_code":"PPL",
    "gn:name":"Al Janbah",
    "gn:population":0,
    "gn:timezone":"Asia/Aden",
    "iso:country":"YE",
    "name:ara_x_preferred":[
        "\u0627\u0644\u062c\u0646\u0628\u0629"
    ],
    "name:und_x_variant":[
        "Al Junubah",
        "Al Janbah"
    ],
    "wof:name":"Al Janbah",
    "wof:placetype":"locality"
},
  "geometry": {"coordinates":[44.90969000000001,14.47957],"type":"Point"}
}