{
  "type": "Feature",
  "properties": {
    "gn:country":"YE",
    "gn:fcode":"PPLF",
    "gn:population":9,
    "iso:country":"YE",
    "name:ara_x_preferred":[
        "\u0100l Sh\u0101\u2018ib"
    ],
    "name:ara_x_variant":[
        "\u0622\u0644 \u0634\u0627\u0639\u0628"
    ],
    "qs:name":"\u0100l Sh\u0101\u2018ib",
    "qs:photos_9r":0,
    "qs:photos_sr":0,
    "qs:pop_sr":"1",
    "wof:name":"\u0100l Sh\u0101\u2018ib",
    "wof:placetype":"locality",
    "wof:population":9
},
  "geometry": {"coordinates":[43.74095,16.92569],"type":"Point"}
}