{
  "type": "Feature",
  "properties": {
    "gn:country":"YE",
    "gn:fcode":"PPL",
    "gn:pop":8,
    "iso:country":"YE",
    "name:ara_x_preferred":[
        "Bi\u2019r \u1e28ib\u0101n"
    ],
    "name:ara_x_variant":[
        "\u0628\u0626\u0631\u062d\u0628\u0627\u0646"
    ],
    "name:eng_x_preferred":[
        "Bir Hiban"
    ],
    "name:eng_x_variant":[
        "\u0100l Shayrabin"
    ],
    "qs:name":"Bi\u2019r \u1e28ib\u0101n",
    "qs:photos_9r":0,
    "qs:photos_sr":0,
    "qs:pop_sr":"1",
    "wof:name":"Bi\u2019r \u1e28ib\u0101n",
    "wof:placetype":"locality",
    "wof:population":8
},
  "geometry": {"coordinates":[44.50509,16.79572],"type":"Point"}
}