{
  "type": "Feature",
  "properties": {
    "gn:country":"YE",
    "gn:fcode":"PPL",
    "gn:population":5,
    "iso:country":"YE",
    "name:ara_x_preferred":[
        "\u0628\u064a\u062a \u0642\u064a\u0633"
    ],
    "name:eng_x_preferred":[
        "Bayt Qays"
    ],
    "name:eng_x_variant":[
        "Al Kawlah al \u2018Uly\u0101"
    ],
    "qs:name":"Bayt Qays",
    "qs:photos_9r":0,
    "qs:photos_sr":0,
    "qs:pop_sr":"1",
    "wof:name":"Bayt Qays",
    "wof:placetype":"locality",
    "wof:population":5
},
  "geometry": {"coordinates":[43.35852,16.08632],"type":"Point"}
}