{
  "type": "Feature",
  "properties": {
    "gn:admin1_code":"8.0",
    "gn:admin2_code":"1811.0",
    "gn:asciiname":"Sunfur",
    "gn:country_code":"YE",
    "gn:dem":616,
    "gn:feature_class":"P",
    "gn:feature_code":"PPL",
    "gn:name":"Sunfur",
    "gn:population":0,
    "gn:timezone":"Asia/Aden",
    "iso:country":"YE",
    "wof:name":"Sunfur",
    "wof:placetype":"locality"
},
  "geometry": {"coordinates":[43.61667,14.96667],"type":"Point"}
}