{
  "type": "Feature",
  "properties": {
    "gn:admin1_code":"24.0",
    "gn:admin2_code":"2512.0",
    "gn:asciiname":"Az Zira'",
    "gn:country_code":"YE",
    "gn:dem":756,
    "gn:feature_class":"P",
    "gn:feature_code":"PPL",
    "gn:name":"Az Zir\u0101\u2018",
    "gn:population":0,
    "gn:timezone":"Asia/Aden",
    "iso:country":"YE",
    "name:ara_x_preferred":[
        "\u0627\u0644\u0632\u0631\u0627\u0639"
    ],
    "name:und_x_variant":[
        "Az Zir\u0101\u2018"
    ],
    "wof:name":"Az Zira'",
    "wof:placetype":"locality"
},
  "geometry": {"coordinates":[44.17368,13.10878],"type":"Point"}
}