{
  "type": "Feature",
  "properties": {
    "gn:admin1_code":"8.0",
    "gn:admin2_code":"1825.0",
    "gn:asciiname":"Qaryat al Rurudi",
    "gn:country_code":"YE",
    "gn:dem":127,
    "gn:feature_class":"P",
    "gn:feature_code":"PPL",
    "gn:name":"Qaryat al Rur\u016bd\u012b",
    "gn:population":0,
    "gn:timezone":"Asia/Aden",
    "iso:country":"YE",
    "wof:name":"Qaryat al Rurudi",
    "wof:placetype":"locality"
},
  "geometry": {"coordinates":[43.40056,13.99889],"type":"Point"}
}