{
  "type": "Feature",
  "properties": {
    "gn:admin1_code":"23.0",
    "gn:admin2_code":"1111.0",
    "gn:asciiname":"Zuhrat Uthaj",
    "gn:country_code":"YE",
    "gn:dem":957,
    "gn:feature_class":"P",
    "gn:feature_code":"PPL",
    "gn:name":"Z\u0327uhrat Uthaj",
    "gn:population":0,
    "gn:timezone":"Asia/Aden",
    "iso:country":"YE",
    "name:und_x_variant":[
        "Z\u0327uhrat Uthaj"
    ],
    "wof:name":"Zuhrat Uthaj",
    "wof:placetype":"locality"
},
  "geometry": {"coordinates":[43.87866,14.02847],"type":"Point"}
}