{
  "type": "Feature",
  "properties": {
    "gn:gn_country":"YE",
    "gn:gn_fcode":"PPL",
    "gn:gn_pop":15,
    "gn:population":15,
    "iso:country":"YE",
    "name:ara_x_preferred":[
        "\u0628\u0646 \u0627\u0644\u062d\u0646\u0628\u064a"
    ],
    "name:eng_x_preferred":[
        "Bin Al Hanabi"
    ],
    "name:eng_x_variant":[
        "\u2018Awaq al \u2018Aq\u0101r"
    ],
    "qs_pg:aaroncc":"YE",
    "qs_pg:gn_country":"YE",
    "qs_pg:gn_fcode":"PPL",
    "qs_pg:gn_pop":15,
    "qs_pg:name":"Bin al \u1e28anab\u012b",
    "qs_pg:photos_9r":0,
    "qs_pg:photos_sr":0,
    "qs_pg:pop_sr":1,
    "qs_pg:qs_pg_placetype":"locality",
    "wof:name":"Bin al \u1e28anab\u012b",
    "wof:placetype":"locality",
    "wof:population":15
},
  "geometry": {"coordinates":[43.06615,16.00466],"type":"Point"}
}