{
  "type": "Feature",
  "properties": {
    "gn:admin1_code":"16.0",
    "gn:admin2_code":"2316.0",
    "gn:asciiname":"Bayt al Jabri",
    "gn:country_code":"YE",
    "gn:dem":2339,
    "gn:feature_class":"P",
    "gn:feature_code":"PPL",
    "gn:name":"Bayt al Jabr\u012b",
    "gn:population":0,
    "gn:timezone":"Asia/Aden",
    "iso:country":"YE",
    "name:und_x_variant":[
        "Bayt al Jabr\u012b"
    ],
    "wof:name":"Bayt al Jabri",
    "wof:placetype":"locality"
},
  "geometry": {"coordinates":[44.49799,15.28238],"type":"Point"}
}