{
  "type": "Feature",
  "properties": {
    "gn:admin1_code":"16.0",
    "gn:admin2_code":"2303.0",
    "gn:asciiname":"Bani Shukwan",
    "gn:country_code":"YE",
    "gn:dem":2090,
    "gn:feature_class":"P",
    "gn:feature_code":"PPL",
    "gn:name":"Ban\u012b Shukw\u0101n",
    "gn:population":0,
    "gn:timezone":"Asia/Aden",
    "iso:country":"YE",
    "name:und_x_variant":[
        "Ban\u012b Shukw\u0101n"
    ],
    "wof:name":"Bani Shukwan",
    "wof:placetype":"locality"
},
  "geometry": {"coordinates":[44.46979,15.68697],"type":"Point"}
}