{
  "type": "Feature",
  "properties": {
    "gn:country":"YE",
    "gn:fcode":"PPL",
    "gn:pop":1,
    "iso:country":"YE",
    "name:ara_x_preferred":[
        "Ulif\u0101\u2019"
    ],
    "name:ara_x_variant":[
        "\u0639\u0644\u0641\u0627\u0621"
    ],
    "name:eng_x_preferred":[
        "Ulifa"
    ],
    "qs:name":"Ulif\u0101\u2019",
    "qs:photos_9r":0,
    "qs:photos_sr":0,
    "qs:pop_sr":"1",
    "wof:name":"Ulif\u0101\u2019",
    "wof:placetype":"locality",
    "wof:population":1
},
  "geometry": {"coordinates":[45.23693,14.96245],"type":"Point"}
}