{
  "type": "Feature",
  "properties": {
    "gn:admin1_code":"10.0",
    "gn:admin2_code":"2702.0",
    "gn:asciiname":"Al Hajar",
    "gn:country_code":"YE",
    "gn:dem":2677,
    "gn:feature_class":"P",
    "gn:feature_code":"PPL",
    "gn:name":"Al \u1e28ajar",
    "gn:population":0,
    "gn:timezone":"Asia/Aden",
    "iso:country":"YE",
    "name:und_x_variant":[
        "Al \u1e28ajar"
    ],
    "wof:name":"Al Hajar",
    "wof:placetype":"locality"
},
  "geometry": {"coordinates":[43.78354,15.47133],"type":"Point"}
}