{
  "type": "Feature",
  "properties": {
    "gn:gn_country":"YE",
    "gn:gn_fcode":"PPL",
    "gn:gn_pop":28,
    "gn:population":28,
    "iso:country":"YE",
    "name:ara_x_preferred":[
        "Dh\u012b \u2018Akbir\u0101n"
    ],
    "name:ara_x_variant":[
        "\u0630\u064a \u0639\u0643\u0628\u0631\u0627\u0646"
    ],
    "name:eng_x_preferred":[
        "Dhi 'Akbiran"
    ],
    "name:eng_x_variant":[
        "Ar R\u0101qib\u012byah"
    ],
    "qs_pg:aaroncc":"YE",
    "qs_pg:gn_country":"YE",
    "qs_pg:gn_fcode":"PPL",
    "qs_pg:gn_pop":28,
    "qs_pg:name":"Dh\u012b \u2018Akbir\u0101n",
    "qs_pg:photos_9r":0,
    "qs_pg:photos_sr":0,
    "qs_pg:pop_sr":1,
    "qs_pg:qs_pg_placetype":"locality",
    "wof:name":"Dh\u012b \u2018Akbir\u0101n",
    "wof:placetype":"locality",
    "wof:population":28
},
  "geometry": {"coordinates":[43.66449,16.95131],"type":"Point"}
}