{
  "type": "Feature",
  "properties": {
    "gn:admin1_code":"8.0",
    "gn:admin2_code":"1806.0",
    "gn:asciiname":"An Najjari",
    "gn:country_code":"YE",
    "gn:dem":75,
    "gn:feature_class":"P",
    "gn:feature_code":"PPL",
    "gn:name":"An Najj\u0101r\u012b",
    "gn:population":0,
    "gn:timezone":"Asia/Aden",
    "iso:country":"YE",
    "name:und_x_variant":[
        "Dayr Nagari",
        "An Najj\u0101r\u012b"
    ],
    "wof:name":"An Najjari",
    "wof:placetype":"locality"
},
  "geometry": {"coordinates":[43.08271,15.47244],"type":"Point"}
}