{
  "type": "Feature",
  "properties": {
    "gn:admin1_code":"23.0",
    "gn:admin2_code":"1113.0",
    "gn:asciiname":"Ribat al Qusaymi",
    "gn:country_code":"YE",
    "gn:dem":2139,
    "gn:feature_class":"P",
    "gn:feature_code":"PPL",
    "gn:name":"Rib\u0101\u0163 al Qu\u015faym\u012b",
    "gn:population":0,
    "gn:timezone":"Asia/Aden",
    "iso:country":"YE",
    "name:und_x_variant":[
        "Rib\u0101\u0163 al Qu\u015faym\u012b"
    ],
    "wof:name":"Ribat al Qusaymi",
    "wof:placetype":"locality"
},
  "geometry": {"coordinates":[44.30049,13.98887],"type":"Point"}
}