{
  "type": "Feature",
  "properties": {
    "gn:admin1_code":"23.0",
    "gn:admin2_code":"1117.0",
    "gn:asciiname":"Sharaf Himyar",
    "gn:country_code":"YE",
    "gn:dem":2174,
    "gn:feature_class":"P",
    "gn:feature_code":"PPL",
    "gn:name":"Sharaf \u1e28imyar",
    "gn:population":0,
    "gn:timezone":"Asia/Aden",
    "iso:country":"YE",
    "name:und_x_variant":[
        "Sharaf \u1e28imyar"
    ],
    "wof:name":"Sharaf Himyar",
    "wof:placetype":"locality"
},
  "geometry": {"coordinates":[43.97202,13.8464],"type":"Point"}
}