{
  "type": "Feature",
  "properties": {
    "gn:admin1_code":"16.0",
    "gn:admin2_code":"2301.0",
    "gn:asciiname":"Zahrat al Hadrami",
    "gn:country_code":"YE",
    "gn:dem":2633,
    "gn:feature_class":"P",
    "gn:feature_code":"PPL",
    "gn:name":"Z\u0327ahrat al \u1e28a\u1e11ram\u012b",
    "gn:population":0,
    "gn:timezone":"Asia/Aden",
    "iso:country":"YE",
    "name:ara_x_preferred":[
        "\u0638\u0647\u0631\u0629 \u0627\u0644\u062d\u0636\u0631\u0645\u064a"
    ],
    "name:und_x_variant":[
        "Z\u0327ahrat al \u1e28a\u1e11ram\u012b"
    ],
    "wof:name":"Zahrat al Hadrami",
    "wof:placetype":"locality"
},
  "geometry": {"coordinates":[44.0435,15.52579],"type":"Point"}
}