{
  "type": "Feature",
  "properties": {
    "gn:admin1_code":"8.0",
    "gn:admin2_code":"1806.0",
    "gn:asciiname":"Dayr al Hulayl",
    "gn:country_code":"YE",
    "gn:dem":105,
    "gn:feature_class":"P",
    "gn:feature_code":"PPL",
    "gn:name":"Dayr al \u1e28ulayl",
    "gn:population":0,
    "gn:timezone":"Asia/Aden",
    "iso:country":"YE",
    "wof:name":"Dayr al Hulayl",
    "wof:placetype":"locality"
},
  "geometry": {"coordinates":[43.16667,15.45],"type":"Point"}
}