{
  "type": "Feature",
  "properties": {
    "gn:admin1_code":"14.0",
    "gn:admin2_code":"2602.0",
    "gn:asciiname":"'Adwan",
    "gn:country_code":"YE",
    "gn:dem":1096,
    "gn:feature_class":"P",
    "gn:feature_code":"PPL",
    "gn:name":"\u2018Adw\u0101n",
    "gn:population":0,
    "gn:timezone":"Asia/Aden",
    "iso:country":"YE",
    "name:ara_x_preferred":[
        "\u0639\u062f\u0648\u0627\u0646"
    ],
    "name:und_x_variant":[
        "\u2018Adw\u0101n"
    ],
    "wof:name":"'Adwan",
    "wof:placetype":"locality"
},
  "geometry": {"coordinates":[45.08711,15.79915],"type":"Point"}
}