{
  "type": "Feature",
  "properties": {
    "gn:admin1_code":"14.0",
    "gn:admin2_code":"2610.0",
    "gn:asciiname":"Jumaylah",
    "gn:country_code":"YE",
    "gn:dem":1719,
    "gn:feature_class":"P",
    "gn:feature_code":"PPL",
    "gn:name":"Jumaylah",
    "gn:population":0,
    "gn:timezone":"Asia/Aden",
    "iso:country":"YE",
    "name:ara_x_preferred":[
        "\u062c\u0645\u064a\u0644\u0629"
    ],
    "wof:name":"Jumaylah",
    "wof:placetype":"locality"
},
  "geometry": {"coordinates":[45.17934,14.68442],"type":"Point"}
}