{
  "type": "Feature",
  "properties": {
    "gn:admin1_code":"26.0",
    "gn:admin2_code":"1310.0",
    "gn:asciiname":"Al Batat",
    "gn:country_code":"YE",
    "gn:dem":2157,
    "gn:feature_class":"P",
    "gn:feature_code":"PPL",
    "gn:name":"Al Bat\u0101t",
    "gn:population":0,
    "gn:timezone":"Asia/Aden",
    "iso:country":"YE",
    "name:ara_x_preferred":[
        "\u0627\u0644\u0628\u062a\u0627\u062a"
    ],
    "name:und_x_variant":[
        "Bayt al Bat\u0101t",
        "Al Bat\u0101t"
    ],
    "wof:name":"Al Batat",
    "wof:placetype":"locality"
},
  "geometry": {"coordinates":[44.24505,15.56855],"type":"Point"}
}