{
  "type": "Feature",
  "properties": {
    "gn:admin1_code":"23.0",
    "gn:admin2_code":"1111.0",
    "gn:asciiname":"Wa`il",
    "gn:country_code":"YE",
    "gn:dem":1204,
    "gn:feature_class":"P",
    "gn:feature_code":"PPL",
    "gn:name":"Wa\u2018il",
    "gn:population":0,
    "gn:timezone":"Asia/Aden",
    "iso:country":"YE",
    "name:und_x_variant":[
        "Wa\u2018il"
    ],
    "wof:name":"Wa`il",
    "wof:placetype":"locality"
},
  "geometry": {"coordinates":[43.99676,13.9494],"type":"Point"}
}