{
  "type": "Feature",
  "properties": {
    "gn:admin1_code":"23.0",
    "gn:admin2_code":"1101.0",
    "gn:asciiname":"Al Jurbah",
    "gn:country_code":"YE",
    "gn:dem":2291,
    "gn:feature_class":"P",
    "gn:feature_code":"PPL",
    "gn:name":"Al Jurbah",
    "gn:population":0,
    "gn:timezone":"Asia/Aden",
    "iso:country":"YE",
    "name:ara_x_preferred":[
        "\u0627\u0644\u062c\u0631\u0628\u0629"
    ],
    "wof:name":"Al Jurbah",
    "wof:placetype":"locality"
},
  "geometry": {"coordinates":[44.21023,14.26577],"type":"Point"}
}