{
  "type": "Feature",
  "properties": {
    "gn:admin1_code":"11.0",
    "gn:admin2_code":"2003.0",
    "gn:asciiname":"Shabin",
    "gn:country_code":"YE",
    "gn:dem":2214,
    "gn:feature_class":"P",
    "gn:feature_code":"PPL",
    "gn:name":"Sh\u0101bin",
    "gn:population":0,
    "gn:timezone":"Asia/Aden",
    "iso:country":"YE",
    "name:ara_x_preferred":[
        "Sh\u0101bin"
    ],
    "wof:name":"Shabin",
    "wof:placetype":"locality"
},
  "geometry": {"coordinates":[44.00449,14.69102],"type":"Point"}
}