{
  "type": "Feature",
  "properties": {
    "gn:admin1_code":"19.0",
    "gn:admin2_code":"2919.0",
    "gn:asciiname":"Qa'at A'la'",
    "gn:country_code":"YE",
    "gn:dem":2152,
    "gn:feature_class":"P",
    "gn:feature_code":"PPL",
    "gn:name":"Q\u0101\u2018at A\u2018l\u0101\u2019",
    "gn:population":0,
    "gn:timezone":"Asia/Aden",
    "iso:country":"YE",
    "name:ara_x_preferred":[
        "\u0642\u0627\u0639\u0629 \u0623\u0639\u0644\u0627\u0621"
    ],
    "name:und_x_variant":[
        "Q\u0101\u2018at A\u2018l\u0101\u2019"
    ],
    "wof:name":"Qa'at A'la'",
    "wof:placetype":"locality"
},
  "geometry": {"coordinates":[43.94334,16.06311],"type":"Point"}
}