{
  "type": "Feature",
  "properties": {
    "gn:admin1_code":"25.0",
    "gn:admin2_code":"1517.0",
    "gn:asciiname":"Al Ma'barayn",
    "gn:country_code":"YE",
    "gn:dem":1535,
    "gn:feature_class":"P",
    "gn:feature_code":"PPL",
    "gn:name":"Al Ma\u2018barayn",
    "gn:population":0,
    "gn:timezone":"Asia/Aden",
    "iso:country":"YE",
    "name:ara_x_preferred":[
        "\u0627\u0644\u0645\u0639\u0628\u0631\u064a\u0646"
    ],
    "name:und_x_variant":[
        "Al Ma\u2018barayn"
    ],
    "wof:name":"Al Ma'barayn",
    "wof:placetype":"locality"
},
  "geometry": {"coordinates":[44.19714000000001,13.22223],"type":"Point"}
}