{
  "type": "Feature",
  "properties": {
    "gn:admin1_code":"23.0",
    "gn:admin2_code":"1120.0",
    "gn:asciiname":"Al Manzar",
    "gn:country_code":"YE",
    "gn:dem":2304,
    "gn:feature_class":"P",
    "gn:feature_code":"PPL",
    "gn:name":"Al Manz\u0327ar",
    "gn:population":0,
    "gn:timezone":"Asia/Aden",
    "iso:country":"YE",
    "name:ara_x_preferred":[
        "\u0627\u0644\u0645\u0646\u0638\u0631"
    ],
    "name:und_x_variant":[
        "Al Manz\u0327ar"
    ],
    "wof:name":"Al Manzar",
    "wof:placetype":"locality"
},
  "geometry": {"coordinates":[44.11999,14.04218],"type":"Point"}
}