{
  "type": "Feature",
  "properties": {
    "gn:admin1_code":"19.0",
    "gn:admin2_code":"2920.0",
    "gn:asciiname":"Bayt Mas'ad",
    "gn:country_code":"YE",
    "gn:dem":2246,
    "gn:feature_class":"P",
    "gn:feature_code":"PPL",
    "gn:name":"Bayt Mas\u2018ad",
    "gn:population":0,
    "gn:timezone":"Asia/Aden",
    "iso:country":"YE",
    "name:ara_x_preferred":[
        "\u0628\u064a\u062a \u0645\u0633\u0639\u062f"
    ],
    "name:und_x_variant":[
        "Bayt Mas\u2018ad"
    ],
    "wof:name":"Bayt Mas'ad",
    "wof:placetype":"locality"
},
  "geometry": {"coordinates":[43.96551,16.15235],"type":"Point"}
}