{
  "type": "Feature",
  "properties": {
    "gn:admin1_code":"20.0",
    "gn:admin2_code":"1404.0",
    "gn:asciiname":"Al Maqsurah",
    "gn:country_code":"YE",
    "gn:dem":1990,
    "gn:feature_class":"P",
    "gn:feature_code":"PPL",
    "gn:name":"Al Maq\u015f\u016brah",
    "gn:population":0,
    "gn:timezone":"Asia/Aden",
    "iso:country":"YE",
    "name:und_x_variant":[
        "Al Maq\u015f\u016brah"
    ],
    "wof:name":"Al Maqsurah",
    "wof:placetype":"locality"
},
  "geometry": {"coordinates":[45.67768,14.07161],"type":"Point"}
}