{
  "type": "Feature",
  "properties": {
    "gn:admin1_code":"19.0",
    "gn:admin2_code":"2903.0",
    "gn:asciiname":"Al Khawr",
    "gn:country_code":"YE",
    "gn:dem":1735,
    "gn:feature_class":"P",
    "gn:feature_code":"PPL",
    "gn:name":"Al Khawr",
    "gn:population":0,
    "gn:timezone":"Asia/Aden",
    "iso:country":"YE",
    "name:ara_x_preferred":[
        "\u0627\u0644\u062e\u0648\u0631"
    ],
    "name:ara_x_variant":[
        "\u062e\u0648\u0631"
    ],
    "name:nld_x_preferred":[
        "Al Khawr"
    ],
    "wof:name":"Al Khawr",
    "wof:placetype":"locality"
},
  "geometry": {"coordinates":[43.89276,16.40846],"type":"Point"}
}