{
  "type": "Feature",
  "properties": {
    "gn:admin1_code":"8.0",
    "gn:admin2_code":"1801.0",
    "gn:asciiname":"Bayt Ma'ruf 'Ali",
    "gn:country_code":"YE",
    "gn:dem":45,
    "gn:feature_class":"P",
    "gn:feature_code":"PPL",
    "gn:name":"Bayt Ma\u2018r\u016bf \u2018Al\u012b",
    "gn:population":0,
    "gn:timezone":"Asia/Aden",
    "iso:country":"YE",
    "name:ara_x_preferred":[
        "\u0628\u064a\u062a \u0645\u0639\u0631\u0648\u0641 \u0639\u0644\u064a"
    ],
    "name:und_x_variant":[
        "Bayt Ma\u2018r\u016bf \u2018Al\u012b"
    ],
    "wof:name":"Bayt Ma'ruf 'Ali",
    "wof:placetype":"locality"
},
  "geometry": {"coordinates":[42.93053,15.74551],"type":"Point"}
}