{
  "type": "Feature",
  "properties": {
    "gn:admin1_code":"22.0",
    "gn:admin2_code":"1712.0",
    "gn:asciiname":"As Sakit",
    "gn:country_code":"YE",
    "gn:dem":373,
    "gn:feature_class":"P",
    "gn:feature_code":"PPL",
    "gn:name":"As S\u0101kit",
    "gn:population":0,
    "gn:timezone":"Asia/Aden",
    "iso:country":"YE",
    "name:ara_x_preferred":[
        "As S\u0101kit"
    ],
    "wof:name":"As Sakit",
    "wof:placetype":"locality"
},
  "geometry": {"coordinates":[43.34298,15.97648],"type":"Point"}
}