{
  "type": "Feature",
  "properties": {
    "gn:admin1_code":"11.0",
    "gn:admin2_code":"2010.0",
    "gn:asciiname":"Dar al `Ushaw",
    "gn:country_code":"YE",
    "gn:dem":2281,
    "gn:feature_class":"P",
    "gn:feature_code":"PPL",
    "gn:name":"D\u0101r al \u2018Ushaw",
    "gn:population":0,
    "gn:timezone":"Asia/Aden",
    "iso:country":"YE",
    "name:und_x_variant":[
        "D\u0101r al \u2018Ushaw"
    ],
    "wof:name":"Dar al `Ushaw",
    "wof:placetype":"locality"
},
  "geometry": {"coordinates":[44.32827,14.4352],"type":"Point"}
}