{
  "type": "Feature",
  "properties": {
    "gn:admin1_code":"23.0",
    "gn:admin2_code":"1101.0",
    "gn:asciiname":"Sha'b Zayd",
    "gn:country_code":"YE",
    "gn:dem":1324,
    "gn:feature_class":"P",
    "gn:feature_code":"PPL",
    "gn:name":"Sha\u2018b Zayd",
    "gn:population":0,
    "gn:timezone":"Asia/Aden",
    "iso:country":"YE",
    "name:ara_x_preferred":[
        "\u0634\u0639\u0628 \u0632\u064a\u062f"
    ],
    "name:und_x_variant":[
        "Sha\u2018b Zayd"
    ],
    "wof:name":"Sha'b Zayd",
    "wof:placetype":"locality"
},
  "geometry": {"coordinates":[44.09764000000001,14.36288],"type":"Point"}
}