{
  "type": "Feature",
  "properties": {
    "gn:admin1_code":"16.0",
    "gn:admin2_code":"2310.0",
    "gn:asciiname":"Bayt al Mud`i",
    "gn:country_code":"YE",
    "gn:dem":1967,
    "gn:feature_class":"P",
    "gn:feature_code":"PPL",
    "gn:name":"Bayt al Mud\u2018\u012b",
    "gn:population":0,
    "gn:timezone":"Asia/Aden",
    "iso:country":"YE",
    "name:nno_x_preferred":[
        "Bayt al-Mud`I"
    ],
    "name:und_x_variant":[
        "Bayt al Mud\u2018\u012b"
    ],
    "wof:name":"Bayt al Mud`i",
    "wof:placetype":"locality"
},
  "geometry": {"coordinates":[43.74221,15.11236],"type":"Point"}
}