{
  "type": "Feature",
  "properties": {
    "gn:admin1_code":"4.0",
    "gn:admin2_code":"1912.0",
    "gn:asciiname":"Qabr Hud",
    "gn:cc2":"YE",
    "gn:country_code":"YE",
    "gn:dem":701,
    "gn:feature_class":"P",
    "gn:feature_code":"PPL",
    "gn:name":"Qabr H\u016bd",
    "gn:population":0,
    "gn:timezone":"Asia/Aden",
    "iso:country":"YE",
    "name:und_x_variant":[
        "Quabr H\u016bd",
        "Qabr Nab\u012b All\u0101h H\u016bd",
        "Qabr H\u016bd"
    ],
    "wof:name":"Qabr Hud",
    "wof:placetype":"locality"
},
  "geometry": {"coordinates":[49.56667,16.15],"type":"Point"}
}