{
  "type": "Feature",
  "properties": {
    "gn:admin1_code":"10.0",
    "gn:admin2_code":"2702.0",
    "gn:asciiname":"Bayt Man`ayn",
    "gn:country_code":"YE",
    "gn:dem":2860,
    "gn:feature_class":"P",
    "gn:feature_code":"PPL",
    "gn:name":"Bayt Man\u2018ayn",
    "gn:population":0,
    "gn:timezone":"Asia/Aden",
    "iso:country":"YE",
    "name:und_x_variant":[
        "Bayt Man\u2018ayn"
    ],
    "wof:name":"Bayt Man`ayn",
    "wof:placetype":"locality"
},
  "geometry": {"coordinates":[43.79326,15.54979],"type":"Point"}
}