{
  "type": "Feature",
  "properties": {
    "gn:admin1_code":"10.0",
    "gn:admin2_code":"2703.0",
    "gn:asciiname":"Zawikhah",
    "gn:country_code":"YE",
    "gn:dem":1942,
    "gn:feature_class":"P",
    "gn:feature_code":"PPL",
    "gn:name":"Z\u0101wikhah",
    "gn:population":0,
    "gn:timezone":"Asia/Aden",
    "iso:country":"YE",
    "name:und_x_variant":[
        "Z\u0101wikhah"
    ],
    "wof:name":"Zawikhah",
    "wof:placetype":"locality"
},
  "geometry": {"coordinates":[43.67538,15.44144],"type":"Point"}
}