{
  "type": "Feature",
  "properties": {
    "gn:admin1_code":"15.0",
    "gn:admin2_code":"2208.0",
    "gn:asciiname":"Al Ghari",
    "gn:country_code":"YE",
    "gn:dem":2202,
    "gn:feature_class":"P",
    "gn:feature_code":"PPL",
    "gn:name":"Al Gh\u0101r\u012b",
    "gn:population":0,
    "gn:timezone":"Asia/Aden",
    "iso:country":"YE",
    "name:ara_x_preferred":[
        "Al Gh\u0101r\u012b"
    ],
    "name:ara_x_variant":[
        "\u0627\u0644\u063a\u0627\u0631\u064a"
    ],
    "wof:name":"Al Ghari",
    "wof:placetype":"locality"
},
  "geometry": {"coordinates":[43.41911,16.79014],"type":"Point"}
}