{
  "type": "Feature",
  "properties": {
    "gn:admin1_code":"18.0",
    "gn:admin2_code":"3001.0",
    "gn:asciiname":"Ar Raza'im",
    "gn:country_code":"YE",
    "gn:dem":2058,
    "gn:feature_class":"P",
    "gn:feature_code":"PPL",
    "gn:name":"Ar Raz\u0101\u2019im",
    "gn:population":0,
    "gn:timezone":"Asia/Aden",
    "iso:country":"YE",
    "name:und_x_variant":[
        "Razaim",
        "Ar Raz\u0101\u2019im",
        "Ruzaym"
    ],
    "wof:name":"Ar Raza'im",
    "wof:placetype":"locality"
},
  "geometry": {"coordinates":[44.8668,13.97062],"type":"Point"}
}