{
  "type": "Feature",
  "properties": {
    "gn:admin1_code":"25.0",
    "gn:admin2_code":"1509.0",
    "gn:asciiname":"Al Ahjaf",
    "gn:country_code":"YE",
    "gn:dem":1158,
    "gn:feature_class":"P",
    "gn:feature_code":"PPL",
    "gn:name":"Al A\u1e29j\u0101f",
    "gn:population":0,
    "gn:timezone":"Asia/Aden",
    "iso:country":"YE",
    "name:ara_x_preferred":[
        "Al A\u1e29j\u0101f"
    ],
    "name:ara_x_variant":[
        "\u0627\u0644\u0623\u062d\u062c\u0627\u0641"
    ],
    "wof:name":"Al Ahjaf",
    "wof:placetype":"locality"
},
  "geometry": {"coordinates":[43.93696,13.55314],"type":"Point"}
}