{
  "type": "Feature",
  "properties": {
    "gn:admin1_code":"22.0",
    "gn:admin2_code":"1705.0",
    "gn:asciiname":"Al Faranitah",
    "gn:country_code":"YE",
    "gn:dem":116,
    "gn:feature_class":"P",
    "gn:feature_code":"PPL",
    "gn:name":"Al Far\u0101nitah",
    "gn:population":0,
    "gn:timezone":"Asia/Aden",
    "iso:country":"YE",
    "name:und_x_variant":[
        "Al Far\u0101nitah",
        "\u1e28ayr\u0101n"
    ],
    "wof:name":"Al Faranitah",
    "wof:placetype":"locality"
},
  "geometry": {"coordinates":[43.1099,16.2717],"type":"Point"}
}