{
  "type": "Feature",
  "properties": {
    "gn:country":"YE",
    "gn:fcode":"PPL",
    "gn:pop":20,
    "iso:country":"YE",
    "name:ara_x_preferred":[
        "\u0634\u0627\u0637\u0626 \u0627\u0644\u062c\u0631\u064a\u062f\u0627\u0621"
    ],
    "name:eng_x_preferred":[
        "Shati Al Jurayda"
    ],
    "qs:name":"Sh\u0101\u0163i\u2019 al Jurayd\u0101\u2019",
    "qs:photos_9r":0,
    "qs:photos_sr":0,
    "qs:pop_sr":"1",
    "wof:name":"Sh\u0101\u0163i\u2019 al Jurayd\u0101\u2019",
    "wof:placetype":"locality",
    "wof:population":20
},
  "geometry": {"coordinates":[43.56216,16.49572],"type":"Point"}
}