{
  "type": "Feature",
  "properties": {
    "gn:admin1_code":"27.0",
    "gn:admin2_code":"3103.0",
    "gn:asciiname":"Al `Ubr",
    "gn:country_code":"YE",
    "gn:dem":2066,
    "gn:feature_class":"P",
    "gn:feature_code":"PPL",
    "gn:name":"Al \u2018Ubr",
    "gn:population":0,
    "gn:timezone":"Asia/Aden",
    "iso:country":"YE",
    "name:ara_x_preferred":[
        "Al \u2018Ubr"
    ],
    "wof:name":"Al `Ubr",
    "wof:placetype":"locality"
},
  "geometry": {"coordinates":[43.86017,14.62402],"type":"Point"}
}