{
  "type": "Feature",
  "properties": {
    "gn:admin1_code":"22.0",
    "gn:admin2_code":"1707.0",
    "gn:asciiname":"Al `Ashamiyah",
    "gn:country_code":"YE",
    "gn:dem":1453,
    "gn:feature_class":"P",
    "gn:feature_code":"PPL",
    "gn:name":"Al \u2018Ash\u0101m\u012byah",
    "gn:population":0,
    "gn:timezone":"Asia/Aden",
    "iso:country":"YE",
    "name:und_x_variant":[
        "Al \u2018Ash\u0101m\u012byah"
    ],
    "wof:name":"Al `Ashamiyah",
    "wof:placetype":"locality"
},
  "geometry": {"coordinates":[43.45904,16.19621],"type":"Point"}
}