{
  "type": "Feature",
  "properties": {
    "gn:admin1_code":"1.0",
    "gn:admin2_code":"1211.0",
    "gn:asciiname":"Tiran",
    "gn:cc2":"YE",
    "gn:country_code":"YE",
    "gn:dem":52,
    "gn:feature_class":"P",
    "gn:feature_code":"PPL",
    "gn:name":"T\u012br\u0101n",
    "gn:population":0,
    "gn:timezone":"Asia/Aden",
    "iso:country":"YE",
    "name:ara_x_preferred":[
        "T\u012br\u0101n"
    ],
    "name:ceb_x_preferred":[
        "Tiran"
    ],
    "name:deu_x_preferred":[
        "Tiran"
    ],
    "name:fra_x_preferred":[
        "Tiran"
    ],
    "name:heb_x_preferred":[
        "\u05d8\u05d9\u05e8\u05df"
    ],
    "name:jpn_x_preferred":[
        "\u30c1\u30e9\u30f3"
    ],
    "name:nld_x_preferred":[
        "Tiran"
    ],
    "name:pol_x_preferred":[
        "Tiran"
    ],
    "name:rus_x_preferred":[
        "\u0422\u0438\u0440\u0430\u043d\u0430"
    ],
    "name:slv_x_preferred":[
        "Tiran"
    ],
    "name:swe_x_preferred":[
        "Tiran"
    ],
    "name:tur_x_preferred":[
        "Tiran"
    ],
    "name:ukr_x_preferred":[
        "\u0422\u0438\u0440\u0430\u043d\u0430"
    ],
    "name:und_x_variant":[
        "Teram"
    ],
    "name:vep_x_preferred":[
        "Tiran"
    ],
    "wof:name":"Tiran",
    "wof:placetype":"locality"
},
  "geometry": {"coordinates":[45.365,13.22056],"type":"Point"}
}