{
  "type": "Feature",
  "properties": {
    "gn:admin1_code":"1.0",
    "gn:admin2_code":"1211.0",
    "gn:asciiname":"Tiran",
    "gn:cc2":"YE",
    "gn:country_code":"YE",
    "gn:dem":52,
    "gn:feature_class":"P",
    "gn:feature_code":"PPL",
    "gn:name":"T\u012br\u0101n",
    "gn:population":0,
    "gn:timezone":"Asia/Aden",
    "iso:country":"YE",
    "name:ara_x_preferred":[
        "T\u012br\u0101n"
    ],
    "name:und_x_variant":[
        "Teram"
    ],
    "wof:name":"Tiran",
    "wof:placetype":"locality"
},
  "geometry": {"coordinates":[45.365,13.22056],"type":"Point"}
}