{
  "type": "Feature",
  "properties": {
    "gn:admin1_code":"23.0",
    "gn:admin2_code":"1112.0",
    "gn:asciiname":"Ad Duhrah",
    "gn:country_code":"YE",
    "gn:dem":2372,
    "gn:feature_class":"P",
    "gn:feature_code":"PPL",
    "gn:name":"A\u1e11 \u1e10uhrah",
    "gn:population":0,
    "gn:timezone":"Asia/Aden",
    "iso:country":"YE",
    "name:und_x_variant":[
        "A\u1e11 \u1e10uhrah"
    ],
    "wof:name":"Ad Duhrah",
    "wof:placetype":"locality"
},
  "geometry": {"coordinates":[44.11108,13.96332],"type":"Point"}
}