{
  "type": "Feature",
  "properties": {
    "gn:admin1_code":"15.0",
    "gn:admin2_code":"2209.0",
    "gn:asciiname":"Qabtanat Fadil",
    "gn:country_code":"YE",
    "gn:dem":2413,
    "gn:feature_class":"P",
    "gn:feature_code":"PPL",
    "gn:name":"Qab\u0163an\u0101t F\u0101\u1e11il",
    "gn:population":0,
    "gn:timezone":"Asia/Aden",
    "iso:country":"YE",
    "name:ara_x_preferred":[
        "\u0642\u0628\u0637\u0646\u0627\u062a \u0641\u0627\u0636\u0644"
    ],
    "name:und_x_variant":[
        "Qu\u0163ayn\u0101t F\u0101\u1e11il",
        "Qab\u0163an\u0101t F\u0101\u1e11il"
    ],
    "wof:name":"Qabtanat Fadil",
    "wof:placetype":"locality"
},
  "geometry": {"coordinates":[43.48831,16.82203],"type":"Point"}
}