{
  "type": "Feature",
  "properties": {
    "gn:admin1_code":"10.0",
    "gn:admin2_code":"2704.0",
    "gn:asciiname":"Mahall ash Sha`afil",
    "gn:country_code":"YE",
    "gn:dem":305,
    "gn:feature_class":"P",
    "gn:feature_code":"PPL",
    "gn:name":"Ma\u1e29all ash Sha\u2018\u0101fil",
    "gn:population":0,
    "gn:timezone":"Asia/Aden",
    "iso:country":"YE",
    "name:und_x_variant":[
        "Ma\u1e29all ash Sha\u2018\u0101fil"
    ],
    "wof:name":"Mahall ash Sha`afil",
    "wof:placetype":"locality"
},
  "geometry": {"coordinates":[43.29256,15.45419],"type":"Point"}
}