{
  "type": "Feature",
  "properties": {
    "gn:country":"YE",
    "gn:fcode":"PPL",
    "gn:pop":9,
    "iso:country":"YE",
    "name:ara_x_preferred":[
        "\u0633\u0648\u062f\u0629"
    ],
    "name:eng_x_preferred":[
        "SUdah"
    ],
    "qs:name":"S\u016bdah",
    "qs:photos_9r":0,
    "qs:photos_sr":0,
    "qs:pop_sr":"1",
    "wd:wordcount":55,
    "wof:name":"S\u016bdah",
    "wof:placetype":"locality",
    "wof:population":9
},
  "geometry": {"coordinates":[45.2013,14.31278],"type":"Point"}
}