{
  "type": "Feature",
  "properties": {
    "gn:admin1_code":"11.0",
    "gn:admin2_code":"1102.0",
    "gn:asciiname":"Maj`ah",
    "gn:country_code":"YE",
    "gn:dem":2059,
    "gn:feature_class":"P",
    "gn:feature_code":"PPL",
    "gn:name":"Maj\u2018ah",
    "gn:population":0,
    "gn:timezone":"Asia/Aden",
    "iso:country":"YE",
    "name:ara_x_preferred":[
        "\u0645\u062c\u0639\u0629"
    ],
    "name:und_x_variant":[
        "Maj\u2018ah",
        "Maja\u2018ah"
    ],
    "wof:name":"Maj`ah",
    "wof:placetype":"locality"
},
  "geometry": {"coordinates":[44.28096,14.3811],"type":"Point"}
}