{
  "type": "Feature",
  "properties": {
    "gn:admin1_code":"18.0",
    "gn:admin2_code":"3006.0",
    "gn:asciiname":"Kawkabah",
    "gn:country_code":"YE",
    "gn:dem":1427,
    "gn:feature_class":"P",
    "gn:feature_code":"PPL",
    "gn:name":"Kawkabah",
    "gn:population":0,
    "gn:timezone":"Asia/Aden",
    "iso:country":"YE",
    "name:und_x_variant":[
        "Khaubar",
        "Kaukaba",
        "Kawkabah"
    ],
    "wof:name":"Kawkabah",
    "wof:placetype":"locality"
},
  "geometry": {"coordinates":[44.73712,13.74146],"type":"Point"}
}