{
  "type": "Feature",
  "properties": {
    "gn:admin1_code":"11.0",
    "gn:admin2_code":"2005.0",
    "gn:asciiname":"Ar Rabi`ah",
    "gn:country_code":"YE",
    "gn:dem":2018,
    "gn:feature_class":"P",
    "gn:feature_code":"PPL",
    "gn:name":"Ar R\u0101b\u012b\u2018ah",
    "gn:population":0,
    "gn:timezone":"Asia/Aden",
    "iso:country":"YE",
    "name:und_x_variant":[
        "Ar R\u0101b\u012b\u2018ah"
    ],
    "wof:name":"Ar Rabi`ah",
    "wof:placetype":"locality"
},
  "geometry": {"coordinates":[44.03645,14.49037],"type":"Point"}
}