{
  "type": "Feature",
  "properties": {
    "gn:admin1_code":"25.0",
    "gn:admin2_code":"1505.0",
    "gn:asciiname":"Yi`an",
    "gn:country_code":"YE",
    "gn:dem":398,
    "gn:feature_class":"P",
    "gn:feature_code":"PPL",
    "gn:name":"Yi\u2018\u0101n",
    "gn:population":0,
    "gn:timezone":"Asia/Aden",
    "iso:country":"YE",
    "name:ara_x_preferred":[
        "Yi\u2018\u0101n"
    ],
    "wof:name":"Yi`an",
    "wof:placetype":"locality"
},
  "geometry": {"coordinates":[43.58917,13.60611],"type":"Point"}
}