{
  "type": "Feature",
  "properties": {
    "gn:admin1_code":"24.0",
    "gn:admin2_code":"2513.0",
    "gn:asciiname":"Summanah",
    "gn:country_code":"YE",
    "gn:dem":2,
    "gn:feature_class":"P",
    "gn:feature_code":"PPL",
    "gn:name":"Summ\u0101nah",
    "gn:population":0,
    "gn:timezone":"Asia/Aden",
    "iso:country":"YE",
    "name:und_x_variant":[
        "Muhammad \u2018Al\u012b Bin F\u0101ti\u1e29",
        "Muhammad \u2018Ali Bin Fatha Sumana",
        "Summ\u0101nah"
    ],
    "wof:name":"Summanah",
    "wof:placetype":"locality"
},
  "geometry": {"coordinates":[43.63029,12.73505],"type":"Point"}
}