{
  "type": "Feature",
  "properties": {
    "gn:gn_country":"YE",
    "gn:gn_fcode":"PPL",
    "gn:gn_pop":2,
    "gn:population":2,
    "iso:country":"YE",
    "name:ara_x_preferred":[
        "Khid\u0101fir"
    ],
    "name:ara_x_variant":[
        "\u062e\u062f\u0627\u0641\u0631"
    ],
    "name:eng_x_preferred":[
        "Khidafir"
    ],
    "qs_pg:aaroncc":"YE",
    "qs_pg:gn_country":"YE",
    "qs_pg:gn_fcode":"PPL",
    "qs_pg:gn_pop":2,
    "qs_pg:name":"Khid\u0101fir",
    "qs_pg:photos_9r":0,
    "qs_pg:photos_sr":0,
    "qs_pg:pop_sr":1,
    "qs_pg:qs_pg_placetype":"locality",
    "wof:name":"Khid\u0101fir",
    "wof:placetype":"locality",
    "wof:population":2
},
  "geometry": {"coordinates":[45.17229,14.61986],"type":"Point"}
}