{
  "type": "Feature",
  "properties": {
    "gn:admin1_code":"22.0",
    "gn:admin2_code":"1726.0",
    "gn:asciiname":"Kharab Ja`mal",
    "gn:country_code":"YE",
    "gn:dem":987,
    "gn:feature_class":"P",
    "gn:feature_code":"PPL",
    "gn:name":"Khar\u0101b Ja\u2018mal",
    "gn:population":0,
    "gn:timezone":"Asia/Aden",
    "iso:country":"YE",
    "name:und_x_variant":[
        "Khar\u0101b Ja\u2018mal"
    ],
    "wof:name":"Kharab Ja`mal",
    "wof:placetype":"locality"
},
  "geometry": {"coordinates":[43.54457,15.66252],"type":"Point"}
}