{
  "type": "Feature",
  "properties": {
    "gn:admin1_code":"15.0",
    "gn:admin2_code":"2210.0",
    "gn:asciiname":"As Sinn",
    "gn:country_code":"YE",
    "gn:dem":1749,
    "gn:feature_class":"P",
    "gn:feature_code":"PPL",
    "gn:name":"As Sinn",
    "gn:population":0,
    "gn:timezone":"Asia/Aden",
    "iso:country":"YE",
    "wof:name":"As Sinn",
    "wof:placetype":"locality"
},
  "geometry": {"coordinates":[43.3527,17.1476],"type":"Point"}
}