{
  "type": "Feature",
  "properties": {
    "gn:admin1_code":"22.0",
    "gn:admin2_code":"1718.0",
    "gn:asciiname":"Al Hawq",
    "gn:country_code":"YE",
    "gn:dem":1705,
    "gn:feature_class":"P",
    "gn:feature_code":"PPL",
    "gn:name":"Al \u1e28awq",
    "gn:population":0,
    "gn:timezone":"Asia/Aden",
    "iso:country":"YE",
    "name:und_x_variant":[
        "Al \u1e28awq"
    ],
    "wof:name":"Al Hawq",
    "wof:placetype":"locality"
},
  "geometry": {"coordinates":[43.66146,15.81669],"type":"Point"}
}