{
  "type": "Feature",
  "properties": {
    "gn:admin1_code":"8.0",
    "gn:admin2_code":"1817.0",
    "gn:asciiname":"Bayt Ahmad Qaybal",
    "gn:country_code":"YE",
    "gn:dem":73,
    "gn:feature_class":"P",
    "gn:feature_code":"PPL",
    "gn:name":"Bayt A\u1e29mad Qaybal",
    "gn:population":0,
    "gn:timezone":"Asia/Aden",
    "iso:country":"YE",
    "name:und_x_variant":[
        "Bayt A\u1e29mad Qaybal"
    ],
    "wof:name":"Bayt Ahmad Qaybal",
    "wof:placetype":"locality"
},
  "geometry": {"coordinates":[43.25984,14.60695],"type":"Point"}
}