{
  "type": "Feature",
  "properties": {
    "gn:admin1_code":"16.0",
    "gn:admin2_code":"2302.0",
    "gn:asciiname":"Bayt ad Daba'",
    "gn:country_code":"YE",
    "gn:dem":2525,
    "gn:feature_class":"P",
    "gn:feature_code":"PPL",
    "gn:name":"Bayt ad Daba\u2019",
    "gn:population":0,
    "gn:timezone":"Asia/Aden",
    "iso:country":"YE",
    "name:ara_x_preferred":[
        "\u0628\u064a\u062a \u0627\u0644\u062f\u0628\u0623"
    ],
    "name:und_x_variant":[
        "Bayt ad Daba\u2019"
    ],
    "wof:name":"Bayt ad Daba'",
    "wof:placetype":"locality"
},
  "geometry": {"coordinates":[44.22576,15.86708],"type":"Point"}
}