{
  "type": "Feature",
  "properties": {
    "gn:country":"YE",
    "gn:fcode":"PPL",
    "gn:pop":3,
    "iso:country":"YE",
    "name:ara_x_preferred":[
        "\u0627\u0644\u062c\u062d\u0641\u0629"
    ],
    "name:eng_x_preferred":[
        "Al Jahifah"
    ],
    "qs:name":"Al Ja\u1e29ifah",
    "qs:photos_9r":0,
    "qs:photos_sr":0,
    "qs:pop_sr":"1",
    "wof:name":"Al Ja\u1e29ifah",
    "wof:placetype":"locality",
    "wof:population":3
},
  "geometry": {"coordinates":[43.48138,16.08552],"type":"Point"}
}