{
  "type": "Feature",
  "properties": {
    "gn:admin1_code":"19.0",
    "gn:admin2_code":"2919.0",
    "gn:asciiname":"Khamir",
    "gn:country_code":"YE",
    "gn:dem":2465,
    "gn:feature_class":"P",
    "gn:feature_code":"PPLA2",
    "gn:name":"Khamir",
    "gn:population":0,
    "gn:timezone":"Asia/Aden",
    "iso:country":"YE",
    "name:ara_x_preferred":[
        "\u062e\u0645\u0631"
    ],
    "name:und_x_variant":[
        "Hamir",
        "Khamir",
        "H\u0331amr",
        "Khamr"
    ],
    "wof:name":"Khamir",
    "wof:placetype":"locality"
},
  "geometry": {"coordinates":[43.95362,15.98792],"type":"Point"}
}