{
  "type": "Feature",
  "properties": {
    "gn:admin1_code":"24.0",
    "gn:admin2_code":"2512.0",
    "gn:asciiname":"Adh Dhira' al Aswad",
    "gn:country_code":"YE",
    "gn:dem":1413,
    "gn:feature_class":"P",
    "gn:feature_code":"PPL",
    "gn:name":"Adh Dhir\u0101\u2018 al Aswad",
    "gn:population":0,
    "gn:timezone":"Asia/Aden",
    "iso:country":"YE",
    "name:ara_x_preferred":[
        "\u0627\u0644\u0630\u0631\u0627\u0639 \u0627\u0644\u0627\u0633\u0648\u062f"
    ],
    "name:und_x_variant":[
        "Adh Dhir\u0101\u2018 al Aswad"
    ],
    "wof:name":"Adh Dhira' al Aswad",
    "wof:placetype":"locality"
},
  "geometry": {"coordinates":[44.15984,13.19503],"type":"Point"}
}