{
  "type": "Feature",
  "properties": {
    "gn:admin1_code":"18.0",
    "gn:admin2_code":"3005.0",
    "gn:asciiname":"Al Munadi",
    "gn:country_code":"YE",
    "gn:dem":1376,
    "gn:feature_class":"P",
    "gn:feature_code":"PPL",
    "gn:name":"Al Mun\u0101d\u012b",
    "gn:population":0,
    "gn:timezone":"Asia/Aden",
    "iso:country":"YE",
    "name:ara_x_preferred":[
        "Al Mun\u0101d\u012b"
    ],
    "name:und_x_variant":[
        "Min\u0101d\u012b"
    ],
    "wof:name":"Al Munadi",
    "wof:placetype":"locality"
},
  "geometry": {"coordinates":[44.75,13.79426],"type":"Point"}
}