{
  "type": "Feature",
  "properties": {
    "gn:country":"YE",
    "gn:fcode":"PPL",
    "gn:population":5,
    "iso:country":"YE",
    "name:ara_x_preferred":[
        "\u0627\u0644\u062e\u0631\u0634"
    ],
    "name:eng_x_preferred":[
        "Al Khursh"
    ],
    "name:eng_x_variant":[
        "An Nishm\u0101t"
    ],
    "qs:name":"Al Khursh",
    "qs:photos_9r":0,
    "qs:photos_sr":0,
    "qs:pop_sr":"1",
    "wof:name":"Al Khursh",
    "wof:placetype":"locality",
    "wof:population":5
},
  "geometry": {"coordinates":[43.44229,16.11888],"type":"Point"}
}