{
  "type": "Feature",
  "properties": {
    "gn:admin1_code":"22.0",
    "gn:admin2_code":"1722.0",
    "gn:asciiname":"As Sarbah",
    "gn:country_code":"YE",
    "gn:dem":568,
    "gn:feature_class":"P",
    "gn:feature_code":"PPL",
    "gn:name":"As Sarbah",
    "gn:population":0,
    "gn:timezone":"Asia/Aden",
    "iso:country":"YE",
    "wof:name":"As Sarbah",
    "wof:placetype":"locality"
},
  "geometry": {"coordinates":[43.33033,15.85286],"type":"Point"}
}