{
  "type": "Feature",
  "properties": {
    "gn:admin1_code":"15.0",
    "gn:admin2_code":"2211.0",
    "gn:asciiname":"Rabi`",
    "gn:country_code":"YE",
    "gn:dem":1894,
    "gn:feature_class":"P",
    "gn:feature_code":"PPL",
    "gn:name":"Rab\u012b\u2018",
    "gn:population":0,
    "gn:timezone":"Asia/Aden",
    "iso:country":"YE",
    "name:und_x_variant":[
        "Rab\u012b\u2018"
    ],
    "wof:name":"Rabi`",
    "wof:placetype":"locality"
},
  "geometry": {"coordinates":[43.71667,16.98333],"type":"Point"}
}