{
  "type": "Feature",
  "properties": {
    "gn:country":"YE",
    "gn:fcode":"PPL",
    "gn:pop":18,
    "iso:country":"YE",
    "name:ara_x_preferred":[
        "Al \u2018Am\u012bsh\u0101\u2019"
    ],
    "name:ara_x_variant":[
        "\u0627\u0644\u0639\u0645\u064a\u0634\u0627\u0621"
    ],
    "name:eng_x_preferred":[
        "Al 'Amisha"
    ],
    "qs:name":"Al \u2018Am\u012bsh\u0101\u2019",
    "qs:photos_9r":0,
    "qs:photos_sr":0,
    "qs:pop_sr":"1",
    "wof:name":"Al \u2018Am\u012bsh\u0101\u2019",
    "wof:placetype":"locality",
    "wof:population":18
},
  "geometry": {"coordinates":[43.34181,16.14396],"type":"Point"}
}