{
  "type": "Feature",
  "properties": {
    "gn:admin1_code":"4.0",
    "gn:admin2_code":"1911.0",
    "gn:asciiname":"Ba Hafar",
    "gn:country_code":"YE",
    "gn:dem":583,
    "gn:feature_class":"P",
    "gn:feature_code":"PPL",
    "gn:name":"B\u0101 \u1e28af\u0101r",
    "gn:population":0,
    "gn:timezone":"Asia/Aden",
    "iso:country":"YE",
    "name:nno_x_preferred":[
        "Ba Hafar"
    ],
    "name:rus_x_preferred":[
        "\u0411\u0430-\u0425\u0443\u0444\u0430\u0440\u0430"
    ],
    "name:und_x_variant":[
        "B\u0101 \u1e28af\u0101r"
    ],
    "wof:name":"Ba Hafar",
    "wof:placetype":"locality"
},
  "geometry": {"coordinates":[49.20583,16.12722],"type":"Point"}
}