{
  "type": "Feature",
  "properties": {
    "gn:country":"YE",
    "gn:fcode":"PPL",
    "gn:pop":8,
    "iso:country":"YE",
    "name:ara_x_preferred":[
        "\u0627\u0644\u0642\u0645\u0628\u0648\u0631"
    ],
    "name:eng_x_preferred":[
        "Al QambUr"
    ],
    "qs:name":"Al Qamb\u016br",
    "qs:photos_9r":0,
    "qs:photos_sr":0,
    "qs:pop_sr":"1",
    "wof:name":"Al Qamb\u016br",
    "wof:placetype":"locality",
    "wof:population":8
},
  "geometry": {"coordinates":[43.08145,16.33576],"type":"Point"}
}