{
  "type": "Feature",
  "properties": {
    "gn:admin1_code":"19.0",
    "gn:admin2_code":"2916.0",
    "gn:asciiname":"Bayt ar Rayis",
    "gn:country_code":"YE",
    "gn:dem":1209,
    "gn:feature_class":"P",
    "gn:feature_code":"PPL",
    "gn:name":"Bayt ar R\u0101yis",
    "gn:population":0,
    "gn:timezone":"Asia/Aden",
    "iso:country":"YE",
    "name:ara_x_preferred":[
        "\u0628\u064a\u062a \u0627\u0644\u0631\u0627\u064a\u0633"
    ],
    "name:und_x_variant":[
        "Bayt ar R\u0101yis"
    ],
    "wof:name":"Bayt ar Rayis",
    "wof:placetype":"locality"
},
  "geometry": {"coordinates":[43.65082,15.54868],"type":"Point"}
}