{
  "type": "Feature",
  "properties": {
    "gn:admin1_code":"23.0",
    "gn:admin2_code":"1115.0",
    "gn:asciiname":"Al Jay'at",
    "gn:country_code":"YE",
    "gn:dem":1958,
    "gn:feature_class":"P",
    "gn:feature_code":"PPL",
    "gn:name":"Al Jay\u2019\u0101t",
    "gn:population":0,
    "gn:timezone":"Asia/Aden",
    "iso:country":"YE",
    "name:und_x_variant":[
        "Al Jay\u2019\u0101t"
    ],
    "wof:name":"Al Jay'at",
    "wof:placetype":"locality"
},
  "geometry": {"coordinates":[44.2162,13.9069],"type":"Point"}
}