{
  "type": "Feature",
  "properties": {
    "gn:admin1_code":"22.0",
    "gn:admin2_code":"1722.0",
    "gn:asciiname":"Dayr Maq`as",
    "gn:country_code":"YE",
    "gn:dem":216,
    "gn:feature_class":"P",
    "gn:feature_code":"PPL",
    "gn:name":"Dayr Maq\u2018as",
    "gn:population":0,
    "gn:timezone":"Asia/Aden",
    "iso:country":"YE",
    "name:und_x_variant":[
        "Dayr Maq\u2018as"
    ],
    "wof:name":"Dayr Maq`as",
    "wof:placetype":"locality"
},
  "geometry": {"coordinates":[43.24825,15.70501],"type":"Point"}
}