{
  "type": "Feature",
  "properties": {
    "gn:admin1_code":"20.0",
    "gn:admin2_code":"1419.0",
    "gn:asciiname":"Al Musayni'ah",
    "gn:country_code":"YE",
    "gn:dem":1968,
    "gn:feature_class":"P",
    "gn:feature_code":"PPL",
    "gn:name":"Al Mu\u015fayni\u2018ah",
    "gn:population":0,
    "gn:timezone":"Asia/Aden",
    "iso:country":"YE",
    "name:ara_x_preferred":[
        "\u0627\u0644\u0645\u0635\u064a\u0646\u0639\u0629"
    ],
    "name:und_x_variant":[
        "Al Mu\u015fayni\u2018ah"
    ],
    "wof:name":"Al Musayni'ah",
    "wof:placetype":"locality"
},
  "geometry": {"coordinates":[45.02424,14.31366],"type":"Point"}
}