{
  "type": "Feature",
  "properties": {
    "gn:admin1_code":"5.0",
    "gn:admin2_code":"2102.0",
    "gn:asciiname":"Sharij Ba Wahal",
    "gn:country_code":"YE",
    "gn:dem":1519,
    "gn:feature_class":"P",
    "gn:feature_code":"PPL",
    "gn:name":"Sharij B\u0101 Wahal",
    "gn:population":0,
    "gn:timezone":"Asia/Aden",
    "iso:country":"YE",
    "name:und_x_variant":[
        "Sharij B\u0101 Wahal"
    ],
    "wof:name":"Sharij Ba Wahal",
    "wof:placetype":"locality"
},
  "geometry": {"coordinates":[47.13333,15.11667],"type":"Point"}
}