{
  "type": "Feature",
  "properties": {
    "gn:admin1_code":"19.0",
    "gn:admin2_code":"2901.0",
    "gn:asciiname":"Khiyarah",
    "gn:country_code":"YE",
    "gn:dem":1696,
    "gn:feature_class":"P",
    "gn:feature_code":"PPL",
    "gn:name":"Khiy\u0101rah",
    "gn:population":0,
    "gn:timezone":"Asia/Aden",
    "iso:country":"YE",
    "name:und_x_variant":[
        "Khiy\u0101rah"
    ],
    "wof:name":"Khiyarah",
    "wof:placetype":"locality"
},
  "geometry": {"coordinates":[44.01827,16.4966],"type":"Point"}
}