{
  "type": "Feature",
  "properties": {
    "gn:admin1_code":"20.0",
    "gn:admin2_code":"1404.0",
    "gn:asciiname":"Al Wasitah",
    "gn:country_code":"YE",
    "gn:dem":2026,
    "gn:feature_class":"P",
    "gn:feature_code":"PPL",
    "gn:name":"Al W\u0101si\u0163ah",
    "gn:population":0,
    "gn:timezone":"Asia/Aden",
    "iso:country":"YE",
    "name:und_x_variant":[
        "Al W\u0101si\u0163ah"
    ],
    "wof:name":"Al Wasitah",
    "wof:placetype":"locality"
},
  "geometry": {"coordinates":[45.77111,14.10896],"type":"Point"}
}