{
  "type": "Feature",
  "properties": {
    "gn:admin1_code":"8.0",
    "gn:admin2_code":"1817.0",
    "gn:asciiname":"Buyut ad Dalasha'",
    "gn:country_code":"YE",
    "gn:dem":137,
    "gn:feature_class":"P",
    "gn:feature_code":"PPL",
    "gn:name":"Buy\u016bt ad Dal\u0101sh\u0101\u2019",
    "gn:population":0,
    "gn:timezone":"Asia/Aden",
    "iso:country":"YE",
    "name:und_x_variant":[
        "Buy\u016bt ad Dal\u0101sh\u0101\u2019"
    ],
    "wof:name":"Buyut ad Dalasha'",
    "wof:placetype":"locality"
},
  "geometry": {"coordinates":[43.39588,14.5656],"type":"Point"}
}