{
  "type": "Feature",
  "properties": {
    "gn:admin1_code":"19.0",
    "gn:admin2_code":"2911.0",
    "gn:asciiname":"Mahall Sufi ad Dayn",
    "gn:country_code":"YE",
    "gn:dem":2565,
    "gn:feature_class":"P",
    "gn:feature_code":"PPL",
    "gn:name":"Ma\u1e29all \u015euf\u012b ad Dayn",
    "gn:population":0,
    "gn:timezone":"Asia/Aden",
    "iso:country":"YE",
    "name:und_x_variant":[
        "Ma\u1e29all \u015euf\u012b ad Dayn"
    ],
    "wof:name":"Mahall Sufi ad Dayn",
    "wof:placetype":"locality"
},
  "geometry": {"coordinates":[44.0763,15.73568],"type":"Point"}
}