{
  "type": "Feature",
  "properties": {
    "gn:admin1_code":"8.0",
    "gn:admin2_code":"1810.0",
    "gn:asciiname":"Adh Dhi 'abi",
    "gn:country_code":"YE",
    "gn:dem":123,
    "gn:feature_class":"P",
    "gn:feature_code":"PPL",
    "gn:name":"Adh Dhi \u2019\u0101b\u012b",
    "gn:population":0,
    "gn:timezone":"Asia/Aden",
    "iso:country":"YE",
    "name:ara_x_preferred":[
        "Adh Dhi \u2019\u0101b\u012b"
    ],
    "wof:name":"Adh Dhi 'abi",
    "wof:placetype":"locality"
},
  "geometry": {"coordinates":[43.19937,15.00273],"type":"Point"}
}