{
  "type": "Feature",
  "properties": {
    "gn:admin1_code":"8.0",
    "gn:admin2_code":"1817.0",
    "gn:asciiname":"Bani al Habili",
    "gn:country_code":"YE",
    "gn:dem":353,
    "gn:feature_class":"P",
    "gn:feature_code":"PPL",
    "gn:name":"Ban\u012b al \u1e28ab\u012bl\u012b",
    "gn:population":0,
    "gn:timezone":"Asia/Aden",
    "iso:country":"YE",
    "name:und_x_variant":[
        "Ban\u012b al \u1e28ab\u012bl\u012b"
    ],
    "wof:name":"Bani al Habili",
    "wof:placetype":"locality"
},
  "geometry": {"coordinates":[43.51523,14.38842],"type":"Point"}
}