{
  "type": "Feature",
  "properties": {
    "gn:admin1_code":"15.0",
    "gn:admin2_code":"2212.0",
    "gn:asciiname":"Sharamat",
    "gn:country_code":"YE",
    "gn:dem":2015,
    "gn:feature_class":"P",
    "gn:feature_code":"PPL",
    "gn:name":"Sharam\u0101t",
    "gn:population":0,
    "gn:timezone":"Asia/Aden",
    "iso:country":"YE",
    "name:und_x_variant":[
        "Sharam\u0101t"
    ],
    "wof:name":"Sharamat",
    "wof:placetype":"locality"
},
  "geometry": {"coordinates":[43.83228,16.79629],"type":"Point"}
}