{
  "type": "Feature",
  "properties": {
    "gn:admin1_code":"25.0",
    "gn:admin2_code":"1515.0",
    "gn:asciiname":"Ar Raddaynah",
    "gn:country_code":"YE",
    "gn:dem":1113,
    "gn:feature_class":"P",
    "gn:feature_code":"PPL",
    "gn:name":"Ar Raddaynah",
    "gn:population":0,
    "gn:timezone":"Asia/Aden",
    "iso:country":"YE",
    "wof:name":"Ar Raddaynah",
    "wof:placetype":"locality"
},
  "geometry": {"coordinates":[43.99462,13.24388],"type":"Point"}
}