{
  "type": "Feature",
  "properties": {
    "gn:admin1_code":"20.0",
    "gn:admin2_code":"1415.0",
    "gn:asciiname":"Al Hajafah",
    "gn:country_code":"YE",
    "gn:dem":2119,
    "gn:feature_class":"P",
    "gn:feature_code":"PPL",
    "gn:name":"Al \u1e28ajafah",
    "gn:population":0,
    "gn:timezone":"Asia/Aden",
    "iso:country":"YE",
    "name:ara_x_preferred":[
        "\u0627\u0644\u062d\u062c\u0641\u0629"
    ],
    "name:und_x_variant":[
        "Al \u1e28ijfah",
        "Al \u1e28ajfah",
        "Al \u1e28ajafah"
    ],
    "wof:name":"Al Hajafah",
    "wof:placetype":"locality"
},
  "geometry": {"coordinates":[44.83838,14.44941],"type":"Point"}
}