{
  "type": "Feature",
  "properties": {
    "gn:admin1_code":"11.0",
    "gn:admin2_code":"1101.0",
    "gn:asciiname":"Bayt an Najri",
    "gn:country_code":"YE",
    "gn:dem":2476,
    "gn:feature_class":"P",
    "gn:feature_code":"PPL",
    "gn:name":"Bayt an Najr\u012b",
    "gn:population":0,
    "gn:timezone":"Asia/Aden",
    "iso:country":"YE",
    "name:ara_x_preferred":[
        "\u0628\u064a\u062a \u0627\u0644\u0646\u062c\u0631\u064a"
    ],
    "name:und_x_variant":[
        "Bayt an Najr\u012b"
    ],
    "wof:name":"Bayt an Najri",
    "wof:placetype":"locality"
},
  "geometry": {"coordinates":[44.25141,14.28918],"type":"Point"}
}