{
  "type": "Feature",
  "properties": {
    "gn:admin1_code":"28.0",
    "gn:admin2_code":"1926.0",
    "gn:asciiname":"Maqayshuh",
    "gn:country_code":"YE",
    "gn:dem":274,
    "gn:feature_class":"P",
    "gn:feature_code":"PPL",
    "gn:name":"Maqaysh\u016bh",
    "gn:population":0,
    "gn:timezone":"Asia/Aden",
    "iso:country":"YE",
    "wof:name":"Maqayshuh",
    "wof:placetype":"locality"
},
  "geometry": {"coordinates":[54.16973,12.56242],"type":"Point"}
}