{
  "type": "Feature",
  "properties": {
    "gn:country":"YE",
    "gn:fcode":"PPL",
    "gn:population":7,
    "iso:country":"YE",
    "name:ara_x_preferred":[
        "\u0627\u0644\u0645\u0631\u0648\u0649"
    ],
    "qs:name":"Al Marw\u00e1",
    "qs:photos_9r":0,
    "qs:photos_sr":0,
    "qs:pop_sr":"1",
    "wof:name":"Al Marw\u00e1",
    "wof:placetype":"locality",
    "wof:population":7
},
  "geometry": {"coordinates":[43.3445,16.27862],"type":"Point"}
}