{
  "type": "Feature",
  "properties": {
    "gn:admin1_code":"8.0",
    "gn:admin2_code":"1812.0",
    "gn:asciiname":"Ar Razim",
    "gn:country_code":"YE",
    "gn:dem":1123,
    "gn:feature_class":"P",
    "gn:feature_code":"PPL",
    "gn:name":"Ar R\u0101zim",
    "gn:population":0,
    "gn:timezone":"Asia/Aden",
    "iso:country":"YE",
    "name:ara_x_preferred":[
        "\u0627\u0644\u0631\u0627\u0632\u0645"
    ],
    "name:und_x_variant":[
        "Ar R\u0101zim"
    ],
    "wof:name":"Ar Razim",
    "wof:placetype":"locality"
},
  "geometry": {"coordinates":[43.4241,14.89306],"type":"Point"}
}