{
  "type": "Feature",
  "properties": {
    "gn:admin1_code":"19.0",
    "gn:admin2_code":"2912.0",
    "gn:asciiname":"Bayt al Iqra`",
    "gn:country_code":"YE",
    "gn:dem":2611,
    "gn:feature_class":"P",
    "gn:feature_code":"PPL",
    "gn:name":"Bayt al Iqra\u2018",
    "gn:population":0,
    "gn:timezone":"Asia/Aden",
    "iso:country":"YE",
    "name:und_x_variant":[
        "Bayt al Iqra\u2018"
    ],
    "wof:name":"Bayt al Iqra`",
    "wof:placetype":"locality"
},
  "geometry": {"coordinates":[43.82483,15.73455],"type":"Point"}
}