{
  "type": "Feature",
  "properties": {
    "gn:admin1_code":"11.0",
    "gn:admin2_code":"2004.0",
    "gn:asciiname":"Zahr al Himar",
    "gn:country_code":"YE",
    "gn:dem":1316,
    "gn:feature_class":"P",
    "gn:feature_code":"PPL",
    "gn:name":"Z\u0327ahr al \u1e28im\u0101r",
    "gn:population":0,
    "gn:timezone":"Asia/Aden",
    "iso:country":"YE",
    "name:ara_x_preferred":[
        "\u0638\u0647\u0631 \u0627\u0644\u062d\u0645\u0627\u0631"
    ],
    "name:und_x_variant":[
        "Z\u0327ahr al \u1e28im\u0101r"
    ],
    "wof:name":"Zahr al Himar",
    "wof:placetype":"locality"
},
  "geometry": {"coordinates":[44.09597,14.36559],"type":"Point"}
}