{
  "type": "Feature",
  "properties": {
    "gn:admin1_code":"8.0",
    "gn:admin2_code":"1810.0",
    "gn:asciiname":"Bin Ahmad",
    "gn:country_code":"YE",
    "gn:dem":100,
    "gn:feature_class":"P",
    "gn:feature_code":"PPL",
    "gn:name":"Bin A\u1e29mad",
    "gn:population":0,
    "gn:timezone":"Asia/Aden",
    "iso:country":"YE",
    "name:und_x_variant":[
        "Ben Ahmed",
        "Ban Ahmad",
        "Bin A\u1e29mad"
    ],
    "wof:name":"Bin Ahmad",
    "wof:placetype":"locality"
},
  "geometry": {"coordinates":[43.13711,15.04771],"type":"Point"}
}