{
  "type": "Feature",
  "properties": {
    "gn:admin1_code":"19.0",
    "gn:admin2_code":"2901.0",
    "gn:asciiname":"Al Hawl",
    "gn:country_code":"YE",
    "gn:dem":1644,
    "gn:feature_class":"P",
    "gn:feature_code":"PPL",
    "gn:name":"Al \u1e28awl",
    "gn:population":0,
    "gn:timezone":"Asia/Aden",
    "iso:country":"YE",
    "name:und_x_variant":[
        "Al \u1e28awl"
    ],
    "wof:name":"Al Hawl",
    "wof:placetype":"locality"
},
  "geometry": {"coordinates":[44.04679,16.42581],"type":"Point"}
}