{
  "type": "Feature",
  "properties": {
    "gn:country":"YE",
    "gn:fcode":"PPL",
    "gn:pop":9,
    "iso:country":"YE",
    "name:ara_x_preferred":[
        "\u0627\u0644 \u0634\u064a\u062d\u0627\u0646"
    ],
    "name:eng_x_preferred":[
        "Al Shayhan"
    ],
    "qs:name":"\u0100l Shay\u1e29\u0101n",
    "qs:photos_9r":0,
    "qs:photos_sr":0,
    "qs:pop_sr":"1",
    "wof:name":"\u0100l Shay\u1e29\u0101n",
    "wof:placetype":"locality",
    "wof:population":9
},
  "geometry": {"coordinates":[43.39519,16.85656],"type":"Point"}
}