{
  "type": "Feature",
  "properties": {
    "gn:admin1_code":"23.0",
    "gn:admin2_code":"1109.0",
    "gn:asciiname":"Shi`b Rashid",
    "gn:country_code":"YE",
    "gn:dem":826,
    "gn:feature_class":"P",
    "gn:feature_code":"PPL",
    "gn:name":"Shi\u2018b R\u0101shid",
    "gn:population":0,
    "gn:timezone":"Asia/Aden",
    "iso:country":"YE",
    "name:ara_x_preferred":[
        "Shi\u2018b R\u0101shid"
    ],
    "name:ara_x_variant":[
        "\u0634\u0639\u0628 \u0631\u0627\u0634\u062f"
    ],
    "wof:name":"Shi`b Rashid",
    "wof:placetype":"locality"
},
  "geometry": {"coordinates":[43.77782,14.10651],"type":"Point"}
}