{
  "type": "Feature",
  "properties": {
    "gn:admin1_code":"24.0",
    "gn:admin2_code":"2513.0",
    "gn:asciiname":"Al Ghurabiyah",
    "gn:country_code":"YE",
    "gn:dem":260,
    "gn:feature_class":"P",
    "gn:feature_code":"PPL",
    "gn:name":"Al Ghur\u0101b\u012byah",
    "gn:population":0,
    "gn:timezone":"Asia/Aden",
    "iso:country":"YE",
    "name:und_x_variant":[
        "Al Ghur\u0101b\u012byah"
    ],
    "wof:name":"Al Ghurabiyah",
    "wof:placetype":"locality"
},
  "geometry": {"coordinates":[44.01535,12.90739],"type":"Point"}
}