{
  "type": "Feature",
  "properties": {
    "gn:admin1_code":"20.0",
    "gn:admin2_code":"1414.0",
    "gn:asciiname":"Muqaysah",
    "gn:country_code":"YE",
    "gn:dem":2195,
    "gn:feature_class":"P",
    "gn:feature_code":"PPL",
    "gn:name":"Muqaysah",
    "gn:population":0,
    "gn:timezone":"Asia/Aden",
    "iso:country":"YE",
    "wof:name":"Muqaysah",
    "wof:placetype":"locality"
},
  "geometry": {"coordinates":[44.77845,14.4425],"type":"Point"}
}