{
  "type": "Feature",
  "properties": {
    "gn:admin1_code":"4.0",
    "gn:admin2_code":"1910.0",
    "gn:asciiname":"Hisn Al `Abdat",
    "gn:country_code":"YE",
    "gn:dem":659,
    "gn:feature_class":"P",
    "gn:feature_code":"PPL",
    "gn:name":"\u1e28i\u015fn \u0100l \u2018Abd\u0101t",
    "gn:population":0,
    "gn:timezone":"Asia/Aden",
    "iso:country":"YE",
    "name:ara_x_preferred":[
        "\u1e28i\u015fn \u0100l \u2018Abd\u0101t"
    ],
    "name:und_x_variant":[
        "\u1e28u\u015fn \u0100l \u2018Abd\u0101t"
    ],
    "wof:name":"Hisn Al `Abdat",
    "wof:placetype":"locality"
},
  "geometry": {"coordinates":[48.71389,15.91944],"type":"Point"}
}