{
  "type": "Feature",
  "properties": {
    "gn:admin1_code":"25.0",
    "gn:admin2_code":"1501.0",
    "gn:asciiname":"Qaryat al Farshah",
    "gn:country_code":"YE",
    "gn:dem":1257,
    "gn:feature_class":"P",
    "gn:feature_code":"PPL",
    "gn:name":"Qaryat al Farshah",
    "gn:population":0,
    "gn:timezone":"Asia/Aden",
    "iso:country":"YE",
    "wof:name":"Qaryat al Farshah",
    "wof:placetype":"locality"
},
  "geometry": {"coordinates":[44.25229,13.60855],"type":"Point"}
}