{
  "type": "Feature",
  "properties": {
    "gn:admin1_code":"16.0",
    "gn:admin2_code":"2309.0",
    "gn:asciiname":"Hisn Bani Sulayman",
    "gn:country_code":"YE",
    "gn:dem":2809,
    "gn:feature_class":"P",
    "gn:feature_code":"PPL",
    "gn:name":"\u1e28i\u015fn Ban\u012b Sulaym\u0101n",
    "gn:population":0,
    "gn:timezone":"Asia/Aden",
    "iso:country":"YE",
    "name:und_x_variant":[
        "\u1e28i\u015fn Ban\u012b Sulaym\u0101n"
    ],
    "wof:name":"Hisn Bani Sulayman",
    "wof:placetype":"locality"
},
  "geometry": {"coordinates":[43.94861,15.19667],"type":"Point"}
}