{
  "type": "Feature",
  "properties": {
    "gn:admin1_code":"15.0",
    "gn:admin2_code":"2210.0",
    "gn:asciiname":"Kanb at Tariq",
    "gn:country_code":"YE",
    "gn:dem":2009,
    "gn:feature_class":"P",
    "gn:feature_code":"PPL",
    "gn:name":"Kanb a\u0163 \u0162ar\u012bq",
    "gn:population":0,
    "gn:timezone":"Asia/Aden",
    "iso:country":"YE",
    "name:und_x_variant":[
        "Kanb a\u0163 \u0162ar\u012bq"
    ],
    "wof:name":"Kanb at Tariq",
    "wof:placetype":"locality"
},
  "geometry": {"coordinates":[43.56379,17.11421],"type":"Point"}
}