{
  "type": "Feature",
  "properties": {
    "gn:admin1_code":"23.0",
    "gn:admin2_code":"1101.0",
    "gn:asciiname":"Al Jawab",
    "gn:country_code":"YE",
    "gn:dem":1457,
    "gn:feature_class":"P",
    "gn:feature_code":"PPL",
    "gn:name":"Al Jaw\u0101b",
    "gn:population":0,
    "gn:timezone":"Asia/Aden",
    "iso:country":"YE",
    "name:ara_x_preferred":[
        "\u0627\u0644\u062c\u0648\u0627\u0628"
    ],
    "name:und_x_variant":[
        "Al Jaw\u0101b"
    ],
    "wof:name":"Al Jawab",
    "wof:placetype":"locality"
},
  "geometry": {"coordinates":[44.13909,14.29348],"type":"Point"}
}