{
  "type": "Feature",
  "properties": {
    "gn:admin1_code":"19.0",
    "gn:admin2_code":"2903.0",
    "gn:asciiname":"Qasabat al Quff",
    "gn:country_code":"YE",
    "gn:dem":1388,
    "gn:feature_class":"P",
    "gn:feature_code":"PPLL",
    "gn:name":"Qa\u015fabat al Quff",
    "gn:population":0,
    "gn:timezone":"Asia/Aden",
    "iso:country":"YE",
    "name:ara_x_preferred":[
        "\u0642\u0635\u0628\u0629 \u0627\u0644\u0642\u0641"
    ],
    "name:und_x_variant":[
        "Qa\u015fabat al Quff"
    ],
    "wof:name":"Qasabat al Quff",
    "wof:placetype":"locality"
},
  "geometry": {"coordinates":[43.84106,16.14707000000001],"type":"Point"}
}