{
  "type": "Feature",
  "properties": {
    "gn:admin1_code":"23.0",
    "gn:admin2_code":"1101.0",
    "gn:asciiname":"Ad Daranah",
    "gn:country_code":"YE",
    "gn:dem":1468,
    "gn:feature_class":"P",
    "gn:feature_code":"PPL",
    "gn:name":"Ad Daranah",
    "gn:population":0,
    "gn:timezone":"Asia/Aden",
    "iso:country":"YE",
    "name:ara_x_preferred":[
        "\u0627\u0644\u062f\u0631\u0646\u0629"
    ],
    "wof:name":"Ad Daranah",
    "wof:placetype":"locality"
},
  "geometry": {"coordinates":[44.13431,14.36563],"type":"Point"}
}