{
  "type": "Feature",
  "properties": {
    "gn:admin1_code":"22.0",
    "gn:admin2_code":"1724.0",
    "gn:asciiname":"Junayt",
    "gn:country_code":"YE",
    "gn:dem":539,
    "gn:feature_class":"P",
    "gn:feature_code":"PPL",
    "gn:name":"Junayt",
    "gn:population":0,
    "gn:timezone":"Asia/Aden",
    "iso:country":"YE",
    "wof:name":"Junayt",
    "wof:placetype":"locality"
},
  "geometry": {"coordinates":[43.43555,15.65938],"type":"Point"}
}