{
  "type": "Feature",
  "properties": {
    "gn:admin1_code":"23.0",
    "gn:admin2_code":"1109.0",
    "gn:asciiname":"Al Masani`",
    "gn:country_code":"YE",
    "gn:dem":1251,
    "gn:feature_class":"P",
    "gn:feature_code":"PPL",
    "gn:name":"Al Mas\u0101ni\u2018",
    "gn:population":0,
    "gn:timezone":"Asia/Aden",
    "iso:country":"YE",
    "name:ara_x_preferred":[
        "\u0627\u0644\u0645\u0635\u0627\u0646\u0639"
    ],
    "name:und_x_variant":[
        "Al Mas\u0101ni\u2018",
        "Al Ma\u015f\u0101ni\u2018"
    ],
    "wof:name":"Al Masani`",
    "wof:placetype":"locality"
},
  "geometry": {"coordinates":[44.03935,14.18765],"type":"Point"}
}