{
  "type": "Feature",
  "properties": {
    "gn:admin1_code":"25.0",
    "gn:admin2_code":"1516.0",
    "gn:asciiname":"Al Haymah",
    "gn:country_code":"YE",
    "gn:dem":506,
    "gn:feature_class":"P",
    "gn:feature_code":"PPL",
    "gn:name":"Al \u1e28aymah",
    "gn:population":0,
    "gn:timezone":"Asia/Aden",
    "iso:country":"YE",
    "name:ara_x_preferred":[
        "\u0627\u0644\u062d\u064a\u0645\u0629"
    ],
    "name:und_x_variant":[
        "\u1e28aymat Sha\u2018b\u016b",
        "Al \u1e28aymah"
    ],
    "wof:name":"Al Haymah",
    "wof:placetype":"locality"
},
  "geometry": {"coordinates":[43.72029000000001,13.20653],"type":"Point"}
}