{
  "type": "Feature",
  "properties": {
    "gn:admin1_code":"20.0",
    "gn:admin2_code":"1412.0",
    "gn:asciiname":"Barkan",
    "gn:country_code":"YE",
    "gn:dem":2000,
    "gn:feature_class":"P",
    "gn:feature_code":"PPL",
    "gn:name":"Bark\u0101n",
    "gn:population":0,
    "gn:timezone":"Asia/Aden",
    "iso:country":"YE",
    "name:ara_x_preferred":[
        "\u0628\u0631\u0643\u0627\u0646"
    ],
    "name:ces_x_preferred":[
        "Barkan"
    ],
    "name:fas_x_preferred":[
        "\u0628\u0631\u06a9\u0627\u0646"
    ],
    "name:heb_x_preferred":[
        "\u05d1\u05e8\u05e7\u05df"
    ],
    "name:nno_x_preferred":[
        "Barkan"
    ],
    "name:pol_x_preferred":[
        "Barkan"
    ],
    "name:rus_x_preferred":[
        "\u0411\u0430\u0440\u043a\u0430\u043d"
    ],
    "name:und_x_variant":[
        "Bark\u0101n"
    ],
    "wof:name":"Barkan",
    "wof:placetype":"locality"
},
  "geometry": {"coordinates":[45.33863,14.40089],"type":"Point"}
}