{
  "type": "Feature",
  "properties": {
    "gn:admin1_code":"16.0",
    "gn:admin2_code":"2307.0",
    "gn:asciiname":"Bayt Na`amah",
    "gn:country_code":"YE",
    "gn:dem":2779,
    "gn:feature_class":"P",
    "gn:feature_code":"PPL",
    "gn:name":"Bayt Na\u2018\u0101mah",
    "gn:population":0,
    "gn:timezone":"Asia/Aden",
    "iso:country":"YE",
    "name:ara_x_preferred":[
        "\u0628\u064a\u062a \u0646\u0639\u0627\u0645\u0629"
    ],
    "name:nno_x_preferred":[
        "Bayt Na`Amah"
    ],
    "name:und_x_variant":[
        "Bayt Na\u2018\u0101mah"
    ],
    "wof:name":"Bayt Na`amah",
    "wof:placetype":"locality"
},
  "geometry": {"coordinates":[44.10747,15.29632],"type":"Point"}
}