{
  "type": "Feature",
  "properties": {
    "gn:admin1_code":"23.0",
    "gn:admin2_code":"1113.0",
    "gn:asciiname":"Dhi Thidd",
    "gn:country_code":"YE",
    "gn:dem":1981,
    "gn:feature_class":"P",
    "gn:feature_code":"PPL",
    "gn:name":"Dh\u012b Thidd",
    "gn:population":0,
    "gn:timezone":"Asia/Aden",
    "iso:country":"YE",
    "name:ara_x_preferred":[
        "Dh\u012b Thidd"
    ],
    "wof:name":"Dhi Thidd",
    "wof:placetype":"locality"
},
  "geometry": {"coordinates":[44.33547,13.9703],"type":"Point"}
}