{
  "type": "Feature",
  "properties": {
    "gn:admin1_code":"15.0",
    "gn:admin2_code":"2203.0",
    "gn:asciiname":"Mishat al `Utbah",
    "gn:country_code":"YE",
    "gn:dem":1032,
    "gn:feature_class":"P",
    "gn:feature_code":"PPL",
    "gn:name":"Mishat al \u2018U\u0163bah",
    "gn:population":0,
    "gn:timezone":"Asia/Aden",
    "iso:country":"YE",
    "name:ara_x_preferred":[
        "\u0627\u0644\u0645\u0634\u0629"
    ],
    "name:und_x_variant":[
        "Mishat al \u2018U\u0163bah",
        "Al Mishah"
    ],
    "wof:name":"Mishat al `Utbah",
    "wof:placetype":"locality"
},
  "geometry": {"coordinates":[43.22276,17.12909],"type":"Point"}
}