{
  "type": "Feature",
  "properties": {
    "gn:admin1_code":"15.0",
    "gn:admin2_code":"2209.0",
    "gn:asciiname":"Al Hadban",
    "gn:country_code":"YE",
    "gn:dem":1560,
    "gn:feature_class":"P",
    "gn:feature_code":"PPL",
    "gn:name":"\u0100l \u1e28adb\u0101n",
    "gn:population":0,
    "gn:timezone":"Asia/Aden",
    "iso:country":"YE",
    "name:ara_x_preferred":[
        "\u0627\u0644 \u062d\u062f\u0628\u0627\u0646"
    ],
    "name:und_x_variant":[
        "Alt Jadb\u0101n",
        "\u0100l \u1e28adb\u0101n"
    ],
    "wof:name":"Al Hadban",
    "wof:placetype":"locality"
},
  "geometry": {"coordinates":[43.34569000000001,16.8807],"type":"Point"}
}