{
  "type": "Feature",
  "properties": {
    "gn:admin1_code":"23.0",
    "gn:admin2_code":"1101.0",
    "gn:asciiname":"As Sabt",
    "gn:country_code":"YE",
    "gn:dem":1359,
    "gn:feature_class":"P",
    "gn:feature_code":"PPL",
    "gn:name":"As Sabt",
    "gn:population":0,
    "gn:timezone":"Asia/Aden",
    "iso:country":"YE",
    "name:ara_x_preferred":[
        "\u0627\u0644\u0633\u0628\u062a"
    ],
    "name:und_x_variant":[
        "Sabt al Kar\u0101bah",
        "As Sabt"
    ],
    "wof:name":"As Sabt",
    "wof:placetype":"locality"
},
  "geometry": {"coordinates":[44.06187,14.42685],"type":"Point"}
}