{
  "type": "Feature",
  "properties": {
    "gn:admin1_code":"24.0",
    "gn:admin2_code":"2512.0",
    "gn:asciiname":"Al Hujjaj",
    "gn:country_code":"YE",
    "gn:dem":1774,
    "gn:feature_class":"P",
    "gn:feature_code":"PPL",
    "gn:name":"Al \u1e28ujj\u0101j",
    "gn:population":0,
    "gn:timezone":"Asia/Aden",
    "iso:country":"YE",
    "name:ara_x_preferred":[
        "\u0627\u0644\u062d\u062c\u0627\u062c"
    ],
    "name:und_x_variant":[
        "Al \u1e28ujj\u0101j",
        "Al \u1e28ajj\u0101j"
    ],
    "wof:name":"Al Hujjaj",
    "wof:placetype":"locality"
},
  "geometry": {"coordinates":[44.18225,13.18104],"type":"Point"}
}