{
  "type": "Feature",
  "properties": {
    "gn:admin1_code":"24.0",
    "gn:admin2_code":"2513.0",
    "gn:asciiname":"Al `Affaj",
    "gn:country_code":"YE",
    "gn:dem":339,
    "gn:feature_class":"P",
    "gn:feature_code":"PPL",
    "gn:name":"Al \u2018Aff\u0101j",
    "gn:population":0,
    "gn:timezone":"Asia/Aden",
    "iso:country":"YE",
    "name:ara_x_preferred":[
        "Al \u2018Aff\u0101j"
    ],
    "wof:name":"Al `Affaj",
    "wof:placetype":"locality"
},
  "geometry": {"coordinates":[44.11008,12.94072],"type":"Point"}
}