{
  "type": "Feature",
  "properties": {
    "gn:admin1_code":"25.0",
    "gn:admin2_code":"1513.0",
    "gn:asciiname":"Ghuwayl",
    "gn:country_code":"YE",
    "gn:dem":1376,
    "gn:feature_class":"P",
    "gn:feature_code":"PPL",
    "gn:name":"Ghuwayl",
    "gn:population":0,
    "gn:timezone":"Asia/Aden",
    "iso:country":"YE",
    "wof:name":"Ghuwayl",
    "wof:placetype":"locality"
},
  "geometry": {"coordinates":[44.13244,13.46072],"type":"Point"}
}