{
  "type": "Feature",
  "properties": {
    "gn:admin1_code":"25.0",
    "gn:admin2_code":"1505.0",
    "gn:asciiname":"Marah",
    "gn:country_code":"YE",
    "gn:dem":672,
    "gn:feature_class":"P",
    "gn:feature_code":"PPL",
    "gn:name":"Mara\u1e29",
    "gn:population":0,
    "gn:timezone":"Asia/Aden",
    "iso:country":"YE",
    "name:und_x_variant":[
        "Mara\u1e29"
    ],
    "wof:name":"Marah",
    "wof:placetype":"locality"
},
  "geometry": {"coordinates":[43.64974,13.56446],"type":"Point"}
}