{
  "type": "Feature",
  "properties": {
    "gn:country":"YE",
    "gn:fcode":"PPLA2",
    "gn:pop":645,
    "iso:country":"YE",
    "name:ara_x_preferred":[
        "\u0633\u062d\u064a\u0644 \u0634\u0628\u0627\u0645"
    ],
    "qs:name":"Su\u1e29ayl Shib\u0101m",
    "qs:photos_9r":0,
    "qs:photos_sr":0,
    "qs:pop_sr":"2",
    "wof:name":"Su\u1e29ayl Shib\u0101m",
    "wof:placetype":"locality",
    "wof:population":645
},
  "geometry": {"coordinates":[48.63864,15.91448],"type":"Point"}
}