{
  "type": "Feature",
  "properties": {
    "gn:admin1_code":"8.0",
    "gn:admin2_code":"1817.0",
    "gn:asciiname":"Buyut Sulayman Hibah",
    "gn:country_code":"YE",
    "gn:dem":81,
    "gn:feature_class":"P",
    "gn:feature_code":"PPL",
    "gn:name":"Buy\u016bt Sulaym\u0101n Hibah",
    "gn:population":0,
    "gn:timezone":"Asia/Aden",
    "iso:country":"YE",
    "name:und_x_variant":[
        "Buy\u016bt Sulaym\u0101n Hibah"
    ],
    "wof:name":"Buyut Sulayman Hibah",
    "wof:placetype":"locality"
},
  "geometry": {"coordinates":[43.22412,14.40849],"type":"Point"}
}