{
  "type": "Feature",
  "properties": {
    "gn:admin1_code":"25.0",
    "gn:admin2_code":"1515.0",
    "gn:asciiname":"Al Mahilah",
    "gn:country_code":"YE",
    "gn:dem":1922,
    "gn:feature_class":"P",
    "gn:feature_code":"PPL",
    "gn:name":"Al Ma\u1e29\u012blah",
    "gn:population":0,
    "gn:timezone":"Asia/Aden",
    "iso:country":"YE",
    "name:ara_x_preferred":[
        "Dh\u0101fir"
    ],
    "name:ara_x_variant":[
        "\u0627\u0644\u0645\u062d\u064a\u0644\u0629"
    ],
    "name:und_x_variant":[
        "Al Ma\u1e29\u012blah"
    ],
    "wof:name":"Al Mahilah",
    "wof:placetype":"locality"
},
  "geometry": {"coordinates":[44.13476,13.23087],"type":"Point"}
}