{
  "type": "Feature",
  "properties": {
    "gn:admin1_code":"11.0",
    "gn:admin2_code":"2005.0",
    "gn:asciiname":"Al Barr",
    "gn:country_code":"YE",
    "gn:dem":1741,
    "gn:feature_class":"P",
    "gn:feature_code":"PPL",
    "gn:name":"Al Barr",
    "gn:population":0,
    "gn:timezone":"Asia/Aden",
    "iso:country":"YE",
    "wof:name":"Al Barr",
    "wof:placetype":"locality"
},
  "geometry": {"coordinates":[44.05563,14.48439],"type":"Point"}
}