{
  "type": "Feature",
  "properties": {
    "gn:admin1_code":"11.0",
    "gn:admin2_code":"2005.0",
    "gn:asciiname":"Al Barr",
    "gn:country_code":"YE",
    "gn:dem":1741,
    "gn:feature_class":"P",
    "gn:feature_code":"PPL",
    "gn:name":"Al Barr",
    "gn:population":0,
    "gn:timezone":"Asia/Aden",
    "iso:country":"YE",
    "name:ara_x_preferred":[
        "\u0623\u0644 \u0628\u0627\u0631"
    ],
    "name:azb_x_preferred":[
        "\u0627\u0644 \u0628\u0627\u0631"
    ],
    "name:dan_x_preferred":[
        "Al Barr"
    ],
    "name:deu_x_preferred":[
        "Al Barr"
    ],
    "name:fas_x_preferred":[
        "\u0627\u0644 \u0628\u0627\u0631"
    ],
    "name:fra_x_preferred":[
        "Al Barr"
    ],
    "name:ita_x_preferred":[
        "Al Barr"
    ],
    "name:nld_x_preferred":[
        "Al Barr"
    ],
    "name:pol_x_preferred":[
        "Al Barr"
    ],
    "name:por_x_preferred":[
        "Al Barr"
    ],
    "name:rus_x_preferred":[
        "\u0411\u0430\u0440\u0440"
    ],
    "name:swe_x_preferred":[
        "Al Barr"
    ],
    "wof:name":"Al Barr",
    "wof:placetype":"locality"
},
  "geometry": {"coordinates":[44.05563,14.48439],"type":"Point"}
}