{
  "type": "Feature",
  "properties": {
    "gn:admin1_code":"20.0",
    "gn:admin2_code":"1412.0",
    "gn:asciiname":"Al `Ayl",
    "gn:country_code":"YE",
    "gn:dem":2066,
    "gn:feature_class":"P",
    "gn:feature_code":"PPL",
    "gn:name":"Al \u2018Ayl",
    "gn:population":0,
    "gn:timezone":"Asia/Aden",
    "iso:country":"YE",
    "name:ara_x_preferred":[
        "Al \u2018Ayl"
    ],
    "name:ara_x_variant":[
        "\u0627\u0644\u0639\u064a\u0644"
    ],
    "wof:name":"Al `Ayl",
    "wof:placetype":"locality"
},
  "geometry": {"coordinates":[45.27352,14.53968],"type":"Point"}
}