{
  "type": "Feature",
  "properties": {
    "gn:country":"YE",
    "gn:fcode":"PPLA2",
    "gn:population":69404,
    "iso:country":"YE",
    "name:ara_x_preferred":[
        "\u0633\u064a\u0627\u0646"
    ],
    "name:ceb_x_preferred":[
        "Sayy\u0101n"
    ],
    "name:eng_x_preferred":[
        "Sayyan"
    ],
    "name:fas_x_preferred":[
        "\u0633\u06cc\u0627\u0646"
    ],
    "name:fra_x_preferred":[
        "Sayyan"
    ],
    "name:jpn_x_preferred":[
        "\u30b5\u30a4\u30e4\u30fc\u30f3"
    ],
    "name:nld_x_preferred":[
        "Sayyan"
    ],
    "name:nno_x_preferred":[
        "Sayyan"
    ],
    "name:pol_x_preferred":[
        "Sajjan"
    ],
    "name:und_x_variant":[
        "Saiy\u0101n"
    ],
    "qs:name":"Sayy\u0101n",
    "qs:photos_9r":0,
    "qs:photos_sr":0,
    "qs:pop_sr":"8",
    "wd:wordcount":121,
    "wof:name":"Sayy\u0101n",
    "wof:placetype":"locality",
    "wof:population":69404
},
  "geometry": {"coordinates":[44.32442,15.17177],"type":"Point"}
}