{
  "type": "Feature",
  "properties": {
    "gn:country":"YE",
    "gn:fcode":"PPLA2",
    "gn:pop":69404,
    "iso:country":"YE",
    "name:ara_x_preferred":[
        "\u0633\u064a\u0627\u0646"
    ],
    "name:unk_x_variant":[
        "Saiy\u0101n"
    ],
    "qs:name":"Sayy\u0101n",
    "qs:photos_9r":0,
    "qs:photos_sr":0,
    "qs:pop_sr":"8",
    "wd:wordcount":121,
    "wof:name":"Sayy\u0101n",
    "wof:placetype":"locality",
    "wof:population":69404
},
  "geometry": {"coordinates":[44.32442,15.17177],"type":"Point"}
}