{
  "type": "Feature",
  "properties": {
    "gn:admin1_code":"15.0",
    "gn:admin2_code":"2209.0",
    "gn:asciiname":"Al `Ala` Wadi Saqayn",
    "gn:country_code":"YE",
    "gn:dem":2280,
    "gn:feature_class":"P",
    "gn:feature_code":"PPL",
    "gn:name":"Al \u2018Al\u0101\u2018 W\u0101d\u012b S\u0101qayn",
    "gn:population":0,
    "gn:timezone":"Asia/Aden",
    "iso:country":"YE",
    "name:und_x_variant":[
        "Al \u2018Al\u0101\u2018 W\u0101d\u012b S\u0101qayn"
    ],
    "wof:name":"Al `Ala` Wadi Saqayn",
    "wof:placetype":"locality"
},
  "geometry": {"coordinates":[43.52724,16.88735],"type":"Point"}
}