{
  "type": "Feature",
  "properties": {
    "gn:admin1_code":"19.0",
    "gn:admin2_code":"2919.0",
    "gn:asciiname":"Bayt ash Shaqdhah",
    "gn:country_code":"YE",
    "gn:dem":2487,
    "gn:feature_class":"P",
    "gn:feature_code":"PPL",
    "gn:name":"Bayt ash Shaqdhah",
    "gn:population":0,
    "gn:timezone":"Asia/Aden",
    "iso:country":"YE",
    "name:ara_x_preferred":[
        "\u0628\u064a\u062a \u0627\u0644\u0634\u0642\u0630\u0629"
    ],
    "wof:name":"Bayt ash Shaqdhah",
    "wof:placetype":"locality"
},
  "geometry": {"coordinates":[43.99144,16.0232],"type":"Point"}
}