{
  "type": "Feature",
  "properties": {
    "gn:country":"YE",
    "gn:fcode":"PPL",
    "gn:pop":64,
    "iso:country":"YE",
    "name:ara_x_preferred":[
        "\u0622\u0644 \u0645\u0633\u0639\u0648\u062f"
    ],
    "name:eng_x_preferred":[
        "Al Mas'Ud"
    ],
    "name:eng_x_variant":[
        "Al \u2018Am\u012bsh"
    ],
    "qs:name":"\u0100l Mas\u2018\u016bd",
    "qs:photos_9r":0,
    "qs:photos_sr":0,
    "qs:pop_sr":"1",
    "wof:name":"\u0100l Mas\u2018\u016bd",
    "wof:placetype":"locality",
    "wof:population":64
},
  "geometry": {"coordinates":[43.72424,16.94844],"type":"Point"}
}