{
  "type": "Feature",
  "properties": {
    "gn:admin1_code":"4.0",
    "gn:admin2_code":"1907.0",
    "gn:asciiname":"`Ard Al Huwayl",
    "gn:country_code":"YE",
    "gn:dem":697,
    "gn:feature_class":"P",
    "gn:feature_code":"PPL",
    "gn:name":"\u2018Ar\u1e11 \u0100l \u1e28uwayl",
    "gn:population":0,
    "gn:timezone":"Asia/Aden",
    "iso:country":"YE",
    "name:und_x_variant":[
        "\u2018Ar\u1e0d \u0100l \u1e24awail",
        "\u2018Ar\u1e11 \u0100l \u1e28uwayl"
    ],
    "wof:name":"`Ard Al Huwayl",
    "wof:placetype":"locality"
},
  "geometry": {"coordinates":[48.26667,15.83333],"type":"Point"}
}