{
  "type": "Feature",
  "properties": {
    "gn:country":"YE",
    "gn:fcode":"PPL",
    "gn:pop":8,
    "iso:country":"YE",
    "name:ara_x_preferred":[
        "\u0627\u0644\u062b\u0648\u0627\u0647\u0631"
    ],
    "qs:name":"Ath Thaw\u0101hir",
    "qs:photos_9r":0,
    "qs:photos_sr":0,
    "qs:pop_sr":"1",
    "wof:name":"Ath Thaw\u0101hir",
    "wof:placetype":"locality",
    "wof:population":8
},
  "geometry": {"coordinates":[43.40712,16.13818],"type":"Point"}
}