{
  "type": "Feature",
  "properties": {
    "gn:admin1_code":"8.0",
    "gn:admin2_code":"1806.0",
    "gn:asciiname":"Dar al Kalfud",
    "gn:country_code":"YE",
    "gn:dem":82,
    "gn:feature_class":"P",
    "gn:feature_code":"PPL",
    "gn:name":"D\u0101r al Kalf\u016bd",
    "gn:population":0,
    "gn:timezone":"Asia/Aden",
    "iso:country":"YE",
    "name:und_x_variant":[
        "D\u0101r al Kalf\u016bd"
    ],
    "wof:name":"Dar al Kalfud",
    "wof:placetype":"locality"
},
  "geometry": {"coordinates":[43.09617,15.39484],"type":"Point"}
}