{
  "type": "Feature",
  "properties": {
    "gn:country":"YE",
    "gn:fcode":"PPL",
    "gn:pop":15,
    "iso:country":"YE",
    "name:ara_x_preferred":[
        "\u0627\u0644\u062e\u0631\u0628\u0629"
    ],
    "name:eng_x_preferred":[
        "Al Kharabah"
    ],
    "name:eng_x_variant":[
        "Sirr J\u0101bir"
    ],
    "qs:name":"Al Kharabah",
    "qs:photos_9r":0,
    "qs:photos_sr":0,
    "qs:pop_sr":"1",
    "wd:wordcount":25,
    "wof:name":"Al Kharabah",
    "wof:placetype":"locality",
    "wof:population":15
},
  "geometry": {"coordinates":[43.85743,13.34872],"type":"Point"}
}