{
  "type": "Feature",
  "properties": {
    "gn:admin1_code":"10.0",
    "gn:admin2_code":"2704.0",
    "gn:asciiname":"Shathah",
    "gn:country_code":"YE",
    "gn:dem":1272,
    "gn:feature_class":"P",
    "gn:feature_code":"PPL",
    "gn:name":"Sh\u0101thah",
    "gn:population":0,
    "gn:timezone":"Asia/Aden",
    "iso:country":"YE",
    "name:ara_x_preferred":[
        "\u0634\u0637\u062d\u0629"
    ],
    "name:ceb_x_preferred":[
        "Sha\u0163\u1e29ah"
    ],
    "name:fas_x_preferred":[
        "\u0634\u0637\u062d\u0647"
    ],
    "name:hye_x_preferred":[
        "\u0547\u0561\u057f\u0570\u0561"
    ],
    "name:nno_x_preferred":[
        "Shathah"
    ],
    "name:pol_x_preferred":[
        "Szatha at-Tahta"
    ],
    "name:rus_x_preferred":[
        "\u0428\u0430\u0442\u0445\u0430"
    ],
    "name:sco_x_preferred":[
        "Shathah"
    ],
    "name:und_x_variant":[
        "Sh\u0101thah"
    ],
    "name:vie_x_preferred":[
        "Shathah"
    ],
    "wof:name":"Shathah",
    "wof:placetype":"locality"
},
  "geometry": {"coordinates":[43.41644,15.51268],"type":"Point"}
}