{
  "type": "Feature",
  "properties": {
    "gn:admin1_code":"10.0",
    "gn:admin2_code":"2704.0",
    "gn:asciiname":"Shathah",
    "gn:country_code":"YE",
    "gn:dem":1272,
    "gn:feature_class":"P",
    "gn:feature_code":"PPL",
    "gn:name":"Sh\u0101thah",
    "gn:population":0,
    "gn:timezone":"Asia/Aden",
    "iso:country":"YE",
    "name:und_x_variant":[
        "Sh\u0101thah"
    ],
    "wof:name":"Shathah",
    "wof:placetype":"locality"
},
  "geometry": {"coordinates":[43.41644,15.51268],"type":"Point"}
}