{
  "type": "Feature",
  "properties": {
    "gn:admin1_code":"23.0",
    "gn:admin2_code":"1101.0",
    "gn:asciiname":"Al Maqrud",
    "gn:country_code":"YE",
    "gn:dem":1256,
    "gn:feature_class":"P",
    "gn:feature_code":"PPL",
    "gn:name":"Al Maqr\u016b\u1e11",
    "gn:population":0,
    "gn:timezone":"Asia/Aden",
    "iso:country":"YE",
    "name:ara_x_preferred":[
        "\u0627\u0644\u0645\u0642\u0631\u0648\u0636"
    ],
    "name:und_x_variant":[
        "Al Maqr\u016b\u1e11"
    ],
    "wof:name":"Al Maqrud",
    "wof:placetype":"locality"
},
  "geometry": {"coordinates":[44.07059,14.29259],"type":"Point"}
}