{
  "type": "Feature",
  "properties": {
    "gn:admin1_code":"4.0",
    "gn:admin2_code":"1922.0",
    "gn:asciiname":"Burayyirah",
    "gn:cc2":"YE",
    "gn:country_code":"YE",
    "gn:dem":1433,
    "gn:feature_class":"P",
    "gn:feature_code":"PPL",
    "gn:name":"Burayyirah",
    "gn:population":0,
    "gn:timezone":"Asia/Aden",
    "iso:country":"YE",
    "name:nno_x_preferred":[
        "Burayyirah"
    ],
    "name:und_x_variant":[
        "Buraiyirah"
    ],
    "wof:name":"Burayyirah",
    "wof:placetype":"locality"
},
  "geometry": {"coordinates":[48.06667,15.05],"type":"Point"}
}