{
  "type": "Feature",
  "properties": {
    "gn:country":"YE",
    "gn:fcode":"PPL",
    "gn:population":5,
    "iso:country":"YE",
    "name:ara_x_preferred":[
        "\u062d\u0648\u0629 \u062d\u0630\u0648\u0644"
    ],
    "name:eng_x_preferred":[
        "Hawwah HadhUl"
    ],
    "name:eng_x_variant":[
        "Ath Thim\u0101r"
    ],
    "qs:name":"\u1e28awwah \u1e28adh\u016bl",
    "qs:photos_9r":0,
    "qs:photos_sr":0,
    "qs:pop_sr":"1",
    "wof:name":"\u1e28awwah \u1e28adh\u016bl",
    "wof:placetype":"locality",
    "wof:population":5
},
  "geometry": {"coordinates":[44.47274,16.64363],"type":"Point"}
}