{
  "type": "Feature",
  "properties": {
    "gn:admin1_code":"25.0",
    "gn:admin2_code":"1515.0",
    "gn:asciiname":"Al Quhayfah",
    "gn:country_code":"YE",
    "gn:dem":1196,
    "gn:feature_class":"P",
    "gn:feature_code":"PPL",
    "gn:name":"Al Qu\u1e29ayfah",
    "gn:population":0,
    "gn:timezone":"Asia/Aden",
    "iso:country":"YE",
    "name:ara_x_preferred":[
        "\u0627\u0644\u0642\u062d\u064a\u0641\u0629"
    ],
    "name:und_x_variant":[
        "Al Qu\u1e29ayfah"
    ],
    "wof:name":"Al Quhayfah",
    "wof:placetype":"locality"
},
  "geometry": {"coordinates":[43.95981,13.19917],"type":"Point"}
}