{
  "type": "Feature",
  "properties": {
    "gn:admin1_code":"23.0",
    "gn:admin2_code":"1104.0",
    "gn:asciiname":"Ribat Salih",
    "gn:country_code":"YE",
    "gn:dem":2396,
    "gn:feature_class":"P",
    "gn:feature_code":"PPL",
    "gn:name":"Rib\u0101\u0163 \u015e\u0101li\u1e29",
    "gn:population":0,
    "gn:timezone":"Asia/Aden",
    "iso:country":"YE",
    "name:ara_x_preferred":[
        "Rib\u0101\u0163 \u015e\u0101li\u1e29"
    ],
    "name:ara_x_variant":[
        "\u0631\u0628\u0627\u0637 \u0635\u0627\u0644\u062d"
    ],
    "wof:name":"Ribat Salih",
    "wof:placetype":"locality"
},
  "geometry": {"coordinates":[44.46276,14.03209],"type":"Point"}
}