{
  "type": "Feature",
  "properties": {
    "gn:admin1_code":"22.0",
    "gn:admin2_code":"1726.0",
    "gn:asciiname":"Dhira` al Khatam",
    "gn:country_code":"YE",
    "gn:dem":816,
    "gn:feature_class":"P",
    "gn:feature_code":"PPL",
    "gn:name":"Dhir\u0101\u2018 al Kha\u0163\u0101m",
    "gn:population":0,
    "gn:timezone":"Asia/Aden",
    "iso:country":"YE",
    "name:und_x_variant":[
        "Dhir\u0101\u2018 al Kha\u0163\u0101m"
    ],
    "wof:name":"Dhira` al Khatam",
    "wof:placetype":"locality"
},
  "geometry": {"coordinates":[43.54928,15.67305],"type":"Point"}
}