{
  "type": "Feature",
  "properties": {
    "gn:admin1_code":"8.0",
    "gn:admin2_code":"1812.0",
    "gn:asciiname":"Al Majban",
    "gn:country_code":"YE",
    "gn:dem":1386,
    "gn:feature_class":"P",
    "gn:feature_code":"PPL",
    "gn:name":"Al Majban",
    "gn:population":0,
    "gn:timezone":"Asia/Aden",
    "iso:country":"YE",
    "name:ara_x_preferred":[
        "\u0627\u0644\u0645\u062c\u0628\u0646"
    ],
    "wof:name":"Al Majban",
    "wof:placetype":"locality"
},
  "geometry": {"coordinates":[43.44129,14.90338],"type":"Point"}
}