{
  "type": "Feature",
  "properties": {
    "gn:admin1_code":"20.0",
    "gn:admin2_code":"1420.0",
    "gn:asciiname":"Al Watiyah",
    "gn:country_code":"YE",
    "gn:dem":2034,
    "gn:feature_class":"P",
    "gn:feature_code":"PPL",
    "gn:name":"Al Wa\u0163\u012byah",
    "gn:population":0,
    "gn:timezone":"Asia/Aden",
    "iso:country":"YE",
    "name:ara_x_preferred":[
        "\u0627\u0644\u0648\u0637\u064a\u0629"
    ],
    "name:und_x_variant":[
        "Al Wa\u0163\u012byah"
    ],
    "wof:name":"Al Watiyah",
    "wof:placetype":"locality"
},
  "geometry": {"coordinates":[45.34558,14.34846],"type":"Point"}
}