{
  "type": "Feature",
  "properties": {
    "gn:admin1_code":"19.0",
    "gn:admin2_code":"2916.0",
    "gn:asciiname":"Al Juruf",
    "gn:country_code":"YE",
    "gn:dem":2451,
    "gn:feature_class":"P",
    "gn:feature_code":"PPL",
    "gn:name":"Al Jur\u016bf",
    "gn:population":0,
    "gn:timezone":"Asia/Aden",
    "iso:country":"YE",
    "name:ara_x_preferred":[
        "Al Jur\u016bf"
    ],
    "wof:name":"Al Juruf",
    "wof:placetype":"locality"
},
  "geometry": {"coordinates":[43.68384,15.59066],"type":"Point"}
}