{
  "type": "Feature",
  "properties": {
    "gn:admin1_code":"16.0",
    "gn:admin2_code":"2316.0",
    "gn:asciiname":"Mahwash",
    "gn:country_code":"YE",
    "gn:dem":2339,
    "gn:feature_class":"P",
    "gn:feature_code":"PPL",
    "gn:name":"Ma\u1e29wash",
    "gn:population":0,
    "gn:timezone":"Asia/Aden",
    "iso:country":"YE",
    "name:und_x_variant":[
        "Ma\u1e29wash"
    ],
    "wof:name":"Mahwash",
    "wof:placetype":"locality"
},
  "geometry": {"coordinates":[44.41667,15.21667],"type":"Point"}
}