{
  "type": "Feature",
  "properties": {
    "gn:admin1_code":"19.0",
    "gn:admin2_code":"2907.0",
    "gn:asciiname":"Al Manjarah",
    "gn:country_code":"YE",
    "gn:dem":1004,
    "gn:feature_class":"P",
    "gn:feature_code":"PPL",
    "gn:name":"Al Manjarah",
    "gn:population":0,
    "gn:timezone":"Asia/Aden",
    "iso:country":"YE",
    "name:ara_x_preferred":[
        "\u0627\u0644\u0645\u0646\u062c\u0631\u0629"
    ],
    "wof:name":"Al Manjarah",
    "wof:placetype":"locality"
},
  "geometry": {"coordinates":[43.61366,16.03843],"type":"Point"}
}