{
  "type": "Feature",
  "properties": {
    "gn:admin1_code":"19.0",
    "gn:admin2_code":"2920.0",
    "gn:asciiname":"Bayt al Hajuri",
    "gn:country_code":"YE",
    "gn:dem":2072,
    "gn:feature_class":"P",
    "gn:feature_code":"PPL",
    "gn:name":"Bayt al \u1e28aj\u016br\u012b",
    "gn:population":0,
    "gn:timezone":"Asia/Aden",
    "iso:country":"YE",
    "name:ara_x_preferred":[
        "\u0628\u064a\u062a \u0627\u0644\u062d\u062c\u0648\u0631\u064a"
    ],
    "name:und_x_variant":[
        "Bayt al Hijr\u012b",
        "Bayt al \u1e28aj\u016br\u012b"
    ],
    "wof:name":"Bayt al Hajuri",
    "wof:placetype":"locality"
},
  "geometry": {"coordinates":[43.91954000000001,16.15489],"type":"Point"}
}