{
  "type": "Feature",
  "properties": {
    "gn:admin1_code":"24.0",
    "gn:admin2_code":"2512.0",
    "gn:asciiname":"Al Kahif",
    "gn:country_code":"YE",
    "gn:dem":1410,
    "gn:feature_class":"P",
    "gn:feature_code":"PPL",
    "gn:name":"Al Ka\u1e29\u012bf",
    "gn:population":0,
    "gn:timezone":"Asia/Aden",
    "iso:country":"YE",
    "name:ara_x_preferred":[
        "\u0627\u0644\u0643\u062d\u064a\u0641"
    ],
    "name:und_x_variant":[
        "Al Ka\u1e29\u012bf"
    ],
    "wof:name":"Al Kahif",
    "wof:placetype":"locality"
},
  "geometry": {"coordinates":[44.19462,13.16996],"type":"Point"}
}