{
  "type": "Feature",
  "properties": {
    "gn:country":"YE",
    "gn:fcode":"PPL",
    "gn:population":2,
    "iso:country":"YE",
    "name:ara_x_preferred":[
        "\u0627\u0644\u0633\u0648\u062f"
    ],
    "name:ara_x_variant":[
        "\u0633\u0648\u0627\u062f \u0627\u0644\u0639\u0631\u0627\u0642"
    ],
    "name:cat_x_preferred":[
        "Sawad"
    ],
    "name:eng_x_preferred":[
        "Sawad"
    ],
    "name:fas_x_preferred":[
        "\u0633\u0648\u0627\u062f"
    ],
    "name:fra_x_preferred":[
        "Sawad"
    ],
    "name:ind_x_preferred":[
        "Sawad"
    ],
    "name:ita_x_preferred":[
        "Sawad"
    ],
    "name:jpn_x_preferred":[
        "\u30b5\u30ef\u30fc\u30c9"
    ],
    "name:por_x_preferred":[
        "Savad"
    ],
    "name:rus_x_preferred":[
        "\u0421\u0430\u0432\u0430\u0434"
    ],
    "name:srp_x_preferred":[
        "\u0421\u0430\u0432\u0430\u0434"
    ],
    "name:vec_x_preferred":[
        "Sawad"
    ],
    "name:zho_x_preferred":[
        "\u8428\u74e6\u5fb7"
    ],
    "qs:name":"As Sawad",
    "qs:photos_9r":0,
    "qs:photos_sr":0,
    "qs:pop_sr":"1",
    "wd:wordcount":158,
    "wof:name":"As Sawad",
    "wof:placetype":"locality",
    "wof:population":2
},
  "geometry": {"coordinates":[43.41113,16.29243],"type":"Point"}
}