{
  "type": "Feature",
  "properties": {
    "gn:country":"YE",
    "gn:fcode":"PPL",
    "gn:pop":2,
    "iso:country":"YE",
    "name:ara_x_preferred":[
        "\u0627\u0644\u0633\u0648\u062f"
    ],
    "qs:name":"As Sawad",
    "qs:photos_9r":0,
    "qs:photos_sr":0,
    "qs:pop_sr":"1",
    "wd:wordcount":158,
    "wof:name":"As Sawad",
    "wof:placetype":"locality",
    "wof:population":2
},
  "geometry": {"coordinates":[43.41113,16.29243],"type":"Point"}
}