{
  "type": "Feature",
  "properties": {
    "gn:admin1_code":"22.0",
    "gn:admin2_code":"1725.0",
    "gn:asciiname":"Bayt al 'Aql",
    "gn:country_code":"YE",
    "gn:dem":735,
    "gn:feature_class":"P",
    "gn:feature_code":"PPL",
    "gn:name":"Bayt al \u2018Aql",
    "gn:population":0,
    "gn:timezone":"Asia/Aden",
    "iso:country":"YE",
    "name:ara_x_preferred":[
        "\u0628\u064a\u062a \u0627\u0644\u0639\u0642\u0644"
    ],
    "name:und_x_variant":[
        "Bayt al \u2018Aql"
    ],
    "wof:name":"Bayt al 'Aql",
    "wof:placetype":"locality"
},
  "geometry": {"coordinates":[43.5316,15.5762],"type":"Point"}
}