{
  "type": "Feature",
  "properties": {
    "gn:admin1_code":"19.0",
    "gn:admin2_code":"2918.0",
    "gn:asciiname":"Al 'Ushshah",
    "gn:country_code":"YE",
    "gn:dem":2237,
    "gn:feature_class":"P",
    "gn:feature_code":"PPL",
    "gn:name":"Al \u2018Ushshah",
    "gn:population":0,
    "gn:timezone":"Asia/Aden",
    "iso:country":"YE",
    "name:ara_x_preferred":[
        "\u0627\u0644\u0639\u0634\u0629"
    ],
    "name:und_x_variant":[
        "Al \u2018Ushshah"
    ],
    "wof:name":"Al 'Ushshah",
    "wof:placetype":"locality"
},
  "geometry": {"coordinates":[44.01195,15.70554],"type":"Point"}
}