{
  "type": "Feature",
  "properties": {
    "gn:admin1_code":"8.0",
    "gn:admin2_code":"1810.0",
    "gn:asciiname":"Al Barid",
    "gn:country_code":"YE",
    "gn:dem":138,
    "gn:feature_class":"P",
    "gn:feature_code":"PPL",
    "gn:name":"Al B\u0101rid",
    "gn:population":0,
    "gn:timezone":"Asia/Aden",
    "iso:country":"YE",
    "name:ara_x_preferred":[
        "Al B\u0101rid"
    ],
    "wof:name":"Al Barid",
    "wof:placetype":"locality"
},
  "geometry": {"coordinates":[43.20245,15.08879],"type":"Point"}
}