{
  "type": "Feature",
  "properties": {
    "gn:country":"YE",
    "gn:fcode":"PPL",
    "gn:population":21,
    "iso:country":"YE",
    "name:ara_x_preferred":[
        "\u0627\u0644\u0645\u0639\u0645\u0631"
    ],
    "qs:name":"Al Ma\u2018mar",
    "qs:photos_9r":0,
    "qs:photos_sr":0,
    "qs:pop_sr":"1",
    "wof:name":"Al Ma\u2018mar",
    "wof:placetype":"locality",
    "wof:population":21
},
  "geometry": {"coordinates":[43.70938,16.94432],"type":"Point"}
}