{
  "type": "Feature",
  "properties": {
    "gn:country":"YE",
    "gn:fcode":"PPL",
    "gn:pop":1,
    "iso:country":"YE",
    "name:ara_x_preferred":[
        "Al Mishr\u0101\u1e29"
    ],
    "name:ara_x_variant":[
        "\u0627\u0644\u0645\u0634\u0631\u0627\u062d"
    ],
    "name:eng_x_preferred":[
        "Al Mishrah"
    ],
    "qs:name":"Al Mishr\u0101\u1e29",
    "qs:photos_9r":0,
    "qs:photos_sr":0,
    "qs:pop_sr":"1",
    "wof:name":"Al Mishr\u0101\u1e29",
    "wof:placetype":"locality",
    "wof:population":1
},
  "geometry": {"coordinates":[43.85188,13.40811],"type":"Point"}
}