{
  "type": "Feature",
  "properties": {
    "gn:admin1_code":"25.0",
    "gn:admin2_code":"1505.0",
    "gn:asciiname":"Maghrabat Bani Ja`far",
    "gn:country_code":"YE",
    "gn:dem":1110,
    "gn:feature_class":"P",
    "gn:feature_code":"PPL",
    "gn:name":"Maghrabat Ban\u012b Ja\u2018far",
    "gn:population":0,
    "gn:timezone":"Asia/Aden",
    "iso:country":"YE",
    "name:und_x_variant":[
        "Maghrabat Ban\u012b Ja\u2018far"
    ],
    "wof:name":"Maghrabat Bani Ja`far",
    "wof:placetype":"locality"
},
  "geometry": {"coordinates":[43.7227,13.68433],"type":"Point"}
}