{
  "type": "Feature",
  "properties": {
    "gn:admin1_code":"23.0",
    "gn:admin2_code":"1107.0",
    "gn:asciiname":"Az Zirah",
    "gn:cc2":"YE",
    "gn:country_code":"YE",
    "gn:dem":2224,
    "gn:feature_class":"P",
    "gn:feature_code":"PPL",
    "gn:name":"Az Z\u012brah",
    "gn:population":0,
    "gn:timezone":"Asia/Aden",
    "iso:country":"YE",
    "name:und_x_variant":[
        "Ez Zira",
        "Az Z\u012brah"
    ],
    "wof:name":"Az Zirah",
    "wof:placetype":"locality"
},
  "geometry": {"coordinates":[44.23333,14.08333],"type":"Point"}
}