{
  "type": "Feature",
  "properties": {
    "gn:country":"YE",
    "gn:fcode":"PPL",
    "gn:pop":10,
    "iso:country":"YE",
    "name:ara_x_preferred":[
        "\u0627\u0644 \u0632\u064a\u062f\u0629"
    ],
    "name:eng_x_preferred":[
        "Al Zaydah"
    ],
    "name:eng_x_variant":[
        "Sha\u2018b al \u1e28amr"
    ],
    "qs:name":"\u0100l Zaydah",
    "qs:photos_9r":0,
    "qs:photos_sr":0,
    "qs:pop_sr":"1",
    "wd:wordcount":23,
    "wof:name":"\u0100l Zaydah",
    "wof:placetype":"locality",
    "wof:population":10
},
  "geometry": {"coordinates":[45.33598,15.39579],"type":"Point"}
}