{
  "type": "Feature",
  "properties": {
    "gn:country":"YE",
    "gn:fcode":"FRM",
    "gn:population":1,
    "iso:country":"YE",
    "name:ara_x_preferred":[
        "\u062e\u0628\u0627\u062b\u0629"
    ],
    "qs:name":"Khab\u0101thah",
    "qs:photos_9r":0,
    "qs:photos_sr":0,
    "qs:pop_sr":"1",
    "wof:name":"Khab\u0101thah",
    "wof:placetype":"locality",
    "wof:population":1
},
  "geometry": {"coordinates":[43.81144,13.43116],"type":"Point"}
}