{
  "type": "Feature",
  "properties": {
    "gn:country":"YE",
    "gn:fcode":"PPL",
    "gn:population":8,
    "iso:country":"YE",
    "name:ara_x_preferred":[
        "\u0628\u0644\u0629"
    ],
    "name:eng_x_preferred":[
        "Billah"
    ],
    "name:eng_x_variant":[
        "Al Qa\u1e11bah"
    ],
    "qs:name":"Billah",
    "qs:photos_9r":0,
    "qs:photos_sr":0,
    "qs:pop_sr":"1",
    "wd:wordcount":398,
    "wof:name":"Billah",
    "wof:placetype":"locality",
    "wof:population":8
},
  "geometry": {"coordinates":[44.32631,17.0361],"type":"Point"}
}