{
  "type": "Feature",
  "properties": {
    "gn:admin1_code":"8.0",
    "gn:admin2_code":"1825.0",
    "gn:asciiname":"Suq Muha",
    "gn:cc2":"YE",
    "gn:country_code":"YE",
    "gn:dem":226,
    "gn:feature_class":"P",
    "gn:feature_code":"PPL",
    "gn:name":"S\u016bq Muha",
    "gn:population":0,
    "gn:timezone":"Asia/Aden",
    "iso:country":"YE",
    "name:und_x_variant":[
        "Suk Muha",
        "S\u016bq Muha"
    ],
    "wof:name":"Suq Muha",
    "wof:placetype":"locality"
},
  "geometry": {"coordinates":[43.45,14.18333],"type":"Point"}
}