{
  "type": "Feature",
  "properties": {
    "gn:admin1_code":"19.0",
    "gn:admin2_code":"2908.0",
    "gn:asciiname":"As Sa'da'",
    "gn:country_code":"YE",
    "gn:dem":1020,
    "gn:feature_class":"P",
    "gn:feature_code":"PPL",
    "gn:name":"A\u015f \u015ea\u2018d\u0101\u2019",
    "gn:population":0,
    "gn:timezone":"Asia/Aden",
    "iso:country":"YE",
    "name:ara_x_preferred":[
        "\u0627\u0644\u0635\u0639\u062f\u0627\u0621"
    ],
    "name:und_x_variant":[
        "A\u015f \u015ea\u2018d\u0101\u2019"
    ],
    "wof:name":"As Sa'da'",
    "wof:placetype":"locality"
},
  "geometry": {"coordinates":[43.75316,16.05584],"type":"Point"}
}