{
  "type": "Feature",
  "properties": {
    "gn:country":"YE",
    "gn:fcode":"PPL",
    "gn:pop":3,
    "iso:country":"YE",
    "name:ara_x_preferred":[
        "\u0627\u0644\u0631\u0627\u062d\u0629"
    ],
    "qs:name":"Ar R\u0101\u1e29ah",
    "qs:photos_9r":0,
    "qs:photos_sr":0,
    "qs:pop_sr":"1",
    "wof:name":"Ar R\u0101\u1e29ah",
    "wof:placetype":"locality",
    "wof:population":3
},
  "geometry": {"coordinates":[43.36967,16.78686],"type":"Point"}
}