{
  "type": "Feature",
  "properties": {
    "gn:country":"YE",
    "gn:fcode":"PPL",
    "gn:population":23,
    "iso:country":"YE",
    "name:ara_x_preferred":[
        "\u0627\u0644\u0639\u0627\u0631\u0636\u0629"
    ],
    "name:arz_x_preferred":[
        "\u0627\u0644\u0639\u0627\u0631\u0636\u0647"
    ],
    "name:eng_x_preferred":[
        "Al 'Ariuah"
    ],
    "name:eng_x_variant":[
        "Al Qu\u1e29\u016bf"
    ],
    "qs:name":"Al \u2018\u0100ri\u1e11ah",
    "qs:photos_9r":0,
    "qs:photos_sr":0,
    "qs:pop_sr":"1",
    "wof:name":"Al \u2018\u0100ri\u1e11ah",
    "wof:placetype":"locality",
    "wof:population":23
},
  "geometry": {"coordinates":[43.78491,13.12816],"type":"Point"}
}