{
  "type": "Feature",
  "properties": {
    "gn:admin1_code":"11.0",
    "gn:admin2_code":"2002.0",
    "gn:asciiname":"Al Madarah",
    "gn:country_code":"YE",
    "gn:dem":2339,
    "gn:feature_class":"P",
    "gn:feature_code":"PPL",
    "gn:name":"Al Mad\u0101rah",
    "gn:population":0,
    "gn:timezone":"Asia/Aden",
    "iso:country":"YE",
    "name:und_x_variant":[
        "Al Mad\u0101rah"
    ],
    "wof:name":"Al Madarah",
    "wof:placetype":"locality"
},
  "geometry": {"coordinates":[44.31556,14.84443],"type":"Point"}
}