{
  "type": "Feature",
  "properties": {
    "gn:admin1_code":"8.0",
    "gn:admin2_code":"1810.0",
    "gn:asciiname":"Bani al Qudaymi",
    "gn:country_code":"YE",
    "gn:dem":370,
    "gn:feature_class":"P",
    "gn:feature_code":"PPL",
    "gn:name":"Ban\u012b al Qudaym\u012b",
    "gn:population":0,
    "gn:timezone":"Asia/Aden",
    "iso:country":"YE",
    "name:ara_x_preferred":[
        "\u0628\u0646\u064a \u0627\u0644\u0642\u062f\u064a\u0645\u064a"
    ],
    "name:und_x_variant":[
        "Ban\u012b al Qudaym\u012b"
    ],
    "wof:name":"Bani al Qudaymi",
    "wof:placetype":"locality"
},
  "geometry": {"coordinates":[43.43525,15.03064],"type":"Point"}
}