{
  "type": "Feature",
  "properties": {
    "gn:admin1_code":"25.0",
    "gn:admin2_code":"1516.0",
    "gn:asciiname":"Sabr",
    "gn:country_code":"YE",
    "gn:dem":699,
    "gn:feature_class":"P",
    "gn:feature_code":"PPL",
    "gn:name":"\u015eabr",
    "gn:population":0,
    "gn:timezone":"Asia/Aden",
    "iso:country":"YE",
    "name:ara_x_preferred":[
        "\u0635\u0628\u0631"
    ],
    "name:und_x_variant":[
        "\u015eabr"
    ],
    "wof:name":"Sabr",
    "wof:placetype":"locality"
},
  "geometry": {"coordinates":[43.85206,13.16918],"type":"Point"}
}