{
  "type": "Feature",
  "properties": {
    "gn:admin1_code":"16.0",
    "gn:admin2_code":"2302.0",
    "gn:asciiname":"Al Ma'mar",
    "gn:country_code":"YE",
    "gn:dem":1565,
    "gn:feature_class":"P",
    "gn:feature_code":"PPL",
    "gn:name":"Al Ma\u2018mar",
    "gn:population":0,
    "gn:timezone":"Asia/Aden",
    "iso:country":"YE",
    "name:ara_x_preferred":[
        "\u0627\u0644\u0645\u0639\u0645\u0631"
    ],
    "name:und_x_variant":[
        "Al Ma\u2018mar"
    ],
    "wof:name":"Al Ma'mar",
    "wof:placetype":"locality"
},
  "geometry": {"coordinates":[44.25455,16.00367],"type":"Point"}
}