{
  "type": "Feature",
  "properties": {
    "gn:admin1_code":"22.0",
    "gn:admin2_code":"1722.0",
    "gn:asciiname":"Bani Mubalish",
    "gn:country_code":"YE",
    "gn:dem":482,
    "gn:feature_class":"P",
    "gn:feature_code":"PPL",
    "gn:name":"Ban\u012b Mub\u0101lish",
    "gn:population":0,
    "gn:timezone":"Asia/Aden",
    "iso:country":"YE",
    "name:und_x_variant":[
        "Ban\u012b Mub\u0101lish"
    ],
    "wof:name":"Bani Mubalish",
    "wof:placetype":"locality"
},
  "geometry": {"coordinates":[43.30316,15.78261],"type":"Point"}
}