{
  "type": "Feature",
  "properties": {
    "gn:admin1_code":"15.0",
    "gn:admin2_code":"2206.0",
    "gn:asciiname":"Al Wathan",
    "gn:country_code":"YE",
    "gn:dem":1208,
    "gn:feature_class":"P",
    "gn:feature_code":"PPL",
    "gn:name":"Al Wathan",
    "gn:population":0,
    "gn:timezone":"Asia/Aden",
    "iso:country":"YE",
    "name:ara_x_preferred":[
        "\u0627\u0644\u0648\u062b\u0646"
    ],
    "wof:name":"Al Wathan",
    "wof:placetype":"locality"
},
  "geometry": {"coordinates":[43.18997,16.91429],"type":"Point"}
}