{
  "type": "Feature",
  "properties": {
    "gn:admin1_code":"22.0",
    "gn:admin2_code":"1725.0",
    "gn:asciiname":"At Tawash",
    "gn:country_code":"YE",
    "gn:dem":754,
    "gn:feature_class":"P",
    "gn:feature_code":"PPL",
    "gn:name":"A\u0163 \u0162aw\u0101sh",
    "gn:population":0,
    "gn:timezone":"Asia/Aden",
    "iso:country":"YE",
    "name:ara_x_preferred":[
        "\u0627\u0644\u0637\u0648\u0627\u0634"
    ],
    "name:und_x_variant":[
        "A\u0163 \u0162aw\u0101sh"
    ],
    "wof:name":"At Tawash",
    "wof:placetype":"locality"
},
  "geometry": {"coordinates":[43.53753,15.5543],"type":"Point"}
}