{
  "type": "Feature",
  "properties": {
    "gn:admin1_code":"24.0",
    "gn:admin2_code":"2511.0",
    "gn:asciiname":"Shasar",
    "gn:country_code":"YE",
    "gn:dem":612,
    "gn:feature_class":"P",
    "gn:feature_code":"PPL",
    "gn:name":"Sha\u015far",
    "gn:population":0,
    "gn:timezone":"Asia/Aden",
    "iso:country":"YE",
    "name:und_x_variant":[
        "Sha\u015far"
    ],
    "wof:name":"Shasar",
    "wof:placetype":"locality"
},
  "geometry": {"coordinates":[44.48132,13.17264],"type":"Point"}
}