{
  "type": "Feature",
  "properties": {
    "gn:country":"YE",
    "gn:fcode":"PPL",
    "gn:population":4,
    "iso:country":"YE",
    "name:ara_x_preferred":[
        "\u0642\u0644\u0639\u0629 \u0627\u0644\u0628\u062a\u0631\u0629"
    ],
    "name:eng_x_preferred":[
        "Qal'at Al Batrah"
    ],
    "name:eng_x_variant":[
        "Al Mashraqah"
    ],
    "qs:name":"Qal\u2018at al Batrah",
    "qs:photos_9r":0,
    "qs:photos_sr":0,
    "qs:pop_sr":"1",
    "wof:name":"Qal\u2018at al Batrah",
    "wof:placetype":"locality",
    "wof:population":4
},
  "geometry": {"coordinates":[43.39378,16.2483],"type":"Point"}
}