{
  "type": "Feature",
  "properties": {
    "gn:admin1_code":"21.0",
    "gn:admin2_code":"1610.0",
    "gn:asciiname":"Maqam al `Amir",
    "gn:country_code":"YE",
    "gn:dem":2059,
    "gn:feature_class":"P",
    "gn:feature_code":"PPL",
    "gn:name":"Maq\u0101m al \u2018\u0100mir",
    "gn:population":0,
    "gn:timezone":"Asia/Aden",
    "iso:country":"YE",
    "name:ara_x_preferred":[
        "\u0645\u0642\u0627\u0645 \u0627\u0644\u0639\u0627\u0645\u0631"
    ],
    "name:und_x_variant":[
        "Qaryat al \u2018\u0100mir",
        "Maq\u0101m al \u2018\u0100mir"
    ],
    "wof:name":"Maqam al `Amir",
    "wof:placetype":"locality"
},
  "geometry": {"coordinates":[44.23079,16.72395],"type":"Point"}
}