{
  "type": "Feature",
  "properties": {
    "gn:admin1_code":"15.0",
    "gn:admin2_code":"2211.0",
    "gn:asciiname":"Hayjat Bin Wuhaysh",
    "gn:country_code":"YE",
    "gn:dem":2177,
    "gn:feature_class":"P",
    "gn:feature_code":"PPL",
    "gn:name":"Hayjat Bin Wu\u1e29aysh",
    "gn:population":0,
    "gn:timezone":"Asia/Aden",
    "iso:country":"YE",
    "name:und_x_variant":[
        "Hayjat Bin Wu\u1e29aysh"
    ],
    "wof:name":"Hayjat Bin Wuhaysh",
    "wof:placetype":"locality"
},
  "geometry": {"coordinates":[43.58855,16.93443],"type":"Point"}
}