{
  "type": "Feature",
  "properties": {
    "gn:admin1_code":"11.0",
    "gn:admin2_code":"2002.0",
    "gn:asciiname":"Al Akhwar",
    "gn:country_code":"YE",
    "gn:dem":1980,
    "gn:feature_class":"P",
    "gn:feature_code":"PPL",
    "gn:name":"Al Akhw\u0101r",
    "gn:population":0,
    "gn:timezone":"Asia/Aden",
    "iso:country":"YE",
    "name:ara_x_preferred":[
        "Al Akhw\u0101r"
    ],
    "wof:name":"Al Akhwar",
    "wof:placetype":"locality"
},
  "geometry": {"coordinates":[44.25335,14.62512],"type":"Point"}
}