{
  "type": "Feature",
  "properties": {
    "gn:admin1_code":"16.0",
    "gn:admin2_code":"2309.0",
    "gn:asciiname":"Al Haddadiyah",
    "gn:country_code":"YE",
    "gn:dem":1038,
    "gn:feature_class":"P",
    "gn:feature_code":"PPL",
    "gn:name":"Al \u1e28add\u0101d\u012byah",
    "gn:population":0,
    "gn:timezone":"Asia/Aden",
    "iso:country":"YE",
    "name:und_x_variant":[
        "Al \u1e28add\u0101d\u012byah"
    ],
    "wof:name":"Al Haddadiyah",
    "wof:placetype":"locality"
},
  "geometry": {"coordinates":[43.87825,14.85975],"type":"Point"}
}