{
  "type": "Feature",
  "properties": {
    "gn:admin1_code":"22.0",
    "gn:admin2_code":"1720.0",
    "gn:asciiname":"Bayt Abu Musalli",
    "gn:country_code":"YE",
    "gn:dem":1633,
    "gn:feature_class":"P",
    "gn:feature_code":"PPL",
    "gn:name":"Bayt Ab\u016b Musall\u012b",
    "gn:population":0,
    "gn:timezone":"Asia/Aden",
    "iso:country":"YE",
    "name:und_x_variant":[
        "Bayt Ab\u016b Musall\u012b"
    ],
    "wof:name":"Bayt Abu Musalli",
    "wof:placetype":"locality"
},
  "geometry": {"coordinates":[43.59033,15.7722],"type":"Point"}
}