{
  "type": "Feature",
  "properties": {
    "gn:admin1_code":"8.0",
    "gn:admin2_code":"1801.0",
    "gn:asciiname":"Mahall",
    "gn:country_code":"YE",
    "gn:dem":130,
    "gn:feature_class":"P",
    "gn:feature_code":"PPL",
    "gn:name":"Ma\u1e29all",
    "gn:population":0,
    "gn:timezone":"Asia/Aden",
    "iso:country":"YE",
    "name:und_x_variant":[
        "Ma\u1e29all"
    ],
    "wof:name":"Mahall",
    "wof:placetype":"locality"
},
  "geometry": {"coordinates":[43.15,15.65],"type":"Point"}
}