{
  "type": "Feature",
  "properties": {
    "gn:admin1_code":"25.0",
    "gn:admin2_code":"1515.0",
    "gn:asciiname":"Qawrimah",
    "gn:country_code":"YE",
    "gn:dem":1440,
    "gn:feature_class":"P",
    "gn:feature_code":"PPL",
    "gn:name":"Qawrimah",
    "gn:population":0,
    "gn:timezone":"Asia/Aden",
    "iso:country":"YE",
    "wof:name":"Qawrimah",
    "wof:placetype":"locality"
},
  "geometry": {"coordinates":[44.04948,13.24515],"type":"Point"}
}