{
  "type": "Feature",
  "properties": {
    "gn:admin1_code":"16.0",
    "gn:admin2_code":"2303.0",
    "gn:asciiname":"Al 'Arjan",
    "gn:country_code":"YE",
    "gn:dem":2158,
    "gn:feature_class":"P",
    "gn:feature_code":"PPL",
    "gn:name":"Al \u2018Arj\u0101n",
    "gn:population":0,
    "gn:timezone":"Asia/Aden",
    "iso:country":"YE",
    "name:ara_x_preferred":[
        "\u0627\u0644\u0639\u0631\u062c\u0627\u0646"
    ],
    "name:und_x_variant":[
        "Al \u2018Arj\u0101n"
    ],
    "wof:name":"Al 'Arjan",
    "wof:placetype":"locality"
},
  "geometry": {"coordinates":[44.58246,15.68758],"type":"Point"}
}