{
  "type": "Feature",
  "properties": {
    "gn:admin1_code":"8.0",
    "gn:admin2_code":"1812.0",
    "gn:asciiname":"Wadi ar Rumman",
    "gn:country_code":"YE",
    "gn:dem":1149,
    "gn:feature_class":"P",
    "gn:feature_code":"PPL",
    "gn:name":"W\u0101d\u012b ar Rumm\u0101n",
    "gn:population":0,
    "gn:timezone":"Asia/Aden",
    "iso:country":"YE",
    "name:ara_x_preferred":[
        "\u0648\u0627\u062f\u064a \u0627\u0644\u0631\u0645\u0627\u0646"
    ],
    "name:und_x_variant":[
        "W\u0101d\u012b ar Rumm\u0101n"
    ],
    "wof:name":"Wadi ar Rumman",
    "wof:placetype":"locality"
},
  "geometry": {"coordinates":[43.48367,14.91418],"type":"Point"}
}