{
  "type": "Feature",
  "properties": {
    "gn:admin1_code":"22.0",
    "gn:admin2_code":"1704.0",
    "gn:asciiname":"Qaryat Hatab",
    "gn:country_code":"YE",
    "gn:dem":166,
    "gn:feature_class":"P",
    "gn:feature_code":"PPL",
    "gn:name":"Qaryat \u1e28a\u0163ab",
    "gn:population":0,
    "gn:timezone":"Asia/Aden",
    "iso:country":"YE",
    "name:und_x_variant":[
        "Qaryat \u1e28a\u0163ab"
    ],
    "wof:name":"Qaryat Hatab",
    "wof:placetype":"locality"
},
  "geometry": {"coordinates":[43.15693,15.98919],"type":"Point"}
}