{
  "type": "Feature",
  "properties": {
    "gn:country":"YE",
    "gn:fcode":"PPL",
    "gn:pop":2,
    "iso:country":"YE",
    "name:ara_x_preferred":[
        "\u0627\u0644\u0645\u0628\u0631\u0643"
    ],
    "name:eng_x_preferred":[
        "Al Mabrak"
    ],
    "qs:name":"Al Mabrak",
    "qs:photos_9r":0,
    "qs:photos_sr":0,
    "qs:pop_sr":"1",
    "wd:wordcount":30,
    "wof:name":"Al Mabrak",
    "wof:placetype":"locality",
    "wof:population":2
},
  "geometry": {"coordinates":[43.85633,13.43538],"type":"Point"}
}