{
  "type": "Feature",
  "properties": {
    "gn:admin1_code":"8.0",
    "gn:admin2_code":"1812.0",
    "gn:asciiname":"Al 'Arsah",
    "gn:country_code":"YE",
    "gn:dem":1234,
    "gn:feature_class":"P",
    "gn:feature_code":"PPL",
    "gn:name":"Al \u2018Ar\u015fah",
    "gn:population":0,
    "gn:timezone":"Asia/Aden",
    "iso:country":"YE",
    "name:ara_x_preferred":[
        "\u0627\u0644\u0639\u0631\u0635\u0629"
    ],
    "name:und_x_variant":[
        "Al \u2018Ar\u015fah"
    ],
    "wof:name":"Al 'Arsah",
    "wof:placetype":"locality"
},
  "geometry": {"coordinates":[43.43969,14.92008],"type":"Point"}
}