{
  "type": "Feature",
  "properties": {
    "gn:admin1_code":"4.0",
    "gn:admin2_code":"1929.0",
    "gn:asciiname":"An Najil",
    "gn:country_code":"YE",
    "gn:dem":18,
    "gn:feature_class":"P",
    "gn:feature_code":"PPL",
    "gn:name":"An Naj\u012bl",
    "gn:population":0,
    "gn:timezone":"Asia/Aden",
    "iso:country":"YE",
    "name:fas_x_preferred":[
        "\u0627\u0646 \u0646\u062c\u06cc\u0644"
    ],
    "name:nno_x_preferred":[
        "An Najil"
    ],
    "name:und_x_variant":[
        "Al-Nijil",
        "An Naj\u012bl"
    ],
    "wof:name":"An Najil",
    "wof:placetype":"locality"
},
  "geometry": {"coordinates":[49.21516,14.60417],"type":"Point"}
}