{
  "type": "Feature",
  "properties": {
    "gn:admin1_code":"23.0",
    "gn:admin2_code":"1120.0",
    "gn:asciiname":"`Asiq",
    "gn:country_code":"YE",
    "gn:dem":1990,
    "gn:feature_class":"P",
    "gn:feature_code":"PPL",
    "gn:name":"\u2018As\u012bq",
    "gn:population":0,
    "gn:timezone":"Asia/Aden",
    "iso:country":"YE",
    "name:ara_x_preferred":[
        "\u2018As\u012bq"
    ],
    "name:ara_x_variant":[
        "\u0639\u0633\u064a\u0642"
    ],
    "wof:name":"`Asiq",
    "wof:placetype":"locality"
},
  "geometry": {"coordinates":[44.13333,14.01667],"type":"Point"}
}