{
  "type": "Feature",
  "properties": {
    "gn:admin1_code":"15.0",
    "gn:admin2_code":"2210.0",
    "gn:asciiname":"Al Falajat",
    "gn:country_code":"YE",
    "gn:dem":2546,
    "gn:feature_class":"P",
    "gn:feature_code":"PPL",
    "gn:name":"Al Falaj\u0101t",
    "gn:population":0,
    "gn:timezone":"Asia/Aden",
    "iso:country":"YE",
    "name:ara_x_preferred":[
        "\u0627\u0644\u0641\u0644\u062c\u0627\u062a"
    ],
    "name:und_x_variant":[
        "Al Falaj\u0101t"
    ],
    "wof:name":"Al Falajat",
    "wof:placetype":"locality"
},
  "geometry": {"coordinates":[43.40505,17.15555],"type":"Point"}
}