{
  "type": "Feature",
  "properties": {
    "gn:admin1_code":"16.0",
    "gn:admin2_code":"2302.0",
    "gn:asciiname":"Halhal Bani `Ali",
    "gn:country_code":"YE",
    "gn:dem":1758,
    "gn:feature_class":"P",
    "gn:feature_code":"PPL",
    "gn:name":"\u1e28al\u1e29al Ban\u012b \u2018Al\u012b",
    "gn:population":0,
    "gn:timezone":"Asia/Aden",
    "iso:country":"YE",
    "name:und_x_variant":[
        "\u1e28al\u1e29al Ban\u012b \u2018Al\u012b"
    ],
    "wof:name":"Halhal Bani `Ali",
    "wof:placetype":"locality"
},
  "geometry": {"coordinates":[44.23615,15.94689],"type":"Point"}
}