{
  "type": "Feature",
  "properties": {
    "gn:admin1_code":"25.0",
    "gn:admin2_code":"1508.0",
    "gn:asciiname":"Ziblah",
    "gn:cc2":"YE",
    "gn:country_code":"YE",
    "gn:dem":395,
    "gn:feature_class":"P",
    "gn:feature_code":"PPL",
    "gn:name":"Ziblah",
    "gn:population":0,
    "gn:timezone":"Asia/Aden",
    "iso:country":"YE",
    "name:und_x_variant":[
        "Zubla",
        "Ziblah"
    ],
    "wof:name":"Ziblah",
    "wof:placetype":"locality"
},
  "geometry": {"coordinates":[43.65,13.38333],"type":"Point"}
}