{
  "type": "Feature",
  "properties": {
    "gn:admin1_code":"22.0",
    "gn:admin2_code":"1721.0",
    "gn:asciiname":"Al `Asarah",
    "gn:country_code":"YE",
    "gn:dem":1446,
    "gn:feature_class":"P",
    "gn:feature_code":"PPL",
    "gn:name":"Al \u2018A\u015farah",
    "gn:population":0,
    "gn:timezone":"Asia/Aden",
    "iso:country":"YE",
    "name:und_x_variant":[
        "Al \u2018A\u015farah"
    ],
    "wof:name":"Al `Asarah",
    "wof:placetype":"locality"
},
  "geometry": {"coordinates":[43.4042,15.85055],"type":"Point"}
}