{
  "type": "Feature",
  "properties": {
    "gn:country":"YE",
    "gn:fcode":"PPL",
    "gn:population":13,
    "iso:country":"YE",
    "name:ara_x_preferred":[
        "\u063a\u0648\u0644 \u0627\u0644\u0645\u0636\u0649"
    ],
    "name:eng_x_preferred":[
        "Ghawl Al Maua"
    ],
    "name:eng_x_variant":[
        "Al Ghumrah"
    ],
    "qs:name":"Ghawl al Ma\u1e11\u00e1",
    "qs:photos_9r":0,
    "qs:photos_sr":0,
    "qs:pop_sr":"1",
    "wof:name":"Ghawl al Ma\u1e11\u00e1",
    "wof:placetype":"locality",
    "wof:population":13
},
  "geometry": {"coordinates":[43.48011,16.23635],"type":"Point"}
}