{
  "type": "Feature",
  "properties": {
    "gn:country":"YE",
    "gn:fcode":"PPL",
    "gn:population":3,
    "iso:country":"YE",
    "name:ara_x_preferred":[
        "\u063a\u0648\u0644 \u0627\u0644\u0643\u0627\u062f\u0629"
    ],
    "name:eng_x_preferred":[
        "Ghawl Al Kadah"
    ],
    "name:eng_x_variant":[
        "Sh\u0101\u0163i\u2019 al \u1e28\u0101jj"
    ],
    "qs:name":"Ghawl al K\u0101dah",
    "qs:photos_9r":0,
    "qs:photos_sr":0,
    "qs:pop_sr":"1",
    "wof:name":"Ghawl al K\u0101dah",
    "wof:placetype":"locality",
    "wof:population":3
},
  "geometry": {"coordinates":[43.31148,16.55567],"type":"Point"}
}