{
  "type": "Feature",
  "properties": {
    "gn:admin1_code":"19.0",
    "gn:admin2_code":"2908.0",
    "gn:asciiname":"Al Ghuruz",
    "gn:country_code":"YE",
    "gn:dem":941,
    "gn:feature_class":"P",
    "gn:feature_code":"PPL",
    "gn:name":"Al Ghuruz",
    "gn:population":0,
    "gn:timezone":"Asia/Aden",
    "iso:country":"YE",
    "name:ara_x_preferred":[
        "\u0627\u0644\u063a\u0631\u0632"
    ],
    "name:und_x_variant":[
        "Ban\u012b Mift\u0101\u1e29 al Ghuruz",
        "Al Ghuruz"
    ],
    "wof:name":"Al Ghuruz",
    "wof:placetype":"locality"
},
  "geometry": {"coordinates":[43.71963,16.02214],"type":"Point"}
}