{
  "type": "Feature",
  "properties": {
    "gn:country":"YE",
    "gn:fcode":"PPL",
    "gn:population":5,
    "iso:country":"YE",
    "name:ara_x_preferred":[
        "\u062a\u0648\u064a\u0645"
    ],
    "name:eng_x_preferred":[
        "Tawim"
    ],
    "qs:name":"Taw\u012bm",
    "qs:photos_9r":0,
    "qs:photos_sr":0,
    "qs:pop_sr":"1",
    "wof:name":"Taw\u012bm",
    "wof:placetype":"locality",
    "wof:population":5
},
  "geometry": {"coordinates":[44.51182,16.79021],"type":"Point"}
}