{
  "type": "Feature",
  "properties": {
    "gn:admin1_code":"14.0",
    "gn:admin2_code":"2603.0",
    "gn:asciiname":"Nakhla'",
    "gn:country_code":"YE",
    "gn:dem":1156,
    "gn:feature_class":"P",
    "gn:feature_code":"PPLL",
    "gn:name":"Nakhl\u0101\u2018",
    "gn:population":0,
    "gn:timezone":"Asia/Aden",
    "iso:country":"YE",
    "name:ara_x_preferred":[
        "\u0646\u062e\u0644\u0627\u0621"
    ],
    "name:und_x_variant":[
        "Nakhl\u0101\u2018"
    ],
    "wof:name":"Nakhla'",
    "wof:placetype":"locality"
},
  "geometry": {"coordinates":[45.19869,15.61604],"type":"Point"}
}