{
  "type": "Feature",
  "properties": {
    "gn:admin1_code":"10.0",
    "gn:admin2_code":"2704.0",
    "gn:asciiname":"Ad Damigh",
    "gn:country_code":"YE",
    "gn:dem":1311,
    "gn:feature_class":"P",
    "gn:feature_code":"PPL",
    "gn:name":"Ad D\u0101migh",
    "gn:population":0,
    "gn:timezone":"Asia/Aden",
    "iso:country":"YE",
    "name:ara_x_preferred":[
        "Ad D\u0101migh"
    ],
    "wof:name":"Ad Damigh",
    "wof:placetype":"locality"
},
  "geometry": {"coordinates":[43.43899999999999,15.53592],"type":"Point"}
}