{
  "type": "Feature",
  "properties": {
    "gn:admin1_code":"11.0",
    "gn:asciiname":"Al Qa`",
    "gn:country_code":"YE",
    "gn:dem":2462,
    "gn:feature_class":"P",
    "gn:feature_code":"PPL",
    "gn:name":"Al Q\u0101\u2018",
    "gn:population":0,
    "gn:timezone":"Asia/Aden",
    "iso:country":"YE",
    "name:ara_x_preferred":[
        "\u0627\u0644\u0642\u0627\u0639"
    ],
    "name:und_x_variant":[
        "Al Q\u0101\u2018"
    ],
    "wof:name":"Al Qa`",
    "wof:placetype":"locality"
},
  "geometry": {"coordinates":[44.44655,14.28799],"type":"Point"}
}