{
  "type": "Feature",
  "properties": {
    "gn:admin1_code":"20.0",
    "gn:admin2_code":"1407.0",
    "gn:asciiname":"Al Ma`zub",
    "gn:country_code":"YE",
    "gn:dem":2001,
    "gn:feature_class":"P",
    "gn:feature_code":"PPL",
    "gn:name":"Al Ma\u2018z\u016bb",
    "gn:population":0,
    "gn:timezone":"Asia/Aden",
    "iso:country":"YE",
    "name:ara_x_preferred":[
        "\u0627\u0644\u0645\u0639\u0632\u0648\u0628"
    ],
    "name:und_x_variant":[
        "Al Ma\u2018z\u016bb"
    ],
    "wof:name":"Al Ma`zub",
    "wof:placetype":"locality"
},
  "geometry": {"coordinates":[45.38827,14.21527],"type":"Point"}
}