{
  "type": "Feature",
  "properties": {
    "gn:admin1_code":"18.0",
    "gn:admin2_code":"3009.0",
    "gn:asciiname":"Qaryat Najd Khulban",
    "gn:country_code":"YE",
    "gn:dem":1257,
    "gn:feature_class":"P",
    "gn:feature_code":"PPL",
    "gn:name":"Qaryat Najd Khulb\u0101n",
    "gn:population":0,
    "gn:timezone":"Asia/Aden",
    "iso:country":"YE",
    "name:und_x_variant":[
        "Qaryat Najd Khulb\u0101n"
    ],
    "wof:name":"Qaryat Najd Khulban",
    "wof:placetype":"locality"
},
  "geometry": {"coordinates":[44.38788,13.65103],"type":"Point"}
}