{
  "type": "Feature",
  "properties": {
    "gn:admin1_code":"15.0",
    "gn:admin2_code":"2208.0",
    "gn:asciiname":"Al Fadil",
    "gn:country_code":"YE",
    "gn:dem":1357,
    "gn:feature_class":"P",
    "gn:feature_code":"PPL",
    "gn:name":"\u0100l F\u0101\u1e11il",
    "gn:population":0,
    "gn:timezone":"Asia/Aden",
    "iso:country":"YE",
    "name:ara_x_preferred":[
        "\u0100l F\u0101\u1e11il"
    ],
    "wof:name":"Al Fadil",
    "wof:placetype":"locality"
},
  "geometry": {"coordinates":[43.37156,16.73299],"type":"Point"}
}