{
  "type": "Feature",
  "properties": {
    "gn:admin1_code":"25.0",
    "gn:admin2_code":"1517.0",
    "gn:asciiname":"Ma`azij",
    "gn:country_code":"YE",
    "gn:dem":1516,
    "gn:feature_class":"P",
    "gn:feature_code":"PPL",
    "gn:name":"Ma\u2018\u0101z\u012bj",
    "gn:population":0,
    "gn:timezone":"Asia/Aden",
    "iso:country":"YE",
    "name:und_x_variant":[
        "Ma\u2018\u0101z\u012bj"
    ],
    "wof:name":"Ma`azij",
    "wof:placetype":"locality"
},
  "geometry": {"coordinates":[44.27964,13.33402],"type":"Point"}
}