{
  "type": "Feature",
  "properties": {
    "gn:admin1_code":"20.0",
    "gn:asciiname":"Fawq al Hidha'",
    "gn:country_code":"YE",
    "gn:dem":2244,
    "gn:feature_class":"P",
    "gn:feature_code":"PPL",
    "gn:name":"Fawq al \u1e28idh\u0101\u2019",
    "gn:population":0,
    "gn:timezone":"Asia/Aden",
    "iso:country":"YE",
    "name:ara_x_preferred":[
        "\u0641\u0648\u0642 \u0627\u0644\u062d\u0630\u0627\u0621"
    ],
    "name:und_x_variant":[
        "Fawq al \u1e28idh\u0101\u2019"
    ],
    "wof:name":"Fawq al Hidha'",
    "wof:placetype":"locality"
},
  "geometry": {"coordinates":[44.38644,14.43636],"type":"Point"}
}