{
  "type": "Feature",
  "properties": {
    "gn:admin1_code":"25.0",
    "gn:admin2_code":"1516.0",
    "gn:asciiname":"Al Hadarah",
    "gn:country_code":"YE",
    "gn:dem":592,
    "gn:feature_class":"P",
    "gn:feature_code":"PPL",
    "gn:name":"Al \u1e28a\u1e11\u0101rah",
    "gn:population":0,
    "gn:timezone":"Asia/Aden",
    "iso:country":"YE",
    "name:ara_x_preferred":[
        "\u0627\u0644\u062d\u0636\u0627\u0631\u0629"
    ],
    "name:und_x_variant":[
        "Al \u1e28a\u1e11\u0101rah"
    ],
    "wof:name":"Al Hadarah",
    "wof:placetype":"locality"
},
  "geometry": {"coordinates":[43.77892,13.17384],"type":"Point"}
}