{
  "type": "Feature",
  "properties": {
    "gn:admin1_code":"22.0",
    "gn:admin2_code":"1704.0",
    "gn:asciiname":"Al Qambur",
    "gn:country_code":"YE",
    "gn:dem":154,
    "gn:feature_class":"P",
    "gn:feature_code":"PPL",
    "gn:name":"Al Qamb\u016br",
    "gn:population":0,
    "gn:timezone":"Asia/Aden",
    "iso:country":"YE",
    "name:und_x_variant":[
        "Al Qamb\u016br"
    ],
    "wof:name":"Al Qambur",
    "wof:placetype":"locality"
},
  "geometry": {"coordinates":[43.1619,16.04727999999999],"type":"Point"}
}