{
  "type": "Feature",
  "properties": {
    "gn:admin1_code":"23.0",
    "gn:admin2_code":"1109.0",
    "gn:asciiname":"Qaryat al Mayyah",
    "gn:country_code":"YE",
    "gn:dem":1230,
    "gn:feature_class":"P",
    "gn:feature_code":"PPL",
    "gn:name":"Qaryat al Mayyah",
    "gn:population":0,
    "gn:timezone":"Asia/Aden",
    "iso:country":"YE",
    "wof:name":"Qaryat al Mayyah",
    "wof:placetype":"locality"
},
  "geometry": {"coordinates":[43.99631,14.17999],"type":"Point"}
}