{
  "type": "Feature",
  "properties": {
    "gn:admin1_code":"8.0",
    "gn:admin2_code":"1813.0",
    "gn:asciiname":"As Saqi",
    "gn:country_code":"YE",
    "gn:dem":147,
    "gn:feature_class":"P",
    "gn:feature_code":"PPL",
    "gn:name":"As S\u0101q\u012b",
    "gn:population":0,
    "gn:timezone":"Asia/Aden",
    "iso:country":"YE",
    "name:ara_x_preferred":[
        "\u0627\u0644\u0633\u0627\u0642\u064a"
    ],
    "name:und_x_variant":[
        "As S\u0101q\u012b"
    ],
    "wof:name":"As Saqi",
    "wof:placetype":"locality"
},
  "geometry": {"coordinates":[43.28031,14.96386],"type":"Point"}
}