{
  "type": "Feature",
  "properties": {
    "gn:admin1_code":"25.0",
    "gn:admin2_code":"1515.0",
    "gn:asciiname":"Ba'r",
    "gn:country_code":"YE",
    "gn:dem":1929,
    "gn:feature_class":"P",
    "gn:feature_code":"PPL",
    "gn:name":"Ba\u2018r",
    "gn:population":0,
    "gn:timezone":"Asia/Aden",
    "iso:country":"YE",
    "name:ara_x_preferred":[
        "\u0628\u0639\u0631"
    ],
    "name:und_x_variant":[
        "Ba\u2018r"
    ],
    "wof:name":"Ba'r",
    "wof:placetype":"locality"
},
  "geometry": {"coordinates":[44.15544000000001,13.24437],"type":"Point"}
}