{
  "type": "Feature",
  "properties": {
    "gn:country":"YE",
    "gn:fcode":"PPL",
    "gn:pop":5,
    "iso:country":"YE",
    "name:ara_x_preferred":[
        "\u0627\u0644\u0633\u0644\u064a\u0644"
    ],
    "name:eng_x_preferred":[
        "As Sulayl"
    ],
    "qs:name":"As Sulayl",
    "qs:photos_9r":0,
    "qs:photos_sr":0,
    "qs:pop_sr":"1",
    "wof:name":"As Sulayl",
    "wof:placetype":"locality",
    "wof:population":5
},
  "geometry": {"coordinates":[44.33607,17.03185],"type":"Point"}
}