{
  "type": "Feature",
  "properties": {
    "gn:country":"YE",
    "gn:fcode":"PPL",
    "gn:pop":14,
    "iso:country":"YE",
    "name:ara_x_preferred":[
        "Im\u015f\u0101\u1e29"
    ],
    "name:ara_x_variant":[
        "\u0625\u0645\u0635\u0627\u062d"
    ],
    "name:eng_x_preferred":[
        "Imsah"
    ],
    "qs:name":"Im\u015f\u0101\u1e29",
    "qs:photos_9r":0,
    "qs:photos_sr":0,
    "qs:pop_sr":"1",
    "wof:name":"Im\u015f\u0101\u1e29",
    "wof:placetype":"locality",
    "wof:population":14
},
  "geometry": {"coordinates":[43.42077,17.5224],"type":"Point"}
}