{
  "type": "Feature",
  "properties": {
    "gn:admin1_code":"25.0",
    "gn:admin2_code":"1521.0",
    "gn:asciiname":"Qirtas",
    "gn:country_code":"YE",
    "gn:dem":558,
    "gn:feature_class":"P",
    "gn:feature_code":"PPL",
    "gn:name":"Qir\u0163\u0101s",
    "gn:population":0,
    "gn:timezone":"Asia/Aden",
    "iso:country":"YE",
    "name:ara_x_preferred":[
        "Qir\u0163\u0101s"
    ],
    "name:ara_x_variant":[
        "\u0642\u0631\u0637\u0627\u0633"
    ],
    "wof:name":"Qirtas",
    "wof:placetype":"locality"
},
  "geometry": {"coordinates":[43.77933,13.32128],"type":"Point"}
}