{
  "type": "Feature",
  "properties": {
    "gn:admin1_code":"16.0",
    "gn:admin2_code":"2316.0",
    "gn:asciiname":"Mahdabah",
    "gn:country_code":"YE",
    "gn:dem":2312,
    "gn:feature_class":"P",
    "gn:feature_code":"PPL",
    "gn:name":"Mah\u1e11abah",
    "gn:population":0,
    "gn:timezone":"Asia/Aden",
    "iso:country":"YE",
    "name:und_x_variant":[
        "Mah\u1e11abah"
    ],
    "wof:name":"Mahdabah",
    "wof:placetype":"locality"
},
  "geometry": {"coordinates":[44.47393,15.1523],"type":"Point"}
}