{
  "type": "Feature",
  "properties": {
    "gn:admin1_code":"8.0",
    "gn:admin2_code":"1807.0",
    "gn:asciiname":"Mahall al Bunn",
    "gn:country_code":"YE",
    "gn:dem":67,
    "gn:feature_class":"P",
    "gn:feature_code":"PPL",
    "gn:name":"Ma\u1e29all al Bunn",
    "gn:population":0,
    "gn:timezone":"Asia/Aden",
    "iso:country":"YE",
    "name:und_x_variant":[
        "Ma\u1e29all al Bunn"
    ],
    "wof:name":"Mahall al Bunn",
    "wof:placetype":"locality"
},
  "geometry": {"coordinates":[43.04857,15.37457],"type":"Point"}
}