{
  "type": "Feature",
  "properties": {
    "gn:admin1_code":"11.0",
    "gn:admin2_code":"2012.0",
    "gn:asciiname":"Qurazah",
    "gn:country_code":"YE",
    "gn:dem":2272,
    "gn:feature_class":"P",
    "gn:feature_code":"PPL",
    "gn:name":"Qur\u0101z\u0327ah",
    "gn:population":0,
    "gn:timezone":"Asia/Aden",
    "iso:country":"YE",
    "name:und_x_variant":[
        "Qur\u0101z\u0327ah"
    ],
    "wof:name":"Qurazah",
    "wof:placetype":"locality"
},
  "geometry": {"coordinates":[44.10724,14.5724],"type":"Point"}
}