{
  "type": "Feature",
  "properties": {
    "gn:admin1_code":"8.0",
    "gn:admin2_code":"1807.0",
    "gn:asciiname":"Mahall Qasim 'Ali",
    "gn:country_code":"YE",
    "gn:dem":49,
    "gn:feature_class":"P",
    "gn:feature_code":"PPL",
    "gn:name":"Ma\u1e29all Q\u0101sim \u2018Al\u012b",
    "gn:population":0,
    "gn:timezone":"Asia/Aden",
    "iso:country":"YE",
    "name:ara_x_preferred":[
        "\u0645\u062d\u0644 \u0642\u0627\u0633\u0645 \u0639\u0644\u064a"
    ],
    "name:und_x_variant":[
        "Ma\u1e29all Q\u0101sim \u2018Al\u012b"
    ],
    "wof:name":"Mahall Qasim 'Ali",
    "wof:placetype":"locality"
},
  "geometry": {"coordinates":[42.98235,15.20251],"type":"Point"}
}