{
  "type": "Feature",
  "properties": {
    "gn:country":"YE",
    "gn:fcode":"PPL",
    "gn:population":4,
    "iso:country":"YE",
    "name:ara_x_preferred":[
        "\u0627\u0644\u0642\u0637\u0641"
    ],
    "name:eng_x_preferred":[
        "Al Qataf"
    ],
    "name:eng_x_variant":[
        "Bi\u2019r al \u1e28az\u0327\u0101\u2019ir"
    ],
    "qs:name":"Al Qa\u0163af",
    "qs:photos_9r":0,
    "qs:photos_sr":0,
    "qs:pop_sr":"1",
    "wof:name":"Al Qa\u0163af",
    "wof:placetype":"locality",
    "wof:population":4
},
  "geometry": {"coordinates":[43.29919,16.64989],"type":"Point"}
}