{
  "type": "Feature",
  "properties": {
    "gn:admin1_code":"25.0",
    "gn:admin2_code":"1517.0",
    "gn:asciiname":"Sharaq",
    "gn:country_code":"YE",
    "gn:dem":1342,
    "gn:feature_class":"P",
    "gn:feature_code":"PPL",
    "gn:name":"Shar\u0101q",
    "gn:population":0,
    "gn:timezone":"Asia/Aden",
    "iso:country":"YE",
    "name:ara_x_preferred":[
        "\u0634\u0631\u0627\u0642"
    ],
    "name:und_x_variant":[
        "Shar\u0101q"
    ],
    "wof:name":"Sharaq",
    "wof:placetype":"locality"
},
  "geometry": {"coordinates":[44.22125,13.23896],"type":"Point"}
}