{
  "type": "Feature",
  "properties": {
    "gn:admin1_code":"15.0",
    "gn:admin2_code":"2208.0",
    "gn:asciiname":"Al Mirkabah",
    "gn:country_code":"YE",
    "gn:dem":1227,
    "gn:feature_class":"P",
    "gn:feature_code":"PPL",
    "gn:name":"Al Mirk\u0101bah",
    "gn:population":0,
    "gn:timezone":"Asia/Aden",
    "iso:country":"YE",
    "name:ara_x_preferred":[
        "\u0627\u0644\u0645\u0631\u0643\u0627\u0628\u0629"
    ],
    "name:und_x_variant":[
        "Al Mirk\u0101bah"
    ],
    "wof:name":"Al Mirkabah",
    "wof:placetype":"locality"
},
  "geometry": {"coordinates":[43.34825,16.64719],"type":"Point"}
}