{
  "type": "Feature",
  "properties": {
    "gn:admin1_code":"25.0",
    "gn:admin2_code":"1515.0",
    "gn:asciiname":"Al Mad haf",
    "gn:country_code":"YE",
    "gn:dem":1123,
    "gn:feature_class":"P",
    "gn:feature_code":"PPLL",
    "gn:name":"Al Mad haf",
    "gn:population":0,
    "gn:timezone":"Asia/Aden",
    "iso:country":"YE",
    "name:ara_x_preferred":[
        "\u0627\u0644\u0645\u062f\u0647\u0641"
    ],
    "name:und_x_variant":[
        "Al Mad\u00b7haf"
    ],
    "wof:name":"Al Mad haf",
    "wof:placetype":"locality"
},
  "geometry": {"coordinates":[43.99627,13.17803],"type":"Point"}
}