{
  "type": "Feature",
  "properties": {
    "gn:country":"YE",
    "gn:fcode":"PPL",
    "gn:population":9,
    "iso:country":"YE",
    "name:ara_x_preferred":[
        "\u0627\u0644\u0635\u062f\u0642\u0629"
    ],
    "qs:name":"A\u015f \u015eadaqah",
    "qs:photos_9r":0,
    "qs:photos_sr":0,
    "qs:pop_sr":"1",
    "wof:name":"A\u015f \u015eadaqah",
    "wof:placetype":"locality",
    "wof:population":9
},
  "geometry": {"coordinates":[43.29857,16.12301],"type":"Point"}
}