{
  "type": "Feature",
  "properties": {
    "gn:admin1_code":"19.0",
    "gn:admin2_code":"2904.0",
    "gn:asciiname":"Qasabat Qasan",
    "gn:country_code":"YE",
    "gn:dem":1421,
    "gn:feature_class":"P",
    "gn:feature_code":"PPL",
    "gn:name":"Qa\u015fabat Qa\u015f\u0101n",
    "gn:population":0,
    "gn:timezone":"Asia/Aden",
    "iso:country":"YE",
    "name:ara_x_preferred":[
        "\u0642\u0635\u0628\u0629 \u0642\u0635\u0627\u0646"
    ],
    "name:und_x_variant":[
        "Qa\u015fabat Qa\u015f\u0101n"
    ],
    "wof:name":"Qasabat Qasan",
    "wof:placetype":"locality"
},
  "geometry": {"coordinates":[43.70716,16.37361],"type":"Point"}
}