{
  "type": "Feature",
  "properties": {
    "gn:admin1_code":"8.0",
    "gn:admin2_code":"1813.0",
    "gn:asciiname":"Al Musiyah",
    "gn:country_code":"YE",
    "gn:dem":72,
    "gn:feature_class":"P",
    "gn:feature_code":"PPL",
    "gn:name":"Al M\u016bs\u012byah",
    "gn:population":0,
    "gn:timezone":"Asia/Aden",
    "iso:country":"YE",
    "name:und_x_variant":[
        "Al M\u016bs\u012byah"
    ],
    "wof:name":"Al Musiyah",
    "wof:placetype":"locality"
},
  "geometry": {"coordinates":[43.18184,14.80116],"type":"Point"}
}