{
  "type": "Feature",
  "properties": {
    "gn:admin1_code":"22.0",
    "gn:admin2_code":"1727.0",
    "gn:asciiname":"Bayt ar Raddi",
    "gn:country_code":"YE",
    "gn:dem":1392,
    "gn:feature_class":"P",
    "gn:feature_code":"PPL",
    "gn:name":"Bayt ar Ra\u1e11\u1e11\u012b",
    "gn:population":0,
    "gn:timezone":"Asia/Aden",
    "iso:country":"YE",
    "name:ara_x_preferred":[
        "\u0628\u064a\u062a \u0627\u0644\u0631\u0636\u064a"
    ],
    "name:und_x_variant":[
        "Bayt ar Ra\u1e11\u1e11\u012b"
    ],
    "wof:name":"Bayt ar Raddi",
    "wof:placetype":"locality"
},
  "geometry": {"coordinates":[43.58965,15.57319],"type":"Point"}
}