{
  "type": "Feature",
  "properties": {
    "gn:admin1_code":"15.0",
    "gn:admin2_code":"2215.0",
    "gn:asciiname":"Jarfah",
    "gn:country_code":"YE",
    "gn:dem":1895,
    "gn:feature_class":"P",
    "gn:feature_code":"PPL",
    "gn:name":"Jarfah",
    "gn:population":0,
    "gn:timezone":"Asia/Aden",
    "iso:country":"YE",
    "wof:name":"Jarfah",
    "wof:placetype":"locality"
},
  "geometry": {"coordinates":[43.77455,16.91193],"type":"Point"}
}