{
  "type": "Feature",
  "properties": {
    "gn:country":"YE",
    "gn:fcode":"PPL",
    "gn:population":1,
    "iso:country":"YE",
    "name:ara_x_preferred":[
        "\u0627\u0644\u0645\u062c\u0631\u0628"
    ],
    "qs:name":"Al Mijrab",
    "qs:photos_9r":0,
    "qs:photos_sr":0,
    "qs:pop_sr":"1",
    "wof:name":"Al Mijrab",
    "wof:placetype":"locality",
    "wof:population":1
},
  "geometry": {"coordinates":[43.38438,16.24662],"type":"Point"}
}