{
  "type": "Feature",
  "properties": {
    "gn:admin1_code":"19.0",
    "gn:admin2_code":"2902.0",
    "gn:asciiname":"At Tahtah",
    "gn:country_code":"YE",
    "gn:dem":1896,
    "gn:feature_class":"P",
    "gn:feature_code":"PPL",
    "gn:name":"A\u0163 \u0162a\u1e29\u0163a\u1e29",
    "gn:population":0,
    "gn:timezone":"Asia/Aden",
    "iso:country":"YE",
    "name:und_x_variant":[
        "A\u0163 \u0162a\u1e29\u0163a\u1e29"
    ],
    "wof:name":"At Tahtah",
    "wof:placetype":"locality"
},
  "geometry": {"coordinates":[43.94765,16.24214],"type":"Point"}
}