{
  "type": "Feature",
  "properties": {
    "gn:admin1_code":"22.0",
    "gn:admin2_code":"1724.0",
    "gn:asciiname":"Bani Sawd",
    "gn:country_code":"YE",
    "gn:dem":437,
    "gn:feature_class":"P",
    "gn:feature_code":"PPL",
    "gn:name":"Ban\u012b Sawd",
    "gn:population":0,
    "gn:timezone":"Asia/Aden",
    "iso:country":"YE",
    "name:und_x_variant":[
        "Ban\u012b Sawd"
    ],
    "wof:name":"Bani Sawd",
    "wof:placetype":"locality"
},
  "geometry": {"coordinates":[43.41387,15.68776],"type":"Point"}
}