{
  "type": "Feature",
  "properties": {
    "gn:admin1_code":"11.0",
    "gn:admin2_code":"2010.0",
    "gn:asciiname":"Bayt Mihras",
    "gn:country_code":"YE",
    "gn:dem":2581,
    "gn:feature_class":"P",
    "gn:feature_code":"PPL",
    "gn:name":"Bayt Mihr\u0101s",
    "gn:population":0,
    "gn:timezone":"Asia/Aden",
    "iso:country":"YE",
    "name:und_x_variant":[
        "Bayt Mihr\u0101s"
    ],
    "wof:name":"Bayt Mihras",
    "wof:placetype":"locality"
},
  "geometry": {"coordinates":[44.52383,14.41264],"type":"Point"}
}