{
  "type": "Feature",
  "properties": {
    "gn:admin1_code":"16.0",
    "gn:admin2_code":"2313.0",
    "gn:asciiname":"`Adhubah",
    "gn:country_code":"YE",
    "gn:dem":2403,
    "gn:feature_class":"P",
    "gn:feature_code":"PPL",
    "gn:name":"\u2018Adh\u016bbah",
    "gn:population":0,
    "gn:timezone":"Asia/Aden",
    "iso:country":"YE",
    "name:und_x_variant":[
        "\u2018Adh\u016bbah"
    ],
    "wof:name":"`Adhubah",
    "wof:placetype":"locality"
},
  "geometry": {"coordinates":[44.50929,15.31701],"type":"Point"}
}