{
  "type": "Feature",
  "properties": {
    "gn:admin1_code":"21.0",
    "gn:admin2_code":"1603.0",
    "gn:asciiname":"Sirhan",
    "gn:country_code":"YE",
    "gn:dem":1190,
    "gn:feature_class":"P",
    "gn:feature_code":"PPL",
    "gn:name":"Sir\u1e29\u0101n",
    "gn:population":0,
    "gn:timezone":"Asia/Aden",
    "iso:country":"YE",
    "name:ara_x_preferred":[
        "\u0633\u0631\u062d\u0627\u0646"
    ],
    "name:und_x_variant":[
        "Sir\u1e29\u0101n"
    ],
    "wof:name":"Sirhan",
    "wof:placetype":"locality"
},
  "geometry": {"coordinates":[44.49715,16.27729],"type":"Point"}
}