{
  "type": "Feature",
  "properties": {
    "gn:admin1_code":"8.0",
    "gn:admin2_code":"1824.0",
    "gn:asciiname":"Mahwa `Umari",
    "gn:country_code":"YE",
    "gn:dem":112,
    "gn:feature_class":"P",
    "gn:feature_code":"PPL",
    "gn:name":"Ma\u1e29w\u00e1 \u2018Um\u0101r\u012b",
    "gn:population":0,
    "gn:timezone":"Asia/Aden",
    "iso:country":"YE",
    "name:und_x_variant":[
        "Ma\u1e29w\u00e1 \u2018Um\u0101r\u012b"
    ],
    "wof:name":"Mahwa `Umari",
    "wof:placetype":"locality"
},
  "geometry": {"coordinates":[43.32009,14.17469],"type":"Point"}
}