{
  "type": "Feature",
  "properties": {
    "gn:admin1_code":"20.0",
    "gn:admin2_code":"1402.0",
    "gn:asciiname":"Ash Shuwayhit",
    "gn:country_code":"YE",
    "gn:dem":1843,
    "gn:feature_class":"P",
    "gn:feature_code":"PPL",
    "gn:name":"Ash Shuway\u1e29i\u0163",
    "gn:population":0,
    "gn:timezone":"Asia/Aden",
    "iso:country":"YE",
    "name:ara_x_preferred":[
        "\u0627\u0644\u0634\u0648\u064a\u062d\u0637"
    ],
    "name:und_x_variant":[
        "Ash Shuway\u1e29i\u0163"
    ],
    "wof:name":"Ash Shuwayhit",
    "wof:placetype":"locality"
},
  "geometry": {"coordinates":[45.55953,14.4466],"type":"Point"}
}