{
  "type": "Feature",
  "properties": {
    "gn:country":"YE",
    "gn:fcode":"PPL",
    "gn:pop":3,
    "iso:country":"YE",
    "name:ara_x_preferred":[
        "\u0642\u0627\u0626\u0645 \u0628\u0634\u064a\u0631"
    ],
    "name:eng_x_preferred":[
        "Qaim Bashir"
    ],
    "name:eng_x_variant":[
        "Ab\u0101 al Qur\u016bn"
    ],
    "qs:name":"Q\u0101\u2019im Bash\u012br",
    "qs:photos_9r":0,
    "qs:photos_sr":0,
    "qs:pop_sr":"1",
    "wof:name":"Q\u0101\u2019im Bash\u012br",
    "wof:placetype":"locality",
    "wof:population":3
},
  "geometry": {"coordinates":[43.2344,16.68178],"type":"Point"}
}