{
  "type": "Feature",
  "properties": {
    "gn:admin1_code":"8.0",
    "gn:admin2_code":"1807.0",
    "gn:asciiname":"Mahall Tahbul",
    "gn:country_code":"YE",
    "gn:dem":54,
    "gn:feature_class":"P",
    "gn:feature_code":"PPL",
    "gn:name":"Ma\u1e29all \u0162a\u1e29b\u016bl",
    "gn:population":0,
    "gn:timezone":"Asia/Aden",
    "iso:country":"YE",
    "name:ara_x_preferred":[
        "\u0645\u062d\u0644 \u0637\u062d\u0628\u0648\u0644"
    ],
    "name:und_x_variant":[
        "Ma\u1e29all \u0162a\u1e29b\u016bl"
    ],
    "wof:name":"Mahall Tahbul",
    "wof:placetype":"locality"
},
  "geometry": {"coordinates":[43.01737,15.34959],"type":"Point"}
}