{
  "type": "Feature",
  "properties": {
    "gn:admin1_code":"23.0",
    "gn:admin2_code":"1112.0",
    "gn:asciiname":"Ma`barah",
    "gn:country_code":"YE",
    "gn:dem":2277,
    "gn:feature_class":"P",
    "gn:feature_code":"PPL",
    "gn:name":"Ma\u2018barah",
    "gn:population":0,
    "gn:timezone":"Asia/Aden",
    "iso:country":"YE",
    "name:und_x_variant":[
        "Ma\u2018barah"
    ],
    "wof:name":"Ma`barah",
    "wof:placetype":"locality"
},
  "geometry": {"coordinates":[44.11845,13.94664],"type":"Point"}
}