{
  "type": "Feature",
  "properties": {
    "gn:country":"YE",
    "gn:fcode":"PPL",
    "gn:population":41,
    "iso:country":"YE",
    "name:ara_x_preferred":[
        "\u0627\u0644\u0642\u0635\u0628\u0629"
    ],
    "qs:name":"Al Qa\u015fabah",
    "qs:photos_9r":0,
    "qs:photos_sr":0,
    "qs:pop_sr":"1",
    "wof:name":"Al Qa\u015fabah",
    "wof:placetype":"locality",
    "wof:population":41
},
  "geometry": {"coordinates":[43.44536,16.16807],"type":"Point"}
}