{
  "type": "Feature",
  "properties": {
    "gn:country":"YE",
    "gn:fcode":"PPL",
    "gn:pop":6,
    "iso:country":"YE",
    "name:ara_x_preferred":[
        "\u0627\u0644\u0633\u0642\u064a\u0641\u0629"
    ],
    "name:eng_x_preferred":[
        "As Saqifah"
    ],
    "qs:name":"As Saq\u012bfah",
    "qs:photos_9r":0,
    "qs:photos_sr":0,
    "qs:pop_sr":"1",
    "wof:name":"As Saq\u012bfah",
    "wof:placetype":"locality",
    "wof:population":6
},
  "geometry": {"coordinates":[45.52604,15.00403],"type":"Point"}
}