{
  "type": "Feature",
  "properties": {
    "gn:admin1_code":"11.0",
    "gn:admin2_code":"2003.0",
    "gn:asciiname":"Wa`r",
    "gn:country_code":"YE",
    "gn:dem":1991,
    "gn:feature_class":"P",
    "gn:feature_code":"PPL",
    "gn:name":"Wa\u2018r",
    "gn:population":0,
    "gn:timezone":"Asia/Aden",
    "iso:country":"YE",
    "name:und_x_variant":[
        "Wa\u2018r"
    ],
    "wof:name":"Wa`r",
    "wof:placetype":"locality"
},
  "geometry": {"coordinates":[43.96184,14.70234],"type":"Point"}
}