{
  "type": "Feature",
  "properties": {
    "gn:country":"YE",
    "gn:fcode":"PPL",
    "gn:population":4,
    "iso:country":"YE",
    "name:ara_x_preferred":[
        "\u0627\u0644\u0644\u062d\u062c"
    ],
    "name:eng_x_preferred":[
        "Al Lahij"
    ],
    "name:eng_x_variant":[
        "Qarwa\u2018"
    ],
    "qs:name":"Al La\u1e29ij",
    "qs:photos_9r":0,
    "qs:photos_sr":0,
    "qs:pop_sr":"1",
    "wof:name":"Al La\u1e29ij",
    "wof:placetype":"locality",
    "wof:population":4
},
  "geometry": {"coordinates":[43.25334,17.13718],"type":"Point"}
}