{
  "type": "Feature",
  "properties": {
    "gn:admin1_code":"1.0",
    "gn:admin2_code":"1210.0",
    "gn:asciiname":"Ba Shaharah",
    "gn:country_code":"YE",
    "gn:dem":22,
    "gn:feature_class":"P",
    "gn:feature_code":"PPL",
    "gn:name":"B\u0101 Sha\u1e29\u0101rah",
    "gn:population":0,
    "gn:timezone":"Asia/Aden",
    "iso:country":"YE",
    "name:und_x_variant":[
        "B\u0101 Sha\u1e29\u0101rah"
    ],
    "wof:name":"Ba Shaharah",
    "wof:placetype":"locality"
},
  "geometry": {"coordinates":[45.36528,13.14083],"type":"Point"}
}