{
  "type": "Feature",
  "properties": {
    "gn:admin1_code":"22.0",
    "gn:admin2_code":"1704.0",
    "gn:asciiname":"Al Mahamirah",
    "gn:country_code":"YE",
    "gn:dem":219,
    "gn:feature_class":"P",
    "gn:feature_code":"PPL",
    "gn:name":"Al Ma\u1e29\u0101mirah",
    "gn:population":0,
    "gn:timezone":"Asia/Aden",
    "iso:country":"YE",
    "name:und_x_variant":[
        "Al Ma\u1e29\u0101mirah"
    ],
    "wof:name":"Al Mahamirah",
    "wof:placetype":"locality"
},
  "geometry": {"coordinates":[43.22938,16.02041],"type":"Point"}
}