{
  "type": "Feature",
  "properties": {
    "gn:admin1_code":"8.0",
    "gn:admin2_code":"1812.0",
    "gn:asciiname":"Az Zaqur",
    "gn:country_code":"YE",
    "gn:dem":1184,
    "gn:feature_class":"P",
    "gn:feature_code":"PPL",
    "gn:name":"Az Z\u0101q\u016br",
    "gn:population":0,
    "gn:timezone":"Asia/Aden",
    "iso:country":"YE",
    "name:ara_x_preferred":[
        "\u0627\u0644\u0632\u0627\u0642\u0648\u0631"
    ],
    "name:und_x_variant":[
        "Az Z\u0101q\u016br"
    ],
    "wof:name":"Az Zaqur",
    "wof:placetype":"locality"
},
  "geometry": {"coordinates":[43.43437,14.91915],"type":"Point"}
}