{
  "type": "Feature",
  "properties": {
    "gn:country":"YE",
    "gn:fcode":"PPL",
    "gn:pop":6,
    "iso:country":"YE",
    "name:ara_x_preferred":[
        "\u0627\u0644\u062f\u0641\u0646\u0629"
    ],
    "name:eng_x_preferred":[
        "Ad Dafnah"
    ],
    "qs:name":"Ad Dafnah",
    "qs:photos_9r":0,
    "qs:photos_sr":0,
    "qs:pop_sr":"1",
    "wof:name":"Ad Dafnah",
    "wof:placetype":"locality",
    "wof:population":6
},
  "geometry": {"coordinates":[43.78554,13.16203],"type":"Point"}
}