{
  "type": "Feature",
  "properties": {
    "gn:admin1_code":"4.0",
    "gn:admin2_code":"1917.0",
    "gn:asciiname":"Ghayl al Halikah",
    "gn:cc2":"YE",
    "gn:country_code":"YE",
    "gn:dem":1584,
    "gn:feature_class":"P",
    "gn:feature_code":"PPL",
    "gn:name":"Ghayl al \u1e28\u0101likah",
    "gn:population":0,
    "gn:timezone":"Asia/Aden",
    "iso:country":"YE",
    "name:und_x_variant":[
        "Ghail Halka",
        "Ghail al-H\u0101likah",
        "Ghayl al \u1e28\u0101likah"
    ],
    "wof:name":"Ghayl al Halikah",
    "wof:placetype":"locality"
},
  "geometry": {"coordinates":[48.76667,14.93333],"type":"Point"}
}