{
  "type": "Feature",
  "properties": {
    "gn:admin1_code":"25.0",
    "gn:admin2_code":"1501.0",
    "gn:asciiname":"Mu`aytib",
    "gn:country_code":"YE",
    "gn:dem":1294,
    "gn:feature_class":"P",
    "gn:feature_code":"PPL",
    "gn:name":"Mu\u2018ay\u0163ib",
    "gn:population":0,
    "gn:timezone":"Asia/Aden",
    "iso:country":"YE",
    "name:und_x_variant":[
        "Mu\u2018ay\u0163ib"
    ],
    "wof:name":"Mu`aytib",
    "wof:placetype":"locality"
},
  "geometry": {"coordinates":[44.21661,13.66222],"type":"Point"}
}