{
  "type": "Feature",
  "properties": {
    "gn:admin1_code":"8.0",
    "gn:admin2_code":"1810.0",
    "gn:asciiname":"Ad Daqawinah",
    "gn:country_code":"YE",
    "gn:dem":83,
    "gn:feature_class":"P",
    "gn:feature_code":"PPL",
    "gn:name":"Ad Daq\u0101winah",
    "gn:population":0,
    "gn:timezone":"Asia/Aden",
    "iso:country":"YE",
    "name:und_x_variant":[
        "Ad Daq\u0101wanah",
        "Ad Daq\u0101winah"
    ],
    "wof:name":"Ad Daqawinah",
    "wof:placetype":"locality"
},
  "geometry": {"coordinates":[43.09637,15.06555],"type":"Point"}
}