{
  "type": "Feature",
  "properties": {
    "gn:admin1_code":"22.0",
    "gn:admin2_code":"1709.0",
    "gn:asciiname":"Al Habit",
    "gn:country_code":"YE",
    "gn:dem":1039,
    "gn:feature_class":"P",
    "gn:feature_code":"PPL",
    "gn:name":"Al \u1e28\u0101bi\u0163",
    "gn:population":0,
    "gn:timezone":"Asia/Aden",
    "iso:country":"YE",
    "name:ara_x_preferred":[
        "Al \u1e28\u0101bi\u0163"
    ],
    "wof:name":"Al Habit",
    "wof:placetype":"locality"
},
  "geometry": {"coordinates":[43.5175,15.98363],"type":"Point"}
}