{
  "type": "Feature",
  "properties": {
    "gn:admin1_code":"24.0",
    "gn:admin2_code":"2513.0",
    "gn:asciiname":"An Nabiyah",
    "gn:country_code":"YE",
    "gn:dem":121,
    "gn:feature_class":"P",
    "gn:feature_code":"PPL",
    "gn:name":"An N\u0101b\u012byah",
    "gn:population":0,
    "gn:timezone":"Asia/Aden",
    "iso:country":"YE",
    "name:und_x_variant":[
        "Umm N\u0101biyah",
        "An Nabiya",
        "Am Nabia",
        "Am Nabiya",
        "Am N\u0101biyah",
        "An N\u0101b\u012byah"
    ],
    "wof:name":"An Nabiyah",
    "wof:placetype":"locality"
},
  "geometry": {"coordinates":[43.68953,12.8218],"type":"Point"}
}