{
  "type": "Feature",
  "properties": {
    "gn:admin1_code":"10.0",
    "gn:admin2_code":"2709.0",
    "gn:asciiname":"Bayt Turki",
    "gn:country_code":"YE",
    "gn:dem":1682,
    "gn:feature_class":"P",
    "gn:feature_code":"PPL",
    "gn:name":"Bayt Turk\u012b",
    "gn:population":0,
    "gn:timezone":"Asia/Aden",
    "iso:country":"YE",
    "name:und_x_variant":[
        "Bayt Turk\u012b"
    ],
    "wof:name":"Bayt Turki",
    "wof:placetype":"locality"
},
  "geometry": {"coordinates":[43.51994000000001,15.45864],"type":"Point"}
}