{
  "type": "Feature",
  "properties": {
    "gn:admin1_code":"23.0",
    "gn:admin2_code":"1101.0",
    "gn:asciiname":"Zahrat al Quham",
    "gn:country_code":"YE",
    "gn:dem":1279,
    "gn:feature_class":"P",
    "gn:feature_code":"PPL",
    "gn:name":"Z\u0327ahrat al Qu\u1e29am",
    "gn:population":0,
    "gn:timezone":"Asia/Aden",
    "iso:country":"YE",
    "name:ara_x_preferred":[
        "\u0638\u0647\u0631\u0629 \u0627\u0644\u0642\u062d\u0645"
    ],
    "name:und_x_variant":[
        "Z\u0327ahrat al Qu\u1e29am"
    ],
    "wof:name":"Zahrat al Quham",
    "wof:placetype":"locality"
},
  "geometry": {"coordinates":[44.09486,14.25805],"type":"Point"}
}