{
  "type": "Feature",
  "properties": {
    "gn:admin1_code":"14.0",
    "gn:admin2_code":"2613.0",
    "gn:asciiname":"Al Lamad",
    "gn:country_code":"YE",
    "gn:dem":1062,
    "gn:feature_class":"P",
    "gn:feature_code":"PPL",
    "gn:name":"\u0100l Lamad",
    "gn:population":0,
    "gn:timezone":"Asia/Aden",
    "iso:country":"YE",
    "name:ara_x_preferred":[
        "\u0627\u0644 \u0644\u0645\u062f"
    ],
    "name:und_x_variant":[
        "\u0100l Lamad"
    ],
    "wof:name":"Al Lamad",
    "wof:placetype":"locality"
},
  "geometry": {"coordinates":[45.41313,15.50424],"type":"Point"}
}