{
  "type": "Feature",
  "properties": {
    "gn:country":"YE",
    "gn:fcode":"PPL",
    "gn:pop":26,
    "iso:country":"YE",
    "name:ara_x_preferred":[
        "\u0627\u0644\u062d\u0631\u064a\u0628"
    ],
    "name:eng_x_preferred":[
        "Al Hurayb"
    ],
    "qs:name":"Al \u1e28urayb",
    "qs:photos_9r":0,
    "qs:photos_sr":0,
    "qs:pop_sr":"1",
    "wof:name":"Al \u1e28urayb",
    "wof:placetype":"locality",
    "wof:population":26
},
  "geometry": {"coordinates":[43.40682,16.30114],"type":"Point"}
}