{
  "type": "Feature",
  "properties": {
    "gn:country":"YE",
    "gn:fcode":"PPL",
    "gn:pop":21,
    "iso:country":"YE",
    "name:ara_x_preferred":[
        "\u0628\u0626\u0631 \u0628\u0631\u0643\u0627\u062a"
    ],
    "name:eng_x_preferred":[
        "Bir Barakat"
    ],
    "name:eng_x_variant":[
        "Ma\u1e29all \u1e28awshib"
    ],
    "qs:name":"Bi\u2019r Barak\u0101t",
    "qs:photos_9r":0,
    "qs:photos_sr":0,
    "qs:pop_sr":"1",
    "wof:name":"Bi\u2019r Barak\u0101t",
    "wof:placetype":"locality",
    "wof:population":21
},
  "geometry": {"coordinates":[43.77227,16.93402],"type":"Point"}
}