{
  "type": "Feature",
  "properties": {
    "gn:admin1_code":"11.0",
    "gn:admin2_code":"2005.0",
    "gn:asciiname":"Al Wak",
    "gn:cc2":"YE",
    "gn:country_code":"YE",
    "gn:dem":1901,
    "gn:feature_class":"P",
    "gn:feature_code":"PPL",
    "gn:name":"Al Wak",
    "gn:population":0,
    "gn:timezone":"Asia/Aden",
    "iso:country":"YE",
    "name:und_x_variant":[
        "El Wak",
        "Waq",
        "Al Wak"
    ],
    "wof:name":"Al Wak",
    "wof:placetype":"locality"
},
  "geometry": {"coordinates":[43.96667,14.46667],"type":"Point"}
}