{
  "type": "Feature",
  "properties": {
    "gn:admin1_code":"8.0",
    "gn:admin2_code":"1808.0",
    "gn:asciiname":"Mazra'at Balghayth 'Ali Dawm",
    "gn:country_code":"YE",
    "gn:dem":120,
    "gn:feature_class":"P",
    "gn:feature_code":"PPL",
    "gn:name":"Mazra\u2018at Balghayth \u2018Al\u012b Dawm",
    "gn:population":0,
    "gn:timezone":"Asia/Aden",
    "iso:country":"YE",
    "name:ara_x_preferred":[
        "\u0645\u0632\u0631\u0639\u0629 \u0628\u0644\u063a\u064a\u062b \u0639\u0644\u064a \u062f\u0648\u0645"
    ],
    "name:und_x_variant":[
        "Mazra\u2018at Balghayth \u2018Al\u012b Dawm"
    ],
    "wof:name":"Mazra'at Balghayth 'Ali Dawm",
    "wof:placetype":"locality"
},
  "geometry": {"coordinates":[43.19832,15.357],"type":"Point"}
}