{
  "type": "Feature",
  "properties": {
    "gn:admin1_code":"11.0",
    "gn:admin2_code":"2007.0",
    "gn:asciiname":"Mahall al Asraf",
    "gn:country_code":"YE",
    "gn:dem":917,
    "gn:feature_class":"P",
    "gn:feature_code":"PPL",
    "gn:name":"Ma\u1e29all al A\u015fr\u0101f",
    "gn:population":0,
    "gn:timezone":"Asia/Aden",
    "iso:country":"YE",
    "name:und_x_variant":[
        "Ma\u1e29all al A\u015fr\u0101f"
    ],
    "wof:name":"Mahall al Asraf",
    "wof:placetype":"locality"
},
  "geometry": {"coordinates":[43.64583,14.35487],"type":"Point"}
}