{
  "type": "Feature",
  "properties": {
    "gn:admin1_code":"23.0",
    "gn:admin2_code":"1108.0",
    "gn:asciiname":"Ash Shaturah",
    "gn:country_code":"YE",
    "gn:dem":2265,
    "gn:feature_class":"P",
    "gn:feature_code":"PPL",
    "gn:name":"Ash Shat\u016brah",
    "gn:population":0,
    "gn:timezone":"Asia/Aden",
    "iso:country":"YE",
    "name:ara_x_preferred":[
        "\u0627\u0644\u0634\u0646\u0648\u0631\u0629"
    ],
    "name:und_x_variant":[
        "Ash Shat\u016brah",
        "Ash Shan\u016brah"
    ],
    "wof:name":"Ash Shaturah",
    "wof:placetype":"locality"
},
  "geometry": {"coordinates":[44.09387,14.0506],"type":"Point"}
}