{
  "type": "Feature",
  "properties": {
    "gn:admin1_code":"11.0",
    "gn:admin2_code":"2008.0",
    "gn:asciiname":"Dhi Majid",
    "gn:country_code":"YE",
    "gn:dem":2381,
    "gn:feature_class":"P",
    "gn:feature_code":"PPL",
    "gn:name":"Dh\u012b M\u0101jid",
    "gn:population":0,
    "gn:timezone":"Asia/Aden",
    "iso:country":"YE",
    "name:ara_x_preferred":[
        "Dh\u012b M\u0101jid"
    ],
    "wof:name":"Dhi Majid",
    "wof:placetype":"locality"
},
  "geometry": {"coordinates":[44.42092,14.60996],"type":"Point"}
}