{
  "type": "Feature",
  "properties": {
    "gn:admin1_code":"8.0",
    "gn:admin2_code":"1807.0",
    "gn:asciiname":"Mahall Muhammad al Mashla'",
    "gn:country_code":"YE",
    "gn:dem":56,
    "gn:feature_class":"P",
    "gn:feature_code":"PPL",
    "gn:name":"Ma\u1e29all Mu\u1e29ammad al Mashl\u0101\u2019",
    "gn:population":0,
    "gn:timezone":"Asia/Aden",
    "iso:country":"YE",
    "name:ara_x_preferred":[
        "\u0645\u062d\u0644 \u0645\u062d\u0645\u062f \u0627\u0644\u0645\u0634\u0644\u0627\u0621"
    ],
    "name:und_x_variant":[
        "Ma\u1e29all Mu\u1e29ammad al Mashl\u0101\u2019"
    ],
    "wof:name":"Mahall Muhammad al Mashla'",
    "wof:placetype":"locality"
},
  "geometry": {"coordinates":[43.01772,15.34378],"type":"Point"}
}