{
  "type": "Feature",
  "properties": {
    "gn:admin1_code":"19.0",
    "gn:admin2_code":"2901.0",
    "gn:asciiname":"Ghawl al Qasabah",
    "gn:country_code":"YE",
    "gn:dem":1193,
    "gn:feature_class":"P",
    "gn:feature_code":"PPL",
    "gn:name":"Ghawl al Qa\u015fabah",
    "gn:population":0,
    "gn:timezone":"Asia/Aden",
    "iso:country":"YE",
    "name:ara_x_preferred":[
        "\u063a\u0648\u0644 \u0627\u0644\u0642\u0635\u0628\u0629"
    ],
    "name:und_x_variant":[
        "Ghawl al Qa\u015fabah"
    ],
    "wof:name":"Ghawl al Qasabah",
    "wof:placetype":"locality"
},
  "geometry": {"coordinates":[43.55004,16.3647],"type":"Point"}
}