{
  "type": "Feature",
  "properties": {
    "gn:admin1_code":"8.0",
    "gn:admin2_code":"1810.0",
    "gn:asciiname":"Mahall al Qayyim",
    "gn:country_code":"YE",
    "gn:dem":18,
    "gn:feature_class":"P",
    "gn:feature_code":"PPL",
    "gn:name":"Ma\u1e29all al Qayyim",
    "gn:population":0,
    "gn:timezone":"Asia/Aden",
    "iso:country":"YE",
    "name:und_x_variant":[
        "Ma\u1e29all al Qayyim"
    ],
    "wof:name":"Mahall al Qayyim",
    "wof:placetype":"locality"
},
  "geometry": {"coordinates":[42.89069,15.07759],"type":"Point"}
}