{
  "type": "Feature",
  "properties": {
    "gn:admin1_code":"16.0",
    "gn:admin2_code":"2316.0",
    "gn:asciiname":"Bayt al Khabani",
    "gn:country_code":"YE",
    "gn:dem":2197,
    "gn:feature_class":"P",
    "gn:feature_code":"PPL",
    "gn:name":"Bayt al Khab\u0101n\u012b",
    "gn:population":0,
    "gn:timezone":"Asia/Aden",
    "iso:country":"YE",
    "name:ara_x_preferred":[
        "\u0628\u064a\u062a \u0627\u0644\u062e\u0628\u0627\u0646\u064a"
    ],
    "name:und_x_variant":[
        "Bayt al Khab\u0101n\u012b"
    ],
    "wof:name":"Bayt al Khabani",
    "wof:placetype":"locality"
},
  "geometry": {"coordinates":[44.50817,15.11483],"type":"Point"}
}