{
  "type": "Feature",
  "properties": {
    "gn:admin1_code":"8.0",
    "gn:admin2_code":"1802.0",
    "gn:asciiname":"Dayr `Urrah",
    "gn:country_code":"YE",
    "gn:dem":78,
    "gn:feature_class":"P",
    "gn:feature_code":"PPL",
    "gn:name":"Dayr \u2018Urrah",
    "gn:population":0,
    "gn:timezone":"Asia/Aden",
    "iso:country":"YE",
    "name:und_x_variant":[
        "Dayr \u2018Urrah",
        "Arra"
    ],
    "wof:name":"Dayr `Urrah",
    "wof:placetype":"locality"
},
  "geometry": {"coordinates":[43.01717,15.62888],"type":"Point"}
}