{
  "type": "Feature",
  "properties": {
    "gn:country":"YE",
    "gn:fcode":"PPL",
    "gn:population":6,
    "iso:country":"YE",
    "name:ara_x_preferred":[
        "\u062d\u0646\u0627\u0646"
    ],
    "name:eng_x_preferred":[
        "Hannan"
    ],
    "name:eng_x_variant":[
        "Al Q\u0101\u2019im"
    ],
    "qs:name":"\u1e28ann\u0101n",
    "qs:photos_9r":0,
    "qs:photos_sr":0,
    "qs:pop_sr":"1",
    "wof:name":"\u1e28ann\u0101n",
    "wof:placetype":"locality",
    "wof:population":6
},
  "geometry": {"coordinates":[44.14563,17.0444],"type":"Point"}
}