{
  "type": "Feature",
  "properties": {
    "gn:admin1_code":"19.0",
    "gn:admin2_code":"2917.0",
    "gn:asciiname":"Bayt `Awad",
    "gn:country_code":"YE",
    "gn:dem":2618,
    "gn:feature_class":"P",
    "gn:feature_code":"PPL",
    "gn:name":"Bayt \u2018Aw\u0101\u1e11",
    "gn:population":0,
    "gn:timezone":"Asia/Aden",
    "iso:country":"YE",
    "name:und_x_variant":[
        "Bayt \u2018Aw\u0101\u1e11"
    ],
    "wof:name":"Bayt `Awad",
    "wof:placetype":"locality"
},
  "geometry": {"coordinates":[43.90867,15.55317],"type":"Point"}
}