{
  "type": "Feature",
  "properties": {
    "gn:country":"YE",
    "gn:fcode":"PPLF",
    "gn:pop":4,
    "iso:country":"YE",
    "name:ara_x_preferred":[
        "Dh\u016b \u2018Ayyid"
    ],
    "name:ara_x_variant":[
        "\u0630\u0648 \u0639\u064a\u062f"
    ],
    "name:eng_x_preferred":[
        "DhU 'Ayyid"
    ],
    "name:eng_x_variant":[
        "Al Ja\u2018rah"
    ],
    "qs:name":"Dh\u016b \u2018Ayyid",
    "qs:photos_9r":0,
    "qs:photos_sr":0,
    "qs:pop_sr":"1",
    "wof:name":"Dh\u016b \u2018Ayyid",
    "wof:placetype":"locality",
    "wof:population":4
},
  "geometry": {"coordinates":[44.05753,16.87635],"type":"Point"}
}