{
  "type": "Feature",
  "properties": {
    "gn:admin1_code":"8.0",
    "gn:admin2_code":"1812.0",
    "gn:asciiname":"Ad Dajrah",
    "gn:country_code":"YE",
    "gn:dem":1529,
    "gn:feature_class":"P",
    "gn:feature_code":"PPL",
    "gn:name":"Ad Dajrah",
    "gn:population":0,
    "gn:timezone":"Asia/Aden",
    "iso:country":"YE",
    "name:ara_x_preferred":[
        "\u0627\u0644\u062f\u062c\u0631\u0629"
    ],
    "wof:name":"Ad Dajrah",
    "wof:placetype":"locality"
},
  "geometry": {"coordinates":[43.45225,14.88292],"type":"Point"}
}