{
  "type": "Feature",
  "properties": {
    "gn:admin1_code":"14.0",
    "gn:admin2_code":"2606.0",
    "gn:asciiname":"Al az Zama'",
    "gn:country_code":"YE",
    "gn:dem":1487,
    "gn:feature_class":"P",
    "gn:feature_code":"PPL",
    "gn:name":"\u0100l az\u0327 Z\u0327am\u0101\u2019",
    "gn:population":0,
    "gn:timezone":"Asia/Aden",
    "iso:country":"YE",
    "name:ara_x_preferred":[
        "\u0622\u0644 \u0627\u0644\u0638\u0645\u0627\u0621"
    ],
    "name:und_x_variant":[
        "\u0100l az\u0327 Z\u0327am\u0101\u2019"
    ],
    "wof:name":"Al az Zama'",
    "wof:placetype":"locality"
},
  "geometry": {"coordinates":[45.01043,15.45172],"type":"Point"}
}