{
  "type": "Feature",
  "properties": {
    "gn:admin1_code":"14.0",
    "gn:asciiname":"Al Shalwah",
    "gn:country_code":"YE",
    "gn:dem":1183,
    "gn:feature_class":"P",
    "gn:feature_code":"PPL",
    "gn:name":"\u0100l Shalwah",
    "gn:population":0,
    "gn:timezone":"Asia/Aden",
    "iso:country":"YE",
    "name:ara_x_preferred":[
        "\u0622\u0644 \u0634\u0644\u0648\u0629"
    ],
    "name:und_x_variant":[
        "\u0100l Shalwah"
    ],
    "wof:name":"Al Shalwah",
    "wof:placetype":"locality"
},
  "geometry": {"coordinates":[44.53834000000001,16.27502],"type":"Point"}
}