{
  "type": "Feature",
  "properties": {
    "gn:admin1_code":"20.0",
    "gn:admin2_code":"1418.0",
    "gn:asciiname":"Qaryat al Hasan",
    "gn:country_code":"YE",
    "gn:dem":2669,
    "gn:feature_class":"P",
    "gn:feature_code":"PPL",
    "gn:name":"Qaryat al \u1e28asan",
    "gn:population":0,
    "gn:timezone":"Asia/Aden",
    "iso:country":"YE",
    "name:und_x_variant":[
        "Qaryat al \u1e28asan"
    ],
    "wof:name":"Qaryat al Hasan",
    "wof:placetype":"locality"
},
  "geometry": {"coordinates":[44.76021,14.25369],"type":"Point"}
}