{
  "type": "Feature",
  "properties": {
    "gn:admin1_code":"19.0",
    "gn:admin2_code":"2920.0",
    "gn:asciiname":"Al Hadabah",
    "gn:country_code":"YE",
    "gn:dem":2372,
    "gn:feature_class":"P",
    "gn:feature_code":"PPL",
    "gn:name":"Al \u1e28adabah",
    "gn:population":0,
    "gn:timezone":"Asia/Aden",
    "iso:country":"YE",
    "name:ara_x_preferred":[
        "\u0627\u0644\u062d\u062f\u0628\u0629"
    ],
    "name:und_x_variant":[
        "Al \u1e28adabah"
    ],
    "wof:name":"Al Hadabah",
    "wof:placetype":"locality"
},
  "geometry": {"coordinates":[43.97641,16.11097],"type":"Point"}
}