{
  "type": "Feature",
  "properties": {
    "gn:admin1_code":"8.0",
    "gn:admin2_code":"1810.0",
    "gn:asciiname":"As Sawalimah",
    "gn:country_code":"YE",
    "gn:dem":195,
    "gn:feature_class":"P",
    "gn:feature_code":"PPL",
    "gn:name":"As Saw\u0101limah",
    "gn:population":0,
    "gn:timezone":"Asia/Aden",
    "iso:country":"YE",
    "name:ara_x_preferred":[
        "\u0627\u0644\u0633\u0648\u0627\u0644\u0645\u0629"
    ],
    "name:und_x_variant":[
        "As Saw\u0101limah"
    ],
    "wof:name":"As Sawalimah",
    "wof:placetype":"locality"
},
  "geometry": {"coordinates":[43.25713,15.23046],"type":"Point"}
}