{
  "type": "Feature",
  "properties": {
    "gn:admin1_code":"8.0",
    "gn:admin2_code":"1812.0",
    "gn:asciiname":"Habil Raybah",
    "gn:country_code":"YE",
    "gn:dem":293,
    "gn:feature_class":"P",
    "gn:feature_code":"PPL",
    "gn:name":"\u1e28ab\u012bl Raybah",
    "gn:population":0,
    "gn:timezone":"Asia/Aden",
    "iso:country":"YE",
    "name:ara_x_preferred":[
        "\u062d\u0628\u064a\u0644 \u0631\u064a\u0628\u0629"
    ],
    "name:und_x_variant":[
        "\u1e28ab\u012bl Raybah",
        "\u1e28ubayl R\u012bbah"
    ],
    "wof:name":"Habil Raybah",
    "wof:placetype":"locality"
},
  "geometry": {"coordinates":[43.40243,14.95506],"type":"Point"}
}