{
  "type": "Feature",
  "properties": {
    "gn:gn_country":"YE",
    "gn:gn_fcode":"PPL",
    "gn:gn_pop":17,
    "gn:population":17,
    "iso:country":"YE",
    "name:ara_x_preferred":[
        "\u0627\u0644\u0639\u0646\u062c\u0629"
    ],
    "name:eng_x_preferred":[
        "Al 'Anijah"
    ],
    "qs_pg:aaroncc":"YE",
    "qs_pg:gn_country":"YE",
    "qs_pg:gn_fcode":"PPL",
    "qs_pg:gn_pop":17,
    "qs_pg:name":"Al \u2018Anijah",
    "qs_pg:photos_9r":0,
    "qs_pg:photos_sr":0,
    "qs_pg:pop_sr":1,
    "qs_pg:qs_pg_placetype":"locality",
    "wof:name":"Al \u2018Anijah",
    "wof:placetype":"locality",
    "wof:population":17
},
  "geometry": {"coordinates":[43.2821,17.46592],"type":"Point"}
}