{
  "type": "Feature",
  "properties": {
    "gn:country":"YE",
    "gn:fcode":"PPL",
    "gn:population":6,
    "iso:country":"YE",
    "name:ara_x_preferred":[
        "\u0628\u0626\u0631 \u062f\u0639\u0646\u064a\u0634"
    ],
    "name:eng_x_preferred":[
        "Bir Du'naysh"
    ],
    "name:eng_x_variant":[
        "Naq\u012bl al W\u0101\u2019"
    ],
    "qs:name":"Bi\u2019r Du\u2018naysh",
    "qs:photos_9r":0,
    "qs:photos_sr":0,
    "qs:pop_sr":"1",
    "wof:name":"Bi\u2019r Du\u2018naysh",
    "wof:placetype":"locality",
    "wof:population":6
},
  "geometry": {"coordinates":[43.79905,16.83226],"type":"Point"}
}