{
  "type": "Feature",
  "properties": {
    "gn:admin1_code":"5.0",
    "gn:admin2_code":"2110.0",
    "gn:asciiname":"Qaryat al Ghayl",
    "gn:cc2":"YE",
    "gn:country_code":"YE",
    "gn:dem":1247,
    "gn:feature_class":"P",
    "gn:feature_code":"PPL",
    "gn:name":"Qaryat al Ghayl",
    "gn:population":0,
    "gn:timezone":"Asia/Aden",
    "iso:country":"YE",
    "name:und_x_variant":[
        "Qaryat al-Ghail",
        "Qaryat al Ghayl"
    ],
    "wof:name":"Qaryat al Ghayl",
    "wof:placetype":"locality"
},
  "geometry": {"coordinates":[46.46667,14.31667],"type":"Point"}
}