{
  "type": "Feature",
  "properties": {
    "gn:admin1_code":"22.0",
    "gn:admin2_code":"1728.0",
    "gn:asciiname":"Mahall Bani al Qadhafi",
    "gn:country_code":"YE",
    "gn:dem":1248,
    "gn:feature_class":"P",
    "gn:feature_code":"PPL",
    "gn:name":"Ma\u1e29all Ban\u012b al Qadhaf\u012b",
    "gn:population":0,
    "gn:timezone":"Asia/Aden",
    "iso:country":"YE",
    "name:und_x_variant":[
        "Ma\u1e29all Ban\u012b al Qadhaf\u012b"
    ],
    "wof:name":"Mahall Bani al Qadhafi",
    "wof:placetype":"locality"
},
  "geometry": {"coordinates":[43.56761,15.69044],"type":"Point"}
}