{
  "type": "Feature",
  "properties": {
    "gn:admin1_code":"8.0",
    "gn:admin2_code":"1815.0",
    "gn:asciiname":"Mahall ash Sha`wah",
    "gn:country_code":"YE",
    "gn:dem":205,
    "gn:feature_class":"P",
    "gn:feature_code":"PPL",
    "gn:name":"Ma\u1e29all ash Sha\u2018wah",
    "gn:population":0,
    "gn:timezone":"Asia/Aden",
    "iso:country":"YE",
    "name:und_x_variant":[
        "Ma\u1e29all ash Sha\u2018wah",
        "Ma\u1e29all Sha\u2018wah"
    ],
    "wof:name":"Mahall ash Sha`wah",
    "wof:placetype":"locality"
},
  "geometry": {"coordinates":[43.40856,14.81976],"type":"Point"}
}