{
  "type": "Feature",
  "properties": {
    "gn:admin1_code":"8.0",
    "gn:admin2_code":"1801.0",
    "gn:asciiname":"Dayr al Hajarah",
    "gn:country_code":"YE",
    "gn:dem":138,
    "gn:feature_class":"P",
    "gn:feature_code":"PPL",
    "gn:name":"Dayr al \u1e28ajarah",
    "gn:population":0,
    "gn:timezone":"Asia/Aden",
    "iso:country":"YE",
    "name:und_x_variant":[
        "Dayr al \u1e28ajarah",
        "Dayr al \u1e28ujrah"
    ],
    "wof:name":"Dayr al Hajarah",
    "wof:placetype":"locality"
},
  "geometry": {"coordinates":[43.14852,15.74076],"type":"Point"}
}