{
  "type": "Feature",
  "properties": {
    "gn:gn_country":"YE",
    "gn:gn_fcode":"PPLX",
    "gn:gn_pop":63,
    "gn:population":63,
    "iso:country":"YE",
    "name:ara_x_preferred":[
        "\u0627\u0644 \u0627\u0644\u0639\u062c\u0631\u064a"
    ],
    "qs_pg:aaroncc":"YE",
    "qs_pg:gn_country":"YE",
    "qs_pg:gn_fcode":"PPLX",
    "qs_pg:gn_pop":63,
    "qs_pg:name":"\u0100l al \u2018Ujr\u012b",
    "qs_pg:photos_9r":0,
    "qs_pg:photos_sr":0,
    "qs_pg:pop_sr":1,
    "qs_pg:qs_pg_placetype":"neighbourhood",
    "wof:name":"\u0100l al \u2018Ujr\u012b",
    "wof:placetype":"neighbourhood",
    "wof:population":63
},
  "geometry": {"coordinates":[43.59692,17.0605],"type":"Point"}
}