{
  "type": "Feature",
  "properties": {
    "gn:admin1_code":"16.0",
    "gn:admin2_code":"2307.0",
    "gn:asciiname":"Al Masna`ah",
    "gn:country_code":"YE",
    "gn:dem":2658,
    "gn:feature_class":"P",
    "gn:feature_code":"PPL",
    "gn:name":"Al Ma\u015fna\u2018ah",
    "gn:population":0,
    "gn:timezone":"Asia/Aden",
    "iso:country":"YE",
    "name:und_x_variant":[
        "Al Ma\u015fna\u2018ah"
    ],
    "wof:name":"Al Masna`ah",
    "wof:placetype":"locality"
},
  "geometry": {"coordinates":[44.00100000000001,15.14216],"type":"Point"}
}