{
  "type": "Feature",
  "properties": {
    "gn:admin1_code":"25.0",
    "gn:admin2_code":"1513.0",
    "gn:asciiname":"`Afanan",
    "gn:country_code":"YE",
    "gn:dem":1469,
    "gn:feature_class":"P",
    "gn:feature_code":"PPL",
    "gn:name":"\u2018Afan\u0101n",
    "gn:population":0,
    "gn:timezone":"Asia/Aden",
    "iso:country":"YE",
    "name:und_x_variant":[
        "\u2018Afan\u0101n"
    ],
    "wof:name":"`Afanan",
    "wof:placetype":"locality"
},
  "geometry": {"coordinates":[44.30346,13.32216],"type":"Point"}
}