{
  "type": "Feature",
  "properties": {
    "gn:admin1_code":"22.0",
    "gn:admin2_code":"1713.0",
    "gn:asciiname":"Al Ma`bush",
    "gn:country_code":"YE",
    "gn:dem":452,
    "gn:feature_class":"P",
    "gn:feature_code":"PPL",
    "gn:name":"Al Ma\u2018b\u016bsh",
    "gn:population":0,
    "gn:timezone":"Asia/Aden",
    "iso:country":"YE",
    "name:und_x_variant":[
        "Al Ma\u2018b\u016bsh"
    ],
    "wof:name":"Al Ma`bush",
    "wof:placetype":"locality"
},
  "geometry": {"coordinates":[43.3112,15.90472],"type":"Point"}
}