{
  "type": "Feature",
  "properties": {
    "gn:admin1_code":"14.0",
    "gn:admin2_code":"2608.0",
    "gn:asciiname":"Al 'Arab",
    "gn:country_code":"YE",
    "gn:dem":2005,
    "gn:feature_class":"P",
    "gn:feature_code":"PPL",
    "gn:name":"Al \u2018Ar\u0101b",
    "gn:population":0,
    "gn:timezone":"Asia/Aden",
    "iso:country":"YE",
    "name:ara_x_preferred":[
        "\u0627\u0644\u0639\u0631\u0627\u0628"
    ],
    "name:und_x_variant":[
        "Al \u2018Ar\u0101b"
    ],
    "wof:name":"Al 'Arab",
    "wof:placetype":"locality"
},
  "geometry": {"coordinates":[45.13321,15.00216],"type":"Point"}
}