{
  "type": "Feature",
  "properties": {
    "gn:admin1_code":"24.0",
    "gn:admin2_code":"2513.0",
    "gn:asciiname":"Shatt at Tawil",
    "gn:country_code":"YE",
    "gn:dem":349,
    "gn:feature_class":"P",
    "gn:feature_code":"PPL",
    "gn:name":"Sha\u0163\u0163 a\u0163 \u0162aw\u012bl",
    "gn:population":0,
    "gn:timezone":"Asia/Aden",
    "iso:country":"YE",
    "name:und_x_variant":[
        "Sha\u0163\u0163 a\u0163 \u0162aw\u012bl"
    ],
    "wof:name":"Shatt at Tawil",
    "wof:placetype":"locality"
},
  "geometry": {"coordinates":[43.98352,12.99288],"type":"Point"}
}