{
  "type": "Feature",
  "properties": {
    "gn:admin1_code":"8.0",
    "gn:admin2_code":"1810.0",
    "gn:asciiname":"Mahall `Ali Qasim",
    "gn:country_code":"YE",
    "gn:dem":81,
    "gn:feature_class":"P",
    "gn:feature_code":"PPL",
    "gn:name":"Ma\u1e29all \u2018Al\u012b Q\u0101sim",
    "gn:population":0,
    "gn:timezone":"Asia/Aden",
    "iso:country":"YE",
    "name:ara_x_preferred":[
        "\u0645\u062d\u0644 \u0639\u0644\u064a \u0642\u0627\u0633\u0645"
    ],
    "name:und_x_variant":[
        "Ma\u1e29all \u2018Al\u012b Q\u0101sim"
    ],
    "wof:name":"Mahall `Ali Qasim",
    "wof:placetype":"locality"
},
  "geometry": {"coordinates":[43.08867,15.18392],"type":"Point"}
}