{
  "type": "Feature",
  "properties": {
    "gn:admin1_code":"25.0",
    "gn:admin2_code":"1512.0",
    "gn:asciiname":"Mukhray`ah",
    "gn:country_code":"YE",
    "gn:dem":1782,
    "gn:feature_class":"P",
    "gn:feature_code":"PPL",
    "gn:name":"Mukhray\u2018ah",
    "gn:population":0,
    "gn:timezone":"Asia/Aden",
    "iso:country":"YE",
    "name:und_x_variant":[
        "Mukhray\u2018ah"
    ],
    "wof:name":"Mukhray`ah",
    "wof:placetype":"locality"
},
  "geometry": {"coordinates":[44.03167,13.44754],"type":"Point"}
}