{
  "type": "Feature",
  "properties": {
    "gn:admin1_code":"14.0",
    "gn:admin2_code":"2613.0",
    "gn:asciiname":"Ar Rakah",
    "gn:country_code":"YE",
    "gn:dem":1073,
    "gn:feature_class":"P",
    "gn:feature_code":"PPL",
    "gn:name":"Ar R\u0101kah",
    "gn:population":0,
    "gn:timezone":"Asia/Aden",
    "iso:country":"YE",
    "name:ara_x_preferred":[
        "\u0627\u0644\u0631\u0627\u0643\u0629"
    ],
    "name:und_x_variant":[
        "Ar R\u0101kah"
    ],
    "wof:name":"Ar Rakah",
    "wof:placetype":"locality"
},
  "geometry": {"coordinates":[45.40256,15.47404],"type":"Point"}
}