{
  "type": "Feature",
  "properties": {
    "gn:admin1_code":"16.0",
    "gn:admin2_code":"2314.0",
    "gn:asciiname":"Al Khatri",
    "gn:country_code":"YE",
    "gn:dem":2243,
    "gn:feature_class":"P",
    "gn:feature_code":"PPL",
    "gn:name":"Al Kha\u0163r\u012b",
    "gn:population":0,
    "gn:timezone":"Asia/Aden",
    "iso:country":"YE",
    "name:ara_x_preferred":[
        "\u0627\u0644\u062e\u0637\u0631\u0649"
    ],
    "name:und_x_variant":[
        "Al Kha\u0163r\u012b"
    ],
    "wof:name":"Al Khatri",
    "wof:placetype":"locality"
},
  "geometry": {"coordinates":[44.95309,15.1243],"type":"Point"}
}