{
  "type": "Feature",
  "properties": {
    "gn:admin1_code":"24.0",
    "gn:admin2_code":"2509.0",
    "gn:asciiname":"Al Hashfar",
    "gn:country_code":"YE",
    "gn:dem":945,
    "gn:feature_class":"P",
    "gn:feature_code":"PPL",
    "gn:name":"Al \u1e28ashfar",
    "gn:population":0,
    "gn:timezone":"Asia/Aden",
    "iso:country":"YE",
    "name:und_x_variant":[
        "Al \u1e28ashfar"
    ],
    "wof:name":"Al Hashfar",
    "wof:placetype":"locality"
},
  "geometry": {"coordinates":[44.44856,13.51458],"type":"Point"}
}