{
  "type": "Feature",
  "properties": {
    "gn:admin1_code":"15.0",
    "gn:admin2_code":"2212.0",
    "gn:asciiname":"Al Maqam",
    "gn:country_code":"YE",
    "gn:dem":1870,
    "gn:feature_class":"P",
    "gn:feature_code":"PPL",
    "gn:name":"Al Maq\u0101m",
    "gn:population":0,
    "gn:timezone":"Asia/Aden",
    "iso:country":"YE",
    "name:ara_x_preferred":[
        "\u0627\u0644\u0645\u0642\u0627\u0645"
    ],
    "name:und_x_variant":[
        "Al Maq\u0101m"
    ],
    "wof:name":"Al Maqam",
    "wof:placetype":"locality"
},
  "geometry": {"coordinates":[43.82624000000001,16.97997],"type":"Point"}
}