{
  "type": "Feature",
  "properties": {
    "gn:admin1_code":"23.0",
    "gn:admin2_code":"1102.0",
    "gn:asciiname":"Al Mihfad al 'Ali",
    "gn:country_code":"YE",
    "gn:dem":2681,
    "gn:feature_class":"P",
    "gn:feature_code":"PPL",
    "gn:name":"Al Mi\u1e29fad al \u2018\u0100l\u012b",
    "gn:population":0,
    "gn:timezone":"Asia/Aden",
    "iso:country":"YE",
    "name:ara_x_preferred":[
        "\u0627\u0644\u0645\u062d\u0641\u062f \u0627\u0644\u0639\u0627\u0644\u064a"
    ],
    "name:und_x_variant":[
        "Al Mi\u1e29fad al \u2018\u0100l\u012b"
    ],
    "wof:name":"Al Mihfad al 'Ali",
    "wof:placetype":"locality"
},
  "geometry": {"coordinates":[44.20193,14.3412],"type":"Point"}
}