{
  "type": "Feature",
  "properties": {
    "gn:admin1_code":"8.0",
    "gn:admin2_code":"1819.0",
    "gn:asciiname":"Al Hab`i",
    "gn:country_code":"YE",
    "gn:dem":244,
    "gn:feature_class":"P",
    "gn:feature_code":"PPL",
    "gn:name":"Al \u1e28ab\u2018\u012b",
    "gn:population":0,
    "gn:timezone":"Asia/Aden",
    "iso:country":"YE",
    "name:und_x_variant":[
        "El Hurbi",
        "Al Hurbi",
        "Al \u1e28ab\u2018\u012b"
    ],
    "wof:name":"Al Hab`i",
    "wof:placetype":"locality"
},
  "geometry": {"coordinates":[43.51806,13.91528],"type":"Point"}
}