{
  "type": "Feature",
  "properties": {
    "gn:admin1_code":"8.0",
    "gn:admin2_code":"1818.0",
    "gn:asciiname":"Ad Dar",
    "gn:country_code":"YE",
    "gn:dem":613,
    "gn:feature_class":"P",
    "gn:feature_code":"PPL",
    "gn:name":"Ad D\u0101r",
    "gn:population":0,
    "gn:timezone":"Asia/Aden",
    "iso:country":"YE",
    "name:ara_x_preferred":[
        "Ad D\u0101r"
    ],
    "name:ara_x_variant":[
        "\u0627\u0644\u062f\u0627\u0631"
    ],
    "wof:name":"Ad Dar",
    "wof:placetype":"locality"
},
  "geometry": {"coordinates":[43.7113,13.99119],"type":"Point"}
}