{
  "type": "Feature",
  "properties": {
    "gn:admin1_code":"23.0",
    "gn:admin2_code":"1105.0",
    "gn:asciiname":"Manzil `Ulwan",
    "gn:country_code":"YE",
    "gn:dem":2470,
    "gn:feature_class":"P",
    "gn:feature_code":"PPL",
    "gn:name":"Manzil \u2018Ulw\u0101n",
    "gn:population":0,
    "gn:timezone":"Asia/Aden",
    "iso:country":"YE",
    "name:ara_x_preferred":[
        "\u0645\u0646\u0632\u0644 \u0639\u0644\u0648\u0627\u0646"
    ],
    "name:und_x_variant":[
        "Manzil \u2018Alw\u0101n",
        "Manzil \u2018Ulw\u0101n"
    ],
    "wof:name":"Manzil `Ulwan",
    "wof:placetype":"locality"
},
  "geometry": {"coordinates":[44.36797,14.02373],"type":"Point"}
}