{
  "type": "Feature",
  "properties": {
    "gn:country":"YE",
    "gn:fcode":"PPLF",
    "gn:pop":56,
    "iso:country":"YE",
    "name:ara_x_preferred":[
        "\u0622\u0644 \u0627\u0644\u0630\u064a\u0628\u0627\u0646"
    ],
    "name:eng_x_preferred":[
        "Al Adh Dhayban"
    ],
    "qs:name":"\u0100l adh Dhayb\u0101n",
    "qs:photos_9r":0,
    "qs:photos_sr":0,
    "qs:pop_sr":"1",
    "wof:name":"\u0100l adh Dhayb\u0101n",
    "wof:placetype":"locality",
    "wof:population":56
},
  "geometry": {"coordinates":[43.68502,16.98902],"type":"Point"}
}