{
  "type": "Feature",
  "properties": {
    "gn:admin1_code":"8.0",
    "gn:admin2_code":"1826.0",
    "gn:asciiname":"Al Tuhayta'",
    "gn:country_code":"YE",
    "gn:dem":64,
    "gn:feature_class":"P",
    "gn:feature_code":"PPLA2",
    "gn:name":"Al Tu\u1e29ayt\u0101\u2019",
    "gn:population":0,
    "gn:timezone":"Asia/Aden",
    "iso:country":"YE",
    "name:ara_x_preferred":[
        "\u0627\u0644\u062a\u062d\u064a\u062a\u0627\u0621"
    ],
    "name:und_x_variant":[
        "Tahaite",
        "At Tu\u1e29aytah",
        "At Ta\u1e29ayth\u0101",
        "At Tu\u1e29ayta",
        "At Tu\u1e29ayth\u0101",
        "Al Tu\u1e29ayt\u0101\u2019",
        "At Tu\u1e29ayt\u0101\u2019"
    ],
    "wof:name":"Al Tuhayta'",
    "wof:placetype":"locality"
},
  "geometry": {"coordinates":[43.22637,14.18356],"type":"Point"}
}