{
  "type": "Feature",
  "properties": {
    "gn:admin1_code":"22.0",
    "gn:admin2_code":"1717.0",
    "gn:asciiname":"Ad Dayq",
    "gn:country_code":"YE",
    "gn:dem":643,
    "gn:feature_class":"P",
    "gn:feature_code":"PPL",
    "gn:name":"A\u1e11 \u1e10ayq",
    "gn:population":0,
    "gn:timezone":"Asia/Aden",
    "iso:country":"YE",
    "name:und_x_variant":[
        "A\u1e11 \u1e10ayq"
    ],
    "wof:name":"Ad Dayq",
    "wof:placetype":"locality"
},
  "geometry": {"coordinates":[43.58045,15.85373],"type":"Point"}
}