{
  "type": "Feature",
  "properties": {
    "gn:admin1_code":"23.0",
    "gn:admin2_code":"1107.0",
    "gn:asciiname":"Al Quhim",
    "gn:country_code":"YE",
    "gn:dem":1642,
    "gn:feature_class":"P",
    "gn:feature_code":"PPL",
    "gn:name":"Al Qu\u1e29\u012bm",
    "gn:population":0,
    "gn:timezone":"Asia/Aden",
    "iso:country":"YE",
    "name:ara_x_preferred":[
        "Al Qu\u1e29\u012bm"
    ],
    "wof:name":"Al Quhim",
    "wof:placetype":"locality"
},
  "geometry": {"coordinates":[44.18119,14.1826],"type":"Point"}
}