{
  "type": "Feature",
  "properties": {
    "gn:admin1_code":"23.0",
    "gn:admin2_code":"1113.0",
    "gn:asciiname":"Maswarah",
    "gn:country_code":"YE",
    "gn:dem":1785,
    "gn:feature_class":"P",
    "gn:feature_code":"PPL",
    "gn:name":"Maswarah",
    "gn:population":0,
    "gn:timezone":"Asia/Aden",
    "iso:country":"YE",
    "name:und_x_variant":[
        "Ma\u015fna\u2018ah"
    ],
    "wof:name":"Maswarah",
    "wof:placetype":"locality"
},
  "geometry": {"coordinates":[44.41017,13.97752],"type":"Point"}
}