{
  "type": "Feature",
  "properties": {
    "gn:admin1_code":"8.0",
    "gn:admin2_code":"1805.0",
    "gn:asciiname":"Musawi al Hillah",
    "gn:country_code":"YE",
    "gn:dem":47,
    "gn:feature_class":"P",
    "gn:feature_code":"PPL",
    "gn:name":"Mus\u0101w\u012b al \u1e28illah",
    "gn:population":0,
    "gn:timezone":"Asia/Aden",
    "iso:country":"YE",
    "name:ara_x_preferred":[
        "\u0645\u0633\u0627\u0648\u064a \u0627\u0644\u062d\u0644\u0629"
    ],
    "name:und_x_variant":[
        "Mus\u0101w\u012b al \u1e28illah"
    ],
    "wof:name":"Musawi al Hillah",
    "wof:placetype":"locality"
},
  "geometry": {"coordinates":[42.96988,15.36954],"type":"Point"}
}