{
  "type": "Feature",
  "properties": {
    "gn:country":"YE",
    "gn:fcode":"PPL",
    "gn:pop":3,
    "iso:country":"YE",
    "name:ara_x_preferred":[
        "\u0646\u064a\u062f \u0627\u0644\u0646\u0639\u064a\u0645"
    ],
    "name:eng_x_preferred":[
        "Nayd Al Na'im"
    ],
    "qs:name":"Nayd al Na\u2018\u012bm",
    "qs:photos_9r":0,
    "qs:photos_sr":0,
    "qs:pop_sr":"1",
    "wof:name":"Nayd al Na\u2018\u012bm",
    "wof:placetype":"locality",
    "wof:population":3
},
  "geometry": {"coordinates":[43.25273,17.18286],"type":"Point"}
}