{
  "type": "Feature",
  "properties": {
    "gn:admin1_code":"10.0",
    "gn:admin2_code":"2703.0",
    "gn:asciiname":"Al `Arif",
    "gn:country_code":"YE",
    "gn:dem":1848,
    "gn:feature_class":"P",
    "gn:feature_code":"PPL",
    "gn:name":"Al \u2018Ar\u012bf",
    "gn:population":0,
    "gn:timezone":"Asia/Aden",
    "iso:country":"YE",
    "name:ara_x_preferred":[
        "Al \u2018Ar\u012bf"
    ],
    "name:fas_x_preferred":[
        "\u0627\u0644\u0639\u0631\u06cc\u0641"
    ],
    "name:nno_x_preferred":[
        "Al `Arif"
    ],
    "wof:name":"Al `Arif",
    "wof:placetype":"locality"
},
  "geometry": {"coordinates":[43.6534,15.41835],"type":"Point"}
}