{
  "type": "Feature",
  "properties": {
    "gn:admin1_code":"11.0",
    "gn:admin2_code":"2010.0",
    "gn:asciiname":"Bayt al Jamal",
    "gn:country_code":"YE",
    "gn:dem":2234,
    "gn:feature_class":"P",
    "gn:feature_code":"PPL",
    "gn:name":"Bayt al Jamal",
    "gn:population":0,
    "gn:timezone":"Asia/Aden",
    "iso:country":"YE",
    "wof:name":"Bayt al Jamal",
    "wof:placetype":"locality"
},
  "geometry": {"coordinates":[44.18136,14.53441],"type":"Point"}
}