{
  "type": "Feature",
  "properties": {
    "gn:admin1_code":"11.0",
    "gn:admin2_code":"2006.0",
    "gn:asciiname":"Suq al Ithnayn",
    "gn:country_code":"YE",
    "gn:dem":1279,
    "gn:feature_class":"P",
    "gn:feature_code":"PPL",
    "gn:name":"S\u016bq al Ithnayn",
    "gn:population":0,
    "gn:timezone":"Asia/Aden",
    "iso:country":"YE",
    "name:und_x_variant":[
        "S\u016bq al Ithnayn"
    ],
    "wof:name":"Suq al Ithnayn",
    "wof:placetype":"locality"
},
  "geometry": {"coordinates":[43.81705,14.36215],"type":"Point"}
}