{
  "type": "Feature",
  "properties": {
    "gn:admin1_code":"8.0",
    "gn:admin2_code":"1810.0",
    "gn:asciiname":"Shaba",
    "gn:country_code":"YE",
    "gn:dem":431,
    "gn:feature_class":"P",
    "gn:feature_code":"PPL",
    "gn:name":"Shaba",
    "gn:population":0,
    "gn:timezone":"Asia/Aden",
    "iso:country":"YE",
    "name:bar_x_preferred":[
        "Shaba"
    ],
    "name:ceb_x_preferred":[
        "Shaba"
    ],
    "name:deu_x_preferred":[
        "Shaba"
    ],
    "name:ita_x_preferred":[
        "Shaba"
    ],
    "name:swe_x_preferred":[
        "Shaba"
    ],
    "wof:name":"Shaba",
    "wof:placetype":"locality"
},
  "geometry": {"coordinates":[43.48722,15.01476],"type":"Point"}
}