{
  "type": "Feature",
  "properties": {
    "gn:admin1_code":"23.0",
    "gn:admin2_code":"1105.0",
    "gn:asciiname":"Rawhan",
    "gn:country_code":"YE",
    "gn:dem":2349,
    "gn:feature_class":"P",
    "gn:feature_code":"PPL",
    "gn:name":"Raw\u1e29\u0101n",
    "gn:population":0,
    "gn:timezone":"Asia/Aden",
    "iso:country":"YE",
    "name:ara_x_preferred":[
        "\u0631\u0648\u062d\u0627\u0646"
    ],
    "name:und_x_variant":[
        "Raw\u1e29\u0101n"
    ],
    "wof:name":"Rawhan",
    "wof:placetype":"locality"
},
  "geometry": {"coordinates":[44.41905,14.01001],"type":"Point"}
}