{
  "type": "Feature",
  "properties": {
    "gn:country":"YE",
    "gn:fcode":"PPL",
    "gn:pop":1,
    "iso:country":"YE",
    "name:ara_x_preferred":[
        "Al Mur\u0101d\u012b"
    ],
    "name:ara_x_variant":[
        "\u0627\u0644\u0645\u0631\u0627\u062f\u064a"
    ],
    "name:eng_x_preferred":[
        "Al Muradi"
    ],
    "qs:name":"Al Mur\u0101d\u012b",
    "qs:photos_9r":0,
    "qs:photos_sr":0,
    "qs:pop_sr":"1",
    "wof:name":"Al Mur\u0101d\u012b",
    "wof:placetype":"locality",
    "wof:population":1
},
  "geometry": {"coordinates":[45.11655,14.71007],"type":"Point"}
}