{
  "type": "Feature",
  "properties": {
    "gn:country":"YE",
    "gn:fcode":"PPL",
    "gn:pop":6,
    "iso:country":"YE",
    "name:ara_x_preferred":[
        "\u0627\u0644\u0631\u062f\u064a\u062d"
    ],
    "qs:name":"Ar Ruday\u1e29",
    "qs:photos_9r":0,
    "qs:photos_sr":0,
    "qs:pop_sr":"1",
    "wof:name":"Ar Ruday\u1e29",
    "wof:placetype":"locality",
    "wof:population":6
},
  "geometry": {"coordinates":[43.30639,16.60303],"type":"Point"}
}