{
  "type": "Feature",
  "properties": {
    "gn:admin1_code":"22.0",
    "gn:admin2_code":"1726.0",
    "gn:asciiname":"Sabahiyah",
    "gn:country_code":"YE",
    "gn:dem":735,
    "gn:feature_class":"P",
    "gn:feature_code":"PPL",
    "gn:name":"Sab\u0101\u1e29\u012byah",
    "gn:population":0,
    "gn:timezone":"Asia/Aden",
    "iso:country":"YE",
    "name:und_x_variant":[
        "Sab\u0101\u1e29\u012byah",
        "Sib\u0101\u1e29\u012byah"
    ],
    "wof:name":"Sabahiyah",
    "wof:placetype":"locality"
},
  "geometry": {"coordinates":[43.53009,15.67853],"type":"Point"}
}