{
  "type": "Feature",
  "properties": {
    "gn:admin1_code":"15.0",
    "gn:admin2_code":"2208.0",
    "gn:asciiname":"Hayfat Athabi",
    "gn:country_code":"YE",
    "gn:dem":1234,
    "gn:feature_class":"P",
    "gn:feature_code":"PPL",
    "gn:name":"\u1e28ayfat Athab\u012b",
    "gn:population":0,
    "gn:timezone":"Asia/Aden",
    "iso:country":"YE",
    "name:ara_x_preferred":[
        "\u062d\u064a\u0641\u0629 \u0623\u062b\u0628\u064a"
    ],
    "name:und_x_variant":[
        "\u1e28ayfat Athab\u012b"
    ],
    "wof:name":"Hayfat Athabi",
    "wof:placetype":"locality"
},
  "geometry": {"coordinates":[43.35416,16.67446],"type":"Point"}
}