{
  "type": "Feature",
  "properties": {
    "gn:admin1_code":"1.0",
    "gn:admin2_code":"1201.0",
    "gn:asciiname":"Al Khabr",
    "gn:country_code":"YE",
    "gn:dem":848,
    "gn:feature_class":"P",
    "gn:feature_code":"PPL",
    "gn:name":"Al Khabr",
    "gn:population":0,
    "gn:timezone":"Asia/Aden",
    "iso:country":"YE",
    "name:ara_x_preferred":[
        "\u0627\u0644\u062e\u0628\u0631"
    ],
    "name:fas_x_preferred":[
        "\u0627\u0644\u062e\u0627\u0628\u0631"
    ],
    "name:nno_x_preferred":[
        "Al Khabr"
    ],
    "name:sco_x_preferred":[
        "Al Khabr"
    ],
    "wof:name":"Al Khabr",
    "wof:placetype":"locality"
},
  "geometry": {"coordinates":[47.06031,14.13867],"type":"Point"}
}