{
  "type": "Feature",
  "properties": {
    "gn:admin1_code":"23.0",
    "gn:admin2_code":"1106.0",
    "gn:asciiname":"Dar Sa`id",
    "gn:country_code":"YE",
    "gn:dem":2190,
    "gn:feature_class":"P",
    "gn:feature_code":"PPL",
    "gn:name":"D\u0101r Sa\u2018\u012bd",
    "gn:population":0,
    "gn:timezone":"Asia/Aden",
    "iso:country":"YE",
    "name:ara_x_preferred":[
        "\u062f\u0627\u0631 \u0633\u0639\u064a\u062f"
    ],
    "name:und_x_variant":[
        "D\u0101r Sa\u2018\u012bd"
    ],
    "wof:name":"Dar Sa`id",
    "wof:placetype":"locality"
},
  "geometry": {"coordinates":[44.43998,14.11125],"type":"Point"}
}