{
  "type": "Feature",
  "properties": {
    "gn:country":"YE",
    "gn:fcode":"PPL",
    "gn:population":3,
    "iso:country":"YE",
    "name:ara_x_preferred":[
        "\u0642\u0628\u0627\u0642\u0628"
    ],
    "name:eng_x_preferred":[
        "Qibaqab"
    ],
    "name:eng_x_variant":[
        "Al Jufr\u0101\u2019"
    ],
    "qs:name":"Qib\u0101qab",
    "qs:photos_9r":0,
    "qs:photos_sr":0,
    "qs:pop_sr":"1",
    "wof:name":"Qib\u0101qab",
    "wof:placetype":"locality",
    "wof:population":3
},
  "geometry": {"coordinates":[43.37815,16.3442],"type":"Point"}
}