{
  "type": "Feature",
  "properties": {
    "gn:admin1_code":"25.0",
    "gn:admin2_code":"1503.0",
    "gn:asciiname":"Ash Shurayf",
    "gn:country_code":"YE",
    "gn:dem":1653,
    "gn:feature_class":"P",
    "gn:feature_code":"PPL",
    "gn:name":"Ash Shurayf",
    "gn:population":0,
    "gn:timezone":"Asia/Aden",
    "iso:country":"YE",
    "wof:name":"Ash Shurayf",
    "wof:placetype":"locality"
},
  "geometry": {"coordinates":[43.84641,13.76929],"type":"Point"}
}