{
  "type": "Feature",
  "properties": {
    "gn:admin1_code":"10.0",
    "gn:admin2_code":"2702.0",
    "gn:asciiname":"Hajar Zuhayr",
    "gn:country_code":"YE",
    "gn:dem":2143,
    "gn:feature_class":"P",
    "gn:feature_code":"PPL",
    "gn:name":"\u1e28ajar Zuhayr",
    "gn:population":0,
    "gn:timezone":"Asia/Aden",
    "iso:country":"YE",
    "name:und_x_variant":[
        "\u1e28ajar Zuhayr"
    ],
    "wof:name":"Hajar Zuhayr",
    "wof:placetype":"locality"
},
  "geometry": {"coordinates":[43.70441,15.49012],"type":"Point"}
}