{
  "type": "Feature",
  "properties": {
    "gn:country":"YE",
    "gn:fcode":"PPL",
    "gn:pop":23,
    "iso:country":"YE",
    "name:ara_x_preferred":[
        "\u0627\u0644\u0642\u064a\u0641\u0629"
    ],
    "name:eng_x_preferred":[
        "Al Qayfah"
    ],
    "name:nno_x_preferred":[
        "Ar Riqqah"
    ],
    "qs:name":"Al Qayfah",
    "qs:photos_9r":0,
    "qs:photos_sr":0,
    "qs:pop_sr":"1",
    "wof:name":"Al Qayfah",
    "wof:placetype":"locality",
    "wof:population":23
},
  "geometry": {"coordinates":[44.37508,16.78095],"type":"Point"}
}