{
  "type": "Feature",
  "properties": {
    "gn:country":"YE",
    "gn:fcode":"PPL",
    "gn:pop":1,
    "iso:country":"YE",
    "name:ara_x_preferred":[
        "A\u015f \u015e\u0101bir"
    ],
    "name:ara_x_variant":[
        "\u0627\u0644\u0635\u0627\u0628\u0631"
    ],
    "qs:name":"A\u015f \u015e\u0101bir",
    "qs:photos_9r":0,
    "qs:photos_sr":0,
    "qs:pop_sr":"1",
    "wof:name":"A\u015f \u015e\u0101bir",
    "wof:placetype":"locality",
    "wof:population":1
},
  "geometry": {"coordinates":[43.30347,16.65145],"type":"Point"}
}