{
  "type": "Feature",
  "properties": {
    "gn:admin1_code":"18.0",
    "gn:admin2_code":"3006.0",
    "gn:asciiname":"Al Kabar",
    "gn:country_code":"YE",
    "gn:dem":1453,
    "gn:feature_class":"P",
    "gn:feature_code":"PPL",
    "gn:name":"Al Kabar",
    "gn:population":0,
    "gn:timezone":"Asia/Aden",
    "iso:country":"YE",
    "name:und_x_variant":[
        "Kab\u0101r",
        "Al Kabar"
    ],
    "wof:name":"Al Kabar",
    "wof:placetype":"locality"
},
  "geometry": {"coordinates":[44.73441,13.71512],"type":"Point"}
}