{
  "type": "Feature",
  "properties": {
    "gn:country":"YE",
    "gn:fcode":"PPLX",
    "gn:pop":2,
    "iso:country":"YE",
    "name:ara_x_preferred":[
        "\u0627\u0644\u062e\u0631\u0627\u0628 \u0627\u0644\u062e\u0627\u0631\u062c\u064a"
    ],
    "qs:name":"Al Khar\u0101b al Kharij\u012b",
    "qs:photos_9r":0,
    "qs:photos_sr":0,
    "qs:pop_sr":"1",
    "wof:name":"Al Khar\u0101b al Kharij\u012b",
    "wof:placetype":"neighbourhood",
    "wof:population":2
},
  "geometry": {"coordinates":[43.74317,16.21243],"type":"Point"}
}