{
  "type": "Feature",
  "properties": {
    "gn:admin1_code":"8.0",
    "gn:admin2_code":"1801.0",
    "gn:asciiname":"Al Jihadimah",
    "gn:country_code":"YE",
    "gn:dem":181,
    "gn:feature_class":"P",
    "gn:feature_code":"PPL",
    "gn:name":"Al Jih\u0101\u1e11imah",
    "gn:population":0,
    "gn:timezone":"Asia/Aden",
    "iso:country":"YE",
    "name:und_x_variant":[
        "Al Jih\u0101\u1e11imah"
    ],
    "wof:name":"Al Jihadimah",
    "wof:placetype":"locality"
},
  "geometry": {"coordinates":[43.21613,15.81066],"type":"Point"}
}