{
  "type": "Feature",
  "properties": {
    "gn:admin1_code":"14.0",
    "gn:admin2_code":"2604.0",
    "gn:asciiname":"Al 'Aridah",
    "gn:country_code":"YE",
    "gn:dem":1669,
    "gn:feature_class":"P",
    "gn:feature_code":"PPL",
    "gn:name":"Al \u2018\u0100ri\u1e11ah",
    "gn:population":0,
    "gn:timezone":"Asia/Aden",
    "iso:country":"YE",
    "name:ara_x_preferred":[
        "\u0627\u0644\u0639\u0627\u0631\u0636\u0629"
    ],
    "name:und_x_variant":[
        "Al \u2018\u0100ri\u1e11ah"
    ],
    "wof:name":"Al 'Aridah",
    "wof:placetype":"locality"
},
  "geometry": {"coordinates":[44.68763,15.49479],"type":"Point"}
}