{
  "type": "Feature",
  "properties": {
    "gn:admin1_code":"8.0",
    "gn:admin2_code":"1812.0",
    "gn:asciiname":"Al Mawtin",
    "gn:country_code":"YE",
    "gn:dem":1453,
    "gn:feature_class":"P",
    "gn:feature_code":"PPL",
    "gn:name":"Al Maw\u0163in",
    "gn:population":0,
    "gn:timezone":"Asia/Aden",
    "iso:country":"YE",
    "name:ara_x_preferred":[
        "\u0627\u0644\u0645\u0648\u0637\u0646"
    ],
    "name:und_x_variant":[
        "Al Maw\u0163in"
    ],
    "wof:name":"Al Mawtin",
    "wof:placetype":"locality"
},
  "geometry": {"coordinates":[43.44049,14.89514],"type":"Point"}
}