{
  "type": "Feature",
  "properties": {
    "gn:admin1_code":"8.0",
    "gn:admin2_code":"1814.0",
    "gn:asciiname":"Al Manqam al Asfal",
    "gn:country_code":"YE",
    "gn:dem":45,
    "gn:feature_class":"P",
    "gn:feature_code":"PPL",
    "gn:name":"Al Manqam al Asfal",
    "gn:population":0,
    "gn:timezone":"Asia/Aden",
    "iso:country":"YE",
    "name:und_x_variant":[
        "Al Manqam",
        "Al Manqam al Asfal"
    ],
    "wof:name":"Al Manqam al Asfal",
    "wof:placetype":"locality"
},
  "geometry": {"coordinates":[43.12745,14.60831],"type":"Point"}
}