{
  "type": "Feature",
  "properties": {
    "gn:country":"YE",
    "gn:fcode":"PPLF",
    "gn:pop":6,
    "iso:country":"YE",
    "name:ara_x_preferred":[
        "\u0630\u0648 \u0628\u062e\u062a\u0627\u0646"
    ],
    "name:eng_x_preferred":[
        "DhU Bakhtan"
    ],
    "name:eng_x_variant":[
        "An Nuwayrah"
    ],
    "qs:name":"Dh\u016b Bakht\u0101n",
    "qs:photos_9r":0,
    "qs:photos_sr":0,
    "qs:pop_sr":"1",
    "wof:name":"Dh\u016b Bakht\u0101n",
    "wof:placetype":"locality",
    "wof:population":6
},
  "geometry": {"coordinates":[44.01746,16.88965],"type":"Point"}
}