{
  "type": "Feature",
  "properties": {
    "gn:admin1_code":"11.0",
    "gn:admin2_code":"2003.0",
    "gn:asciiname":"Qarn `Arrah",
    "gn:country_code":"YE",
    "gn:dem":2177,
    "gn:feature_class":"P",
    "gn:feature_code":"PPL",
    "gn:name":"Qarn \u2018Arrah",
    "gn:population":0,
    "gn:timezone":"Asia/Aden",
    "iso:country":"YE",
    "name:und_x_variant":[
        "Qarn \u2018Arrah"
    ],
    "wof:name":"Qarn `Arrah",
    "wof:placetype":"locality"
},
  "geometry": {"coordinates":[43.95222,14.76806],"type":"Point"}
}