{
  "type": "Feature",
  "properties": {
    "gn:admin1_code":"18.0",
    "gn:admin2_code":"3009.0",
    "gn:asciiname":"Al Hayfah",
    "gn:country_code":"YE",
    "gn:dem":2022,
    "gn:feature_class":"P",
    "gn:feature_code":"PPL",
    "gn:name":"Al \u1e28ayfah",
    "gn:population":0,
    "gn:timezone":"Asia/Aden",
    "iso:country":"YE",
    "name:fas_x_preferred":[
        "\u0627\u0644\u062d\u06cc\u0641\u0647"
    ],
    "name:nno_x_preferred":[
        "Al Hayfah"
    ],
    "name:und_x_variant":[
        "Al \u1e28ayfah",
        "Al Haifa",
        "El Heifa"
    ],
    "wof:name":"Al Hayfah",
    "wof:placetype":"locality"
},
  "geometry": {"coordinates":[44.55,13.73333],"type":"Point"}
}