{
  "type": "Feature",
  "properties": {
    "gn:admin1_code":"24.0",
    "gn:admin2_code":"2510.0",
    "gn:asciiname":"`Anafat",
    "gn:country_code":"YE",
    "gn:dem":1407,
    "gn:feature_class":"P",
    "gn:feature_code":"PPL",
    "gn:name":"\u2018Anaf\u0101t",
    "gn:population":0,
    "gn:timezone":"Asia/Aden",
    "iso:country":"YE",
    "name:und_x_variant":[
        "\u2018Anaf\u0101t"
    ],
    "wof:name":"`Anafat",
    "wof:placetype":"locality"
},
  "geometry": {"coordinates":[44.4159,13.28598],"type":"Point"}
}