{
  "type": "Feature",
  "properties": {
    "gn:admin1_code":"19.0",
    "gn:admin2_code":"2903.0",
    "gn:asciiname":"Al Mayrah",
    "gn:country_code":"YE",
    "gn:dem":1315,
    "gn:feature_class":"P",
    "gn:feature_code":"PPL",
    "gn:name":"Al Mayrah",
    "gn:population":0,
    "gn:timezone":"Asia/Aden",
    "iso:country":"YE",
    "name:ara_x_preferred":[
        "\u0627\u0644\u0645\u064a\u0631\u0629"
    ],
    "wof:name":"Al Mayrah",
    "wof:placetype":"locality"
},
  "geometry": {"coordinates":[43.79116,16.35626],"type":"Point"}
}