{
  "type": "Feature",
  "properties": {
    "gn:admin1_code":"11.0",
    "gn:admin2_code":"2001.0",
    "gn:asciiname":"Adh Dhira`",
    "gn:country_code":"YE",
    "gn:dem":2510,
    "gn:feature_class":"P",
    "gn:feature_code":"PPL",
    "gn:name":"Adh Dhir\u0101\u2018",
    "gn:population":0,
    "gn:timezone":"Asia/Aden",
    "iso:country":"YE",
    "name:ara_x_preferred":[
        "Adh Dhir\u0101\u2018"
    ],
    "wof:name":"Adh Dhira`",
    "wof:placetype":"locality"
},
  "geometry": {"coordinates":[44.38092,14.90407],"type":"Point"}
}