{
  "type": "Feature",
  "properties": {
    "gn:admin1_code":"8.0",
    "gn:admin2_code":"1802.0",
    "gn:asciiname":"Dayr Bani Mumi",
    "gn:country_code":"YE",
    "gn:dem":25,
    "gn:feature_class":"P",
    "gn:feature_code":"PPL",
    "gn:name":"Dayr Ban\u012b M\u016bm\u012b",
    "gn:population":0,
    "gn:timezone":"Asia/Aden",
    "iso:country":"YE",
    "name:und_x_variant":[
        "Dayr Ban\u012b M\u016bm\u012b"
    ],
    "wof:name":"Dayr Bani Mumi",
    "wof:placetype":"locality"
},
  "geometry": {"coordinates":[42.83429,15.54843],"type":"Point"}
}