{
  "type": "Feature",
  "properties": {
    "gn:admin1_code":"5.0",
    "gn:admin2_code":"2103.0",
    "gn:asciiname":"Al Buwayridah",
    "gn:country_code":"YE",
    "gn:dem":1013,
    "gn:feature_class":"P",
    "gn:feature_code":"PPL",
    "gn:name":"Al Buwayridah",
    "gn:population":0,
    "gn:timezone":"Asia/Aden",
    "iso:country":"YE",
    "name:und_x_variant":[
        "Al-Buwairidah",
        "Al Buwayridah"
    ],
    "wof:name":"Al Buwayridah",
    "wof:placetype":"locality"
},
  "geometry": {"coordinates":[46.91835,14.90506],"type":"Point"}
}