{
  "type": "Feature",
  "properties": {
    "gn:admin1_code":"16.0",
    "gn:admin2_code":"2310.0",
    "gn:asciiname":"Bayt Madar",
    "gn:country_code":"YE",
    "gn:dem":1807,
    "gn:feature_class":"P",
    "gn:feature_code":"PPL",
    "gn:name":"Bayt Mad\u0101r",
    "gn:population":0,
    "gn:timezone":"Asia/Aden",
    "iso:country":"YE",
    "name:und_x_variant":[
        "Bayt Mad\u0101r"
    ],
    "wof:name":"Bayt Madar",
    "wof:placetype":"locality"
},
  "geometry": {"coordinates":[43.69884,15.19714],"type":"Point"}
}