{
  "type": "Feature",
  "properties": {
    "gn:admin1_code":"20.0",
    "gn:admin2_code":"1416.0",
    "gn:asciiname":"Al Farazi`ah",
    "gn:country_code":"YE",
    "gn:dem":2246,
    "gn:feature_class":"P",
    "gn:feature_code":"PPL",
    "gn:name":"Al Far\u0101zi\u2018ah",
    "gn:population":0,
    "gn:timezone":"Asia/Aden",
    "iso:country":"YE",
    "name:ara_x_preferred":[
        "\u0627\u0644\u0641\u0631\u0627\u0632\u0639\u0629"
    ],
    "name:und_x_variant":[
        "Al Far\u0101zi\u2018ah"
    ],
    "wof:name":"Al Farazi`ah",
    "wof:placetype":"locality"
},
  "geometry": {"coordinates":[44.74353,14.38823],"type":"Point"}
}