{
  "type": "Feature",
  "properties": {
    "gn:admin1_code":"10.0",
    "gn:admin2_code":"2706.0",
    "gn:asciiname":"Al Lihf",
    "gn:country_code":"YE",
    "gn:dem":2052,
    "gn:feature_class":"P",
    "gn:feature_code":"PPL",
    "gn:name":"Al Li\u1e29f",
    "gn:population":0,
    "gn:timezone":"Asia/Aden",
    "iso:country":"YE",
    "name:ara_x_preferred":[
        "Al Li\u1e29f"
    ],
    "wof:name":"Al Lihf",
    "wof:placetype":"locality"
},
  "geometry": {"coordinates":[43.44062,15.38683],"type":"Point"}
}