{
  "type": "Feature",
  "properties": {
    "gn:country":"YE",
    "gn:fcode":"PPL",
    "gn:population":12,
    "iso:country":"YE",
    "name:ara_x_preferred":[
        "\u0627\u0644\u0645\u0637\u0628\u0642"
    ],
    "name:eng_x_preferred":[
        "Al Matbaq"
    ],
    "name:eng_x_variant":[
        "Al Q\u0101bilah"
    ],
    "qs:name":"Al Ma\u0163baq",
    "qs:photos_9r":0,
    "qs:photos_sr":0,
    "qs:pop_sr":"1",
    "wof:name":"Al Ma\u0163baq",
    "wof:placetype":"locality",
    "wof:population":12
},
  "geometry": {"coordinates":[43.25012,16.01872],"type":"Point"}
}