{
  "type": "Feature",
  "properties": {
    "gn:admin1_code":"22.0",
    "gn:admin2_code":"1702.0",
    "gn:asciiname":"Al Mahajjabiyah",
    "gn:country_code":"YE",
    "gn:dem":86,
    "gn:feature_class":"P",
    "gn:feature_code":"PPL",
    "gn:name":"Al Ma\u1e29ajjab\u012byah",
    "gn:population":0,
    "gn:timezone":"Asia/Aden",
    "iso:country":"YE",
    "name:und_x_variant":[
        "Al Ma\u1e29ajjab\u012byah"
    ],
    "wof:name":"Al Mahajjabiyah",
    "wof:placetype":"locality"
},
  "geometry": {"coordinates":[43.03754,16.38168],"type":"Point"}
}