{
  "type": "Feature",
  "properties": {
    "gn:admin1_code":"23.0",
    "gn:admin2_code":"1120.0",
    "gn:asciiname":"Dhi Saylah",
    "gn:country_code":"YE",
    "gn:dem":1681,
    "gn:feature_class":"P",
    "gn:feature_code":"PPL",
    "gn:name":"Dh\u012b \u015eaylah",
    "gn:population":0,
    "gn:timezone":"Asia/Aden",
    "iso:country":"YE",
    "name:und_x_variant":[
        "Dh\u012b \u015eaylah"
    ],
    "wof:name":"Dhi Saylah",
    "wof:placetype":"locality"
},
  "geometry": {"coordinates":[44.27924,13.8796],"type":"Point"}
}