{
  "type": "Feature",
  "properties": {
    "gn:country":"YE",
    "gn:fcode":"PPL",
    "gn:population":3,
    "iso:country":"YE",
    "name:ara_x_preferred":[
        "\u062d\u062c\u0631"
    ],
    "name:eng_x_preferred":[
        "Hajr"
    ],
    "name:zho_x_preferred":[
        "\u0100l \u2018\u0100mir"
    ],
    "qs:name":"\u1e28ajr",
    "qs:photos_9r":0,
    "qs:photos_sr":0,
    "qs:pop_sr":"1",
    "wd:wordcount":46,
    "wof:name":"\u1e28ajr",
    "wof:placetype":"locality",
    "wof:population":3
},
  "geometry": {"coordinates":[45.41754,14.65591],"type":"Point"}
}