{
  "type": "Feature",
  "properties": {
    "gn:admin1_code":"15.0",
    "gn:admin2_code":"2206.0",
    "gn:asciiname":"Al Manwar",
    "gn:country_code":"YE",
    "gn:dem":329,
    "gn:feature_class":"P",
    "gn:feature_code":"PPL",
    "gn:name":"Al Manwar",
    "gn:population":0,
    "gn:timezone":"Asia/Aden",
    "iso:country":"YE",
    "name:ara_x_preferred":[
        "\u0627\u0644\u0645\u0646\u0648\u0631"
    ],
    "wof:name":"Al Manwar",
    "wof:placetype":"locality"
},
  "geometry": {"coordinates":[43.1597,16.88169],"type":"Point"}
}