{
  "type": "Feature",
  "properties": {
    "gn:admin1_code":"23.0",
    "gn:admin2_code":"1115.0",
    "gn:asciiname":"Dhi al Bulays",
    "gn:country_code":"YE",
    "gn:dem":1977,
    "gn:feature_class":"P",
    "gn:feature_code":"PPL",
    "gn:name":"Dh\u012b al Bulays",
    "gn:population":0,
    "gn:timezone":"Asia/Aden",
    "iso:country":"YE",
    "name:und_x_variant":[
        "Dh\u012b al Bulays"
    ],
    "wof:name":"Dhi al Bulays",
    "wof:placetype":"locality"
},
  "geometry": {"coordinates":[44.27282,13.81266],"type":"Point"}
}