{
  "type": "Feature",
  "properties": {
    "gn:admin1_code":"16.0",
    "gn:admin2_code":"2312.0",
    "gn:asciiname":"Hurayshifah",
    "gn:country_code":"YE",
    "gn:dem":1742,
    "gn:feature_class":"P",
    "gn:feature_code":"PPL",
    "gn:name":"\u1e28urayshifah",
    "gn:population":0,
    "gn:timezone":"Asia/Aden",
    "iso:country":"YE",
    "name:ara_x_preferred":[
        "\u062d\u0631\u064a\u0634\u0641\u0629"
    ],
    "name:und_x_variant":[
        "\u1e28urayshifah"
    ],
    "wof:name":"Hurayshifah",
    "wof:placetype":"locality"
},
  "geometry": {"coordinates":[44.79663,15.31746],"type":"Point"}
}