{
  "type": "Feature",
  "properties": {
    "gn:admin1_code":"23.0",
    "gn:admin2_code":"1104.0",
    "gn:asciiname":"Sani",
    "gn:country_code":"YE",
    "gn:dem":2592,
    "gn:feature_class":"P",
    "gn:feature_code":"PPL",
    "gn:name":"San\u012b",
    "gn:population":0,
    "gn:timezone":"Asia/Aden",
    "iso:country":"YE",
    "name:ara_x_preferred":[
        "\u0633\u0646\u064a"
    ],
    "name:ceb_x_preferred":[
        "Sani"
    ],
    "name:deu_x_preferred":[
        "Sani"
    ],
    "name:fra_x_preferred":[
        "Sani"
    ],
    "name:ind_x_preferred":[
        "Sani"
    ],
    "name:ita_x_preferred":[
        "Sani"
    ],
    "name:swe_x_preferred":[
        "Sani"
    ],
    "name:und_x_variant":[
        "San\u012b"
    ],
    "wof:name":"Sani",
    "wof:placetype":"locality"
},
  "geometry": {"coordinates":[44.48387,14.01381],"type":"Point"}
}