{
  "type": "Feature",
  "properties": {
    "gn:admin1_code":"10.0",
    "gn:admin2_code":"2703.0",
    "gn:asciiname":"Ad Dubrah",
    "gn:country_code":"YE",
    "gn:dem":2368,
    "gn:feature_class":"P",
    "gn:feature_code":"PPL",
    "gn:name":"A\u1e11 \u1e10ubrah",
    "gn:population":0,
    "gn:timezone":"Asia/Aden",
    "iso:country":"YE",
    "name:und_x_variant":[
        "A\u1e11 \u1e10ubrah"
    ],
    "wof:name":"Ad Dubrah",
    "wof:placetype":"locality"
},
  "geometry": {"coordinates":[43.62485,15.49673],"type":"Point"}
}