{
  "type": "Feature",
  "properties": {
    "gn:admin1_code":"22.0",
    "gn:admin2_code":"1702.0",
    "gn:asciiname":"Al Hammah",
    "gn:country_code":"YE",
    "gn:dem":153,
    "gn:feature_class":"P",
    "gn:feature_code":"PPL",
    "gn:name":"Al \u1e28ammah",
    "gn:population":0,
    "gn:timezone":"Asia/Aden",
    "iso:country":"YE",
    "name:ara_x_preferred":[
        "\u0627\u0644\u062d\u0645\u0629"
    ],
    "name:und_x_variant":[
        "Al \u1e28ammah"
    ],
    "wof:name":"Al Hammah",
    "wof:placetype":"locality"
},
  "geometry": {"coordinates":[43.14508,16.56631],"type":"Point"}
}