{
  "type": "Feature",
  "properties": {
    "gn:country":"YE",
    "gn:fcode":"PPL",
    "gn:pop":5,
    "iso:country":"YE",
    "name:ara_x_preferred":[
        "\u0627\u0644\u0645\u062f\u0627\u0631\u0629"
    ],
    "qs:name":"Al Mad\u0101rah",
    "qs:photos_9r":0,
    "qs:photos_sr":0,
    "qs:pop_sr":"1",
    "wof:name":"Al Mad\u0101rah",
    "wof:placetype":"locality",
    "wof:population":5
},
  "geometry": {"coordinates":[43.70984,16.07524],"type":"Point"}
}