{
  "type": "Feature",
  "properties": {
    "gn:admin1_code":"11.0",
    "gn:admin2_code":"2006.0",
    "gn:asciiname":"Suq al Khamis",
    "gn:country_code":"YE",
    "gn:dem":1252,
    "gn:feature_class":"P",
    "gn:feature_code":"PPL",
    "gn:name":"S\u016bq al Kham\u012bs",
    "gn:population":0,
    "gn:timezone":"Asia/Aden",
    "iso:country":"YE",
    "name:und_x_variant":[
        "S\u016bq al Kham\u012bs"
    ],
    "wof:name":"Suq al Khamis",
    "wof:placetype":"locality"
},
  "geometry": {"coordinates":[43.81667,14.35],"type":"Point"}
}