{
  "type": "Feature",
  "properties": {
    "gn:admin1_code":"25.0",
    "gn:admin2_code":"1504.0",
    "gn:asciiname":"Ghawl",
    "gn:country_code":"YE",
    "gn:dem":1273,
    "gn:feature_class":"P",
    "gn:feature_code":"PPL",
    "gn:name":"Ghawl",
    "gn:population":0,
    "gn:timezone":"Asia/Aden",
    "iso:country":"YE",
    "name:und_x_variant":[
        "Al Ghawl Ban\u012b Salm\u0101n"
    ],
    "wof:name":"Ghawl",
    "wof:placetype":"locality"
},
  "geometry": {"coordinates":[43.81233,13.73474],"type":"Point"}
}