{
  "type": "Feature",
  "properties": {
    "gn:admin1_code":"5.0",
    "gn:admin2_code":"2109.0",
    "gn:asciiname":"Bayt Sultan",
    "gn:country_code":"YE",
    "gn:dem":1161,
    "gn:feature_class":"P",
    "gn:feature_code":"PPL",
    "gn:name":"Bayt Sul\u0163\u0101n",
    "gn:population":0,
    "gn:timezone":"Asia/Aden",
    "iso:country":"YE",
    "name:und_x_variant":[
        "Beit Sultan",
        "Bayn Sult\u0101n",
        "Bayt Sul\u0163\u0101n"
    ],
    "wof:name":"Bayt Sultan",
    "wof:placetype":"locality"
},
  "geometry": {"coordinates":[46.16508,14.47316],"type":"Point"}
}