{
  "type": "Feature",
  "properties": {
    "gn:admin1_code":"23.0",
    "gn:admin2_code":"1101.0",
    "gn:asciiname":"Ar Rukham",
    "gn:country_code":"YE",
    "gn:dem":1491,
    "gn:feature_class":"P",
    "gn:feature_code":"PPL",
    "gn:name":"Ar Rukh\u0101m",
    "gn:population":0,
    "gn:timezone":"Asia/Aden",
    "iso:country":"YE",
    "name:ara_x_preferred":[
        "\u0627\u0644\u0631\u062e\u0627\u0645"
    ],
    "name:und_x_variant":[
        "Ar Rukh\u0101m"
    ],
    "wof:name":"Ar Rukham",
    "wof:placetype":"locality"
},
  "geometry": {"coordinates":[44.13344,14.36406],"type":"Point"}
}