{
  "type": "Feature",
  "properties": {
    "gn:admin1_code":"20.0",
    "gn:admin2_code":"1404.0",
    "gn:asciiname":"Al Yasirah",
    "gn:country_code":"YE",
    "gn:dem":1965,
    "gn:feature_class":"P",
    "gn:feature_code":"PPL",
    "gn:name":"Al Y\u0101sirah",
    "gn:population":0,
    "gn:timezone":"Asia/Aden",
    "iso:country":"YE",
    "name:und_x_variant":[
        "Al Y\u0101sirah"
    ],
    "wof:name":"Al Yasirah",
    "wof:placetype":"locality"
},
  "geometry": {"coordinates":[45.8262,14.20638],"type":"Point"}
}