{
  "type": "Feature",
  "properties": {
    "gn:admin1_code":"22.0",
    "gn:admin2_code":"1701.0",
    "gn:asciiname":"Al Julah",
    "gn:country_code":"YE",
    "gn:dem":231,
    "gn:feature_class":"P",
    "gn:feature_code":"PPL",
    "gn:name":"Al J\u016blah",
    "gn:population":0,
    "gn:timezone":"Asia/Aden",
    "iso:country":"YE",
    "name:und_x_variant":[
        "Al J\u016blah"
    ],
    "wof:name":"Al Julah",
    "wof:placetype":"locality"
},
  "geometry": {"coordinates":[43.23536,16.51537],"type":"Point"}
}