{
  "type": "Feature",
  "properties": {
    "gn:admin1_code":"20.0",
    "gn:admin2_code":"1404.0",
    "gn:asciiname":"Ar Rumiyah",
    "gn:country_code":"YE",
    "gn:dem":2013,
    "gn:feature_class":"P",
    "gn:feature_code":"PPL",
    "gn:name":"Ar R\u016bmiyah",
    "gn:population":0,
    "gn:timezone":"Asia/Aden",
    "iso:country":"YE",
    "name:ara_x_preferred":[
        "\u0627\u0644\u0631\u0648\u0645\u064a\u0629"
    ],
    "name:und_x_variant":[
        "Ar R\u016bmiyah",
        "Ar R\u016bm\u012byah"
    ],
    "wof:name":"Ar Rumiyah",
    "wof:placetype":"locality"
},
  "geometry": {"coordinates":[45.70554,14.15976],"type":"Point"}
}