{
  "type": "Feature",
  "properties": {
    "gn:admin1_code":"8.0",
    "gn:admin2_code":"1802.0",
    "gn:asciiname":"Buyut Ahmad Hunaysh",
    "gn:country_code":"YE",
    "gn:dem":25,
    "gn:feature_class":"P",
    "gn:feature_code":"PPL",
    "gn:name":"Buy\u016bt A\u1e29mad \u1e28unaysh",
    "gn:population":0,
    "gn:timezone":"Asia/Aden",
    "iso:country":"YE",
    "name:ara_x_preferred":[
        "\u0628\u064a\u0648\u062a \u0623\u062d\u0645\u062f \u062d\u0646\u064a\u0634"
    ],
    "name:und_x_variant":[
        "Buy\u016bt A\u1e29mad \u1e28unaysh"
    ],
    "wof:name":"Buyut Ahmad Hunaysh",
    "wof:placetype":"locality"
},
  "geometry": {"coordinates":[42.85637,15.76452],"type":"Point"}
}