{
  "type": "Feature",
  "properties": {
    "gn:admin1_code":"1.0",
    "gn:admin2_code":"1204.0",
    "gn:asciiname":"Am Sidrah",
    "gn:country_code":"YE",
    "gn:dem":952,
    "gn:feature_class":"P",
    "gn:feature_code":"PPL",
    "gn:name":"Am Sidrah",
    "gn:population":0,
    "gn:timezone":"Asia/Aden",
    "iso:country":"YE",
    "name:und_x_variant":[
        "As Sidrah"
    ],
    "wof:name":"Am Sidrah",
    "wof:placetype":"locality"
},
  "geometry": {"coordinates":[45.76011,13.76617],"type":"Point"}
}