{
  "type": "Feature",
  "properties": {
    "gn:admin1_code":"25.0",
    "gn:admin2_code":"1515.0",
    "gn:asciiname":"As Su`ayr",
    "gn:country_code":"YE",
    "gn:dem":1382,
    "gn:feature_class":"P",
    "gn:feature_code":"PPL",
    "gn:name":"As Su\u2018ayr",
    "gn:population":0,
    "gn:timezone":"Asia/Aden",
    "iso:country":"YE",
    "name:ara_x_preferred":[
        "\u0627\u0644\u0633\u0639\u064a\u0631"
    ],
    "name:und_x_variant":[
        "As Su\u2018ayr"
    ],
    "wof:name":"As Su`ayr",
    "wof:placetype":"locality"
},
  "geometry": {"coordinates":[43.90411,13.1753],"type":"Point"}
}