{
  "type": "Feature",
  "properties": {
    "gn:admin1_code":"16.0",
    "gn:admin2_code":"2310.0",
    "gn:asciiname":"`Arjaz",
    "gn:country_code":"YE",
    "gn:dem":2394,
    "gn:feature_class":"P",
    "gn:feature_code":"PPL",
    "gn:name":"\u2018Arjaz",
    "gn:population":0,
    "gn:timezone":"Asia/Aden",
    "iso:country":"YE",
    "name:nno_x_preferred":[
        "`Arjaz"
    ],
    "name:und_x_variant":[
        "\u2018Arjaz"
    ],
    "name:urd_x_preferred":[
        "\u0627\u0631\u062c\u0627\u0632"
    ],
    "wof:name":"`Arjaz",
    "wof:placetype":"locality"
},
  "geometry": {"coordinates":[43.72913,15.03529],"type":"Point"}
}