{
  "type": "Feature",
  "properties": {
    "gn:admin1_code":"22.0",
    "gn:admin2_code":"1714.0",
    "gn:asciiname":"Bayt Yahya Mansur",
    "gn:country_code":"YE",
    "gn:dem":568,
    "gn:feature_class":"P",
    "gn:feature_code":"PPL",
    "gn:name":"Bayt Ya\u1e29y\u00e1 Man\u015f\u016br",
    "gn:population":0,
    "gn:timezone":"Asia/Aden",
    "iso:country":"YE",
    "name:und_x_variant":[
        "Bayt Ya\u1e29y\u00e1 Man\u015f\u016br",
        "Al Jaw\u0101nah"
    ],
    "wof:name":"Bayt Yahya Mansur",
    "wof:placetype":"locality"
},
  "geometry": {"coordinates":[43.40187,15.98338],"type":"Point"}
}