{
  "type": "Feature",
  "properties": {
    "gn:admin1_code":"25.0",
    "gn:admin2_code":"1505.0",
    "gn:asciiname":"Mirab",
    "gn:country_code":"YE",
    "gn:dem":1353,
    "gn:feature_class":"P",
    "gn:feature_code":"PPL",
    "gn:name":"M\u012br\u0101b",
    "gn:population":0,
    "gn:timezone":"Asia/Aden",
    "iso:country":"YE",
    "name:ara_x_preferred":[
        "M\u012br\u0101b"
    ],
    "name:und_x_variant":[
        "Miyrab"
    ],
    "wof:name":"Mirab",
    "wof:placetype":"locality"
},
  "geometry": {"coordinates":[43.72378,13.73732],"type":"Point"}
}