{
  "type": "Feature",
  "properties": {
    "gn:admin1_code":"8.0",
    "gn:admin2_code":"1810.0",
    "gn:asciiname":"Duhrah",
    "gn:country_code":"YE",
    "gn:dem":226,
    "gn:feature_class":"P",
    "gn:feature_code":"PPL",
    "gn:name":"Du\u1e29rah",
    "gn:population":0,
    "gn:timezone":"Asia/Aden",
    "iso:country":"YE",
    "name:und_x_variant":[
        "Du\u1e29rah"
    ],
    "wof:name":"Duhrah",
    "wof:placetype":"locality"
},
  "geometry": {"coordinates":[43.28849,15.16035],"type":"Point"}
}