{
  "type": "Feature",
  "properties": {
    "gn:country":"YE",
    "gn:fcode":"PPLL",
    "gn:population":96,
    "iso:country":"YE",
    "name:ara_x_preferred":[
        "\u0627\u0644\u0642\u0631\u0634\u0629"
    ],
    "name:ara_x_variant":[
        "\u0639\u0632\u0644\u0629 \u0627\u0644\u0642\u0631\u0634\u0629"
    ],
    "name:arz_x_preferred":[
        "\u0639\u0632\u0644\u0647 \u0627\u0644\u0642\u0631\u0634\u0647"
    ],
    "name:eng_x_preferred":[
        "Al Qurshah"
    ],
    "qs:name":"Al Qurshah",
    "qs:photos_9r":0,
    "qs:photos_sr":0,
    "qs:pop_sr":"1",
    "wof:name":"Al Qurshah",
    "wof:placetype":"locality",
    "wof:population":96
},
  "geometry": {"coordinates":[44.43351,16.7464],"type":"Point"}
}