{
  "type": "Feature",
  "properties": {
    "gn:country":"YE",
    "gn:fcode":"PPLF",
    "gn:pop":2,
    "iso:country":"YE",
    "name:ara_x_preferred":[
        "\u063a\u0648\u0644 \u0645\u0634\u064a\u0646\u0629"
    ],
    "name:eng_x_preferred":[
        "Ghawl Mushaynah"
    ],
    "qs:name":"Ghawl Mushaynah",
    "qs:photos_9r":0,
    "qs:photos_sr":0,
    "qs:pop_sr":"1",
    "wof:name":"Ghawl Mushaynah",
    "wof:placetype":"locality",
    "wof:population":2
},
  "geometry": {"coordinates":[43.43058,16.43453],"type":"Point"}
}