{
  "type": "Feature",
  "properties": {
    "gn:admin1_code":"5.0",
    "gn:admin2_code":"2117.0",
    "gn:asciiname":"Sabakhah",
    "gn:country_code":"YE",
    "gn:dem":494,
    "gn:feature_class":"P",
    "gn:feature_code":"PPL",
    "gn:name":"Sabakhah",
    "gn:population":0,
    "gn:timezone":"Asia/Aden",
    "iso:country":"YE",
    "wof:name":"Sabakhah",
    "wof:placetype":"locality"
},
  "geometry": {"coordinates":[47.29611,14.08958],"type":"Point"}
}