{
  "type": "Feature",
  "properties": {
    "gn:admin1_code":"11.0",
    "gn:admin2_code":"2005.0",
    "gn:asciiname":"Al Mafrah",
    "gn:country_code":"YE",
    "gn:dem":2090,
    "gn:feature_class":"P",
    "gn:feature_code":"PPL",
    "gn:name":"Al Mafra\u1e29",
    "gn:population":0,
    "gn:timezone":"Asia/Aden",
    "iso:country":"YE",
    "name:und_x_variant":[
        "Al Mafra\u1e29"
    ],
    "wof:name":"Al Mafrah",
    "wof:placetype":"locality"
},
  "geometry": {"coordinates":[43.96034,14.49646],"type":"Point"}
}