{
  "type": "Feature",
  "properties": {
    "gn:admin1_code":"19.0",
    "gn:admin2_code":"2912.0",
    "gn:asciiname":"Al Jisami",
    "gn:country_code":"YE",
    "gn:dem":2228,
    "gn:feature_class":"P",
    "gn:feature_code":"PPL",
    "gn:name":"Al Jis\u0101m\u012b",
    "gn:population":0,
    "gn:timezone":"Asia/Aden",
    "iso:country":"YE",
    "name:ara_x_preferred":[
        "Al Jis\u0101m\u012b"
    ],
    "name:ara_x_variant":[
        "\u0627\u0644\u062c\u0633\u0627\u0645\u064a"
    ],
    "wof:name":"Al Jisami",
    "wof:placetype":"locality"
},
  "geometry": {"coordinates":[43.99675,15.79688],"type":"Point"}
}