{
  "type": "Feature",
  "properties": {
    "gn:admin1_code":"18.0",
    "gn:admin2_code":"3009.0",
    "gn:asciiname":"Al Madad",
    "gn:country_code":"YE",
    "gn:dem":2163,
    "gn:feature_class":"P",
    "gn:feature_code":"PPL",
    "gn:name":"Al Madad",
    "gn:population":0,
    "gn:timezone":"Asia/Aden",
    "iso:country":"YE",
    "wof:name":"Al Madad",
    "wof:placetype":"locality"
},
  "geometry": {"coordinates":[44.49132,13.73914],"type":"Point"}
}