{
  "type": "Feature",
  "properties": {
    "gn:admin1_code":"23.0",
    "gn:admin2_code":"1101.0",
    "gn:asciiname":"Al Hisn",
    "gn:country_code":"YE",
    "gn:dem":1661,
    "gn:feature_class":"P",
    "gn:feature_code":"PPL",
    "gn:name":"Al \u1e28i\u015fn",
    "gn:population":0,
    "gn:timezone":"Asia/Aden",
    "iso:country":"YE",
    "name:ara_x_preferred":[
        "\u0627\u0644\u062d\u0635\u0646"
    ],
    "name:und_x_variant":[
        "Al \u1e28i\u015fn"
    ],
    "wof:name":"Al Hisn",
    "wof:placetype":"locality"
},
  "geometry": {"coordinates":[44.14873,14.26342],"type":"Point"}
}