{
  "type": "Feature",
  "properties": {
    "gn:admin1_code":"16.0",
    "gn:admin2_code":"2302.0",
    "gn:asciiname":"Hawim",
    "gn:country_code":"YE",
    "gn:dem":2672,
    "gn:feature_class":"P",
    "gn:feature_code":"PPL",
    "gn:name":"H\u0101wim",
    "gn:population":0,
    "gn:timezone":"Asia/Aden",
    "iso:country":"YE",
    "name:ara_x_preferred":[
        "H\u0101wim"
    ],
    "wof:name":"Hawim",
    "wof:placetype":"locality"
},
  "geometry": {"coordinates":[44.19527,15.83909],"type":"Point"}
}