{
  "type": "Feature",
  "properties": {
    "gn:admin1_code":"15.0",
    "gn:admin2_code":"2211.0",
    "gn:asciiname":"Al Miti`",
    "gn:country_code":"YE",
    "gn:dem":1904,
    "gn:feature_class":"P",
    "gn:feature_code":"PPL",
    "gn:name":"\u0100l Mi\u0163\u012b\u2018",
    "gn:population":0,
    "gn:timezone":"Asia/Aden",
    "iso:country":"YE",
    "name:ara_x_preferred":[
        "\u0100l Mi\u0163\u012b\u2018"
    ],
    "name:ara_x_variant":[
        "\u0627\u0644 \u0645\u0637\u064a\u0639"
    ],
    "wof:name":"Al Miti`",
    "wof:placetype":"locality"
},
  "geometry": {"coordinates":[43.70305,17.0209],"type":"Point"}
}