{
  "type": "Feature",
  "properties": {
    "gn:admin1_code":"8.0",
    "gn:admin2_code":"1817.0",
    "gn:asciiname":"Al Jarubah ad Dar",
    "gn:country_code":"YE",
    "gn:dem":236,
    "gn:feature_class":"P",
    "gn:feature_code":"PPL",
    "gn:name":"Al Jar\u016bbah ad D\u0101r",
    "gn:population":0,
    "gn:timezone":"Asia/Aden",
    "iso:country":"YE",
    "name:und_x_variant":[
        "Al Jar\u016bbah ad D\u0101r"
    ],
    "wof:name":"Al Jarubah ad Dar",
    "wof:placetype":"locality"
},
  "geometry": {"coordinates":[43.4256,14.38759],"type":"Point"}
}