{
  "type": "Feature",
  "properties": {
    "gn:admin1_code":"15.0",
    "gn:admin2_code":"2204.0",
    "gn:asciiname":"Al Jarashah",
    "gn:country_code":"YE",
    "gn:dem":1660,
    "gn:feature_class":"P",
    "gn:feature_code":"PPL",
    "gn:name":"Al Jarashah",
    "gn:population":0,
    "gn:timezone":"Asia/Aden",
    "iso:country":"YE",
    "name:ara_x_preferred":[
        "\u0627\u0644\u062c\u0631\u0634\u0629"
    ],
    "wof:name":"Al Jarashah",
    "wof:placetype":"locality"
},
  "geometry": {"coordinates":[43.3419,16.9847],"type":"Point"}
}