{
  "type": "Feature",
  "properties": {
    "gn:admin1_code":"22.0",
    "gn:admin2_code":"1709.0",
    "gn:asciiname":"Al Ma'rif",
    "gn:country_code":"YE",
    "gn:dem":1588,
    "gn:feature_class":"P",
    "gn:feature_code":"PPL",
    "gn:name":"Al Ma\u2018rif",
    "gn:population":0,
    "gn:timezone":"Asia/Aden",
    "iso:country":"YE",
    "name:ara_x_preferred":[
        "\u0627\u0644\u0645\u0639\u0631\u0641"
    ],
    "name:und_x_variant":[
        "Al Ma\u2018rif"
    ],
    "wof:name":"Al Ma'rif",
    "wof:placetype":"locality"
},
  "geometry": {"coordinates":[43.4836,16.04364],"type":"Point"}
}