{
  "type": "Feature",
  "properties": {
    "gn:admin1_code":"14.0",
    "gn:admin2_code":"2601.0",
    "gn:asciiname":"Umm as Salam",
    "gn:country_code":"YE",
    "gn:dem":1219,
    "gn:feature_class":"P",
    "gn:feature_code":"PPLL",
    "gn:name":"Umm as Salam",
    "gn:population":0,
    "gn:timezone":"Asia/Aden",
    "iso:country":"YE",
    "name:ara_x_preferred":[
        "\u0623\u0645 \u0627\u0644\u0633\u0644\u0645"
    ],
    "wof:name":"Umm as Salam",
    "wof:placetype":"locality"
},
  "geometry": {"coordinates":[44.76032,15.83784],"type":"Point"}
}