{
  "type": "Feature",
  "properties": {
    "gn:admin1_code":"4.0",
    "gn:admin2_code":"1921.0",
    "gn:asciiname":"Al Ma`barah",
    "gn:country_code":"YE",
    "gn:dem":1350,
    "gn:feature_class":"P",
    "gn:feature_code":"PPL",
    "gn:name":"Al Ma\u2018barah",
    "gn:population":0,
    "gn:timezone":"Asia/Aden",
    "iso:country":"YE",
    "name:und_x_variant":[
        "Al Ma\u2018barah"
    ],
    "wof:name":"Al Ma`barah",
    "wof:placetype":"locality"
},
  "geometry": {"coordinates":[47.81667,15.28333],"type":"Point"}
}