{
  "type": "Feature",
  "properties": {
    "gn:country":"YE",
    "gn:fcode":"PPL",
    "gn:pop":1,
    "iso:country":"YE",
    "name:ara_x_preferred":[
        "Lujj Mir\u2018\u0101b"
    ],
    "name:ara_x_variant":[
        "\u0644\u062c \u0645\u0631\u0639\u0627\u0646"
    ],
    "name:eng_x_preferred":[
        "Lujj Mir'ab"
    ],
    "qs:name":"Lujj Mir\u2018\u0101b",
    "qs:photos_9r":0,
    "qs:photos_sr":0,
    "qs:pop_sr":"1",
    "wof:name":"Lujj Mir\u2018\u0101b",
    "wof:placetype":"locality",
    "wof:population":1
},
  "geometry": {"coordinates":[43.38145,16.22558],"type":"Point"}
}