{
  "type": "Feature",
  "properties": {
    "gn:admin1_code":"23.0",
    "gn:admin2_code":"1117.0",
    "gn:asciiname":"Al Widir",
    "gn:country_code":"YE",
    "gn:dem":2145,
    "gn:feature_class":"P",
    "gn:feature_code":"PPL",
    "gn:name":"Al Wid\u012br",
    "gn:population":0,
    "gn:timezone":"Asia/Aden",
    "iso:country":"YE",
    "name:ara_x_preferred":[
        "Al Wid\u012br"
    ],
    "name:ara_x_variant":[
        "\u0627\u0644\u0648\u062f\u064a\u0631"
    ],
    "name:und_x_variant":[
        "Al Wudayr"
    ],
    "wof:name":"Al Widir",
    "wof:placetype":"locality"
},
  "geometry": {"coordinates":[43.94115,13.84954],"type":"Point"}
}