{
  "type": "Feature",
  "properties": {
    "gn:admin1_code":"25.0",
    "gn:admin2_code":"1509.0",
    "gn:asciiname":"Al Wad",
    "gn:country_code":"YE",
    "gn:dem":1803,
    "gn:feature_class":"P",
    "gn:feature_code":"PPL",
    "gn:name":"Al W\u0101d",
    "gn:population":0,
    "gn:timezone":"Asia/Aden",
    "iso:country":"YE",
    "name:ara_x_preferred":[
        "Al W\u0101d"
    ],
    "wof:name":"Al Wad",
    "wof:placetype":"locality"
},
  "geometry": {"coordinates":[43.90472000000001,13.45167],"type":"Point"}
}