{
  "type": "Feature",
  "properties": {
    "gn:admin1_code":"24.0",
    "gn:admin2_code":"2512.0",
    "gn:asciiname":"Al Nimrah",
    "gn:country_code":"YE",
    "gn:dem":1602,
    "gn:feature_class":"P",
    "gn:feature_code":"PPL",
    "gn:name":"Al Nimrah",
    "gn:population":0,
    "gn:timezone":"Asia/Aden",
    "iso:country":"YE",
    "name:ara_x_preferred":[
        "\u0627\u0644\u0646\u0645\u0631\u0629"
    ],
    "wof:name":"Al Nimrah",
    "wof:placetype":"locality"
},
  "geometry": {"coordinates":[44.19531,13.18365],"type":"Point"}
}