{
  "type": "Feature",
  "properties": {
    "gn:admin1_code":"21.0",
    "gn:admin2_code":"1610.0",
    "gn:asciiname":"As Sawadah",
    "gn:country_code":"YE",
    "gn:dem":2134,
    "gn:feature_class":"P",
    "gn:feature_code":"PPL",
    "gn:name":"As Saw\u0101dah",
    "gn:population":0,
    "gn:timezone":"Asia/Aden",
    "iso:country":"YE",
    "name:ara_x_preferred":[
        "\u0627\u0644\u0633\u0648\u0627\u062f\u0629"
    ],
    "name:und_x_variant":[
        "As Saw\u0101dah"
    ],
    "wof:name":"As Sawadah",
    "wof:placetype":"locality"
},
  "geometry": {"coordinates":[44.30149,16.72904],"type":"Point"}
}