{
  "type": "Feature",
  "properties": {
    "gn:country":"YE",
    "gn:fcode":"PPL",
    "gn:pop":1,
    "iso:country":"YE",
    "name:ara_x_preferred":[
        "\u0627\u0644\u0643\u0631\u0627\u062b\u0629"
    ],
    "name:eng_x_preferred":[
        "Al Karathah"
    ],
    "qs:name":"Al Kar\u0101thah",
    "qs:photos_9r":0,
    "qs:photos_sr":0,
    "qs:pop_sr":"1",
    "wof:name":"Al Kar\u0101thah",
    "wof:placetype":"locality",
    "wof:population":1
},
  "geometry": {"coordinates":[43.81172,13.4824],"type":"Point"}
}