{
  "type": "Feature",
  "properties": {
    "gn:admin1_code":"8.0",
    "gn:admin2_code":"1818.0",
    "gn:asciiname":"Hasib Bani Matar",
    "gn:country_code":"YE",
    "gn:dem":522,
    "gn:feature_class":"P",
    "gn:feature_code":"PPL",
    "gn:name":"\u1e28a\u015f\u012bb Ban\u012b Ma\u0163ar",
    "gn:population":0,
    "gn:timezone":"Asia/Aden",
    "iso:country":"YE",
    "name:und_x_variant":[
        "\u1e28a\u015f\u012bb Ban\u012b Ma\u0163ar"
    ],
    "wof:name":"Hasib Bani Matar",
    "wof:placetype":"locality"
},
  "geometry": {"coordinates":[43.67081,14.03506],"type":"Point"}
}