{
  "type": "Feature",
  "properties": {
    "gn:admin1_code":"8.0",
    "gn:admin2_code":"1816.0",
    "gn:asciiname":"Al Lijam",
    "gn:country_code":"YE",
    "gn:dem":170,
    "gn:feature_class":"P",
    "gn:feature_code":"PPL",
    "gn:name":"Al Lij\u0101m",
    "gn:population":0,
    "gn:timezone":"Asia/Aden",
    "iso:country":"YE",
    "name:ara_x_preferred":[
        "Al Lij\u0101m"
    ],
    "wof:name":"Al Lijam",
    "wof:placetype":"locality"
},
  "geometry": {"coordinates":[43.42123,14.64496],"type":"Point"}
}