{
  "type": "Feature",
  "properties": {
    "gn:admin1_code":"24.0",
    "gn:admin2_code":"2512.0",
    "gn:asciiname":"Hawb al Hajari",
    "gn:country_code":"YE",
    "gn:dem":1442,
    "gn:feature_class":"P",
    "gn:feature_code":"PPL",
    "gn:name":"Hawb al \u1e28ajar\u012b",
    "gn:population":0,
    "gn:timezone":"Asia/Aden",
    "iso:country":"YE",
    "name:ara_x_preferred":[
        "\u0647\u0648\u0628 \u0627\u0644\u062d\u062c\u0631\u064a"
    ],
    "name:und_x_variant":[
        "Hawb al \u1e28ajar\u012b"
    ],
    "wof:name":"Hawb al Hajari",
    "wof:placetype":"locality"
},
  "geometry": {"coordinates":[44.17308,13.183],"type":"Point"}
}