{
  "type": "Feature",
  "properties": {
    "gn:admin1_code":"4.0",
    "gn:admin2_code":"1928.0",
    "gn:asciiname":"Dar Mahrus",
    "gn:country_code":"YE",
    "gn:dem":1159,
    "gn:feature_class":"P",
    "gn:feature_code":"PPL",
    "gn:name":"D\u0101r Ma\u1e29r\u016bs",
    "gn:population":0,
    "gn:timezone":"Asia/Aden",
    "iso:country":"YE",
    "name:und_x_variant":[
        "D\u0101r Ma\u1e29r\u016bs"
    ],
    "wof:name":"Dar Mahrus",
    "wof:placetype":"locality"
},
  "geometry": {"coordinates":[48.08333,15.48333],"type":"Point"}
}