{
  "type": "Feature",
  "properties": {
    "gn:admin1_code":"8.0",
    "gn:admin2_code":"1805.0",
    "gn:asciiname":"Mahall al Bahsi",
    "gn:country_code":"YE",
    "gn:dem":53,
    "gn:feature_class":"P",
    "gn:feature_code":"PPL",
    "gn:name":"Ma\u1e29all al Ba\u1e29\u015f\u012b",
    "gn:population":0,
    "gn:timezone":"Asia/Aden",
    "iso:country":"YE",
    "name:ara_x_preferred":[
        "\u0645\u062d\u0644 \u0627\u0644\u0628\u062d\u0635\u064a"
    ],
    "name:und_x_variant":[
        "Ma\u1e29all al Ba\u1e29\u015f\u012b"
    ],
    "wof:name":"Mahall al Bahsi",
    "wof:placetype":"locality"
},
  "geometry": {"coordinates":[42.99087,15.41769],"type":"Point"}
}