{
  "type": "Feature",
  "properties": {
    "gn:country":"YE",
    "gn:fcode":"PPL",
    "gn:pop":3,
    "iso:country":"YE",
    "name:ara_x_preferred":[
        "\u0627\u0644\u062c\u062f\u0644\u0629"
    ],
    "name:eng_x_preferred":[
        "Al Jadlah"
    ],
    "name:eng_x_variant":[
        "A\u015f \u015eirah"
    ],
    "qs:name":"Al Jadlah",
    "qs:photos_9r":0,
    "qs:photos_sr":0,
    "qs:pop_sr":"1",
    "wof:name":"Al Jadlah",
    "wof:placetype":"locality",
    "wof:population":3
},
  "geometry": {"coordinates":[43.36616,16.08091],"type":"Point"}
}