{
  "type": "Feature",
  "properties": {
    "gn:admin1_code":"10.0",
    "gn:admin2_code":"2704.0",
    "gn:asciiname":"Al Hijrah",
    "gn:country_code":"YE",
    "gn:dem":1014,
    "gn:feature_class":"P",
    "gn:feature_code":"PPL",
    "gn:name":"Al Hijrah",
    "gn:population":0,
    "gn:timezone":"Asia/Aden",
    "iso:country":"YE",
    "wof:name":"Al Hijrah",
    "wof:placetype":"locality"
},
  "geometry": {"coordinates":[43.36218,15.45056],"type":"Point"}
}