{
  "type": "Feature",
  "properties": {
    "gn:admin1_code":"22.0",
    "gn:admin2_code":"1718.0",
    "gn:asciiname":"Sayat `Affar",
    "gn:country_code":"YE",
    "gn:dem":1925,
    "gn:feature_class":"P",
    "gn:feature_code":"PPL",
    "gn:name":"\u015e\u0101yat \u2018Aff\u0101r",
    "gn:population":0,
    "gn:timezone":"Asia/Aden",
    "iso:country":"YE",
    "name:und_x_variant":[
        "\u015e\u0101yat \u2018Aff\u0101r"
    ],
    "wof:name":"Sayat `Affar",
    "wof:placetype":"locality"
},
  "geometry": {"coordinates":[43.6752,15.80054],"type":"Point"}
}