{
  "type": "Feature",
  "properties": {
    "gn:admin1_code":"22.0",
    "gn:admin2_code":"1717.0",
    "gn:asciiname":"Suq ad Dawmah",
    "gn:country_code":"YE",
    "gn:dem":767,
    "gn:feature_class":"P",
    "gn:feature_code":"PPL",
    "gn:name":"S\u016bq ad Dawmah",
    "gn:population":0,
    "gn:timezone":"Asia/Aden",
    "iso:country":"YE",
    "name:und_x_variant":[
        "S\u016bq ad Dawmah"
    ],
    "wof:name":"Suq ad Dawmah",
    "wof:placetype":"locality"
},
  "geometry": {"coordinates":[43.62756,15.94673],"type":"Point"}
}