{
  "type": "Feature",
  "properties": {
    "gn:admin1_code":"8.0",
    "gn:admin2_code":"1817.0",
    "gn:asciiname":"Buyut al `Ijaliyah",
    "gn:country_code":"YE",
    "gn:dem":286,
    "gn:feature_class":"P",
    "gn:feature_code":"PPL",
    "gn:name":"Buy\u016bt al \u2018Ij\u0101l\u012byah",
    "gn:population":0,
    "gn:timezone":"Asia/Aden",
    "iso:country":"YE",
    "name:und_x_variant":[
        "Buy\u016bt al \u2018Ij\u0101l\u012byah"
    ],
    "wof:name":"Buyut al `Ijaliyah",
    "wof:placetype":"locality"
},
  "geometry": {"coordinates":[43.49405,14.50769],"type":"Point"}
}