{
  "type": "Feature",
  "properties": {
    "gn:admin1_code":"14.0",
    "gn:admin2_code":"2614.0",
    "gn:asciiname":"Al Khash'ah",
    "gn:country_code":"YE",
    "gn:dem":2048,
    "gn:feature_class":"P",
    "gn:feature_code":"PPL",
    "gn:name":"Al Khash\u2018ah",
    "gn:population":0,
    "gn:timezone":"Asia/Aden",
    "iso:country":"YE",
    "name:ara_x_preferred":[
        "\u0627\u0644\u062e\u0634\u0639\u0629"
    ],
    "name:und_x_variant":[
        "Al Khash\u2018ah"
    ],
    "wof:name":"Al Khash'ah",
    "wof:placetype":"locality"
},
  "geometry": {"coordinates":[45.17451,15.0417],"type":"Point"}
}