{
  "type": "Feature",
  "properties": {
    "gn:admin1_code":"8.0",
    "gn:admin2_code":"1813.0",
    "gn:asciiname":"Mahall ash Shabahiyah",
    "gn:country_code":"YE",
    "gn:dem":218,
    "gn:feature_class":"P",
    "gn:feature_code":"PPL",
    "gn:name":"Ma\u1e29all ash Shab\u0101\u1e29\u012byah",
    "gn:population":0,
    "gn:timezone":"Asia/Aden",
    "iso:country":"YE",
    "name:und_x_variant":[
        "Ma\u1e29all ash Shab\u0101\u1e29\u012byah"
    ],
    "wof:name":"Mahall ash Shabahiyah",
    "wof:placetype":"locality"
},
  "geometry": {"coordinates":[43.37175,14.93139],"type":"Point"}
}