{
  "type": "Feature",
  "properties": {
    "gn:admin1_code":"22.0",
    "gn:admin2_code":"1704.0",
    "gn:asciiname":"Al Wati",
    "gn:country_code":"YE",
    "gn:dem":242,
    "gn:feature_class":"P",
    "gn:feature_code":"PPL",
    "gn:name":"Al W\u0101\u0163\u012b",
    "gn:population":0,
    "gn:timezone":"Asia/Aden",
    "iso:country":"YE",
    "name:ara_x_preferred":[
        "Al W\u0101\u0163\u012b"
    ],
    "wof:name":"Al Wati",
    "wof:placetype":"locality"
},
  "geometry": {"coordinates":[43.2438,15.98867],"type":"Point"}
}