{
  "type": "Feature",
  "properties": {
    "gn:admin1_code":"8.0",
    "gn:admin2_code":"1817.0",
    "gn:asciiname":"Al Jurbishiyah",
    "gn:country_code":"YE",
    "gn:dem":169,
    "gn:feature_class":"P",
    "gn:feature_code":"PPL",
    "gn:name":"Al Jurbish\u012byah",
    "gn:population":0,
    "gn:timezone":"Asia/Aden",
    "iso:country":"YE",
    "name:und_x_variant":[
        "Al Jurbish\u012byah"
    ],
    "wof:name":"Al Jurbishiyah",
    "wof:placetype":"locality"
},
  "geometry": {"coordinates":[43.42196,14.58577],"type":"Point"}
}