{
  "type": "Feature",
  "properties": {
    "gn:admin1_code":"11.0",
    "gn:admin2_code":"2005.0",
    "gn:asciiname":"Akrafan",
    "gn:country_code":"YE",
    "gn:dem":2283,
    "gn:feature_class":"P",
    "gn:feature_code":"PPL",
    "gn:name":"Akraf\u0101n",
    "gn:population":0,
    "gn:timezone":"Asia/Aden",
    "iso:country":"YE",
    "name:und_x_variant":[
        "Akraf\u0101n"
    ],
    "wof:name":"Akrafan",
    "wof:placetype":"locality"
},
  "geometry": {"coordinates":[44.05502,14.51864],"type":"Point"}
}