{
  "type": "Feature",
  "properties": {
    "gn:country":"YE",
    "gn:fcode":"PPL",
    "gn:population":2,
    "iso:country":"YE",
    "name:ara_x_preferred":[
        "\u0627\u0644 \u0634\u0631\u0648\u064a\u062f"
    ],
    "name:eng_x_preferred":[
        "Al Shurwayd"
    ],
    "name:eng_x_variant":[
        "Ad Dammin"
    ],
    "qs:name":"\u0100l Shurwayd",
    "qs:photos_9r":0,
    "qs:photos_sr":0,
    "qs:pop_sr":"1",
    "wof:name":"\u0100l Shurwayd",
    "wof:placetype":"locality",
    "wof:population":2
},
  "geometry": {"coordinates":[43.79165,17.04022],"type":"Point"}
}