{
  "type": "Feature",
  "properties": {
    "gn:admin1_code":"23.0",
    "gn:admin2_code":"1120.0",
    "gn:asciiname":"Jabal ash Shabb",
    "gn:country_code":"YE",
    "gn:dem":2481,
    "gn:feature_class":"P",
    "gn:feature_code":"PPL",
    "gn:name":"Jabal ash Shabb",
    "gn:population":0,
    "gn:timezone":"Asia/Aden",
    "iso:country":"YE",
    "wof:name":"Jabal ash Shabb",
    "wof:placetype":"locality"
},
  "geometry": {"coordinates":[44.09664,13.9806],"type":"Point"}
}