{
  "type": "Feature",
  "properties": {
    "gn:admin1_code":"8.0",
    "gn:admin2_code":"1802.0",
    "gn:asciiname":"Al Maqas",
    "gn:country_code":"YE",
    "gn:dem":32,
    "gn:feature_class":"P",
    "gn:feature_code":"PPL",
    "gn:name":"Al Maq\u0101\u015f",
    "gn:population":0,
    "gn:timezone":"Asia/Aden",
    "iso:country":"YE",
    "name:ara_x_preferred":[
        "\u0627\u0644\u0645\u0642\u0627\u0635"
    ],
    "name:und_x_variant":[
        "Al Maq\u0101\u015f"
    ],
    "wof:name":"Al Maqas",
    "wof:placetype":"locality"
},
  "geometry": {"coordinates":[42.85778,15.65071],"type":"Point"}
}