{
  "type": "Feature",
  "properties": {
    "gn:admin1_code":"19.0",
    "gn:admin2_code":"2903.0",
    "gn:asciiname":"Dhabub",
    "gn:country_code":"YE",
    "gn:dem":1443,
    "gn:feature_class":"P",
    "gn:feature_code":"PPL",
    "gn:name":"Dhab\u016bb",
    "gn:population":0,
    "gn:timezone":"Asia/Aden",
    "iso:country":"YE",
    "name:ara_x_preferred":[
        "\u0630\u0628\u0648\u0628"
    ],
    "name:und_x_variant":[
        "Dhab\u016bb"
    ],
    "wof:name":"Dhabub",
    "wof:placetype":"locality"
},
  "geometry": {"coordinates":[43.78879000000001,16.46822],"type":"Point"}
}