{
  "type": "Feature",
  "properties": {
    "gn:country":"YE",
    "gn:fcode":"PPL",
    "gn:pop":4,
    "iso:country":"YE",
    "name:ara_x_preferred":[
        "\u0627\u0644\u0645\u0648\u062a\u0631"
    ],
    "name:eng_x_preferred":[
        "Al Mawtir"
    ],
    "qs:name":"Al Mawtir",
    "qs:photos_9r":0,
    "qs:photos_sr":0,
    "qs:pop_sr":"1",
    "wof:name":"Al Mawtir",
    "wof:placetype":"locality",
    "wof:population":4
},
  "geometry": {"coordinates":[43.30522,17.45656],"type":"Point"}
}