{
  "type": "Feature",
  "properties": {
    "gn:admin1_code":"15.0",
    "gn:admin2_code":"2205.0",
    "gn:asciiname":"Umm 'Abadiyah",
    "gn:country_code":"YE",
    "gn:dem":414,
    "gn:feature_class":"P",
    "gn:feature_code":"PPL",
    "gn:name":"Umm \u2018Ab\u0101d\u012byah",
    "gn:population":0,
    "gn:timezone":"Asia/Aden",
    "iso:country":"YE",
    "name:ara_x_preferred":[
        "\u0623\u0645 \u0639\u0628\u0627\u062f\u064a\u0629"
    ],
    "name:und_x_variant":[
        "Umm \u2018Ab\u0101d\u012byah"
    ],
    "wof:name":"Umm 'Abadiyah",
    "wof:placetype":"locality"
},
  "geometry": {"coordinates":[43.24126,16.83649],"type":"Point"}
}