{
  "type": "Feature",
  "properties": {
    "gn:admin1_code":"23.0",
    "gn:admin2_code":"1114.0",
    "gn:asciiname":"Muqaybirah",
    "gn:country_code":"YE",
    "gn:dem":1532,
    "gn:feature_class":"P",
    "gn:feature_code":"PPL",
    "gn:name":"Muqaybirah",
    "gn:population":0,
    "gn:timezone":"Asia/Aden",
    "iso:country":"YE",
    "wof:name":"Muqaybirah",
    "wof:placetype":"locality"
},
  "geometry": {"coordinates":[44.29268,13.7098],"type":"Point"}
}