{
  "type": "Feature",
  "properties": {
    "gn:admin1_code":"19.0",
    "gn:admin2_code":"2913.0",
    "gn:asciiname":"Lahaf an Nashr",
    "gn:country_code":"YE",
    "gn:dem":1184,
    "gn:feature_class":"P",
    "gn:feature_code":"PPLL",
    "gn:name":"La\u1e29af an Nashr",
    "gn:population":0,
    "gn:timezone":"Asia/Aden",
    "iso:country":"YE",
    "name:ara_x_preferred":[
        "\u0644\u062d\u0641 \u0627\u0644\u0646\u0634\u0631"
    ],
    "name:und_x_variant":[
        "La\u1e29af an Nashr"
    ],
    "wof:name":"Lahaf an Nashr",
    "wof:placetype":"locality"
},
  "geometry": {"coordinates":[43.7909,16.01846],"type":"Point"}
}