{
  "type": "Feature",
  "properties": {
    "gn:country":"YE",
    "gn:fcode":"PPL",
    "gn:pop":16,
    "iso:country":"YE",
    "name:ara_x_preferred":[
        "\u0627\u0644\u063a\u0648\u0627\u0631\u0628"
    ],
    "qs:name":"Al Ghaw\u0101rib",
    "qs:photos_9r":0,
    "qs:photos_sr":0,
    "qs:pop_sr":"1",
    "wof:name":"Al Ghaw\u0101rib",
    "wof:placetype":"locality",
    "wof:population":16
},
  "geometry": {"coordinates":[43.45347,16.20616],"type":"Point"}
}