{
  "type": "Feature",
  "properties": {
    "gn:admin1_code":"23.0",
    "gn:admin2_code":"1104.0",
    "gn:asciiname":"Ribat `Umqah",
    "gn:country_code":"YE",
    "gn:dem":2441,
    "gn:feature_class":"P",
    "gn:feature_code":"PPL",
    "gn:name":"Rib\u0101\u0163 \u2018Umqah",
    "gn:population":0,
    "gn:timezone":"Asia/Aden",
    "iso:country":"YE",
    "name:ara_x_preferred":[
        "\u0631\u0628\u0627\u0637 \u0639\u0645\u0642\u0629"
    ],
    "name:und_x_variant":[
        "Rib\u0101\u0163 \u2018Amqah",
        "Rib\u0101\u0163 \u2018Umqah"
    ],
    "wof:name":"Ribat `Umqah",
    "wof:placetype":"locality"
},
  "geometry": {"coordinates":[44.56093,14.10125],"type":"Point"}
}