{
  "type": "Feature",
  "properties": {
    "gn:country":"YE",
    "gn:fcode":"PPL",
    "gn:pop":16,
    "iso:country":"YE",
    "name:ara_x_preferred":[
        "\u0645\u0642\u062c\u0631 \u0627\u0644\u0631\u0643\u0628"
    ],
    "name:eng_x_preferred":[
        "Maqjar Ar Rakab"
    ],
    "qs:name":"Maqjar ar Rakab",
    "qs:photos_9r":0,
    "qs:photos_sr":0,
    "qs:pop_sr":"1",
    "wof:name":"Maqjar ar Rakab",
    "wof:placetype":"locality",
    "wof:population":16
},
  "geometry": {"coordinates":[43.29644,16.30068],"type":"Point"}
}