{
  "type": "Feature",
  "properties": {
    "gn:country":"YE",
    "gn:fcode":"FRM",
    "gn:population":1,
    "iso:country":"YE",
    "name:ara_x_preferred":[
        "\u0645\u0632\u0631\u0639\u0629 \u0628\u0646 \u0633\u0639\u064a\u062f\u0627\u0646"
    ],
    "qs:name":"Mazra\u2018at Bin Sa\u2018\u012bd\u0101n",
    "qs:photos_9r":0,
    "qs:photos_sr":0,
    "qs:pop_sr":"1",
    "wof:name":"Mazra\u2018at Bin Sa\u2018\u012bd\u0101n",
    "wof:placetype":"locality",
    "wof:population":1
},
  "geometry": {"coordinates":[45.01125,16.97818],"type":"Point"}
}