{
  "type": "Feature",
  "properties": {
    "gn:admin1_code":"10.0",
    "gn:admin2_code":"2703.0",
    "gn:asciiname":"Bayt al Jaradi",
    "gn:country_code":"YE",
    "gn:dem":2243,
    "gn:feature_class":"P",
    "gn:feature_code":"PPL",
    "gn:name":"Bayt al Jar\u0101d\u012b",
    "gn:population":0,
    "gn:timezone":"Asia/Aden",
    "iso:country":"YE",
    "name:und_x_variant":[
        "Bayt al Jar\u0101d\u012b"
    ],
    "wof:name":"Bayt al Jaradi",
    "wof:placetype":"locality"
},
  "geometry": {"coordinates":[43.61969000000001,15.48679],"type":"Point"}
}