{
  "type": "Feature",
  "properties": {
    "gn:admin1_code":"19.0",
    "gn:admin2_code":"2908.0",
    "gn:asciiname":"Hadabat at Tasah",
    "gn:country_code":"YE",
    "gn:dem":1033,
    "gn:feature_class":"P",
    "gn:feature_code":"PPL",
    "gn:name":"\u1e28adabat a\u0163 \u0162\u0101sah",
    "gn:population":0,
    "gn:timezone":"Asia/Aden",
    "iso:country":"YE",
    "name:ara_x_preferred":[
        "\u062d\u062f\u0628\u0629 \u0627\u0644\u0637\u0627\u0633\u0629"
    ],
    "name:und_x_variant":[
        "\u1e28adabat a\u0163 \u0162\u0101sah"
    ],
    "wof:name":"Hadabat at Tasah",
    "wof:placetype":"locality"
},
  "geometry": {"coordinates":[43.77528,16.07481],"type":"Point"}
}