{
  "type": "Feature",
  "properties": {
    "gn:country":"YE",
    "gn:fcode":"PPL",
    "gn:population":2,
    "iso:country":"YE",
    "name:ara_x_preferred":[
        "Ash Shib\u0101\u1e29"
    ],
    "name:ara_x_variant":[
        "\u0627\u0644\u0634\u0628\u0627\u062d"
    ],
    "name:eng_x_preferred":[
        "Ash Shibah"
    ],
    "name:eng_x_variant":[
        "Ar Raq\u012bqah"
    ],
    "qs:name":"Ash Shib\u0101\u1e29",
    "qs:photos_9r":0,
    "qs:photos_sr":0,
    "qs:pop_sr":"1",
    "wof:name":"Ash Shib\u0101\u1e29",
    "wof:placetype":"locality",
    "wof:population":2
},
  "geometry": {"coordinates":[43.26899,17.13559],"type":"Point"}
}