{
  "type": "Feature",
  "properties": {
    "gn:admin1_code":"25.0",
    "gn:admin2_code":"1504.0",
    "gn:asciiname":"Al Madrub",
    "gn:country_code":"YE",
    "gn:dem":1019,
    "gn:feature_class":"P",
    "gn:feature_code":"PPL",
    "gn:name":"Al Ma\u1e11r\u016bb",
    "gn:population":0,
    "gn:timezone":"Asia/Aden",
    "iso:country":"YE",
    "name:ara_x_preferred":[
        "\u0627\u0644\u0645\u0636\u0631\u0648\u0628"
    ],
    "name:und_x_variant":[
        "Al Ma\u1e11r\u016bb"
    ],
    "wof:name":"Al Madrub",
    "wof:placetype":"locality"
},
  "geometry": {"coordinates":[43.7198,13.79572],"type":"Point"}
}