{
  "type": "Feature",
  "properties": {
    "gn:country":"YE",
    "gn:fcode":"PPL",
    "gn:population":9,
    "iso:country":"YE",
    "name:ara_x_preferred":[
        "Al \u2018Andij\u0101\u2019"
    ],
    "name:ara_x_variant":[
        "\u0627\u0644\u0639\u0646\u062f\u062c\u0627\u0621"
    ],
    "name:eng_x_preferred":[
        "Al 'Andija"
    ],
    "name:eng_x_variant":[
        "Q\u012bmat al \u1e28\u0101jj"
    ],
    "qs:name":"Al \u2018Andij\u0101\u2019",
    "qs:photos_9r":0,
    "qs:photos_sr":0,
    "qs:pop_sr":"1",
    "wof:name":"Al \u2018Andij\u0101\u2019",
    "wof:placetype":"locality",
    "wof:population":9
},
  "geometry": {"coordinates":[43.46252,16.18446],"type":"Point"}
}