{
  "type": "Feature",
  "properties": {
    "gn:admin1_code":"24.0",
    "gn:admin2_code":"2512.0",
    "gn:asciiname":"Al Maqsus",
    "gn:country_code":"YE",
    "gn:dem":2014,
    "gn:feature_class":"P",
    "gn:feature_code":"PPL",
    "gn:name":"Al Maq\u015f\u016b\u015f",
    "gn:population":0,
    "gn:timezone":"Asia/Aden",
    "iso:country":"YE",
    "name:ara_x_preferred":[
        "\u0627\u0644\u0645\u0642\u0635\u0648\u0635"
    ],
    "name:und_x_variant":[
        "Al Maq\u015f\u016b\u015f"
    ],
    "wof:name":"Al Maqsus",
    "wof:placetype":"locality"
},
  "geometry": {"coordinates":[44.16618,13.2423],"type":"Point"}
}