{
  "type": "Feature",
  "properties": {
    "gn:country":"YE",
    "gn:fcode":"PPL",
    "gn:pop":5,
    "iso:country":"YE",
    "name:ara_x_preferred":[
        "\u0627\u0644\u0642\u0635\u064a\u0629"
    ],
    "qs:name":"Al Qa\u015f\u012byah",
    "qs:photos_9r":0,
    "qs:photos_sr":0,
    "qs:pop_sr":"1",
    "wof:name":"Al Qa\u015f\u012byah",
    "wof:placetype":"locality",
    "wof:population":5
},
  "geometry": {"coordinates":[43.43645,16.34084],"type":"Point"}
}