{
  "type": "Feature",
  "properties": {
    "gn:admin1_code":"14.0",
    "gn:admin2_code":"2613.0",
    "gn:asciiname":"Al Jithwah",
    "gn:country_code":"YE",
    "gn:dem":1073,
    "gn:feature_class":"P",
    "gn:feature_code":"PPL",
    "gn:name":"Al Jithwah",
    "gn:population":0,
    "gn:timezone":"Asia/Aden",
    "iso:country":"YE",
    "name:ara_x_preferred":[
        "\u0627\u0644\u062c\u062b\u0648\u0629"
    ],
    "name:und_x_variant":[
        "Jilhwa",
        "Juthwah"
    ],
    "wof:name":"Al Jithwah",
    "wof:placetype":"locality"
},
  "geometry": {"coordinates":[45.42149000000001,15.48649],"type":"Point"}
}