{
  "type": "Feature",
  "properties": {
    "gn:admin1_code":"20.0",
    "gn:admin2_code":"1419.0",
    "gn:asciiname":"Al Hindawanah",
    "gn:country_code":"YE",
    "gn:dem":1960,
    "gn:feature_class":"P",
    "gn:feature_code":"PPL",
    "gn:name":"Al Hindaw\u0101nah",
    "gn:population":0,
    "gn:timezone":"Asia/Aden",
    "iso:country":"YE",
    "name:ara_x_preferred":[
        "\u0627\u0644\u0647\u0646\u062f\u0648\u0627\u0646\u0629"
    ],
    "name:und_x_variant":[
        "Al Hindaw\u0101nah"
    ],
    "wof:name":"Al Hindawanah",
    "wof:placetype":"locality"
},
  "geometry": {"coordinates":[45.05318,14.32706],"type":"Point"}
}