{
  "type": "Feature",
  "properties": {
    "gn:admin1_code":"8.0",
    "gn:admin2_code":"1814.0",
    "gn:asciiname":"Sanif al `Abbasi",
    "gn:country_code":"YE",
    "gn:dem":69,
    "gn:feature_class":"P",
    "gn:feature_code":"PPL",
    "gn:name":"\u015ean\u012bf al \u2018Abb\u0101s\u012b",
    "gn:population":0,
    "gn:timezone":"Asia/Aden",
    "iso:country":"YE",
    "name:und_x_variant":[
        "\u2018Abb\u0101s\u012b",
        "Al \u2018Abb\u0101si",
        "Abassi",
        "\u015ean\u012bf al \u2018Abb\u0101s\u012b",
        "Al \u2018Abb\u0101s"
    ],
    "wof:name":"Sanif al `Abbasi",
    "wof:placetype":"locality"
},
  "geometry": {"coordinates":[43.24212,14.60212],"type":"Point"}
}