{
  "type": "Feature",
  "properties": {
    "gn:admin1_code":"15.0",
    "gn:admin2_code":"2203.0",
    "gn:asciiname":"As Sawdah",
    "gn:country":"YE",
    "gn:country_code":"YE",
    "gn:dem":1229,
    "gn:fcode":"PPL",
    "gn:feature_class":"P",
    "gn:feature_code":"PPL",
    "gn:name":"As Sawdah",
    "gn:population":2,
    "gn:timezone":"Asia/Aden",
    "iso:country":"YE",
    "name:ara_x_preferred":[
        "\u0627\u0644\u0633\u0648\u062f\u0629"
    ],
    "name:ara_x_variant":[
        "\u0627\u0644\u0633\u0648\u062f\u0627"
    ],
    "name:arz_x_preferred":[
        "\u0627\u0644\u0633\u0648\u062f\u0627"
    ],
    "name:eng_x_preferred":[
        "Al-Sawda"
    ],
    "name:fas_x_preferred":[
        "\u0627\u0644\u0633\u0648\u062f\u0627"
    ],
    "name:nld_x_preferred":[
        "Al-Sawda"
    ],
    "name:nno_x_preferred":[
        "Al-Sawda"
    ],
    "name:pol_x_preferred":[
        "As-Sauda"
    ],
    "name:rus_x_preferred":[
        "\u042d\u0441-\u0421\u0430\u0443\u0434\u0430"
    ],
    "name:ukr_x_preferred":[
        "\u0410\u0441-\u0421\u0430\u0443\u0434\u0430"
    ],
    "name:vie_x_preferred":[
        "Al-Sawda"
    ],
    "qs:name":"As Sawdah",
    "qs:photos_9r":0,
    "qs:photos_sr":0,
    "qs:pop_sr":"1",
    "wd:wordcount":498,
    "wof:name":"As Sawdah",
    "wof:placetype":"locality",
    "wof:population":2
},
  "geometry": {"coordinates":[43.29481,17.27118],"type":"Point"}
}