{
  "type": "Feature",
  "properties": {
    "gn:admin1_code":"11.0",
    "gn:admin2_code":"2011.0",
    "gn:asciiname":"Al Jirah",
    "gn:country_code":"YE",
    "gn:dem":1931,
    "gn:feature_class":"P",
    "gn:feature_code":"PPL",
    "gn:name":"Al Jirah",
    "gn:population":0,
    "gn:timezone":"Asia/Aden",
    "iso:country":"YE",
    "wof:name":"Al Jirah",
    "wof:placetype":"locality"
},
  "geometry": {"coordinates":[43.99362,14.76675],"type":"Point"}
}