{
  "type": "Feature",
  "properties": {
    "gn:country":"YE",
    "gn:fcode":"PPL",
    "gn:pop":3,
    "iso:country":"YE",
    "name:ara_x_preferred":[
        "S\u0101mir"
    ],
    "name:ara_x_variant":[
        "\u0633\u0627\u0645\u0631"
    ],
    "qs:name":"S\u0101mir",
    "qs:photos_9r":0,
    "qs:photos_sr":0,
    "qs:pop_sr":"1",
    "wd:wordcount":224,
    "wof:name":"S\u0101mir",
    "wof:placetype":"locality",
    "wof:population":3
},
  "geometry": {"coordinates":[43.38487,16.25301],"type":"Point"}
}