{
  "type": "Feature",
  "properties": {
    "gn:country":"YE",
    "gn:fcode":"PPL",
    "gn:pop":5,
    "iso:country":"YE",
    "name:ara_x_preferred":[
        "\u0627\u0644\u062e\u0628\u0627\u0634\u064a\u0629"
    ],
    "name:eng_x_preferred":[
        "Al Khibashiyah"
    ],
    "name:unk_x_variant":[
        "\u0627\u0644\u062e\u0628\u0627\u0634\u064a\u0629"
    ],
    "qs:name":"Al Khib\u0101sh\u012byah",
    "qs:photos_9r":0,
    "qs:photos_sr":0,
    "qs:pop_sr":"1",
    "wof:name":"Al Khib\u0101sh\u012byah",
    "wof:placetype":"locality",
    "wof:population":5
},
  "geometry": {"coordinates":[42.89419,16.07608],"type":"Point"}
}