{
  "type": "Feature",
  "properties": {
    "gn:admin1_code":"24.0",
    "gn:admin2_code":"2511.0",
    "gn:asciiname":"Khabt",
    "gn:country_code":"YE",
    "gn:dem":397,
    "gn:feature_class":"P",
    "gn:feature_code":"PPL",
    "gn:name":"Khab\u0163",
    "gn:population":0,
    "gn:timezone":"Asia/Aden",
    "iso:country":"YE",
    "name:und_x_variant":[
        "Khab\u0163"
    ],
    "wof:name":"Khabt",
    "wof:placetype":"locality"
},
  "geometry": {"coordinates":[44.39251,13.03507],"type":"Point"}
}