{
  "type": "Feature",
  "properties": {
    "gn:gn_country":"YE",
    "gn:gn_fcode":"PPL",
    "gn:gn_pop":25,
    "gn:population":25,
    "iso:country":"YE",
    "name:ara_x_preferred":[
        "\u0639\u0641\u0649"
    ],
    "name:eng_x_preferred":[
        "Afiy"
    ],
    "name:eng_x_variant":[
        "Fa\u0163\u012bs",
        "'Afiy"
    ],
    "name:unk_x_variant":[
        "\u2018Af\u012b"
    ],
    "qs_pg:aaroncc":"YE",
    "qs_pg:gn_country":"YE",
    "qs_pg:gn_fcode":"PPL",
    "qs_pg:gn_pop":25,
    "qs_pg:name":"\u2018Af\u012by",
    "qs_pg:photos_9r":0,
    "qs_pg:photos_sr":0,
    "qs_pg:pop_sr":1,
    "qs_pg:qs_pg_placetype":"locality",
    "wof:name":"\u2018Af\u012by",
    "wof:placetype":"locality",
    "wof:population":25
},
  "geometry": {"coordinates":[44.89252,16.96279],"type":"Point"}
}