{
  "type": "Feature",
  "properties": {
    "gn:admin1_code":"11.0",
    "gn:admin2_code":"2010.0",
    "gn:asciiname":"Dar al Huwayti",
    "gn:country_code":"YE",
    "gn:dem":2369,
    "gn:feature_class":"P",
    "gn:feature_code":"PPL",
    "gn:name":"D\u0101r al \u1e28uwayt\u012b",
    "gn:population":0,
    "gn:timezone":"Asia/Aden",
    "iso:country":"YE",
    "name:und_x_variant":[
        "D\u0101r al \u1e28uwayt\u012b"
    ],
    "wof:name":"Dar al Huwayti",
    "wof:placetype":"locality"
},
  "geometry": {"coordinates":[44.25821,14.51605],"type":"Point"}
}