{
  "type": "Feature",
  "properties": {
    "gn:admin1_code":"22.0",
    "gn:admin2_code":"1701.0",
    "gn:asciiname":"Malus",
    "gn:country_code":"YE",
    "gn:dem":215,
    "gn:feature_class":"P",
    "gn:feature_code":"PPL",
    "gn:name":"M\u0101l\u016bs",
    "gn:population":0,
    "gn:timezone":"Asia/Aden",
    "iso:country":"YE",
    "name:ara_x_preferred":[
        "M\u0101l\u016bs"
    ],
    "wof:name":"Malus",
    "wof:placetype":"locality"
},
  "geometry": {"coordinates":[43.21155,16.50322],"type":"Point"}
}