{
  "type": "Feature",
  "properties": {
    "gn:admin1_code":"14.0",
    "gn:asciiname":"An Nashigh",
    "gn:country_code":"YE",
    "gn:dem":1645,
    "gn:feature_class":"P",
    "gn:feature_code":"PPL",
    "gn:name":"An N\u0101shigh",
    "gn:population":0,
    "gn:timezone":"Asia/Aden",
    "iso:country":"YE",
    "name:ara_x_preferred":[
        "\u0627\u0644\u0646\u0627\u0634\u063a"
    ],
    "name:und_x_variant":[
        "An N\u0101shigh"
    ],
    "wof:name":"An Nashigh",
    "wof:placetype":"locality"
},
  "geometry": {"coordinates":[44.80485,16.49537],"type":"Point"}
}