{
  "type": "Feature",
  "properties": {
    "gn:country":"YE",
    "gn:fcode":"PPL",
    "gn:population":7,
    "iso:country":"YE",
    "name:ara_x_preferred":[
        "\u0627\u0644\u0645\u062f\u0641\u0646"
    ],
    "name:eng_x_preferred":[
        "Al Madfan"
    ],
    "name:eng_x_variant":[
        "Fawq as Sab\u2018"
    ],
    "qs:name":"Al Madfan",
    "qs:photos_9r":0,
    "qs:photos_sr":0,
    "qs:pop_sr":"1",
    "wof:name":"Al Madfan",
    "wof:placetype":"locality",
    "wof:population":7
},
  "geometry": {"coordinates":[45.3609,14.45902],"type":"Point"}
}