{
  "type": "Feature",
  "properties": {
    "gn:admin1_code":"18.0",
    "gn:admin2_code":"3009.0",
    "gn:asciiname":"Al Kishrar",
    "gn:country_code":"YE",
    "gn:dem":1481,
    "gn:feature_class":"P",
    "gn:feature_code":"PPL",
    "gn:name":"Al Kishr\u0101r",
    "gn:population":0,
    "gn:timezone":"Asia/Aden",
    "iso:country":"YE",
    "name:ara_x_preferred":[
        "Al Kishr\u0101r"
    ],
    "wof:name":"Al Kishrar",
    "wof:placetype":"locality"
},
  "geometry": {"coordinates":[44.43923,13.72828],"type":"Point"}
}