{
  "type": "Feature",
  "properties": {
    "gn:admin1_code":"4.0",
    "gn:admin2_code":"1909.0",
    "gn:asciiname":"Makhraqah",
    "gn:country_code":"YE",
    "gn:dem":809,
    "gn:feature_class":"P",
    "gn:feature_code":"PPL",
    "gn:name":"Makhraqah",
    "gn:population":0,
    "gn:timezone":"Asia/Aden",
    "iso:country":"YE",
    "wof:name":"Makhraqah",
    "wof:placetype":"locality"
},
  "geometry": {"coordinates":[48.83333,15.68333],"type":"Point"}
}