{
  "type": "Feature",
  "properties": {
    "gn:admin1_code":"15.0",
    "gn:admin2_code":"2209.0",
    "gn:asciiname":"Ar Rukbat",
    "gn:country_code":"YE",
    "gn:dem":2324,
    "gn:feature_class":"P",
    "gn:feature_code":"PPL",
    "gn:name":"Ar Rukb\u0101t",
    "gn:population":0,
    "gn:timezone":"Asia/Aden",
    "iso:country":"YE",
    "name:ara_x_preferred":[
        "Ar Rukb\u0101t"
    ],
    "name:ara_x_variant":[
        "\u0627\u0644\u0631\u0643\u0628\u0627\u062a"
    ],
    "wof:name":"Ar Rukbat",
    "wof:placetype":"locality"
},
  "geometry": {"coordinates":[43.45732,16.83313],"type":"Point"}
}