{
  "type": "Feature",
  "properties": {
    "gn:admin1_code":"8.0",
    "gn:admin2_code":"1813.0",
    "gn:asciiname":"Mahall al Jalal",
    "gn:country_code":"YE",
    "gn:dem":196,
    "gn:feature_class":"P",
    "gn:feature_code":"PPL",
    "gn:name":"Ma\u1e29all al Jal\u0101l",
    "gn:population":0,
    "gn:timezone":"Asia/Aden",
    "iso:country":"YE",
    "name:und_x_variant":[
        "Ma\u1e29all al Jal\u0101l"
    ],
    "wof:name":"Mahall al Jalal",
    "wof:placetype":"locality"
},
  "geometry": {"coordinates":[43.37267,14.9112],"type":"Point"}
}