{
  "type": "Feature",
  "properties": {
    "gn:admin1_code":"11.0",
    "gn:admin2_code":"2012.0",
    "gn:asciiname":"Bayt ash Shami",
    "gn:country_code":"YE",
    "gn:dem":2020,
    "gn:feature_class":"P",
    "gn:feature_code":"PPL",
    "gn:name":"Bayt ash Sh\u0101m\u012b",
    "gn:population":0,
    "gn:timezone":"Asia/Aden",
    "iso:country":"YE",
    "name:und_x_variant":[
        "Bayt ash Sh\u0101m\u012b"
    ],
    "wof:name":"Bayt ash Shami",
    "wof:placetype":"locality"
},
  "geometry": {"coordinates":[44.08733,14.5802],"type":"Point"}
}