{
  "type": "Feature",
  "properties": {
    "gn:admin1_code":"8.0",
    "gn:admin2_code":"1818.0",
    "gn:asciiname":"Mintashah",
    "gn:country_code":"YE",
    "gn:dem":381,
    "gn:feature_class":"P",
    "gn:feature_code":"PPL",
    "gn:name":"Min\u0163\u0101shah",
    "gn:population":0,
    "gn:timezone":"Asia/Aden",
    "iso:country":"YE",
    "name:und_x_variant":[
        "Min\u0163\u0101shah"
    ],
    "wof:name":"Mintashah",
    "wof:placetype":"locality"
},
  "geometry": {"coordinates":[43.56875,14.10924],"type":"Point"}
}