{
  "type": "Feature",
  "properties": {
    "gn:admin1_code":"11.0",
    "gn:admin2_code":"2010.0",
    "gn:asciiname":"Dhi Hawir",
    "gn:country_code":"YE",
    "gn:dem":2107,
    "gn:feature_class":"P",
    "gn:feature_code":"PPL",
    "gn:name":"Dh\u012b \u1e28\u0101wir",
    "gn:population":0,
    "gn:timezone":"Asia/Aden",
    "iso:country":"YE",
    "name:ara_x_preferred":[
        "Dh\u012b \u1e28\u0101wir"
    ],
    "wof:name":"Dhi Hawir",
    "wof:placetype":"locality"
},
  "geometry": {"coordinates":[44.21583,14.5187],"type":"Point"}
}