{
  "type": "Feature",
  "properties": {
    "gn:admin1_code":"25.0",
    "gn:admin2_code":"1518.0",
    "gn:asciiname":"Al Hasab",
    "gn:country_code":"YE",
    "gn:dem":1317,
    "gn:feature_class":"P",
    "gn:feature_code":"PPL",
    "gn:name":"Al Hasab",
    "gn:population":0,
    "gn:timezone":"Asia/Aden",
    "iso:country":"YE",
    "name:ara_x_preferred":[
        "\u0627\u0644\u062d\u0635\u064a"
    ],
    "name:und_x_variant":[
        "\u0627\u0644\u062d\u0635\u064a"
    ],
    "wof:name":"Al Hasab",
    "wof:placetype":"locality"
},
  "geometry": {"coordinates":[43.99412,13.57667],"type":"Point"}
}