{
  "type": "Feature",
  "properties": {
    "gn:country":"YE",
    "gn:fcode":"PPL",
    "gn:pop":9,
    "iso:country":"YE",
    "name:ara_x_preferred":[
        "\u0627\u0644\u062d\u0644\u0641\u0629"
    ],
    "name:eng_x_preferred":[
        "Al Halafah"
    ],
    "qs:name":"Al \u1e28alafah",
    "qs:photos_9r":0,
    "qs:photos_sr":0,
    "qs:pop_sr":"1",
    "wof:name":"Al \u1e28alafah",
    "wof:placetype":"locality",
    "wof:population":9
},
  "geometry": {"coordinates":[44.54099,16.9326],"type":"Point"}
}