{
  "type": "Feature",
  "properties": {
    "gn:admin1_code":"15.0",
    "gn:admin2_code":"2205.0",
    "gn:asciiname":"Al 'Ammar",
    "gn:country_code":"YE",
    "gn:dem":1584,
    "gn:feature_class":"P",
    "gn:feature_code":"PPL",
    "gn:name":"Al \u2018Amm\u0101r",
    "gn:population":0,
    "gn:timezone":"Asia/Aden",
    "iso:country":"YE",
    "name:ara_x_preferred":[
        "\u0627\u0644\u0639\u0645\u0627\u0631"
    ],
    "name:und_x_variant":[
        "Al \u2018Amm\u0101r"
    ],
    "wof:name":"Al 'Ammar",
    "wof:placetype":"locality"
},
  "geometry": {"coordinates":[43.24874000000001,16.91532999999999],"type":"Point"}
}