{
  "type": "Feature",
  "properties": {
    "gn:admin1_code":"16.0",
    "gn:admin2_code":"2303.0",
    "gn:asciiname":"Madawir",
    "gn:country_code":"YE",
    "gn:dem":2564,
    "gn:feature_class":"P",
    "gn:feature_code":"PPL",
    "gn:name":"Mad\u0101wir",
    "gn:population":0,
    "gn:timezone":"Asia/Aden",
    "iso:country":"YE",
    "name:und_x_variant":[
        "Mad\u0101wir"
    ],
    "wof:name":"Madawir",
    "wof:placetype":"locality"
},
  "geometry": {"coordinates":[44.42822,15.54572],"type":"Point"}
}