{
  "type": "Feature",
  "properties": {
    "gn:admin1_code":"23.0",
    "gn:admin2_code":"1113.0",
    "gn:asciiname":"Ar Raba`i",
    "gn:country_code":"YE",
    "gn:dem":2417,
    "gn:feature_class":"P",
    "gn:feature_code":"PPL",
    "gn:name":"Ar Rab\u0101\u2018\u012b",
    "gn:population":0,
    "gn:timezone":"Asia/Aden",
    "iso:country":"YE",
    "name:und_x_variant":[
        "Ar Rab\u0101\u2018\u012b"
    ],
    "wof:name":"Ar Raba`i",
    "wof:placetype":"locality"
},
  "geometry": {"coordinates":[44.26519,13.94276],"type":"Point"}
}