{
  "type": "Feature",
  "properties": {
    "gn:admin1_code":"1.0",
    "gn:admin2_code":"1202.0",
    "gn:asciiname":"Hisn Bin Maiam",
    "gn:country_code":"YE",
    "gn:dem":817,
    "gn:feature_class":"P",
    "gn:feature_code":"PPL",
    "gn:name":"\u1e28i\u015fn Bin Maiam",
    "gn:population":0,
    "gn:timezone":"Asia/Aden",
    "iso:country":"YE",
    "name:und_x_variant":[
        "\u1e28i\u015fn Bin Maiam"
    ],
    "wof:name":"Hisn Bin Maiam",
    "wof:placetype":"locality"
},
  "geometry": {"coordinates":[46.11199000000001,13.92211],"type":"Point"}
}