{
  "type": "Feature",
  "properties": {
    "gn:gn_country":"YE",
    "gn:gn_fcode":"PPLX",
    "gn:gn_pop":1,
    "gn:population":1,
    "iso:country":"YE",
    "name:ara_x_preferred":[
        "\u0627\u0644\u0635\u0641\u064a\u0640\u062d"
    ],
    "qs_pg:aaroncc":"YE",
    "qs_pg:gn_country":"YE",
    "qs_pg:gn_fcode":"PPLX",
    "qs_pg:gn_pop":1,
    "qs_pg:name":"A\u015f \u015eufay\u1e29",
    "qs_pg:photos_9r":0,
    "qs_pg:photos_sr":0,
    "qs_pg:pop_sr":1,
    "qs_pg:qs_pg_placetype":"neighbourhood",
    "wof:name":"A\u015f \u015eufay\u1e29",
    "wof:placetype":"neighbourhood",
    "wof:population":1
},
  "geometry": {"coordinates":[43.68938,16.18867],"type":"Point"}
}