{
  "type": "Feature",
  "properties": {
    "gn:admin1_code":"21.0",
    "gn:admin2_code":"1612.0",
    "gn:asciiname":"Dihmah",
    "gn:country_code":"YE",
    "gn:dem":1446,
    "gn:feature_class":"P",
    "gn:feature_code":"PPL",
    "gn:name":"Dihmah",
    "gn:population":0,
    "gn:timezone":"Asia/Aden",
    "iso:country":"YE",
    "wof:name":"Dihmah",
    "wof:placetype":"locality"
},
  "geometry": {"coordinates":[44.25505,16.58496],"type":"Point"}
}