{
  "type": "Feature",
  "properties": {
    "gn:country":"YE",
    "gn:fcode":"PPL",
    "gn:pop":1,
    "iso:country":"YE",
    "name:ara_x_preferred":[
        "\u0627\u0644\u062d\u0644\u0627\u0648"
    ],
    "qs:name":"Al \u1e28al\u0101w",
    "qs:photos_9r":0,
    "qs:photos_sr":0,
    "qs:pop_sr":"1",
    "wof:name":"Al \u1e28al\u0101w",
    "wof:placetype":"locality",
    "wof:population":1
},
  "geometry": {"coordinates":[43.39576,16.67348],"type":"Point"}
}