{
  "type": "Feature",
  "properties": {
    "gn:admin1_code":"22.0",
    "gn:admin2_code":"1725.0",
    "gn:asciiname":"Bani 'Ulayban",
    "gn:country_code":"YE",
    "gn:dem":1130,
    "gn:feature_class":"P",
    "gn:feature_code":"PPL",
    "gn:name":"Ban\u012b \u2018Ulayb\u0101n",
    "gn:population":0,
    "gn:timezone":"Asia/Aden",
    "iso:country":"YE",
    "name:ara_x_preferred":[
        "\u0628\u0646\u064a \u0639\u0644\u064a\u0627\u0646"
    ],
    "name:und_x_variant":[
        "Ban\u012b \u2018Ulayb\u0101n"
    ],
    "wof:name":"Bani 'Ulayban",
    "wof:placetype":"locality"
},
  "geometry": {"coordinates":[43.56043,15.59417],"type":"Point"}
}