{
  "type": "Feature",
  "properties": {
    "gn:admin1_code":"16.0",
    "gn:admin2_code":"2309.0",
    "gn:asciiname":"As Subar",
    "gn:country_code":"YE",
    "gn:dem":1768,
    "gn:feature_class":"P",
    "gn:feature_code":"PPL",
    "gn:name":"A\u015f \u015eub\u0101r",
    "gn:population":0,
    "gn:timezone":"Asia/Aden",
    "iso:country":"YE",
    "name:ara_x_preferred":[
        "A\u015f \u015eub\u0101r"
    ],
    "wof:name":"As Subar",
    "wof:placetype":"locality"
},
  "geometry": {"coordinates":[43.91497,15.04837],"type":"Point"}
}