{
  "type": "Feature",
  "properties": {
    "gn:country":"YE",
    "gn:fcode":"PPL",
    "gn:population":2,
    "iso:country":"YE",
    "name:ara_x_preferred":[
        "\u0627\u0644\u0639\u0642\u0644\u0629"
    ],
    "qs:name":"Al \u2018Uqlah",
    "qs:photos_9r":0,
    "qs:photos_sr":0,
    "qs:pop_sr":"1",
    "wof:name":"Al \u2018Uqlah",
    "wof:placetype":"locality",
    "wof:population":2
},
  "geometry": {"coordinates":[45.25732,14.04939],"type":"Point"}
}