{
  "type": "Feature",
  "properties": {
    "gn:admin1_code":"8.0",
    "gn:admin2_code":"1810.0",
    "gn:asciiname":"Al Mashahirah",
    "gn:country_code":"YE",
    "gn:dem":220,
    "gn:feature_class":"P",
    "gn:feature_code":"PPL",
    "gn:name":"Al Mash\u0101hirah",
    "gn:population":0,
    "gn:timezone":"Asia/Aden",
    "iso:country":"YE",
    "name:ara_x_preferred":[
        "\u0627\u0644\u0645\u0634\u0627\u0647\u0631\u0629"
    ],
    "name:und_x_variant":[
        "\u1e28izz al Mush\u0101harah",
        "Al Mash\u0101hirah"
    ],
    "wof:name":"Al Mashahirah",
    "wof:placetype":"locality"
},
  "geometry": {"coordinates":[43.35826,15.03983],"type":"Point"}
}