{
  "type": "Feature",
  "properties": {
    "gn:admin1_code":"15.0",
    "gn:admin2_code":"2209.0",
    "gn:asciiname":"Majjat al Ghallah",
    "gn:country_code":"YE",
    "gn:dem":2537,
    "gn:feature_class":"P",
    "gn:feature_code":"PPL",
    "gn:name":"Majjat al Ghallah",
    "gn:population":0,
    "gn:timezone":"Asia/Aden",
    "iso:country":"YE",
    "wof:name":"Majjat al Ghallah",
    "wof:placetype":"locality"
},
  "geometry": {"coordinates":[43.51667,16.96667],"type":"Point"}
}