{
  "type": "Feature",
  "properties": {
    "gn:admin1_code":"22.0",
    "gn:admin2_code":"1722.0",
    "gn:asciiname":"Al `Ushur",
    "gn:country_code":"YE",
    "gn:dem":557,
    "gn:feature_class":"P",
    "gn:feature_code":"PPL",
    "gn:name":"Al \u2018Ushur",
    "gn:population":0,
    "gn:timezone":"Asia/Aden",
    "iso:country":"YE",
    "name:ara_x_preferred":[
        "Al \u2018Ushur"
    ],
    "wof:name":"Al `Ushur",
    "wof:placetype":"locality"
},
  "geometry": {"coordinates":[43.38318,15.78525],"type":"Point"}
}