{
  "type": "Feature",
  "properties": {
    "gn:admin1_code":"11.0",
    "gn:admin2_code":"2011.0",
    "gn:asciiname":"Hirthan",
    "gn:country_code":"YE",
    "gn:dem":1697,
    "gn:feature_class":"P",
    "gn:feature_code":"PPL",
    "gn:name":"\u1e28irth\u0101n",
    "gn:population":0,
    "gn:timezone":"Asia/Aden",
    "iso:country":"YE",
    "name:ara_x_preferred":[
        "\u1e28irth\u0101n"
    ],
    "wof:name":"Hirthan",
    "wof:placetype":"locality"
},
  "geometry": {"coordinates":[44.04974,14.70117],"type":"Point"}
}