{
  "type": "Feature",
  "properties": {
    "gn:admin1_code":"15.0",
    "gn:admin2_code":"2206.0",
    "gn:asciiname":"'Awsat",
    "gn:country_code":"YE",
    "gn:dem":771,
    "gn:feature_class":"P",
    "gn:feature_code":"PPL",
    "gn:name":"\u2018Awsat",
    "gn:population":0,
    "gn:timezone":"Asia/Aden",
    "iso:country":"YE",
    "name:ara_x_preferred":[
        "\u0639\u0648\u0633\u062a"
    ],
    "name:und_x_variant":[
        "\u2018Awsat"
    ],
    "wof:name":"'Awsat",
    "wof:placetype":"locality"
},
  "geometry": {"coordinates":[43.17935,16.88839],"type":"Point"}
}