{
  "type": "Feature",
  "properties": {
    "gn:country":"YE",
    "gn:fcode":"PPL",
    "gn:population":5,
    "iso:country":"YE",
    "name:ara_x_preferred":[
        "\u0645\u0635\u064a\u062f\u0629"
    ],
    "name:eng_x_preferred":[
        "Musaydah"
    ],
    "name:eng_x_variant":[
        "Sar\u012b"
    ],
    "qs:name":"Mu\u015faydah",
    "qs:photos_9r":0,
    "qs:photos_sr":0,
    "qs:pop_sr":"1",
    "wof:name":"Mu\u015faydah",
    "wof:placetype":"locality",
    "wof:population":5
},
  "geometry": {"coordinates":[43.39437,16.73826],"type":"Point"}
}