{
  "type": "Feature",
  "properties": {
    "gn:admin1_code":"14.0",
    "gn:admin2_code":"2613.0",
    "gn:asciiname":"Al Hadba' Al Muhsin",
    "gn:country_code":"YE",
    "gn:dem":1056,
    "gn:feature_class":"P",
    "gn:feature_code":"PPL",
    "gn:name":"Al \u1e28adb\u0101\u2019 \u0100l Mu\u1e29sin",
    "gn:population":0,
    "gn:timezone":"Asia/Aden",
    "iso:country":"YE",
    "name:ara_x_preferred":[
        "\u0627\u0644\u062d\u062f\u0628\u0627\u0621 \u0627\u0644 \u0645\u062d\u0633\u0646"
    ],
    "name:und_x_variant":[
        "Al \u1e28adb\u0101\u2019",
        "Al \u1e28adb\u0101\u2019 \u0100l Mu\u1e29sin"
    ],
    "wof:name":"Al Hadba' Al Muhsin",
    "wof:placetype":"locality"
},
  "geometry": {"coordinates":[45.43774000000001,15.51006],"type":"Point"}
}