{
  "type": "Feature",
  "properties": {
    "gn:admin1_code":"25.0",
    "gn:admin2_code":"1511.0",
    "gn:asciiname":"Al `Armah",
    "gn:country_code":"YE",
    "gn:dem":1652,
    "gn:feature_class":"P",
    "gn:feature_code":"PPL",
    "gn:name":"Al \u2018Armah",
    "gn:population":0,
    "gn:timezone":"Asia/Aden",
    "iso:country":"YE",
    "name:und_x_variant":[
        "Al \u2018Armah"
    ],
    "wof:name":"Al `Armah",
    "wof:placetype":"locality"
},
  "geometry": {"coordinates":[44.08387000000001,13.46805],"type":"Point"}
}