{
  "type": "Feature",
  "properties": {
    "gn:admin1_code":"16.0",
    "gn:admin2_code":"2309.0",
    "gn:asciiname":"Bayt Umm Jalli",
    "gn:country_code":"YE",
    "gn:dem":2703,
    "gn:feature_class":"P",
    "gn:feature_code":"PPL",
    "gn:name":"Bayt Umm Jall\u012b",
    "gn:population":0,
    "gn:timezone":"Asia/Aden",
    "iso:country":"YE",
    "name:und_x_variant":[
        "Bayt Umm Jall\u012b"
    ],
    "wof:name":"Bayt Umm Jalli",
    "wof:placetype":"locality"
},
  "geometry": {"coordinates":[43.93801,15.19831],"type":"Point"}
}