{
  "type": "Feature",
  "properties": {
    "gn:admin1_code":"11.0",
    "gn:admin2_code":"2010.0",
    "gn:asciiname":"Shir`ah",
    "gn:country_code":"YE",
    "gn:dem":2482,
    "gn:feature_class":"P",
    "gn:feature_code":"PPL",
    "gn:name":"Shir\u2018ah",
    "gn:population":0,
    "gn:timezone":"Asia/Aden",
    "iso:country":"YE",
    "name:und_x_variant":[
        "Shir\u2018ah",
        "Shirah"
    ],
    "wof:name":"Shir`ah",
    "wof:placetype":"locality"
},
  "geometry": {"coordinates":[44.47462,14.39681],"type":"Point"}
}