{
  "type": "Feature",
  "properties": {
    "gn:admin1_code":"4.0",
    "gn:admin2_code":"1921.0",
    "gn:asciiname":"Az Zahir",
    "gn:cc2":"YE",
    "gn:country_code":"YE",
    "gn:dem":957,
    "gn:feature_class":"P",
    "gn:feature_code":"PPL",
    "gn:name":"Az Z\u0101hir",
    "gn:population":0,
    "gn:timezone":"Asia/Aden",
    "iso:country":"YE",
    "name:ara_x_preferred":[
        "Az Z\u0101hir"
    ],
    "name:und_x_variant":[
        "Al Z\u0101hir"
    ],
    "wof:name":"Az Zahir",
    "wof:placetype":"locality"
},
  "geometry": {"coordinates":[47.93333,15.23333],"type":"Point"}
}