{
  "type": "Feature",
  "properties": {
    "gn:admin1_code":"25.0",
    "gn:admin2_code":"1502.0",
    "gn:asciiname":"As Sulmayn",
    "gn:country_code":"YE",
    "gn:dem":1050,
    "gn:feature_class":"P",
    "gn:feature_code":"PPL",
    "gn:name":"As Sulmayn",
    "gn:population":0,
    "gn:timezone":"Asia/Aden",
    "iso:country":"YE",
    "name:ara_x_preferred":[
        "\u0627\u0644\u0633\u0644\u0645\u064a\u0646"
    ],
    "name:und_x_variant":[
        "As Salm\u012bn"
    ],
    "wof:name":"As Sulmayn",
    "wof:placetype":"locality"
},
  "geometry": {"coordinates":[43.93396,13.63504],"type":"Point"}
}