{
  "type": "Feature",
  "properties": {
    "gn:admin1_code":"5.0",
    "gn:admin2_code":"2110.0",
    "gn:asciiname":"Bi'r Ramadah",
    "gn:country_code":"YE",
    "gn:dem":1267,
    "gn:feature_class":"P",
    "gn:feature_code":"PPL",
    "gn:name":"Bi\u2019r Ram\u0101dah",
    "gn:population":0,
    "gn:timezone":"Asia/Aden",
    "iso:country":"YE",
    "name:und_x_variant":[
        "B\u012br Ram\u0101da",
        "Bi\u2019r Ram\u0101dah"
    ],
    "wof:name":"Bi'r Ramadah",
    "wof:placetype":"locality"
},
  "geometry": {"coordinates":[46.22832,14.45478],"type":"Point"}
}