{
  "type": "Feature",
  "properties": {
    "gn:admin1_code":"22.0",
    "gn:admin2_code":"1712.0",
    "gn:asciiname":"Al Ja`far",
    "gn:country_code":"YE",
    "gn:dem":457,
    "gn:feature_class":"P",
    "gn:feature_code":"PPL",
    "gn:name":"Al Ja\u2018far",
    "gn:population":0,
    "gn:timezone":"Asia/Aden",
    "iso:country":"YE",
    "name:und_x_variant":[
        "Al Ja\u2018far"
    ],
    "wof:name":"Al Ja`far",
    "wof:placetype":"locality"
},
  "geometry": {"coordinates":[43.27462,16.11201],"type":"Point"}
}