{
  "type": "Feature",
  "properties": {
    "gn:admin1_code":"20.0",
    "gn:admin2_code":"1414.0",
    "gn:asciiname":"Qaryat al Qadiri",
    "gn:country_code":"YE",
    "gn:dem":2115,
    "gn:feature_class":"P",
    "gn:feature_code":"PPL",
    "gn:name":"Qaryat al Q\u0101dir\u012b",
    "gn:population":0,
    "gn:timezone":"Asia/Aden",
    "iso:country":"YE",
    "name:und_x_variant":[
        "Qaryat al Q\u0101dir\u012b"
    ],
    "wof:name":"Qaryat al Qadiri",
    "wof:placetype":"locality"
},
  "geometry": {"coordinates":[44.862,14.42159],"type":"Point"}
}