{
  "type": "Feature",
  "properties": {
    "gn:country":"YE",
    "gn:fcode":"PPL",
    "gn:pop":3,
    "iso:country":"YE",
    "name:ara_x_preferred":[
        "Dh\u016b N\u0101shir"
    ],
    "name:ara_x_variant":[
        "\u0630\u0648 \u0646\u0627\u0634\u0631"
    ],
    "name:eng_x_preferred":[
        "DhU Nashir"
    ],
    "qs:name":"Dh\u016b N\u0101shir",
    "qs:photos_9r":0,
    "qs:photos_sr":0,
    "qs:pop_sr":"1",
    "wof:name":"Dh\u016b N\u0101shir",
    "wof:placetype":"locality",
    "wof:population":3
},
  "geometry": {"coordinates":[43.98371,16.7107],"type":"Point"}
}