{
  "type": "Feature",
  "properties": {
    "gn:country":"YE",
    "gn:fcode":"PPL",
    "gn:population":16,
    "iso:country":"YE",
    "name:ara_x_preferred":[
        "\u0627\u0644\u0645\u0631\u062a\u0641\u0639"
    ],
    "name:eng_x_preferred":[
        "Al Murtafi'"
    ],
    "name:eng_x_variant":[
        "Ar Ra\u1e11im"
    ],
    "qs_pg:aaroncc":"YE",
    "qs_pg:gn_country":"YE",
    "qs_pg:gn_fcode":"PPL",
    "qs_pg:gn_pop":16,
    "qs_pg:name":"Al Murtafi\u2018",
    "qs_pg:photos_9r":0,
    "qs_pg:photos_sr":0,
    "qs_pg:pop_sr":1,
    "qs_pg:qs_pg_placetype":"locality",
    "wof:name":"Al Murtafi\u2018",
    "wof:placetype":"locality",
    "wof:population":16
},
  "geometry": {"coordinates":[44.85075,16.11694],"type":"Point"}
}