{
  "type": "Feature",
  "properties": {
    "gn:admin1_code":"15.0",
    "gn:admin2_code":"2207.0",
    "gn:asciiname":"At Tawayil",
    "gn:country_code":"YE",
    "gn:dem":739,
    "gn:feature_class":"P",
    "gn:feature_code":"PPL",
    "gn:name":"A\u0163 \u0162aw\u0101yil",
    "gn:population":0,
    "gn:timezone":"Asia/Aden",
    "iso:country":"YE",
    "name:ara_x_preferred":[
        "\u0627\u0644\u0637\u0648\u0627\u064a\u0644"
    ],
    "name:und_x_variant":[
        "A\u0163 \u0162aw\u0101yil"
    ],
    "wof:name":"At Tawayil",
    "wof:placetype":"locality"
},
  "geometry": {"coordinates":[43.31,16.77127999999999],"type":"Point"}
}