{
  "type": "Feature",
  "properties": {
    "gn:admin1_code":"11.0",
    "gn:admin2_code":"2007.0",
    "gn:asciiname":"Sufal an Naqil",
    "gn:country_code":"YE",
    "gn:dem":456,
    "gn:feature_class":"P",
    "gn:feature_code":"PPL",
    "gn:name":"Suf\u0101l an Naq\u012bl",
    "gn:population":0,
    "gn:timezone":"Asia/Aden",
    "iso:country":"YE",
    "name:und_x_variant":[
        "Suf\u0101l an Naq\u012bl"
    ],
    "wof:name":"Sufal an Naqil",
    "wof:placetype":"locality"
},
  "geometry": {"coordinates":[43.55504000000001,14.28925],"type":"Point"}
}