{
  "type": "Feature",
  "properties": {
    "gn:admin1_code":"4.0",
    "gn:admin2_code":"1907.0",
    "gn:asciiname":"Al Bi'r",
    "gn:country_code":"YE",
    "gn:dem":963,
    "gn:feature_class":"P",
    "gn:feature_code":"PPL",
    "gn:name":"Al Bi\u2019r",
    "gn:population":0,
    "gn:timezone":"Asia/Aden",
    "iso:country":"YE",
    "name:ara_x_preferred":[
        "Al Bi\u2019r"
    ],
    "wof:name":"Al Bi'r",
    "wof:placetype":"locality"
},
  "geometry": {"coordinates":[48.55,15.95],"type":"Point"}
}