{
  "type": "Feature",
  "properties": {
    "gn:admin1_code":"24.0",
    "gn:admin2_code":"2512.0",
    "gn:asciiname":"Hawb al Hayd",
    "gn:country_code":"YE",
    "gn:dem":1429,
    "gn:feature_class":"P",
    "gn:feature_code":"PPL",
    "gn:name":"Hawb al \u1e28ayd",
    "gn:population":0,
    "gn:timezone":"Asia/Aden",
    "iso:country":"YE",
    "name:ara_x_preferred":[
        "\u0647\u0648\u0628 \u0627\u0644\u062d\u064a\u062f"
    ],
    "name:und_x_variant":[
        "Hawb al \u1e28ayd"
    ],
    "wof:name":"Hawb al Hayd",
    "wof:placetype":"locality"
},
  "geometry": {"coordinates":[44.19773,13.17277],"type":"Point"}
}