{
  "type": "Feature",
  "properties": {
    "gn:admin1_code":"23.0",
    "gn:admin2_code":"1107.0",
    "gn:asciiname":"Ribat al Farsh",
    "gn:country_code":"YE",
    "gn:dem":1589,
    "gn:feature_class":"P",
    "gn:feature_code":"PPL",
    "gn:name":"Rib\u0101\u0163 al Farsh",
    "gn:population":0,
    "gn:timezone":"Asia/Aden",
    "iso:country":"YE",
    "name:und_x_variant":[
        "Rib\u0101\u0163 al Farsh"
    ],
    "wof:name":"Ribat al Farsh",
    "wof:placetype":"locality"
},
  "geometry": {"coordinates":[44.17756,14.06336],"type":"Point"}
}