{
  "type": "Feature",
  "properties": {
    "gn:admin1_code":"14.0",
    "gn:admin2_code":"2607.0",
    "gn:asciiname":"Al Misnah al Harajah",
    "gn:country_code":"YE",
    "gn:dem":1271,
    "gn:feature_class":"P",
    "gn:feature_code":"PPL",
    "gn:name":"Al Misnah al Harajah",
    "gn:population":0,
    "gn:timezone":"Asia/Aden",
    "iso:country":"YE",
    "name:ara_x_preferred":[
        "\u0627\u0644\u0645\u0633\u0646\u0629 \u0627\u0644\u062d\u0631\u062c\u0629"
    ],
    "wof:name":"Al Misnah al Harajah",
    "wof:placetype":"locality"
},
  "geometry": {"coordinates":[45.28953,15.04742],"type":"Point"}
}