{
  "type": "Feature",
  "properties": {
    "gn:admin1_code":"25.0",
    "gn:admin2_code":"1506.0",
    "gn:asciiname":"As Sufaydah",
    "gn:country_code":"YE",
    "gn:dem":126,
    "gn:feature_class":"P",
    "gn:feature_code":"PPL",
    "gn:name":"As Sufaydah",
    "gn:population":0,
    "gn:timezone":"Asia/Aden",
    "iso:country":"YE",
    "wof:name":"As Sufaydah",
    "wof:placetype":"locality"
},
  "geometry": {"coordinates":[43.44003,13.30635],"type":"Point"}
}