{
  "type": "Feature",
  "properties": {
    "gn:gn_country":"YE",
    "gn:gn_fcode":"PPL",
    "gn:gn_pop":9,
    "gn:population":9,
    "iso:country":"YE",
    "name:ara_x_preferred":[
        "Al \u2018Ar\u016bq"
    ],
    "name:ara_x_variant":[
        "\u0627\u0644\u0639\u0631\u0648\u0642"
    ],
    "name:eng_x_preferred":[
        "Al 'ArUq"
    ],
    "name:eng_x_variant":[
        "Al Man\u1e29\u0101\u2019"
    ],
    "qs_pg:aaroncc":"YE",
    "qs_pg:gn_country":"YE",
    "qs_pg:gn_fcode":"PPL",
    "qs_pg:gn_pop":9,
    "qs_pg:name":"Al \u2018Ar\u016bq",
    "qs_pg:photos_9r":0,
    "qs_pg:photos_sr":0,
    "qs_pg:pop_sr":1,
    "qs_pg:qs_pg_placetype":"locality",
    "wof:name":"Al \u2018Ar\u016bq",
    "wof:placetype":"locality",
    "wof:population":9
},
  "geometry": {"coordinates":[44.49694,16.88791],"type":"Point"}
}