{
  "type": "Feature",
  "properties": {
    "gn:admin1_code":"20.0",
    "gn:admin2_code":"1416.0",
    "gn:asciiname":"Al Majhal",
    "gn:country_code":"YE",
    "gn:dem":2202,
    "gn:feature_class":"P",
    "gn:feature_code":"PPL",
    "gn:name":"Al Majhal",
    "gn:population":0,
    "gn:timezone":"Asia/Aden",
    "iso:country":"YE",
    "wof:name":"Al Majhal",
    "wof:placetype":"locality"
},
  "geometry": {"coordinates":[44.77402,14.40314],"type":"Point"}
}