{
  "type": "Feature",
  "properties": {
    "gn:country":"YE",
    "gn:fcode":"PPL",
    "gn:pop":2,
    "iso:country":"YE",
    "name:ara_x_preferred":[
        "\u0627\u0644\u0645\u0642\u0635\u0631\u0629"
    ],
    "name:eng_x_preferred":[
        "Al Maqsirah"
    ],
    "name:eng_x_variant":[
        "Al Ma\u1e29jan"
    ],
    "qs:name":"Al Maq\u015firah",
    "qs:photos_9r":0,
    "qs:photos_sr":0,
    "qs:pop_sr":"1",
    "wof:name":"Al Maq\u015firah",
    "wof:placetype":"locality",
    "wof:population":2
},
  "geometry": {"coordinates":[45.18836,14.97719],"type":"Point"}
}