{
  "type": "Feature",
  "properties": {
    "gn:admin1_code":"8.0",
    "gn:admin2_code":"1818.0",
    "gn:asciiname":"Suq al Khamis",
    "gn:country_code":"YE",
    "gn:dem":598,
    "gn:feature_class":"P",
    "gn:feature_code":"PPL",
    "gn:name":"S\u016bq al Kham\u012bs",
    "gn:population":0,
    "gn:timezone":"Asia/Aden",
    "iso:country":"YE",
    "name:und_x_variant":[
        "S\u016bq al Kham\u012bs"
    ],
    "wof:name":"Suq al Khamis",
    "wof:placetype":"locality"
},
  "geometry": {"coordinates":[43.74008,14.0564],"type":"Point"}
}