{
  "type": "Feature",
  "properties": {
    "gn:admin1_code":"22.0",
    "gn:admin2_code":"1727.0",
    "gn:asciiname":"Al Hawmar",
    "gn:country_code":"YE",
    "gn:dem":1500,
    "gn:feature_class":"P",
    "gn:feature_code":"PPL",
    "gn:name":"Al \u1e28awmar",
    "gn:population":0,
    "gn:timezone":"Asia/Aden",
    "iso:country":"YE",
    "name:und_x_variant":[
        "Al \u1e28awmar"
    ],
    "wof:name":"Al Hawmar",
    "wof:placetype":"locality"
},
  "geometry": {"coordinates":[43.57551,15.58705],"type":"Point"}
}