{
  "type": "Feature",
  "properties": {
    "gn:country":"YE",
    "gn:fcode":"PPL",
    "gn:pop":8,
    "iso:country":"YE",
    "name:ara_x_preferred":[
        "\u0627\u0644\u0628\u064a\u0627\u062f\u0629"
    ],
    "name:eng_x_preferred":[
        "Al Bayadah"
    ],
    "name:eng_x_variant":[
        "Lujj Khayshah"
    ],
    "qs:name":"Al Bay\u0101dah",
    "qs:photos_9r":0,
    "qs:photos_sr":0,
    "qs:pop_sr":"1",
    "wd:wordcount":48,
    "wof:name":"Al Bay\u0101dah",
    "wof:placetype":"locality",
    "wof:population":8
},
  "geometry": {"coordinates":[44.19659,16.92987],"type":"Point"}
}