{
  "type": "Feature",
  "properties": {
    "gn:country":"YE",
    "gn:fcode":"PPL",
    "gn:pop":6,
    "iso:country":"YE",
    "name:ara_x_preferred":[
        "\u0646\u0635\u064a\u0631"
    ],
    "name:eng_x_preferred":[
        "Nasir"
    ],
    "name:eng_x_variant":[
        "Al \u2018A\u015ff\u016br\u012byah"
    ],
    "qs:name":"Na\u015f\u012br",
    "qs:photos_9r":0,
    "qs:photos_sr":0,
    "qs:pop_sr":"1",
    "wof:name":"Na\u015f\u012br",
    "wof:placetype":"locality",
    "wof:population":6
},
  "geometry": {"coordinates":[45.28849,14.97636],"type":"Point"}
}