{
  "type": "Feature",
  "properties": {
    "gn:admin1_code":"11.0",
    "gn:admin2_code":"2001.0",
    "gn:asciiname":"Ash Shi`b",
    "gn:country_code":"YE",
    "gn:dem":2341,
    "gn:feature_class":"P",
    "gn:feature_code":"PPL",
    "gn:name":"Ash Shi\u2018b",
    "gn:population":0,
    "gn:timezone":"Asia/Aden",
    "iso:country":"YE",
    "name:ara_x_preferred":[
        "Ash Shi\u2018b"
    ],
    "name:nno_x_preferred":[
        "Ash Shi`b"
    ],
    "wof:name":"Ash Shi`b",
    "wof:placetype":"locality"
},
  "geometry": {"coordinates":[44.39011,14.90589],"type":"Point"}
}