{
  "type": "Feature",
  "properties": {
    "gn:admin1_code":"22.0",
    "gn:admin2_code":"1724.0",
    "gn:asciiname":"Al Mazahirah",
    "gn:country_code":"YE",
    "gn:dem":373,
    "gn:feature_class":"P",
    "gn:feature_code":"PPL",
    "gn:name":"Al Maz\u0101hirah",
    "gn:population":0,
    "gn:timezone":"Asia/Aden",
    "iso:country":"YE",
    "name:und_x_variant":[
        "Al Maz\u0101hirah"
    ],
    "wof:name":"Al Mazahirah",
    "wof:placetype":"locality"
},
  "geometry": {"coordinates":[43.40515,15.65904],"type":"Point"}
}