{
  "type": "Feature",
  "properties": {
    "gn:admin1_code":"8.0",
    "gn:admin2_code":"1808.0",
    "gn:asciiname":"'Abd Allah Mallah",
    "gn:country_code":"YE",
    "gn:dem":101,
    "gn:feature_class":"P",
    "gn:feature_code":"PPL",
    "gn:name":"\u2018Abd All\u0101h Mall\u0101\u1e29",
    "gn:population":0,
    "gn:timezone":"Asia/Aden",
    "iso:country":"YE",
    "name:ara_x_preferred":[
        "\u0639\u0628\u062f \u0627\u0644\u0644\u0647 \u0645\u0644\u0627\u062d"
    ],
    "name:und_x_variant":[
        "\u2018Abd All\u0101h Mall\u0101\u1e29"
    ],
    "wof:name":"'Abd Allah Mallah",
    "wof:placetype":"locality"
},
  "geometry": {"coordinates":[43.14362,15.3213],"type":"Point"}
}