{
  "type": "Feature",
  "properties": {
    "gn:admin1_code":"23.0",
    "gn:admin2_code":"1107.0",
    "gn:asciiname":"Al `Ahab",
    "gn:country_code":"YE",
    "gn:dem":2082,
    "gn:feature_class":"P",
    "gn:feature_code":"PPL",
    "gn:name":"Al \u2018Ah\u0101b",
    "gn:population":0,
    "gn:timezone":"Asia/Aden",
    "iso:country":"YE",
    "name:ara_x_preferred":[
        "Al \u2018Ah\u0101b"
    ],
    "wof:name":"Al `Ahab",
    "wof:placetype":"locality"
},
  "geometry": {"coordinates":[44.23209,14.1422],"type":"Point"}
}