{
  "type": "Feature",
  "properties": {
    "gn:admin1_code":"23.0",
    "gn:admin2_code":"1101.0",
    "gn:asciiname":"Al Huraqah",
    "gn:country_code":"YE",
    "gn:dem":1797,
    "gn:feature_class":"P",
    "gn:feature_code":"PPL",
    "gn:name":"Al \u1e28uraqah",
    "gn:population":0,
    "gn:timezone":"Asia/Aden",
    "iso:country":"YE",
    "name:ara_x_preferred":[
        "\u0627\u0644\u062d\u0631\u0642\u0629"
    ],
    "name:und_x_variant":[
        "Al \u1e28uraqah"
    ],
    "wof:name":"Al Huraqah",
    "wof:placetype":"locality"
},
  "geometry": {"coordinates":[44.20112,14.25127],"type":"Point"}
}