{
  "type": "Feature",
  "properties": {
    "gn:admin1_code":"15.0",
    "gn:admin2_code":"2201.0",
    "gn:asciiname":"Qahar at Tijar",
    "gn:country_code":"YE",
    "gn:dem":2108,
    "gn:feature_class":"P",
    "gn:feature_code":"PPL",
    "gn:name":"Qahar at Tij\u0101r",
    "gn:population":0,
    "gn:timezone":"Asia/Aden",
    "iso:country":"YE",
    "name:ara_x_preferred":[
        "\u0642\u0647\u0631 \u0627\u0644\u062a\u062c\u0627\u0631"
    ],
    "name:und_x_variant":[
        "Qahar at Tij\u0101r"
    ],
    "wof:name":"Qahar at Tijar",
    "wof:placetype":"locality"
},
  "geometry": {"coordinates":[43.43373,17.33225],"type":"Point"}
}