{
  "type": "Feature",
  "properties": {
    "gn:admin1_code":"14.0",
    "gn:admin2_code":"2607.0",
    "gn:asciiname":"Badw al 'Ard",
    "gn:country_code":"YE",
    "gn:dem":1199,
    "gn:feature_class":"P",
    "gn:feature_code":"PPLL",
    "gn:name":"Badw al \u2018Ar\u1e11",
    "gn:population":0,
    "gn:timezone":"Asia/Aden",
    "iso:country":"YE",
    "name:ara_x_preferred":[
        "\u0628\u062f\u0648 \u0627\u0644\u0639\u0631\u0636"
    ],
    "name:und_x_variant":[
        "Badw al \u2018Ar\u1e11"
    ],
    "wof:name":"Badw al 'Ard",
    "wof:placetype":"locality"
},
  "geometry": {"coordinates":[45.41458,15.11535],"type":"Point"}
}