{
  "type": "Feature",
  "properties": {
    "gn:country":"YE",
    "gn:fcode":"PPL",
    "gn:population":3,
    "iso:country":"YE",
    "name:ara_x_preferred":[
        "\u0627\u0644 \u0635\u0644\u0627\u062d"
    ],
    "name:eng_x_preferred":[
        "Al Salah"
    ],
    "name:eng_x_variant":[
        "Al Wahidah"
    ],
    "qs:name":"\u0100l \u015eal\u0101\u1e29",
    "qs:photos_9r":0,
    "qs:photos_sr":0,
    "qs:pop_sr":"1",
    "wof:name":"\u0100l \u015eal\u0101\u1e29",
    "wof:placetype":"locality",
    "wof:population":3
},
  "geometry": {"coordinates":[43.35903,16.75253],"type":"Point"}
}