{
  "type": "Feature",
  "properties": {
    "gn:country":"YE",
    "gn:fcode":"PPL",
    "gn:pop":1,
    "iso:country":"YE",
    "name:ara_x_preferred":[
        "\u063a\u0627\u0631\u0628 \u0627\u0644\u0633\u0646\u0627\u0645"
    ],
    "name:eng_x_preferred":[
        "Gharib As Sinnam"
    ],
    "name:eng_x_variant":[
        "Al Qaz\u2018\u012b"
    ],
    "qs:name":"Gh\u0101rib as Sinn\u0101m",
    "qs:photos_9r":0,
    "qs:photos_sr":0,
    "qs:pop_sr":"1",
    "wof:name":"Gh\u0101rib as Sinn\u0101m",
    "wof:placetype":"locality",
    "wof:population":1
},
  "geometry": {"coordinates":[43.31506,16.65545],"type":"Point"}
}