{
  "type": "Feature",
  "properties": {
    "gn:admin1_code":"16.0",
    "gn:admin2_code":"2316.0",
    "gn:asciiname":"Hajbah",
    "gn:country_code":"YE",
    "gn:dem":2349,
    "gn:feature_class":"P",
    "gn:feature_code":"PPL",
    "gn:name":"\u1e28ajbah",
    "gn:population":0,
    "gn:timezone":"Asia/Aden",
    "iso:country":"YE",
    "name:und_x_variant":[
        "\u1e28ajbah"
    ],
    "wof:name":"Hajbah",
    "wof:placetype":"locality"
},
  "geometry": {"coordinates":[44.42568,15.14732],"type":"Point"}
}