{
  "type": "Feature",
  "properties": {
    "gn:admin1_code":"14.0",
    "gn:admin2_code":"2610.0",
    "gn:asciiname":"Kawlat Hidah",
    "gn:country_code":"YE",
    "gn:dem":1704,
    "gn:feature_class":"P",
    "gn:feature_code":"PPL",
    "gn:name":"Kawlat \u1e28i\u1e11ah",
    "gn:population":0,
    "gn:timezone":"Asia/Aden",
    "iso:country":"YE",
    "name:und_x_variant":[
        "Kawlat \u1e28i\u1e11ah"
    ],
    "wof:name":"Kawlat Hidah",
    "wof:placetype":"locality"
},
  "geometry": {"coordinates":[45.18492,14.67524],"type":"Point"}
}