{
  "type": "Feature",
  "properties": {
    "gn:admin1_code":"16.0",
    "gn:admin2_code":"2307.0",
    "gn:asciiname":"Adam",
    "gn:country_code":"YE",
    "gn:dem":2565,
    "gn:feature_class":"P",
    "gn:feature_code":"PPL",
    "gn:name":"Adam",
    "gn:population":0,
    "gn:timezone":"Asia/Aden",
    "iso:country":"YE",
    "wof:name":"Adam",
    "wof:placetype":"locality"
},
  "geometry": {"coordinates":[44.05396,15.19737],"type":"Point"}
}