{
  "type": "Feature",
  "properties": {
    "gn:country":"YE",
    "gn:fcode":"PPL",
    "gn:pop":2,
    "iso:country":"YE",
    "name:ara_x_preferred":[
        "\u062c\u0628\u0648\u0628 \u0628\u0646 \u062d\u0634\u062d\u0634"
    ],
    "name:eng_x_preferred":[
        "JibUb Bin Hashhash"
    ],
    "name:unk_x_variant":[
        "Jab\u016bb Bin \u1e28ash\u1e29ash"
    ],
    "qs:name":"Jib\u016bb Bin \u1e28ash\u1e29ash",
    "qs:photos_9r":0,
    "qs:photos_sr":0,
    "qs:pop_sr":"1",
    "wof:name":"Jib\u016bb Bin \u1e28ash\u1e29ash",
    "wof:placetype":"locality",
    "wof:population":2
},
  "geometry": {"coordinates":[44.87652,16.9357],"type":"Point"}
}