{
  "type": "Feature",
  "properties": {
    "gn:country":"YE",
    "gn:fcode":"PPL",
    "gn:pop":1,
    "iso:country":"YE",
    "name:ara_x_preferred":[
        "\u0644\u0628\u0648\u0629"
    ],
    "name:eng_x_preferred":[
        "Labwah"
    ],
    "name:eng_x_variant":[
        "Al Mawdinah"
    ],
    "qs:name":"Labwah",
    "qs:photos_9r":0,
    "qs:photos_sr":0,
    "qs:pop_sr":"1",
    "wof:name":"Labwah",
    "wof:placetype":"locality",
    "wof:population":1
},
  "geometry": {"coordinates":[43.28784,17.39551],"type":"Point"}
}