{
  "type": "Feature",
  "properties": {
    "gn:country":"YE",
    "gn:fcode":"PPL",
    "gn:pop":6,
    "iso:country":"YE",
    "name:ara_x_preferred":[
        "\u0627\u0644\u062e\u0627\u0644\u0641\u0629"
    ],
    "name:eng_x_preferred":[
        "Al Khalifah"
    ],
    "qs:name":"Al Kh\u0101lifah",
    "qs:photos_9r":0,
    "qs:photos_sr":0,
    "qs:pop_sr":"1",
    "wof:name":"Al Kh\u0101lifah",
    "wof:placetype":"locality",
    "wof:population":6
},
  "geometry": {"coordinates":[45.3387,14.64946],"type":"Point"}
}