{
  "type": "Feature",
  "properties": {
    "gn:admin1_code":"23.0",
    "gn:admin2_code":"1102.0",
    "gn:asciiname":"Al Jarda'",
    "gn:country_code":"YE",
    "gn:dem":2617,
    "gn:feature_class":"P",
    "gn:feature_code":"PPL",
    "gn:name":"Al Jard\u0101\u2019",
    "gn:population":0,
    "gn:timezone":"Asia/Aden",
    "iso:country":"YE",
    "name:und_x_variant":[
        "Al Jard\u0101\u2019"
    ],
    "wof:name":"Al Jarda'",
    "wof:placetype":"locality"
},
  "geometry": {"coordinates":[44.37876,14.24734],"type":"Point"}
}