{
  "type": "Feature",
  "properties": {
    "gn:admin1_code":"18.0",
    "gn:admin2_code":"3006.0",
    "gn:asciiname":"Lakmat ad Darb",
    "gn:country_code":"YE",
    "gn:dem":1378,
    "gn:feature_class":"P",
    "gn:feature_code":"PPL",
    "gn:name":"Lakmat ad Darb",
    "gn:population":0,
    "gn:timezone":"Asia/Aden",
    "iso:country":"YE",
    "name:und_x_variant":[
        "Ad Darb"
    ],
    "wof:name":"Lakmat ad Darb",
    "wof:placetype":"locality"
},
  "geometry": {"coordinates":[44.75,13.78303],"type":"Point"}
}