{
  "type": "Feature",
  "properties": {
    "gn:country":"YE",
    "gn:fcode":"PPL",
    "gn:pop":3,
    "iso:country":"YE",
    "name:ara_x_preferred":[
        "\u0627\u0644\u0639\u0645\u0627\u0634\u064a\u0629"
    ],
    "name:eng_x_preferred":[
        "Al 'Amashiyah"
    ],
    "name:unk_x_variant":[
        "\u0627\u0644\u0639\u0645\u0627\u0634\u064a\u0629"
    ],
    "qs:name":"Al \u2018Am\u0101sh\u012byah",
    "qs:photos_9r":0,
    "qs:photos_sr":0,
    "qs:pop_sr":"1",
    "wof:name":"Al \u2018Am\u0101sh\u012byah",
    "wof:placetype":"locality",
    "wof:population":3
},
  "geometry": {"coordinates":[42.92419,16.24414],"type":"Point"}
}