{
  "type": "Feature",
  "properties": {
    "gn:admin1_code":"18.0",
    "gn:admin2_code":"3006.0",
    "gn:asciiname":"Humayrah",
    "gn:cc2":"YE",
    "gn:country_code":"YE",
    "gn:dem":1649,
    "gn:feature_class":"P",
    "gn:feature_code":"PPL",
    "gn:name":"\u1e28umayrah",
    "gn:population":0,
    "gn:timezone":"Asia/Aden",
    "iso:country":"YE",
    "name:und_x_variant":[
        "Hamaira",
        "\u1e28umayrah"
    ],
    "wof:name":"Humayrah",
    "wof:placetype":"locality"
},
  "geometry": {"coordinates":[44.71667,13.71667],"type":"Point"}
}