{
  "type": "Feature",
  "properties": {
    "gn:admin1_code":"25.0",
    "gn:admin2_code":"1504.0",
    "gn:asciiname":"Halyah",
    "gn:country_code":"YE",
    "gn:dem":861,
    "gn:feature_class":"P",
    "gn:feature_code":"PPL",
    "gn:name":"\u1e28alyah",
    "gn:population":0,
    "gn:timezone":"Asia/Aden",
    "iso:country":"YE",
    "name:und_x_variant":[
        "\u1e28alyah"
    ],
    "wof:name":"Halyah",
    "wof:placetype":"locality"
},
  "geometry": {"coordinates":[43.73613,13.80967],"type":"Point"}
}