{
  "type": "Feature",
  "properties": {
    "gn:country":"YE",
    "gn:fcode":"PPL",
    "gn:population":7,
    "iso:country":"YE",
    "name:ara_x_preferred":[
        "\u0627\u0644\u0645\u062f\u0641\u0631"
    ],
    "name:eng_x_preferred":[
        "Al Madfir"
    ],
    "name:eng_x_variant":[
        "Al Ba\u1e29irah"
    ],
    "qs:name":"Al Madfir",
    "qs:photos_9r":0,
    "qs:photos_sr":0,
    "qs:pop_sr":"1",
    "wof:name":"Al Madfir",
    "wof:placetype":"locality",
    "wof:population":7
},
  "geometry": {"coordinates":[43.79693,16.87164],"type":"Point"}
}