{
  "type": "Feature",
  "properties": {
    "gn:admin1_code":"15.0",
    "gn:admin2_code":"2201.0",
    "gn:asciiname":"At Tawf",
    "gn:country_code":"YE",
    "gn:dem":2253,
    "gn:feature_class":"P",
    "gn:feature_code":"PPL",
    "gn:name":"A\u0163 \u0162awf",
    "gn:population":0,
    "gn:timezone":"Asia/Aden",
    "iso:country":"YE",
    "name:und_x_variant":[
        "A\u0163 \u0162awf"
    ],
    "wof:name":"At Tawf",
    "wof:placetype":"locality"
},
  "geometry": {"coordinates":[43.42811,17.39818],"type":"Point"}
}