{
  "type": "Feature",
  "properties": {
    "gn:admin1_code":"16.0",
    "gn:admin2_code":"2302.0",
    "gn:asciiname":"Ghawlat Zindan",
    "gn:country_code":"YE",
    "gn:dem":2372,
    "gn:feature_class":"P",
    "gn:feature_code":"PPL",
    "gn:name":"Ghawlat Zind\u0101n",
    "gn:population":0,
    "gn:timezone":"Asia/Aden",
    "iso:country":"YE",
    "name:und_x_variant":[
        "Ghawlat Zind\u0101n"
    ],
    "wof:name":"Ghawlat Zindan",
    "wof:placetype":"locality"
},
  "geometry": {"coordinates":[44.23896,15.70826],"type":"Point"}
}