{
  "type": "Feature",
  "properties": {
    "gn:admin1_code":"8.0",
    "gn:admin2_code":"1824.0",
    "gn:asciiname":"Mahwa al Jatim",
    "gn:country_code":"YE",
    "gn:dem":123,
    "gn:feature_class":"P",
    "gn:feature_code":"PPL",
    "gn:name":"Ma\u1e29w\u00e1 al Jat\u012bm",
    "gn:population":0,
    "gn:timezone":"Asia/Aden",
    "iso:country":"YE",
    "name:und_x_variant":[
        "Ma\u1e29w\u00e1 al Jat\u012bm",
        "Bayt al Jat\u012bm"
    ],
    "wof:name":"Mahwa al Jatim",
    "wof:placetype":"locality"
},
  "geometry": {"coordinates":[43.34397,14.20393],"type":"Point"}
}