{
  "type": "Feature",
  "properties": {
    "gn:admin1_code":"23.0",
    "gn:admin2_code":"1102.0",
    "gn:asciiname":"Al Mahfad as Safil",
    "gn:country_code":"YE",
    "gn:dem":2720,
    "gn:feature_class":"P",
    "gn:feature_code":"PPL",
    "gn:name":"Al Ma\u1e29fad as S\u0101fil",
    "gn:population":0,
    "gn:timezone":"Asia/Aden",
    "iso:country":"YE",
    "name:ara_x_preferred":[
        "\u0627\u0644\u0645\u062d\u0641\u062f \u0627\u0644\u0633\u0627\u0641\u0644"
    ],
    "name:und_x_variant":[
        "Al Ma\u1e29fad as S\u0101fil"
    ],
    "wof:name":"Al Mahfad as Safil",
    "wof:placetype":"locality"
},
  "geometry": {"coordinates":[44.19961,14.34206],"type":"Point"}
}