{
  "type": "Feature",
  "properties": {
    "gn:admin1_code":"25.0",
    "gn:admin2_code":"1504.0",
    "gn:asciiname":"Wajanat",
    "gn:country_code":"YE",
    "gn:dem":1410,
    "gn:feature_class":"P",
    "gn:feature_code":"PPL",
    "gn:name":"Wajan\u0101t",
    "gn:population":0,
    "gn:timezone":"Asia/Aden",
    "iso:country":"YE",
    "name:ara_x_preferred":[
        "\u0623\u062c\u0646\u0627\u062a"
    ],
    "name:und_x_variant":[
        "Wajan\u0101t",
        "Ajn\u0101t"
    ],
    "wof:name":"Wajanat",
    "wof:placetype":"locality"
},
  "geometry": {"coordinates":[43.79598,13.72431],"type":"Point"}
}