{
  "type": "Feature",
  "properties": {
    "gn:admin1_code":"10.0",
    "gn:admin2_code":"2704.0",
    "gn:asciiname":"As Siyalah",
    "gn:country_code":"YE",
    "gn:dem":1300,
    "gn:feature_class":"P",
    "gn:feature_code":"PPL",
    "gn:name":"As Siy\u0101lah",
    "gn:population":0,
    "gn:timezone":"Asia/Aden",
    "iso:country":"YE",
    "name:und_x_variant":[
        "As Siy\u0101lah"
    ],
    "wof:name":"As Siyalah",
    "wof:placetype":"locality"
},
  "geometry": {"coordinates":[43.41333,15.5304],"type":"Point"}
}