{
  "type": "Feature",
  "properties": {
    "gn:admin1_code":"23.0",
    "gn:admin2_code":"1101.0",
    "gn:asciiname":"Sabal Aranib",
    "gn:country_code":"YE",
    "gn:dem":985,
    "gn:feature_class":"P",
    "gn:feature_code":"PPL",
    "gn:name":"Sabal Ar\u0101nib",
    "gn:population":0,
    "gn:timezone":"Asia/Aden",
    "iso:country":"YE",
    "name:ara_x_preferred":[
        "\u0633\u0628\u0644 \u0623\u0631\u0627\u0646\u0628"
    ],
    "name:und_x_variant":[
        "Sabal Ar\u0101nib"
    ],
    "wof:name":"Sabal Aranib",
    "wof:placetype":"locality"
},
  "geometry": {"coordinates":[44.00277,14.25464],"type":"Point"}
}