{
  "type": "Feature",
  "properties": {
    "gn:country":"YE",
    "gn:fcode":"PPL",
    "gn:population":18,
    "iso:country":"YE",
    "name:ara_x_preferred":[
        "\u0627\u0644\u0645\u062d\u062c\u0644"
    ],
    "qs:name":"Al Ma\u1e29jal",
    "qs:photos_9r":0,
    "qs:photos_sr":0,
    "qs:pop_sr":"1",
    "wof:name":"Al Ma\u1e29jal",
    "wof:placetype":"locality",
    "wof:population":18
},
  "geometry": {"coordinates":[43.67859,16.72511],"type":"Point"}
}