{
  "type": "Feature",
  "properties": {
    "gn:admin1_code":"19.0",
    "gn:admin2_code":"2903.0",
    "gn:asciiname":"Falhan",
    "gn:country_code":"YE",
    "gn:dem":1519,
    "gn:feature_class":"P",
    "gn:feature_code":"PPL",
    "gn:name":"Fal\u1e29\u0101n",
    "gn:population":0,
    "gn:timezone":"Asia/Aden",
    "iso:country":"YE",
    "name:ara_x_preferred":[
        "\u0641\u0644\u062d\u0627\u0646"
    ],
    "name:und_x_variant":[
        "Fal\u1e29\u0101n"
    ],
    "wof:name":"Falhan",
    "wof:placetype":"locality"
},
  "geometry": {"coordinates":[43.87225,16.37255],"type":"Point"}
}