{
  "type": "Feature",
  "properties": {
    "gn:admin1_code":"16.0",
    "gn:admin2_code":"2305.0",
    "gn:asciiname":"Silmah",
    "gn:country_code":"YE",
    "gn:dem":2608,
    "gn:feature_class":"P",
    "gn:feature_code":"PPL",
    "gn:name":"Silmah",
    "gn:population":0,
    "gn:timezone":"Asia/Aden",
    "iso:country":"YE",
    "wof:name":"Silmah",
    "wof:placetype":"locality"
},
  "geometry": {"coordinates":[44.44456,15.36009],"type":"Point"}
}