{
  "type": "Feature",
  "properties": {
    "gn:admin1_code":"22.0",
    "gn:admin2_code":"1717.0",
    "gn:asciiname":"Bayt `Ibash",
    "gn:country_code":"YE",
    "gn:dem":941,
    "gn:feature_class":"P",
    "gn:feature_code":"PPL",
    "gn:name":"Bayt \u2018Ib\u0101sh",
    "gn:population":0,
    "gn:timezone":"Asia/Aden",
    "iso:country":"YE",
    "name:und_x_variant":[
        "Bayt \u2018Ib\u0101sh"
    ],
    "wof:name":"Bayt `Ibash",
    "wof:placetype":"locality"
},
  "geometry": {"coordinates":[43.64399,15.84316],"type":"Point"}
}