{
  "type": "Feature",
  "properties": {
    "gn:admin1_code":"8.0",
    "gn:admin2_code":"1817.0",
    "gn:asciiname":"Al Qahaliyah",
    "gn:country_code":"YE",
    "gn:dem":81,
    "gn:feature_class":"P",
    "gn:feature_code":"PPL",
    "gn:name":"Al Qa\u1e29al\u012byah",
    "gn:population":0,
    "gn:timezone":"Asia/Aden",
    "iso:country":"YE",
    "name:und_x_variant":[
        "Al Qa\u1e29al\u012byah"
    ],
    "wof:name":"Al Qahaliyah",
    "wof:placetype":"locality"
},
  "geometry": {"coordinates":[43.21308,14.56906],"type":"Point"}
}