{
  "type": "Feature",
  "properties": {
    "gn:admin1_code":"22.0",
    "gn:admin2_code":"1727.0",
    "gn:asciiname":"Bayt Rassam",
    "gn:country_code":"YE",
    "gn:dem":1516,
    "gn:feature_class":"P",
    "gn:feature_code":"PPL",
    "gn:name":"Bayt Rass\u0101m",
    "gn:population":0,
    "gn:timezone":"Asia/Aden",
    "iso:country":"YE",
    "name:ara_x_preferred":[
        "\u0628\u064a\u062a \u0631\u0633\u0627\u0645"
    ],
    "name:und_x_variant":[
        "Bayt Rass\u0101m"
    ],
    "wof:name":"Bayt Rassam",
    "wof:placetype":"locality"
},
  "geometry": {"coordinates":[43.58458,15.58476],"type":"Point"}
}