{
  "type": "Feature",
  "properties": {
    "gn:country":"YE",
    "gn:fcode":"PPL",
    "gn:pop":5,
    "iso:country":"YE",
    "name:ara_x_preferred":[
        "\u0627\u0644\u0645\u062e\u0644\u0648\u0637\u0629"
    ],
    "name:eng_x_preferred":[
        "Al MakhlUtah"
    ],
    "name:eng_x_variant":[
        "Bin \u1e28alw\u0101n"
    ],
    "qs:name":"Al Makhl\u016b\u0163ah",
    "qs:photos_9r":0,
    "qs:photos_sr":0,
    "qs:pop_sr":"1",
    "wof:name":"Al Makhl\u016b\u0163ah",
    "wof:placetype":"locality",
    "wof:population":5
},
  "geometry": {"coordinates":[43.3078,16.18227],"type":"Point"}
}