{
  "type": "Feature",
  "properties": {
    "gn:admin1_code":"16.0",
    "gn:admin2_code":"2301.0",
    "gn:asciiname":"Bayt ad Dahak",
    "gn:country_code":"YE",
    "gn:dem":2257,
    "gn:feature_class":"P",
    "gn:feature_code":"PPL",
    "gn:name":"Bayt a\u1e11 \u1e10a\u1e29\u0101k",
    "gn:population":0,
    "gn:timezone":"Asia/Aden",
    "iso:country":"YE",
    "name:und_x_variant":[
        "Bayt a\u1e11 \u1e10a\u1e29\u0101k"
    ],
    "wof:name":"Bayt ad Dahak",
    "wof:placetype":"locality"
},
  "geometry": {"coordinates":[44.11881,15.44209],"type":"Point"}
}