{
  "type": "Feature",
  "properties": {
    "gn:country":"YE",
    "gn:fcode":"PPL",
    "gn:pop":6,
    "iso:country":"YE",
    "name:ara_x_preferred":[
        "\u0627\u0644\u0634\u0631\u0641"
    ],
    "qs:name":"Ash Sharf",
    "qs:photos_9r":0,
    "qs:photos_sr":0,
    "qs:pop_sr":"1",
    "wof:name":"Ash Sharf",
    "wof:placetype":"locality",
    "wof:population":6
},
  "geometry": {"coordinates":[43.40028,16.33231],"type":"Point"}
}