{
  "type": "Feature",
  "properties": {
    "gn:admin1_code":"25.0",
    "gn:admin2_code":"1502.0",
    "gn:asciiname":"Wadi al Hajib",
    "gn:country_code":"YE",
    "gn:dem":1553,
    "gn:feature_class":"P",
    "gn:feature_code":"PPL",
    "gn:name":"W\u0101d\u012b al \u1e28\u0101jib",
    "gn:population":0,
    "gn:timezone":"Asia/Aden",
    "iso:country":"YE",
    "name:und_x_variant":[
        "W\u0101d\u012b al \u1e28\u0101jib"
    ],
    "wof:name":"Wadi al Hajib",
    "wof:placetype":"locality"
},
  "geometry": {"coordinates":[44.0405,13.74116],"type":"Point"}
}