{
  "type": "Feature",
  "properties": {
    "gn:admin1_code":"15.0",
    "gn:admin2_code":"2210.0",
    "gn:asciiname":"Duba`ah",
    "gn:country_code":"YE",
    "gn:dem":1512,
    "gn:feature_class":"P",
    "gn:feature_code":"PPL",
    "gn:name":"\u1e10ub\u0101\u2018ah",
    "gn:population":0,
    "gn:timezone":"Asia/Aden",
    "iso:country":"YE",
    "name:ara_x_preferred":[
        "\u0636\u0628\u0627\u0639\u0629"
    ],
    "name:und_x_variant":[
        "\u1e10ub\u0101\u2018ah"
    ],
    "wof:name":"Duba`ah",
    "wof:placetype":"locality"
},
  "geometry": {"coordinates":[43.37435,17.12231],"type":"Point"}
}