{
  "type": "Feature",
  "properties": {
    "gn:admin1_code":"8.0",
    "gn:admin2_code":"1802.0",
    "gn:asciiname":"Bani al Maghas",
    "gn:country_code":"YE",
    "gn:dem":28,
    "gn:feature_class":"P",
    "gn:feature_code":"PPL",
    "gn:name":"Ban\u012b al Magh\u0101\u015f",
    "gn:population":0,
    "gn:timezone":"Asia/Aden",
    "iso:country":"YE",
    "name:ara_x_preferred":[
        "\u0628\u0646\u064a \u0627\u0644\u0645\u063a\u0627\u0635"
    ],
    "name:und_x_variant":[
        "Ban\u012b al Magh\u0101\u015f"
    ],
    "wof:name":"Bani al Maghas",
    "wof:placetype":"locality"
},
  "geometry": {"coordinates":[42.82054,15.67438],"type":"Point"}
}