{
  "type": "Feature",
  "properties": {
    "gn:country":"YE",
    "gn:fcode":"PPLX",
    "gn:pop":44,
    "iso:country":"YE",
    "name:ara_x_preferred":[
        "\u0628\u0626\u0631 \u062d\u0637\u0628\u0646"
    ],
    "qs:name":"Bi\u2019r \u1e28a\u0163aban",
    "qs:photos_9r":0,
    "qs:photos_sr":0,
    "qs:pop_sr":"1",
    "wof:name":"Bi\u2019r \u1e28a\u0163aban",
    "wof:placetype":"neighbourhood",
    "wof:population":44
},
  "geometry": {"coordinates":[43.7711,16.93678],"type":"Point"}
}