{
  "type": "Feature",
  "properties": {
    "gn:admin1_code":"14.0",
    "gn:admin2_code":"1404.0",
    "gn:asciiname":"Al Mifa'",
    "gn:country_code":"YE",
    "gn:dem":1963,
    "gn:feature_class":"P",
    "gn:feature_code":"PPL",
    "gn:name":"Al Mif\u0101'",
    "gn:population":0,
    "gn:timezone":"Asia/Aden",
    "iso:country":"YE",
    "wof:name":"Al Mifa'",
    "wof:placetype":"locality"
},
  "geometry": {"coordinates":[45.81667,14.2125],"type":"Point"}
}