{
  "type": "Feature",
  "properties": {
    "gn:admin1_code":"14.0",
    "gn:admin2_code":"2609.0",
    "gn:asciiname":"Al Mithabah",
    "gn:country_code":"YE",
    "gn:dem":1846,
    "gn:feature_class":"P",
    "gn:feature_code":"PPL",
    "gn:name":"Al M\u012bth\u0101bah",
    "gn:population":0,
    "gn:timezone":"Asia/Aden",
    "iso:country":"YE",
    "name:ara_x_preferred":[
        "\u0627\u0644\u0645\u064a\u062b\u0627\u0628\u0629"
    ],
    "name:und_x_variant":[
        "Al M\u012bth\u0101bah"
    ],
    "wof:name":"Al Mithabah",
    "wof:placetype":"locality"
},
  "geometry": {"coordinates":[45.21493,14.82574],"type":"Point"}
}