{
  "type": "Feature",
  "properties": {
    "gn:admin1_code":"25.0",
    "gn:admin2_code":"1509.0",
    "gn:asciiname":"Al Qurabah",
    "gn:country_code":"YE",
    "gn:dem":790,
    "gn:feature_class":"P",
    "gn:feature_code":"PPL",
    "gn:name":"Al Qur\u0101bah",
    "gn:population":0,
    "gn:timezone":"Asia/Aden",
    "iso:country":"YE",
    "name:ara_x_preferred":[
        "\u0627\u0644\u0642\u0631\u0627\u0628\u0629"
    ],
    "name:und_x_variant":[
        "Al Qur\u0101bah"
    ],
    "wof:name":"Al Qurabah",
    "wof:placetype":"locality"
},
  "geometry": {"coordinates":[43.84759,13.38145],"type":"Point"}
}