{
  "type": "Feature",
  "properties": {
    "gn:admin1_code":"8.0",
    "gn:admin2_code":"1801.0",
    "gn:asciiname":"Majhaf",
    "gn:country_code":"YE",
    "gn:dem":183,
    "gn:feature_class":"P",
    "gn:feature_code":"PPL",
    "gn:name":"Maj\u1e29af",
    "gn:population":0,
    "gn:timezone":"Asia/Aden",
    "iso:country":"YE",
    "name:und_x_variant":[
        "Maj\u1e29af"
    ],
    "wof:name":"Majhaf",
    "wof:placetype":"locality"
},
  "geometry": {"coordinates":[43.20724000000001,15.86124],"type":"Point"}
}