{
  "type": "Feature",
  "properties": {
    "gn:admin1_code":"10.0",
    "gn:admin2_code":"2706.0",
    "gn:asciiname":"Bayt `Inqad",
    "gn:country_code":"YE",
    "gn:dem":1595,
    "gn:feature_class":"P",
    "gn:feature_code":"PPL",
    "gn:name":"Bayt \u2018Inq\u0101d",
    "gn:population":0,
    "gn:timezone":"Asia/Aden",
    "iso:country":"YE",
    "name:und_x_variant":[
        "Bayt \u2018Inq\u0101d"
    ],
    "wof:name":"Bayt `Inqad",
    "wof:placetype":"locality"
},
  "geometry": {"coordinates":[43.46517,15.36146],"type":"Point"}
}