{
  "type": "Feature",
  "properties": {
    "gn:admin1_code":"8.0",
    "gn:admin2_code":"1810.0",
    "gn:asciiname":"Al `Abdiyah",
    "gn:country_code":"YE",
    "gn:dem":13,
    "gn:feature_class":"P",
    "gn:feature_code":"PPL",
    "gn:name":"Al \u2018Abd\u012byah",
    "gn:population":0,
    "gn:timezone":"Asia/Aden",
    "iso:country":"YE",
    "name:ara_x_preferred":[
        "\u0627\u0644\u0639\u0628\u062f\u064a\u0629"
    ],
    "name:und_x_variant":[
        "Ma\u1e29all \u2018Abad",
        "Al \u2018Abd\u012byah"
    ],
    "wof:name":"Al `Abdiyah",
    "wof:placetype":"locality"
},
  "geometry": {"coordinates":[42.92494,15.00609],"type":"Point"}
}