{
  "type": "Feature",
  "properties": {
    "gn:admin1_code":"23.0",
    "gn:admin2_code":"1101.0",
    "gn:asciiname":"Su'ayfah",
    "gn:country_code":"YE",
    "gn:dem":1160,
    "gn:feature_class":"P",
    "gn:feature_code":"PPL",
    "gn:name":"\u015eu\u2018ayfah",
    "gn:population":0,
    "gn:timezone":"Asia/Aden",
    "iso:country":"YE",
    "name:ara_x_preferred":[
        "\u0635\u0639\u064a\u0641\u0629"
    ],
    "name:und_x_variant":[
        "\u015eu\u2018ayfah"
    ],
    "wof:name":"Su'ayfah",
    "wof:placetype":"locality"
},
  "geometry": {"coordinates":[44.02346,14.31208],"type":"Point"}
}