{
  "type": "Feature",
  "properties": {
    "gn:admin1_code":"8.0",
    "gn:admin2_code":"1818.0",
    "gn:asciiname":"Al Mijba'",
    "gn:country_code":"YE",
    "gn:dem":385,
    "gn:feature_class":"P",
    "gn:feature_code":"PPL",
    "gn:name":"Al Mijb\u0101\u2019",
    "gn:population":0,
    "gn:timezone":"Asia/Aden",
    "iso:country":"YE",
    "name:ara_x_preferred":[
        "\u0627\u0644\u0645\u062c\u0628\u0627\u0621"
    ],
    "name:und_x_variant":[
        "Al Majb\u0101\u2019",
        "Al Mijb\u0101\u2019"
    ],
    "wof:name":"Al Mijba'",
    "wof:placetype":"locality"
},
  "geometry": {"coordinates":[43.61618,14.10228],"type":"Point"}
}