{
  "type": "Feature",
  "properties": {
    "gn:admin1_code":"22.0",
    "gn:admin2_code":"1724.0",
    "gn:asciiname":"Bayt Ahmad `Ali",
    "gn:country_code":"YE",
    "gn:dem":318,
    "gn:feature_class":"P",
    "gn:feature_code":"PPL",
    "gn:name":"Bayt A\u1e29mad \u2018Al\u012b",
    "gn:population":0,
    "gn:timezone":"Asia/Aden",
    "iso:country":"YE",
    "name:und_x_variant":[
        "Bayt A\u1e29mad \u2018Al\u012b"
    ],
    "wof:name":"Bayt Ahmad `Ali",
    "wof:placetype":"locality"
},
  "geometry": {"coordinates":[43.32648,15.6674],"type":"Point"}
}