{
  "type": "Feature",
  "properties": {
    "gn:admin1_code":"23.0",
    "gn:admin2_code":"1105.0",
    "gn:asciiname":"Bayt al Kabsh",
    "gn:country_code":"YE",
    "gn:dem":2987,
    "gn:feature_class":"P",
    "gn:feature_code":"PPL",
    "gn:name":"Bayt al Kabsh",
    "gn:population":0,
    "gn:timezone":"Asia/Aden",
    "iso:country":"YE",
    "name:ara_x_preferred":[
        "\u0628\u064a\u062a \u0627\u0644\u0643\u0628\u0634"
    ],
    "wof:name":"Bayt al Kabsh",
    "wof:placetype":"locality"
},
  "geometry": {"coordinates":[44.33793,14.07786],"type":"Point"}
}