{
  "type": "Feature",
  "properties": {
    "gn:admin1_code":"11.0",
    "gn:admin2_code":"2011.0",
    "gn:asciiname":"Bayt `Isa",
    "gn:country_code":"YE",
    "gn:dem":2534,
    "gn:feature_class":"P",
    "gn:feature_code":"PPL",
    "gn:name":"Bayt \u2018\u012as\u00e1",
    "gn:population":0,
    "gn:timezone":"Asia/Aden",
    "iso:country":"YE",
    "name:und_x_variant":[
        "Bayt \u2018\u012as\u00e1"
    ],
    "wof:name":"Bayt `Isa",
    "wof:placetype":"locality"
},
  "geometry": {"coordinates":[44.01911,14.77105],"type":"Point"}
}