{
  "type": "Feature",
  "properties": {
    "gn:admin1_code":"11.0",
    "gn:admin2_code":"2008.0",
    "gn:asciiname":"Al Mishwaf",
    "gn:country_code":"YE",
    "gn:dem":2409,
    "gn:feature_class":"P",
    "gn:feature_code":"PPL",
    "gn:name":"Al Mishw\u0101f",
    "gn:population":0,
    "gn:timezone":"Asia/Aden",
    "iso:country":"YE",
    "name:ara_x_preferred":[
        "Al Mishw\u0101f"
    ],
    "wof:name":"Al Mishwaf",
    "wof:placetype":"locality"
},
  "geometry": {"coordinates":[44.40514,14.59497],"type":"Point"}
}