{
  "type": "Feature",
  "properties": {
    "gn:admin1_code":"11.0",
    "gn:asciiname":"Thaylah",
    "gn:country_code":"YE",
    "gn:dem":2532,
    "gn:feature_class":"P",
    "gn:feature_code":"PPL",
    "gn:name":"Thaylah",
    "gn:population":0,
    "gn:timezone":"Asia/Aden",
    "iso:country":"YE",
    "name:ara_x_preferred":[
        "\u062b\u064a\u0644\u0629"
    ],
    "wof:name":"Thaylah",
    "wof:placetype":"locality"
},
  "geometry": {"coordinates":[44.32938,14.35995],"type":"Point"}
}