{
  "type": "Feature",
  "properties": {
    "gn:admin1_code":"4.0",
    "gn:admin2_code":"1930.0",
    "gn:asciiname":"Sharj Ba Salih",
    "gn:country_code":"YE",
    "gn:dem":1750,
    "gn:feature_class":"P",
    "gn:feature_code":"PPL",
    "gn:name":"Sharj B\u0101 \u015e\u0101li\u1e29",
    "gn:population":0,
    "gn:timezone":"Asia/Aden",
    "iso:country":"YE",
    "name:und_x_variant":[
        "Sharj B\u0101 \u015e\u0101li\u1e29"
    ],
    "wof:name":"Sharj Ba Salih",
    "wof:placetype":"locality"
},
  "geometry": {"coordinates":[48.71667,14.78333],"type":"Point"}
}