{
  "type": "Feature",
  "properties": {
    "gn:admin1_code":"11.0",
    "gn:admin2_code":"2012.0",
    "gn:asciiname":"Bayt Ahmad Qa'id",
    "gn:country_code":"YE",
    "gn:dem":1926,
    "gn:feature_class":"P",
    "gn:feature_code":"PPL",
    "gn:name":"Bayt A\u1e29mad Q\u0101\u2019id",
    "gn:population":0,
    "gn:timezone":"Asia/Aden",
    "iso:country":"YE",
    "name:und_x_variant":[
        "Bayt A\u1e29mad Q\u0101\u2019id"
    ],
    "wof:name":"Bayt Ahmad Qa'id",
    "wof:placetype":"locality"
},
  "geometry": {"coordinates":[44.10241,14.70953],"type":"Point"}
}