{
  "type": "Feature",
  "properties": {
    "gn:admin1_code":"24.0",
    "gn:admin2_code":"2512.0",
    "gn:asciiname":"Al Qarda",
    "gn:country_code":"YE",
    "gn:dem":1356,
    "gn:feature_class":"P",
    "gn:feature_code":"PPL",
    "gn:name":"Al Qar\u1e11\u00e1",
    "gn:population":0,
    "gn:timezone":"Asia/Aden",
    "iso:country":"YE",
    "name:ara_x_preferred":[
        "\u0627\u0644\u0642\u0631\u0636\u0649"
    ],
    "name:und_x_variant":[
        "Al Qar\u1e11\u00e1"
    ],
    "wof:name":"Al Qarda",
    "wof:placetype":"locality"
},
  "geometry": {"coordinates":[44.19513,13.20271],"type":"Point"}
}