{
  "type": "Feature",
  "properties": {
    "gn:admin1_code":"5.0",
    "gn:admin2_code":"2115.0",
    "gn:asciiname":"Al Hasusah",
    "gn:country_code":"YE",
    "gn:dem":642,
    "gn:feature_class":"P",
    "gn:feature_code":"PPL",
    "gn:name":"Al \u1e28as\u016bsah",
    "gn:population":0,
    "gn:timezone":"Asia/Aden",
    "iso:country":"YE",
    "name:und_x_variant":[
        "Al \u1e28as\u016bsah"
    ],
    "wof:name":"Al Hasusah",
    "wof:placetype":"locality"
},
  "geometry": {"coordinates":[47.34216,14.36522],"type":"Point"}
}