{
  "type": "Feature",
  "properties": {
    "gn:admin1_code":"15.0",
    "gn:admin2_code":"2209.0",
    "gn:asciiname":"Alt `Utayf",
    "gn:country_code":"YE",
    "gn:dem":2412,
    "gn:feature_class":"P",
    "gn:feature_code":"PPL",
    "gn:name":"Alt \u2018U\u0163ayf",
    "gn:population":0,
    "gn:timezone":"Asia/Aden",
    "iso:country":"YE",
    "name:ara_x_preferred":[
        "\u0627\u0644\u062a \u0639\u0637\u064a\u0641"
    ],
    "name:und_x_variant":[
        "Alt \u2018U\u0163ayf"
    ],
    "wof:name":"Alt `Utayf",
    "wof:placetype":"locality"
},
  "geometry": {"coordinates":[43.47412,16.85447000000001],"type":"Point"}
}