{
  "type": "Feature",
  "properties": {
    "gn:admin1_code":"5.0",
    "gn:admin2_code":"2112.0",
    "gn:asciiname":"Shi`b al Bi'r",
    "gn:country_code":"YE",
    "gn:dem":1354,
    "gn:feature_class":"P",
    "gn:feature_code":"PPL",
    "gn:name":"Shi\u2018b al Bi\u2019r",
    "gn:population":0,
    "gn:timezone":"Asia/Aden",
    "iso:country":"YE",
    "name:und_x_variant":[
        "Shi\u2018b al Bi\u2019r"
    ],
    "wof:name":"Shi`b al Bi'r",
    "wof:placetype":"locality"
},
  "geometry": {"coordinates":[46.83857,14.3788],"type":"Point"}
}