{
  "type": "Feature",
  "properties": {
    "gn:admin1_code":"14.0",
    "gn:admin2_code":"2606.0",
    "gn:asciiname":"Ash Shatlan",
    "gn:country_code":"YE",
    "gn:dem":1545,
    "gn:feature_class":"P",
    "gn:feature_code":"PPL",
    "gn:name":"Ash Sha\u0163l\u0101n",
    "gn:population":0,
    "gn:timezone":"Asia/Aden",
    "iso:country":"YE",
    "name:ara_x_preferred":[
        "Ash Shu\u0163l\u0101n"
    ],
    "name:ara_x_variant":[
        "\u0627\u0644\u0634\u0637\u0644\u0627\u0646"
    ],
    "name:und_x_variant":[
        "Ash Sha\u0163l\u0101n"
    ],
    "wof:name":"Ash Shatlan",
    "wof:placetype":"locality"
},
  "geometry": {"coordinates":[44.87936,15.41662],"type":"Point"}
}