{
  "type": "Feature",
  "properties": {
    "gn:country":"YE",
    "gn:fcode":"HSE",
    "gn:pop":5,
    "iso:country":"YE",
    "name:ara_x_preferred":[
        "\u0622\u0644 \u0627\u0644\u0639\u0631\u062c\u0627\u0621"
    ],
    "qs:name":"\u0100l al \u2018Arj\u0101\u2019",
    "qs:photos_9r":0,
    "qs:photos_sr":0,
    "qs:pop_sr":"1",
    "wof:name":"\u0100l al \u2018Arj\u0101\u2019",
    "wof:placetype":"locality",
    "wof:population":5
},
  "geometry": {"coordinates":[44.06451,16.91394],"type":"Point"}
}