{
  "type": "Feature",
  "properties": {
    "gn:admin1_code":"25.0",
    "gn:admin2_code":"1505.0",
    "gn:asciiname":"As Sufah",
    "gn:country_code":"YE",
    "gn:dem":541,
    "gn:feature_class":"P",
    "gn:feature_code":"PPL",
    "gn:name":"A\u015f \u015e\u016bfah",
    "gn:population":0,
    "gn:timezone":"Asia/Aden",
    "iso:country":"YE",
    "name:und_x_variant":[
        "A\u015f \u015e\u016bfah"
    ],
    "wof:name":"As Sufah",
    "wof:placetype":"locality"
},
  "geometry": {"coordinates":[43.67338,13.51743],"type":"Point"}
}