{
  "type": "Feature",
  "properties": {
    "gn:admin1_code":"20.0",
    "gn:asciiname":"Hayd al `Ashshah",
    "gn:country_code":"YE",
    "gn:dem":-9999,
    "gn:feature_class":"P",
    "gn:feature_code":"PPL",
    "gn:name":"\u1e28ayd al \u2018Ashshah",
    "gn:population":0,
    "gn:timezone":"Asia/Aden",
    "iso:country":"YE",
    "name:ara_x_preferred":[
        "\u062d\u064a\u062f \u0627\u0644\u0639\u0634\u0629"
    ],
    "name:und_x_variant":[
        "\u1e28ayd al \u2018Ashshah"
    ],
    "wof:name":"Hayd al `Ashshah",
    "wof:placetype":"locality"
},
  "geometry": {"coordinates":[0.78085,0.25123],"type":"Point"}
}