{
  "type": "Feature",
  "properties": {
    "gn:admin1_code":"19.0",
    "gn:admin2_code":"2901.0",
    "gn:asciiname":"Bayt Jashish",
    "gn:cc2":"YE",
    "gn:country_code":"YE",
    "gn:dem":1226,
    "gn:feature_class":"P",
    "gn:feature_code":"PPL",
    "gn:name":"Bayt Jash\u012bsh",
    "gn:population":0,
    "gn:timezone":"Asia/Aden",
    "iso:country":"YE",
    "name:und_x_variant":[
        "Beit Jashish",
        "Bayt Jash\u012bsh"
    ],
    "wof:name":"Bayt Jashish",
    "wof:placetype":"locality"
},
  "geometry": {"coordinates":[43.53333,16.55],"type":"Point"}
}