{
  "type": "Feature",
  "properties": {
    "gn:country":"YE",
    "gn:fcode":"PPLX",
    "gn:population":23,
    "iso:country":"YE",
    "name:ara_x_preferred":[
        "Zil\u0101l"
    ],
    "name:ara_x_variant":[
        "\u0632\u0644\u0627\u0644"
    ],
    "qs:name":"Zil\u0101l",
    "qs:photos_9r":0,
    "qs:photos_sr":0,
    "qs:pop_sr":"1",
    "wof:name":"Zil\u0101l",
    "wof:placetype":"neighbourhood",
    "wof:population":23
},
  "geometry": {"coordinates":[43.75107,16.75935],"type":"Point"}
}