{
  "type": "Feature",
  "properties": {
    "gn:admin1_code":"15.0",
    "gn:admin2_code":"2214.0",
    "gn:asciiname":"Madarat Gharir",
    "gn:country_code":"YE",
    "gn:dem":1927,
    "gn:feature_class":"P",
    "gn:feature_code":"PPL",
    "gn:name":"Mad\u0101rat Ghar\u012br",
    "gn:population":0,
    "gn:timezone":"Asia/Aden",
    "iso:country":"YE",
    "name:und_x_variant":[
        "Mad\u0101rat Ghar\u012br"
    ],
    "wof:name":"Madarat Gharir",
    "wof:placetype":"locality"
},
  "geometry": {"coordinates":[44.05293,16.87634],"type":"Point"}
}