{
  "type": "Feature",
  "properties": {
    "gn:admin1_code":"16.0",
    "gn:admin2_code":"2311.0",
    "gn:asciiname":"Taym",
    "gn:country_code":"YE",
    "gn:dem":1409,
    "gn:feature_class":"P",
    "gn:feature_code":"PPL",
    "gn:name":"Taym",
    "gn:population":0,
    "gn:timezone":"Asia/Aden",
    "iso:country":"YE",
    "name:und_x_variant":[
        "Teim",
        "Taym"
    ],
    "wof:name":"Taym",
    "wof:placetype":"locality"
},
  "geometry": {"coordinates":[43.63333,15.03333],"type":"Point"}
}