{
  "type": "Feature",
  "properties": {
    "gn:admin1_code":"8.0",
    "gn:admin2_code":"1812.0",
    "gn:asciiname":"Al Qarn",
    "gn:country_code":"YE",
    "gn:dem":1819,
    "gn:feature_class":"P",
    "gn:feature_code":"PPL",
    "gn:name":"Al Qarn",
    "gn:population":0,
    "gn:timezone":"Asia/Aden",
    "iso:country":"YE",
    "name:ara_x_preferred":[
        "\u0627\u0644\u0642\u0631\u0646"
    ],
    "name:nno_x_preferred":[
        "Al Qarn"
    ],
    "wof:name":"Al Qarn",
    "wof:placetype":"locality"
},
  "geometry": {"coordinates":[43.4961,14.88816],"type":"Point"}
}