{
  "type": "Feature",
  "properties": {
    "gn:admin1_code":"8.0",
    "gn:admin2_code":"1814.0",
    "gn:asciiname":"Bayt Yahya 'Ali",
    "gn:country_code":"YE",
    "gn:dem":36,
    "gn:feature_class":"P",
    "gn:feature_code":"PPL",
    "gn:name":"Bayt Ya\u1e29y\u00e1 \u2018Al\u012b",
    "gn:population":0,
    "gn:timezone":"Asia/Aden",
    "iso:country":"YE",
    "name:ara_x_preferred":[
        "\u0628\u064a\u062a \u064a\u062d\u064a\u0649 \u0639\u0644\u064a"
    ],
    "name:und_x_variant":[
        "Bayt Ya\u1e29y\u00e1 \u2018Al\u012b"
    ],
    "wof:name":"Bayt Yahya 'Ali",
    "wof:placetype":"locality"
},
  "geometry": {"coordinates":[43.06619,14.7894],"type":"Point"}
}