{
  "type": "Feature",
  "properties": {
    "gn:country":"YE",
    "gn:fcode":"PPL",
    "gn:population":2,
    "iso:country":"YE",
    "name:ara_x_preferred":[
        "Al \u1e28i\u0163\u0101wir"
    ],
    "name:ara_x_variant":[
        "\u0627\u0644\u062d\u0637\u0627\u0648\u0631"
    ],
    "name:eng_x_preferred":[
        "Al Hitawir"
    ],
    "name:eng_x_variant":[
        "A\u015f \u015eawmilah"
    ],
    "qs:name":"Al \u1e28i\u0163\u0101wir",
    "qs:photos_9r":0,
    "qs:photos_sr":0,
    "qs:pop_sr":"1",
    "wof:name":"Al \u1e28i\u0163\u0101wir",
    "wof:placetype":"locality",
    "wof:population":2
},
  "geometry": {"coordinates":[43.35255,17.53308],"type":"Point"}
}