{
  "type": "Feature",
  "properties": {
    "gn:admin1_code":"16.0",
    "gn:admin2_code":"2314.0",
    "gn:asciiname":"Ar Rasafah",
    "gn:country_code":"YE",
    "gn:dem":1437,
    "gn:feature_class":"P",
    "gn:feature_code":"PPL",
    "gn:name":"Ar Ra\u015fafah",
    "gn:population":0,
    "gn:timezone":"Asia/Aden",
    "iso:country":"YE",
    "name:ara_x_preferred":[
        "\u0627\u0644\u0631\u0635\u0641\u0629"
    ],
    "name:und_x_variant":[
        "Ar Ra\u015fafah"
    ],
    "wof:name":"Ar Rasafah",
    "wof:placetype":"locality"
},
  "geometry": {"coordinates":[44.97175,15.02473],"type":"Point"}
}