{
  "type": "Feature",
  "properties": {
    "gn:admin1_code":"16.0",
    "gn:admin2_code":"2304.0",
    "gn:asciiname":"Ratikh",
    "gn:country_code":"YE",
    "gn:dem":2338,
    "gn:feature_class":"P",
    "gn:feature_code":"PPL",
    "gn:name":"R\u0101tikh",
    "gn:population":0,
    "gn:timezone":"Asia/Aden",
    "iso:country":"YE",
    "name:ara_x_preferred":[
        "R\u0101tikh"
    ],
    "wof:name":"Ratikh",
    "wof:placetype":"locality"
},
  "geometry": {"coordinates":[44.44711,15.48998],"type":"Point"}
}