{
  "type": "Feature",
  "properties": {
    "gn:gn_country":"YE",
    "gn:gn_fcode":"PPL",
    "gn:gn_pop":15,
    "gn:population":15,
    "iso:country":"YE",
    "name:ara_x_preferred":[
        "\u0627\u0644\u062d\u064a\u0648\u0633"
    ],
    "name:eng_x_preferred":[
        "Al Haywas"
    ],
    "qs_pg:aaroncc":"YE",
    "qs_pg:gn_country":"YE",
    "qs_pg:gn_fcode":"PPL",
    "qs_pg:gn_pop":15,
    "qs_pg:name":"Al \u1e28aywas",
    "qs_pg:photos_9r":0,
    "qs_pg:photos_sr":0,
    "qs_pg:pop_sr":1,
    "qs_pg:qs_pg_placetype":"locality",
    "wof:name":"Al \u1e28aywas",
    "wof:placetype":"locality",
    "wof:population":15
},
  "geometry": {"coordinates":[45.92696,14.52792],"type":"Point"}
}