{
  "type": "Feature",
  "properties": {
    "gn:country":"YE",
    "gn:fcode":"PPL",
    "gn:population":8,
    "iso:country":"YE",
    "name:ara_x_preferred":[
        "\u0627\u0644\u062f\u062d\u0631\u0629"
    ],
    "name:ara_x_variant":[
        "\u0627\u0644\u0636\u0647\u0631\u0629"
    ],
    "name:arz_x_preferred":[
        "\u0627\u0644\u0636\u0647\u0631\u0647"
    ],
    "name:eng_x_preferred":[
        "Ad Dahrah"
    ],
    "name:fas_x_preferred":[
        "\u0627\u0644\u062f\u0647\u0631\u0627\u0647"
    ],
    "name:nld_x_preferred":[
        "Ad Dahrah"
    ],
    "name:nno_x_preferred":[
        "Ad Dahrah"
    ],
    "qs:name":"Ad Da\u1e29rah",
    "qs:photos_9r":0,
    "qs:photos_sr":0,
    "qs:pop_sr":"1",
    "wd:wordcount":42,
    "wof:name":"Ad Da\u1e29rah",
    "wof:placetype":"locality",
    "wof:population":8
},
  "geometry": {"coordinates":[44.24132,16.53975],"type":"Point"}
}