{
  "type": "Feature",
  "properties": {
    "gn:country":"YE",
    "gn:fcode":"PPL",
    "gn:pop":8,
    "iso:country":"YE",
    "name:ara_x_preferred":[
        "\u0627\u0644\u062f\u062d\u0631\u0629"
    ],
    "qs:name":"Ad Da\u1e29rah",
    "qs:photos_9r":0,
    "qs:photos_sr":0,
    "qs:pop_sr":"1",
    "wd:wordcount":42,
    "wof:name":"Ad Da\u1e29rah",
    "wof:placetype":"locality",
    "wof:population":8
},
  "geometry": {"coordinates":[44.24132,16.53975],"type":"Point"}
}