{
  "type": "Feature",
  "properties": {
    "gn:admin1_code":"20.0",
    "gn:asciiname":"Al Wajidiyah",
    "gn:country_code":"YE",
    "gn:dem":2543,
    "gn:feature_class":"P",
    "gn:feature_code":"PPL",
    "gn:name":"Al W\u0101jid\u012byah",
    "gn:population":0,
    "gn:timezone":"Asia/Aden",
    "iso:country":"YE",
    "name:ara_x_preferred":[
        "\u0627\u0644\u0648\u0627\u062c\u062f\u064a\u0629"
    ],
    "name:und_x_variant":[
        "Al W\u0101jid\u012byah"
    ],
    "wof:name":"Al Wajidiyah",
    "wof:placetype":"locality"
},
  "geometry": {"coordinates":[44.44327,14.39311],"type":"Point"}
}