{
  "type": "Feature",
  "properties": {
    "gn:admin1_code":"15.0",
    "gn:admin2_code":"2208.0",
    "gn:asciiname":"As Sunah",
    "gn:country_code":"YE",
    "gn:dem":1939,
    "gn:feature_class":"P",
    "gn:feature_code":"PPL",
    "gn:name":"As S\u016bnah",
    "gn:population":0,
    "gn:timezone":"Asia/Aden",
    "iso:country":"YE",
    "name:ara_x_preferred":[
        "\u0627\u0644\u0633\u0648\u0646\u0629"
    ],
    "name:und_x_variant":[
        "As S\u016bnah"
    ],
    "wof:name":"As Sunah",
    "wof:placetype":"locality"
},
  "geometry": {"coordinates":[43.37472,16.76522000000001],"type":"Point"}
}