{
  "type": "Feature",
  "properties": {
    "gn:admin1_code":"5.0",
    "gn:admin2_code":"2115.0",
    "gn:asciiname":"As Safah",
    "gn:country_code":"YE",
    "gn:dem":784,
    "gn:feature_class":"P",
    "gn:feature_code":"PPL",
    "gn:name":"A\u015f \u015eaf\u0101h",
    "gn:population":0,
    "gn:timezone":"Asia/Aden",
    "iso:country":"YE",
    "name:und_x_variant":[
        "Al-Saf\u0101h",
        "A\u015f \u015eaf\u0101h"
    ],
    "wof:name":"As Safah",
    "wof:placetype":"locality"
},
  "geometry": {"coordinates":[47.25264,14.44041],"type":"Point"}
}