{
  "type": "Feature",
  "properties": {
    "gn:admin1_code":"20.0",
    "gn:admin2_code":"1418.0",
    "gn:asciiname":"Al Kawlah",
    "gn:country_code":"YE",
    "gn:dem":1985,
    "gn:feature_class":"P",
    "gn:feature_code":"PPL",
    "gn:name":"Al Kawlah",
    "gn:population":0,
    "gn:timezone":"Asia/Aden",
    "iso:country":"YE",
    "wof:name":"Al Kawlah",
    "wof:placetype":"locality"
},
  "geometry": {"coordinates":[44.87055,14.2541],"type":"Point"}
}