{
  "type": "Feature",
  "properties": {
    "gn:country":"YE",
    "gn:fcode":"PPL",
    "gn:pop":4,
    "iso:country":"YE",
    "name:ara_x_preferred":[
        "\u0627\u0644\u062d\u0648\u064a\u0643"
    ],
    "name:eng_x_preferred":[
        "Al Huwayk"
    ],
    "qs:name":"Al \u1e28uwayk",
    "qs:photos_9r":0,
    "qs:photos_sr":0,
    "qs:pop_sr":"1",
    "wof:name":"Al \u1e28uwayk",
    "wof:placetype":"locality",
    "wof:population":4
},
  "geometry": {"coordinates":[45.6731,14.03842],"type":"Point"}
}