{
  "type": "Feature",
  "properties": {
    "gn:admin1_code":"5.0",
    "gn:admin2_code":"2106.0",
    "gn:asciiname":"Hassim Badi",
    "gn:country_code":"YE",
    "gn:dem":1226,
    "gn:elevation":"2.0",
    "gn:feature_class":"P",
    "gn:feature_code":"PPL",
    "gn:name":"Hassim Bad\u012b",
    "gn:population":0,
    "gn:timezone":"Asia/Aden",
    "iso:country":"YE",
    "name:und_x_variant":[
        "Hassim Bedi",
        "Hassim Bad\u012b"
    ],
    "wof:name":"Hassim Badi",
    "wof:placetype":"locality"
},
  "geometry": {"coordinates":[45.53527,14.82486],"type":"Point"}
}