{
  "type": "Feature",
  "properties": {
    "gn:gn_country":"YE",
    "gn:gn_fcode":"PPLX",
    "gn:gn_pop":5,
    "gn:population":5,
    "iso:country":"YE",
    "name:ara_x_preferred":[
        "\u0628\u064a\u062a \u0639\u0648\u0636\u0629"
    ],
    "qs_pg:aaroncc":"YE",
    "qs_pg:gn_country":"YE",
    "qs_pg:gn_fcode":"PPLX",
    "qs_pg:gn_pop":5,
    "qs_pg:name":"Bayt \u2018Aw\u1e11ah",
    "qs_pg:photos_9r":0,
    "qs_pg:photos_sr":0,
    "qs_pg:pop_sr":1,
    "qs_pg:qs_pg_placetype":"neighbourhood",
    "wof:name":"Bayt \u2018Aw\u1e11ah",
    "wof:placetype":"neighbourhood",
    "wof:population":5
},
  "geometry": {"coordinates":[43.69448,16.21905],"type":"Point"}
}