{
  "type": "Feature",
  "properties": {
    "gn:admin1_code":"11.0",
    "gn:admin2_code":"2006.0",
    "gn:asciiname":"Ad Dula`",
    "gn:country_code":"YE",
    "gn:dem":1465,
    "gn:feature_class":"P",
    "gn:feature_code":"PPL",
    "gn:name":"A\u1e11 \u1e10ula\u2018",
    "gn:population":0,
    "gn:timezone":"Asia/Aden",
    "iso:country":"YE",
    "name:und_x_variant":[
        "A\u1e11 \u1e10ula\u2018"
    ],
    "wof:name":"Ad Dula`",
    "wof:placetype":"locality"
},
  "geometry": {"coordinates":[43.90855,14.32952],"type":"Point"}
}