{
  "type": "Feature",
  "properties": {
    "gn:admin1_code":"23.0",
    "gn:admin2_code":"1102.0",
    "gn:asciiname":"Difan al Jabal",
    "gn:country_code":"YE",
    "gn:dem":2958,
    "gn:feature_class":"P",
    "gn:feature_code":"PPL",
    "gn:name":"Dif\u0101n al Jabal",
    "gn:population":0,
    "gn:timezone":"Asia/Aden",
    "iso:country":"YE",
    "name:ara_x_preferred":[
        "\u062f\u0641\u0627\u0646 \u0627\u0644\u062c\u0628\u0644"
    ],
    "name:und_x_variant":[
        "Daf\u0101n al Jabal",
        "Dif\u0101n al Jabal"
    ],
    "wof:name":"Difan al Jabal",
    "wof:placetype":"locality"
},
  "geometry": {"coordinates":[44.26954,14.16579],"type":"Point"}
}