{
  "type": "Feature",
  "properties": {
    "gn:admin1_code":"8.0",
    "gn:admin2_code":"1802.0",
    "gn:asciiname":"Madinat Mawr",
    "gn:country_code":"YE",
    "gn:dem":70,
    "gn:feature_class":"P",
    "gn:feature_code":"PPL",
    "gn:name":"Mad\u012bnat Mawr",
    "gn:population":0,
    "gn:timezone":"Asia/Aden",
    "iso:country":"YE",
    "name:und_x_variant":[
        "Mad\u012bnat Mawr",
        "Mawr"
    ],
    "wof:name":"Madinat Mawr",
    "wof:placetype":"locality"
},
  "geometry": {"coordinates":[42.96722000000001,15.66742],"type":"Point"}
}