{
  "type": "Feature",
  "properties": {
    "gn:admin1_code":"24.0",
    "gn:admin2_code":"2511.0",
    "gn:asciiname":"Dar Salim al Hajj",
    "gn:country_code":"YE",
    "gn:dem":514,
    "gn:feature_class":"P",
    "gn:feature_code":"PPL",
    "gn:name":"D\u0101r S\u0101lim al \u1e28\u0101jj",
    "gn:population":0,
    "gn:timezone":"Asia/Aden",
    "iso:country":"YE",
    "name:und_x_variant":[
        "D\u0101r S\u0101lim al \u1e28\u0101jj"
    ],
    "wof:name":"Dar Salim al Hajj",
    "wof:placetype":"locality"
},
  "geometry": {"coordinates":[44.41819,13.13732],"type":"Point"}
}