{
  "type": "Feature",
  "properties": {
    "gn:country":"YE",
    "gn:fcode":"PPL",
    "gn:pop":6,
    "iso:country":"YE",
    "name:ara_x_preferred":[
        "\u0627\u0644\u0641\u0637\u064a\u0631\u064a"
    ],
    "name:eng_x_preferred":[
        "Al Fatiri"
    ],
    "name:eng_x_variant":[
        "Al \u2018Udnah"
    ],
    "qs:name":"Al Fa\u0163\u012br\u012b",
    "qs:photos_9r":0,
    "qs:photos_sr":0,
    "qs:pop_sr":"1",
    "wof:name":"Al Fa\u0163\u012br\u012b",
    "wof:placetype":"locality",
    "wof:population":6
},
  "geometry": {"coordinates":[43.61284,16.26258],"type":"Point"}
}