{
  "type": "Feature",
  "properties": {
    "gn:country":"YE",
    "gn:fcode":"PPL",
    "gn:population":1,
    "iso:country":"YE",
    "name:ara_x_preferred":[
        "\u0100l \u1e28\u0101jib"
    ],
    "name:ara_x_variant":[
        "\u0627\u0644 \u062d\u0627\u062c\u0628"
    ],
    "qs:name":"\u0100l \u1e28\u0101jib",
    "qs:photos_9r":0,
    "qs:photos_sr":0,
    "qs:pop_sr":"1",
    "wof:name":"\u0100l \u1e28\u0101jib",
    "wof:placetype":"locality",
    "wof:population":1
},
  "geometry": {"coordinates":[43.34712,16.86001],"type":"Point"}
}