{
  "type": "Feature",
  "properties": {
    "gn:gn_country":"YE",
    "gn:gn_fcode":"PPL",
    "gn:gn_pop":1,
    "gn:population":1,
    "iso:country":"YE",
    "name:ara_x_preferred":[
        "Z\u0327\u0101hir Shughub"
    ],
    "name:ara_x_variant":[
        "\u0638\u0627\u0647\u0631 \u0634\u063a\u0628"
    ],
    "name:eng_x_preferred":[
        "Zahir Shughub"
    ],
    "name:eng_x_variant":[
        "Z\u0327ahar \u015e\u0101li\u1e29"
    ],
    "qs_pg:aaroncc":"YE",
    "qs_pg:gn_country":"YE",
    "qs_pg:gn_fcode":"PPL",
    "qs_pg:gn_pop":1,
    "qs_pg:name":"Z\u0327\u0101hir Shughub",
    "qs_pg:photos_9r":0,
    "qs_pg:photos_sr":0,
    "qs_pg:pop_sr":1,
    "qs_pg:qs_pg_placetype":"locality",
    "wof:name":"Z\u0327\u0101hir Shughub",
    "wof:placetype":"locality",
    "wof:population":1
},
  "geometry": {"coordinates":[43.35573,16.65851],"type":"Point"}
}