{
  "type": "Feature",
  "properties": {
    "gn:admin1_code":"4.0",
    "gn:admin2_code":"1918.0",
    "gn:asciiname":"Jarif",
    "gn:country_code":"YE",
    "gn:dem":1088,
    "gn:feature_class":"P",
    "gn:feature_code":"PPL",
    "gn:name":"Jar\u012bf",
    "gn:population":0,
    "gn:timezone":"Asia/Aden",
    "iso:country":"YE",
    "name:und_x_variant":[
        "Jar\u012bf"
    ],
    "wof:name":"Jarif",
    "wof:placetype":"locality"
},
  "geometry": {"coordinates":[48.35278,15.24556],"type":"Point"}
}