{
  "type": "Feature",
  "properties": {
    "gn:admin1_code":"19.0",
    "gn:admin2_code":"2904.0",
    "gn:asciiname":"Dhu Ja`man",
    "gn:country_code":"YE",
    "gn:dem":1173,
    "gn:feature_class":"P",
    "gn:feature_code":"PPL",
    "gn:name":"Dh\u016b Ja\u2018m\u0101n",
    "gn:population":0,
    "gn:timezone":"Asia/Aden",
    "iso:country":"YE",
    "name:und_x_variant":[
        "Dh\u016b Ja\u2018m\u0101n"
    ],
    "wof:name":"Dhu Ja`man",
    "wof:placetype":"locality"
},
  "geometry": {"coordinates":[43.78638,16.1867],"type":"Point"}
}