{
  "type": "Feature",
  "properties": {
    "gn:admin1_code":"24.0",
    "gn:admin2_code":"2512.0",
    "gn:asciiname":"Ash Shurayghah",
    "gn:country_code":"YE",
    "gn:dem":1450,
    "gn:feature_class":"P",
    "gn:feature_code":"PPL",
    "gn:name":"Ash Shurayghah",
    "gn:population":0,
    "gn:timezone":"Asia/Aden",
    "iso:country":"YE",
    "name:ara_x_preferred":[
        "\u0627\u0644\u0634\u0631\u064a\u063a\u0629"
    ],
    "wof:name":"Ash Shurayghah",
    "wof:placetype":"locality"
},
  "geometry": {"coordinates":[44.19031,13.20215],"type":"Point"}
}