{
  "type": "Feature",
  "properties": {
    "gn:admin1_code":"15.0",
    "gn:admin2_code":"2214.0",
    "gn:asciiname":"Al Hamdah",
    "gn:country_code":"YE",
    "gn:dem":1756,
    "gn:feature_class":"P",
    "gn:feature_code":"PPL",
    "gn:name":"Al \u1e28am\u1e11ah",
    "gn:population":0,
    "gn:timezone":"Asia/Aden",
    "iso:country":"YE",
    "name:ara_x_preferred":[
        "\u0627\u0644\u062d\u0645\u0636\u0629"
    ],
    "name:und_x_variant":[
        "Al \u1e28am\u1e11ah"
    ],
    "wof:name":"Al Hamdah",
    "wof:placetype":"locality"
},
  "geometry": {"coordinates":[44.18925,17.14918],"type":"Point"}
}