{
  "type": "Feature",
  "properties": {
    "gn:admin1_code":"14.0",
    "gn:asciiname":"Musaykah",
    "gn:country_code":"YE",
    "gn:dem":1194,
    "gn:feature_class":"P",
    "gn:feature_code":"PPLL",
    "gn:name":"Musaykah",
    "gn:population":0,
    "gn:timezone":"Asia/Aden",
    "iso:country":"YE",
    "name:ara_x_preferred":[
        "\u0645\u0633\u064a\u0643\u0629"
    ],
    "wof:name":"Musaykah",
    "wof:placetype":"locality"
},
  "geometry": {"coordinates":[44.59749,16.27142000000001],"type":"Point"}
}