{
  "type": "Feature",
  "properties": {
    "gn:admin1_code":"16.0",
    "gn:admin2_code":"2303.0",
    "gn:asciiname":"Al Khatwah",
    "gn:country_code":"YE",
    "gn:dem":1338,
    "gn:feature_class":"P",
    "gn:feature_code":"PPLL",
    "gn:name":"Al Kha\u0163wah",
    "gn:population":0,
    "gn:timezone":"Asia/Aden",
    "iso:country":"YE",
    "name:ara_x_preferred":[
        "\u0627\u0644\u062e\u0637\u0648\u0629"
    ],
    "name:und_x_variant":[
        "Al Kha\u0163wah"
    ],
    "wof:name":"Al Khatwah",
    "wof:placetype":"locality"
},
  "geometry": {"coordinates":[44.43521,15.98957],"type":"Point"}
}