{
  "type": "Feature",
  "properties": {
    "gn:admin1_code":"25.0",
    "gn:admin2_code":"1509.0",
    "gn:asciiname":"Al Hariqah",
    "gn:country_code":"YE",
    "gn:dem":854,
    "gn:feature_class":"P",
    "gn:feature_code":"PPL",
    "gn:name":"Al \u1e28ariqah",
    "gn:population":0,
    "gn:timezone":"Asia/Aden",
    "iso:country":"YE",
    "name:und_x_variant":[
        "Al \u1e28ariqah"
    ],
    "wof:name":"Al Hariqah",
    "wof:placetype":"locality"
},
  "geometry": {"coordinates":[43.7945,13.50995],"type":"Point"}
}