{
  "type": "Feature",
  "properties": {
    "gn:admin1_code":"11.0",
    "gn:admin2_code":"2012.0",
    "gn:asciiname":"Bayt Abu Hasan",
    "gn:country_code":"YE",
    "gn:dem":1995,
    "gn:feature_class":"P",
    "gn:feature_code":"PPL",
    "gn:name":"Bayt Ab\u016b \u1e28asan",
    "gn:population":0,
    "gn:timezone":"Asia/Aden",
    "iso:country":"YE",
    "name:und_x_variant":[
        "Bayt Ab\u016b \u1e28asan"
    ],
    "wof:name":"Bayt Abu Hasan",
    "wof:placetype":"locality"
},
  "geometry": {"coordinates":[44.22971,14.66991],"type":"Point"}
}