{
  "type": "Feature",
  "properties": {
    "gn:admin1_code":"8.0",
    "gn:admin2_code":"1817.0",
    "gn:asciiname":"Al Hillah",
    "gn:country_code":"YE",
    "gn:dem":160,
    "gn:feature_class":"P",
    "gn:feature_code":"PPL",
    "gn:name":"Al \u1e28illah",
    "gn:population":0,
    "gn:timezone":"Asia/Aden",
    "iso:country":"YE",
    "name:und_x_variant":[
        "Al \u1e28illah"
    ],
    "wof:name":"Al Hillah",
    "wof:placetype":"locality"
},
  "geometry": {"coordinates":[43.3788,14.47903],"type":"Point"}
}