{
  "type": "Feature",
  "properties": {
    "gn:admin1_code":"8.0",
    "gn:admin2_code":"1807.0",
    "gn:asciiname":"Dayr Ahmad",
    "gn:country_code":"YE",
    "gn:dem":105,
    "gn:feature_class":"P",
    "gn:feature_code":"PPL",
    "gn:name":"Dayr A\u1e29mad",
    "gn:population":0,
    "gn:timezone":"Asia/Aden",
    "iso:country":"YE",
    "name:und_x_variant":[
        "Dayr A\u1e29mad"
    ],
    "wof:name":"Dayr Ahmad",
    "wof:placetype":"locality"
},
  "geometry": {"coordinates":[43.1744,15.39489],"type":"Point"}
}