{
  "type": "Feature",
  "properties": {
    "gn:country":"YE",
    "gn:fcode":"TRB",
    "gn:pop":12,
    "iso:country":"YE",
    "name:ara_x_preferred":[
        "\u0628\u062f\u0648 \u0631\u062d\u0644\u0629 \u0627\u0644\u0646\u0639\u0627\u0645"
    ],
    "qs:name":"Badw Ri\u1e29lat an Na\u2018\u0101m",
    "qs:photos_9r":0,
    "qs:photos_sr":0,
    "qs:pop_sr":"1",
    "wof:name":"Badw Ri\u1e29lat an Na\u2018\u0101m",
    "wof:placetype":"locality",
    "wof:population":12
},
  "geometry": {"coordinates":[44.20965,16.99038],"type":"Point"}
}