{
  "type": "Feature",
  "properties": {
    "gn:country":"YE",
    "gn:fcode":"PPL",
    "gn:population":25,
    "iso:country":"YE",
    "name:ara_x_preferred":[
        "\u0634\u0639\u0628 \u0627\u0644\u0645\u0637\u062d\u0646"
    ],
    "name:eng_x_preferred":[
        "Sha'b Al Mathan"
    ],
    "name:eng_x_variant":[
        "Am \u2018Ataq al Mash\u2018\u016bf"
    ],
    "qs:name":"Sha\u2018b al Ma\u0163\u1e29an",
    "qs:photos_9r":0,
    "qs:photos_sr":0,
    "qs:pop_sr":"1",
    "wof:name":"Sha\u2018b al Ma\u0163\u1e29an",
    "wof:placetype":"locality",
    "wof:population":25
},
  "geometry": {"coordinates":[43.80477,13.13915],"type":"Point"}
}