{
  "type": "Feature",
  "properties": {
    "gn:admin1_code":"10.0",
    "gn:admin2_code":"2709.0",
    "gn:asciiname":"Az Za`la",
    "gn:country_code":"YE",
    "gn:dem":1299,
    "gn:feature_class":"P",
    "gn:feature_code":"PPL",
    "gn:name":"Az Za\u2018l\u0101",
    "gn:population":0,
    "gn:timezone":"Asia/Aden",
    "iso:country":"YE",
    "name:und_x_variant":[
        "Az Za\u2018l\u0101"
    ],
    "wof:name":"Az Za`la",
    "wof:placetype":"locality"
},
  "geometry": {"coordinates":[43.54333,15.51275],"type":"Point"}
}