{
  "type": "Feature",
  "properties": {
    "gn:country":"YE",
    "gn:fcode":"PPL",
    "gn:pop":3,
    "iso:country":"YE",
    "name:ara_x_preferred":[
        "\u0627\u0644\u0645\u062c\u0628\u062a"
    ],
    "name:eng_x_preferred":[
        "Al Majbut"
    ],
    "name:eng_x_variant":[
        "Al Lis\u0101n"
    ],
    "qs:name":"Al Majbut",
    "qs:photos_9r":0,
    "qs:photos_sr":0,
    "qs:pop_sr":"1",
    "wof:name":"Al Majbut",
    "wof:placetype":"locality",
    "wof:population":3
},
  "geometry": {"coordinates":[43.33517,16.51918],"type":"Point"}
}