{
  "type": "Feature",
  "properties": {
    "gn:admin1_code":"8.0",
    "gn:admin2_code":"1815.0",
    "gn:asciiname":"Sanif al Humarah",
    "gn:country_code":"YE",
    "gn:dem":296,
    "gn:feature_class":"P",
    "gn:feature_code":"PPL",
    "gn:name":"\u015eanif al \u1e28umarah",
    "gn:population":0,
    "gn:timezone":"Asia/Aden",
    "iso:country":"YE",
    "name:und_x_variant":[
        "\u015eanif al \u1e28umarah"
    ],
    "wof:name":"Sanif al Humarah",
    "wof:placetype":"locality"
},
  "geometry": {"coordinates":[43.45232,14.80846],"type":"Point"}
}