{
  "type": "Feature",
  "properties": {
    "gn:admin1_code":"8.0",
    "gn:admin2_code":"1810.0",
    "gn:asciiname":"Muhammad Qasim",
    "gn:country_code":"YE",
    "gn:dem":107,
    "gn:feature_class":"P",
    "gn:feature_code":"PPL",
    "gn:name":"Mu\u1e29ammad Q\u0101sim",
    "gn:population":0,
    "gn:timezone":"Asia/Aden",
    "iso:country":"YE",
    "name:ara_x_preferred":[
        "\u0645\u062d\u0645\u062f \u0642\u0627\u0633\u0645"
    ],
    "name:und_x_variant":[
        "Mu\u1e29ammad Q\u0101sim"
    ],
    "wof:name":"Muhammad Qasim",
    "wof:placetype":"locality"
},
  "geometry": {"coordinates":[43.1388,15.16135],"type":"Point"}
}