{
  "type": "Feature",
  "properties": {
    "gn:admin1_code":"22.0",
    "gn:admin2_code":"1720.0",
    "gn:asciiname":"As Sawani`",
    "gn:country_code":"YE",
    "gn:dem":940,
    "gn:feature_class":"P",
    "gn:feature_code":"PPL",
    "gn:name":"A\u015f \u015eaw\u0101ni\u2018",
    "gn:population":0,
    "gn:timezone":"Asia/Aden",
    "iso:country":"YE",
    "name:und_x_variant":[
        "A\u015f \u015eaw\u0101ni\u2018"
    ],
    "wof:name":"As Sawani`",
    "wof:placetype":"locality"
},
  "geometry": {"coordinates":[43.4983,15.72175],"type":"Point"}
}