{
  "type": "Feature",
  "properties": {
    "gn:country":"YE",
    "gn:fcode":"PPL",
    "gn:pop":6,
    "iso:country":"YE",
    "name:ara_x_preferred":[
        "\u0642\u0631\u0649 \u0627\u0644\u0639\u0627\u062f\u064a"
    ],
    "name:eng_x_preferred":[
        "Qara Al 'Adi"
    ],
    "name:eng_x_variant":[
        "Al Maghribah"
    ],
    "qs:name":"Qar\u00e1 al \u2018\u0100d\u012b",
    "qs:photos_9r":0,
    "qs:photos_sr":0,
    "qs:pop_sr":"1",
    "wof:name":"Qar\u00e1 al \u2018\u0100d\u012b",
    "wof:placetype":"locality",
    "wof:population":6
},
  "geometry": {"coordinates":[43.38028,16.80707],"type":"Point"}
}