{
  "type": "Feature",
  "properties": {
    "gn:country":"YE",
    "gn:fcode":"PPL",
    "gn:population":20,
    "iso:country":"YE",
    "name:ara_x_preferred":[
        "\u0627\u0644\u062d\u0632\u0628\u0629"
    ],
    "name:eng_x_preferred":[
        "Al Hazibah"
    ],
    "name:eng_x_variant":[
        "\u0100l \u015e\u0101nib"
    ],
    "qs:name":"Al \u1e28azibah",
    "qs:photos_9r":0,
    "qs:photos_sr":0,
    "qs:pop_sr":"1",
    "wof:name":"Al \u1e28azibah",
    "wof:placetype":"locality",
    "wof:population":20
},
  "geometry": {"coordinates":[43.38692,16.0502],"type":"Point"}
}