{
  "type": "Feature",
  "properties": {
    "gn:admin1_code":"16.0",
    "gn:admin2_code":"2306.0",
    "gn:asciiname":"Dar `Amru",
    "gn:country_code":"YE",
    "gn:dem":2429,
    "gn:feature_class":"P",
    "gn:feature_code":"PPL",
    "gn:name":"D\u0101r \u2018Amr\u016b",
    "gn:population":0,
    "gn:timezone":"Asia/Aden",
    "iso:country":"YE",
    "name:ara_x_preferred":[
        "D\u0101r \u2018Amr\u016b"
    ],
    "name:und_x_variant":[
        "D\u0101r \u2018Amr"
    ],
    "wof:name":"Dar `Amru",
    "wof:placetype":"locality"
},
  "geometry": {"coordinates":[44.28992,15.13347],"type":"Point"}
}