{
  "type": "Feature",
  "properties": {
    "gn:country":"YE",
    "gn:fcode":"PPL",
    "gn:population":2,
    "iso:country":"YE",
    "name:ara_x_preferred":[
        "\u0627\u0644\u0645\u0642\u0631"
    ],
    "qs:name":"Al Maqar",
    "qs:photos_9r":0,
    "qs:photos_sr":0,
    "qs:pop_sr":"1",
    "wof:name":"Al Maqar",
    "wof:placetype":"locality",
    "wof:population":2
},
  "geometry": {"coordinates":[43.2727,16.50964],"type":"Point"}
}