{
  "type": "Feature",
  "properties": {
    "gn:admin1_code":"18.0",
    "gn:admin2_code":"3001.0",
    "gn:asciiname":"Dar al Hajj",
    "gn:country_code":"YE",
    "gn:dem":2141,
    "gn:feature_class":"P",
    "gn:feature_code":"PPL",
    "gn:name":"D\u0101r al \u1e28\u0101jj",
    "gn:population":0,
    "gn:timezone":"Asia/Aden",
    "iso:country":"YE",
    "name:ara_x_preferred":[
        "\u062f\u0627\u0631 \u0627\u0644\u062d\u0627\u062c"
    ],
    "name:und_x_variant":[
        "D\u0101r al \u1e28\u0101j",
        "D\u0101r al \u1e28\u0101jj"
    ],
    "wof:name":"Dar al Hajj",
    "wof:placetype":"locality"
},
  "geometry": {"coordinates":[44.79604000000001,14.09615],"type":"Point"}
}