{
  "type": "Feature",
  "properties": {
    "gn:admin1_code":"23.0",
    "gn:admin2_code":"1106.0",
    "gn:asciiname":"Bayt Wuhaysh",
    "gn:country_code":"YE",
    "gn:dem":2656,
    "gn:feature_class":"P",
    "gn:feature_code":"PPL",
    "gn:name":"Bayt Wu\u1e29aysh",
    "gn:population":0,
    "gn:timezone":"Asia/Aden",
    "iso:country":"YE",
    "name:ara_x_preferred":[
        "\u0628\u064a\u062a \u0648\u062d\u064a\u0634"
    ],
    "name:und_x_variant":[
        "Bayt Wu\u1e29aysh"
    ],
    "wof:name":"Bayt Wuhaysh",
    "wof:placetype":"locality"
},
  "geometry": {"coordinates":[44.35664000000001,14.16081],"type":"Point"}
}