{
  "type": "Feature",
  "properties": {
    "gn:admin1_code":"5.0",
    "gn:admin2_code":"2112.0",
    "gn:asciiname":"AL-khasha upper",
    "gn:country_code":"YE",
    "gn:dem":1323,
    "gn:elevation":"1260.0",
    "gn:feature_class":"P",
    "gn:feature_code":"PPL",
    "gn:name":"AL-khash\u0101 upper",
    "gn:population":1100,
    "gn:timezone":"Asia/Aden",
    "iso:country":"YE",
    "name:ara_x_colloquial":[
        "\u0627\u0644\u062e\u0634\u0639\u0629 \u0627\u0644\u0639\u0644\u064a\u0627"
    ],
    "name:ara_x_historical":[
        "\u0627\u0644\u062e\u0634\u0639\u0629 \u0627\u0644\u0639\u0644\u064a\u0627"
    ],
    "name:ara_x_preferred":[
        "\u0627\u0644\u062e\u0634\u0639\u0629 \u0627\u0644\u0639\u0644\u064a\u0627"
    ],
    "wof:name":"AL-khasha upper",
    "wof:placetype":"locality",
    "wof:population":1100
},
  "geometry": {"coordinates":[46.71365,14.34044],"type":"Point"}
}