{
  "type": "Feature",
  "properties": {
    "gn:admin1_code":"1.0",
    "gn:admin2_code":"1204.0",
    "gn:asciiname":"Sakin Ahl as Sayyid",
    "gn:country_code":"YE",
    "gn:dem":1054,
    "gn:feature_class":"P",
    "gn:feature_code":"PPL",
    "gn:name":"S\u0101kin Ahl as Sayyid",
    "gn:population":0,
    "gn:timezone":"Asia/Aden",
    "iso:country":"YE",
    "name:ara_x_preferred":[
        "\u0623\u0645\u062d\u0628\u064a\u0644"
    ],
    "name:und_x_variant":[
        "S\u0101kin Ahl as Sayyid",
        "Am \u1e28ab\u012bl"
    ],
    "wof:name":"Sakin Ahl as Sayyid",
    "wof:placetype":"locality"
},
  "geometry": {"coordinates":[45.78228,13.85052],"type":"Point"}
}