{
  "type": "Feature",
  "properties": {
    "gn:country":"YE",
    "gn:fcode":"PPL",
    "gn:pop":6,
    "iso:country":"YE",
    "name:ara_x_preferred":[
        "\u0627\u0644\u0642\u0631\u064a\u0629"
    ],
    "qs:name":"Al Qaryah",
    "qs:photos_9r":0,
    "qs:photos_sr":0,
    "qs:pop_sr":"1",
    "wof:name":"Al Qaryah",
    "wof:placetype":"locality",
    "wof:population":6
},
  "geometry": {"coordinates":[43.34913,16.84472],"type":"Point"}
}