{
  "type": "Feature",
  "properties": {
    "gn:country":"YE",
    "gn:fcode":"PPL",
    "gn:population":2,
    "iso:country":"YE",
    "name:ara_x_preferred":[
        "\u0645\u063a\u0631\u0628\u0629 \u0627\u0644\u062d\u062c\u0641\u0629"
    ],
    "name:eng_x_preferred":[
        "Maghribat Al Hajifah"
    ],
    "name:eng_x_variant":[
        "Bayt a\u0163 \u0162awf"
    ],
    "qs_pg:aaroncc":"YE",
    "qs_pg:gn_country":"YE",
    "qs_pg:gn_fcode":"PPL",
    "qs_pg:gn_pop":2,
    "qs_pg:name":"Maghribat al \u1e28ajifah",
    "qs_pg:photos_9r":0,
    "qs_pg:photos_sr":0,
    "qs_pg:pop_sr":1,
    "qs_pg:qs_pg_placetype":"locality",
    "wof:name":"Maghribat al \u1e28ajifah",
    "wof:placetype":"locality",
    "wof:population":2
},
  "geometry": {"coordinates":[43.48205,16.08687],"type":"Point"}
}