{
  "type": "Feature",
  "properties": {
    "gn:admin1_code":"22.0",
    "gn:admin2_code":"1707.0",
    "gn:asciiname":"Al 'Ashari",
    "gn:country_code":"YE",
    "gn:dem":1217,
    "gn:feature_class":"P",
    "gn:feature_code":"PPL",
    "gn:name":"Al \u2018Ash\u0101r\u012b",
    "gn:population":0,
    "gn:timezone":"Asia/Aden",
    "iso:country":"YE",
    "name:ara_x_preferred":[
        "Al \u2018Ash\u0101r\u012b"
    ],
    "name:ara_x_variant":[
        "\u0627\u0644\u0639\u0634\u0627\u0631\u064a"
    ],
    "wof:name":"Al 'Ashari",
    "wof:placetype":"locality"
},
  "geometry": {"coordinates":[43.43161,16.08356],"type":"Point"}
}