{
  "type": "Feature",
  "properties": {
    "gn:admin1_code":"16.0",
    "gn:admin2_code":"2310.0",
    "gn:asciiname":"Bahil",
    "gn:country_code":"YE",
    "gn:dem":1144,
    "gn:feature_class":"P",
    "gn:feature_code":"PPL",
    "gn:name":"B\u0101\u1e29il",
    "gn:population":0,
    "gn:timezone":"Asia/Aden",
    "iso:country":"YE",
    "name:ara_x_preferred":[
        "B\u0101\u1e29il"
    ],
    "wof:name":"Bahil",
    "wof:placetype":"locality"
},
  "geometry": {"coordinates":[43.65938,15.12318],"type":"Point"}
}