{
  "type": "Feature",
  "properties": {
    "gn:country":"YE",
    "gn:fcode":"PPL",
    "gn:population":46,
    "iso:country":"YE",
    "name:ara_x_preferred":[
        "\u0623\u0639\u0648\u062c"
    ],
    "name:eng_x_preferred":[
        "A'waj"
    ],
    "name:eng_x_variant":[
        "Al \u1e28ir\u0101r"
    ],
    "qs:name":"A\u2018waj",
    "qs:photos_9r":0,
    "qs:photos_sr":0,
    "qs:pop_sr":"1",
    "wof:name":"A\u2018waj",
    "wof:placetype":"locality",
    "wof:population":46
},
  "geometry": {"coordinates":[43.67832,16.94253],"type":"Point"}
}