{
  "type": "Feature",
  "properties": {
    "gn:admin1_code":"25.0",
    "gn:admin2_code":"1505.0",
    "gn:asciiname":"As Suwah",
    "gn:country_code":"YE",
    "gn:dem":342,
    "gn:feature_class":"P",
    "gn:feature_code":"PPL",
    "gn:name":"As Suwa\u1e29",
    "gn:population":0,
    "gn:timezone":"Asia/Aden",
    "iso:country":"YE",
    "name:und_x_variant":[
        "As Suwa\u1e29"
    ],
    "wof:name":"As Suwah",
    "wof:placetype":"locality"
},
  "geometry": {"coordinates":[43.60459,13.87103],"type":"Point"}
}