{
  "type": "Feature",
  "properties": {
    "gn:admin1_code":"20.0",
    "gn:admin2_code":"1404.0",
    "gn:asciiname":"Am Hamra'",
    "gn:country_code":"YE",
    "gn:dem":2031,
    "gn:feature_class":"P",
    "gn:feature_code":"PPL",
    "gn:name":"Am \u1e28amr\u0101\u2019",
    "gn:population":0,
    "gn:timezone":"Asia/Aden",
    "iso:country":"YE",
    "name:und_x_variant":[
        "Am \u1e28amr\u0101\u2019",
        "Al \u1e28amr\u0101\u2019",
        "Umm \u1e28amr\u0101\u2019"
    ],
    "wof:name":"Am Hamra'",
    "wof:placetype":"locality"
},
  "geometry": {"coordinates":[45.71917,14.04028],"type":"Point"}
}