{
  "type": "Feature",
  "properties": {
    "gn:admin1_code":"24.0",
    "gn:admin2_code":"2511.0",
    "gn:asciiname":"Wali `Abd ar Rahim",
    "gn:country_code":"YE",
    "gn:dem":486,
    "gn:feature_class":"P",
    "gn:feature_code":"PPL",
    "gn:name":"Wal\u012b \u2018Abd ar Ra\u1e29\u012bm",
    "gn:population":0,
    "gn:timezone":"Asia/Aden",
    "iso:country":"YE",
    "name:und_x_variant":[
        "Wali Abdur Rahim",
        "Wal\u012b \u2018Abd ar Ra\u1e29\u012bm"
    ],
    "wof:name":"Wali `Abd ar Rahim",
    "wof:placetype":"locality"
},
  "geometry": {"coordinates":[44.34438,13.10085],"type":"Point"}
}