{
  "type": "Feature",
  "properties": {
    "gn:admin1_code":"16.0",
    "gn:admin2_code":"2302.0",
    "gn:asciiname":"Hibashah",
    "gn:country_code":"YE",
    "gn:dem":1724,
    "gn:feature_class":"P",
    "gn:feature_code":"PPL",
    "gn:name":"\u1e28ib\u0101shah",
    "gn:population":0,
    "gn:timezone":"Asia/Aden",
    "iso:country":"YE",
    "name:ara_x_preferred":[
        "\u062d\u0628\u0627\u0634\u0629"
    ],
    "name:und_x_variant":[
        "\u1e28ib\u0101shah"
    ],
    "wof:name":"Hibashah",
    "wof:placetype":"locality"
},
  "geometry": {"coordinates":[44.23582,15.95659],"type":"Point"}
}