{
  "type": "Feature",
  "properties": {
    "gn:country":"YE",
    "gn:fcode":"PPLX",
    "gn:population":201,
    "iso:country":"YE",
    "name:ara_x_preferred":[
        "Al \u2018Ar\u012bj"
    ],
    "name:ara_x_variant":[
        "\u0627\u0644\u0639\u0631\u064a\u062c"
    ],
    "qs:name":"Al \u2018Ar\u012bj",
    "qs:photos_9r":0,
    "qs:photos_sr":0,
    "qs:pop_sr":"2",
    "wof:name":"Al \u2018Ar\u012bj",
    "wof:placetype":"neighbourhood",
    "wof:population":201
},
  "geometry": {"coordinates":[43.67957,17.01815],"type":"Point"}
}