{
  "type": "Feature",
  "properties": {
    "gn:admin1_code":"24.0",
    "gn:admin2_code":"2512.0",
    "gn:asciiname":"Al Harwah",
    "gn:country_code":"YE",
    "gn:dem":1174,
    "gn:feature_class":"P",
    "gn:feature_code":"PPL",
    "gn:name":"Al Harwah",
    "gn:population":0,
    "gn:timezone":"Asia/Aden",
    "iso:country":"YE",
    "name:ara_x_preferred":[
        "\u0627\u0644\u0647\u0631\u0648\u0629"
    ],
    "wof:name":"Al Harwah",
    "wof:placetype":"locality"
},
  "geometry": {"coordinates":[44.14568,13.17884],"type":"Point"}
}