{
  "type": "Feature",
  "properties": {
    "gn:admin1_code":"19.0",
    "gn:admin2_code":"2916.0",
    "gn:asciiname":"Bayt al Humaydi",
    "gn:country_code":"YE",
    "gn:dem":2280,
    "gn:feature_class":"P",
    "gn:feature_code":"PPL",
    "gn:name":"Bayt al \u1e28umayd\u012b",
    "gn:population":0,
    "gn:timezone":"Asia/Aden",
    "iso:country":"YE",
    "name:und_x_variant":[
        "Bayt al \u1e28umayd\u012b"
    ],
    "wof:name":"Bayt al Humaydi",
    "wof:placetype":"locality"
},
  "geometry": {"coordinates":[43.7127,15.60319],"type":"Point"}
}