{
  "type": "Feature",
  "properties": {
    "gn:admin1_code":"23.0",
    "gn:admin2_code":"1106.0",
    "gn:asciiname":"Dhi Mahanit",
    "gn:country_code":"YE",
    "gn:dem":2919,
    "gn:feature_class":"P",
    "gn:feature_code":"PPL",
    "gn:name":"Dh\u012b Ma\u1e29\u0101ni\u0163",
    "gn:population":0,
    "gn:timezone":"Asia/Aden",
    "iso:country":"YE",
    "name:ara_x_preferred":[
        "Dh\u012b Mi\u1e29\u0101ni\u1e11"
    ],
    "name:ara_x_variant":[
        "\u0630\u064a \u0645\u062d\u0627\u0646\u0637"
    ],
    "name:und_x_variant":[
        "Dh\u012b Ma\u1e29\u0101ni\u0163"
    ],
    "wof:name":"Dhi Mahanit",
    "wof:placetype":"locality"
},
  "geometry": {"coordinates":[44.36567,14.10177],"type":"Point"}
}