{
  "type": "Feature",
  "properties": {
    "gn:admin1_code":"25.0",
    "gn:admin2_code":"1505.0",
    "gn:asciiname":"Al Mahatibah",
    "gn:country_code":"YE",
    "gn:dem":423,
    "gn:feature_class":"P",
    "gn:feature_code":"PPL",
    "gn:name":"Al Ma\u1e29\u0101\u0163ibah",
    "gn:population":0,
    "gn:timezone":"Asia/Aden",
    "iso:country":"YE",
    "name:ara_x_preferred":[
        "\u0645\u062d\u0627\u0637\u0628\u0629"
    ],
    "name:und_x_variant":[
        "Al Ma\u1e29\u0101\u0163ibah",
        "Ma\u1e29\u0101\u0163ibah",
        "Ma\u1e29\u0101\u0163bah"
    ],
    "wof:name":"Al Mahatibah",
    "wof:placetype":"locality"
},
  "geometry": {"coordinates":[43.58017,13.79154],"type":"Point"}
}