{
  "type": "Feature",
  "properties": {
    "gn:admin1_code":"19.0",
    "gn:admin2_code":"2919.0",
    "gn:asciiname":"Bayt Mujammal",
    "gn:country_code":"YE",
    "gn:dem":2380,
    "gn:feature_class":"P",
    "gn:feature_code":"PPL",
    "gn:name":"Bayt Mujammal",
    "gn:population":0,
    "gn:timezone":"Asia/Aden",
    "iso:country":"YE",
    "name:ara_x_preferred":[
        "\u0628\u064a\u062a \u0645\u062c\u0645\u0644"
    ],
    "wof:name":"Bayt Mujammal",
    "wof:placetype":"locality"
},
  "geometry": {"coordinates":[43.93212,16.0163],"type":"Point"}
}