{
  "type": "Feature",
  "properties": {
    "gn:country":"YE",
    "gn:fcode":"PPL",
    "gn:pop":16,
    "iso:country":"YE",
    "name:ara_x_preferred":[
        "Al Juth\u0101m"
    ],
    "name:ara_x_variant":[
        "\u0627\u0644\u062c\u062b\u0627\u0645"
    ],
    "name:eng_x_preferred":[
        "Al Jutham"
    ],
    "name:eng_x_variant":[
        "Al Ma\u1e11b\u0101yah"
    ],
    "qs:name":"Al Juth\u0101m",
    "qs:photos_9r":0,
    "qs:photos_sr":0,
    "qs:pop_sr":"1",
    "wof:name":"Al Juth\u0101m",
    "wof:placetype":"locality",
    "wof:population":16
},
  "geometry": {"coordinates":[44.0283,16.68451],"type":"Point"}
}