{
  "type": "Feature",
  "properties": {
    "gn:admin1_code":"20.0",
    "gn:admin2_code":"1410.0",
    "gn:asciiname":"Al Qurayy",
    "gn:country_code":"YE",
    "gn:dem":1936,
    "gn:feature_class":"P",
    "gn:feature_code":"PPL",
    "gn:name":"Al Qurayy",
    "gn:population":0,
    "gn:timezone":"Asia/Aden",
    "iso:country":"YE",
    "name:ara_x_preferred":[
        "\u0627\u0644\u0642\u0631\u064a"
    ],
    "wof:name":"Al Qurayy",
    "wof:placetype":"locality"
},
  "geometry": {"coordinates":[45.56159,14.2121],"type":"Point"}
}