{
  "type": "Feature",
  "properties": {
    "gn:admin1_code":"14.0",
    "gn:admin2_code":"2609.0",
    "gn:asciiname":"As Sadarah",
    "gn:country_code":"YE",
    "gn:dem":1360,
    "gn:feature_class":"P",
    "gn:feature_code":"PPL",
    "gn:name":"A\u015f \u015ead\u0101rah",
    "gn:population":0,
    "gn:timezone":"Asia/Aden",
    "iso:country":"YE",
    "name:ara_x_preferred":[
        "\u0627\u0644\u0635\u062f\u0627\u0631\u0629"
    ],
    "name:und_x_variant":[
        "\u015ead\u0101rah",
        "A\u015f \u015ead\u0101rah"
    ],
    "wof:name":"As Sadarah",
    "wof:placetype":"locality"
},
  "geometry": {"coordinates":[45.32884,14.89316],"type":"Point"}
}