{
  "type": "Feature",
  "properties": {
    "gn:gn_country":"YE",
    "gn:gn_fcode":"PPL",
    "gn:gn_pop":2,
    "gn:population":2,
    "iso:country":"YE",
    "name:ara_x_preferred":[
        "\u0627\u0644\u0639\u0645\u0627\u0631\u0629"
    ],
    "name:eng_x_preferred":[
        "Al 'Amarah"
    ],
    "name:eng_x_variant":[
        "Bi\u2019r a\u015f \u015eagh\u012brah"
    ],
    "qs_pg:aaroncc":"YE",
    "qs_pg:gn_country":"YE",
    "qs_pg:gn_fcode":"PPL",
    "qs_pg:gn_pop":2,
    "qs_pg:name":"Al \u2018Am\u0101rah",
    "qs_pg:photos_9r":0,
    "qs_pg:photos_sr":0,
    "qs_pg:pop_sr":1,
    "qs_pg:qs_pg_placetype":"locality",
    "wof:name":"Al \u2018Am\u0101rah",
    "wof:placetype":"locality",
    "wof:population":2
},
  "geometry": {"coordinates":[43.67972,16.14474],"type":"Point"}
}