{
  "type": "Feature",
  "properties": {
    "gn:admin1_code":"8.0",
    "gn:admin2_code":"1806.0",
    "gn:asciiname":"Dayr az Zayh al Yamani",
    "gn:country_code":"YE",
    "gn:dem":57,
    "gn:feature_class":"P",
    "gn:feature_code":"PPL",
    "gn:name":"Dayr az Zay\u1e29 al Yam\u0101n\u012b",
    "gn:population":0,
    "gn:timezone":"Asia/Aden",
    "iso:country":"YE",
    "name:und_x_variant":[
        "Dayr az Zay\u1e29 al Yam\u0101n\u012b"
    ],
    "wof:name":"Dayr az Zayh al Yamani",
    "wof:placetype":"locality"
},
  "geometry": {"coordinates":[43.00979,15.37021],"type":"Point"}
}