{
  "type": "Feature",
  "properties": {
    "gn:admin1_code":"11.0",
    "gn:admin2_code":"2011.0",
    "gn:asciiname":"Bayt al `Umaysi",
    "gn:country_code":"YE",
    "gn:dem":2372,
    "gn:feature_class":"P",
    "gn:feature_code":"PPL",
    "gn:name":"Bayt al \u2018Umays\u012b",
    "gn:population":0,
    "gn:timezone":"Asia/Aden",
    "iso:country":"YE",
    "name:und_x_variant":[
        "Bayt al \u2018Umays\u012b"
    ],
    "wof:name":"Bayt al `Umaysi",
    "wof:placetype":"locality"
},
  "geometry": {"coordinates":[44.15191,14.73249],"type":"Point"}
}