{
  "type": "Feature",
  "properties": {
    "gn:admin1_code":"23.0",
    "gn:admin2_code":"1120.0",
    "gn:asciiname":"Al Hanami",
    "gn:country_code":"YE",
    "gn:dem":2582,
    "gn:feature_class":"P",
    "gn:feature_code":"PPL",
    "gn:name":"Al \u1e28an\u0101m\u012b",
    "gn:population":0,
    "gn:timezone":"Asia/Aden",
    "iso:country":"YE",
    "name:und_x_variant":[
        "Al \u1e28an\u0101m\u012b"
    ],
    "wof:name":"Al Hanami",
    "wof:placetype":"locality"
},
  "geometry": {"coordinates":[44.088,13.99478],"type":"Point"}
}