{
  "type": "Feature",
  "properties": {
    "gn:country":"YE",
    "gn:fcode":"PPL",
    "gn:pop":4,
    "iso:country":"YE",
    "name:ara_x_preferred":[
        "\u0646\u064a\u062f \u0627\u0644\u062e\u0630\u0644\u0629"
    ],
    "name:eng_x_preferred":[
        "Nayd Al Khudhlah"
    ],
    "qs:name":"Nayd al Khudhlah",
    "qs:photos_9r":0,
    "qs:photos_sr":0,
    "qs:pop_sr":"1",
    "wof:name":"Nayd al Khudhlah",
    "wof:placetype":"locality",
    "wof:population":4
},
  "geometry": {"coordinates":[43.28414,17.19647],"type":"Point"}
}