{
  "type": "Feature",
  "properties": {
    "gn:gn_country":"YE",
    "gn:gn_fcode":"PPL",
    "gn:gn_pop":2,
    "gn:population":2,
    "iso:country":"YE",
    "name:ara_x_preferred":[
        "\u0627\u0644\u062a\u0648\u0627\u0642\u0631"
    ],
    "name:eng_x_preferred":[
        "At Tawaqir"
    ],
    "name:eng_x_variant":[
        "Al Gharrah"
    ],
    "qs_pg:aaroncc":"YE",
    "qs_pg:gn_country":"YE",
    "qs_pg:gn_fcode":"PPL",
    "qs_pg:gn_pop":2,
    "qs_pg:name":"At Taw\u0101qir",
    "qs_pg:photos_9r":0,
    "qs_pg:photos_sr":0,
    "qs_pg:pop_sr":1,
    "qs_pg:qs_pg_placetype":"locality",
    "wof:name":"At Taw\u0101qir",
    "wof:placetype":"locality",
    "wof:population":2
},
  "geometry": {"coordinates":[43.68258,16.04243],"type":"Point"}
}