{
  "type": "Feature",
  "properties": {
    "gn:admin1_code":"22.0",
    "gn:admin2_code":"1714.0",
    "gn:asciiname":"Al `Umayriyah",
    "gn:country_code":"YE",
    "gn:dem":1260,
    "gn:feature_class":"P",
    "gn:feature_code":"PPL",
    "gn:name":"Al \u2018Umayr\u012byah",
    "gn:population":0,
    "gn:timezone":"Asia/Aden",
    "iso:country":"YE",
    "name:und_x_variant":[
        "Al \u2018Umayr\u012byah"
    ],
    "wof:name":"Al `Umayriyah",
    "wof:placetype":"locality"
},
  "geometry": {"coordinates":[43.39526,15.94136],"type":"Point"}
}