{
  "type": "Feature",
  "properties": {
    "gn:country":"YE",
    "gn:fcode":"PPL",
    "gn:population":3,
    "iso:country":"YE",
    "name:ara_x_preferred":[
        "\u0627\u0644\u062c\u0631\u064a\u062f\u0627\u0621"
    ],
    "qs:name":"Al Jurayd\u0101\u2019",
    "qs:photos_9r":0,
    "qs:photos_sr":0,
    "qs:pop_sr":"1",
    "wof:name":"Al Jurayd\u0101\u2019",
    "wof:placetype":"locality",
    "wof:population":3
},
  "geometry": {"coordinates":[45.83847,14.27889],"type":"Point"}
}