{
  "type": "Feature",
  "properties": {
    "gn:country":"YE",
    "gn:fcode":"PPL",
    "gn:pop":6,
    "iso:country":"YE",
    "name:ara_x_preferred":[
        "\u063a\u064a\u0644 \u0627\u0644\u0639\u0628\u0644\u0627\u0621"
    ],
    "name:eng_x_preferred":[
        "Ghayl Al 'Abla"
    ],
    "name:eng_x_variant":[
        "Al B\u016br\u1e29ah"
    ],
    "qs:name":"Ghayl al \u2018Abl\u0101\u2019",
    "qs:photos_9r":0,
    "qs:photos_sr":0,
    "qs:pop_sr":"1",
    "wof:name":"Ghayl al \u2018Abl\u0101\u2019",
    "wof:placetype":"locality",
    "wof:population":6
},
  "geometry": {"coordinates":[43.62413,16.31889],"type":"Point"}
}