{
  "type": "Feature",
  "properties": {
    "gn:country":"YE",
    "gn:fcode":"PPL",
    "gn:pop":2,
    "iso:country":"YE",
    "name:ara_x_preferred":[
        "\u0627\u0644\u0631\u0632\u0648\u0629"
    ],
    "name:eng_x_preferred":[
        "Ar Razwah"
    ],
    "qs:name":"Ar Razwah",
    "qs:photos_9r":0,
    "qs:photos_sr":0,
    "qs:pop_sr":"1",
    "wof:name":"Ar Razwah",
    "wof:placetype":"locality",
    "wof:population":2
},
  "geometry": {"coordinates":[45.07674,14.91035],"type":"Point"}
}