{
  "type": "Feature",
  "properties": {
    "gn:admin1_code":"23.0",
    "gn:admin2_code":"1112.0",
    "gn:asciiname":"Al Jabanah",
    "gn:country_code":"YE",
    "gn:dem":2664,
    "gn:feature_class":"P",
    "gn:feature_code":"PPL",
    "gn:name":"Al Jab\u0101nah",
    "gn:population":0,
    "gn:timezone":"Asia/Aden",
    "iso:country":"YE",
    "name:und_x_variant":[
        "Al Jab\u0101nah"
    ],
    "wof:name":"Al Jabanah",
    "wof:placetype":"locality"
},
  "geometry": {"coordinates":[44.1155,13.89601],"type":"Point"}
}