{
  "type": "Feature",
  "properties": {
    "gn:admin1_code":"4.0",
    "gn:admin2_code":"1928.0",
    "gn:asciiname":"Duqmat Hima",
    "gn:country_code":"YE",
    "gn:dem":1026,
    "gn:feature_class":"P",
    "gn:feature_code":"PPL",
    "gn:name":"Duqmat \u1e28im\u00e1",
    "gn:population":0,
    "gn:timezone":"Asia/Aden",
    "iso:country":"YE",
    "name:und_x_variant":[
        "Duqmat \u1e28im\u00e1"
    ],
    "wof:name":"Duqmat Hima",
    "wof:placetype":"locality"
},
  "geometry": {"coordinates":[48.05,15.48333],"type":"Point"}
}