{
  "type": "Feature",
  "properties": {
    "gn:country":"YE",
    "gn:fcode":"PPL",
    "gn:pop":7,
    "iso:country":"YE",
    "name:ara_x_preferred":[
        "Afr\u0101\u2019"
    ],
    "name:ara_x_variant":[
        "\u0623\u0641\u0631\u0627\u0621"
    ],
    "name:eng_x_preferred":[
        "Afra"
    ],
    "qs:name":"Afr\u0101\u2019",
    "qs:photos_9r":0,
    "qs:photos_sr":0,
    "qs:pop_sr":"1",
    "wof:name":"Afr\u0101\u2019",
    "wof:placetype":"locality",
    "wof:population":7
},
  "geometry": {"coordinates":[44.0692,16.36676],"type":"Point"}
}