{
  "type": "Feature",
  "properties": {
    "gn:admin1_code":"8.0",
    "gn:admin2_code":"1818.0",
    "gn:asciiname":"Al Ma`sil",
    "gn:country_code":"YE",
    "gn:dem":456,
    "gn:feature_class":"P",
    "gn:feature_code":"PPL",
    "gn:name":"Al Ma\u2018sil",
    "gn:population":0,
    "gn:timezone":"Asia/Aden",
    "iso:country":"YE",
    "name:und_x_variant":[
        "Al Ma\u2018sil"
    ],
    "wof:name":"Al Ma`sil",
    "wof:placetype":"locality"
},
  "geometry": {"coordinates":[43.64402000000001,14.08185],"type":"Point"}
}