{
  "type": "Feature",
  "properties": {
    "gn:admin1_code":"19.0",
    "gn:admin2_code":"2918.0",
    "gn:asciiname":"Al Ja'if al A`la",
    "gn:country_code":"YE",
    "gn:dem":2610,
    "gn:feature_class":"P",
    "gn:feature_code":"PPL",
    "gn:name":"Al J\u0101\u2019if al A\u2018l\u00e1",
    "gn:population":0,
    "gn:timezone":"Asia/Aden",
    "iso:country":"YE",
    "name:und_x_variant":[
        "Al J\u0101\u2019if al A\u2018l\u00e1",
        "Al J\u0101\u2019if"
    ],
    "wof:name":"Al Ja'if al A`la",
    "wof:placetype":"locality"
},
  "geometry": {"coordinates":[44.05871,15.62555],"type":"Point"}
}