{
  "type": "Feature",
  "properties": {
    "gn:admin1_code":"25.0",
    "gn:admin2_code":"1504.0",
    "gn:asciiname":"Najd Wadi Bukayr",
    "gn:country_code":"YE",
    "gn:dem":1364,
    "gn:feature_class":"P",
    "gn:feature_code":"PPL",
    "gn:name":"Najd W\u0101d\u012b Bukayr",
    "gn:population":0,
    "gn:timezone":"Asia/Aden",
    "iso:country":"YE",
    "name:und_x_variant":[
        "Najd W\u0101d\u012b Bukayr"
    ],
    "wof:name":"Najd Wadi Bukayr",
    "wof:placetype":"locality"
},
  "geometry": {"coordinates":[43.76447,13.74279],"type":"Point"}
}