{
  "type": "Feature",
  "properties": {
    "gn:admin1_code":"16.0",
    "gn:admin2_code":"2307.0",
    "gn:asciiname":"Bayt Jum`an",
    "gn:country_code":"YE",
    "gn:dem":2714,
    "gn:feature_class":"P",
    "gn:feature_code":"PPL",
    "gn:name":"Bayt Jum\u2018\u0101n",
    "gn:population":0,
    "gn:timezone":"Asia/Aden",
    "iso:country":"YE",
    "name:und_x_variant":[
        "Bayt Jum\u2018\u0101n"
    ],
    "wof:name":"Bayt Jum`an",
    "wof:placetype":"locality"
},
  "geometry": {"coordinates":[44.11151,15.20003],"type":"Point"}
}