{
  "type": "Feature",
  "properties": {
    "gn:admin1_code":"15.0",
    "gn:admin2_code":"2212.0",
    "gn:asciiname":"Al Khamis",
    "gn:country_code":"YE",
    "gn:dem":1900,
    "gn:feature_class":"P",
    "gn:feature_code":"PPL",
    "gn:name":"\u0100l Kham\u012bs",
    "gn:population":0,
    "gn:timezone":"Asia/Aden",
    "iso:country":"YE",
    "name:ara_x_preferred":[
        "\u0622\u0644 \u062e\u0645\u064a\u0633"
    ],
    "name:und_x_variant":[
        "\u0100l Kham\u012bs"
    ],
    "wof:name":"Al Khamis",
    "wof:placetype":"locality"
},
  "geometry": {"coordinates":[43.71398,16.95875],"type":"Point"}
}