{
  "type": "Feature",
  "properties": {
    "gn:admin1_code":"26.0",
    "gn:admin2_code":"1310.0",
    "gn:asciiname":"Al Qasham",
    "gn:country_code":"YE",
    "gn:dem":2174,
    "gn:feature_class":"P",
    "gn:feature_code":"PPL",
    "gn:name":"Al Qasham",
    "gn:population":0,
    "gn:timezone":"Asia/Aden",
    "iso:country":"YE",
    "name:ara_x_preferred":[
        "\u0627\u0644\u0642\u0634\u0645"
    ],
    "name:und_x_variant":[
        "Bayt al Qasham",
        "Al Qasham"
    ],
    "wof:name":"Al Qasham",
    "wof:placetype":"locality"
},
  "geometry": {"coordinates":[44.2292,15.51827],"type":"Point"}
}