{
  "type": "Feature",
  "properties": {
    "gn:admin1_code":"25.0",
    "gn:admin2_code":"1502.0",
    "gn:asciiname":"Akamat al Jawf",
    "gn:country_code":"YE",
    "gn:dem":991,
    "gn:feature_class":"P",
    "gn:feature_code":"PPL",
    "gn:name":"Akamat al Jawf",
    "gn:population":0,
    "gn:timezone":"Asia/Aden",
    "iso:country":"YE",
    "wof:name":"Akamat al Jawf",
    "wof:placetype":"locality"
},
  "geometry": {"coordinates":[43.84571,13.67483],"type":"Point"}
}