{
  "type": "Feature",
  "properties": {
    "gn:country":"YE",
    "gn:fcode":"PPL",
    "gn:pop":3,
    "iso:country":"YE",
    "name:ara_x_preferred":[
        "\u0647\u0648\u062f \u0627\u0644\u0639\u0631\u062c\u0629"
    ],
    "name:eng_x_preferred":[
        "Hawd Al 'Arijah"
    ],
    "qs:name":"Hawd al \u2018Arijah",
    "qs:photos_9r":0,
    "qs:photos_sr":0,
    "qs:pop_sr":"1",
    "wof:name":"Hawd al \u2018Arijah",
    "wof:placetype":"locality",
    "wof:population":3
},
  "geometry": {"coordinates":[43.3219,16.35898],"type":"Point"}
}