{
  "type": "Feature",
  "properties": {
    "gn:admin1_code":"19.0",
    "gn:admin2_code":"2908.0",
    "gn:asciiname":"Manjalan",
    "gn:country_code":"YE",
    "gn:dem":1116,
    "gn:feature_class":"P",
    "gn:feature_code":"PPL",
    "gn:name":"Manjal\u0101n",
    "gn:population":0,
    "gn:timezone":"Asia/Aden",
    "iso:country":"YE",
    "name:und_x_variant":[
        "Manjal\u0101n"
    ],
    "wof:name":"Manjalan",
    "wof:placetype":"locality"
},
  "geometry": {"coordinates":[43.8015,16.09358],"type":"Point"}
}