{
  "type": "Feature",
  "properties": {
    "gn:admin1_code":"20.0",
    "gn:admin2_code":"1406.0",
    "gn:asciiname":"Al Hijlah",
    "gn:country_code":"YE",
    "gn:dem":1994,
    "gn:feature_class":"P",
    "gn:feature_code":"PPL",
    "gn:name":"Al \u1e28ijlah",
    "gn:population":0,
    "gn:timezone":"Asia/Aden",
    "iso:country":"YE",
    "name:und_x_variant":[
        "Al \u1e28ijlah"
    ],
    "wof:name":"Al Hijlah",
    "wof:placetype":"locality"
},
  "geometry": {"coordinates":[45.48502,14.10091],"type":"Point"}
}