{
  "type": "Feature",
  "properties": {
    "gn:admin1_code":"24.0",
    "gn:admin2_code":"2511.0",
    "gn:asciiname":"Sakin Qubanah",
    "gn:country_code":"YE",
    "gn:dem":595,
    "gn:feature_class":"P",
    "gn:feature_code":"PPL",
    "gn:name":"S\u0101kin Qub\u0101nah",
    "gn:population":0,
    "gn:timezone":"Asia/Aden",
    "iso:country":"YE",
    "name:und_x_variant":[
        "S\u0101kin Qub\u0101nah"
    ],
    "wof:name":"Sakin Qubanah",
    "wof:placetype":"locality"
},
  "geometry": {"coordinates":[44.32323,13.15807],"type":"Point"}
}