{
  "type": "Feature",
  "properties": {
    "gn:admin1_code":"22.0",
    "gn:admin2_code":"1725.0",
    "gn:asciiname":"Bayt al 'Ajuz",
    "gn:country_code":"YE",
    "gn:dem":770,
    "gn:feature_class":"P",
    "gn:feature_code":"PPL",
    "gn:name":"Bayt al \u2018Aj\u016bz",
    "gn:population":0,
    "gn:timezone":"Asia/Aden",
    "iso:country":"YE",
    "name:ara_x_preferred":[
        "\u0628\u064a\u062a \u0627\u0644\u0639\u062c\u0648\u0632"
    ],
    "name:und_x_variant":[
        "Bayt al \u2018Aj\u016bz"
    ],
    "wof:name":"Bayt al 'Ajuz",
    "wof:placetype":"locality"
},
  "geometry": {"coordinates":[43.53183,15.57741],"type":"Point"}
}