{
  "type": "Feature",
  "properties": {
    "gn:admin1_code":"25.0",
    "gn:admin2_code":"1503.0",
    "gn:asciiname":"`Adan Atrus",
    "gn:country_code":"YE",
    "gn:dem":1478,
    "gn:feature_class":"P",
    "gn:feature_code":"PPL",
    "gn:name":"\u2018Adan Atr\u016bs",
    "gn:population":0,
    "gn:timezone":"Asia/Aden",
    "iso:country":"YE",
    "name:ara_x_preferred":[
        "\u0639\u062f\u0646 \u0623\u062a\u0631\u0648\u0633"
    ],
    "name:und_x_variant":[
        "\u2018Adan Atr\u016bs"
    ],
    "wof:name":"`Adan Atrus",
    "wof:placetype":"locality"
},
  "geometry": {"coordinates":[43.84245,13.76677],"type":"Point"}
}