{
  "type": "Feature",
  "properties": {
    "gn:admin1_code":"8.0",
    "gn:admin2_code":"1807.0",
    "gn:asciiname":"Mazra'at 'Ali 'Ali Sayim",
    "gn:country_code":"YE",
    "gn:dem":78,
    "gn:feature_class":"P",
    "gn:feature_code":"PPL",
    "gn:name":"Mazra\u2018at \u2018Al\u012b \u2018Al\u012b \u015e\u0101yim",
    "gn:population":0,
    "gn:timezone":"Asia/Aden",
    "iso:country":"YE",
    "name:ara_x_preferred":[
        "\u0645\u0632\u0631\u0639\u0629 \u0639\u0644\u064a \u0639\u0644\u064a \u0635\u0627\u064a\u0645"
    ],
    "name:und_x_variant":[
        "Mazra\u2018at \u2018Al\u012b \u2018Al\u012b \u015e\u0101yim"
    ],
    "wof:name":"Mazra'at 'Ali 'Ali Sayim",
    "wof:placetype":"locality"
},
  "geometry": {"coordinates":[43.09095,15.36983],"type":"Point"}
}