{
  "type": "Feature",
  "properties": {
    "gn:admin1_code":"8.0",
    "gn:admin2_code":"1826.0",
    "gn:asciiname":"Al Mija`ar",
    "gn:country_code":"YE",
    "gn:dem":81,
    "gn:feature_class":"P",
    "gn:feature_code":"PPL",
    "gn:name":"Al Mija\u2018ar",
    "gn:population":0,
    "gn:timezone":"Asia/Aden",
    "iso:country":"YE",
    "name:und_x_variant":[
        "Al Mija\u2018ar"
    ],
    "wof:name":"Al Mija`ar",
    "wof:placetype":"locality"
},
  "geometry": {"coordinates":[43.27438,14.20435],"type":"Point"}
}