{
  "type": "Feature",
  "properties": {
    "gn:admin1_code":"15.0",
    "gn:admin2_code":"2211.0",
    "gn:asciiname":"Al Mayfa`",
    "gn:country_code":"YE",
    "gn:dem":1961,
    "gn:feature_class":"P",
    "gn:feature_code":"PPL",
    "gn:name":"Al Mayf\u0101`",
    "gn:population":0,
    "gn:timezone":"Asia/Aden",
    "iso:country":"YE",
    "wof:name":"Al Mayfa`",
    "wof:placetype":"locality"
},
  "geometry": {"coordinates":[43.63333,17.03333],"type":"Point"}
}