{
  "type": "Feature",
  "properties": {
    "gn:admin1_code":"8.0",
    "gn:admin2_code":"1814.0",
    "gn:asciiname":"Al Mukayminiyah",
    "gn:country_code":"YE",
    "gn:dem":38,
    "gn:feature_class":"P",
    "gn:feature_code":"PPL",
    "gn:name":"Al Mukaymin\u012byah",
    "gn:population":0,
    "gn:timezone":"Asia/Aden",
    "iso:country":"YE",
    "name:und_x_variant":[
        "Al Mukaymin\u012byah",
        "Mukaymin\u012byah"
    ],
    "wof:name":"Al Mukayminiyah",
    "wof:placetype":"locality"
},
  "geometry": {"coordinates":[43.09468,14.74305],"type":"Point"}
}