{
  "type": "Feature",
  "properties": {
    "gn:admin1_code":"28.0",
    "gn:admin2_code":"1926.0",
    "gn:asciiname":"'Aduhin",
    "gn:country_code":"YE",
    "gn:dem":352,
    "gn:feature_class":"P",
    "gn:feature_code":"PPL",
    "gn:name":"\u2018Ad\u016bhin",
    "gn:population":0,
    "gn:timezone":"Asia/Aden",
    "iso:country":"YE",
    "wof:name":"'Aduhin",
    "wof:placetype":"locality"
},
  "geometry": {"coordinates":[54.36756999999999,12.48076],"type":"Point"}
}