{
  "type": "Feature",
  "properties": {
    "gn:admin1_code":"16.0",
    "gn:admin2_code":"2307.0",
    "gn:asciiname":"Hushwam",
    "gn:country_code":"YE",
    "gn:dem":2717,
    "gn:feature_class":"P",
    "gn:feature_code":"PPL",
    "gn:name":"\u1e28ushwam",
    "gn:population":0,
    "gn:timezone":"Asia/Aden",
    "iso:country":"YE",
    "name:und_x_variant":[
        "\u1e28ushwam"
    ],
    "wof:name":"Hushwam",
    "wof:placetype":"locality"
},
  "geometry": {"coordinates":[44.01006,15.18327],"type":"Point"}
}