{
  "type": "Feature",
  "properties": {
    "gn:country":"YE",
    "gn:fcode":"PPL",
    "gn:pop":1,
    "iso:country":"YE",
    "name:ara_x_preferred":[
        "\u2018Ish\u0101sh"
    ],
    "name:ara_x_variant":[
        "\u0639\u0634\u0627\u0634"
    ],
    "name:eng_x_preferred":[
        "Ishash"
    ],
    "name:eng_x_variant":[
        "Al J\u0101\u2019izah",
        "'Ishash"
    ],
    "qs:name":"\u2018Ish\u0101sh",
    "qs:photos_9r":0,
    "qs:photos_sr":0,
    "qs:pop_sr":"1",
    "wof:name":"\u2018Ish\u0101sh",
    "wof:placetype":"locality",
    "wof:population":1
},
  "geometry": {"coordinates":[43.65476,16.16681],"type":"Point"}
}