{
  "type": "Feature",
  "properties": {
    "gn:country":"YE",
    "gn:fcode":"PPL",
    "gn:population":7,
    "iso:country":"YE",
    "name:ara_x_preferred":[
        "\u0627\u0644\u0644\u0628\u062f\u0629"
    ],
    "name:eng_x_preferred":[
        "Al Labidah"
    ],
    "name:eng_x_variant":[
        "Az\u0327 Z\u0327al\u0101m\u012b"
    ],
    "qs:name":"Al Labidah",
    "qs:photos_9r":0,
    "qs:photos_sr":0,
    "qs:pop_sr":"1",
    "wof:name":"Al Labidah",
    "wof:placetype":"locality",
    "wof:population":7
},
  "geometry": {"coordinates":[43.27,17.164],"type":"Point"}
}