{
  "type": "Feature",
  "properties": {
    "gn:admin1_code":"11.0",
    "gn:asciiname":"Dar adh Dhira`",
    "gn:country_code":"YE",
    "gn:dem":2681,
    "gn:feature_class":"P",
    "gn:feature_code":"PPL",
    "gn:name":"D\u0101r adh Dhir\u0101\u2018",
    "gn:population":0,
    "gn:timezone":"Asia/Aden",
    "iso:country":"YE",
    "name:ara_x_preferred":[
        "\u062f\u0627\u0631 \u0627\u0644\u0630\u0631\u0627\u0639"
    ],
    "name:und_x_variant":[
        "D\u0101r adh Dhir\u0101\u2018"
    ],
    "wof:name":"Dar adh Dhira`",
    "wof:placetype":"locality"
},
  "geometry": {"coordinates":[44.2975,14.32833],"type":"Point"}
}