{
  "type": "Feature",
  "properties": {
    "gn:country":"YE",
    "gn:fcode":"PPL",
    "gn:population":3,
    "iso:country":"YE",
    "name:ara_x_preferred":[
        "\u062c\u0631\u0628\u0629 \u0627\u0644 \u063a\u0627\u0644\u064a\u0629"
    ],
    "name:eng_x_preferred":[
        "Jurbat Al Ghaliyah"
    ],
    "name:eng_x_variant":[
        "Al Qa\u015fbah"
    ],
    "qs:name":"Jurbat \u0100l Gh\u0101l\u012byah",
    "qs:photos_9r":0,
    "qs:photos_sr":0,
    "qs:pop_sr":"1",
    "wof:name":"Jurbat \u0100l Gh\u0101l\u012byah",
    "wof:placetype":"locality",
    "wof:population":3
},
  "geometry": {"coordinates":[44.34153,17.04257],"type":"Point"}
}