{
  "type": "Feature",
  "properties": {
    "gn:country":"YE",
    "gn:fcode":"PPL",
    "gn:population":1,
    "iso:country":"YE",
    "name:ara_x_preferred":[
        "\u0627\u0644\u0645\u0632\u0627\u0628\u0631\u064a\u0646"
    ],
    "name:eng_x_preferred":[
        "Al Muzabirayn"
    ],
    "name:eng_x_variant":[
        "Anw\u0101zah"
    ],
    "qs_pg:aaroncc":"YE",
    "qs_pg:gn_country":"YE",
    "qs_pg:gn_fcode":"PPL",
    "qs_pg:gn_pop":1,
    "qs_pg:name":"Al Muz\u0101birayn",
    "qs_pg:photos_9r":0,
    "qs_pg:photos_sr":0,
    "qs_pg:pop_sr":1,
    "qs_pg:qs_pg_placetype":"locality",
    "wof:name":"Al Muz\u0101birayn",
    "wof:placetype":"locality",
    "wof:population":1
},
  "geometry": {"coordinates":[43.95678,13.21725],"type":"Point"}
}