{
  "type": "Feature",
  "properties": {
    "gn:admin1_code":"23.0",
    "gn:admin2_code":"1105.0",
    "gn:asciiname":"Dhi Hiyad",
    "gn:country_code":"YE",
    "gn:dem":2900,
    "gn:feature_class":"P",
    "gn:feature_code":"PPL",
    "gn:name":"Dh\u012b \u1e28iy\u0101\u1e11",
    "gn:population":0,
    "gn:timezone":"Asia/Aden",
    "iso:country":"YE",
    "name:ara_x_preferred":[
        "Dh\u012b \u1e28iy\u0101\u1e11"
    ],
    "wof:name":"Dhi Hiyad",
    "wof:placetype":"locality"
},
  "geometry": {"coordinates":[44.29779,14.08932],"type":"Point"}
}