{
  "type": "Feature",
  "properties": {
    "gn:admin1_code":"23.0",
    "gn:admin2_code":"1114.0",
    "gn:asciiname":"Al Kharabah",
    "gn:country_code":"YE",
    "gn:dem":1555,
    "gn:feature_class":"P",
    "gn:feature_code":"PPL",
    "gn:name":"Al Khar\u0101bah",
    "gn:population":0,
    "gn:timezone":"Asia/Aden",
    "iso:country":"YE",
    "name:und_x_variant":[
        "Al Khar\u0101bah"
    ],
    "wof:name":"Al Kharabah",
    "wof:placetype":"locality"
},
  "geometry": {"coordinates":[44.26363,13.74343],"type":"Point"}
}