{
  "type": "Feature",
  "properties": {
    "gn:admin1_code":"8.0",
    "gn:admin2_code":"1807.0",
    "gn:asciiname":"Mahall ad Dahl",
    "gn:country_code":"YE",
    "gn:dem":85,
    "gn:feature_class":"P",
    "gn:feature_code":"PPL",
    "gn:name":"Ma\u1e29all ad Dahl",
    "gn:population":0,
    "gn:timezone":"Asia/Aden",
    "iso:country":"YE",
    "name:und_x_variant":[
        "Ma\u1e29all ad Dahl"
    ],
    "wof:name":"Mahall ad Dahl",
    "wof:placetype":"locality"
},
  "geometry": {"coordinates":[43.09039,15.31956],"type":"Point"}
}