{
  "type": "Feature",
  "properties": {
    "gn:admin1_code":"19.0",
    "gn:admin2_code":"2907.0",
    "gn:asciiname":"Suwayr",
    "gn:country_code":"YE",
    "gn:dem":1269,
    "gn:feature_class":"P",
    "gn:feature_code":"PPLA2",
    "gn:name":"\u015euwayr",
    "gn:population":0,
    "gn:timezone":"Asia/Aden",
    "iso:country":"YE",
    "name:ara_x_preferred":[
        "\u0635\u0648\u064a\u0631"
    ],
    "name:und_x_variant":[
        "\u015euwayr"
    ],
    "wof:name":"Suwayr",
    "wof:placetype":"locality"
},
  "geometry": {"coordinates":[43.60986,16.1818],"type":"Point"}
}