{
  "type": "Feature",
  "properties": {
    "gn:country":"YE",
    "gn:fcode":"PPL",
    "gn:population":3,
    "iso:country":"YE",
    "name:ara_x_preferred":[
        "\u0634\u064a\u062f \u0627\u0644\u0646\u0628\u0634\u0629"
    ],
    "name:eng_x_preferred":[
        "Shayd An Nabshah"
    ],
    "name:eng_x_variant":[
        "Al Faysh"
    ],
    "qs:name":"Shayd an Nabshah",
    "qs:photos_9r":0,
    "qs:photos_sr":0,
    "qs:pop_sr":"1",
    "wof:name":"Shayd an Nabshah",
    "wof:placetype":"locality",
    "wof:population":3
},
  "geometry": {"coordinates":[43.34232,17.37686],"type":"Point"}
}