{
  "type": "Feature",
  "properties": {
    "gn:admin1_code":"21.0",
    "gn:admin2_code":"1603.0",
    "gn:asciiname":"'Uqdat al Batini",
    "gn:country_code":"YE",
    "gn:dem":1299,
    "gn:feature_class":"P",
    "gn:feature_code":"PPL",
    "gn:name":"\u2018Uqdat al B\u0101\u0163in\u012b",
    "gn:population":0,
    "gn:timezone":"Asia/Aden",
    "iso:country":"YE",
    "name:ara_x_preferred":[
        "\u0639\u0642\u062f\u0629 \u0627\u0644\u0628\u0627\u0637\u0646\u064a"
    ],
    "name:und_x_variant":[
        "\u2018Uqdat al B\u0101\u0163in\u012b"
    ],
    "wof:name":"'Uqdat al Batini",
    "wof:placetype":"locality"
},
  "geometry": {"coordinates":[44.27745,16.30256],"type":"Point"}
}