{
  "type": "Feature",
  "properties": {
    "gn:admin1_code":"15.0",
    "gn:admin2_code":"2202.0",
    "gn:asciiname":"`Irq al Mas`ud",
    "gn:country_code":"YE",
    "gn:dem":1645,
    "gn:feature_class":"P",
    "gn:feature_code":"PPL",
    "gn:name":"\u2018Irq al Mas\u2018\u016bd",
    "gn:population":0,
    "gn:timezone":"Asia/Aden",
    "iso:country":"YE",
    "name:ara_x_preferred":[
        "\u0639\u0631\u0642 \u0627\u0644\u0645\u0633\u0639\u0648\u062f"
    ],
    "name:und_x_variant":[
        "\u2018Irq al Mas\u2018\u016bd"
    ],
    "wof:name":"`Irq al Mas`ud",
    "wof:placetype":"locality"
},
  "geometry": {"coordinates":[43.29791,17.37865],"type":"Point"}
}