{
  "type": "Feature",
  "properties": {
    "gn:admin1_code":"19.0",
    "gn:admin2_code":"2901.0",
    "gn:asciiname":"Dawran al 'Ulya",
    "gn:country_code":"YE",
    "gn:dem":1584,
    "gn:feature_class":"P",
    "gn:feature_code":"PPL",
    "gn:name":"Dawr\u0101n al \u2018Uly\u0101",
    "gn:population":0,
    "gn:timezone":"Asia/Aden",
    "iso:country":"YE",
    "name:ara_x_preferred":[
        "\u062f\u0648\u0631\u0627\u0646 \u0627\u0644\u0639\u0644\u064a\u0627"
    ],
    "name:und_x_variant":[
        "Dawr\u0101n al \u2018Uly\u0101"
    ],
    "wof:name":"Dawran al 'Ulya",
    "wof:placetype":"locality"
},
  "geometry": {"coordinates":[44.09561,16.24735],"type":"Point"}
}