{
  "type": "Feature",
  "properties": {
    "gn:admin1_code":"14.0",
    "gn:admin2_code":"2603.0",
    "gn:asciiname":"Al Qaltah",
    "gn:country_code":"YE",
    "gn:dem":1298,
    "gn:feature_class":"P",
    "gn:feature_code":"PPL",
    "gn:name":"Al Qaltah",
    "gn:population":0,
    "gn:timezone":"Asia/Aden",
    "iso:country":"YE",
    "wof:name":"Al Qaltah",
    "wof:placetype":"locality"
},
  "geometry": {"coordinates":[44.88274000000001,15.61159],"type":"Point"}
}