{
  "type": "Feature",
  "properties": {
    "gn:country":"YE",
    "gn:fcode":"PPL",
    "gn:pop":7,
    "iso:country":"YE",
    "name:ara_x_preferred":[
        "\u0627\u0644\u0645\u0644\u062d\u0629 \u0627\u0644\u0639\u0644\u064a\u0627"
    ],
    "name:eng_x_preferred":[
        "Al Milhah Al 'Ulya"
    ],
    "qs:name":"Al Mil\u1e29ah al \u2018Uly\u0101",
    "qs:photos_9r":0,
    "qs:photos_sr":0,
    "qs:pop_sr":"1",
    "wof:name":"Al Mil\u1e29ah al \u2018Uly\u0101",
    "wof:placetype":"locality",
    "wof:population":7
},
  "geometry": {"coordinates":[43.93887,16.75387],"type":"Point"}
}