{
  "type": "Feature",
  "properties": {
    "gn:country":"YE",
    "gn:fcode":"PPL",
    "gn:population":14,
    "iso:country":"YE",
    "name:ara_x_preferred":[
        "\u0645\u0642\u0634\u0628 \u0635\u0627\u0644\u062d"
    ],
    "name:eng_x_preferred":[
        "Maqshab Salih"
    ],
    "name:eng_x_variant":[
        "Gh\u0101rib al Qaryah"
    ],
    "qs:name":"Maqshab \u015e\u0101li\u1e29",
    "qs:photos_9r":0,
    "qs:photos_sr":0,
    "qs:pop_sr":"1",
    "wof:name":"Maqshab \u015e\u0101li\u1e29",
    "wof:placetype":"locality",
    "wof:population":14
},
  "geometry": {"coordinates":[44.34666,16.59472],"type":"Point"}
}