{
  "type": "Feature",
  "properties": {
    "gn:admin1_code":"23.0",
    "gn:admin2_code":"1101.0",
    "gn:asciiname":"Al Hudayf",
    "gn:country_code":"YE",
    "gn:dem":1094,
    "gn:feature_class":"P",
    "gn:feature_code":"PPL",
    "gn:name":"Al Hudayf",
    "gn:population":0,
    "gn:timezone":"Asia/Aden",
    "iso:country":"YE",
    "name:ara_x_preferred":[
        "\u0627\u0644\u0647\u062f\u064a\u0641"
    ],
    "wof:name":"Al Hudayf",
    "wof:placetype":"locality"
},
  "geometry": {"coordinates":[44.03268,14.3109],"type":"Point"}
}