{
  "type": "Feature",
  "properties": {
    "gn:country":"YE",
    "gn:fcode":"PPL",
    "gn:pop":5,
    "iso:country":"YE",
    "name:ara_x_preferred":[
        "\u0627\u0644\u0641\u0631\u0641\u0629"
    ],
    "name:eng_x_preferred":[
        "Al Fariqah\""
    ],
    "qs:name":"Al Fariqah",
    "qs:photos_9r":0,
    "qs:photos_sr":0,
    "qs:pop_sr":"1",
    "wof:name":"Al Fariqah",
    "wof:placetype":"locality",
    "wof:population":5
},
  "geometry": {"coordinates":[43.46196,16.1601],"type":"Point"}
}