{
  "type": "Feature",
  "properties": {
    "gn:country":"YE",
    "gn:fcode":"PPL",
    "gn:population":1,
    "iso:country":"YE",
    "name:ara_x_preferred":[
        "Al Mi\u1e29m\u0101y"
    ],
    "name:ara_x_variant":[
        "\u0627\u0644\u0645\u062d\u0645\u0627\u064a"
    ],
    "qs:name":"Al Mi\u1e29m\u0101y",
    "qs:photos_9r":0,
    "qs:photos_sr":0,
    "qs:pop_sr":"1",
    "wof:name":"Al Mi\u1e29m\u0101y",
    "wof:placetype":"locality",
    "wof:population":1
},
  "geometry": {"coordinates":[43.26549,17.40368],"type":"Point"}
}