{
  "type": "Feature",
  "properties": {
    "gn:admin1_code":"22.0",
    "gn:admin2_code":"1701.0",
    "gn:asciiname":"Al `Irq al Ahmar",
    "gn:country_code":"YE",
    "gn:dem":697,
    "gn:feature_class":"P",
    "gn:feature_code":"PPL",
    "gn:name":"Al \u2018Irq al A\u1e29mar",
    "gn:population":0,
    "gn:timezone":"Asia/Aden",
    "iso:country":"YE",
    "name:und_x_variant":[
        "Al \u2018Irq al A\u1e29mar"
    ],
    "wof:name":"Al `Irq al Ahmar",
    "wof:placetype":"locality"
},
  "geometry": {"coordinates":[43.30701,16.55999],"type":"Point"}
}