{
  "type": "Feature",
  "properties": {
    "gn:admin1_code":"8.0",
    "gn:admin2_code":"1820.0",
    "gn:asciiname":"Ad Dahiyah",
    "gn:country_code":"YE",
    "gn:dem":124,
    "gn:feature_class":"P",
    "gn:feature_code":"PPL",
    "gn:name":"A\u1e11 \u1e10\u0101\u1e29iyah",
    "gn:population":0,
    "gn:timezone":"Asia/Aden",
    "iso:country":"YE",
    "name:und_x_variant":[
        "A\u1e11 \u1e10\u0101\u1e29iyah"
    ],
    "wof:name":"Ad Dahiyah",
    "wof:placetype":"locality"
},
  "geometry": {"coordinates":[43.41484000000001,13.86958],"type":"Point"}
}