{
  "type": "Feature",
  "properties": {
    "gn:admin1_code":"18.0",
    "gn:admin2_code":"3002.0",
    "gn:asciiname":"As Sin`ah",
    "gn:country_code":"YE",
    "gn:dem":2549,
    "gn:feature_class":"P",
    "gn:feature_code":"PPL",
    "gn:name":"A\u015f \u015ein\u2018ah",
    "gn:population":0,
    "gn:timezone":"Asia/Aden",
    "iso:country":"YE",
    "name:und_x_variant":[
        "A\u015f \u015ein\u2018ah"
    ],
    "wof:name":"As Sin`ah",
    "wof:placetype":"locality"
},
  "geometry": {"coordinates":[44.79261,14.17773],"type":"Point"}
}