{
  "type": "Feature",
  "properties": {
    "gn:admin1_code":"11.0",
    "gn:admin2_code":"2007.0",
    "gn:asciiname":"Ar Rakab",
    "gn:country_code":"YE",
    "gn:dem":499,
    "gn:feature_class":"P",
    "gn:feature_code":"PPL",
    "gn:name":"Ar Rakab",
    "gn:population":0,
    "gn:timezone":"Asia/Aden",
    "iso:country":"YE",
    "wof:name":"Ar Rakab",
    "wof:placetype":"locality"
},
  "geometry": {"coordinates":[43.51355,14.27116],"type":"Point"}
}