{
  "type": "Feature",
  "properties": {
    "gn:admin1_code":"8.0",
    "gn:admin2_code":"1817.0",
    "gn:asciiname":"Sanif `Abd Allah `Umar",
    "gn:country_code":"YE",
    "gn:dem":159,
    "gn:feature_class":"P",
    "gn:feature_code":"PPL",
    "gn:name":"\u015ean\u012bf \u2018Abd All\u0101h \u2018Umar",
    "gn:population":0,
    "gn:timezone":"Asia/Aden",
    "iso:country":"YE",
    "name:und_x_variant":[
        "\u015ean\u012bf \u2018Abd All\u0101h \u2018Umar"
    ],
    "wof:name":"Sanif `Abd Allah `Umar",
    "wof:placetype":"locality"
},
  "geometry": {"coordinates":[43.41716,14.5376],"type":"Point"}
}