{
  "type": "Feature",
  "properties": {
    "gn:admin1_code":"25.0",
    "gn:admin2_code":"1501.0",
    "gn:asciiname":"Anjad",
    "gn:country_code":"YE",
    "gn:dem":1112,
    "gn:feature_class":"P",
    "gn:feature_code":"PPL",
    "gn:name":"Anjad",
    "gn:population":0,
    "gn:timezone":"Asia/Aden",
    "iso:country":"YE",
    "name:ben_x_preferred":[
        "\u0986\u099e\u09cd\u099c\u09be\u09a6"
    ],
    "name:bpy_x_preferred":[
        "\u0986\u099e\u09cd\u099c\u09be\u09a6"
    ],
    "name:ceb_x_preferred":[
        "Anjad"
    ],
    "name:ita_x_preferred":[
        "Anjad"
    ],
    "name:mlg_x_preferred":[
        "Anjad"
    ],
    "name:msa_x_preferred":[
        "Anjad"
    ],
    "name:new_x_preferred":[
        "\u0905\u0902\u091c\u093e\u0926"
    ],
    "name:nld_x_preferred":[
        "Anjad"
    ],
    "name:por_x_preferred":[
        "Anjad"
    ],
    "name:spa_x_preferred":[
        "Anjad"
    ],
    "name:swe_x_preferred":[
        "Anjad"
    ],
    "name:vie_x_preferred":[
        "Anjad"
    ],
    "name:zho_x_preferred":[
        "\u963f\u6069\u8d3e\u5fb7"
    ],
    "wof:name":"Anjad",
    "wof:placetype":"locality"
},
  "geometry": {"coordinates":[44.32315,13.51644],"type":"Point"}
}