{
  "type": "Feature",
  "properties": {
    "gn:admin1_code":"16.0",
    "gn:admin2_code":"2302.0",
    "gn:asciiname":"Bani `Utban",
    "gn:country_code":"YE",
    "gn:dem":2626,
    "gn:feature_class":"P",
    "gn:feature_code":"PPL",
    "gn:name":"Ban\u012b \u2018Utb\u0101n",
    "gn:population":0,
    "gn:timezone":"Asia/Aden",
    "iso:country":"YE",
    "name:und_x_variant":[
        "Otban",
        "Ban\u00ee Otb\u00e2n",
        "Ban\u012b \u2018Atb\u0101n",
        "Ban\u012b \u2018Utb\u0101n"
    ],
    "wof:name":"Bani `Utban",
    "wof:placetype":"locality"
},
  "geometry": {"coordinates":[44.17008,15.72583],"type":"Point"}
}