{
  "type": "Feature",
  "properties": {
    "gn:admin1_code":"19.0",
    "gn:admin2_code":"2903.0",
    "gn:asciiname":"Mahlah",
    "gn:country_code":"YE",
    "gn:dem":1318,
    "gn:feature_class":"P",
    "gn:feature_code":"PPL",
    "gn:name":"Ma\u1e29l\u0101h",
    "gn:population":0,
    "gn:timezone":"Asia/Aden",
    "iso:country":"YE",
    "name:ara_x_preferred":[
        "\u0645\u062d\u0644\u0627\u0629"
    ],
    "name:und_x_variant":[
        "Ma\u1e29l\u0101h"
    ],
    "wof:name":"Mahlah",
    "wof:placetype":"locality"
},
  "geometry": {"coordinates":[43.80687,16.36363],"type":"Point"}
}