{
  "type": "Feature",
  "properties": {
    "gn:admin1_code":"25.0",
    "gn:admin2_code":"1522.0",
    "gn:asciiname":"Qaryat al Ma`adin",
    "gn:country_code":"YE",
    "gn:dem":1625,
    "gn:feature_class":"P",
    "gn:feature_code":"PPL",
    "gn:name":"Qaryat al Ma\u2018\u0101din",
    "gn:population":0,
    "gn:timezone":"Asia/Aden",
    "iso:country":"YE",
    "name:und_x_variant":[
        "Qaryat al Ma\u2018\u0101din"
    ],
    "wof:name":"Qaryat al Ma`adin",
    "wof:placetype":"locality"
},
  "geometry": {"coordinates":[44.13477,13.2546],"type":"Point"}
}