{
  "type": "Feature",
  "properties": {
    "gn:admin1_code":"15.0",
    "gn:admin2_code":"2203.0",
    "gn:asciiname":"Lubb",
    "gn:country_code":"YE",
    "gn:dem":2255,
    "gn:feature_class":"P",
    "gn:feature_code":"PPL",
    "gn:name":"Lubb",
    "gn:population":0,
    "gn:timezone":"Asia/Aden",
    "iso:country":"YE",
    "name:ara_x_preferred":[
        "\u0644\u0628"
    ],
    "wof:name":"Lubb",
    "wof:placetype":"locality"
},
  "geometry": {"coordinates":[43.24293,17.16258],"type":"Point"}
}