{
  "type": "Feature",
  "properties": {
    "gn:country":"YE",
    "gn:fcode":"PPL",
    "gn:pop":5,
    "iso:country":"YE",
    "name:ara_x_preferred":[
        "\u062c\u0631\u0628 \u0627\u0644\u0623\u0628\u0644"
    ],
    "name:eng_x_preferred":[
        "Jurb Al Abal"
    ],
    "name:eng_x_variant":[
        "Qa\u0163i\u2018at R\u0101bi\u2018"
    ],
    "qs:name":"Jurb al Abal",
    "qs:photos_9r":0,
    "qs:photos_sr":0,
    "qs:pop_sr":"1",
    "wof:name":"Jurb al Abal",
    "wof:placetype":"locality",
    "wof:population":5
},
  "geometry": {"coordinates":[43.25258,16.10184],"type":"Point"}
}