{
  "type": "Feature",
  "properties": {
    "gn:admin1_code":"16.0",
    "gn:admin2_code":"2302.0",
    "gn:asciiname":"Al Balad",
    "gn:country_code":"YE",
    "gn:dem":2472,
    "gn:feature_class":"P",
    "gn:feature_code":"PPL",
    "gn:name":"Al Balad",
    "gn:population":0,
    "gn:timezone":"Asia/Aden",
    "iso:country":"YE",
    "name:ara_x_preferred":[
        "\u0627\u0644\u0628\u0644\u062f"
    ],
    "name:ell_x_preferred":[
        "\u0391\u03bb \u039c\u03c0\u03b1\u03bb\u03ac\u03bd\u03c4"
    ],
    "name:fas_x_preferred":[
        "\u0627\u0644\u0628\u0644\u0627\u062f"
    ],
    "name:nno_x_preferred":[
        "Al Balad"
    ],
    "wof:name":"Al Balad",
    "wof:placetype":"locality"
},
  "geometry": {"coordinates":[44.20488,15.69036],"type":"Point"}
}