{
  "type": "Feature",
  "properties": {
    "gn:admin1_code":"24.0",
    "gn:admin2_code":"2512.0",
    "gn:asciiname":"Ash Shutayt",
    "gn:country_code":"YE",
    "gn:dem":1052,
    "gn:feature_class":"P",
    "gn:feature_code":"PPL",
    "gn:name":"Ash Shu\u0163ay\u0163",
    "gn:population":0,
    "gn:timezone":"Asia/Aden",
    "iso:country":"YE",
    "name:ara_x_preferred":[
        "\u0627\u0644\u0634\u0637\u064a\u0637"
    ],
    "name:und_x_variant":[
        "Ash Shu\u0163ay\u0163"
    ],
    "wof:name":"Ash Shutayt",
    "wof:placetype":"locality"
},
  "geometry": {"coordinates":[44.21397,13.18434],"type":"Point"}
}