{
  "type": "Feature",
  "properties": {
    "gn:country":"YE",
    "gn:fcode":"PPL",
    "gn:pop":11,
    "iso:country":"YE",
    "name:ara_x_preferred":[
        "\u0627\u0644\u062a \u0627\u0644\u0644\u0643\u0648\u0627\u0646"
    ],
    "name:eng_x_preferred":[
        "Alt Al Lakwan"
    ],
    "qs:name":"Alt al Lakw\u0101n",
    "qs:photos_9r":0,
    "qs:photos_sr":0,
    "qs:pop_sr":"1",
    "wof:name":"Alt al Lakw\u0101n",
    "wof:placetype":"locality",
    "wof:population":11
},
  "geometry": {"coordinates":[43.46578,16.98662],"type":"Point"}
}