{
  "type": "Feature",
  "properties": {
    "gn:admin1_code":"22.0",
    "gn:admin2_code":"1720.0",
    "gn:asciiname":"Mahall Kurman",
    "gn:country_code":"YE",
    "gn:dem":763,
    "gn:feature_class":"P",
    "gn:feature_code":"PPL",
    "gn:name":"Ma\u1e29all Kurm\u0101n",
    "gn:population":0,
    "gn:timezone":"Asia/Aden",
    "iso:country":"YE",
    "name:und_x_variant":[
        "Ma\u1e29all Kurm\u0101n"
    ],
    "wof:name":"Mahall Kurman",
    "wof:placetype":"locality"
},
  "geometry": {"coordinates":[43.52235,15.75123],"type":"Point"}
}