{
  "type": "Feature",
  "properties": {
    "gn:admin1_code":"10.0",
    "gn:admin2_code":"2709.0",
    "gn:asciiname":"Al Quranah",
    "gn:country_code":"YE",
    "gn:dem":1272,
    "gn:feature_class":"P",
    "gn:feature_code":"PPL",
    "gn:name":"Al Qur\u0101nah",
    "gn:population":0,
    "gn:timezone":"Asia/Aden",
    "iso:country":"YE",
    "name:und_x_variant":[
        "Al Qur\u0101nah"
    ],
    "wof:name":"Al Quranah",
    "wof:placetype":"locality"
},
  "geometry": {"coordinates":[43.50801,15.50147],"type":"Point"}
}