{
  "type": "Feature",
  "properties": {
    "gn:admin1_code":"1.0",
    "gn:admin2_code":"1211.0",
    "gn:asciiname":"Shuqrah",
    "gn:country_code":"YE",
    "gn:dem":10,
    "gn:feature_class":"P",
    "gn:feature_code":"PPL",
    "gn:name":"Shuqrah",
    "gn:population":0,
    "gn:timezone":"Asia/Aden",
    "iso:country":"YE",
    "name:ara_x_preferred":[
        "\u0634\u0642\u0631\u0629"
    ],
    "name:und_x_variant":[
        "Shuqr\u0101\u2019",
        "Shaqr\u0101\u2019",
        "Shuqrah"
    ],
    "wof:name":"Shuqrah",
    "wof:placetype":"locality"
},
  "geometry": {"coordinates":[45.69709,13.35677],"type":"Point"}
}