{
  "type": "Feature",
  "properties": {
    "gn:admin1_code":"20.0",
    "gn:admin2_code":"2010.0",
    "gn:asciiname":"Al Mu`arbid",
    "gn:country_code":"YE",
    "gn:dem":2177,
    "gn:feature_class":"P",
    "gn:feature_code":"PPL",
    "gn:name":"Al Mu\u2018arbid",
    "gn:population":0,
    "gn:timezone":"Asia/Aden",
    "iso:country":"YE",
    "name:ara_x_preferred":[
        "\u0627\u0644\u0645\u0639\u0631\u0628\u062f"
    ],
    "name:und_x_variant":[
        "Al Mu\u2018arbid"
    ],
    "wof:name":"Al Mu`arbid",
    "wof:placetype":"locality"
},
  "geometry": {"coordinates":[44.36303,14.41067],"type":"Point"}
}