{
  "type": "Feature",
  "properties": {
    "gn:country":"YE",
    "gn:fcode":"PPL",
    "gn:pop":3,
    "iso:country":"YE",
    "name:ara_x_preferred":[
        "\u0627\u0644\u063a\u0645\u0627\u0631"
    ],
    "qs:name":"Al Gham\u0101r",
    "qs:photos_9r":0,
    "qs:photos_sr":0,
    "qs:pop_sr":"1",
    "wof:name":"Al Gham\u0101r",
    "wof:placetype":"locality",
    "wof:population":3
},
  "geometry": {"coordinates":[43.62461,16.24892],"type":"Point"}
}