{
  "type": "Feature",
  "properties": {
    "gn:country":"YE",
    "gn:fcode":"PPL",
    "gn:pop":6,
    "iso:country":"YE",
    "name:ara_x_preferred":[
        "\u0627\u0644\u0645\u062f\u0627\u0631\u0645 \u0627\u0644\u0634\u0648\u0645\u0627\u0621"
    ],
    "name:eng_x_preferred":[
        "Al Mudarim Ash Shawma"
    ],
    "name:unk_x_variant":[
        "\u0627\u0644\u0645\u062f\u0627\u0631\u0645 \u0627\u0644\u0634\u0648\u0645\u0627\u0621"
    ],
    "qs:name":"Al Mud\u0101rim ash Shawm\u0101\u2019",
    "qs:photos_9r":0,
    "qs:photos_sr":0,
    "qs:pop_sr":"1",
    "wof:name":"Al Mud\u0101rim ash Shawm\u0101\u2019",
    "wof:placetype":"locality",
    "wof:population":6
},
  "geometry": {"coordinates":[43.21646,16.2095],"type":"Point"}
}