{
  "type": "Feature",
  "properties": {
    "gn:country":"YE",
    "gn:fcode":"PPL",
    "gn:population":23,
    "iso:country":"YE",
    "name:ara_x_preferred":[
        "\u0627\u0644\u0638\u0631\u0627\u0648\u0639"
    ],
    "name:eng_x_preferred":[
        "Az Zirawa'"
    ],
    "name:eng_x_variant":[
        "Al Maw\u0163al"
    ],
    "qs:name":"Az\u0327 Z\u0327ir\u0101wa\u2018",
    "qs:photos_9r":0,
    "qs:photos_sr":0,
    "qs:pop_sr":"1",
    "wof:name":"Az\u0327 Z\u0327ir\u0101wa\u2018",
    "wof:placetype":"locality",
    "wof:population":23
},
  "geometry": {"coordinates":[43.2799,16.90318],"type":"Point"}
}