{
  "type": "Feature",
  "properties": {
    "gn:country":"YE",
    "gn:fcode":"PPL",
    "gn:population":10,
    "iso:country":"YE",
    "name:ara_x_preferred":[
        "\u0627\u0644\u062e\u0648"
    ],
    "name:eng_x_preferred":[
        "Al Khaw"
    ],
    "qs:name":"Al Khaw",
    "qs:photos_9r":0,
    "qs:photos_sr":0,
    "qs:pop_sr":"1",
    "wof:name":"Al Khaw",
    "wof:placetype":"locality",
    "wof:population":10
},
  "geometry": {"coordinates":[43.37944,16.33764],"type":"Point"}
}