{
  "type": "Feature",
  "properties": {
    "gn:country":"YE",
    "gn:fcode":"PPL",
    "gn:pop":1,
    "iso:country":"YE",
    "name:ara_x_preferred":[
        "\u062e\u0631\u0627\u0628 \u0627\u0644\u062d\u062c\u064a"
    ],
    "name:eng_x_preferred":[
        "Kharab Al Haji"
    ],
    "qs:name":"Khar\u0101b al \u1e28aj\u012b",
    "qs:photos_9r":0,
    "qs:photos_sr":0,
    "qs:pop_sr":"1",
    "wof:name":"Khar\u0101b al \u1e28aj\u012b",
    "wof:placetype":"locality",
    "wof:population":1
},
  "geometry": {"coordinates":[43.70231,16.08406],"type":"Point"}
}