{
  "type": "Feature",
  "properties": {
    "gn:country":"YE",
    "gn:fcode":"PPL",
    "gn:population":4,
    "iso:country":"YE",
    "name:ara_x_preferred":[
        "\u062a\u062e\u0644\u0627\u0644"
    ],
    "name:eng_x_preferred":[
        "Takhlal"
    ],
    "qs:name":"Takhl\u0101l",
    "qs:photos_9r":0,
    "qs:photos_sr":0,
    "qs:pop_sr":"1",
    "wof:name":"Takhl\u0101l",
    "wof:placetype":"locality",
    "wof:population":4
},
  "geometry": {"coordinates":[45.17167,14.43966],"type":"Point"}
}