{
  "type": "Feature",
  "properties": {
    "gn:admin1_code":"3.0",
    "gn:admin2_code":"2804.0",
    "gn:asciiname":"Ash Shaykh al Jawhari",
    "gn:country_code":"YE",
    "gn:dem":35,
    "gn:feature_class":"P",
    "gn:feature_code":"PPL",
    "gn:name":"Ash Shaykh al Jawhar\u012b",
    "gn:population":0,
    "gn:timezone":"Asia/Aden",
    "iso:country":"YE",
    "name:und_x_variant":[
        "Jauhari",
        "Al Jauhari",
        "Jawhar\u012b",
        "Ash Shaykh al Jawhar\u012b"
    ],
    "wof:name":"Ash Shaykh al Jawhari",
    "wof:placetype":"locality"
},
  "geometry": {"coordinates":[52.48605,16.48263],"type":"Point"}
}