{
  "type": "Feature",
  "properties": {
    "gn:gn_country":"YE",
    "gn:gn_fcode":"PPL",
    "gn:gn_pop":3,
    "gn:population":3,
    "iso:country":"YE",
    "name:ara_x_preferred":[
        "\u0642\u0644\u0629 \u0627\u0644\u0645\u062c\u0627\u0631\u064a\u0646"
    ],
    "name:eng_x_preferred":[
        "Qullat Al Mujarin"
    ],
    "name:eng_x_variant":[
        "Sha\u2018b Ghur\u0101b"
    ],
    "qs_pg:aaroncc":"YE",
    "qs_pg:gn_country":"YE",
    "qs_pg:gn_fcode":"PPL",
    "qs_pg:gn_pop":3,
    "qs_pg:name":"Qullat al Muj\u0101r\u012bn",
    "qs_pg:photos_9r":0,
    "qs_pg:photos_sr":0,
    "qs_pg:pop_sr":1,
    "qs_pg:qs_pg_placetype":"locality",
    "wof:name":"Qullat al Muj\u0101r\u012bn",
    "wof:placetype":"locality",
    "wof:population":3
},
  "geometry": {"coordinates":[43.25324,16.86177],"type":"Point"}
}