{
  "type": "Feature",
  "properties": {
    "gn:admin1_code":"14.0",
    "gn:admin2_code":"2611.0",
    "gn:asciiname":"Al Aqta'",
    "gn:country_code":"YE",
    "gn:dem":2066,
    "gn:feature_class":"P",
    "gn:feature_code":"PPLA2",
    "gn:name":"Al Aq\u0163a\u2018",
    "gn:population":0,
    "gn:timezone":"Asia/Aden",
    "iso:country":"YE",
    "name:ara_x_preferred":[
        "\u0627\u0644\u0623\u0642\u0637\u0639"
    ],
    "name:und_x_variant":[
        "Al Aq\u0163a\u2018"
    ],
    "wof:name":"Al Aqta'",
    "wof:placetype":"locality"
},
  "geometry": {"coordinates":[45.35123,14.66217],"type":"Point"}
}