{
  "type": "Feature",
  "properties": {
    "gn:country":"YE",
    "gn:fcode":"PPLX",
    "gn:population":1,
    "iso:country":"YE",
    "name:ara_x_preferred":[
        "\u0627\u0644\u062d\u0648\u064a\u0629"
    ],
    "name:arz_x_preferred":[
        "\u0627\u0644\u062d\u0648\u064a\u0647"
    ],
    "name:ell_x_preferred":[
        "\u0391\u03bb \u03a7\u03b1\u03bf\u03c5\u0390\u03b3\u03b9\u03b1"
    ],
    "name:fas_x_preferred":[
        "\u0627\u0644\u0647\u0648\u0627\u06cc\u0647"
    ],
    "name:fra_x_preferred":[
        "Al-Hawiyya"
    ],
    "name:mzn_x_preferred":[
        "\u0627\u0644\u062d\u0648\u06cc\u0647"
    ],
    "name:nno_x_preferred":[
        "Al Hawiyah"
    ],
    "name:pol_x_preferred":[
        "Al-Hawijja"
    ],
    "name:urd_x_preferred":[
        "\u0627\u0644\u062d\u0648\u06cc\u06c1"
    ],
    "qs:name":"Al \u1e28aw\u012byah",
    "qs:photos_9r":0,
    "qs:photos_sr":0,
    "qs:pop_sr":"1",
    "wd:wordcount":24,
    "wof:name":"Al \u1e28aw\u012byah",
    "wof:placetype":"neighbourhood",
    "wof:population":1
},
  "geometry": {"coordinates":[43.47953,16.02894],"type":"Point"}
}