{
  "type": "Feature",
  "properties": {
    "gn:admin1_code":"24.0",
    "gn:admin2_code":"2512.0",
    "gn:asciiname":"Rubayy",
    "gn:country_code":"YE",
    "gn:dem":1184,
    "gn:feature_class":"P",
    "gn:feature_code":"PPL",
    "gn:name":"Rubayy",
    "gn:population":0,
    "gn:timezone":"Asia/Aden",
    "iso:country":"YE",
    "name:ara_x_preferred":[
        "\u0631\u0628\u064a"
    ],
    "name:und_x_variant":[
        "Rub\u00e1"
    ],
    "wof:name":"Rubayy",
    "wof:placetype":"locality"
},
  "geometry": {"coordinates":[44.1757,13.16939],"type":"Point"}
}