{
  "type": "Feature",
  "properties": {
    "gn:country":"YE",
    "gn:fcode":"PPLX",
    "gn:population":74,
    "iso:country":"YE",
    "name:ara_x_preferred":[
        "\u0627\u0644\u0642\u0635\u0631"
    ],
    "name:eng_x_preferred":[
        "Al-Qasr"
    ],
    "name:fas_x_preferred":[
        "\u0627\u0644\u0642\u0635\u0631"
    ],
    "name:mzn_x_preferred":[
        "\u0627\u0644\u0642\u0635\u0631"
    ],
    "name:nld_x_preferred":[
        "Al-Qasr"
    ],
    "name:nno_x_preferred":[
        "Al-Qasr"
    ],
    "qs:name":"Al Qa\u015fr",
    "qs:photos_9r":0,
    "qs:photos_sr":0,
    "qs:pop_sr":"1",
    "wd:wordcount":55,
    "wof:name":"Al Qa\u015fr",
    "wof:placetype":"neighbourhood",
    "wof:population":74
},
  "geometry": {"coordinates":[43.76118,16.93902],"type":"Point"}
}