{
  "type": "Feature",
  "properties": {
    "gn:country":"YE",
    "gn:fcode":"PPL",
    "gn:population":6,
    "iso:country":"YE",
    "name:ara_x_preferred":[
        "\u0627\u0644\u0637\u0641\u0629"
    ],
    "qs:name":"A\u0163 \u0162iffah",
    "qs:photos_9r":0,
    "qs:photos_sr":0,
    "qs:pop_sr":"1",
    "wof:name":"A\u0163 \u0162iffah",
    "wof:placetype":"locality",
    "wof:population":6
},
  "geometry": {"coordinates":[43.27041,16.52669],"type":"Point"}
}