{
  "type": "Feature",
  "properties": {
    "gn:country":"YE",
    "gn:fcode":"PPL",
    "gn:population":3,
    "iso:country":"YE",
    "name:ara_x_preferred":[
        "\u0627\u0644\u0645\u0648\u0628\u0631\u0629"
    ],
    "qs:name":"Al Muwayrah",
    "qs:photos_9r":0,
    "qs:photos_sr":0,
    "qs:pop_sr":"1",
    "wof:name":"Al Muwayrah",
    "wof:placetype":"locality",
    "wof:population":3
},
  "geometry": {"coordinates":[43.26309,17.39981],"type":"Point"}
}