{
  "type": "Feature",
  "properties": {
    "gn:admin1_code":"23.0",
    "gn:admin2_code":"1113.0",
    "gn:asciiname":"Dar Barakat",
    "gn:country_code":"YE",
    "gn:dem":1662,
    "gn:feature_class":"P",
    "gn:feature_code":"PPL",
    "gn:name":"D\u0101r Barak\u0101t",
    "gn:population":0,
    "gn:timezone":"Asia/Aden",
    "iso:country":"YE",
    "name:und_x_variant":[
        "D\u0101r Barak\u0101t"
    ],
    "wof:name":"Dar Barakat",
    "wof:placetype":"locality"
},
  "geometry": {"coordinates":[44.44037,13.96628],"type":"Point"}
}