{
  "type": "Feature",
  "properties": {
    "gn:country":"YE",
    "gn:fcode":"PPL",
    "gn:pop":7,
    "iso:country":"YE",
    "name:ara_x_preferred":[
        "\u0642\u0644\u0629 \u0627\u0644\u0647\u0645\u0644"
    ],
    "name:eng_x_preferred":[
        "Qillat Al Haml"
    ],
    "name:eng_x_variant":[
        "\u1e28adabat al Jash"
    ],
    "qs:name":"Qillat al Haml",
    "qs:photos_9r":0,
    "qs:photos_sr":0,
    "qs:pop_sr":"1",
    "wof:name":"Qillat al Haml",
    "wof:placetype":"locality",
    "wof:population":7
},
  "geometry": {"coordinates":[43.44909,16.70891],"type":"Point"}
}