{
  "type": "Feature",
  "properties": {
    "gn:gn_country":"YE",
    "gn:gn_fcode":"PPLX",
    "gn:gn_pop":1,
    "gn:population":1,
    "iso:country":"YE",
    "name:ara_x_preferred":[
        "\u0627\u0644\u0638\u0647\u0631\u0629"
    ],
    "qs_pg:aaroncc":"YE",
    "qs_pg:gn_country":"YE",
    "qs_pg:gn_fcode":"PPLX",
    "qs_pg:gn_pop":1,
    "qs_pg:name":"Az\u0327 Z\u0327ahrah",
    "qs_pg:photos_9r":0,
    "qs_pg:photos_sr":0,
    "qs_pg:pop_sr":1,
    "qs_pg:qs_pg_placetype":"neighbourhood",
    "wof:name":"Az\u0327 Z\u0327ahrah",
    "wof:placetype":"neighbourhood",
    "wof:population":1
},
  "geometry": {"coordinates":[43.66772,16.01988],"type":"Point"}
}