{
  "type": "Feature",
  "properties": {
    "gn:country":"YE",
    "gn:fcode":"PPL",
    "gn:pop":3,
    "iso:country":"YE",
    "name:ara_x_preferred":[
        "\u0627\u0644\u062d\u0628\u064a\u0644 \u0628\u0646\u0649 \u0646\u0648\u0631"
    ],
    "name:eng_x_preferred":[
        "Al Habil Bani NUr"
    ],
    "qs:name":"Al \u1e28ab\u012bl Ban\u012b N\u016br",
    "qs:photos_9r":0,
    "qs:photos_sr":0,
    "qs:pop_sr":"1",
    "wof:name":"Al \u1e28ab\u012bl Ban\u012b N\u016br",
    "wof:placetype":"locality",
    "wof:population":3
},
  "geometry": {"coordinates":[43.35537,16.10921],"type":"Point"}
}