{
  "type": "Feature",
  "properties": {
    "gn:gn_country":"YE",
    "gn:gn_fcode":"PPL",
    "gn:gn_pop":10,
    "gn:population":10,
    "iso:country":"YE",
    "name:ara_x_preferred":[
        "\u0627\u0644\u062f\u0648\u0627\u0643\u0644\u0629"
    ],
    "name:eng_x_preferred":[
        "Ad Diwakilah"
    ],
    "name:eng_x_variant":[
        "Al Mil\u0101m"
    ],
    "qs_pg:aaroncc":"YE",
    "qs_pg:gn_country":"YE",
    "qs_pg:gn_fcode":"PPL",
    "qs_pg:gn_pop":10,
    "qs_pg:name":"Ad Diw\u0101kilah",
    "qs_pg:photos_9r":0,
    "qs_pg:photos_sr":0,
    "qs_pg:pop_sr":1,
    "qs_pg:qs_pg_placetype":"locality",
    "wof:name":"Ad Diw\u0101kilah",
    "wof:placetype":"locality",
    "wof:population":10
},
  "geometry": {"coordinates":[43.15515,16.30269],"type":"Point"}
}