{
  "type": "Feature",
  "properties": {
    "gn:country":"YE",
    "gn:fcode":"PPL",
    "gn:pop":11,
    "iso:country":"YE",
    "name:ara_x_preferred":[
        "\u0627\u0644\u0645\u062d\u062b\u0644\u0629"
    ],
    "name:eng_x_preferred":[
        "Al Muhathilah"
    ],
    "name:eng_x_variant":[
        "Al \u1e28\u0101yirah"
    ],
    "qs:name":"Al Mu\u1e29athilah",
    "qs:photos_9r":0,
    "qs:photos_sr":0,
    "qs:pop_sr":"1",
    "wof:name":"Al Mu\u1e29athilah",
    "wof:placetype":"locality",
    "wof:population":11
},
  "geometry": {"coordinates":[43.39445,16.06136],"type":"Point"}
}