{
  "type": "Feature",
  "properties": {
    "gn:admin1_code":"8.0",
    "gn:admin2_code":"1816.0",
    "gn:asciiname":"As Sayyal",
    "gn:country_code":"YE",
    "gn:dem":229,
    "gn:feature_class":"P",
    "gn:feature_code":"PPL",
    "gn:name":"As Sayy\u0101l",
    "gn:population":0,
    "gn:timezone":"Asia/Aden",
    "iso:country":"YE",
    "name:ara_x_preferred":[
        "\u0627\u0644\u0633\u064a\u0627\u0644"
    ],
    "name:und_x_variant":[
        "As Sayy\u0101l"
    ],
    "wof:name":"As Sayyal",
    "wof:placetype":"locality"
},
  "geometry": {"coordinates":[43.43411,14.74029],"type":"Point"}
}