{
  "type": "Feature",
  "properties": {
    "gn:admin1_code":"23.0",
    "gn:admin2_code":"1101.0",
    "gn:asciiname":"Khalbash",
    "gn:country_code":"YE",
    "gn:dem":1132,
    "gn:feature_class":"P",
    "gn:feature_code":"PPL",
    "gn:name":"Khalbash",
    "gn:population":0,
    "gn:timezone":"Asia/Aden",
    "iso:country":"YE",
    "name:ara_x_preferred":[
        "\u062e\u0644\u0628\u0634"
    ],
    "wof:name":"Khalbash",
    "wof:placetype":"locality"
},
  "geometry": {"coordinates":[44.03443,14.29396],"type":"Point"}
}