{
  "type": "Feature",
  "properties": {
    "gn:admin1_code":"19.0",
    "gn:admin2_code":"2912.0",
    "gn:asciiname":"Thawmah",
    "gn:country_code":"YE",
    "gn:dem":2522,
    "gn:feature_class":"P",
    "gn:feature_code":"PPL",
    "gn:name":"Thawma\u1e29",
    "gn:population":0,
    "gn:timezone":"Asia/Aden",
    "iso:country":"YE",
    "name:und_x_variant":[
        "Thawma\u1e29"
    ],
    "wof:name":"Thawmah",
    "wof:placetype":"locality"
},
  "geometry": {"coordinates":[43.90579,15.78708],"type":"Point"}
}