{
  "type": "Feature",
  "properties": {
    "gn:admin1_code":"16.0",
    "gn:admin2_code":"2303.0",
    "gn:asciiname":"Al Farhah",
    "gn:country_code":"YE",
    "gn:dem":1877,
    "gn:feature_class":"P",
    "gn:feature_code":"PPLL",
    "gn:name":"Al Far\u1e29ah",
    "gn:population":0,
    "gn:timezone":"Asia/Aden",
    "iso:country":"YE",
    "name:ara_x_preferred":[
        "\u0627\u0644\u0641\u0631\u062d\u0629"
    ],
    "name:und_x_variant":[
        "Al Far\u1e29ah"
    ],
    "wof:name":"Al Farhah",
    "wof:placetype":"locality"
},
  "geometry": {"coordinates":[44.49042,15.85459],"type":"Point"}
}