{
  "type": "Feature",
  "properties": {
    "gn:admin1_code":"8.0",
    "gn:admin2_code":"1810.0",
    "gn:asciiname":"Dayr al Manzar",
    "gn:country_code":"YE",
    "gn:dem":41,
    "gn:feature_class":"P",
    "gn:feature_code":"PPL",
    "gn:name":"Dayr al Manz\u0327ar",
    "gn:population":0,
    "gn:timezone":"Asia/Aden",
    "iso:country":"YE",
    "name:und_x_variant":[
        "Dayr al Manz\u0327ar"
    ],
    "wof:name":"Dayr al Manzar",
    "wof:placetype":"locality"
},
  "geometry": {"coordinates":[43.01402,14.98205],"type":"Point"}
}