{
  "type": "Feature",
  "properties": {
    "gn:country":"YE",
    "gn:fcode":"PPL",
    "gn:population":2,
    "iso:country":"YE",
    "name:ara_x_preferred":[
        "\u0627\u0644\u062d\u0648\u064a\u0629"
    ],
    "name:eng_x_preferred":[
        "Al Huwayyah"
    ],
    "name:eng_x_variant":[
        "Di\u2018y\u0101\u2019"
    ],
    "qs_pg:aaroncc":"YE",
    "qs_pg:gn_country":"YE",
    "qs_pg:gn_fcode":"PPL",
    "qs_pg:gn_pop":2,
    "qs_pg:name":"Al \u1e28uwayyah",
    "qs_pg:photos_9r":0,
    "qs_pg:photos_sr":0,
    "qs_pg:pop_sr":1,
    "qs_pg:qs_pg_placetype":"locality",
    "wof:name":"Al \u1e28uwayyah",
    "wof:placetype":"locality",
    "wof:population":2
},
  "geometry": {"coordinates":[45.5228,15.00308],"type":"Point"}
}