{
  "type": "Feature",
  "properties": {
    "gn:admin1_code":"19.0",
    "gn:admin2_code":"2909.0",
    "gn:asciiname":"`Iyal Yahya",
    "gn:country_code":"YE",
    "gn:dem":1926,
    "gn:feature_class":"P",
    "gn:feature_code":"PPL",
    "gn:name":"\u2018Iy\u0101l Ya\u1e29y\u00e1",
    "gn:population":0,
    "gn:timezone":"Asia/Aden",
    "iso:country":"YE",
    "name:und_x_variant":[
        "\u2018Iy\u0101l Ya\u1e29y\u00e1"
    ],
    "wof:name":"`Iyal Yahya",
    "wof:placetype":"locality"
},
  "geometry": {"coordinates":[44.11538,15.98046],"type":"Point"}
}