{
  "type": "Feature",
  "properties": {
    "gn:admin1_code":"25.0",
    "gn:admin2_code":"1517.0",
    "gn:asciiname":"Dhari' al Karish",
    "gn:country_code":"YE",
    "gn:dem":1262,
    "gn:feature_class":"P",
    "gn:feature_code":"PPL",
    "gn:name":"Dh\u0101ri\u2018 al Kar\u012bsh",
    "gn:population":0,
    "gn:timezone":"Asia/Aden",
    "iso:country":"YE",
    "name:ara_x_preferred":[
        "\u0630\u0627\u0631\u0639 \u0627\u0644\u0643\u0631\u064a\u0634"
    ],
    "name:und_x_variant":[
        "Dh\u0101ri\u2018 al Kar\u012bsh"
    ],
    "wof:name":"Dhari' al Karish",
    "wof:placetype":"locality"
},
  "geometry": {"coordinates":[44.24886,13.21861],"type":"Point"}
}