{
  "type": "Feature",
  "properties": {
    "gn:admin1_code":"24.0",
    "gn:admin2_code":"2512.0",
    "gn:asciiname":"Al 'Amid",
    "gn:country_code":"YE",
    "gn:dem":1171,
    "gn:feature_class":"P",
    "gn:feature_code":"PPL",
    "gn:name":"Al \u2018Am\u012bd",
    "gn:population":0,
    "gn:timezone":"Asia/Aden",
    "iso:country":"YE",
    "name:ara_x_preferred":[
        "\u0627\u0644\u0639\u0645\u064a\u062f"
    ],
    "name:und_x_variant":[
        "Al \u2018Am\u012bd"
    ],
    "wof:name":"Al 'Amid",
    "wof:placetype":"locality"
},
  "geometry": {"coordinates":[44.20057,13.21046],"type":"Point"}
}