{
  "type": "Feature",
  "properties": {
    "gn:admin1_code":"23.0",
    "gn:admin2_code":"1109.0",
    "gn:asciiname":"An Nujud",
    "gn:country_code":"YE",
    "gn:dem":1369,
    "gn:feature_class":"P",
    "gn:feature_code":"PPL",
    "gn:name":"An Nuj\u016bd",
    "gn:population":0,
    "gn:timezone":"Asia/Aden",
    "iso:country":"YE",
    "name:ara_x_preferred":[
        "An Nuj\u016bd"
    ],
    "name:ara_x_variant":[
        "\u0627\u0644\u0646\u062c\u0648\u062f"
    ],
    "wof:name":"An Nujud",
    "wof:placetype":"locality"
},
  "geometry": {"coordinates":[43.95627,14.11188],"type":"Point"}
}