{
  "type": "Feature",
  "properties": {
    "gn:admin1_code":"22.0",
    "gn:admin2_code":"1724.0",
    "gn:asciiname":"Al Musayra'",
    "gn:country_code":"YE",
    "gn:dem":436,
    "gn:feature_class":"P",
    "gn:feature_code":"PPL",
    "gn:name":"Al Mu\u015fayr\u0101\u2019",
    "gn:population":0,
    "gn:timezone":"Asia/Aden",
    "iso:country":"YE",
    "name:und_x_variant":[
        "Al Mu\u015fayr\u0101\u2019"
    ],
    "wof:name":"Al Musayra'",
    "wof:placetype":"locality"
},
  "geometry": {"coordinates":[43.37995,15.74118],"type":"Point"}
}