{
  "type": "Feature",
  "properties": {
    "gn:admin1_code":"25.0",
    "gn:admin2_code":"1502.0",
    "gn:asciiname":"Shi`b as Sawa'",
    "gn:country_code":"YE",
    "gn:dem":1421,
    "gn:feature_class":"P",
    "gn:feature_code":"PPL",
    "gn:name":"Shi\u2018b as Saw\u0101\u2019",
    "gn:population":0,
    "gn:timezone":"Asia/Aden",
    "iso:country":"YE",
    "name:und_x_variant":[
        "Shi\u2018b as Saw\u0101\u2019"
    ],
    "wof:name":"Shi`b as Sawa'",
    "wof:placetype":"locality"
},
  "geometry": {"coordinates":[44.06346,13.70436],"type":"Point"}
}