{
  "type": "Feature",
  "properties": {
    "gn:admin1_code":"25.0",
    "gn:admin2_code":"1501.0",
    "gn:asciiname":"Al Qub`ah",
    "gn:country_code":"YE",
    "gn:dem":1043,
    "gn:feature_class":"P",
    "gn:feature_code":"PPL",
    "gn:name":"Al Qub\u2018ah",
    "gn:population":0,
    "gn:timezone":"Asia/Aden",
    "iso:country":"YE",
    "name:und_x_variant":[
        "Al Qub\u2018ah"
    ],
    "wof:name":"Al Qub`ah",
    "wof:placetype":"locality"
},
  "geometry": {"coordinates":[44.38902,13.54196],"type":"Point"}
}