{
  "type": "Feature",
  "properties": {
    "gn:admin1_code":"16.0",
    "gn:admin2_code":"2313.0",
    "gn:asciiname":"Basiq",
    "gn:country_code":"YE",
    "gn:dem":2494,
    "gn:feature_class":"P",
    "gn:feature_code":"PPL",
    "gn:name":"B\u0101siq",
    "gn:population":0,
    "gn:timezone":"Asia/Aden",
    "iso:country":"YE",
    "name:ara_x_preferred":[
        "B\u0101siq"
    ],
    "wof:name":"Basiq",
    "wof:placetype":"locality"
},
  "geometry": {"coordinates":[44.50443,15.45703],"type":"Point"}
}