{
  "type": "Feature",
  "properties": {
    "gn:admin1_code":"4.0",
    "gn:admin2_code":"1910.0",
    "gn:asciiname":"Sawm Bin Hammam",
    "gn:cc2":"YE",
    "gn:country_code":"YE",
    "gn:dem":652,
    "gn:feature_class":"P",
    "gn:feature_code":"PPL",
    "gn:name":"Sawm Bin \u1e28amm\u0101m",
    "gn:population":0,
    "gn:timezone":"Asia/Aden",
    "iso:country":"YE",
    "name:und_x_variant":[
        "Saum Bin \u1e24amm\u0101m",
        "Sawm Bin \u1e28amm\u0101m"
    ],
    "wof:name":"Sawm Bin Hammam",
    "wof:placetype":"locality"
},
  "geometry": {"coordinates":[48.76667,15.93333],"type":"Point"}
}