{
  "type": "Feature",
  "properties": {
    "gn:admin1_code":"18.0",
    "gn:admin2_code":"3004.0",
    "gn:asciiname":"Al Ahsun",
    "gn:country_code":"YE",
    "gn:dem":1977,
    "gn:feature_class":"P",
    "gn:feature_code":"PPL",
    "gn:name":"Al A\u1e29\u015f\u016bn",
    "gn:population":0,
    "gn:timezone":"Asia/Aden",
    "iso:country":"YE",
    "name:ara_x_preferred":[
        "Al A\u1e29\u015f\u016bn"
    ],
    "name:und_x_variant":[
        "Ekdid",
        "Aqd\u012bd"
    ],
    "wof:name":"Al Ahsun",
    "wof:placetype":"locality"
},
  "geometry": {"coordinates":[44.82992,13.8668],"type":"Point"}
}