{
  "type": "Feature",
  "properties": {
    "gn:admin1_code":"19.0",
    "gn:admin2_code":"2914.0",
    "gn:asciiname":"Karin",
    "gn:country_code":"YE",
    "gn:dem":1815,
    "gn:feature_class":"P",
    "gn:feature_code":"PPL",
    "gn:name":"K\u0101rin",
    "gn:population":0,
    "gn:timezone":"Asia/Aden",
    "iso:country":"YE",
    "name:ara_x_preferred":[
        "K\u0101rin"
    ],
    "name:und_x_variant":[
        "Qal\u2018a"
    ],
    "wof:name":"Karin",
    "wof:placetype":"locality"
},
  "geometry": {"coordinates":[43.78333,15.85],"type":"Point"}
}