{
  "type": "Feature",
  "properties": {
    "gn:country":"YE",
    "gn:fcode":"PPL",
    "gn:pop":28,
    "iso:country":"YE",
    "name:ara_x_preferred":[
        "\u062c\u0639\u062f\u0628"
    ],
    "name:eng_x_preferred":[
        "Ja'dab"
    ],
    "name:eng_x_variant":[
        "Al \u1e28aj\u0101wirah"
    ],
    "qs:name":"Ja\u2018dab",
    "qs:photos_9r":0,
    "qs:photos_sr":0,
    "qs:pop_sr":"1",
    "wof:name":"Ja\u2018dab",
    "wof:placetype":"locality",
    "wof:population":28
},
  "geometry": {"coordinates":[43.6577,16.88546],"type":"Point"}
}