{
  "type": "Feature",
  "properties": {
    "gn:admin1_code":"16.0",
    "gn:admin2_code":"2307.0",
    "gn:asciiname":"Al Qasr",
    "gn:country_code":"YE",
    "gn:dem":3032,
    "gn:feature_class":"P",
    "gn:feature_code":"PPL",
    "gn:name":"Al Qa\u015fr",
    "gn:population":0,
    "gn:timezone":"Asia/Aden",
    "iso:country":"YE",
    "name:und_x_variant":[
        "Al Qa\u015fr"
    ],
    "wof:name":"Al Qasr",
    "wof:placetype":"locality"
},
  "geometry": {"coordinates":[43.99732,15.29908],"type":"Point"}
}