{
  "type": "Feature",
  "properties": {
    "gn:country":"YE",
    "gn:fcode":"PPL",
    "gn:pop":2,
    "iso:country":"YE",
    "name:ara_x_preferred":[
        "\u0628\u0646\u0649 \u0645\u0635\u0644\u062d"
    ],
    "name:eng_x_preferred":[
        "Bani Maslah"
    ],
    "qs:name":"Ban\u012b Ma\u015fla\u1e29",
    "qs:photos_9r":0,
    "qs:photos_sr":0,
    "qs:pop_sr":"1",
    "wof:name":"Ban\u012b Ma\u015fla\u1e29",
    "wof:placetype":"locality",
    "wof:population":2
},
  "geometry": {"coordinates":[43.35203,16.16946],"type":"Point"}
}