{
  "type": "Feature",
  "properties": {
    "gn:admin1_code":"15.0",
    "gn:admin2_code":"2207.0",
    "gn:asciiname":"Al Hassamah",
    "gn:country_code":"YE",
    "gn:dem":311,
    "gn:feature_class":"P",
    "gn:feature_code":"PPL",
    "gn:name":"Al \u1e28a\u015f\u015f\u0101mah",
    "gn:population":0,
    "gn:timezone":"Asia/Aden",
    "iso:country":"YE",
    "name:ara_x_preferred":[
        "\u0627\u0644\u062d\u0635\u0627\u0645\u0629"
    ],
    "name:und_x_variant":[
        "Al \u1e28a\u015f\u015f\u0101mah"
    ],
    "wof:name":"Al Hassamah",
    "wof:placetype":"locality"
},
  "geometry": {"coordinates":[43.23953,16.81497],"type":"Point"}
}