{
  "type": "Feature",
  "properties": {
    "gn:admin1_code":"8.0",
    "gn:admin2_code":"1810.0",
    "gn:asciiname":"Al Quhamiyah",
    "gn:country_code":"YE",
    "gn:dem":145,
    "gn:feature_class":"P",
    "gn:feature_code":"PPL",
    "gn:name":"Al Qu\u1e29\u0101m\u012byah",
    "gn:population":0,
    "gn:timezone":"Asia/Aden",
    "iso:country":"YE",
    "name:ara_x_preferred":[
        "\u0627\u0644\u0642\u062d\u0627\u0645\u064a\u0629"
    ],
    "name:und_x_variant":[
        "Ma\u1e29all al Q\u0101dir \u2018Abdah",
        "Al Qu\u1e29\u0101m\u012byah",
        "Ma\u1e29all al Q\u0101dir \u2018Abduh"
    ],
    "wof:name":"Al Quhamiyah",
    "wof:placetype":"locality"
},
  "geometry": {"coordinates":[43.19998,15.16601],"type":"Point"}
}