{
  "type": "Feature",
  "properties": {
    "gn:country":"YE",
    "gn:fcode":"PPL",
    "gn:pop":2,
    "iso:country":"YE",
    "name:ara_x_preferred":[
        "\u0634\u0631\u0642\u0629"
    ],
    "qs:name":"Sharqah",
    "qs:photos_9r":0,
    "qs:photos_sr":0,
    "qs:pop_sr":"1",
    "wd:wordcount":2661,
    "wof:name":"Sharqah",
    "wof:placetype":"locality",
    "wof:population":2
},
  "geometry": {"coordinates":[43.43015,16.4092],"type":"Point"}
}