{
  "type": "Feature",
  "properties": {
    "gn:admin1_code":"25.0",
    "gn:admin2_code":"1515.0",
    "gn:asciiname":"Masajid Adim",
    "gn:country_code":"YE",
    "gn:dem":1769,
    "gn:feature_class":"P",
    "gn:feature_code":"PPL",
    "gn:name":"Mas\u0101jid Ad\u012bm",
    "gn:population":0,
    "gn:timezone":"Asia/Aden",
    "iso:country":"YE",
    "wof:name":"Masajid Adim",
    "wof:placetype":"locality"
},
  "geometry": {"coordinates":[44.125,13.18333],"type":"Point"}
}