{
  "type": "Feature",
  "properties": {
    "gn:admin1_code":"23.0",
    "gn:admin2_code":"1101.0",
    "gn:asciiname":"'Arshah",
    "gn:country_code":"YE",
    "gn:dem":1539,
    "gn:feature_class":"P",
    "gn:feature_code":"PPL",
    "gn:name":"\u2018Arshah",
    "gn:population":0,
    "gn:timezone":"Asia/Aden",
    "iso:country":"YE",
    "name:ara_x_preferred":[
        "\u0639\u0631\u0634\u0629"
    ],
    "name:und_x_variant":[
        "\u2018Arshah"
    ],
    "wof:name":"'Arshah",
    "wof:placetype":"locality"
},
  "geometry": {"coordinates":[44.14264,14.33084],"type":"Point"}
}