{
  "type": "Feature",
  "properties": {
    "gn:admin1_code":"25.0",
    "gn:admin2_code":"1521.0",
    "gn:asciiname":"Subayrah",
    "gn:country_code":"YE",
    "gn:dem":1307,
    "gn:feature_class":"P",
    "gn:feature_code":"PPL",
    "gn:name":"\u015eubayrah",
    "gn:population":0,
    "gn:timezone":"Asia/Aden",
    "iso:country":"YE",
    "name:und_x_variant":[
        "\u015eubayrah"
    ],
    "wof:name":"Subayrah",
    "wof:placetype":"locality"
},
  "geometry": {"coordinates":[44.06372,13.35287],"type":"Point"}
}