{
  "type": "Feature",
  "properties": {
    "gn:admin1_code":"16.0",
    "gn:admin2_code":"2307.0",
    "gn:asciiname":"Wadhah",
    "gn:country_code":"YE",
    "gn:dem":2982,
    "gn:feature_class":"P",
    "gn:feature_code":"PPL",
    "gn:name":"Wa\u1e11\u1e29ah",
    "gn:population":0,
    "gn:timezone":"Asia/Aden",
    "iso:country":"YE",
    "name:und_x_variant":[
        "Wa\u1e11\u1e29ah"
    ],
    "wof:name":"Wadhah",
    "wof:placetype":"locality"
},
  "geometry": {"coordinates":[43.98999,15.30159],"type":"Point"}
}