{
  "type": "Feature",
  "properties": {
    "gn:admin1_code":"20.0",
    "gn:admin2_code":"1414.0",
    "gn:asciiname":"Kuraydim",
    "gn:country_code":"YE",
    "gn:dem":1814,
    "gn:feature_class":"P",
    "gn:feature_code":"PPL",
    "gn:name":"Kuraydim",
    "gn:population":0,
    "gn:timezone":"Asia/Aden",
    "iso:country":"YE",
    "name:ara_x_preferred":[
        "\u0643\u0631\u064a\u062f\u0645"
    ],
    "wof:name":"Kuraydim",
    "wof:placetype":"locality"
},
  "geometry": {"coordinates":[44.90525,14.66098],"type":"Point"}
}