{
  "type": "Feature",
  "properties": {
    "gn:admin1_code":"19.0",
    "gn:admin2_code":"2912.0",
    "gn:asciiname":"Bayt at Tammah",
    "gn:country_code":"YE",
    "gn:dem":2343,
    "gn:feature_class":"P",
    "gn:feature_code":"PPL",
    "gn:name":"Bayt a\u0163 \u0162amm\u0101\u1e29",
    "gn:population":0,
    "gn:timezone":"Asia/Aden",
    "iso:country":"YE",
    "name:und_x_variant":[
        "Bayt a\u0163 \u0162amm\u0101\u1e29"
    ],
    "wof:name":"Bayt at Tammah",
    "wof:placetype":"locality"
},
  "geometry": {"coordinates":[43.77933,15.7166],"type":"Point"}
}