{
  "type": "Feature",
  "properties": {
    "gn:country":"YE",
    "gn:fcode":"PPLX",
    "gn:pop":2,
    "iso:country":"YE",
    "name:ara_x_preferred":[
        "\u0641\u0648\u0642 \u0627\u0644\u0628\u0631\u0643\u0629"
    ],
    "qs:name":"Fawq al Birkah",
    "qs:photos_9r":0,
    "qs:photos_sr":0,
    "qs:pop_sr":"1",
    "wof:name":"Fawq al Birkah",
    "wof:placetype":"neighbourhood",
    "wof:population":2
},
  "geometry": {"coordinates":[43.69688,16.21708],"type":"Point"}
}