{
  "type": "Feature",
  "properties": {
    "gn:admin1_code":"23.0",
    "gn:admin2_code":"1111.0",
    "gn:asciiname":"Al Ahmud Qudas",
    "gn:country_code":"YE",
    "gn:dem":1371,
    "gn:feature_class":"P",
    "gn:feature_code":"PPL",
    "gn:name":"Al A\u1e29m\u016bd Qud\u0101s",
    "gn:population":0,
    "gn:timezone":"Asia/Aden",
    "iso:country":"YE",
    "name:ara_x_preferred":[
        "Al A\u1e29m\u016bd Qud\u0101s"
    ],
    "wof:name":"Al Ahmud Qudas",
    "wof:placetype":"locality"
},
  "geometry": {"coordinates":[43.82638,14.02476],"type":"Point"}
}