{
  "type": "Feature",
  "properties": {
    "gn:admin1_code":"8.0",
    "gn:admin2_code":"1802.0",
    "gn:asciiname":"Al Mishqaq",
    "gn:country_code":"YE",
    "gn:dem":68,
    "gn:feature_class":"P",
    "gn:feature_code":"PPL",
    "gn:name":"Al Mishq\u0101q",
    "gn:population":0,
    "gn:timezone":"Asia/Aden",
    "iso:country":"YE",
    "name:ara_x_preferred":[
        "\u0627\u0644\u0645\u0634\u0642\u0640\u0627\u0642"
    ],
    "name:und_x_variant":[
        "Al Mishq\u0101q"
    ],
    "wof:name":"Al Mishqaq",
    "wof:placetype":"locality"
},
  "geometry": {"coordinates":[42.98025,15.69147],"type":"Point"}
}