{
  "type": "Feature",
  "properties": {
    "gn:admin1_code":"15.0",
    "gn:admin2_code":"2202.0",
    "gn:asciiname":"Al Qa`ban",
    "gn:country_code":"YE",
    "gn:dem":2371,
    "gn:feature_class":"P",
    "gn:feature_code":"PPL",
    "gn:name":"\u0100l Qa\u2018b\u0101n",
    "gn:population":0,
    "gn:timezone":"Asia/Aden",
    "iso:country":"YE",
    "name:ara_x_preferred":[
        "\u0627\u0644 \u0642\u0628\u0639\u0627\u0646"
    ],
    "name:und_x_variant":[
        "Adh Dh\u0101r\u012b \u0100l Qa\u2018b\u0101n",
        "\u0100l Qa\u2018b\u0101n"
    ],
    "wof:name":"Al Qa`ban",
    "wof:placetype":"locality"
},
  "geometry": {"coordinates":[43.40193,17.29159],"type":"Point"}
}