{
  "type": "Feature",
  "properties": {
    "gn:admin1_code":"21.0",
    "gn:admin2_code":"1602.0",
    "gn:asciiname":"Bayt Al 'Azib",
    "gn:country_code":"YE",
    "gn:dem":1311,
    "gn:feature_class":"P",
    "gn:feature_code":"PPL",
    "gn:name":"Bayt \u0100l \u2018Az\u0327\u012bb",
    "gn:population":0,
    "gn:timezone":"Asia/Aden",
    "iso:country":"YE",
    "name:ara_x_preferred":[
        "\u0628\u064a\u062a \u0622\u0644 \u0639\u0638\u064a\u0628"
    ],
    "name:und_x_variant":[
        "Bayt \u0100l \u2018Az\u0327\u012bb"
    ],
    "wof:name":"Bayt Al 'Azib",
    "wof:placetype":"locality"
},
  "geometry": {"coordinates":[44.4393,16.48811],"type":"Point"}
}