{
  "type": "Feature",
  "properties": {
    "gn:admin1_code":"19.0",
    "gn:admin2_code":"2905.0",
    "gn:asciiname":"Al Gharib",
    "gn:country_code":"YE",
    "gn:dem":2126,
    "gn:feature_class":"P",
    "gn:feature_code":"PPL",
    "gn:name":"Al Gh\u0101rib",
    "gn:population":0,
    "gn:timezone":"Asia/Aden",
    "iso:country":"YE",
    "name:ara_x_preferred":[
        "Al Gh\u0101rib"
    ],
    "wof:name":"Al Gharib",
    "wof:placetype":"locality"
},
  "geometry": {"coordinates":[43.7216,16.19559],"type":"Point"}
}