{
  "type": "Feature",
  "properties": {
    "gn:admin1_code":"15.0",
    "gn:admin2_code":"2211.0",
    "gn:asciiname":"Khiyam Sahhar",
    "gn:cc2":"YE",
    "gn:country_code":"YE",
    "gn:dem":2160,
    "gn:feature_class":"P",
    "gn:feature_code":"PPL",
    "gn:name":"Khiy\u0101m Sa\u1e29\u1e29\u0101r",
    "gn:population":0,
    "gn:timezone":"Asia/Aden",
    "iso:country":"YE",
    "name:und_x_variant":[
        "Khiyam Sih\u0101r",
        "Khiy\u0101m Sa\u1e29\u0101r",
        "Khiy\u0101m Sa\u1e29\u1e29\u0101r"
    ],
    "wof:name":"Khiyam Sahhar",
    "wof:placetype":"locality"
},
  "geometry": {"coordinates":[43.73333,16.78333],"type":"Point"}
}