{
  "type": "Feature",
  "properties": {
    "gn:admin1_code":"20.0",
    "gn:admin2_code":"1416.0",
    "gn:asciiname":"As Suwar",
    "gn:country_code":"YE",
    "gn:dem":2142,
    "gn:feature_class":"P",
    "gn:feature_code":"PPL",
    "gn:name":"As Suw\u0101r",
    "gn:population":0,
    "gn:timezone":"Asia/Aden",
    "iso:country":"YE",
    "name:ara_x_preferred":[
        "As Suw\u0101r"
    ],
    "wof:name":"As Suwar",
    "wof:placetype":"locality"
},
  "geometry": {"coordinates":[44.81714,14.31131],"type":"Point"}
}