{
  "type": "Feature",
  "properties": {
    "gn:country":"YE",
    "gn:fcode":"PPL",
    "gn:population":12,
    "iso:country":"YE",
    "name:ara_x_preferred":[
        "Adh Dhiy\u0101b"
    ],
    "name:ara_x_variant":[
        "\u0627\u0644\u0630\u064a\u0627\u0628"
    ],
    "name:eng_x_preferred":[
        "Adh Dhiyab"
    ],
    "name:eng_x_variant":[
        "Ash Shurayj"
    ],
    "qs:name":"Adh Dhiy\u0101b",
    "qs:photos_9r":0,
    "qs:photos_sr":0,
    "qs:pop_sr":"1",
    "wof:name":"Adh Dhiy\u0101b",
    "wof:placetype":"locality",
    "wof:population":12
},
  "geometry": {"coordinates":[44.22142,16.85025],"type":"Point"}
}