{
  "type": "Feature",
  "properties": {
    "gn:admin1_code":"14.0",
    "gn:admin2_code":"2606.0",
    "gn:asciiname":"Al Masariyah",
    "gn:country_code":"YE",
    "gn:dem":1538,
    "gn:feature_class":"P",
    "gn:feature_code":"PPL",
    "gn:name":"Al Ma\u015f\u0101r\u012byah",
    "gn:population":0,
    "gn:timezone":"Asia/Aden",
    "iso:country":"YE",
    "name:ara_x_preferred":[
        "\u0627\u0644\u0645\u0635\u0627\u0631\u064a\u0629"
    ],
    "name:und_x_variant":[
        "Al Ma\u015f\u0101r\u012byah"
    ],
    "wof:name":"Al Masariyah",
    "wof:placetype":"locality"
},
  "geometry": {"coordinates":[45.06614,15.47285],"type":"Point"}
}