{
  "type": "Feature",
  "properties": {
    "gn:admin1_code":"11.0",
    "gn:admin2_code":"2011.0",
    "gn:asciiname":"Al Mahrum",
    "gn:country_code":"YE",
    "gn:dem":2347,
    "gn:feature_class":"P",
    "gn:feature_code":"PPL",
    "gn:name":"Al Ma\u1e29r\u016bm",
    "gn:population":0,
    "gn:timezone":"Asia/Aden",
    "iso:country":"YE",
    "name:und_x_variant":[
        "Al Ma\u1e29r\u016bm"
    ],
    "wof:name":"Al Mahrum",
    "wof:placetype":"locality"
},
  "geometry": {"coordinates":[44.06226,14.72372],"type":"Point"}
}