{
  "type": "Feature",
  "properties": {
    "gn:admin1_code":"21.0",
    "gn:admin2_code":"1611.0",
    "gn:asciiname":"Al Qari",
    "gn:country_code":"YE",
    "gn:dem":2091,
    "gn:feature_class":"P",
    "gn:feature_code":"PPL",
    "gn:name":"Al Qar\u012b",
    "gn:population":0,
    "gn:timezone":"Asia/Aden",
    "iso:country":"YE",
    "name:ara_x_preferred":[
        "\u0627\u0644\u0642\u0631\u064a"
    ],
    "name:und_x_variant":[
        "Al Qar\u012b"
    ],
    "wof:name":"Al Qari",
    "wof:placetype":"locality"
},
  "geometry": {"coordinates":[44.41634000000001,16.68021],"type":"Point"}
}