{
  "type": "Feature",
  "properties": {
    "gn:admin1_code":"15.0",
    "gn:admin2_code":"2207.0",
    "gn:asciiname":"Ar Rawbah",
    "gn:country_code":"YE",
    "gn:dem":344,
    "gn:feature_class":"P",
    "gn:feature_code":"PPL",
    "gn:name":"Ar Rawbah",
    "gn:population":0,
    "gn:timezone":"Asia/Aden",
    "iso:country":"YE",
    "name:ara_x_preferred":[
        "\u0627\u0644\u0631\u0648\u0628\u0629"
    ],
    "wof:name":"Ar Rawbah",
    "wof:placetype":"locality"
},
  "geometry": {"coordinates":[43.23418,16.82484],"type":"Point"}
}