{
  "type": "Feature",
  "properties": {
    "gn:country":"YE",
    "gn:fcode":"PPL",
    "gn:pop":12,
    "iso:country":"YE",
    "name:ara_x_preferred":[
        "\u0627\u0644\u0645\u0639\u0632\u064a\u0628\u0629"
    ],
    "name:eng_x_preferred":[
        "Al Mu'zaybah"
    ],
    "qs:name":"Al Mu\u2018zaybah",
    "qs:photos_9r":0,
    "qs:photos_sr":0,
    "qs:pop_sr":"1",
    "wof:name":"Al Mu\u2018zaybah",
    "wof:placetype":"locality",
    "wof:population":12
},
  "geometry": {"coordinates":[43.381,16.02782],"type":"Point"}
}