{
  "type": "Feature",
  "properties": {
    "gn:admin1_code":"11.0",
    "gn:asciiname":"Al Jabub",
    "gn:country_code":"YE",
    "gn:dem":2154,
    "gn:feature_class":"P",
    "gn:feature_code":"PPL",
    "gn:name":"Al Jab\u016bb",
    "gn:population":0,
    "gn:timezone":"Asia/Aden",
    "iso:country":"YE",
    "name:ara_x_preferred":[
        "\u0627\u0644\u062c\u0628\u0648\u0628"
    ],
    "name:und_x_variant":[
        "Al Jab\u016bb"
    ],
    "wof:name":"Al Jabub",
    "wof:placetype":"locality"
},
  "geometry": {"coordinates":[44.2817,14.36077],"type":"Point"}
}