{
  "type": "Feature",
  "properties": {
    "gn:country":"YE",
    "gn:fcode":"MKT",
    "gn:population":2,
    "iso:country":"YE",
    "name:ara_x_preferred":[
        "\u062e\u0631\u0627\u0628 \u0633\u0648\u0642 \u0627\u0644\u062b\u0644\u0648\u062b"
    ],
    "qs:name":"Khar\u0101b S\u016bq ath Thal\u016bth",
    "qs:photos_9r":0,
    "qs:photos_sr":0,
    "qs:pop_sr":"1",
    "wof:name":"Khar\u0101b S\u016bq ath Thal\u016bth",
    "wof:placetype":"locality",
    "wof:population":2
},
  "geometry": {"coordinates":[43.34532,16.99181],"type":"Point"}
}