{
  "type": "Feature",
  "properties": {
    "gn:admin1_code":"14.0",
    "gn:admin2_code":"2611.0",
    "gn:asciiname":"Al Hijlah",
    "gn:country_code":"YE",
    "gn:dem":2058,
    "gn:feature_class":"P",
    "gn:feature_code":"PPL",
    "gn:name":"Al \u1e28ijlah",
    "gn:population":0,
    "gn:timezone":"Asia/Aden",
    "iso:country":"YE",
    "name:ara_x_preferred":[
        "\u0627\u0644\u062d\u062c\u0644\u0629"
    ],
    "name:und_x_variant":[
        "Al \u1e28ijlah"
    ],
    "wof:name":"Al Hijlah",
    "wof:placetype":"locality"
},
  "geometry": {"coordinates":[45.32849,14.63577],"type":"Point"}
}