{
  "type": "Feature",
  "properties": {
    "gn:admin1_code":"8.0",
    "gn:admin2_code":"1812.0",
    "gn:asciiname":"Ad Darah",
    "gn:country_code":"YE",
    "gn:dem":1364,
    "gn:feature_class":"P",
    "gn:feature_code":"PPL",
    "gn:name":"Ad D\u0101rah",
    "gn:population":0,
    "gn:timezone":"Asia/Aden",
    "iso:country":"YE",
    "name:ara_x_preferred":[
        "\u0627\u0644\u062f\u0627\u0631\u0629"
    ],
    "name:und_x_variant":[
        "Ad D\u0101rah"
    ],
    "wof:name":"Ad Darah",
    "wof:placetype":"locality"
},
  "geometry": {"coordinates":[43.43501,14.91392],"type":"Point"}
}