{
  "type": "Feature",
  "properties": {
    "gn:country":"YE",
    "gn:fcode":"PPL",
    "gn:population":52,
    "iso:country":"YE",
    "name:ara_x_preferred":[
        "\u0627\u0644\u0645\u0634\u064a\u0628"
    ],
    "qs:name":"Al Mushayb",
    "qs:photos_9r":0,
    "qs:photos_sr":0,
    "qs:pop_sr":"1",
    "wof:name":"Al Mushayb",
    "wof:placetype":"locality",
    "wof:population":52
},
  "geometry": {"coordinates":[43.35094,16.15459],"type":"Point"}
}