{
  "type": "Feature",
  "properties": {
    "gn:admin1_code":"15.0",
    "gn:admin2_code":"2205.0",
    "gn:asciiname":"Al Makhnaq",
    "gn:country_code":"YE",
    "gn:dem":636,
    "gn:feature_class":"P",
    "gn:feature_code":"PPL",
    "gn:name":"Al Makhnaq",
    "gn:population":0,
    "gn:timezone":"Asia/Aden",
    "iso:country":"YE",
    "wof:name":"Al Makhnaq",
    "wof:placetype":"locality"
},
  "geometry": {"coordinates":[43.22217,16.89961],"type":"Point"}
}