{
  "type": "Feature",
  "properties": {
    "gn:admin1_code":"20.0",
    "gn:asciiname":"Al Haqqah",
    "gn:country_code":"YE",
    "gn:dem":2483,
    "gn:feature_class":"P",
    "gn:feature_code":"PPL",
    "gn:name":"Al \u1e28aqqah",
    "gn:population":0,
    "gn:timezone":"Asia/Aden",
    "iso:country":"YE",
    "name:ara_x_preferred":[
        "\u0627\u0644\u062d\u0642\u0629"
    ],
    "name:und_x_variant":[
        "Al \u1e28aqqah"
    ],
    "wof:name":"Al Haqqah",
    "wof:placetype":"locality"
},
  "geometry": {"coordinates":[44.27857,14.47376],"type":"Point"}
}