{
  "type": "Feature",
  "properties": {
    "gn:admin1_code":"23.0",
    "gn:admin2_code":"1106.0",
    "gn:asciiname":"Al Jamri",
    "gn:country_code":"YE",
    "gn:dem":2325,
    "gn:feature_class":"P",
    "gn:feature_code":"PPL",
    "gn:name":"Al Jamr\u012b",
    "gn:population":0,
    "gn:timezone":"Asia/Aden",
    "iso:country":"YE",
    "name:ara_x_preferred":[
        "\u0627\u0644\u062c\u0645\u0631\u064a"
    ],
    "name:und_x_variant":[
        "Al Jumar\u012b",
        "Al Jamr\u012b"
    ],
    "wof:name":"Al Jamri",
    "wof:placetype":"locality"
},
  "geometry": {"coordinates":[44.40689,14.11341],"type":"Point"}
}