{
  "type": "Feature",
  "properties": {
    "gn:country":"YE",
    "gn:fcode":"PPL",
    "gn:population":5,
    "iso:country":"YE",
    "name:ara_x_preferred":[
        "\u0627\u0644\u0645\u0633\u0644\u0627\u0645 \u0628\u0646\u0649 \u0632\u064a\u0646"
    ],
    "name:eng_x_preferred":[
        "Al Mislam Bani Zayn"
    ],
    "name:eng_x_variant":[
        "\u0100l Firw\u0101n"
    ],
    "qs:name":"Al Misl\u0101m Ban\u012b Zayn",
    "qs:photos_9r":0,
    "qs:photos_sr":0,
    "qs:pop_sr":"1",
    "wof:name":"Al Misl\u0101m Ban\u012b Zayn",
    "wof:placetype":"locality",
    "wof:population":5
},
  "geometry": {"coordinates":[43.3149,16.1316],"type":"Point"}
}