{
  "type": "Feature",
  "properties": {
    "gn:admin1_code":"18.0",
    "gn:admin2_code":"3002.0",
    "gn:asciiname":"Qaryat Sihar",
    "gn:country_code":"YE",
    "gn:dem":2204,
    "gn:feature_class":"P",
    "gn:feature_code":"PPL",
    "gn:name":"Qaryat S\u012b\u1e29\u0101r",
    "gn:population":0,
    "gn:timezone":"Asia/Aden",
    "iso:country":"YE",
    "name:und_x_variant":[
        "Qaryat S\u012b\u1e29\u0101r"
    ],
    "wof:name":"Qaryat Sihar",
    "wof:placetype":"locality"
},
  "geometry": {"coordinates":[44.56572,14.03137],"type":"Point"}
}