{
  "type": "Feature",
  "properties": {
    "gn:admin1_code":"8.0",
    "gn:admin2_code":"1802.0",
    "gn:asciiname":"Mahall al 'Aqil",
    "gn:country_code":"YE",
    "gn:dem":38,
    "gn:feature_class":"P",
    "gn:feature_code":"PPL",
    "gn:name":"Ma\u1e29all al \u2018\u0100qil",
    "gn:population":0,
    "gn:timezone":"Asia/Aden",
    "iso:country":"YE",
    "name:ara_x_preferred":[
        "\u0645\u062d\u0644 \u0627\u0644\u0639\u0627\u0642\u0644"
    ],
    "name:und_x_variant":[
        "Ma\u1e29all al \u2018\u0100qil"
    ],
    "wof:name":"Mahall al 'Aqil",
    "wof:placetype":"locality"
},
  "geometry": {"coordinates":[42.90073,15.59628],"type":"Point"}
}