{
  "type": "Feature",
  "properties": {
    "gn:admin1_code":"21.0",
    "gn:admin2_code":"1603.0",
    "gn:asciiname":"As Sadarah",
    "gn:country_code":"YE",
    "gn:dem":1264,
    "gn:feature_class":"P",
    "gn:feature_code":"PPLL",
    "gn:name":"A\u015f \u015ead\u0101rah",
    "gn:population":0,
    "gn:timezone":"Asia/Aden",
    "iso:country":"YE",
    "name:ara_x_preferred":[
        "\u0627\u0644\u0635\u062f\u0627\u0631\u0629"
    ],
    "name:und_x_variant":[
        "A\u015f \u015ead\u0101rah"
    ],
    "wof:name":"As Sadarah",
    "wof:placetype":"locality"
},
  "geometry": {"coordinates":[44.38444000000001,16.2534],"type":"Point"}
}