{
  "type": "Feature",
  "properties": {
    "gn:admin1_code":"8.0",
    "gn:admin2_code":"1809.0",
    "gn:asciiname":"Al Harabah",
    "gn:country_code":"YE",
    "gn:dem":290,
    "gn:feature_class":"P",
    "gn:feature_code":"PPL",
    "gn:name":"Al \u1e28ar\u0101bah",
    "gn:population":0,
    "gn:timezone":"Asia/Aden",
    "iso:country":"YE",
    "name:und_x_variant":[
        "Al \u1e28ar\u0101bah"
    ],
    "wof:name":"Al Harabah",
    "wof:placetype":"locality"
},
  "geometry": {"coordinates":[43.32347,15.22975],"type":"Point"}
}