{
  "type": "Feature",
  "properties": {
    "gn:admin1_code":"4.0",
    "gn:admin2_code":"1923.0",
    "gn:asciiname":"Hisn Ghaytaq",
    "gn:cc2":"YE",
    "gn:country_code":"YE",
    "gn:dem":665,
    "gn:feature_class":"P",
    "gn:feature_code":"PPL",
    "gn:name":"\u1e28i\u015fn Ghay\u0163aq",
    "gn:population":0,
    "gn:timezone":"Asia/Aden",
    "iso:country":"YE",
    "name:und_x_variant":[
        "Gay\u0163aq",
        "Husn Ghail\u0101q",
        "\u1e28u\u015fn Ghay\u0163aq",
        "\u1e24u\u1e63n Ghai\u1e6daq",
        "\u1e28i\u015fn Ghay\u0163aq"
    ],
    "wof:name":"Hisn Ghaytaq",
    "wof:placetype":"locality"
},
  "geometry": {"coordinates":[47.85,14.58333],"type":"Point"}
}