{
  "type": "Feature",
  "properties": {
    "gn:admin1_code":"26.0",
    "gn:admin2_code":"1310.0",
    "gn:asciiname":"Al Hunbasi",
    "gn:country_code":"YE",
    "gn:dem":2163,
    "gn:feature_class":"P",
    "gn:feature_code":"PPL",
    "gn:name":"Al \u1e28unba\u015f\u012b",
    "gn:population":0,
    "gn:timezone":"Asia/Aden",
    "iso:country":"YE",
    "name:ara_x_preferred":[
        "\u0627\u0644\u062d\u0646\u0628\u0635\u064a"
    ],
    "name:und_x_variant":[
        "Al \u1e28unba\u015f\u012b"
    ],
    "wof:name":"Al Hunbasi",
    "wof:placetype":"locality"
},
  "geometry": {"coordinates":[44.24471,15.54115],"type":"Point"}
}