{
  "type": "Feature",
  "properties": {
    "gn:admin1_code":"19.0",
    "gn:admin2_code":"2901.0",
    "gn:asciiname":"Al Ghalsum",
    "gn:country_code":"YE",
    "gn:dem":1591,
    "gn:feature_class":"P",
    "gn:feature_code":"PPL",
    "gn:name":"Al Ghal\u015f\u016bm",
    "gn:population":0,
    "gn:timezone":"Asia/Aden",
    "iso:country":"YE",
    "name:ara_x_preferred":[
        "\u0627\u0644\u063a\u0644\u0635\u0648\u0645"
    ],
    "name:und_x_variant":[
        "Al Ghal\u015f\u016bm"
    ],
    "wof:name":"Al Ghalsum",
    "wof:placetype":"locality"
},
  "geometry": {"coordinates":[44.09055,16.43211],"type":"Point"}
}