{
  "type": "Feature",
  "properties": {
    "gn:admin1_code":"19.0",
    "gn:admin2_code":"2919.0",
    "gn:asciiname":"Bin Ghuli",
    "gn:country_code":"YE",
    "gn:dem":2539,
    "gn:feature_class":"P",
    "gn:feature_code":"PPL",
    "gn:name":"Bin Gh\u016bl\u012b",
    "gn:population":0,
    "gn:timezone":"Asia/Aden",
    "iso:country":"YE",
    "name:ara_x_preferred":[
        "Ibn Gh\u016bl\u012b"
    ],
    "name:ara_x_variant":[
        "\u0628\u0646 \u063a\u0648\u0644\u064a"
    ],
    "name:und_x_variant":[
        "Bin Gh\u016bl\u012b"
    ],
    "wof:name":"Bin Ghuli",
    "wof:placetype":"locality"
},
  "geometry": {"coordinates":[44.00964000000001,15.99874],"type":"Point"}
}