{
  "type": "Feature",
  "properties": {
    "gn:admin1_code":"11.0",
    "gn:admin2_code":"2001.0",
    "gn:asciiname":"Bayt al Hatimi",
    "gn:country_code":"YE",
    "gn:dem":2119,
    "gn:feature_class":"P",
    "gn:feature_code":"PPL",
    "gn:name":"Bayt al \u1e28\u0101tim\u012b",
    "gn:population":0,
    "gn:timezone":"Asia/Aden",
    "iso:country":"YE",
    "name:und_x_variant":[
        "Bayt al \u1e28\u0101tim\u012b"
    ],
    "wof:name":"Bayt al Hatimi",
    "wof:placetype":"locality"
},
  "geometry": {"coordinates":[44.66302,14.98236],"type":"Point"}
}