{
  "type": "Feature",
  "properties": {
    "gn:admin1_code":"16.0",
    "gn:admin2_code":"2306.0",
    "gn:asciiname":"Bayt al `Utmi",
    "gn:country_code":"YE",
    "gn:dem":1668,
    "gn:feature_class":"P",
    "gn:feature_code":"PPL",
    "gn:name":"Bayt al \u2018Utm\u012b",
    "gn:population":0,
    "gn:timezone":"Asia/Aden",
    "iso:country":"YE",
    "name:und_x_variant":[
        "Bayt al \u2018Utm\u012b"
    ],
    "wof:name":"Bayt al `Utmi",
    "wof:placetype":"locality"
},
  "geometry": {"coordinates":[44.18706,15.02726],"type":"Point"}
}