{
  "type": "Feature",
  "properties": {
    "gn:admin1_code":"25.0",
    "gn:admin2_code":"1501.0",
    "gn:asciiname":"Az Zuhayr",
    "gn:country_code":"YE",
    "gn:dem":998,
    "gn:feature_class":"P",
    "gn:feature_code":"PPL",
    "gn:name":"Az\u0327 Z\u0327uhayr",
    "gn:population":0,
    "gn:timezone":"Asia/Aden",
    "iso:country":"YE",
    "name:und_x_variant":[
        "Ed Duhair",
        "Az\u0327 Z\u0327uhayr"
    ],
    "wof:name":"Az Zuhayr",
    "wof:placetype":"locality"
},
  "geometry": {"coordinates":[44.46338,13.60487],"type":"Point"}
}