{
  "type": "Feature",
  "properties": {
    "gn:country":"YE",
    "gn:fcode":"PPL",
    "gn:pop":3,
    "iso:country":"YE",
    "name:ara_x_preferred":[
        "\u0100l Quml\u0101n"
    ],
    "name:ara_x_variant":[
        "\u0627\u0644 \u0642\u0645\u0644\u0627\u0646"
    ],
    "name:eng_x_preferred":[
        "Al Qumlan"
    ],
    "name:nno_x_preferred":[
        "Al Mu\u1e11ayq"
    ],
    "qs:name":"\u0100l Quml\u0101n",
    "qs:photos_9r":0,
    "qs:photos_sr":0,
    "qs:pop_sr":"1",
    "wof:name":"\u0100l Quml\u0101n",
    "wof:placetype":"locality",
    "wof:population":3
},
  "geometry": {"coordinates":[43.7577,17.12313],"type":"Point"}
}