{
  "type": "Feature",
  "properties": {
    "gn:admin1_code":"25.0",
    "gn:admin2_code":"1501.0",
    "gn:asciiname":"Shi`b al Basam",
    "gn:country_code":"YE",
    "gn:dem":1334,
    "gn:feature_class":"P",
    "gn:feature_code":"PPL",
    "gn:name":"Shi\u2018b al Basam",
    "gn:population":0,
    "gn:timezone":"Asia/Aden",
    "iso:country":"YE",
    "name:und_x_variant":[
        "Shi\u2018b al Basam"
    ],
    "wof:name":"Shi`b al Basam",
    "wof:placetype":"locality"
},
  "geometry": {"coordinates":[44.25738,13.68244],"type":"Point"}
}