{
  "type": "Feature",
  "properties": {
    "gn:admin1_code":"10.0",
    "gn:admin2_code":"2703.0",
    "gn:asciiname":"Al `Ayazir",
    "gn:country_code":"YE",
    "gn:dem":1876,
    "gn:feature_class":"P",
    "gn:feature_code":"PPL",
    "gn:name":"Al \u2018Ay\u0101zir",
    "gn:population":0,
    "gn:timezone":"Asia/Aden",
    "iso:country":"YE",
    "name:ara_x_preferred":[
        "Al \u2018Ay\u0101zir"
    ],
    "wof:name":"Al `Ayazir",
    "wof:placetype":"locality"
},
  "geometry": {"coordinates":[43.63902,15.41404],"type":"Point"}
}