{
  "type": "Feature",
  "properties": {
    "gn:admin1_code":"8.0",
    "gn:admin2_code":"1811.0",
    "gn:asciiname":"Al Midman",
    "gn:country_code":"YE",
    "gn:dem":565,
    "gn:feature_class":"P",
    "gn:feature_code":"PPL",
    "gn:name":"Al Midman",
    "gn:population":0,
    "gn:timezone":"Asia/Aden",
    "iso:country":"YE",
    "wof:name":"Al Midman",
    "wof:placetype":"locality"
},
  "geometry": {"coordinates":[43.58604,14.97865],"type":"Point"}
}