{
  "type": "Feature",
  "properties": {
    "gn:country":"YE",
    "gn:fcode":"PPL",
    "gn:population":6,
    "iso:country":"YE",
    "name:ara_x_preferred":[
        "Ikhb\u0101b"
    ],
    "name:ara_x_variant":[
        "\u0625\u062e\u0628\u0627\u0628"
    ],
    "name:eng_x_preferred":[
        "Ikhbab"
    ],
    "name:eng_x_variant":[
        "Jar\u0101bah"
    ],
    "qs:name":"Ikhb\u0101b",
    "qs:photos_9r":0,
    "qs:photos_sr":0,
    "qs:pop_sr":"1",
    "wof:name":"Ikhb\u0101b",
    "wof:placetype":"locality",
    "wof:population":6
},
  "geometry": {"coordinates":[43.40301,17.02788],"type":"Point"}
}