{
  "type": "Feature",
  "properties": {
    "gn:admin1_code":"8.0",
    "gn:admin2_code":"1805.0",
    "gn:asciiname":"Mahall Qashshash",
    "gn:country_code":"YE",
    "gn:dem":32,
    "gn:feature_class":"P",
    "gn:feature_code":"PPL",
    "gn:name":"Ma\u1e29all Qashsh\u0101sh",
    "gn:population":0,
    "gn:timezone":"Asia/Aden",
    "iso:country":"YE",
    "name:ara_x_preferred":[
        "\u0645\u062d\u0644 \u0642\u0634\u0627\u0634"
    ],
    "name:und_x_variant":[
        "Ma\u1e29all Qashsh\u0101sh"
    ],
    "wof:name":"Mahall Qashshash",
    "wof:placetype":"locality"
},
  "geometry": {"coordinates":[42.91076,15.20987],"type":"Point"}
}