{
  "type": "Feature",
  "properties": {
    "gn:admin1_code":"25.0",
    "gn:admin2_code":"1511.0",
    "gn:asciiname":"Al Mujayrin",
    "gn:country_code":"YE",
    "gn:dem":1334,
    "gn:feature_class":"P",
    "gn:feature_code":"PPL",
    "gn:name":"Al Mujayr\u012bn",
    "gn:population":0,
    "gn:timezone":"Asia/Aden",
    "iso:country":"YE",
    "name:ara_x_preferred":[
        "\u0627\u0644\u0645\u062c\u064a\u0631\u064a\u0646"
    ],
    "name:und_x_variant":[
        "Al Mujayr\u012bn"
    ],
    "wof:name":"Al Mujayrin",
    "wof:placetype":"locality"
},
  "geometry": {"coordinates":[43.95745,13.50596],"type":"Point"}
}