{
  "type": "Feature",
  "properties": {
    "gn:admin1_code":"22.0",
    "gn:admin2_code":"1724.0",
    "gn:asciiname":"Qaryat az Zawmahiyah",
    "gn:country_code":"YE",
    "gn:dem":371,
    "gn:feature_class":"P",
    "gn:feature_code":"PPL",
    "gn:name":"Qaryat az Zawma\u1e29\u012byah",
    "gn:population":0,
    "gn:timezone":"Asia/Aden",
    "iso:country":"YE",
    "name:und_x_variant":[
        "Qaryat az Zawma\u1e29\u012byah"
    ],
    "wof:name":"Qaryat az Zawmahiyah",
    "wof:placetype":"locality"
},
  "geometry": {"coordinates":[43.39532,15.60487],"type":"Point"}
}