{
  "type": "Feature",
  "properties": {
    "gn:country":"YE",
    "gn:fcode":"PPL",
    "gn:pop":1,
    "iso:country":"YE",
    "name:ara_x_preferred":[
        "\u0627\u0644\u0646\u0645\u0631\u0629"
    ],
    "name:eng_x_preferred":[
        "An Nimrah"
    ],
    "qs:name":"An Nimrah",
    "qs:photos_9r":0,
    "qs:photos_sr":0,
    "qs:pop_sr":"1",
    "wof:name":"An Nimrah",
    "wof:placetype":"locality",
    "wof:population":1
},
  "geometry": {"coordinates":[44.47535,16.88405],"type":"Point"}
}