{
  "type": "Feature",
  "properties": {
    "gn:country":"YE",
    "gn:fcode":"PPL",
    "gn:population":49,
    "iso:country":"YE",
    "name:ara_x_preferred":[
        "\u0641\u0644\u064a\u0641\u0644"
    ],
    "name:arz_x_preferred":[
        "\u0641\u0644\u064a\u0641\u0644"
    ],
    "name:eng_x_preferred":[
        "Fulayful"
    ],
    "name:eng_x_variant":[
        "Al \u1e28anjal\u012b"
    ],
    "qs:name":"Fulayful",
    "qs:photos_9r":0,
    "qs:photos_sr":0,
    "qs:pop_sr":"1",
    "wof:name":"Fulayful",
    "wof:placetype":"locality",
    "wof:population":49
},
  "geometry": {"coordinates":[45.43264,15.5008],"type":"Point"}
}