{
  "type": "Feature",
  "properties": {
    "gn:country":"YE",
    "gn:fcode":"HSE",
    "gn:pop":2,
    "iso:country":"YE",
    "name:ara_x_preferred":[
        "\u0627\u0644\u0645\u0631\u0648\u064a"
    ],
    "qs:name":"Al Marw\u012b",
    "qs:photos_9r":0,
    "qs:photos_sr":0,
    "qs:pop_sr":"1",
    "wof:name":"Al Marw\u012b",
    "wof:placetype":"locality",
    "wof:population":2
},
  "geometry": {"coordinates":[43.2571,17.12009],"type":"Point"}
}