{
  "type": "Feature",
  "properties": {
    "gn:admin1_code":"14.0",
    "gn:admin2_code":"2614.0",
    "gn:asciiname":"Al 'Uqaybat",
    "gn:country_code":"YE",
    "gn:dem":2044,
    "gn:feature_class":"P",
    "gn:feature_code":"PPL",
    "gn:name":"Al \u2018Uqayb\u0101t",
    "gn:population":0,
    "gn:timezone":"Asia/Aden",
    "iso:country":"YE",
    "name:ara_x_preferred":[
        "\u0627\u0644\u0639\u0642\u064a\u0628\u0627\u062a"
    ],
    "name:und_x_variant":[
        "Al \u2018Uqayb\u0101t"
    ],
    "wof:name":"Al 'Uqaybat",
    "wof:placetype":"locality"
},
  "geometry": {"coordinates":[45.18071,15.04538],"type":"Point"}
}