{
  "type": "Feature",
  "properties": {
    "gn:admin1_code":"23.0",
    "gn:admin2_code":"1101.0",
    "gn:asciiname":"Al Miqbayah",
    "gn:country_code":"YE",
    "gn:dem":1193,
    "gn:feature_class":"P",
    "gn:feature_code":"PPL",
    "gn:name":"Al Miqb\u0101yah",
    "gn:population":0,
    "gn:timezone":"Asia/Aden",
    "iso:country":"YE",
    "name:ara_x_preferred":[
        "\u0627\u0644\u0645\u0642\u0628\u0627\u064a\u0629"
    ],
    "name:und_x_variant":[
        "Al Miqb\u0101yah"
    ],
    "wof:name":"Al Miqbayah",
    "wof:placetype":"locality"
},
  "geometry": {"coordinates":[44.04962,14.33352],"type":"Point"}
}