{
  "type": "Feature",
  "properties": {
    "gn:admin1_code":"8.0",
    "gn:admin2_code":"1810.0",
    "gn:asciiname":"Mahall Mabariq",
    "gn:country_code":"YE",
    "gn:dem":142,
    "gn:feature_class":"P",
    "gn:feature_code":"PPL",
    "gn:name":"Ma\u1e29all Mab\u0101riq",
    "gn:population":0,
    "gn:timezone":"Asia/Aden",
    "iso:country":"YE",
    "name:ara_x_preferred":[
        "\u0645\u062d\u0644 \u0645\u0628\u0627\u0631\u0642"
    ],
    "name:und_x_variant":[
        "Ma\u1e29all Mab\u0101riq"
    ],
    "wof:name":"Mahall Mabariq",
    "wof:placetype":"locality"
},
  "geometry": {"coordinates":[43.19074000000001,15.1843],"type":"Point"}
}