{
  "type": "Feature",
  "properties": {
    "gn:admin1_code":"5.0",
    "gn:asciiname":"Hadwan",
    "gn:country_code":"YE",
    "gn:dem":1192,
    "gn:feature_class":"P",
    "gn:feature_code":"PPL",
    "gn:name":"\u1e28a\u1e11w\u0101n",
    "gn:population":0,
    "gn:timezone":"Asia/Aden",
    "iso:country":"YE",
    "name:ara_x_preferred":[
        "\u062d\u0636\u0648\u0627\u0646"
    ],
    "name:und_x_variant":[
        "\u1e28a\u1e11w\u0101n"
    ],
    "wof:name":"Hadwan",
    "wof:placetype":"locality"
},
  "geometry": {"coordinates":[46.01359,14.52631],"type":"Point"}
}