{
  "type": "Feature",
  "properties": {
    "gn:admin1_code":"26.0",
    "gn:admin2_code":"1310.0",
    "gn:asciiname":"Al Khabshah",
    "gn:country_code":"YE",
    "gn:dem":2166,
    "gn:feature_class":"P",
    "gn:feature_code":"PPL",
    "gn:name":"Al Khabshah",
    "gn:population":0,
    "gn:timezone":"Asia/Aden",
    "iso:country":"YE",
    "wof:name":"Al Khabshah",
    "wof:placetype":"locality"
},
  "geometry": {"coordinates":[44.33321,15.58],"type":"Point"}
}