{
  "type": "Feature",
  "properties": {
    "gn:admin1_code":"15.0",
    "gn:admin2_code":"2205.0",
    "gn:asciiname":"Al Qullal",
    "gn:country_code":"YE",
    "gn:dem":1032,
    "gn:feature_class":"P",
    "gn:feature_code":"PPL",
    "gn:name":"Al Qullal",
    "gn:population":0,
    "gn:timezone":"Asia/Aden",
    "iso:country":"YE",
    "name:ara_x_preferred":[
        "\u0627\u0644\u0642\u0644\u0644"
    ],
    "wof:name":"Al Qullal",
    "wof:placetype":"locality"
},
  "geometry": {"coordinates":[43.27671,16.84391],"type":"Point"}
}