{
  "type": "Feature",
  "properties": {
    "gn:country":"YE",
    "gn:fcode":"PPL",
    "gn:population":6,
    "iso:country":"YE",
    "name:ara_x_preferred":[
        "\u0627\u0644 \u0645\u0631\u064a\u0645"
    ],
    "name:eng_x_preferred":[
        "Al Muraym"
    ],
    "name:eng_x_variant":[
        "Al \u1e28ay\u016bdah"
    ],
    "qs:name":"\u0100l Muraym",
    "qs:photos_9r":0,
    "qs:photos_sr":0,
    "qs:pop_sr":"1",
    "wof:name":"\u0100l Muraym",
    "wof:placetype":"locality",
    "wof:population":6
},
  "geometry": {"coordinates":[44.28633,16.92131],"type":"Point"}
}