{
  "type": "Feature",
  "properties": {
    "gn:admin1_code":"15.0",
    "gn:admin2_code":"2210.0",
    "gn:asciiname":"Az Zawr",
    "gn:country_code":"YE",
    "gn:dem":2002,
    "gn:feature_class":"P",
    "gn:feature_code":"PPL",
    "gn:name":"Az Zawr",
    "gn:population":0,
    "gn:timezone":"Asia/Aden",
    "iso:country":"YE",
    "wof:name":"Az Zawr",
    "wof:placetype":"locality"
},
  "geometry": {"coordinates":[43.58754,17.02591],"type":"Point"}
}