{
  "type": "Feature",
  "properties": {
    "gn:country":"YE",
    "gn:fcode":"PPL",
    "gn:pop":3,
    "iso:country":"YE",
    "name:ara_x_preferred":[
        "\u063a\u0627\u0631\u0628 \u0627\u0644\u0644\u0627\u0639\u0649"
    ],
    "name:eng_x_preferred":[
        "Gharib Al La'a"
    ],
    "name:eng_x_variant":[
        "Hakr al Asfal"
    ],
    "qs:name":"Gh\u0101rib al L\u0101\u2018\u00e1",
    "qs:photos_9r":0,
    "qs:photos_sr":0,
    "qs:pop_sr":"1",
    "wof:name":"Gh\u0101rib al L\u0101\u2018\u00e1",
    "wof:placetype":"locality",
    "wof:population":3
},
  "geometry": {"coordinates":[43.36951,16.34242],"type":"Point"}
}