{
  "type": "Feature",
  "properties": {
    "gn:admin1_code":"25.0",
    "gn:admin2_code":"1505.0",
    "gn:asciiname":"Maqwalah",
    "gn:country_code":"YE",
    "gn:dem":762,
    "gn:feature_class":"P",
    "gn:feature_code":"PPL",
    "gn:name":"Maqwalah",
    "gn:population":0,
    "gn:timezone":"Asia/Aden",
    "iso:country":"YE",
    "name:ara_x_preferred":[
        "\u0645\u0642\u0648\u0644\u0629"
    ],
    "wof:name":"Maqwalah",
    "wof:placetype":"locality"
},
  "geometry": {"coordinates":[43.77026,13.56321],"type":"Point"}
}