{
  "type": "Feature",
  "properties": {
    "gn:admin1_code":"19.0",
    "gn:admin2_code":"2904.0",
    "gn:asciiname":"Al Hawazirah",
    "gn:country_code":"YE",
    "gn:dem":1544,
    "gn:feature_class":"P",
    "gn:feature_code":"PPL",
    "gn:name":"Al \u1e28aw\u0101zirah",
    "gn:population":0,
    "gn:timezone":"Asia/Aden",
    "iso:country":"YE",
    "name:ara_x_preferred":[
        "\u0627\u0644\u062d\u0648\u0627\u0632\u0631\u0629"
    ],
    "name:und_x_variant":[
        "Al \u1e28aw\u0101zirah"
    ],
    "wof:name":"Al Hawazirah",
    "wof:placetype":"locality"
},
  "geometry": {"coordinates":[43.77255,16.10991],"type":"Point"}
}