{
  "type": "Feature",
  "properties": {
    "gn:country":"YE",
    "gn:fcode":"PPL",
    "gn:pop":9,
    "iso:country":"YE",
    "name:ara_x_preferred":[
        "\u0627\u0644\u0637\u0648\u064a\u0631\u0627\u0646"
    ],
    "name:eng_x_preferred":[
        "At Tuwayran"
    ],
    "qs:name":"A\u0163 \u0162uwayr\u0101n",
    "qs:photos_9r":0,
    "qs:photos_sr":0,
    "qs:pop_sr":"1",
    "wof:name":"A\u0163 \u0162uwayr\u0101n",
    "wof:placetype":"locality",
    "wof:population":9
},
  "geometry": {"coordinates":[43.77143,13.18192],"type":"Point"}
}