{
  "type": "Feature",
  "properties": {
    "gn:admin1_code":"24.0",
    "gn:admin2_code":"2512.0",
    "gn:asciiname":"As Sulb",
    "gn:country_code":"YE",
    "gn:dem":988,
    "gn:feature_class":"P",
    "gn:feature_code":"PPL",
    "gn:name":"A\u015f \u015eulb",
    "gn:population":0,
    "gn:timezone":"Asia/Aden",
    "iso:country":"YE",
    "name:ara_x_preferred":[
        "\u0627\u0644\u0635\u0644\u0628"
    ],
    "name:und_x_variant":[
        "A\u015f \u015eulb"
    ],
    "wof:name":"As Sulb",
    "wof:placetype":"locality"
},
  "geometry": {"coordinates":[44.23156,13.20251],"type":"Point"}
}