{
  "type": "Feature",
  "properties": {
    "gn:admin1_code":"25.0",
    "gn:admin2_code":"1501.0",
    "gn:asciiname":"At Tabin",
    "gn:country_code":"YE",
    "gn:dem":1246,
    "gn:feature_class":"P",
    "gn:feature_code":"PPL",
    "gn:name":"A\u0163 \u0162ab\u012bn",
    "gn:population":0,
    "gn:timezone":"Asia/Aden",
    "iso:country":"YE",
    "name:und_x_variant":[
        "A\u0163 \u0162ab\u012bn"
    ],
    "wof:name":"At Tabin",
    "wof:placetype":"locality"
},
  "geometry": {"coordinates":[44.18235,13.58192],"type":"Point"}
}