{
  "type": "Feature",
  "properties": {
    "gn:admin1_code":"22.0",
    "gn:admin2_code":"1704.0",
    "gn:asciiname":"Dayr al Hashi",
    "gn:country_code":"YE",
    "gn:dem":82,
    "gn:feature_class":"P",
    "gn:feature_code":"PPL",
    "gn:name":"Dayr al \u1e28ash\u012b",
    "gn:population":0,
    "gn:timezone":"Asia/Aden",
    "iso:country":"YE",
    "name:und_x_variant":[
        "Dayr al \u1e28ash\u012b"
    ],
    "wof:name":"Dayr al Hashi",
    "wof:placetype":"locality"
},
  "geometry": {"coordinates":[43.01667,16.05],"type":"Point"}
}