{
  "type": "Feature",
  "properties": {
    "gn:admin1_code":"24.0",
    "gn:admin2_code":"2513.0",
    "gn:asciiname":"Dhi Wadinah",
    "gn:country_code":"YE",
    "gn:dem":324,
    "gn:feature_class":"P",
    "gn:feature_code":"PPL",
    "gn:name":"Dh\u012b W\u0101dinah",
    "gn:population":0,
    "gn:timezone":"Asia/Aden",
    "iso:country":"YE",
    "name:und_x_variant":[
        "Dh\u012b W\u0101dinah"
    ],
    "wof:name":"Dhi Wadinah",
    "wof:placetype":"locality"
},
  "geometry": {"coordinates":[44.12108,12.93539],"type":"Point"}
}