{
  "type": "Feature",
  "properties": {
    "gn:admin1_code":"25.0",
    "gn:admin2_code":"1501.0",
    "gn:asciiname":"Al Mawjir",
    "gn:country_code":"YE",
    "gn:dem":1164,
    "gn:feature_class":"P",
    "gn:feature_code":"PPL",
    "gn:name":"Al Mawjir",
    "gn:population":0,
    "gn:timezone":"Asia/Aden",
    "iso:country":"YE",
    "name:und_x_variant":[
        "Moja",
        "El Moja",
        "Al Mawjir",
        "Al Moja",
        "M\u012byah"
    ],
    "wof:name":"Al Mawjir",
    "wof:placetype":"locality"
},
  "geometry": {"coordinates":[44.3989,13.60577],"type":"Point"}
}