{
  "type": "Feature",
  "properties": {
    "gn:country":"YE",
    "gn:fcode":"PPL",
    "gn:pop":9,
    "iso:country":"YE",
    "name:ara_x_preferred":[
        "\u0627\u0644\u0634\u062c\u0639\u0629"
    ],
    "qs:name":"Ash Shaj\u2018ah",
    "qs:photos_9r":0,
    "qs:photos_sr":0,
    "qs:pop_sr":"1",
    "wof:name":"Ash Shaj\u2018ah",
    "wof:placetype":"locality",
    "wof:population":9
},
  "geometry": {"coordinates":[43.41088,16.0931],"type":"Point"}
}