{
  "type": "Feature",
  "properties": {
    "gn:admin1_code":"15.0",
    "gn:admin2_code":"2209.0",
    "gn:asciiname":"Jum`at Naki",
    "gn:country_code":"YE",
    "gn:dem":2426,
    "gn:feature_class":"P",
    "gn:feature_code":"PPL",
    "gn:name":"Jum\u2018at Nak\u012b",
    "gn:population":0,
    "gn:timezone":"Asia/Aden",
    "iso:country":"YE",
    "name:und_x_variant":[
        "Jum\u2018at Nak\u012b"
    ],
    "wof:name":"Jum`at Naki",
    "wof:placetype":"locality"
},
  "geometry": {"coordinates":[43.38333,16.91667],"type":"Point"}
}