{
  "type": "Feature",
  "properties": {
    "gn:admin1_code":"11.0",
    "gn:admin2_code":"2006.0",
    "gn:asciiname":"Mashra`ah",
    "gn:country_code":"YE",
    "gn:dem":720,
    "gn:feature_class":"P",
    "gn:feature_code":"PPL",
    "gn:name":"Mashra\u2018ah",
    "gn:population":0,
    "gn:timezone":"Asia/Aden",
    "iso:country":"YE",
    "name:ara_x_preferred":[
        "\u0645\u0634\u0631\u0639\u0629"
    ],
    "name:und_x_variant":[
        "Mashra\u2018ah"
    ],
    "wof:name":"Mashra`ah",
    "wof:placetype":"locality"
},
  "geometry": {"coordinates":[43.71858,14.46784],"type":"Point"}
}