{
  "type": "Feature",
  "properties": {
    "gn:admin1_code":"8.0",
    "gn:admin2_code":"1806.0",
    "gn:asciiname":"Dayr al Qaham",
    "gn:country_code":"YE",
    "gn:dem":85,
    "gn:feature_class":"P",
    "gn:feature_code":"PPL",
    "gn:name":"Dayr al Qa\u1e29am",
    "gn:population":0,
    "gn:timezone":"Asia/Aden",
    "iso:country":"YE",
    "name:und_x_variant":[
        "Dayr al Qa\u1e29am"
    ],
    "wof:name":"Dayr al Qaham",
    "wof:placetype":"locality"
},
  "geometry": {"coordinates":[43.09659,15.5045],"type":"Point"}
}