{
  "type": "Feature",
  "properties": {
    "gn:admin1_code":"8.0",
    "gn:admin2_code":"1824.0",
    "gn:asciiname":"Bayt ash Shu`aybi",
    "gn:country_code":"YE",
    "gn:dem":235,
    "gn:feature_class":"P",
    "gn:feature_code":"PPL",
    "gn:name":"Bayt ash Shu\u2018ayb\u012b",
    "gn:population":0,
    "gn:timezone":"Asia/Aden",
    "iso:country":"YE",
    "name:und_x_variant":[
        "Bayt ash Shu\u2018ayb\u012b"
    ],
    "wof:name":"Bayt ash Shu`aybi",
    "wof:placetype":"locality"
},
  "geometry": {"coordinates":[43.45078,14.3205],"type":"Point"}
}