{
  "type": "Feature",
  "properties": {
    "gn:admin1_code":"16.0",
    "gn:admin2_code":"2310.0",
    "gn:asciiname":"Bayt al Mushriqi",
    "gn:country_code":"YE",
    "gn:dem":1893,
    "gn:feature_class":"P",
    "gn:feature_code":"PPL",
    "gn:name":"Bayt al Mushriq\u012b",
    "gn:population":0,
    "gn:timezone":"Asia/Aden",
    "iso:country":"YE",
    "name:und_x_variant":[
        "Bayt al Mushriq\u012b"
    ],
    "wof:name":"Bayt al Mushriqi",
    "wof:placetype":"locality"
},
  "geometry": {"coordinates":[43.71734,15.17656],"type":"Point"}
}