{
  "type": "Feature",
  "properties": {
    "gn:admin1_code":"1.0",
    "gn:admin2_code":"1209.0",
    "gn:asciiname":"Masani`",
    "gn:country_code":"YE",
    "gn:dem":17,
    "gn:feature_class":"P",
    "gn:feature_code":"PPL",
    "gn:name":"Ma\u015f\u0101ni\u2018",
    "gn:population":0,
    "gn:timezone":"Asia/Aden",
    "iso:country":"YE",
    "name:und_x_variant":[
        "Maa\u2019 Sani",
        "Ma\u015f\u0101ni\u2018"
    ],
    "wof:name":"Masani`",
    "wof:placetype":"locality"
},
  "geometry": {"coordinates":[46.70599,13.45917],"type":"Point"}
}