{
  "type": "Feature",
  "properties": {
    "gn:country":"YE",
    "gn:fcode":"PPL",
    "gn:pop":3,
    "iso:country":"YE",
    "name:ara_x_preferred":[
        "\u0627\u0644\u0645\u062d\u0634\u0631\u0629"
    ],
    "name:eng_x_preferred":[
        "Mahsharah"
    ],
    "qs:name":"Ma\u1e29sharah",
    "qs:photos_9r":0,
    "qs:photos_sr":0,
    "qs:pop_sr":"1",
    "wof:name":"Ma\u1e29sharah",
    "wof:placetype":"locality",
    "wof:population":3
},
  "geometry": {"coordinates":[43.25895,17.26324],"type":"Point"}
}