{
  "type": "Feature",
  "properties": {
    "gn:gn_country":"YE",
    "gn:gn_fcode":"PPL",
    "gn:gn_pop":10,
    "gn:population":10,
    "iso:country":"YE",
    "name:ara_x_preferred":[
        "\u0634\u0639\u0628 \u0627\u0644\u062c\u0646\u0639"
    ],
    "name:eng_x_preferred":[
        "Sha'b Al Jani'"
    ],
    "qs_pg:aaroncc":"YE",
    "qs_pg:gn_country":"YE",
    "qs_pg:gn_fcode":"PPL",
    "qs_pg:gn_pop":10,
    "qs_pg:name":"Sha\u2018b al Jani\u2018",
    "qs_pg:photos_9r":0,
    "qs_pg:photos_sr":0,
    "qs_pg:pop_sr":1,
    "qs_pg:qs_pg_placetype":"locality",
    "wof:name":"Sha\u2018b al Jani\u2018",
    "wof:placetype":"locality",
    "wof:population":10
},
  "geometry": {"coordinates":[45.32364,14.63238],"type":"Point"}
}