{
  "type": "Feature",
  "properties": {
    "gn:admin1_code":"8.0",
    "gn:admin2_code":"1815.0",
    "gn:asciiname":"Dayr at Tubayn",
    "gn:country_code":"YE",
    "gn:dem":154,
    "gn:feature_class":"P",
    "gn:feature_code":"PPL",
    "gn:name":"Dayr at Tubayn",
    "gn:population":0,
    "gn:timezone":"Asia/Aden",
    "iso:country":"YE",
    "wof:name":"Dayr at Tubayn",
    "wof:placetype":"locality"
},
  "geometry": {"coordinates":[43.38112,14.82966],"type":"Point"}
}