{
  "type": "Feature",
  "properties": {
    "gn:admin1_code":"25.0",
    "gn:admin2_code":"1501.0",
    "gn:asciiname":"Ash Shi`bayn",
    "gn:country_code":"YE",
    "gn:dem":1278,
    "gn:feature_class":"P",
    "gn:feature_code":"PPL",
    "gn:name":"Ash Shi\u2018bayn",
    "gn:population":0,
    "gn:timezone":"Asia/Aden",
    "iso:country":"YE",
    "name:und_x_variant":[
        "Ash Shi\u2018bayn"
    ],
    "wof:name":"Ash Shi`bayn",
    "wof:placetype":"locality"
},
  "geometry": {"coordinates":[44.36477,13.59629],"type":"Point"}
}