{
  "type": "Feature",
  "properties": {
    "gn:admin1_code":"25.0",
    "gn:admin2_code":"1511.0",
    "gn:asciiname":"Shi`b al Muhla'",
    "gn:country_code":"YE",
    "gn:dem":1163,
    "gn:feature_class":"P",
    "gn:feature_code":"PPL",
    "gn:name":"Shi\u2018b al Muhl\u0101\u2019",
    "gn:population":0,
    "gn:timezone":"Asia/Aden",
    "iso:country":"YE",
    "name:und_x_variant":[
        "Shi\u2018b al Muhl\u0101\u2019"
    ],
    "wof:name":"Shi`b al Muhla'",
    "wof:placetype":"locality"
},
  "geometry": {"coordinates":[43.94617,13.55615],"type":"Point"}
}