{
  "type": "Feature",
  "properties": {
    "gn:admin1_code":"23.0",
    "gn:admin2_code":"1114.0",
    "gn:asciiname":"`Ard al A`wir",
    "gn:country_code":"YE",
    "gn:dem":2014,
    "gn:feature_class":"P",
    "gn:feature_code":"PPL",
    "gn:name":"\u2018Ar\u1e11 al A\u2018wir",
    "gn:population":0,
    "gn:timezone":"Asia/Aden",
    "iso:country":"YE",
    "name:und_x_variant":[
        "\u2018Ar\u1e11 al A\u2018wir"
    ],
    "wof:name":"`Ard al A`wir",
    "wof:placetype":"locality"
},
  "geometry": {"coordinates":[44.32701,13.95653],"type":"Point"}
}