{
  "type": "Feature",
  "properties": {
    "gn:admin1_code":"18.0",
    "gn:admin2_code":"3006.0",
    "gn:asciiname":"Darja Nishff",
    "gn:country_code":"YE",
    "gn:dem":1488,
    "gn:feature_class":"P",
    "gn:feature_code":"PPL",
    "gn:name":"Darja Nishff",
    "gn:population":0,
    "gn:timezone":"Asia/Aden",
    "iso:country":"YE",
    "wof:name":"Darja Nishff",
    "wof:placetype":"locality"
},
  "geometry": {"coordinates":[44.73333,13.66667],"type":"Point"}
}