{
  "type": "Feature",
  "properties": {
    "gn:admin1_code":"16.0",
    "gn:admin2_code":"2316.0",
    "gn:asciiname":"Al `Asrah",
    "gn:country_code":"YE",
    "gn:dem":2358,
    "gn:feature_class":"P",
    "gn:feature_code":"PPL",
    "gn:name":"Al \u2018A\u015frah",
    "gn:population":0,
    "gn:timezone":"Asia/Aden",
    "iso:country":"YE",
    "name:und_x_variant":[
        "Al \u2018A\u015frah"
    ],
    "wof:name":"Al `Asrah",
    "wof:placetype":"locality"
},
  "geometry": {"coordinates":[44.51267,15.2944],"type":"Point"}
}