{
  "type": "Feature",
  "properties": {
    "gn:admin1_code":"5.0",
    "gn:admin2_code":"2117.0",
    "gn:asciiname":"Al Mithaf",
    "gn:country_code":"YE",
    "gn:dem":522,
    "gn:feature_class":"P",
    "gn:feature_code":"PPL",
    "gn:name":"Al Mi\u0163h\u0101f",
    "gn:population":0,
    "gn:timezone":"Asia/Aden",
    "iso:country":"YE",
    "name:ara_x_preferred":[
        "Al Mi\u0163h\u0101f"
    ],
    "name:und_x_variant":[
        "Mi\u0163h\u0101f"
    ],
    "wof:name":"Al Mithaf",
    "wof:placetype":"locality"
},
  "geometry": {"coordinates":[47.29996,14.09709],"type":"Point"}
}