{
  "type": "Feature",
  "properties": {
    "gn:admin1_code":"24.0",
    "gn:admin2_code":"2513.0",
    "gn:asciiname":"Al Mijza`",
    "gn:country_code":"YE",
    "gn:dem":419,
    "gn:feature_class":"P",
    "gn:feature_code":"PPL",
    "gn:name":"Al Mijza\u2018",
    "gn:population":0,
    "gn:timezone":"Asia/Aden",
    "iso:country":"YE",
    "name:ara_x_preferred":[
        "\u0627\u0644\u0645\u062c\u0632\u0627\u0639"
    ],
    "name:und_x_variant":[
        "Em Mijza",
        "Am Mijza\u2018",
        "Al Mijza\u2018"
    ],
    "wof:name":"Al Mijza`",
    "wof:placetype":"locality"
},
  "geometry": {"coordinates":[44.0999,12.99114],"type":"Point"}
}