{
  "type": "Feature",
  "properties": {
    "gn:admin1_code":"10.0",
    "gn:admin2_code":"2704.0",
    "gn:asciiname":"Al Humar",
    "gn:country_code":"YE",
    "gn:dem":389,
    "gn:feature_class":"P",
    "gn:feature_code":"PPL",
    "gn:name":"Al \u1e28umar",
    "gn:population":0,
    "gn:timezone":"Asia/Aden",
    "iso:country":"YE",
    "name:und_x_variant":[
        "Al \u1e28umar"
    ],
    "wof:name":"Al Humar",
    "wof:placetype":"locality"
},
  "geometry": {"coordinates":[43.32552,15.50801],"type":"Point"}
}