{
  "type": "Feature",
  "properties": {
    "gn:admin1_code":"15.0",
    "gn:admin2_code":"2208.0",
    "gn:asciiname":"Jahwar",
    "gn:country_code":"YE",
    "gn:dem":1259,
    "gn:feature_class":"P",
    "gn:feature_code":"PPL",
    "gn:name":"Jahwar",
    "gn:population":0,
    "gn:timezone":"Asia/Aden",
    "iso:country":"YE",
    "name:ara_x_preferred":[
        "\u062c\u0647\u0648\u0631"
    ],
    "wof:name":"Jahwar",
    "wof:placetype":"locality"
},
  "geometry": {"coordinates":[43.36364,16.6856],"type":"Point"}
}