{
  "type": "Feature",
  "properties": {
    "gn:country":"YE",
    "gn:fcode":"PPL",
    "gn:pop":4,
    "iso:country":"YE",
    "name:ara_x_preferred":[
        "\u0642\u0627\u064a\u0645 \u0645\u0636\u0628"
    ],
    "name:eng_x_preferred":[
        "Qayim Mauab"
    ],
    "qs:name":"Q\u0101yim Ma\u1e11ab",
    "qs:photos_9r":0,
    "qs:photos_sr":0,
    "qs:pop_sr":"1",
    "wof:name":"Q\u0101yim Ma\u1e11ab",
    "wof:placetype":"locality",
    "wof:population":4
},
  "geometry": {"coordinates":[43.33281,16.32898],"type":"Point"}
}