{
  "type": "Feature",
  "properties": {
    "gn:admin1_code":"23.0",
    "gn:admin2_code":"1110.0",
    "gn:asciiname":"Al A`dan",
    "gn:country_code":"YE",
    "gn:dem":701,
    "gn:feature_class":"P",
    "gn:feature_code":"PPL",
    "gn:name":"Al A\u2018d\u0101n",
    "gn:population":0,
    "gn:timezone":"Asia/Aden",
    "iso:country":"YE",
    "name:ara_x_preferred":[
        "Al A\u2018d\u0101n"
    ],
    "name:ara_x_variant":[
        "\u0627\u0644\u0623\u0639\u062f\u0627\u0646"
    ],
    "wof:name":"Al A`dan",
    "wof:placetype":"locality"
},
  "geometry": {"coordinates":[43.74006,13.96876],"type":"Point"}
}