{
  "type": "Feature",
  "properties": {
    "gn:admin1_code":"4.0",
    "gn:admin2_code":"1929.0",
    "gn:asciiname":"Al Harshiyat",
    "gn:country_code":"YE",
    "gn:dem":56,
    "gn:feature_class":"P",
    "gn:feature_code":"PPL",
    "gn:name":"Al \u1e28arsh\u012by\u0101t",
    "gn:population":0,
    "gn:timezone":"Asia/Aden",
    "iso:country":"YE",
    "name:und_x_variant":[
        "Harshiyat",
        "Al \u1e28arsh\u012by\u0101t"
    ],
    "wof:name":"Al Harshiyat",
    "wof:placetype":"locality"
},
  "geometry": {"coordinates":[49.17918,14.58871],"type":"Point"}
}