{
  "type": "Feature",
  "properties": {
    "gn:admin1_code":"16.0",
    "gn:admin2_code":"2313.0",
    "gn:asciiname":"Bani Fallah",
    "gn:country_code":"YE",
    "gn:dem":2487,
    "gn:feature_class":"P",
    "gn:feature_code":"PPL",
    "gn:name":"Ban\u012b Fall\u0101\u1e29",
    "gn:population":0,
    "gn:timezone":"Asia/Aden",
    "iso:country":"YE",
    "name:ara_x_preferred":[
        "\u0628\u0646\u064a \u0641\u0644\u0627\u062d"
    ],
    "name:und_x_variant":[
        "Ban\u012b Fala\u1e29",
        "Ban\u012b Fall\u0101\u1e29"
    ],
    "wof:name":"Bani Fallah",
    "wof:placetype":"locality"
},
  "geometry": {"coordinates":[44.56607,15.34467],"type":"Point"}
}