{
  "type": "Feature",
  "properties": {
    "gn:country":"YE",
    "gn:fcode":"PPL",
    "gn:population":12,
    "iso:country":"YE",
    "name:ara_x_preferred":[
        "\u0647\u0632\u0627\u0632"
    ],
    "name:eng_x_preferred":[
        "Hazzaz"
    ],
    "name:eng_x_variant":[
        "\u1e28ulay\u015fah"
    ],
    "qs:name":"Hazz\u0101z",
    "qs:photos_9r":0,
    "qs:photos_sr":0,
    "qs:pop_sr":"1",
    "wof:name":"Hazz\u0101z",
    "wof:placetype":"locality",
    "wof:population":12
},
  "geometry": {"coordinates":[45.33595,14.15474],"type":"Point"}
}