{
  "type": "Feature",
  "properties": {
    "gn:country":"YE",
    "gn:fcode":"PPL",
    "gn:pop":5,
    "iso:country":"YE",
    "name:ara_x_preferred":[
        "Bi\u2019r \u2018Az\u012bz"
    ],
    "name:ara_x_variant":[
        "\u0628\u0626\u0631 \u0639\u0632\u064a\u0632"
    ],
    "name:eng_x_preferred":[
        "Bir 'Aziz"
    ],
    "name:nno_x_preferred":[
        "Al-`Asilah"
    ],
    "qs:name":"Bi\u2019r \u2018Az\u012bz",
    "qs:photos_9r":0,
    "qs:photos_sr":0,
    "qs:pop_sr":"1",
    "wof:name":"Bi\u2019r \u2018Az\u012bz",
    "wof:placetype":"locality",
    "wof:population":5
},
  "geometry": {"coordinates":[44.11942,17.03733],"type":"Point"}
}