{
  "type": "Feature",
  "properties": {
    "gn:country":"YE",
    "gn:fcode":"PPL",
    "gn:pop":2,
    "iso:country":"YE",
    "name:ara_x_preferred":[
        "Khuz\u0101fir"
    ],
    "name:ara_x_variant":[
        "\u062e\u0632\u0627\u0641\u0631"
    ],
    "name:eng_x_preferred":[
        "Khuzafir"
    ],
    "qs:name":"Khuz\u0101fir",
    "qs:photos_9r":0,
    "qs:photos_sr":0,
    "qs:pop_sr":"1",
    "wof:name":"Khuz\u0101fir",
    "wof:placetype":"locality",
    "wof:population":2
},
  "geometry": {"coordinates":[43.96253,13.1653],"type":"Point"}
}