{
  "type": "Feature",
  "properties": {
    "gn:admin1_code":"25.0",
    "gn:admin2_code":"1515.0",
    "gn:asciiname":"Dhi al Khayr",
    "gn:country_code":"YE",
    "gn:dem":1062,
    "gn:feature_class":"P",
    "gn:feature_code":"PPL",
    "gn:name":"Dh\u012b al Khayr",
    "gn:population":0,
    "gn:timezone":"Asia/Aden",
    "iso:country":"YE",
    "name:ara_x_preferred":[
        "\u0630\u064a \u0627\u0644\u062e\u064a\u0631"
    ],
    "name:und_x_variant":[
        "Dh\u012b al Khayr"
    ],
    "wof:name":"Dhi al Khayr",
    "wof:placetype":"locality"
},
  "geometry": {"coordinates":[43.98614,13.16218],"type":"Point"}
}