{
  "type": "Feature",
  "properties": {
    "gn:admin1_code":"19.0",
    "gn:admin2_code":"2910.0",
    "gn:asciiname":"Tumhan",
    "gn:country_code":"YE",
    "gn:dem":2185,
    "gn:feature_class":"P",
    "gn:feature_code":"PPL",
    "gn:name":"\u0162um\u1e29\u0101n",
    "gn:population":0,
    "gn:timezone":"Asia/Aden",
    "iso:country":"YE",
    "name:ara_x_preferred":[
        "\u0637\u0645\u062d\u0627\u0646"
    ],
    "name:und_x_variant":[
        "\u0162um\u1e29\u0101n"
    ],
    "wof:name":"Tumhan",
    "wof:placetype":"locality"
},
  "geometry": {"coordinates":[44.05478,15.84906],"type":"Point"}
}