{
  "type": "Feature",
  "properties": {
    "gn:country":"YE",
    "gn:fcode":"PPL",
    "gn:pop":1,
    "iso:country":"YE",
    "name:ara_x_preferred":[
        "\u0645\u0648\u0642\u0631 \u0633\u0639\u064a\u062f"
    ],
    "name:eng_x_preferred":[
        "Mawqar Sa'id"
    ],
    "name:nno_x_preferred":[
        "Al Hanakah"
    ],
    "qs:name":"Mawqar Sa\u2018\u012bd",
    "qs:photos_9r":0,
    "qs:photos_sr":0,
    "qs:pop_sr":"1",
    "wof:name":"Mawqar Sa\u2018\u012bd",
    "wof:placetype":"locality",
    "wof:population":1
},
  "geometry": {"coordinates":[43.46224,16.00301],"type":"Point"}
}