{
  "type": "Feature",
  "properties": {
    "gn:country":"YE",
    "gn:fcode":"PPL",
    "gn:population":9,
    "iso:country":"YE",
    "name:ara_x_preferred":[
        "\u062c\u0628\u0644 \u062d\u0645\u0627\u0645\u064a"
    ],
    "name:eng_x_preferred":[
        "Jabal Hammami"
    ],
    "name:msa_x_preferred":[
        "Zarean"
    ],
    "qs:name":"Jabal \u1e28amm\u0101m\u012b",
    "qs:photos_9r":0,
    "qs:photos_sr":0,
    "qs:pop_sr":"1",
    "wof:name":"Jabal \u1e28amm\u0101m\u012b",
    "wof:placetype":"locality",
    "wof:population":9
},
  "geometry": {"coordinates":[43.71454,16.0588],"type":"Point"}
}