{
  "type": "Feature",
  "properties": {
    "gn:admin1_code":"5.0",
    "gn:admin2_code":"2117.0",
    "gn:asciiname":"Hawrah al `Ulya",
    "gn:country_code":"YE",
    "gn:dem":392,
    "gn:feature_class":"P",
    "gn:feature_code":"PPL",
    "gn:name":"\u1e28awrah al \u2018Uly\u0101",
    "gn:population":0,
    "gn:timezone":"Asia/Aden",
    "iso:country":"YE",
    "name:und_x_variant":[
        "Haura al \u2018Ulya",
        "\u1e28awrah al \u2018Uly\u0101"
    ],
    "wof:name":"Hawrah al `Ulya",
    "wof:placetype":"locality"
},
  "geometry": {"coordinates":[47.30761,14.03571],"type":"Point"}
}