{
  "type": "Feature",
  "properties": {
    "gn:admin1_code":"21.0",
    "gn:admin2_code":"1603.0",
    "gn:asciiname":"Al Marbah",
    "gn:country_code":"YE",
    "gn:dem":1249,
    "gn:feature_class":"P",
    "gn:feature_code":"PPLL",
    "gn:name":"Al Marba\u1e29",
    "gn:population":0,
    "gn:timezone":"Asia/Aden",
    "iso:country":"YE",
    "name:ara_x_preferred":[
        "\u0627\u0644\u0645\u0631\u0628\u062d"
    ],
    "name:und_x_variant":[
        "Al Marba\u1e29"
    ],
    "wof:name":"Al Marbah",
    "wof:placetype":"locality"
},
  "geometry": {"coordinates":[44.39878,16.09418],"type":"Point"}
}