{
  "type": "Feature",
  "properties": {
    "gn:country":"YE",
    "gn:fcode":"PPL",
    "gn:pop":2,
    "iso:country":"YE",
    "name:ara_x_preferred":[
        "\u0627\u0644\u0645\u0639\u0637\u0646"
    ],
    "qs:name":"Al Ma\u2018\u0163an",
    "qs:photos_9r":0,
    "qs:photos_sr":0,
    "qs:pop_sr":"1",
    "wof:name":"Al Ma\u2018\u0163an",
    "wof:placetype":"locality",
    "wof:population":2
},
  "geometry": {"coordinates":[43.32694,17.50177],"type":"Point"}
}