{
  "type": "Feature",
  "properties": {
    "gn:admin1_code":"16.0",
    "gn:admin2_code":"2302.0",
    "gn:asciiname":"Al Hayfah",
    "gn:country_code":"YE",
    "gn:dem":2606,
    "gn:feature_class":"P",
    "gn:feature_code":"PPL",
    "gn:name":"Al \u1e28ayfah",
    "gn:population":0,
    "gn:timezone":"Asia/Aden",
    "iso:country":"YE",
    "name:fas_x_preferred":[
        "\u0627\u0644\u062d\u06cc\u0641\u0647"
    ],
    "name:nno_x_preferred":[
        "Al Hayfah"
    ],
    "name:und_x_variant":[
        "El-\u1e28aifah",
        "Hayf\u0101\u2019",
        "Hayafa",
        "Haifa",
        "\u1e24ayfah",
        "Al \u1e28ayfah"
    ],
    "wof:name":"Al Hayfah",
    "wof:placetype":"locality"
},
  "geometry": {"coordinates":[44.21564,15.80483],"type":"Point"}
}