{
  "type": "Feature",
  "properties": {
    "gn:admin1_code":"20.0",
    "gn:admin2_code":"1417.0",
    "gn:asciiname":"Khirbat Jaradah",
    "gn:country_code":"YE",
    "gn:dem":2453,
    "gn:feature_class":"P",
    "gn:feature_code":"PPL",
    "gn:name":"Khirbat Jar\u0101dah",
    "gn:population":0,
    "gn:timezone":"Asia/Aden",
    "iso:country":"YE",
    "name:und_x_variant":[
        "Khirbat Jar\u0101dah"
    ],
    "wof:name":"Khirbat Jaradah",
    "wof:placetype":"locality"
},
  "geometry": {"coordinates":[44.66109,14.27629],"type":"Point"}
}