{
  "type": "Feature",
  "properties": {
    "gn:admin1_code":"19.0",
    "gn:admin2_code":"2915.0",
    "gn:asciiname":"Bayt as Sayyid",
    "gn:country_code":"YE",
    "gn:dem":2128,
    "gn:feature_class":"P",
    "gn:feature_code":"PPL",
    "gn:name":"Bayt as Sayyid",
    "gn:population":0,
    "gn:timezone":"Asia/Aden",
    "iso:country":"YE",
    "wof:name":"Bayt as Sayyid",
    "wof:placetype":"locality"
},
  "geometry": {"coordinates":[43.75375,15.72534],"type":"Point"}
}