{
  "type": "Feature",
  "properties": {
    "gn:admin1_code":"23.0",
    "gn:admin2_code":"1110.0",
    "gn:asciiname":"Al Mafjar",
    "gn:country_code":"YE",
    "gn:dem":837,
    "gn:feature_class":"P",
    "gn:feature_code":"PPL",
    "gn:name":"Al Mafjar",
    "gn:population":0,
    "gn:timezone":"Asia/Aden",
    "iso:country":"YE",
    "name:fas_x_preferred":[
        "\u0627\u0644\u0645\u0641\u062c\u0627\u0631"
    ],
    "name:gle_x_preferred":[
        "Al Mafjar"
    ],
    "name:nno_x_preferred":[
        "Al Mafjar"
    ],
    "name:urd_x_preferred":[
        "\u0627\u0644\u0645\u0641\u062c\u0631"
    ],
    "wof:name":"Al Mafjar",
    "wof:placetype":"locality"
},
  "geometry": {"coordinates":[43.8093,14.01179],"type":"Point"}
}