{
  "type": "Feature",
  "properties": {
    "gn:admin1_code":"1.0",
    "gn:admin2_code":"1210.0",
    "gn:asciiname":"`Amudiyah",
    "gn:country_code":"YE",
    "gn:dem":24,
    "gn:feature_class":"P",
    "gn:feature_code":"PPL",
    "gn:name":"\u2018Am\u016bd\u012byah",
    "gn:population":0,
    "gn:timezone":"Asia/Aden",
    "iso:country":"YE",
    "name:nno_x_preferred":[
        "`Amudiyah"
    ],
    "name:und_x_variant":[
        "Amudiya",
        "\u2018Am\u016bd\u012byah"
    ],
    "name:urd_x_preferred":[
        "\u0639\u0645\u0648\u062f\u06cc\u06c1"
    ],
    "wof:name":"`Amudiyah",
    "wof:placetype":"locality"
},
  "geometry": {"coordinates":[45.36222,13.13389],"type":"Point"}
}