{
  "type": "Feature",
  "properties": {
    "gn:admin1_code":"19.0",
    "gn:admin2_code":"2919.0",
    "gn:asciiname":"Baydan",
    "gn:country_code":"YE",
    "gn:dem":2401,
    "gn:feature_class":"P",
    "gn:feature_code":"PPL",
    "gn:name":"Bay\u1e11\u0101n",
    "gn:population":0,
    "gn:timezone":"Asia/Aden",
    "iso:country":"YE",
    "name:ara_x_preferred":[
        "\u0628\u064a\u0636\u0627\u0646"
    ],
    "name:und_x_variant":[
        "Ma\u1e29all Bay\u1e11\u0101n",
        "Bay\u1e11\u0101n"
    ],
    "wof:name":"Baydan",
    "wof:placetype":"locality"
},
  "geometry": {"coordinates":[43.97318,16.06414],"type":"Point"}
}