{
  "type": "Feature",
  "properties": {
    "gn:admin1_code":"4.0",
    "gn:admin2_code":"1923.0",
    "gn:asciiname":"Ghumsah",
    "gn:country_code":"YE",
    "gn:dem":1231,
    "gn:feature_class":"P",
    "gn:feature_code":"PPL",
    "gn:name":"Ghumsah",
    "gn:population":0,
    "gn:timezone":"Asia/Aden",
    "iso:country":"YE",
    "wof:name":"Ghumsah",
    "wof:placetype":"locality"
},
  "geometry": {"coordinates":[47.65,14.83333],"type":"Point"}
}