{
  "type": "Feature",
  "properties": {
    "gn:admin1_code":"11.0",
    "gn:admin2_code":"2007.0",
    "gn:asciiname":"Bani az Zakhm",
    "gn:country_code":"YE",
    "gn:dem":349,
    "gn:feature_class":"P",
    "gn:feature_code":"PPL",
    "gn:name":"Ban\u012b az Zakhm",
    "gn:population":0,
    "gn:timezone":"Asia/Aden",
    "iso:country":"YE",
    "name:und_x_variant":[
        "Ban\u012b az Zakhm"
    ],
    "wof:name":"Bani az Zakhm",
    "wof:placetype":"locality"
},
  "geometry": {"coordinates":[43.5368,14.30108],"type":"Point"}
}