{
  "type": "Feature",
  "properties": {
    "gn:country":"YE",
    "gn:fcode":"PPL",
    "gn:pop":2,
    "iso:country":"YE",
    "name:ara_x_preferred":[
        "Az\u0327 Z\u0327\u0101hir\u012bn"
    ],
    "name:ara_x_variant":[
        "\u0627\u0644\u0638\u0627\u0647\u0631\u064a\u0646"
    ],
    "name:eng_x_preferred":[
        "Az Zahirin"
    ],
    "qs:name":"Az\u0327 Z\u0327\u0101hir\u012bn",
    "qs:photos_9r":0,
    "qs:photos_sr":0,
    "qs:pop_sr":"1",
    "wof:name":"Az\u0327 Z\u0327\u0101hir\u012bn",
    "wof:placetype":"locality",
    "wof:population":2
},
  "geometry": {"coordinates":[43.33249,16.7384],"type":"Point"}
}