{
  "type": "Feature",
  "properties": {
    "gn:admin1_code":"20.0",
    "gn:admin2_code":"1404.0",
    "gn:asciiname":"Buridah",
    "gn:country_code":"YE",
    "gn:dem":2027,
    "gn:feature_class":"P",
    "gn:feature_code":"PPL",
    "gn:name":"B\u016bridah",
    "gn:population":0,
    "gn:timezone":"Asia/Aden",
    "iso:country":"YE",
    "name:und_x_variant":[
        "B\u016bridah"
    ],
    "wof:name":"Buridah",
    "wof:placetype":"locality"
},
  "geometry": {"coordinates":[45.73671,14.04964],"type":"Point"}
}