{
  "type": "Feature",
  "properties": {
    "gn:admin1_code":"16.0",
    "gn:admin2_code":"2305.0",
    "gn:asciiname":"Bayt Hadir",
    "gn:country_code":"YE",
    "gn:dem":2428,
    "gn:feature_class":"P",
    "gn:feature_code":"PPL",
    "gn:name":"Bayt \u1e28\u0101\u1e11ir",
    "gn:population":0,
    "gn:timezone":"Asia/Aden",
    "iso:country":"YE",
    "name:ara_x_preferred":[
        "\u0628\u064a\u062a \u062d\u0627\u0636\u0631"
    ],
    "name:nno_x_preferred":[
        "Bayt Hadir"
    ],
    "name:und_x_variant":[
        "Bayt \u1e28\u0101\u1e11ir",
        "\u1e28a\u1e11ir"
    ],
    "wof:name":"Bayt Hadir",
    "wof:placetype":"locality"
},
  "geometry": {"coordinates":[44.3366,15.3446],"type":"Point"}
}