{
  "type": "Feature",
  "properties": {
    "gn:admin1_code":"22.0",
    "gn:admin2_code":"1727.0",
    "gn:asciiname":"Mahall Hikam",
    "gn:country_code":"YE",
    "gn:dem":1825,
    "gn:feature_class":"P",
    "gn:feature_code":"PPL",
    "gn:name":"Ma\u1e29all \u1e28ikam",
    "gn:population":0,
    "gn:timezone":"Asia/Aden",
    "iso:country":"YE",
    "name:und_x_variant":[
        "Ma\u1e29all \u1e28ikam"
    ],
    "wof:name":"Mahall Hikam",
    "wof:placetype":"locality"
},
  "geometry": {"coordinates":[43.60775,15.6121],"type":"Point"}
}