{
  "type": "Feature",
  "properties": {
    "gn:country":"YE",
    "gn:fcode":"PPLX",
    "gn:pop":1,
    "iso:country":"YE",
    "name:ara_x_preferred":[
        "\u062f\u0631\u0628 \u0627\u0644\u062d\u0648\u062f"
    ],
    "qs:name":"Darb al \u1e28awd",
    "qs:photos_9r":0,
    "qs:photos_sr":0,
    "qs:pop_sr":"1",
    "wof:name":"Darb al \u1e28awd",
    "wof:placetype":"neighbourhood",
    "wof:population":1
},
  "geometry": {"coordinates":[43.68599,16.15383],"type":"Point"}
}