{
  "type": "Feature",
  "properties": {
    "gn:admin1_code":"8.0",
    "gn:admin2_code":"1825.0",
    "gn:asciiname":"Ar Rawdah",
    "gn:country_code":"YE",
    "gn:dem":245,
    "gn:feature_class":"P",
    "gn:feature_code":"PPL",
    "gn:name":"Ar Raw\u1e11ah",
    "gn:population":0,
    "gn:timezone":"Asia/Aden",
    "iso:country":"YE",
    "name:und_x_variant":[
        "Ar Raw\u1e11ah"
    ],
    "wof:name":"Ar Rawdah",
    "wof:placetype":"locality"
},
  "geometry": {"coordinates":[43.48942,14.2213],"type":"Point"}
}