{
  "type": "Feature",
  "properties": {
    "gn:admin1_code":"11.0",
    "gn:admin2_code":"2006.0",
    "gn:asciiname":"`Urwish",
    "gn:country_code":"YE",
    "gn:dem":1150,
    "gn:feature_class":"P",
    "gn:feature_code":"PPL",
    "gn:name":"\u2018Urwish",
    "gn:population":0,
    "gn:timezone":"Asia/Aden",
    "iso:country":"YE",
    "name:ara_x_preferred":[
        "\u2018Urwish"
    ],
    "wof:name":"`Urwish",
    "wof:placetype":"locality"
},
  "geometry": {"coordinates":[43.80889000000001,14.28],"type":"Point"}
}