{
  "type": "Feature",
  "properties": {
    "gn:country":"YE",
    "gn:fcode":"PPL",
    "gn:pop":6,
    "iso:country":"YE",
    "name:ara_x_preferred":[
        "\u0627\u0644\u0645\u0634\u0643"
    ],
    "name:eng_x_preferred":[
        "Al Mashshak"
    ],
    "name:eng_x_variant":[
        "Sha\u2018b al \u2018A\u0163abah"
    ],
    "qs:name":"Al Mashshak",
    "qs:photos_9r":0,
    "qs:photos_sr":0,
    "qs:pop_sr":"1",
    "wof:name":"Al Mashshak",
    "wof:placetype":"locality",
    "wof:population":6
},
  "geometry": {"coordinates":[43.26981,16.11361],"type":"Point"}
}