{
  "type": "Feature",
  "properties": {
    "gn:country":"YE",
    "gn:fcode":"PPL",
    "gn:population":1,
    "iso:country":"YE",
    "name:ara_x_preferred":[
        "\u0634\u0630\u0646\u0629"
    ],
    "qs:name":"Shadhnah",
    "qs:photos_9r":0,
    "qs:photos_sr":0,
    "qs:pop_sr":"1",
    "wof:name":"Shadhnah",
    "wof:placetype":"locality",
    "wof:population":1
},
  "geometry": {"coordinates":[43.31055,17.38177],"type":"Point"}
}