{
  "type": "Feature",
  "properties": {
    "gn:country":"YE",
    "gn:fcode":"PPL",
    "gn:population":2,
    "iso:country":"YE",
    "name:ara_x_preferred":[
        "\u0627\u0644\u0645\u062d\u0627\u0645\u0627\u0647"
    ],
    "name:eng_x_preferred":[
        "Al Mahamah"
    ],
    "name:eng_x_variant":[
        "Sha\u2018b al Jamal"
    ],
    "qs:name":"Al Ma\u1e29\u0101m\u0101h",
    "qs:photos_9r":0,
    "qs:photos_sr":0,
    "qs:pop_sr":"1",
    "wof:name":"Al Ma\u1e29\u0101m\u0101h",
    "wof:placetype":"locality",
    "wof:population":2
},
  "geometry": {"coordinates":[43.2319,17.13769],"type":"Point"}
}