{
  "type": "Feature",
  "properties": {
    "gn:admin1_code":"19.0",
    "gn:admin2_code":"2903.0",
    "gn:asciiname":"Ad Dayyiq",
    "gn:country_code":"YE",
    "gn:dem":1198,
    "gn:feature_class":"P",
    "gn:feature_code":"PPL",
    "gn:name":"A\u1e11 \u1e10ayyiq",
    "gn:population":0,
    "gn:timezone":"Asia/Aden",
    "iso:country":"YE",
    "name:ara_x_preferred":[
        "\u0627\u0644\u0636\u064a\u0642"
    ],
    "name:und_x_variant":[
        "A\u1e11 \u1e10ayyiq"
    ],
    "wof:name":"Ad Dayyiq",
    "wof:placetype":"locality"
},
  "geometry": {"coordinates":[43.85651,16.25277],"type":"Point"}
}