{
  "type": "Feature",
  "properties": {
    "gn:admin1_code":"20.0",
    "gn:asciiname":"Al `Aqabah",
    "gn:country_code":"YE",
    "gn:dem":2520,
    "gn:feature_class":"P",
    "gn:feature_code":"PPL",
    "gn:name":"Al \u2018Aqabah",
    "gn:population":0,
    "gn:timezone":"Asia/Aden",
    "iso:country":"YE",
    "name:ara_x_preferred":[
        "\u0627\u0644\u0639\u0642\u0628\u0629"
    ],
    "name:und_x_variant":[
        "Al \u2018Aqabah"
    ],
    "wof:name":"Al `Aqabah",
    "wof:placetype":"locality"
},
  "geometry": {"coordinates":[44.38244,14.46908],"type":"Point"}
}