{
  "type": "Feature",
  "properties": {
    "gn:admin1_code":"22.0",
    "gn:admin2_code":"1725.0",
    "gn:asciiname":"Kharawda'",
    "gn:country_code":"YE",
    "gn:dem":526,
    "gn:feature_class":"P",
    "gn:feature_code":"PPL",
    "gn:name":"Kharaw\u1e11\u0101\u2019",
    "gn:population":0,
    "gn:timezone":"Asia/Aden",
    "iso:country":"YE",
    "name:und_x_variant":[
        "Kharaw\u1e11\u0101\u2019"
    ],
    "wof:name":"Kharawda'",
    "wof:placetype":"locality"
},
  "geometry": {"coordinates":[43.4731,15.56691],"type":"Point"}
}