{
  "type": "Feature",
  "properties": {
    "gn:country":"YE",
    "gn:fcode":"PPL",
    "gn:pop":4,
    "iso:country":"YE",
    "name:ara_x_preferred":[
        "\u0627\u0644\u0634\u0639\u0628 \u0627\u0644\u0623\u062d\u0645\u0631"
    ],
    "name:eng_x_preferred":[
        "Ash Sha'b Al Ahmar"
    ],
    "name:eng_x_variant":[
        "Ad Dar\u016bb"
    ],
    "qs:name":"Ash Sha\u2018b al A\u1e29mar",
    "qs:photos_9r":0,
    "qs:photos_sr":0,
    "qs:pop_sr":"1",
    "wof:name":"Ash Sha\u2018b al A\u1e29mar",
    "wof:placetype":"locality",
    "wof:population":4
},
  "geometry": {"coordinates":[45.36455,14.52701],"type":"Point"}
}