{
  "type": "Feature",
  "properties": {
    "gn:admin1_code":"8.0",
    "gn:admin2_code":"1808.0",
    "gn:asciiname":"Al Kufiyah",
    "gn:country_code":"YE",
    "gn:dem":117,
    "gn:feature_class":"P",
    "gn:feature_code":"PPL",
    "gn:name":"Al K\u016bf\u012byah",
    "gn:population":0,
    "gn:timezone":"Asia/Aden",
    "iso:country":"YE",
    "name:ara_x_preferred":[
        "\u0627\u0644\u0643\u0648\u0641\u064a\u0629"
    ],
    "name:und_x_variant":[
        "K\u016bf\u012byah",
        "Al K\u016bf\u012byah"
    ],
    "wof:name":"Al Kufiyah",
    "wof:placetype":"locality"
},
  "geometry": {"coordinates":[43.17634,15.31759],"type":"Point"}
}