{
  "type": "Feature",
  "properties": {
    "gn:admin1_code":"23.0",
    "gn:admin2_code":"1115.0",
    "gn:asciiname":"Dufesor",
    "gn:country_code":"YE",
    "gn:dem":1799,
    "gn:feature_class":"P",
    "gn:feature_code":"PPL",
    "gn:name":"Dufesor",
    "gn:population":0,
    "gn:timezone":"Asia/Aden",
    "iso:country":"YE",
    "name:und_x_variant":[
        "\u1e10\u016br\u0101fah",
        "Douf\u0113va",
        "Douf\u00e9va"
    ],
    "wof:name":"Dufesor",
    "wof:placetype":"locality"
},
  "geometry": {"coordinates":[44.15239,13.80638],"type":"Point"}
}