{
  "type": "Feature",
  "properties": {
    "gn:admin1_code":"8.0",
    "gn:admin2_code":"1815.0",
    "gn:asciiname":"Dayr Kuddaf",
    "gn:country_code":"YE",
    "gn:dem":183,
    "gn:feature_class":"P",
    "gn:feature_code":"PPL",
    "gn:name":"Dayr Kuddaf",
    "gn:population":0,
    "gn:timezone":"Asia/Aden",
    "iso:country":"YE",
    "wof:name":"Dayr Kuddaf",
    "wof:placetype":"locality"
},
  "geometry": {"coordinates":[43.38127,14.74815],"type":"Point"}
}