{
  "type": "Feature",
  "properties": {
    "gn:admin1_code":"23.0",
    "gn:admin2_code":"1109.0",
    "gn:asciiname":"Al Ahmul",
    "gn:country_code":"YE",
    "gn:dem":1151,
    "gn:feature_class":"P",
    "gn:feature_code":"PPL",
    "gn:name":"Al Ahm\u016bl",
    "gn:population":0,
    "gn:timezone":"Asia/Aden",
    "iso:country":"YE",
    "name:ara_x_preferred":[
        "Al Ahm\u016bl"
    ],
    "wof:name":"Al Ahmul",
    "wof:placetype":"locality"
},
  "geometry": {"coordinates":[44.00319,14.17613],"type":"Point"}
}