{
  "type": "Feature",
  "properties": {
    "gn:admin1_code":"20.0",
    "gn:admin2_code":"1407.0",
    "gn:asciiname":"Hadarah",
    "gn:country_code":"YE",
    "gn:dem":1832,
    "gn:feature_class":"P",
    "gn:feature_code":"PPL",
    "gn:name":"\u1e28a\u1e11\u0101rah",
    "gn:population":0,
    "gn:timezone":"Asia/Aden",
    "iso:country":"YE",
    "name:ara_x_preferred":[
        "\u062d\u0636\u0627\u0631\u0629"
    ],
    "name:und_x_variant":[
        "\u1e28a\u1e11\u0101rah"
    ],
    "wof:name":"Hadarah",
    "wof:placetype":"locality"
},
  "geometry": {"coordinates":[45.2172,14.04298],"type":"Point"}
}