{
  "type": "Feature",
  "properties": {
    "gn:admin1_code":"23.0",
    "gn:admin2_code":"1108.0",
    "gn:asciiname":"Al Almanah",
    "gn:country_code":"YE",
    "gn:dem":2048,
    "gn:feature_class":"P",
    "gn:feature_code":"PPL",
    "gn:name":"Al Almanah",
    "gn:population":0,
    "gn:timezone":"Asia/Aden",
    "iso:country":"YE",
    "name:ara_x_preferred":[
        "\u0627\u0644\u0623\u062d\u0645\u0646\u0629"
    ],
    "name:und_x_variant":[
        "Al A\u1e29manah"
    ],
    "wof:name":"Al Almanah",
    "wof:placetype":"locality"
},
  "geometry": {"coordinates":[44.01904,14.03901],"type":"Point"}
}