{
  "type": "Feature",
  "properties": {
    "gn:admin1_code":"23.0",
    "gn:admin2_code":"1114.0",
    "gn:asciiname":"Akamat al Jarin",
    "gn:country_code":"YE",
    "gn:dem":1595,
    "gn:feature_class":"P",
    "gn:feature_code":"PPL",
    "gn:name":"Akamat al Jar\u012bn",
    "gn:population":0,
    "gn:timezone":"Asia/Aden",
    "iso:country":"YE",
    "name:und_x_variant":[
        "Akamat al Jar\u012bn"
    ],
    "wof:name":"Akamat al Jarin",
    "wof:placetype":"locality"
},
  "geometry": {"coordinates":[44.36208,13.79624],"type":"Point"}
}