{
  "type": "Feature",
  "properties": {
    "gn:admin1_code":"15.0",
    "gn:admin2_code":"2210.0",
    "gn:asciiname":"Al Sarmad",
    "gn:country_code":"YE",
    "gn:dem":2218,
    "gn:feature_class":"P",
    "gn:feature_code":"PPL",
    "gn:name":"\u0100l Sarmad",
    "gn:population":0,
    "gn:timezone":"Asia/Aden",
    "iso:country":"YE",
    "name:ara_x_preferred":[
        "\u0627\u0644 \u0633\u0631\u0645\u062f"
    ],
    "name:und_x_variant":[
        "Sarmad",
        "\u0100l Sarmad"
    ],
    "wof:name":"Al Sarmad",
    "wof:placetype":"locality"
},
  "geometry": {"coordinates":[43.4281,17.21518],"type":"Point"}
}