{
  "type": "Feature",
  "properties": {
    "gn:admin1_code":"22.0",
    "gn:admin2_code":"1704.0",
    "gn:asciiname":"Al Hinik",
    "gn:country_code":"YE",
    "gn:dem":232,
    "gn:feature_class":"P",
    "gn:feature_code":"PPL",
    "gn:name":"Al \u1e28in\u012bk",
    "gn:population":0,
    "gn:timezone":"Asia/Aden",
    "iso:country":"YE",
    "name:ara_x_preferred":[
        "Al \u1e28in\u012bk"
    ],
    "wof:name":"Al Hinik",
    "wof:placetype":"locality"
},
  "geometry": {"coordinates":[43.23951,15.99801],"type":"Point"}
}