{
  "type": "Feature",
  "properties": {
    "gn:country":"YE",
    "gn:fcode":"PPL",
    "gn:pop":4,
    "iso:country":"YE",
    "name:ara_x_preferred":[
        "\u0631\u062d\u0627\u0628"
    ],
    "name:eng_x_preferred":[
        "Rahab"
    ],
    "qs:name":"Ra\u1e29\u0101b",
    "qs:photos_9r":0,
    "qs:photos_sr":0,
    "qs:pop_sr":"1",
    "wof:name":"Ra\u1e29\u0101b",
    "wof:placetype":"locality",
    "wof:population":4
},
  "geometry": {"coordinates":[45.34433,14.30582],"type":"Point"}
}