{
  "type": "Feature",
  "properties": {
    "gn:admin1_code":"20.0",
    "gn:admin2_code":"1404.0",
    "gn:asciiname":"Hayd al Masqa",
    "gn:country_code":"YE",
    "gn:dem":2022,
    "gn:feature_class":"P",
    "gn:feature_code":"PPL",
    "gn:name":"\u1e28ayd al Masq\u00e1",
    "gn:population":0,
    "gn:timezone":"Asia/Aden",
    "iso:country":"YE",
    "name:und_x_variant":[
        "\u1e28ayd al Masq\u00e1"
    ],
    "wof:name":"Hayd al Masqa",
    "wof:placetype":"locality"
},
  "geometry": {"coordinates":[45.76665,14.11645],"type":"Point"}
}