{
  "type": "Feature",
  "properties": {
    "gn:admin1_code":"23.0",
    "gn:admin2_code":"1113.0",
    "gn:asciiname":"As Salulah",
    "gn:country_code":"YE",
    "gn:dem":2032,
    "gn:feature_class":"P",
    "gn:feature_code":"PPL",
    "gn:name":"A\u015f \u015eal\u016blah",
    "gn:population":0,
    "gn:timezone":"Asia/Aden",
    "iso:country":"YE",
    "name:und_x_variant":[
        "Salula",
        "A\u015f \u015eal\u016blah",
        "Sal\u016blah"
    ],
    "wof:name":"As Salulah",
    "wof:placetype":"locality"
},
  "geometry": {"coordinates":[44.35619000000001,13.9745],"type":"Point"}
}