{
  "type": "Feature",
  "properties": {
    "gn:admin1_code":"8.0",
    "gn:admin2_code":"1810.0",
    "gn:asciiname":"Al Makabinah",
    "gn:country_code":"YE",
    "gn:dem":121,
    "gn:feature_class":"P",
    "gn:feature_code":"PPL",
    "gn:name":"Al Mak\u0101binah",
    "gn:population":0,
    "gn:timezone":"Asia/Aden",
    "iso:country":"YE",
    "name:ara_x_preferred":[
        "\u0627\u0644\u0645\u0643\u0627\u0628\u0646\u0629"
    ],
    "name:und_x_variant":[
        "Ma\u1e29all as Saw\u0101jidah",
        "Al Mak\u0101binah"
    ],
    "wof:name":"Al Makabinah",
    "wof:placetype":"locality"
},
  "geometry": {"coordinates":[43.16786,15.14717],"type":"Point"}
}