{
  "type": "Feature",
  "properties": {
    "gn:admin1_code":"15.0",
    "gn:admin2_code":"2205.0",
    "gn:asciiname":"Gharib 'Abbash",
    "gn:country_code":"YE",
    "gn:dem":399,
    "gn:feature_class":"P",
    "gn:feature_code":"PPL",
    "gn:name":"Gh\u0101rib \u2018Abb\u0101sh",
    "gn:population":0,
    "gn:timezone":"Asia/Aden",
    "iso:country":"YE",
    "name:ara_x_preferred":[
        "Gh\u0101rib \u2018Abb\u0101sh"
    ],
    "name:ara_x_variant":[
        "\u063a\u0627\u0631\u0628 \u0639\u0628\u0627\u0634"
    ],
    "wof:name":"Gharib 'Abbash",
    "wof:placetype":"locality"
},
  "geometry": {"coordinates":[43.245,16.8277],"type":"Point"}
}