{
  "type": "Feature",
  "properties": {
    "gn:admin1_code":"8.0",
    "gn:admin2_code":"1810.0",
    "gn:asciiname":"Mahall al Qadiri",
    "gn:country_code":"YE",
    "gn:dem":166,
    "gn:feature_class":"P",
    "gn:feature_code":"PPL",
    "gn:name":"Ma\u1e29all al Q\u0101dir\u012b",
    "gn:population":0,
    "gn:timezone":"Asia/Aden",
    "iso:country":"YE",
    "name:und_x_variant":[
        "Ma\u1e29all al Q\u0101dir\u012b"
    ],
    "wof:name":"Mahall al Qadiri",
    "wof:placetype":"locality"
},
  "geometry": {"coordinates":[43.26004,15.04128],"type":"Point"}
}