{
  "type": "Feature",
  "properties": {
    "gn:admin1_code":"19.0",
    "gn:admin2_code":"2919.0",
    "gn:asciiname":"Ar Rukabi al Asfal",
    "gn:country_code":"YE",
    "gn:dem":1583,
    "gn:feature_class":"P",
    "gn:feature_code":"PPL",
    "gn:name":"Ar Ruk\u0101b\u012b al Asfal",
    "gn:population":0,
    "gn:timezone":"Asia/Aden",
    "iso:country":"YE",
    "name:ara_x_preferred":[
        "\u0627\u0644\u0631\u0643\u0627\u0628\u064a \u0627\u0644\u0623\u0633\u0641\u0644"
    ],
    "name:und_x_variant":[
        "Ar Ruk\u0101b\u012b al Asfal"
    ],
    "wof:name":"Ar Rukabi al Asfal",
    "wof:placetype":"locality"
},
  "geometry": {"coordinates":[43.80966,16.0624],"type":"Point"}
}