{
  "type": "Feature",
  "properties": {
    "gn:country":"YE",
    "gn:fcode":"PPLX",
    "gn:population":6,
    "iso:country":"YE",
    "name:ara_x_preferred":[
        "\u0627\u0644\u0634\u0631\u064a\u0629 \u0627\u0644\u0633\u0641\u0644\u0649"
    ],
    "name:ara_x_variant":[
        "\u0645\u062f\u064a\u0631\u064a\u0629 \u064a\u0645\u0646\u064a\u0629"
    ],
    "name:bug_x_preferred":[
        "Distrik ri Yaman"
    ],
    "name:deu_x_preferred":[
        "Distrikt in Jemen"
    ],
    "name:eng_x_preferred":[
        "district of Yemen"
    ],
    "name:fas_x_preferred":[
        "\u0641\u0647\u0631\u0633\u062a \u0646\u0627\u062d\u06cc\u0647\u200c\u0647\u0627\u06cc \u06cc\u0645\u0646"
    ],
    "name:heb_x_preferred":[
        "\u05de\u05d7\u05d5\u05d6 \u05d1\u05ea\u05d9\u05de\u05df"
    ],
    "name:ita_x_preferred":[
        "Distretti dello Yemen"
    ],
    "name:nan_x_preferred":[
        "Yemen \u00ea ko\u0101n"
    ],
    "name:nld_x_preferred":[
        "district van Jemen"
    ],
    "name:rus_x_preferred":[
        "\u043c\u0443\u0434\u0438\u0440\u0438\u044f \u0432 \u0419\u0435\u043c\u0435\u043d\u0435"
    ],
    "name:tur_x_preferred":[
        "Yemen'in il\u00e7eleri"
    ],
    "name:urd_x_preferred":[
        "\u0641\u06c1\u0631\u0633\u062a \u06cc\u0645\u0646 \u06a9\u06d2 \u0627\u0636\u0644\u0627\u0639"
    ],
    "qs:name":"Ash Sharyah as Sufl\u00e1",
    "qs:photos_9r":0,
    "qs:photos_sr":0,
    "qs:pop_sr":"1",
    "wd:wordcount":956,
    "wof:name":"Ash Sharyah as Sufl\u00e1",
    "wof:placetype":"neighbourhood",
    "wof:population":6
},
  "geometry": {"coordinates":[45.36555,14.37212],"type":"Point"}
}