{
  "type": "Feature",
  "properties": {
    "gn:country":"YE",
    "gn:fcode":"PPLX",
    "gn:pop":6,
    "iso:country":"YE",
    "name:ara_x_preferred":[
        "\u0627\u0644\u0634\u0631\u064a\u0629 \u0627\u0644\u0633\u0641\u0644\u0649"
    ],
    "qs:name":"Ash Sharyah as Sufl\u00e1",
    "qs:photos_9r":0,
    "qs:photos_sr":0,
    "qs:pop_sr":"1",
    "wd:wordcount":956,
    "wof:name":"Ash Sharyah as Sufl\u00e1",
    "wof:placetype":"neighbourhood",
    "wof:population":6
},
  "geometry": {"coordinates":[45.36555,14.37212],"type":"Point"}
}