{
  "type": "Feature",
  "properties": {
    "gn:country":"YE",
    "gn:fcode":"PPL",
    "gn:population":7,
    "iso:country":"YE",
    "name:ara_x_preferred":[
        "\u0627\u0644 \u062c\u0639\u0628\u0644"
    ],
    "name:eng_x_preferred":[
        "Al Ja'bal"
    ],
    "name:eng_x_variant":[
        "Al Madf\u016bn"
    ],
    "qs:name":"\u0100l Ja\u2018bal",
    "qs:photos_9r":0,
    "qs:photos_sr":0,
    "qs:pop_sr":"1",
    "wof:name":"\u0100l Ja\u2018bal",
    "wof:placetype":"locality",
    "wof:population":7
},
  "geometry": {"coordinates":[43.38951,16.80422],"type":"Point"}
}