{
  "type": "Feature",
  "properties": {
    "gn:country":"YE",
    "gn:fcode":"PPL",
    "gn:pop":6,
    "iso:country":"YE",
    "name:ara_x_preferred":[
        "\u062d\u062f\u0628\u0629 \u0627\u0644\u0628\u0633\u0629"
    ],
    "name:eng_x_preferred":[
        "Hadibat Al Bissah"
    ],
    "qs:name":"\u1e28adibat al Bissah",
    "qs:photos_9r":0,
    "qs:photos_sr":0,
    "qs:pop_sr":"1",
    "wof:name":"\u1e28adibat al Bissah",
    "wof:placetype":"locality",
    "wof:population":6
},
  "geometry": {"coordinates":[43.37697,16.29436],"type":"Point"}
}