{
  "type": "Feature",
  "properties": {
    "gn:country":"YE",
    "gn:fcode":"PPLF",
    "gn:pop":67,
    "iso:country":"YE",
    "name:ara_x_preferred":[
        "\u0639\u0634\u0631\u064a"
    ],
    "qs:name":"\u2018Ashar\u012b",
    "qs:photos_9r":0,
    "qs:photos_sr":0,
    "qs:pop_sr":"1",
    "wof:name":"\u2018Ashar\u012b",
    "wof:placetype":"locality",
    "wof:population":67
},
  "geometry": {"coordinates":[43.67367,16.94712],"type":"Point"}
}