{
  "type": "Feature",
  "properties": {
    "gn:admin1_code":"8.0",
    "gn:admin2_code":"1815.0",
    "gn:asciiname":"Umm Za`awir",
    "gn:country_code":"YE",
    "gn:dem":116,
    "gn:feature_class":"P",
    "gn:feature_code":"PPL",
    "gn:name":"Umm Za\u2018\u0101wir",
    "gn:population":0,
    "gn:timezone":"Asia/Aden",
    "iso:country":"YE",
    "name:und_x_variant":[
        "Umm Za\u2018\u0101wir"
    ],
    "wof:name":"Umm Za`awir",
    "wof:placetype":"locality"
},
  "geometry": {"coordinates":[43.25485,14.74193],"type":"Point"}
}