{
  "type": "Feature",
  "properties": {
    "gn:admin1_code":"22.0",
    "gn:admin2_code":"1725.0",
    "gn:asciiname":"An Numayr",
    "gn:country_code":"YE",
    "gn:dem":657,
    "gn:feature_class":"P",
    "gn:feature_code":"PPL",
    "gn:name":"An Numayr",
    "gn:population":0,
    "gn:timezone":"Asia/Aden",
    "iso:country":"YE",
    "name:ara_x_preferred":[
        "\u0627\u0644\u0646\u0645\u064a\u0631"
    ],
    "wof:name":"An Numayr",
    "wof:placetype":"locality"
},
  "geometry": {"coordinates":[43.52113,15.55163],"type":"Point"}
}