{
  "type": "Feature",
  "properties": {
    "gn:admin1_code":"23.0",
    "gn:admin2_code":"1111.0",
    "gn:asciiname":"Bayt al Haddad",
    "gn:country_code":"YE",
    "gn:dem":1468,
    "gn:feature_class":"P",
    "gn:feature_code":"PPL",
    "gn:name":"Bayt al \u1e28add\u0101d",
    "gn:population":0,
    "gn:timezone":"Asia/Aden",
    "iso:country":"YE",
    "name:ara_x_preferred":[
        "\u0628\u064a\u062a \u0627\u0644\u062d\u062f\u0627\u062f"
    ],
    "name:und_x_variant":[
        "Qaryat al \u1e28add\u0101d",
        "Bayt al \u1e28add\u0101d"
    ],
    "wof:name":"Bayt al Haddad",
    "wof:placetype":"locality"
},
  "geometry": {"coordinates":[43.89602,14.06821],"type":"Point"}
}