{
  "type": "Feature",
  "properties": {
    "gn:country":"YE",
    "gn:fcode":"PPL",
    "gn:pop":2,
    "iso:country":"YE",
    "name:ara_x_preferred":[
        "\u0627\u0644\u0645\u063a\u0631\u0628\u0629"
    ],
    "qs:name":"Al Maghrabah",
    "qs:photos_9r":0,
    "qs:photos_sr":0,
    "qs:pop_sr":"1",
    "wd:wordcount":55,
    "wof:name":"Al Maghrabah",
    "wof:placetype":"locality",
    "wof:population":2
},
  "geometry": {"coordinates":[43.68527,16.04094],"type":"Point"}
}