{
  "type": "Feature",
  "properties": {
    "gn:admin1_code":"24.0",
    "gn:admin2_code":"2508.0",
    "gn:asciiname":"Al Hayd al Asfal",
    "gn:country_code":"YE",
    "gn:dem":1232,
    "gn:feature_class":"P",
    "gn:feature_code":"PPL",
    "gn:name":"Al \u1e28ayd al Asfal",
    "gn:population":0,
    "gn:timezone":"Asia/Aden",
    "iso:country":"YE",
    "name:und_x_variant":[
        "Al \u1e28ayd al Asfal"
    ],
    "wof:name":"Al Hayd al Asfal",
    "wof:placetype":"locality"
},
  "geometry": {"coordinates":[44.97111,13.40611],"type":"Point"}
}