{
  "type": "Feature",
  "properties": {
    "gn:admin1_code":"19.0",
    "gn:admin2_code":"2919.0",
    "gn:asciiname":"Manayib Sharih",
    "gn:country_code":"YE",
    "gn:dem":2502,
    "gn:feature_class":"P",
    "gn:feature_code":"PPL",
    "gn:name":"Man\u0101yib Shar\u012b\u1e29",
    "gn:population":0,
    "gn:timezone":"Asia/Aden",
    "iso:country":"YE",
    "name:ara_x_preferred":[
        "\u0645\u0646\u0627\u064a\u0628 \u0634\u0631\u064a\u062d"
    ],
    "name:und_x_variant":[
        "Man\u0101yib Shar\u012b\u1e29"
    ],
    "wof:name":"Manayib Sharih",
    "wof:placetype":"locality"
},
  "geometry": {"coordinates":[44.00789,16.00688],"type":"Point"}
}