{
  "type": "Feature",
  "properties": {
    "gn:admin1_code":"14.0",
    "gn:admin2_code":"2605.0",
    "gn:asciiname":"Al Mihzarah",
    "gn:country_code":"YE",
    "gn:dem":2000,
    "gn:feature_class":"P",
    "gn:feature_code":"PPL",
    "gn:name":"Al Mi\u1e29z\u0101rah",
    "gn:population":0,
    "gn:timezone":"Asia/Aden",
    "iso:country":"YE",
    "name:ara_x_preferred":[
        "\u0627\u0644\u0645\u062d\u0632\u0627\u0631\u0629"
    ],
    "name:und_x_variant":[
        "Al Mi\u1e29z\u0101rah"
    ],
    "wof:name":"Al Mihzarah",
    "wof:placetype":"locality"
},
  "geometry": {"coordinates":[44.75094,15.41723],"type":"Point"}
}