{
  "type": "Feature",
  "properties": {
    "gn:admin1_code":"8.0",
    "gn:admin2_code":"1824.0",
    "gn:asciiname":"Mashi`ah",
    "gn:country_code":"YE",
    "gn:dem":176,
    "gn:feature_class":"P",
    "gn:feature_code":"PPL",
    "gn:name":"M\u0101shi\u2018ah",
    "gn:population":0,
    "gn:timezone":"Asia/Aden",
    "iso:country":"YE",
    "name:ara_x_preferred":[
        "\u0645\u0627\u0634\u0639\u0629"
    ],
    "name:und_x_variant":[
        "M\u0101shi\u2018ah"
    ],
    "wof:name":"Mashi`ah",
    "wof:placetype":"locality"
},
  "geometry": {"coordinates":[43.4777,13.98843],"type":"Point"}
}