{
  "type": "Feature",
  "properties": {
    "gn:admin1_code":"25.0",
    "gn:admin2_code":"1515.0",
    "gn:asciiname":"Al Mayqa`",
    "gn:country_code":"YE",
    "gn:dem":1779,
    "gn:feature_class":"P",
    "gn:feature_code":"PPL",
    "gn:name":"Al Mayq\u0101\u2018",
    "gn:population":0,
    "gn:timezone":"Asia/Aden",
    "iso:country":"YE",
    "name:und_x_variant":[
        "Al Mayq\u0101\u2018"
    ],
    "wof:name":"Al Mayqa`",
    "wof:placetype":"locality"
},
  "geometry": {"coordinates":[44.11199000000001,13.16097],"type":"Point"}
}