{
  "type": "Feature",
  "properties": {
    "gn:gn_country":"YE",
    "gn:gn_fcode":"PPL",
    "gn:gn_pop":50,
    "gn:population":50,
    "iso:country":"YE",
    "name:ara_x_preferred":[
        "\u0631\u0627\u0643\u0628 \u0627\u0644\u0639\u0643\u0634\u064a"
    ],
    "name:eng_x_preferred":[
        "Rakib Al 'Akshi"
    ],
    "name:eng_x_variant":[
        "Al Ghurayqah"
    ],
    "qs_pg:aaroncc":"YE",
    "qs_pg:gn_country":"YE",
    "qs_pg:gn_fcode":"PPL",
    "qs_pg:gn_pop":50,
    "qs_pg:name":"R\u0101kib al \u2018Aksh\u012b",
    "qs_pg:photos_9r":0,
    "qs_pg:photos_sr":0,
    "qs_pg:pop_sr":1,
    "qs_pg:qs_pg_placetype":"locality",
    "wof:name":"R\u0101kib al \u2018Aksh\u012b",
    "wof:placetype":"locality",
    "wof:population":50
},
  "geometry": {"coordinates":[43.30358,16.27491],"type":"Point"}
}