{
  "type": "Feature",
  "properties": {
    "gn:gn_country":"YE",
    "gn:gn_fcode":"PPL",
    "gn:gn_pop":3,
    "gn:population":3,
    "iso:country":"YE",
    "name:ara_x_preferred":[
        "\u0627\u0644\u062d\u0633\u064a\u0628\u0629"
    ],
    "name:eng_x_preferred":[
        "Al Husaybah"
    ],
    "qs_pg:aaroncc":"YE",
    "qs_pg:gn_country":"YE",
    "qs_pg:gn_fcode":"PPL",
    "qs_pg:gn_pop":3,
    "qs_pg:name":"Al \u1e28usaybah",
    "qs_pg:photos_9r":0,
    "qs_pg:photos_sr":0,
    "qs_pg:pop_sr":1,
    "qs_pg:qs_pg_placetype":"locality",
    "wof:name":"Al \u1e28usaybah",
    "wof:placetype":"locality",
    "wof:population":3
},
  "geometry": {"coordinates":[43.6157,16.04402],"type":"Point"}
}