{
  "type": "Feature",
  "properties": {
    "gn:admin1_code":"8.0",
    "gn:admin2_code":"1824.0",
    "gn:asciiname":"Al Ja`afirah",
    "gn:country_code":"YE",
    "gn:dem":230,
    "gn:feature_class":"P",
    "gn:feature_code":"PPL",
    "gn:name":"Al Ja\u2018\u0101firah",
    "gn:population":0,
    "gn:timezone":"Asia/Aden",
    "iso:country":"YE",
    "name:und_x_variant":[
        "Al Ja\u2018\u0101firah"
    ],
    "wof:name":"Al Ja`afirah",
    "wof:placetype":"locality"
},
  "geometry": {"coordinates":[43.41863,14.37097],"type":"Point"}
}