{
  "type": "Feature",
  "properties": {
    "gn:country":"YE",
    "gn:fcode":"PPL",
    "gn:population":5,
    "iso:country":"YE",
    "name:ara_x_preferred":[
        "\u0627\u0644\u0645\u062d\u0641\u062f\u0629"
    ],
    "name:eng_x_preferred":[
        "Al Mahfadah"
    ],
    "name:eng_x_variant":[
        "\u1e28illat al Biq\u0101f"
    ],
    "qs:name":"Al Ma\u1e29fadah",
    "qs:photos_9r":0,
    "qs:photos_sr":0,
    "qs:pop_sr":"1",
    "wof:name":"Al Ma\u1e29fadah",
    "wof:placetype":"locality",
    "wof:population":5
},
  "geometry": {"coordinates":[43.68844,16.13445],"type":"Point"}
}