{
  "type": "Feature",
  "properties": {
    "gn:admin1_code":"22.0",
    "gn:admin2_code":"1717.0",
    "gn:asciiname":"Al Hasabah",
    "gn:country_code":"YE",
    "gn:dem":936,
    "gn:feature_class":"P",
    "gn:feature_code":"PPL",
    "gn:name":"Al \u1e28a\u015fabah",
    "gn:population":0,
    "gn:timezone":"Asia/Aden",
    "iso:country":"YE",
    "name:und_x_variant":[
        "Al \u1e28a\u015fabah"
    ],
    "wof:name":"Al Hasabah",
    "wof:placetype":"locality"
},
  "geometry": {"coordinates":[43.64531,15.83821],"type":"Point"}
}