{
  "type": "Feature",
  "properties": {
    "gn:country":"YE",
    "gn:fcode":"PPL",
    "gn:pop":8,
    "iso:country":"YE",
    "name:ara_x_preferred":[
        "\u0627\u0644\u0644\u062c\u0645\u0629"
    ],
    "name:eng_x_preferred":[
        "Al Lajmah"
    ],
    "qs:name":"Al Lajmah",
    "qs:photos_9r":0,
    "qs:photos_sr":0,
    "qs:pop_sr":"1",
    "wof:name":"Al Lajmah",
    "wof:placetype":"locality",
    "wof:population":8
},
  "geometry": {"coordinates":[45.31663,14.7111],"type":"Point"}
}