{
  "type": "Feature",
  "properties": {
    "gn:country":"YE",
    "gn:fcode":"PPLL",
    "gn:pop":5,
    "iso:country":"YE",
    "name:ara_x_preferred":[
        "\u0627\u0644\u0642\u0631\u0648"
    ],
    "name:eng_x_preferred":[
        "Al QarU"
    ],
    "name:eng_x_variant":[
        "Dh\u012b \u2018Ayn"
    ],
    "qs:name":"Al Qar\u016b",
    "qs:photos_9r":0,
    "qs:photos_sr":0,
    "qs:pop_sr":"1",
    "wof:name":"Al Qar\u016b",
    "wof:placetype":"locality",
    "wof:population":5
},
  "geometry": {"coordinates":[43.28407,16.23485],"type":"Point"}
}