{
  "type": "Feature",
  "properties": {
    "gn:country":"YE",
    "gn:fcode":"PPL",
    "gn:population":1,
    "iso:country":"YE",
    "name:ara_x_preferred":[
        "Adh Dhunb\u016bb"
    ],
    "name:ara_x_variant":[
        "\u0627\u0644\u0630\u0646\u0628\u0648\u0628"
    ],
    "name:eng_x_preferred":[
        "Adh DhunbUb"
    ],
    "name:eng_x_variant":[
        "Al F\u0101\u015fah"
    ],
    "qs_pg:aaroncc":"YE",
    "qs_pg:gn_country":"YE",
    "qs_pg:gn_fcode":"PPL",
    "qs_pg:gn_pop":1,
    "qs_pg:name":"Adh Dhunb\u016bb",
    "qs_pg:photos_9r":0,
    "qs_pg:photos_sr":0,
    "qs_pg:pop_sr":1,
    "qs_pg:qs_pg_placetype":"locality",
    "wof:name":"Adh Dhunb\u016bb",
    "wof:placetype":"locality",
    "wof:population":1
},
  "geometry": {"coordinates":[43.99573,13.23359],"type":"Point"}
}