{
  "type": "Feature",
  "properties": {
    "gn:admin1_code":"18.0",
    "gn:admin2_code":"3002.0",
    "gn:asciiname":"Az Zahirah",
    "gn:country_code":"YE",
    "gn:dem":2133,
    "gn:feature_class":"P",
    "gn:feature_code":"PPL",
    "gn:name":"Az\u0327 Z\u0327\u0101hirah",
    "gn:population":0,
    "gn:timezone":"Asia/Aden",
    "iso:country":"YE",
    "name:und_x_variant":[
        "Az\u0327 Z\u0327\u0101hirah"
    ],
    "wof:name":"Az Zahirah",
    "wof:placetype":"locality"
},
  "geometry": {"coordinates":[44.7395,14.08221],"type":"Point"}
}