{
  "type": "Feature",
  "properties": {
    "gn:admin1_code":"18.0",
    "gn:admin2_code":"3005.0",
    "gn:asciiname":"Lakmat al Ash`ub",
    "gn:country_code":"YE",
    "gn:dem":1398,
    "gn:feature_class":"P",
    "gn:feature_code":"PPL",
    "gn:name":"Lakmat al Ash\u2018\u016bb",
    "gn:population":0,
    "gn:timezone":"Asia/Aden",
    "iso:country":"YE",
    "name:und_x_variant":[
        "Lakmat ash Shub",
        "Lakamat Al Ash\u2019ub",
        "Lakmat al Ash\u2018\u016bb"
    ],
    "wof:name":"Lakmat al Ash`ub",
    "wof:placetype":"locality"
},
  "geometry": {"coordinates":[44.75455,13.82778],"type":"Point"}
}