{
  "type": "Feature",
  "properties": {
    "gn:admin1_code":"19.0",
    "gn:admin2_code":"2917.0",
    "gn:asciiname":"Thalsa'",
    "gn:country_code":"YE",
    "gn:dem":3078,
    "gn:feature_class":"P",
    "gn:feature_code":"PPL",
    "gn:name":"Thals\u0101\u2019",
    "gn:population":0,
    "gn:timezone":"Asia/Aden",
    "iso:country":"YE",
    "name:nno_x_preferred":[
        "Thalsa'"
    ],
    "name:und_x_variant":[
        "Thals\u0101\u2019"
    ],
    "wof:name":"Thalsa'",
    "wof:placetype":"locality"
},
  "geometry": {"coordinates":[43.81667,15.61667],"type":"Point"}
}