{
  "type": "Feature",
  "properties": {
    "gn:admin1_code":"11.0",
    "gn:admin2_code":"2003.0",
    "gn:asciiname":"Bayt al Humayni",
    "gn:country_code":"YE",
    "gn:dem":2015,
    "gn:feature_class":"P",
    "gn:feature_code":"PPL",
    "gn:name":"Bayt al \u1e28umayn\u012b",
    "gn:population":0,
    "gn:timezone":"Asia/Aden",
    "iso:country":"YE",
    "name:und_x_variant":[
        "Bayt al \u1e28umayn\u012b"
    ],
    "wof:name":"Bayt al Humayni",
    "wof:placetype":"locality"
},
  "geometry": {"coordinates":[43.93853,14.73629],"type":"Point"}
}