{
  "type": "Feature",
  "properties": {
    "gn:country":"YE",
    "gn:fcode":"PPL",
    "gn:pop":2,
    "iso:country":"YE",
    "name:ara_x_preferred":[
        "\u0627\u0644\u0645\u062e\u062f\u0645"
    ],
    "name:eng_x_preferred":[
        "Al Makhdam"
    ],
    "name:eng_x_variant":[
        "As Saqy\u0101n"
    ],
    "qs:name":"Al Makhdam",
    "qs:photos_9r":0,
    "qs:photos_sr":0,
    "qs:pop_sr":"1",
    "wof:name":"Al Makhdam",
    "wof:placetype":"locality",
    "wof:population":2
},
  "geometry": {"coordinates":[45.2819,14.1129],"type":"Point"}
}