{
  "type": "Feature",
  "properties": {
    "gn:admin1_code":"25.0",
    "gn:admin2_code":"1502.0",
    "gn:asciiname":"Al `Arakim",
    "gn:country_code":"YE",
    "gn:dem":1398,
    "gn:feature_class":"P",
    "gn:feature_code":"PPL",
    "gn:name":"Al \u2018Ar\u0101kim",
    "gn:population":0,
    "gn:timezone":"Asia/Aden",
    "iso:country":"YE",
    "name:ara_x_preferred":[
        "Al \u2018Ar\u0101kim"
    ],
    "wof:name":"Al `Arakim",
    "wof:placetype":"locality"
},
  "geometry": {"coordinates":[44.08876,13.64016],"type":"Point"}
}