{
  "type": "Feature",
  "properties": {
    "gn:admin1_code":"8.0",
    "gn:admin2_code":"1806.0",
    "gn:asciiname":"Dayr ash Sharfayn",
    "gn:country_code":"YE",
    "gn:dem":69,
    "gn:feature_class":"P",
    "gn:feature_code":"PPL",
    "gn:name":"Dayr ash Sharfayn",
    "gn:population":0,
    "gn:timezone":"Asia/Aden",
    "iso:country":"YE",
    "wof:name":"Dayr ash Sharfayn",
    "wof:placetype":"locality"
},
  "geometry": {"coordinates":[43.06437,15.4817],"type":"Point"}
}