{
  "type": "Feature",
  "properties": {
    "gn:admin1_code":"16.0",
    "gn:admin2_code":"2312.0",
    "gn:asciiname":"Rayib",
    "gn:country_code":"YE",
    "gn:dem":2108,
    "gn:feature_class":"P",
    "gn:feature_code":"PPL",
    "gn:name":"R\u0101yib",
    "gn:population":0,
    "gn:timezone":"Asia/Aden",
    "iso:country":"YE",
    "name:ara_x_preferred":[
        "\u0631\u0627\u064a\u0628"
    ],
    "name:und_x_variant":[
        "R\u0101yib"
    ],
    "wof:name":"Rayib",
    "wof:placetype":"locality"
},
  "geometry": {"coordinates":[44.73548,15.28302],"type":"Point"}
}