{
  "type": "Feature",
  "properties": {
    "gn:admin1_code":"24.0",
    "gn:admin2_code":"2512.0",
    "gn:asciiname":"Al Ma`suq",
    "gn:country_code":"YE",
    "gn:dem":1216,
    "gn:feature_class":"P",
    "gn:feature_code":"PPL",
    "gn:name":"Al Ma\u2018s\u016bq",
    "gn:population":0,
    "gn:timezone":"Asia/Aden",
    "iso:country":"YE",
    "name:und_x_variant":[
        "Al Ma\u2018s\u016bq"
    ],
    "wof:name":"Al Ma`suq",
    "wof:placetype":"locality"
},
  "geometry": {"coordinates":[44.16283,13.18784],"type":"Point"}
}