{
  "type": "Feature",
  "properties": {
    "gn:admin1_code":"14.0",
    "gn:admin2_code":"2610.0",
    "gn:asciiname":"Al Majza`ah",
    "gn:country_code":"YE",
    "gn:dem":1669,
    "gn:feature_class":"P",
    "gn:feature_code":"PPL",
    "gn:name":"Al Majza\u2018ah",
    "gn:population":0,
    "gn:timezone":"Asia/Aden",
    "iso:country":"YE",
    "name:ara_x_preferred":[
        "\u0627\u0644\u0645\u062c\u0632\u0639\u0629"
    ],
    "name:und_x_variant":[
        "Al Majza\u2018ah"
    ],
    "wof:name":"Al Majza`ah",
    "wof:placetype":"locality"
},
  "geometry": {"coordinates":[45.15141,14.73553],"type":"Point"}
}