{
  "type": "Feature",
  "properties": {
    "gn:admin1_code":"15.0",
    "gn:admin2_code":"2212.0",
    "gn:asciiname":"Al Hadirah",
    "gn:country_code":"YE",
    "gn:dem":2044,
    "gn:feature_class":"P",
    "gn:feature_code":"PPL",
    "gn:name":"Al \u1e28a\u1e11\u012brah",
    "gn:population":0,
    "gn:timezone":"Asia/Aden",
    "iso:country":"YE",
    "name:und_x_variant":[
        "Al \u1e28a\u1e11\u012brah"
    ],
    "wof:name":"Al Hadirah",
    "wof:placetype":"locality"
},
  "geometry": {"coordinates":[43.84121,16.80487],"type":"Point"}
}