{
  "type": "Feature",
  "properties": {
    "gn:admin1_code":"19.0",
    "gn:admin2_code":"2908.0",
    "gn:asciiname":"Al 'Adi",
    "gn:country_code":"YE",
    "gn:dem":1694,
    "gn:feature_class":"P",
    "gn:feature_code":"PPL",
    "gn:name":"Al \u2018\u0100d\u012b",
    "gn:population":0,
    "gn:timezone":"Asia/Aden",
    "iso:country":"YE",
    "name:ara_x_preferred":[
        "Al \u2018\u0100d\u012b"
    ],
    "name:ara_x_variant":[
        "\u0627\u0644\u0639\u0627\u062f\u064a"
    ],
    "wof:name":"Al 'Adi",
    "wof:placetype":"locality"
},
  "geometry": {"coordinates":[43.72574,16.09582],"type":"Point"}
}