{
  "type": "Feature",
  "properties": {
    "gn:country":"YE",
    "gn:fcode":"PPL",
    "gn:population":5,
    "iso:country":"YE",
    "name:ara_x_preferred":[
        "\u0627\u0644\u0633\u0627\u062f\u0629"
    ],
    "name:ara_x_variant":[
        "\u0645\u062f\u064a\u0631\u064a\u0629 \u0627\u0644\u0633\u062f\u0629"
    ],
    "name:ceb_x_preferred":[
        "As Saddah"
    ],
    "name:eng_x_preferred":[
        "As Saddah District"
    ],
    "name:fra_x_preferred":[
        "As Saddah"
    ],
    "name:nan_x_preferred":[
        "As Saddah Ko\u0101n"
    ],
    "name:nno_x_preferred":[
        "As Saddah-distriktet"
    ],
    "name:urd_x_preferred":[
        "\u0627\u0644\u0633\u062f\u06c1 \u0636\u0644\u0639"
    ],
    "name:vie_x_preferred":[
        "As Saddah"
    ],
    "qs:name":"As S\u0101ddah",
    "qs:photos_9r":0,
    "qs:photos_sr":0,
    "qs:pop_sr":"1",
    "wd:wordcount":57,
    "wof:name":"As S\u0101ddah",
    "wof:placetype":"locality",
    "wof:population":5
},
  "geometry": {"coordinates":[44.04591,17.05864],"type":"Point"}
}