{
  "type": "Feature",
  "properties": {
    "gn:admin1_code":"22.0",
    "gn:admin2_code":"1726.0",
    "gn:asciiname":"Bayt al Badi",
    "gn:country_code":"YE",
    "gn:dem":1192,
    "gn:feature_class":"P",
    "gn:feature_code":"PPL",
    "gn:name":"Bayt al B\u0101d\u012b",
    "gn:population":0,
    "gn:timezone":"Asia/Aden",
    "iso:country":"YE",
    "name:und_x_variant":[
        "Bayt al B\u0101d\u012b"
    ],
    "wof:name":"Bayt al Badi",
    "wof:placetype":"locality"
},
  "geometry": {"coordinates":[43.52871,15.63278],"type":"Point"}
}