{
  "type": "Feature",
  "properties": {
    "gn:admin1_code":"16.0",
    "gn:admin2_code":"2312.0",
    "gn:asciiname":"Al Ma`yanah",
    "gn:country_code":"YE",
    "gn:dem":2124,
    "gn:feature_class":"P",
    "gn:feature_code":"PPL",
    "gn:name":"Al Ma\u2018yanah",
    "gn:population":0,
    "gn:timezone":"Asia/Aden",
    "iso:country":"YE",
    "name:und_x_variant":[
        "Al Ma\u2018yanah"
    ],
    "wof:name":"Al Ma`yanah",
    "wof:placetype":"locality"
},
  "geometry": {"coordinates":[44.60417,15.225],"type":"Point"}
}