{
  "type": "Feature",
  "properties": {
    "gn:admin1_code":"21.0",
    "gn:admin2_code":"1601.0",
    "gn:asciiname":"As Sulayl al 'Ajiz",
    "gn:country_code":"YE",
    "gn:dem":1002,
    "gn:feature_class":"P",
    "gn:feature_code":"PPLL",
    "gn:name":"As Sulayl al \u2018Aj\u012bz",
    "gn:population":0,
    "gn:timezone":"Asia/Aden",
    "iso:country":"YE",
    "name:ara_x_preferred":[
        "\u0627\u0644\u0633\u0644\u064a\u0644 \u0627\u0644\u0639\u062c\u064a\u0632"
    ],
    "name:und_x_variant":[
        "As Sulayl al \u2018Aj\u012bz"
    ],
    "wof:name":"As Sulayl al 'Ajiz",
    "wof:placetype":"locality"
},
  "geometry": {"coordinates":[45.39426,15.87867],"type":"Point"}
}