{
  "type": "Feature",
  "properties": {
    "gn:country":"YE",
    "gn:fcode":"PPL",
    "gn:pop":8,
    "iso:country":"YE",
    "name:ara_x_preferred":[
        "Al Bid\u0101yi\u2018"
    ],
    "name:ara_x_variant":[
        "\u0627\u0644\u0628\u062f\u0627\u064a\u0639"
    ],
    "name:eng_x_preferred":[
        "Al Bidayi'"
    ],
    "name:eng_x_variant":[
        "Al Gham\u0101r"
    ],
    "qs:name":"Al Bid\u0101yi\u2018",
    "qs:photos_9r":0,
    "qs:photos_sr":0,
    "qs:pop_sr":"1",
    "wof:name":"Al Bid\u0101yi\u2018",
    "wof:placetype":"locality",
    "wof:population":8
},
  "geometry": {"coordinates":[45.13676,14.32066],"type":"Point"}
}