{
  "type": "Feature",
  "properties": {
    "gn:admin1_code":"18.0",
    "gn:admin2_code":"3005.0",
    "gn:asciiname":"As Sararah",
    "gn:country_code":"YE",
    "gn:dem":1528,
    "gn:feature_class":"P",
    "gn:feature_code":"PPL",
    "gn:name":"A\u015f \u015ear\u0101rah",
    "gn:population":0,
    "gn:timezone":"Asia/Aden",
    "iso:country":"YE",
    "name:und_x_variant":[
        "A\u015f \u015ear\u0101rah",
        "Sarara",
        "\u015ear\u0101rah"
    ],
    "wof:name":"As Sararah",
    "wof:placetype":"locality"
},
  "geometry": {"coordinates":[44.81522,13.75522],"type":"Point"}
}