{
  "type": "Feature",
  "properties": {
    "gn:admin1_code":"10.0",
    "gn:admin2_code":"2707.0",
    "gn:asciiname":"Ar Rufi`",
    "gn:country_code":"YE",
    "gn:dem":338,
    "gn:feature_class":"P",
    "gn:feature_code":"PPL",
    "gn:name":"Ar Ruf\u012b\u2018",
    "gn:population":0,
    "gn:timezone":"Asia/Aden",
    "iso:country":"YE",
    "name:ara_x_preferred":[
        "Ar Ruf\u012b\u2018"
    ],
    "wof:name":"Ar Rufi`",
    "wof:placetype":"locality"
},
  "geometry": {"coordinates":[43.39667,15.19147],"type":"Point"}
}