{
  "type": "Feature",
  "properties": {
    "gn:admin1_code":"4.0",
    "gn:admin2_code":"1919.0",
    "gn:asciiname":"Shurayj",
    "gn:cc2":"YE",
    "gn:country_code":"YE",
    "gn:dem":699,
    "gn:feature_class":"P",
    "gn:feature_code":"PPL",
    "gn:name":"Shurayj",
    "gn:population":0,
    "gn:timezone":"Asia/Aden",
    "iso:country":"YE",
    "name:und_x_variant":[
        "Shuraij",
        "Sharaij",
        "Shurayj"
    ],
    "wof:name":"Shurayj",
    "wof:placetype":"locality"
},
  "geometry": {"coordinates":[48.06389,15.74528],"type":"Point"}
}