{
  "type": "Feature",
  "properties": {
    "gn:admin1_code":"22.0",
    "gn:admin2_code":"1704.0",
    "gn:asciiname":"Al Mubsham",
    "gn:country_code":"YE",
    "gn:dem":173,
    "gn:feature_class":"P",
    "gn:feature_code":"PPL",
    "gn:name":"Al Mubsh\u0101m",
    "gn:population":0,
    "gn:timezone":"Asia/Aden",
    "iso:country":"YE",
    "name:ara_x_preferred":[
        "Al Mubsh\u0101m"
    ],
    "wof:name":"Al Mubsham",
    "wof:placetype":"locality"
},
  "geometry": {"coordinates":[43.18904000000001,16.02585],"type":"Point"}
}