{
  "type": "Feature",
  "properties": {
    "gn:admin1_code":"20.0",
    "gn:admin2_code":"1412.0",
    "gn:asciiname":"Naq`at al Aghwal",
    "gn:country_code":"YE",
    "gn:dem":2058,
    "gn:feature_class":"P",
    "gn:feature_code":"PPL",
    "gn:name":"Naq\u2018at al Aghw\u0101l",
    "gn:population":0,
    "gn:timezone":"Asia/Aden",
    "iso:country":"YE",
    "name:und_x_variant":[
        "Naq\u2018at al Aghw\u0101l"
    ],
    "wof:name":"Naq`at al Aghwal",
    "wof:placetype":"locality"
},
  "geometry": {"coordinates":[45.23092000000001,14.52944],"type":"Point"}
}