{
  "type": "Feature",
  "properties": {
    "gn:admin1_code":"19.0",
    "gn:admin2_code":"2912.0",
    "gn:asciiname":"Wathiq",
    "gn:country_code":"YE",
    "gn:dem":2342,
    "gn:feature_class":"P",
    "gn:feature_code":"PPL",
    "gn:name":"Wath\u012bq",
    "gn:population":0,
    "gn:timezone":"Asia/Aden",
    "iso:country":"YE",
    "name:und_x_variant":[
        "Wath\u012bq"
    ],
    "wof:name":"Wathiq",
    "wof:placetype":"locality"
},
  "geometry": {"coordinates":[43.8499,15.81183],"type":"Point"}
}