{
  "type": "Feature",
  "properties": {
    "gn:admin1_code":"20.0",
    "gn:admin2_code":"1407.0",
    "gn:asciiname":"Al Ma`udah",
    "gn:country_code":"YE",
    "gn:dem":2006,
    "gn:feature_class":"P",
    "gn:feature_code":"PPLA2",
    "gn:name":"\u0100l Ma\u2018\u016bdah",
    "gn:population":0,
    "gn:timezone":"Asia/Aden",
    "iso:country":"YE",
    "name:ara_x_preferred":[
        "\u0627\u0644\u0637\u0641\u0629"
    ],
    "name:ara_x_variant":[
        "\u0627\u0644\u062d\u0643\u0648\u0645\u0629",
        "\u0627\u0644 \u0645\u0639\u0648\u0636\u0629"
    ],
    "name:und_x_variant":[
        "Qaryat \u0100l Ma\u2018\u016bdah",
        "Al Q\u0101\u2018",
        "A\u0163 \u0163affah",
        "Al Huk\u016bmah",
        "\u0100l Ma\u2018\u016bdah"
    ],
    "wof:name":"Al Ma`udah",
    "wof:placetype":"locality"
},
  "geometry": {"coordinates":[45.38732,14.21055],"type":"Point"}
}