{
  "type": "Feature",
  "properties": {
    "gn:admin1_code":"8.0",
    "gn:admin2_code":"1814.0",
    "gn:asciiname":"Az Zaybalah",
    "gn:country_code":"YE",
    "gn:dem":35,
    "gn:feature_class":"P",
    "gn:feature_code":"PPL",
    "gn:name":"Az Zaybalah",
    "gn:population":0,
    "gn:timezone":"Asia/Aden",
    "iso:country":"YE",
    "name:ara_x_preferred":[
        "\u0627\u0644\u0632\u064a\u0628\u0644\u0629"
    ],
    "name:und_x_variant":[
        "Ma\u1e29all \u1e28usayn Ya\u1e29y\u00e1 al Muhandis",
        "Az Zaybalah"
    ],
    "wof:name":"Az Zaybalah",
    "wof:placetype":"locality"
},
  "geometry": {"coordinates":[43.07638,14.74578],"type":"Point"}
}