{
  "type": "Feature",
  "properties": {
    "gn:admin1_code":"25.0",
    "gn:admin2_code":"1515.0",
    "gn:asciiname":"Al Qahb",
    "gn:country_code":"YE",
    "gn:dem":1038,
    "gn:feature_class":"P",
    "gn:feature_code":"PPL",
    "gn:name":"Al Qahb",
    "gn:population":0,
    "gn:timezone":"Asia/Aden",
    "iso:country":"YE",
    "wof:name":"Al Qahb",
    "wof:placetype":"locality"
},
  "geometry": {"coordinates":[43.99222,13.27583],"type":"Point"}
}