{
  "type": "Feature",
  "properties": {
    "gn:country":"YE",
    "gn:fcode":"PPL",
    "gn:population":8,
    "iso:country":"YE",
    "name:ara_x_preferred":[
        "\u0627\u0644\u062e\u0645\u064a\u0644\u0629"
    ],
    "name:eng_x_preferred":[
        "Al Khamilah"
    ],
    "name:eng_x_variant":[
        "Ar Rabi\u2018"
    ],
    "qs:name":"Al Kham\u012blah",
    "qs:photos_9r":0,
    "qs:photos_sr":0,
    "qs:pop_sr":"1",
    "wd:wordcount":23,
    "wof:name":"Al Kham\u012blah",
    "wof:placetype":"locality",
    "wof:population":8
},
  "geometry": {"coordinates":[43.41378,16.13929],"type":"Point"}
}