{
  "type": "Feature",
  "properties": {
    "gn:admin1_code":"22.0",
    "gn:admin2_code":"1710.0",
    "gn:asciiname":"Dayr ad Dahiyah",
    "gn:country_code":"YE",
    "gn:dem":616,
    "gn:feature_class":"P",
    "gn:feature_code":"PPL",
    "gn:name":"Dayr a\u1e11 \u1e10ah\u012byah",
    "gn:population":0,
    "gn:timezone":"Asia/Aden",
    "iso:country":"YE",
    "name:ara_x_preferred":[
        "\u062f\u064a\u0631 \u0627\u0644\u0636\u0647\u064a\u0629"
    ],
    "name:und_x_variant":[
        "Dayr a\u1e11 \u1e10ah\u012byah"
    ],
    "wof:name":"Dayr ad Dahiyah",
    "wof:placetype":"locality"
},
  "geometry": {"coordinates":[43.38936,16.02483],"type":"Point"}
}