{
  "type": "Feature",
  "properties": {
    "gn:admin1_code":"22.0",
    "gn:admin2_code":"1727.0",
    "gn:asciiname":"Bayt Mashaqah",
    "gn:country_code":"YE",
    "gn:dem":1456,
    "gn:feature_class":"P",
    "gn:feature_code":"PPL",
    "gn:name":"Bayt Mas\u1e29aqah",
    "gn:population":0,
    "gn:timezone":"Asia/Aden",
    "iso:country":"YE",
    "name:ara_x_preferred":[
        "\u0628\u064a\u062a \u0645\u0633\u0640\u062d\u0642\u0640\u0629"
    ],
    "name:und_x_variant":[
        "Bayt Mas\u1e29aqah"
    ],
    "wof:name":"Bayt Mashaqah",
    "wof:placetype":"locality"
},
  "geometry": {"coordinates":[43.59193,15.59453],"type":"Point"}
}