{
  "type": "Feature",
  "properties": {
    "gn:country":"YE",
    "gn:fcode":"PPL",
    "gn:population":6,
    "iso:country":"YE",
    "name:ara_x_preferred":[
        "\u0627\u0644\u062c\u0648\u0632"
    ],
    "qs:name":"Al Jawz",
    "qs:photos_9r":0,
    "qs:photos_sr":0,
    "qs:pop_sr":"1",
    "wof:name":"Al Jawz",
    "wof:placetype":"locality",
    "wof:population":6
},
  "geometry": {"coordinates":[43.36371,16.67913],"type":"Point"}
}