{
  "type": "Feature",
  "properties": {
    "gn:admin1_code":"11.0",
    "gn:admin2_code":"2009.0",
    "gn:asciiname":"Sanaban",
    "gn:country_code":"YE",
    "gn:dem":2357,
    "gn:feature_class":"P",
    "gn:feature_code":"PPL",
    "gn:name":"Sanab\u0101n",
    "gn:population":0,
    "gn:timezone":"Asia/Aden",
    "iso:country":"YE",
    "name:und_x_variant":[
        "Sanab\u0101n",
        "Shukian"
    ],
    "wof:name":"Sanaban",
    "wof:placetype":"locality"
},
  "geometry": {"coordinates":[44.6635,14.42533],"type":"Point"}
}