{
  "type": "Feature",
  "properties": {
    "gn:admin1_code":"23.0",
    "gn:admin2_code":"1120.0",
    "gn:asciiname":"Dar al Muwah",
    "gn:country_code":"YE",
    "gn:dem":2486,
    "gn:feature_class":"P",
    "gn:feature_code":"PPL",
    "gn:name":"D\u0101r al Muwah",
    "gn:population":0,
    "gn:timezone":"Asia/Aden",
    "iso:country":"YE",
    "name:und_x_variant":[
        "D\u0101r al Muwah"
    ],
    "wof:name":"Dar al Muwah",
    "wof:placetype":"locality"
},
  "geometry": {"coordinates":[44.20817,13.9786],"type":"Point"}
}