{
  "type": "Feature",
  "properties": {
    "gn:admin1_code":"22.0",
    "gn:admin2_code":"1704.0",
    "gn:asciiname":"Al Musbar",
    "gn:country_code":"YE",
    "gn:dem":143,
    "gn:feature_class":"P",
    "gn:feature_code":"PPL",
    "gn:name":"Al Mu\u015fb\u0101r",
    "gn:population":0,
    "gn:timezone":"Asia/Aden",
    "iso:country":"YE",
    "name:ara_x_preferred":[
        "Al Mu\u015fb\u0101r"
    ],
    "wof:name":"Al Musbar",
    "wof:placetype":"locality"
},
  "geometry": {"coordinates":[43.18582,16.13334],"type":"Point"}
}