{
  "type": "Feature",
  "properties": {
    "gn:admin1_code":"3.0",
    "gn:admin2_code":"2806.0",
    "gn:asciiname":"Al Ghayl",
    "gn:cc2":"YE",
    "gn:country_code":"YE",
    "gn:dem":174,
    "gn:feature_class":"P",
    "gn:feature_code":"PPL",
    "gn:name":"Al Ghayl",
    "gn:population":0,
    "gn:timezone":"Asia/Aden",
    "iso:country":"YE",
    "name:und_x_variant":[
        "Ghayl",
        "Gheil",
        "Al Ghayl"
    ],
    "wof:name":"Al Ghayl",
    "wof:placetype":"locality"
},
  "geometry": {"coordinates":[50.89694,15.50139],"type":"Point"}
}