{
  "type": "Feature",
  "properties": {
    "gn:admin1_code":"22.0",
    "gn:admin2_code":"1725.0",
    "gn:asciiname":"Bayt al 'Awwadi",
    "gn:country_code":"YE",
    "gn:dem":1252,
    "gn:feature_class":"P",
    "gn:feature_code":"PPL",
    "gn:name":"Bayt al \u2018Aww\u0101\u1e11\u012b",
    "gn:population":0,
    "gn:timezone":"Asia/Aden",
    "iso:country":"YE",
    "name:ara_x_preferred":[
        "\u0628\u064a\u062a \u0627\u0644\u0639\u0648\u0627\u0636\u0640\u064a"
    ],
    "name:und_x_variant":[
        "Bayt al \u2018Aww\u0101\u1e11\u012b"
    ],
    "wof:name":"Bayt al 'Awwadi",
    "wof:placetype":"locality"
},
  "geometry": {"coordinates":[43.54899,15.58628],"type":"Point"}
}