{
  "type": "Feature",
  "properties": {
    "gn:admin1_code":"11.0",
    "gn:admin2_code":"2005.0",
    "gn:asciiname":"Shaqr Bani Suwayd",
    "gn:country_code":"YE",
    "gn:dem":2011,
    "gn:feature_class":"P",
    "gn:feature_code":"PPL",
    "gn:name":"Shaqr Ban\u012b Suwayd",
    "gn:population":0,
    "gn:timezone":"Asia/Aden",
    "iso:country":"YE",
    "name:und_x_variant":[
        "Shaqr Ban\u012b Suwayd"
    ],
    "wof:name":"Shaqr Bani Suwayd",
    "wof:placetype":"locality"
},
  "geometry": {"coordinates":[44.01415,14.52081],"type":"Point"}
}