{
  "type": "Feature",
  "properties": {
    "gn:admin1_code":"11.0",
    "gn:admin2_code":"2001.0",
    "gn:asciiname":"Bani Nusayr",
    "gn:country_code":"YE",
    "gn:dem":2112,
    "gn:feature_class":"P",
    "gn:feature_code":"PPL",
    "gn:name":"Ban\u012b Nu\u015fayr",
    "gn:population":0,
    "gn:timezone":"Asia/Aden",
    "iso:country":"YE",
    "name:und_x_variant":[
        "Ban\u012b Nu\u015fayr"
    ],
    "wof:name":"Bani Nusayr",
    "wof:placetype":"locality"
},
  "geometry": {"coordinates":[44.55043,14.80112],"type":"Point"}
}