{
  "type": "Feature",
  "properties": {
    "gn:admin1_code":"5.0",
    "gn:admin2_code":"2107.0",
    "gn:asciiname":"Dhummar",
    "gn:country_code":"YE",
    "gn:dem":1198,
    "gn:elevation":"2.0",
    "gn:feature_class":"P",
    "gn:feature_code":"PPL",
    "gn:name":"Dhummar",
    "gn:population":0,
    "gn:timezone":"Asia/Aden",
    "iso:country":"YE",
    "name:und_x_variant":[
        "Dummar",
        "Dhummar"
    ],
    "wof:name":"Dhummar",
    "wof:placetype":"locality"
},
  "geometry": {"coordinates":[45.72586,14.69256],"type":"Point"}
}