{
  "type": "Feature",
  "properties": {
    "gn:admin1_code":"22.0",
    "gn:admin2_code":"1712.0",
    "gn:asciiname":"Al Madakhinah",
    "gn:country_code":"YE",
    "gn:dem":339,
    "gn:feature_class":"P",
    "gn:feature_code":"PPL",
    "gn:name":"Al Mad\u0101khinah",
    "gn:population":0,
    "gn:timezone":"Asia/Aden",
    "iso:country":"YE",
    "name:und_x_variant":[
        "Al Mad\u0101khinah",
        "Al Madakhinah"
    ],
    "wof:name":"Al Madakhinah",
    "wof:placetype":"locality"
},
  "geometry": {"coordinates":[43.25464,16.09691],"type":"Point"}
}