{
  "type": "Feature",
  "properties": {
    "gn:admin1_code":"23.0",
    "gn:admin2_code":"1120.0",
    "gn:asciiname":"Al Mijma`ah",
    "gn:country_code":"YE",
    "gn:dem":2402,
    "gn:feature_class":"P",
    "gn:feature_code":"PPL",
    "gn:name":"Al Mijma\u2018ah",
    "gn:population":0,
    "gn:timezone":"Asia/Aden",
    "iso:country":"YE",
    "name:ara_x_preferred":[
        "\u0627\u0644\u0645\u062c\u0645\u0639\u0629"
    ],
    "name:und_x_variant":[
        "Al Mijma\u2018ah",
        "Al Majma\u2018ah"
    ],
    "wof:name":"Al Mijma`ah",
    "wof:placetype":"locality"
},
  "geometry": {"coordinates":[44.10892,14.0165],"type":"Point"}
}