{
  "type": "Feature",
  "properties": {
    "gn:admin1_code":"16.0",
    "gn:admin2_code":"2307.0",
    "gn:asciiname":"`Attan",
    "gn:country_code":"YE",
    "gn:dem":2373,
    "gn:feature_class":"P",
    "gn:feature_code":"PPL",
    "gn:name":"\u2018A\u0163\u0163\u0101n",
    "gn:population":0,
    "gn:timezone":"Asia/Aden",
    "iso:country":"YE",
    "name:ara_x_preferred":[
        "\u2018A\u0163\u0163\u0101n"
    ],
    "name:ara_x_variant":[
        "\u0639\u0637\u0627\u0646"
    ],
    "wof:name":"`Attan",
    "wof:placetype":"locality"
},
  "geometry": {"coordinates":[44.17808,15.31392],"type":"Point"}
}