{
  "type": "Feature",
  "properties": {
    "gn:country":"YE",
    "gn:fcode":"PPL",
    "gn:pop":39,
    "iso:country":"YE",
    "name:ara_x_preferred":[
        "Al Q\u0101hir"
    ],
    "name:ara_x_variant":[
        "\u0627\u0644\u0642\u0627\u0647\u0631"
    ],
    "name:eng_x_preferred":[
        "Al Qahir"
    ],
    "name:eng_x_variant":[
        "Al Muhay\u2018"
    ],
    "qs:name":"Al Q\u0101hir",
    "qs:photos_9r":0,
    "qs:photos_sr":0,
    "qs:pop_sr":"1",
    "wd:wordcount":255,
    "wof:name":"Al Q\u0101hir",
    "wof:placetype":"locality",
    "wof:population":39
},
  "geometry": {"coordinates":[43.78071,13.2469],"type":"Point"}
}