{
  "type": "Feature",
  "properties": {
    "gn:admin1_code":"16.0",
    "gn:admin2_code":"2314.0",
    "gn:asciiname":"Wabir al 'Ali",
    "gn:country_code":"YE",
    "gn:dem":2226,
    "gn:feature_class":"P",
    "gn:feature_code":"PPL",
    "gn:name":"Wab\u012br al \u2018\u0100l\u012b",
    "gn:population":0,
    "gn:timezone":"Asia/Aden",
    "iso:country":"YE",
    "name:ara_x_preferred":[
        "\u0648\u0628\u064a\u0631 \u0627\u0644\u0639\u0627\u0644\u064a"
    ],
    "name:und_x_variant":[
        "Wab\u012br al \u2018\u0100l\u012b"
    ],
    "wof:name":"Wabir al 'Ali",
    "wof:placetype":"locality"
},
  "geometry": {"coordinates":[44.91935,15.14573],"type":"Point"}
}