{
  "type": "Feature",
  "properties": {
    "gn:admin1_code":"22.0",
    "gn:admin2_code":"1724.0",
    "gn:asciiname":"Qaryat az Zuqayl",
    "gn:country_code":"YE",
    "gn:dem":430,
    "gn:feature_class":"P",
    "gn:feature_code":"PPL",
    "gn:name":"Qaryat az Zuqayl",
    "gn:population":0,
    "gn:timezone":"Asia/Aden",
    "iso:country":"YE",
    "wof:name":"Qaryat az Zuqayl",
    "wof:placetype":"locality"
},
  "geometry": {"coordinates":[43.41544,15.64435],"type":"Point"}
}