{
  "type": "Feature",
  "properties": {
    "gn:admin1_code":"4.0",
    "gn:admin2_code":"1914.0",
    "gn:asciiname":"Tawban",
    "gn:country_code":"YE",
    "gn:dem":109,
    "gn:feature_class":"P",
    "gn:feature_code":"PPL",
    "gn:name":"Tawb\u0101n",
    "gn:population":0,
    "gn:timezone":"Asia/Aden",
    "iso:country":"YE",
    "name:nno_x_preferred":[
        "Tawban"
    ],
    "name:und_x_variant":[
        "Tawb\u0101n"
    ],
    "wof:name":"Tawban",
    "wof:placetype":"locality"
},
  "geometry": {"coordinates":[50.00074,14.92675],"type":"Point"}
}