{
  "type": "Feature",
  "properties": {
    "gn:admin1_code":"22.0",
    "gn:admin2_code":"1720.0",
    "gn:asciiname":"Al Hadan",
    "gn:country_code":"YE",
    "gn:dem":1146,
    "gn:feature_class":"P",
    "gn:feature_code":"PPL",
    "gn:name":"Al \u1e28a\u1e11an",
    "gn:population":0,
    "gn:timezone":"Asia/Aden",
    "iso:country":"YE",
    "name:und_x_variant":[
        "Al \u1e28a\u1e11an"
    ],
    "wof:name":"Al Hadan",
    "wof:placetype":"locality"
},
  "geometry": {"coordinates":[43.54309,15.71706],"type":"Point"}
}