{
  "type": "Feature",
  "properties": {
    "gn:admin1_code":"8.0",
    "gn:admin2_code":"1813.0",
    "gn:asciiname":"Mahall al Himsi",
    "gn:country_code":"YE",
    "gn:dem":52,
    "gn:feature_class":"P",
    "gn:feature_code":"PPL",
    "gn:name":"Ma\u1e29all al \u1e28im\u015f\u012b",
    "gn:population":0,
    "gn:timezone":"Asia/Aden",
    "iso:country":"YE",
    "name:ara_x_preferred":[
        "\u0645\u062d\u0644 \u0627\u0644\u062d\u0645\u0635\u064a"
    ],
    "name:und_x_variant":[
        "Ma\u1e29all al \u1e28im\u015f\u012b"
    ],
    "wof:name":"Mahall al Himsi",
    "wof:placetype":"locality"
},
  "geometry": {"coordinates":[43.14247,14.74375],"type":"Point"}
}