{
  "type": "Feature",
  "properties": {
    "gn:admin1_code":"11.0",
    "gn:asciiname":"Hazzat ar Rakab",
    "gn:country_code":"YE",
    "gn:dem":-9999,
    "gn:feature_class":"P",
    "gn:feature_code":"PPL",
    "gn:name":"\u1e28azzat ar Rakab",
    "gn:population":0,
    "gn:timezone":"Asia/Aden",
    "iso:country":"YE",
    "name:ara_x_preferred":[
        "\u062d\u0632\u0629 \u0627\u0644\u0631\u0643\u0628"
    ],
    "name:und_x_variant":[
        "\u1e28azzat ar Rakab"
    ],
    "wof:name":"Hazzat ar Rakab",
    "wof:placetype":"locality"
},
  "geometry": {"coordinates":[0.77994,0.25207],"type":"Point"}
}