{
  "type": "Feature",
  "properties": {
    "gn:admin1_code":"20.0",
    "gn:admin2_code":"1410.0",
    "gn:asciiname":"Al 'Amiriyah",
    "gn:country_code":"YE",
    "gn:dem":1978,
    "gn:feature_class":"P",
    "gn:feature_code":"PPL",
    "gn:name":"Al \u2018\u0100mir\u012byah",
    "gn:population":0,
    "gn:timezone":"Asia/Aden",
    "iso:country":"YE",
    "name:ara_x_preferred":[
        "\u0627\u0644\u0639\u0627\u0645\u0631\u064a\u0629"
    ],
    "name:und_x_variant":[
        "Al \u2018\u0100mir\u012byah"
    ],
    "wof:name":"Al 'Amiriyah",
    "wof:placetype":"locality"
},
  "geometry": {"coordinates":[45.56919,14.00873],"type":"Point"}
}