{
  "type": "Feature",
  "properties": {
    "gn:admin1_code":"18.0",
    "gn:admin2_code":"1501.0",
    "gn:asciiname":"Tamhan",
    "gn:country_code":"YE",
    "gn:dem":1378,
    "gn:feature_class":"P",
    "gn:feature_code":"PPL",
    "gn:name":"Tamhan",
    "gn:population":0,
    "gn:timezone":"Asia/Aden",
    "iso:country":"YE",
    "name:und_x_variant":[
        "A\u0163 \u0162am\u1e29\u0101n",
        "Tamhan"
    ],
    "wof:name":"Tamhan",
    "wof:placetype":"locality"
},
  "geometry": {"coordinates":[44.3948,13.68175],"type":"Point"}
}