{
  "type": "Feature",
  "properties": {
    "gn:admin1_code":"18.0",
    "gn:admin2_code":"3009.0",
    "gn:asciiname":"Khulban",
    "gn:country_code":"YE",
    "gn:dem":1172,
    "gn:feature_class":"P",
    "gn:feature_code":"PPL",
    "gn:name":"Khulb\u0101n",
    "gn:population":0,
    "gn:timezone":"Asia/Aden",
    "iso:country":"YE",
    "name:ara_x_preferred":[
        "Khulb\u0101n"
    ],
    "name:und_x_variant":[
        "\u1e28ulb\u0101n"
    ],
    "wof:name":"Khulban",
    "wof:placetype":"locality"
},
  "geometry": {"coordinates":[44.39474000000001,13.63902],"type":"Point"}
}