{
  "type": "Feature",
  "properties": {
    "gn:admin1_code":"25.0",
    "gn:admin2_code":"1504.0",
    "gn:asciiname":"Al Qahfah",
    "gn:country_code":"YE",
    "gn:dem":1097,
    "gn:feature_class":"P",
    "gn:feature_code":"PPL",
    "gn:name":"Al Qa\u1e29fah",
    "gn:population":0,
    "gn:timezone":"Asia/Aden",
    "iso:country":"YE",
    "name:ara_x_preferred":[
        "\u0627\u0644\u0642\u062d\u0641\u0629"
    ],
    "name:und_x_variant":[
        "Al Qa\u1e29fah",
        "Al Qi\u1e29fah"
    ],
    "wof:name":"Al Qahfah",
    "wof:placetype":"locality"
},
  "geometry": {"coordinates":[43.77831,13.76131],"type":"Point"}
}