{
  "type": "Feature",
  "properties": {
    "gn:admin1_code":"25.0",
    "gn:admin2_code":"1505.0",
    "gn:asciiname":"Qula`ah",
    "gn:country_code":"YE",
    "gn:dem":435,
    "gn:feature_class":"P",
    "gn:feature_code":"PPL",
    "gn:name":"Qul\u0101\u2018ah",
    "gn:population":0,
    "gn:timezone":"Asia/Aden",
    "iso:country":"YE",
    "name:ara_x_preferred":[
        "\u0627\u0644\u0642\u0644\u0627\u0639\u0629"
    ],
    "name:und_x_variant":[
        "Qul\u0101\u2018ah",
        "Al Qil\u0101\u2018ah"
    ],
    "wof:name":"Qula`ah",
    "wof:placetype":"locality"
},
  "geometry": {"coordinates":[43.58736,13.77356],"type":"Point"}
}