{
  "type": "Feature",
  "properties": {
    "gn:admin1_code":"24.0",
    "gn:admin2_code":"2510.0",
    "gn:asciiname":"Ja`imah",
    "gn:country_code":"YE",
    "gn:dem":773,
    "gn:feature_class":"P",
    "gn:feature_code":"PPL",
    "gn:name":"J\u0101\u2018imah",
    "gn:population":0,
    "gn:timezone":"Asia/Aden",
    "iso:country":"YE",
    "name:und_x_variant":[
        "J\u0101\u2018imah",
        "Al Ja\u2018mah"
    ],
    "wof:name":"Ja`imah",
    "wof:placetype":"locality"
},
  "geometry": {"coordinates":[44.38,13.21573],"type":"Point"}
}