{
  "type": "Feature",
  "properties": {
    "gn:admin1_code":"25.0",
    "gn:admin2_code":"1505.0",
    "gn:asciiname":"Ma`mal al Bumiyah",
    "gn:country_code":"YE",
    "gn:dem":309,
    "gn:feature_class":"P",
    "gn:feature_code":"PPL",
    "gn:name":"Ma\u2018mal al B\u016bm\u012byah",
    "gn:population":0,
    "gn:timezone":"Asia/Aden",
    "iso:country":"YE",
    "name:und_x_variant":[
        "Ma\u2018mal al B\u016bm\u012byah",
        "Qaryat al B\u016bm\u012byah"
    ],
    "wof:name":"Ma`mal al Bumiyah",
    "wof:placetype":"locality"
},
  "geometry": {"coordinates":[43.50384,13.81212],"type":"Point"}
}