{
  "type": "Feature",
  "properties": {
    "gn:admin1_code":"24.0",
    "gn:admin2_code":"2512.0",
    "gn:asciiname":"Tamalluki",
    "gn:country_code":"YE",
    "gn:dem":786,
    "gn:feature_class":"P",
    "gn:feature_code":"PPL",
    "gn:name":"Tamalluk\u012b",
    "gn:population":0,
    "gn:timezone":"Asia/Aden",
    "iso:country":"YE",
    "name:ara_x_preferred":[
        "\u062a\u0645\u0644\u0643\u064a"
    ],
    "name:und_x_variant":[
        "Tamalluk\u012b"
    ],
    "wof:name":"Tamalluki",
    "wof:placetype":"locality"
},
  "geometry": {"coordinates":[44.17236,13.11009],"type":"Point"}
}