{
  "type": "Feature",
  "properties": {
    "gn:admin1_code":"19.0",
    "gn:admin2_code":"2910.0",
    "gn:asciiname":"`Araqah",
    "gn:country_code":"YE",
    "gn:dem":2375,
    "gn:feature_class":"P",
    "gn:feature_code":"PPL",
    "gn:name":"\u2018Araqah",
    "gn:population":0,
    "gn:timezone":"Asia/Aden",
    "iso:country":"YE",
    "name:und_x_variant":[
        "\u2018Araqah"
    ],
    "wof:name":"`Araqah",
    "wof:placetype":"locality"
},
  "geometry": {"coordinates":[44.11667,15.83333],"type":"Point"}
}