{
  "type": "Feature",
  "properties": {
    "gn:admin1_code":"23.0",
    "gn:admin2_code":"1117.0",
    "gn:asciiname":"Al Jurnayn",
    "gn:country_code":"YE",
    "gn:dem":2215,
    "gn:feature_class":"P",
    "gn:feature_code":"PPL",
    "gn:name":"Al Jurnayn",
    "gn:population":0,
    "gn:timezone":"Asia/Aden",
    "iso:country":"YE",
    "name:ara_x_preferred":[
        "\u0627\u0644\u062c\u0631\u0646\u064a\u0646"
    ],
    "wof:name":"Al Jurnayn",
    "wof:placetype":"locality"
},
  "geometry": {"coordinates":[43.97202,13.83216],"type":"Point"}
}