{
  "type": "Feature",
  "properties": {
    "gn:country":"YE",
    "gn:fcode":"PPL",
    "gn:pop":5,
    "iso:country":"YE",
    "name:ara_x_preferred":[
        "\u0627\u0644\u0637\u0631\u0627\u0647 \u0627\u0644\u0634\u0631\u0642\u064a\u0629"
    ],
    "name:eng_x_preferred":[
        "At Tarah Ash Sharqiyah"
    ],
    "qs:name":"A\u0163 \u0162ar\u0101h ash Sharq\u012byah",
    "qs:photos_9r":0,
    "qs:photos_sr":0,
    "qs:pop_sr":"1",
    "wof:name":"A\u0163 \u0162ar\u0101h ash Sharq\u012byah",
    "wof:placetype":"locality",
    "wof:population":5
},
  "geometry": {"coordinates":[44.44542,17.3138],"type":"Point"}
}