{
  "type": "Feature",
  "properties": {
    "gn:admin1_code":"8.0",
    "gn:admin2_code":"1813.0",
    "gn:asciiname":"Buyut ash Shalali`ah",
    "gn:country_code":"YE",
    "gn:dem":63,
    "gn:feature_class":"P",
    "gn:feature_code":"PPL",
    "gn:name":"Buyut ash Shal\u0101li\u2018ah",
    "gn:population":0,
    "gn:timezone":"Asia/Aden",
    "iso:country":"YE",
    "name:und_x_variant":[
        "Buyut ash Shal\u0101li\u2018ah"
    ],
    "wof:name":"Buyut ash Shalali`ah",
    "wof:placetype":"locality"
},
  "geometry": {"coordinates":[43.18112,14.77155],"type":"Point"}
}