{
  "type": "Feature",
  "properties": {
    "gn:country":"YE",
    "gn:fcode":"PPL",
    "gn:population":4,
    "iso:country":"YE",
    "name:ara_x_preferred":[
        "\u0627\u0644\u0642\u0645\u0639"
    ],
    "name:eng_x_preferred":[
        "Al Qam'"
    ],
    "name:eng_x_variant":[
        "Al Misra\u1e29"
    ],
    "qs:name":"Al Qam\u2018",
    "qs:photos_9r":0,
    "qs:photos_sr":0,
    "qs:pop_sr":"1",
    "wof:name":"Al Qam\u2018",
    "wof:placetype":"locality",
    "wof:population":4
},
  "geometry": {"coordinates":[44.29242,17.39358],"type":"Point"}
}