{
  "type": "Feature",
  "properties": {
    "gn:country":"YE",
    "gn:fcode":"PPL",
    "gn:pop":4,
    "iso:country":"YE",
    "name:ara_x_preferred":[
        "A\u015f \u015e\u012br\u0101\u2019"
    ],
    "name:ara_x_variant":[
        "\u0627\u0644\u0635\u064a\u0631\u0627\u0621"
    ],
    "qs:name":"A\u015f \u015e\u012br\u0101\u2019",
    "qs:photos_9r":0,
    "qs:photos_sr":0,
    "qs:pop_sr":"1",
    "wof:name":"A\u015f \u015e\u012br\u0101\u2019",
    "wof:placetype":"locality",
    "wof:population":4
},
  "geometry": {"coordinates":[43.35131,16.19383],"type":"Point"}
}