{
  "type": "Feature",
  "properties": {
    "gn:admin1_code":"4.0",
    "gn:admin2_code":"1921.0",
    "gn:asciiname":"Dakwah",
    "gn:country_code":"YE",
    "gn:dem":1168,
    "gn:feature_class":"P",
    "gn:feature_code":"PPL",
    "gn:name":"Dakwah",
    "gn:population":0,
    "gn:timezone":"Asia/Aden",
    "iso:country":"YE",
    "wof:name":"Dakwah",
    "wof:placetype":"locality"
},
  "geometry": {"coordinates":[48.05,15.35],"type":"Point"}
}