{
  "type": "Feature",
  "properties": {
    "gn:admin1_code":"27.0",
    "gn:admin2_code":"3105.0",
    "gn:asciiname":"Khudayshah",
    "gn:country_code":"YE",
    "gn:dem":521,
    "gn:feature_class":"P",
    "gn:feature_code":"PPL",
    "gn:name":"Khudayshah",
    "gn:population":0,
    "gn:timezone":"Asia/Aden",
    "iso:country":"YE",
    "wof:name":"Khudayshah",
    "wof:placetype":"locality"
},
  "geometry": {"coordinates":[43.63078,14.42136],"type":"Point"}
}