{
  "type": "Feature",
  "properties": {
    "gn:admin1_code":"8.0",
    "gn:admin2_code":"1802.0",
    "gn:asciiname":"Al Maghafir",
    "gn:country_code":"YE",
    "gn:dem":16,
    "gn:feature_class":"P",
    "gn:feature_code":"PPL",
    "gn:name":"Al Magh\u0101f\u012br",
    "gn:population":0,
    "gn:timezone":"Asia/Aden",
    "iso:country":"YE",
    "name:ara_x_preferred":[
        "Al Mugh\u0101f\u012br"
    ],
    "name:ara_x_variant":[
        "\u0627\u0644\u0645\u063a\u0627\u0641\u064a\u0631"
    ],
    "name:und_x_variant":[
        "Al Magh\u0101f\u012br"
    ],
    "wof:name":"Al Maghafir",
    "wof:placetype":"locality"
},
  "geometry": {"coordinates":[42.78514000000001,15.68645],"type":"Point"}
}