{
  "type": "Feature",
  "properties": {
    "gn:admin1_code":"20.0",
    "gn:admin2_code":"1414.0",
    "gn:asciiname":"Dhi Kalib al Asfal",
    "gn:country_code":"YE",
    "gn:dem":2026,
    "gn:feature_class":"P",
    "gn:feature_code":"PPL",
    "gn:name":"Dh\u012b K\u0101lib al Asfal",
    "gn:population":0,
    "gn:timezone":"Asia/Aden",
    "iso:country":"YE",
    "name:und_x_variant":[
        "Dh\u012b K\u0101lib al Asfal"
    ],
    "wof:name":"Dhi Kalib al Asfal",
    "wof:placetype":"locality"
},
  "geometry": {"coordinates":[44.88102,14.55545],"type":"Point"}
}