{
  "type": "Feature",
  "properties": {
    "gn:admin1_code":"16.0",
    "gn:admin2_code":"2309.0",
    "gn:asciiname":"Al Hijarat",
    "gn:country_code":"YE",
    "gn:dem":1517,
    "gn:feature_class":"P",
    "gn:feature_code":"PPL",
    "gn:name":"Al \u1e28ij\u0101r\u0101t",
    "gn:population":0,
    "gn:timezone":"Asia/Aden",
    "iso:country":"YE",
    "name:ara_x_preferred":[
        "Al \u1e28ij\u0101r\u0101t"
    ],
    "wof:name":"Al Hijarat",
    "wof:placetype":"locality"
},
  "geometry": {"coordinates":[43.84382,15.06576],"type":"Point"}
}