{
  "type": "Feature",
  "properties": {
    "gn:admin1_code":"19.0",
    "gn:admin2_code":"2901.0",
    "gn:asciiname":"An Naq`",
    "gn:country_code":"YE",
    "gn:dem":1204,
    "gn:feature_class":"P",
    "gn:feature_code":"PPL",
    "gn:name":"An Naq\u2018",
    "gn:population":0,
    "gn:timezone":"Asia/Aden",
    "iso:country":"YE",
    "name:und_x_variant":[
        "An Naq\u2018"
    ],
    "wof:name":"An Naq`",
    "wof:placetype":"locality"
},
  "geometry": {"coordinates":[43.56845,16.35361],"type":"Point"}
}