{
  "type": "Feature",
  "properties": {
    "gn:country":"YE",
    "gn:fcode":"MKT",
    "gn:pop":21,
    "iso:country":"YE",
    "name:ara_x_preferred":[
        "\u0627\u0644\u0633\u0648\u0642 \u0627\u0644\u0642\u062f\u064a\u0645"
    ],
    "name:eng_x_preferred":[
        "As SUq Al Qadim"
    ],
    "qs:name":"As S\u016bq al Qad\u012bm",
    "qs:photos_9r":0,
    "qs:photos_sr":0,
    "qs:pop_sr":"1",
    "wof:name":"As S\u016bq al Qad\u012bm",
    "wof:placetype":"locality",
    "wof:population":21
},
  "geometry": {"coordinates":[43.70775,16.05089],"type":"Point"}
}