{
  "type": "Feature",
  "properties": {
    "gn:country":"YE",
    "gn:fcode":"PPL",
    "gn:pop":1,
    "iso:country":"YE",
    "name:ara_x_preferred":[
        "\u0627\u0644\u062f\u0645\u0646\u0629"
    ],
    "qs:name":"Ad Dimnah",
    "qs:photos_9r":0,
    "qs:photos_sr":0,
    "qs:pop_sr":"1",
    "wof:name":"Ad Dimnah",
    "wof:placetype":"locality",
    "wof:population":1
},
  "geometry": {"coordinates":[43.67793,16.08288],"type":"Point"}
}