{
  "type": "Feature",
  "properties": {
    "gn:admin1_code":"16.0",
    "gn:admin2_code":"2302.0",
    "gn:asciiname":"Wabran",
    "gn:country_code":"YE",
    "gn:dem":2193,
    "gn:feature_class":"P",
    "gn:feature_code":"PPL",
    "gn:name":"Wabr\u0101n",
    "gn:population":0,
    "gn:timezone":"Asia/Aden",
    "iso:country":"YE",
    "name:und_x_variant":[
        "Wabr\u0101n"
    ],
    "wof:name":"Wabran",
    "wof:placetype":"locality"
},
  "geometry": {"coordinates":[44.36266,15.83892],"type":"Point"}
}