{
  "type": "Feature",
  "properties": {
    "gn:admin1_code":"23.0",
    "gn:admin2_code":"1114.0",
    "gn:asciiname":"Qaryat al Mabrak",
    "gn:country_code":"YE",
    "gn:dem":1893,
    "gn:feature_class":"P",
    "gn:feature_code":"PPL",
    "gn:name":"Qaryat al Mabr\u0101k",
    "gn:population":0,
    "gn:timezone":"Asia/Aden",
    "iso:country":"YE",
    "name:und_x_variant":[
        "Qaryat al Mabr\u0101k"
    ],
    "wof:name":"Qaryat al Mabrak",
    "wof:placetype":"locality"
},
  "geometry": {"coordinates":[44.32677,13.73772],"type":"Point"}
}