{
  "type": "Feature",
  "properties": {
    "gn:admin1_code":"23.0",
    "gn:admin2_code":"1102.0",
    "gn:asciiname":"Ribat al Qal`ah",
    "gn:country_code":"YE",
    "gn:dem":2533,
    "gn:feature_class":"P",
    "gn:feature_code":"PPL",
    "gn:name":"Rib\u0101\u0163 al Qal\u2018ah",
    "gn:population":0,
    "gn:timezone":"Asia/Aden",
    "iso:country":"YE",
    "name:ara_x_preferred":[
        "\u0631\u0628\u0627\u0637 \u0627\u0644\u0642\u0644\u0639\u0629"
    ],
    "name:und_x_variant":[
        "Rib\u0101\u0163 al Qal\u2018ah"
    ],
    "wof:name":"Ribat al Qal`ah",
    "wof:placetype":"locality"
},
  "geometry": {"coordinates":[44.3418,14.2048],"type":"Point"}
}