{
  "type": "Feature",
  "properties": {
    "gn:gn_country":"YE",
    "gn:gn_fcode":"PPL",
    "gn:gn_pop":9,
    "gn:population":9,
    "iso:country":"YE",
    "name:ara_x_preferred":[
        "\u0627\u0644\u0645\u0631 \u0627\u0628\u0639\u0629"
    ],
    "qs_pg:aaroncc":"YE",
    "qs_pg:gn_country":"YE",
    "qs_pg:gn_fcode":"PPL",
    "qs_pg:gn_pop":9,
    "qs_pg:name":"Al Mar\u0101bi\u2018ah",
    "qs_pg:photos_9r":0,
    "qs_pg:photos_sr":0,
    "qs_pg:pop_sr":1,
    "qs_pg:qs_pg_placetype":"locality",
    "wof:name":"Al Mar\u0101bi\u2018ah",
    "wof:placetype":"locality",
    "wof:population":9
},
  "geometry": {"coordinates":[43.33106,16.0836],"type":"Point"}
}