{
  "type": "Feature",
  "properties": {
    "gn:admin1_code":"5.0",
    "gn:admin2_code":"2107.0",
    "gn:asciiname":"Al Qarnayn",
    "gn:country_code":"YE",
    "gn:dem":1127,
    "gn:feature_class":"P",
    "gn:feature_code":"PPL",
    "gn:name":"Al Qarnayn",
    "gn:population":0,
    "gn:timezone":"Asia/Aden",
    "iso:country":"YE",
    "name:und_x_variant":[
        "Al Qurnain",
        "Al Qarnayn"
    ],
    "wof:name":"Al Qarnayn",
    "wof:placetype":"locality"
},
  "geometry": {"coordinates":[45.71362,14.81501],"type":"Point"}
}