{
  "type": "Feature",
  "properties": {
    "gn:admin1_code":"22.0",
    "gn:admin2_code":"1724.0",
    "gn:asciiname":"Shafadara",
    "gn:cc2":"YE",
    "gn:country_code":"YE",
    "gn:dem":441,
    "gn:feature_class":"P",
    "gn:feature_code":"PPL",
    "gn:name":"Shafadara",
    "gn:population":0,
    "gn:timezone":"Asia/Aden",
    "iso:country":"YE",
    "name:und_x_variant":[
        "Shefadere",
        "Shafadara"
    ],
    "wof:name":"Shafadara",
    "wof:placetype":"locality"
},
  "geometry": {"coordinates":[43.43333,15.73333],"type":"Point"}
}