{
  "type": "Feature",
  "properties": {
    "gn:admin1_code":"10.0",
    "gn:admin2_code":"2703.0",
    "gn:asciiname":"Tanub",
    "gn:country_code":"YE",
    "gn:dem":2028,
    "gn:feature_class":"P",
    "gn:feature_code":"PPL",
    "gn:name":"Tan\u016bb",
    "gn:population":0,
    "gn:timezone":"Asia/Aden",
    "iso:country":"YE",
    "name:und_x_variant":[
        "Tan\u016bb"
    ],
    "wof:name":"Tanub",
    "wof:placetype":"locality"
},
  "geometry": {"coordinates":[43.58534,15.49163],"type":"Point"}
}