{
  "type": "Feature",
  "properties": {
    "gn:admin1_code":"15.0",
    "gn:admin2_code":"2210.0",
    "gn:asciiname":"Al Jirbah",
    "gn:country_code":"YE",
    "gn:dem":1896,
    "gn:feature_class":"P",
    "gn:feature_code":"PPL",
    "gn:name":"Al Jirbah",
    "gn:population":0,
    "gn:timezone":"Asia/Aden",
    "iso:country":"YE",
    "name:ara_x_preferred":[
        "\u0627\u0644\u062c\u0631\u0628\u0629"
    ],
    "name:fas_x_preferred":[
        "\u0627\u0644\u062c\u06cc\u0631\u0628\u0627\u0647"
    ],
    "name:nno_x_preferred":[
        "Al Jirbah"
    ],
    "wof:name":"Al Jirbah",
    "wof:placetype":"locality"
},
  "geometry": {"coordinates":[43.55078,17.17709],"type":"Point"}
}