{
  "type": "Feature",
  "properties": {
    "gn:admin1_code":"8.0",
    "gn:admin2_code":"1813.0",
    "gn:asciiname":"Mahall Husayn Hamzah",
    "gn:country_code":"YE",
    "gn:dem":242,
    "gn:feature_class":"P",
    "gn:feature_code":"PPL",
    "gn:name":"Ma\u1e29all \u1e28usayn \u1e28amzah",
    "gn:population":0,
    "gn:timezone":"Asia/Aden",
    "iso:country":"YE",
    "name:ara_x_preferred":[
        "\u0645\u062d\u0644 \u062d\u0633\u064a\u0646 \u062d\u0645\u0632\u0629"
    ],
    "name:und_x_variant":[
        "Ma\u1e29all \u1e28usayn \u1e28amzah"
    ],
    "wof:name":"Mahall Husayn Hamzah",
    "wof:placetype":"locality"
},
  "geometry": {"coordinates":[43.39146,14.93432],"type":"Point"}
}