{
  "type": "Feature",
  "properties": {
    "gn:admin1_code":"23.0",
    "gn:admin2_code":"1110.0",
    "gn:asciiname":"Al Awtaf",
    "gn:country_code":"YE",
    "gn:dem":712,
    "gn:feature_class":"P",
    "gn:feature_code":"PPL",
    "gn:name":"Al Aw\u0163\u0101f",
    "gn:population":0,
    "gn:timezone":"Asia/Aden",
    "iso:country":"YE",
    "name:ara_x_preferred":[
        "Al Aw\u0163\u0101f"
    ],
    "wof:name":"Al Awtaf",
    "wof:placetype":"locality"
},
  "geometry": {"coordinates":[43.71446,13.92543],"type":"Point"}
}