{
  "type": "Feature",
  "properties": {
    "gn:admin1_code":"24.0",
    "gn:admin2_code":"2508.0",
    "gn:asciiname":"Al Jiblah",
    "gn:country_code":"YE",
    "gn:dem":458,
    "gn:feature_class":"P",
    "gn:feature_code":"PPL",
    "gn:name":"Al Jiblah",
    "gn:population":0,
    "gn:timezone":"Asia/Aden",
    "iso:country":"YE",
    "wof:name":"Al Jiblah",
    "wof:placetype":"locality"
},
  "geometry": {"coordinates":[44.87861,13.38556],"type":"Point"}
}