{
  "type": "Feature",
  "properties": {
    "gn:country":"YE",
    "gn:fcode":"PPL",
    "gn:population":2,
    "iso:country":"YE",
    "name:ara_x_preferred":[
        "\u0627\u0644\u062d\u0633\u064a\u0646"
    ],
    "qs:name":"Al \u1e28usayn",
    "qs:photos_9r":0,
    "qs:photos_sr":0,
    "qs:pop_sr":"1",
    "wof:name":"Al \u1e28usayn",
    "wof:placetype":"locality",
    "wof:population":2
},
  "geometry": {"coordinates":[43.3147,16.64268],"type":"Point"}
}