{
  "type": "Feature",
  "properties": {
    "gn:admin1_code":"19.0",
    "gn:admin2_code":"2920.0",
    "gn:asciiname":"Bayt Radman",
    "gn:country_code":"YE",
    "gn:dem":2301,
    "gn:feature_class":"P",
    "gn:feature_code":"PPL",
    "gn:name":"Bayt Radm\u0101n",
    "gn:population":0,
    "gn:timezone":"Asia/Aden",
    "iso:country":"YE",
    "name:ara_x_preferred":[
        "\u0628\u064a\u062a \u0631\u062f\u0645\u0627\u0646"
    ],
    "name:und_x_variant":[
        "Bayt Radm\u0101n"
    ],
    "wof:name":"Bayt Radman",
    "wof:placetype":"locality"
},
  "geometry": {"coordinates":[43.96677,16.12929],"type":"Point"}
}