{
  "type": "Feature",
  "properties": {
    "gn:admin1_code":"5.0",
    "gn:asciiname":"Al Barakah",
    "gn:country_code":"YE",
    "gn:dem":1193,
    "gn:feature_class":"P",
    "gn:feature_code":"PPL",
    "gn:name":"Al Barakah",
    "gn:population":0,
    "gn:timezone":"Asia/Aden",
    "iso:country":"YE",
    "name:ara_x_preferred":[
        "\u0627\u0644\u0628\u0631\u0643\u0629"
    ],
    "wof:name":"Al Barakah",
    "wof:placetype":"locality"
},
  "geometry": {"coordinates":[45.9239,14.57698],"type":"Point"}
}