{
  "type": "Feature",
  "properties": {
    "gn:admin1_code":"11.0",
    "gn:admin2_code":"2006.0",
    "gn:asciiname":"Mishraq",
    "gn:country_code":"YE",
    "gn:dem":1683,
    "gn:feature_class":"P",
    "gn:feature_code":"PPL",
    "gn:name":"Mishr\u0101q",
    "gn:population":0,
    "gn:timezone":"Asia/Aden",
    "iso:country":"YE",
    "name:ara_x_preferred":[
        "Mishr\u0101q"
    ],
    "wof:name":"Mishraq",
    "wof:placetype":"locality"
},
  "geometry": {"coordinates":[43.90579,14.30406],"type":"Point"}
}