{
  "type": "Feature",
  "properties": {
    "gn:admin1_code":"25.0",
    "gn:admin2_code":"1502.0",
    "gn:asciiname":"Sabat",
    "gn:country_code":"YE",
    "gn:dem":1027,
    "gn:feature_class":"P",
    "gn:feature_code":"PPL",
    "gn:name":"Sab\u0101t",
    "gn:population":0,
    "gn:timezone":"Asia/Aden",
    "iso:country":"YE",
    "name:ara_x_preferred":[
        "\u0633\u0628\u0627\u062a"
    ],
    "name:und_x_variant":[
        "Sab\u0101t"
    ],
    "wof:name":"Sabat",
    "wof:placetype":"locality"
},
  "geometry": {"coordinates":[43.88169,13.62617],"type":"Point"}
}