{
  "type": "Feature",
  "properties": {
    "gn:admin1_code":"19.0",
    "gn:admin2_code":"2920.0",
    "gn:asciiname":"Al Masbah",
    "gn:country_code":"YE",
    "gn:dem":2173,
    "gn:feature_class":"P",
    "gn:feature_code":"PPL",
    "gn:name":"Al Masba\u1e29",
    "gn:population":0,
    "gn:timezone":"Asia/Aden",
    "iso:country":"YE",
    "name:und_x_variant":[
        "Al Masba\u1e29"
    ],
    "wof:name":"Al Masbah",
    "wof:placetype":"locality"
},
  "geometry": {"coordinates":[43.9457,16.11234],"type":"Point"}
}