{
  "type": "Feature",
  "properties": {
    "gn:admin1_code":"14.0",
    "gn:admin2_code":"2609.0",
    "gn:asciiname":"Al `Affah",
    "gn:country_code":"YE",
    "gn:dem":1160,
    "gn:elevation":"2.0",
    "gn:feature_class":"P",
    "gn:feature_code":"PPL",
    "gn:name":"Al \u2018Affah",
    "gn:population":0,
    "gn:timezone":"Asia/Aden",
    "iso:country":"YE",
    "name:und_x_variant":[
        "Al \u2018Affah"
    ],
    "wof:name":"Al `Affah",
    "wof:placetype":"locality"
},
  "geometry": {"coordinates":[45.5042,14.95662],"type":"Point"}
}