{
  "type": "Feature",
  "properties": {
    "gn:admin1_code":"8.0",
    "gn:admin2_code":"1801.0",
    "gn:asciiname":"Ad Darwishiyah",
    "gn:country_code":"YE",
    "gn:dem":57,
    "gn:feature_class":"P",
    "gn:feature_code":"PPL",
    "gn:name":"Ad Darw\u012bsh\u012byah",
    "gn:population":0,
    "gn:timezone":"Asia/Aden",
    "iso:country":"YE",
    "name:ara_x_preferred":[
        "\u0627\u0644\u062f\u0631\u0648\u064a\u0634\u064a\u0629"
    ],
    "name:und_x_variant":[
        "Ad Darw\u012bsh\u012byah"
    ],
    "wof:name":"Ad Darwishiyah",
    "wof:placetype":"locality"
},
  "geometry": {"coordinates":[42.94619,15.78374],"type":"Point"}
}