{
  "type": "Feature",
  "properties": {
    "gn:admin1_code":"11.0",
    "gn:admin2_code":"2006.0",
    "gn:asciiname":"Qaryat al Mawsatah",
    "gn:country_code":"YE",
    "gn:dem":1277,
    "gn:feature_class":"P",
    "gn:feature_code":"PPL",
    "gn:name":"Qaryat al Mawsa\u0163ah",
    "gn:population":0,
    "gn:timezone":"Asia/Aden",
    "iso:country":"YE",
    "name:und_x_variant":[
        "Qaryat al Mawsa\u0163ah",
        "Qaryat al Muwassa\u0163ah"
    ],
    "wof:name":"Qaryat al Mawsatah",
    "wof:placetype":"locality"
},
  "geometry": {"coordinates":[43.74303,14.3487],"type":"Point"}
}