{
  "type": "Feature",
  "properties": {
    "gn:admin1_code":"14.0",
    "gn:admin2_code":"2614.0",
    "gn:asciiname":"Al Hajr",
    "gn:country_code":"YE",
    "gn:dem":2035,
    "gn:feature_class":"P",
    "gn:feature_code":"PPL",
    "gn:name":"Al Hajr",
    "gn:population":0,
    "gn:timezone":"Asia/Aden",
    "iso:country":"YE",
    "name:ara_x_preferred":[
        "\u0627\u0644\u0647\u062c\u0631"
    ],
    "name:und_x_variant":[
        "\u2018Uzlat al Hajar",
        "Al Hajr"
    ],
    "wof:name":"Al Hajr",
    "wof:placetype":"locality"
},
  "geometry": {"coordinates":[45.17329,15.04092],"type":"Point"}
}