{
  "type": "Feature",
  "properties": {
    "gn:admin1_code":"23.0",
    "gn:admin2_code":"1101.0",
    "gn:asciiname":"Akimah as Sufla",
    "gn:country_code":"YE",
    "gn:dem":1443,
    "gn:feature_class":"P",
    "gn:feature_code":"PPL",
    "gn:name":"Akimah as Sufl\u00e1",
    "gn:population":0,
    "gn:timezone":"Asia/Aden",
    "iso:country":"YE",
    "name:ara_x_preferred":[
        "\u0623\u0643\u0645\u0629 \u0627\u0644\u0633\u0641\u0644\u0649"
    ],
    "name:und_x_variant":[
        "Akimah as Sufl\u00e1"
    ],
    "wof:name":"Akimah as Sufla",
    "wof:placetype":"locality"
},
  "geometry": {"coordinates":[44.13765,14.28976],"type":"Point"}
}