{
  "type": "Feature",
  "properties": {
    "gn:admin1_code":"14.0",
    "gn:admin2_code":"2608.0",
    "gn:asciiname":"Rahbah (Al Kawlah)",
    "gn:country_code":"YE",
    "gn:dem":1483,
    "gn:feature_class":"P",
    "gn:feature_code":"PPLA2",
    "gn:name":"Ra\u1e29bah (Al Kawlah)",
    "gn:population":0,
    "gn:timezone":"Asia/Aden",
    "iso:country":"YE",
    "name:ara_x_preferred":[
        "\u0631\u062d\u0628\u0629"
    ],
    "name:ara_x_variant":[
        "\u0631\u062d\u0628\u0629 \u0627\u0644\u0643\u0648\u0644\u0629",
        "\u0631\u062d\u0628\u0629 (\u0627\u0644\u0643\u0648\u0644\u0629)"
    ],
    "name:und_x_variant":[
        "Al Kawlah Ra\u1e29abah",
        "Ra\u1e29abah",
        "Ra\u1e29abah al Kawlah",
        "Ra\u1e29bah (Al Kawlah)"
    ],
    "wof:name":"Rahbah (Al Kawlah)",
    "wof:placetype":"locality"
},
  "geometry": {"coordinates":[44.98893,14.8953],"type":"Point"}
}