{
  "type": "Feature",
  "properties": {
    "gn:admin1_code":"25.0",
    "gn:admin2_code":"1504.0",
    "gn:asciiname":"Al Khawamis",
    "gn:country_code":"YE",
    "gn:dem":764,
    "gn:feature_class":"P",
    "gn:feature_code":"PPL",
    "gn:name":"Al Khaw\u0101mis",
    "gn:population":0,
    "gn:timezone":"Asia/Aden",
    "iso:country":"YE",
    "name:ara_x_preferred":[
        "\u0627\u0644\u062e\u0648\u0627\u0645\u0633"
    ],
    "name:und_x_variant":[
        "Al Khaw\u0101mis",
        "Hamada"
    ],
    "wof:name":"Al Khawamis",
    "wof:placetype":"locality"
},
  "geometry": {"coordinates":[43.78823,13.83742],"type":"Point"}
}