{
  "type": "Feature",
  "properties": {
    "gn:admin1_code":"19.0",
    "gn:admin2_code":"2920.0",
    "gn:asciiname":"Dammaj",
    "gn:country_code":"YE",
    "gn:dem":2216,
    "gn:feature_class":"P",
    "gn:feature_code":"PPL",
    "gn:name":"Damm\u0101j",
    "gn:population":0,
    "gn:timezone":"Asia/Aden",
    "iso:country":"YE",
    "name:und_x_variant":[
        "Damm\u0101j"
    ],
    "wof:name":"Dammaj",
    "wof:placetype":"locality"
},
  "geometry": {"coordinates":[44.01082,16.10765],"type":"Point"}
}