{
  "type": "Feature",
  "properties": {
    "gn:admin1_code":"19.0",
    "gn:admin2_code":"2920.0",
    "gn:asciiname":"Dammaj",
    "gn:country_code":"YE",
    "gn:dem":2216,
    "gn:feature_class":"P",
    "gn:feature_code":"PPL",
    "gn:name":"Damm\u0101j",
    "gn:population":0,
    "gn:timezone":"Asia/Aden",
    "iso:country":"YE",
    "name:ara_x_preferred":[
        "\u062f\u0645\u0627\u062c"
    ],
    "name:ceb_x_preferred":[
        "Damm\u0101j"
    ],
    "name:fas_x_preferred":[
        "\u0634\u0647\u0631 \u062f\u0645\u0627\u062c"
    ],
    "name:fra_x_preferred":[
        "Dammaj"
    ],
    "name:nno_x_preferred":[
        "Dammaj"
    ],
    "name:rus_x_preferred":[
        "\u0414\u0430\u043c\u043c\u0430\u0434\u0436"
    ],
    "wof:name":"Dammaj",
    "wof:placetype":"locality"
},
  "geometry": {"coordinates":[44.01082,16.10765],"type":"Point"}
}