{
  "type": "Feature",
  "properties": {
    "gn:admin1_code":"19.0",
    "gn:admin2_code":"2903.0",
    "gn:asciiname":"Al Qahaz",
    "gn:country_code":"YE",
    "gn:dem":1137,
    "gn:feature_class":"P",
    "gn:feature_code":"PPL",
    "gn:name":"Al Qa\u1e29az",
    "gn:population":0,
    "gn:timezone":"Asia/Aden",
    "iso:country":"YE",
    "name:ara_x_preferred":[
        "\u0627\u0644\u0642\u062d\u0632"
    ],
    "name:und_x_variant":[
        "Al Qa\u1e29az"
    ],
    "wof:name":"Al Qahaz",
    "wof:placetype":"locality"
},
  "geometry": {"coordinates":[43.80641,16.17278],"type":"Point"}
}