{
  "type": "Feature",
  "properties": {
    "gn:admin1_code":"25.0",
    "gn:admin2_code":"1504.0",
    "gn:asciiname":"Al Hajarah",
    "gn:country_code":"YE",
    "gn:dem":807,
    "gn:feature_class":"P",
    "gn:feature_code":"PPL",
    "gn:name":"Al \u1e28ajarah",
    "gn:population":0,
    "gn:timezone":"Asia/Aden",
    "iso:country":"YE",
    "name:ara_x_preferred":[
        "\u0627\u0644\u062d\u062c\u0631\u0629"
    ],
    "name:und_x_variant":[
        "Al \u1e28ajarah",
        "Al \u1e28ujrah"
    ],
    "wof:name":"Al Hajarah",
    "wof:placetype":"locality"
},
  "geometry": {"coordinates":[43.81233,13.63833],"type":"Point"}
}