{
  "type": "Feature",
  "properties": {
    "gn:admin1_code":"23.0",
    "gn:admin2_code":"1115.0",
    "gn:asciiname":"Dhil Mahmar",
    "gn:country_code":"YE",
    "gn:dem":2409,
    "gn:feature_class":"P",
    "gn:feature_code":"PPL",
    "gn:name":"Dhil Ma\u1e29mar",
    "gn:population":0,
    "gn:timezone":"Asia/Aden",
    "iso:country":"YE",
    "name:und_x_variant":[
        "Dhil Ma\u1e29mar"
    ],
    "wof:name":"Dhil Mahmar",
    "wof:placetype":"locality"
},
  "geometry": {"coordinates":[44.14646,13.85466],"type":"Point"}
}