{
  "type": "Feature",
  "properties": {
    "gn:admin1_code":"22.0",
    "gn:admin2_code":"1726.0",
    "gn:asciiname":"Al `Ard",
    "gn:country_code":"YE",
    "gn:dem":1031,
    "gn:feature_class":"P",
    "gn:feature_code":"PPL",
    "gn:name":"Al \u2018Ar\u1e11",
    "gn:population":0,
    "gn:timezone":"Asia/Aden",
    "iso:country":"YE",
    "name:ara_x_preferred":[
        "Al \u2018Ar\u1e11"
    ],
    "wof:name":"Al `Ard",
    "wof:placetype":"locality"
},
  "geometry": {"coordinates":[43.52807,15.63953],"type":"Point"}
}