{
  "type": "Feature",
  "properties": {
    "gn:admin1_code":"11.0",
    "gn:admin2_code":"2001.0",
    "gn:asciiname":"Al Aghwal",
    "gn:country_code":"YE",
    "gn:dem":2387,
    "gn:feature_class":"P",
    "gn:feature_code":"PPL",
    "gn:name":"Al Aghw\u0101l",
    "gn:population":0,
    "gn:timezone":"Asia/Aden",
    "iso:country":"YE",
    "name:ara_x_preferred":[
        "Al Aghw\u0101l"
    ],
    "wof:name":"Al Aghwal",
    "wof:placetype":"locality"
},
  "geometry": {"coordinates":[44.45865,14.62964],"type":"Point"}
}