{
  "type": "Feature",
  "properties": {
    "gn:admin1_code":"25.0",
    "gn:admin2_code":"1502.0",
    "gn:asciiname":"Az Zaribah",
    "gn:country_code":"YE",
    "gn:dem":1391,
    "gn:feature_class":"P",
    "gn:feature_code":"PPL",
    "gn:name":"Az\u0327 Z\u0327\u0101ribah",
    "gn:population":0,
    "gn:timezone":"Asia/Aden",
    "iso:country":"YE",
    "name:und_x_variant":[
        "Az\u0327 Z\u0327\u0101ribah"
    ],
    "wof:name":"Az Zaribah",
    "wof:placetype":"locality"
},
  "geometry": {"coordinates":[44.14779,13.61092],"type":"Point"}
}