{
  "type": "Feature",
  "properties": {
    "gn:admin1_code":"11.0",
    "gn:admin2_code":"2006.0",
    "gn:asciiname":"Qaryat Buna'ah",
    "gn:country_code":"YE",
    "gn:dem":1541,
    "gn:feature_class":"P",
    "gn:feature_code":"PPL",
    "gn:name":"Qaryat Bun\u0101\u2019ah",
    "gn:population":0,
    "gn:timezone":"Asia/Aden",
    "iso:country":"YE",
    "name:und_x_variant":[
        "Qaryat Bun\u0101\u2019ah"
    ],
    "wof:name":"Qaryat Buna'ah",
    "wof:placetype":"locality"
},
  "geometry": {"coordinates":[43.73466,14.40775],"type":"Point"}
}