{
  "type": "Feature",
  "properties": {
    "gn:admin1_code":"10.0",
    "gn:admin2_code":"2705.0",
    "gn:asciiname":"Al Madwarah",
    "gn:country_code":"YE",
    "gn:dem":956,
    "gn:feature_class":"P",
    "gn:feature_code":"PPL",
    "gn:name":"Al Madwarah",
    "gn:population":0,
    "gn:timezone":"Asia/Aden",
    "iso:country":"YE",
    "wof:name":"Al Madwarah",
    "wof:placetype":"locality"
},
  "geometry": {"coordinates":[43.3258,15.34001],"type":"Point"}
}