{
  "type": "Feature",
  "properties": {
    "gn:admin1_code":"23.0",
    "gn:admin2_code":"1113.0",
    "gn:asciiname":"Al Manawib",
    "gn:country_code":"YE",
    "gn:dem":2610,
    "gn:feature_class":"P",
    "gn:feature_code":"PPL",
    "gn:name":"Al Man\u0101wib",
    "gn:population":0,
    "gn:timezone":"Asia/Aden",
    "iso:country":"YE",
    "name:ara_x_preferred":[
        "\u0627\u0644\u0645\u0646\u0627\u0648\u0628"
    ],
    "name:und_x_variant":[
        "Al Man\u0101wib"
    ],
    "wof:name":"Al Manawib",
    "wof:placetype":"locality"
},
  "geometry": {"coordinates":[44.25412,14.00163],"type":"Point"}
}