{
  "type": "Feature",
  "properties": {
    "gn:admin1_code":"5.0",
    "gn:asciiname":"Shatran",
    "gn:country_code":"YE",
    "gn:dem":1230,
    "gn:feature_class":"P",
    "gn:feature_code":"PPL",
    "gn:name":"Shatr\u0101n",
    "gn:population":0,
    "gn:timezone":"Asia/Aden",
    "iso:country":"YE",
    "name:ara_x_preferred":[
        "\u0634\u062a\u0631\u0627\u0646"
    ],
    "name:und_x_variant":[
        "Shatr\u0101n"
    ],
    "wof:name":"Shatran",
    "wof:placetype":"locality"
},
  "geometry": {"coordinates":[46.80624,14.43758],"type":"Point"}
}