{
  "type": "Feature",
  "properties": {
    "gn:admin1_code":"19.0",
    "gn:admin2_code":"2916.0",
    "gn:asciiname":"Bani Salim",
    "gn:country_code":"YE",
    "gn:dem":1545,
    "gn:feature_class":"P",
    "gn:feature_code":"PPL",
    "gn:name":"Ban\u012b S\u0101lim",
    "gn:population":0,
    "gn:timezone":"Asia/Aden",
    "iso:country":"YE",
    "name:und_x_variant":[
        "Ban\u012b S\u0101lim"
    ],
    "wof:name":"Bani Salim",
    "wof:placetype":"locality"
},
  "geometry": {"coordinates":[43.69857,15.65443],"type":"Point"}
}