{
  "type": "Feature",
  "properties": {
    "gn:admin1_code":"23.0",
    "gn:admin2_code":"1116.0",
    "gn:asciiname":"Ra's al Wadi",
    "gn:country_code":"YE",
    "gn:dem":1943,
    "gn:feature_class":"P",
    "gn:feature_code":"PPL",
    "gn:name":"Ra\u2019s al W\u0101d\u012b",
    "gn:population":0,
    "gn:timezone":"Asia/Aden",
    "iso:country":"YE",
    "name:und_x_variant":[
        "Ra\u2019s al W\u0101d\u012b"
    ],
    "wof:name":"Ra's al Wadi",
    "wof:placetype":"locality"
},
  "geometry": {"coordinates":[44.11154000000001,13.8475],"type":"Point"}
}