{
  "type": "Feature",
  "properties": {
    "gn:admin1_code":"18.0",
    "gn:admin2_code":"3009.0",
    "gn:asciiname":"As Sayrat",
    "gn:country_code":"YE",
    "gn:dem":2219,
    "gn:feature_class":"P",
    "gn:feature_code":"PPL",
    "gn:name":"A\u015f \u015eayr\u0101t",
    "gn:population":0,
    "gn:timezone":"Asia/Aden",
    "iso:country":"YE",
    "name:und_x_variant":[
        "A\u015f \u015eayr\u0101t"
    ],
    "wof:name":"As Sayrat",
    "wof:placetype":"locality"
},
  "geometry": {"coordinates":[44.49533,13.73336],"type":"Point"}
}