{
  "type": "Feature",
  "properties": {
    "gn:admin1_code":"11.0",
    "gn:admin2_code":"2006.0",
    "gn:asciiname":"Mirba'i",
    "gn:country_code":"YE",
    "gn:dem":1720,
    "gn:feature_class":"P",
    "gn:feature_code":"PPL",
    "gn:name":"Mirb\u0101\u2019\u012b",
    "gn:population":0,
    "gn:timezone":"Asia/Aden",
    "iso:country":"YE",
    "name:ara_x_preferred":[
        "Mirb\u0101\u2019\u012b"
    ],
    "wof:name":"Mirba'i",
    "wof:placetype":"locality"
},
  "geometry": {"coordinates":[43.91451,14.30575],"type":"Point"}
}