{
  "type": "Feature",
  "properties": {
    "gn:admin1_code":"19.0",
    "gn:admin2_code":"2905.0",
    "gn:asciiname":"Al Qawim",
    "gn:country_code":"YE",
    "gn:dem":1760,
    "gn:feature_class":"P",
    "gn:feature_code":"PPL",
    "gn:name":"Al Qaw\u012bm",
    "gn:population":0,
    "gn:timezone":"Asia/Aden",
    "iso:country":"YE",
    "name:ara_x_preferred":[
        "\u0627\u0644\u0642\u0648\u064a\u0645"
    ],
    "name:und_x_variant":[
        "Al Qaw\u012bm"
    ],
    "wof:name":"Al Qawim",
    "wof:placetype":"locality"
},
  "geometry": {"coordinates":[43.67053,16.16474],"type":"Point"}
}