{
  "type": "Feature",
  "properties": {
    "gn:admin1_code":"5.0",
    "gn:admin2_code":"2107.0",
    "gn:asciiname":"Al Wasi`ah",
    "gn:country_code":"YE",
    "gn:dem":1114,
    "gn:elevation":"2.0",
    "gn:feature_class":"P",
    "gn:feature_code":"PPL",
    "gn:name":"Al Was\u012b\u2018ah",
    "gn:population":0,
    "gn:timezone":"Asia/Aden",
    "iso:country":"YE",
    "name:und_x_variant":[
        "Al Was\u012b\u2018ah"
    ],
    "wof:name":"Al Wasi`ah",
    "wof:placetype":"locality"
},
  "geometry": {"coordinates":[45.72368,14.82975],"type":"Point"}
}