{
  "type": "Feature",
  "properties": {
    "gn:admin1_code":"22.0",
    "gn:admin2_code":"1722.0",
    "gn:asciiname":"Sha`fah",
    "gn:country_code":"YE",
    "gn:dem":450,
    "gn:feature_class":"P",
    "gn:feature_code":"PPL",
    "gn:name":"Sha\u2018fah",
    "gn:population":0,
    "gn:timezone":"Asia/Aden",
    "iso:country":"YE",
    "name:und_x_variant":[
        "Sha\u2018fah"
    ],
    "wof:name":"Sha`fah",
    "wof:placetype":"locality"
},
  "geometry": {"coordinates":[43.4774,15.78827],"type":"Point"}
}