{
  "type": "Feature",
  "properties": {
    "gn:admin1_code":"25.0",
    "gn:admin2_code":"1515.0",
    "gn:asciiname":"Muhaydah",
    "gn:country_code":"YE",
    "gn:dem":1320,
    "gn:feature_class":"P",
    "gn:feature_code":"PPL",
    "gn:name":"Mu\u1e29ay\u1e11ah",
    "gn:population":0,
    "gn:timezone":"Asia/Aden",
    "iso:country":"YE",
    "name:und_x_variant":[
        "Mu\u1e29ay\u1e11ah"
    ],
    "wof:name":"Muhaydah",
    "wof:placetype":"locality"
},
  "geometry": {"coordinates":[44.00669,13.23818],"type":"Point"}
}