{
  "type": "Feature",
  "properties": {
    "gn:admin1_code":"8.0",
    "gn:admin2_code":"1802.0",
    "gn:asciiname":"Al Azraq",
    "gn:country_code":"YE",
    "gn:dem":19,
    "gn:feature_class":"P",
    "gn:feature_code":"PPL",
    "gn:name":"Al Azraq",
    "gn:population":0,
    "gn:timezone":"Asia/Aden",
    "iso:country":"YE",
    "name:ara_x_preferred":[
        "\u0627\u0644\u0627\u0632\u0631\u0642"
    ],
    "wof:name":"Al Azraq",
    "wof:placetype":"locality"
},
  "geometry": {"coordinates":[42.79538,15.69488],"type":"Point"}
}