{
  "type": "Feature",
  "properties": {
    "gn:admin1_code":"23.0",
    "gn:admin2_code":"1109.0",
    "gn:asciiname":"Qaryat `Abar",
    "gn:country_code":"YE",
    "gn:dem":1708,
    "gn:feature_class":"P",
    "gn:feature_code":"PPL",
    "gn:name":"Qaryat \u2018Abar",
    "gn:population":0,
    "gn:timezone":"Asia/Aden",
    "iso:country":"YE",
    "name:ara_x_preferred":[
        "\u0639\u0628\u0631"
    ],
    "name:und_x_variant":[
        "Qaryat \u2018Abar",
        "\u2018Abr"
    ],
    "wof:name":"Qaryat `Abar",
    "wof:placetype":"locality"
},
  "geometry": {"coordinates":[44.04344,14.07515],"type":"Point"}
}