{
  "type": "Feature",
  "properties": {
    "gn:country":"YE",
    "gn:fcode":"PPL",
    "gn:population":8,
    "iso:country":"YE",
    "name:ara_x_preferred":[
        "\u0627\u0644\u0639\u062c\u0645\u0629"
    ],
    "name:eng_x_preferred":[
        "Al 'Ajmah"
    ],
    "name:eng_x_variant":[
        "Ar Raqraqah"
    ],
    "qs:name":"Al \u2018Ajmah",
    "qs:photos_9r":0,
    "qs:photos_sr":0,
    "qs:pop_sr":"1",
    "wof:name":"Al \u2018Ajmah",
    "wof:placetype":"locality",
    "wof:population":8
},
  "geometry": {"coordinates":[45.4411,14.93507],"type":"Point"}
}