{
  "type": "Feature",
  "properties": {
    "gn:admin1_code":"22.0",
    "gn:admin2_code":"1727.0",
    "gn:asciiname":"Bani Hadid",
    "gn:country_code":"YE",
    "gn:dem":1350,
    "gn:feature_class":"P",
    "gn:feature_code":"PPL",
    "gn:name":"Ban\u012b \u1e28ad\u012bd",
    "gn:population":0,
    "gn:timezone":"Asia/Aden",
    "iso:country":"YE",
    "name:und_x_variant":[
        "Ban\u012b \u1e28ad\u012bd"
    ],
    "wof:name":"Bani Hadid",
    "wof:placetype":"locality"
},
  "geometry": {"coordinates":[43.56541,15.56579],"type":"Point"}
}