{
  "type": "Feature",
  "properties": {
    "gn:country":"YE",
    "gn:fcode":"PPL",
    "gn:population":13,
    "iso:country":"YE",
    "name:ara_x_preferred":[
        "\u062d\u062c\u064a\u062c"
    ],
    "name:eng_x_preferred":[
        "Hujayj"
    ],
    "qs:name":"\u1e28ujayj",
    "qs:photos_9r":0,
    "qs:photos_sr":0,
    "qs:pop_sr":"1",
    "wof:name":"\u1e28ujayj",
    "wof:placetype":"locality",
    "wof:population":13
},
  "geometry": {"coordinates":[43.82573,13.1256],"type":"Point"}
}