{
  "type": "Feature",
  "properties": {
    "gn:admin1_code":"8.0",
    "gn:admin2_code":"1807.0",
    "gn:asciiname":"Mahall Abkar 'Ali Qasim",
    "gn:country_code":"YE",
    "gn:dem":35,
    "gn:feature_class":"P",
    "gn:feature_code":"PPL",
    "gn:name":"Ma\u1e29all Abkar \u2018Al\u012b Q\u0101sim",
    "gn:population":0,
    "gn:timezone":"Asia/Aden",
    "iso:country":"YE",
    "name:ara_x_preferred":[
        "\u0645\u062d\u0644 \u0623\u0628\u0643\u0631 \u0639\u0644\u0649 \u0642\u0627\u0633\u0645"
    ],
    "name:und_x_variant":[
        "Ma\u1e29all Abkar \u2018Al\u012b Q\u0101sim"
    ],
    "wof:name":"Mahall Abkar 'Ali Qasim",
    "wof:placetype":"locality"
},
  "geometry": {"coordinates":[42.94795,15.22905],"type":"Point"}
}