{
  "type": "Feature",
  "properties": {
    "gn:admin1_code":"8.0",
    "gn:admin2_code":"1812.0",
    "gn:asciiname":"Adh Dhafara",
    "gn:country_code":"YE",
    "gn:dem":1182,
    "gn:feature_class":"P",
    "gn:feature_code":"PPL",
    "gn:name":"Adh Dhaf\u0101r\u00e1",
    "gn:population":0,
    "gn:timezone":"Asia/Aden",
    "iso:country":"YE",
    "name:ara_x_preferred":[
        "\u0627\u0644\u0630\u0641\u0627\u0631\u0649"
    ],
    "name:und_x_variant":[
        "Adh Dhaf\u0101r\u012b",
        "Adh Dhaf\u0101r\u00e1"
    ],
    "wof:name":"Adh Dhafara",
    "wof:placetype":"locality"
},
  "geometry": {"coordinates":[43.47312,14.92458],"type":"Point"}
}