{
  "type": "Feature",
  "properties": {
    "gn:admin1_code":"25.0",
    "gn:admin2_code":"1515.0",
    "gn:asciiname":"Al Laws",
    "gn:country_code":"YE",
    "gn:dem":1019,
    "gn:feature_class":"P",
    "gn:feature_code":"PPL",
    "gn:name":"Al Law\u015f",
    "gn:population":0,
    "gn:timezone":"Asia/Aden",
    "iso:country":"YE",
    "name:ara_x_preferred":[
        "\u0627\u0644\u0644\u0648\u0635"
    ],
    "name:und_x_variant":[
        "Al Law\u015f"
    ],
    "wof:name":"Al Laws",
    "wof:placetype":"locality"
},
  "geometry": {"coordinates":[43.94951,13.21292],"type":"Point"}
}