{
  "type": "Feature",
  "properties": {
    "gn:admin1_code":"19.0",
    "gn:admin2_code":"2912.0",
    "gn:asciiname":"Sha`b",
    "gn:country_code":"YE",
    "gn:dem":2300,
    "gn:feature_class":"P",
    "gn:feature_code":"PPL",
    "gn:name":"Sha\u2018b",
    "gn:population":0,
    "gn:timezone":"Asia/Aden",
    "iso:country":"YE",
    "name:und_x_variant":[
        "Sha\u2018b"
    ],
    "wof:name":"Sha`b",
    "wof:placetype":"locality"
},
  "geometry": {"coordinates":[43.924,15.81058],"type":"Point"}
}