{
  "type": "Feature",
  "properties": {
    "gn:admin1_code":"21.0",
    "gn:admin2_code":"1612.0",
    "gn:asciiname":"Al Hazm",
    "gn:country_code":"YE",
    "gn:dem":1341,
    "gn:feature_class":"P",
    "gn:feature_code":"PPL",
    "gn:name":"Al \u1e28azm",
    "gn:population":0,
    "gn:timezone":"Asia/Aden",
    "iso:country":"YE",
    "name:ara_x_preferred":[
        "\u0627\u0644\u062d\u0632\u0645"
    ],
    "name:ceb_x_preferred":[
        "Al Hazm"
    ],
    "name:fra_x_preferred":[
        "Al Hazm"
    ],
    "name:nld_x_preferred":[
        "Al Hazm"
    ],
    "name:spa_x_preferred":[
        "Al Hazm"
    ],
    "name:und_x_variant":[
        "Al \u1e28azm"
    ],
    "wof:name":"Al Hazm",
    "wof:placetype":"locality"
},
  "geometry": {"coordinates":[44.28127,16.50692],"type":"Point"}
}