{
  "type": "Feature",
  "properties": {
    "gn:admin1_code":"8.0",
    "gn:admin2_code":"1813.0",
    "gn:asciiname":"Dayr al Jawabihah",
    "gn:country_code":"YE",
    "gn:dem":175,
    "gn:feature_class":"P",
    "gn:feature_code":"PPL",
    "gn:name":"Dayr al Jaw\u0101bi\u1e29ah",
    "gn:population":0,
    "gn:timezone":"Asia/Aden",
    "iso:country":"YE",
    "name:und_x_variant":[
        "Dayr al Jaw\u0101bi\u1e29ah"
    ],
    "wof:name":"Dayr al Jawabihah",
    "wof:placetype":"locality"
},
  "geometry": {"coordinates":[43.37217,14.89291],"type":"Point"}
}