{
  "type": "Feature",
  "properties": {
    "gn:admin1_code":"25.0",
    "gn:admin2_code":"1506.0",
    "gn:asciiname":"An Nujaybah",
    "gn:country_code":"YE",
    "gn:dem":133,
    "gn:feature_class":"P",
    "gn:feature_code":"PPL",
    "gn:name":"An Nujaybah",
    "gn:population":0,
    "gn:timezone":"Asia/Aden",
    "iso:country":"YE",
    "name:ara_x_preferred":[
        "\u0627\u0644\u0646\u062c\u064a\u0628\u0629"
    ],
    "wof:name":"An Nujaybah",
    "wof:placetype":"locality"
},
  "geometry": {"coordinates":[43.48431,13.56594],"type":"Point"}
}