{
  "type": "Feature",
  "properties": {
    "gn:admin1_code":"8.0",
    "gn:admin2_code":"1825.0",
    "gn:asciiname":"Mahwa `Uqban",
    "gn:country_code":"YE",
    "gn:dem":111,
    "gn:feature_class":"P",
    "gn:feature_code":"PPL",
    "gn:name":"Ma\u1e29w\u00e1 \u2018Uqb\u0101n",
    "gn:population":0,
    "gn:timezone":"Asia/Aden",
    "iso:country":"YE",
    "name:und_x_variant":[
        "Ma\u1e29w\u00e1 \u2018Uqb\u0101n"
    ],
    "wof:name":"Mahwa `Uqban",
    "wof:placetype":"locality"
},
  "geometry": {"coordinates":[43.33205,14.13018],"type":"Point"}
}