{
  "type": "Feature",
  "properties": {
    "gn:country":"YE",
    "gn:fcode":"PPL",
    "gn:pop":7,
    "iso:country":"YE",
    "name:ara_x_preferred":[
        "\u0645\u0633\u0641\u0640\u0639"
    ],
    "name:eng_x_preferred":[
        "Masfa'"
    ],
    "qs:name":"Masfa\u2018",
    "qs:photos_9r":0,
    "qs:photos_sr":0,
    "qs:pop_sr":"1",
    "wof:name":"Masfa\u2018",
    "wof:placetype":"locality",
    "wof:population":7
},
  "geometry": {"coordinates":[43.31165,16.46171],"type":"Point"}
}