{
  "type": "Feature",
  "properties": {
    "gn:admin1_code":"24.0",
    "gn:admin2_code":"2510.0",
    "gn:asciiname":"Al Kurb `Anafat",
    "gn:country_code":"YE",
    "gn:dem":1646,
    "gn:feature_class":"P",
    "gn:feature_code":"PPL",
    "gn:name":"Al Kurb \u2018Anaf\u0101t",
    "gn:population":0,
    "gn:timezone":"Asia/Aden",
    "iso:country":"YE",
    "name:und_x_variant":[
        "Al Kurb \u2018Anaf\u0101t"
    ],
    "wof:name":"Al Kurb `Anafat",
    "wof:placetype":"locality"
},
  "geometry": {"coordinates":[44.4053,13.29466],"type":"Point"}
}