{
  "type": "Feature",
  "properties": {
    "gn:admin1_code":"22.0",
    "gn:admin2_code":"1719.0",
    "gn:asciiname":"Bayt Qadam",
    "gn:country_code":"YE",
    "gn:dem":2012,
    "gn:feature_class":"P",
    "gn:feature_code":"PPL",
    "gn:name":"Bayt Qadam",
    "gn:population":0,
    "gn:timezone":"Asia/Aden",
    "iso:country":"YE",
    "name:und_x_variant":[
        "Jabal Bayt Qadam"
    ],
    "wof:name":"Bayt Qadam",
    "wof:placetype":"locality"
},
  "geometry": {"coordinates":[43.68551,15.68474],"type":"Point"}
}