{
  "type": "Feature",
  "properties": {
    "gn:admin1_code":"22.0",
    "gn:admin2_code":"1707.0",
    "gn:asciiname":"Ash Shirak",
    "gn:country_code":"YE",
    "gn:dem":1457,
    "gn:feature_class":"P",
    "gn:feature_code":"PPL",
    "gn:name":"Ash Shir\u0101k",
    "gn:population":0,
    "gn:timezone":"Asia/Aden",
    "iso:country":"YE",
    "name:ara_x_preferred":[
        "Ash Shir\u0101k"
    ],
    "name:ara_x_variant":[
        "\u0627\u0644\u0634\u0631\u0627\u0643"
    ],
    "wof:name":"Ash Shirak",
    "wof:placetype":"locality"
},
  "geometry": {"coordinates":[43.45938,16.19518],"type":"Point"}
}