{
  "type": "Feature",
  "properties": {
    "gn:admin1_code":"25.0",
    "gn:admin2_code":"1521.0",
    "gn:asciiname":"Al Khiyami",
    "gn:country_code":"YE",
    "gn:dem":1202,
    "gn:feature_class":"P",
    "gn:feature_code":"PPL",
    "gn:name":"Al Khiy\u0101m\u012b",
    "gn:population":0,
    "gn:timezone":"Asia/Aden",
    "iso:country":"YE",
    "name:ara_x_preferred":[
        "Al Khiy\u0101m\u012b"
    ],
    "wof:name":"Al Khiyami",
    "wof:placetype":"locality"
},
  "geometry": {"coordinates":[43.95583,13.33438],"type":"Point"}
}