{
  "type": "Feature",
  "properties": {
    "gn:admin1_code":"19.0",
    "gn:admin2_code":"2904.0",
    "gn:asciiname":"Dhu Ju'man",
    "gn:country_code":"YE",
    "gn:dem":1313,
    "gn:feature_class":"P",
    "gn:feature_code":"PPL",
    "gn:name":"Dh\u016b Ju\u2018m\u0101n",
    "gn:population":0,
    "gn:timezone":"Asia/Aden",
    "iso:country":"YE",
    "name:ara_x_preferred":[
        "Dh\u016b Ju\u2018m\u0101n"
    ],
    "name:ara_x_variant":[
        "\u0630\u0648 \u062c\u0639\u0645\u0627\u0646"
    ],
    "wof:name":"Dhu Ju'man",
    "wof:placetype":"locality"
},
  "geometry": {"coordinates":[43.77092,16.31311],"type":"Point"}
}