{
  "type": "Feature",
  "properties": {
    "gn:admin1_code":"14.0",
    "gn:admin2_code":"2604.0",
    "gn:asciiname":"Ar Rayifah",
    "gn:country_code":"YE",
    "gn:dem":1848,
    "gn:feature_class":"P",
    "gn:feature_code":"PPL",
    "gn:name":"Ar R\u0101yifah",
    "gn:population":0,
    "gn:timezone":"Asia/Aden",
    "iso:country":"YE",
    "name:ara_x_preferred":[
        "\u0627\u0644\u0631\u0627\u064a\u0641\u0629"
    ],
    "name:und_x_variant":[
        "Ar R\u0101yighah",
        "Ar R\u0101yifah"
    ],
    "wof:name":"Ar Rayifah",
    "wof:placetype":"locality"
},
  "geometry": {"coordinates":[44.6277,15.44159],"type":"Point"}
}