{
  "type": "Feature",
  "properties": {
    "gn:admin1_code":"8.0",
    "gn:admin2_code":"1815.0",
    "gn:asciiname":"Al Uthmaniyah",
    "gn:country_code":"YE",
    "gn:dem":117,
    "gn:feature_class":"P",
    "gn:feature_code":"PPL",
    "gn:name":"Al Uthm\u0101n\u012byah",
    "gn:population":0,
    "gn:timezone":"Asia/Aden",
    "iso:country":"YE",
    "name:und_x_variant":[
        "Al Uthm\u0101n\u012byah",
        "Al \u2018Uthm\u0101n\u012byah"
    ],
    "wof:name":"Al Uthmaniyah",
    "wof:placetype":"locality"
},
  "geometry": {"coordinates":[43.25681,14.71352],"type":"Point"}
}