{
  "type": "Feature",
  "properties": {
    "gn:admin1_code":"23.0",
    "gn:asciiname":"Shatt `Udaynah",
    "gn:country_code":"YE",
    "gn:dem":1321,
    "gn:feature_class":"P",
    "gn:feature_code":"PPL",
    "gn:name":"Sha\u0163\u0163 \u2018Udaynah",
    "gn:population":0,
    "gn:timezone":"Asia/Aden",
    "iso:country":"YE",
    "name:ara_x_preferred":[
        "\u0634\u0637 \u0639\u062f\u064a\u0646\u0629"
    ],
    "name:und_x_variant":[
        "Sha\u0163\u0163 \u2018Udaynah"
    ],
    "wof:name":"Shatt `Udaynah",
    "wof:placetype":"locality"
},
  "geometry": {"coordinates":[44.08722,14.36738],"type":"Point"}
}