{
  "type": "Feature",
  "properties": {
    "gn:admin1_code":"16.0",
    "gn:admin2_code":"2303.0",
    "gn:asciiname":"Ash Shalatin",
    "gn:country_code":"YE",
    "gn:dem":2154,
    "gn:feature_class":"P",
    "gn:feature_code":"PPL",
    "gn:name":"Ash Shal\u0101\u0163\u012bn",
    "gn:population":0,
    "gn:timezone":"Asia/Aden",
    "iso:country":"YE",
    "name:ara_x_preferred":[
        "\u0627\u0644\u0634\u0644\u0627\u0637\u064a\u0646"
    ],
    "name:und_x_variant":[
        "Ash Shal\u0101\u0163\u012bn"
    ],
    "wof:name":"Ash Shalatin",
    "wof:placetype":"locality"
},
  "geometry": {"coordinates":[44.525,15.74905],"type":"Point"}
}