{
  "type": "Feature",
  "properties": {
    "gn:admin1_code":"24.0",
    "gn:admin2_code":"2515.0",
    "gn:asciiname":"`Ubar al Jadid",
    "gn:country_code":"YE",
    "gn:dem":96,
    "gn:feature_class":"P",
    "gn:feature_code":"PPL",
    "gn:name":"\u2018Ubar al Jad\u012bd",
    "gn:population":0,
    "gn:timezone":"Asia/Aden",
    "iso:country":"YE",
    "name:und_x_variant":[
        "\u2018Ubar al Jad\u012bd"
    ],
    "wof:name":"`Ubar al Jadid",
    "wof:placetype":"locality"
},
  "geometry": {"coordinates":[44.93056,13.05889],"type":"Point"}
}