{
  "type": "Feature",
  "properties": {
    "gn:admin1_code":"8.0",
    "gn:admin2_code":"1817.0",
    "gn:asciiname":"Al Maq'ashiyah",
    "gn:country_code":"YE",
    "gn:dem":97,
    "gn:feature_class":"P",
    "gn:feature_code":"PPL",
    "gn:name":"Al Maq\u2018ash\u012byah",
    "gn:population":0,
    "gn:timezone":"Asia/Aden",
    "iso:country":"YE",
    "name:ara_x_preferred":[
        "\u0627\u0644\u0645\u0642\u0639\u0634\u064a\u0629"
    ],
    "name:und_x_variant":[
        "Al Maq\u2018ash\u012byah"
    ],
    "wof:name":"Al Maq'ashiyah",
    "wof:placetype":"locality"
},
  "geometry": {"coordinates":[43.24115,14.50057],"type":"Point"}
}