{
  "type": "Feature",
  "properties": {
    "gn:admin1_code":"24.0",
    "gn:admin2_code":"2511.0",
    "gn:asciiname":"Al Usha",
    "gn:country_code":"YE",
    "gn:dem":458,
    "gn:feature_class":"P",
    "gn:feature_code":"PPL",
    "gn:name":"Al Usha",
    "gn:population":0,
    "gn:timezone":"Asia/Aden",
    "iso:country":"YE",
    "wof:name":"Al Usha",
    "wof:placetype":"locality"
},
  "geometry": {"coordinates":[44.36333,13.08278],"type":"Point"}
}