{
  "type": "Feature",
  "properties": {
    "gn:country":"YE",
    "gn:fcode":"PPL",
    "gn:population":1,
    "iso:country":"YE",
    "name:ara_x_preferred":[
        "\u0627\u0644\u0645\u0636\u0628\u0627\u0631"
    ],
    "qs:name":"Al Ma\u1e11b\u0101r",
    "qs:photos_9r":0,
    "qs:photos_sr":0,
    "qs:pop_sr":"1",
    "wof:name":"Al Ma\u1e11b\u0101r",
    "wof:placetype":"locality",
    "wof:population":1
},
  "geometry": {"coordinates":[43.37565,16.18843],"type":"Point"}
}