{
  "type": "Feature",
  "properties": {
    "gn:admin1_code":"14.0",
    "gn:admin2_code":"2609.0",
    "gn:asciiname":"Far' as Saqiyah",
    "gn:country_code":"YE",
    "gn:dem":1819,
    "gn:feature_class":"P",
    "gn:feature_code":"PPL",
    "gn:name":"Far\u2018 as S\u0101qiyah",
    "gn:population":0,
    "gn:timezone":"Asia/Aden",
    "iso:country":"YE",
    "name:ara_x_preferred":[
        "\u0641\u0631\u0639 \u0627\u0644\u0633\u0627\u0642\u064a\u0629"
    ],
    "name:und_x_variant":[
        "Far\u2018 as S\u0101qiyah"
    ],
    "wof:name":"Far' as Saqiyah",
    "wof:placetype":"locality"
},
  "geometry": {"coordinates":[45.28672,14.91508],"type":"Point"}
}