{
  "type": "Feature",
  "properties": {
    "gn:admin1_code":"16.0",
    "gn:admin2_code":"2302.0",
    "gn:asciiname":"Al Mashamini",
    "gn:country_code":"YE",
    "gn:dem":2491,
    "gn:feature_class":"P",
    "gn:feature_code":"PPL",
    "gn:name":"Al Mash\u0101m\u012bn\u012b",
    "gn:population":0,
    "gn:timezone":"Asia/Aden",
    "iso:country":"YE",
    "name:und_x_variant":[
        "Al Mash\u0101m\u012bn\u012b"
    ],
    "wof:name":"Al Mashamini",
    "wof:placetype":"locality"
},
  "geometry": {"coordinates":[44.24541,15.78689],"type":"Point"}
}