{
  "type": "Feature",
  "properties": {
    "gn:admin1_code":"23.0",
    "gn:admin2_code":"1114.0",
    "gn:asciiname":"As Sayhar",
    "gn:country_code":"YE",
    "gn:dem":1782,
    "gn:feature_class":"P",
    "gn:feature_code":"PPL",
    "gn:name":"A\u015f \u015eay\u1e29\u0101r",
    "gn:population":0,
    "gn:timezone":"Asia/Aden",
    "iso:country":"YE",
    "name:und_x_variant":[
        "A\u015f \u015eay\u1e29\u0101r",
        "\u1e28i\u015en \u015ea\u1e29\u1e29\u0101r"
    ],
    "wof:name":"As Sayhar",
    "wof:placetype":"locality"
},
  "geometry": {"coordinates":[44.32024000000001,13.88968],"type":"Point"}
}