{
  "type": "Feature",
  "properties": {
    "gn:admin1_code":"19.0",
    "gn:admin2_code":"2902.0",
    "gn:asciiname":"Dhu `Alayyan",
    "gn:country_code":"YE",
    "gn:dem":1580,
    "gn:feature_class":"P",
    "gn:feature_code":"PPL",
    "gn:name":"Dh\u016b \u2018Alayy\u0101n",
    "gn:population":0,
    "gn:timezone":"Asia/Aden",
    "iso:country":"YE",
    "name:und_x_variant":[
        "Dh\u016b \u2018Alayy\u0101n"
    ],
    "wof:name":"Dhu `Alayyan",
    "wof:placetype":"locality"
},
  "geometry": {"coordinates":[44.07566,16.26187],"type":"Point"}
}