{
  "type": "Feature",
  "properties": {
    "gn:admin1_code":"24.0",
    "gn:admin2_code":"2513.0",
    "gn:asciiname":"`Ubarah",
    "gn:country_code":"YE",
    "gn:dem":319,
    "gn:feature_class":"P",
    "gn:feature_code":"PPL",
    "gn:name":"\u2018Ubarah",
    "gn:population":0,
    "gn:timezone":"Asia/Aden",
    "iso:country":"YE",
    "name:und_x_variant":[
        "\u2018Ubarah"
    ],
    "wof:name":"`Ubarah",
    "wof:placetype":"locality"
},
  "geometry": {"coordinates":[44.12693,12.92574],"type":"Point"}
}