{
  "type": "Feature",
  "properties": {
    "gn:admin1_code":"14.0",
    "gn:admin2_code":"2606.0",
    "gn:asciiname":"Al Qatid",
    "gn:country_code":"YE",
    "gn:dem":1491,
    "gn:feature_class":"P",
    "gn:feature_code":"PPLL",
    "gn:name":"Al Qat\u012bd",
    "gn:population":0,
    "gn:timezone":"Asia/Aden",
    "iso:country":"YE",
    "name:ara_x_preferred":[
        "\u0627\u0644\u0642\u062a\u064a\u062f"
    ],
    "name:und_x_variant":[
        "Al Qat\u012bd"
    ],
    "wof:name":"Al Qatid",
    "wof:placetype":"locality"
},
  "geometry": {"coordinates":[44.79672,15.51539],"type":"Point"}
}