{
  "type": "Feature",
  "properties": {
    "gn:admin1_code":"16.0",
    "gn:admin2_code":"2313.0",
    "gn:asciiname":"Juj",
    "gn:country_code":"YE",
    "gn:dem":2559,
    "gn:feature_class":"P",
    "gn:feature_code":"PPL",
    "gn:name":"J\u016bj",
    "gn:population":0,
    "gn:timezone":"Asia/Aden",
    "iso:country":"YE",
    "name:ara_x_preferred":[
        "J\u016bj"
    ],
    "wof:name":"Juj",
    "wof:placetype":"locality"
},
  "geometry": {"coordinates":[44.47502,15.43555],"type":"Point"}
}