{
  "type": "Feature",
  "properties": {
    "gn:admin1_code":"19.0",
    "gn:admin2_code":"2907.0",
    "gn:asciiname":"Al Qurun",
    "gn:country_code":"YE",
    "gn:dem":1202,
    "gn:feature_class":"P",
    "gn:feature_code":"PPL",
    "gn:name":"Al Qur\u016bn",
    "gn:population":0,
    "gn:timezone":"Asia/Aden",
    "iso:country":"YE",
    "name:ara_x_preferred":[
        "Al Qur\u016bn"
    ],
    "wof:name":"Al Qurun",
    "wof:placetype":"locality"
},
  "geometry": {"coordinates":[43.61652,16.10438],"type":"Point"}
}