{
  "type": "Feature",
  "properties": {
    "gn:country":"YE",
    "gn:fcode":"PPL",
    "gn:population":3,
    "iso:country":"YE",
    "name:ara_x_preferred":[
        "\u0639\u0648\u0642 \u0627\u0644\u0639\u0644\u0627\u0645\u0629"
    ],
    "name:eng_x_preferred":[
        "Awaq Al 'Alamah"
    ],
    "name:eng_x_variant":[
        "'Awaq Al 'Alamah"
    ],
    "name:urd_x_preferred":[
        "\u0627\u0644\u0645\u0641\u062c\u0631"
    ],
    "qs:name":"\u2018Awaq al \u2018Al\u0101mah",
    "qs:photos_9r":0,
    "qs:photos_sr":0,
    "qs:pop_sr":"1",
    "wof:name":"\u2018Awaq al \u2018Al\u0101mah",
    "wof:placetype":"locality",
    "wof:population":3
},
  "geometry": {"coordinates":[43.43539,16.21588],"type":"Point"}
}