{
  "type": "Feature",
  "properties": {
    "gn:country":"YE",
    "gn:fcode":"PPL",
    "gn:pop":3,
    "iso:country":"YE",
    "name:ara_x_preferred":[
        "\u0630\u0631\u0627\u0639 \u0627\u0644\u062d\u0645\u0631\u0627\u0621"
    ],
    "name:eng_x_preferred":[
        "Dhira' Al Hamra"
    ],
    "qs:name":"Dhir\u0101\u2018 al \u1e28amr\u0101\u2019",
    "qs:photos_9r":0,
    "qs:photos_sr":0,
    "qs:pop_sr":"1",
    "wof:name":"Dhir\u0101\u2018 al \u1e28amr\u0101\u2019",
    "wof:placetype":"locality",
    "wof:population":3
},
  "geometry": {"coordinates":[43.44561,16.36123],"type":"Point"}
}