{
  "type": "Feature",
  "properties": {
    "gn:admin1_code":"25.0",
    "gn:admin2_code":"1501.0",
    "gn:asciiname":"Al Mitlah",
    "gn:country_code":"YE",
    "gn:dem":1382,
    "gn:feature_class":"P",
    "gn:feature_code":"PPL",
    "gn:name":"Al Mi\u0163l\u0101\u1e29",
    "gn:population":0,
    "gn:timezone":"Asia/Aden",
    "iso:country":"YE",
    "name:ara_x_preferred":[
        "Al Mi\u0163l\u0101\u1e29"
    ],
    "wof:name":"Al Mitlah",
    "wof:placetype":"locality"
},
  "geometry": {"coordinates":[44.18634,13.69856],"type":"Point"}
}