{
  "type": "Feature",
  "properties": {
    "gn:admin1_code":"21.0",
    "gn:admin2_code":"1606.0",
    "gn:asciiname":"Farsha",
    "gn:country_code":"YE",
    "gn:dem":1177,
    "gn:feature_class":"P",
    "gn:feature_code":"PPL",
    "gn:name":"Farsh\u0101",
    "gn:population":0,
    "gn:timezone":"Asia/Aden",
    "iso:country":"YE",
    "name:ara_x_preferred":[
        "\u0641\u0631\u0634\u0627"
    ],
    "name:und_x_variant":[
        "Farsh\u0101\u2019",
        "Farsh\u0101"
    ],
    "wof:name":"Farsha",
    "wof:placetype":"locality"
},
  "geometry": {"coordinates":[44.54374,16.25629],"type":"Point"}
}