{
  "type": "Feature",
  "properties": {
    "gn:gn_country":"YE",
    "gn:gn_fcode":"PPL",
    "gn:gn_pop":80,
    "gn:population":80,
    "iso:country":"YE",
    "name:ara_x_preferred":[
        "\u0627\u0644\u0628\u0644\u0627\u062f \u0627\u0644\u0641\u0648\u0642\u064a\u0629"
    ],
    "name:eng_x_preferred":[
        "Al Balad Al Fawqiyah"
    ],
    "qs_pg:aaroncc":"YE",
    "qs_pg:gn_country":"YE",
    "qs_pg:gn_fcode":"PPL",
    "qs_pg:gn_pop":80,
    "qs_pg:name":"Al Bal\u0101d al Fawq\u012byah",
    "qs_pg:photos_9r":0,
    "qs_pg:photos_sr":0,
    "qs_pg:pop_sr":1,
    "qs_pg:qs_pg_placetype":"locality",
    "wof:name":"Al Bal\u0101d al Fawq\u012byah",
    "wof:placetype":"locality",
    "wof:population":80
},
  "geometry": {"coordinates":[51.2018,15.2123],"type":"Point"}
}