{
  "type": "Feature",
  "properties": {
    "gn:admin1_code":"22.0",
    "gn:admin2_code":"1729.0",
    "gn:asciiname":"Ash Sharqi",
    "gn:country_code":"YE",
    "gn:dem":1504,
    "gn:feature_class":"P",
    "gn:feature_code":"PPL",
    "gn:name":"Ash Sharq\u012b",
    "gn:population":0,
    "gn:timezone":"Asia/Aden",
    "iso:country":"YE",
    "name:und_x_variant":[
        "Ash Sharq\u012b"
    ],
    "wof:name":"Ash Sharqi",
    "wof:placetype":"locality"
},
  "geometry": {"coordinates":[43.60486,15.63433],"type":"Point"}
}