{
  "type": "Feature",
  "properties": {
    "gn:country":"YE",
    "gn:fcode":"PPL",
    "gn:pop":11,
    "iso:country":"YE",
    "name:ara_x_preferred":[
        "As Sirw\u0101\u1e29"
    ],
    "name:ara_x_variant":[
        "\u0627\u0644\u0633\u0631\u0648\u0627\u062d"
    ],
    "name:eng_x_preferred":[
        "As Sirwah"
    ],
    "name:eng_x_variant":[
        "\u2018Am\u0101rah"
    ],
    "qs:name":"As Sirw\u0101\u1e29",
    "qs:photos_9r":0,
    "qs:photos_sr":0,
    "qs:pop_sr":"1",
    "wof:name":"As Sirw\u0101\u1e29",
    "wof:placetype":"locality",
    "wof:population":11
},
  "geometry": {"coordinates":[44.07459,16.99008],"type":"Point"}
}