{
  "type": "Feature",
  "properties": {
    "gn:country":"YE",
    "gn:fcode":"PPL",
    "gn:pop":18,
    "iso:country":"YE",
    "name:ara_x_preferred":[
        "\u0643\u0646\u064a\u0629"
    ],
    "qs:name":"Kun\u012byah",
    "qs:photos_9r":0,
    "qs:photos_sr":0,
    "qs:pop_sr":"1",
    "wof:name":"Kun\u012byah",
    "wof:placetype":"locality",
    "wof:population":18
},
  "geometry": {"coordinates":[43.29154,16.88549],"type":"Point"}
}