{
  "type": "Feature",
  "properties": {
    "gn:admin1_code":"23.0",
    "gn:admin2_code":"1107.0",
    "gn:asciiname":"Al Mishamas",
    "gn:country_code":"YE",
    "gn:dem":1835,
    "gn:feature_class":"P",
    "gn:feature_code":"PPL",
    "gn:name":"Al Misham\u0101s",
    "gn:population":0,
    "gn:timezone":"Asia/Aden",
    "iso:country":"YE",
    "name:und_x_variant":[
        "Al Misham\u0101s"
    ],
    "wof:name":"Al Mishamas",
    "wof:placetype":"locality"
},
  "geometry": {"coordinates":[44.23661,14.22151],"type":"Point"}
}