{
  "type": "Feature",
  "properties": {
    "gn:country":"YE",
    "gn:fcode":"PPL",
    "gn:pop":2,
    "iso:country":"YE",
    "name:ara_x_preferred":[
        "\u0627\u0644\u062d\u0632\u0628\u0629"
    ],
    "name:eng_x_preferred":[
        "Al Hizbah"
    ],
    "name:eng_x_variant":[
        "Kawlat al Qad\u016b\u1e29ah"
    ],
    "qs:name":"Al \u1e28izbah",
    "qs:photos_9r":0,
    "qs:photos_sr":0,
    "qs:pop_sr":"1",
    "wof:name":"Al \u1e28izbah",
    "wof:placetype":"locality",
    "wof:population":2
},
  "geometry": {"coordinates":[45.43399,14.41382],"type":"Point"}
}