{
  "type": "Feature",
  "properties": {
    "gn:admin1_code":"23.0",
    "gn:admin2_code":"1117.0",
    "gn:asciiname":"Al Hujum",
    "gn:country_code":"YE",
    "gn:dem":2225,
    "gn:feature_class":"P",
    "gn:feature_code":"PPL",
    "gn:name":"Al Hujum",
    "gn:population":0,
    "gn:timezone":"Asia/Aden",
    "iso:country":"YE",
    "wof:name":"Al Hujum",
    "wof:placetype":"locality"
},
  "geometry": {"coordinates":[43.9535,13.87384],"type":"Point"}
}