{
  "type": "Feature",
  "properties": {
    "gn:admin1_code":"1.0",
    "gn:admin2_code":"1211.0",
    "gn:asciiname":"Al Makhzan al Fawqi",
    "gn:country_code":"YE",
    "gn:dem":51,
    "gn:feature_class":"P",
    "gn:feature_code":"PPL",
    "gn:name":"Al Makhzan al Fawq\u012b",
    "gn:population":0,
    "gn:timezone":"Asia/Aden",
    "iso:country":"YE",
    "name:nno_x_preferred":[
        "Al Makhzan Al Fawqi"
    ],
    "name:und_x_variant":[
        "Al Makhzan al Fawq\u012b"
    ],
    "wof:name":"Al Makhzan al Fawqi",
    "wof:placetype":"locality"
},
  "geometry": {"coordinates":[45.31556,13.19083],"type":"Point"}
}