{
  "type": "Feature",
  "properties": {
    "gn:admin1_code":"14.0",
    "gn:admin2_code":"2607.0",
    "gn:asciiname":"Al Washha",
    "gn:country_code":"YE",
    "gn:dem":1172,
    "gn:feature_class":"P",
    "gn:feature_code":"PPL",
    "gn:name":"Al Wash\u1e29\u0101",
    "gn:population":0,
    "gn:timezone":"Asia/Aden",
    "iso:country":"YE",
    "name:ara_x_preferred":[
        "\u0627\u0644\u0648\u0634\u062d\u0627"
    ],
    "name:und_x_variant":[
        "Al Wash\u1e29\u0101"
    ],
    "wof:name":"Al Washha",
    "wof:placetype":"locality"
},
  "geometry": {"coordinates":[45.25264,15.26178],"type":"Point"}
}