{
  "type": "Feature",
  "properties": {
    "gn:admin1_code":"11.0",
    "gn:admin2_code":"2006.0",
    "gn:asciiname":"Suq Shafrah",
    "gn:country_code":"YE",
    "gn:dem":1517,
    "gn:feature_class":"P",
    "gn:feature_code":"PPL",
    "gn:name":"S\u016bq Shafrah",
    "gn:population":0,
    "gn:timezone":"Asia/Aden",
    "iso:country":"YE",
    "name:und_x_variant":[
        "S\u016bq Shafrah"
    ],
    "wof:name":"Suq Shafrah",
    "wof:placetype":"locality"
},
  "geometry": {"coordinates":[43.85076,14.29131],"type":"Point"}
}