{
  "type": "Feature",
  "properties": {
    "gn:admin1_code":"11.0",
    "gn:admin2_code":"2004.0",
    "gn:asciiname":"Sidd",
    "gn:country_code":"YE",
    "gn:dem":2679,
    "gn:feature_class":"P",
    "gn:feature_code":"PPL",
    "gn:name":"Sidd",
    "gn:population":0,
    "gn:timezone":"Asia/Aden",
    "iso:country":"YE",
    "wof:name":"Sidd",
    "wof:placetype":"locality"
},
  "geometry": {"coordinates":[44.12316,14.50962],"type":"Point"}
}