{
  "type": "Feature",
  "properties": {
    "gn:admin1_code":"19.0",
    "gn:admin2_code":"2903.0",
    "gn:asciiname":"Mahfinah",
    "gn:country_code":"YE",
    "gn:dem":1406,
    "gn:feature_class":"P",
    "gn:feature_code":"PPL",
    "gn:name":"Ma\u1e29finah",
    "gn:population":0,
    "gn:timezone":"Asia/Aden",
    "iso:country":"YE",
    "name:und_x_variant":[
        "Ma\u1e29finah"
    ],
    "wof:name":"Mahfinah",
    "wof:placetype":"locality"
},
  "geometry": {"coordinates":[43.76321,16.40591],"type":"Point"}
}