{
  "type": "Feature",
  "properties": {
    "gn:admin1_code":"8.0",
    "gn:admin2_code":"1812.0",
    "gn:asciiname":"Wadi Shuraym",
    "gn:country_code":"YE",
    "gn:dem":512,
    "gn:feature_class":"P",
    "gn:feature_code":"PPL",
    "gn:name":"W\u0101d\u012b Shuraym",
    "gn:population":0,
    "gn:timezone":"Asia/Aden",
    "iso:country":"YE",
    "name:ara_x_preferred":[
        "\u0648\u0627\u062f\u064a \u0634\u0631\u064a\u0645"
    ],
    "name:und_x_variant":[
        "W\u0101d\u012b Shuraym"
    ],
    "wof:name":"Wadi Shuraym",
    "wof:placetype":"locality"
},
  "geometry": {"coordinates":[43.44184,14.93547],"type":"Point"}
}