{
  "type": "Feature",
  "properties": {
    "gn:country":"YE",
    "gn:fcode":"PPL",
    "gn:population":7,
    "iso:country":"YE",
    "name:ara_x_preferred":[
        "\u0627\u0644\u0631\u062d\u0627\u0628 \u0627\u0644\u0633\u0641\u0644\u0649"
    ],
    "name:eng_x_preferred":[
        "Ar Rahab As Sufla"
    ],
    "name:eng_x_variant":[
        "Al Bas\u012b\u0163"
    ],
    "qs:name":"Ar Ra\u1e29\u0101b as Sufl\u00e1",
    "qs:photos_9r":0,
    "qs:photos_sr":0,
    "qs:pop_sr":"1",
    "wof:name":"Ar Ra\u1e29\u0101b as Sufl\u00e1",
    "wof:placetype":"locality",
    "wof:population":7
},
  "geometry": {"coordinates":[44.19338,16.89612],"type":"Point"}
}