{
  "type": "Feature",
  "properties": {
    "gn:country":"YE",
    "gn:fcode":"PPLF",
    "gn:population":2,
    "iso:country":"YE",
    "name:ara_x_preferred":[
        "\u0648\u0639\u064a\u0644"
    ],
    "name:eng_x_preferred":[
        "Wa'il"
    ],
    "qs:name":"Wa\u2018\u012bl",
    "qs:photos_9r":0,
    "qs:photos_sr":0,
    "qs:pop_sr":"1",
    "wof:name":"Wa\u2018\u012bl",
    "wof:placetype":"locality",
    "wof:population":2
},
  "geometry": {"coordinates":[43.73177,16.32131],"type":"Point"}
}