{
  "type": "Feature",
  "properties": {
    "gn:admin1_code":"20.0",
    "gn:asciiname":"Qism `Umar",
    "gn:country_code":"YE",
    "gn:dem":2451,
    "gn:feature_class":"P",
    "gn:feature_code":"PPL",
    "gn:name":"Qism \u2018Umar",
    "gn:population":0,
    "gn:timezone":"Asia/Aden",
    "iso:country":"YE",
    "name:ara_x_preferred":[
        "\u0642\u0633\u0645 \u0639\u0645\u0631"
    ],
    "name:und_x_variant":[
        "Qism \u2018Umar"
    ],
    "wof:name":"Qism `Umar",
    "wof:placetype":"locality"
},
  "geometry": {"coordinates":[44.36556,14.44723],"type":"Point"}
}