{
  "type": "Feature",
  "properties": {
    "gn:country":"YE",
    "gn:fcode":"PPLL",
    "gn:pop":21,
    "iso:country":"YE",
    "name:ara_x_preferred":[
        "Misq\u0101m"
    ],
    "name:ara_x_variant":[
        "\u0645\u0633\u0642\u0627\u0645"
    ],
    "name:eng_x_preferred":[
        "Misqam"
    ],
    "qs:name":"Misq\u0101m",
    "qs:photos_9r":0,
    "qs:photos_sr":0,
    "qs:pop_sr":"1",
    "wof:name":"Misq\u0101m",
    "wof:placetype":"locality",
    "wof:population":21
},
  "geometry": {"coordinates":[43.54005,17.33316],"type":"Point"}
}