{
  "type": "Feature",
  "properties": {
    "gn:country":"YE",
    "gn:fcode":"PPL",
    "gn:pop":3,
    "iso:country":"YE",
    "name:ara_x_preferred":[
        "\u0639\u0637\u064a\u0641\u0629"
    ],
    "name:eng_x_preferred":[
        "Utayfah"
    ],
    "qs:name":"\u2018U\u0163ayfah",
    "qs:photos_9r":0,
    "qs:photos_sr":0,
    "qs:pop_sr":"1",
    "wof:name":"\u2018U\u0163ayfah",
    "wof:placetype":"locality",
    "wof:population":3
},
  "geometry": {"coordinates":[45.07417,14.99977],"type":"Point"}
}