{
  "type": "Feature",
  "properties": {
    "gn:country":"YE",
    "gn:fcode":"PPL",
    "gn:population":11,
    "iso:country":"YE",
    "name:ara_x_preferred":[
        "\u0627\u0644\u0646\u0648\u0628\u0629"
    ],
    "name:eng_x_preferred":[
        "An Nawbah"
    ],
    "name:eng_x_variant":[
        "Al \u2018Akrimah"
    ],
    "qs:name":"An Nawbah",
    "qs:photos_9r":0,
    "qs:photos_sr":0,
    "qs:pop_sr":"1",
    "wof:name":"An Nawbah",
    "wof:placetype":"locality",
    "wof:population":11
},
  "geometry": {"coordinates":[43.84658,13.33989],"type":"Point"}
}