{
  "type": "Feature",
  "properties": {
    "gn:admin1_code":"16.0",
    "gn:admin2_code":"2308.0",
    "gn:asciiname":"Quramish",
    "gn:country_code":"YE",
    "gn:dem":1661,
    "gn:feature_class":"P",
    "gn:feature_code":"PPL",
    "gn:name":"Qur\u0101mish",
    "gn:population":0,
    "gn:timezone":"Asia/Aden",
    "iso:country":"YE",
    "name:ara_x_preferred":[
        "Qur\u0101mish"
    ],
    "wof:name":"Quramish",
    "wof:placetype":"locality"
},
  "geometry": {"coordinates":[43.87307,15.27373],"type":"Point"}
}