{
  "type": "Feature",
  "properties": {
    "gn:admin1_code":"10.0",
    "gn:admin2_code":"2704.0",
    "gn:asciiname":"Mahall Aza`",
    "gn:country_code":"YE",
    "gn:dem":808,
    "gn:feature_class":"P",
    "gn:feature_code":"PPL",
    "gn:name":"Ma\u1e29all Aza\u2018",
    "gn:population":0,
    "gn:timezone":"Asia/Aden",
    "iso:country":"YE",
    "name:und_x_variant":[
        "Ma\u1e29all Aza\u2018"
    ],
    "wof:name":"Mahall Aza`",
    "wof:placetype":"locality"
},
  "geometry": {"coordinates":[43.28404000000001,15.5032],"type":"Point"}
}