{
  "type": "Feature",
  "properties": {
    "gn:admin1_code":"15.0",
    "gn:admin2_code":"2203.0",
    "gn:asciiname":"Al Jahadi",
    "gn:country_code":"YE",
    "gn:dem":1761,
    "gn:feature_class":"P",
    "gn:feature_code":"PPL",
    "gn:name":"Al Ja\u1e29ad\u012b",
    "gn:population":0,
    "gn:timezone":"Asia/Aden",
    "iso:country":"YE",
    "name:ara_x_preferred":[
        "\u0627\u0644\u062c\u062d\u062f\u064a"
    ],
    "name:und_x_variant":[
        "Al Ja\u1e29ad\u012b",
        "Jahd\u012b"
    ],
    "wof:name":"Al Jahadi",
    "wof:placetype":"locality"
},
  "geometry": {"coordinates":[43.26596,17.17773],"type":"Point"}
}