{
  "type": "Feature",
  "properties": {
    "gn:admin1_code":"23.0",
    "gn:admin2_code":"1101.0",
    "gn:asciiname":"Kawlat al Burta",
    "gn:country_code":"YE",
    "gn:dem":1338,
    "gn:feature_class":"P",
    "gn:feature_code":"PPL",
    "gn:name":"Kawlat al Bur\u0163\u00e1",
    "gn:population":0,
    "gn:timezone":"Asia/Aden",
    "iso:country":"YE",
    "name:ara_x_preferred":[
        "\u0643\u0648\u0644\u0629 \u0627\u0644\u0628\u0631\u0637\u0649"
    ],
    "name:und_x_variant":[
        "Kawlat al Bur\u0163\u00e1"
    ],
    "wof:name":"Kawlat al Burta",
    "wof:placetype":"locality"
},
  "geometry": {"coordinates":[44.10571,14.31563],"type":"Point"}
}