{
  "type": "Feature",
  "properties": {
    "gn:admin1_code":"18.0",
    "gn:admin2_code":"3005.0",
    "gn:asciiname":"Dar Hasir",
    "gn:country_code":"YE",
    "gn:dem":1516,
    "gn:feature_class":"P",
    "gn:feature_code":"PPL",
    "gn:name":"D\u0101r Hasir",
    "gn:population":0,
    "gn:timezone":"Asia/Aden",
    "iso:country":"YE",
    "name:und_x_variant":[
        "D\u0101r Hasir"
    ],
    "wof:name":"Dar Hasir",
    "wof:placetype":"locality"
},
  "geometry": {"coordinates":[44.80532,13.74667],"type":"Point"}
}