{
  "type": "Feature",
  "properties": {
    "gn:admin1_code":"19.0",
    "gn:admin2_code":"2904.0",
    "gn:asciiname":"Az Ziyadiyah",
    "gn:country_code":"YE",
    "gn:dem":1274,
    "gn:feature_class":"P",
    "gn:feature_code":"PPL",
    "gn:name":"Az Ziy\u0101d\u012byah",
    "gn:population":0,
    "gn:timezone":"Asia/Aden",
    "iso:country":"YE",
    "name:ara_x_preferred":[
        "\u0627\u0644\u0632\u064a\u0627\u062f\u064a\u0629"
    ],
    "name:und_x_variant":[
        "Az Ziy\u0101d\u012byah"
    ],
    "wof:name":"Az Ziyadiyah",
    "wof:placetype":"locality"
},
  "geometry": {"coordinates":[43.78424,16.22324],"type":"Point"}
}