{
  "type": "Feature",
  "properties": {
    "gn:country":"YE",
    "gn:fcode":"PPL",
    "gn:pop":2,
    "iso:country":"YE",
    "name:ara_x_preferred":[
        "\u0642\u0632\u0639\u0629 \u0647\u0627\u062f\u064a"
    ],
    "name:eng_x_preferred":[
        "Qaz'at Hadi"
    ],
    "name:eng_x_variant":[
        "Al Fuqar\u0101\u2019"
    ],
    "qs:name":"Qaz\u2018at H\u0101d\u012b",
    "qs:photos_9r":0,
    "qs:photos_sr":0,
    "qs:pop_sr":"1",
    "wof:name":"Qaz\u2018at H\u0101d\u012b",
    "wof:placetype":"locality",
    "wof:population":2
},
  "geometry": {"coordinates":[45.54674,15.03965],"type":"Point"}
}