{
  "type": "Feature",
  "properties": {
    "gn:admin1_code":"23.0",
    "gn:admin2_code":"1110.0",
    "gn:asciiname":"Ar Ruwaynah",
    "gn:country_code":"YE",
    "gn:dem":518,
    "gn:feature_class":"P",
    "gn:feature_code":"PPL",
    "gn:name":"Ar Ruwaynah",
    "gn:population":0,
    "gn:timezone":"Asia/Aden",
    "iso:country":"YE",
    "wof:name":"Ar Ruwaynah",
    "wof:placetype":"locality"
},
  "geometry": {"coordinates":[43.67593,13.90625],"type":"Point"}
}