{
  "type": "Feature",
  "properties": {
    "gn:admin1_code":"4.0",
    "gn:admin2_code":"1922.0",
    "gn:asciiname":"Al Marr",
    "gn:country_code":"YE",
    "gn:dem":1442,
    "gn:feature_class":"P",
    "gn:feature_code":"PPL",
    "gn:name":"Al Marr",
    "gn:population":0,
    "gn:timezone":"Asia/Aden",
    "iso:country":"YE",
    "wof:name":"Al Marr",
    "wof:placetype":"locality"
},
  "geometry": {"coordinates":[47.81667,15.03333],"type":"Point"}
}