{
  "type": "Feature",
  "properties": {
    "gn:admin1_code":"14.0",
    "gn:admin2_code":"2608.0",
    "gn:asciiname":"Hujayrah",
    "gn:country_code":"YE",
    "gn:dem":1762,
    "gn:feature_class":"P",
    "gn:feature_code":"PPL",
    "gn:name":"Hujayrah",
    "gn:population":0,
    "gn:timezone":"Asia/Aden",
    "iso:country":"YE",
    "name:ara_x_preferred":[
        "\u0647\u062c\u064a\u0631\u0629"
    ],
    "wof:name":"Hujayrah",
    "wof:placetype":"locality"
},
  "geometry": {"coordinates":[45.17788,14.96671],"type":"Point"}
}