{
  "type": "Feature",
  "properties": {
    "gn:admin1_code":"22.0",
    "gn:admin2_code":"1707.0",
    "gn:asciiname":"Al Gharib",
    "gn:country_code":"YE",
    "gn:dem":1353,
    "gn:feature_class":"P",
    "gn:feature_code":"PPL",
    "gn:name":"Al Gh\u0101rib",
    "gn:population":8,
    "gn:timezone":"Asia/Aden",
    "iso:country":"YE",
    "name:ara_x_preferred":[
        "Al Gh\u0101rib"
    ],
    "name:ara_x_variant":[
        "\u0627\u0644\u063a\u0627\u0631\u0628"
    ],
    "wof:name":"Al Gharib",
    "wof:placetype":"locality",
    "wof:population":8
},
  "geometry": {"coordinates":[43.45022,16.18434],"type":"Point"}
}