{
  "type": "Feature",
  "properties": {
    "gn:admin1_code":"18.0",
    "gn:admin2_code":"3002.0",
    "gn:asciiname":"As Sayh",
    "gn:country_code":"YE",
    "gn:dem":2327,
    "gn:feature_class":"P",
    "gn:feature_code":"PPL",
    "gn:name":"A\u015f \u015eay\u1e29",
    "gn:population":0,
    "gn:timezone":"Asia/Aden",
    "iso:country":"YE",
    "name:und_x_variant":[
        "A\u015f \u015eay\u1e29"
    ],
    "wof:name":"As Sayh",
    "wof:placetype":"locality"
},
  "geometry": {"coordinates":[44.76079,14.2028],"type":"Point"}
}