{
  "type": "Feature",
  "properties": {
    "gn:admin1_code":"25.0",
    "gn:admin2_code":"1504.0",
    "gn:asciiname":"Shi`b Ghazi",
    "gn:country_code":"YE",
    "gn:dem":1042,
    "gn:feature_class":"P",
    "gn:feature_code":"PPL",
    "gn:name":"Shi\u2018b Gh\u0101z\u012b",
    "gn:population":0,
    "gn:timezone":"Asia/Aden",
    "iso:country":"YE",
    "name:ara_x_preferred":[
        "Shi\u2018b Gh\u0101z\u012b"
    ],
    "name:ara_x_variant":[
        "\u0634\u0639\u0628 \u063a\u0627\u0632\u064a"
    ],
    "wof:name":"Shi`b Ghazi",
    "wof:placetype":"locality"
},
  "geometry": {"coordinates":[43.85978,13.60294],"type":"Point"}
}