{
  "type": "Feature",
  "properties": {
    "gn:admin1_code":"16.0",
    "gn:admin2_code":"2312.0",
    "gn:asciiname":"Bayt al Ghasham",
    "gn:country_code":"YE",
    "gn:dem":2259,
    "gn:feature_class":"P",
    "gn:feature_code":"PPLL",
    "gn:name":"Bayt al Ghasham",
    "gn:population":0,
    "gn:timezone":"Asia/Aden",
    "iso:country":"YE",
    "name:ara_x_preferred":[
        "\u0628\u064a\u062a \u0627\u0644\u063a\u0634\u0645"
    ],
    "wof:name":"Bayt al Ghasham",
    "wof:placetype":"locality"
},
  "geometry": {"coordinates":[44.68137,15.33181],"type":"Point"}
}