{
  "type": "Feature",
  "properties": {
    "gn:admin1_code":"15.0",
    "gn:admin2_code":"2209.0",
    "gn:asciiname":"Alt Za'id",
    "gn:country_code":"YE",
    "gn:dem":2226,
    "gn:feature_class":"P",
    "gn:feature_code":"PPL",
    "gn:name":"Alt Z\u0101\u2019id",
    "gn:population":0,
    "gn:timezone":"Asia/Aden",
    "iso:country":"YE",
    "name:ara_x_preferred":[
        "Alt Z\u0101\u2019id"
    ],
    "wof:name":"Alt Za'id",
    "wof:placetype":"locality"
},
  "geometry": {"coordinates":[43.57403,16.92013],"type":"Point"}
}