{
  "type": "Feature",
  "properties": {
    "gn:country":"YE",
    "gn:fcode":"PPL",
    "gn:pop":2,
    "iso:country":"YE",
    "name:ara_x_preferred":[
        "\u0627\u0644\u062d\u0648\u062c"
    ],
    "name:eng_x_preferred":[
        "Al Hawj"
    ],
    "name:eng_x_variant":[
        "Al \u1e28i\u015fn"
    ],
    "qs:name":"Al \u1e28awj",
    "qs:photos_9r":0,
    "qs:photos_sr":0,
    "qs:pop_sr":"1",
    "wof:name":"Al \u1e28awj",
    "wof:placetype":"locality",
    "wof:population":2
},
  "geometry": {"coordinates":[43.94588,13.12588],"type":"Point"}
}