{
  "type": "Feature",
  "properties": {
    "gn:gn_country":"YE",
    "gn:gn_fcode":"PPLL",
    "gn:gn_pop":5,
    "gn:population":5,
    "iso:country":"YE",
    "name:ara_x_preferred":[
        "\u0628\u064a\u0646 \u0639\u062c\u0645\u0629"
    ],
    "name:eng_x_preferred":[
        "Bayn 'Ujmah"
    ],
    "qs_pg:aaroncc":"YE",
    "qs_pg:gn_country":"YE",
    "qs_pg:gn_fcode":"PPLL",
    "qs_pg:gn_pop":5,
    "qs_pg:name":"Bayn \u2018Ujmah",
    "qs_pg:photos_9r":0,
    "qs_pg:photos_sr":0,
    "qs_pg:pop_sr":1,
    "qs_pg:qs_pg_placetype":"locality",
    "wof:name":"Bayn \u2018Ujmah",
    "wof:placetype":"locality",
    "wof:population":5
},
  "geometry": {"coordinates":[43.33788,16.97608],"type":"Point"}
}