{
  "type": "Feature",
  "properties": {
    "gn:admin1_code":"24.0",
    "gn:admin2_code":"2513.0",
    "gn:asciiname":"Harbi",
    "gn:country_code":"YE",
    "gn:dem":256,
    "gn:feature_class":"P",
    "gn:feature_code":"PPL",
    "gn:name":"\u1e28arb\u012b",
    "gn:population":0,
    "gn:timezone":"Asia/Aden",
    "iso:country":"YE",
    "name:und_x_variant":[
        "\u1e28arb\u012b"
    ],
    "wof:name":"Harbi",
    "wof:placetype":"locality"
},
  "geometry": {"coordinates":[43.97438,12.88564],"type":"Point"}
}