{
  "type": "Feature",
  "properties": {
    "gn:admin1_code":"8.0",
    "gn:admin2_code":"1824.0",
    "gn:asciiname":"Az Zawiyah",
    "gn:country_code":"YE",
    "gn:dem":64,
    "gn:feature_class":"P",
    "gn:feature_code":"PPL",
    "gn:name":"Az Z\u0101wiyah",
    "gn:population":0,
    "gn:timezone":"Asia/Aden",
    "iso:country":"YE",
    "name:und_x_variant":[
        "Az Z\u0101wiyah"
    ],
    "wof:name":"Az Zawiyah",
    "wof:placetype":"locality"
},
  "geometry": {"coordinates":[43.22257000000001,14.26782],"type":"Point"}
}