{
  "type": "Feature",
  "properties": {
    "gn:admin1_code":"18.0",
    "gn:admin2_code":"3007.0",
    "gn:asciiname":"Muwabah",
    "gn:country_code":"YE",
    "gn:dem":2284,
    "gn:feature_class":"P",
    "gn:feature_code":"PPL",
    "gn:name":"Muwabah",
    "gn:population":0,
    "gn:timezone":"Asia/Aden",
    "iso:country":"YE",
    "wof:name":"Muwabah",
    "wof:placetype":"locality"
},
  "geometry": {"coordinates":[44.67816,13.74661],"type":"Point"}
}