{
  "type": "Feature",
  "properties": {
    "gn:admin1_code":"22.0",
    "gn:admin2_code":"1725.0",
    "gn:asciiname":"Al Qishamah",
    "gn:country_code":"YE",
    "gn:dem":950,
    "gn:feature_class":"P",
    "gn:feature_code":"PPL",
    "gn:name":"Al Qish\u0101mah",
    "gn:population":0,
    "gn:timezone":"Asia/Aden",
    "iso:country":"YE",
    "name:und_x_variant":[
        "Al Qish\u0101mah"
    ],
    "wof:name":"Al Qishamah",
    "wof:placetype":"locality"
},
  "geometry": {"coordinates":[43.50973,15.61638],"type":"Point"}
}