{
  "type": "Feature",
  "properties": {
    "gn:admin1_code":"23.0",
    "gn:admin2_code":"1111.0",
    "gn:asciiname":"Al Hafah",
    "gn:country_code":"YE",
    "gn:dem":1628,
    "gn:feature_class":"P",
    "gn:feature_code":"PPL",
    "gn:name":"Al \u1e28\u0101fah",
    "gn:population":0,
    "gn:timezone":"Asia/Aden",
    "iso:country":"YE",
    "name:ara_x_preferred":[
        "\u0627\u0644\u062d\u0627\u0641\u0629"
    ],
    "name:und_x_variant":[
        "Al \u1e28\u0101fah",
        "Al \u1e28\u0101ffah"
    ],
    "wof:name":"Al Hafah",
    "wof:placetype":"locality"
},
  "geometry": {"coordinates":[43.87075,13.88866],"type":"Point"}
}