{
  "type": "Feature",
  "properties": {
    "gn:admin1_code":"22.0",
    "gn:admin2_code":"1720.0",
    "gn:asciiname":"Suq ad Dam",
    "gn:country_code":"YE",
    "gn:dem":929,
    "gn:feature_class":"P",
    "gn:feature_code":"PPL",
    "gn:name":"S\u016bq ad D\u0101m",
    "gn:population":0,
    "gn:timezone":"Asia/Aden",
    "iso:country":"YE",
    "name:und_x_variant":[
        "S\u016bq ad D\u0101m"
    ],
    "wof:name":"Suq ad Dam",
    "wof:placetype":"locality"
},
  "geometry": {"coordinates":[43.53536,15.7286],"type":"Point"}
}