{
  "type": "Feature",
  "properties": {
    "gn:admin1_code":"14.0",
    "gn:admin2_code":"2606.0",
    "gn:asciiname":"Al Hasram",
    "gn:country_code":"YE",
    "gn:dem":1510,
    "gn:feature_class":"P",
    "gn:feature_code":"PPL",
    "gn:name":"Al \u1e28a\u015fram",
    "gn:population":0,
    "gn:timezone":"Asia/Aden",
    "iso:country":"YE",
    "name:ara_x_preferred":[
        "\u0627\u0644\u062d\u0635\u0631\u0645"
    ],
    "name:und_x_variant":[
        "Al \u1e28a\u015fram"
    ],
    "wof:name":"Al Hasram",
    "wof:placetype":"locality"
},
  "geometry": {"coordinates":[44.92498,15.44036],"type":"Point"}
}