{
  "type": "Feature",
  "properties": {
    "gn:admin1_code":"23.0",
    "gn:admin2_code":"1105.0",
    "gn:asciiname":"Dhi Nasir",
    "gn:country_code":"YE",
    "gn:dem":2173,
    "gn:feature_class":"P",
    "gn:feature_code":"PPL",
    "gn:name":"Dh\u012b N\u0101\u015fir",
    "gn:population":0,
    "gn:timezone":"Asia/Aden",
    "iso:country":"YE",
    "name:ara_x_preferred":[
        "Dh\u012b N\u0101\u015fir"
    ],
    "wof:name":"Dhi Nasir",
    "wof:placetype":"locality"
},
  "geometry": {"coordinates":[44.35873,13.98976],"type":"Point"}
}