{
  "type": "Feature",
  "properties": {
    "gn:admin1_code":"5.0",
    "gn:admin2_code":"2103.0",
    "gn:asciiname":"Ar Rabasah",
    "gn:country_code":"YE",
    "gn:dem":1233,
    "gn:feature_class":"P",
    "gn:feature_code":"PPL",
    "gn:name":"Ar Rabasah",
    "gn:population":0,
    "gn:timezone":"Asia/Aden",
    "iso:country":"YE",
    "name:und_x_variant":[
        "Al Rabasah",
        "Ar Rabasah"
    ],
    "wof:name":"Ar Rabasah",
    "wof:placetype":"locality"
},
  "geometry": {"coordinates":[47.19665,14.83879],"type":"Point"}
}