{
  "type": "Feature",
  "properties": {
    "gn:admin1_code":"11.0",
    "gn:admin2_code":"2011.0",
    "gn:asciiname":"Al Buraykah",
    "gn:country_code":"YE",
    "gn:dem":2348,
    "gn:feature_class":"P",
    "gn:feature_code":"PPL",
    "gn:name":"Al Buraykah",
    "gn:population":0,
    "gn:timezone":"Asia/Aden",
    "iso:country":"YE",
    "wof:name":"Al Buraykah",
    "wof:placetype":"locality"
},
  "geometry": {"coordinates":[44.10787,14.82668],"type":"Point"}
}