{
  "type": "Feature",
  "properties": {
    "gn:admin1_code":"11.0",
    "gn:admin2_code":"2011.0",
    "gn:asciiname":"Al Buraykah",
    "gn:country_code":"YE",
    "gn:dem":2348,
    "gn:feature_class":"P",
    "gn:feature_code":"PPL",
    "gn:name":"Al Buraykah",
    "gn:population":0,
    "gn:timezone":"Asia/Aden",
    "iso:country":"YE",
    "name:fas_x_preferred":[
        "\u0627\u0644\u0628\u0648\u0631\u06cc\u06a9\u0647"
    ],
    "name:nno_x_preferred":[
        "Al Buraykah"
    ],
    "wof:name":"Al Buraykah",
    "wof:placetype":"locality"
},
  "geometry": {"coordinates":[44.10787,14.82668],"type":"Point"}
}