{
  "type": "Feature",
  "properties": {
    "gn:admin1_code":"16.0",
    "gn:admin2_code":"2303.0",
    "gn:asciiname":"Khamis Namlah",
    "gn:country_code":"YE",
    "gn:dem":1526,
    "gn:feature_class":"P",
    "gn:feature_code":"PPL",
    "gn:name":"Kham\u012bs Namlah",
    "gn:population":0,
    "gn:timezone":"Asia/Aden",
    "iso:country":"YE",
    "name:ara_x_preferred":[
        "\u062e\u0645\u064a\u0633 \u0646\u0645\u0644\u0629"
    ],
    "name:und_x_variant":[
        "Kham\u012bs Namlah"
    ],
    "wof:name":"Khamis Namlah",
    "wof:placetype":"locality"
},
  "geometry": {"coordinates":[44.70156,15.59077],"type":"Point"}
}