{
  "type": "Feature",
  "properties": {
    "gn:country":"YE",
    "gn:fcode":"PPL",
    "gn:population":9,
    "iso:country":"YE",
    "name:ara_x_preferred":[
        "\u0643\u0631\u0633 \u0627\u0644\u0647\u064a\u0627\u0634\u0629"
    ],
    "name:eng_x_preferred":[
        "Kurs Al Hiyashah"
    ],
    "name:eng_x_variant":[
        "\u1e28ab\u012bl ar Rakkib al Gharb\u012b"
    ],
    "qs:name":"Kurs al Hiy\u0101shah",
    "qs:photos_9r":0,
    "qs:photos_sr":0,
    "qs:pop_sr":"1",
    "wof:name":"Kurs al Hiy\u0101shah",
    "wof:placetype":"locality",
    "wof:population":9
},
  "geometry": {"coordinates":[43.16122,16.26323],"type":"Point"}
}