{
  "type": "Feature",
  "properties": {
    "gn:admin1_code":"18.0",
    "gn:admin2_code":"3006.0",
    "gn:asciiname":"Jaws al Jammal",
    "gn:country_code":"YE",
    "gn:dem":1273,
    "gn:feature_class":"P",
    "gn:feature_code":"PPL",
    "gn:name":"Jaws al Jamm\u0101l",
    "gn:population":0,
    "gn:timezone":"Asia/Aden",
    "iso:country":"YE",
    "name:und_x_variant":[
        "Jaws al Jamm\u0101l",
        "Jawl al Jamm\u0101l"
    ],
    "wof:name":"Jaws al Jammal",
    "wof:placetype":"locality"
},
  "geometry": {"coordinates":[44.69116,13.82956],"type":"Point"}
}