{
  "type": "Feature",
  "properties": {
    "gn:admin1_code":"23.0",
    "gn:admin2_code":"1112.0",
    "gn:asciiname":"Mayadinah",
    "gn:country_code":"YE",
    "gn:dem":2729,
    "gn:feature_class":"P",
    "gn:feature_code":"PPL",
    "gn:name":"May\u0101dinah",
    "gn:population":0,
    "gn:timezone":"Asia/Aden",
    "iso:country":"YE",
    "name:und_x_variant":[
        "May\u0101dinah"
    ],
    "wof:name":"Mayadinah",
    "wof:placetype":"locality"
},
  "geometry": {"coordinates":[44.08558,13.87732],"type":"Point"}
}