{
  "type": "Feature",
  "properties": {
    "gn:admin1_code":"8.0",
    "gn:admin2_code":"1802.0",
    "gn:asciiname":"Al `Abbasiyah",
    "gn:country_code":"YE",
    "gn:dem":33,
    "gn:feature_class":"P",
    "gn:feature_code":"PPL",
    "gn:name":"Al \u2018Abb\u0101s\u012byah",
    "gn:population":0,
    "gn:timezone":"Asia/Aden",
    "iso:country":"YE",
    "name:und_x_variant":[
        "Al \u2018Abb\u0101s\u012byah"
    ],
    "wof:name":"Al `Abbasiyah",
    "wof:placetype":"locality"
},
  "geometry": {"coordinates":[42.88872,15.76697],"type":"Point"}
}