{
  "type": "Feature",
  "properties": {
    "gn:admin1_code":"14.0",
    "gn:admin2_code":"2613.0",
    "gn:asciiname":"Al Ma`ashar",
    "gn:country_code":"YE",
    "gn:dem":1076,
    "gn:feature_class":"P",
    "gn:feature_code":"PPL",
    "gn:name":"Al Ma\u2018\u0101sh\u0101r",
    "gn:population":0,
    "gn:timezone":"Asia/Aden",
    "iso:country":"YE",
    "name:ara_x_preferred":[
        "\u0627\u0644\u0645\u0639\u0627\u0634\u064a\u0631"
    ],
    "name:ara_x_variant":[
        "\u0627\u0644\u0645\u0639\u0634\u0627\u0631"
    ],
    "name:und_x_variant":[
        "Al Ma\u2018\u0101sh\u012br",
        "Al Ma\u2018\u0101sh\u0101r"
    ],
    "wof:name":"Al Ma`ashar",
    "wof:placetype":"locality"
},
  "geometry": {"coordinates":[45.39075,15.46336],"type":"Point"}
}