{
  "type": "Feature",
  "properties": {
    "gn:admin1_code":"19.0",
    "gn:admin2_code":"2912.0",
    "gn:asciiname":"Lughabah",
    "gn:country_code":"YE",
    "gn:dem":2291,
    "gn:feature_class":"P",
    "gn:feature_code":"PPL",
    "gn:name":"Lugh\u0101bah",
    "gn:population":0,
    "gn:timezone":"Asia/Aden",
    "iso:country":"YE",
    "name:und_x_variant":[
        "Lugh\u0101bah"
    ],
    "wof:name":"Lughabah",
    "wof:placetype":"locality"
},
  "geometry": {"coordinates":[43.88089,15.68094],"type":"Point"}
}