{
  "type": "Feature",
  "properties": {
    "gn:admin1_code":"5.0",
    "gn:admin2_code":"2115.0",
    "gn:asciiname":"Laslab",
    "gn:country_code":"YE",
    "gn:dem":1332,
    "gn:feature_class":"P",
    "gn:feature_code":"PPL",
    "gn:name":"La\u015fl\u0101b",
    "gn:population":0,
    "gn:timezone":"Asia/Aden",
    "iso:country":"YE",
    "name:und_x_variant":[
        "La\u015fl\u0101b"
    ],
    "wof:name":"Laslab",
    "wof:placetype":"locality"
},
  "geometry": {"coordinates":[47.15,14.58333],"type":"Point"}
}