{
  "type": "Feature",
  "properties": {
    "gn:admin1_code":"23.0",
    "gn:admin2_code":"1101.0",
    "gn:asciiname":"As Sululah",
    "gn:country_code":"YE",
    "gn:dem":1802,
    "gn:feature_class":"P",
    "gn:feature_code":"PPL",
    "gn:name":"A\u015f \u015eul\u016blah",
    "gn:population":0,
    "gn:timezone":"Asia/Aden",
    "iso:country":"YE",
    "name:ara_x_preferred":[
        "\u0627\u0644\u0635\u0644\u0648\u0644\u0629"
    ],
    "name:und_x_variant":[
        "A\u015f \u015eul\u016blah"
    ],
    "wof:name":"As Sululah",
    "wof:placetype":"locality"
},
  "geometry": {"coordinates":[44.21382,14.26057],"type":"Point"}
}