{
  "type": "Feature",
  "properties": {
    "gn:country":"YE",
    "gn:fcode":"PPL",
    "gn:pop":32,
    "iso:country":"YE",
    "name:ara_x_preferred":[
        "\u0634\u0642\u064a\u0645"
    ],
    "name:eng_x_preferred":[
        "Shuqaym"
    ],
    "qs:name":"Shuqaym",
    "qs:photos_9r":0,
    "qs:photos_sr":0,
    "qs:pop_sr":"1",
    "wof:name":"Shuqaym",
    "wof:placetype":"locality",
    "wof:population":32
},
  "geometry": {"coordinates":[44.20348,17.31379],"type":"Point"}
}