{
  "type": "Feature",
  "properties": {
    "gn:admin1_code":"19.0",
    "gn:admin2_code":"2919.0",
    "gn:asciiname":"Al Midwar",
    "gn:country_code":"YE",
    "gn:dem":2393,
    "gn:feature_class":"P",
    "gn:feature_code":"PPL",
    "gn:name":"Al Midw\u0101r",
    "gn:population":0,
    "gn:timezone":"Asia/Aden",
    "iso:country":"YE",
    "name:ara_x_preferred":[
        "Al Midw\u0101r"
    ],
    "name:ara_x_variant":[
        "\u0627\u0644\u0645\u062f\u0648\u0627\u0631"
    ],
    "wof:name":"Al Midwar",
    "wof:placetype":"locality"
},
  "geometry": {"coordinates":[43.95567,16.01369],"type":"Point"}
}