{
  "type": "Feature",
  "properties": {
    "gn:admin1_code":"16.0",
    "gn:admin2_code":"2313.0",
    "gn:asciiname":"Al Fayshani",
    "gn:country_code":"YE",
    "gn:dem":2798,
    "gn:feature_class":"P",
    "gn:feature_code":"PPL",
    "gn:name":"Al Faysh\u0101n\u012b",
    "gn:population":0,
    "gn:timezone":"Asia/Aden",
    "iso:country":"YE",
    "name:und_x_variant":[
        "Al Faysh\u0101n\u012b"
    ],
    "wof:name":"Al Fayshani",
    "wof:placetype":"locality"
},
  "geometry": {"coordinates":[44.64276,15.37875],"type":"Point"}
}