{
  "type": "Feature",
  "properties": {
    "gn:country":"YE",
    "gn:fcode":"PPL",
    "gn:population":19,
    "iso:country":"YE",
    "name:ara_x_preferred":[
        "\u0627\u0644\u062d\u0627\u0631\u0629"
    ],
    "qs:name":"Al \u1e28\u0101rrah",
    "qs:photos_9r":0,
    "qs:photos_sr":0,
    "qs:pop_sr":"1",
    "wof:name":"Al \u1e28\u0101rrah",
    "wof:placetype":"locality",
    "wof:population":19
},
  "geometry": {"coordinates":[43.26958,16.19266],"type":"Point"}
}