{
  "type": "Feature",
  "properties": {
    "gn:admin1_code":"23.0",
    "gn:admin2_code":"1101.0",
    "gn:asciiname":"Musayni'ah",
    "gn:country_code":"YE",
    "gn:dem":1426,
    "gn:feature_class":"P",
    "gn:feature_code":"PPL",
    "gn:name":"Mu\u015fayni\u2018ah",
    "gn:population":0,
    "gn:timezone":"Asia/Aden",
    "iso:country":"YE",
    "name:ara_x_preferred":[
        "\u0645\u0635\u064a\u0646\u0639\u0629"
    ],
    "name:und_x_variant":[
        "Mu\u015fayni\u2018ah"
    ],
    "wof:name":"Musayni'ah",
    "wof:placetype":"locality"
},
  "geometry": {"coordinates":[44.11115,14.30229],"type":"Point"}
}