{
  "type": "Feature",
  "properties": {
    "gn:admin1_code":"22.0",
    "gn:admin2_code":"1726.0",
    "gn:asciiname":"Markaz `Azi",
    "gn:country_code":"YE",
    "gn:dem":1761,
    "gn:feature_class":"P",
    "gn:feature_code":"PPL",
    "gn:name":"Markaz \u2018Az\u012b",
    "gn:population":0,
    "gn:timezone":"Asia/Aden",
    "iso:country":"YE",
    "name:und_x_variant":[
        "Markaz \u2018Az\u012b"
    ],
    "wof:name":"Markaz `Azi",
    "wof:placetype":"locality"
},
  "geometry": {"coordinates":[43.55217,15.63556],"type":"Point"}
}