{
  "type": "Feature",
  "properties": {
    "gn:country":"YE",
    "gn:fcode":"PPL",
    "gn:population":3,
    "iso:country":"YE",
    "name:ara_x_preferred":[
        "\u0627\u0644\u0639\u0647\u064a\u062f"
    ],
    "name:eng_x_preferred":[
        "Al 'Uhayd"
    ],
    "name:eng_x_variant":[
        "Al Hayl\u0101n"
    ],
    "qs:name":"Al \u2018Uhayd",
    "qs:photos_9r":0,
    "qs:photos_sr":0,
    "qs:pop_sr":"1",
    "wof:name":"Al \u2018Uhayd",
    "wof:placetype":"locality",
    "wof:population":3
},
  "geometry": {"coordinates":[45.3827,14.82709],"type":"Point"}
}