{
  "type": "Feature",
  "properties": {
    "gn:admin1_code":"23.0",
    "gn:admin2_code":"3003.0",
    "gn:asciiname":"Bana Fadl",
    "gn:country_code":"YE",
    "gn:dem":2340,
    "gn:feature_class":"P",
    "gn:feature_code":"PPL",
    "gn:name":"Ban\u0101 Fa\u1e11l",
    "gn:population":0,
    "gn:timezone":"Asia/Aden",
    "iso:country":"YE",
    "name:und_x_variant":[
        "Bah\u0101",
        "Ban\u0101 Fa\u1e11l"
    ],
    "wof:name":"Bana Fadl",
    "wof:placetype":"locality"
},
  "geometry": {"coordinates":[44.51146,13.98946],"type":"Point"}
}