{
  "type": "Feature",
  "properties": {
    "gn:admin1_code":"11.0",
    "gn:admin2_code":"2009.0",
    "gn:asciiname":"Hayd Isbil",
    "gn:country_code":"YE",
    "gn:dem":2625,
    "gn:feature_class":"P",
    "gn:feature_code":"PPL",
    "gn:name":"\u1e28ayd Isb\u012bl",
    "gn:population":0,
    "gn:timezone":"Asia/Aden",
    "iso:country":"YE",
    "name:und_x_variant":[
        "\u1e28ayd Isb\u012bl",
        "Jarf Isb\u012bl"
    ],
    "wof:name":"Hayd Isbil",
    "wof:placetype":"locality"
},
  "geometry": {"coordinates":[44.64852,14.55743],"type":"Point"}
}