{
  "type": "Feature",
  "properties": {
    "gn:admin1_code":"19.0",
    "gn:admin2_code":"2918.0",
    "gn:asciiname":"Bayt Rayyash",
    "gn:country_code":"YE",
    "gn:dem":2741,
    "gn:feature_class":"P",
    "gn:feature_code":"PPL",
    "gn:name":"Bayt Rayy\u0101sh",
    "gn:population":0,
    "gn:timezone":"Asia/Aden",
    "iso:country":"YE",
    "name:und_x_variant":[
        "Bayt Rayy\u0101sh"
    ],
    "wof:name":"Bayt Rayyash",
    "wof:placetype":"locality"
},
  "geometry": {"coordinates":[43.91185,15.61697],"type":"Point"}
}