{
  "type": "Feature",
  "properties": {
    "gn:admin1_code":"8.0",
    "gn:admin2_code":"1810.0",
    "gn:asciiname":"Dayr al Khushmu`",
    "gn:country_code":"YE",
    "gn:dem":170,
    "gn:feature_class":"P",
    "gn:feature_code":"PPL",
    "gn:name":"Dayr al Khushm\u016b\u2018",
    "gn:population":0,
    "gn:timezone":"Asia/Aden",
    "iso:country":"YE",
    "name:und_x_variant":[
        "Dayr al Khushm\u016b\u2018"
    ],
    "wof:name":"Dayr al Khushmu`",
    "wof:placetype":"locality"
},
  "geometry": {"coordinates":[43.25423,15.06743],"type":"Point"}
}