{
  "type": "Feature",
  "properties": {
    "gn:country":"YE",
    "gn:fcode":"PPL",
    "gn:pop":3,
    "iso:country":"YE",
    "name:ara_x_preferred":[
        "\u0627\u0644\u0645\u0631\u062a\u0643\u0627\u0621"
    ],
    "name:eng_x_preferred":[
        "Al Martika"
    ],
    "qs:name":"Al Martik\u0101\u2019",
    "qs:photos_9r":0,
    "qs:photos_sr":0,
    "qs:pop_sr":"1",
    "wof:name":"Al Martik\u0101\u2019",
    "wof:placetype":"locality",
    "wof:population":3
},
  "geometry": {"coordinates":[43.26074,17.11765],"type":"Point"}
}