{
  "type": "Feature",
  "properties": {
    "gn:admin1_code":"11.0",
    "gn:admin2_code":"2005.0",
    "gn:asciiname":"Al Khiyarah",
    "gn:country_code":"YE",
    "gn:dem":1993,
    "gn:feature_class":"P",
    "gn:feature_code":"PPL",
    "gn:name":"Al Khiy\u0101rah",
    "gn:population":0,
    "gn:timezone":"Asia/Aden",
    "iso:country":"YE",
    "name:und_x_variant":[
        "Al Khiy\u0101rah"
    ],
    "wof:name":"Al Khiyarah",
    "wof:placetype":"locality"
},
  "geometry": {"coordinates":[44.01625,14.49114],"type":"Point"}
}