{
  "type": "Feature",
  "properties": {
    "gn:admin1_code":"19.0",
    "gn:admin2_code":"2919.0",
    "gn:asciiname":"Bayt Sadilah",
    "gn:country_code":"YE",
    "gn:dem":2424,
    "gn:feature_class":"P",
    "gn:feature_code":"PPL",
    "gn:name":"Bayt Sadilah",
    "gn:population":0,
    "gn:timezone":"Asia/Aden",
    "iso:country":"YE",
    "name:ara_x_preferred":[
        "\u0628\u064a\u062a \u0633\u062f\u0644\u0629"
    ],
    "wof:name":"Bayt Sadilah",
    "wof:placetype":"locality"
},
  "geometry": {"coordinates":[43.99132,16.03311],"type":"Point"}
}