{
  "type": "Feature",
  "properties": {
    "gn:country":"YE",
    "gn:fcode":"PPLX",
    "gn:pop":21,
    "iso:country":"YE",
    "name:ara_x_preferred":[
        "Al \u2018Abil"
    ],
    "name:ara_x_variant":[
        "\u0627\u0644\u0639\u0628\u0644"
    ],
    "qs:name":"Al \u2018Abil",
    "qs:photos_9r":0,
    "qs:photos_sr":0,
    "qs:pop_sr":"1",
    "wof:name":"Al \u2018Abil",
    "wof:placetype":"neighbourhood",
    "wof:population":21
},
  "geometry": {"coordinates":[44.39425,16.65517],"type":"Point"}
}