{
  "type": "Feature",
  "properties": {
    "gn:admin1_code":"24.0",
    "gn:admin2_code":"2509.0",
    "gn:asciiname":"Al Lajamah",
    "gn:country_code":"YE",
    "gn:dem":728,
    "gn:feature_class":"P",
    "gn:feature_code":"PPL",
    "gn:name":"Al Lajamah",
    "gn:population":0,
    "gn:timezone":"Asia/Aden",
    "iso:country":"YE",
    "name:und_x_variant":[
        "Lijma",
        "Al Lajamah"
    ],
    "wof:name":"Al Lajamah",
    "wof:placetype":"locality"
},
  "geometry": {"coordinates":[44.58774,13.51276],"type":"Point"}
}