{
  "type": "Feature",
  "properties": {
    "gn:admin1_code":"14.0",
    "gn:admin2_code":"2602.0",
    "gn:asciiname":"As Suqayra'",
    "gn:country_code":"YE",
    "gn:dem":1122,
    "gn:feature_class":"P",
    "gn:feature_code":"PPL",
    "gn:name":"A\u015f \u015euqayr\u0101\u2018",
    "gn:population":0,
    "gn:timezone":"Asia/Aden",
    "iso:country":"YE",
    "name:ara_x_preferred":[
        "\u0627\u0644\u0635\u0642\u064a\u0631\u0627\u0621"
    ],
    "name:und_x_variant":[
        "A\u015f \u015euqayr\u0101\u2018"
    ],
    "wof:name":"As Suqayra'",
    "wof:placetype":"locality"
},
  "geometry": {"coordinates":[45.04881,15.72807],"type":"Point"}
}