{
  "type": "Feature",
  "properties": {
    "gn:admin1_code":"18.0",
    "gn:admin2_code":"3006.0",
    "gn:asciiname":"Adh Dhahabi",
    "gn:country_code":"YE",
    "gn:dem":1549,
    "gn:feature_class":"P",
    "gn:feature_code":"PPL",
    "gn:name":"Adh Dhahab\u012b",
    "gn:population":0,
    "gn:timezone":"Asia/Aden",
    "iso:country":"YE",
    "name:und_x_variant":[
        "Adh Dhahab\u012b"
    ],
    "wof:name":"Adh Dhahabi",
    "wof:placetype":"locality"
},
  "geometry": {"coordinates":[44.71184,13.77558],"type":"Point"}
}