{
  "type": "Feature",
  "properties": {
    "gn:admin1_code":"23.0",
    "gn:admin2_code":"1108.0",
    "gn:asciiname":"Washir",
    "gn:country_code":"YE",
    "gn:dem":2613,
    "gn:feature_class":"P",
    "gn:feature_code":"PPL",
    "gn:name":"Wash\u012br",
    "gn:population":0,
    "gn:timezone":"Asia/Aden",
    "iso:country":"YE",
    "name:ara_x_preferred":[
        "\u0648\u0634\u064a\u0631"
    ],
    "name:tur_x_preferred":[
        "Va\u015fir"
    ],
    "name:und_x_variant":[
        "Wash\u012br"
    ],
    "wof:name":"Washir",
    "wof:placetype":"locality"
},
  "geometry": {"coordinates":[44.06363,14.05688],"type":"Point"}
}