{
  "type": "Feature",
  "properties": {
    "gn:admin1_code":"25.0",
    "gn:admin2_code":"1515.0",
    "gn:asciiname":"Al Hawbayn al Asfal",
    "gn:country_code":"YE",
    "gn:dem":2012,
    "gn:feature_class":"P",
    "gn:feature_code":"PPL",
    "gn:name":"Al \u1e28awbayn al Asfal",
    "gn:population":0,
    "gn:timezone":"Asia/Aden",
    "iso:country":"YE",
    "name:ara_x_preferred":[
        "\u0627\u0644\u062d\u0628\u064a\u0646 \u0627\u0644\u0623\u0633\u0641\u0644"
    ],
    "name:und_x_variant":[
        "Al \u1e28awbayn al Asfal"
    ],
    "wof:name":"Al Hawbayn al Asfal",
    "wof:placetype":"locality"
},
  "geometry": {"coordinates":[44.15212,13.21789],"type":"Point"}
}