{
  "type": "Feature",
  "properties": {
    "gn:country":"YE",
    "gn:fcode":"PPL",
    "gn:pop":4,
    "iso:country":"YE",
    "name:ara_x_preferred":[
        "\u062f\u0645\u0634 \u0627\u0644\u0641\u0627\u0648\u064a\u0629"
    ],
    "name:eng_x_preferred":[
        "Damsh Al Fawiyah"
    ],
    "name:eng_x_variant":[
        "Al Mufli\u0163a\u1e29"
    ],
    "qs:name":"Damsh al F\u0101w\u012byah",
    "qs:photos_9r":0,
    "qs:photos_sr":0,
    "qs:pop_sr":"1",
    "wof:name":"Damsh al F\u0101w\u012byah",
    "wof:placetype":"locality",
    "wof:population":4
},
  "geometry": {"coordinates":[43.2916,16.2643],"type":"Point"}
}