{
  "type": "Feature",
  "properties": {
    "gn:admin1_code":"25.0",
    "gn:admin2_code":"1512.0",
    "gn:asciiname":"Al Mihal",
    "gn:country_code":"YE",
    "gn:dem":1574,
    "gn:feature_class":"P",
    "gn:feature_code":"PPL",
    "gn:name":"Al M\u012bh\u0101l",
    "gn:population":0,
    "gn:timezone":"Asia/Aden",
    "iso:country":"YE",
    "name:ara_x_preferred":[
        "Al M\u012bh\u0101l"
    ],
    "wof:name":"Al Mihal",
    "wof:placetype":"locality"
},
  "geometry": {"coordinates":[44.09691,13.51451],"type":"Point"}
}