{
  "type": "Feature",
  "properties": {
    "gn:admin1_code":"20.0",
    "gn:admin2_code":"1420.0",
    "gn:asciiname":"Al Qu`ah",
    "gn:country_code":"YE",
    "gn:dem":1982,
    "gn:feature_class":"P",
    "gn:feature_code":"PPL",
    "gn:name":"Al Q\u016b\u2018ah",
    "gn:population":0,
    "gn:timezone":"Asia/Aden",
    "iso:country":"YE",
    "name:ara_x_preferred":[
        "\u0627\u0644\u0645\u0634\u0628\u0629"
    ],
    "name:und_x_variant":[
        "Al Q\u016b\u2018ah",
        "Al Mishbah"
    ],
    "wof:name":"Al Qu`ah",
    "wof:placetype":"locality"
},
  "geometry": {"coordinates":[45.31578,14.24155],"type":"Point"}
}