{
  "type": "Feature",
  "properties": {
    "gn:admin1_code":"23.0",
    "gn:admin2_code":"1107.0",
    "gn:asciiname":"Shanin",
    "gn:country_code":"YE",
    "gn:dem":1652,
    "gn:feature_class":"P",
    "gn:feature_code":"PPL",
    "gn:name":"Shan\u012bn",
    "gn:population":0,
    "gn:timezone":"Asia/Aden",
    "iso:country":"YE",
    "name:ara_x_preferred":[
        "\u0634\u0646\u064a\u0646 \u0627\u0644\u0646\u0648\u0628\u0629"
    ],
    "name:und_x_variant":[
        "Shan\u012bn",
        "Shan\u012bn an Nawbah"
    ],
    "wof:name":"Shanin",
    "wof:placetype":"locality"
},
  "geometry": {"coordinates":[44.19721,14.09383],"type":"Point"}
}