{
  "type": "Feature",
  "properties": {
    "gn:admin1_code":"23.0",
    "gn:admin2_code":"1116.0",
    "gn:asciiname":"`Araj",
    "gn:country_code":"YE",
    "gn:dem":1938,
    "gn:feature_class":"P",
    "gn:feature_code":"PPL",
    "gn:name":"\u2018Araj",
    "gn:population":0,
    "gn:timezone":"Asia/Aden",
    "iso:country":"YE",
    "name:und_x_variant":[
        "\u2018Araj"
    ],
    "wof:name":"`Araj",
    "wof:placetype":"locality"
},
  "geometry": {"coordinates":[44.08189,13.83543],"type":"Point"}
}