{
  "type": "Feature",
  "properties": {
    "gn:country":"YE",
    "gn:fcode":"PPL",
    "gn:pop":3,
    "iso:country":"YE",
    "name:ara_x_preferred":[
        "A\u015f \u015eiw\u0101ni\u2018"
    ],
    "name:ara_x_variant":[
        "\u0627\u0644\u0635\u0648\u0627\u0646\u0639"
    ],
    "qs:name":"A\u015f \u015eiw\u0101ni\u2018",
    "qs:photos_9r":0,
    "qs:photos_sr":0,
    "qs:pop_sr":"1",
    "wof:name":"A\u015f \u015eiw\u0101ni\u2018",
    "wof:placetype":"locality",
    "wof:population":3
},
  "geometry": {"coordinates":[43.37502,16.34412],"type":"Point"}
}