{
  "type": "Feature",
  "properties": {
    "gn:admin1_code":"22.0",
    "gn:admin2_code":"1704.0",
    "gn:asciiname":"Abs",
    "gn:country_code":"YE",
    "gn:dem":194,
    "gn:feature_class":"P",
    "gn:feature_code":"PPLA2",
    "gn:name":"Abs",
    "gn:population":0,
    "gn:timezone":"Asia/Aden",
    "iso:country":"YE",
    "name:ara_x_preferred":[
        "\u2018Abs"
    ],
    "name:ara_x_variant":[
        "\u0639\u0628\u0633"
    ],
    "name:eng_x_preferred":[
        "Abs"
    ],
    "name:und_x_variant":[
        "Mutayyin",
        "S\u016bq \u2018Abs"
    ],
    "wof:name":"Abs",
    "wof:placetype":"locality"
},
  "geometry": {"coordinates":[43.19725,16.00295],"type":"Point"}
}