{
  "type": "Feature",
  "properties": {
    "gn:admin1_code":"22.0",
    "gn:admin2_code":"1730.0",
    "gn:asciiname":"Dhira' as Siyab",
    "gn:country_code":"YE",
    "gn:dem":617,
    "gn:feature_class":"P",
    "gn:feature_code":"PPL",
    "gn:name":"Dhir\u0101\u2018 a\u015f \u015eiy\u0101b",
    "gn:population":1,
    "gn:timezone":"Asia/Aden",
    "iso:country":"YE",
    "name:ara_x_preferred":[
        "\u0630\u0631\u0627\u0639 \u0627\u0644\u0635\u064a\u0627\u0628"
    ],
    "name:und_x_variant":[
        "Dhir\u0101\u2018 a\u015f \u015eiy\u0101b"
    ],
    "wof:name":"Dhira' as Siyab",
    "wof:placetype":"locality",
    "wof:population":1
},
  "geometry": {"coordinates":[43.34934000000001,16.3035],"type":"Point"}
}