{
  "type": "Feature",
  "properties": {
    "gn:country":"YE",
    "gn:fcode":"PPL",
    "gn:pop":7,
    "iso:country":"YE",
    "name:ara_x_preferred":[
        "\u0627\u0644\u064a\u0648\u0633\u0641\u064a\u0629"
    ],
    "name:eng_x_preferred":[
        "Al YUsifiyah"
    ],
    "name:eng_x_variant":[
        "Al Ba\u1e29\u0163\u012brah"
    ],
    "qs:name":"Al Y\u016bsif\u012byah",
    "qs:photos_9r":0,
    "qs:photos_sr":0,
    "qs:pop_sr":"1",
    "wof:name":"Al Y\u016bsif\u012byah",
    "wof:placetype":"locality",
    "wof:population":7
},
  "geometry": {"coordinates":[45.43262,14.0452],"type":"Point"}
}