{
  "type": "Feature",
  "properties": {
    "gn:admin1_code":"23.0",
    "gn:admin2_code":"1101.0",
    "gn:asciiname":"Farsh at Tahir",
    "gn:country_code":"YE",
    "gn:dem":1287,
    "gn:feature_class":"P",
    "gn:feature_code":"PPL",
    "gn:name":"Farsh a\u0163 \u0162\u0101hir",
    "gn:population":0,
    "gn:timezone":"Asia/Aden",
    "iso:country":"YE",
    "name:ara_x_preferred":[
        "\u0641\u0631\u0634 \u0627\u0644\u0637\u0627\u0647\u0631"
    ],
    "name:und_x_variant":[
        "Farsh a\u0163 \u0162\u0101hir"
    ],
    "wof:name":"Farsh at Tahir",
    "wof:placetype":"locality"
},
  "geometry": {"coordinates":[44.07946,14.32114],"type":"Point"}
}