{
  "type": "Feature",
  "properties": {
    "gn:admin1_code":"23.0",
    "gn:admin2_code":"1102.0",
    "gn:asciiname":"Ash Shammari",
    "gn:country_code":"YE",
    "gn:dem":1561,
    "gn:feature_class":"P",
    "gn:feature_code":"PPL",
    "gn:name":"Ash Shamm\u0101r\u012b",
    "gn:population":0,
    "gn:timezone":"Asia/Aden",
    "iso:country":"YE",
    "name:ara_x_preferred":[
        "\u0627\u0644\u0634\u0645\u0627\u0631\u064a"
    ],
    "name:und_x_variant":[
        "Najd ash Sham\u0101r\u012b",
        "Ash Shamm\u0101r\u012b"
    ],
    "wof:name":"Ash Shammari",
    "wof:placetype":"locality"
},
  "geometry": {"coordinates":[44.16014000000001,14.29122],"type":"Point"}
}