{
  "type": "Feature",
  "properties": {
    "gn:country":"YE",
    "gn:fcode":"PPL",
    "gn:pop":6,
    "iso:country":"YE",
    "name:ara_x_preferred":[
        "\u0628\u064a\u062a \u0627\u0644\u062c\u0644\u0627\u0644"
    ],
    "name:eng_x_preferred":[
        "Bayt Al Jallal"
    ],
    "name:unk_x_variant":[
        "Bayt al Jal\u0101l"
    ],
    "qs:name":"Bayt al Jall\u0101l",
    "qs:photos_9r":0,
    "qs:photos_sr":0,
    "qs:pop_sr":"1",
    "wof:name":"Bayt al Jall\u0101l",
    "wof:placetype":"locality",
    "wof:population":6
},
  "geometry": {"coordinates":[43.37548,16.35074],"type":"Point"}
}