{
  "type": "Feature",
  "properties": {
    "gn:admin1_code":"22.0",
    "gn:admin2_code":"1722.0",
    "gn:asciiname":"Bayt ad Dubba",
    "gn:country_code":"YE",
    "gn:dem":708,
    "gn:feature_class":"P",
    "gn:feature_code":"PPL",
    "gn:name":"Bayt ad Dubb\u0101",
    "gn:population":0,
    "gn:timezone":"Asia/Aden",
    "iso:country":"YE",
    "name:und_x_variant":[
        "Bayt ad Dubb\u0101"
    ],
    "wof:name":"Bayt ad Dubba",
    "wof:placetype":"locality"
},
  "geometry": {"coordinates":[43.32578,15.84223],"type":"Point"}
}