{
  "type": "Feature",
  "properties": {
    "gn:admin1_code":"19.0",
    "gn:admin2_code":"2907.0",
    "gn:asciiname":"Mahall al Mi'zab",
    "gn:country_code":"YE",
    "gn:dem":1002,
    "gn:feature_class":"P",
    "gn:feature_code":"PPL",
    "gn:name":"Ma\u1e29all al Mi\u2018z\u0101b",
    "gn:population":0,
    "gn:timezone":"Asia/Aden",
    "iso:country":"YE",
    "name:ara_x_preferred":[
        "\u0645\u062d\u0644 \u0627\u0644\u0645\u0639\u0632\u0627\u0628"
    ],
    "name:und_x_variant":[
        "Ma\u1e29all al Mi\u2018z\u0101b"
    ],
    "wof:name":"Mahall al Mi'zab",
    "wof:placetype":"locality"
},
  "geometry": {"coordinates":[43.61644,16.04065],"type":"Point"}
}