{
  "type": "Feature",
  "properties": {
    "gn:admin1_code":"4.0",
    "gn:admin2_code":"1911.0",
    "gn:asciiname":"As Suwayri",
    "gn:cc2":"YE",
    "gn:country_code":"YE",
    "gn:dem":626,
    "gn:feature_class":"P",
    "gn:feature_code":"PPL",
    "gn:name":"As Suwayr\u012b",
    "gn:population":0,
    "gn:timezone":"Asia/Aden",
    "iso:country":"YE",
    "name:und_x_variant":[
        "Suweiri",
        "Al-Suwairi",
        "As Suwayr\u012b"
    ],
    "wof:name":"As Suwayri",
    "wof:placetype":"locality"
},
  "geometry": {"coordinates":[49.02,15.97972],"type":"Point"}
}