{
  "type": "Feature",
  "properties": {
    "gn:country":"YE",
    "gn:fcode":"PPL",
    "gn:pop":51,
    "iso:country":"YE",
    "name:ara_x_preferred":[
        "Abw\u0101y"
    ],
    "name:ara_x_variant":[
        "\u0623\u0628\u0648\u0627\u064a"
    ],
    "name:eng_x_preferred":[
        "Abway"
    ],
    "qs:name":"Abw\u0101y",
    "qs:photos_9r":0,
    "qs:photos_sr":0,
    "qs:pop_sr":"1",
    "wof:name":"Abw\u0101y",
    "wof:placetype":"locality",
    "wof:population":51
},
  "geometry": {"coordinates":[43.33456,16.98517],"type":"Point"}
}