{
  "type": "Feature",
  "properties": {
    "gn:admin1_code":"25.0",
    "gn:admin2_code":"1515.0",
    "gn:asciiname":"Hadarim",
    "gn:country_code":"YE",
    "gn:dem":1790,
    "gn:feature_class":"P",
    "gn:feature_code":"PPL",
    "gn:name":"\u1e28a\u1e11\u0101rim",
    "gn:population":0,
    "gn:timezone":"Asia/Aden",
    "iso:country":"YE",
    "name:und_x_variant":[
        "\u1e28a\u1e11\u0101rim"
    ],
    "wof:name":"Hadarim",
    "wof:placetype":"locality"
},
  "geometry": {"coordinates":[44.12134,13.17184],"type":"Point"}
}