{
  "type": "Feature",
  "properties": {
    "gn:admin1_code":"5.0",
    "gn:admin2_code":"2110.0",
    "gn:asciiname":"Baduwah",
    "gn:country_code":"YE",
    "gn:dem":1151,
    "gn:feature_class":"P",
    "gn:feature_code":"PPL",
    "gn:name":"Bad\u016bwah",
    "gn:population":0,
    "gn:timezone":"Asia/Aden",
    "iso:country":"YE",
    "name:und_x_variant":[
        "Bad\u016bwah"
    ],
    "wof:name":"Baduwah",
    "wof:placetype":"locality"
},
  "geometry": {"coordinates":[46.4592,14.39835],"type":"Point"}
}