{
  "type": "Feature",
  "properties": {
    "gn:admin1_code":"22.0",
    "gn:admin2_code":"1720.0",
    "gn:asciiname":"Shi`b al Gharas",
    "gn:country_code":"YE",
    "gn:dem":618,
    "gn:feature_class":"P",
    "gn:feature_code":"PPL",
    "gn:name":"Shi\u2018b al Gharas",
    "gn:population":0,
    "gn:timezone":"Asia/Aden",
    "iso:country":"YE",
    "name:und_x_variant":[
        "Shi\u2018b al Gharas"
    ],
    "wof:name":"Shi`b al Gharas",
    "wof:placetype":"locality"
},
  "geometry": {"coordinates":[43.52388,15.8526],"type":"Point"}
}