{
  "type": "Feature",
  "properties": {
    "gn:country":"YE",
    "gn:fcode":"PPL",
    "gn:population":16,
    "iso:country":"YE",
    "name:ara_x_preferred":[
        "\u0627\u0644\u0645\u062a\u0632\u0644"
    ],
    "qs:name":"Al Mitzal",
    "qs:photos_9r":0,
    "qs:photos_sr":0,
    "qs:pop_sr":"1",
    "wof:name":"Al Mitzal",
    "wof:placetype":"locality",
    "wof:population":16
},
  "geometry": {"coordinates":[43.25818,16.84259],"type":"Point"}
}