{
  "type": "Feature",
  "properties": {
    "gn:admin1_code":"22.0",
    "gn:admin2_code":"1709.0",
    "gn:asciiname":"Dhira' Hadi",
    "gn:country_code":"YE",
    "gn:dem":1821,
    "gn:feature_class":"P",
    "gn:feature_code":"PPL",
    "gn:name":"Dhir\u0101\u2018 H\u0101d\u012b",
    "gn:population":0,
    "gn:timezone":"Asia/Aden",
    "iso:country":"YE",
    "name:ara_x_preferred":[
        "Dhir\u0101\u2018 H\u0101d\u012b"
    ],
    "name:ara_x_variant":[
        "\u0630\u0631\u0627\u0639 \u0647\u0627\u062f\u064a"
    ],
    "wof:name":"Dhira' Hadi",
    "wof:placetype":"locality"
},
  "geometry": {"coordinates":[43.46449000000001,16.01407],"type":"Point"}
}