{
  "type": "Feature",
  "properties": {
    "gn:admin1_code":"23.0",
    "gn:admin2_code":"1102.0",
    "gn:asciiname":"Yafa'ah al 'Ulya",
    "gn:country_code":"YE",
    "gn:dem":2675,
    "gn:feature_class":"P",
    "gn:feature_code":"PPL",
    "gn:name":"Yaf\u0101\u2018ah al \u2018Uly\u0101",
    "gn:population":0,
    "gn:timezone":"Asia/Aden",
    "iso:country":"YE",
    "name:ara_x_preferred":[
        "\u064a\u0641\u0627\u0639\u0629 \u0627\u0644\u0639\u0644\u064a\u0627"
    ],
    "name:und_x_variant":[
        "Yaf\u0101\u2018ah al \u2018Uly\u0101"
    ],
    "wof:name":"Yafa'ah al 'Ulya",
    "wof:placetype":"locality"
},
  "geometry": {"coordinates":[44.20172,14.3485],"type":"Point"}
}