{
  "type": "Feature",
  "properties": {
    "gn:admin1_code":"22.0",
    "gn:admin2_code":"1727.0",
    "gn:asciiname":"Bayt al Marani",
    "gn:country_code":"YE",
    "gn:dem":1588,
    "gn:feature_class":"P",
    "gn:feature_code":"PPL",
    "gn:name":"Bayt al Mar\u0101n\u012b",
    "gn:population":0,
    "gn:timezone":"Asia/Aden",
    "iso:country":"YE",
    "name:und_x_variant":[
        "Bayt al Mar\u0101n\u012b"
    ],
    "wof:name":"Bayt al Marani",
    "wof:placetype":"locality"
},
  "geometry": {"coordinates":[43.5859,15.59798],"type":"Point"}
}