{
  "type": "Feature",
  "properties": {
    "gn:admin1_code":"19.0",
    "gn:admin2_code":"2904.0",
    "gn:asciiname":"Mahall Dishaylah",
    "gn:country_code":"YE",
    "gn:dem":1204,
    "gn:feature_class":"P",
    "gn:feature_code":"PPL",
    "gn:name":"Ma\u1e29all Dishaylah",
    "gn:population":0,
    "gn:timezone":"Asia/Aden",
    "iso:country":"YE",
    "name:und_x_variant":[
        "Ma\u1e29all Dishaylah"
    ],
    "wof:name":"Mahall Dishaylah",
    "wof:placetype":"locality"
},
  "geometry": {"coordinates":[43.77696,16.20304],"type":"Point"}
}