{
  "type": "Feature",
  "properties": {
    "gn:admin1_code":"8.0",
    "gn:admin2_code":"1817.0",
    "gn:asciiname":"Al Hajib",
    "gn:country_code":"YE",
    "gn:dem":360,
    "gn:feature_class":"P",
    "gn:feature_code":"PPL",
    "gn:name":"Al \u1e28\u0101jib",
    "gn:population":0,
    "gn:timezone":"Asia/Aden",
    "iso:country":"YE",
    "name:ara_x_preferred":[
        "Al \u1e28\u0101jib"
    ],
    "wof:name":"Al Hajib",
    "wof:placetype":"locality"
},
  "geometry": {"coordinates":[43.53532,14.45984],"type":"Point"}
}