{
  "type": "Feature",
  "properties": {
    "gn:admin1_code":"19.0",
    "gn:admin2_code":"2908.0",
    "gn:asciiname":"Al Hawashi",
    "gn:country_code":"YE",
    "gn:dem":1053,
    "gn:feature_class":"P",
    "gn:feature_code":"PPL",
    "gn:name":"Al \u1e28aw\u0101sh\u012b",
    "gn:population":0,
    "gn:timezone":"Asia/Aden",
    "iso:country":"YE",
    "name:ara_x_preferred":[
        "\u0627\u0644\u062d\u0648\u0627\u0634\u064a"
    ],
    "name:und_x_variant":[
        "Al \u1e28aw\u0101sh\u012b"
    ],
    "wof:name":"Al Hawashi",
    "wof:placetype":"locality"
},
  "geometry": {"coordinates":[43.79626,16.08743],"type":"Point"}
}