{
  "type": "Feature",
  "properties": {
    "gn:country":"YE",
    "gn:fcode":"PPL",
    "gn:population":16,
    "iso:country":"YE",
    "name:ara_x_preferred":[
        "\u0627\u0644\u062d\u062c\u0648\u0631\u064a"
    ],
    "name:eng_x_preferred":[
        "Al HajUri"
    ],
    "name:eng_x_variant":[
        "\u1e28i\u015fn an Naq\u012bb"
    ],
    "qs:name":"Al \u1e28aj\u016br\u012b",
    "qs:photos_9r":0,
    "qs:photos_sr":0,
    "qs:pop_sr":"1",
    "wof:name":"Al \u1e28aj\u016br\u012b",
    "wof:placetype":"locality",
    "wof:population":16
},
  "geometry": {"coordinates":[43.69987,16.16264],"type":"Point"}
}