{
  "type": "Feature",
  "properties": {
    "gn:admin1_code":"22.0",
    "gn:admin2_code":"1702.0",
    "gn:asciiname":"Ar Rakib",
    "gn:country_code":"YE",
    "gn:dem":92,
    "gn:feature_class":"P",
    "gn:feature_code":"PPL",
    "gn:name":"Ar R\u0101kib",
    "gn:population":0,
    "gn:timezone":"Asia/Aden",
    "iso:country":"YE",
    "name:ara_x_preferred":[
        "Ar R\u0101kib"
    ],
    "wof:name":"Ar Rakib",
    "wof:placetype":"locality"
},
  "geometry": {"coordinates":[43.03709,16.40342],"type":"Point"}
}