{
  "type": "Feature",
  "properties": {
    "gn:gn_country":"YE",
    "gn:gn_fcode":"PPL",
    "gn:gn_pop":10,
    "gn:population":10,
    "iso:country":"YE",
    "name:ara_x_preferred":[
        "\u0627\u0644\u062d\u0627\u0632\u0629 \u0627\u0644\u0642\u0635\u0627\u0639\u064a"
    ],
    "name:eng_x_preferred":[
        "Al Hazah Al Qasa'i"
    ],
    "name:eng_x_variant":[
        "La\u1e29\u1e29 al \u2018Ajish"
    ],
    "qs_pg:aaroncc":"YE",
    "qs_pg:gn_country":"YE",
    "qs_pg:gn_fcode":"PPL",
    "qs_pg:gn_pop":10,
    "qs_pg:name":"Al \u1e28\u0101zah al Qa\u015f\u0101\u2018\u012b",
    "qs_pg:photos_9r":0,
    "qs_pg:photos_sr":0,
    "qs_pg:pop_sr":1,
    "qs_pg:qs_pg_placetype":"locality",
    "wof:name":"Al \u1e28\u0101zah al Qa\u015f\u0101\u2018\u012b",
    "wof:placetype":"locality",
    "wof:population":10
},
  "geometry": {"coordinates":[43.29094,16.21806],"type":"Point"}
}