{
  "type": "Feature",
  "properties": {
    "gn:admin1_code":"23.0",
    "gn:admin2_code":"1109.0",
    "gn:asciiname":"Hazm al `Udayn",
    "gn:country_code":"YE",
    "gn:dem":2099,
    "gn:feature_class":"P",
    "gn:feature_code":"PPLA2",
    "gn:name":"\u1e28azm al \u2018Udayn",
    "gn:population":0,
    "gn:timezone":"Asia/Aden",
    "iso:country":"YE",
    "name:und_x_variant":[
        "\u1e28azm al \u2018Udayn"
    ],
    "wof:name":"Hazm al `Udayn",
    "wof:placetype":"locality"
},
  "geometry": {"coordinates":[44.00526,14.02743],"type":"Point"}
}