{
  "type": "Feature",
  "properties": {
    "gn:country":"YE",
    "gn:fcode":"PPL",
    "gn:population":1,
    "iso:country":"YE",
    "name:ara_x_preferred":[
        "\u0627\u0644\u0643\u062f\u0643\u0627\u062f"
    ],
    "qs:name":"Al Kadk\u0101d",
    "qs:photos_9r":0,
    "qs:photos_sr":0,
    "qs:pop_sr":"1",
    "wof:name":"Al Kadk\u0101d",
    "wof:placetype":"locality",
    "wof:population":1
},
  "geometry": {"coordinates":[43.97975,13.21136],"type":"Point"}
}