{
  "type": "Feature",
  "properties": {
    "gn:admin1_code":"10.0",
    "gn:admin2_code":"2707.0",
    "gn:asciiname":"Shi`b al Birak",
    "gn:country_code":"YE",
    "gn:dem":691,
    "gn:feature_class":"P",
    "gn:feature_code":"PPL",
    "gn:name":"Shi\u2018b al Birak",
    "gn:population":0,
    "gn:timezone":"Asia/Aden",
    "iso:country":"YE",
    "name:und_x_variant":[
        "Shi\u2018b al Birak"
    ],
    "wof:name":"Shi`b al Birak",
    "wof:placetype":"locality"
},
  "geometry": {"coordinates":[43.42854000000001,15.27699],"type":"Point"}
}