{
  "type": "Feature",
  "properties": {
    "gn:admin1_code":"14.0",
    "gn:admin2_code":"2608.0",
    "gn:asciiname":"As Sakari'",
    "gn:country_code":"YE",
    "gn:dem":1526,
    "gn:feature_class":"P",
    "gn:feature_code":"PPL",
    "gn:name":"As Sak\u0101ri\u2018",
    "gn:population":0,
    "gn:timezone":"Asia/Aden",
    "iso:country":"YE",
    "name:ara_x_preferred":[
        "\u0627\u0644\u0633\u0643\u0627\u0631\u0639"
    ],
    "name:und_x_variant":[
        "As Sak\u0101ri\u2018"
    ],
    "wof:name":"As Sakari'",
    "wof:placetype":"locality"
},
  "geometry": {"coordinates":[45.07695,15.02501],"type":"Point"}
}