{
  "type": "Feature",
  "properties": {
    "gn:admin1_code":"21.0",
    "gn:admin2_code":"1602.0",
    "gn:asciiname":"As Sa'adi",
    "gn:country_code":"YE",
    "gn:dem":1262,
    "gn:feature_class":"P",
    "gn:feature_code":"PPLL",
    "gn:name":"As Sa\u2018\u0101d\u012b",
    "gn:population":0,
    "gn:timezone":"Asia/Aden",
    "iso:country":"YE",
    "name:ara_x_preferred":[
        "\u0627\u0644\u0633\u0639\u0627\u062f\u064a"
    ],
    "name:und_x_variant":[
        "As Sa\u2018\u0101d\u012b"
    ],
    "wof:name":"As Sa'adi",
    "wof:placetype":"locality"
},
  "geometry": {"coordinates":[44.40962,16.39763],"type":"Point"}
}