{
  "type": "Feature",
  "properties": {
    "gn:admin1_code":"20.0",
    "gn:admin2_code":"1410.0",
    "gn:asciiname":"Al Hujayrah",
    "gn:country_code":"YE",
    "gn:dem":1986,
    "gn:feature_class":"P",
    "gn:feature_code":"PPL",
    "gn:name":"Al Hujayrah",
    "gn:population":0,
    "gn:timezone":"Asia/Aden",
    "iso:country":"YE",
    "wof:name":"Al Hujayrah",
    "wof:placetype":"locality"
},
  "geometry": {"coordinates":[45.57618,14.02918],"type":"Point"}
}