{
  "type": "Feature",
  "properties": {
    "gn:admin1_code":"8.0",
    "gn:admin2_code":"1810.0",
    "gn:asciiname":"Az Zahwaniyah",
    "gn:country_code":"YE",
    "gn:dem":64,
    "gn:feature_class":"P",
    "gn:feature_code":"PPL",
    "gn:name":"Az Zahwan\u012byah",
    "gn:population":0,
    "gn:timezone":"Asia/Aden",
    "iso:country":"YE",
    "name:und_x_variant":[
        "Az Zahwan\u012byah"
    ],
    "wof:name":"Az Zahwaniyah",
    "wof:placetype":"locality"
},
  "geometry": {"coordinates":[43.04582,15.17335],"type":"Point"}
}