{
  "type": "Feature",
  "properties": {
    "gn:admin1_code":"15.0",
    "gn:admin2_code":"2206.0",
    "gn:asciiname":"Ar Rahwah",
    "gn:country_code":"YE",
    "gn:dem":356,
    "gn:feature_class":"P",
    "gn:feature_code":"PPL",
    "gn:name":"Ar Rahwah",
    "gn:population":0,
    "gn:timezone":"Asia/Aden",
    "iso:country":"YE",
    "name:ara_x_preferred":[
        "\u0627\u0644\u0631\u0647\u0648\u0629"
    ],
    "wof:name":"Ar Rahwah",
    "wof:placetype":"locality"
},
  "geometry": {"coordinates":[43.19643,16.87453],"type":"Point"}
}