{
  "type": "Feature",
  "properties": {
    "gn:admin1_code":"19.0",
    "gn:admin2_code":"2918.0",
    "gn:asciiname":"Madawar",
    "gn:country_code":"YE",
    "gn:dem":2216,
    "gn:feature_class":"P",
    "gn:feature_code":"PPL",
    "gn:name":"Mad\u0101war",
    "gn:population":0,
    "gn:timezone":"Asia/Aden",
    "iso:country":"YE",
    "name:ara_x_preferred":[
        "\u0645\u062f\u0627\u0648\u0631"
    ],
    "name:und_x_variant":[
        "Mad\u0101war"
    ],
    "wof:name":"Madawar",
    "wof:placetype":"locality"
},
  "geometry": {"coordinates":[44.00102,15.71227],"type":"Point"}
}