{
  "type": "Feature",
  "properties": {
    "gn:admin1_code":"15.0",
    "gn:admin2_code":"2203.0",
    "gn:asciiname":"Dhat al Khayfan",
    "gn:country_code":"YE",
    "gn:dem":1746,
    "gn:feature_class":"P",
    "gn:feature_code":"PPL",
    "gn:name":"Dh\u0101t al Khayf\u0101n",
    "gn:population":0,
    "gn:timezone":"Asia/Aden",
    "iso:country":"YE",
    "name:ara_x_preferred":[
        "\u0630\u0627\u062a \u0627\u0644\u062e\u064a\u0641\u0627\u0646"
    ],
    "name:und_x_variant":[
        "Dh\u0101t al Khayf\u0101n"
    ],
    "wof:name":"Dhat al Khayfan",
    "wof:placetype":"locality"
},
  "geometry": {"coordinates":[43.24859,17.18084],"type":"Point"}
}