{
  "type": "Feature",
  "properties": {
    "gn:admin1_code":"16.0",
    "gn:admin2_code":"2302.0",
    "gn:asciiname":"Bayt Qawb",
    "gn:country_code":"YE",
    "gn:dem":2322,
    "gn:feature_class":"P",
    "gn:feature_code":"PPL",
    "gn:name":"Bayt Qawb",
    "gn:population":0,
    "gn:timezone":"Asia/Aden",
    "iso:country":"YE",
    "wof:name":"Bayt Qawb",
    "wof:placetype":"locality"
},
  "geometry": {"coordinates":[44.25684,15.70131],"type":"Point"}
}