{
  "type": "Feature",
  "properties": {
    "gn:admin1_code":"25.0",
    "gn:admin2_code":"1515.0",
    "gn:asciiname":"Ash Shama'iyah ash Sharqiyah",
    "gn:country_code":"YE",
    "gn:dem":1450,
    "gn:feature_class":"P",
    "gn:feature_code":"PPL",
    "gn:name":"Ash Sham\u0101\u2019iyah ash Sharq\u012byah",
    "gn:population":0,
    "gn:timezone":"Asia/Aden",
    "iso:country":"YE",
    "name:und_x_variant":[
        "Ash Sham\u0101\u2019iyah ash Sharq\u012byah"
    ],
    "wof:name":"Ash Shama'iyah ash Sharqiyah",
    "wof:placetype":"locality"
},
  "geometry": {"coordinates":[44.02813,13.20896],"type":"Point"}
}