{
  "type": "Feature",
  "properties": {
    "gn:admin1_code":"8.0",
    "gn:admin2_code":"1809.0",
    "gn:asciiname":"Dayr Shuwayl",
    "gn:country_code":"YE",
    "gn:dem":53,
    "gn:feature_class":"P",
    "gn:feature_code":"PPL",
    "gn:name":"Dayr Shuwayl",
    "gn:population":0,
    "gn:timezone":"Asia/Aden",
    "iso:country":"YE",
    "wof:name":"Dayr Shuwayl",
    "wof:placetype":"locality"
},
  "geometry": {"coordinates":[43.01588,15.1635],"type":"Point"}
}