{
  "type": "Feature",
  "properties": {
    "gn:admin1_code":"16.0",
    "gn:admin2_code":"2316.0",
    "gn:asciiname":"Qutayn al Qashami",
    "gn:country_code":"YE",
    "gn:dem":2276,
    "gn:feature_class":"P",
    "gn:feature_code":"PPL",
    "gn:name":"Qu\u0163ayn al Qash\u0101m\u012b",
    "gn:population":0,
    "gn:timezone":"Asia/Aden",
    "iso:country":"YE",
    "name:und_x_variant":[
        "Qu\u0163ayn al Qash\u0101m\u012b"
    ],
    "wof:name":"Qutayn al Qashami",
    "wof:placetype":"locality"
},
  "geometry": {"coordinates":[44.4466,15.11087],"type":"Point"}
}