{
  "type": "Feature",
  "properties": {
    "gn:admin1_code":"19.0",
    "gn:admin2_code":"2911.0",
    "gn:asciiname":"Bayt al Hamdi",
    "gn:country_code":"YE",
    "gn:dem":2199,
    "gn:feature_class":"P",
    "gn:feature_code":"PPL",
    "gn:name":"Bayt al \u1e28amd\u012b",
    "gn:population":0,
    "gn:timezone":"Asia/Aden",
    "iso:country":"YE",
    "name:ara_x_preferred":[
        "\u0628\u064a\u062a \u0627\u0644\u062d\u0645\u062f\u064a"
    ],
    "name:und_x_variant":[
        "Bayt al \u1e28amd\u012b"
    ],
    "wof:name":"Bayt al Hamdi",
    "wof:placetype":"locality"
},
  "geometry": {"coordinates":[44.0512,15.7816],"type":"Point"}
}