{
  "type": "Feature",
  "properties": {
    "gn:admin1_code":"16.0",
    "gn:admin2_code":"2313.0",
    "gn:asciiname":"Al Hikam",
    "gn:country_code":"YE",
    "gn:dem":2548,
    "gn:feature_class":"P",
    "gn:feature_code":"PPL",
    "gn:name":"Al \u1e28ik\u0101m",
    "gn:population":0,
    "gn:timezone":"Asia/Aden",
    "iso:country":"YE",
    "name:ara_x_preferred":[
        "\u0627\u0644\u062d\u0643\u0627\u0645"
    ],
    "name:und_x_variant":[
        "Al \u1e28ik\u0101m"
    ],
    "wof:name":"Al Hikam",
    "wof:placetype":"locality"
},
  "geometry": {"coordinates":[44.5053,15.3543],"type":"Point"}
}