{
  "type": "Feature",
  "properties": {
    "gn:admin1_code":"22.0",
    "gn:admin2_code":"1721.0",
    "gn:asciiname":"Sa`dan al Amrud",
    "gn:country_code":"YE",
    "gn:dem":1534,
    "gn:feature_class":"P",
    "gn:feature_code":"PPL",
    "gn:name":"Sa\u2018d\u0101n al Amr\u016bd",
    "gn:population":0,
    "gn:timezone":"Asia/Aden",
    "iso:country":"YE",
    "name:und_x_variant":[
        "Sa\u2018d\u0101n al Amr\u016bd",
        "Si\u2018d\u0101n"
    ],
    "wof:name":"Sa`dan al Amrud",
    "wof:placetype":"locality"
},
  "geometry": {"coordinates":[43.46378,15.86484],"type":"Point"}
}