{
  "type": "Feature",
  "properties": {
    "gn:admin1_code":"23.0",
    "gn:admin2_code":"1115.0",
    "gn:asciiname":"Dhi Hurmat",
    "gn:country_code":"YE",
    "gn:dem":2477,
    "gn:feature_class":"P",
    "gn:feature_code":"PPL",
    "gn:name":"Dh\u012b \u1e28urm\u0101t",
    "gn:population":0,
    "gn:timezone":"Asia/Aden",
    "iso:country":"YE",
    "name:ara_x_preferred":[
        "Dh\u012b \u1e28urm\u0101t"
    ],
    "wof:name":"Dhi Hurmat",
    "wof:placetype":"locality"
},
  "geometry": {"coordinates":[44.13895,13.84403],"type":"Point"}
}