{
  "type": "Feature",
  "properties": {
    "gn:admin1_code":"15.0",
    "gn:admin2_code":"2210.0",
    "gn:asciiname":"Al Ghuraybah",
    "gn:country_code":"YE",
    "gn:dem":1992,
    "gn:feature_class":"P",
    "gn:feature_code":"PPL",
    "gn:name":"\u0100l Ghuraybah",
    "gn:population":0,
    "gn:timezone":"Asia/Aden",
    "iso:country":"YE",
    "name:ara_x_preferred":[
        "\u0627\u0644 \u063a\u0631\u064a\u0628\u0629"
    ],
    "name:und_x_variant":[
        "\u0100l Ghar\u012bsah",
        "\u0100l Ghuraybah"
    ],
    "wof:name":"Al Ghuraybah",
    "wof:placetype":"locality"
},
  "geometry": {"coordinates":[43.57901,17.07564],"type":"Point"}
}