{
  "type": "Feature",
  "properties": {
    "gn:admin1_code":"15.0",
    "gn:admin2_code":"2208.0",
    "gn:asciiname":"Jidan",
    "gn:cc2":"YE",
    "gn:country_code":"YE",
    "gn:dem":2428,
    "gn:feature_class":"P",
    "gn:feature_code":"PPL",
    "gn:name":"J\u012bd\u0101n",
    "gn:population":0,
    "gn:timezone":"Asia/Aden",
    "iso:country":"YE",
    "name:ara_x_preferred":[
        "J\u012bd\u0101n"
    ],
    "name:und_x_variant":[
        "Jindhan"
    ],
    "wof:name":"Jidan",
    "wof:placetype":"locality"
},
  "geometry": {"coordinates":[43.41667,16.78333],"type":"Point"}
}