{
  "type": "Feature",
  "properties": {
    "gn:admin1_code":"8.0",
    "gn:admin2_code":"1812.0",
    "gn:asciiname":"Al Miqwar",
    "gn:country_code":"YE",
    "gn:dem":1182,
    "gn:feature_class":"P",
    "gn:feature_code":"PPL",
    "gn:name":"Al Miqw\u0101r",
    "gn:population":0,
    "gn:timezone":"Asia/Aden",
    "iso:country":"YE",
    "name:ara_x_preferred":[
        "\u0627\u0644\u0645\u0642\u0648\u0627\u0631"
    ],
    "name:und_x_variant":[
        "Al Miqw\u0101r"
    ],
    "wof:name":"Al Miqwar",
    "wof:placetype":"locality"
},
  "geometry": {"coordinates":[43.43312,14.92139],"type":"Point"}
}