{
  "type": "Feature",
  "properties": {
    "gn:country":"YE",
    "gn:fcode":"PPL",
    "gn:pop":5,
    "iso:country":"YE",
    "name:ara_x_preferred":[
        "\u0623\u0642\u0631\u0639"
    ],
    "name:eng_x_preferred":[
        "Aqra'"
    ],
    "name:eng_x_variant":[
        "\u1e28ar\u0101n"
    ],
    "qs:name":"Aqra\u2018",
    "qs:photos_9r":0,
    "qs:photos_sr":0,
    "qs:pop_sr":"1",
    "wof:name":"Aqra\u2018",
    "wof:placetype":"locality",
    "wof:population":5
},
  "geometry": {"coordinates":[43.33916,16.89235],"type":"Point"}
}