{
  "type": "Feature",
  "properties": {
    "gn:admin1_code":"10.0",
    "gn:admin2_code":"2709.0",
    "gn:asciiname":"Nu`man",
    "gn:country_code":"YE",
    "gn:dem":1611,
    "gn:feature_class":"P",
    "gn:feature_code":"PPL",
    "gn:name":"Nu\u2018m\u0101n",
    "gn:population":0,
    "gn:timezone":"Asia/Aden",
    "iso:country":"YE",
    "name:ara_x_preferred":[
        "Nu\u2018m\u0101n"
    ],
    "wof:name":"Nu`man",
    "wof:placetype":"locality"
},
  "geometry": {"coordinates":[43.51018,15.46719],"type":"Point"}
}