{
  "type": "Feature",
  "properties": {
    "gn:admin1_code":"22.0",
    "gn:admin2_code":"1726.0",
    "gn:asciiname":"Ash Shawahil",
    "gn:country_code":"YE",
    "gn:dem":1533,
    "gn:feature_class":"P",
    "gn:feature_code":"PPL",
    "gn:name":"Ash Shaw\u0101hil",
    "gn:population":0,
    "gn:timezone":"Asia/Aden",
    "iso:country":"YE",
    "name:und_x_variant":[
        "Ash Shaw\u0101hil"
    ],
    "wof:name":"Ash Shawahil",
    "wof:placetype":"locality"
},
  "geometry": {"coordinates":[43.54845,15.62948],"type":"Point"}
}