{
  "type": "Feature",
  "properties": {
    "gn:admin1_code":"24.0",
    "gn:admin2_code":"2513.0",
    "gn:asciiname":"Ashai Zuwaira",
    "gn:country_code":"YE",
    "gn:dem":332,
    "gn:feature_class":"P",
    "gn:feature_code":"PPL",
    "gn:name":"Ashai Zuwaira",
    "gn:population":0,
    "gn:timezone":"Asia/Aden",
    "iso:country":"YE",
    "wof:name":"Ashai Zuwaira",
    "wof:placetype":"locality"
},
  "geometry": {"coordinates":[43.95806,12.97482],"type":"Point"}
}