{
  "type": "Feature",
  "properties": {
    "gn:admin1_code":"4.0",
    "gn:admin2_code":"1909.0",
    "gn:asciiname":"Birak",
    "gn:cc2":"YE",
    "gn:country_code":"YE",
    "gn:dem":955,
    "gn:feature_class":"P",
    "gn:feature_code":"PPL",
    "gn:name":"Birak",
    "gn:population":0,
    "gn:timezone":"Asia/Aden",
    "iso:country":"YE",
    "name:und_x_variant":[
        "Birik",
        "Birak"
    ],
    "wof:name":"Birak",
    "wof:placetype":"locality"
},
  "geometry": {"coordinates":[48.83333,15.51667],"type":"Point"}
}