{
  "type": "Feature",
  "properties": {
    "gn:admin1_code":"27.0",
    "gn:admin2_code":"3101.0",
    "gn:asciiname":"Az Zawi",
    "gn:country_code":"YE",
    "gn:dem":687,
    "gn:feature_class":"P",
    "gn:feature_code":"PPL",
    "gn:name":"Az Z\u0101w\u012b",
    "gn:population":0,
    "gn:timezone":"Asia/Aden",
    "iso:country":"YE",
    "name:ara_x_preferred":[
        "Az Z\u0101w\u012b"
    ],
    "wof:name":"Az Zawi",
    "wof:placetype":"locality"
},
  "geometry": {"coordinates":[43.54594,14.88627],"type":"Point"}
}