{
  "type": "Feature",
  "properties": {
    "gn:admin1_code":"19.0",
    "gn:admin2_code":"2909.0",
    "gn:asciiname":"Al Harash",
    "gn:country_code":"YE",
    "gn:dem":2270,
    "gn:feature_class":"P",
    "gn:feature_code":"PPL",
    "gn:name":"Al \u1e28arash",
    "gn:population":0,
    "gn:timezone":"Asia/Aden",
    "iso:country":"YE",
    "name:ara_x_preferred":[
        "\u0627\u0644\u062d\u0631\u0634"
    ],
    "name:und_x_variant":[
        "Al \u1e28arash"
    ],
    "wof:name":"Al Harash",
    "wof:placetype":"locality"
},
  "geometry": {"coordinates":[44.15245,16.06461],"type":"Point"}
}