{
  "type": "Feature",
  "properties": {
    "gn:admin1_code":"24.0",
    "gn:admin2_code":"2512.0",
    "gn:asciiname":"Al Qajr",
    "gn:country_code":"YE",
    "gn:dem":1095,
    "gn:feature_class":"P",
    "gn:feature_code":"PPL",
    "gn:name":"Al Qajr",
    "gn:population":0,
    "gn:timezone":"Asia/Aden",
    "iso:country":"YE",
    "name:ara_x_preferred":[
        "\u0627\u0644\u0642\u062c\u0631"
    ],
    "wof:name":"Al Qajr",
    "wof:placetype":"locality"
},
  "geometry": {"coordinates":[44.16066,13.12418],"type":"Point"}
}