{
  "type": "Feature",
  "properties": {
    "gn:admin1_code":"16.0",
    "gn:admin2_code":"2303.0",
    "gn:asciiname":"Sha'b Ghaylan",
    "gn:country_code":"YE",
    "gn:dem":2086,
    "gn:feature_class":"P",
    "gn:feature_code":"PPL",
    "gn:name":"Sha\u2018b Ghayl\u0101n",
    "gn:population":0,
    "gn:timezone":"Asia/Aden",
    "iso:country":"YE",
    "name:ara_x_preferred":[
        "\u0634\u0639\u0628 \u063a\u064a\u0644\u0627\u0646"
    ],
    "name:und_x_variant":[
        "Sha\u2018b Ghayl\u0101n"
    ],
    "wof:name":"Sha'b Ghaylan",
    "wof:placetype":"locality"
},
  "geometry": {"coordinates":[44.4054,15.61774],"type":"Point"}
}