{
  "type": "Feature",
  "properties": {
    "gn:admin1_code":"19.0",
    "gn:admin2_code":"2905.0",
    "gn:asciiname":"Al Qasabah",
    "gn:country_code":"YE",
    "gn:dem":1303,
    "gn:feature_class":"P",
    "gn:feature_code":"PPL",
    "gn:name":"Al Qa\u015fabah",
    "gn:population":0,
    "gn:timezone":"Asia/Aden",
    "iso:country":"YE",
    "name:ara_x_preferred":[
        "\u0627\u0644\u0642\u0635\u0628\u0640\u0629"
    ],
    "name:und_x_variant":[
        "Al Qa\u015fabah"
    ],
    "wof:name":"Al Qasabah",
    "wof:placetype":"locality"
},
  "geometry": {"coordinates":[43.72832,16.16418],"type":"Point"}
}