{
  "type": "Feature",
  "properties": {
    "gn:country":"YE",
    "gn:fcode":"PPL",
    "gn:population":11,
    "iso:country":"YE",
    "name:ara_x_preferred":[
        "Al \u2018\u0100bir"
    ],
    "name:ara_x_variant":[
        "\u0627\u0644\u0639\u0627\u0628\u0631"
    ],
    "name:eng_x_preferred":[
        "Al 'Abir"
    ],
    "name:eng_x_variant":[
        "\u0162awr Ba\u015f\u012br"
    ],
    "qs:name":"Al \u2018\u0100bir",
    "qs:photos_9r":0,
    "qs:photos_sr":0,
    "qs:pop_sr":"1",
    "wof:name":"Al \u2018\u0100bir",
    "wof:placetype":"locality",
    "wof:population":11
},
  "geometry": {"coordinates":[45.80622,14.27972],"type":"Point"}
}