{
  "type": "Feature",
  "properties": {
    "gn:admin1_code":"14.0",
    "gn:admin2_code":"2607.0",
    "gn:asciiname":"Al Ghumayyis",
    "gn:country_code":"YE",
    "gn:dem":1288,
    "gn:feature_class":"P",
    "gn:feature_code":"PPL",
    "gn:name":"Al Ghumayyis",
    "gn:population":0,
    "gn:timezone":"Asia/Aden",
    "iso:country":"YE",
    "name:ara_x_preferred":[
        "\u0627\u0644\u063a\u0645\u064a\u0633"
    ],
    "wof:name":"Al Ghumayyis",
    "wof:placetype":"locality"
},
  "geometry": {"coordinates":[45.3336,15.02541],"type":"Point"}
}