{
  "type": "Feature",
  "properties": {
    "gn:admin1_code":"8.0",
    "gn:admin2_code":"1805.0",
    "gn:asciiname":"Dayr al Busut",
    "gn:country_code":"YE",
    "gn:dem":58,
    "gn:feature_class":"P",
    "gn:feature_code":"PPL",
    "gn:name":"Dayr al Bu\u015f\u016b\u0163",
    "gn:population":0,
    "gn:timezone":"Asia/Aden",
    "iso:country":"YE",
    "name:und_x_variant":[
        "Dayr al Bu\u015f\u016b\u0163"
    ],
    "wof:name":"Dayr al Busut",
    "wof:placetype":"locality"
},
  "geometry": {"coordinates":[43.02926,15.46264],"type":"Point"}
}