{
  "type": "Feature",
  "properties": {
    "gn:admin1_code":"25.0",
    "gn:admin2_code":"1515.0",
    "gn:asciiname":"Mahalib ad Dakhil",
    "gn:country_code":"YE",
    "gn:dem":1126,
    "gn:feature_class":"P",
    "gn:feature_code":"PPL",
    "gn:name":"Ma\u1e29\u0101l\u012bb ad D\u0101khil",
    "gn:population":1,
    "gn:timezone":"Asia/Aden",
    "iso:country":"YE",
    "name:ara_x_preferred":[
        "\u0627\u0644\u0645\u062d\u0627\u0644\u064a\u0628 \u0627\u0644\u062f\u0627\u062e\u0644"
    ],
    "name:und_x_variant":[
        "Ma\u1e29\u0101l\u012bb ad D\u0101khil"
    ],
    "wof:name":"Mahalib ad Dakhil",
    "wof:placetype":"locality",
    "wof:population":1
},
  "geometry": {"coordinates":[43.9843,13.24172],"type":"Point"}
}