{
  "type": "Feature",
  "properties": {
    "gn:country":"YE",
    "gn:fcode":"HSE",
    "gn:pop":1,
    "iso:country":"YE",
    "name:ara_x_preferred":[
        "Al Qur\u1e11iy\u0101t"
    ],
    "name:ara_x_variant":[
        "\u0627\u0644\u0642\u0631\u0636\u064a\u0627\u062a"
    ],
    "qs:name":"Al Qur\u1e11iy\u0101t",
    "qs:photos_9r":0,
    "qs:photos_sr":0,
    "qs:pop_sr":"1",
    "wof:name":"Al Qur\u1e11iy\u0101t",
    "wof:placetype":"locality",
    "wof:population":1
},
  "geometry": {"coordinates":[43.27522,16.21792],"type":"Point"}
}