{
  "type": "Feature",
  "properties": {
    "gn:admin1_code":"25.0",
    "gn:admin2_code":"1501.0",
    "gn:asciiname":"Wabaran",
    "gn:country_code":"YE",
    "gn:dem":1317,
    "gn:feature_class":"P",
    "gn:feature_code":"PPL",
    "gn:name":"Wabar\u0101n",
    "gn:population":0,
    "gn:timezone":"Asia/Aden",
    "iso:country":"YE",
    "name:und_x_variant":[
        "Wabar\u0101n"
    ],
    "wof:name":"Wabaran",
    "wof:placetype":"locality"
},
  "geometry": {"coordinates":[44.39245,13.55351],"type":"Point"}
}