{
  "type": "Feature",
  "properties": {
    "gn:admin1_code":"25.0",
    "gn:admin2_code":"1523.0",
    "gn:asciiname":"Al Qatab",
    "gn:country_code":"YE",
    "gn:dem":2083,
    "gn:feature_class":"P",
    "gn:feature_code":"PPL",
    "gn:name":"Al Qa\u1e6dab",
    "gn:population":0,
    "gn:timezone":"Asia/Aden",
    "iso:country":"YE",
    "name:und_x_variant":[
        "Al Qa\u1e6dab"
    ],
    "wof:name":"Al Qatab",
    "wof:placetype":"locality"
},
  "geometry": {"coordinates":[44.08292,13.3847],"type":"Point"}
}