{
  "type": "Feature",
  "properties": {
    "gn:country":"YE",
    "gn:fcode":"PPL",
    "gn:population":3,
    "iso:country":"YE",
    "name:ara_x_preferred":[
        "\u0627\u0644\u0642\u0631\u0639\u0627\u0621"
    ],
    "name:eng_x_preferred":[
        "Al Qar'a"
    ],
    "name:eng_x_variant":[
        "Al \u2018Uwayr\u012b"
    ],
    "qs:name":"Al Qar\u2018\u0101\u2019",
    "qs:photos_9r":0,
    "qs:photos_sr":0,
    "qs:pop_sr":"1",
    "wof:name":"Al Qar\u2018\u0101\u2019",
    "wof:placetype":"locality",
    "wof:population":3
},
  "geometry": {"coordinates":[43.63909,16.0601],"type":"Point"}
}