{
  "type": "Feature",
  "properties": {
    "gn:country":"YE",
    "gn:fcode":"FRM",
    "gn:pop":2,
    "iso:country":"YE",
    "name:ara_x_preferred":[
        "\u0627\u0644\u0637\u0644\u062d"
    ],
    "qs:name":"A\u0163 \u0162al\u1e29",
    "qs:photos_9r":0,
    "qs:photos_sr":0,
    "qs:pop_sr":"1",
    "wof:name":"A\u0163 \u0162al\u1e29",
    "wof:placetype":"locality",
    "wof:population":2
},
  "geometry": {"coordinates":[44.10408,16.37403],"type":"Point"}
}