{
  "type": "Feature",
  "properties": {
    "gn:country":"YE",
    "gn:fcode":"PPL",
    "gn:pop":20,
    "iso:country":"YE",
    "name:ara_x_preferred":[
        "\u0628\u064a\u062a \u0627\u0644\u0623\u0647\u0646\u0648\u0645\u064a"
    ],
    "name:eng_x_preferred":[
        "Bayt Al Ahnawmi"
    ],
    "qs:name":"Bayt al Ahnawm\u012b",
    "qs:photos_9r":0,
    "qs:photos_sr":0,
    "qs:pop_sr":"1",
    "wof:name":"Bayt al Ahnawm\u012b",
    "wof:placetype":"locality",
    "wof:population":20
},
  "geometry": {"coordinates":[43.43805,16.04876],"type":"Point"}
}