{
  "type": "Feature",
  "properties": {
    "gn:admin1_code":"19.0",
    "gn:admin2_code":"2912.0",
    "gn:asciiname":"Al Halhalah",
    "gn:country_code":"YE",
    "gn:dem":2560,
    "gn:feature_class":"P",
    "gn:feature_code":"PPL",
    "gn:name":"Al \u1e28al\u1e29alah",
    "gn:population":0,
    "gn:timezone":"Asia/Aden",
    "iso:country":"YE",
    "name:und_x_variant":[
        "Al \u1e28al\u1e29alah",
        "\u1e28al\u1e29al"
    ],
    "wof:name":"Al Halhalah",
    "wof:placetype":"locality"
},
  "geometry": {"coordinates":[43.87879,15.87114],"type":"Point"}
}