{
  "type": "Feature",
  "properties": {
    "gn:admin1_code":"23.0",
    "gn:admin2_code":"1120.0",
    "gn:asciiname":"Al Ja`ashi",
    "gn:country_code":"YE",
    "gn:dem":2630,
    "gn:feature_class":"P",
    "gn:feature_code":"PPL",
    "gn:name":"Al Ja\u2018\u0101sh\u012b",
    "gn:population":0,
    "gn:timezone":"Asia/Aden",
    "iso:country":"YE",
    "name:und_x_variant":[
        "Al Ja\u2018\u0101sh\u012b"
    ],
    "wof:name":"Al Ja`ashi",
    "wof:placetype":"locality"
},
  "geometry": {"coordinates":[44.21679,13.96493],"type":"Point"}
}