{
  "type": "Feature",
  "properties": {
    "gn:admin1_code":"16.0",
    "gn:admin2_code":"2302.0",
    "gn:asciiname":"Dar A`la",
    "gn:country_code":"YE",
    "gn:dem":2155,
    "gn:feature_class":"P",
    "gn:feature_code":"PPL",
    "gn:name":"D\u0101r A\u2018l\u00e1",
    "gn:population":0,
    "gn:timezone":"Asia/Aden",
    "iso:country":"YE",
    "name:ara_x_preferred":[
        "D\u0101r A\u2018l\u00e1"
    ],
    "wof:name":"Dar A`la",
    "wof:placetype":"locality"
},
  "geometry": {"coordinates":[44.24771,15.58511],"type":"Point"}
}