{
  "type": "Feature",
  "properties": {
    "gn:admin1_code":"19.0",
    "gn:admin2_code":"2919.0",
    "gn:asciiname":"Al Mahjal",
    "gn:country_code":"YE",
    "gn:dem":1552,
    "gn:feature_class":"P",
    "gn:feature_code":"PPL",
    "gn:name":"Al Ma\u1e29jal",
    "gn:population":0,
    "gn:timezone":"Asia/Aden",
    "iso:country":"YE",
    "name:ara_x_preferred":[
        "\u0627\u0644\u0645\u062d\u062c\u0644"
    ],
    "name:und_x_variant":[
        "Al Ma\u1e29jal"
    ],
    "wof:name":"Al Mahjal",
    "wof:placetype":"locality"
},
  "geometry": {"coordinates":[43.84165,16.09321],"type":"Point"}
}