{
  "type": "Feature",
  "properties": {
    "gn:admin1_code":"1.0",
    "gn:admin2_code":"1201.0",
    "gn:asciiname":"Al Haq",
    "gn:country_code":"YE",
    "gn:dem":629,
    "gn:feature_class":"P",
    "gn:feature_code":"PPL",
    "gn:name":"Al \u1e28\u0101q",
    "gn:population":0,
    "gn:timezone":"Asia/Aden",
    "iso:country":"YE",
    "name:ara_x_preferred":[
        "\u0627\u0644\u062d\u0627\u0642"
    ],
    "name:ara_x_variant":[
        "Al \u1e28\u0101q"
    ],
    "wof:name":"Al Haq",
    "wof:placetype":"locality"
},
  "geometry": {"coordinates":[46.85591,14.08711],"type":"Point"}
}