{
  "type": "Feature",
  "properties": {
    "gn:admin1_code":"10.0",
    "gn:admin2_code":"2709.0",
    "gn:asciiname":"Bayt Shahidhi",
    "gn:country_code":"YE",
    "gn:dem":1435,
    "gn:feature_class":"P",
    "gn:feature_code":"PPL",
    "gn:name":"Bayt Sh\u0101\u1e29idh\u012b",
    "gn:population":0,
    "gn:timezone":"Asia/Aden",
    "iso:country":"YE",
    "name:und_x_variant":[
        "Bayt Sh\u0101\u1e29idh\u012b",
        "Bayt ash Sh\u0101\u1e29idh\u012b"
    ],
    "wof:name":"Bayt Shahidhi",
    "wof:placetype":"locality"
},
  "geometry": {"coordinates":[43.49927,15.46653],"type":"Point"}
}