{
  "type": "Feature",
  "properties": {
    "gn:country":"YE",
    "gn:fcode":"PPL",
    "gn:population":5,
    "iso:country":"YE",
    "name:ara_x_preferred":[
        "\u0627\u0644\u0628\u062d\u0631\u0629"
    ],
    "name:eng_x_preferred":[
        "Al Bahirah"
    ],
    "name:eng_x_variant":[
        "Al Ma\u1e29r\u016bj"
    ],
    "qs:name":"Al Ba\u1e29irah",
    "qs:photos_9r":0,
    "qs:photos_sr":0,
    "qs:pop_sr":"1",
    "wof:name":"Al Ba\u1e29irah",
    "wof:placetype":"locality",
    "wof:population":5
},
  "geometry": {"coordinates":[44.82837,16.83859],"type":"Point"}
}