{
  "type": "Feature",
  "properties": {
    "gn:country":"YE",
    "gn:fcode":"PPL",
    "gn:population":1,
    "iso:country":"YE",
    "name:ara_x_preferred":[
        "Shi\u2018r\u0101n"
    ],
    "name:ara_x_variant":[
        "\u0634\u0639\u0631\u0627\u0646"
    ],
    "name:eng_x_preferred":[
        "Shi'ran"
    ],
    "qs:name":"Shi\u2018r\u0101n",
    "qs:photos_9r":0,
    "qs:photos_sr":0,
    "qs:pop_sr":"1",
    "wof:name":"Shi\u2018r\u0101n",
    "wof:placetype":"locality",
    "wof:population":1
},
  "geometry": {"coordinates":[43.44336,16.68322],"type":"Point"}
}