{
  "type": "Feature",
  "properties": {
    "gn:admin1_code":"19.0",
    "gn:admin2_code":"2909.0",
    "gn:asciiname":"Dhaybin",
    "gn:country_code":"YE",
    "gn:dem":1876,
    "gn:feature_class":"P",
    "gn:feature_code":"PPLA2",
    "gn:name":"Dhayb\u012bn",
    "gn:population":0,
    "gn:timezone":"Asia/Aden",
    "iso:country":"YE",
    "name:ara_x_preferred":[
        "Dh\u012b B\u012bn"
    ],
    "name:ara_x_variant":[
        "\u0630\u064a \u0628\u064a\u0646",
        "\u0630\u064a\u0628\u064a\u0646"
    ],
    "name:und_x_variant":[
        "\u1e0e\u012b B\u012bn",
        "Dh\u012b Bayn",
        "Dhubayn",
        "Dhayb\u012bn"
    ],
    "wof:name":"Dhaybin",
    "wof:placetype":"locality"
},
  "geometry": {"coordinates":[44.12917,15.97712],"type":"Point"}
}