{
  "type": "Feature",
  "properties": {
    "gn:country":"YE",
    "gn:fcode":"PPLX",
    "gn:pop":4,
    "iso:country":"YE",
    "name:ara_x_preferred":[
        "\u0100l R\u0101shid"
    ],
    "name:ara_x_variant":[
        "\u0622\u0644 \u0631\u0627\u0634\u062f"
    ],
    "qs:name":"\u0100l R\u0101shid",
    "qs:photos_9r":0,
    "qs:photos_sr":0,
    "qs:pop_sr":"1",
    "wof:name":"\u0100l R\u0101shid",
    "wof:placetype":"neighbourhood",
    "wof:population":4
},
  "geometry": {"coordinates":[43.80102,16.88804],"type":"Point"}
}