{
  "type": "Feature",
  "properties": {
    "gn:admin1_code":"23.0",
    "gn:admin2_code":"1102.0",
    "gn:asciiname":"Najd as Sadd",
    "gn:country_code":"YE",
    "gn:dem":2295,
    "gn:feature_class":"P",
    "gn:feature_code":"PPLL",
    "gn:name":"Najd as Sadd",
    "gn:population":0,
    "gn:timezone":"Asia/Aden",
    "iso:country":"YE",
    "name:ara_x_preferred":[
        "\u0646\u062c\u062f \u0627\u0644\u0633\u062f"
    ],
    "wof:name":"Najd as Sadd",
    "wof:placetype":"locality"
},
  "geometry": {"coordinates":[44.17813,14.32293],"type":"Point"}
}