{
  "type": "Feature",
  "properties": {
    "gn:country":"YE",
    "gn:fcode":"PPL",
    "gn:pop":13,
    "iso:country":"YE",
    "name:ara_x_preferred":[
        "\u0627\u0644\u0628\u0631\u0627\u0643"
    ],
    "qs:name":"Al Bar\u0101k",
    "qs:photos_9r":0,
    "qs:photos_sr":0,
    "qs:pop_sr":"1",
    "wof:name":"Al Bar\u0101k",
    "wof:placetype":"locality",
    "wof:population":13
},
  "geometry": {"coordinates":[43.3346,16.84241],"type":"Point"}
}