{
  "type": "Feature",
  "properties": {
    "gn:admin1_code":"22.0",
    "gn:admin2_code":"1705.0",
    "gn:asciiname":"Al Ma`awizah",
    "gn:country_code":"YE",
    "gn:dem":125,
    "gn:feature_class":"P",
    "gn:feature_code":"PPL",
    "gn:name":"Al Ma\u2018\u0101wizah",
    "gn:population":0,
    "gn:timezone":"Asia/Aden",
    "iso:country":"YE",
    "name:ara_x_preferred":[
        "\u0627\u0644\u0645\u0639\u0627\u0648\u0632\u0629"
    ],
    "name:und_x_variant":[
        "Al Mi\u2018\u0101wizah",
        "Mi\u2019\u0101wizah",
        "Al Ma\u2018awzah",
        "Al Ma\u2018\u0101wizah"
    ],
    "wof:name":"Al Ma`awizah",
    "wof:placetype":"locality"
},
  "geometry": {"coordinates":[43.13037,16.27332],"type":"Point"}
}