{
  "type": "Feature",
  "properties": {
    "gn:admin1_code":"8.0",
    "gn:admin2_code":"1801.0",
    "gn:asciiname":"Buyut Faris",
    "gn:country_code":"YE",
    "gn:dem":53,
    "gn:feature_class":"P",
    "gn:feature_code":"PPL",
    "gn:name":"Buy\u016bt F\u0101ris",
    "gn:population":0,
    "gn:timezone":"Asia/Aden",
    "iso:country":"YE",
    "name:ara_x_preferred":[
        "\u0628\u064a\u0648\u062a \u0641\u0627\u0631\u0633"
    ],
    "name:und_x_variant":[
        "Buy\u016bt F\u0101ris"
    ],
    "wof:name":"Buyut Faris",
    "wof:placetype":"locality"
},
  "geometry": {"coordinates":[42.91173,15.77473],"type":"Point"}
}