{
  "type": "Feature",
  "properties": {
    "gn:admin1_code":"11.0",
    "gn:admin2_code":"2012.0",
    "gn:asciiname":"Al Mihdajah",
    "gn:country_code":"YE",
    "gn:dem":1987,
    "gn:feature_class":"P",
    "gn:feature_code":"PPL",
    "gn:name":"Al Mi\u1e29d\u0101jah",
    "gn:population":0,
    "gn:timezone":"Asia/Aden",
    "iso:country":"YE",
    "name:und_x_variant":[
        "Al Mi\u1e29d\u0101jah"
    ],
    "wof:name":"Al Mihdajah",
    "wof:placetype":"locality"
},
  "geometry": {"coordinates":[44.21484,14.63464],"type":"Point"}
}