{
  "type": "Feature",
  "properties": {
    "gn:admin1_code":"23.0",
    "gn:admin2_code":"1108.0",
    "gn:asciiname":"Ar Ruqay`iyah",
    "gn:country_code":"YE",
    "gn:dem":1307,
    "gn:feature_class":"P",
    "gn:feature_code":"PPL",
    "gn:name":"Ar Ruqay\u2018\u012byah",
    "gn:population":0,
    "gn:timezone":"Asia/Aden",
    "iso:country":"YE",
    "name:ara_x_preferred":[
        "\u0627\u0644\u0631\u0642\u0639\u0628\u0629"
    ],
    "name:und_x_variant":[
        "Ar Ruqay\u2018\u012byah",
        "Ar Raq\u2018abah"
    ],
    "wof:name":"Ar Ruqay`iyah",
    "wof:placetype":"locality"
},
  "geometry": {"coordinates":[44.06558,14.19464],"type":"Point"}
}