{
  "type": "Feature",
  "properties": {
    "gn:admin1_code":"23.0",
    "gn:admin2_code":"1104.0",
    "gn:asciiname":"Al Fajrah",
    "gn:country_code":"YE",
    "gn:dem":2311,
    "gn:feature_class":"P",
    "gn:feature_code":"PPL",
    "gn:name":"Al Fajrah",
    "gn:population":0,
    "gn:timezone":"Asia/Aden",
    "iso:country":"YE",
    "name:ara_x_preferred":[
        "\u0627\u0644\u0641\u062c\u0631\u0629"
    ],
    "wof:name":"Al Fajrah",
    "wof:placetype":"locality"
},
  "geometry": {"coordinates":[44.46477,14.08632],"type":"Point"}
}