{
  "type": "Feature",
  "properties": {
    "gn:admin1_code":"25.0",
    "gn:admin2_code":"1515.0",
    "gn:asciiname":"Al Manzarah",
    "gn:country_code":"YE",
    "gn:dem":1174,
    "gn:feature_class":"P",
    "gn:feature_code":"PPL",
    "gn:name":"Al Manz\u0327arah",
    "gn:population":0,
    "gn:timezone":"Asia/Aden",
    "iso:country":"YE",
    "name:ara_x_preferred":[
        "\u0627\u0644\u0645\u0646\u0638\u0631\u0629"
    ],
    "name:und_x_variant":[
        "Al Manz\u0327arah"
    ],
    "wof:name":"Al Manzarah",
    "wof:placetype":"locality"
},
  "geometry": {"coordinates":[43.97344,13.16884],"type":"Point"}
}