{
  "type": "Feature",
  "properties": {
    "gn:country":"YE",
    "gn:fcode":"PPLL",
    "gn:pop":7,
    "iso:country":"YE",
    "name:ara_x_preferred":[
        "Al Miqsh\u0101b"
    ],
    "name:ara_x_variant":[
        "\u0627\u0644\u0645\u0642\u0634\u0627\u0628"
    ],
    "qs:name":"Al Miqsh\u0101b",
    "qs:photos_9r":0,
    "qs:photos_sr":0,
    "qs:pop_sr":"1",
    "wof:name":"Al Miqsh\u0101b",
    "wof:placetype":"locality",
    "wof:population":7
},
  "geometry": {"coordinates":[43.28246,16.24085],"type":"Point"}
}