{
  "type": "Feature",
  "properties": {
    "gn:admin1_code":"25.0",
    "gn:admin2_code":"1505.0",
    "gn:asciiname":"Hadizah",
    "gn:country_code":"YE",
    "gn:dem":1108,
    "gn:feature_class":"P",
    "gn:feature_code":"PPL",
    "gn:name":"Had\u012bz\u0327ah",
    "gn:population":0,
    "gn:timezone":"Asia/Aden",
    "iso:country":"YE",
    "name:und_x_variant":[
        "Had\u012bz\u0327ah"
    ],
    "wof:name":"Hadizah",
    "wof:placetype":"locality"
},
  "geometry": {"coordinates":[43.72777,13.71591],"type":"Point"}
}