{
  "type": "Feature",
  "properties": {
    "gn:admin1_code":"10.0",
    "gn:admin2_code":"2707.0",
    "gn:asciiname":"Al Marbaz",
    "gn:country_code":"YE",
    "gn:dem":1581,
    "gn:feature_class":"P",
    "gn:feature_code":"PPL",
    "gn:name":"Al Marbaz\u0327",
    "gn:population":0,
    "gn:timezone":"Asia/Aden",
    "iso:country":"YE",
    "name:und_x_variant":[
        "Al Marbaz\u0327"
    ],
    "wof:name":"Al Marbaz",
    "wof:placetype":"locality"
},
  "geometry": {"coordinates":[43.46324,15.31067],"type":"Point"}
}