{
  "type": "Feature",
  "properties": {
    "gn:admin1_code":"8.0",
    "gn:admin2_code":"1810.0",
    "gn:asciiname":"Mahall al Kubayh",
    "gn:country_code":"YE",
    "gn:dem":126,
    "gn:feature_class":"P",
    "gn:feature_code":"PPL",
    "gn:name":"Ma\u1e29all al Kubay\u1e29",
    "gn:population":0,
    "gn:timezone":"Asia/Aden",
    "iso:country":"YE",
    "name:und_x_variant":[
        "Ma\u1e29all al Kubay\u1e29"
    ],
    "wof:name":"Mahall al Kubayh",
    "wof:placetype":"locality"
},
  "geometry": {"coordinates":[43.17919000000001,15.05906],"type":"Point"}
}