{
  "type": "Feature",
  "properties": {
    "gn:country":"YE",
    "gn:fcode":"PPL",
    "gn:pop":5,
    "iso:country":"YE",
    "name:ara_x_preferred":[
        "\u0630\u0648 \u0627\u0644\u0646\u0645\u0631\u064a\u0646 \u0642\u0634\u0627\u064a\u0628"
    ],
    "name:eng_x_preferred":[
        "DhU An Nimrin Qushayib"
    ],
    "qs:name":"Dh\u016b an Nimr\u012bn Qush\u0101yib",
    "qs:photos_9r":0,
    "qs:photos_sr":0,
    "qs:pop_sr":"1",
    "wof:name":"Dh\u016b an Nimr\u012bn Qush\u0101yib",
    "wof:placetype":"locality",
    "wof:population":5
},
  "geometry": {"coordinates":[45.27105,14.03216],"type":"Point"}
}