{
  "type": "Feature",
  "properties": {
    "gn:country":"YE",
    "gn:fcode":"PPL",
    "gn:pop":4,
    "iso:country":"YE",
    "name:ara_x_preferred":[
        "\u0627\u0644\u0631\u0632\u064a\u062d\u064a\u0640\u0629"
    ],
    "name:eng_x_preferred":[
        "Ar Rizayhiyah"
    ],
    "name:eng_x_variant":[
        "Al Kaw\u0101r"
    ],
    "qs:name":"Ar Rizay\u1e29\u012byah",
    "qs:photos_9r":0,
    "qs:photos_sr":0,
    "qs:pop_sr":"1",
    "wof:name":"Ar Rizay\u1e29\u012byah",
    "wof:placetype":"locality",
    "wof:population":4
},
  "geometry": {"coordinates":[43.30962,16.15571],"type":"Point"}
}