{
  "type": "Feature",
  "properties": {
    "gn:admin1_code":"22.0",
    "gn:admin2_code":"1727.0",
    "gn:asciiname":"Bayt Ghurabi",
    "gn:country_code":"YE",
    "gn:dem":1241,
    "gn:feature_class":"P",
    "gn:feature_code":"PPL",
    "gn:name":"Bayt Ghur\u0101b\u012b",
    "gn:population":0,
    "gn:timezone":"Asia/Aden",
    "iso:country":"YE",
    "name:ara_x_preferred":[
        "\u0628\u064a\u062a \u063a\u0631\u0627\u0628\u064a"
    ],
    "name:und_x_variant":[
        "Bayt Ghur\u0101b\u012b"
    ],
    "wof:name":"Bayt Ghurabi",
    "wof:placetype":"locality"
},
  "geometry": {"coordinates":[43.57058,15.58115],"type":"Point"}
}