{
  "type": "Feature",
  "properties": {
    "gn:admin1_code":"8.0",
    "gn:admin2_code":"1824.0",
    "gn:asciiname":"Sanif `Amir",
    "gn:country_code":"YE",
    "gn:dem":189,
    "gn:feature_class":"P",
    "gn:feature_code":"PPL",
    "gn:name":"\u015ean\u012bf \u2018\u0100mir",
    "gn:population":0,
    "gn:timezone":"Asia/Aden",
    "iso:country":"YE",
    "name:und_x_variant":[
        "\u015ean\u012bf \u2018\u0100mir"
    ],
    "wof:name":"Sanif `Amir",
    "wof:placetype":"locality"
},
  "geometry": {"coordinates":[43.44049,14.27834],"type":"Point"}
}