{
  "type": "Feature",
  "properties": {
    "gn:admin1_code":"22.0",
    "gn:admin2_code":"1725.0",
    "gn:asciiname":"Kharab al Ashraf",
    "gn:country_code":"YE",
    "gn:dem":858,
    "gn:feature_class":"P",
    "gn:feature_code":"PPL",
    "gn:name":"Khar\u0101b al Ashr\u0101f",
    "gn:population":0,
    "gn:timezone":"Asia/Aden",
    "iso:country":"YE",
    "name:ara_x_preferred":[
        "\u062e\u0631\u0627\u0628 \u0627\u0644\u0627\u0634\u0631\u0627\u0641"
    ],
    "name:und_x_variant":[
        "Khar\u0101b al Ashr\u0101f"
    ],
    "wof:name":"Kharab al Ashraf",
    "wof:placetype":"locality"
},
  "geometry": {"coordinates":[43.50627,15.58219],"type":"Point"}
}