{
  "type": "Feature",
  "properties": {
    "gn:admin1_code":"22.0",
    "gn:admin2_code":"1719.0",
    "gn:asciiname":"Mahall al Jawmar",
    "gn:country_code":"YE",
    "gn:dem":1550,
    "gn:feature_class":"P",
    "gn:feature_code":"PPL",
    "gn:name":"Ma\u1e29all al Jawmar",
    "gn:population":0,
    "gn:timezone":"Asia/Aden",
    "iso:country":"YE",
    "name:und_x_variant":[
        "Ma\u1e29all al Jawmar"
    ],
    "wof:name":"Mahall al Jawmar",
    "wof:placetype":"locality"
},
  "geometry": {"coordinates":[43.68332,15.69655],"type":"Point"}
}