{
  "type": "Feature",
  "properties": {
    "gn:country":"YE",
    "gn:fcode":"PPL",
    "gn:pop":6,
    "iso:country":"YE",
    "name:ara_x_preferred":[
        "\u0100l Q\u0101\u015fir"
    ],
    "name:ara_x_variant":[
        "\u0622\u0644 \u0642\u0627\u0635\u0631"
    ],
    "qs:name":"\u0100l Q\u0101\u015fir",
    "qs:photos_9r":0,
    "qs:photos_sr":0,
    "qs:pop_sr":"1",
    "wof:name":"\u0100l Q\u0101\u015fir",
    "wof:placetype":"locality",
    "wof:population":6
},
  "geometry": {"coordinates":[44.18888,16.91923],"type":"Point"}
}