{
  "type": "Feature",
  "properties": {
    "gn:admin1_code":"8.0",
    "gn:admin2_code":"1825.0",
    "gn:asciiname":"Al `Arish",
    "gn:country_code":"YE",
    "gn:dem":194,
    "gn:feature_class":"P",
    "gn:feature_code":"PPL",
    "gn:name":"Al \u2018Ar\u012bsh",
    "gn:population":0,
    "gn:timezone":"Asia/Aden",
    "iso:country":"YE",
    "name:ara_x_preferred":[
        "Al \u2018Ar\u012bsh"
    ],
    "name:gle_x_preferred":[
        "Al `Arish"
    ],
    "name:nno_x_preferred":[
        "Al `Arish"
    ],
    "wof:name":"Al `Arish",
    "wof:placetype":"locality"
},
  "geometry": {"coordinates":[43.41705,14.14537],"type":"Point"}
}