{
  "type": "Feature",
  "properties": {
    "gn:admin1_code":"1.0",
    "gn:admin2_code":"1204.0",
    "gn:asciiname":"Lawdar",
    "gn:country_code":"YE",
    "gn:dem":993,
    "gn:feature_class":"P",
    "gn:feature_code":"PPLA2",
    "gn:name":"Lawdar",
    "gn:population":0,
    "gn:timezone":"Asia/Aden",
    "iso:country":"YE",
    "name:ara_x_preferred":[
        "\u0644\u0648\u062f\u0631"
    ],
    "name:deu_x_preferred":[
        "Lawdar"
    ],
    "name:fas_x_preferred":[
        "\u0644\u0648\u062f\u0631"
    ],
    "name:hrv_x_preferred":[
        "Lodar"
    ],
    "name:nno_x_preferred":[
        "Lawdar"
    ],
    "name:und_x_variant":[
        "Al-Ghudr",
        "Laudar"
    ],
    "wof:name":"Lawdar",
    "wof:placetype":"locality"
},
  "geometry": {"coordinates":[45.86859000000001,13.88282],"type":"Point"}
}