{
  "type": "Feature",
  "properties": {
    "gn:admin1_code":"10.0",
    "gn:admin2_code":"2703.0",
    "gn:asciiname":"Juban",
    "gn:country_code":"YE",
    "gn:dem":2136,
    "gn:feature_class":"P",
    "gn:feature_code":"PPL",
    "gn:name":"J\u016bb\u0101n",
    "gn:population":0,
    "gn:timezone":"Asia/Aden",
    "iso:country":"YE",
    "name:ara_x_preferred":[
        "J\u016bb\u0101n"
    ],
    "name:ceb_x_preferred":[
        "Juban"
    ],
    "name:fra_x_preferred":[
        "Juban"
    ],
    "name:swe_x_preferred":[
        "Juban"
    ],
    "wof:name":"Juban",
    "wof:placetype":"locality"
},
  "geometry": {"coordinates":[43.67325,15.46682],"type":"Point"}
}