{
  "type": "Feature",
  "properties": {
    "gn:admin1_code":"8.0",
    "gn:admin2_code":"1812.0",
    "gn:asciiname":"Al Adram",
    "gn:country_code":"YE",
    "gn:dem":1174,
    "gn:feature_class":"P",
    "gn:feature_code":"PPL",
    "gn:name":"Al Adr\u0101m",
    "gn:population":0,
    "gn:timezone":"Asia/Aden",
    "iso:country":"YE",
    "name:ara_x_preferred":[
        "\u0627\u0644\u0627\u062f\u0631\u0627\u0645"
    ],
    "name:und_x_variant":[
        "Al Adr\u0101m"
    ],
    "wof:name":"Al Adram",
    "wof:placetype":"locality"
},
  "geometry": {"coordinates":[43.44082,14.92187],"type":"Point"}
}