{
  "type": "Feature",
  "properties": {
    "gn:admin1_code":"8.0",
    "gn:admin2_code":"1819.0",
    "gn:asciiname":"Dar Qudayrah",
    "gn:country_code":"YE",
    "gn:dem":275,
    "gn:feature_class":"P",
    "gn:feature_code":"PPL",
    "gn:name":"D\u0101r Qudayrah",
    "gn:population":0,
    "gn:timezone":"Asia/Aden",
    "iso:country":"YE",
    "name:ara_x_preferred":[
        "\u062f\u0627\u0631 \u0642\u062f\u064a\u0631\u0629"
    ],
    "name:und_x_variant":[
        "D\u0101r Qudayrah"
    ],
    "wof:name":"Dar Qudayrah",
    "wof:placetype":"locality"
},
  "geometry": {"coordinates":[43.54899,13.90929],"type":"Point"}
}