{
  "type": "Feature",
  "properties": {
    "gn:admin1_code":"8.0",
    "gn:admin2_code":"1802.0",
    "gn:asciiname":"Al Lubayniyah",
    "gn:country_code":"YE",
    "gn:dem":41,
    "gn:feature_class":"P",
    "gn:feature_code":"PPL",
    "gn:name":"Al Lubayn\u012byah",
    "gn:population":0,
    "gn:timezone":"Asia/Aden",
    "iso:country":"YE",
    "name:und_x_variant":[
        "Al Lubayn\u012byah"
    ],
    "wof:name":"Al Lubayniyah",
    "wof:placetype":"locality"
},
  "geometry": {"coordinates":[42.90576,15.75021],"type":"Point"}
}