{
  "type": "Feature",
  "properties": {
    "gn:admin1_code":"27.0",
    "gn:admin2_code":"2007.0",
    "gn:asciiname":"Suq Bayt al Ba`dani",
    "gn:country_code":"YE",
    "gn:dem":374,
    "gn:feature_class":"P",
    "gn:feature_code":"PPL",
    "gn:name":"S\u016bq Bayt al Ba\u2018d\u0101n\u012b",
    "gn:population":0,
    "gn:timezone":"Asia/Aden",
    "iso:country":"YE",
    "name:ara_x_preferred":[
        "\u0633\u0648\u0642 \u0628\u064a\u062a \u0627\u0644\u0628\u0639\u062f\u0627\u0646\u064a"
    ],
    "name:und_x_variant":[
        "Bayt al Ba\u2018d\u0101n\u012b",
        "S\u016bq Bayt al Ba\u2018d\u0101n\u012b"
    ],
    "wof:name":"Suq Bayt al Ba`dani",
    "wof:placetype":"locality"
},
  "geometry": {"coordinates":[43.56071,14.37354],"type":"Point"}
}