{
  "type": "Feature",
  "properties": {
    "gn:admin1_code":"23.0",
    "gn:admin2_code":"1103.0",
    "gn:asciiname":"Al Qadmah",
    "gn:country_code":"YE",
    "gn:dem":2230,
    "gn:feature_class":"P",
    "gn:feature_code":"PPL",
    "gn:name":"Al Qadmah",
    "gn:population":0,
    "gn:timezone":"Asia/Aden",
    "iso:country":"YE",
    "name:ara_x_preferred":[
        "\u0627\u0644\u0642\u062f\u0645\u0629"
    ],
    "name:und_x_variant":[
        "Al Qudmah",
        "Al Qadmah"
    ],
    "wof:name":"Al Qadmah",
    "wof:placetype":"locality"
},
  "geometry": {"coordinates":[44.63393,14.15204],"type":"Point"}
}