{
  "type": "Feature",
  "properties": {
    "gn:country":"YE",
    "gn:fcode":"PPLX",
    "gn:pop":4,
    "iso:country":"YE",
    "name:ara_x_preferred":[
        "\u0627\u0644\u062e\u0645\u064a\u0633"
    ],
    "qs:name":"Al Kham\u012bs",
    "qs:photos_9r":0,
    "qs:photos_sr":0,
    "qs:pop_sr":"1",
    "wof:name":"Al Kham\u012bs",
    "wof:placetype":"neighbourhood",
    "wof:population":4
},
  "geometry": {"coordinates":[44.24988,16.59323],"type":"Point"}
}