{
  "type": "Feature",
  "properties": {
    "gn:country":"YE",
    "gn:fcode":"PPL",
    "gn:pop":6,
    "iso:country":"YE",
    "name:ara_x_preferred":[
        "\u0627\u0644\u0634\u0631\u0642\u064a\u0629"
    ],
    "qs:name":"Ash Sharq\u012byah",
    "qs:photos_9r":0,
    "qs:photos_sr":0,
    "qs:pop_sr":"1",
    "wd:wordcount":64,
    "wof:name":"Ash Sharq\u012byah",
    "wof:placetype":"locality",
    "wof:population":6
},
  "geometry": {"coordinates":[43.35885,16.30081],"type":"Point"}
}