{
  "type": "Feature",
  "properties": {
    "gn:country":"YE",
    "gn:fcode":"PPL",
    "gn:population":6,
    "iso:country":"YE",
    "name:ara_x_preferred":[
        "\u0627\u0644\u0634\u0631\u0642\u064a\u0629"
    ],
    "name:cat_x_preferred":[
        "Ash-Sharqiyah"
    ],
    "name:eng_x_preferred":[
        "Ash Sharqiyah"
    ],
    "name:fin_x_preferred":[
        "Al-\u0160arqiyya"
    ],
    "name:fra_x_preferred":[
        "Ach-Charqiya"
    ],
    "name:jpn_x_preferred":[
        "\u30a2\u30c3\u30fb\u30b7\u30e3\u30eb\u30ad\u30fc\u30e4"
    ],
    "name:nld_x_preferred":[
        "Ash Sharqiyah"
    ],
    "name:pol_x_preferred":[
        "Asz-Szarkijja"
    ],
    "name:rus_x_preferred":[
        "\u042d\u0448-\u0428\u0430\u0440\u043a\u0438\u044f"
    ],
    "name:spa_x_preferred":[
        "Ash Sharqiyah"
    ],
    "qs:name":"Ash Sharq\u012byah",
    "qs:photos_9r":0,
    "qs:photos_sr":0,
    "qs:pop_sr":"1",
    "wd:wordcount":64,
    "wof:name":"Ash Sharq\u012byah",
    "wof:placetype":"locality",
    "wof:population":6
},
  "geometry": {"coordinates":[43.35885,16.30081],"type":"Point"}
}