{
  "type": "Feature",
  "properties": {
    "gn:admin1_code":"11.0",
    "gn:admin2_code":"1102.0",
    "gn:asciiname":"Ad Dabr",
    "gn:country_code":"YE",
    "gn:dem":2214,
    "gn:feature_class":"P",
    "gn:feature_code":"PPL",
    "gn:name":"A\u1e11 \u1e10abr",
    "gn:population":0,
    "gn:timezone":"Asia/Aden",
    "iso:country":"YE",
    "name:ara_x_preferred":[
        "\u0627\u0644\u0636\u0628\u0631"
    ],
    "name:fas_x_preferred":[
        "\u0627\u0644\u062f\u0627\u0628\u0631"
    ],
    "name:nno_x_preferred":[
        "Ad Dabr"
    ],
    "name:und_x_variant":[
        "A\u1e11 \u1e10abr",
        "A\u1e11 \u1e10ubr"
    ],
    "wof:name":"Ad Dabr",
    "wof:placetype":"locality"
},
  "geometry": {"coordinates":[44.28699,14.34672],"type":"Point"}
}