{
  "type": "Feature",
  "properties": {
    "gn:country":"YE",
    "gn:fcode":"PPL",
    "gn:pop":6,
    "iso:country":"YE",
    "name:ara_x_preferred":[
        "Al Mi\u1e29d\u0101b"
    ],
    "name:ara_x_variant":[
        "\u0627\u0644\u0645\u062d\u062f\u0627\u0628"
    ],
    "name:eng_x_preferred":[
        "Al Mihdab"
    ],
    "name:eng_x_variant":[
        "Al Muth\u0101mil"
    ],
    "qs:name":"Al Mi\u1e29d\u0101b",
    "qs:photos_9r":0,
    "qs:photos_sr":0,
    "qs:pop_sr":"1",
    "wof:name":"Al Mi\u1e29d\u0101b",
    "wof:placetype":"locality",
    "wof:population":6
},
  "geometry": {"coordinates":[43.20161,17.13612],"type":"Point"}
}