{
  "type": "Feature",
  "properties": {
    "gn:admin1_code":"14.0",
    "gn:asciiname":"Al `Adbah",
    "gn:country_code":"YE",
    "gn:dem":1162,
    "gn:feature_class":"P",
    "gn:feature_code":"PPL",
    "gn:name":"Al \u2018A\u1e11bah",
    "gn:population":0,
    "gn:timezone":"Asia/Aden",
    "iso:country":"YE",
    "name:ara_x_preferred":[
        "\u0627\u0644\u0639\u0636\u0628\u0629"
    ],
    "name:und_x_variant":[
        "Al \u2018A\u1e11bah"
    ],
    "wof:name":"Al `Adbah",
    "wof:placetype":"locality"
},
  "geometry": {"coordinates":[44.59539,16.22583],"type":"Point"}
}