{
  "type": "Feature",
  "properties": {
    "gn:admin1_code":"11.0",
    "gn:admin2_code":"2007.0",
    "gn:asciiname":"Sharaf Bani Lahib",
    "gn:country_code":"YE",
    "gn:dem":893,
    "gn:feature_class":"P",
    "gn:feature_code":"PPL",
    "gn:name":"Sharaf Ban\u012b L\u0101hib",
    "gn:population":0,
    "gn:timezone":"Asia/Aden",
    "iso:country":"YE",
    "name:und_x_variant":[
        "Sharaf Ban\u012b L\u0101hib"
    ],
    "wof:name":"Sharaf Bani Lahib",
    "wof:placetype":"locality"
},
  "geometry": {"coordinates":[43.70278,14.24949],"type":"Point"}
}