{
  "type": "Feature",
  "properties": {
    "gn:country":"YE",
    "gn:fcode":"PPL",
    "gn:pop":9,
    "iso:country":"YE",
    "name:ara_x_preferred":[
        "\u0627\u0644\u0645\u0635\u0627\u0631\u064a\u0629"
    ],
    "name:eng_x_preferred":[
        "Al Masariyah"
    ],
    "name:vie_x_preferred":[
        "Al-Sawda"
    ],
    "qs:name":"Al Ma\u015f\u0101r\u012byah",
    "qs:photos_9r":0,
    "qs:photos_sr":0,
    "qs:pop_sr":"1",
    "wof:name":"Al Ma\u015f\u0101r\u012byah",
    "wof:placetype":"locality",
    "wof:population":9
},
  "geometry": {"coordinates":[45.51829,15.00193],"type":"Point"}
}