{
  "type": "Feature",
  "properties": {
    "gn:country":"YE",
    "gn:fcode":"PPL",
    "gn:pop":2,
    "iso:country":"YE",
    "name:ara_x_preferred":[
        "\u0627\u0644\u062f\u0627\u0631\u0629"
    ],
    "qs:name":"Ad D\u0101rah",
    "qs:photos_9r":0,
    "qs:photos_sr":0,
    "qs:pop_sr":"1",
    "wof:name":"Ad D\u0101rah",
    "wof:placetype":"locality",
    "wof:population":2
},
  "geometry": {"coordinates":[43.74066,16.11229],"type":"Point"}
}