{
  "type": "Feature",
  "properties": {
    "gn:admin1_code":"11.0",
    "gn:admin2_code":"2003.0",
    "gn:asciiname":"Al Ma`zibah",
    "gn:country_code":"YE",
    "gn:dem":1475,
    "gn:feature_class":"P",
    "gn:feature_code":"PPL",
    "gn:name":"Al Ma\u2018zibah",
    "gn:population":0,
    "gn:timezone":"Asia/Aden",
    "iso:country":"YE",
    "name:und_x_variant":[
        "Al Ma\u2018zibah",
        "Al Ma\u2018zabah"
    ],
    "wof:name":"Al Ma`zibah",
    "wof:placetype":"locality"
},
  "geometry": {"coordinates":[43.97186,14.65503],"type":"Point"}
}