{
  "type": "Feature",
  "properties": {
    "gn:admin1_code":"25.0",
    "gn:admin2_code":"1505.0",
    "gn:asciiname":"Nujayd Khayashin",
    "gn:country_code":"YE",
    "gn:dem":913,
    "gn:feature_class":"P",
    "gn:feature_code":"PPL",
    "gn:name":"Nujayd Khay\u0101shin",
    "gn:population":0,
    "gn:timezone":"Asia/Aden",
    "iso:country":"YE",
    "name:und_x_variant":[
        "Nujayd Khay\u0101shin"
    ],
    "wof:name":"Nujayd Khayashin",
    "wof:placetype":"locality"
},
  "geometry": {"coordinates":[43.71343,13.67978],"type":"Point"}
}