{
  "type": "Feature",
  "properties": {
    "gn:admin1_code":"23.0",
    "gn:admin2_code":"1113.0",
    "gn:asciiname":"Kharabat `Udhanah",
    "gn:country_code":"YE",
    "gn:dem":2172,
    "gn:feature_class":"P",
    "gn:feature_code":"PPL",
    "gn:name":"Khar\u0101bat \u2018Udh\u0101nah",
    "gn:population":0,
    "gn:timezone":"Asia/Aden",
    "iso:country":"YE",
    "name:und_x_variant":[
        "Khar\u0101bat \u2018Udh\u0101nah"
    ],
    "wof:name":"Kharabat `Udhanah",
    "wof:placetype":"locality"
},
  "geometry": {"coordinates":[44.30623,13.93472],"type":"Point"}
}