{
  "type": "Feature",
  "properties": {
    "gn:admin1_code":"14.0",
    "gn:admin2_code":"2609.0",
    "gn:asciiname":"Al `Adi",
    "gn:country_code":"YE",
    "gn:dem":1185,
    "gn:feature_class":"P",
    "gn:feature_code":"PPL",
    "gn:name":"Al \u2018\u0100d\u012b",
    "gn:population":0,
    "gn:timezone":"Asia/Aden",
    "iso:country":"YE",
    "name:ara_x_preferred":[
        "Al \u2018\u0100d\u012b"
    ],
    "name:ara_x_variant":[
        "\u0627\u0644\u0639\u0627\u062f\u064a"
    ],
    "name:und_x_variant":[
        "Ar\u1e11\u012b",
        "Al \u2018Ar\u1e11",
        "Al \u2018Ar\u1e11\u012b"
    ],
    "wof:name":"Al `Adi",
    "wof:placetype":"locality"
},
  "geometry": {"coordinates":[45.46625,14.9455],"type":"Point"}
}