{
  "type": "Feature",
  "properties": {
    "gn:admin1_code":"21.0",
    "gn:admin2_code":"1602.0",
    "gn:asciiname":"Al Waghirah",
    "gn:country_code":"YE",
    "gn:dem":1266,
    "gn:feature_class":"P",
    "gn:feature_code":"PPL",
    "gn:name":"Al W\u0101ghirah",
    "gn:population":0,
    "gn:timezone":"Asia/Aden",
    "iso:country":"YE",
    "name:ara_x_preferred":[
        "\u0627\u0644\u0648\u0627\u063a\u0631\u0629"
    ],
    "name:und_x_variant":[
        "Al W\u0101ghirah"
    ],
    "wof:name":"Al Waghirah",
    "wof:placetype":"locality"
},
  "geometry": {"coordinates":[44.34899,16.4278],"type":"Point"}
}