{
  "type": "Feature",
  "properties": {
    "gn:admin1_code":"4.0",
    "gn:admin2_code":"1907.0",
    "gn:asciiname":"Findah",
    "gn:cc2":"YE",
    "gn:country_code":"YE",
    "gn:dem":701,
    "gn:feature_class":"P",
    "gn:feature_code":"PPL",
    "gn:name":"Findah",
    "gn:population":0,
    "gn:timezone":"Asia/Aden",
    "iso:country":"YE",
    "name:nno_x_preferred":[
        "Findah"
    ],
    "name:und_x_variant":[
        "Findih"
    ],
    "wof:name":"Findah",
    "wof:placetype":"locality"
},
  "geometry": {"coordinates":[48.28222,15.83639],"type":"Point"}
}