{
  "type": "Feature",
  "properties": {
    "gn:admin1_code":"5.0",
    "gn:admin2_code":"2102.0",
    "gn:asciiname":"Kalwah",
    "gn:country_code":"YE",
    "gn:dem":1379,
    "gn:feature_class":"P",
    "gn:feature_code":"PPL",
    "gn:name":"Kalwah",
    "gn:population":0,
    "gn:timezone":"Asia/Aden",
    "iso:country":"YE",
    "name:ara_x_preferred":[
        "\u0643\u0644\u0648\u0629"
    ],
    "wof:name":"Kalwah",
    "wof:placetype":"locality"
},
  "geometry": {"coordinates":[47.5125,15.05567],"type":"Point"}
}