{
  "type": "Feature",
  "properties": {
    "gn:country":"YE",
    "gn:fcode":"PPL",
    "gn:population":1,
    "iso:country":"YE",
    "name:ara_x_preferred":[
        "Al Jufr\u0101\u2019"
    ],
    "name:ara_x_variant":[
        "\u0627\u0644\u062c\u0641\u0631\u0627\u0621"
    ],
    "name:eng_x_preferred":[
        "Al Jufra"
    ],
    "name:eng_x_variant":[
        "Al Man\u0101yish"
    ],
    "qs:name":"Al Jufr\u0101\u2019",
    "qs:photos_9r":0,
    "qs:photos_sr":0,
    "qs:pop_sr":"1",
    "wof:name":"Al Jufr\u0101\u2019",
    "wof:placetype":"locality",
    "wof:population":1
},
  "geometry": {"coordinates":[43.27607,17.40136],"type":"Point"}
}