{
  "type": "Feature",
  "properties": {
    "gn:admin1_code":"23.0",
    "gn:admin2_code":"1102.0",
    "gn:asciiname":"Al Qadari",
    "gn:country_code":"YE",
    "gn:dem":1570,
    "gn:feature_class":"P",
    "gn:feature_code":"PPL",
    "gn:name":"Al Qad\u0101r\u012b",
    "gn:population":0,
    "gn:timezone":"Asia/Aden",
    "iso:country":"YE",
    "name:ara_x_preferred":[
        "\u0627\u0644\u0642\u062f\u0627\u0631\u064a"
    ],
    "name:und_x_variant":[
        "Al Qad\u0101r\u012b"
    ],
    "wof:name":"Al Qadari",
    "wof:placetype":"locality"
},
  "geometry": {"coordinates":[44.19506,14.29362],"type":"Point"}
}