{
  "type": "Feature",
  "properties": {
    "gn:admin1_code":"24.0",
    "gn:admin2_code":"2512.0",
    "gn:asciiname":"Al Lajm",
    "gn:country_code":"YE",
    "gn:dem":1085,
    "gn:feature_class":"P",
    "gn:feature_code":"PPL",
    "gn:name":"Al Lajm",
    "gn:population":0,
    "gn:timezone":"Asia/Aden",
    "iso:country":"YE",
    "name:ara_x_preferred":[
        "\u0627\u0644\u0644\u062c\u0645"
    ],
    "wof:name":"Al Lajm",
    "wof:placetype":"locality"
},
  "geometry": {"coordinates":[44.22964,13.21357],"type":"Point"}
}