{
  "type": "Feature",
  "properties": {
    "gn:admin1_code":"22.0",
    "gn:admin2_code":"1725.0",
    "gn:asciiname":"Al Hijazi al Asfal",
    "gn:country_code":"YE",
    "gn:dem":768,
    "gn:feature_class":"P",
    "gn:feature_code":"PPL",
    "gn:name":"Al \u1e28ij\u0101z\u012b al Asfal",
    "gn:population":0,
    "gn:timezone":"Asia/Aden",
    "iso:country":"YE",
    "name:ara_x_preferred":[
        "\u0627\u0644\u062d\u062c\u0627\u0632\u064a \u0627\u0644\u0623\u0633\u0641\u0644"
    ],
    "name:und_x_variant":[
        "Al \u1e28ij\u0101z\u012b al Asfal"
    ],
    "wof:name":"Al Hijazi al Asfal",
    "wof:placetype":"locality"
},
  "geometry": {"coordinates":[43.51268,15.57731],"type":"Point"}
}