{
  "type": "Feature",
  "properties": {
    "gn:admin1_code":"22.0",
    "gn:admin2_code":"1707.0",
    "gn:asciiname":"Sha'b Dawbi'",
    "gn:country_code":"YE",
    "gn:dem":1190,
    "gn:feature_class":"P",
    "gn:feature_code":"PPL",
    "gn:name":"Sha\u2018b Dawbi\u2018",
    "gn:population":0,
    "gn:timezone":"Asia/Aden",
    "iso:country":"YE",
    "name:ara_x_preferred":[
        "\u0634\u0639\u0628 \u062f\u0648\u0628\u0639"
    ],
    "name:und_x_variant":[
        "Sha\u2018b Dawbi\u2018"
    ],
    "wof:name":"Sha'b Dawbi'",
    "wof:placetype":"locality"
},
  "geometry": {"coordinates":[43.43687,16.11182],"type":"Point"}
}