{
  "type": "Feature",
  "properties": {
    "gn:admin1_code":"8.0",
    "gn:admin2_code":"1810.0",
    "gn:asciiname":"Dayr Yunus",
    "gn:country_code":"YE",
    "gn:dem":79,
    "gn:feature_class":"P",
    "gn:feature_code":"PPL",
    "gn:name":"Dayr Y\u016bnus",
    "gn:population":0,
    "gn:timezone":"Asia/Aden",
    "iso:country":"YE",
    "name:und_x_variant":[
        "Dayr Y\u016bnus"
    ],
    "wof:name":"Dayr Yunus",
    "wof:placetype":"locality"
},
  "geometry": {"coordinates":[43.06538,15.07482],"type":"Point"}
}