{
  "type": "Feature",
  "properties": {
    "gn:admin1_code":"28.0",
    "gn:admin2_code":"1926.0",
    "gn:asciiname":"Muhtaynaq",
    "gn:country_code":"YE",
    "gn:dem":437,
    "gn:feature_class":"P",
    "gn:feature_code":"PPL",
    "gn:name":"Mu\u1e29taynaq",
    "gn:population":0,
    "gn:timezone":"Asia/Aden",
    "iso:country":"YE",
    "wof:name":"Muhtaynaq",
    "wof:placetype":"locality"
},
  "geometry": {"coordinates":[54.36543,12.53531],"type":"Point"}
}