{
  "type": "Feature",
  "properties": {
    "gn:admin1_code":"8.0",
    "gn:admin2_code":"1813.0",
    "gn:asciiname":"Al Mahallah",
    "gn:country_code":"YE",
    "gn:dem":90,
    "gn:feature_class":"P",
    "gn:feature_code":"PPL",
    "gn:name":"Al Ma\u1e29allah",
    "gn:population":0,
    "gn:timezone":"Asia/Aden",
    "iso:country":"YE",
    "name:und_x_variant":[
        "Al Ma\u1e29allah"
    ],
    "wof:name":"Al Mahallah",
    "wof:placetype":"locality"
},
  "geometry": {"coordinates":[43.20151,14.83906],"type":"Point"}
}