{
  "type": "Feature",
  "properties": {
    "gn:admin1_code":"23.0",
    "gn:admin2_code":"1101.0",
    "gn:asciiname":"Dhi Ayman",
    "gn:country_code":"YE",
    "gn:dem":2373,
    "gn:feature_class":"P",
    "gn:feature_code":"PPL",
    "gn:name":"Dh\u012b Ayman",
    "gn:population":0,
    "gn:timezone":"Asia/Aden",
    "iso:country":"YE",
    "name:ara_x_preferred":[
        "\u0630\u064a \u0623\u064a\u0645\u0646"
    ],
    "name:und_x_variant":[
        "Dh\u012b Ayman"
    ],
    "wof:name":"Dhi Ayman",
    "wof:placetype":"locality"
},
  "geometry": {"coordinates":[44.23387,14.29043],"type":"Point"}
}