{
  "type": "Feature",
  "properties": {
    "gn:admin1_code":"20.0",
    "gn:admin2_code":"2010.0",
    "gn:asciiname":"Karban",
    "gn:country_code":"YE",
    "gn:dem":2126,
    "gn:feature_class":"P",
    "gn:feature_code":"PPL",
    "gn:name":"Karb\u0101n",
    "gn:population":0,
    "gn:timezone":"Asia/Aden",
    "iso:country":"YE",
    "name:ara_x_preferred":[
        "Kurb\u0101n"
    ],
    "name:ara_x_variant":[
        "\u0643\u0631\u0628\u0627\u0646"
    ],
    "name:und_x_variant":[
        "Karb\u0101n"
    ],
    "wof:name":"Karban",
    "wof:placetype":"locality"
},
  "geometry": {"coordinates":[44.3505,14.41041],"type":"Point"}
}