{
  "type": "Feature",
  "properties": {
    "gn:admin1_code":"23.0",
    "gn:admin2_code":"1120.0",
    "gn:asciiname":"Qaryat ash Shahi",
    "gn:country_code":"YE",
    "gn:dem":2375,
    "gn:feature_class":"P",
    "gn:feature_code":"PPL",
    "gn:name":"Qaryat ash Sh\u0101\u1e29\u012b",
    "gn:population":0,
    "gn:timezone":"Asia/Aden",
    "iso:country":"YE",
    "name:und_x_variant":[
        "Qaryat ash Sh\u0101\u1e29\u012b"
    ],
    "wof:name":"Qaryat ash Shahi",
    "wof:placetype":"locality"
},
  "geometry": {"coordinates":[44.2274,13.96023],"type":"Point"}
}