{
  "type": "Feature",
  "properties": {
    "gn:admin1_code":"15.0",
    "gn:admin2_code":"2203.0",
    "gn:asciiname":"Al Mushshah",
    "gn:country_code":"YE",
    "gn:dem":1503,
    "gn:feature_class":"P",
    "gn:feature_code":"PPL",
    "gn:name":"Al Mushshah",
    "gn:population":0,
    "gn:timezone":"Asia/Aden",
    "iso:country":"YE",
    "wof:name":"Al Mushshah",
    "wof:placetype":"locality"
},
  "geometry": {"coordinates":[43.23882,17.19047999999999],"type":"Point"}
}