{
  "type": "Feature",
  "properties": {
    "gn:admin1_code":"23.0",
    "gn:admin2_code":"1113.0",
    "gn:asciiname":"Hidhar",
    "gn:country_code":"YE",
    "gn:dem":1939,
    "gn:feature_class":"P",
    "gn:feature_code":"PPL",
    "gn:name":"\u1e28idhar",
    "gn:population":0,
    "gn:timezone":"Asia/Aden",
    "iso:country":"YE",
    "name:und_x_variant":[
        "\u1e28idhar"
    ],
    "wof:name":"Hidhar",
    "wof:placetype":"locality"
},
  "geometry": {"coordinates":[44.34898,13.95444],"type":"Point"}
}