{
  "type": "Feature",
  "properties": {
    "gn:country":"YE",
    "gn:fcode":"PPL",
    "gn:pop":1,
    "iso:country":"YE",
    "name:ara_x_preferred":[
        "\u0627\u0644\u0644\u0648\u064a\u0637\u064a"
    ],
    "name:eng_x_preferred":[
        "Al Wayti"
    ],
    "qs:name":"Al Way\u0163\u012b",
    "qs:photos_9r":0,
    "qs:photos_sr":0,
    "qs:pop_sr":"1",
    "wof:name":"Al Way\u0163\u012b",
    "wof:placetype":"locality",
    "wof:population":1
},
  "geometry": {"coordinates":[43.98213,13.08848],"type":"Point"}
}