{
  "type": "Feature",
  "properties": {
    "gn:country":"YE",
    "gn:fcode":"PPL",
    "gn:population":9,
    "iso:country":"YE",
    "name:ara_x_preferred":[
        "\u0627\u0644\u0633\u0648\u062f\u064a"
    ],
    "qs:name":"As Sawd\u012b",
    "qs:photos_9r":0,
    "qs:photos_sr":0,
    "qs:pop_sr":"1",
    "wof:name":"As Sawd\u012b",
    "wof:placetype":"locality",
    "wof:population":9
},
  "geometry": {"coordinates":[43.34356,16.34053],"type":"Point"}
}