{
  "type": "Feature",
  "properties": {
    "gn:admin1_code":"23.0",
    "gn:admin2_code":"1108.0",
    "gn:asciiname":"Al `Alayah",
    "gn:country_code":"YE",
    "gn:dem":2180,
    "gn:feature_class":"P",
    "gn:feature_code":"PPL",
    "gn:name":"Al \u2018Al\u0101yah",
    "gn:population":0,
    "gn:timezone":"Asia/Aden",
    "iso:country":"YE",
    "name:ara_x_preferred":[
        "\u0627\u0644\u0639\u0644\u0627\u0628\u0629"
    ],
    "name:und_x_variant":[
        "Al \u2018Al\u0101yah",
        "Al \u2018Il\u0101bah"
    ],
    "wof:name":"Al `Alayah",
    "wof:placetype":"locality"
},
  "geometry": {"coordinates":[44.09146,14.08635],"type":"Point"}
}