{
  "type": "Feature",
  "properties": {
    "gn:admin1_code":"22.0",
    "gn:admin2_code":"1718.0",
    "gn:asciiname":"Al Lahif",
    "gn:country_code":"YE",
    "gn:dem":1889,
    "gn:feature_class":"P",
    "gn:feature_code":"PPL",
    "gn:name":"Al L\u0101\u1e29if",
    "gn:population":0,
    "gn:timezone":"Asia/Aden",
    "iso:country":"YE",
    "name:ara_x_preferred":[
        "Al L\u0101\u1e29if"
    ],
    "wof:name":"Al Lahif",
    "wof:placetype":"locality"
},
  "geometry": {"coordinates":[43.69559,15.76795],"type":"Point"}
}