{
  "type": "Feature",
  "properties": {
    "gn:admin1_code":"19.0",
    "gn:admin2_code":"2917.0",
    "gn:asciiname":"Bani al Fulayhi",
    "gn:country_code":"YE",
    "gn:dem":3196,
    "gn:feature_class":"P",
    "gn:feature_code":"PPL",
    "gn:name":"Ban\u012b al Fulay\u1e29\u012b",
    "gn:population":0,
    "gn:timezone":"Asia/Aden",
    "iso:country":"YE",
    "name:und_x_variant":[
        "Ban\u012b al Fulay\u1e29\u012b"
    ],
    "wof:name":"Bani al Fulayhi",
    "wof:placetype":"locality"
},
  "geometry": {"coordinates":[43.77195,15.616],"type":"Point"}
}