{
  "type": "Feature",
  "properties": {
    "gn:admin1_code":"4.0",
    "gn:admin2_code":"1911.0",
    "gn:asciiname":"Ar Ramlah",
    "gn:cc2":"YE",
    "gn:country_code":"YE",
    "gn:dem":614,
    "gn:feature_class":"P",
    "gn:feature_code":"PPL",
    "gn:name":"Ar Ramlah",
    "gn:population":0,
    "gn:timezone":"Asia/Aden",
    "iso:country":"YE",
    "name:nno_x_preferred":[
        "Ar Ramlah"
    ],
    "name:und_x_variant":[
        "Al-Ramlah"
    ],
    "wof:name":"Ar Ramlah",
    "wof:placetype":"locality"
},
  "geometry": {"coordinates":[48.98333,16.01667],"type":"Point"}
}