{
  "type": "Feature",
  "properties": {
    "gn:country":"YE",
    "gn:fcode":"PPL",
    "gn:population":45,
    "iso:country":"YE",
    "name:ara_x_preferred":[
        "Al W\u0101d\u012b"
    ],
    "name:ara_x_variant":[
        "\u0627\u0644\u0648\u0627\u062f\u064a"
    ],
    "name:eng_x_preferred":[
        "Al Wadi"
    ],
    "name:eng_x_variant":[
        "Gharb al Mudakkil"
    ],
    "qs:name":"Al W\u0101d\u012b",
    "qs:photos_9r":0,
    "qs:photos_sr":0,
    "qs:pop_sr":"1",
    "wof:name":"Al W\u0101d\u012b",
    "wof:placetype":"locality",
    "wof:population":45
},
  "geometry": {"coordinates":[43.81544,16.82361],"type":"Point"}
}