{
  "type": "Feature",
  "properties": {
    "gn:admin1_code":"19.0",
    "gn:admin2_code":"2913.0",
    "gn:asciiname":"Ad Dumaynah",
    "gn:country_code":"YE",
    "gn:dem":1717,
    "gn:feature_class":"P",
    "gn:feature_code":"PPL",
    "gn:name":"Ad Dumaynah",
    "gn:population":0,
    "gn:timezone":"Asia/Aden",
    "iso:country":"YE",
    "name:ara_x_preferred":[
        "\u0627\u0644\u062f\u0645\u064a\u0646\u0629"
    ],
    "wof:name":"Ad Dumaynah",
    "wof:placetype":"locality"
},
  "geometry": {"coordinates":[43.77722,16.02936],"type":"Point"}
}