{
  "type": "Feature",
  "properties": {
    "gn:admin1_code":"25.0",
    "gn:admin2_code":"1513.0",
    "gn:asciiname":"Ukaymat Bashir",
    "gn:country_code":"YE",
    "gn:dem":1191,
    "gn:feature_class":"P",
    "gn:feature_code":"PPL",
    "gn:name":"Ukaymat Bash\u012br",
    "gn:population":0,
    "gn:timezone":"Asia/Aden",
    "iso:country":"YE",
    "name:und_x_variant":[
        "Ukaymat Bash\u012br"
    ],
    "wof:name":"Ukaymat Bashir",
    "wof:placetype":"locality"
},
  "geometry": {"coordinates":[44.20024,13.4583],"type":"Point"}
}