{
  "type": "Feature",
  "properties": {
    "gn:admin1_code":"18.0",
    "gn:admin2_code":"3003.0",
    "gn:asciiname":"Al Lakim",
    "gn:country_code":"YE",
    "gn:dem":2078,
    "gn:feature_class":"P",
    "gn:feature_code":"PPL",
    "gn:name":"Al Lak\u012bm",
    "gn:population":0,
    "gn:timezone":"Asia/Aden",
    "iso:country":"YE",
    "name:und_x_variant":[
        "Al Lak\u012bm"
    ],
    "wof:name":"Al Lakim",
    "wof:placetype":"locality"
},
  "geometry": {"coordinates":[44.78392,13.86941],"type":"Point"}
}