{
  "type": "Feature",
  "properties": {
    "gn:admin1_code":"22.0",
    "gn:admin2_code":"1727.0",
    "gn:asciiname":"Bayt Shamsan",
    "gn:country_code":"YE",
    "gn:dem":1628,
    "gn:feature_class":"P",
    "gn:feature_code":"PPL",
    "gn:name":"Bayt Shams\u0101n",
    "gn:population":0,
    "gn:timezone":"Asia/Aden",
    "iso:country":"YE",
    "name:ara_x_preferred":[
        "\u0628\u064a\u062a \u0634\u0645\u0633\u0627\u0646"
    ],
    "name:und_x_variant":[
        "Bayt Shams\u0101n"
    ],
    "wof:name":"Bayt Shamsan",
    "wof:placetype":"locality"
},
  "geometry": {"coordinates":[43.59599,15.58692],"type":"Point"}
}