{
  "type": "Feature",
  "properties": {
    "gn:admin1_code":"23.0",
    "gn:admin2_code":"1109.0",
    "gn:asciiname":"Najd Hamadi",
    "gn:country_code":"YE",
    "gn:dem":1524,
    "gn:feature_class":"P",
    "gn:feature_code":"PPL",
    "gn:name":"Najd \u1e28am\u0101d\u012b",
    "gn:population":0,
    "gn:timezone":"Asia/Aden",
    "iso:country":"YE",
    "name:ara_x_preferred":[
        "\u0646\u062c\u062f \u062d\u0645\u0627\u062f\u064a"
    ],
    "name:und_x_variant":[
        "Najd \u1e28um\u0101d\u012b",
        "Najd \u1e28am\u0101d\u012b"
    ],
    "wof:name":"Najd Hamadi",
    "wof:placetype":"locality"
},
  "geometry": {"coordinates":[43.96961,14.09903],"type":"Point"}
}