{
  "type": "Feature",
  "properties": {
    "gn:admin1_code":"25.0",
    "gn:admin2_code":"1513.0",
    "gn:asciiname":"Sala`if",
    "gn:country_code":"YE",
    "gn:dem":1120,
    "gn:feature_class":"P",
    "gn:feature_code":"PPL",
    "gn:name":"Sal\u0101\u2018if",
    "gn:population":0,
    "gn:timezone":"Asia/Aden",
    "iso:country":"YE",
    "name:und_x_variant":[
        "Sal\u0101\u2018if"
    ],
    "wof:name":"Sala`if",
    "wof:placetype":"locality"
},
  "geometry": {"coordinates":[44.31529000000001,13.35718],"type":"Point"}
}