{
  "type": "Feature",
  "properties": {
    "gn:admin1_code":"1.0",
    "gn:admin2_code":"1202.0",
    "gn:asciiname":"Al Qarn",
    "gn:country_code":"YE",
    "gn:dem":840,
    "gn:feature_class":"P",
    "gn:feature_code":"PPL",
    "gn:name":"Al Qarn",
    "gn:population":0,
    "gn:timezone":"Asia/Aden",
    "iso:country":"YE",
    "wof:name":"Al Qarn",
    "wof:placetype":"locality"
},
  "geometry": {"coordinates":[46.09414,13.92525],"type":"Point"}
}