{
  "type": "Feature",
  "properties": {
    "gn:admin1_code":"23.0",
    "gn:admin2_code":"1117.0",
    "gn:asciiname":"Al Mawsatah",
    "gn:country_code":"YE",
    "gn:dem":2142,
    "gn:feature_class":"P",
    "gn:feature_code":"PPL",
    "gn:name":"Al Mawsa\u0163ah",
    "gn:population":0,
    "gn:timezone":"Asia/Aden",
    "iso:country":"YE",
    "name:ara_x_preferred":[
        "\u0627\u0644\u0645\u0648\u0633\u0637\u0629"
    ],
    "name:und_x_variant":[
        "Al Mawsa\u0163ah",
        "Al Muwassa\u0163ah",
        "Al Mawsi\u0163ah"
    ],
    "wof:name":"Al Mawsatah",
    "wof:placetype":"locality"
},
  "geometry": {"coordinates":[43.96561,13.85072],"type":"Point"}
}