{
  "type": "Feature",
  "properties": {
    "gn:admin1_code":"22.0",
    "gn:admin2_code":"1720.0",
    "gn:asciiname":"Al Maghrabah",
    "gn:country_code":"YE",
    "gn:dem":1699,
    "gn:feature_class":"P",
    "gn:feature_code":"PPL",
    "gn:name":"Al Maghrabah",
    "gn:population":0,
    "gn:timezone":"Asia/Aden",
    "iso:country":"YE",
    "wof:name":"Al Maghrabah",
    "wof:placetype":"locality"
},
  "geometry": {"coordinates":[43.59823,15.75349],"type":"Point"}
}