{
  "type": "Feature",
  "properties": {
    "gn:admin1_code":"19.0",
    "gn:admin2_code":"2902.0",
    "gn:asciiname":"Qa' al Khablan",
    "gn:country_code":"YE",
    "gn:dem":1579,
    "gn:feature_class":"P",
    "gn:feature_code":"PPL",
    "gn:name":"Q\u0101\u2018 al Khabl\u0101n",
    "gn:population":0,
    "gn:timezone":"Asia/Aden",
    "iso:country":"YE",
    "name:ara_x_preferred":[
        "\u0642\u0627\u0639 \u0627\u0644\u062e\u0628\u0644\u0627\u0646"
    ],
    "name:und_x_variant":[
        "Q\u0101\u2018 al Khabl\u0101n"
    ],
    "wof:name":"Qa' al Khablan",
    "wof:placetype":"locality"
},
  "geometry": {"coordinates":[44.07984,16.27865],"type":"Point"}
}