{
  "type": "Feature",
  "properties": {
    "gn:admin1_code":"25.0",
    "gn:admin2_code":"1514.0",
    "gn:asciiname":"Al Hud",
    "gn:country_code":"YE",
    "gn:dem":1972,
    "gn:feature_class":"P",
    "gn:feature_code":"PPL",
    "gn:name":"Al \u1e28\u016bd",
    "gn:population":0,
    "gn:timezone":"Asia/Aden",
    "iso:country":"YE",
    "name:ara_x_preferred":[
        "Al \u1e28\u016bd"
    ],
    "wof:name":"Al Hud",
    "wof:placetype":"locality"
},
  "geometry": {"coordinates":[44.18959,13.36341],"type":"Point"}
}