{
  "type": "Feature",
  "properties": {
    "gn:admin1_code":"15.0",
    "gn:admin2_code":"2211.0",
    "gn:asciiname":"Al `Izah",
    "gn:country_code":"YE",
    "gn:dem":1847,
    "gn:feature_class":"P",
    "gn:feature_code":"PPL",
    "gn:name":"\u0100l \u2018\u012az\u0327ah",
    "gn:population":0,
    "gn:timezone":"Asia/Aden",
    "iso:country":"YE",
    "name:ara_x_preferred":[
        "\u0627\u0644 \u0639\u064a\u0638\u0629"
    ],
    "name:und_x_variant":[
        "\u0100l \u2018\u012a\u1e11ah",
        "\u0100l \u2018\u012az\u0327ah"
    ],
    "wof:name":"Al `Izah",
    "wof:placetype":"locality"
},
  "geometry": {"coordinates":[43.76753,17.01715],"type":"Point"}
}