{
  "type": "Feature",
  "properties": {
    "gn:country":"YE",
    "gn:fcode":"PPL",
    "gn:pop":3,
    "iso:country":"YE",
    "name:ara_x_preferred":[
        "\u0627\u0644\u0643\u0648\u0631"
    ],
    "qs:name":"Al Kawr",
    "qs:photos_9r":0,
    "qs:photos_sr":0,
    "qs:pop_sr":"1",
    "wd:wordcount":23,
    "wof:name":"Al Kawr",
    "wof:placetype":"locality",
    "wof:population":3
},
  "geometry": {"coordinates":[43.3038,16.02541],"type":"Point"}
}