{
  "type": "Feature",
  "properties": {
    "gn:country":"YE",
    "gn:fcode":"PPLX",
    "gn:pop":32,
    "iso:country":"YE",
    "name:ara_x_preferred":[
        "\u0627\u0644\u0631\u0634\u064a\u062d \u0627\u0644\u0623\u0633\u0641\u0644"
    ],
    "qs:name":"Ar Rushay\u1e29 al Asfal",
    "qs:photos_9r":0,
    "qs:photos_sr":0,
    "qs:pop_sr":"1",
    "wof:name":"Ar Rushay\u1e29 al Asfal",
    "wof:placetype":"neighbourhood",
    "wof:population":32
},
  "geometry": {"coordinates":[43.65156,13.40004],"type":"Point"}
}