{
  "type": "Feature",
  "properties": {
    "gn:country":"YE",
    "gn:fcode":"PPL",
    "gn:pop":7,
    "iso:country":"YE",
    "name:ara_x_preferred":[
        "\u0627\u0644\u0634\u062c\u064a\u0646\u0629"
    ],
    "name:eng_x_preferred":[
        "Ash Shujaynah"
    ],
    "name:eng_x_variant":[
        "Al Muq\u0101bil"
    ],
    "qs:name":"Ash Shujaynah",
    "qs:photos_9r":0,
    "qs:photos_sr":0,
    "qs:pop_sr":"1",
    "wof:name":"Ash Shujaynah",
    "wof:placetype":"locality",
    "wof:population":7
},
  "geometry": {"coordinates":[43.44824,16.14597],"type":"Point"}
}