{
  "type": "Feature",
  "properties": {
    "gn:admin1_code":"20.0",
    "gn:admin2_code":"1420.0",
    "gn:asciiname":"Ruzayqah",
    "gn:country_code":"YE",
    "gn:dem":1980,
    "gn:feature_class":"P",
    "gn:feature_code":"PPL",
    "gn:name":"Ruzayqah",
    "gn:population":0,
    "gn:timezone":"Asia/Aden",
    "iso:country":"YE",
    "wof:name":"Ruzayqah",
    "wof:placetype":"locality"
},
  "geometry": {"coordinates":[45.39561,14.41754],"type":"Point"}
}