{
  "type": "Feature",
  "properties": {
    "gn:admin1_code":"25.0",
    "gn:admin2_code":"1508.0",
    "gn:asciiname":"Qaryat ad Dahiyah",
    "gn:country_code":"YE",
    "gn:dem":432,
    "gn:feature_class":"P",
    "gn:feature_code":"PPL",
    "gn:name":"Qaryat a\u1e11 \u1e10\u0101\u1e29iyah",
    "gn:population":0,
    "gn:timezone":"Asia/Aden",
    "iso:country":"YE",
    "name:und_x_variant":[
        "Qaryat a\u1e11 \u1e10\u0101\u1e29iyah"
    ],
    "wof:name":"Qaryat ad Dahiyah",
    "wof:placetype":"locality"
},
  "geometry": {"coordinates":[43.70405,13.29755],"type":"Point"}
}