{
  "type": "Feature",
  "properties": {
    "gn:admin1_code":"8.0",
    "gn:admin2_code":"1814.0",
    "gn:asciiname":"Kuram",
    "gn:country_code":"YE",
    "gn:dem":12,
    "gn:feature_class":"P",
    "gn:feature_code":"PPL",
    "gn:name":"Kuram",
    "gn:population":0,
    "gn:timezone":"Asia/Aden",
    "iso:country":"YE",
    "name:und_x_variant":[
        "Kurem",
        "Kuram"
    ],
    "wof:name":"Kuram",
    "wof:placetype":"locality"
},
  "geometry": {"coordinates":[43.02312,14.56892],"type":"Point"}
}