{
  "type": "Feature",
  "properties": {
    "gn:admin1_code":"1.0",
    "gn:admin2_code":"1208.0",
    "gn:asciiname":"Mukharrabiyah",
    "gn:cc2":"YE",
    "gn:country_code":"YE",
    "gn:dem":799,
    "gn:feature_class":"P",
    "gn:feature_code":"PPL",
    "gn:name":"Mukharrab\u012byah",
    "gn:population":0,
    "gn:timezone":"Asia/Aden",
    "iso:country":"YE",
    "name:und_x_variant":[
        "Makharrabyra",
        "Makharrabiya",
        "Mukharrab\u012byah"
    ],
    "wof:name":"Mukharrabiyah",
    "wof:placetype":"locality"
},
  "geometry": {"coordinates":[45.98333,13.78333],"type":"Point"}
}