{
  "type": "Feature",
  "properties": {
    "gn:admin1_code":"11.0",
    "gn:admin2_code":"2001.0",
    "gn:asciiname":"Maryad",
    "gn:country_code":"YE",
    "gn:dem":2390,
    "gn:feature_class":"P",
    "gn:feature_code":"PPL",
    "gn:name":"Maryad",
    "gn:population":0,
    "gn:timezone":"Asia/Aden",
    "iso:country":"YE",
    "wof:name":"Maryad",
    "wof:placetype":"locality"
},
  "geometry": {"coordinates":[44.59587,14.66166],"type":"Point"}
}