{
  "type": "Feature",
  "properties": {
    "gn:admin1_code":"22.0",
    "gn:admin2_code":"1727.0",
    "gn:asciiname":"Mahall Majad",
    "gn:country_code":"YE",
    "gn:dem":1657,
    "gn:feature_class":"P",
    "gn:feature_code":"PPL",
    "gn:name":"Ma\u1e29all Majad",
    "gn:population":0,
    "gn:timezone":"Asia/Aden",
    "iso:country":"YE",
    "name:und_x_variant":[
        "Ma\u1e29all Majad"
    ],
    "wof:name":"Mahall Majad",
    "wof:placetype":"locality"
},
  "geometry": {"coordinates":[43.591,15.58779],"type":"Point"}
}