{
  "type": "Feature",
  "properties": {
    "gn:admin1_code":"16.0",
    "gn:admin2_code":"2316.0",
    "gn:asciiname":"Qawil",
    "gn:country_code":"YE",
    "gn:dem":2305,
    "gn:feature_class":"P",
    "gn:feature_code":"PPL",
    "gn:name":"Q\u0101wil",
    "gn:population":0,
    "gn:timezone":"Asia/Aden",
    "iso:country":"YE",
    "name:ara_x_preferred":[
        "Q\u0101wil"
    ],
    "name:und_x_variant":[
        "Qawl"
    ],
    "wof:name":"Qawil",
    "wof:placetype":"locality"
},
  "geometry": {"coordinates":[44.48556,15.16908],"type":"Point"}
}