{
  "type": "Feature",
  "properties": {
    "gn:country":"YE",
    "gn:fcode":"PPL",
    "gn:pop":2,
    "iso:country":"YE",
    "name:ara_x_preferred":[
        "\u062c\u0645\u0627\u0646\u0629"
    ],
    "qs:name":"Jim\u0101nah",
    "qs:photos_9r":0,
    "qs:photos_sr":0,
    "qs:pop_sr":"1",
    "wof:name":"Jim\u0101nah",
    "wof:placetype":"locality",
    "wof:population":2
},
  "geometry": {"coordinates":[43.33026,16.09303],"type":"Point"}
}