{
  "type": "Feature",
  "properties": {
    "gn:admin1_code":"23.0",
    "gn:admin2_code":"1102.0",
    "gn:asciiname":"Jartat",
    "gn:country_code":"YE",
    "gn:dem":2686,
    "gn:feature_class":"P",
    "gn:feature_code":"PPL",
    "gn:name":"Jart\u0101t",
    "gn:population":0,
    "gn:timezone":"Asia/Aden",
    "iso:country":"YE",
    "name:ara_x_preferred":[
        "\u062c\u0631\u062a\u0627\u062a"
    ],
    "name:und_x_variant":[
        "Jart\u0101t"
    ],
    "wof:name":"Jartat",
    "wof:placetype":"locality"
},
  "geometry": {"coordinates":[44.20044,14.34304],"type":"Point"}
}