{
  "type": "Feature",
  "properties": {
    "gn:admin1_code":"27.0",
    "gn:admin2_code":"3105.0",
    "gn:asciiname":"`Arsimah",
    "gn:country_code":"YE",
    "gn:dem":447,
    "gn:feature_class":"P",
    "gn:feature_code":"PPL",
    "gn:name":"\u2018Ar\u015fimah",
    "gn:population":0,
    "gn:timezone":"Asia/Aden",
    "iso:country":"YE",
    "name:und_x_variant":[
        "\u2018Ar\u015fimah",
        "Ar\u015f\u012bmah"
    ],
    "wof:name":"`Arsimah",
    "wof:placetype":"locality"
},
  "geometry": {"coordinates":[43.55359,14.4026],"type":"Point"}
}