{
  "type": "Feature",
  "properties": {
    "gn:country":"YE",
    "gn:fcode":"PPLX",
    "gn:population":19,
    "iso:country":"YE",
    "name:ara_x_preferred":[
        "\u0627\u0644\u0631\u0647\u0648\u0629"
    ],
    "qs:name":"Ar Rahwah",
    "qs:photos_9r":0,
    "qs:photos_sr":0,
    "qs:pop_sr":"1",
    "wof:name":"Ar Rahwah",
    "wof:placetype":"neighbourhood",
    "wof:population":19
},
  "geometry": {"coordinates":[43.41865,17.36535],"type":"Point"}
}