{
  "type": "Feature",
  "properties": {
    "gn:admin1_code":"22.0",
    "gn:admin2_code":"1727.0",
    "gn:asciiname":"Bayt az Zahar",
    "gn:country_code":"YE",
    "gn:dem":1520,
    "gn:feature_class":"P",
    "gn:feature_code":"PPL",
    "gn:name":"Bayt az\u0327 Zah\u0101r",
    "gn:population":0,
    "gn:timezone":"Asia/Aden",
    "iso:country":"YE",
    "name:ara_x_preferred":[
        "\u0628\u064a\u062a \u0627\u0644\u0638\u0647\u0627\u0631"
    ],
    "name:und_x_variant":[
        "Bayt az\u0327 Zah\u0101r"
    ],
    "wof:name":"Bayt az Zahar",
    "wof:placetype":"locality"
},
  "geometry": {"coordinates":[43.57046,15.57629],"type":"Point"}
}