{
  "type": "Feature",
  "properties": {
    "gn:country":"YE",
    "gn:fcode":"FRM",
    "gn:pop":1,
    "iso:country":"YE",
    "name:ara_x_preferred":[
        "\u0623\u0645 \u0627\u0644\u062c\u0627\u0631"
    ],
    "qs:name":"Umm al J\u0101r",
    "qs:photos_9r":0,
    "qs:photos_sr":0,
    "qs:pop_sr":"1",
    "wof:name":"Umm al J\u0101r",
    "wof:placetype":"locality",
    "wof:population":1
},
  "geometry": {"coordinates":[44.86586,16.0637],"type":"Point"}
}