{
  "type": "Feature",
  "properties": {
    "gn:country":"YE",
    "gn:fcode":"PPL",
    "gn:population":2,
    "iso:country":"YE",
    "name:ara_x_preferred":[
        "\u0627\u0644\u0634\u0631\u0642\u064a"
    ],
    "qs:name":"Ash Sharq\u012b",
    "qs:photos_9r":0,
    "qs:photos_sr":0,
    "qs:pop_sr":"1",
    "wof:name":"Ash Sharq\u012b",
    "wof:placetype":"locality",
    "wof:population":2
},
  "geometry": {"coordinates":[43.33299,16.2233],"type":"Point"}
}