{
  "type": "Feature",
  "properties": {
    "gn:country":"YE",
    "gn:fcode":"PPL",
    "gn:pop":10,
    "iso:country":"YE",
    "name:ara_x_preferred":[
        "\u0639\u0645\u0627\u0642\u064a\u0629"
    ],
    "name:eng_x_preferred":[
        "Amaqiyah"
    ],
    "qs:name":"\u2018Am\u0101q\u012byah",
    "qs:photos_9r":0,
    "qs:photos_sr":0,
    "qs:pop_sr":"1",
    "wof:name":"\u2018Am\u0101q\u012byah",
    "wof:placetype":"locality",
    "wof:population":10
},
  "geometry": {"coordinates":[43.44783,16.74639],"type":"Point"}
}