{
  "type": "Feature",
  "properties": {
    "gn:admin1_code":"10.0",
    "gn:admin2_code":"2707.0",
    "gn:asciiname":"Al Khamlu`",
    "gn:country_code":"YE",
    "gn:dem":372,
    "gn:feature_class":"P",
    "gn:feature_code":"PPL",
    "gn:name":"Al Khaml\u016b\u2018",
    "gn:population":0,
    "gn:timezone":"Asia/Aden",
    "iso:country":"YE",
    "name:und_x_variant":[
        "Al Khaml\u016b\u2018"
    ],
    "wof:name":"Al Khamlu`",
    "wof:placetype":"locality"
},
  "geometry": {"coordinates":[43.42126,15.18583],"type":"Point"}
}