{
  "type": "Feature",
  "properties": {
    "gn:admin1_code":"1.0",
    "gn:admin2_code":"1210.0",
    "gn:asciiname":"Hisn Al Shaddad",
    "gn:cc2":"YE",
    "gn:country_code":"YE",
    "gn:dem":12,
    "gn:feature_class":"P",
    "gn:feature_code":"PPL",
    "gn:name":"\u1e28i\u015fn \u0100l Shadd\u0101d",
    "gn:population":0,
    "gn:timezone":"Asia/Aden",
    "iso:country":"YE",
    "name:und_x_variant":[
        "Dahal Ahmad",
        "\u1e28i\u015fn Shadad",
        "\u1e28u\u015fn Shadad",
        "\u1e28i\u015fn \u0100l Shadd\u0101d"
    ],
    "wof:name":"Hisn Al Shaddad",
    "wof:placetype":"locality"
},
  "geometry": {"coordinates":[45.38639000000001,13.11778],"type":"Point"}
}