{
  "type": "Feature",
  "properties": {
    "gn:admin1_code":"23.0",
    "gn:admin2_code":"1101.0",
    "gn:asciiname":"Sha'b al Wali",
    "gn:country_code":"YE",
    "gn:dem":1257,
    "gn:feature_class":"P",
    "gn:feature_code":"PPL",
    "gn:name":"Sha\u2018b al Wal\u012b",
    "gn:population":0,
    "gn:timezone":"Asia/Aden",
    "iso:country":"YE",
    "name:ara_x_preferred":[
        "\u0634\u0639\u0628 \u0627\u0644\u0648\u0644\u064a"
    ],
    "name:und_x_variant":[
        "Sha\u2018b al Wal\u012b"
    ],
    "wof:name":"Sha'b al Wali",
    "wof:placetype":"locality"
},
  "geometry": {"coordinates":[44.08882,14.27025],"type":"Point"}
}