{
  "type": "Feature",
  "properties": {
    "gn:admin1_code":"15.0",
    "gn:admin2_code":"2203.0",
    "gn:asciiname":"Al Jur`at",
    "gn:country_code":"YE",
    "gn:dem":1401,
    "gn:feature_class":"P",
    "gn:feature_code":"PPL",
    "gn:name":"Al Jur\u2018\u0101t",
    "gn:population":0,
    "gn:timezone":"Asia/Aden",
    "iso:country":"YE",
    "name:ara_x_preferred":[
        "Al Jur\u2018\u0101t"
    ],
    "wof:name":"Al Jur`at",
    "wof:placetype":"locality"
},
  "geometry": {"coordinates":[43.28838,17.16673],"type":"Point"}
}