{
  "type": "Feature",
  "properties": {
    "gn:admin1_code":"11.0",
    "gn:admin2_code":"1101.0",
    "gn:asciiname":"Sahfah",
    "gn:country_code":"YE",
    "gn:dem":2390,
    "gn:feature_class":"P",
    "gn:feature_code":"PPL",
    "gn:name":"\u015ea\u1e29fah",
    "gn:population":0,
    "gn:timezone":"Asia/Aden",
    "iso:country":"YE",
    "name:ara_x_preferred":[
        "\u0635\u062d\u0641\u0629"
    ],
    "name:und_x_variant":[
        "\u015ea\u1e29fah"
    ],
    "wof:name":"Sahfah",
    "wof:placetype":"locality"
},
  "geometry": {"coordinates":[44.25022,14.30271],"type":"Point"}
}