{
  "type": "Feature",
  "properties": {
    "gn:admin1_code":"8.0",
    "gn:admin2_code":"1813.0",
    "gn:asciiname":"Harat an Nur",
    "gn:country_code":"YE",
    "gn:dem":145,
    "gn:feature_class":"P",
    "gn:feature_code":"PPL",
    "gn:name":"\u1e28\u0101rat an N\u016br",
    "gn:population":0,
    "gn:timezone":"Asia/Aden",
    "iso:country":"YE",
    "name:ara_x_preferred":[
        "Ar R\u0101kib"
    ],
    "name:ara_x_variant":[
        "\u062d\u0627\u0631\u0629 \u0627\u0644\u0646\u0648\u0631"
    ],
    "name:und_x_variant":[
        "\u1e28\u0101rat an N\u016br"
    ],
    "wof:name":"Harat an Nur",
    "wof:placetype":"locality"
},
  "geometry": {"coordinates":[43.2407,14.96738],"type":"Point"}
}