{
  "type": "Feature",
  "properties": {
    "gn:admin1_code":"14.0",
    "gn:admin2_code":"2606.0",
    "gn:asciiname":"Nujayran",
    "gn:country_code":"YE",
    "gn:dem":1273,
    "gn:feature_class":"P",
    "gn:feature_code":"PPL",
    "gn:name":"Nujayr\u0101n",
    "gn:population":0,
    "gn:timezone":"Asia/Aden",
    "iso:country":"YE",
    "name:ara_x_preferred":[
        "\u0646\u062c\u064a\u0631\u0627\u0646"
    ],
    "name:und_x_variant":[
        "Nujayr\u0101n"
    ],
    "wof:name":"Nujayran",
    "wof:placetype":"locality"
},
  "geometry": {"coordinates":[44.96708,15.56221],"type":"Point"}
}