{
  "type": "Feature",
  "properties": {
    "gn:admin1_code":"11.0",
    "gn:asciiname":"Najd al Mikhzan",
    "gn:country_code":"YE",
    "gn:dem":2616,
    "gn:feature_class":"P",
    "gn:feature_code":"PPL",
    "gn:name":"Najd al Mikhz\u0101n",
    "gn:population":0,
    "gn:timezone":"Asia/Aden",
    "iso:country":"YE",
    "name:ara_x_preferred":[
        "\u0646\u062c\u062f \u0627\u0644\u0645\u062e\u0632\u0627\u0646"
    ],
    "name:und_x_variant":[
        "Najd al Mikhz\u0101n"
    ],
    "wof:name":"Najd al Mikhzan",
    "wof:placetype":"locality"
},
  "geometry": {"coordinates":[44.32135,14.33182],"type":"Point"}
}