{
  "type": "Feature",
  "properties": {
    "gn:admin1_code":"20.0",
    "gn:admin2_code":"1403.0",
    "gn:asciiname":"Al Hamatah",
    "gn:country_code":"YE",
    "gn:dem":1739,
    "gn:feature_class":"P",
    "gn:feature_code":"PPL",
    "gn:name":"Al \u1e28am\u0101\u0163ah",
    "gn:population":0,
    "gn:timezone":"Asia/Aden",
    "iso:country":"YE",
    "name:ara_x_preferred":[
        "\u0627\u0644\u062d\u0645\u0627\u0637\u0629"
    ],
    "name:und_x_variant":[
        "Al \u1e28am\u0101\u0163ah",
        "Hamatah",
        "Al \u1e28am\u0101lah"
    ],
    "wof:name":"Al Hamatah",
    "wof:placetype":"locality"
},
  "geometry": {"coordinates":[45.72037,14.4764],"type":"Point"}
}