{
  "type": "Feature",
  "properties": {
    "gn:admin1_code":"15.0",
    "gn:admin2_code":"2203.0",
    "gn:asciiname":"Al Haqabah",
    "gn:country_code":"YE",
    "gn:dem":854,
    "gn:feature_class":"P",
    "gn:feature_code":"PPL",
    "gn:name":"Al \u1e28aqabah",
    "gn:population":0,
    "gn:timezone":"Asia/Aden",
    "iso:country":"YE",
    "name:ara_x_preferred":[
        "\u0627\u0644\u062d\u0642\u0628\u0629"
    ],
    "name:und_x_variant":[
        "Al \u1e28aqabah"
    ],
    "wof:name":"Al Haqabah",
    "wof:placetype":"locality"
},
  "geometry": {"coordinates":[43.26571,17.25592],"type":"Point"}
}