{
  "type": "Feature",
  "properties": {
    "gn:admin1_code":"25.0",
    "gn:admin2_code":"1501.0",
    "gn:asciiname":"Murayran",
    "gn:country_code":"YE",
    "gn:dem":1346,
    "gn:feature_class":"P",
    "gn:feature_code":"PPL",
    "gn:name":"Murayr\u0101n",
    "gn:population":0,
    "gn:timezone":"Asia/Aden",
    "iso:country":"YE",
    "name:und_x_variant":[
        "Murayr\u0101n"
    ],
    "wof:name":"Murayran",
    "wof:placetype":"locality"
},
  "geometry": {"coordinates":[44.30914,13.61789],"type":"Point"}
}