{
  "type": "Feature",
  "properties": {
    "gn:admin1_code":"8.0",
    "gn:admin2_code":"1815.0",
    "gn:asciiname":"Qaryat al Battarah",
    "gn:country_code":"YE",
    "gn:dem":176,
    "gn:feature_class":"P",
    "gn:feature_code":"PPL",
    "gn:name":"Qaryat al Battarah",
    "gn:population":0,
    "gn:timezone":"Asia/Aden",
    "iso:country":"YE",
    "name:und_x_variant":[
        "Qaryat al Batt\u0101rah"
    ],
    "wof:name":"Qaryat al Battarah",
    "wof:placetype":"locality"
},
  "geometry": {"coordinates":[43.38715,14.76206],"type":"Point"}
}