{
  "type": "Feature",
  "properties": {
    "gn:country":"YE",
    "gn:fcode":"PPL",
    "gn:population":8,
    "iso:country":"YE",
    "name:ara_x_preferred":[
        "\u0627\u0644\u0639\u062b\u064a\u0645\u064a\u0629"
    ],
    "name:eng_x_preferred":[
        "Al 'Uthaymiyah"
    ],
    "name:eng_x_variant":[
        "Al Mukhrij\u012byah"
    ],
    "qs:name":"Al \u2018Uthaym\u012byah",
    "qs:photos_9r":0,
    "qs:photos_sr":0,
    "qs:pop_sr":"1",
    "wof:name":"Al \u2018Uthaym\u012byah",
    "wof:placetype":"locality",
    "wof:population":8
},
  "geometry": {"coordinates":[45.05683,14.28631],"type":"Point"}
}