{
  "type": "Feature",
  "properties": {
    "gn:admin1_code":"23.0",
    "gn:admin2_code":"1114.0",
    "gn:asciiname":"Kashe",
    "gn:country_code":"YE",
    "gn:dem":1594,
    "gn:feature_class":"P",
    "gn:feature_code":"PPL",
    "gn:name":"Kashe",
    "gn:population":0,
    "gn:timezone":"Asia/Aden",
    "iso:country":"YE",
    "wof:name":"Kashe",
    "wof:placetype":"locality"
},
  "geometry": {"coordinates":[44.26667,13.75],"type":"Point"}
}