{
  "type": "Feature",
  "properties": {
    "gn:admin1_code":"23.0",
    "gn:admin2_code":"1109.0",
    "gn:asciiname":"Suq as Sabt",
    "gn:country_code":"YE",
    "gn:dem":1133,
    "gn:feature_class":"P",
    "gn:feature_code":"PPL",
    "gn:name":"S\u016bq as Sabt",
    "gn:population":0,
    "gn:timezone":"Asia/Aden",
    "iso:country":"YE",
    "name:ara_x_preferred":[
        "\u0633\u0648\u0642 \u0627\u0644\u0633\u0628\u062a"
    ],
    "name:und_x_variant":[
        "S\u016bq as Sabt"
    ],
    "wof:name":"Suq as Sabt",
    "wof:placetype":"locality"
},
  "geometry": {"coordinates":[43.92801,14.09065],"type":"Point"}
}