{
  "type": "Feature",
  "properties": {
    "gn:admin1_code":"8.0",
    "gn:admin2_code":"1817.0",
    "gn:asciiname":"Al Ghazaliyah",
    "gn:country_code":"YE",
    "gn:dem":256,
    "gn:feature_class":"P",
    "gn:feature_code":"PPL",
    "gn:name":"Al Ghaz\u0101l\u012byah",
    "gn:population":0,
    "gn:timezone":"Asia/Aden",
    "iso:country":"YE",
    "name:ara_x_preferred":[
        "\u0627\u0644\u063a\u0632\u0627\u0644\u064a\u0629"
    ],
    "name:und_x_variant":[
        "Al Ghaz\u0101l\u012byah"
    ],
    "wof:name":"Al Ghazaliyah",
    "wof:placetype":"locality"
},
  "geometry": {"coordinates":[43.47119,14.61144],"type":"Point"}
}