{
  "type": "Feature",
  "properties": {
    "gn:country":"YE",
    "gn:fcode":"PPL",
    "gn:pop":25,
    "iso:country":"YE",
    "name:ara_x_preferred":[
        "\u0627\u0644\u062c\u0648\u0629"
    ],
    "name:unk_x_variant":[
        "Al Jawwah"
    ],
    "qs:name":"Al Jawwah al Kha\u0163\u0101r",
    "qs:photos_9r":0,
    "qs:photos_sr":0,
    "qs:pop_sr":"1",
    "wof:name":"Al Jawwah al Kha\u0163\u0101r",
    "wof:placetype":"locality",
    "wof:population":25
},
  "geometry": {"coordinates":[44.20854,16.94063],"type":"Point"}
}