{
  "type": "Feature",
  "properties": {
    "gn:admin1_code":"14.0",
    "gn:admin2_code":"2611.0",
    "gn:asciiname":"Khalilat as Sa`idi",
    "gn:country_code":"YE",
    "gn:dem":2096,
    "gn:feature_class":"P",
    "gn:feature_code":"PPL",
    "gn:name":"Khal\u012blat as Sa\u2018\u012bd\u012b",
    "gn:population":0,
    "gn:timezone":"Asia/Aden",
    "iso:country":"YE",
    "name:und_x_variant":[
        "Khal\u012blat as Sa\u2018\u012bd\u012b",
        "Khal\u012blah"
    ],
    "wof:name":"Khalilat as Sa`idi",
    "wof:placetype":"locality"
},
  "geometry": {"coordinates":[45.38607,14.66721],"type":"Point"}
}