{
  "type": "Feature",
  "properties": {
    "gn:admin1_code":"23.0",
    "gn:admin2_code":"1114.0",
    "gn:asciiname":"As Salqa`",
    "gn:country_code":"YE",
    "gn:dem":1740,
    "gn:feature_class":"P",
    "gn:feature_code":"PPL",
    "gn:name":"A\u015f \u015ealqa\u2018",
    "gn:population":0,
    "gn:timezone":"Asia/Aden",
    "iso:country":"YE",
    "name:und_x_variant":[
        "A\u015f \u015ealqa\u2018"
    ],
    "wof:name":"As Salqa`",
    "wof:placetype":"locality"
},
  "geometry": {"coordinates":[44.355,13.88006],"type":"Point"}
}