{
  "type": "Feature",
  "properties": {
    "gn:admin1_code":"19.0",
    "gn:admin2_code":"2903.0",
    "gn:asciiname":"Al Gharb",
    "gn:country_code":"YE",
    "gn:dem":1139,
    "gn:feature_class":"P",
    "gn:feature_code":"PPL",
    "gn:name":"Al Gharb",
    "gn:population":0,
    "gn:timezone":"Asia/Aden",
    "iso:country":"YE",
    "name:ara_x_preferred":[
        "\u0627\u0644\u063a\u0628\u0631"
    ],
    "wof:name":"Al Gharb",
    "wof:placetype":"locality"
},
  "geometry": {"coordinates":[43.79778,16.16182],"type":"Point"}
}