{
  "type": "Feature",
  "properties": {
    "gn:gn_country":"YE",
    "gn:gn_fcode":"PPLX",
    "gn:gn_pop":13,
    "gn:population":13,
    "iso:country":"YE",
    "name:ara_x_preferred":[
        "\u2018A\u015f\u012bm"
    ],
    "name:ara_x_variant":[
        "\u0639\u0635\u064a\u0645"
    ],
    "qs_pg:aaroncc":"YE",
    "qs_pg:gn_country":"YE",
    "qs_pg:gn_fcode":"PPLX",
    "qs_pg:gn_pop":13,
    "qs_pg:name":"\u2018A\u015f\u012bm",
    "qs_pg:photos_9r":0,
    "qs_pg:photos_sr":0,
    "qs_pg:pop_sr":1,
    "qs_pg:qs_pg_placetype":"neighbourhood",
    "wof:name":"\u2018A\u015f\u012bm",
    "wof:placetype":"neighbourhood",
    "wof:population":13
},
  "geometry": {"coordinates":[44.37579,16.71069],"type":"Point"}
}