{
  "type": "Feature",
  "properties": {
    "gn:admin1_code":"25.0",
    "gn:admin2_code":"1501.0",
    "gn:asciiname":"Qaryat An`am",
    "gn:country_code":"YE",
    "gn:dem":1210,
    "gn:feature_class":"P",
    "gn:feature_code":"PPL",
    "gn:name":"Qaryat An\u2018am",
    "gn:population":0,
    "gn:timezone":"Asia/Aden",
    "iso:country":"YE",
    "name:und_x_variant":[
        "Qaryat An\u2018am"
    ],
    "wof:name":"Qaryat An`am",
    "wof:placetype":"locality"
},
  "geometry": {"coordinates":[44.23938,13.63371],"type":"Point"}
}