{
  "type": "Feature",
  "properties": {
    "gn:admin1_code":"22.0",
    "gn:admin2_code":"1722.0",
    "gn:asciiname":"Mahall Salim Fa'iz",
    "gn:country_code":"YE",
    "gn:dem":555,
    "gn:feature_class":"P",
    "gn:feature_code":"PPL",
    "gn:name":"Ma\u1e29all S\u0101lim F\u0101\u2019iz",
    "gn:population":0,
    "gn:timezone":"Asia/Aden",
    "iso:country":"YE",
    "name:und_x_variant":[
        "Ma\u1e29all S\u0101lim F\u0101\u2019iz"
    ],
    "wof:name":"Mahall Salim Fa'iz",
    "wof:placetype":"locality"
},
  "geometry": {"coordinates":[43.317,15.79513],"type":"Point"}
}