{
  "type": "Feature",
  "properties": {
    "gn:admin1_code":"23.0",
    "gn:admin2_code":"1106.0",
    "gn:asciiname":"Bayt Muharram",
    "gn:country_code":"YE",
    "gn:dem":2283,
    "gn:feature_class":"P",
    "gn:feature_code":"PPL",
    "gn:name":"Bayt Mu\u1e29arram",
    "gn:population":0,
    "gn:timezone":"Asia/Aden",
    "iso:country":"YE",
    "name:ara_x_preferred":[
        "\u0628\u064a\u062a \u0645\u062d\u0631\u0645"
    ],
    "name:und_x_variant":[
        "Bayt Mu\u1e29arram"
    ],
    "wof:name":"Bayt Muharram",
    "wof:placetype":"locality"
},
  "geometry": {"coordinates":[44.40851,14.12144],"type":"Point"}
}