{
  "type": "Feature",
  "properties": {
    "gn:country":"YE",
    "gn:fcode":"PPL",
    "gn:pop":1,
    "iso:country":"YE",
    "name:ara_x_preferred":[
        "\u0627\u0644\u0638\u0641\u0631"
    ],
    "qs:name":"Az\u0327 Z\u0327afar",
    "qs:photos_9r":0,
    "qs:photos_sr":0,
    "qs:pop_sr":"1",
    "wof:name":"Az\u0327 Z\u0327afar",
    "wof:placetype":"locality",
    "wof:population":1
},
  "geometry": {"coordinates":[43.39244,16.13737],"type":"Point"}
}