{
  "type": "Feature",
  "properties": {
    "gn:admin1_code":"5.0",
    "gn:admin2_code":"2115.0",
    "gn:asciiname":"Ar Ridahah",
    "gn:country_code":"YE",
    "gn:dem":738,
    "gn:feature_class":"P",
    "gn:feature_code":"PPL",
    "gn:name":"Ar Rid\u0101\u1e29ah",
    "gn:population":0,
    "gn:timezone":"Asia/Aden",
    "iso:country":"YE",
    "name:und_x_variant":[
        "Radeha",
        "Al-Rid\u0101hah",
        "Radaha",
        "Ar Rid\u0101\u1e29ah"
    ],
    "wof:name":"Ar Ridahah",
    "wof:placetype":"locality"
},
  "geometry": {"coordinates":[47.27778,14.43143],"type":"Point"}
}