{
  "type": "Feature",
  "properties": {
    "gn:country":"YE",
    "gn:fcode":"PPL",
    "gn:pop":5,
    "iso:country":"YE",
    "name:ara_x_preferred":[
        "\u0627\u0644\u062c\u0628\u0631"
    ],
    "name:eng_x_preferred":[
        "Al Jabar"
    ],
    "name:eng_x_variant":[
        "\u0100l \u1e28umayq\u0101n"
    ],
    "qs:name":"Al Jabar",
    "qs:photos_9r":0,
    "qs:photos_sr":0,
    "qs:pop_sr":"1",
    "wd:wordcount":14,
    "wof:name":"Al Jabar",
    "wof:placetype":"locality",
    "wof:population":5
},
  "geometry": {"coordinates":[45.55789,14.04074],"type":"Point"}
}