{
  "type": "Feature",
  "properties": {
    "gn:admin1_code":"22.0",
    "gn:admin2_code":"1725.0",
    "gn:asciiname":"Al Akwas",
    "gn:country_code":"YE",
    "gn:dem":752,
    "gn:feature_class":"P",
    "gn:feature_code":"PPL",
    "gn:name":"Al Akw\u0101s",
    "gn:population":0,
    "gn:timezone":"Asia/Aden",
    "iso:country":"YE",
    "name:ara_x_preferred":[
        "\u0627\u0644\u0623\u0643\u0648\u0627\u0633"
    ],
    "name:und_x_variant":[
        "Al Akw\u0101s"
    ],
    "wof:name":"Al Akwas",
    "wof:placetype":"locality"
},
  "geometry": {"coordinates":[43.53982,15.55254],"type":"Point"}
}