{
  "type": "Feature",
  "properties": {
    "gn:admin1_code":"21.0",
    "gn:admin2_code":"1603.0",
    "gn:asciiname":"An Na'amah al 'Ulya",
    "gn:country_code":"YE",
    "gn:dem":1194,
    "gn:feature_class":"P",
    "gn:feature_code":"PPL",
    "gn:name":"An Na\u2018\u0101mah al \u2018Uly\u0101",
    "gn:population":0,
    "gn:timezone":"Asia/Aden",
    "iso:country":"YE",
    "name:ara_x_preferred":[
        "\u0627\u0644\u0646\u0639\u0627\u0645\u0629 \u0627\u0644\u0639\u0644\u064a\u0627"
    ],
    "name:und_x_variant":[
        "An Na\u2018\u0101mah al \u2018Uly\u0101"
    ],
    "wof:name":"An Na'amah al 'Ulya",
    "wof:placetype":"locality"
},
  "geometry": {"coordinates":[44.49712,16.28862],"type":"Point"}
}