{
  "type": "Feature",
  "properties": {
    "gn:country":"YE",
    "gn:fcode":"PPL",
    "gn:pop":5,
    "iso:country":"YE",
    "name:ara_x_preferred":[
        "\u0627\u0644\u0642\u0648\u0627\u0639\u0640\u0640\u062f"
    ],
    "name:eng_x_preferred":[
        "Al Qawa'id"
    ],
    "qs:name":"Al Qaw\u0101\u2018id",
    "qs:photos_9r":0,
    "qs:photos_sr":0,
    "qs:pop_sr":"1",
    "wof:name":"Al Qaw\u0101\u2018id",
    "wof:placetype":"locality",
    "wof:population":5
},
  "geometry": {"coordinates":[43.39849,16.04278],"type":"Point"}
}