{
  "type": "Feature",
  "properties": {
    "gn:admin1_code":"1.0",
    "gn:admin2_code":"1204.0",
    "gn:asciiname":"Am Faysh",
    "gn:country_code":"YE",
    "gn:dem":1019,
    "gn:feature_class":"P",
    "gn:feature_code":"PPL",
    "gn:name":"Am Faysh",
    "gn:population":0,
    "gn:timezone":"Asia/Aden",
    "iso:country":"YE",
    "name:und_x_variant":[
        "Umm Faysh",
        "Am Faysh",
        "Al Faysh"
    ],
    "wof:name":"Am Faysh",
    "wof:placetype":"locality"
},
  "geometry": {"coordinates":[45.83754,13.56231],"type":"Point"}
}