{
  "type": "Feature",
  "properties": {
    "gn:admin1_code":"16.0",
    "gn:admin2_code":"2313.0",
    "gn:asciiname":"Mahall Naq`ah",
    "gn:country_code":"YE",
    "gn:dem":2300,
    "gn:feature_class":"P",
    "gn:feature_code":"PPL",
    "gn:name":"Ma\u1e29all Naq\u2018ah",
    "gn:population":0,
    "gn:timezone":"Asia/Aden",
    "iso:country":"YE",
    "name:und_x_variant":[
        "Ma\u1e29all Naq\u2018ah"
    ],
    "wof:name":"Mahall Naq`ah",
    "wof:placetype":"locality"
},
  "geometry": {"coordinates":[44.66118,15.34496],"type":"Point"}
}