{
  "type": "Feature",
  "properties": {
    "gn:admin1_code":"10.0",
    "gn:admin2_code":"2709.0",
    "gn:asciiname":"Al Ma`ras",
    "gn:country_code":"YE",
    "gn:dem":1925,
    "gn:feature_class":"P",
    "gn:feature_code":"PPL",
    "gn:name":"Al Ma\u2018ras",
    "gn:population":0,
    "gn:timezone":"Asia/Aden",
    "iso:country":"YE",
    "name:und_x_variant":[
        "Al Ma\u2018ras"
    ],
    "wof:name":"Al Ma`ras",
    "wof:placetype":"locality"
},
  "geometry": {"coordinates":[43.5253,15.48002],"type":"Point"}
}