{
  "type": "Feature",
  "properties": {
    "gn:admin1_code":"15.0",
    "gn:admin2_code":"2209.0",
    "gn:asciiname":"`Itfat Bin Bishr",
    "gn:country_code":"YE",
    "gn:dem":2157,
    "gn:feature_class":"P",
    "gn:feature_code":"PPL",
    "gn:name":"\u2018I\u0163fat Bin Bishr",
    "gn:population":0,
    "gn:timezone":"Asia/Aden",
    "iso:country":"YE",
    "name:und_x_variant":[
        "\u2018I\u0163fat Bin Bishr"
    ],
    "wof:name":"`Itfat Bin Bishr",
    "wof:placetype":"locality"
},
  "geometry": {"coordinates":[43.54535,16.84333],"type":"Point"}
}