{
  "type": "Feature",
  "properties": {
    "gn:admin1_code":"16.0",
    "gn:admin2_code":"2307.0",
    "gn:asciiname":"Sayh",
    "gn:country_code":"YE",
    "gn:dem":1960,
    "gn:feature_class":"P",
    "gn:feature_code":"PPL",
    "gn:name":"\u015eay\u1e29",
    "gn:population":0,
    "gn:timezone":"Asia/Aden",
    "iso:country":"YE",
    "name:und_x_variant":[
        "\u015eay\u1e29"
    ],
    "wof:name":"Sayh",
    "wof:placetype":"locality"
},
  "geometry": {"coordinates":[43.89113,15.39472],"type":"Point"}
}