{
  "type": "Feature",
  "properties": {
    "gn:country":"YE",
    "gn:fcode":"PPL",
    "gn:population":10,
    "iso:country":"YE",
    "name:ara_x_preferred":[
        "Al Qur\u1e29\u0101\u2019"
    ],
    "name:ara_x_variant":[
        "\u0627\u0644\u0642\u0631\u062d\u0627\u0621"
    ],
    "name:eng_x_preferred":[
        "Al Qurha"
    ],
    "name:eng_x_variant":[
        "Ath Thaybah"
    ],
    "qs:name":"Al Qur\u1e29\u0101\u2019",
    "qs:photos_9r":0,
    "qs:photos_sr":0,
    "qs:pop_sr":"1",
    "wof:name":"Al Qur\u1e29\u0101\u2019",
    "wof:placetype":"locality",
    "wof:population":10
},
  "geometry": {"coordinates":[44.47612,16.65071],"type":"Point"}
}