{
  "type": "Feature",
  "properties": {
    "gn:admin1_code":"11.0",
    "gn:admin2_code":"2003.0",
    "gn:asciiname":"Bayt al Bariq",
    "gn:country_code":"YE",
    "gn:dem":1948,
    "gn:feature_class":"P",
    "gn:feature_code":"PPL",
    "gn:name":"Bayt al B\u0101riq",
    "gn:population":0,
    "gn:timezone":"Asia/Aden",
    "iso:country":"YE",
    "name:und_x_variant":[
        "Bayt al B\u0101riq"
    ],
    "wof:name":"Bayt al Bariq",
    "wof:placetype":"locality"
},
  "geometry": {"coordinates":[43.90291,14.78177],"type":"Point"}
}