{
  "type": "Feature",
  "properties": {
    "gn:admin1_code":"11.0",
    "gn:admin2_code":"2001.0",
    "gn:asciiname":"Ash Sha`mali",
    "gn:country_code":"YE",
    "gn:dem":2191,
    "gn:feature_class":"P",
    "gn:feature_code":"PPL",
    "gn:name":"Ash Sha\u2018mal\u012b",
    "gn:population":0,
    "gn:timezone":"Asia/Aden",
    "iso:country":"YE",
    "name:ara_x_preferred":[
        "Ash Shu\u2018mul\u012b"
    ],
    "name:ara_x_variant":[
        "\u0627\u0644\u0634\u0639\u0645\u0644\u064a"
    ],
    "name:und_x_variant":[
        "Ash Sha\u2018mal\u012b"
    ],
    "wof:name":"Ash Sha`mali",
    "wof:placetype":"locality"
},
  "geometry": {"coordinates":[44.63376,14.74191],"type":"Point"}
}