{
  "type": "Feature",
  "properties": {
    "gn:admin1_code":"15.0",
    "gn:admin2_code":"2212.0",
    "gn:asciiname":"Al Lajij",
    "gn:country_code":"YE",
    "gn:dem":2016,
    "gn:feature_class":"P",
    "gn:feature_code":"PPL",
    "gn:name":"Al Laj\u012bj",
    "gn:population":0,
    "gn:timezone":"Asia/Aden",
    "iso:country":"YE",
    "name:ara_x_preferred":[
        "\u0627\u0644\u0644\u062c\u064a\u062c"
    ],
    "name:und_x_variant":[
        "Al Laj\u012bj"
    ],
    "wof:name":"Al Lajij",
    "wof:placetype":"locality"
},
  "geometry": {"coordinates":[43.83027,16.78855],"type":"Point"}
}