{
  "type": "Feature",
  "properties": {
    "gn:admin1_code":"25.0",
    "gn:admin2_code":"1516.0",
    "gn:asciiname":"Al `Uqdah",
    "gn:country_code":"YE",
    "gn:dem":646,
    "gn:feature_class":"P",
    "gn:feature_code":"PPL",
    "gn:name":"Al \u2018Uqdah",
    "gn:population":0,
    "gn:timezone":"Asia/Aden",
    "iso:country":"YE",
    "name:ara_x_preferred":[
        "\u0627\u0644\u0639\u0642\u062f\u0629"
    ],
    "name:und_x_variant":[
        "Al \u2018Uqdah"
    ],
    "wof:name":"Al `Uqdah",
    "wof:placetype":"locality"
},
  "geometry": {"coordinates":[43.81817,13.14274],"type":"Point"}
}