{
  "type": "Feature",
  "properties": {
    "gn:admin1_code":"23.0",
    "gn:admin2_code":"1102.0",
    "gn:asciiname":"Bayt Kandash",
    "gn:country_code":"YE",
    "gn:dem":2789,
    "gn:feature_class":"P",
    "gn:feature_code":"PPL",
    "gn:name":"Bayt Kand\u0101sh",
    "gn:population":0,
    "gn:timezone":"Asia/Aden",
    "iso:country":"YE",
    "name:ara_x_preferred":[
        "\u0628\u064a\u062a \u0643\u0646\u062f\u0627\u0634"
    ],
    "name:und_x_variant":[
        "Bayt Kind\u0101sh",
        "Bayt Kand\u0101sh"
    ],
    "wof:name":"Bayt Kandash",
    "wof:placetype":"locality"
},
  "geometry": {"coordinates":[44.33733,14.1462],"type":"Point"}
}