{
  "type": "Feature",
  "properties": {
    "gn:admin1_code":"19.0",
    "gn:admin2_code":"2901.0",
    "gn:asciiname":"Al Mizhat",
    "gn:country_code":"YE",
    "gn:dem":1819,
    "gn:feature_class":"P",
    "gn:feature_code":"PPL",
    "gn:name":"Al Miz\u1e29\u0101\u0163",
    "gn:population":0,
    "gn:timezone":"Asia/Aden",
    "iso:country":"YE",
    "name:ara_x_preferred":[
        "Al Miz\u1e29\u0101\u0163"
    ],
    "name:und_x_variant":[
        "Al Mas\u1e29a\u0163"
    ],
    "wof:name":"Al Mizhat",
    "wof:placetype":"locality"
},
  "geometry": {"coordinates":[43.89321,16.63424],"type":"Point"}
}