{
  "type": "Feature",
  "properties": {
    "gn:admin1_code":"23.0",
    "gn:admin2_code":"1101.0",
    "gn:asciiname":"'Adan Mashariq",
    "gn:country_code":"YE",
    "gn:dem":1649,
    "gn:feature_class":"P",
    "gn:feature_code":"PPL",
    "gn:name":"\u2018Adan Mash\u0101riq",
    "gn:population":0,
    "gn:timezone":"Asia/Aden",
    "iso:country":"YE",
    "name:ara_x_preferred":[
        "\u0639\u062f\u0646 \u0645\u0634\u0627\u0631\u0642"
    ],
    "name:und_x_variant":[
        "\u2018Adan Mash\u0101riq"
    ],
    "wof:name":"'Adan Mashariq",
    "wof:placetype":"locality"
},
  "geometry": {"coordinates":[44.14857,14.25904],"type":"Point"}
}