{
  "type": "Feature",
  "properties": {
    "gn:admin1_code":"1.0",
    "gn:admin2_code":"1211.0",
    "gn:asciiname":"Kadamat al Faysh",
    "gn:country_code":"YE",
    "gn:dem":17,
    "gn:feature_class":"P",
    "gn:feature_code":"PPL",
    "gn:name":"Kadamat al Faysh",
    "gn:population":0,
    "gn:timezone":"Asia/Aden",
    "iso:country":"YE",
    "name:nno_x_preferred":[
        "Kadamat Al Faysh"
    ],
    "wof:name":"Kadamat al Faysh",
    "wof:placetype":"locality"
},
  "geometry": {"coordinates":[45.33111,13.09056],"type":"Point"}
}