{
  "type": "Feature",
  "properties": {
    "gn:admin1_code":"22.0",
    "gn:admin2_code":"1709.0",
    "gn:asciiname":"Al Haniyah",
    "gn:country_code":"YE",
    "gn:dem":1791,
    "gn:feature_class":"P",
    "gn:feature_code":"PPL",
    "gn:name":"Al \u1e28an\u012byah",
    "gn:population":0,
    "gn:timezone":"Asia/Aden",
    "iso:country":"YE",
    "name:ara_x_preferred":[
        "\u0627\u0644\u062d\u0646\u064a\u0640\u0629"
    ],
    "name:und_x_variant":[
        "Al \u1e28an\u012byah"
    ],
    "wof:name":"Al Haniyah",
    "wof:placetype":"locality"
},
  "geometry": {"coordinates":[43.45821,16.00552],"type":"Point"}
}