{
  "type": "Feature",
  "properties": {
    "gn:admin1_code":"25.0",
    "gn:admin2_code":"1516.0",
    "gn:asciiname":"Hasib al Ghawbah",
    "gn:country_code":"YE",
    "gn:dem":710,
    "gn:feature_class":"P",
    "gn:feature_code":"PPL",
    "gn:name":"\u1e28a\u015fib al Ghawbah",
    "gn:population":0,
    "gn:timezone":"Asia/Aden",
    "iso:country":"YE",
    "name:ara_x_preferred":[
        "\u062d\u0635\u0628 \u0627\u0644\u063a\u0648\u0628\u0629"
    ],
    "name:und_x_variant":[
        "Al \u1e28a\u015fib",
        "\u1e28\u0101shid",
        "\u1e28a\u015fib al Ghawbah"
    ],
    "wof:name":"Hasib al Ghawbah",
    "wof:placetype":"locality"
},
  "geometry": {"coordinates":[43.85448,13.16711],"type":"Point"}
}