{
  "type": "Feature",
  "properties": {
    "gn:country":"YE",
    "gn:fcode":"PPL",
    "gn:pop":3,
    "iso:country":"YE",
    "name:ara_x_preferred":[
        "\u062c\u0628\u0627\u0631\u0629"
    ],
    "name:eng_x_preferred":[
        "Jabarah"
    ],
    "qs:name":"Jab\u0101rah",
    "qs:photos_9r":0,
    "qs:photos_sr":0,
    "qs:pop_sr":"1",
    "wof:name":"Jab\u0101rah",
    "wof:placetype":"locality",
    "wof:population":3
},
  "geometry": {"coordinates":[43.26374,17.16983],"type":"Point"}
}