{
  "type": "Feature",
  "properties": {
    "gn:admin1_code":"8.0",
    "gn:admin2_code":"1818.0",
    "gn:asciiname":"Al Madhruh Rubay`a'",
    "gn:country_code":"YE",
    "gn:dem":610,
    "gn:feature_class":"P",
    "gn:feature_code":"PPL",
    "gn:name":"Al Madhr\u016b\u1e29 Rubay\u2018\u0101\u2019",
    "gn:population":0,
    "gn:timezone":"Asia/Aden",
    "iso:country":"YE",
    "name:und_x_variant":[
        "Al Madhr\u016b\u1e29 Rubay\u2018\u0101\u2019"
    ],
    "wof:name":"Al Madhruh Rubay`a'",
    "wof:placetype":"locality"
},
  "geometry": {"coordinates":[43.75899,14.06427],"type":"Point"}
}