{
  "type": "Feature",
  "properties": {
    "gn:admin1_code":"21.0",
    "gn:admin2_code":"1610.0",
    "gn:asciiname":"Qadmah",
    "gn:country_code":"YE",
    "gn:dem":2180,
    "gn:feature_class":"P",
    "gn:feature_code":"PPL",
    "gn:name":"Qadmah",
    "gn:population":0,
    "gn:timezone":"Asia/Aden",
    "iso:country":"YE",
    "name:ara_x_preferred":[
        "\u0642\u062f\u0645\u0629"
    ],
    "wof:name":"Qadmah",
    "wof:placetype":"locality"
},
  "geometry": {"coordinates":[44.25776,16.77211],"type":"Point"}
}