{
  "type": "Feature",
  "properties": {
    "gn:admin1_code":"11.0",
    "gn:admin2_code":"2011.0",
    "gn:asciiname":"Shawqabah",
    "gn:country_code":"YE",
    "gn:dem":2011,
    "gn:feature_class":"P",
    "gn:feature_code":"PPL",
    "gn:name":"Shawqabah",
    "gn:population":0,
    "gn:timezone":"Asia/Aden",
    "iso:country":"YE",
    "wof:name":"Shawqabah",
    "wof:placetype":"locality"
},
  "geometry": {"coordinates":[44.03239,14.71973],"type":"Point"}
}