{
  "type": "Feature",
  "properties": {
    "gn:admin1_code":"25.0",
    "gn:admin2_code":"1504.0",
    "gn:asciiname":"Al Ghawniyah",
    "gn:country_code":"YE",
    "gn:dem":952,
    "gn:feature_class":"P",
    "gn:feature_code":"PPL",
    "gn:name":"Al Ghawn\u012byah",
    "gn:population":0,
    "gn:timezone":"Asia/Aden",
    "iso:country":"YE",
    "name:ara_x_preferred":[
        "\u0627\u0644\u063a\u0648\u0646\u064a\u0629"
    ],
    "name:und_x_variant":[
        "Al Ghawn\u012byah"
    ],
    "wof:name":"Al Ghawniyah",
    "wof:placetype":"locality"
},
  "geometry": {"coordinates":[43.76483,13.69897],"type":"Point"}
}