{
  "type": "Feature",
  "properties": {
    "gn:admin1_code":"21.0",
    "gn:admin2_code":"1605.0",
    "gn:asciiname":"Al Kurayf",
    "gn:country_code":"YE",
    "gn:dem":1041,
    "gn:feature_class":"P",
    "gn:feature_code":"PPLL",
    "gn:name":"Al Kurayf",
    "gn:population":0,
    "gn:timezone":"Asia/Aden",
    "iso:country":"YE",
    "name:ara_x_preferred":[
        "\u0627\u0644\u0643\u0631\u064a\u0641"
    ],
    "wof:name":"Al Kurayf",
    "wof:placetype":"locality"
},
  "geometry": {"coordinates":[45.13183,15.97185],"type":"Point"}
}