{
  "type": "Feature",
  "properties": {
    "gn:admin1_code":"5.0",
    "gn:admin2_code":"2109.0",
    "gn:asciiname":"An Nuqayt",
    "gn:country_code":"YE",
    "gn:dem":1165,
    "gn:feature_class":"P",
    "gn:feature_code":"PPL",
    "gn:name":"An Nuqay\u0163",
    "gn:population":0,
    "gn:timezone":"Asia/Aden",
    "iso:country":"YE",
    "name:und_x_variant":[
        "An Nuqeil",
        "An Nuqayl",
        "An Nuqay\u0163"
    ],
    "wof:name":"An Nuqayt",
    "wof:placetype":"locality"
},
  "geometry": {"coordinates":[46.17001,14.46558],"type":"Point"}
}