{
  "type": "Feature",
  "properties": {
    "gn:admin1_code":"8.0",
    "gn:admin2_code":"1815.0",
    "gn:asciiname":"Milhani",
    "gn:country_code":"YE",
    "gn:dem":123,
    "gn:feature_class":"P",
    "gn:feature_code":"PPL",
    "gn:name":"Mil\u1e29\u0101n\u012b",
    "gn:population":0,
    "gn:timezone":"Asia/Aden",
    "iso:country":"YE",
    "name:ara_x_preferred":[
        "Mil\u1e29\u0101n\u012b"
    ],
    "wof:name":"Milhani",
    "wof:placetype":"locality"
},
  "geometry": {"coordinates":[43.33552,14.79878],"type":"Point"}
}