{
  "type": "Feature",
  "properties": {
    "gn:country":"YE",
    "gn:fcode":"PPL",
    "gn:population":14,
    "iso:country":"YE",
    "name:ara_x_preferred":[
        "\u0648\u0627\u062f\u064a \u0627\u0644\u0623\u062b\u0628\u0648\u062a"
    ],
    "name:eng_x_preferred":[
        "Wadi Al AthbUt"
    ],
    "name:eng_x_variant":[
        "\u1e28ayd al Quflah"
    ],
    "qs:name":"W\u0101d\u012b al Athb\u016bt",
    "qs:photos_9r":0,
    "qs:photos_sr":0,
    "qs:pop_sr":"1",
    "wof:name":"W\u0101d\u012b al Athb\u016bt",
    "wof:placetype":"locality",
    "wof:population":14
},
  "geometry": {"coordinates":[43.73701,13.44788],"type":"Point"}
}