{
  "type": "Feature",
  "properties": {
    "gn:admin1_code":"21.0",
    "gn:admin2_code":"1610.0",
    "gn:asciiname":"Ar Rihayt",
    "gn:country_code":"YE",
    "gn:dem":1882,
    "gn:feature_class":"P",
    "gn:feature_code":"PPL",
    "gn:name":"Ar Rihay\u0163",
    "gn:population":0,
    "gn:timezone":"Asia/Aden",
    "iso:country":"YE",
    "name:und_x_variant":[
        "Ar Rihay\u0163"
    ],
    "wof:name":"Ar Rihayt",
    "wof:placetype":"locality"
},
  "geometry": {"coordinates":[44.56374,16.81726],"type":"Point"}
}