{
  "type": "Feature",
  "properties": {
    "gn:admin1_code":"15.0",
    "gn:admin2_code":"2203.0",
    "gn:asciiname":"Jar'a",
    "gn:country_code":"YE",
    "gn:dem":807,
    "gn:feature_class":"P",
    "gn:feature_code":"PPL",
    "gn:name":"Jar\u2018\u0101",
    "gn:population":0,
    "gn:timezone":"Asia/Aden",
    "iso:country":"YE",
    "name:ara_x_preferred":[
        "\u062c\u0631\u0639\u0627"
    ],
    "name:und_x_variant":[
        "Jar\u2018\u0101"
    ],
    "wof:name":"Jar'a",
    "wof:placetype":"locality"
},
  "geometry": {"coordinates":[43.25628,17.26152],"type":"Point"}
}