{
  "type": "Feature",
  "properties": {
    "gn:admin1_code":"8.0",
    "gn:admin2_code":"1802.0",
    "gn:asciiname":"Buyut as Sayfani",
    "gn:country_code":"YE",
    "gn:dem":29,
    "gn:feature_class":"P",
    "gn:feature_code":"PPL",
    "gn:name":"Buy\u016bt as Sayf\u0101n\u012b",
    "gn:population":0,
    "gn:timezone":"Asia/Aden",
    "iso:country":"YE",
    "name:und_x_variant":[
        "Buy\u016bt as Sayf\u0101n\u012b"
    ],
    "wof:name":"Buyut as Sayfani",
    "wof:placetype":"locality"
},
  "geometry": {"coordinates":[42.86729,15.58168],"type":"Point"}
}