{
  "type": "Feature",
  "properties": {
    "gn:country":"YE",
    "gn:fcode":"PPL",
    "gn:pop":3,
    "iso:country":"YE",
    "name:ara_x_preferred":[
        "\u0627\u0644\u0634\u0642\u064a\u0631\u0629"
    ],
    "name:eng_x_preferred":[
        "Al Shuqayrah"
    ],
    "qs:name":"Al Shuqayrah",
    "qs:photos_9r":0,
    "qs:photos_sr":0,
    "qs:pop_sr":"1",
    "wof:name":"Al Shuqayrah",
    "wof:placetype":"locality",
    "wof:population":3
},
  "geometry": {"coordinates":[43.78421,13.47174],"type":"Point"}
}