{
  "type": "Feature",
  "properties": {
    "gn:country":"YE",
    "gn:fcode":"PPL",
    "gn:pop":12,
    "iso:country":"YE",
    "name:ara_x_preferred":[
        "\u0634\u0645\u0644\u0644"
    ],
    "name:eng_x_preferred":[
        "Shamlil"
    ],
    "name:eng_x_variant":[
        "Al Qa\u015fabah"
    ],
    "qs:name":"Shamlil",
    "qs:photos_9r":0,
    "qs:photos_sr":0,
    "qs:pop_sr":"1",
    "wof:name":"Shamlil",
    "wof:placetype":"locality",
    "wof:population":12
},
  "geometry": {"coordinates":[44.24338,17.12502],"type":"Point"}
}