{
  "type": "Feature",
  "properties": {
    "gn:admin1_code":"15.0",
    "gn:admin2_code":"2207.0",
    "gn:asciiname":"Al Khilaf",
    "gn:country_code":"YE",
    "gn:dem":337,
    "gn:feature_class":"P",
    "gn:feature_code":"PPL",
    "gn:name":"Al Khil\u0101f",
    "gn:population":0,
    "gn:timezone":"Asia/Aden",
    "iso:country":"YE",
    "name:ara_x_preferred":[
        "Al Khil\u0101f"
    ],
    "name:ara_x_variant":[
        "\u0627\u0644\u062e\u0644\u0627\u0641"
    ],
    "wof:name":"Al Khilaf",
    "wof:placetype":"locality"
},
  "geometry": {"coordinates":[43.25195,16.81268],"type":"Point"}
}