{
  "type": "Feature",
  "properties": {
    "gn:admin1_code":"25.0",
    "gn:admin2_code":"1502.0",
    "gn:asciiname":"Nashit",
    "gn:country_code":"YE",
    "gn:dem":1128,
    "gn:feature_class":"P",
    "gn:feature_code":"PPL",
    "gn:name":"Nash\u012b\u0163",
    "gn:population":0,
    "gn:timezone":"Asia/Aden",
    "iso:country":"YE",
    "name:ara_x_preferred":[
        "\u0646\u0634\u064a\u0637"
    ],
    "name:und_x_variant":[
        "Nash\u012b\u0163"
    ],
    "wof:name":"Nashit",
    "wof:placetype":"locality"
},
  "geometry": {"coordinates":[43.98778,13.64056],"type":"Point"}
}