{
  "type": "Feature",
  "properties": {
    "gn:admin1_code":"25.0",
    "gn:admin2_code":"1504.0",
    "gn:asciiname":"Qataran",
    "gn:country_code":"YE",
    "gn:dem":1246,
    "gn:feature_class":"P",
    "gn:feature_code":"PPL",
    "gn:name":"Qa\u0163ar\u0101n",
    "gn:population":0,
    "gn:timezone":"Asia/Aden",
    "iso:country":"YE",
    "name:und_x_variant":[
        "Qa\u0163ar\u0101n"
    ],
    "wof:name":"Qataran",
    "wof:placetype":"locality"
},
  "geometry": {"coordinates":[43.91275,13.72862],"type":"Point"}
}