{
  "type": "Feature",
  "properties": {
    "gn:admin1_code":"11.0",
    "gn:admin2_code":"2005.0",
    "gn:asciiname":"Suq al `Uwal",
    "gn:country_code":"YE",
    "gn:dem":1335,
    "gn:feature_class":"P",
    "gn:feature_code":"PPL",
    "gn:name":"S\u016bq al \u2018Uwal",
    "gn:population":0,
    "gn:timezone":"Asia/Aden",
    "iso:country":"YE",
    "name:und_x_variant":[
        "S\u016bq al \u2018Uwal"
    ],
    "wof:name":"Suq al `Uwal",
    "wof:placetype":"locality"
},
  "geometry": {"coordinates":[43.94534,14.39705],"type":"Point"}
}