{
  "type": "Feature",
  "properties": {
    "gn:country":"YE",
    "gn:fcode":"PPL",
    "gn:pop":1,
    "iso:country":"YE",
    "name:ara_x_preferred":[
        "\u0645\u0639\u064a\u0646\u0640\u0629 \u0627\u0644\u0639\u0627\u0637\u0640\u0641"
    ],
    "name:eng_x_preferred":[
        "Mu'aynat Al 'Atif"
    ],
    "name:unk_x_variant":[
        "Ma\u2018\u012bnat al \u2018\u0100\u0163if"
    ],
    "qs:name":"Mu\u2018aynat al \u2018\u0100\u0163if",
    "qs:photos_9r":0,
    "qs:photos_sr":0,
    "qs:pop_sr":"1",
    "wof:name":"Mu\u2018aynat al \u2018\u0100\u0163if",
    "wof:placetype":"locality",
    "wof:population":1
},
  "geometry": {"coordinates":[43.83742,13.4501],"type":"Point"}
}