{
  "type": "Feature",
  "properties": {
    "gn:country":"YE",
    "gn:fcode":"PPL",
    "gn:pop":10,
    "iso:country":"YE",
    "name:ara_x_preferred":[
        "Al \u2018Am\u016bd"
    ],
    "name:ara_x_variant":[
        "\u0627\u0644\u0639\u0645\u0648\u062f"
    ],
    "name:eng_x_preferred":[
        "Al 'AmUd"
    ],
    "name:eng_x_variant":[
        "Ash Sharj"
    ],
    "qs:name":"Al \u2018Am\u016bd",
    "qs:photos_9r":0,
    "qs:photos_sr":0,
    "qs:pop_sr":"1",
    "wof:name":"Al \u2018Am\u016bd",
    "wof:placetype":"locality",
    "wof:population":10
},
  "geometry": {"coordinates":[45.15981,14.36317],"type":"Point"}
}