{
  "type": "Feature",
  "properties": {
    "gn:admin1_code":"18.0",
    "gn:admin2_code":"3002.0",
    "gn:asciiname":"`Asma",
    "gn:country_code":"YE",
    "gn:dem":2317,
    "gn:feature_class":"P",
    "gn:feature_code":"PPL",
    "gn:name":"\u2018Asm\u00e1",
    "gn:population":0,
    "gn:timezone":"Asia/Aden",
    "iso:country":"YE",
    "name:ara_x_preferred":[
        "\u2018A\u015fm\u012b"
    ],
    "name:ara_x_variant":[
        "\u0639\u0633\u0645\u0649"
    ],
    "name:und_x_variant":[
        "\u2018Asm\u00e1"
    ],
    "wof:name":"`Asma",
    "wof:placetype":"locality"
},
  "geometry": {"coordinates":[44.64002,14.0289],"type":"Point"}
}