{
  "type": "Feature",
  "properties": {
    "gn:admin1_code":"4.0",
    "gn:admin2_code":"1928.0",
    "gn:asciiname":"Diyar Bin Tamim",
    "gn:country_code":"YE",
    "gn:dem":780,
    "gn:feature_class":"P",
    "gn:feature_code":"PPL",
    "gn:name":"Diy\u0101r Bin Tam\u012bm",
    "gn:population":0,
    "gn:timezone":"Asia/Aden",
    "iso:country":"YE",
    "name:und_x_variant":[
        "Diy\u0101r Bin Tam\u012bm"
    ],
    "wof:name":"Diyar Bin Tamim",
    "wof:placetype":"locality"
},
  "geometry": {"coordinates":[48.08333,15.58333],"type":"Point"}
}