{
  "type": "Feature",
  "properties": {
    "gn:admin1_code":"16.0",
    "gn:admin2_code":"2305.0",
    "gn:asciiname":"Safiyat tamish",
    "gn:country_code":"YE",
    "gn:dem":2329,
    "gn:feature_class":"P",
    "gn:feature_code":"PPL",
    "gn:name":"\u015e\u0101fiyat \u0163\u0101mish",
    "gn:population":0,
    "gn:timezone":"Asia/Aden",
    "iso:country":"YE",
    "name:ara_x_preferred":[
        "\u0635\u0627\u0641\u064a\u0629 \u0637\u0627\u0645\u0634"
    ],
    "name:und_x_variant":[
        "\u015e\u0101fiyat \u0163\u0101mish"
    ],
    "wof:name":"Safiyat tamish",
    "wof:placetype":"locality"
},
  "geometry": {"coordinates":[44.27707,15.29151],"type":"Point"}
}