{
  "type": "Feature",
  "properties": {
    "gn:admin1_code":"16.0",
    "gn:admin2_code":"2301.0",
    "gn:asciiname":"Bayt al Hunaysh",
    "gn:country_code":"YE",
    "gn:dem":2280,
    "gn:feature_class":"P",
    "gn:feature_code":"PPL",
    "gn:name":"Bayt al \u1e28unaysh",
    "gn:population":0,
    "gn:timezone":"Asia/Aden",
    "iso:country":"YE",
    "name:und_x_variant":[
        "Bayt al \u1e28unaysh"
    ],
    "wof:name":"Bayt al Hunaysh",
    "wof:placetype":"locality"
},
  "geometry": {"coordinates":[44.10812,15.443],"type":"Point"}
}