{
  "type": "Feature",
  "properties": {
    "gn:admin1_code":"15.0",
    "gn:admin2_code":"2206.0",
    "gn:asciiname":"Qullat Bin al Halwaj",
    "gn:country_code":"YE",
    "gn:dem":721,
    "gn:feature_class":"P",
    "gn:feature_code":"PPL",
    "gn:name":"Qullat Bin al Halwaj",
    "gn:population":0,
    "gn:timezone":"Asia/Aden",
    "iso:country":"YE",
    "name:ara_x_preferred":[
        "\u0642\u0644\u0629 \u0628\u0646 \u0627\u0644\u0647\u0644\u0648\u062c"
    ],
    "wof:name":"Qullat Bin al Halwaj",
    "wof:placetype":"locality"
},
  "geometry": {"coordinates":[43.17675,16.88736],"type":"Point"}
}