{
  "type": "Feature",
  "properties": {
    "gn:country":"YE",
    "gn:fcode":"PPL",
    "gn:pop":11,
    "iso:country":"YE",
    "name:ara_x_preferred":[
        "\u0627\u0644\u0633\u0648\u062f\u0629"
    ],
    "qs:name":"As Sawdah",
    "qs:photos_9r":0,
    "qs:photos_sr":0,
    "qs:pop_sr":"1",
    "wd:wordcount":498,
    "wof:name":"As Sawdah",
    "wof:placetype":"locality",
    "wof:population":11
},
  "geometry": {"coordinates":[43.3621,16.0677],"type":"Point"}
}