{
  "type": "Feature",
  "properties": {
    "gn:country":"YE",
    "gn:fcode":"PPL",
    "gn:population":11,
    "iso:country":"YE",
    "name:ara_x_preferred":[
        "\u0627\u0644\u0633\u0648\u062f\u0629"
    ],
    "name:ara_x_variant":[
        "\u0627\u0644\u0633\u0648\u062f\u0627"
    ],
    "name:eng_x_preferred":[
        "Al-Sawda"
    ],
    "name:fas_x_preferred":[
        "\u0627\u0644\u0633\u0648\u062f\u0627"
    ],
    "name:nld_x_preferred":[
        "Al-Sawda"
    ],
    "name:nno_x_preferred":[
        "Al-Sawda"
    ],
    "name:pol_x_preferred":[
        "As-Sauda"
    ],
    "name:rus_x_preferred":[
        "\u042d\u0441-\u0421\u0430\u0443\u0434\u0430"
    ],
    "name:ukr_x_preferred":[
        "\u0410\u0441-\u0421\u0430\u0443\u0434\u0430"
    ],
    "name:vie_x_preferred":[
        "Al-Sawda"
    ],
    "qs:name":"As Sawdah",
    "qs:photos_9r":0,
    "qs:photos_sr":0,
    "qs:pop_sr":"1",
    "wd:wordcount":498,
    "wof:name":"As Sawdah",
    "wof:placetype":"locality",
    "wof:population":11
},
  "geometry": {"coordinates":[43.3621,16.0677],"type":"Point"}
}