{
  "type": "Feature",
  "properties": {
    "gn:admin1_code":"14.0",
    "gn:admin2_code":"2605.0",
    "gn:asciiname":"Dar al Jusham",
    "gn:country_code":"YE",
    "gn:dem":2058,
    "gn:feature_class":"P",
    "gn:feature_code":"PPL",
    "gn:name":"D\u0101r al Jusham",
    "gn:population":0,
    "gn:timezone":"Asia/Aden",
    "iso:country":"YE",
    "name:ara_x_preferred":[
        "\u062f\u0627\u0631 \u0627\u0644\u062c\u0634\u0645"
    ],
    "name:und_x_variant":[
        "D\u0101r al Jusham"
    ],
    "wof:name":"Dar al Jusham",
    "wof:placetype":"locality"
},
  "geometry": {"coordinates":[44.70899,15.43363],"type":"Point"}
}