{
  "type": "Feature",
  "properties": {
    "gn:admin1_code":"11.0",
    "gn:admin2_code":"2005.0",
    "gn:asciiname":"Sutah",
    "gn:country_code":"YE",
    "gn:dem":2528,
    "gn:feature_class":"P",
    "gn:feature_code":"PPL",
    "gn:name":"Su\u0163a\u1e29",
    "gn:population":0,
    "gn:timezone":"Asia/Aden",
    "iso:country":"YE",
    "name:und_x_variant":[
        "Su\u0163a\u1e29"
    ],
    "wof:name":"Sutah",
    "wof:placetype":"locality"
},
  "geometry": {"coordinates":[43.92746,14.47512],"type":"Point"}
}