{
  "type": "Feature",
  "properties": {
    "gn:admin1_code":"19.0",
    "gn:admin2_code":"2920.0",
    "gn:asciiname":"As Sirar",
    "gn:country_code":"YE",
    "gn:dem":2369,
    "gn:feature_class":"P",
    "gn:feature_code":"PPL",
    "gn:name":"As Sir\u0101r",
    "gn:population":0,
    "gn:timezone":"Asia/Aden",
    "iso:country":"YE",
    "name:ara_x_preferred":[
        "As Sir\u0101r"
    ],
    "wof:name":"As Sirar",
    "wof:placetype":"locality"
},
  "geometry": {"coordinates":[43.97921,16.11202999999999],"type":"Point"}
}