{
  "type": "Feature",
  "properties": {
    "gn:admin1_code":"8.0",
    "gn:admin2_code":"1813.0",
    "gn:asciiname":"Ad Dahrah",
    "gn:country_code":"YE",
    "gn:dem":166,
    "gn:feature_class":"P",
    "gn:feature_code":"PPL",
    "gn:name":"Ad Da\u1e29rah",
    "gn:population":0,
    "gn:timezone":"Asia/Aden",
    "iso:country":"YE",
    "name:fas_x_preferred":[
        "\u0627\u0644\u062f\u0647\u0631\u0647"
    ],
    "name:nno_x_preferred":[
        "Ad Dahrah"
    ],
    "wof:name":"Ad Dahrah",
    "wof:placetype":"locality"
},
  "geometry": {"coordinates":[43.2936,14.96861],"type":"Point"}
}