{
  "type": "Feature",
  "properties": {
    "gn:admin1_code":"23.0",
    "gn:admin2_code":"1113.0",
    "gn:asciiname":"Al Mahdathah",
    "gn:country_code":"YE",
    "gn:dem":1730,
    "gn:feature_class":"P",
    "gn:feature_code":"PPL",
    "gn:name":"Al Ma\u1e29dathah",
    "gn:population":0,
    "gn:timezone":"Asia/Aden",
    "iso:country":"YE",
    "name:und_x_variant":[
        "Al Ma\u1e29dathah"
    ],
    "wof:name":"Al Mahdathah",
    "wof:placetype":"locality"
},
  "geometry": {"coordinates":[44.37922,13.92277],"type":"Point"}
}