{
  "type": "Feature",
  "properties": {
    "gn:country":"YE",
    "gn:fcode":"PPL",
    "gn:population":3,
    "iso:country":"YE",
    "name:ara_x_preferred":[
        "\u0634\u0639\u0628\u0629 \u0627\u0644\u0646\u0642\u064a\u0644"
    ],
    "name:eng_x_preferred":[
        "Sha'bat An Nuqayl"
    ],
    "name:eng_x_variant":[
        "Maqlabah"
    ],
    "qs:name":"Sha\u2018bat an Nuqayl",
    "qs:photos_9r":0,
    "qs:photos_sr":0,
    "qs:pop_sr":"1",
    "wof:name":"Sha\u2018bat an Nuqayl",
    "wof:placetype":"locality",
    "wof:population":3
},
  "geometry": {"coordinates":[43.80192,13.49126],"type":"Point"}
}