{
  "type": "Feature",
  "properties": {
    "gn:country":"YE",
    "gn:fcode":"PPL",
    "gn:population":6,
    "iso:country":"YE",
    "name:ara_x_preferred":[
        "\u0628\u064a\u062a \u0627\u0644\u062c\u0647\u0631\u0627\u0646\u064a"
    ],
    "name:eng_x_preferred":[
        "Bayt Al Jahrani"
    ],
    "name:eng_x_variant":[
        "Al \u1e28a\u015fab"
    ],
    "qs:name":"Bayt al Jahr\u0101n\u012b",
    "qs:photos_9r":0,
    "qs:photos_sr":0,
    "qs:pop_sr":"1",
    "wof:name":"Bayt al Jahr\u0101n\u012b",
    "wof:placetype":"locality",
    "wof:population":6
},
  "geometry": {"coordinates":[45.27286,14.34724],"type":"Point"}
}