{
  "type": "Feature",
  "properties": {
    "gn:admin1_code":"21.0",
    "gn:admin2_code":"1603.0",
    "gn:asciiname":"Surbat al Faqih",
    "gn:country_code":"YE",
    "gn:dem":1190,
    "gn:feature_class":"P",
    "gn:feature_code":"PPL",
    "gn:name":"Surbat al Faq\u012bh",
    "gn:population":0,
    "gn:timezone":"Asia/Aden",
    "iso:country":"YE",
    "name:ara_x_preferred":[
        "\u0633\u0631\u0628\u0629 \u0627\u0644\u0641\u0642\u064a\u0647"
    ],
    "name:und_x_variant":[
        "Surbat al Faq\u012bh"
    ],
    "wof:name":"Surbat al Faqih",
    "wof:placetype":"locality"
},
  "geometry": {"coordinates":[44.45125,16.25861],"type":"Point"}
}