{
  "type": "Feature",
  "properties": {
    "gn:admin1_code":"5.0",
    "gn:admin2_code":"2103.0",
    "gn:asciiname":"Bin Haydar",
    "gn:cc2":"YE",
    "gn:country_code":"YE",
    "gn:dem":1226,
    "gn:feature_class":"P",
    "gn:feature_code":"PPL",
    "gn:name":"Bin \u1e28aydar",
    "gn:population":0,
    "gn:timezone":"Asia/Aden",
    "iso:country":"YE",
    "name:und_x_variant":[
        "Bin \u1e24aidar",
        "Bin \u1e28aydar"
    ],
    "wof:name":"Bin Haydar",
    "wof:placetype":"locality"
},
  "geometry": {"coordinates":[47.13333,14.88333],"type":"Point"}
}