{
  "type": "Feature",
  "properties": {
    "gn:admin1_code":"19.0",
    "gn:admin2_code":"2910.0",
    "gn:asciiname":"Mahall `Athar",
    "gn:country_code":"YE",
    "gn:dem":2175,
    "gn:feature_class":"P",
    "gn:feature_code":"PPL",
    "gn:name":"Ma\u1e29all \u2018Ath\u0101r",
    "gn:population":0,
    "gn:timezone":"Asia/Aden",
    "iso:country":"YE",
    "name:und_x_variant":[
        "Ma\u1e29all \u2018Ath\u0101r"
    ],
    "wof:name":"Mahall `Athar",
    "wof:placetype":"locality"
},
  "geometry": {"coordinates":[44.07679,15.88542],"type":"Point"}
}