{
  "type": "Feature",
  "properties": {
    "gn:admin1_code":"10.0",
    "gn:admin2_code":"2702.0",
    "gn:asciiname":"Jaw`an",
    "gn:country_code":"YE",
    "gn:dem":2593,
    "gn:feature_class":"P",
    "gn:feature_code":"PPL",
    "gn:name":"Jaw\u2018\u0101n",
    "gn:population":0,
    "gn:timezone":"Asia/Aden",
    "iso:country":"YE",
    "name:und_x_variant":[
        "Jaw\u2018\u0101n"
    ],
    "wof:name":"Jaw`an",
    "wof:placetype":"locality"
},
  "geometry": {"coordinates":[43.76344,15.47274],"type":"Point"}
}