{
  "type": "Feature",
  "properties": {
    "gn:country":"YE",
    "gn:fcode":"PPL",
    "gn:pop":3,
    "iso:country":"YE",
    "name:ara_x_preferred":[
        "\u0627\u0644\u0642\u0631\u064a\u0634"
    ],
    "name:eng_x_preferred":[
        "Al Quraysh"
    ],
    "qs:name":"Al Quraysh",
    "qs:photos_9r":0,
    "qs:photos_sr":0,
    "qs:pop_sr":"1",
    "wof:name":"Al Quraysh",
    "wof:placetype":"locality",
    "wof:population":3
},
  "geometry": {"coordinates":[45.08473,14.8463],"type":"Point"}
}