{
  "type": "Feature",
  "properties": {
    "gn:admin1_code":"19.0",
    "gn:admin2_code":"2920.0",
    "gn:asciiname":"Darb 'Ubayd",
    "gn:country_code":"YE",
    "gn:dem":2219,
    "gn:feature_class":"P",
    "gn:feature_code":"PPL",
    "gn:name":"Darb \u2018Ubayd",
    "gn:population":0,
    "gn:timezone":"Asia/Aden",
    "iso:country":"YE",
    "name:ara_x_preferred":[
        "\u062f\u0631\u0628 \u0639\u0628\u064a\u062f"
    ],
    "name:und_x_variant":[
        "Darb \u2018Ubayd"
    ],
    "wof:name":"Darb 'Ubayd",
    "wof:placetype":"locality"
},
  "geometry": {"coordinates":[43.95452,16.15536],"type":"Point"}
}