{
  "type": "Feature",
  "properties": {
    "gn:admin1_code":"21.0",
    "gn:admin2_code":"1612.0",
    "gn:asciiname":"Jurn Na`mah",
    "gn:country_code":"YE",
    "gn:dem":1320,
    "gn:feature_class":"P",
    "gn:feature_code":"PPL",
    "gn:name":"Jurn Na\u2018mah",
    "gn:population":0,
    "gn:timezone":"Asia/Aden",
    "iso:country":"YE",
    "name:ara_x_preferred":[
        "\u062c\u0631\u0646 \u0646\u0639\u0645\u0629"
    ],
    "name:und_x_variant":[
        "Jurni\u2018mah",
        "Jurn Na\u2018mah"
    ],
    "wof:name":"Jurn Na`mah",
    "wof:placetype":"locality"
},
  "geometry": {"coordinates":[44.31813,16.4971],"type":"Point"}
}