{
  "type": "Feature",
  "properties": {
    "gn:admin1_code":"16.0",
    "gn:admin2_code":"2304.0",
    "gn:asciiname":"Al Hazzah",
    "gn:country_code":"YE",
    "gn:dem":2313,
    "gn:feature_class":"P",
    "gn:feature_code":"PPL",
    "gn:name":"Al \u1e28azzah",
    "gn:population":0,
    "gn:timezone":"Asia/Aden",
    "iso:country":"YE",
    "name:und_x_variant":[
        "Al \u1e28azzah"
    ],
    "wof:name":"Al Hazzah",
    "wof:placetype":"locality"
},
  "geometry": {"coordinates":[44.34362,15.46054],"type":"Point"}
}