{
  "type": "Feature",
  "properties": {
    "gn:admin1_code":"15.0",
    "gn:admin2_code":"2205.0",
    "gn:asciiname":"Al Jal`",
    "gn:country_code":"YE",
    "gn:dem":2184,
    "gn:feature_class":"P",
    "gn:feature_code":"PPL",
    "gn:name":"Al Jal\u2018",
    "gn:population":0,
    "gn:timezone":"Asia/Aden",
    "iso:country":"YE",
    "name:ara_x_preferred":[
        "\u0627\u0644\u062c\u0644\u0639"
    ],
    "name:und_x_variant":[
        "Al Jal\u2018"
    ],
    "wof:name":"Al Jal`",
    "wof:placetype":"locality"
},
  "geometry": {"coordinates":[43.277,16.95692],"type":"Point"}
}