{
  "type": "Feature",
  "properties": {
    "gn:admin1_code":"25.0",
    "gn:admin2_code":"1507.0",
    "gn:asciiname":"As Saymar",
    "gn:country_code":"YE",
    "gn:dem":22,
    "gn:feature_class":"P",
    "gn:feature_code":"PPL",
    "gn:name":"As Saym\u0101r",
    "gn:population":0,
    "gn:timezone":"Asia/Aden",
    "iso:country":"YE",
    "name:ara_x_preferred":[
        "\u0627\u0644\u0633\u064a\u0645\u0627\u0631"
    ],
    "name:und_x_variant":[
        "As Saym\u0101r"
    ],
    "wof:name":"As Saymar",
    "wof:placetype":"locality"
},
  "geometry": {"coordinates":[43.41428,13.00734],"type":"Point"}
}