{
  "type": "Feature",
  "properties": {
    "gn:admin1_code":"23.0",
    "gn:admin2_code":"1120.0",
    "gn:asciiname":"Mashwarah",
    "gn:country_code":"YE",
    "gn:dem":2279,
    "gn:feature_class":"P",
    "gn:feature_code":"PPL",
    "gn:name":"Mashwarah",
    "gn:population":0,
    "gn:timezone":"Asia/Aden",
    "iso:country":"YE",
    "wof:name":"Mashwarah",
    "wof:placetype":"locality"
},
  "geometry": {"coordinates":[44.10639000000001,13.97595],"type":"Point"}
}