{
  "type": "Feature",
  "properties": {
    "gn:country":"YE",
    "gn:fcode":"PPL",
    "gn:population":9,
    "iso:country":"YE",
    "name:ara_x_preferred":[
        "\u0634\u0627\u0637\u0626 \u0627\u0644\u062a\u0645\u0627\u0631\u0629"
    ],
    "name:eng_x_preferred":[
        "Shati At Tamarah"
    ],
    "name:eng_x_variant":[
        "Al Mushayb"
    ],
    "qs:name":"Sh\u0101\u0163i\u2019 at Tam\u0101rah",
    "qs:photos_9r":0,
    "qs:photos_sr":0,
    "qs:pop_sr":"1",
    "wof:name":"Sh\u0101\u0163i\u2019 at Tam\u0101rah",
    "wof:placetype":"locality",
    "wof:population":9
},
  "geometry": {"coordinates":[43.46738,16.43393],"type":"Point"}
}