{
  "type": "Feature",
  "properties": {
    "gn:admin1_code":"20.0",
    "gn:admin2_code":"1410.0",
    "gn:asciiname":"Quraydah",
    "gn:country_code":"YE",
    "gn:dem":1925,
    "gn:feature_class":"P",
    "gn:feature_code":"PPL",
    "gn:name":"Quray\u1e11ah",
    "gn:population":0,
    "gn:timezone":"Asia/Aden",
    "iso:country":"YE",
    "name:und_x_variant":[
        "Quray\u1e11ah",
        "Qar\u012b\u1e11ah"
    ],
    "wof:name":"Quraydah",
    "wof:placetype":"locality"
},
  "geometry": {"coordinates":[45.53127,14.04754],"type":"Point"}
}