{
  "type": "Feature",
  "properties": {
    "gn:admin1_code":"8.0",
    "gn:admin2_code":"1819.0",
    "gn:asciiname":"As Salamah",
    "gn:country_code":"YE",
    "gn:dem":241,
    "gn:feature_class":"P",
    "gn:feature_code":"PPL",
    "gn:name":"As Sal\u0101mah",
    "gn:population":0,
    "gn:timezone":"Asia/Aden",
    "iso:country":"YE",
    "name:und_x_variant":[
        "As Sal\u0101mah"
    ],
    "wof:name":"As Salamah",
    "wof:placetype":"locality"
},
  "geometry": {"coordinates":[43.51849,13.92753],"type":"Point"}
}