{
  "type": "Feature",
  "properties": {
    "gn:admin1_code":"25.0",
    "gn:admin2_code":"1511.0",
    "gn:asciiname":"Ra's",
    "gn:country_code":"YE",
    "gn:dem":1440,
    "gn:feature_class":"P",
    "gn:feature_code":"PPL",
    "gn:name":"Ra\u2019s",
    "gn:population":0,
    "gn:timezone":"Asia/Aden",
    "iso:country":"YE",
    "name:und_x_variant":[
        "Ra\u2019s"
    ],
    "wof:name":"Ra's",
    "wof:placetype":"locality"
},
  "geometry": {"coordinates":[43.9819,13.49757],"type":"Point"}
}