{
  "type": "Feature",
  "properties": {
    "gn:admin1_code":"22.0",
    "gn:admin2_code":"1709.0",
    "gn:asciiname":"Al Wasitah",
    "gn:country_code":"YE",
    "gn:dem":999,
    "gn:feature_class":"P",
    "gn:feature_code":"PPL",
    "gn:name":"Al W\u0101si\u0163ah",
    "gn:population":0,
    "gn:timezone":"Asia/Aden",
    "iso:country":"YE",
    "name:ara_x_preferred":[
        "\u0627\u0644\u0648\u0627\u0633\u0637\u0640\u0629"
    ],
    "name:und_x_variant":[
        "Al W\u0101si\u0163ah"
    ],
    "wof:name":"Al Wasitah",
    "wof:placetype":"locality"
},
  "geometry": {"coordinates":[43.44374000000001,16.01548],"type":"Point"}
}