{
  "type": "Feature",
  "properties": {
    "gn:admin1_code":"4.0",
    "gn:admin2_code":"1919.0",
    "gn:asciiname":"Hisn Maqis",
    "gn:country_code":"YE",
    "gn:dem":903,
    "gn:feature_class":"P",
    "gn:feature_code":"PPL",
    "gn:name":"\u1e28i\u015fn Maqis",
    "gn:population":0,
    "gn:timezone":"Asia/Aden",
    "iso:country":"YE",
    "name:und_x_variant":[
        "\u1e28i\u015fn Maqis"
    ],
    "wof:name":"Hisn Maqis",
    "wof:placetype":"locality"
},
  "geometry": {"coordinates":[48.26667,15.75],"type":"Point"}
}