{
  "type": "Feature",
  "properties": {
    "gn:admin1_code":"15.0",
    "gn:admin2_code":"2208.0",
    "gn:asciiname":"Qurad",
    "gn:country_code":"YE",
    "gn:dem":2059,
    "gn:feature_class":"P",
    "gn:feature_code":"PPL",
    "gn:name":"Qur\u0101\u1e11",
    "gn:population":0,
    "gn:timezone":"Asia/Aden",
    "iso:country":"YE",
    "name:ara_x_preferred":[
        "Qur\u0101\u1e11"
    ],
    "name:ara_x_variant":[
        "\u0642\u0631\u0627\u0636"
    ],
    "name:und_x_variant":[
        "Ma\u1e29all\u0101t Qur\u0101\u1e11"
    ],
    "wof:name":"Qurad",
    "wof:placetype":"locality"
},
  "geometry": {"coordinates":[43.45635,16.6934],"type":"Point"}
}