{
  "type": "Feature",
  "properties": {
    "gn:admin1_code":"28.0",
    "gn:admin2_code":"1926.0",
    "gn:asciiname":"Mirkoh",
    "gn:country_code":"YE",
    "gn:dem":388,
    "gn:feature_class":"P",
    "gn:feature_code":"PPLL",
    "gn:name":"Mirkoh",
    "gn:population":0,
    "gn:timezone":"Asia/Aden",
    "iso:country":"YE",
    "name:und_x_variant":[
        "Mirgo",
        "Mirkoh",
        "D\u012b M\u012brk\u016b"
    ],
    "wof:name":"Mirkoh",
    "wof:placetype":"locality"
},
  "geometry": {"coordinates":[54.13934,12.44536],"type":"Point"}
}