{
  "type": "Feature",
  "properties": {
    "gn:gn_country":"YE",
    "gn:gn_fcode":"PPL",
    "gn:gn_pop":1,
    "gn:population":1,
    "iso:country":"YE",
    "name:ara_x_preferred":[
        "\u0631\u0647\u0648\u0629 \u062d\u0645\u0631"
    ],
    "name:eng_x_preferred":[
        "Rahwat Hamr"
    ],
    "qs_pg:aaroncc":"YE",
    "qs_pg:gn_country":"YE",
    "qs_pg:gn_fcode":"PPL",
    "qs_pg:gn_pop":1,
    "qs_pg:name":"Rahwat \u1e28amr",
    "qs_pg:photos_9r":0,
    "qs_pg:photos_sr":0,
    "qs_pg:pop_sr":1,
    "qs_pg:qs_pg_placetype":"locality",
    "wof:name":"Rahwat \u1e28amr",
    "wof:placetype":"locality",
    "wof:population":1
},
  "geometry": {"coordinates":[45.13852,13.79398],"type":"Point"}
}