{
  "type": "Feature",
  "properties": {
    "gn:admin1_code":"8.0",
    "gn:admin2_code":"1812.0",
    "gn:asciiname":"Al Maqsa'",
    "gn:country_code":"YE",
    "gn:dem":1324,
    "gn:feature_class":"P",
    "gn:feature_code":"PPL",
    "gn:name":"Al Maq\u015fa\u2018",
    "gn:population":0,
    "gn:timezone":"Asia/Aden",
    "iso:country":"YE",
    "name:ara_x_preferred":[
        "\u0627\u0644\u0645\u0642\u0635\u0639"
    ],
    "name:und_x_variant":[
        "Al Maq\u015fa\u2018"
    ],
    "wof:name":"Al Maqsa'",
    "wof:placetype":"locality"
},
  "geometry": {"coordinates":[43.4338,14.91499],"type":"Point"}
}