{
  "type": "Feature",
  "properties": {
    "gn:admin1_code":"20.0",
    "gn:asciiname":"Dar al Kharif",
    "gn:country_code":"YE",
    "gn:dem":2242,
    "gn:feature_class":"P",
    "gn:feature_code":"PPL",
    "gn:name":"D\u0101r al Khar\u012bf",
    "gn:population":0,
    "gn:timezone":"Asia/Aden",
    "iso:country":"YE",
    "name:ara_x_preferred":[
        "\u062f\u0627\u0631 \u0627\u0644\u062e\u0631\u064a\u0641"
    ],
    "name:und_x_variant":[
        "D\u0101r al Khar\u012bf"
    ],
    "wof:name":"Dar al Kharif",
    "wof:placetype":"locality"
},
  "geometry": {"coordinates":[44.38605,14.43343],"type":"Point"}
}