{
  "type": "Feature",
  "properties": {
    "gn:admin1_code":"25.0",
    "gn:admin2_code":"1517.0",
    "gn:asciiname":"Al `Iqam",
    "gn:country_code":"YE",
    "gn:dem":1494,
    "gn:feature_class":"P",
    "gn:feature_code":"PPL",
    "gn:name":"Al \u2018Iq\u0101m",
    "gn:population":0,
    "gn:timezone":"Asia/Aden",
    "iso:country":"YE",
    "name:ara_x_preferred":[
        "Al \u2018Iq\u0101m"
    ],
    "wof:name":"Al `Iqam",
    "wof:placetype":"locality"
},
  "geometry": {"coordinates":[44.32269,13.28522],"type":"Point"}
}