{
  "type": "Feature",
  "properties": {
    "gn:admin1_code":"23.0",
    "gn:admin2_code":"1109.0",
    "gn:asciiname":"Al Bariqah",
    "gn:country_code":"YE",
    "gn:dem":1385,
    "gn:feature_class":"P",
    "gn:feature_code":"PPL",
    "gn:name":"Al Bariqah",
    "gn:population":0,
    "gn:timezone":"Asia/Aden",
    "iso:country":"YE",
    "wof:name":"Al Bariqah",
    "wof:placetype":"locality"
},
  "geometry": {"coordinates":[43.96061,14.02699],"type":"Point"}
}