{
  "type": "Feature",
  "properties": {
    "gn:admin1_code":"23.0",
    "gn:admin2_code":"1101.0",
    "gn:asciiname":"Ikam al 'Asaq",
    "gn:country_code":"YE",
    "gn:dem":1023,
    "gn:feature_class":"P",
    "gn:feature_code":"PPL",
    "gn:name":"Ik\u0101m al \u2018Asaq",
    "gn:population":0,
    "gn:timezone":"Asia/Aden",
    "iso:country":"YE",
    "name:ara_x_preferred":[
        "\u0625\u0643\u0627\u0645 \u0627\u0644\u0639\u0633\u0642"
    ],
    "name:und_x_variant":[
        "Ik\u0101m al \u2018Asaq"
    ],
    "wof:name":"Ikam al 'Asaq",
    "wof:placetype":"locality"
},
  "geometry": {"coordinates":[44.0177,14.27771],"type":"Point"}
}