{
  "type": "Feature",
  "properties": {
    "gn:admin1_code":"8.0",
    "gn:admin2_code":"1812.0",
    "gn:asciiname":"Ar Ribat",
    "gn:country_code":"YE",
    "gn:dem":1496,
    "gn:feature_class":"P",
    "gn:feature_code":"PPL",
    "gn:name":"Ar Rib\u0101\u0163",
    "gn:population":0,
    "gn:timezone":"Asia/Aden",
    "iso:country":"YE",
    "name:ara_x_preferred":[
        "\u0627\u0644\u0631\u0628\u0627\u0637"
    ],
    "name:und_x_variant":[
        "Ar Rib\u0101\u0163"
    ],
    "wof:name":"Ar Ribat",
    "wof:placetype":"locality"
},
  "geometry": {"coordinates":[43.46982,14.8961],"type":"Point"}
}