{
  "type": "Feature",
  "properties": {
    "gn:country":"YE",
    "gn:fcode":"PPL",
    "gn:pop":19,
    "iso:country":"YE",
    "name:ara_x_preferred":[
        "\u0648\u0627\u062f\u064a \u0641\u0631\u0629"
    ],
    "name:eng_x_preferred":[
        "Wadi Farah"
    ],
    "name:eng_x_variant":[
        "Al Jurb"
    ],
    "qs:name":"W\u0101d\u012b Farah",
    "qs:photos_9r":0,
    "qs:photos_sr":0,
    "qs:pop_sr":"1",
    "wof:name":"W\u0101d\u012b Farah",
    "wof:placetype":"locality",
    "wof:population":19
},
  "geometry": {"coordinates":[43.47963,16.0833],"type":"Point"}
}