{
  "type": "Feature",
  "properties": {
    "gn:admin1_code":"25.0",
    "gn:admin2_code":"1502.0",
    "gn:asciiname":"Lughabah",
    "gn:country_code":"YE",
    "gn:dem":922,
    "gn:feature_class":"P",
    "gn:feature_code":"PPL",
    "gn:name":"Lugh\u0101bah",
    "gn:population":0,
    "gn:timezone":"Asia/Aden",
    "iso:country":"YE",
    "name:ara_x_preferred":[
        "\u0644\u063a\u0627\u0628\u0629"
    ],
    "name:und_x_variant":[
        "Lugh\u0101bah"
    ],
    "wof:name":"Lughabah",
    "wof:placetype":"locality"
},
  "geometry": {"coordinates":[43.87625,13.66213],"type":"Point"}
}