{
  "type": "Feature",
  "properties": {
    "gn:admin1_code":"19.0",
    "gn:admin2_code":"2919.0",
    "gn:asciiname":"Bayt as Siba'i",
    "gn:country_code":"YE",
    "gn:dem":2488,
    "gn:feature_class":"P",
    "gn:feature_code":"PPL",
    "gn:name":"Bayt as Sib\u0101\u2018\u012b",
    "gn:population":0,
    "gn:timezone":"Asia/Aden",
    "iso:country":"YE",
    "name:ara_x_preferred":[
        "\u0628\u064a\u062a \u0627\u0644\u0633\u0628\u0627\u0639\u064a"
    ],
    "name:und_x_variant":[
        "Bayt as Sib\u0101\u2018\u012b"
    ],
    "wof:name":"Bayt as Siba'i",
    "wof:placetype":"locality"
},
  "geometry": {"coordinates":[44.03384000000001,16.00385],"type":"Point"}
}