{
  "type": "Feature",
  "properties": {
    "gn:country":"YE",
    "gn:fcode":"PPL",
    "gn:population":4,
    "iso:country":"YE",
    "name:ara_x_preferred":[
        "\u0627\u0644\u062a \u062d\u0644\u0627\u0633\u0629"
    ],
    "name:eng_x_preferred":[
        "Alt Halasah"
    ],
    "name:eng_x_variant":[
        "Ibn \u2018Az\u0327r\u016bs"
    ],
    "qs:name":"Alt \u1e28al\u0101sah",
    "qs:photos_9r":0,
    "qs:photos_sr":0,
    "qs:pop_sr":"1",
    "wof:name":"Alt \u1e28al\u0101sah",
    "wof:placetype":"locality",
    "wof:population":4
},
  "geometry": {"coordinates":[43.27299,16.91463],"type":"Point"}
}