{
  "type": "Feature",
  "properties": {
    "gn:admin1_code":"4.0",
    "gn:admin2_code":"1908.0",
    "gn:asciiname":"Khumayr",
    "gn:cc2":"YE",
    "gn:country_code":"YE",
    "gn:dem":671,
    "gn:feature_class":"P",
    "gn:feature_code":"PPL",
    "gn:name":"Khumayr",
    "gn:population":0,
    "gn:timezone":"Asia/Aden",
    "iso:country":"YE",
    "name:und_x_variant":[
        "Khumair",
        "Khumayr"
    ],
    "wof:name":"Khumayr",
    "wof:placetype":"locality"
},
  "geometry": {"coordinates":[48.59889,15.90833],"type":"Point"}
}