{
  "type": "Feature",
  "properties": {
    "gn:country":"YE",
    "gn:fcode":"PPL",
    "gn:pop":3,
    "iso:country":"YE",
    "name:ara_x_preferred":[
        "\u0645\u0641\u062c\u0631 \u0645\u0642\u0631\u0648\u062f"
    ],
    "name:eng_x_preferred":[
        "Mafjar MaqrUd"
    ],
    "qs:name":"Mafjar Maqr\u016bd",
    "qs:photos_9r":0,
    "qs:photos_sr":0,
    "qs:pop_sr":"1",
    "wof:name":"Mafjar Maqr\u016bd",
    "wof:placetype":"locality",
    "wof:population":3
},
  "geometry": {"coordinates":[43.28938,16.31193],"type":"Point"}
}