{
  "type": "Feature",
  "properties": {
    "gn:admin1_code":"21.0",
    "gn:admin2_code":"1602.0",
    "gn:asciiname":"Al Jannah",
    "gn:country_code":"YE",
    "gn:dem":1294,
    "gn:feature_class":"P",
    "gn:feature_code":"PPLL",
    "gn:name":"Al Jannah",
    "gn:population":0,
    "gn:timezone":"Asia/Aden",
    "iso:country":"YE",
    "name:ara_x_preferred":[
        "\u0627\u0644\u062c\u0646\u0629"
    ],
    "wof:name":"Al Jannah",
    "wof:placetype":"locality"
},
  "geometry": {"coordinates":[44.40177,16.4288],"type":"Point"}
}