{
  "type": "Feature",
  "properties": {
    "gn:admin1_code":"21.0",
    "gn:admin2_code":"1603.0",
    "gn:asciiname":"Ar Ruways",
    "gn:country_code":"YE",
    "gn:dem":1249,
    "gn:feature_class":"P",
    "gn:feature_code":"PPL",
    "gn:name":"Ar Ruways",
    "gn:population":0,
    "gn:timezone":"Asia/Aden",
    "iso:country":"YE",
    "name:ara_x_preferred":[
        "\u0627\u0644\u0631\u0648\u064a\u0633"
    ],
    "wof:name":"Ar Ruways",
    "wof:placetype":"locality"
},
  "geometry": {"coordinates":[44.38676,16.11433],"type":"Point"}
}