{
  "type": "Feature",
  "properties": {
    "gn:admin1_code":"4.0",
    "gn:admin2_code":"1908.0",
    "gn:asciiname":"Qaraqir",
    "gn:cc2":"YE",
    "gn:country_code":"YE",
    "gn:dem":658,
    "gn:feature_class":"P",
    "gn:feature_code":"PPL",
    "gn:name":"Qar\u0101qir",
    "gn:population":0,
    "gn:timezone":"Asia/Aden",
    "iso:country":"YE",
    "name:und_x_variant":[
        "Qur\u0101qir",
        "Qar\u0101qir"
    ],
    "wof:name":"Qaraqir",
    "wof:placetype":"locality"
},
  "geometry": {"coordinates":[48.66667,15.95],"type":"Point"}
}