{
  "type": "Feature",
  "properties": {
    "gn:country":"YE",
    "gn:fcode":"PPL",
    "gn:pop":5,
    "iso:country":"YE",
    "name:ara_x_preferred":[
        "\u063a\u0627\u0631\u0628 \u0627\u0644\u0645\u0643\u0627\u0631\u0645\u0629"
    ],
    "name:eng_x_preferred":[
        "Gharib Al Mukarimah"
    ],
    "qs:name":"Gh\u0101rib al Muk\u0101rimah",
    "qs:photos_9r":0,
    "qs:photos_sr":0,
    "qs:pop_sr":"1",
    "wof:name":"Gh\u0101rib al Muk\u0101rimah",
    "wof:placetype":"locality",
    "wof:population":5
},
  "geometry": {"coordinates":[43.43472,16.05235],"type":"Point"}
}