{
  "type": "Feature",
  "properties": {
    "gn:admin1_code":"25.0",
    "gn:admin2_code":"1502.0",
    "gn:asciiname":"Taysalah",
    "gn:country_code":"YE",
    "gn:dem":1410,
    "gn:feature_class":"P",
    "gn:feature_code":"PPL",
    "gn:name":"\u0162aysalah",
    "gn:population":0,
    "gn:timezone":"Asia/Aden",
    "iso:country":"YE",
    "name:und_x_variant":[
        "\u0162aysalah"
    ],
    "wof:name":"Taysalah",
    "wof:placetype":"locality"
},
  "geometry": {"coordinates":[44.16558,13.62862],"type":"Point"}
}