{
  "type": "Feature",
  "properties": {
    "gn:admin1_code":"28.0",
    "gn:admin2_code":"1926.0",
    "gn:asciiname":"Shilhin",
    "gn:country_code":"YE",
    "gn:dem":340,
    "gn:feature_class":"P",
    "gn:feature_code":"PPL",
    "gn:name":"Shilh\u012bn",
    "gn:population":0,
    "gn:timezone":"Asia/Aden",
    "iso:country":"YE",
    "name:ara_x_preferred":[
        "Shilh\u012bn"
    ],
    "name:und_x_variant":[
        "Shillyin",
        "R\u016bs"
    ],
    "wof:name":"Shilhin",
    "wof:placetype":"locality"
},
  "geometry": {"coordinates":[54.32193,12.51141],"type":"Point"}
}