{
  "type": "Feature",
  "properties": {
    "gn:admin1_code":"23.0",
    "gn:admin2_code":"1101.0",
    "gn:asciiname":"Mashra`ah",
    "gn:country_code":"YE",
    "gn:dem":2540,
    "gn:feature_class":"P",
    "gn:feature_code":"PPL",
    "gn:name":"Mashra\u2018ah",
    "gn:population":0,
    "gn:timezone":"Asia/Aden",
    "iso:country":"YE",
    "name:und_x_variant":[
        "Mashra\u2018ah"
    ],
    "wof:name":"Mashra`ah",
    "wof:placetype":"locality"
},
  "geometry": {"coordinates":[44.26419,14.28921],"type":"Point"}
}