{
  "type": "Feature",
  "properties": {
    "gn:admin1_code":"8.0",
    "gn:admin2_code":"1817.0",
    "gn:asciiname":"Al Mansariyah",
    "gn:country_code":"YE",
    "gn:dem":178,
    "gn:feature_class":"P",
    "gn:feature_code":"PPL",
    "gn:name":"Al Man\u015far\u012byah",
    "gn:population":0,
    "gn:timezone":"Asia/Aden",
    "iso:country":"YE",
    "name:und_x_variant":[
        "Al Man\u015far\u012byah"
    ],
    "wof:name":"Al Mansariyah",
    "wof:placetype":"locality"
},
  "geometry": {"coordinates":[43.42258,14.48473],"type":"Point"}
}