{
  "type": "Feature",
  "properties": {
    "gn:admin1_code":"8.0",
    "gn:admin2_code":"1815.0",
    "gn:asciiname":"Dayr Dawid",
    "gn:country_code":"YE",
    "gn:dem":146,
    "gn:feature_class":"P",
    "gn:feature_code":"PPL",
    "gn:name":"Dayr D\u0101wid",
    "gn:population":0,
    "gn:timezone":"Asia/Aden",
    "iso:country":"YE",
    "name:und_x_variant":[
        "Dayr D\u0101wid",
        "Dayr D\u0101wud"
    ],
    "wof:name":"Dayr Dawid",
    "wof:placetype":"locality"
},
  "geometry": {"coordinates":[43.33517,14.75022],"type":"Point"}
}