{
  "type": "Feature",
  "properties": {
    "gn:admin1_code":"23.0",
    "gn:admin2_code":"1110.0",
    "gn:asciiname":"Al Huqm",
    "gn:country_code":"YE",
    "gn:dem":729,
    "gn:feature_class":"P",
    "gn:feature_code":"PPL",
    "gn:name":"Al Huqm",
    "gn:population":0,
    "gn:timezone":"Asia/Aden",
    "iso:country":"YE",
    "wof:name":"Al Huqm",
    "wof:placetype":"locality"
},
  "geometry": {"coordinates":[43.72046,13.93146],"type":"Point"}
}