{
  "type": "Feature",
  "properties": {
    "gn:country":"YE",
    "gn:fcode":"PPL",
    "gn:pop":6,
    "iso:country":"YE",
    "name:ara_x_preferred":[
        "\u0627\u0644\u0645\u064a\u062b\u0627\u0628\u0629"
    ],
    "name:eng_x_preferred":[
        "Al Maythabah"
    ],
    "qs:name":"Al Mayth\u0101bah",
    "qs:photos_9r":0,
    "qs:photos_sr":0,
    "qs:pop_sr":"1",
    "wof:name":"Al Mayth\u0101bah",
    "wof:placetype":"locality",
    "wof:population":6
},
  "geometry": {"coordinates":[45.371,14.2073],"type":"Point"}
}