{
  "type": "Feature",
  "properties": {
    "gn:admin1_code":"22.0",
    "gn:admin2_code":"1722.0",
    "gn:asciiname":"Al Ghumr",
    "gn:country_code":"YE",
    "gn:dem":702,
    "gn:feature_class":"P",
    "gn:feature_code":"PPL",
    "gn:name":"Al Ghumr",
    "gn:population":0,
    "gn:timezone":"Asia/Aden",
    "iso:country":"YE",
    "wof:name":"Al Ghumr",
    "wof:placetype":"locality"
},
  "geometry": {"coordinates":[43.37549,15.82837],"type":"Point"}
}