{
  "type": "Feature",
  "properties": {
    "gn:country":"YE",
    "gn:fcode":"PPL",
    "gn:pop":11,
    "iso:country":"YE",
    "name:ara_x_preferred":[
        "\u0633\u062c\u0631"
    ],
    "name:eng_x_preferred":[
        "Sajr"
    ],
    "qs:name":"Sajr",
    "qs:photos_9r":0,
    "qs:photos_sr":0,
    "qs:pop_sr":"1",
    "wof:name":"Sajr",
    "wof:placetype":"locality",
    "wof:population":11
},
  "geometry": {"coordinates":[43.29176,16.9557],"type":"Point"}
}