{
  "type": "Feature",
  "properties": {
    "gn:admin1_code":"25.0",
    "gn:admin2_code":"1501.0",
    "gn:asciiname":"Sulayq",
    "gn:country_code":"YE",
    "gn:dem":1164,
    "gn:feature_class":"P",
    "gn:feature_code":"PPL",
    "gn:name":"Sulayq",
    "gn:population":0,
    "gn:timezone":"Asia/Aden",
    "iso:country":"YE",
    "wof:name":"Sulayq",
    "wof:placetype":"locality"
},
  "geometry": {"coordinates":[44.35616,13.53669],"type":"Point"}
}