{
  "type": "Feature",
  "properties": {
    "gn:admin1_code":"22.0",
    "gn:admin2_code":"1725.0",
    "gn:asciiname":"Al Qafl",
    "gn:country_code":"YE",
    "gn:dem":1268,
    "gn:feature_class":"P",
    "gn:feature_code":"PPL",
    "gn:name":"Al Qafl",
    "gn:population":0,
    "gn:timezone":"Asia/Aden",
    "iso:country":"YE",
    "name:ara_x_preferred":[
        "\u0627\u0644\u0642\u0641\u0644"
    ],
    "wof:name":"Al Qafl",
    "wof:placetype":"locality"
},
  "geometry": {"coordinates":[43.54988,15.58544],"type":"Point"}
}