{
  "type": "Feature",
  "properties": {
    "gn:admin1_code":"15.0",
    "gn:admin2_code":"2212.0",
    "gn:asciiname":"Rawnat al Hamzat",
    "gn:country_code":"YE",
    "gn:dem":1891,
    "gn:feature_class":"P",
    "gn:feature_code":"PPL",
    "gn:name":"Rawnat al \u1e28amz\u0101t",
    "gn:population":0,
    "gn:timezone":"Asia/Aden",
    "iso:country":"YE",
    "name:ara_x_preferred":[
        "\u0631\u0648\u0646\u0629 \u0627\u0644\u062d\u0645\u0632\u0627\u062a"
    ],
    "name:und_x_variant":[
        "Rawnat al \u1e28amz\u0101t"
    ],
    "wof:name":"Rawnat al Hamzat",
    "wof:placetype":"locality"
},
  "geometry": {"coordinates":[43.72036,16.94196],"type":"Point"}
}