{
  "type": "Feature",
  "properties": {
    "gn:admin1_code":"23.0",
    "gn:admin2_code":"1117.0",
    "gn:asciiname":"As Safi`ah",
    "gn:country_code":"YE",
    "gn:dem":2167,
    "gn:feature_class":"P",
    "gn:feature_code":"PPL",
    "gn:name":"A\u015f \u015eaf\u012b\u2018ah",
    "gn:population":0,
    "gn:timezone":"Asia/Aden",
    "iso:country":"YE",
    "name:und_x_variant":[
        "A\u015f \u015eaf\u012b\u2018ah",
        "Safijaah"
    ],
    "wof:name":"As Safi`ah",
    "wof:placetype":"locality"
},
  "geometry": {"coordinates":[43.99028,13.85022],"type":"Point"}
}