{
  "type": "Feature",
  "properties": {
    "gn:admin1_code":"11.0",
    "gn:admin2_code":"2001.0",
    "gn:asciiname":"Al Humaydah",
    "gn:country_code":"YE",
    "gn:dem":2121,
    "gn:feature_class":"P",
    "gn:feature_code":"PPL",
    "gn:name":"Al \u1e28umay\u1e11ah",
    "gn:population":0,
    "gn:timezone":"Asia/Aden",
    "iso:country":"YE",
    "name:ara_x_preferred":[
        "\u0627\u0644\u062d\u0645\u064a\u0636\u0629"
    ],
    "name:und_x_variant":[
        "Al \u1e28umay\u1e11ah"
    ],
    "wof:name":"Al Humaydah",
    "wof:placetype":"locality"
},
  "geometry": {"coordinates":[44.7636,14.72972],"type":"Point"}
}