{
  "type": "Feature",
  "properties": {
    "gn:admin1_code":"8.0",
    "gn:admin2_code":"1802.0",
    "gn:asciiname":"Dayr Abkar",
    "gn:country_code":"YE",
    "gn:dem":84,
    "gn:feature_class":"P",
    "gn:feature_code":"PPL",
    "gn:name":"Dayr Abkar",
    "gn:population":0,
    "gn:timezone":"Asia/Aden",
    "iso:country":"YE",
    "name:und_x_variant":[
        "Dayr \u2018Akar"
    ],
    "wof:name":"Dayr Abkar",
    "wof:placetype":"locality"
},
  "geometry": {"coordinates":[43.04557,15.62493],"type":"Point"}
}