{
  "type": "Feature",
  "properties": {
    "gn:admin1_code":"8.0",
    "gn:admin2_code":"1817.0",
    "gn:asciiname":"Al Kara`imah",
    "gn:country_code":"YE",
    "gn:dem":16,
    "gn:feature_class":"P",
    "gn:feature_code":"PPL",
    "gn:name":"Al Kar\u0101\u2018imah",
    "gn:population":0,
    "gn:timezone":"Asia/Aden",
    "iso:country":"YE",
    "name:und_x_variant":[
        "Al Kar\u0101\u2018imah"
    ],
    "wof:name":"Al Kara`imah",
    "wof:placetype":"locality"
},
  "geometry": {"coordinates":[43.07008,14.32457],"type":"Point"}
}