{
  "type": "Feature",
  "properties": {
    "gn:admin1_code":"8.0",
    "gn:admin2_code":"1824.0",
    "gn:asciiname":"Ash Shurukh",
    "gn:country_code":"YE",
    "gn:dem":260,
    "gn:feature_class":"P",
    "gn:feature_code":"PPL",
    "gn:name":"Ash Shur\u016bkh",
    "gn:population":0,
    "gn:timezone":"Asia/Aden",
    "iso:country":"YE",
    "name:ara_x_preferred":[
        "Ash Shur\u016bkh"
    ],
    "wof:name":"Ash Shurukh",
    "wof:placetype":"locality"
},
  "geometry": {"coordinates":[43.44474,14.36784],"type":"Point"}
}