{
  "type": "Feature",
  "properties": {
    "gn:admin1_code":"18.0",
    "gn:admin2_code":"3004.0",
    "gn:asciiname":"Tarabin",
    "gn:country_code":"YE",
    "gn:dem":1775,
    "gn:feature_class":"P",
    "gn:feature_code":"PPL",
    "gn:name":"Tar\u0101bin",
    "gn:population":0,
    "gn:timezone":"Asia/Aden",
    "iso:country":"YE",
    "name:und_x_variant":[
        "Tar\u0101bin"
    ],
    "wof:name":"Tarabin",
    "wof:placetype":"locality"
},
  "geometry": {"coordinates":[44.89496,13.78217],"type":"Point"}
}