{
  "type": "Feature",
  "properties": {
    "gn:admin1_code":"16.0",
    "gn:admin2_code":"2313.0",
    "gn:asciiname":"Al Jabal",
    "gn:country_code":"YE",
    "gn:dem":2906,
    "gn:feature_class":"P",
    "gn:feature_code":"PPL",
    "gn:name":"Al Jabal",
    "gn:population":0,
    "gn:timezone":"Asia/Aden",
    "iso:country":"YE",
    "wof:name":"Al Jabal",
    "wof:placetype":"locality"
},
  "geometry": {"coordinates":[44.49543,15.38286],"type":"Point"}
}