{
  "type": "Feature",
  "properties": {
    "gn:admin1_code":"19.0",
    "gn:admin2_code":"2903.0",
    "gn:asciiname":"`Ashish",
    "gn:country_code":"YE",
    "gn:dem":1145,
    "gn:feature_class":"P",
    "gn:feature_code":"PPL",
    "gn:name":"\u2018Ash\u012bsh",
    "gn:population":0,
    "gn:timezone":"Asia/Aden",
    "iso:country":"YE",
    "name:ara_x_preferred":[
        "\u2018Ash\u012bsh"
    ],
    "name:ara_x_variant":[
        "\u0639\u0634\u064a\u0634"
    ],
    "name:und_x_variant":[
        "Al \u2018Ishash"
    ],
    "wof:name":"`Ashish",
    "wof:placetype":"locality"
},
  "geometry": {"coordinates":[43.81406,16.2024],"type":"Point"}
}