{
  "type": "Feature",
  "properties": {
    "gn:admin1_code":"16.0",
    "gn:admin2_code":"2304.0",
    "gn:asciiname":"Al Hayuf",
    "gn:country_code":"YE",
    "gn:dem":2349,
    "gn:feature_class":"P",
    "gn:feature_code":"PPL",
    "gn:name":"Al \u1e28ay\u016bf",
    "gn:population":0,
    "gn:timezone":"Asia/Aden",
    "iso:country":"YE",
    "name:und_x_variant":[
        "Al \u1e28ay\u016bf"
    ],
    "wof:name":"Al Hayuf",
    "wof:placetype":"locality"
},
  "geometry": {"coordinates":[44.37622,15.4521],"type":"Point"}
}