{
  "type": "Feature",
  "properties": {
    "gn:admin1_code":"20.0",
    "gn:asciiname":"Qism al Qarri",
    "gn:country_code":"YE",
    "gn:dem":2564,
    "gn:feature_class":"P",
    "gn:feature_code":"PPL",
    "gn:name":"Qism al Qarr\u012b",
    "gn:population":0,
    "gn:timezone":"Asia/Aden",
    "iso:country":"YE",
    "name:ara_x_preferred":[
        "\u0642\u0633\u0645 \u0627\u0644\u0642\u0631\u064a"
    ],
    "name:und_x_variant":[
        "Qism al Qarr\u012b"
    ],
    "wof:name":"Qism al Qarri",
    "wof:placetype":"locality"
},
  "geometry": {"coordinates":[44.47727,14.46478],"type":"Point"}
}