{
  "type": "Feature",
  "properties": {
    "gn:admin1_code":"20.0",
    "gn:admin2_code":"1415.0",
    "gn:asciiname":"Khubzah",
    "gn:country_code":"YE",
    "gn:dem":2306,
    "gn:feature_class":"P",
    "gn:feature_code":"PPL",
    "gn:name":"Khubzah",
    "gn:population":0,
    "gn:timezone":"Asia/Aden",
    "iso:country":"YE",
    "name:ara_x_preferred":[
        "\u062e\u0628\u0632\u0629"
    ],
    "name:fas_x_preferred":[
        "\u062e\u0628\u0632\u0647"
    ],
    "wof:name":"Khubzah",
    "wof:placetype":"locality"
},
  "geometry": {"coordinates":[44.79686,14.56352],"type":"Point"}
}