{
  "type": "Feature",
  "properties": {
    "gn:country":"YE",
    "gn:fcode":"PPL",
    "gn:pop":8,
    "iso:country":"YE",
    "name:ara_x_preferred":[
        "\u0646\u0648\u0628\u0629 \u0628\u0646 \u062c\u0639\u0641\u0631"
    ],
    "name:eng_x_preferred":[
        "Nawbat Bin Ja'far"
    ],
    "qs:name":"Nawbat Bin Ja\u2018far",
    "qs:photos_9r":0,
    "qs:photos_sr":0,
    "qs:pop_sr":"1",
    "wof:name":"Nawbat Bin Ja\u2018far",
    "wof:placetype":"locality",
    "wof:population":8
},
  "geometry": {"coordinates":[45.13072,13.79609],"type":"Point"}
}