{
  "type": "Feature",
  "properties": {
    "gn:admin1_code":"20.0",
    "gn:admin2_code":"1417.0",
    "gn:asciiname":"Bayt ar Rahabi",
    "gn:country_code":"YE",
    "gn:dem":2506,
    "gn:feature_class":"P",
    "gn:feature_code":"PPL",
    "gn:name":"Bayt ar Ra\u1e29\u0101b\u012b",
    "gn:population":0,
    "gn:timezone":"Asia/Aden",
    "iso:country":"YE",
    "name:und_x_variant":[
        "Bayt ar Ra\u1e29\u0101b\u012b"
    ],
    "wof:name":"Bayt ar Rahabi",
    "wof:placetype":"locality"
},
  "geometry": {"coordinates":[44.65031,14.25977],"type":"Point"}
}