{
  "type": "Feature",
  "properties": {
    "gn:admin1_code":"15.0",
    "gn:admin2_code":"2204.0",
    "gn:asciiname":"Tibrayah",
    "gn:country_code":"YE",
    "gn:dem":1412,
    "gn:feature_class":"P",
    "gn:feature_code":"PPL",
    "gn:name":"Tibr\u0101yah",
    "gn:population":0,
    "gn:timezone":"Asia/Aden",
    "iso:country":"YE",
    "name:ara_x_preferred":[
        "\u062a\u0628\u0631\u0627\u0628\u0629"
    ],
    "name:und_x_variant":[
        "Tibr\u0101yah"
    ],
    "wof:name":"Tibrayah",
    "wof:placetype":"locality"
},
  "geometry": {"coordinates":[43.26702,17.0241],"type":"Point"}
}