{
  "type": "Feature",
  "properties": {
    "gn:admin1_code":"19.0",
    "gn:admin2_code":"2901.0",
    "gn:asciiname":"Al Ghara'ish",
    "gn:country_code":"YE",
    "gn:dem":1873,
    "gn:feature_class":"P",
    "gn:feature_code":"PPLL",
    "gn:name":"Al Ghar\u0101\u2019ish",
    "gn:population":0,
    "gn:timezone":"Asia/Aden",
    "iso:country":"YE",
    "name:ara_x_preferred":[
        "\u0627\u0644\u063a\u0631\u0627\u0626\u0634"
    ],
    "name:und_x_variant":[
        "Al Ghar\u0101\u2019ish"
    ],
    "wof:name":"Al Ghara'ish",
    "wof:placetype":"locality"
},
  "geometry": {"coordinates":[44.00149,16.43807],"type":"Point"}
}