{
  "type": "Feature",
  "properties": {
    "gn:admin1_code":"4.0",
    "gn:admin2_code":"1930.0",
    "gn:asciiname":"Ar Rishah",
    "gn:cc2":"YE",
    "gn:country_code":"YE",
    "gn:dem":736,
    "gn:feature_class":"P",
    "gn:feature_code":"PPL",
    "gn:name":"Ar R\u012bshah",
    "gn:population":0,
    "gn:timezone":"Asia/Aden",
    "iso:country":"YE",
    "name:und_x_variant":[
        "Al-R\u012bshah",
        "Ar R\u012bshah"
    ],
    "wof:name":"Ar Rishah",
    "wof:placetype":"locality"
},
  "geometry": {"coordinates":[48.96667,14.66667],"type":"Point"}
}