{
  "type": "Feature",
  "properties": {
    "gn:country":"YE",
    "gn:fcode":"PPL",
    "gn:population":1,
    "iso:country":"YE",
    "name:ara_x_preferred":[
        "\u0623\u0645 \u0627\u0644\u062d\u0644\u0642"
    ],
    "qs:name":"Umm al \u1e28alaq",
    "qs:photos_9r":0,
    "qs:photos_sr":0,
    "qs:pop_sr":"1",
    "wof:name":"Umm al \u1e28alaq",
    "wof:placetype":"locality",
    "wof:population":1
},
  "geometry": {"coordinates":[44.0022,16.69673],"type":"Point"}
}