{
  "type": "Feature",
  "properties": {
    "gn:admin1_code":"11.0",
    "gn:admin2_code":"2007.0",
    "gn:asciiname":"Qutaybiyah",
    "gn:country_code":"YE",
    "gn:dem":974,
    "gn:feature_class":"P",
    "gn:feature_code":"PPL",
    "gn:name":"Qu\u0163ayb\u012byah",
    "gn:population":0,
    "gn:timezone":"Asia/Aden",
    "iso:country":"YE",
    "name:und_x_variant":[
        "Qu\u0163ayb\u012byah"
    ],
    "wof:name":"Qutaybiyah",
    "wof:placetype":"locality"
},
  "geometry": {"coordinates":[43.58985,14.28401],"type":"Point"}
}