{
  "type": "Feature",
  "properties": {
    "gn:admin1_code":"22.0",
    "gn:admin2_code":"1725.0",
    "gn:asciiname":"Al 'Ashali",
    "gn:country_code":"YE",
    "gn:dem":987,
    "gn:feature_class":"P",
    "gn:feature_code":"PPL",
    "gn:name":"Al \u2018Ash\u0101l\u012b",
    "gn:population":0,
    "gn:timezone":"Asia/Aden",
    "iso:country":"YE",
    "name:ara_x_preferred":[
        "\u0627\u0644\u0639\u0634\u0627\u0644\u064a"
    ],
    "name:und_x_variant":[
        "Al \u2018Ash\u0101l\u012b"
    ],
    "wof:name":"Al 'Ashali",
    "wof:placetype":"locality"
},
  "geometry": {"coordinates":[43.52576,15.59285],"type":"Point"}
}