{
  "type": "Feature",
  "properties": {
    "gn:admin1_code":"5.0",
    "gn:admin2_code":"2108.0",
    "gn:asciiname":"`Ubarah",
    "gn:country_code":"YE",
    "gn:dem":1353,
    "gn:elevation":"2.0",
    "gn:feature_class":"P",
    "gn:feature_code":"PPL",
    "gn:name":"\u2018Ubarah",
    "gn:population":0,
    "gn:timezone":"Asia/Aden",
    "iso:country":"YE",
    "name:und_x_variant":[
        "\u2018Ubara",
        "\u2018Ubarah"
    ],
    "wof:name":"`Ubarah",
    "wof:placetype":"locality"
},
  "geometry": {"coordinates":[45.85,14.51185],"type":"Point"}
}