{
  "type": "Feature",
  "properties": {
    "gn:admin1_code":"8.0",
    "gn:admin2_code":"1808.0",
    "gn:asciiname":"Mahall an Nubi",
    "gn:country_code":"YE",
    "gn:dem":134,
    "gn:feature_class":"P",
    "gn:feature_code":"PPL",
    "gn:name":"Ma\u1e29all an N\u016bb\u012b",
    "gn:population":0,
    "gn:timezone":"Asia/Aden",
    "iso:country":"YE",
    "name:ara_x_preferred":[
        "\u0645\u062d\u0644 \u0627\u0644\u0646\u0648\u0628\u064a"
    ],
    "name:und_x_variant":[
        "Ma\u1e29all an N\u016bb\u012b"
    ],
    "wof:name":"Mahall an Nubi",
    "wof:placetype":"locality"
},
  "geometry": {"coordinates":[43.17825,15.26028],"type":"Point"}
}