{
  "type": "Feature",
  "properties": {
    "gn:admin1_code":"8.0",
    "gn:admin2_code":"1815.0",
    "gn:asciiname":"Dabr as Sud",
    "gn:country_code":"YE",
    "gn:dem":194,
    "gn:feature_class":"P",
    "gn:feature_code":"PPL",
    "gn:name":"\u1e10abr as S\u016bd",
    "gn:population":0,
    "gn:timezone":"Asia/Aden",
    "iso:country":"YE",
    "name:ara_x_preferred":[
        "\u0636\u0628\u0631 \u0627\u0644\u0633\u0648\u062f"
    ],
    "name:und_x_variant":[
        "\u1e10abr as S\u016bd"
    ],
    "wof:name":"Dabr as Sud",
    "wof:placetype":"locality"
},
  "geometry": {"coordinates":[43.40988,14.82674],"type":"Point"}
}