{
  "type": "Feature",
  "properties": {
    "gn:admin1_code":"23.0",
    "gn:admin2_code":"1101.0",
    "gn:asciiname":"An Naqil",
    "gn:country_code":"YE",
    "gn:dem":1590,
    "gn:feature_class":"P",
    "gn:feature_code":"PPL",
    "gn:name":"An Naq\u012bl",
    "gn:population":0,
    "gn:timezone":"Asia/Aden",
    "iso:country":"YE",
    "name:ara_x_preferred":[
        "\u0627\u0644\u0646\u0642\u064a\u0644"
    ],
    "name:und_x_variant":[
        "An Naq\u012bl"
    ],
    "wof:name":"An Naqil",
    "wof:placetype":"locality"
},
  "geometry": {"coordinates":[44.153,14.33531],"type":"Point"}
}