{
  "type": "Feature",
  "properties": {
    "gn:admin1_code":"19.0",
    "gn:admin2_code":"2920.0",
    "gn:asciiname":"Al Hayfah",
    "gn:country_code":"YE",
    "gn:dem":2086,
    "gn:feature_class":"P",
    "gn:feature_code":"PPL",
    "gn:name":"Al \u1e28ayfah",
    "gn:population":0,
    "gn:timezone":"Asia/Aden",
    "iso:country":"YE",
    "name:ara_x_preferred":[
        "\u0627\u0644\u062d\u064a\u0641\u0629"
    ],
    "name:fas_x_preferred":[
        "\u0627\u0644\u062d\u06cc\u0641\u0647"
    ],
    "name:nno_x_preferred":[
        "Al Hayfah"
    ],
    "name:und_x_variant":[
        "Al \u1e28ayfah"
    ],
    "wof:name":"Al Hayfah",
    "wof:placetype":"locality"
},
  "geometry": {"coordinates":[43.92299000000001,16.09018],"type":"Point"}
}