{
  "type": "Feature",
  "properties": {
    "gn:admin1_code":"18.0",
    "gn:admin2_code":"3006.0",
    "gn:asciiname":"Saywat",
    "gn:country_code":"YE",
    "gn:dem":1595,
    "gn:feature_class":"P",
    "gn:feature_code":"PPL",
    "gn:name":"Saywat",
    "gn:population":0,
    "gn:timezone":"Asia/Aden",
    "iso:country":"YE",
    "name:und_x_variant":[
        "Saiwat",
        "Sewat",
        "Saywat"
    ],
    "wof:name":"Saywat",
    "wof:placetype":"locality"
},
  "geometry": {"coordinates":[44.68379,13.77836],"type":"Point"}
}