{
  "type": "Feature",
  "properties": {
    "gn:admin1_code":"20.0",
    "gn:admin2_code":"1418.0",
    "gn:asciiname":"Bayt al Wuhayshi",
    "gn:country_code":"YE",
    "gn:dem":2087,
    "gn:feature_class":"P",
    "gn:feature_code":"PPL",
    "gn:name":"Bayt al Wu\u1e29aysh\u012b",
    "gn:population":0,
    "gn:timezone":"Asia/Aden",
    "iso:country":"YE",
    "name:und_x_variant":[
        "Bayt al Wu\u1e29aysh\u012b"
    ],
    "wof:name":"Bayt al Wuhayshi",
    "wof:placetype":"locality"
},
  "geometry": {"coordinates":[44.69812,14.19524],"type":"Point"}
}