{
  "type": "Feature",
  "properties": {
    "gn:country":"YE",
    "gn:fcode":"PPL",
    "gn:pop":27,
    "iso:country":"YE",
    "name:ara_x_preferred":[
        "\u0623\u0628\u0648 \u0645\u0634\u0639\u0641"
    ],
    "name:eng_x_preferred":[
        "AbU Mash'af"
    ],
    "name:eng_x_variant":[
        "Al Khurbah"
    ],
    "qs:name":"Ab\u016b Mash\u2018af",
    "qs:photos_9r":0,
    "qs:photos_sr":0,
    "qs:pop_sr":"1",
    "wof:name":"Ab\u016b Mash\u2018af",
    "wof:placetype":"locality",
    "wof:population":27
},
  "geometry": {"coordinates":[43.73491,16.94432],"type":"Point"}
}