{
  "type": "Feature",
  "properties": {
    "gn:admin1_code":"11.0",
    "gn:admin2_code":"2005.0",
    "gn:asciiname":"Ad Dula`",
    "gn:country_code":"YE",
    "gn:dem":1896,
    "gn:feature_class":"P",
    "gn:feature_code":"PPL",
    "gn:name":"A\u1e11 \u1e10ul\u0101\u2018",
    "gn:population":0,
    "gn:timezone":"Asia/Aden",
    "iso:country":"YE",
    "name:ara_x_preferred":[
        "A\u1e11 \u1e10ul\u0101\u2018"
    ],
    "wof:name":"Ad Dula`",
    "wof:placetype":"locality"
},
  "geometry": {"coordinates":[44.0106,14.49701],"type":"Point"}
}