{
  "type": "Feature",
  "properties": {
    "gn:country":"YE",
    "gn:fcode":"PPL",
    "gn:population":4,
    "iso:country":"YE",
    "name:ara_x_preferred":[
        "Al Mu\u1e11b\u0101r"
    ],
    "name:ara_x_variant":[
        "\u0627\u0644\u0645\u0636\u0628\u0627\u0631"
    ],
    "qs:name":"Al Mu\u1e11b\u0101r",
    "qs:photos_9r":0,
    "qs:photos_sr":0,
    "qs:pop_sr":"1",
    "wof:name":"Al Mu\u1e11b\u0101r",
    "wof:placetype":"locality",
    "wof:population":4
},
  "geometry": {"coordinates":[43.40557,16.00164],"type":"Point"}
}