{
  "type": "Feature",
  "properties": {
    "gn:admin1_code":"25.0",
    "gn:admin2_code":"1515.0",
    "gn:asciiname":"Al Masbub",
    "gn:country_code":"YE",
    "gn:dem":1321,
    "gn:feature_class":"P",
    "gn:feature_code":"PPL",
    "gn:name":"Al Masb\u016bb",
    "gn:population":0,
    "gn:timezone":"Asia/Aden",
    "iso:country":"YE",
    "name:ara_x_preferred":[
        "\u0627\u0644\u0645\u0633\u0628\u0648\u0628"
    ],
    "name:und_x_variant":[
        "Al Masb\u016bb"
    ],
    "wof:name":"Al Masbub",
    "wof:placetype":"locality"
},
  "geometry": {"coordinates":[44.12794,13.20212],"type":"Point"}
}