{
  "type": "Feature",
  "properties": {
    "gn:admin1_code":"11.0",
    "gn:admin2_code":"2001.0",
    "gn:asciiname":"Mishqah",
    "gn:country_code":"YE",
    "gn:dem":2168,
    "gn:feature_class":"P",
    "gn:feature_code":"PPL",
    "gn:name":"Mishq\u0101\u1e29",
    "gn:population":0,
    "gn:timezone":"Asia/Aden",
    "iso:country":"YE",
    "name:ara_x_preferred":[
        "Mishq\u0101\u1e29"
    ],
    "wof:name":"Mishqah",
    "wof:placetype":"locality"
},
  "geometry": {"coordinates":[44.71981,14.72156],"type":"Point"}
}