{
  "type": "Feature",
  "properties": {
    "gn:country":"YE",
    "gn:fcode":"PPL",
    "gn:pop":1,
    "iso:country":"YE",
    "name:ara_x_preferred":[
        "\u0639\u0646\u0633"
    ],
    "name:eng_x_preferred":[
        "Anis"
    ],
    "name:unk_x_variant":[
        "\u2018Ans"
    ],
    "qs:name":"\u2018Anis",
    "qs:photos_9r":0,
    "qs:photos_sr":0,
    "qs:pop_sr":"1",
    "wd:wordcount":120,
    "wof:name":"\u2018Anis",
    "wof:placetype":"locality",
    "wof:population":1
},
  "geometry": {"coordinates":[43.85125,13.42581],"type":"Point"}
}