{
  "type": "Feature",
  "properties": {
    "gn:admin1_code":"4.0",
    "gn:admin2_code":"1904.0",
    "gn:asciiname":"Zamakh",
    "gn:country_code":"YE",
    "gn:dem":1014,
    "gn:feature_class":"P",
    "gn:feature_code":"PPL",
    "gn:name":"Zamakh",
    "gn:population":0,
    "gn:timezone":"Asia/Aden",
    "iso:country":"YE",
    "name:ara_x_preferred":[
        "\u0632\u0645\u062e"
    ],
    "wof:name":"Zamakh",
    "wof:placetype":"locality"
},
  "geometry": {"coordinates":[47.59863,16.44174],"type":"Point"}
}