{
  "type": "Feature",
  "properties": {
    "gn:admin1_code":"8.0",
    "gn:admin2_code":"1812.0",
    "gn:asciiname":"Al 'Amaj",
    "gn:country_code":"YE",
    "gn:dem":1264,
    "gn:feature_class":"P",
    "gn:feature_code":"PPL",
    "gn:name":"Al \u2018Amaj",
    "gn:population":0,
    "gn:timezone":"Asia/Aden",
    "iso:country":"YE",
    "name:ara_x_preferred":[
        "\u0627\u0644\u0639\u0645\u062c"
    ],
    "name:und_x_variant":[
        "Al \u2018Amaj"
    ],
    "wof:name":"Al 'Amaj",
    "wof:placetype":"locality"
},
  "geometry": {"coordinates":[43.43591,14.91755],"type":"Point"}
}