{
  "type": "Feature",
  "properties": {
    "gn:admin1_code":"25.0",
    "gn:admin2_code":"1515.0",
    "gn:asciiname":"Ad Dimnah",
    "gn:country_code":"YE",
    "gn:dem":2060,
    "gn:feature_class":"P",
    "gn:feature_code":"PPL",
    "gn:name":"Ad Dimnah",
    "gn:population":0,
    "gn:timezone":"Asia/Aden",
    "iso:country":"YE",
    "name:ara_x_preferred":[
        "\u0627\u0644\u062f\u0645\u0646\u0629"
    ],
    "wof:name":"Ad Dimnah",
    "wof:placetype":"locality"
},
  "geometry": {"coordinates":[44.15928,13.21229],"type":"Point"}
}