{
  "type": "Feature",
  "properties": {
    "gn:admin1_code":"8.0",
    "gn:admin2_code":"1813.0",
    "gn:asciiname":"Al Mibrayah",
    "gn:country_code":"YE",
    "gn:dem":139,
    "gn:feature_class":"P",
    "gn:feature_code":"PPL",
    "gn:name":"Al Mibr\u0101yah",
    "gn:population":0,
    "gn:timezone":"Asia/Aden",
    "iso:country":"YE",
    "name:und_x_variant":[
        "Al Mibr\u0101yah"
    ],
    "wof:name":"Al Mibrayah",
    "wof:placetype":"locality"
},
  "geometry": {"coordinates":[43.23862,14.9418],"type":"Point"}
}