{
  "type": "Feature",
  "properties": {
    "gn:country":"YE",
    "gn:fcode":"PPL",
    "gn:population":29,
    "iso:country":"YE",
    "name:ara_x_preferred":[
        "\u0627\u0644 \u0632\u0645\u0627\u0644"
    ],
    "name:eng_x_preferred":[
        "Al Zamal"
    ],
    "name:urd_x_preferred":[
        "\u0633\u06c1\u0645"
    ],
    "qs:name":"\u0100l Zam\u0101l",
    "qs:photos_9r":0,
    "qs:photos_sr":0,
    "qs:pop_sr":"1",
    "wof:name":"\u0100l Zam\u0101l",
    "wof:placetype":"locality",
    "wof:population":29
},
  "geometry": {"coordinates":[44.34185,17.05158],"type":"Point"}
}