{
  "type": "Feature",
  "properties": {
    "gn:admin1_code":"20.0",
    "gn:admin2_code":"1420.0",
    "gn:asciiname":"Shi`b al Hilwah",
    "gn:country_code":"YE",
    "gn:dem":2012,
    "gn:feature_class":"P",
    "gn:feature_code":"PPL",
    "gn:name":"Shi\u2018b al \u1e28ilwah",
    "gn:population":0,
    "gn:timezone":"Asia/Aden",
    "iso:country":"YE",
    "name:und_x_variant":[
        "Shi\u2018b al \u1e28ilwah"
    ],
    "wof:name":"Shi`b al Hilwah",
    "wof:placetype":"locality"
},
  "geometry": {"coordinates":[45.38146,14.39076],"type":"Point"}
}