{
  "type": "Feature",
  "properties": {
    "gn:admin1_code":"23.0",
    "gn:admin2_code":"1110.0",
    "gn:asciiname":"Al Gharib",
    "gn:country_code":"YE",
    "gn:dem":708,
    "gn:feature_class":"P",
    "gn:feature_code":"PPL",
    "gn:name":"Al Gh\u0101rib",
    "gn:population":0,
    "gn:timezone":"Asia/Aden",
    "iso:country":"YE",
    "name:ara_x_preferred":[
        "Al Gh\u0101rib"
    ],
    "name:ara_x_variant":[
        "\u0627\u0644\u063a\u0627\u0631\u0628"
    ],
    "wof:name":"Al Gharib",
    "wof:placetype":"locality"
},
  "geometry": {"coordinates":[43.72386,13.91769],"type":"Point"}
}