{
  "type": "Feature",
  "properties": {
    "gn:admin1_code":"20.0",
    "gn:admin2_code":"1420.0",
    "gn:asciiname":"Al Lisan",
    "gn:country_code":"YE",
    "gn:dem":2039,
    "gn:feature_class":"P",
    "gn:feature_code":"PPL",
    "gn:name":"Al Lis\u0101n",
    "gn:population":0,
    "gn:timezone":"Asia/Aden",
    "iso:country":"YE",
    "name:ara_x_preferred":[
        "Al Lis\u0101n"
    ],
    "wof:name":"Al Lisan",
    "wof:placetype":"locality"
},
  "geometry": {"coordinates":[45.35765,14.31682],"type":"Point"}
}