{
  "type": "Feature",
  "properties": {
    "gn:admin1_code":"25.0",
    "gn:admin2_code":"1515.0",
    "gn:asciiname":"Al Fujr",
    "gn:country_code":"YE",
    "gn:dem":933,
    "gn:feature_class":"P",
    "gn:feature_code":"PPL",
    "gn:name":"Al Fujr",
    "gn:population":0,
    "gn:timezone":"Asia/Aden",
    "iso:country":"YE",
    "wof:name":"Al Fujr",
    "wof:placetype":"locality"
},
  "geometry": {"coordinates":[44.0093,13.14379],"type":"Point"}
}