{
  "type": "Feature",
  "properties": {
    "gn:admin1_code":"22.0",
    "gn:admin2_code":"1707.0",
    "gn:asciiname":"Bayt Ji'wan al 'Ulya",
    "gn:country_code":"YE",
    "gn:dem":1307,
    "gn:feature_class":"P",
    "gn:feature_code":"PPL",
    "gn:name":"Bayt Ji\u2018w\u0101n al \u2018Uly\u0101",
    "gn:population":0,
    "gn:timezone":"Asia/Aden",
    "iso:country":"YE",
    "name:ara_x_preferred":[
        "\u0628\u064a\u062a \u062c\u0639\u0648\u0627\u0646 \u0627\u0644\u0639\u0644\u064a\u0627"
    ],
    "name:und_x_variant":[
        "Bayt Ji\u2018w\u0101n al \u2018Uly\u0101"
    ],
    "wof:name":"Bayt Ji'wan al 'Ulya",
    "wof:placetype":"locality"
},
  "geometry": {"coordinates":[43.44325,16.16181],"type":"Point"}
}