{
  "type": "Feature",
  "properties": {
    "gn:admin1_code":"5.0",
    "gn:admin2_code":"2112.0",
    "gn:asciiname":"Malilah",
    "gn:country_code":"YE",
    "gn:dem":1243,
    "gn:feature_class":"P",
    "gn:feature_code":"PPL",
    "gn:name":"Mal\u012blah",
    "gn:population":0,
    "gn:timezone":"Asia/Aden",
    "iso:country":"YE",
    "name:und_x_variant":[
        "Mal\u012blah"
    ],
    "wof:name":"Malilah",
    "wof:placetype":"locality"
},
  "geometry": {"coordinates":[46.90043,14.32205],"type":"Point"}
}