{
  "type": "Feature",
  "properties": {
    "gn:admin1_code":"16.0",
    "gn:admin2_code":"2311.0",
    "gn:asciiname":"Al Jirwah",
    "gn:country_code":"YE",
    "gn:dem":1736,
    "gn:feature_class":"P",
    "gn:feature_code":"PPL",
    "gn:name":"Al Jirwa\u1e29",
    "gn:population":0,
    "gn:timezone":"Asia/Aden",
    "iso:country":"YE",
    "name:nno_x_preferred":[
        "Al-Jirwah"
    ],
    "name:und_x_variant":[
        "Al Jirwa\u1e29"
    ],
    "wof:name":"Al Jirwah",
    "wof:placetype":"locality"
},
  "geometry": {"coordinates":[43.63053,15.0677],"type":"Point"}
}