{
  "type": "Feature",
  "properties": {
    "gn:admin1_code":"16.0",
    "gn:admin2_code":"2309.0",
    "gn:asciiname":"Az Zuhrah",
    "gn:country_code":"YE",
    "gn:dem":1713,
    "gn:feature_class":"P",
    "gn:feature_code":"PPL",
    "gn:name":"Az\u0327 Zuhrah",
    "gn:population":0,
    "gn:timezone":"Asia/Aden",
    "iso:country":"YE",
    "name:und_x_variant":[
        "Az\u0327 Zuhrah",
        "Az\u0327 Z\u0327urah"
    ],
    "wof:name":"Az Zuhrah",
    "wof:placetype":"locality"
},
  "geometry": {"coordinates":[43.89316,15.00617],"type":"Point"}
}