{
  "type": "Feature",
  "properties": {
    "gn:admin1_code":"24.0",
    "gn:admin2_code":"2511.0",
    "gn:asciiname":"An Nawbah",
    "gn:country_code":"YE",
    "gn:dem":482,
    "gn:feature_class":"P",
    "gn:feature_code":"PPL",
    "gn:name":"An Nawbah",
    "gn:population":0,
    "gn:timezone":"Asia/Aden",
    "iso:country":"YE",
    "name:und_x_variant":[
        "D\u0101r Nawbat al A\u0163w\u0101n",
        "Nabat Matwam",
        "D\u0101r N\u016bbat al A\u0163w\u0101n",
        "An Nawbah",
        "Nawbat al A\u0163w\u0101m"
    ],
    "wof:name":"An Nawbah",
    "wof:placetype":"locality"
},
  "geometry": {"coordinates":[44.4531,13.11214],"type":"Point"}
}