{
  "type": "Feature",
  "properties": {
    "gn:country":"YE",
    "gn:fcode":"PPL",
    "gn:pop":3,
    "iso:country":"YE",
    "name:ara_x_preferred":[
        "\u0627\u0644\u0645\u0631\u0632\u0648\u0642\u0629"
    ],
    "name:eng_x_preferred":[
        "Al MarzUqah"
    ],
    "name:eng_x_variant":[
        "Al Jun\u016bbah"
    ],
    "qs:name":"Al Marz\u016bqah",
    "qs:photos_9r":0,
    "qs:photos_sr":0,
    "qs:pop_sr":"1",
    "wof:name":"Al Marz\u016bqah",
    "wof:placetype":"locality",
    "wof:population":3
},
  "geometry": {"coordinates":[43.25945,17.20655],"type":"Point"}
}