{
  "type": "Feature",
  "properties": {
    "gn:admin1_code":"25.0",
    "gn:admin2_code":"1508.0",
    "gn:asciiname":"`Aysim",
    "gn:country_code":"YE",
    "gn:dem":214,
    "gn:feature_class":"P",
    "gn:feature_code":"PPL",
    "gn:name":"\u2018Ay\u015fim",
    "gn:population":0,
    "gn:timezone":"Asia/Aden",
    "iso:country":"YE",
    "name:ara_x_preferred":[
        "Al \u2018Ay\u015f\u012bm"
    ],
    "name:ara_x_variant":[
        "\u2018Ay\u015fim",
        "\u0639\u064a\u0635\u0645"
    ],
    "wof:name":"`Aysim",
    "wof:placetype":"locality"
},
  "geometry": {"coordinates":[43.51975,13.29249],"type":"Point"}
}