{
  "type": "Feature",
  "properties": {
    "gn:admin1_code":"22.0",
    "gn:admin2_code":"1704.0",
    "gn:asciiname":"Dayn",
    "gn:country_code":"YE",
    "gn:dem":53,
    "gn:feature_class":"P",
    "gn:feature_code":"PPL",
    "gn:name":"Dayn",
    "gn:population":0,
    "gn:timezone":"Asia/Aden",
    "iso:country":"YE",
    "name:und_x_variant":[
        "Dubn",
        "Dayn"
    ],
    "wof:name":"Dayn",
    "wof:placetype":"locality"
},
  "geometry": {"coordinates":[42.96351,15.90927],"type":"Point"}
}