{
  "type": "Feature",
  "properties": {
    "gn:country":"YE",
    "gn:fcode":"PPL",
    "gn:pop":1,
    "iso:country":"YE",
    "name:ara_x_preferred":[
        "\u0627\u0644\u0633\u064a\u0627\u0644"
    ],
    "name:eng_x_preferred":[
        "As Sayal"
    ],
    "name:eng_x_variant":[
        "Dhaw\u0101t al \u2018Arsh"
    ],
    "qs:name":"As Say\u0101l",
    "qs:photos_9r":0,
    "qs:photos_sr":0,
    "qs:pop_sr":"1",
    "wof:name":"As Say\u0101l",
    "wof:placetype":"locality",
    "wof:population":1
},
  "geometry": {"coordinates":[43.3201,17.01206],"type":"Point"}
}