{
  "type": "Feature",
  "properties": {
    "gn:country":"YE",
    "gn:fcode":"PPL",
    "gn:population":2,
    "iso:country":"YE",
    "name:ara_x_preferred":[
        "\u0632\u0648\u0631 \u0639\u0643\u0635\u0629"
    ],
    "name:eng_x_preferred":[
        "Zawr 'Uksah"
    ],
    "name:eng_x_variant":[
        "Ash Shi\u1e29\u0101rah"
    ],
    "qs:name":"Zawr \u2018Uk\u015fah",
    "qs:photos_9r":0,
    "qs:photos_sr":0,
    "qs:pop_sr":"1",
    "wof:name":"Zawr \u2018Uk\u015fah",
    "wof:placetype":"locality",
    "wof:population":2
},
  "geometry": {"coordinates":[44.81944,16.83125],"type":"Point"}
}