{
  "type": "Feature",
  "properties": {
    "gn:admin1_code":"8.0",
    "gn:admin2_code":"1815.0",
    "gn:asciiname":"Buyut Hamid",
    "gn:country_code":"YE",
    "gn:dem":138,
    "gn:feature_class":"P",
    "gn:feature_code":"PPL",
    "gn:name":"Buy\u016bt \u1e28\u0101mid",
    "gn:population":0,
    "gn:timezone":"Asia/Aden",
    "iso:country":"YE",
    "name:ara_x_preferred":[
        "\u0628\u064a\u0648\u062a \u062d\u0627\u0645\u062f"
    ],
    "name:und_x_variant":[
        "\u1e28\u0101mid",
        "Quz\u2018at \u1e28\u0101mid",
        "Buy\u016bt \u1e28\u0101mid"
    ],
    "wof:name":"Buyut Hamid",
    "wof:placetype":"locality"
},
  "geometry": {"coordinates":[43.30717,14.74045],"type":"Point"}
}