{
  "type": "Feature",
  "properties": {
    "gn:country":"YE",
    "gn:fcode":"PPL",
    "gn:population":7,
    "iso:country":"YE",
    "name:ara_x_preferred":[
        "\u0627\u0644\u062e\u0628\u0637\u0646"
    ],
    "name:eng_x_preferred":[
        "Al Khabtan"
    ],
    "name:eng_x_variant":[
        "\u1e28ubayl \u2018Umar"
    ],
    "qs:name":"Al Khab\u0163an",
    "qs:photos_9r":0,
    "qs:photos_sr":0,
    "qs:pop_sr":"1",
    "wof:name":"Al Khab\u0163an",
    "wof:placetype":"locality",
    "wof:population":7
},
  "geometry": {"coordinates":[44.34033,16.56827],"type":"Point"}
}