{
  "type": "Feature",
  "properties": {
    "gn:admin1_code":"23.0",
    "gn:admin2_code":"1109.0",
    "gn:asciiname":"Al Markarad",
    "gn:country_code":"YE",
    "gn:dem":1208,
    "gn:feature_class":"P",
    "gn:feature_code":"PPL",
    "gn:name":"Al Markarad",
    "gn:population":0,
    "gn:timezone":"Asia/Aden",
    "iso:country":"YE",
    "name:ara_x_preferred":[
        "\u0627\u0644\u0645\u0631\u0643\u0631\u062f"
    ],
    "name:und_x_variant":[
        "Al Murkadid",
        "Al Markarad"
    ],
    "wof:name":"Al Markarad",
    "wof:placetype":"locality"
},
  "geometry": {"coordinates":[43.94937,14.08778],"type":"Point"}
}