{
  "type": "Feature",
  "properties": {
    "gn:admin1_code":"23.0",
    "gn:admin2_code":"1101.0",
    "gn:asciiname":"As Sahlah",
    "gn:country_code":"YE",
    "gn:dem":1247,
    "gn:feature_class":"P",
    "gn:feature_code":"PPL",
    "gn:name":"As Sahlah",
    "gn:population":0,
    "gn:timezone":"Asia/Aden",
    "iso:country":"YE",
    "name:ara_x_preferred":[
        "\u0627\u0644\u0633\u0647\u0644\u0629"
    ],
    "wof:name":"As Sahlah",
    "wof:placetype":"locality"
},
  "geometry": {"coordinates":[44.06431,14.29681],"type":"Point"}
}