{
  "type": "Feature",
  "properties": {
    "gn:admin1_code":"19.0",
    "gn:admin2_code":"2905.0",
    "gn:asciiname":"Kuhlan",
    "gn:country_code":"YE",
    "gn:dem":1881,
    "gn:feature_class":"P",
    "gn:feature_code":"PPL",
    "gn:name":"Ku\u1e29l\u0101n",
    "gn:population":0,
    "gn:timezone":"Asia/Aden",
    "iso:country":"YE",
    "name:ara_x_preferred":[
        "Ku\u1e29l\u0101n"
    ],
    "name:ara_x_variant":[
        "\u0643\u062d\u0644\u0627\u0646"
    ],
    "wof:name":"Kuhlan",
    "wof:placetype":"locality"
},
  "geometry": {"coordinates":[43.69216,16.13924],"type":"Point"}
}