{
  "type": "Feature",
  "properties": {
    "gn:admin1_code":"11.0",
    "gn:admin2_code":"2001.0",
    "gn:asciiname":"Hisn Abu Sanad",
    "gn:country_code":"YE",
    "gn:dem":2357,
    "gn:feature_class":"P",
    "gn:feature_code":"PPL",
    "gn:name":"\u1e28i\u015fn Ab\u016b Sanad",
    "gn:population":0,
    "gn:timezone":"Asia/Aden",
    "iso:country":"YE",
    "name:und_x_variant":[
        "\u1e28i\u015fn Ab\u016b Sanad"
    ],
    "wof:name":"Hisn Abu Sanad",
    "wof:placetype":"locality"
},
  "geometry": {"coordinates":[44.40225,14.82359],"type":"Point"}
}