{
  "type": "Feature",
  "properties": {
    "gn:admin1_code":"8.0",
    "gn:admin2_code":"1806.0",
    "gn:asciiname":"Mahall Hatim",
    "gn:country_code":"YE",
    "gn:dem":50,
    "gn:feature_class":"P",
    "gn:feature_code":"PPL",
    "gn:name":"Ma\u1e29all \u1e28\u0101tim",
    "gn:population":0,
    "gn:timezone":"Asia/Aden",
    "iso:country":"YE",
    "name:ara_x_preferred":[
        "\u0645\u062d\u0644 \u062d\u0627\u062a\u0645"
    ],
    "name:und_x_variant":[
        "Ma\u1e29all \u1e28\u0101tim"
    ],
    "wof:name":"Mahall Hatim",
    "wof:placetype":"locality"
},
  "geometry": {"coordinates":[42.98731,15.3725],"type":"Point"}
}