{
  "type": "Feature",
  "properties": {
    "gn:admin1_code":"8.0",
    "gn:admin2_code":"1823.0",
    "gn:asciiname":"Mazra'at as Sayyid Hasan Qanawi",
    "gn:country_code":"YE",
    "gn:dem":38,
    "gn:feature_class":"P",
    "gn:feature_code":"PPL",
    "gn:name":"Mazra\u2018at as Sayyid \u1e28asan Qan\u0101w\u012b",
    "gn:population":0,
    "gn:timezone":"Asia/Aden",
    "iso:country":"YE",
    "name:ara_x_preferred":[
        "\u0645\u0632\u0631\u0639\u0629 \u0627\u0644\u0633\u064a\u062f \u062d\u0633\u0646 \u0642\u0646\u0627\u0648\u064a"
    ],
    "name:und_x_variant":[
        "Mazra\u2018at as Sayyid \u1e28asan Qan\u0101w\u012b"
    ],
    "wof:name":"Mazra'at as Sayyid Hasan Qanawi",
    "wof:placetype":"locality"
},
  "geometry": {"coordinates":[43.05873,14.81406],"type":"Point"}
}