{
  "type": "Feature",
  "properties": {
    "gn:country":"YE",
    "gn:fcode":"PPL",
    "gn:pop":9,
    "iso:country":"YE",
    "name:ara_x_preferred":[
        "\u0627\u0644\u0634\u062f\u064a\u062f\u0629"
    ],
    "name:eng_x_preferred":[
        "Ash Shadidah"
    ],
    "qs:name":"Ash Shad\u012bdah",
    "qs:photos_9r":0,
    "qs:photos_sr":0,
    "qs:pop_sr":"1",
    "wof:name":"Ash Shad\u012bdah",
    "wof:placetype":"locality",
    "wof:population":9
},
  "geometry": {"coordinates":[43.36043,16.23512],"type":"Point"}
}