{
  "type": "Feature",
  "properties": {
    "gn:country":"YE",
    "gn:fcode":"PPLL",
    "gn:pop":3,
    "iso:country":"YE",
    "name:ara_x_preferred":[
        "\u0631\u062d\u0628\u0629 \u0638\u0628\u064a\u0646"
    ],
    "name:eng_x_preferred":[
        "Rahabat Zubayn"
    ],
    "qs:name":"Ra\u1e29abat Z\u0327ubayn",
    "qs:photos_9r":0,
    "qs:photos_sr":0,
    "qs:pop_sr":"1",
    "wof:name":"Ra\u1e29abat Z\u0327ubayn",
    "wof:placetype":"locality",
    "wof:population":3
},
  "geometry": {"coordinates":[44.78444,16.82737],"type":"Point"}
}