{
  "type": "Feature",
  "properties": {
    "gn:country":"YE",
    "gn:fcode":"PPL",
    "gn:population":48,
    "iso:country":"YE",
    "name:ara_x_preferred":[
        "\u0627\u0644\u062c\u0627\u062f\u0629 \u0627\u0644\u0633\u0641\u0644\u0649"
    ],
    "name:eng_x_preferred":[
        "Al Jadah As Sufla"
    ],
    "name:eng_x_variant":[
        "Al Mishy\u0101f"
    ],
    "qs:name":"Al J\u0101dah as Sufl\u00e1",
    "qs:photos_9r":0,
    "qs:photos_sr":0,
    "qs:pop_sr":"1",
    "wof:name":"Al J\u0101dah as Sufl\u00e1",
    "wof:placetype":"locality",
    "wof:population":48
},
  "geometry": {"coordinates":[43.3754,16.16941],"type":"Point"}
}