{
  "type": "Feature",
  "properties": {
    "gn:admin1_code":"8.0",
    "gn:admin2_code":"1814.0",
    "gn:asciiname":"Khabair",
    "gn:country_code":"YE",
    "gn:dem":44,
    "gn:feature_class":"P",
    "gn:feature_code":"PPL",
    "gn:name":"Khabair",
    "gn:population":0,
    "gn:timezone":"Asia/Aden",
    "iso:country":"YE",
    "wof:name":"Khabair",
    "wof:placetype":"locality"
},
  "geometry": {"coordinates":[43.16656,14.63199],"type":"Point"}
}