{
  "type": "Feature",
  "properties": {
    "gn:gn_country":"YE",
    "gn:gn_fcode":"PPL",
    "gn:gn_pop":7,
    "gn:population":7,
    "iso:country":"YE",
    "name:ara_x_preferred":[
        "\u0627\u0644\u062e\u0631\u0642"
    ],
    "name:eng_x_preferred":[
        "Al Kharraq"
    ],
    "qs_pg:aaroncc":"YE",
    "qs_pg:gn_country":"YE",
    "qs_pg:gn_fcode":"PPL",
    "qs_pg:gn_pop":7,
    "qs_pg:name":"Al Kharraq",
    "qs_pg:photos_9r":0,
    "qs_pg:photos_sr":0,
    "qs_pg:pop_sr":1,
    "qs_pg:qs_pg_placetype":"locality",
    "wof:name":"Al Kharraq",
    "wof:placetype":"locality",
    "wof:population":7
},
  "geometry": {"coordinates":[43.25124,16.17696],"type":"Point"}
}