{
  "type": "Feature",
  "properties": {
    "gn:admin1_code":"4.0",
    "gn:admin2_code":"1918.0",
    "gn:asciiname":"Libnat Ba Rushayd",
    "gn:cc2":"YE",
    "gn:country_code":"YE",
    "gn:dem":1690,
    "gn:feature_class":"P",
    "gn:feature_code":"PPL",
    "gn:name":"Libnat B\u0101 Rushayd",
    "gn:population":0,
    "gn:timezone":"Asia/Aden",
    "iso:country":"YE",
    "name:und_x_variant":[
        "Libnat B\u0101 Rashaid",
        "Libnat B\u0101 Rushayd"
    ],
    "wof:name":"Libnat Ba Rushayd",
    "wof:placetype":"locality"
},
  "geometry": {"coordinates":[48.32472,14.78972],"type":"Point"}
}