{
  "type": "Feature",
  "properties": {
    "gn:admin1_code":"25.0",
    "gn:admin2_code":"1515.0",
    "gn:asciiname":"Hayjat Shakbir",
    "gn:country_code":"YE",
    "gn:dem":1160,
    "gn:feature_class":"P",
    "gn:feature_code":"PPL",
    "gn:name":"Hayjat Shakbir",
    "gn:population":0,
    "gn:timezone":"Asia/Aden",
    "iso:country":"YE",
    "name:ara_x_preferred":[
        "\u0647\u064a\u062c\u0629 \u0634\u0643\u0628\u0631"
    ],
    "wof:name":"Hayjat Shakbir",
    "wof:placetype":"locality"
},
  "geometry": {"coordinates":[43.94348,13.15348],"type":"Point"}
}