{
  "type": "Feature",
  "properties": {
    "gn:country":"YE",
    "gn:fcode":"PPL",
    "gn:pop":2,
    "iso:country":"YE",
    "name:ara_x_preferred":[
        "\u0628\u064a\u062a \u0627\u0644\u0633\u0644\u0637\u0627\u0646"
    ],
    "name:eng_x_preferred":[
        "Bayt As Sultan"
    ],
    "name:nno_x_preferred":[
        "Ar Rahabah"
    ],
    "qs:name":"Bayt as Sul\u0163\u0101n",
    "qs:photos_9r":0,
    "qs:photos_sr":0,
    "qs:pop_sr":"1",
    "wof:name":"Bayt as Sul\u0163\u0101n",
    "wof:placetype":"locality",
    "wof:population":2
},
  "geometry": {"coordinates":[43.67504,16.18948],"type":"Point"}
}