{
  "type": "Feature",
  "properties": {
    "gn:country":"YE",
    "gn:fcode":"PPL",
    "gn:population":2,
    "iso:country":"YE",
    "name:ara_x_preferred":[
        "\u2018Anm\u012b"
    ],
    "name:ara_x_variant":[
        "\u0639\u0646\u0645\u064a"
    ],
    "name:eng_x_preferred":[
        "Anmi"
    ],
    "name:eng_x_variant":[
        "\u0100l Hudaysh",
        "'Anmi"
    ],
    "qs:name":"\u2018Anm\u012b",
    "qs:photos_9r":0,
    "qs:photos_sr":0,
    "qs:pop_sr":"1",
    "wof:name":"\u2018Anm\u012b",
    "wof:placetype":"locality",
    "wof:population":2
},
  "geometry": {"coordinates":[43.3612,16.67413],"type":"Point"}
}