{
  "type": "Feature",
  "properties": {
    "gn:admin1_code":"14.0",
    "gn:admin2_code":"2605.0",
    "gn:asciiname":"Al 'Awran",
    "gn:country_code":"YE",
    "gn:dem":1990,
    "gn:feature_class":"P",
    "gn:feature_code":"PPL",
    "gn:name":"Al \u2018Awr\u0101n",
    "gn:population":0,
    "gn:timezone":"Asia/Aden",
    "iso:country":"YE",
    "name:ara_x_preferred":[
        "\u0627\u0644\u0639\u0648\u0631\u0627\u0646"
    ],
    "name:und_x_variant":[
        "Al \u2018Awr\u0101n"
    ],
    "wof:name":"Al 'Awran",
    "wof:placetype":"locality"
},
  "geometry": {"coordinates":[44.74688,15.42195],"type":"Point"}
}