{
  "type": "Feature",
  "properties": {
    "gn:admin1_code":"27.0",
    "gn:admin2_code":"3103.0",
    "gn:asciiname":"Haqibah",
    "gn:country_code":"YE",
    "gn:dem":1823,
    "gn:feature_class":"P",
    "gn:feature_code":"PPL",
    "gn:name":"\u1e28aq\u012bbah",
    "gn:population":0,
    "gn:timezone":"Asia/Aden",
    "iso:country":"YE",
    "name:und_x_variant":[
        "\u1e28aq\u012bbah"
    ],
    "wof:name":"Haqibah",
    "wof:placetype":"locality"
},
  "geometry": {"coordinates":[43.86375,14.60303],"type":"Point"}
}