{
  "type": "Feature",
  "properties": {
    "gn:admin1_code":"14.0",
    "gn:admin2_code":"2606.0",
    "gn:asciiname":"Al Akhl",
    "gn:country_code":"YE",
    "gn:dem":1368,
    "gn:feature_class":"P",
    "gn:feature_code":"PPL",
    "gn:name":"Al Akhl",
    "gn:population":0,
    "gn:timezone":"Asia/Aden",
    "iso:country":"YE",
    "name:ara_x_preferred":[
        "\u0627\u0644\u0623\u062e\u0644"
    ],
    "wof:name":"Al Akhl",
    "wof:placetype":"locality"
},
  "geometry": {"coordinates":[44.88359000000001,15.52666],"type":"Point"}
}