{
  "type": "Feature",
  "properties": {
    "gn:admin1_code":"8.0",
    "gn:admin2_code":"1810.0",
    "gn:asciiname":"Al Jabariyah",
    "gn:country_code":"YE",
    "gn:dem":77,
    "gn:feature_class":"P",
    "gn:feature_code":"PPL",
    "gn:name":"Al Jabar\u012byah",
    "gn:population":0,
    "gn:timezone":"Asia/Aden",
    "iso:country":"YE",
    "name:und_x_variant":[
        "Al Jabar\u012byah"
    ],
    "wof:name":"Al Jabariyah",
    "wof:placetype":"locality"
},
  "geometry": {"coordinates":[43.11121,14.96282],"type":"Point"}
}