{
  "type": "Feature",
  "properties": {
    "gn:admin1_code":"8.0",
    "gn:admin2_code":"1824.0",
    "gn:asciiname":"Hasy Hindah",
    "gn:country_code":"YE",
    "gn:dem":131,
    "gn:feature_class":"P",
    "gn:feature_code":"PPL",
    "gn:name":"\u1e28asy Hindah",
    "gn:population":0,
    "gn:timezone":"Asia/Aden",
    "iso:country":"YE",
    "name:und_x_variant":[
        "\u1e28asy Hindah"
    ],
    "wof:name":"Hasy Hindah",
    "wof:placetype":"locality"
},
  "geometry": {"coordinates":[43.35517,14.30644],"type":"Point"}
}