{
  "type": "Feature",
  "properties": {
    "gn:country":"YE",
    "gn:fcode":"PPL",
    "gn:population":5,
    "iso:country":"YE",
    "name:ara_x_preferred":[
        "\u2018A\u015fir\u012b"
    ],
    "name:ara_x_variant":[
        "\u0639\u0635\u0631\u064a"
    ],
    "qs:name":"\u2018A\u015fir\u012b",
    "qs:photos_9r":0,
    "qs:photos_sr":0,
    "qs:pop_sr":"1",
    "wof:name":"\u2018A\u015fir\u012b",
    "wof:placetype":"locality",
    "wof:population":5
},
  "geometry": {"coordinates":[43.3683,16.67534],"type":"Point"}
}