{
  "type": "Feature",
  "properties": {
    "gn:country":"YE",
    "gn:fcode":"PPL",
    "gn:population":59,
    "iso:country":"YE",
    "name:ara_x_preferred":[
        "Al Murn\u0101f"
    ],
    "name:ara_x_variant":[
        "\u0627\u0644\u0645\u0631\u0646\u0627\u0641"
    ],
    "qs:name":"Al Murn\u0101f",
    "qs:photos_9r":0,
    "qs:photos_sr":0,
    "qs:pop_sr":"1",
    "wof:name":"Al Murn\u0101f",
    "wof:placetype":"locality",
    "wof:population":59
},
  "geometry": {"coordinates":[43.20243,15.99041],"type":"Point"}
}