{
  "type": "Feature",
  "properties": {
    "gn:admin1_code":"15.0",
    "gn:admin2_code":"2215.0",
    "gn:asciiname":"Raqban",
    "gn:country_code":"YE",
    "gn:dem":1871,
    "gn:feature_class":"P",
    "gn:feature_code":"PPL",
    "gn:name":"Raqb\u0101n",
    "gn:population":0,
    "gn:timezone":"Asia/Aden",
    "iso:country":"YE",
    "name:und_x_variant":[
        "Raqb\u0101n"
    ],
    "wof:name":"Raqban",
    "wof:placetype":"locality"
},
  "geometry": {"coordinates":[43.76667,16.93333],"type":"Point"}
}