{
  "type": "Feature",
  "properties": {
    "gn:country":"YE",
    "gn:fcode":"PPL",
    "gn:pop":2,
    "iso:country":"YE",
    "name:ara_x_preferred":[
        "\u0627\u0644\u0645\u0636\u0639\u0629"
    ],
    "name:eng_x_preferred":[
        "Al Miu'ah"
    ],
    "name:eng_x_variant":[
        "\u1e28ufayl\u0101 \u2018Ulkam"
    ],
    "qs:name":"Al Mi\u1e11\u2018ah",
    "qs:photos_9r":0,
    "qs:photos_sr":0,
    "qs:pop_sr":"1",
    "wof:name":"Al Mi\u1e11\u2018ah",
    "wof:placetype":"locality",
    "wof:population":2
},
  "geometry": {"coordinates":[44.31492,16.78896],"type":"Point"}
}