{
  "type": "Feature",
  "properties": {
    "gn:admin1_code":"25.0",
    "gn:admin2_code":"1521.0",
    "gn:asciiname":"Al Hadiyah",
    "gn:country_code":"YE",
    "gn:dem":1400,
    "gn:feature_class":"P",
    "gn:feature_code":"PPL",
    "gn:name":"Al \u1e28ad\u012byah",
    "gn:population":0,
    "gn:timezone":"Asia/Aden",
    "iso:country":"YE",
    "name:und_x_variant":[
        "Al \u1e28ad\u012byah"
    ],
    "wof:name":"Al Hadiyah",
    "wof:placetype":"locality"
},
  "geometry": {"coordinates":[43.9308,13.37464],"type":"Point"}
}