{
  "type": "Feature",
  "properties": {
    "gn:admin1_code":"23.0",
    "gn:admin2_code":"1101.0",
    "gn:asciiname":"Satah",
    "gn:country_code":"YE",
    "gn:dem":1899,
    "gn:feature_class":"P",
    "gn:feature_code":"PPL",
    "gn:name":"\u015ea\u0163a\u1e29",
    "gn:population":0,
    "gn:timezone":"Asia/Aden",
    "iso:country":"YE",
    "name:und_x_variant":[
        "\u015ea\u0163a\u1e29"
    ],
    "wof:name":"Satah",
    "wof:placetype":"locality"
},
  "geometry": {"coordinates":[44.18441,14.2691],"type":"Point"}
}