{
  "type": "Feature",
  "properties": {
    "gn:admin1_code":"25.0",
    "gn:admin2_code":"1502.0",
    "gn:asciiname":"Kuhul",
    "gn:country_code":"YE",
    "gn:dem":1199,
    "gn:feature_class":"P",
    "gn:feature_code":"PPL",
    "gn:name":"Kuh\u016bl",
    "gn:population":0,
    "gn:timezone":"Asia/Aden",
    "iso:country":"YE",
    "name:ara_x_preferred":[
        "Kuh\u016bl"
    ],
    "name:ara_x_variant":[
        "\u0627\u0644\u0643\u062d\u0644"
    ],
    "name:und_x_variant":[
        "Al Ka\u1e29l"
    ],
    "wof:name":"Kuhul",
    "wof:placetype":"locality"
},
  "geometry": {"coordinates":[43.9834,13.6093],"type":"Point"}
}