{
  "type": "Feature",
  "properties": {
    "gn:admin1_code":"16.0",
    "gn:admin2_code":"2301.0",
    "gn:asciiname":"Khabarah",
    "gn:country_code":"YE",
    "gn:dem":2181,
    "gn:feature_class":"P",
    "gn:feature_code":"PPL",
    "gn:name":"Khab\u0101rah",
    "gn:population":0,
    "gn:timezone":"Asia/Aden",
    "iso:country":"YE",
    "name:ara_x_preferred":[
        "\u062e\u0628\u0627\u0631\u0629"
    ],
    "name:nno_x_preferred":[
        "Khabarah"
    ],
    "name:und_x_variant":[
        "Khab\u0101rah"
    ],
    "wof:name":"Khabarah",
    "wof:placetype":"locality"
},
  "geometry": {"coordinates":[44.18202,15.53665],"type":"Point"}
}