{
  "type": "Feature",
  "properties": {
    "gn:admin1_code":"5.0",
    "gn:admin2_code":"2102.0",
    "gn:asciiname":"At Talh",
    "gn:country_code":"YE",
    "gn:dem":1398,
    "gn:feature_class":"P",
    "gn:feature_code":"PPLA2",
    "gn:name":"A\u0163 \u0162al\u1e29",
    "gn:population":0,
    "gn:timezone":"Asia/Aden",
    "iso:country":"YE",
    "name:ara_x_preferred":[
        "\u0627\u0644\u0637\u0644\u062d"
    ],
    "name:und_x_variant":[
        "A\u0163 \u0162al\u1e29"
    ],
    "wof:name":"At Talh",
    "wof:placetype":"locality"
},
  "geometry": {"coordinates":[47.39903,15.156],"type":"Point"}
}