{
  "type": "Feature",
  "properties": {
    "gn:admin1_code":"10.0",
    "gn:admin2_code":"2705.0",
    "gn:asciiname":"Al Mulayhi",
    "gn:country_code":"YE",
    "gn:dem":482,
    "gn:feature_class":"P",
    "gn:feature_code":"PPL",
    "gn:name":"Al Mulay\u1e29\u012b",
    "gn:population":0,
    "gn:timezone":"Asia/Aden",
    "iso:country":"YE",
    "name:und_x_variant":[
        "Al Mulay\u1e29\u012b"
    ],
    "wof:name":"Al Mulayhi",
    "wof:placetype":"locality"
},
  "geometry": {"coordinates":[43.31453,15.34893],"type":"Point"}
}