{
  "type": "Feature",
  "properties": {
    "gn:admin1_code":"8.0",
    "gn:admin2_code":"1818.0",
    "gn:asciiname":"Rub` al Majari",
    "gn:country_code":"YE",
    "gn:dem":757,
    "gn:feature_class":"P",
    "gn:feature_code":"PPL",
    "gn:name":"Rub\u2018 al Maj\u0101r\u012b",
    "gn:population":0,
    "gn:timezone":"Asia/Aden",
    "iso:country":"YE",
    "name:und_x_variant":[
        "Rub\u2018 al Maj\u0101r\u012b"
    ],
    "wof:name":"Rub` al Majari",
    "wof:placetype":"locality"
},
  "geometry": {"coordinates":[43.61754000000001,14.0505],"type":"Point"}
}