{
  "type": "Feature",
  "properties": {
    "gn:admin1_code":"4.0",
    "gn:admin2_code":"1918.0",
    "gn:asciiname":"Ad Dufah",
    "gn:cc2":"YE",
    "gn:country_code":"YE",
    "gn:dem":1065,
    "gn:feature_class":"P",
    "gn:feature_code":"PPL",
    "gn:name":"Ad D\u016bfah",
    "gn:population":0,
    "gn:timezone":"Asia/Aden",
    "iso:country":"YE",
    "name:und_x_variant":[
        "Al-D\u016bfah",
        "Ad D\u016bfah"
    ],
    "wof:name":"Ad Dufah",
    "wof:placetype":"locality"
},
  "geometry": {"coordinates":[48.37222,15.24361],"type":"Point"}
}