{
  "type": "Feature",
  "properties": {
    "gn:country":"YE",
    "gn:fcode":"PPLX",
    "gn:pop":15,
    "iso:country":"YE",
    "name:ara_x_preferred":[
        "Az\u0327 Z\u0327\u0101hir\u012b"
    ],
    "name:ara_x_variant":[
        "\u0627\u0644\u0638\u0627\u0647\u0631\u0649"
    ],
    "qs:name":"Az\u0327 Z\u0327\u0101hir\u012b",
    "qs:photos_9r":0,
    "qs:photos_sr":0,
    "qs:pop_sr":"1",
    "wof:name":"Az\u0327 Z\u0327\u0101hir\u012b",
    "wof:placetype":"neighbourhood",
    "wof:population":15
},
  "geometry": {"coordinates":[43.70921,16.05004],"type":"Point"}
}