{
  "type": "Feature",
  "properties": {
    "gn:admin1_code":"23.0",
    "gn:admin2_code":"1101.0",
    "gn:asciiname":"Minka'ah",
    "gn:country_code":"YE",
    "gn:dem":1198,
    "gn:feature_class":"P",
    "gn:feature_code":"PPL",
    "gn:name":"Mink\u0101\u2018ah",
    "gn:population":0,
    "gn:timezone":"Asia/Aden",
    "iso:country":"YE",
    "name:ara_x_preferred":[
        "\u0645\u0646\u0643\u0627\u0639\u0629"
    ],
    "name:und_x_variant":[
        "Mink\u0101\u2018ah"
    ],
    "wof:name":"Minka'ah",
    "wof:placetype":"locality"
},
  "geometry": {"coordinates":[44.00157,14.29903],"type":"Point"}
}