{
  "type": "Feature",
  "properties": {
    "gn:admin1_code":"16.0",
    "gn:admin2_code":"2308.0",
    "gn:asciiname":"Bayt an Nashsh",
    "gn:country_code":"YE",
    "gn:dem":2986,
    "gn:feature_class":"P",
    "gn:feature_code":"PPL",
    "gn:name":"Bayt an Nashsh",
    "gn:population":0,
    "gn:timezone":"Asia/Aden",
    "iso:country":"YE",
    "wof:name":"Bayt an Nashsh",
    "wof:placetype":"locality"
},
  "geometry": {"coordinates":[43.9439,15.25899],"type":"Point"}
}