{
  "type": "Feature",
  "properties": {
    "gn:country":"YE",
    "gn:fcode":"PPL",
    "gn:pop":2,
    "iso:country":"YE",
    "name:ara_x_preferred":[
        "\u0627\u0644\u062d\u064a\u0641\u0629"
    ],
    "name:eng_x_preferred":[
        "Al Hayfah"
    ],
    "name:fas_x_preferred":[
        "\u0627\u0644 \u0647\u06cc\u0641\u0627\u0647"
    ],
    "name:nld_x_preferred":[
        "Al Hayfah"
    ],
    "name:nno_x_preferred":[
        "Al Hayfah"
    ],
    "qs:name":"Al \u1e28ayfah",
    "qs:photos_9r":0,
    "qs:photos_sr":0,
    "qs:pop_sr":"1",
    "wd:wordcount":23,
    "wof:name":"Al \u1e28ayfah",
    "wof:placetype":"locality",
    "wof:population":2
},
  "geometry": {"coordinates":[43.29286,16.52659],"type":"Point"}
}