{
  "type": "Feature",
  "properties": {
    "gn:admin1_code":"15.0",
    "gn:admin2_code":"2212.0",
    "gn:asciiname":"Al Quma' al Asfal",
    "gn:country_code":"YE",
    "gn:dem":1951,
    "gn:feature_class":"P",
    "gn:feature_code":"PPL",
    "gn:name":"Al Qum\u0101\u2019 al Asfal",
    "gn:population":0,
    "gn:timezone":"Asia/Aden",
    "iso:country":"YE",
    "name:ara_x_preferred":[
        "\u0627\u0644\u0642\u0645\u0627\u0621 \u0627\u0644\u0623\u0633\u0641\u0644"
    ],
    "name:und_x_variant":[
        "Al Qum\u0101\u2019 al Asfal"
    ],
    "wof:name":"Al Quma' al Asfal",
    "wof:placetype":"locality"
},
  "geometry": {"coordinates":[43.80613,16.84603],"type":"Point"}
}