{
  "type": "Feature",
  "properties": {
    "gn:admin1_code":"23.0",
    "gn:admin2_code":"1120.0",
    "gn:asciiname":"Qayhan",
    "gn:country_code":"YE",
    "gn:dem":2457,
    "gn:feature_class":"P",
    "gn:feature_code":"PPL",
    "gn:name":"Qay\u1e29\u0101n",
    "gn:population":0,
    "gn:timezone":"Asia/Aden",
    "iso:country":"YE",
    "name:und_x_variant":[
        "Qay\u1e29\u0101n"
    ],
    "wof:name":"Qayhan",
    "wof:placetype":"locality"
},
  "geometry": {"coordinates":[44.21539,13.99947],"type":"Point"}
}