{
  "type": "Feature",
  "properties": {
    "gn:admin1_code":"22.0",
    "gn:admin2_code":"1724.0",
    "gn:asciiname":"Mahall ash Shi`bah",
    "gn:country_code":"YE",
    "gn:dem":468,
    "gn:feature_class":"P",
    "gn:feature_code":"PPL",
    "gn:name":"Ma\u1e29all ash Shi\u2018bah",
    "gn:population":0,
    "gn:timezone":"Asia/Aden",
    "iso:country":"YE",
    "name:und_x_variant":[
        "Ma\u1e29all ash Shi\u2018bah"
    ],
    "wof:name":"Mahall ash Shi`bah",
    "wof:placetype":"locality"
},
  "geometry": {"coordinates":[43.40931,15.55778],"type":"Point"}
}