{
  "type": "Feature",
  "properties": {
    "gn:admin1_code":"25.0",
    "gn:admin2_code":"1517.0",
    "gn:asciiname":"Al Awhar",
    "gn:country_code":"YE",
    "gn:dem":1300,
    "gn:feature_class":"P",
    "gn:feature_code":"PPL",
    "gn:name":"Al Awhar",
    "gn:population":0,
    "gn:timezone":"Asia/Aden",
    "iso:country":"YE",
    "name:ara_x_preferred":[
        "\u0627\u0644\u0627\u0648\u0647\u0631"
    ],
    "wof:name":"Al Awhar",
    "wof:placetype":"locality"
},
  "geometry": {"coordinates":[44.20378,13.24787],"type":"Point"}
}