{
  "type": "Feature",
  "properties": {
    "gn:country":"YE",
    "gn:fcode":"HSE",
    "gn:pop":1,
    "iso:country":"YE",
    "name:ara_x_preferred":[
        "Dh\u016b Jur\u016bsh"
    ],
    "name:ara_x_variant":[
        "\u0630\u0648 \u062c\u0631\u0648\u0634"
    ],
    "qs:name":"Dh\u016b Jur\u016bsh",
    "qs:photos_9r":0,
    "qs:photos_sr":0,
    "qs:pop_sr":"1",
    "wof:name":"Dh\u016b Jur\u016bsh",
    "wof:placetype":"locality",
    "wof:population":1
},
  "geometry": {"coordinates":[44.06503,16.90899],"type":"Point"}
}