{
  "type": "Feature",
  "properties": {
    "gn:country":"YE",
    "gn:fcode":"PPL",
    "gn:population":8,
    "iso:country":"YE",
    "name:ara_x_preferred":[
        "\u063a\u0627\u0631\u0628 \u0627\u0644\u062c\u0647\u064a\u0631"
    ],
    "name:eng_x_preferred":[
        "Gharib Al Juhayr"
    ],
    "name:eng_x_variant":[
        "Ma\u1e29f\u0101r"
    ],
    "qs:name":"Gh\u0101rib al Juhayr",
    "qs:photos_9r":0,
    "qs:photos_sr":0,
    "qs:pop_sr":"1",
    "wof:name":"Gh\u0101rib al Juhayr",
    "wof:placetype":"locality",
    "wof:population":8
},
  "geometry": {"coordinates":[43.35374,16.73446],"type":"Point"}
}