{
  "type": "Feature",
  "properties": {
    "gn:admin1_code":"25.0",
    "gn:admin2_code":"1513.0",
    "gn:asciiname":"Najd al Jabal",
    "gn:country_code":"YE",
    "gn:dem":1469,
    "gn:feature_class":"P",
    "gn:feature_code":"PPL",
    "gn:name":"Najd al Jabal",
    "gn:population":0,
    "gn:timezone":"Asia/Aden",
    "iso:country":"YE",
    "wof:name":"Najd al Jabal",
    "wof:placetype":"locality"
},
  "geometry": {"coordinates":[44.1137,13.50719],"type":"Point"}
}