{
  "type": "Feature",
  "properties": {
    "gn:country":"YE",
    "gn:fcode":"PPL",
    "gn:population":3,
    "iso:country":"YE",
    "name:ara_x_preferred":[
        "Al \u2018Ash\u0101sh"
    ],
    "name:ara_x_variant":[
        "\u0627\u0644\u0639\u0634\u0627\u0634"
    ],
    "qs:name":"Al \u2018Ash\u0101sh",
    "qs:photos_9r":0,
    "qs:photos_sr":0,
    "qs:pop_sr":"1",
    "wof:name":"Al \u2018Ash\u0101sh",
    "wof:placetype":"locality",
    "wof:population":3
},
  "geometry": {"coordinates":[43.4043,16.36277],"type":"Point"}
}