{
  "type": "Feature",
  "properties": {
    "gn:admin1_code":"22.0",
    "gn:admin2_code":"1711.0",
    "gn:asciiname":"Kuhlan ash Sharaf",
    "gn:cc2":"YE",
    "gn:country_code":"YE",
    "gn:dem":599,
    "gn:feature_class":"P",
    "gn:feature_code":"PPL",
    "gn:name":"Ku\u1e29l\u0101n ash Sharaf",
    "gn:population":0,
    "gn:timezone":"Asia/Aden",
    "iso:country":"YE",
    "name:und_x_variant":[
        "Khillan al-Sharaf",
        "Ku\u1e29l\u0101n ash Sharaf"
    ],
    "wof:name":"Kuhlan ash Sharaf",
    "wof:placetype":"locality"
},
  "geometry": {"coordinates":[43.36667,16.08333],"type":"Point"}
}