{
  "type": "Feature",
  "properties": {
    "gn:admin1_code":"20.0",
    "gn:admin2_code":"1407.0",
    "gn:asciiname":"Sinwan",
    "gn:country_code":"YE",
    "gn:dem":1641,
    "gn:feature_class":"P",
    "gn:feature_code":"PPL",
    "gn:name":"Sinw\u0101n",
    "gn:population":0,
    "gn:timezone":"Asia/Aden",
    "iso:country":"YE",
    "name:ara_x_preferred":[
        "Sinw\u0101n"
    ],
    "wof:name":"Sinwan",
    "wof:placetype":"locality"
},
  "geometry": {"coordinates":[45.30594,14.08049],"type":"Point"}
}