{
  "type": "Feature",
  "properties": {
    "gn:admin1_code":"8.0",
    "gn:admin2_code":"1825.0",
    "gn:asciiname":"Sharij Birah",
    "gn:country_code":"YE",
    "gn:dem":99,
    "gn:feature_class":"P",
    "gn:feature_code":"PPL",
    "gn:name":"Shar\u012bj B\u012brah",
    "gn:population":0,
    "gn:timezone":"Asia/Aden",
    "iso:country":"YE",
    "name:und_x_variant":[
        "Shar\u012bj B\u012brah"
    ],
    "wof:name":"Sharij Birah",
    "wof:placetype":"locality"
},
  "geometry": {"coordinates":[43.29687,14.14461],"type":"Point"}
}