{
  "type": "Feature",
  "properties": {
    "gn:admin1_code":"15.0",
    "gn:admin2_code":"2208.0",
    "gn:asciiname":"Jurna'im",
    "gn:country_code":"YE",
    "gn:dem":1059,
    "gn:feature_class":"P",
    "gn:feature_code":"PPL",
    "gn:name":"Jurna\u2018\u012bm",
    "gn:population":0,
    "gn:timezone":"Asia/Aden",
    "iso:country":"YE",
    "name:ara_x_preferred":[
        "\u062c\u0631\u0646\u0639\u064a\u0645"
    ],
    "name:und_x_variant":[
        "Jurna\u2018\u012bm"
    ],
    "wof:name":"Jurna'im",
    "wof:placetype":"locality"
},
  "geometry": {"coordinates":[43.31791,16.73565],"type":"Point"}
}