{
  "type": "Feature",
  "properties": {
    "gn:admin1_code":"11.0",
    "gn:admin2_code":"2007.0",
    "gn:asciiname":"Kurash",
    "gn:country_code":"YE",
    "gn:dem":822,
    "gn:feature_class":"P",
    "gn:feature_code":"PPL",
    "gn:name":"Kur\u0101sh",
    "gn:population":0,
    "gn:timezone":"Asia/Aden",
    "iso:country":"YE",
    "name:ara_x_preferred":[
        "Kur\u0101sh"
    ],
    "wof:name":"Kurash",
    "wof:placetype":"locality"
},
  "geometry": {"coordinates":[43.64391,14.30887],"type":"Point"}
}