{
  "type": "Feature",
  "properties": {
    "gn:admin1_code":"8.0",
    "gn:admin2_code":"1817.0",
    "gn:asciiname":"Al Jah",
    "gn:cc2":"YE",
    "gn:country_code":"YE",
    "gn:dem":19,
    "gn:feature_class":"P",
    "gn:feature_code":"PPL",
    "gn:name":"Al J\u0101\u1e29",
    "gn:population":0,
    "gn:timezone":"Asia/Aden",
    "iso:country":"YE",
    "name:ara_x_preferred":[
        "Al J\u0101\u1e29"
    ],
    "name:und_x_variant":[
        "Ah Gah",
        "Al Gah",
        "J\u0101h",
        "Al Q\u0101\u2018",
        "Gah",
        "Jab"
    ],
    "wof:name":"Al Jah",
    "wof:placetype":"locality"
},
  "geometry": {"coordinates":[43.06667,14.28333],"type":"Point"}
}