{
  "type": "Feature",
  "properties": {
    "gn:admin1_code":"20.0",
    "gn:admin2_code":"1416.0",
    "gn:asciiname":"`Azzan",
    "gn:country_code":"YE",
    "gn:dem":2237,
    "gn:feature_class":"P",
    "gn:feature_code":"PPL",
    "gn:name":"\u2018Azz\u0101n",
    "gn:population":0,
    "gn:timezone":"Asia/Aden",
    "iso:country":"YE",
    "name:ara_x_preferred":[
        "\u2018Azz\u0101n"
    ],
    "name:ara_x_variant":[
        "\u0639\u0632\u0627\u0646"
    ],
    "name:und_x_variant":[
        "\u2018Iz\u0101n"
    ],
    "wof:name":"`Azzan",
    "wof:placetype":"locality"
},
  "geometry": {"coordinates":[44.75617,14.3986],"type":"Point"}
}