{
  "type": "Feature",
  "properties": {
    "gn:admin1_code":"16.0",
    "gn:admin2_code":"2313.0",
    "gn:asciiname":"Shahik",
    "gn:country_code":"YE",
    "gn:dem":2571,
    "gn:feature_class":"P",
    "gn:feature_code":"PPL",
    "gn:name":"Sh\u0101\u1e29ik",
    "gn:population":0,
    "gn:timezone":"Asia/Aden",
    "iso:country":"YE",
    "name:ara_x_preferred":[
        "Sh\u0101\u1e29ik"
    ],
    "name:fas_x_preferred":[
        "\u0634\u0627\u0647\u06cc\u06a9"
    ],
    "wof:name":"Shahik",
    "wof:placetype":"locality"
},
  "geometry": {"coordinates":[44.42465,15.39561],"type":"Point"}
}