{
  "type": "Feature",
  "properties": {
    "gn:country":"YE",
    "gn:fcode":"PPL",
    "gn:population":3,
    "iso:country":"YE",
    "name:ara_x_preferred":[
        "\u0100l Ni\u015f\u0101r"
    ],
    "name:ara_x_variant":[
        "\u0627\u0644 \u0646\u0635\u0627\u0631"
    ],
    "qs:name":"\u0100l Ni\u015f\u0101r",
    "qs:photos_9r":0,
    "qs:photos_sr":0,
    "qs:pop_sr":"1",
    "wof:name":"\u0100l Ni\u015f\u0101r",
    "wof:placetype":"locality",
    "wof:population":3
},
  "geometry": {"coordinates":[43.37552,16.85281],"type":"Point"}
}