{
  "type": "Feature",
  "properties": {
    "gn:admin1_code":"16.0",
    "gn:admin2_code":"2313.0",
    "gn:asciiname":"Al Ghaylin",
    "gn:country_code":"YE",
    "gn:dem":2525,
    "gn:feature_class":"P",
    "gn:feature_code":"PPL",
    "gn:name":"Al Ghayl\u012bn",
    "gn:population":0,
    "gn:timezone":"Asia/Aden",
    "iso:country":"YE",
    "name:ara_x_preferred":[
        "\u0627\u0644\u063a\u064a\u0644\u064a\u0646"
    ],
    "name:und_x_variant":[
        "Al Ghayl\u012bn"
    ],
    "wof:name":"Al Ghaylin",
    "wof:placetype":"locality"
},
  "geometry": {"coordinates":[44.66391,15.38889],"type":"Point"}
}