{
  "type": "Feature",
  "properties": {
    "gn:country":"YE",
    "gn:fcode":"PPL",
    "gn:population":64,
    "iso:country":"YE",
    "name:ara_x_preferred":[
        "\u0645\u062d\u0644 \u0627\u0644\u063a\u0627\u0632\u064a"
    ],
    "name:eng_x_preferred":[
        "Mahal Al Ghazi"
    ],
    "name:eng_x_variant":[
        "\u2018Awaq al \u2018Al\u0101mah"
    ],
    "name:und_x_variant":[
        "Ma\u1e29all al Gh\u0101z\u012b"
    ],
    "qs:name":"Ma\u1e29al al Gh\u0101z\u012b",
    "qs:photos_9r":0,
    "qs:photos_sr":0,
    "qs:pop_sr":"1",
    "wof:name":"Ma\u1e29al al Gh\u0101z\u012b",
    "wof:placetype":"locality",
    "wof:population":64
},
  "geometry": {"coordinates":[43.1906,16.00274],"type":"Point"}
}