{
  "type": "Feature",
  "properties": {
    "gn:admin1_code":"25.0",
    "gn:admin2_code":"1502.0",
    "gn:asciiname":"As Sufi",
    "gn:country_code":"YE",
    "gn:dem":1328,
    "gn:feature_class":"P",
    "gn:feature_code":"PPL",
    "gn:name":"A\u015f \u015e\u016bf\u012b",
    "gn:population":0,
    "gn:timezone":"Asia/Aden",
    "iso:country":"YE",
    "name:ara_x_preferred":[
        "A\u015f \u015e\u016bf\u012b"
    ],
    "wof:name":"As Sufi",
    "wof:placetype":"locality"
},
  "geometry": {"coordinates":[44.05849,13.64333],"type":"Point"}
}