{
  "type": "Feature",
  "properties": {
    "gn:admin1_code":"18.0",
    "gn:admin2_code":"3002.0",
    "gn:asciiname":"Talibah",
    "gn:country_code":"YE",
    "gn:dem":2347,
    "gn:feature_class":"P",
    "gn:feature_code":"PPL",
    "gn:name":"T\u0101libah",
    "gn:population":0,
    "gn:timezone":"Asia/Aden",
    "iso:country":"YE",
    "name:ara_x_preferred":[
        "\u062a\u0627\u0644\u0628\u0629"
    ],
    "name:und_x_variant":[
        "Ta\u2019labah",
        "T\u0101libah"
    ],
    "wof:name":"Talibah",
    "wof:placetype":"locality"
},
  "geometry": {"coordinates":[44.63489000000001,14.03083],"type":"Point"}
}