{
  "type": "Feature",
  "properties": {
    "gn:admin1_code":"3.0",
    "gn:asciiname":"Hawf",
    "gn:country_code":"YE",
    "gn:dem":17,
    "gn:feature_class":"P",
    "gn:feature_code":"PPLA2",
    "gn:name":"\u1e28awf",
    "gn:population":0,
    "gn:timezone":"Asia/Aden",
    "iso:country":"YE",
    "name:ara_x_preferred":[
        "\u062d\u0648\u0641"
    ],
    "name:und_x_variant":[
        "Hauf",
        "\u1e28awf"
    ],
    "wof:name":"Hawf",
    "wof:placetype":"locality"
},
  "geometry": {"coordinates":[53.03368,16.63383],"type":"Point"}
}