{
  "type": "Feature",
  "properties": {
    "gn:admin1_code":"15.0",
    "gn:admin2_code":"2212.0",
    "gn:asciiname":"Rahwan",
    "gn:country_code":"YE",
    "gn:dem":1784,
    "gn:feature_class":"P",
    "gn:feature_code":"PPL",
    "gn:name":"Rahw\u0101n",
    "gn:population":0,
    "gn:timezone":"Asia/Aden",
    "iso:country":"YE",
    "name:nno_x_preferred":[
        "Rahwan"
    ],
    "name:und_x_variant":[
        "Rahw\u0101n"
    ],
    "wof:name":"Rahwan",
    "wof:placetype":"locality"
},
  "geometry": {"coordinates":[43.79600000000001,17.12084],"type":"Point"}
}