{
  "type": "Feature",
  "properties": {
    "gn:country":"YE",
    "gn:fcode":"PPL",
    "gn:population":9,
    "iso:country":"YE",
    "name:ara_x_preferred":[
        "\u0627\u0644\u062f\u0645\u0646"
    ],
    "qs:name":"Ad Dammin",
    "qs:photos_9r":0,
    "qs:photos_sr":0,
    "qs:pop_sr":"1",
    "wof:name":"Ad Dammin",
    "wof:placetype":"locality",
    "wof:population":9
},
  "geometry": {"coordinates":[43.23352,16.28899],"type":"Point"}
}