{
  "type": "Feature",
  "properties": {
    "gn:admin1_code":"26.0",
    "gn:admin2_code":"1310.0",
    "gn:asciiname":"Bayt Surrah",
    "gn:country_code":"YE",
    "gn:dem":2156,
    "gn:feature_class":"P",
    "gn:feature_code":"PPL",
    "gn:name":"Bayt Surrah",
    "gn:population":0,
    "gn:timezone":"Asia/Aden",
    "iso:country":"YE",
    "name:ara_x_preferred":[
        "\u0628\u064a\u062a \u0633\u0631\u0629"
    ],
    "name:und_x_variant":[
        "Bayt Sirrah",
        "Bayt Surrah",
        "Bayt Sarrah"
    ],
    "wof:name":"Bayt Surrah",
    "wof:placetype":"locality"
},
  "geometry": {"coordinates":[44.24733,15.55332],"type":"Point"}
}