{
  "type": "Feature",
  "properties": {
    "gn:country":"YE",
    "gn:fcode":"PPLX",
    "gn:population":26,
    "iso:country":"YE",
    "name:ara_x_preferred":[
        "\u0100l Durj\u0101n"
    ],
    "name:ara_x_variant":[
        "\u0627\u0644 \u062f\u0631\u062c\u0627\u0646"
    ],
    "qs:name":"\u0100l Durj\u0101n",
    "qs:photos_9r":0,
    "qs:photos_sr":0,
    "qs:pop_sr":"1",
    "wof:name":"\u0100l Durj\u0101n",
    "wof:placetype":"neighbourhood",
    "wof:population":26
},
  "geometry": {"coordinates":[44.4346,16.75016],"type":"Point"}
}