{
  "type": "Feature",
  "properties": {
    "gn:admin1_code":"16.0",
    "gn:admin2_code":"2302.0",
    "gn:asciiname":"Bayt Ramadan",
    "gn:country_code":"YE",
    "gn:dem":2632,
    "gn:feature_class":"P",
    "gn:feature_code":"PPL",
    "gn:name":"Bayt Rama\u1e11\u0101n",
    "gn:population":0,
    "gn:timezone":"Asia/Aden",
    "iso:country":"YE",
    "name:ara_x_preferred":[
        "\u0628\u064a\u062a \u0631\u0645\u0636\u0627\u0646"
    ],
    "name:und_x_variant":[
        "Bayt Rama\u1e11\u0101n"
    ],
    "wof:name":"Bayt Ramadan",
    "wof:placetype":"locality"
},
  "geometry": {"coordinates":[44.1825,15.85609],"type":"Point"}
}