{
  "type": "Feature",
  "properties": {
    "gn:admin1_code":"20.0",
    "gn:admin2_code":"1411.0",
    "gn:asciiname":"Al Matrad",
    "gn:country_code":"YE",
    "gn:dem":2036,
    "gn:feature_class":"P",
    "gn:feature_code":"PPL",
    "gn:name":"Al Ma\u0163rad",
    "gn:population":0,
    "gn:timezone":"Asia/Aden",
    "iso:country":"YE",
    "name:und_x_variant":[
        "Al Ma\u0163rad"
    ],
    "wof:name":"Al Matrad",
    "wof:placetype":"locality"
},
  "geometry": {"coordinates":[45.36667,14.46667],"type":"Point"}
}