{
  "type": "Feature",
  "properties": {
    "gn:admin1_code":"23.0",
    "gn:admin2_code":"1110.0",
    "gn:asciiname":"Al Madad",
    "gn:country_code":"YE",
    "gn:dem":1524,
    "gn:feature_class":"P",
    "gn:feature_code":"PPL",
    "gn:name":"Al Mad\u0101d",
    "gn:population":0,
    "gn:timezone":"Asia/Aden",
    "iso:country":"YE",
    "name:ara_x_preferred":[
        "\u0627\u0644\u0645\u062f\u0627\u0631"
    ],
    "name:und_x_variant":[
        "Al Mad\u0101d",
        "Al Mad\u0101r"
    ],
    "wof:name":"Al Madad",
    "wof:placetype":"locality"
},
  "geometry": {"coordinates":[43.83723,13.93488],"type":"Point"}
}