{
  "type": "Feature",
  "properties": {
    "gn:admin1_code":"8.0",
    "gn:admin2_code":"1814.0",
    "gn:asciiname":"Bayt 'Ali Hasan Hibah",
    "gn:country_code":"YE",
    "gn:dem":20,
    "gn:feature_class":"P",
    "gn:feature_code":"PPL",
    "gn:name":"Bayt \u2018Al\u012b \u1e28asan Hibah",
    "gn:population":0,
    "gn:timezone":"Asia/Aden",
    "iso:country":"YE",
    "name:ara_x_preferred":[
        "\u0628\u064a\u062a \u0639\u0644\u064a \u062d\u0633\u0646 \u0647\u0628\u0629"
    ],
    "name:und_x_variant":[
        "Bayt \u2018Al\u012b \u1e28asan Hibah"
    ],
    "wof:name":"Bayt 'Ali Hasan Hibah",
    "wof:placetype":"locality"
},
  "geometry": {"coordinates":[43.01919,14.71853],"type":"Point"}
}