{
  "type": "Feature",
  "properties": {
    "gn:admin1_code":"16.0",
    "gn:admin2_code":"2308.0",
    "gn:asciiname":"Bayt Li`li`",
    "gn:country_code":"YE",
    "gn:dem":2234,
    "gn:feature_class":"P",
    "gn:feature_code":"PPL",
    "gn:name":"Bayt Li\u2018li\u2018",
    "gn:population":0,
    "gn:timezone":"Asia/Aden",
    "iso:country":"YE",
    "name:und_x_variant":[
        "Bayt Li\u2018li\u2018"
    ],
    "wof:name":"Bayt Li`li`",
    "wof:placetype":"locality"
},
  "geometry": {"coordinates":[43.92001,15.24914],"type":"Point"}
}