{
  "type": "Feature",
  "properties": {
    "gn:country":"YE",
    "gn:fcode":"PPL",
    "gn:population":6,
    "iso:country":"YE",
    "name:ara_x_preferred":[
        "B\u012br R\u0101shid"
    ],
    "name:ara_x_variant":[
        "\u0628\u064a\u0631 \u0631\u0627\u0634\u062f"
    ],
    "qs:name":"B\u012br R\u0101shid",
    "qs:photos_9r":0,
    "qs:photos_sr":0,
    "qs:pop_sr":"1",
    "wof:name":"B\u012br R\u0101shid",
    "wof:placetype":"locality",
    "wof:population":6
},
  "geometry": {"coordinates":[43.98132,16.71096],"type":"Point"}
}