{
  "type": "Feature",
  "properties": {
    "gn:admin1_code":"25.0",
    "gn:admin2_code":"1502.0",
    "gn:asciiname":"Al Huruf",
    "gn:country_code":"YE",
    "gn:dem":987,
    "gn:feature_class":"P",
    "gn:feature_code":"PPL",
    "gn:name":"Al \u1e28ur\u016bf",
    "gn:population":0,
    "gn:timezone":"Asia/Aden",
    "iso:country":"YE",
    "name:ara_x_preferred":[
        "Al \u1e28ur\u016bf"
    ],
    "name:ara_x_variant":[
        "\u0627\u0644\u062d\u0631\u0648\u0641"
    ],
    "wof:name":"Al Huruf",
    "wof:placetype":"locality"
},
  "geometry": {"coordinates":[43.88548,13.64121],"type":"Point"}
}