{
  "type": "Feature",
  "properties": {
    "gn:admin1_code":"16.0",
    "gn:admin2_code":"2312.0",
    "gn:asciiname":"Burj Bani Hilal",
    "gn:country_code":"YE",
    "gn:dem":1942,
    "gn:feature_class":"P",
    "gn:feature_code":"PPL",
    "gn:name":"Burj Ban\u012b Hil\u0101l",
    "gn:population":0,
    "gn:timezone":"Asia/Aden",
    "iso:country":"YE",
    "name:ara_x_preferred":[
        "\u0628\u0631\u062c \u0628\u0646\u064a \u0647\u0644\u0627\u0644"
    ],
    "name:und_x_variant":[
        "Burj Ban\u012b Hil\u0101l"
    ],
    "wof:name":"Burj Bani Hilal",
    "wof:placetype":"locality"
},
  "geometry": {"coordinates":[44.71987,15.18184],"type":"Point"}
}