{
  "type": "Feature",
  "properties": {
    "gn:admin1_code":"23.0",
    "gn:admin2_code":"1111.0",
    "gn:asciiname":"Qasil",
    "gn:country_code":"YE",
    "gn:dem":1554,
    "gn:feature_class":"P",
    "gn:feature_code":"PPL",
    "gn:name":"Qa\u015fil",
    "gn:population":0,
    "gn:timezone":"Asia/Aden",
    "iso:country":"YE",
    "name:und_x_variant":[
        "Qa\u015fil"
    ],
    "wof:name":"Qasil",
    "wof:placetype":"locality"
},
  "geometry": {"coordinates":[43.87337,13.99735],"type":"Point"}
}