{
  "type": "Feature",
  "properties": {
    "gn:admin1_code":"16.0",
    "gn:admin2_code":"2314.0",
    "gn:asciiname":"Di``am",
    "gn:country_code":"YE",
    "gn:dem":2182,
    "gn:feature_class":"P",
    "gn:feature_code":"PPL",
    "gn:name":"Di\u2018\u2018\u0101m",
    "gn:population":0,
    "gn:timezone":"Asia/Aden",
    "iso:country":"YE",
    "name:ara_x_preferred":[
        "Di\u2018\u2018\u0101m"
    ],
    "wof:name":"Di``am",
    "wof:placetype":"locality"
},
  "geometry": {"coordinates":[44.8557,15.08176],"type":"Point"}
}