{
  "type": "Feature",
  "properties": {
    "gn:admin1_code":"16.0",
    "gn:admin2_code":"2312.0",
    "gn:asciiname":"Al Fadaya",
    "gn:country_code":"YE",
    "gn:dem":2224,
    "gn:feature_class":"P",
    "gn:feature_code":"PPL",
    "gn:name":"Al Fa\u1e11\u0101y\u0101",
    "gn:population":0,
    "gn:timezone":"Asia/Aden",
    "iso:country":"YE",
    "name:und_x_variant":[
        "Al Fa\u1e11\u0101y\u0101"
    ],
    "wof:name":"Al Fadaya",
    "wof:placetype":"locality"
},
  "geometry": {"coordinates":[44.68494000000001,15.34475],"type":"Point"}
}