{
  "type": "Feature",
  "properties": {
    "gn:admin1_code":"4.0",
    "gn:admin2_code":"1929.0",
    "gn:asciiname":"Ar Rukayb",
    "gn:cc2":"YE",
    "gn:country_code":"YE",
    "gn:dem":3,
    "gn:feature_class":"P",
    "gn:feature_code":"PPL",
    "gn:name":"Ar Rukayb",
    "gn:population":0,
    "gn:timezone":"Asia/Aden",
    "iso:country":"YE",
    "name:und_x_variant":[
        "Rukub",
        "Al-Rukaib",
        "Ar Rukaib",
        "Ar Rukayb"
    ],
    "wof:name":"Ar Rukayb",
    "wof:placetype":"locality"
},
  "geometry": {"coordinates":[49.20972,14.56889],"type":"Point"}
}