{
  "type": "Feature",
  "properties": {
    "gn:gn_country":"YE",
    "gn:gn_fcode":"PPL",
    "gn:gn_pop":16,
    "gn:population":16,
    "iso:country":"YE",
    "name:ara_x_preferred":[
        "\u0645\u0639\u062c\u0645"
    ],
    "name:eng_x_preferred":[
        "Ma'jim"
    ],
    "qs_pg:aaroncc":"YE",
    "qs_pg:gn_country":"YE",
    "qs_pg:gn_fcode":"PPL",
    "qs_pg:gn_pop":16,
    "qs_pg:name":"Ma\u2018jim",
    "qs_pg:photos_9r":0,
    "qs_pg:photos_sr":0,
    "qs_pg:pop_sr":1,
    "qs_pg:qs_pg_placetype":"locality",
    "wof:name":"Ma\u2018jim",
    "wof:placetype":"locality",
    "wof:population":16
},
  "geometry": {"coordinates":[43.02232,16.45361],"type":"Point"}
}