{
  "type": "Feature",
  "properties": {
    "gn:admin1_code":"25.0",
    "gn:admin2_code":"1522.0",
    "gn:asciiname":"Al Mukayshah",
    "gn:country_code":"YE",
    "gn:dem":1582,
    "gn:feature_class":"P",
    "gn:feature_code":"PPL",
    "gn:name":"Al Mukayshah",
    "gn:population":0,
    "gn:timezone":"Asia/Aden",
    "iso:country":"YE",
    "wof:name":"Al Mukayshah",
    "wof:placetype":"locality"
},
  "geometry": {"coordinates":[44.15825,13.27163],"type":"Point"}
}