{
  "type": "Feature",
  "properties": {
    "gn:admin1_code":"16.0",
    "gn:admin2_code":"2303.0",
    "gn:asciiname":"Al Ma'amir",
    "gn:country_code":"YE",
    "gn:dem":2043,
    "gn:feature_class":"P",
    "gn:feature_code":"PPLL",
    "gn:name":"Al Ma\u2018\u0101mir",
    "gn:population":0,
    "gn:timezone":"Asia/Aden",
    "iso:country":"YE",
    "name:ara_x_preferred":[
        "\u0627\u0644\u0645\u0639\u0627\u0645\u0631"
    ],
    "name:und_x_variant":[
        "Al Ma\u2018\u0101mir"
    ],
    "wof:name":"Al Ma'amir",
    "wof:placetype":"locality"
},
  "geometry": {"coordinates":[44.42177,15.73256],"type":"Point"}
}