{
  "type": "Feature",
  "properties": {
    "gn:admin1_code":"15.0",
    "gn:admin2_code":"2208.0",
    "gn:asciiname":"Alt Maysir",
    "gn:country_code":"YE",
    "gn:dem":2354,
    "gn:feature_class":"P",
    "gn:feature_code":"PPL",
    "gn:name":"Alt Maysir",
    "gn:population":0,
    "gn:timezone":"Asia/Aden",
    "iso:country":"YE",
    "name:ara_x_preferred":[
        "\u0627\u0644\u062a \u0645\u064a\u0633\u0631"
    ],
    "wof:name":"Alt Maysir",
    "wof:placetype":"locality"
},
  "geometry": {"coordinates":[43.48225,16.77356],"type":"Point"}
}