{
  "type": "Feature",
  "properties": {
    "gn:admin1_code":"22.0",
    "gn:admin2_code":"1711.0",
    "gn:asciiname":"Aslam",
    "gn:country_code":"YE",
    "gn:dem":452,
    "gn:feature_class":"P",
    "gn:feature_code":"PPL",
    "gn:name":"Aslam",
    "gn:population":0,
    "gn:timezone":"Asia/Aden",
    "iso:country":"YE",
    "name:ara_x_preferred":[
        "\u0623\u0633\u0644\u0645"
    ],
    "name:ara_x_variant":[
        "\u0627\u0633\u0644\u0645"
    ],
    "name:ceb_x_preferred":[
        "Aslam"
    ],
    "name:deu_x_preferred":[
        "Aslam"
    ],
    "wof:name":"Aslam",
    "wof:placetype":"locality"
},
  "geometry": {"coordinates":[43.29413,16.14614],"type":"Point"}
}