{
  "type": "Feature",
  "properties": {
    "gn:admin1_code":"25.0",
    "gn:admin2_code":"1504.0",
    "gn:asciiname":"Al `Amarah",
    "gn:country_code":"YE",
    "gn:dem":1224,
    "gn:feature_class":"P",
    "gn:feature_code":"PPL",
    "gn:name":"Al \u2018Amarah",
    "gn:population":0,
    "gn:timezone":"Asia/Aden",
    "iso:country":"YE",
    "name:ara_x_preferred":[
        "\u0627\u0644\u0639\u0645\u0631\u0629"
    ],
    "name:und_x_variant":[
        "Al \u2018Amarah",
        "Al \u2018Umrah"
    ],
    "wof:name":"Al `Amarah",
    "wof:placetype":"locality"
},
  "geometry": {"coordinates":[43.78754,13.68875],"type":"Point"}
}