{
  "type": "Feature",
  "properties": {
    "gn:admin1_code":"19.0",
    "gn:admin2_code":"2912.0",
    "gn:asciiname":"Bayt Ghaythan",
    "gn:country_code":"YE",
    "gn:dem":2821,
    "gn:feature_class":"P",
    "gn:feature_code":"PPL",
    "gn:name":"Bayt Ghayth\u0101n",
    "gn:population":0,
    "gn:timezone":"Asia/Aden",
    "iso:country":"YE",
    "name:und_x_variant":[
        "Bayt Ghayth\u0101n"
    ],
    "wof:name":"Bayt Ghaythan",
    "wof:placetype":"locality"
},
  "geometry": {"coordinates":[43.79508,15.69718],"type":"Point"}
}