{
  "type": "Feature",
  "properties": {
    "gn:admin1_code":"19.0",
    "gn:admin2_code":"2920.0",
    "gn:asciiname":"Bayt Rakb",
    "gn:country_code":"YE",
    "gn:dem":2323,
    "gn:feature_class":"P",
    "gn:feature_code":"PPL",
    "gn:name":"Bayt Rakb",
    "gn:population":0,
    "gn:timezone":"Asia/Aden",
    "iso:country":"YE",
    "name:ara_x_preferred":[
        "\u0628\u064a\u062a \u0631\u0643\u0628"
    ],
    "wof:name":"Bayt Rakb",
    "wof:placetype":"locality"
},
  "geometry": {"coordinates":[43.95652000000001,16.06425],"type":"Point"}
}