{
  "type": "Feature",
  "properties": {
    "gn:admin1_code":"22.0",
    "gn:admin2_code":"1722.0",
    "gn:asciiname":"Al Madahijah",
    "gn:country_code":"YE",
    "gn:dem":266,
    "gn:feature_class":"P",
    "gn:feature_code":"PPL",
    "gn:name":"Al Mad\u0101\u1e29ijah",
    "gn:population":0,
    "gn:timezone":"Asia/Aden",
    "iso:country":"YE",
    "name:und_x_variant":[
        "Al Mad\u0101\u1e29ijah"
    ],
    "wof:name":"Al Madahijah",
    "wof:placetype":"locality"
},
  "geometry": {"coordinates":[43.26603,15.8621],"type":"Point"}
}