{
  "type": "Feature",
  "properties": {
    "gn:admin1_code":"11.0",
    "gn:admin2_code":"2001.0",
    "gn:asciiname":"Bani Aslam",
    "gn:country_code":"YE",
    "gn:dem":2139,
    "gn:feature_class":"P",
    "gn:feature_code":"PPL",
    "gn:name":"Ban\u012b Aslam",
    "gn:population":0,
    "gn:timezone":"Asia/Aden",
    "iso:country":"YE",
    "name:ara_x_preferred":[
        "\u0628\u0646\u064a \u0623\u0633\u0644\u0645"
    ],
    "name:und_x_variant":[
        "Ban\u012b Aslam"
    ],
    "wof:name":"Bani Aslam",
    "wof:placetype":"locality"
},
  "geometry": {"coordinates":[44.65089,14.76602],"type":"Point"}
}