{
  "type": "Feature",
  "properties": {
    "gn:admin1_code":"25.0",
    "gn:admin2_code":"1511.0",
    "gn:asciiname":"Shi`b al Mawadim",
    "gn:country_code":"YE",
    "gn:dem":2256,
    "gn:feature_class":"P",
    "gn:feature_code":"PPL",
    "gn:name":"Shi\u2018b al Maw\u0101dim",
    "gn:population":0,
    "gn:timezone":"Asia/Aden",
    "iso:country":"YE",
    "name:und_x_variant":[
        "Shi\u2018b al Maw\u0101dim"
    ],
    "wof:name":"Shi`b al Mawadim",
    "wof:placetype":"locality"
},
  "geometry": {"coordinates":[44.02131,13.54735],"type":"Point"}
}