{
  "type": "Feature",
  "properties": {
    "gn:country":"YE",
    "gn:fcode":"PPL",
    "gn:population":2,
    "iso:country":"YE",
    "name:ara_x_preferred":[
        "\u0645\u0627\u062e\u0631 \u0627\u0644\u0642\u064a\u0645\u0629"
    ],
    "name:eng_x_preferred":[
        "Makhir Al Qimah"
    ],
    "name:eng_x_variant":[
        "A\u015f \u015earw"
    ],
    "qs:name":"Makhir al Q\u012bmah",
    "qs:photos_9r":0,
    "qs:photos_sr":0,
    "qs:pop_sr":"1",
    "wof:name":"Makhir al Q\u012bmah",
    "wof:placetype":"locality",
    "wof:population":2
},
  "geometry": {"coordinates":[43.38255,16.31976],"type":"Point"}
}