{
  "type": "Feature",
  "properties": {
    "gn:admin1_code":"4.0",
    "gn:admin2_code":"1925.0",
    "gn:asciiname":"Al Bayda'",
    "gn:country_code":"YE",
    "gn:dem":97,
    "gn:feature_class":"P",
    "gn:feature_code":"PPL",
    "gn:name":"Al Bay\u1e11\u0101\u2019",
    "gn:population":0,
    "gn:timezone":"Asia/Aden",
    "iso:country":"YE",
    "name:und_x_variant":[
        "Al-Baida",
        "Al Bay\u1e11\u0101\u2019"
    ],
    "wof:name":"Al Bayda'",
    "wof:placetype":"locality"
},
  "geometry": {"coordinates":[48.78222,14.24361],"type":"Point"}
}