{
  "type": "Feature",
  "properties": {
    "gn:admin1_code":"23.0",
    "gn:admin2_code":"1112.0",
    "gn:asciiname":"`Arib",
    "gn:country_code":"YE",
    "gn:dem":1935,
    "gn:feature_class":"P",
    "gn:feature_code":"PPL",
    "gn:name":"\u2018Ar\u012bb",
    "gn:population":0,
    "gn:timezone":"Asia/Aden",
    "iso:country":"YE",
    "name:ara_x_preferred":[
        "\u2018Ar\u012bb"
    ],
    "wof:name":"`Arib",
    "wof:placetype":"locality"
},
  "geometry": {"coordinates":[44.16998,13.92702],"type":"Point"}
}