{
  "type": "Feature",
  "properties": {
    "gn:admin1_code":"8.0",
    "gn:admin2_code":"1819.0",
    "gn:asciiname":"Ad Duraybah",
    "gn:country_code":"YE",
    "gn:dem":233,
    "gn:feature_class":"P",
    "gn:feature_code":"PPL",
    "gn:name":"A\u1e11 \u1e10uraybah",
    "gn:population":0,
    "gn:timezone":"Asia/Aden",
    "iso:country":"YE",
    "name:und_x_variant":[
        "A\u1e11 \u1e10uraybah"
    ],
    "wof:name":"Ad Duraybah",
    "wof:placetype":"locality"
},
  "geometry": {"coordinates":[43.52151,13.97876],"type":"Point"}
}