{
  "type": "Feature",
  "properties": {
    "gn:admin1_code":"23.0",
    "gn:admin2_code":"1115.0",
    "gn:asciiname":"Dhil Habar",
    "gn:country_code":"YE",
    "gn:dem":2138,
    "gn:feature_class":"P",
    "gn:feature_code":"PPL",
    "gn:name":"Dhil \u1e28abar",
    "gn:population":0,
    "gn:timezone":"Asia/Aden",
    "iso:country":"YE",
    "name:und_x_variant":[
        "Dhil \u1e28abar"
    ],
    "wof:name":"Dhil Habar",
    "wof:placetype":"locality"
},
  "geometry": {"coordinates":[44.22982,13.8537],"type":"Point"}
}