{
  "type": "Feature",
  "properties": {
    "gn:admin1_code":"28.0",
    "gn:admin2_code":"1927.0",
    "gn:asciiname":"Bi'r al 'Ajuz",
    "gn:country_code":"YE",
    "gn:dem":11,
    "gn:feature_class":"P",
    "gn:feature_code":"PPL",
    "gn:name":"Bi\u2019r al \u2018Aj\u016bz",
    "gn:population":0,
    "gn:timezone":"Asia/Aden",
    "iso:country":"YE",
    "wof:name":"Bi'r al 'Ajuz",
    "wof:placetype":"locality"
},
  "geometry": {"coordinates":[52.31039000000001,12.1845],"type":"Point"}
}