{
  "type": "Feature",
  "properties": {
    "gn:admin1_code":"21.0",
    "gn:admin2_code":"1611.0",
    "gn:asciiname":"Al Maj`alah",
    "gn:country_code":"YE",
    "gn:dem":1964,
    "gn:feature_class":"P",
    "gn:feature_code":"PPL",
    "gn:name":"Al Maj\u2018alah",
    "gn:population":0,
    "gn:timezone":"Asia/Aden",
    "iso:country":"YE",
    "name:und_x_variant":[
        "Al Maj\u2018alah"
    ],
    "wof:name":"Al Maj`alah",
    "wof:placetype":"locality"
},
  "geometry": {"coordinates":[44.39414,16.64127],"type":"Point"}
}