{
  "type": "Feature",
  "properties": {
    "gn:admin1_code":"24.0",
    "gn:admin2_code":"2506.0",
    "gn:asciiname":"Habil ar Raydah",
    "gn:country_code":"YE",
    "gn:dem":944,
    "gn:feature_class":"P",
    "gn:feature_code":"PPLA2",
    "gn:name":"\u1e28ab\u012bl ar Raydah",
    "gn:population":0,
    "gn:timezone":"Asia/Aden",
    "iso:country":"YE",
    "name:ara_x_preferred":[
        "\u062d\u0628\u064a\u0644 \u0627\u0644\u0631\u064a\u062f\u0629"
    ],
    "name:und_x_variant":[
        "\u1e28ab\u012bl ar Raydah"
    ],
    "wof:name":"Habil ar Raydah",
    "wof:placetype":"locality"
},
  "geometry": {"coordinates":[44.85097,13.6444],"type":"Point"}
}