{
  "type": "Feature",
  "properties": {
    "gn:admin1_code":"8.0",
    "gn:admin2_code":"1817.0",
    "gn:asciiname":"Quz`at al Ma`arif",
    "gn:country_code":"YE",
    "gn:dem":107,
    "gn:feature_class":"P",
    "gn:feature_code":"PPL",
    "gn:name":"Quz\u2018at al Ma\u2018\u0101r\u012bf",
    "gn:population":0,
    "gn:timezone":"Asia/Aden",
    "iso:country":"YE",
    "name:und_x_variant":[
        "Quz\u2018at al Ma\u2018\u0101r\u012bf"
    ],
    "wof:name":"Quz`at al Ma`arif",
    "wof:placetype":"locality"
},
  "geometry": {"coordinates":[43.31973,14.57669],"type":"Point"}
}