{
  "type": "Feature",
  "properties": {
    "gn:admin1_code":"15.0",
    "gn:admin2_code":"2208.0",
    "gn:asciiname":"Al Khawjarah",
    "gn:country_code":"YE",
    "gn:dem":1357,
    "gn:feature_class":"P",
    "gn:feature_code":"PPL",
    "gn:name":"Al Khawjarah",
    "gn:population":0,
    "gn:timezone":"Asia/Aden",
    "iso:country":"YE",
    "wof:name":"Al Khawjarah",
    "wof:placetype":"locality"
},
  "geometry": {"coordinates":[43.34242,16.66854],"type":"Point"}
}