{
  "type": "Feature",
  "properties": {
    "gn:admin1_code":"23.0",
    "gn:admin2_code":"1107.0",
    "gn:asciiname":"Ar Ribat",
    "gn:country_code":"YE",
    "gn:dem":1462,
    "gn:feature_class":"P",
    "gn:feature_code":"PPL",
    "gn:name":"Ar Rib\u0101\u0163",
    "gn:population":0,
    "gn:timezone":"Asia/Aden",
    "iso:country":"YE",
    "name:ara_x_preferred":[
        "Ar Rib\u0101\u0163"
    ],
    "name:nno_x_preferred":[
        "Ar Ribat"
    ],
    "wof:name":"Ar Ribat",
    "wof:placetype":"locality"
},
  "geometry": {"coordinates":[44.16295,14.16769],"type":"Point"}
}