{
  "type": "Feature",
  "properties": {
    "gn:admin1_code":"18.0",
    "gn:admin2_code":"3001.0",
    "gn:asciiname":"Ma`thah",
    "gn:country_code":"YE",
    "gn:dem":2027,
    "gn:feature_class":"P",
    "gn:feature_code":"PPL",
    "gn:name":"Ma\u2018thah",
    "gn:population":0,
    "gn:timezone":"Asia/Aden",
    "iso:country":"YE",
    "name:und_x_variant":[
        "Ma\u2018thah"
    ],
    "wof:name":"Ma`thah",
    "wof:placetype":"locality"
},
  "geometry": {"coordinates":[44.83265,14.0029],"type":"Point"}
}