{
  "type": "Feature",
  "properties": {
    "gn:admin1_code":"16.0",
    "gn:admin2_code":"2313.0",
    "gn:asciiname":"Bayt al Habal",
    "gn:country_code":"YE",
    "gn:dem":2471,
    "gn:feature_class":"P",
    "gn:feature_code":"PPL",
    "gn:name":"Bayt al Habal",
    "gn:population":0,
    "gn:timezone":"Asia/Aden",
    "iso:country":"YE",
    "name:ara_x_preferred":[
        "\u0628\u064a\u062a \u0627\u0644\u0647\u0628\u0644"
    ],
    "wof:name":"Bayt al Habal",
    "wof:placetype":"locality"
},
  "geometry": {"coordinates":[44.51404,15.34065],"type":"Point"}
}