{
  "type": "Feature",
  "properties": {
    "gn:admin1_code":"4.0",
    "gn:admin2_code":"1917.0",
    "gn:asciiname":"Jirwid",
    "gn:cc2":"YE",
    "gn:country_code":"YE",
    "gn:dem":1122,
    "gn:feature_class":"P",
    "gn:feature_code":"PPL",
    "gn:name":"Jirwid",
    "gn:population":0,
    "gn:timezone":"Asia/Aden",
    "iso:country":"YE",
    "name:und_x_variant":[
        "Al Ghaidat Jirwid",
        "Jirwid"
    ],
    "wof:name":"Jirwid",
    "wof:placetype":"locality"
},
  "geometry": {"coordinates":[48.95,14.88333],"type":"Point"}
}