{
  "type": "Feature",
  "properties": {
    "gn:admin1_code":"11.0",
    "gn:admin2_code":"2007.0",
    "gn:asciiname":"Al Jurn",
    "gn:country_code":"YE",
    "gn:dem":1165,
    "gn:feature_class":"P",
    "gn:feature_code":"PPL",
    "gn:name":"Al Jurn",
    "gn:population":0,
    "gn:timezone":"Asia/Aden",
    "iso:country":"YE",
    "name:ara_x_preferred":[
        "\u0627\u0644\u062c\u0631\u0646"
    ],
    "wof:name":"Al Jurn",
    "wof:placetype":"locality"
},
  "geometry": {"coordinates":[43.72459,14.329],"type":"Point"}
}