{
  "type": "Feature",
  "properties": {
    "gn:country":"YE",
    "gn:fcode":"PPL",
    "gn:pop":1,
    "iso:country":"YE",
    "name:ara_x_preferred":[
        "Al Jur\u016bb"
    ],
    "name:ara_x_variant":[
        "\u0627\u0644\u062c\u0631\u0648\u0628"
    ],
    "qs:name":"Al Jur\u016bb",
    "qs:photos_9r":0,
    "qs:photos_sr":0,
    "qs:pop_sr":"1",
    "wof:name":"Al Jur\u016bb",
    "wof:placetype":"locality",
    "wof:population":1
},
  "geometry": {"coordinates":[43.36238,16.22926],"type":"Point"}
}