{
  "type": "Feature",
  "properties": {
    "gn:admin1_code":"20.0",
    "gn:admin2_code":"1412.0",
    "gn:asciiname":"`Uqlat Bunayyan",
    "gn:country_code":"YE",
    "gn:dem":1983,
    "gn:feature_class":"P",
    "gn:feature_code":"PPL",
    "gn:name":"\u2018Uqlat Bunayy\u0101n",
    "gn:population":0,
    "gn:timezone":"Asia/Aden",
    "iso:country":"YE",
    "name:und_x_variant":[
        "\u2018Uqlat Bunayy\u0101n"
    ],
    "wof:name":"`Uqlat Bunayyan",
    "wof:placetype":"locality"
},
  "geometry": {"coordinates":[45.3009,14.39268],"type":"Point"}
}