{
  "type": "Feature",
  "properties": {
    "gn:admin1_code":"16.0",
    "gn:admin2_code":"2303.0",
    "gn:asciiname":"Bani Rassam",
    "gn:country_code":"YE",
    "gn:dem":2384,
    "gn:feature_class":"P",
    "gn:feature_code":"PPL",
    "gn:name":"Ban\u012b Rass\u0101m",
    "gn:population":0,
    "gn:timezone":"Asia/Aden",
    "iso:country":"YE",
    "name:und_x_variant":[
        "Ban\u012b Rass\u0101m"
    ],
    "wof:name":"Bani Rassam",
    "wof:placetype":"locality"
},
  "geometry": {"coordinates":[44.43319,15.52835],"type":"Point"}
}