{
  "type": "Feature",
  "properties": {
    "gn:admin1_code":"23.0",
    "gn:admin2_code":"1114.0",
    "gn:asciiname":"Az Zara'ib",
    "gn:country_code":"YE",
    "gn:dem":1467,
    "gn:feature_class":"P",
    "gn:feature_code":"PPL",
    "gn:name":"Az Zar\u0101\u2019ib",
    "gn:population":0,
    "gn:timezone":"Asia/Aden",
    "iso:country":"YE",
    "name:und_x_variant":[
        "Zerab",
        "Zira",
        "Az Zar\u0101\u2019ib",
        "Zirab"
    ],
    "wof:name":"Az Zara'ib",
    "wof:placetype":"locality"
},
  "geometry": {"coordinates":[44.24168,13.74318],"type":"Point"}
}