{
  "type": "Feature",
  "properties": {
    "gn:admin1_code":"20.0",
    "gn:admin2_code":"1411.0",
    "gn:asciiname":"Dhahabah",
    "gn:country_code":"YE",
    "gn:dem":1996,
    "gn:feature_class":"P",
    "gn:feature_code":"PPL",
    "gn:name":"Dhahabah",
    "gn:population":0,
    "gn:timezone":"Asia/Aden",
    "iso:country":"YE",
    "name:und_x_variant":[
        "Shiz\u0327ah"
    ],
    "wof:name":"Dhahabah",
    "wof:placetype":"locality"
},
  "geometry": {"coordinates":[45.24697000000001,14.30579],"type":"Point"}
}