{
  "type": "Feature",
  "properties": {
    "gn:admin1_code":"11.0",
    "gn:admin2_code":"1103.0",
    "gn:asciiname":"Habalat al Jaradi",
    "gn:country_code":"YE",
    "gn:dem":2528,
    "gn:feature_class":"P",
    "gn:feature_code":"PPL",
    "gn:name":"\u1e28abalat al Jar\u0101d\u012b",
    "gn:population":0,
    "gn:timezone":"Asia/Aden",
    "iso:country":"YE",
    "name:ara_x_preferred":[
        "\u062d\u0628\u0644\u0629 \u0627\u0644\u062c\u0631\u0627\u062f\u064a"
    ],
    "name:und_x_variant":[
        "Bayt al Jar\u0101d\u012b",
        "\u1e28abalat al Jar\u0101d\u012b"
    ],
    "wof:name":"Habalat al Jaradi",
    "wof:placetype":"locality"
},
  "geometry": {"coordinates":[44.46263,14.26328],"type":"Point"}
}