{
  "type": "Feature",
  "properties": {
    "gn:admin1_code":"25.0",
    "gn:admin2_code":"1502.0",
    "gn:asciiname":"Al Maqran",
    "gn:country_code":"YE",
    "gn:dem":1506,
    "gn:feature_class":"P",
    "gn:feature_code":"PPL",
    "gn:name":"Al Maqr\u0101n",
    "gn:population":0,
    "gn:timezone":"Asia/Aden",
    "iso:country":"YE",
    "name:ara_x_preferred":[
        "\u0627\u0644\u0645\u0642\u0631\u0627\u0646"
    ],
    "name:und_x_variant":[
        "Al Maqr\u0101n",
        "Al Miqr\u0101n"
    ],
    "wof:name":"Al Maqran",
    "wof:placetype":"locality"
},
  "geometry": {"coordinates":[43.97314,13.76586],"type":"Point"}
}