{
  "type": "Feature",
  "properties": {
    "gn:admin1_code":"16.0",
    "gn:admin2_code":"2303.0",
    "gn:asciiname":"Al 'Arwat",
    "gn:country_code":"YE",
    "gn:dem":2150,
    "gn:feature_class":"P",
    "gn:feature_code":"PPL",
    "gn:name":"Al \u2018Arw\u0101t",
    "gn:population":0,
    "gn:timezone":"Asia/Aden",
    "iso:country":"YE",
    "name:ara_x_preferred":[
        "\u0627\u0644\u0639\u0631\u0648\u0627\u062a"
    ],
    "name:und_x_variant":[
        "Al \u2018Arw\u0101t"
    ],
    "wof:name":"Al 'Arwat",
    "wof:placetype":"locality"
},
  "geometry": {"coordinates":[44.58845,15.69485],"type":"Point"}
}