{
  "type": "Feature",
  "properties": {
    "gn:admin1_code":"8.0",
    "gn:admin2_code":"1807.0",
    "gn:asciiname":"Bayt al Mu'allim",
    "gn:country_code":"YE",
    "gn:dem":173,
    "gn:feature_class":"P",
    "gn:feature_code":"PPL",
    "gn:name":"Bayt al Mu\u2018allim",
    "gn:population":0,
    "gn:timezone":"Asia/Aden",
    "iso:country":"YE",
    "name:ara_x_preferred":[
        "\u0628\u064a\u062a \u0627\u0644\u0645\u0639\u0644\u0645"
    ],
    "name:und_x_variant":[
        "Bayt al Mu\u2018allim"
    ],
    "wof:name":"Bayt al Mu'allim",
    "wof:placetype":"locality"
},
  "geometry": {"coordinates":[43.24368,15.40364],"type":"Point"}
}