{
  "type": "Feature",
  "properties": {
    "gn:admin1_code":"15.0",
    "gn:admin2_code":"2206.0",
    "gn:asciiname":"Sha'b Mita'b",
    "gn:country_code":"YE",
    "gn:dem":593,
    "gn:feature_class":"P",
    "gn:feature_code":"PPL",
    "gn:name":"Sha\u2018b Mita\u2018b",
    "gn:population":0,
    "gn:timezone":"Asia/Aden",
    "iso:country":"YE",
    "name:ara_x_preferred":[
        "\u0634\u0639\u0628 \u0645\u062a\u0639\u0628"
    ],
    "name:und_x_variant":[
        "Sha\u2018b Mita\u2018b"
    ],
    "wof:name":"Sha'b Mita'b",
    "wof:placetype":"locality"
},
  "geometry": {"coordinates":[43.20142,16.89834],"type":"Point"}
}