{
  "type": "Feature",
  "properties": {
    "gn:country":"YE",
    "gn:fcode":"PPL",
    "gn:population":8,
    "iso:country":"YE",
    "name:ara_x_preferred":[
        "\u0630\u0648 \u062f\u0639\u0643\u0645"
    ],
    "name:eng_x_preferred":[
        "DhU Da'kam"
    ],
    "name:eng_x_variant":[
        "Al Mah\u016bb"
    ],
    "qs:name":"Dh\u016b Da\u2018kam",
    "qs:photos_9r":0,
    "qs:photos_sr":0,
    "qs:pop_sr":"1",
    "wof:name":"Dh\u016b Da\u2018kam",
    "wof:placetype":"locality",
    "wof:population":8
},
  "geometry": {"coordinates":[44.02713,16.88611],"type":"Point"}
}