{
  "type": "Feature",
  "properties": {
    "gn:country":"YE",
    "gn:fcode":"PPL",
    "gn:population":6,
    "iso:country":"YE",
    "name:ara_x_preferred":[
        "\u0639\u0641\u0627\u0648\u0629"
    ],
    "name:eng_x_preferred":[
        "Afawah"
    ],
    "name:eng_x_variant":[
        "Gh\u0101rib Majdibah",
        "'Afawah"
    ],
    "qs:name":"\u2018Af\u0101wah",
    "qs:photos_9r":0,
    "qs:photos_sr":0,
    "qs:pop_sr":"1",
    "wof:name":"\u2018Af\u0101wah",
    "wof:placetype":"locality",
    "wof:population":6
},
  "geometry": {"coordinates":[43.27865,16.49981],"type":"Point"}
}