{
  "type": "Feature",
  "properties": {
    "gn:admin1_code":"8.0",
    "gn:admin2_code":"1824.0",
    "gn:asciiname":"Al Mahajibah",
    "gn:country_code":"YE",
    "gn:dem":162,
    "gn:feature_class":"P",
    "gn:feature_code":"PPL",
    "gn:name":"Al Ma\u1e29\u0101jibah",
    "gn:population":0,
    "gn:timezone":"Asia/Aden",
    "iso:country":"YE",
    "name:und_x_variant":[
        "Al Ma\u1e29\u0101jibah"
    ],
    "wof:name":"Al Mahajibah",
    "wof:placetype":"locality"
},
  "geometry": {"coordinates":[43.40974,14.24899],"type":"Point"}
}