{
  "type": "Feature",
  "properties": {
    "gn:admin1_code":"15.0",
    "gn:admin2_code":"2206.0",
    "gn:asciiname":"Umm Zawari",
    "gn:country_code":"YE",
    "gn:dem":430,
    "gn:feature_class":"P",
    "gn:feature_code":"PPL",
    "gn:name":"Umm Zaw\u0101r\u012b",
    "gn:population":0,
    "gn:timezone":"Asia/Aden",
    "iso:country":"YE",
    "name:ara_x_preferred":[
        "\u0623\u0645 \u0632\u0648\u0627\u0631\u064a"
    ],
    "name:und_x_variant":[
        "Umm Zaw\u0101r\u012b"
    ],
    "wof:name":"Umm Zawari",
    "wof:placetype":"locality"
},
  "geometry": {"coordinates":[43.18512,16.87518],"type":"Point"}
}