{
  "type": "Feature",
  "properties": {
    "gn:admin1_code":"19.0",
    "gn:admin2_code":"2918.0",
    "gn:asciiname":"Bayt `Askar",
    "gn:country_code":"YE",
    "gn:dem":2353,
    "gn:feature_class":"P",
    "gn:feature_code":"PPL",
    "gn:name":"Bayt \u2018Askar",
    "gn:population":0,
    "gn:timezone":"Asia/Aden",
    "iso:country":"YE",
    "name:und_x_variant":[
        "Bayt \u2018Askar"
    ],
    "wof:name":"Bayt `Askar",
    "wof:placetype":"locality"
},
  "geometry": {"coordinates":[43.87598,15.90365],"type":"Point"}
}