{
  "type": "Feature",
  "properties": {
    "gn:admin1_code":"21.0",
    "gn:admin2_code":"1601.0",
    "gn:asciiname":"Al Hujruf",
    "gn:country_code":"YE",
    "gn:dem":1485,
    "gn:feature_class":"P",
    "gn:feature_code":"PPL",
    "gn:name":"Al \u1e28ujr\u016bf",
    "gn:population":0,
    "gn:timezone":"Asia/Aden",
    "iso:country":"YE",
    "name:ara_x_preferred":[
        "Al \u1e28ujr\u016bf"
    ],
    "wof:name":"Al Hujruf",
    "wof:placetype":"locality"
},
  "geometry": {"coordinates":[44.83416,16.72335],"type":"Point"}
}