{
  "type": "Feature",
  "properties": {
    "gn:admin1_code":"23.0",
    "gn:admin2_code":"1106.0",
    "gn:asciiname":"`Ufar",
    "gn:country_code":"YE",
    "gn:dem":2764,
    "gn:feature_class":"P",
    "gn:feature_code":"PPL",
    "gn:name":"\u2018Uf\u0101r",
    "gn:population":0,
    "gn:timezone":"Asia/Aden",
    "iso:country":"YE",
    "name:ara_x_preferred":[
        "\u2018Uf\u0101r"
    ],
    "wof:name":"`Ufar",
    "wof:placetype":"locality"
},
  "geometry": {"coordinates":[44.3831,14.14888],"type":"Point"}
}