{
  "type": "Feature",
  "properties": {
    "gn:admin1_code":"20.0",
    "gn:asciiname":"Al Makkak",
    "gn:country_code":"YE",
    "gn:dem":2247,
    "gn:feature_class":"P",
    "gn:feature_code":"PPL",
    "gn:name":"Al Makk\u0101k",
    "gn:population":0,
    "gn:timezone":"Asia/Aden",
    "iso:country":"YE",
    "name:ara_x_preferred":[
        "\u0627\u0644\u0645\u0643\u0627\u0643"
    ],
    "name:und_x_variant":[
        "Al Makk\u0101k"
    ],
    "wof:name":"Al Makkak",
    "wof:placetype":"locality"
},
  "geometry": {"coordinates":[44.37872,14.40729],"type":"Point"}
}