{
  "type": "Feature",
  "properties": {
    "gn:admin1_code":"15.0",
    "gn:admin2_code":"2208.0",
    "gn:asciiname":"Qullat Abu Shayif",
    "gn:country_code":"YE",
    "gn:dem":1639,
    "gn:feature_class":"P",
    "gn:feature_code":"PPL",
    "gn:name":"Qullat Ab\u016b Sh\u0101yif",
    "gn:population":0,
    "gn:timezone":"Asia/Aden",
    "iso:country":"YE",
    "name:ara_x_preferred":[
        "\u0627\u0644\u0642\u0644\u0629"
    ],
    "name:und_x_variant":[
        "Qullat Ab\u016b Sh\u0101yif",
        "Al Qullah"
    ],
    "wof:name":"Qullat Abu Shayif",
    "wof:placetype":"locality"
},
  "geometry": {"coordinates":[43.39852,16.68545],"type":"Point"}
}