{
  "type": "Feature",
  "properties": {
    "gn:admin1_code":"8.0",
    "gn:admin2_code":"1817.0",
    "gn:asciiname":"Bani Amin",
    "gn:country_code":"YE",
    "gn:dem":110,
    "gn:feature_class":"P",
    "gn:feature_code":"PPL",
    "gn:name":"Ban\u012b Am\u012bn",
    "gn:population":0,
    "gn:timezone":"Asia/Aden",
    "iso:country":"YE",
    "name:und_x_variant":[
        "Ban\u012b Am\u012bn"
    ],
    "wof:name":"Bani Amin",
    "wof:placetype":"locality"
},
  "geometry": {"coordinates":[43.2834,14.4225],"type":"Point"}
}