{
  "type": "Feature",
  "properties": {
    "gn:admin1_code":"22.0",
    "gn:admin2_code":"1710.0",
    "gn:asciiname":"Al Mabrak",
    "gn:country_code":"YE",
    "gn:dem":737,
    "gn:feature_class":"P",
    "gn:feature_code":"PPL",
    "gn:name":"Al Mabrak",
    "gn:population":0,
    "gn:timezone":"Asia/Aden",
    "iso:country":"YE",
    "name:ara_x_preferred":[
        "\u0627\u0644\u0645\u0628\u0631\u0643"
    ],
    "name:fas_x_preferred":[
        "\u0645\u0628\u0631\u0627\u06a9"
    ],
    "name:nno_x_preferred":[
        "Al Mabrak"
    ],
    "name:sco_x_preferred":[
        "Al Mabrak"
    ],
    "name:sqi_x_preferred":[
        "Al Mabrak"
    ],
    "wof:name":"Al Mabrak",
    "wof:placetype":"locality"
},
  "geometry": {"coordinates":[43.39912,16.02996],"type":"Point"}
}