{
  "type": "Feature",
  "properties": {
    "gn:admin1_code":"22.0",
    "gn:admin2_code":"1720.0",
    "gn:asciiname":"Mahall Bani Hamzah",
    "gn:country_code":"YE",
    "gn:dem":873,
    "gn:feature_class":"P",
    "gn:feature_code":"PPL",
    "gn:name":"Ma\u1e29all Ban\u012b \u1e28amzah",
    "gn:population":0,
    "gn:timezone":"Asia/Aden",
    "iso:country":"YE",
    "name:und_x_variant":[
        "Ma\u1e29all Ban\u012b \u1e28amzah"
    ],
    "wof:name":"Mahall Bani Hamzah",
    "wof:placetype":"locality"
},
  "geometry": {"coordinates":[43.5146,15.73645],"type":"Point"}
}