{
  "type": "Feature",
  "properties": {
    "gn:admin1_code":"18.0",
    "gn:admin2_code":"3009.0",
    "gn:asciiname":"Hasaban",
    "gn:country_code":"YE",
    "gn:dem":1293,
    "gn:feature_class":"P",
    "gn:feature_code":"PPL",
    "gn:name":"\u1e28a\u015fab\u0101n",
    "gn:population":0,
    "gn:timezone":"Asia/Aden",
    "iso:country":"YE",
    "name:und_x_variant":[
        "\u1e28a\u015fab\u0101n"
    ],
    "wof:name":"Hasaban",
    "wof:placetype":"locality"
},
  "geometry": {"coordinates":[44.49285,13.80597],"type":"Point"}
}