{
  "type": "Feature",
  "properties": {
    "gn:admin1_code":"22.0",
    "gn:admin2_code":"1710.0",
    "gn:asciiname":"Afatim",
    "gn:country_code":"YE",
    "gn:dem":1428,
    "gn:feature_class":"P",
    "gn:feature_code":"PPL",
    "gn:name":"Af\u0101\u0163im",
    "gn:population":0,
    "gn:timezone":"Asia/Aden",
    "iso:country":"YE",
    "name:ara_x_preferred":[
        "Af\u0101\u0163im"
    ],
    "name:ara_x_variant":[
        "\u0623\u0641\u0627\u0637\u0645"
    ],
    "wof:name":"Afatim",
    "wof:placetype":"locality"
},
  "geometry": {"coordinates":[43.41796,16.03946],"type":"Point"}
}