{
  "type": "Feature",
  "properties": {
    "gn:admin1_code":"15.0",
    "gn:admin2_code":"2209.0",
    "gn:asciiname":"Jaw` an",
    "gn:country_code":"YE",
    "gn:dem":2487,
    "gn:feature_class":"P",
    "gn:feature_code":"PPL",
    "gn:name":"Jaw\u2018 \u0101n",
    "gn:population":0,
    "gn:timezone":"Asia/Aden",
    "iso:country":"YE",
    "name:ara_x_preferred":[
        "\u062c\u0648\u0639\u0627\u0646"
    ],
    "name:und_x_variant":[
        "Jaw\u2018 \u0101n"
    ],
    "wof:name":"Jaw` an",
    "wof:placetype":"locality"
},
  "geometry": {"coordinates":[43.43392,16.85742999999999],"type":"Point"}
}