{
  "type": "Feature",
  "properties": {
    "gn:admin1_code":"25.0",
    "gn:admin2_code":"1513.0",
    "gn:asciiname":"Az Zil`ah",
    "gn:country_code":"YE",
    "gn:dem":947,
    "gn:feature_class":"P",
    "gn:feature_code":"PPL",
    "gn:name":"Az\u0327 Z\u0327il\u2018ah",
    "gn:population":0,
    "gn:timezone":"Asia/Aden",
    "iso:country":"YE",
    "name:und_x_variant":[
        "El Kuhef",
        "Al Kuhef",
        "Az\u0327 Z\u0327il\u2018ah",
        "Al Ku\u1e29ayf"
    ],
    "wof:name":"Az Zil`ah",
    "wof:placetype":"locality"
},
  "geometry": {"coordinates":[44.35554000000001,13.39715],"type":"Point"}
}