{
  "type": "Feature",
  "properties": {
    "gn:admin1_code":"15.0",
    "gn:admin2_code":"2203.0",
    "gn:asciiname":"Al Qar'ah",
    "gn:country_code":"YE",
    "gn:dem":1812,
    "gn:feature_class":"P",
    "gn:feature_code":"PPL",
    "gn:name":"Al Qar\u2018ah",
    "gn:population":0,
    "gn:timezone":"Asia/Aden",
    "iso:country":"YE",
    "name:ara_x_preferred":[
        "\u0627\u0644\u0642\u0631\u0639\u0629"
    ],
    "name:und_x_variant":[
        "Al Qar\u2018ah"
    ],
    "wof:name":"Al Qar'ah",
    "wof:placetype":"locality"
},
  "geometry": {"coordinates":[43.27937,17.2116],"type":"Point"}
}