{
  "type": "Feature",
  "properties": {
    "gn:country":"YE",
    "gn:fcode":"PPL",
    "gn:population":1,
    "iso:country":"YE",
    "name:ara_x_preferred":[
        "\u0627\u0644\u0645\u062d\u0635\u064a"
    ],
    "name:eng_x_preferred":[
        "Al Mahsi"
    ],
    "name:eng_x_variant":[
        "\u1e28ayfat Daby\u0101n"
    ],
    "qs:name":"Al Ma\u1e29\u015f\u012b",
    "qs:photos_9r":0,
    "qs:photos_sr":0,
    "qs:pop_sr":"1",
    "wof:name":"Al Ma\u1e29\u015f\u012b",
    "wof:placetype":"locality",
    "wof:population":1
},
  "geometry": {"coordinates":[43.39594,16.02564],"type":"Point"}
}