{
  "type": "Feature",
  "properties": {
    "gn:admin1_code":"8.0",
    "gn:admin2_code":"1805.0",
    "gn:asciiname":"Al Jatm",
    "gn:country_code":"YE",
    "gn:dem":18,
    "gn:feature_class":"P",
    "gn:feature_code":"PPL",
    "gn:name":"Al Jatm",
    "gn:population":0,
    "gn:timezone":"Asia/Aden",
    "iso:country":"YE",
    "name:ara_x_preferred":[
        "\u0627\u0644\u062c\u062a\u0645"
    ],
    "wof:name":"Al Jatm",
    "wof:placetype":"locality"
},
  "geometry": {"coordinates":[42.86948,15.18595],"type":"Point"}
}