{
  "type": "Feature",
  "properties": {
    "gn:admin1_code":"15.0",
    "gn:admin2_code":"2212.0",
    "gn:asciiname":"Ash Shaqra'",
    "gn:country_code":"YE",
    "gn:dem":1633,
    "gn:feature_class":"P",
    "gn:feature_code":"PPL",
    "gn:name":"Ash Shaqr\u0101\u2019",
    "gn:population":0,
    "gn:timezone":"Asia/Aden",
    "iso:country":"YE",
    "name:ara_x_preferred":[
        "\u0627\u0644\u0634\u0642\u0631\u0627\u0621"
    ],
    "name:und_x_variant":[
        "Umm Shaqr\u0101\u2019",
        "Ash Shaqr\u0101\u2019"
    ],
    "wof:name":"Ash Shaqra'",
    "wof:placetype":"locality"
},
  "geometry": {"coordinates":[43.93187,16.71069],"type":"Point"}
}