{
  "type": "Feature",
  "properties": {
    "gn:admin1_code":"24.0",
    "gn:admin2_code":"2511.0",
    "gn:asciiname":"Dar al Bayda`",
    "gn:country_code":"YE",
    "gn:dem":703,
    "gn:feature_class":"P",
    "gn:feature_code":"PPL",
    "gn:name":"D\u0101r al Bayd\u0101\u2018",
    "gn:population":0,
    "gn:timezone":"Asia/Aden",
    "iso:country":"YE",
    "name:und_x_variant":[
        "D\u0101r al Bayd\u0101\u2018"
    ],
    "wof:name":"Dar al Bayda`",
    "wof:placetype":"locality"
},
  "geometry": {"coordinates":[44.30043,13.20059],"type":"Point"}
}