{
  "type": "Feature",
  "properties": {
    "gn:admin1_code":"25.0",
    "gn:admin2_code":"1508.0",
    "gn:asciiname":"Ad Darabi",
    "gn:country_code":"YE",
    "gn:dem":416,
    "gn:feature_class":"P",
    "gn:feature_code":"PPL",
    "gn:name":"Ad Dar\u0101b\u012b",
    "gn:population":0,
    "gn:timezone":"Asia/Aden",
    "iso:country":"YE",
    "name:ara_x_preferred":[
        "\u0627\u0644\u062f\u0631\u0627\u0628\u064a"
    ],
    "name:und_x_variant":[
        "Ad Dar\u0101b\u012b"
    ],
    "wof:name":"Ad Darabi",
    "wof:placetype":"locality"
},
  "geometry": {"coordinates":[43.68599,13.32083],"type":"Point"}
}