{
  "type": "Feature",
  "properties": {
    "gn:admin1_code":"14.0",
    "gn:admin2_code":"2605.0",
    "gn:asciiname":"Dalawah",
    "gn:country_code":"YE",
    "gn:dem":1935,
    "gn:feature_class":"P",
    "gn:feature_code":"PPLL",
    "gn:name":"Dal\u0101wah",
    "gn:population":0,
    "gn:timezone":"Asia/Aden",
    "iso:country":"YE",
    "name:ara_x_preferred":[
        "\u062f\u0644\u0627\u0648\u0629"
    ],
    "name:und_x_variant":[
        "Dal\u0101wah"
    ],
    "wof:name":"Dalawah",
    "wof:placetype":"locality"
},
  "geometry": {"coordinates":[44.75963,15.37925],"type":"Point"}
}