{
  "type": "Feature",
  "properties": {
    "gn:country":"YE",
    "gn:fcode":"PPL",
    "gn:pop":9,
    "iso:country":"YE",
    "name:ara_x_preferred":[
        "A\u015f \u015eir\u0101\u0163i\u1e29"
    ],
    "name:ara_x_variant":[
        "\u0627\u0644\u0635\u0631\u0627\u0637\u0640\u062d"
    ],
    "name:eng_x_preferred":[
        "As Siratih"
    ],
    "name:eng_x_variant":[
        "\u1e28ad\u012byat al Birr"
    ],
    "qs:name":"A\u015f \u015eir\u0101\u0163i\u1e29",
    "qs:photos_9r":0,
    "qs:photos_sr":0,
    "qs:pop_sr":"1",
    "wof:name":"A\u015f \u015eir\u0101\u0163i\u1e29",
    "wof:placetype":"locality",
    "wof:population":9
},
  "geometry": {"coordinates":[43.71198,16.22083],"type":"Point"}
}