{
  "type": "Feature",
  "properties": {
    "gn:admin1_code":"8.0",
    "gn:admin2_code":"1809.0",
    "gn:asciiname":"Dayr Harish",
    "gn:country_code":"YE",
    "gn:dem":106,
    "gn:feature_class":"P",
    "gn:feature_code":"PPL",
    "gn:name":"Dayr \u1e28ar\u012bsh",
    "gn:population":0,
    "gn:timezone":"Asia/Aden",
    "iso:country":"YE",
    "name:und_x_variant":[
        "Dayr \u1e28ar\u012bsh",
        "Dayr \u1e28arish",
        "Dayr Harish"
    ],
    "wof:name":"Dayr Harish",
    "wof:placetype":"locality"
},
  "geometry": {"coordinates":[43.13062,15.23607],"type":"Point"}
}