{
  "type": "Feature",
  "properties": {
    "gn:country":"YE",
    "gn:fcode":"PPL",
    "gn:pop":55,
    "iso:country":"YE",
    "name:ara_x_preferred":[
        "\u0645\u0628\u064a\u0637\u062d"
    ],
    "name:eng_x_preferred":[
        "Mabaytih"
    ],
    "name:eng_x_variant":[
        "Al Jar\u012br"
    ],
    "qs:name":"Mabay\u0163i\u1e29",
    "qs:photos_9r":0,
    "qs:photos_sr":0,
    "qs:pop_sr":"1",
    "wof:name":"Mabay\u0163i\u1e29",
    "wof:placetype":"locality",
    "wof:population":55
},
  "geometry": {"coordinates":[43.36653,16.14467],"type":"Point"}
}