{
  "type": "Feature",
  "properties": {
    "gn:admin1_code":"16.0",
    "gn:admin2_code":"2303.0",
    "gn:asciiname":"Bani Firas",
    "gn:country_code":"YE",
    "gn:dem":2081,
    "gn:feature_class":"P",
    "gn:feature_code":"PPL",
    "gn:name":"Ban\u012b Fir\u0101\u015f",
    "gn:population":0,
    "gn:timezone":"Asia/Aden",
    "iso:country":"YE",
    "name:und_x_variant":[
        "Ban\u012b Fir\u0101\u015f"
    ],
    "wof:name":"Bani Firas",
    "wof:placetype":"locality"
},
  "geometry": {"coordinates":[44.4657,15.65903],"type":"Point"}
}