{
  "type": "Feature",
  "properties": {
    "gn:admin1_code":"15.0",
    "gn:admin2_code":"2214.0",
    "gn:asciiname":"Al Maqam",
    "gn:country_code":"YE",
    "gn:dem":1751,
    "gn:feature_class":"P",
    "gn:feature_code":"PPL",
    "gn:name":"Al Maq\u0101m",
    "gn:population":0,
    "gn:timezone":"Asia/Aden",
    "iso:country":"YE",
    "name:und_x_variant":[
        "Al Maq\u0101m"
    ],
    "wof:name":"Al Maqam",
    "wof:placetype":"locality"
},
  "geometry": {"coordinates":[44.13569,16.9171],"type":"Point"}
}