{
  "type": "Feature",
  "properties": {
    "gn:admin1_code":"14.0",
    "gn:admin2_code":"2607.0",
    "gn:asciiname":"Ladah",
    "gn:country_code":"YE",
    "gn:dem":1193,
    "gn:feature_class":"P",
    "gn:feature_code":"PPL",
    "gn:name":"La\u1e11\u0101h",
    "gn:population":0,
    "gn:timezone":"Asia/Aden",
    "iso:country":"YE",
    "name:ara_x_preferred":[
        "\u0644\u0636\u0627\u0629"
    ],
    "name:und_x_variant":[
        "La\u1e11\u0101h"
    ],
    "wof:name":"Ladah",
    "wof:placetype":"locality"
},
  "geometry": {"coordinates":[45.28313,15.17939],"type":"Point"}
}