{
  "type": "Feature",
  "properties": {
    "gn:admin1_code":"23.0",
    "gn:admin2_code":"1107.0",
    "gn:asciiname":"Ar Rijad",
    "gn:country_code":"YE",
    "gn:dem":1541,
    "gn:feature_class":"P",
    "gn:feature_code":"PPL",
    "gn:name":"Ar Rij\u0101d",
    "gn:population":0,
    "gn:timezone":"Asia/Aden",
    "iso:country":"YE",
    "name:ara_x_preferred":[
        "Ar Rij\u0101d"
    ],
    "name:ara_x_variant":[
        "\u0627\u0644\u0631\u062c\u0627\u062f"
    ],
    "wof:name":"Ar Rijad",
    "wof:placetype":"locality"
},
  "geometry": {"coordinates":[44.18435,14.09345],"type":"Point"}
}