{
  "type": "Feature",
  "properties": {
    "gn:country":"YE",
    "gn:fcode":"PPL",
    "gn:population":10,
    "iso:country":"YE",
    "name:ara_x_preferred":[
        "\u0633\u062d\u0627\u064a\u0629"
    ],
    "name:eng_x_preferred":[
        "Sihayah"
    ],
    "name:eng_x_variant":[
        "Al Mi\u1e29d\u0101dah"
    ],
    "qs:name":"Si\u1e29\u0101yah",
    "qs:photos_9r":0,
    "qs:photos_sr":0,
    "qs:pop_sr":"1",
    "wof:name":"Si\u1e29\u0101yah",
    "wof:placetype":"locality",
    "wof:population":10
},
  "geometry": {"coordinates":[43.33427,17.23334],"type":"Point"}
}