{
  "type": "Feature",
  "properties": {
    "gn:admin1_code":"23.0",
    "gn:admin2_code":"1116.0",
    "gn:asciiname":"Tanif",
    "gn:country_code":"YE",
    "gn:dem":1692,
    "gn:feature_class":"P",
    "gn:feature_code":"PPL",
    "gn:name":"\u0162\u0101nif",
    "gn:population":0,
    "gn:timezone":"Asia/Aden",
    "iso:country":"YE",
    "name:ara_x_preferred":[
        "\u0162\u0101nif"
    ],
    "wof:name":"Tanif",
    "wof:placetype":"locality"
},
  "geometry": {"coordinates":[44.09548,13.8097],"type":"Point"}
}