{
  "type": "Feature",
  "properties": {
    "gn:admin1_code":"15.0",
    "gn:admin2_code":"2209.0",
    "gn:asciiname":"Dar Alt",
    "gn:country_code":"YE",
    "gn:dem":2144,
    "gn:feature_class":"P",
    "gn:feature_code":"PPL",
    "gn:name":"D\u0101r Alt",
    "gn:population":0,
    "gn:timezone":"Asia/Aden",
    "iso:country":"YE",
    "name:ara_x_preferred":[
        "D\u0101r Alt"
    ],
    "name:ara_x_variant":[
        "\u062f\u0627\u0631 \u0627\u0644\u062a"
    ],
    "name:und_x_variant":[
        "D\u0101r\u012blah"
    ],
    "wof:name":"Dar Alt",
    "wof:placetype":"locality"
},
  "geometry": {"coordinates":[43.43843,16.89937999999999],"type":"Point"}
}