{
  "type": "Feature",
  "properties": {
    "gn:country":"YE",
    "gn:fcode":"PPL",
    "gn:population":4,
    "iso:country":"YE",
    "name:ara_x_preferred":[
        "\u0627\u0644\u0645\u0631\u0642\u064a"
    ],
    "qs:name":"Al Marq\u012b",
    "qs:photos_9r":0,
    "qs:photos_sr":0,
    "qs:pop_sr":"1",
    "wof:name":"Al Marq\u012b",
    "wof:placetype":"locality",
    "wof:population":4
},
  "geometry": {"coordinates":[43.30054,16.70533],"type":"Point"}
}