{
  "type": "Feature",
  "properties": {
    "gn:country":"YE",
    "gn:fcode":"PPL",
    "gn:pop":10,
    "iso:country":"YE",
    "name:ara_x_preferred":[
        "\u0627\u0644\u0642\u0648\u0633"
    ],
    "name:eng_x_preferred":[
        "Al Qawas"
    ],
    "name:eng_x_variant":[
        "Gh\u0101rib al \u2018Ar\u016bj"
    ],
    "qs:name":"Al Qawas",
    "qs:photos_9r":0,
    "qs:photos_sr":0,
    "qs:pop_sr":"1",
    "wof:name":"Al Qawas",
    "wof:placetype":"locality",
    "wof:population":10
},
  "geometry": {"coordinates":[43.28804,17.47733],"type":"Point"}
}