{
  "type": "Feature",
  "properties": {
    "gn:admin1_code":"21.0",
    "gn:admin2_code":"1610.0",
    "gn:asciiname":"Al 'Ulayb",
    "gn:country_code":"YE",
    "gn:dem":2055,
    "gn:feature_class":"P",
    "gn:feature_code":"PPL",
    "gn:name":"Al \u2018Ulayb",
    "gn:population":0,
    "gn:timezone":"Asia/Aden",
    "iso:country":"YE",
    "name:ara_x_preferred":[
        "\u0627\u0644\u0639\u0644\u064a\u0628"
    ],
    "name:und_x_variant":[
        "Al \u2018Ulayb"
    ],
    "wof:name":"Al 'Ulayb",
    "wof:placetype":"locality"
},
  "geometry": {"coordinates":[44.41195,16.7918],"type":"Point"}
}