{
  "type": "Feature",
  "properties": {
    "gn:country":"YE",
    "gn:fcode":"PPL",
    "gn:pop":15,
    "iso:country":"YE",
    "name:ara_x_preferred":[
        "\u062d\u0628\u0648\u0642\u0648"
    ],
    "name:eng_x_preferred":[
        "HabUqU"
    ],
    "name:eng_x_variant":[
        "Midqah"
    ],
    "qs:name":"\u1e28ab\u016bq\u016b",
    "qs:photos_9r":0,
    "qs:photos_sr":0,
    "qs:pop_sr":"1",
    "wof:name":"\u1e28ab\u016bq\u016b",
    "wof:placetype":"locality",
    "wof:population":15
},
  "geometry": {"coordinates":[43.82895,13.32798],"type":"Point"}
}