{
  "type": "Feature",
  "properties": {
    "gn:country":"YE",
    "gn:fcode":"PPL",
    "gn:pop":7,
    "iso:country":"YE",
    "name:ara_x_preferred":[
        "\u0639\u062c\u0627\u062c\u0629"
    ],
    "name:eng_x_preferred":[
        "Ajajah"
    ],
    "name:eng_x_variant":[
        "'Ajajah"
    ],
    "qs:name":"\u2018Aj\u0101jah",
    "qs:photos_9r":0,
    "qs:photos_sr":0,
    "qs:pop_sr":"1",
    "wof:name":"\u2018Aj\u0101jah",
    "wof:placetype":"locality",
    "wof:population":7
},
  "geometry": {"coordinates":[43.389,17.07405],"type":"Point"}
}