{
  "type": "Feature",
  "properties": {
    "gn:admin1_code":"25.0",
    "gn:admin2_code":"1506.0",
    "gn:asciiname":"Qa`tabiyah",
    "gn:country_code":"YE",
    "gn:dem":7,
    "gn:feature_class":"P",
    "gn:feature_code":"PPL",
    "gn:name":"Qa\u2018\u0163ab\u012byah",
    "gn:population":0,
    "gn:timezone":"Asia/Aden",
    "iso:country":"YE",
    "name:und_x_variant":[
        "Qa\u2018\u0163ab\u012byah"
    ],
    "wof:name":"Qa`tabiyah",
    "wof:placetype":"locality"
},
  "geometry": {"coordinates":[43.2727,13.46038],"type":"Point"}
}