{
  "type": "Feature",
  "properties": {
    "gn:admin1_code":"22.0",
    "gn:admin2_code":"1718.0",
    "gn:asciiname":"Mahall al Hajar",
    "gn:country_code":"YE",
    "gn:dem":2166,
    "gn:feature_class":"P",
    "gn:feature_code":"PPL",
    "gn:name":"Ma\u1e29all al Hajar",
    "gn:population":0,
    "gn:timezone":"Asia/Aden",
    "iso:country":"YE",
    "name:und_x_variant":[
        "Ma\u1e29all al Hajar"
    ],
    "wof:name":"Mahall al Hajar",
    "wof:placetype":"locality"
},
  "geometry": {"coordinates":[43.71143,15.67319],"type":"Point"}
}