{
  "type": "Feature",
  "properties": {
    "gn:admin1_code":"22.0",
    "gn:admin2_code":"1709.0",
    "gn:asciiname":"Bayt al 'Awasib",
    "gn:country_code":"YE",
    "gn:dem":1654,
    "gn:feature_class":"P",
    "gn:feature_code":"PPL",
    "gn:name":"Bayt al \u2018Aw\u0101\u015fib",
    "gn:population":0,
    "gn:timezone":"Asia/Aden",
    "iso:country":"YE",
    "name:ara_x_preferred":[
        "\u0628\u064a\u062a \u0627\u0644\u0639\u0648\u0627\u0635\u0640\u0628"
    ],
    "name:und_x_variant":[
        "Bayt al \u2018Aw\u0101\u015fib"
    ],
    "wof:name":"Bayt al 'Awasib",
    "wof:placetype":"locality"
},
  "geometry": {"coordinates":[43.48171,16.04475],"type":"Point"}
}