{
  "type": "Feature",
  "properties": {
    "gn:admin1_code":"21.0",
    "gn:admin2_code":"1603.0",
    "gn:asciiname":"Al Kharid",
    "gn:country_code":"YE",
    "gn:dem":1282,
    "gn:feature_class":"P",
    "gn:feature_code":"PPLL",
    "gn:name":"Al Kh\u0101rid",
    "gn:population":0,
    "gn:timezone":"Asia/Aden",
    "iso:country":"YE",
    "name:ara_x_preferred":[
        "\u0627\u0644\u062e\u0627\u0631\u062f"
    ],
    "name:und_x_variant":[
        "Al Kh\u0101rid"
    ],
    "wof:name":"Al Kharid",
    "wof:placetype":"locality"
},
  "geometry": {"coordinates":[44.43357,16.04038],"type":"Point"}
}