{
  "type": "Feature",
  "properties": {
    "gn:admin1_code":"25.0",
    "gn:admin2_code":"1502.0",
    "gn:asciiname":"Qaryat ar Rajhah",
    "gn:country_code":"YE",
    "gn:dem":1261,
    "gn:feature_class":"P",
    "gn:feature_code":"PPL",
    "gn:name":"Qaryat ar Raj\u1e29ah",
    "gn:population":0,
    "gn:timezone":"Asia/Aden",
    "iso:country":"YE",
    "name:und_x_variant":[
        "Qaryat ar Raj\u1e29ah"
    ],
    "wof:name":"Qaryat ar Rajhah",
    "wof:placetype":"locality"
},
  "geometry": {"coordinates":[44.03635,13.66855],"type":"Point"}
}