{
  "type": "Feature",
  "properties": {
    "gn:country":"YE",
    "gn:fcode":"PPL",
    "gn:pop":2,
    "iso:country":"YE",
    "name:ara_x_preferred":[
        "\u0627\u0644\u0635\u0627\u0641\u064a\u0629"
    ],
    "name:eng_x_preferred":[
        "As Safiyah"
    ],
    "name:eng_x_variant":[
        "Ar Ri\u1e11\u016bm"
    ],
    "qs:name":"A\u015f \u015e\u0101f\u012byah",
    "qs:photos_9r":0,
    "qs:photos_sr":0,
    "qs:pop_sr":"1",
    "wof:name":"A\u015f \u015e\u0101f\u012byah",
    "wof:placetype":"locality",
    "wof:population":2
},
  "geometry": {"coordinates":[43.35051,16.67984],"type":"Point"}
}