{
  "type": "Feature",
  "properties": {
    "gn:gn_country":"YE",
    "gn:gn_fcode":"PPL",
    "gn:gn_pop":8,
    "gn:population":8,
    "iso:country":"YE",
    "name:ara_x_preferred":[
        "\u0627\u0644\u0645\u0639\u0633 \u0627\u0644\u0623\u0633\u0641\u0644"
    ],
    "qs_pg:aaroncc":"YE",
    "qs_pg:gn_country":"YE",
    "qs_pg:gn_fcode":"PPL",
    "qs_pg:gn_pop":8,
    "qs_pg:name":"Al Ma\u2018s al Asfal",
    "qs_pg:photos_9r":0,
    "qs_pg:photos_sr":0,
    "qs_pg:pop_sr":1,
    "qs_pg:qs_pg_placetype":"locality",
    "wof:name":"Al Ma\u2018s al Asfal",
    "wof:placetype":"locality",
    "wof:population":8
},
  "geometry": {"coordinates":[43.41845,16.365],"type":"Point"}
}