{
  "type": "Feature",
  "properties": {
    "gn:country":"YE",
    "gn:fcode":"PPL",
    "gn:pop":14,
    "iso:country":"YE",
    "name:ara_x_preferred":[
        "\u0630\u0648 \u0648\u0641\u064a\u0640\u0632"
    ],
    "name:eng_x_preferred":[
        "DhU Wafiz"
    ],
    "qs:name":"Dh\u016b Waf\u012bz",
    "qs:photos_9r":0,
    "qs:photos_sr":0,
    "qs:pop_sr":"1",
    "wof:name":"Dh\u016b Waf\u012bz",
    "wof:placetype":"locality",
    "wof:population":14
},
  "geometry": {"coordinates":[43.61251,16.17122],"type":"Point"}
}