{
  "type": "Feature",
  "properties": {
    "gn:admin1_code":"25.0",
    "gn:admin2_code":"1513.0",
    "gn:asciiname":"Kawakibah",
    "gn:country_code":"YE",
    "gn:dem":1387,
    "gn:feature_class":"P",
    "gn:feature_code":"PPL",
    "gn:name":"Kaw\u0101kibah",
    "gn:population":0,
    "gn:timezone":"Asia/Aden",
    "iso:country":"YE",
    "name:und_x_variant":[
        "Kaw\u0101kibah"
    ],
    "wof:name":"Kawakibah",
    "wof:placetype":"locality"
},
  "geometry": {"coordinates":[44.13342,13.50743],"type":"Point"}
}