{
  "type": "Feature",
  "properties": {
    "gn:country":"YE",
    "gn:fcode":"PPL",
    "gn:population":17,
    "iso:country":"YE",
    "name:ara_x_preferred":[
        "Adh Dhir\u0101\u2018"
    ],
    "name:ara_x_variant":[
        "\u0627\u0644\u0630\u0631\u0627\u0639"
    ],
    "qs:name":"Adh Dhir\u0101\u2018",
    "qs:photos_9r":0,
    "qs:photos_sr":0,
    "qs:pop_sr":"1",
    "wof:name":"Adh Dhir\u0101\u2018",
    "wof:placetype":"locality",
    "wof:population":17
},
  "geometry": {"coordinates":[45.12541,14.30999],"type":"Point"}
}