{
  "type": "Feature",
  "properties": {
    "gn:admin1_code":"1.0",
    "gn:admin2_code":"1211.0",
    "gn:asciiname":"Umm Shidyan",
    "gn:cc2":"YE",
    "gn:country_code":"YE",
    "gn:dem":352,
    "gn:feature_class":"P",
    "gn:feature_code":"PPL",
    "gn:name":"Umm Shidy\u0101n",
    "gn:population":0,
    "gn:timezone":"Asia/Aden",
    "iso:country":"YE",
    "name:ara_x_preferred":[
        "Umm Shidy\u0101n"
    ],
    "name:und_x_variant":[
        "Am Shidy\u0101n"
    ],
    "wof:name":"Umm Shidyan",
    "wof:placetype":"locality"
},
  "geometry": {"coordinates":[45.47972,13.42361],"type":"Point"}
}