{
  "type": "Feature",
  "properties": {
    "gn:admin1_code":"8.0",
    "gn:admin2_code":"1813.0",
    "gn:asciiname":"As Sulayhi",
    "gn:country_code":"YE",
    "gn:dem":104,
    "gn:feature_class":"P",
    "gn:feature_code":"PPL",
    "gn:name":"A\u015f \u015eulay\u1e29\u012b",
    "gn:population":0,
    "gn:timezone":"Asia/Aden",
    "iso:country":"YE",
    "name:ara_x_preferred":[
        "\u0627\u0644\u0635\u0644\u064a\u062d\u064a"
    ],
    "name:und_x_variant":[
        "A\u015f \u015eulay\u1e29\u012b"
    ],
    "wof:name":"As Sulayhi",
    "wof:placetype":"locality"
},
  "geometry": {"coordinates":[43.22648,14.85867],"type":"Point"}
}