{
  "type": "Feature",
  "properties": {
    "gn:gn_country":"YE",
    "gn:gn_fcode":"PPL",
    "gn:gn_pop":2,
    "gn:population":2,
    "iso:country":"YE",
    "name:ara_x_preferred":[
        "\u0623\u0645 \u0627\u0644\u0633\u0631\u062d\u0627\u0621"
    ],
    "name:eng_x_preferred":[
        "Umm As Sarha"
    ],
    "qs_pg:aaroncc":"YE",
    "qs_pg:gn_country":"YE",
    "qs_pg:gn_fcode":"PPL",
    "qs_pg:gn_pop":2,
    "qs_pg:name":"Umm as Sar\u1e29\u0101\u2019",
    "qs_pg:photos_9r":0,
    "qs_pg:photos_sr":0,
    "qs_pg:pop_sr":1,
    "qs_pg:qs_pg_placetype":"locality",
    "wof:name":"Umm as Sar\u1e29\u0101\u2019",
    "wof:placetype":"locality",
    "wof:population":2
},
  "geometry": {"coordinates":[46.30785,16.63791],"type":"Point"}
}