{
  "type": "Feature",
  "properties": {
    "gn:admin1_code":"18.0",
    "gn:admin2_code":"3009.0",
    "gn:asciiname":"Zahrah",
    "gn:country_code":"YE",
    "gn:dem":1202,
    "gn:feature_class":"P",
    "gn:feature_code":"PPL",
    "gn:name":"Za\u1e29rah",
    "gn:population":0,
    "gn:timezone":"Asia/Aden",
    "iso:country":"YE",
    "name:und_x_variant":[
        "Za\u1e29rah"
    ],
    "wof:name":"Zahrah",
    "wof:placetype":"locality"
},
  "geometry": {"coordinates":[44.41391,13.6598],"type":"Point"}
}