{
  "type": "Feature",
  "properties": {
    "gn:admin1_code":"8.0",
    "gn:admin2_code":"1810.0",
    "gn:asciiname":"Sharj al `Ammariyah",
    "gn:country_code":"YE",
    "gn:dem":318,
    "gn:feature_class":"P",
    "gn:feature_code":"PPL",
    "gn:name":"Sharj al \u2018Amm\u0101r\u012byah",
    "gn:population":0,
    "gn:timezone":"Asia/Aden",
    "iso:country":"YE",
    "name:ara_x_preferred":[
        "\u0634\u0631\u062c \u0627\u0644\u0639\u0645\u0627\u0631\u064a\u0629"
    ],
    "name:und_x_variant":[
        "Ash Sharj",
        "Sharj al \u2018Amm\u0101r\u012byah"
    ],
    "wof:name":"Sharj al `Ammariyah",
    "wof:placetype":"locality"
},
  "geometry": {"coordinates":[43.38673,15.12993],"type":"Point"}
}