{
  "type": "Feature",
  "properties": {
    "gn:admin1_code":"15.0",
    "gn:admin2_code":"2208.0",
    "gn:asciiname":"Qarn Bin Za'id",
    "gn:country_code":"YE",
    "gn:dem":2208,
    "gn:feature_class":"P",
    "gn:feature_code":"PPL",
    "gn:name":"Qarn Bin Z\u0101\u2019id",
    "gn:population":0,
    "gn:timezone":"Asia/Aden",
    "iso:country":"YE",
    "name:ara_x_preferred":[
        "\u0642\u0631\u0646 \u0628\u0646 \u0632\u0627\u0626\u062f"
    ],
    "name:und_x_variant":[
        "Qarn Bin Z\u0101\u2019id"
    ],
    "wof:name":"Qarn Bin Za'id",
    "wof:placetype":"locality"
},
  "geometry": {"coordinates":[43.42073,16.73071],"type":"Point"}
}