{
  "type": "Feature",
  "properties": {
    "gn:admin1_code":"10.0",
    "gn:admin2_code":"2701.0",
    "gn:asciiname":"Baduqah",
    "gn:country_code":"YE",
    "gn:dem":2832,
    "gn:feature_class":"P",
    "gn:feature_code":"PPL",
    "gn:name":"Bad\u016bqah",
    "gn:population":0,
    "gn:timezone":"Asia/Aden",
    "iso:country":"YE",
    "name:und_x_variant":[
        "Bad\u016bqah"
    ],
    "wof:name":"Baduqah",
    "wof:placetype":"locality"
},
  "geometry": {"coordinates":[43.84432,15.50754],"type":"Point"}
}