{
  "type": "Feature",
  "properties": {
    "gn:admin1_code":"1.0",
    "gn:admin2_code":"1208.0",
    "gn:asciiname":"Sakin Ahl Ahmad `Ali",
    "gn:country_code":"YE",
    "gn:dem":812,
    "gn:feature_class":"P",
    "gn:feature_code":"PPL",
    "gn:name":"S\u0101kin Ahl A\u1e29mad \u2018Al\u012b",
    "gn:population":0,
    "gn:timezone":"Asia/Aden",
    "iso:country":"YE",
    "name:und_x_variant":[
        "S\u0101kin Ahl A\u1e29mad \u2018Al\u012b"
    ],
    "wof:name":"Sakin Ahl Ahmad `Ali",
    "wof:placetype":"locality"
},
  "geometry": {"coordinates":[45.98159,13.75952],"type":"Point"}
}