{
  "type": "Feature",
  "properties": {
    "gn:admin1_code":"23.0",
    "gn:admin2_code":"1107.0",
    "gn:asciiname":"Al Marqab",
    "gn:country_code":"YE",
    "gn:dem":1829,
    "gn:feature_class":"P",
    "gn:feature_code":"PPL",
    "gn:name":"Al Marqab",
    "gn:population":0,
    "gn:timezone":"Asia/Aden",
    "iso:country":"YE",
    "name:ceb_x_preferred":[
        "Al Marqab"
    ],
    "name:heb_x_preferred":[
        "\u05d0\u05dc \u05de\u05e8\u05e7\u05d1"
    ],
    "name:swe_x_preferred":[
        "Al Marqab"
    ],
    "wof:name":"Al Marqab",
    "wof:placetype":"locality"
},
  "geometry": {"coordinates":[44.22161,14.18757],"type":"Point"}
}