{
  "type": "Feature",
  "properties": {
    "gn:admin1_code":"22.0",
    "gn:admin2_code":"1730.0",
    "gn:asciiname":"Al Qal'ah",
    "gn:country_code":"YE",
    "gn:dem":1226,
    "gn:feature_class":"P",
    "gn:feature_code":"PPL",
    "gn:name":"Al Qal\u2018ah",
    "gn:population":0,
    "gn:timezone":"Asia/Aden",
    "iso:country":"YE",
    "name:ara_x_preferred":[
        "\u0627\u0644\u0642\u0644\u0639\u0629"
    ],
    "name:und_x_variant":[
        "Al Qal\u2018ah"
    ],
    "wof:name":"Al Qal'ah",
    "wof:placetype":"locality"
},
  "geometry": {"coordinates":[43.42609,16.31087],"type":"Point"}
}