{
  "type": "Feature",
  "properties": {
    "gn:country":"YE",
    "gn:fcode":"PPL",
    "gn:pop":19,
    "iso:country":"YE",
    "name:ara_x_preferred":[
        "\u0641\u062a\u064a\u0634"
    ],
    "name:eng_x_preferred":[
        "Futaysh"
    ],
    "name:eng_x_variant":[
        "Al \u1e28usayn"
    ],
    "qs:name":"Futaysh",
    "qs:photos_9r":0,
    "qs:photos_sr":0,
    "qs:pop_sr":"1",
    "wof:name":"Futaysh",
    "wof:placetype":"locality",
    "wof:population":19
},
  "geometry": {"coordinates":[43.34392,17.39269],"type":"Point"}
}