{
  "type": "Feature",
  "properties": {
    "gn:admin1_code":"19.0",
    "gn:admin2_code":"2919.0",
    "gn:asciiname":"Bayt 'Utayfah",
    "gn:country_code":"YE",
    "gn:dem":2360,
    "gn:feature_class":"P",
    "gn:feature_code":"PPL",
    "gn:name":"Bayt \u2018U\u0163ayfah",
    "gn:population":0,
    "gn:timezone":"Asia/Aden",
    "iso:country":"YE",
    "name:ara_x_preferred":[
        "\u0628\u064a\u062a \u0639\u0637\u064a\u0641\u0629"
    ],
    "name:und_x_variant":[
        "Bayt \u2018U\u0163ayfah",
        "Bayt \u2018A\u0163\u012bfah"
    ],
    "wof:name":"Bayt 'Utayfah",
    "wof:placetype":"locality"
},
  "geometry": {"coordinates":[43.91746,16.0058],"type":"Point"}
}