{
  "type": "Feature",
  "properties": {
    "gn:admin1_code":"23.0",
    "gn:admin2_code":"1102.0",
    "gn:asciiname":"At Ta'kar",
    "gn:country_code":"YE",
    "gn:dem":2338,
    "gn:feature_class":"P",
    "gn:feature_code":"PPL",
    "gn:name":"At Ta\u2018kar",
    "gn:population":0,
    "gn:timezone":"Asia/Aden",
    "iso:country":"YE",
    "name:ara_x_preferred":[
        "\u0627\u0644\u062a\u0639\u0643\u0631"
    ],
    "name:und_x_variant":[
        "At Ta\u2018kar"
    ],
    "wof:name":"At Ta'kar",
    "wof:placetype":"locality"
},
  "geometry": {"coordinates":[44.19436,14.31861],"type":"Point"}
}