{
  "type": "Feature",
  "properties": {
    "gn:admin1_code":"22.0",
    "gn:admin2_code":"1727.0",
    "gn:asciiname":"Ash Shatt",
    "gn:country_code":"YE",
    "gn:dem":994,
    "gn:feature_class":"P",
    "gn:feature_code":"PPL",
    "gn:name":"Ash Sha\u0163\u0163",
    "gn:population":0,
    "gn:timezone":"Asia/Aden",
    "iso:country":"YE",
    "name:ara_x_preferred":[
        "\u0627\u0644\u0634\u0637"
    ],
    "name:und_x_variant":[
        "Ash Sha\u0163\u0163"
    ],
    "wof:name":"Ash Shatt",
    "wof:placetype":"locality"
},
  "geometry": {"coordinates":[43.62447,15.54459],"type":"Point"}
}