{
  "type": "Feature",
  "properties": {
    "gn:country":"YE",
    "gn:fcode":"PPL",
    "gn:population":4,
    "iso:country":"YE",
    "name:ara_x_preferred":[
        "\u0627\u0644\u062f\u062d\u0642\u0629"
    ],
    "name:eng_x_preferred":[
        "Ad Dahaqah"
    ],
    "name:eng_x_variant":[
        "Jarlimah"
    ],
    "qs:name":"Ad Da\u1e29aqah",
    "qs:photos_9r":0,
    "qs:photos_sr":0,
    "qs:pop_sr":"1",
    "wof:name":"Ad Da\u1e29aqah",
    "wof:placetype":"locality",
    "wof:population":4
},
  "geometry": {"coordinates":[45.22227,14.72819],"type":"Point"}
}