{
  "type": "Feature",
  "properties": {
    "gn:admin1_code":"8.0",
    "gn:admin2_code":"1810.0",
    "gn:asciiname":"Yahya Ibrahim",
    "gn:country_code":"YE",
    "gn:dem":191,
    "gn:feature_class":"P",
    "gn:feature_code":"PPL",
    "gn:name":"Ya\u1e29y\u00e1 Ibr\u0101h\u012bm",
    "gn:population":0,
    "gn:timezone":"Asia/Aden",
    "iso:country":"YE",
    "name:ara_x_preferred":[
        "\u064a\u062d\u064a\u0649 \u0625\u0628\u0631\u0627\u0647\u064a\u0645"
    ],
    "name:und_x_variant":[
        "Ma\u1e29all \u2018Abd All\u0101h Dabaj",
        "Ya\u1e29y\u00e1 Ibr\u0101h\u012bm"
    ],
    "wof:name":"Yahya Ibrahim",
    "wof:placetype":"locality"
},
  "geometry": {"coordinates":[43.24457,15.20642],"type":"Point"}
}