{
  "type": "Feature",
  "properties": {
    "gn:admin1_code":"10.0",
    "gn:admin2_code":"2703.0",
    "gn:asciiname":"Bayt Zar`ah",
    "gn:country_code":"YE",
    "gn:dem":1651,
    "gn:feature_class":"P",
    "gn:feature_code":"PPL",
    "gn:name":"Bayt Zar\u2018ah",
    "gn:population":0,
    "gn:timezone":"Asia/Aden",
    "iso:country":"YE",
    "name:und_x_variant":[
        "Bayt Zar\u2018ah"
    ],
    "wof:name":"Bayt Zar`ah",
    "wof:placetype":"locality"
},
  "geometry": {"coordinates":[43.67489000000001,15.39664],"type":"Point"}
}