{
  "type": "Feature",
  "properties": {
    "gn:admin1_code":"8.0",
    "gn:admin2_code":"1814.0",
    "gn:asciiname":"Al Barit",
    "gn:country_code":"YE",
    "gn:dem":59,
    "gn:feature_class":"P",
    "gn:feature_code":"PPL",
    "gn:name":"Al Bar\u012bt",
    "gn:population":0,
    "gn:timezone":"Asia/Aden",
    "iso:country":"YE",
    "name:und_x_variant":[
        "Al Bar\u012bt"
    ],
    "wof:name":"Al Barit",
    "wof:placetype":"locality"
},
  "geometry": {"coordinates":[43.17163,14.67864],"type":"Point"}
}