{
  "type": "Feature",
  "properties": {
    "gn:admin1_code":"23.0",
    "gn:admin2_code":"1120.0",
    "gn:asciiname":"Al Mamij",
    "gn:country_code":"YE",
    "gn:dem":1776,
    "gn:feature_class":"P",
    "gn:feature_code":"PPL",
    "gn:name":"Al M\u0101mij",
    "gn:population":0,
    "gn:timezone":"Asia/Aden",
    "iso:country":"YE",
    "name:ara_x_preferred":[
        "Al M\u0101mij"
    ],
    "name:ara_x_variant":[
        "\u0627\u0644\u0645\u0627\u0645\u062c"
    ],
    "wof:name":"Al Mamij",
    "wof:placetype":"locality"
},
  "geometry": {"coordinates":[44.19174,14.01847],"type":"Point"}
}