{
  "type": "Feature",
  "properties": {
    "gn:admin1_code":"18.0",
    "gn:admin2_code":"3006.0",
    "gn:asciiname":"Dhi Anas",
    "gn:cc2":"YE",
    "gn:country_code":"YE",
    "gn:dem":1171,
    "gn:feature_class":"P",
    "gn:feature_code":"PPL",
    "gn:name":"Dh\u012b An\u0101s",
    "gn:population":0,
    "gn:timezone":"Asia/Aden",
    "iso:country":"YE",
    "name:ara_x_preferred":[
        "Dh\u012b An\u0101s"
    ],
    "name:und_x_variant":[
        "Di An\u0101s"
    ],
    "wof:name":"Dhi Anas",
    "wof:placetype":"locality"
},
  "geometry": {"coordinates":[44.78333,13.65],"type":"Point"}
}