{
  "type": "Feature",
  "properties": {
    "gn:admin1_code":"1.0",
    "gn:admin2_code":"1207.0",
    "gn:asciiname":"Al `Alaq",
    "gn:country_code":"YE",
    "gn:dem":1635,
    "gn:feature_class":"P",
    "gn:feature_code":"PPL",
    "gn:name":"Al \u2018Alaq",
    "gn:population":0,
    "gn:timezone":"Asia/Aden",
    "iso:country":"YE",
    "name:und_x_variant":[
        "Al \u2018Alaq"
    ],
    "wof:name":"Al `Alaq",
    "wof:placetype":"locality"
},
  "geometry": {"coordinates":[45.31667,13.65],"type":"Point"}
}