{
  "type": "Feature",
  "properties": {
    "gn:admin1_code":"20.0",
    "gn:admin2_code":"1408.0",
    "gn:asciiname":"Al Far`",
    "gn:country_code":"YE",
    "gn:dem":2007,
    "gn:feature_class":"P",
    "gn:feature_code":"PPL",
    "gn:name":"Al Far\u2018",
    "gn:population":0,
    "gn:timezone":"Asia/Aden",
    "iso:country":"YE",
    "name:ara_x_preferred":[
        "\u0627\u0644\u0641\u0631\u0639"
    ],
    "name:und_x_variant":[
        "Al Fara",
        "Am Fara\u2018",
        "Al Far\u2018",
        "Umm Fara\u2018",
        "L\u0101birah"
    ],
    "wof:name":"Al Far`",
    "wof:placetype":"locality"
},
  "geometry": {"coordinates":[45.81852,14.13565],"type":"Point"}
}