{
  "type": "Feature",
  "properties": {
    "gn:admin1_code":"8.0",
    "gn:admin2_code":"1825.0",
    "gn:asciiname":"As San`",
    "gn:country_code":"YE",
    "gn:dem":278,
    "gn:feature_class":"P",
    "gn:feature_code":"PPL",
    "gn:name":"A\u015f \u015ean\u2018",
    "gn:population":0,
    "gn:timezone":"Asia/Aden",
    "iso:country":"YE",
    "name:ara_x_preferred":[
        "\u0627\u0644\u0635\u0646\u0639"
    ],
    "name:und_x_variant":[
        "A\u015f \u015ean\u2018"
    ],
    "wof:name":"As San`",
    "wof:placetype":"locality"
},
  "geometry": {"coordinates":[43.51619,14.20592],"type":"Point"}
}