{
  "type": "Feature",
  "properties": {
    "gn:admin1_code":"11.0",
    "gn:admin2_code":"2010.0",
    "gn:asciiname":"Ar Ribat",
    "gn:country_code":"YE",
    "gn:dem":2338,
    "gn:feature_class":"P",
    "gn:feature_code":"PPL",
    "gn:name":"Ar Rib\u0101\u0163",
    "gn:population":0,
    "gn:timezone":"Asia/Aden",
    "iso:country":"YE",
    "name:ara_x_preferred":[
        "Ar Rib\u0101\u0163"
    ],
    "wof:name":"Ar Ribat",
    "wof:placetype":"locality"
},
  "geometry": {"coordinates":[44.21092,14.55331],"type":"Point"}
}