{
  "type": "Feature",
  "properties": {
    "gn:admin1_code":"22.0",
    "gn:admin2_code":"1704.0",
    "gn:asciiname":"Al Mahall",
    "gn:country_code":"YE",
    "gn:dem":133,
    "gn:feature_class":"P",
    "gn:feature_code":"PPL",
    "gn:name":"Al Ma\u1e29all",
    "gn:population":0,
    "gn:timezone":"Asia/Aden",
    "iso:country":"YE",
    "name:ara_x_preferred":[
        "\u0627\u0644\u0645\u062d\u0644"
    ],
    "name:und_x_variant":[
        "Al Ma\u1e29all"
    ],
    "wof:name":"Al Mahall",
    "wof:placetype":"locality"
},
  "geometry": {"coordinates":[43.16106,16.13645],"type":"Point"}
}