{
  "type": "Feature",
  "properties": {
    "gn:country":"YE",
    "gn:fcode":"PPL",
    "gn:population":4,
    "iso:country":"YE",
    "name:ara_x_preferred":[
        "Shurf\u0101n"
    ],
    "name:ara_x_variant":[
        "\u0634\u0631\u0641\u0627\u0646"
    ],
    "name:eng_x_preferred":[
        "Shurfan"
    ],
    "name:eng_x_variant":[
        "Al Maghtarrib\u012bn"
    ],
    "qs:name":"Shurf\u0101n",
    "qs:photos_9r":0,
    "qs:photos_sr":0,
    "qs:pop_sr":"1",
    "wof:name":"Shurf\u0101n",
    "wof:placetype":"locality",
    "wof:population":4
},
  "geometry": {"coordinates":[43.31224,16.23081],"type":"Point"}
}