{
  "type": "Feature",
  "properties": {
    "gn:admin1_code":"24.0",
    "gn:admin2_code":"2503.0",
    "gn:asciiname":"Qaryat al 'Adi ar Rabi'i",
    "gn:country_code":"YE",
    "gn:dem":2352,
    "gn:feature_class":"P",
    "gn:feature_code":"PPL",
    "gn:name":"Qaryat al \u2018\u0100d\u012b ar Rab\u012b\u2018\u012b",
    "gn:population":0,
    "gn:timezone":"Asia/Aden",
    "iso:country":"YE",
    "name:ara_x_preferred":[
        "\u0642\u0631\u064a\u0629 \u0627\u0644\u0639\u0627\u062f\u064a \u0627\u0644\u0631\u0628\u064a\u0639\u064a"
    ],
    "name:und_x_variant":[
        "Qaryat al \u2018\u0100d\u012b ar Rab\u012b\u2018\u012b"
    ],
    "wof:name":"Qaryat al 'Adi ar Rabi'i",
    "wof:placetype":"locality"
},
  "geometry": {"coordinates":[45.17867,13.77751],"type":"Point"}
}