{
  "type": "Feature",
  "properties": {
    "gn:admin1_code":"21.0",
    "gn:admin2_code":"1610.0",
    "gn:asciiname":"Al 'Ajar",
    "gn:country_code":"YE",
    "gn:dem":1902,
    "gn:feature_class":"P",
    "gn:feature_code":"PPL",
    "gn:name":"Al \u2018Ajar",
    "gn:population":0,
    "gn:timezone":"Asia/Aden",
    "iso:country":"YE",
    "name:ara_x_preferred":[
        "\u0627\u0644\u0639\u062c\u0631"
    ],
    "name:und_x_variant":[
        "Al \u2018Ajar"
    ],
    "wof:name":"Al 'Ajar",
    "wof:placetype":"locality"
},
  "geometry": {"coordinates":[44.54909,16.81651],"type":"Point"}
}