{
  "type": "Feature",
  "properties": {
    "gn:admin1_code":"3.0",
    "gn:admin2_code":"2807.0",
    "gn:asciiname":"`Itab",
    "gn:country_code":"YE",
    "gn:dem":5,
    "gn:feature_class":"P",
    "gn:feature_code":"PPL",
    "gn:name":"\u2018It\u0101b",
    "gn:population":0,
    "gn:timezone":"Asia/Aden",
    "iso:country":"YE",
    "name:ara_x_preferred":[
        "\u2018It\u0101b"
    ],
    "name:und_x_variant":[
        "\u2018At\u0101b"
    ],
    "wof:name":"`Itab",
    "wof:placetype":"locality"
},
  "geometry": {"coordinates":[51.48119000000001,15.33511],"type":"Point"}
}