{
  "type": "Feature",
  "properties": {
    "gn:admin1_code":"16.0",
    "gn:admin2_code":"2304.0",
    "gn:asciiname":"Al Khirbah",
    "gn:country_code":"YE",
    "gn:dem":2354,
    "gn:feature_class":"P",
    "gn:feature_code":"PPL",
    "gn:name":"Al Khirbah",
    "gn:population":0,
    "gn:timezone":"Asia/Aden",
    "iso:country":"YE",
    "name:und_x_variant":[
        "Al Kharibah"
    ],
    "wof:name":"Al Khirbah",
    "wof:placetype":"locality"
},
  "geometry": {"coordinates":[44.30476,15.38178],"type":"Point"}
}