{
  "type": "Feature",
  "properties": {
    "gn:admin1_code":"8.0",
    "gn:admin2_code":"1817.0",
    "gn:asciiname":"Al Qawadir",
    "gn:country_code":"YE",
    "gn:dem":78,
    "gn:feature_class":"P",
    "gn:feature_code":"PPL",
    "gn:name":"Al Qaw\u0101dir",
    "gn:population":0,
    "gn:timezone":"Asia/Aden",
    "iso:country":"YE",
    "name:und_x_variant":[
        "Al Qaw\u0101dir"
    ],
    "wof:name":"Al Qawadir",
    "wof:placetype":"locality"
},
  "geometry": {"coordinates":[43.2299,14.3813],"type":"Point"}
}