{
  "type": "Feature",
  "properties": {
    "gn:admin1_code":"11.0",
    "gn:admin2_code":"2007.0",
    "gn:asciiname":"Al Mishrah",
    "gn:country_code":"YE",
    "gn:dem":825,
    "gn:feature_class":"P",
    "gn:feature_code":"PPL",
    "gn:name":"Al Mishr\u0101\u1e29",
    "gn:population":0,
    "gn:timezone":"Asia/Aden",
    "iso:country":"YE",
    "name:ara_x_preferred":[
        "Al Minsh\u0101\u1e29"
    ],
    "name:ara_x_variant":[
        "\u0627\u0644\u0645\u0634\u0631\u0627\u062d"
    ],
    "name:und_x_variant":[
        "Al Mishr\u0101\u1e29"
    ],
    "wof:name":"Al Mishrah",
    "wof:placetype":"locality"
},
  "geometry": {"coordinates":[43.5948,14.27842],"type":"Point"}
}