{
  "type": "Feature",
  "properties": {
    "iso:country":"YE",
    "name:ara_x_preferred":[
        "\u0627\u0644\u0645\u062d\u0648\u064a\u062a"
    ],
    "name:deu_x_preferred":[
        "Al-Mahwit"
    ],
    "name:eng_x_preferred":[
        "Al Mahwit"
    ],
    "name:epo_x_preferred":[
        "Al Mah\u016dit"
    ],
    "name:fas_x_preferred":[
        "\u0645\u062d\u0648\u06cc\u062a"
    ],
    "name:fra_x_preferred":[
        "Al Mahwit"
    ],
    "name:hbs_x_preferred":[
        "Al Mahvit"
    ],
    "name:hrv_x_preferred":[
        "Al-Mahvit"
    ],
    "name:ita_x_preferred":[
        "Al-Mahwit"
    ],
    "name:jpn_x_preferred":[
        "\u30de\u30d5\u30a6\u30a3\u30fc\u30c8"
    ],
    "name:kat_x_preferred":[
        "\u10d4\u10da-\u10db\u10d0\u10f0\u10d5\u10d8\u10e2\u10d8"
    ],
    "name:nan_x_preferred":[
        "Al Mahwit"
    ],
    "name:nld_x_preferred":[
        "Al Mahwit"
    ],
    "name:nno_x_preferred":[
        "Al Mahwit"
    ],
    "name:pol_x_preferred":[
        "Al-Mahwit"
    ],
    "name:por_x_preferred":[
        "Al Mahwit"
    ],
    "name:ron_x_preferred":[
        "Al Mahwit"
    ],
    "name:rus_x_preferred":[
        "\u041c\u0430\u0445\u0432\u0438\u0442"
    ],
    "name:sco_x_preferred":[
        "Al Mahwit"
    ],
    "name:som_x_preferred":[
        "Al Mahwit"
    ],
    "name:ukr_x_preferred":[
        "\u041c\u0430\u0445\u0432\u0456\u0442"
    ],
    "name:unk_x_variant":[
        "Mahwait"
    ],
    "name:urd_x_preferred":[
        "\u0627\u0644\u0645\u062d\u0648\u06cc\u062a"
    ],
    "name:vie_x_preferred":[
        "Al Mahwait City"
    ],
    "name:zho_min_nan_x_preferred":[
        "Al Mahwit"
    ],
    "name:zho_x_preferred":[
        "\u8fc8\u8d6b\u7ef4\u7279"
    ],
    "qs:gn_country":"YE",
    "qs:gn_fcode":"PPLA",
    "qs:gn_pop":0,
    "qs:name":"Al Mahwit",
    "qs:name_adm0":"Yemen",
    "qs:name_adm1":"Al Mahwit",
    "qs:photos":66,
    "qs:photos_1k":13,
    "qs:photos_9k":1,
    "qs:photos_9r":2,
    "qs:photos_all":66,
    "qs:photos_sr":2,
    "qs:placetype":"Town",
    "qs:pop_sr":"0",
    "qs:woe_adm0":23425002,
    "wd:population":10593,
    "wd:wordcount":178,
    "wof:name":"Al Mahwit",
    "wof:placetype":"locality",
    "wof:population":10593
},
  "geometry": {"coordinates":[43.54481,15.47007],"type":"Point"}
}