{
  "type": "Feature",
  "properties": {
    "gn:admin1_code":"11.0",
    "gn:asciiname":"Al Kharba'",
    "gn:country_code":"YE",
    "gn:dem":2507,
    "gn:feature_class":"P",
    "gn:feature_code":"PPL",
    "gn:name":"Al Kharb\u0101\u2019",
    "gn:population":0,
    "gn:timezone":"Asia/Aden",
    "iso:country":"YE",
    "name:ara_x_preferred":[
        "\u0627\u0644\u062e\u0631\u0628\u0627\u0621"
    ],
    "name:und_x_variant":[
        "Al Kharb\u0101\u2019"
    ],
    "wof:name":"Al Kharba'",
    "wof:placetype":"locality"
},
  "geometry": {"coordinates":[44.46205,14.26994],"type":"Point"}
}