{
  "type": "Feature",
  "properties": {
    "gn:admin1_code":"15.0",
    "gn:admin2_code":"2203.0",
    "gn:asciiname":"Qays",
    "gn:country_code":"YE",
    "gn:dem":836,
    "gn:feature_class":"P",
    "gn:feature_code":"PPL",
    "gn:name":"Qays",
    "gn:population":0,
    "gn:timezone":"Asia/Aden",
    "iso:country":"YE",
    "name:ara_x_preferred":[
        "\u0642\u064a\u0633 \u0639\u064a\u0644\u0627\u0646"
    ],
    "name:cat_x_preferred":[
        "Qays Aylan"
    ],
    "name:fas_x_preferred":[
        "\u0642\u06cc\u0633 \u0639\u06cc\u0644\u0627\u0646"
    ],
    "name:fra_x_preferred":[
        "Qaysites"
    ],
    "name:ita_x_preferred":[
        "Qaysiti"
    ],
    "name:nor_x_preferred":[
        "Qais"
    ],
    "name:rus_x_preferred":[
        "\u041a\u0430\u0439\u0441\u0438\u0442\u044b"
    ],
    "name:spa_x_preferred":[
        "Qais"
    ],
    "name:srp_x_preferred":[
        "\u041a\u0430\u0458\u0441"
    ],
    "name:ukr_x_preferred":[
        "\u041a\u0430\u0439\u0441\u0438\u0442\u0438"
    ],
    "wof:name":"Qays",
    "wof:placetype":"locality"
},
  "geometry": {"coordinates":[43.21628,17.1122],"type":"Point"}
}