{
  "type": "Feature",
  "properties": {
    "gn:admin1_code":"25.0",
    "gn:admin2_code":"1508.0",
    "gn:asciiname":"Al Mihawiyah",
    "gn:country_code":"YE",
    "gn:dem":153,
    "gn:feature_class":"P",
    "gn:feature_code":"PPL",
    "gn:name":"Al Mi\u1e29\u0101w\u012byah",
    "gn:population":0,
    "gn:timezone":"Asia/Aden",
    "iso:country":"YE",
    "name:und_x_variant":[
        "Al Mi\u1e29\u0101w\u012byah"
    ],
    "wof:name":"Al Mihawiyah",
    "wof:placetype":"locality"
},
  "geometry": {"coordinates":[43.46953,13.46505],"type":"Point"}
}