{
  "type": "Feature",
  "properties": {
    "gn:admin1_code":"24.0",
    "gn:admin2_code":"2512.0",
    "gn:asciiname":"Al Mislaq",
    "gn:country_code":"YE",
    "gn:dem":1413,
    "gn:feature_class":"P",
    "gn:feature_code":"PPL",
    "gn:name":"Al Misl\u0101q",
    "gn:population":0,
    "gn:timezone":"Asia/Aden",
    "iso:country":"YE",
    "name:ara_x_preferred":[
        "\u0627\u0644\u0645\u0633\u0644\u0627\u0642"
    ],
    "name:und_x_variant":[
        "Al Misl\u0101q"
    ],
    "wof:name":"Al Mislaq",
    "wof:placetype":"locality"
},
  "geometry": {"coordinates":[44.1889,13.16651],"type":"Point"}
}