{
  "type": "Feature",
  "properties": {
    "gn:admin1_code":"24.0",
    "gn:admin2_code":"2512.0",
    "gn:asciiname":"Rabtah",
    "gn:country_code":"YE",
    "gn:dem":1209,
    "gn:feature_class":"P",
    "gn:feature_code":"PPL",
    "gn:name":"Rab\u0163ah",
    "gn:population":0,
    "gn:timezone":"Asia/Aden",
    "iso:country":"YE",
    "name:ara_x_preferred":[
        "\u0631\u0628\u0637\u0629"
    ],
    "name:und_x_variant":[
        "Rab\u0163ah"
    ],
    "wof:name":"Rabtah",
    "wof:placetype":"locality"
},
  "geometry": {"coordinates":[44.19597,13.21261],"type":"Point"}
}