{
  "type": "Feature",
  "properties": {
    "gn:admin1_code":"11.0",
    "gn:admin2_code":"2004.0",
    "gn:asciiname":"Ad Dal`ayn",
    "gn:country_code":"YE",
    "gn:dem":2337,
    "gn:feature_class":"P",
    "gn:feature_code":"PPL",
    "gn:name":"A\u1e11 \u1e10al\u2018ayn",
    "gn:population":0,
    "gn:timezone":"Asia/Aden",
    "iso:country":"YE",
    "name:und_x_variant":[
        "A\u1e11 \u1e10al\u2018ayn"
    ],
    "wof:name":"Ad Dal`ayn",
    "wof:placetype":"locality"
},
  "geometry": {"coordinates":[44.12888,14.52806],"type":"Point"}
}