{
  "type": "Feature",
  "properties": {
    "gn:admin1_code":"22.0",
    "gn:admin2_code":"1727.0",
    "gn:asciiname":"Qal'at 'Ayshan",
    "gn:country_code":"YE",
    "gn:dem":1356,
    "gn:feature_class":"P",
    "gn:feature_code":"PPL",
    "gn:name":"Qal\u2018at \u2018Aysh\u0101n",
    "gn:population":0,
    "gn:timezone":"Asia/Aden",
    "iso:country":"YE",
    "name:ara_x_preferred":[
        "\u0642\u0644\u0639\u0629 \u0639\u064a\u0634\u0627\u0646"
    ],
    "name:und_x_variant":[
        "Qal\u2018at \u2018Aysh\u0101n"
    ],
    "wof:name":"Qal'at 'Ayshan",
    "wof:placetype":"locality"
},
  "geometry": {"coordinates":[43.62481,15.5561],"type":"Point"}
}