{
  "type": "Feature",
  "properties": {
    "gn:admin1_code":"8.0",
    "gn:admin2_code":"1802.0",
    "gn:asciiname":"Al Qamariyah",
    "gn:country_code":"YE",
    "gn:dem":19,
    "gn:feature_class":"P",
    "gn:feature_code":"PPL",
    "gn:name":"Al Qamar\u012byah",
    "gn:population":0,
    "gn:timezone":"Asia/Aden",
    "iso:country":"YE",
    "name:ara_x_preferred":[
        "\u0627\u0644\u0642\u0645\u0631\u064a\u0629"
    ],
    "name:und_x_variant":[
        "Al Qumr\u012byah",
        "Al Qamar\u012byah"
    ],
    "wof:name":"Al Qamariyah",
    "wof:placetype":"locality"
},
  "geometry": {"coordinates":[42.80619,15.72424],"type":"Point"}
}