{
  "type": "Feature",
  "properties": {
    "gn:admin1_code":"8.0",
    "gn:admin2_code":"1824.0",
    "gn:asciiname":"Al Haslub",
    "gn:country_code":"YE",
    "gn:dem":111,
    "gn:feature_class":"P",
    "gn:feature_code":"PPL",
    "gn:name":"Al \u1e28a\u015fl\u016bb",
    "gn:population":0,
    "gn:timezone":"Asia/Aden",
    "iso:country":"YE",
    "name:und_x_variant":[
        "Al \u1e28a\u015fl\u016bb"
    ],
    "wof:name":"Al Haslub",
    "wof:placetype":"locality"
},
  "geometry": {"coordinates":[43.32954,14.20235],"type":"Point"}
}