{
  "type": "Feature",
  "properties": {
    "gn:country":"YE",
    "gn:fcode":"PPL",
    "gn:pop":18,
    "iso:country":"YE",
    "name:ara_x_preferred":[
        "\u0622\u0644 \u0627\u0644\u0648\u0646\u0627\u0621"
    ],
    "name:eng_x_preferred":[
        "Al Al Wana"
    ],
    "qs:name":"\u0100l al Wan\u0101\u2019",
    "qs:photos_9r":0,
    "qs:photos_sr":0,
    "qs:pop_sr":"1",
    "wof:name":"\u0100l al Wan\u0101\u2019",
    "wof:placetype":"locality",
    "wof:population":18
},
  "geometry": {"coordinates":[43.77676,16.96697],"type":"Point"}
}