{
  "type": "Feature",
  "properties": {
    "gn:country":"YE",
    "gn:fcode":"PPLF",
    "gn:population":7,
    "iso:country":"YE",
    "name:ara_x_preferred":[
        "\u0100l Shib\u0101n"
    ],
    "name:ara_x_variant":[
        "\u0622\u0644 \u0627\u0644\u0634\u0628\u0627\u0646"
    ],
    "name:eng_x_preferred":[
        "Al Shiban"
    ],
    "name:eng_x_variant":[
        "Al \u1e28adabah"
    ],
    "qs:name":"\u0100l Shib\u0101n",
    "qs:photos_9r":0,
    "qs:photos_sr":0,
    "qs:pop_sr":"1",
    "wof:name":"\u0100l Shib\u0101n",
    "wof:placetype":"locality",
    "wof:population":7
},
  "geometry": {"coordinates":[43.62914,16.96469],"type":"Point"}
}