{
  "type": "Feature",
  "properties": {
    "gn:admin1_code":"19.0",
    "gn:admin2_code":"2901.0",
    "gn:asciiname":"Maqam ad Dawali",
    "gn:country_code":"YE",
    "gn:dem":2104,
    "gn:feature_class":"P",
    "gn:feature_code":"PPL",
    "gn:name":"Maq\u0101m ad D\u0101wal\u012b",
    "gn:population":0,
    "gn:timezone":"Asia/Aden",
    "iso:country":"YE",
    "name:und_x_variant":[
        "Maq\u0101m ad D\u0101wal\u012b"
    ],
    "wof:name":"Maqam ad Dawali",
    "wof:placetype":"locality"
},
  "geometry": {"coordinates":[43.91666,16.47739],"type":"Point"}
}