{
  "type": "Feature",
  "properties": {
    "gn:admin1_code":"4.0",
    "gn:admin2_code":"1928.0",
    "gn:asciiname":"Lawsar",
    "gn:country_code":"YE",
    "gn:dem":816,
    "gn:feature_class":"P",
    "gn:feature_code":"PPL",
    "gn:name":"Law\u015f\u0101r",
    "gn:population":0,
    "gn:timezone":"Asia/Aden",
    "iso:country":"YE",
    "name:und_x_variant":[
        "Law\u015f\u0101r"
    ],
    "wof:name":"Lawsar",
    "wof:placetype":"locality"
},
  "geometry": {"coordinates":[48.05,15.53333],"type":"Point"}
}