{
  "type": "Feature",
  "properties": {
    "gn:admin1_code":"16.0",
    "gn:admin2_code":"2303.0",
    "gn:asciiname":"Ar Rasras",
    "gn:country_code":"YE",
    "gn:dem":1804,
    "gn:feature_class":"P",
    "gn:feature_code":"PPL",
    "gn:name":"Ar Ra\u015fr\u0101\u015f",
    "gn:population":0,
    "gn:timezone":"Asia/Aden",
    "iso:country":"YE",
    "name:ara_x_preferred":[
        "\u0627\u0644\u0631\u0635\u0631\u0627\u0635"
    ],
    "name:und_x_variant":[
        "Ar Ra\u015fr\u0101\u015f"
    ],
    "wof:name":"Ar Rasras",
    "wof:placetype":"locality"
},
  "geometry": {"coordinates":[44.58765,15.51284],"type":"Point"}
}