{
  "type": "Feature",
  "properties": {
    "gn:gn_country":"YE",
    "gn:gn_fcode":"PPL",
    "gn:gn_pop":10,
    "gn:population":10,
    "iso:country":"YE",
    "name:ara_x_preferred":[
        "\u0639\u062c\u064a\u0645 \u0627\u0644\u0639\u0633\u0642"
    ],
    "name:eng_x_preferred":[
        "Ujaym Al 'Asaq"
    ],
    "qs_pg:aaroncc":"YE",
    "qs_pg:gn_country":"YE",
    "qs_pg:gn_fcode":"PPL",
    "qs_pg:gn_pop":10,
    "qs_pg:name":"\u2018Ujaym al \u2018Asaq",
    "qs_pg:photos_9r":0,
    "qs_pg:photos_sr":0,
    "qs_pg:pop_sr":1,
    "qs_pg:qs_pg_placetype":"locality",
    "wof:name":"\u2018Ujaym al \u2018Asaq",
    "wof:placetype":"locality",
    "wof:population":10
},
  "geometry": {"coordinates":[45.38889,14.69921],"type":"Point"}
}