{
  "type": "Feature",
  "properties": {
    "gn:admin1_code":"11.0",
    "gn:admin2_code":"2001.0",
    "gn:asciiname":"Al Ghurayqah",
    "gn:country_code":"YE",
    "gn:dem":2092,
    "gn:feature_class":"P",
    "gn:feature_code":"PPL",
    "gn:name":"Al Ghurayqah",
    "gn:population":0,
    "gn:timezone":"Asia/Aden",
    "iso:country":"YE",
    "wof:name":"Al Ghurayqah",
    "wof:placetype":"locality"
},
  "geometry": {"coordinates":[44.56269,14.80803],"type":"Point"}
}