{
  "type": "Feature",
  "properties": {
    "gn:admin1_code":"15.0",
    "gn:admin2_code":"2202.0",
    "gn:asciiname":"Baqbaqan",
    "gn:country_code":"YE",
    "gn:dem":1482,
    "gn:feature_class":"P",
    "gn:feature_code":"PPL",
    "gn:name":"Baqbaq\u0101n",
    "gn:population":0,
    "gn:timezone":"Asia/Aden",
    "iso:country":"YE",
    "name:ara_x_preferred":[
        "\u0628\u0642\u0628\u0642\u0627\u0646"
    ],
    "name:und_x_variant":[
        "Baqbaq\u0101n"
    ],
    "wof:name":"Baqbaqan",
    "wof:placetype":"locality"
},
  "geometry": {"coordinates":[43.24991,17.39699],"type":"Point"}
}