{
  "type": "Feature",
  "properties": {
    "gn:country":"YE",
    "gn:fcode":"PPL",
    "gn:pop":6,
    "iso:country":"YE",
    "name:ara_x_preferred":[
        "\u0627\u0644\u062e\u0631\u0642\u0629"
    ],
    "name:eng_x_preferred":[
        "Al Khariqah"
    ],
    "name:eng_x_variant":[
        "Dh\u016b Quray\u1e29"
    ],
    "qs:name":"Al Khariqah",
    "qs:photos_9r":0,
    "qs:photos_sr":0,
    "qs:pop_sr":"1",
    "wof:name":"Al Khariqah",
    "wof:placetype":"locality",
    "wof:population":6
},
  "geometry": {"coordinates":[43.35682,16.31452],"type":"Point"}
}