{
  "type": "Feature",
  "properties": {
    "gn:admin1_code":"23.0",
    "gn:admin2_code":"1101.0",
    "gn:asciiname":"Hisn Mukhtar",
    "gn:country_code":"YE",
    "gn:dem":1831,
    "gn:feature_class":"P",
    "gn:feature_code":"PPL",
    "gn:name":"\u1e28i\u015fn Mukht\u0101r",
    "gn:population":0,
    "gn:timezone":"Asia/Aden",
    "iso:country":"YE",
    "name:ara_x_preferred":[
        "\u062d\u0635\u0646 \u0645\u062e\u062a\u0627\u0631"
    ],
    "name:und_x_variant":[
        "\u1e28i\u015fn Mukht\u0101r"
    ],
    "wof:name":"Hisn Mukhtar",
    "wof:placetype":"locality"
},
  "geometry": {"coordinates":[44.24124000000001,14.25509],"type":"Point"}
}