{
  "type": "Feature",
  "properties": {
    "gn:admin1_code":"10.0",
    "gn:admin2_code":"2709.0",
    "gn:asciiname":"Bayt Dinas",
    "gn:country_code":"YE",
    "gn:dem":1546,
    "gn:feature_class":"P",
    "gn:feature_code":"PPL",
    "gn:name":"Bayt Din\u0101s",
    "gn:population":0,
    "gn:timezone":"Asia/Aden",
    "iso:country":"YE",
    "name:und_x_variant":[
        "Bayt Din\u0101s"
    ],
    "wof:name":"Bayt Dinas",
    "wof:placetype":"locality"
},
  "geometry": {"coordinates":[43.50762,15.4708],"type":"Point"}
}