{
  "type": "Feature",
  "properties": {
    "gn:admin1_code":"5.0",
    "gn:admin2_code":"2117.0",
    "gn:asciiname":"Al `Irqah",
    "gn:country_code":"YE",
    "gn:dem":12,
    "gn:feature_class":"P",
    "gn:feature_code":"PPL",
    "gn:name":"Al \u2018Irqah",
    "gn:population":0,
    "gn:timezone":"Asia/Aden",
    "iso:country":"YE",
    "name:ara_x_preferred":[
        "\u0627\u0644\u0639\u0631\u0642\u0629"
    ],
    "name:und_x_variant":[
        "\u2018Irqah",
        "\u2018Arqa",
        "\u2018Irka",
        "Irqa",
        "Al \u2018Irqah"
    ],
    "wof:name":"Al `Irqah",
    "wof:placetype":"locality"
},
  "geometry": {"coordinates":[47.35156,13.64854],"type":"Point"}
}