{
  "type": "Feature",
  "properties": {
    "gn:admin1_code":"23.0",
    "gn:admin2_code":"1104.0",
    "gn:asciiname":"Hafaf",
    "gn:country_code":"YE",
    "gn:dem":2495,
    "gn:feature_class":"P",
    "gn:feature_code":"PPL",
    "gn:name":"\u1e28af\u0101f",
    "gn:population":0,
    "gn:timezone":"Asia/Aden",
    "iso:country":"YE",
    "name:ara_x_preferred":[
        "\u062d\u0641\u0627\u0641"
    ],
    "name:und_x_variant":[
        "\u1e28af\u0101t",
        "\u1e28af\u0101f"
    ],
    "wof:name":"Hafaf",
    "wof:placetype":"locality"
},
  "geometry": {"coordinates":[44.45914000000001,14.07733],"type":"Point"}
}