{
  "type": "Feature",
  "properties": {
    "gn:admin1_code":"5.0",
    "gn:admin2_code":"2104.0",
    "gn:asciiname":"Qufl",
    "gn:country_code":"YE",
    "gn:dem":1155,
    "gn:feature_class":"P",
    "gn:feature_code":"PPL",
    "gn:name":"Qufl",
    "gn:population":0,
    "gn:timezone":"Asia/Aden",
    "iso:country":"YE",
    "wof:name":"Qufl",
    "wof:placetype":"locality"
},
  "geometry": {"coordinates":[47.26667,15.31667],"type":"Point"}
}