{
  "type": "Feature",
  "properties": {
    "gn:admin1_code":"19.0",
    "gn:admin2_code":"2901.0",
    "gn:asciiname":"Shaqih",
    "gn:country_code":"YE",
    "gn:dem":1740,
    "gn:feature_class":"P",
    "gn:feature_code":"PPL",
    "gn:name":"Sh\u0101qi\u1e29",
    "gn:population":0,
    "gn:timezone":"Asia/Aden",
    "iso:country":"YE",
    "name:ara_x_preferred":[
        "Sh\u0101qi\u1e29"
    ],
    "wof:name":"Shaqih",
    "wof:placetype":"locality"
},
  "geometry": {"coordinates":[43.99171,16.52172],"type":"Point"}
}