{
  "type": "Feature",
  "properties": {
    "gn:country":"YE",
    "gn:fcode":"PPL",
    "gn:pop":13,
    "iso:country":"YE",
    "name:ara_x_preferred":[
        "\u0645\u062d\u0648\u0644\u0629"
    ],
    "name:eng_x_preferred":[
        "Mahawlah"
    ],
    "name:eng_x_variant":[
        "Ash Sha\u2019f"
    ],
    "qs:name":"Ma\u1e29awlah",
    "qs:photos_9r":0,
    "qs:photos_sr":0,
    "qs:pop_sr":"1",
    "wof:name":"Ma\u1e29awlah",
    "wof:placetype":"locality",
    "wof:population":13
},
  "geometry": {"coordinates":[43.29985,16.88106],"type":"Point"}
}