{
  "type": "Feature",
  "properties": {
    "gn:admin1_code":"14.0",
    "gn:admin2_code":"2608.0",
    "gn:asciiname":"Dhira` Ramadah",
    "gn:country_code":"YE",
    "gn:dem":1862,
    "gn:feature_class":"P",
    "gn:feature_code":"PPL",
    "gn:name":"Dhir\u0101\u2018 Ram\u0101dah",
    "gn:population":0,
    "gn:timezone":"Asia/Aden",
    "iso:country":"YE",
    "name:und_x_variant":[
        "Dhir\u0101\u2018 Ram\u0101dah"
    ],
    "wof:name":"Dhira` Ramadah",
    "wof:placetype":"locality"
},
  "geometry": {"coordinates":[45.12178,14.91346],"type":"Point"}
}