{
  "type": "Feature",
  "properties": {
    "gn:admin1_code":"25.0",
    "gn:admin2_code":"1517.0",
    "gn:asciiname":"Qaryat Dhuwab",
    "gn:country_code":"YE",
    "gn:dem":1419,
    "gn:feature_class":"P",
    "gn:feature_code":"PPL",
    "gn:name":"Qaryat Dhuw\u0101b",
    "gn:population":0,
    "gn:timezone":"Asia/Aden",
    "iso:country":"YE",
    "name:und_x_variant":[
        "Qaryat Dhuw\u0101b"
    ],
    "wof:name":"Qaryat Dhuwab",
    "wof:placetype":"locality"
},
  "geometry": {"coordinates":[44.25212,13.30964],"type":"Point"}
}