{
  "type": "Feature",
  "properties": {
    "gn:admin1_code":"11.0",
    "gn:admin2_code":"1102.0",
    "gn:asciiname":"Dimas",
    "gn:country_code":"YE",
    "gn:dem":2529,
    "gn:feature_class":"P",
    "gn:feature_code":"PPL",
    "gn:name":"Dim\u0101s",
    "gn:population":0,
    "gn:timezone":"Asia/Aden",
    "iso:country":"YE",
    "name:ara_x_preferred":[
        "\u062f\u0645\u0627\u0633"
    ],
    "name:ara_x_variant":[
        "\u062f\u064a\u0645\u0627\u0633"
    ],
    "name:ceb_x_preferred":[
        "Dimas"
    ],
    "name:deu_x_preferred":[
        "Dimas"
    ],
    "name:ita_x_preferred":[
        "Dimas"
    ],
    "name:nds_x_preferred":[
        "Dimas"
    ],
    "name:por_x_preferred":[
        "Dimas"
    ],
    "name:rus_x_preferred":[
        "\u0414\u0438\u043c\u0430\u0441"
    ],
    "name:spa_x_preferred":[
        "Dimas"
    ],
    "name:srp_x_preferred":[
        "\u0414\u0438\u043c\u0430\u0441"
    ],
    "name:swe_x_preferred":[
        "Dimas"
    ],
    "name:tgl_x_preferred":[
        "Dimas"
    ],
    "name:und_x_variant":[
        "Dam\u0101s",
        "Dim\u0101s"
    ],
    "wof:name":"Dimas",
    "wof:placetype":"locality"
},
  "geometry": {"coordinates":[44.43,14.32638],"type":"Point"}
}