{
  "type": "Feature",
  "properties": {
    "gn:gn_country":"YE",
    "gn:gn_fcode":"PPLX",
    "gn:gn_pop":2,
    "gn:population":2,
    "iso:country":"YE",
    "name:ara_x_preferred":[
        "\u0641\u0648\u0642 \u0627\u0644\u0637\u0640\u0648\u0641"
    ],
    "qs_pg:aaroncc":"YE",
    "qs_pg:gn_country":"YE",
    "qs_pg:gn_fcode":"PPLX",
    "qs_pg:gn_pop":2,
    "qs_pg:name":"Fawq a\u0163 \u0162awf",
    "qs_pg:photos_9r":0,
    "qs_pg:photos_sr":0,
    "qs_pg:pop_sr":1,
    "qs_pg:qs_pg_placetype":"neighbourhood",
    "wof:name":"Fawq a\u0163 \u0162awf",
    "wof:placetype":"neighbourhood",
    "wof:population":2
},
  "geometry": {"coordinates":[43.70084,16.18589],"type":"Point"}
}