{
  "type": "Feature",
  "properties": {
    "gn:admin1_code":"19.0",
    "gn:admin2_code":"2919.0",
    "gn:asciiname":"Ar Rashid",
    "gn:country_code":"YE",
    "gn:dem":1582,
    "gn:feature_class":"P",
    "gn:feature_code":"PPL",
    "gn:name":"Ar R\u0101shid",
    "gn:population":0,
    "gn:timezone":"Asia/Aden",
    "iso:country":"YE",
    "name:ara_x_preferred":[
        "Ar R\u0101shid"
    ],
    "name:ara_x_variant":[
        "\u0627\u0644\u0631\u0627\u0634\u062f"
    ],
    "wof:name":"Ar Rashid",
    "wof:placetype":"locality"
},
  "geometry": {"coordinates":[43.84205,16.08815],"type":"Point"}
}