{
  "type": "Feature",
  "properties": {
    "gn:admin1_code":"10.0",
    "gn:admin2_code":"2705.0",
    "gn:asciiname":"Sharaf",
    "gn:country_code":"YE",
    "gn:dem":1724,
    "gn:feature_class":"P",
    "gn:feature_code":"PPL",
    "gn:name":"Sharaf",
    "gn:population":0,
    "gn:timezone":"Asia/Aden",
    "iso:country":"YE",
    "wof:name":"Sharaf",
    "wof:placetype":"locality"
},
  "geometry": {"coordinates":[43.36696,15.29499],"type":"Point"}
}