{
  "type": "Feature",
  "properties": {
    "gn:admin1_code":"10.0",
    "gn:admin2_code":"2705.0",
    "gn:asciiname":"Sharaf",
    "gn:country_code":"YE",
    "gn:dem":1724,
    "gn:feature_class":"P",
    "gn:feature_code":"PPL",
    "gn:name":"Sharaf",
    "gn:population":0,
    "gn:timezone":"Asia/Aden",
    "iso:country":"YE",
    "name:deu_x_preferred":[
        "Sharaf"
    ],
    "name:fas_x_preferred":[
        "\u0634\u0631\u0641"
    ],
    "name:ita_x_preferred":[
        "Sharaf"
    ],
    "name:rus_x_preferred":[
        "\u0428\u0430\u0440\u0430\u0444"
    ],
    "name:tat_x_preferred":[
        "\u0428\u04d9\u0440\u04d9\u0444"
    ],
    "name:ukr_x_preferred":[
        "\u0428\u0430\u0440\u0430\u0444"
    ],
    "wof:name":"Sharaf",
    "wof:placetype":"locality"
},
  "geometry": {"coordinates":[43.36696,15.29499],"type":"Point"}
}