{
  "type": "Feature",
  "properties": {
    "gn:admin1_code":"25.0",
    "gn:admin2_code":"1509.0",
    "gn:asciiname":"Adh Dhanabah",
    "gn:country_code":"YE",
    "gn:dem":767,
    "gn:feature_class":"P",
    "gn:feature_code":"PPL",
    "gn:name":"Adh Dhanabah",
    "gn:population":0,
    "gn:timezone":"Asia/Aden",
    "iso:country":"YE",
    "name:ara_x_preferred":[
        "\u0627\u0644\u0630\u0646\u0628\u0629"
    ],
    "wof:name":"Adh Dhanabah",
    "wof:placetype":"locality"
},
  "geometry": {"coordinates":[43.84627,13.37177],"type":"Point"}
}