{
  "type": "Feature",
  "properties": {
    "gn:country":"YE",
    "gn:fcode":"PPL",
    "gn:population":3,
    "iso:country":"YE",
    "name:ara_x_preferred":[
        "\u0627\u0644\u0642\u0636\u064a\u0644"
    ],
    "name:eng_x_preferred":[
        "Al Quuayl"
    ],
    "name:eng_x_variant":[
        "N\u0101qiz\u0327 al \u2018Uly\u0101"
    ],
    "qs:name":"Al Qu\u1e11ayl",
    "qs:photos_9r":0,
    "qs:photos_sr":0,
    "qs:pop_sr":"1",
    "wof:name":"Al Qu\u1e11ayl",
    "wof:placetype":"locality",
    "wof:population":3
},
  "geometry": {"coordinates":[45.17414,14.74569],"type":"Point"}
}