{
  "type": "Feature",
  "properties": {
    "gn:admin1_code":"24.0",
    "gn:admin2_code":"2501.0",
    "gn:asciiname":"Bani Bakr",
    "gn:country_code":"YE",
    "gn:dem":2154,
    "gn:feature_class":"P",
    "gn:feature_code":"PPLA2",
    "gn:name":"Ban\u012b Bakr",
    "gn:population":0,
    "gn:timezone":"Asia/Aden",
    "iso:country":"YE",
    "name:ara_x_preferred":[
        "\u0628\u0646\u064a \u0628\u0643\u0631"
    ],
    "name:und_x_variant":[
        "Ban\u012b Baq",
        "Ban\u012b Bakk",
        "Ban\u012b Bakr"
    ],
    "wof:name":"Bani Bakr",
    "wof:placetype":"locality"
},
  "geometry": {"coordinates":[45.26667,13.93333],"type":"Point"}
}