{
  "type": "Feature",
  "properties": {
    "gn:country":"YE",
    "gn:fcode":"PPL",
    "gn:pop":21,
    "iso:country":"YE",
    "name:ara_x_preferred":[
        "\u0628\u064a\u062a \u0627\u0644\u0648\u064a\u0634"
    ],
    "name:eng_x_preferred":[
        "Bayt Al Waysh"
    ],
    "name:eng_x_variant":[
        "Al Jal\u2018ah \u0100l Sham\u2018ah"
    ],
    "qs:name":"Bayt al Waysh",
    "qs:photos_9r":0,
    "qs:photos_sr":0,
    "qs:pop_sr":"1",
    "wof:name":"Bayt al Waysh",
    "wof:placetype":"locality",
    "wof:population":21
},
  "geometry": {"coordinates":[44.49012,16.68767],"type":"Point"}
}