{
  "type": "Feature",
  "properties": {
    "gn:admin1_code":"19.0",
    "gn:admin2_code":"2913.0",
    "gn:asciiname":"Bani `Azzam",
    "gn:country_code":"YE",
    "gn:dem":1294,
    "gn:feature_class":"P",
    "gn:feature_code":"PPL",
    "gn:name":"Ban\u012b \u2018Azz\u0101m",
    "gn:population":0,
    "gn:timezone":"Asia/Aden",
    "iso:country":"YE",
    "name:und_x_variant":[
        "Ban\u012b \u2018Azz\u0101m"
    ],
    "wof:name":"Bani `Azzam",
    "wof:placetype":"locality"
},
  "geometry": {"coordinates":[43.76949000000001,15.89939],"type":"Point"}
}