{
  "type": "Feature",
  "properties": {
    "gn:country":"YE",
    "gn:fcode":"PPLX",
    "gn:population":3,
    "iso:country":"YE",
    "name:ara_x_preferred":[
        "\u0623\u062f\u063a\u064a\u0644"
    ],
    "qs:name":"Adghayl",
    "qs:photos_9r":0,
    "qs:photos_sr":0,
    "qs:pop_sr":"1",
    "wof:name":"Adghayl",
    "wof:placetype":"neighbourhood",
    "wof:population":3
},
  "geometry": {"coordinates":[43.3832,17.29166],"type":"Point"}
}