{
  "type": "Feature",
  "properties": {
    "gn:admin1_code":"22.0",
    "gn:admin2_code":"1717.0",
    "gn:asciiname":"Qaryat Majil Sa`id",
    "gn:country_code":"YE",
    "gn:dem":1414,
    "gn:feature_class":"P",
    "gn:feature_code":"PPL",
    "gn:name":"Qaryat M\u0101jil Sa\u2018\u012bd",
    "gn:population":0,
    "gn:timezone":"Asia/Aden",
    "iso:country":"YE",
    "name:und_x_variant":[
        "Qaryat M\u0101jil Sa\u2018\u012bd"
    ],
    "wof:name":"Qaryat Majil Sa`id",
    "wof:placetype":"locality"
},
  "geometry": {"coordinates":[43.62018,15.83635],"type":"Point"}
}