{
  "type": "Feature",
  "properties": {
    "gn:admin1_code":"11.0",
    "gn:admin2_code":"2010.0",
    "gn:asciiname":"Najd al Aslaq",
    "gn:country_code":"YE",
    "gn:dem":2609,
    "gn:feature_class":"P",
    "gn:feature_code":"PPL",
    "gn:name":"Najd al Asl\u0101q",
    "gn:population":0,
    "gn:timezone":"Asia/Aden",
    "iso:country":"YE",
    "name:und_x_variant":[
        "Najd al Asl\u0101q"
    ],
    "wof:name":"Najd al Aslaq",
    "wof:placetype":"locality"
},
  "geometry": {"coordinates":[44.38335,14.36693],"type":"Point"}
}