{
  "type": "Feature",
  "properties": {
    "gn:admin1_code":"20.0",
    "gn:admin2_code":"1414.0",
    "gn:asciiname":"Mawka'",
    "gn:country_code":"YE",
    "gn:dem":2113,
    "gn:feature_class":"P",
    "gn:feature_code":"PPL",
    "gn:name":"Mawk\u0101\u2019",
    "gn:population":0,
    "gn:timezone":"Asia/Aden",
    "iso:country":"YE",
    "name:ara_x_preferred":[
        "\u0645\u0648\u0643\u0627\u0621"
    ],
    "name:und_x_variant":[
        "Mawk\u0101\u2019"
    ],
    "wof:name":"Mawka'",
    "wof:placetype":"locality"
},
  "geometry": {"coordinates":[44.86221,14.48185],"type":"Point"}
}