{
  "type": "Feature",
  "properties": {
    "gn:country":"YE",
    "gn:fcode":"PPL",
    "gn:population":3,
    "iso:country":"YE",
    "name:ara_x_preferred":[
        "\u062f\u0627\u0631 \u0627\u0644\u0633\u0644\u0628"
    ],
    "name:eng_x_preferred":[
        "Dar As Salib"
    ],
    "name:eng_x_variant":[
        "Sha\u2018b al \u1e28\u012byah"
    ],
    "qs:name":"Dar as Salib",
    "qs:photos_9r":0,
    "qs:photos_sr":0,
    "qs:pop_sr":"1",
    "wof:name":"Dar as Salib",
    "wof:placetype":"locality",
    "wof:population":3
},
  "geometry": {"coordinates":[43.46455,16.10423],"type":"Point"}
}