{
  "type": "Feature",
  "properties": {
    "gn:admin1_code":"11.0",
    "gn:admin2_code":"2005.0",
    "gn:asciiname":"Al Ahjaf",
    "gn:country_code":"YE",
    "gn:dem":1958,
    "gn:feature_class":"P",
    "gn:feature_code":"PPL",
    "gn:name":"Al A\u1e29jaf",
    "gn:population":0,
    "gn:timezone":"Asia/Aden",
    "iso:country":"YE",
    "name:und_x_variant":[
        "Al A\u1e29jaf"
    ],
    "wof:name":"Al Ahjaf",
    "wof:placetype":"locality"
},
  "geometry": {"coordinates":[44.00921,14.50644],"type":"Point"}
}