{
  "type": "Feature",
  "properties": {
    "gn:admin1_code":"16.0",
    "gn:admin2_code":"2302.0",
    "gn:asciiname":"Khibat Hizam",
    "gn:country_code":"YE",
    "gn:dem":2621,
    "gn:feature_class":"P",
    "gn:feature_code":"PPL",
    "gn:name":"Khibat Hizam",
    "gn:population":0,
    "gn:timezone":"Asia/Aden",
    "iso:country":"YE",
    "name:ara_x_preferred":[
        "\u062e\u0628\u0629 \u0647\u0632\u0645"
    ],
    "wof:name":"Khibat Hizam",
    "wof:placetype":"locality"
},
  "geometry": {"coordinates":[44.14375,15.69932],"type":"Point"}
}