{
  "type": "Feature",
  "properties": {
    "gn:admin1_code":"11.0",
    "gn:admin2_code":"2007.0",
    "gn:asciiname":"As Sahlah `Aris",
    "gn:country_code":"YE",
    "gn:dem":1130,
    "gn:feature_class":"P",
    "gn:feature_code":"PPL",
    "gn:name":"As Sahlah \u2018\u0100ris",
    "gn:population":0,
    "gn:timezone":"Asia/Aden",
    "iso:country":"YE",
    "name:und_x_variant":[
        "As Sahlah \u2018\u0100ris"
    ],
    "wof:name":"As Sahlah `Aris",
    "wof:placetype":"locality"
},
  "geometry": {"coordinates":[43.55236,14.25132],"type":"Point"}
}