{
  "type": "Feature",
  "properties": {
    "gn:country":"YE",
    "gn:fcode":"PPL",
    "gn:population":4,
    "iso:country":"YE",
    "name:ara_x_preferred":[
        "Bi\u2019r \u2018Anq\u0101n"
    ],
    "name:ara_x_variant":[
        "\u0628\u064a\u0631 \u0639\u0646\u0642\u0627\u0646"
    ],
    "name:eng_x_preferred":[
        "Bir 'Anqan"
    ],
    "name:eng_x_variant":[
        "Bayt al Qal\u2018ah"
    ],
    "qs:name":"Bi\u2019r \u2018Anq\u0101n",
    "qs:photos_9r":0,
    "qs:photos_sr":0,
    "qs:pop_sr":"1",
    "wof:name":"Bi\u2019r \u2018Anq\u0101n",
    "wof:placetype":"locality",
    "wof:population":4
},
  "geometry": {"coordinates":[43.57719,17.06494],"type":"Point"}
}