{
  "type": "Feature",
  "properties": {
    "gn:admin1_code":"4.0",
    "gn:admin2_code":"1918.0",
    "gn:asciiname":"Subaykh",
    "gn:cc2":"YE",
    "gn:country_code":"YE",
    "gn:dem":1099,
    "gn:feature_class":"P",
    "gn:feature_code":"PPL",
    "gn:name":"Subaykh",
    "gn:population":0,
    "gn:timezone":"Asia/Aden",
    "iso:country":"YE",
    "name:nno_x_preferred":[
        "Subaykh"
    ],
    "name:und_x_variant":[
        "Subaikh"
    ],
    "wof:name":"Subaykh",
    "wof:placetype":"locality"
},
  "geometry": {"coordinates":[48.36778,15.23194],"type":"Point"}
}