{
  "type": "Feature",
  "properties": {
    "gn:admin1_code":"8.0",
    "gn:admin2_code":"1810.0",
    "gn:asciiname":"Ash Shakhiyah",
    "gn:country_code":"YE",
    "gn:dem":112,
    "gn:feature_class":"P",
    "gn:feature_code":"PPL",
    "gn:name":"Ash Sh\u0101khiyah",
    "gn:population":0,
    "gn:timezone":"Asia/Aden",
    "iso:country":"YE",
    "name:und_x_variant":[
        "Ash Sh\u0101khiyah"
    ],
    "wof:name":"Ash Shakhiyah",
    "wof:placetype":"locality"
},
  "geometry": {"coordinates":[43.15249,15.11804],"type":"Point"}
}