{
  "type": "Feature",
  "properties": {
    "gn:admin1_code":"21.0",
    "gn:admin2_code":"1605.0",
    "gn:asciiname":"Al Muraqqa`ah",
    "gn:country_code":"YE",
    "gn:dem":1075,
    "gn:feature_class":"P",
    "gn:feature_code":"PPL",
    "gn:name":"Al Muraqqa\u2018ah",
    "gn:population":0,
    "gn:timezone":"Asia/Aden",
    "iso:country":"YE",
    "name:ara_x_preferred":[
        "\u0627\u0644\u0645\u0631\u0642\u0639\u0629"
    ],
    "name:und_x_variant":[
        "Al Muraqqa\u2018ah"
    ],
    "wof:name":"Al Muraqqa`ah",
    "wof:placetype":"locality"
},
  "geometry": {"coordinates":[44.94971,16.06846],"type":"Point"}
}