{
  "type": "Feature",
  "properties": {
    "gn:admin1_code":"14.0",
    "gn:admin2_code":"2606.0",
    "gn:asciiname":"Sha`b ar Rub`ah",
    "gn:country_code":"YE",
    "gn:dem":1500,
    "gn:feature_class":"P",
    "gn:feature_code":"PPL",
    "gn:name":"Sha\u2018b ar Rub\u2018ah",
    "gn:population":0,
    "gn:timezone":"Asia/Aden",
    "iso:country":"YE",
    "name:ara_x_preferred":[
        "\u0634\u0639\u0628 \u0627\u0644\u0631\u0628\u0639\u0629"
    ],
    "name:und_x_variant":[
        "Sha\u2018b ar Rub\u2018ah"
    ],
    "wof:name":"Sha`b ar Rub`ah",
    "wof:placetype":"locality"
},
  "geometry": {"coordinates":[45.04825,15.44502],"type":"Point"}
}