{
  "type": "Feature",
  "properties": {
    "gn:admin1_code":"16.0",
    "gn:admin2_code":"2312.0",
    "gn:asciiname":"Al Masna'ah",
    "gn:country_code":"YE",
    "gn:dem":1640,
    "gn:feature_class":"P",
    "gn:feature_code":"PPL",
    "gn:name":"Al Ma\u015fna\u2018ah",
    "gn:population":0,
    "gn:timezone":"Asia/Aden",
    "iso:country":"YE",
    "name:ara_x_preferred":[
        "\u0627\u0644\u0645\u0635\u0646\u0639\u0629"
    ],
    "name:und_x_variant":[
        "Al Ma\u015fna\u2018ah"
    ],
    "wof:name":"Al Masna'ah",
    "wof:placetype":"locality"
},
  "geometry": {"coordinates":[44.85751,15.28915],"type":"Point"}
}