{
  "type": "Feature",
  "properties": {
    "gn:admin1_code":"23.0",
    "gn:admin2_code":"1101.0",
    "gn:asciiname":"Salahah",
    "gn:country_code":"YE",
    "gn:dem":1236,
    "gn:feature_class":"P",
    "gn:feature_code":"PPL",
    "gn:name":"\u015eal\u0101\u1e29ah",
    "gn:population":0,
    "gn:timezone":"Asia/Aden",
    "iso:country":"YE",
    "name:ara_x_preferred":[
        "\u0635\u0644\u0627\u062d\u0629"
    ],
    "name:und_x_variant":[
        "\u015eal\u0101\u1e29ah"
    ],
    "wof:name":"Salahah",
    "wof:placetype":"locality"
},
  "geometry": {"coordinates":[44.00249,14.33567],"type":"Point"}
}