{
  "type": "Feature",
  "properties": {
    "gn:admin1_code":"21.0",
    "gn:admin2_code":"1601.0",
    "gn:asciiname":"Al Abraq",
    "gn:country_code":"YE",
    "gn:dem":1441,
    "gn:feature_class":"P",
    "gn:feature_code":"PPL",
    "gn:name":"Al Abraq",
    "gn:population":0,
    "gn:timezone":"Asia/Aden",
    "iso:country":"YE",
    "wof:name":"Al Abraq",
    "wof:placetype":"locality"
},
  "geometry": {"coordinates":[44.83478,16.70837],"type":"Point"}
}