{
  "type": "Feature",
  "properties": {
    "gn:admin1_code":"25.0",
    "gn:admin2_code":"1513.0",
    "gn:asciiname":"Al Lukaymah",
    "gn:country_code":"YE",
    "gn:dem":1043,
    "gn:feature_class":"P",
    "gn:feature_code":"PPL",
    "gn:name":"Al Lukaymah",
    "gn:population":0,
    "gn:timezone":"Asia/Aden",
    "iso:country":"YE",
    "name:und_x_variant":[
        "Ukaymah"
    ],
    "wof:name":"Al Lukaymah",
    "wof:placetype":"locality"
},
  "geometry": {"coordinates":[44.31403,13.37143],"type":"Point"}
}