{
  "type": "Feature",
  "properties": {
    "gn:country":"YE",
    "gn:fcode":"PPL",
    "gn:population":1,
    "iso:country":"YE",
    "name:ara_x_preferred":[
        "\u0635\u0646\u0639\u0627\u0621 \u0645\u0639\u064a\u0646"
    ],
    "name:eng_x_preferred":[
        "San'a Ma'in"
    ],
    "name:eng_x_variant":[
        "\u2018Amr\u0101n"
    ],
    "qs:name":"\u015ean\u2018\u0101\u2019 Ma\u2018\u012bn",
    "qs:photos_9r":0,
    "qs:photos_sr":0,
    "qs:pop_sr":"1",
    "wof:name":"\u015ean\u2018\u0101\u2019 Ma\u2018\u012bn",
    "wof:placetype":"locality",
    "wof:population":1
},
  "geometry": {"coordinates":[44.79846,16.13082],"type":"Point"}
}