{
  "type": "Feature",
  "properties": {
    "gn:admin1_code":"25.0",
    "gn:admin2_code":"1503.0",
    "gn:asciiname":"Ar Rujmah",
    "gn:country_code":"YE",
    "gn:dem":1284,
    "gn:feature_class":"P",
    "gn:feature_code":"PPL",
    "gn:name":"Ar Rujmah",
    "gn:population":0,
    "gn:timezone":"Asia/Aden",
    "iso:country":"YE",
    "wof:name":"Ar Rujmah",
    "wof:placetype":"locality"
},
  "geometry": {"coordinates":[43.89337,13.79258],"type":"Point"}
}