{
  "type": "Feature",
  "properties": {
    "gn:admin1_code":"23.0",
    "gn:admin2_code":"1120.0",
    "gn:asciiname":"Al Mana'i",
    "gn:country_code":"YE",
    "gn:dem":2521,
    "gn:feature_class":"P",
    "gn:feature_code":"PPL",
    "gn:name":"Al Man\u0101\u2019\u012b",
    "gn:population":0,
    "gn:timezone":"Asia/Aden",
    "iso:country":"YE",
    "name:ara_x_preferred":[
        "\u0627\u0644\u0645\u0646\u0627\u0626\u064a"
    ],
    "name:und_x_variant":[
        "Al Man\u0101\u2019\u012b"
    ],
    "wof:name":"Al Mana'i",
    "wof:placetype":"locality"
},
  "geometry": {"coordinates":[44.08861,14.02664],"type":"Point"}
}