{
  "type": "Feature",
  "properties": {
    "gn:admin1_code":"19.0",
    "gn:admin2_code":"2908.0",
    "gn:asciiname":"Al Mi'zab",
    "gn:country_code":"YE",
    "gn:dem":1604,
    "gn:feature_class":"P",
    "gn:feature_code":"PPL",
    "gn:name":"Al Mi\u2018z\u0101b",
    "gn:population":0,
    "gn:timezone":"Asia/Aden",
    "iso:country":"YE",
    "name:ara_x_preferred":[
        "Al Mi\u2018z\u0101b"
    ],
    "name:ara_x_variant":[
        "\u0627\u0644\u0645\u0639\u0632\u0627\u0628"
    ],
    "wof:name":"Al Mi'zab",
    "wof:placetype":"locality"
},
  "geometry": {"coordinates":[43.68545,16.04039],"type":"Point"}
}