{
  "type": "Feature",
  "properties": {
    "gn:admin1_code":"23.0",
    "gn:admin2_code":"1117.0",
    "gn:asciiname":"Jarif",
    "gn:country_code":"YE",
    "gn:dem":2180,
    "gn:feature_class":"P",
    "gn:feature_code":"PPL",
    "gn:name":"Jarif",
    "gn:population":0,
    "gn:timezone":"Asia/Aden",
    "iso:country":"YE",
    "name:nno_x_preferred":[
        "Jarif"
    ],
    "wof:name":"Jarif",
    "wof:placetype":"locality"
},
  "geometry": {"coordinates":[43.96511,13.8729],"type":"Point"}
}