{
  "type": "Feature",
  "properties": {
    "gn:admin1_code":"22.0",
    "gn:admin2_code":"1725.0",
    "gn:asciiname":"Al Mantaha",
    "gn:country_code":"YE",
    "gn:dem":688,
    "gn:feature_class":"P",
    "gn:feature_code":"PPL",
    "gn:name":"Al Man\u0163a\u1e29\u00e1",
    "gn:population":0,
    "gn:timezone":"Asia/Aden",
    "iso:country":"YE",
    "name:ara_x_preferred":[
        "\u0627\u0644\u0645\u0646\u0637\u062d\u0640\u0640\u0649"
    ],
    "name:und_x_variant":[
        "Al Man\u0163a\u1e29\u00e1"
    ],
    "wof:name":"Al Mantaha",
    "wof:placetype":"locality"
},
  "geometry": {"coordinates":[43.5011,15.56695],"type":"Point"}
}