{
  "type": "Feature",
  "properties": {
    "gn:admin1_code":"23.0",
    "gn:admin2_code":"1105.0",
    "gn:asciiname":"Khazran",
    "gn:country_code":"YE",
    "gn:dem":2343,
    "gn:feature_class":"P",
    "gn:feature_code":"PPL",
    "gn:name":"Khazr\u0101n",
    "gn:population":0,
    "gn:timezone":"Asia/Aden",
    "iso:country":"YE",
    "name:ara_x_preferred":[
        "\u062e\u0632\u0631\u0627\u0646"
    ],
    "name:und_x_variant":[
        "Khazar\u0101n",
        "Khazr\u0101n"
    ],
    "wof:name":"Khazran",
    "wof:placetype":"locality"
},
  "geometry": {"coordinates":[44.37723,14.04589],"type":"Point"}
}