{
  "type": "Feature",
  "properties": {
    "gn:admin1_code":"19.0",
    "gn:admin2_code":"2914.0",
    "gn:asciiname":"Shi`b Bani Humaydan",
    "gn:country_code":"YE",
    "gn:dem":1472,
    "gn:feature_class":"P",
    "gn:feature_code":"PPL",
    "gn:name":"Shi\u2018b Ban\u012b \u1e28umayd\u0101n",
    "gn:population":0,
    "gn:timezone":"Asia/Aden",
    "iso:country":"YE",
    "name:und_x_variant":[
        "Shi\u2018b Ban\u012b \u1e28umayd\u0101n"
    ],
    "wof:name":"Shi`b Bani Humaydan",
    "wof:placetype":"locality"
},
  "geometry": {"coordinates":[43.74017,15.7751],"type":"Point"}
}