{
  "type": "Feature",
  "properties": {
    "gn:admin1_code":"19.0",
    "gn:admin2_code":"2920.0",
    "gn:asciiname":"Bani Hawmi",
    "gn:country_code":"YE",
    "gn:dem":2242,
    "gn:feature_class":"P",
    "gn:feature_code":"PPL",
    "gn:name":"Ban\u012b \u1e28awm\u012b",
    "gn:population":0,
    "gn:timezone":"Asia/Aden",
    "iso:country":"YE",
    "name:und_x_variant":[
        "Ban\u012b \u1e28awm\u012b"
    ],
    "wof:name":"Bani Hawmi",
    "wof:placetype":"locality"
},
  "geometry": {"coordinates":[43.96667,16.15],"type":"Point"}
}