{
  "type": "Feature",
  "properties": {
    "gn:admin1_code":"1.0",
    "gn:admin2_code":"1211.0",
    "gn:asciiname":"Ar Rawwa",
    "gn:country_code":"YE",
    "gn:dem":106,
    "gn:feature_class":"P",
    "gn:feature_code":"PPL",
    "gn:name":"Ar Raww\u0101",
    "gn:population":0,
    "gn:timezone":"Asia/Aden",
    "iso:country":"YE",
    "name:nno_x_preferred":[
        "Ar Rawwa"
    ],
    "name:und_x_variant":[
        "Ar Raww\u0101"
    ],
    "wof:name":"Ar Rawwa",
    "wof:placetype":"locality"
},
  "geometry": {"coordinates":[45.28167,13.28028],"type":"Point"}
}