{
  "type": "Feature",
  "properties": {
    "gn:admin1_code":"4.0",
    "gn:admin2_code":"1922.0",
    "gn:asciiname":"Al Hinw",
    "gn:cc2":"YE",
    "gn:country_code":"YE",
    "gn:dem":1435,
    "gn:feature_class":"P",
    "gn:feature_code":"PPL",
    "gn:name":"Al \u1e28inw",
    "gn:population":0,
    "gn:timezone":"Asia/Aden",
    "iso:country":"YE",
    "name:ara_x_preferred":[
        "Al \u1e28inw"
    ],
    "name:und_x_variant":[
        "Al-\u1e24in\u016b"
    ],
    "wof:name":"Al Hinw",
    "wof:placetype":"locality"
},
  "geometry": {"coordinates":[48.03333,15.03333],"type":"Point"}
}