{
  "type": "Feature",
  "properties": {
    "gn:admin1_code":"24.0",
    "gn:admin2_code":"2509.0",
    "gn:asciiname":"Sirhan",
    "gn:cc2":"YE",
    "gn:country_code":"YE",
    "gn:dem":467,
    "gn:feature_class":"P",
    "gn:feature_code":"PPL",
    "gn:name":"Sir\u1e29\u0101n",
    "gn:population":0,
    "gn:timezone":"Asia/Aden",
    "iso:country":"YE",
    "name:ara_x_preferred":[
        "Sir\u1e29\u0101n"
    ],
    "name:und_x_variant":[
        "Sarhan"
    ],
    "wof:name":"Sirhan",
    "wof:placetype":"locality"
},
  "geometry": {"coordinates":[44.66667,13.35],"type":"Point"}
}