{
  "type": "Feature",
  "properties": {
    "gn:admin1_code":"23.0",
    "gn:admin2_code":"1115.0",
    "gn:asciiname":"Ikd al Jawazi`",
    "gn:country_code":"YE",
    "gn:dem":2062,
    "gn:feature_class":"P",
    "gn:feature_code":"PPL",
    "gn:name":"Ikd al Jaw\u0101zi\u2018",
    "gn:population":0,
    "gn:timezone":"Asia/Aden",
    "iso:country":"YE",
    "name:und_x_variant":[
        "Ikd al Jaw\u0101zi\u2018"
    ],
    "wof:name":"Ikd al Jawazi`",
    "wof:placetype":"locality"
},
  "geometry": {"coordinates":[44.20035,13.88587],"type":"Point"}
}