{
  "type": "Feature",
  "properties": {
    "gn:country":"YE",
    "gn:fcode":"PPL",
    "gn:pop":8,
    "iso:country":"YE",
    "name:ara_x_preferred":[
        "\u0627\u0644\u0645\u062e\u0644\u0637\u0629"
    ],
    "name:eng_x_preferred":[
        "Al Makhlatah"
    ],
    "name:eng_x_variant":[
        "Sha\u2018b al \u1e28anah"
    ],
    "qs:name":"Al Makhla\u0163ah",
    "qs:photos_9r":0,
    "qs:photos_sr":0,
    "qs:pop_sr":"1",
    "wof:name":"Al Makhla\u0163ah",
    "wof:placetype":"locality",
    "wof:population":8
},
  "geometry": {"coordinates":[44.0121,16.68654],"type":"Point"}
}