{
  "type": "Feature",
  "properties": {
    "gn:admin1_code":"11.0",
    "gn:admin2_code":"2007.0",
    "gn:asciiname":"Al `Aris",
    "gn:country_code":"YE",
    "gn:dem":771,
    "gn:feature_class":"P",
    "gn:feature_code":"PPL",
    "gn:name":"Al \u2018\u0100ris",
    "gn:population":0,
    "gn:timezone":"Asia/Aden",
    "iso:country":"YE",
    "name:ara_x_preferred":[
        "Al \u2018\u0100ris"
    ],
    "wof:name":"Al `Aris",
    "wof:placetype":"locality"
},
  "geometry": {"coordinates":[43.55402,14.23944],"type":"Point"}
}