{
  "type": "Feature",
  "properties": {
    "gn:admin1_code":"20.0",
    "gn:admin2_code":"1405.0",
    "gn:asciiname":"Al Muraddam",
    "gn:country_code":"YE",
    "gn:dem":2040,
    "gn:feature_class":"P",
    "gn:feature_code":"PPL",
    "gn:name":"Al Muraddam",
    "gn:population":0,
    "gn:timezone":"Asia/Aden",
    "iso:country":"YE",
    "wof:name":"Al Muraddam",
    "wof:placetype":"locality"
},
  "geometry": {"coordinates":[45.41544,14.01448],"type":"Point"}
}