{
  "type": "Feature",
  "properties": {
    "gn:admin1_code":"14.0",
    "gn:admin2_code":"2607.0",
    "gn:asciiname":"Hajaj",
    "gn:country_code":"YE",
    "gn:dem":2220,
    "gn:feature_class":"P",
    "gn:feature_code":"PPL",
    "gn:name":"\u1e28aj\u0101j",
    "gn:population":0,
    "gn:timezone":"Asia/Aden",
    "iso:country":"YE",
    "name:und_x_variant":[
        "\u1e28aj\u0101j",
        "\u1e28ajj\u0101j"
    ],
    "wof:name":"Hajaj",
    "wof:placetype":"locality"
},
  "geometry": {"coordinates":[45.19619,15.12105],"type":"Point"}
}