{
  "type": "Feature",
  "properties": {
    "gn:admin1_code":"25.0",
    "gn:admin2_code":"1517.0",
    "gn:asciiname":"Al Kadkad",
    "gn:country_code":"YE",
    "gn:dem":1479,
    "gn:feature_class":"P",
    "gn:feature_code":"PPL",
    "gn:name":"Al Kadkad",
    "gn:population":0,
    "gn:timezone":"Asia/Aden",
    "iso:country":"YE",
    "name:ara_x_preferred":[
        "\u0627\u0644\u0643\u062f\u0643\u062f"
    ],
    "wof:name":"Al Kadkad",
    "wof:placetype":"locality"
},
  "geometry": {"coordinates":[44.19797,13.22748],"type":"Point"}
}