{
  "type": "Feature",
  "properties": {
    "gn:admin1_code":"23.0",
    "gn:admin2_code":"1110.0",
    "gn:asciiname":"Jubah",
    "gn:country_code":"YE",
    "gn:dem":750,
    "gn:feature_class":"P",
    "gn:feature_code":"PPL",
    "gn:name":"Juba\u1e29",
    "gn:population":0,
    "gn:timezone":"Asia/Aden",
    "iso:country":"YE",
    "name:und_x_variant":[
        "Juba\u1e29"
    ],
    "wof:name":"Jubah",
    "wof:placetype":"locality"
},
  "geometry": {"coordinates":[43.75378,13.94956],"type":"Point"}
}