{
  "type": "Feature",
  "properties": {
    "gn:admin1_code":"11.0",
    "gn:admin2_code":"2011.0",
    "gn:asciiname":"Bayt Haidad",
    "gn:cc2":"YE",
    "gn:country_code":"YE",
    "gn:dem":2190,
    "gn:feature_class":"P",
    "gn:feature_code":"PPL",
    "gn:name":"Bayt Haidad",
    "gn:population":0,
    "gn:timezone":"Asia/Aden",
    "iso:country":"YE",
    "name:und_x_variant":[
        "Beit Haidad",
        "Bayt Haidad"
    ],
    "wof:name":"Bayt Haidad",
    "wof:placetype":"locality"
},
  "geometry": {"coordinates":[44.21667,14.71667],"type":"Point"}
}