{
  "type": "Feature",
  "properties": {
    "gn:admin1_code":"20.0",
    "gn:asciiname":"Al Jira'",
    "gn:country_code":"YE",
    "gn:dem":2538,
    "gn:feature_class":"P",
    "gn:feature_code":"PPL",
    "gn:name":"Al Jir\u0101\u2019",
    "gn:population":0,
    "gn:timezone":"Asia/Aden",
    "iso:country":"YE",
    "name:ara_x_preferred":[
        "\u0627\u0644\u062c\u0631\u0627\u0621"
    ],
    "name:und_x_variant":[
        "Al Jir\u0101\u2019"
    ],
    "wof:name":"Al Jira'",
    "wof:placetype":"locality"
},
  "geometry": {"coordinates":[44.469,14.44087],"type":"Point"}
}