{
  "type": "Feature",
  "properties": {
    "gn:admin1_code":"11.0",
    "gn:admin2_code":"2011.0",
    "gn:asciiname":"Bayt Sultan",
    "gn:country_code":"YE",
    "gn:dem":2510,
    "gn:feature_class":"P",
    "gn:feature_code":"PPL",
    "gn:name":"Bayt Sul\u0163\u0101n",
    "gn:population":0,
    "gn:timezone":"Asia/Aden",
    "iso:country":"YE",
    "name:und_x_variant":[
        "Bayt Sul\u0163\u0101n"
    ],
    "wof:name":"Bayt Sultan",
    "wof:placetype":"locality"
},
  "geometry": {"coordinates":[44.03667,14.75953],"type":"Point"}
}