{
  "type": "Feature",
  "properties": {
    "gn:admin1_code":"10.0",
    "gn:admin2_code":"2703.0",
    "gn:asciiname":"Bayt an Nawwar",
    "gn:country_code":"YE",
    "gn:dem":2250,
    "gn:feature_class":"P",
    "gn:feature_code":"PPL",
    "gn:name":"Bayt an Naww\u0101r",
    "gn:population":0,
    "gn:timezone":"Asia/Aden",
    "iso:country":"YE",
    "name:und_x_variant":[
        "Bayt an Naww\u0101r"
    ],
    "wof:name":"Bayt an Nawwar",
    "wof:placetype":"locality"
},
  "geometry": {"coordinates":[43.5676,15.48169],"type":"Point"}
}