{
  "type": "Feature",
  "properties": {
    "gn:country":"YE",
    "gn:fcode":"PPL",
    "gn:pop":3,
    "iso:country":"YE",
    "name:ara_x_preferred":[
        "\u0627\u0644\u062c\u0628\u0647\u0640\u0640\u0629"
    ],
    "name:ara_x_variant":[
        "\u0627\u0644\u062c\u0628\u0647\u0629"
    ],
    "name:eng_x_preferred":[
        "Al Jubhah"
    ],
    "name:eng_x_variant":[
        "Ban\u012b Lubay\u015f"
    ],
    "qs:name":"Al Jubhah",
    "qs:photos_9r":0,
    "qs:photos_sr":0,
    "qs:pop_sr":"1",
    "wof:name":"Al Jubhah",
    "wof:placetype":"locality",
    "wof:population":3
},
  "geometry": {"coordinates":[43.40818,16.09168],"type":"Point"}
}