{
  "type": "Feature",
  "properties": {
    "gn:country":"YE",
    "gn:fcode":"PPL",
    "gn:population":3,
    "iso:country":"YE",
    "name:ara_x_preferred":[
        "\u0627\u0644\u0645\u0631\u0627\u0648\u0646"
    ],
    "name:eng_x_preferred":[
        "Al Marawin"
    ],
    "name:eng_x_variant":[
        "Al Kurs\u012byah"
    ],
    "qs_pg:aaroncc":"YE",
    "qs_pg:gn_country":"YE",
    "qs_pg:gn_fcode":"PPL",
    "qs_pg:gn_pop":3,
    "qs_pg:name":"Al Mar\u0101win",
    "qs_pg:photos_9r":0,
    "qs_pg:photos_sr":0,
    "qs_pg:pop_sr":1,
    "qs_pg:qs_pg_placetype":"locality",
    "wof:name":"Al Mar\u0101win",
    "wof:placetype":"locality",
    "wof:population":3
},
  "geometry": {"coordinates":[43.80355,13.47985],"type":"Point"}
}