{
  "type": "Feature",
  "properties": {
    "gn:admin1_code":"4.0",
    "gn:admin2_code":"1928.0",
    "gn:asciiname":"Nafhun",
    "gn:cc2":"YE",
    "gn:country_code":"YE",
    "gn:dem":831,
    "gn:feature_class":"P",
    "gn:feature_code":"PPL",
    "gn:name":"Naf\u1e29\u016bn",
    "gn:population":0,
    "gn:timezone":"Asia/Aden",
    "iso:country":"YE",
    "name:nno_x_preferred":[
        "Nafhun"
    ],
    "name:und_x_variant":[
        "Laf\u1e29\u016bn",
        "Nef\u1e25aun",
        "Naf\u1e29\u016bn"
    ],
    "wof:name":"Nafhun",
    "wof:placetype":"locality"
},
  "geometry": {"coordinates":[48.05389,15.47833],"type":"Point"}
}