{
  "type": "Feature",
  "properties": {
    "gn:admin1_code":"8.0",
    "gn:admin2_code":"1825.0",
    "gn:asciiname":"As Suqayy",
    "gn:country_code":"YE",
    "gn:dem":263,
    "gn:feature_class":"P",
    "gn:feature_code":"PPL",
    "gn:name":"As Suqayy",
    "gn:population":0,
    "gn:timezone":"Asia/Aden",
    "iso:country":"YE",
    "wof:name":"As Suqayy",
    "wof:placetype":"locality"
},
  "geometry": {"coordinates":[43.50726,14.27995],"type":"Point"}
}