{
  "type": "Feature",
  "properties": {
    "gn:admin1_code":"8.0",
    "gn:admin2_code":"1809.0",
    "gn:asciiname":"Ibrahim Jaylan",
    "gn:country_code":"YE",
    "gn:dem":336,
    "gn:feature_class":"P",
    "gn:feature_code":"PPL",
    "gn:name":"Ibr\u0101h\u012bm Jayl\u0101n",
    "gn:population":0,
    "gn:timezone":"Asia/Aden",
    "iso:country":"YE",
    "name:ara_x_preferred":[
        "\u0625\u0628\u0631\u0627\u0647\u064a\u0645 \u062c\u064a\u0644\u0627\u0646"
    ],
    "name:und_x_variant":[
        "Ibr\u0101h\u012bm Jayl\u0101n"
    ],
    "wof:name":"Ibrahim Jaylan",
    "wof:placetype":"locality"
},
  "geometry": {"coordinates":[43.35532,15.21805],"type":"Point"}
}