{
  "type": "Feature",
  "properties": {
    "gn:admin1_code":"15.0",
    "gn:admin2_code":"2203.0",
    "gn:asciiname":"Ar Rad hah",
    "gn:country_code":"YE",
    "gn:dem":1222,
    "gn:feature_class":"P",
    "gn:feature_code":"PPL",
    "gn:name":"Ar Rad hah",
    "gn:population":0,
    "gn:timezone":"Asia/Aden",
    "iso:country":"YE",
    "name:ara_x_preferred":[
        "\u0627\u0644\u0631\u062f\u0647\u0629"
    ],
    "name:und_x_variant":[
        "Ar Rad\u00b7hah"
    ],
    "wof:name":"Ar Rad hah",
    "wof:placetype":"locality"
},
  "geometry": {"coordinates":[43.23563,17.14395],"type":"Point"}
}