{
  "type": "Feature",
  "properties": {
    "gn:admin1_code":"25.0",
    "gn:admin2_code":"1515.0",
    "gn:asciiname":"Musayfir",
    "gn:country_code":"YE",
    "gn:dem":1571,
    "gn:feature_class":"P",
    "gn:feature_code":"PPL",
    "gn:name":"Mu\u015fayf\u012br",
    "gn:population":0,
    "gn:timezone":"Asia/Aden",
    "iso:country":"YE",
    "name:und_x_variant":[
        "Mu\u015fayf\u012br"
    ],
    "wof:name":"Musayfir",
    "wof:placetype":"locality"
},
  "geometry": {"coordinates":[44.06296,13.23683],"type":"Point"}
}