{
  "type": "Feature",
  "properties": {
    "gn:admin1_code":"25.0",
    "gn:admin2_code":"1517.0",
    "gn:asciiname":"Marawiyah",
    "gn:country_code":"YE",
    "gn:dem":1409,
    "gn:feature_class":"P",
    "gn:feature_code":"PPL",
    "gn:name":"Mar\u0101w\u012byah",
    "gn:population":0,
    "gn:timezone":"Asia/Aden",
    "iso:country":"YE",
    "name:und_x_variant":[
        "Mar\u0101w\u012byah"
    ],
    "wof:name":"Marawiyah",
    "wof:placetype":"locality"
},
  "geometry": {"coordinates":[44.32685,13.27927],"type":"Point"}
}