{
  "type": "Feature",
  "properties": {
    "gn:admin1_code":"11.0",
    "gn:admin2_code":"2010.0",
    "gn:asciiname":"Ribat Qarz",
    "gn:country_code":"YE",
    "gn:dem":2510,
    "gn:feature_class":"P",
    "gn:feature_code":"PPL",
    "gn:name":"Rib\u0101\u0163 Qarz",
    "gn:population":0,
    "gn:timezone":"Asia/Aden",
    "iso:country":"YE",
    "name:und_x_variant":[
        "Rib\u0101\u0163 Qarz"
    ],
    "wof:name":"Ribat Qarz",
    "wof:placetype":"locality"
},
  "geometry": {"coordinates":[44.38333,14.45],"type":"Point"}
}