{
  "type": "Feature",
  "properties": {
    "gn:country":"YE",
    "gn:fcode":"PPL",
    "gn:population":12,
    "iso:country":"YE",
    "name:ara_x_preferred":[
        "\u0642\u0635\u0628\u0629 \u0645\u062a\u0627\u0634"
    ],
    "name:eng_x_preferred":[
        "Qasabat Mitash"
    ],
    "name:eng_x_variant":[
        "\u0100l Ism\u0101\u2018\u012bl"
    ],
    "qs:name":"Qa\u015fabat Mit\u0101sh",
    "qs:photos_9r":0,
    "qs:photos_sr":0,
    "qs:pop_sr":"1",
    "wof:name":"Qa\u015fabat Mit\u0101sh",
    "wof:placetype":"locality",
    "wof:population":12
},
  "geometry": {"coordinates":[43.72352,16.37368],"type":"Point"}
}