{
  "type": "Feature",
  "properties": {
    "gn:country":"YE",
    "gn:fcode":"PPL",
    "gn:population":3,
    "iso:country":"YE",
    "name:ara_x_preferred":[
        "\u0627\u0644\u0646\u0642\u064a\u0644"
    ],
    "qs:name":"An Nuqayl",
    "qs:photos_9r":0,
    "qs:photos_sr":0,
    "qs:pop_sr":"1",
    "wof:name":"An Nuqayl",
    "wof:placetype":"locality",
    "wof:population":3
},
  "geometry": {"coordinates":[43.32048,16.72742],"type":"Point"}
}