{
  "type": "Feature",
  "properties": {
    "gn:admin1_code":"4.0",
    "gn:admin2_code":"1929.0",
    "gn:asciiname":"Fuwwah",
    "gn:country_code":"YE",
    "gn:dem":23,
    "gn:feature_class":"P",
    "gn:feature_code":"PPL",
    "gn:name":"Fuwwah",
    "gn:population":0,
    "gn:timezone":"Asia/Aden",
    "iso:country":"YE",
    "name:ara_x_preferred":[
        "\u0641\u0648\u0629"
    ],
    "name:und_x_variant":[
        "Fuwa",
        "Fuwwah",
        "F\u016bwah"
    ],
    "wof:name":"Fuwwah",
    "wof:placetype":"locality"
},
  "geometry": {"coordinates":[49.04427,14.48736],"type":"Point"}
}