{
  "type": "Feature",
  "properties": {
    "gn:country":"YE",
    "gn:fcode":"PPL",
    "gn:population":5,
    "iso:country":"YE",
    "name:ara_x_preferred":[
        "\u062d\u064a\u062f \u062d\u0628\u0627\u0633"
    ],
    "name:eng_x_preferred":[
        "Hayd Habas"
    ],
    "name:eng_x_variant":[
        "Al Masl\u016bm"
    ],
    "qs:name":"\u1e28ayd \u1e28ab\u0101s",
    "qs:photos_9r":0,
    "qs:photos_sr":0,
    "qs:pop_sr":"1",
    "wof:name":"\u1e28ayd \u1e28ab\u0101s",
    "wof:placetype":"locality",
    "wof:population":5
},
  "geometry": {"coordinates":[45.33222,14.31425],"type":"Point"}
}