{
  "type": "Feature",
  "properties": {
    "gn:admin1_code":"4.0",
    "gn:admin2_code":"1903.0",
    "gn:asciiname":"Buyut Halluf",
    "gn:country_code":"YE",
    "gn:dem":990,
    "gn:feature_class":"P",
    "gn:feature_code":"PPL",
    "gn:name":"Buy\u016bt \u1e28all\u016bf",
    "gn:population":0,
    "gn:timezone":"Asia/Aden",
    "iso:country":"YE",
    "name:ara_x_preferred":[
        "\u0628\u064a\u0648\u062a \u062d\u0644\u0648\u0641"
    ],
    "name:und_x_variant":[
        "\u1e28all\u016bf",
        "Buy\u016bt \u1e28all\u016bf"
    ],
    "wof:name":"Buyut Halluf",
    "wof:placetype":"locality"
},
  "geometry": {"coordinates":[48.84635,16.53097],"type":"Point"}
}