{
  "type": "Feature",
  "properties": {
    "gn:admin1_code":"8.0",
    "gn:admin2_code":"1808.0",
    "gn:asciiname":"Damjan",
    "gn:country_code":"YE",
    "gn:dem":99,
    "gn:feature_class":"P",
    "gn:feature_code":"PPL",
    "gn:name":"\u1e10amj\u0101n",
    "gn:population":0,
    "gn:timezone":"Asia/Aden",
    "iso:country":"YE",
    "name:ara_x_preferred":[
        "\u0636\u0645\u062c\u0627\u0646"
    ],
    "name:und_x_variant":[
        "\u1e10amj\u0101n"
    ],
    "wof:name":"Damjan",
    "wof:placetype":"locality"
},
  "geometry": {"coordinates":[43.14271,15.33715],"type":"Point"}
}