{
  "type": "Feature",
  "properties": {
    "gn:admin1_code":"15.0",
    "gn:admin2_code":"2205.0",
    "gn:asciiname":"An Nazir",
    "gn:country_code":"YE",
    "gn:dem":1782,
    "gn:feature_class":"P",
    "gn:feature_code":"PPLA2",
    "gn:name":"An Naz\u0327\u012br",
    "gn:population":0,
    "gn:timezone":"Asia/Aden",
    "iso:country":"YE",
    "name:ara_x_preferred":[
        "\u0627\u0644\u0646\u0638\u064a\u0631"
    ],
    "name:und_x_variant":[
        "An Na\u1e11\u012br",
        "R\u0101zi\u1e29",
        "An Naz\u0327\u012br"
    ],
    "wof:name":"An Nazir",
    "wof:placetype":"locality"
},
  "geometry": {"coordinates":[43.26226,16.90916],"type":"Point"}
}