{
  "type": "Feature",
  "properties": {
    "gn:admin1_code":"5.0",
    "gn:asciiname":"Huqaysh",
    "gn:country_code":"YE",
    "gn:dem":1218,
    "gn:feature_class":"P",
    "gn:feature_code":"PPL",
    "gn:name":"\u1e28uqaysh",
    "gn:population":0,
    "gn:timezone":"Asia/Aden",
    "iso:country":"YE",
    "name:ara_x_preferred":[
        "\u062d\u0642\u064a\u0633"
    ],
    "name:und_x_variant":[
        "\u1e28uqaysh"
    ],
    "wof:name":"Huqaysh",
    "wof:placetype":"locality"
},
  "geometry": {"coordinates":[45.87415,14.57876],"type":"Point"}
}