{
  "type": "Feature",
  "properties": {
    "gn:admin1_code":"20.0",
    "gn:admin2_code":"1404.0",
    "gn:asciiname":"As Sadah",
    "gn:country_code":"YE",
    "gn:dem":2001,
    "gn:feature_class":"P",
    "gn:feature_code":"PPL",
    "gn:name":"As S\u0101dah",
    "gn:population":0,
    "gn:timezone":"Asia/Aden",
    "iso:country":"YE",
    "name:und_x_variant":[
        "As S\u0101dah"
    ],
    "wof:name":"As Sadah",
    "wof:placetype":"locality"
},
  "geometry": {"coordinates":[45.78522,14.13493],"type":"Point"}
}