{
  "type": "Feature",
  "properties": {
    "gn:admin1_code":"25.0",
    "gn:admin2_code":"1513.0",
    "gn:asciiname":"Dar as Sa`d",
    "gn:country_code":"YE",
    "gn:dem":1340,
    "gn:feature_class":"P",
    "gn:feature_code":"PPL",
    "gn:name":"D\u0101r as Sa\u2018d",
    "gn:population":0,
    "gn:timezone":"Asia/Aden",
    "iso:country":"YE",
    "name:und_x_variant":[
        "D\u0101r as Sa\u2018d"
    ],
    "wof:name":"Dar as Sa`d",
    "wof:placetype":"locality"
},
  "geometry": {"coordinates":[44.13512,13.51415],"type":"Point"}
}