{
  "type": "Feature",
  "properties": {
    "gn:admin1_code":"16.0",
    "gn:admin2_code":"2310.0",
    "gn:asciiname":"As Suwat",
    "gn:country_code":"YE",
    "gn:dem":2308,
    "gn:feature_class":"P",
    "gn:feature_code":"PPL",
    "gn:name":"As Suw\u0101t",
    "gn:population":0,
    "gn:timezone":"Asia/Aden",
    "iso:country":"YE",
    "name:ara_x_preferred":[
        "As Suw\u0101t"
    ],
    "wof:name":"As Suwat",
    "wof:placetype":"locality"
},
  "geometry": {"coordinates":[43.75171,15.0226],"type":"Point"}
}