{
  "type": "Feature",
  "properties": {
    "gn:admin1_code":"2.0",
    "gn:admin2_code":"2402.0",
    "gn:asciiname":"Ash Shaykh `Uthman",
    "gn:country_code":"YE",
    "gn:dem":12,
    "gn:feature_class":"P",
    "gn:feature_code":"PPLA2",
    "gn:name":"Ash Shaykh \u2018Uthm\u0101n",
    "gn:population":0,
    "gn:timezone":"Asia/Aden",
    "iso:country":"YE",
    "name:ara_x_preferred":[
        "\u0627\u0644\u0634\u064a\u062e \u0639\u062b\u0645\u0627\u0646"
    ],
    "name:und_x_variant":[
        "Shekh Othman",
        "Sheikh \u2018Othman",
        "Shaykh \u2018Uthm\u0101n",
        "Sh\u0101ikh Othm\u0101n",
        "Shakh \u2018Uthman",
        "Ash Shaykh \u2018Uthm\u0101n"
    ],
    "wof:name":"Ash Shaykh `Uthman",
    "wof:placetype":"locality"
},
  "geometry": {"coordinates":[44.99309,12.87678],"type":"Point"}
}