{
  "type": "Feature",
  "properties": {
    "gn:country":"YE",
    "gn:fcode":"PPL",
    "gn:population":13,
    "iso:country":"YE",
    "name:ara_x_preferred":[
        "\u0642\u0635\u0628\u0629 \u0639\u0632\u064a\u0632"
    ],
    "name:eng_x_preferred":[
        "Qasabat 'Aziz"
    ],
    "name:eng_x_variant":[
        "Al Khasm\u0101n"
    ],
    "qs:name":"Qa\u015fabat \u2018Az\u012bz",
    "qs:photos_9r":0,
    "qs:photos_sr":0,
    "qs:pop_sr":"1",
    "wof:name":"Qa\u015fabat \u2018Az\u012bz",
    "wof:placetype":"locality",
    "wof:population":13
},
  "geometry": {"coordinates":[43.70965,16.37469],"type":"Point"}
}