{
  "type": "Feature",
  "properties": {
    "gn:country":"YE",
    "gn:fcode":"PPL",
    "gn:pop":4,
    "iso:country":"YE",
    "name:ara_x_preferred":[
        "\u0627\u0644\u0645\u0637\u0627\u0644\u064a\u0639"
    ],
    "name:eng_x_preferred":[
        "Al Matali'"
    ],
    "qs:name":"Al Ma\u0163\u0101l\u012b\u2018",
    "qs:photos_9r":0,
    "qs:photos_sr":0,
    "qs:pop_sr":"1",
    "wof:name":"Al Ma\u0163\u0101l\u012b\u2018",
    "wof:placetype":"locality",
    "wof:population":4
},
  "geometry": {"coordinates":[44.70754,16.11555],"type":"Point"}
}