{
  "type": "Feature",
  "properties": {
    "gn:admin1_code":"25.0",
    "gn:admin2_code":"1517.0",
    "gn:asciiname":"Kabbat al Haddad",
    "gn:country_code":"YE",
    "gn:dem":1330,
    "gn:feature_class":"P",
    "gn:feature_code":"PPL",
    "gn:name":"Kabbat al \u1e28add\u0101d",
    "gn:population":0,
    "gn:timezone":"Asia/Aden",
    "iso:country":"YE",
    "name:ara_x_preferred":[
        "\u0643\u0628\u0629 \u0627\u0644\u062d\u062f\u0627\u062f"
    ],
    "name:und_x_variant":[
        "Kabbat al \u1e28add\u0101d"
    ],
    "wof:name":"Kabbat al Haddad",
    "wof:placetype":"locality"
},
  "geometry": {"coordinates":[44.20314000000001,13.22369],"type":"Point"}
}