{
  "type": "Feature",
  "properties": {
    "gn:admin1_code":"19.0",
    "gn:admin2_code":"2908.0",
    "gn:asciiname":"Al Abraq",
    "gn:country_code":"YE",
    "gn:dem":1926,
    "gn:feature_class":"P",
    "gn:feature_code":"PPL",
    "gn:name":"Al Abr\u0101q",
    "gn:population":0,
    "gn:timezone":"Asia/Aden",
    "iso:country":"YE",
    "name:ara_x_preferred":[
        "Al Abr\u0101q"
    ],
    "name:ara_x_variant":[
        "\u0627\u0644\u0623\u0628\u0631\u0627\u0642"
    ],
    "wof:name":"Al Abraq",
    "wof:placetype":"locality"
},
  "geometry": {"coordinates":[43.71957,16.09422],"type":"Point"}
}