{
  "type": "Feature",
  "properties": {
    "gn:admin1_code":"11.0",
    "gn:admin2_code":"2007.0",
    "gn:asciiname":"Al Hubay`",
    "gn:country_code":"YE",
    "gn:dem":1150,
    "gn:feature_class":"P",
    "gn:feature_code":"PPL",
    "gn:name":"Al Hubay\u2018",
    "gn:population":0,
    "gn:timezone":"Asia/Aden",
    "iso:country":"YE",
    "name:ara_x_preferred":[
        "\u0627\u0644\u0647\u0628\u064a\u0639"
    ],
    "name:und_x_variant":[
        "Al Hubay\u2018"
    ],
    "wof:name":"Al Hubay`",
    "wof:placetype":"locality"
},
  "geometry": {"coordinates":[43.61806,14.25509],"type":"Point"}
}