{
  "type": "Feature",
  "properties": {
    "gn:admin1_code":"8.0",
    "gn:admin2_code":"1818.0",
    "gn:asciiname":"Al Harurah",
    "gn:country_code":"YE",
    "gn:dem":566,
    "gn:feature_class":"P",
    "gn:feature_code":"PPL",
    "gn:name":"Al \u1e28ar\u016brah",
    "gn:population":0,
    "gn:timezone":"Asia/Aden",
    "iso:country":"YE",
    "name:und_x_variant":[
        "Al \u1e28ar\u016brah"
    ],
    "wof:name":"Al Harurah",
    "wof:placetype":"locality"
},
  "geometry": {"coordinates":[43.65006,14.03377],"type":"Point"}
}