{
  "type": "Feature",
  "properties": {
    "gn:admin1_code":"8.0",
    "gn:admin2_code":"1814.0",
    "gn:asciiname":"Al Jama'i",
    "gn:country_code":"YE",
    "gn:dem":32,
    "gn:feature_class":"P",
    "gn:feature_code":"PPL",
    "gn:name":"Al Jam\u0101\u2018\u012b",
    "gn:population":0,
    "gn:timezone":"Asia/Aden",
    "iso:country":"YE",
    "name:ara_x_preferred":[
        "\u0627\u0644\u062c\u0645\u0627\u0639\u064a"
    ],
    "name:und_x_variant":[
        "Al Jam\u0101\u2018\u012b"
    ],
    "wof:name":"Al Jama'i",
    "wof:placetype":"locality"
},
  "geometry": {"coordinates":[43.06984,14.73418],"type":"Point"}
}