{
  "type": "Feature",
  "properties": {
    "gn:admin1_code":"11.0",
    "gn:admin2_code":"2011.0",
    "gn:asciiname":"Ma`mar",
    "gn:country_code":"YE",
    "gn:dem":1929,
    "gn:feature_class":"P",
    "gn:feature_code":"PPL",
    "gn:name":"Ma\u2018mar",
    "gn:population":0,
    "gn:timezone":"Asia/Aden",
    "iso:country":"YE",
    "name:und_x_variant":[
        "Ma\u2018mar"
    ],
    "wof:name":"Ma`mar",
    "wof:placetype":"locality"
},
  "geometry": {"coordinates":[44.14164,14.86246],"type":"Point"}
}