{
  "type": "Feature",
  "properties": {
    "gn:admin1_code":"22.0",
    "gn:admin2_code":"1709.0",
    "gn:asciiname":"Bayt al Kawlah",
    "gn:country_code":"YE",
    "gn:dem":1182,
    "gn:feature_class":"P",
    "gn:feature_code":"PPL",
    "gn:name":"Bayt al Kawlah",
    "gn:population":0,
    "gn:timezone":"Asia/Aden",
    "iso:country":"YE",
    "name:ara_x_preferred":[
        "\u0628\u064a\u062a \u0627\u0644\u0643\u0648\u0644\u0629"
    ],
    "wof:name":"Bayt al Kawlah",
    "wof:placetype":"locality"
},
  "geometry": {"coordinates":[43.44937,16.00845],"type":"Point"}
}