{
  "type": "Feature",
  "properties": {
    "gn:admin1_code":"15.0",
    "gn:admin2_code":"2208.0",
    "gn:asciiname":"Ad Dimnah",
    "gn:country_code":"YE",
    "gn:dem":2244,
    "gn:feature_class":"P",
    "gn:feature_code":"PPL",
    "gn:name":"Ad Dimnah",
    "gn:population":0,
    "gn:timezone":"Asia/Aden",
    "iso:country":"YE",
    "wof:name":"Ad Dimnah",
    "wof:placetype":"locality"
},
  "geometry": {"coordinates":[43.43893,16.79424],"type":"Point"}
}