{
  "type": "Feature",
  "properties": {
    "gn:admin1_code":"16.0",
    "gn:admin2_code":"2302.0",
    "gn:asciiname":"As Safiyah",
    "gn:country_code":"YE",
    "gn:dem":2032,
    "gn:feature_class":"P",
    "gn:feature_code":"PPL",
    "gn:name":"A\u015f \u015e\u0101fiyah",
    "gn:population":0,
    "gn:timezone":"Asia/Aden",
    "iso:country":"YE",
    "name:und_x_variant":[
        "A\u015f \u015e\u0101fiyah"
    ],
    "wof:name":"As Safiyah",
    "wof:placetype":"locality"
},
  "geometry": {"coordinates":[44.32715,15.64842],"type":"Point"}
}