{
  "type": "Feature",
  "properties": {
    "gn:admin1_code":"22.0",
    "gn:admin2_code":"1722.0",
    "gn:asciiname":"Al Qurush",
    "gn:country_code":"YE",
    "gn:dem":334,
    "gn:feature_class":"P",
    "gn:feature_code":"PPL",
    "gn:name":"Al Qur\u016bsh",
    "gn:population":0,
    "gn:timezone":"Asia/Aden",
    "iso:country":"YE",
    "name:ara_x_preferred":[
        "Al Qur\u016bsh"
    ],
    "wof:name":"Al Qurush",
    "wof:placetype":"locality"
},
  "geometry": {"coordinates":[43.29564,15.92635],"type":"Point"}
}