{
  "type": "Feature",
  "properties": {
    "gn:country":"YE",
    "gn:fcode":"PPL",
    "gn:population":4,
    "iso:country":"YE",
    "name:ara_x_preferred":[
        "\u0645\u062d\u0648\u064a\u0631"
    ],
    "name:eng_x_preferred":[
        "Mahwir"
    ],
    "name:eng_x_variant":[
        "Al Jawwah"
    ],
    "qs:name":"Ma\u1e29w\u012br",
    "qs:photos_9r":0,
    "qs:photos_sr":0,
    "qs:pop_sr":"1",
    "wof:name":"Ma\u1e29w\u012br",
    "wof:placetype":"locality",
    "wof:population":4
},
  "geometry": {"coordinates":[43.60707,16.04462],"type":"Point"}
}