{
  "type": "Feature",
  "properties": {
    "gn:admin1_code":"25.0",
    "gn:admin2_code":"1501.0",
    "gn:asciiname":"Ash Shi`bah",
    "gn:country_code":"YE",
    "gn:dem":1220,
    "gn:feature_class":"P",
    "gn:feature_code":"PPL",
    "gn:name":"Ash Shi\u2018bah",
    "gn:population":0,
    "gn:timezone":"Asia/Aden",
    "iso:country":"YE",
    "name:und_x_variant":[
        "Ash Shi\u2018bah"
    ],
    "wof:name":"Ash Shi`bah",
    "wof:placetype":"locality"
},
  "geometry": {"coordinates":[44.18153,13.58999],"type":"Point"}
}