{
  "type": "Feature",
  "properties": {
    "gn:admin1_code":"23.0",
    "gn:admin2_code":"1120.0",
    "gn:asciiname":"Shidhban",
    "gn:country_code":"YE",
    "gn:dem":2439,
    "gn:feature_class":"P",
    "gn:feature_code":"PPL",
    "gn:name":"Shidhb\u0101n",
    "gn:population":0,
    "gn:timezone":"Asia/Aden",
    "iso:country":"YE",
    "name:ara_x_preferred":[
        "Shidhb\u0101n"
    ],
    "wof:name":"Shidhban",
    "wof:placetype":"locality"
},
  "geometry": {"coordinates":[44.20178,13.96054],"type":"Point"}
}