{
  "type": "Feature",
  "properties": {
    "gn:admin1_code":"25.0",
    "gn:admin2_code":"1515.0",
    "gn:asciiname":"Ma`wal",
    "gn:country_code":"YE",
    "gn:dem":1711,
    "gn:feature_class":"P",
    "gn:feature_code":"PPL",
    "gn:name":"Ma\u2018wal",
    "gn:population":0,
    "gn:timezone":"Asia/Aden",
    "iso:country":"YE",
    "name:und_x_variant":[
        "Ma\u2018wal"
    ],
    "wof:name":"Ma`wal",
    "wof:placetype":"locality"
},
  "geometry": {"coordinates":[44.09965,13.2001],"type":"Point"}
}