{
  "type": "Feature",
  "properties": {
    "gn:gn_country":"YE",
    "gn:gn_fcode":"PPLX",
    "gn:gn_pop":75,
    "gn:population":75,
    "iso:country":"YE",
    "name:unk_x_variant":[
        "\u0627\u0644\u062d\u0627\u0631\u0629 \u0627\u0644\u063a\u0631\u0628\u064a\u0629"
    ],
    "qs_pg:aaroncc":"YE",
    "qs_pg:gn_country":"YE",
    "qs_pg:gn_fcode":"PPLX",
    "qs_pg:gn_pop":75,
    "qs_pg:name":"Al \u1e28\u0101rah al Gharb\u012byah",
    "qs_pg:photos_9r":0,
    "qs_pg:photos_sr":0,
    "qs_pg:pop_sr":1,
    "qs_pg:qs_pg_placetype":"neighbourhood",
    "wof:name":"Al \u1e28\u0101rah al Gharb\u012byah",
    "wof:placetype":"neighbourhood",
    "wof:population":75
},
  "geometry": {"coordinates":[42.81109,16.32219],"type":"Point"}
}