{
  "type": "Feature",
  "properties": {
    "gn:admin1_code":"22.0",
    "gn:admin2_code":"1703.0",
    "gn:asciiname":"Dhahib al Hajar",
    "gn:cc2":"YE",
    "gn:country_code":"YE",
    "gn:dem":54,
    "gn:feature_class":"P",
    "gn:feature_code":"PPL",
    "gn:name":"Dh\u0101hib al \u1e28ajar",
    "gn:population":0,
    "gn:timezone":"Asia/Aden",
    "iso:country":"YE",
    "name:und_x_variant":[
        "Dhahib-el-Hajur",
        "Dh\u0101hib al \u1e28ajar"
    ],
    "wof:name":"Dhahib al Hajar",
    "wof:placetype":"locality"
},
  "geometry": {"coordinates":[42.95,16.31667],"type":"Point"}
}