{
  "type": "Feature",
  "properties": {
    "gn:country":"YE",
    "gn:fcode":"PPL",
    "gn:population":15,
    "iso:country":"YE",
    "name:ara_x_preferred":[
        "Ash Shu\u2018\u0101yib"
    ],
    "name:ara_x_variant":[
        "\u0627\u0644\u0634\u0639\u0627\u064a\u0628"
    ],
    "qs_pg:aaroncc":"YE",
    "qs_pg:gn_country":"YE",
    "qs_pg:gn_fcode":"PPL",
    "qs_pg:gn_pop":15,
    "qs_pg:name":"Ash Shu\u2018\u0101yib",
    "qs_pg:photos_9r":0,
    "qs_pg:photos_sr":0,
    "qs_pg:pop_sr":1,
    "qs_pg:qs_pg_placetype":"locality",
    "wof:name":"Ash Shu\u2018\u0101yib",
    "wof:placetype":"locality",
    "wof:population":15
},
  "geometry": {"coordinates":[43.32002,16.13119],"type":"Point"}
}