{
  "type": "Feature",
  "properties": {
    "gn:admin1_code":"22.0",
    "gn:admin2_code":"1711.0",
    "gn:asciiname":"Bayt `Ubr",
    "gn:country_code":"YE",
    "gn:dem":795,
    "gn:feature_class":"P",
    "gn:feature_code":"PPL",
    "gn:name":"Bayt \u2018Ubr",
    "gn:population":0,
    "gn:timezone":"Asia/Aden",
    "iso:country":"YE",
    "name:und_x_variant":[
        "Bayt \u2018Ubr"
    ],
    "wof:name":"Bayt `Ubr",
    "wof:placetype":"locality"
},
  "geometry": {"coordinates":[43.37645,16.11882],"type":"Point"}
}