{
  "type": "Feature",
  "properties": {
    "gn:admin1_code":"14.0",
    "gn:admin2_code":"2614.0",
    "gn:asciiname":"'Ajmat al Mustawwad",
    "gn:country_code":"YE",
    "gn:dem":1864,
    "gn:feature_class":"P",
    "gn:feature_code":"PPL",
    "gn:name":"\u2018Ajmat al Mustawwad",
    "gn:population":0,
    "gn:timezone":"Asia/Aden",
    "iso:country":"YE",
    "name:ara_x_preferred":[
        "\u0639\u062c\u0645\u0629 \u0627\u0644\u0645\u0633\u062a\u0648\u062f"
    ],
    "name:und_x_variant":[
        "\u2018Ajmat al Mustawwad"
    ],
    "wof:name":"'Ajmat al Mustawwad",
    "wof:placetype":"locality"
},
  "geometry": {"coordinates":[45.15517,15.08659],"type":"Point"}
}