{
  "type": "Feature",
  "properties": {
    "gn:admin1_code":"19.0",
    "gn:admin2_code":"2919.0",
    "gn:asciiname":"Tamish",
    "gn:country_code":"YE",
    "gn:dem":2109,
    "gn:feature_class":"P",
    "gn:feature_code":"PPL",
    "gn:name":"\u0162\u0101mish",
    "gn:population":0,
    "gn:timezone":"Asia/Aden",
    "iso:country":"YE",
    "name:ara_x_preferred":[
        "\u0162\u0101mish"
    ],
    "name:ara_x_variant":[
        "\u0637\u0627\u0645\u0634"
    ],
    "wof:name":"Tamish",
    "wof:placetype":"locality"
},
  "geometry": {"coordinates":[43.93821,16.07221],"type":"Point"}
}