{
  "type": "Feature",
  "properties": {
    "gn:admin1_code":"18.0",
    "gn:admin2_code":"3007.0",
    "gn:asciiname":"Al Hadaf",
    "gn:country_code":"YE",
    "gn:dem":1823,
    "gn:feature_class":"P",
    "gn:feature_code":"PPL",
    "gn:name":"Al Hadaf",
    "gn:population":0,
    "gn:timezone":"Asia/Aden",
    "iso:country":"YE",
    "name:und_x_variant":[
        "Madaf",
        "Al Hadaf"
    ],
    "wof:name":"Al Hadaf",
    "wof:placetype":"locality"
},
  "geometry": {"coordinates":[44.63751,13.71547],"type":"Point"}
}