{
  "type": "Feature",
  "properties": {
    "gn:admin1_code":"15.0",
    "gn:admin2_code":"2208.0",
    "gn:asciiname":"Al Mikhari",
    "gn:country_code":"YE",
    "gn:dem":1024,
    "gn:feature_class":"P",
    "gn:feature_code":"PPL",
    "gn:name":"Al Mikh\u0101r\u012b",
    "gn:population":0,
    "gn:timezone":"Asia/Aden",
    "iso:country":"YE",
    "name:ara_x_preferred":[
        "Al Mikh\u0101r\u012b"
    ],
    "name:ara_x_variant":[
        "\u0627\u0644\u0645\u062e\u0627\u0631\u064a"
    ],
    "wof:name":"Al Mikhari",
    "wof:placetype":"locality"
},
  "geometry": {"coordinates":[43.32999,16.64669],"type":"Point"}
}