{
  "type": "Feature",
  "properties": {
    "gn:admin1_code":"22.0",
    "gn:admin2_code":"1730.0",
    "gn:asciiname":"`Asayrah",
    "gn:country_code":"YE",
    "gn:dem":625,
    "gn:feature_class":"P",
    "gn:feature_code":"PPL",
    "gn:name":"\u2018A\u015fayrah",
    "gn:population":0,
    "gn:timezone":"Asia/Aden",
    "iso:country":"YE",
    "name:ara_x_preferred":[
        "\u0639\u0635\u064a\u0631\u0629"
    ],
    "name:und_x_variant":[
        "\u2018A\u015fayrah"
    ],
    "wof:name":"`Asayrah",
    "wof:placetype":"locality"
},
  "geometry": {"coordinates":[43.3508,16.30698],"type":"Point"}
}