{
  "type": "Feature",
  "properties": {
    "gn:admin1_code":"21.0",
    "gn:admin2_code":"1603.0",
    "gn:asciiname":"Al Maryam",
    "gn:country_code":"YE",
    "gn:dem":1181,
    "gn:feature_class":"P",
    "gn:feature_code":"PPL",
    "gn:name":"\u0100l Maryam",
    "gn:population":0,
    "gn:timezone":"Asia/Aden",
    "iso:country":"YE",
    "name:ara_x_preferred":[
        "\u0622\u0644 \u0645\u0631\u064a\u0645"
    ],
    "name:und_x_variant":[
        "\u0100l Maryam"
    ],
    "wof:name":"Al Maryam",
    "wof:placetype":"locality"
},
  "geometry": {"coordinates":[44.49627,16.24881],"type":"Point"}
}