{
  "type": "Feature",
  "properties": {
    "gn:admin1_code":"23.0",
    "gn:admin2_code":"1102.0",
    "gn:asciiname":"'Akabir",
    "gn:country_code":"YE",
    "gn:dem":1529,
    "gn:feature_class":"P",
    "gn:feature_code":"PPL",
    "gn:name":"\u2018Ak\u0101bir",
    "gn:population":0,
    "gn:timezone":"Asia/Aden",
    "iso:country":"YE",
    "name:ara_x_preferred":[
        "\u0639\u0643\u0627\u0628\u0631"
    ],
    "name:und_x_variant":[
        "\u2018Ak\u0101bir"
    ],
    "wof:name":"'Akabir",
    "wof:placetype":"locality"
},
  "geometry": {"coordinates":[44.16698,14.2834],"type":"Point"}
}