{
  "type": "Feature",
  "properties": {
    "gn:admin1_code":"20.0",
    "gn:admin2_code":"1401.0",
    "gn:asciiname":"Al Badi`",
    "gn:country_code":"YE",
    "gn:dem":2049,
    "gn:elevation":"3.0",
    "gn:feature_class":"P",
    "gn:feature_code":"PPL",
    "gn:name":"Al Bad\u012b\u2018",
    "gn:population":0,
    "gn:timezone":"Asia/Aden",
    "iso:country":"YE",
    "name:ara_x_preferred":[
        "\u0627\u0644\u0628\u062f\u064a\u0639"
    ],
    "name:und_x_variant":[
        "Al Bad\u012b\u2018"
    ],
    "wof:name":"Al Badi`",
    "wof:placetype":"locality"
},
  "geometry": {"coordinates":[45.56223,14.67667],"type":"Point"}
}