{
  "type": "Feature",
  "properties": {
    "gn:admin1_code":"4.0",
    "gn:admin2_code":"1918.0",
    "gn:asciiname":"Ar Rubah",
    "gn:cc2":"YE",
    "gn:country_code":"YE",
    "gn:dem":1601,
    "gn:feature_class":"P",
    "gn:feature_code":"PPL",
    "gn:name":"Ar R\u016bbah",
    "gn:population":0,
    "gn:timezone":"Asia/Aden",
    "iso:country":"YE",
    "name:nno_x_preferred":[
        "Ar Rubah"
    ],
    "name:und_x_variant":[
        "Ruba",
        "Al-R\u016bbah",
        "Ar R\u016bbah"
    ],
    "wof:name":"Ar Rubah",
    "wof:placetype":"locality"
},
  "geometry": {"coordinates":[48.405,14.83],"type":"Point"}
}