{
  "type": "Feature",
  "properties": {
    "gn:admin1_code":"16.0",
    "gn:admin2_code":"2306.0",
    "gn:asciiname":"Bayt al Asadi",
    "gn:country_code":"YE",
    "gn:dem":2741,
    "gn:feature_class":"P",
    "gn:feature_code":"PPL",
    "gn:name":"Bayt al Asad\u012b",
    "gn:population":0,
    "gn:timezone":"Asia/Aden",
    "iso:country":"YE",
    "name:und_x_variant":[
        "Bayt al Asad\u012b"
    ],
    "wof:name":"Bayt al Asadi",
    "wof:placetype":"locality"
},
  "geometry": {"coordinates":[44.25278,14.96546],"type":"Point"}
}