{
  "type": "Feature",
  "properties": {
    "gn:admin1_code":"18.0",
    "gn:admin2_code":"3007.0",
    "gn:asciiname":"Hawra'",
    "gn:country_code":"YE",
    "gn:dem":1886,
    "gn:feature_class":"P",
    "gn:feature_code":"PPL",
    "gn:name":"\u1e28awr\u0101\u2019",
    "gn:population":0,
    "gn:timezone":"Asia/Aden",
    "iso:country":"YE",
    "name:und_x_variant":[
        "\u1e28awr\u0101\u2019"
    ],
    "wof:name":"Hawra'",
    "wof:placetype":"locality"
},
  "geometry": {"coordinates":[44.64963,13.72349],"type":"Point"}
}