{
  "type": "Feature",
  "properties": {
    "gn:admin1_code":"19.0",
    "gn:admin2_code":"2904.0",
    "gn:asciiname":"Dhu Mantash",
    "gn:country_code":"YE",
    "gn:dem":1264,
    "gn:feature_class":"P",
    "gn:feature_code":"PPL",
    "gn:name":"Dh\u016b Man\u0163ash",
    "gn:population":0,
    "gn:timezone":"Asia/Aden",
    "iso:country":"YE",
    "name:ara_x_preferred":[
        "\u0630\u0648 \u0645\u0646\u0637\u0634"
    ],
    "name:und_x_variant":[
        "Dh\u016b Man\u0163ash"
    ],
    "wof:name":"Dhu Mantash",
    "wof:placetype":"locality"
},
  "geometry": {"coordinates":[43.78574,16.23422],"type":"Point"}
}