{
  "type": "Feature",
  "properties": {
    "gn:admin1_code":"24.0",
    "gn:admin2_code":"2502.0",
    "gn:asciiname":"Ahl Mansur",
    "gn:country_code":"YE",
    "gn:dem":2248,
    "gn:feature_class":"P",
    "gn:feature_code":"PPL",
    "gn:name":"Ahl Man\u015f\u016br",
    "gn:population":0,
    "gn:timezone":"Asia/Aden",
    "iso:country":"YE",
    "name:und_x_variant":[
        "Mansur",
        "Ahl Man\u015f\u016br"
    ],
    "wof:name":"Ahl Mansur",
    "wof:placetype":"locality"
},
  "geometry": {"coordinates":[45.25397,13.87001],"type":"Point"}
}