{
  "type": "Feature",
  "properties": {
    "gn:country":"YE",
    "gn:fcode":"PPL",
    "gn:pop":4,
    "iso:country":"YE",
    "name:ara_x_preferred":[
        "\u0627\u0644\u0647\u0634\u064a\u0645\u0629"
    ],
    "name:ara_x_variant":[
        "\u0627\u0644\u0647\u0634\u0645\u064a\u0629"
    ],
    "name:eng_x_preferred":[
        "Al Hushaymah"
    ],
    "qs:name":"Al Hushaymah",
    "qs:photos_9r":0,
    "qs:photos_sr":0,
    "qs:pop_sr":"1",
    "wof:name":"Al Hushaymah",
    "wof:placetype":"locality",
    "wof:population":4
},
  "geometry": {"coordinates":[44.40666,17.22969],"type":"Point"}
}