{
  "type": "Feature",
  "properties": {
    "gn:admin1_code":"23.0",
    "gn:admin2_code":"1107.0",
    "gn:asciiname":"Az Zuhrah",
    "gn:country_code":"YE",
    "gn:dem":1466,
    "gn:feature_class":"P",
    "gn:feature_code":"PPL",
    "gn:name":"Az\u0327 Z\u0327uhrah",
    "gn:population":0,
    "gn:timezone":"Asia/Aden",
    "iso:country":"YE",
    "name:und_x_variant":[
        "Az\u0327 Z\u0327uhrah"
    ],
    "wof:name":"Az Zuhrah",
    "wof:placetype":"locality"
},
  "geometry": {"coordinates":[44.1724,14.21125],"type":"Point"}
}