{
  "type": "Feature",
  "properties": {
    "gn:country":"YE",
    "gn:fcode":"PPL",
    "gn:population":1,
    "iso:country":"YE",
    "name:ara_x_preferred":[
        "\u0627\u0644\u062c\u062d\u0632\u0648\u0632"
    ],
    "name:eng_x_preferred":[
        "Al JahzUz"
    ],
    "name:eng_x_variant":[
        "\u0100l \u2018Aw\u0101nah"
    ],
    "qs:name":"Al Ja\u1e29z\u016bz",
    "qs:photos_9r":0,
    "qs:photos_sr":0,
    "qs:pop_sr":"1",
    "wof:name":"Al Ja\u1e29z\u016bz",
    "wof:placetype":"locality",
    "wof:population":1
},
  "geometry": {"coordinates":[43.84152,13.42196],"type":"Point"}
}