{
  "type": "Feature",
  "properties": {
    "gn:admin1_code":"25.0",
    "gn:admin2_code":"1507.0",
    "gn:asciiname":"Al Watan",
    "gn:country_code":"YE",
    "gn:dem":7,
    "gn:feature_class":"P",
    "gn:feature_code":"PPL",
    "gn:name":"Al Wa\u0163an",
    "gn:population":0,
    "gn:timezone":"Asia/Aden",
    "iso:country":"YE",
    "name:und_x_variant":[
        "Al Wa\u0163an"
    ],
    "wof:name":"Al Watan",
    "wof:placetype":"locality"
},
  "geometry": {"coordinates":[43.3232,13.12725],"type":"Point"}
}