{
  "type": "Feature",
  "properties": {
    "gn:country":"YE",
    "gn:fcode":"PPL",
    "gn:population":7,
    "iso:country":"YE",
    "name:ara_x_preferred":[
        "\u063a\u0648\u0644 \u0627\u0644\u0645\u0636"
    ],
    "name:eng_x_preferred":[
        "Ghawl Al Mauu"
    ],
    "name:eng_x_variant":[
        "Al \u2018Aq\u012byah"
    ],
    "qs:name":"Ghawl al Ma\u1e11\u1e11",
    "qs:photos_9r":0,
    "qs:photos_sr":0,
    "qs:pop_sr":"1",
    "wof:name":"Ghawl al Ma\u1e11\u1e11",
    "wof:placetype":"locality",
    "wof:population":7
},
  "geometry": {"coordinates":[43.53585,16.33968],"type":"Point"}
}