{
  "type": "Feature",
  "properties": {
    "gn:admin1_code":"15.0",
    "gn:admin2_code":"2214.0",
    "gn:asciiname":"Ash Shafi`iyah",
    "gn:country_code":"YE",
    "gn:dem":1776,
    "gn:feature_class":"P",
    "gn:feature_code":"PPL",
    "gn:name":"Ash Sh\u0101fi\u2018\u012byah",
    "gn:population":0,
    "gn:timezone":"Asia/Aden",
    "iso:country":"YE",
    "name:ara_x_preferred":[
        "\u0627\u0644\u0634\u0627\u0641\u0639\u064a\u0629"
    ],
    "name:und_x_variant":[
        "Ash Sh\u0101fi\u2018\u012byah"
    ],
    "wof:name":"Ash Shafi`iyah",
    "wof:placetype":"locality"
},
  "geometry": {"coordinates":[44.20346,17.0117],"type":"Point"}
}