{
  "type": "Feature",
  "properties": {
    "gn:admin1_code":"18.0",
    "gn:admin2_code":"3009.0",
    "gn:asciiname":"Al Husayn",
    "gn:cc2":"YE",
    "gn:country_code":"YE",
    "gn:dem":1265,
    "gn:feature_class":"P",
    "gn:feature_code":"PPL",
    "gn:name":"Al \u1e28usayn",
    "gn:population":0,
    "gn:timezone":"Asia/Aden",
    "iso:country":"YE",
    "name:und_x_variant":[
        "El Husen",
        "Al \u1e28usayn"
    ],
    "wof:name":"Al Husayn",
    "wof:placetype":"locality"
},
  "geometry": {"coordinates":[44.55,13.85],"type":"Point"}
}