{
  "type": "Feature",
  "properties": {
    "gn:admin1_code":"8.0",
    "gn:admin2_code":"1810.0",
    "gn:asciiname":"Mahall Bani Suwaydan",
    "gn:country_code":"YE",
    "gn:dem":141,
    "gn:feature_class":"P",
    "gn:feature_code":"PPL",
    "gn:name":"Ma\u1e29all Ban\u012b Suwayd\u0101n",
    "gn:population":0,
    "gn:timezone":"Asia/Aden",
    "iso:country":"YE",
    "name:ara_x_preferred":[
        "\u0645\u062d\u0644 \u0628\u0646\u064a \u0633\u0648\u064a\u062f\u0627\u0646"
    ],
    "name:und_x_variant":[
        "Ma\u1e29all Ban\u012b Suwayd\u0101n"
    ],
    "wof:name":"Mahall Bani Suwaydan",
    "wof:placetype":"locality"
},
  "geometry": {"coordinates":[43.20327,15.10379],"type":"Point"}
}