{
  "type": "Feature",
  "properties": {
    "gn:admin1_code":"8.0",
    "gn:admin2_code":"1809.0",
    "gn:asciiname":"Hardha",
    "gn:cc2":"YE",
    "gn:country_code":"YE",
    "gn:dem":180,
    "gn:feature_class":"P",
    "gn:feature_code":"PPL",
    "gn:name":"Hardha",
    "gn:population":0,
    "gn:timezone":"Asia/Aden",
    "iso:country":"YE",
    "name:und_x_variant":[
        "\u1e28ardah"
    ],
    "wof:name":"Hardha",
    "wof:placetype":"locality"
},
  "geometry": {"coordinates":[43.25,15.25],"type":"Point"}
}