{
  "type": "Feature",
  "properties": {
    "gn:admin1_code":"8.0",
    "gn:admin2_code":"1814.0",
    "gn:asciiname":"Buyut Ma`fa' Dabuki",
    "gn:country_code":"YE",
    "gn:dem":42,
    "gn:feature_class":"P",
    "gn:feature_code":"PPL",
    "gn:name":"Buy\u016bt Ma\u2018f\u0101\u2019 Dab\u016bk\u012b",
    "gn:population":0,
    "gn:timezone":"Asia/Aden",
    "iso:country":"YE",
    "name:und_x_variant":[
        "Buy\u016bt Ma\u2018f\u0101\u2019 Dab\u016bk\u012b",
        "Mi\u015fb\u0101r"
    ],
    "wof:name":"Buyut Ma`fa' Dabuki",
    "wof:placetype":"locality"
},
  "geometry": {"coordinates":[43.1204,14.74213],"type":"Point"}
}