{
  "type": "Feature",
  "properties": {
    "gn:country":"YE",
    "gn:fcode":"PPL",
    "gn:pop":10,
    "iso:country":"YE",
    "name:ara_x_preferred":[
        "\u0627\u0644\u062c\u0631\u0634\u0629"
    ],
    "name:eng_x_preferred":[
        "Al Jurshah"
    ],
    "qs:name":"Al Jurshah",
    "qs:photos_9r":0,
    "qs:photos_sr":0,
    "qs:pop_sr":"1",
    "wof:name":"Al Jurshah",
    "wof:placetype":"locality",
    "wof:population":10
},
  "geometry": {"coordinates":[44.30782,16.54174],"type":"Point"}
}