{
  "type": "Feature",
  "properties": {
    "gn:country":"YE",
    "gn:fcode":"PPL",
    "gn:pop":1,
    "iso:country":"YE",
    "name:ara_x_preferred":[
        "\u0642\u0648\u0632 \u0627\u0644\u0630\u064a\u0628\u0629"
    ],
    "name:eng_x_preferred":[
        "Qawz Adh Dhaybah"
    ],
    "name:eng_x_variant":[
        "Tajdhal"
    ],
    "qs:name":"Qawz adh Dhaybah",
    "qs:photos_9r":0,
    "qs:photos_sr":0,
    "qs:pop_sr":"1",
    "wof:name":"Qawz adh Dhaybah",
    "wof:placetype":"locality",
    "wof:population":1
},
  "geometry": {"coordinates":[44.75939,16.13571],"type":"Point"}
}