{
  "type": "Feature",
  "properties": {
    "gn:country":"YE",
    "gn:fcode":"PPL",
    "gn:pop":2,
    "iso:country":"YE",
    "name:ara_x_preferred":[
        "\u0646\u062e\u0644"
    ],
    "name:eng_x_preferred":[
        "Nakhl"
    ],
    "qs:name":"Nakhl",
    "qs:photos_9r":0,
    "qs:photos_sr":0,
    "qs:pop_sr":"1",
    "wd:wordcount":69,
    "wof:name":"Nakhl",
    "wof:placetype":"locality",
    "wof:population":2
},
  "geometry": {"coordinates":[45.41762,14.83937],"type":"Point"}
}