{
  "type": "Feature",
  "properties": {
    "gn:admin1_code":"22.0",
    "gn:admin2_code":"1727.0",
    "gn:asciiname":"Bayt al Hawmirah",
    "gn:country_code":"YE",
    "gn:dem":1039,
    "gn:feature_class":"P",
    "gn:feature_code":"PPL",
    "gn:name":"Bayt al \u1e28awmirah",
    "gn:population":0,
    "gn:timezone":"Asia/Aden",
    "iso:country":"YE",
    "name:ara_x_preferred":[
        "\u0628\u064a\u062a \u0627\u0644\u062d\u0648\u0645\u0631\u0629"
    ],
    "name:und_x_variant":[
        "Bayt al \u1e28awmirah"
    ],
    "wof:name":"Bayt al Hawmirah",
    "wof:placetype":"locality"
},
  "geometry": {"coordinates":[43.58853,15.55531],"type":"Point"}
}