{
  "type": "Feature",
  "properties": {
    "gn:admin1_code":"19.0",
    "gn:admin2_code":"2919.0",
    "gn:asciiname":"Al Fusayrah",
    "gn:country_code":"YE",
    "gn:dem":2367,
    "gn:feature_class":"P",
    "gn:feature_code":"PPL",
    "gn:name":"Al Fu\u015fayrah",
    "gn:population":0,
    "gn:timezone":"Asia/Aden",
    "iso:country":"YE",
    "name:fas_x_preferred":[
        "\u0627\u0644\u0641\u0635\u06cc\u0631\u062d"
    ],
    "name:nno_x_preferred":[
        "Al Fisirah"
    ],
    "name:und_x_variant":[
        "Al Fu\u015fayrah",
        "Al Fi\u015f\u012brah",
        "Al Fas\u012brah"
    ],
    "wof:name":"Al Fusayrah",
    "wof:placetype":"locality"
},
  "geometry": {"coordinates":[43.91774,16.00656],"type":"Point"}
}