{
  "type": "Feature",
  "properties": {
    "gn:country":"YE",
    "gn:fcode":"PPL",
    "gn:pop":61,
    "iso:country":"YE",
    "name:ara_x_preferred":[
        "Al \u2018Aksh"
    ],
    "name:ara_x_variant":[
        "\u0627\u0644\u0639\u0643\u0634"
    ],
    "name:eng_x_preferred":[
        "Al 'Aksh"
    ],
    "qs:name":"Al \u2018Aksh",
    "qs:photos_9r":0,
    "qs:photos_sr":0,
    "qs:pop_sr":"1",
    "wof:name":"Al \u2018Aksh",
    "wof:placetype":"locality",
    "wof:population":61
},
  "geometry": {"coordinates":[43.30214,16.26118],"type":"Point"}
}