{
  "type": "Feature",
  "properties": {
    "gn:admin1_code":"8.0",
    "gn:admin2_code":"1812.0",
    "gn:asciiname":"Al Ma'zab",
    "gn:country_code":"YE",
    "gn:dem":1485,
    "gn:feature_class":"P",
    "gn:feature_code":"PPL",
    "gn:name":"Al Ma\u2018zab",
    "gn:population":0,
    "gn:timezone":"Asia/Aden",
    "iso:country":"YE",
    "name:ara_x_preferred":[
        "\u0627\u0644\u0645\u0639\u0632\u0628"
    ],
    "name:und_x_variant":[
        "Al Ma\u2018zab"
    ],
    "wof:name":"Al Ma'zab",
    "wof:placetype":"locality"
},
  "geometry": {"coordinates":[43.43654,14.90016],"type":"Point"}
}