{
  "type": "Feature",
  "properties": {
    "gn:admin1_code":"8.0",
    "gn:admin2_code":"1814.0",
    "gn:asciiname":"Ad Dabbabiyah",
    "gn:country_code":"YE",
    "gn:dem":61,
    "gn:feature_class":"P",
    "gn:feature_code":"PPL",
    "gn:name":"Ad Dabb\u0101b\u012byah",
    "gn:population":0,
    "gn:timezone":"Asia/Aden",
    "iso:country":"YE",
    "name:ara_x_preferred":[
        "\u0627\u0644\u062f\u0628\u0627\u0628\u064a\u0629"
    ],
    "name:und_x_variant":[
        "Ad Dabb\u0101b\u012byah"
    ],
    "wof:name":"Ad Dabbabiyah",
    "wof:placetype":"locality"
},
  "geometry": {"coordinates":[43.22216,14.62711],"type":"Point"}
}