{
  "type": "Feature",
  "properties": {
    "gn:admin1_code":"19.0",
    "gn:admin2_code":"2907.0",
    "gn:asciiname":"Al Kharratin",
    "gn:country_code":"YE",
    "gn:dem":906,
    "gn:feature_class":"P",
    "gn:feature_code":"PPL",
    "gn:name":"Al Kharr\u0101\u0163\u012bn",
    "gn:population":0,
    "gn:timezone":"Asia/Aden",
    "iso:country":"YE",
    "name:und_x_variant":[
        "Al Kharr\u0101\u0163\u012bn"
    ],
    "wof:name":"Al Kharratin",
    "wof:placetype":"locality"
},
  "geometry": {"coordinates":[43.60278,15.98395],"type":"Point"}
}