{
  "type": "Feature",
  "properties": {
    "gn:admin1_code":"25.0",
    "gn:admin2_code":"1513.0",
    "gn:asciiname":"Habil Saba'",
    "gn:country_code":"YE",
    "gn:dem":1170,
    "gn:feature_class":"P",
    "gn:feature_code":"PPL",
    "gn:name":"\u1e28ab\u012bl Sab\u0101\u2019",
    "gn:population":0,
    "gn:timezone":"Asia/Aden",
    "iso:country":"YE",
    "name:und_x_variant":[
        "\u1e28ab\u012bl Sab\u0101\u2019"
    ],
    "wof:name":"Habil Saba'",
    "wof:placetype":"locality"
},
  "geometry": {"coordinates":[44.21116,13.44884],"type":"Point"}
}