{
  "type": "Feature",
  "properties": {
    "gn:admin1_code":"8.0",
    "gn:admin2_code":"1824.0",
    "gn:asciiname":"Al Miskinah",
    "gn:country_code":"YE",
    "gn:dem":166,
    "gn:feature_class":"P",
    "gn:feature_code":"PPL",
    "gn:name":"Al Misk\u012bnah",
    "gn:population":0,
    "gn:timezone":"Asia/Aden",
    "iso:country":"YE",
    "name:und_x_variant":[
        "Al Misk\u012bnah"
    ],
    "wof:name":"Al Miskinah",
    "wof:placetype":"locality"
},
  "geometry": {"coordinates":[43.37866,14.34491],"type":"Point"}
}