{
  "type": "Feature",
  "properties": {
    "gn:admin1_code":"20.0",
    "gn:admin2_code":"1420.0",
    "gn:asciiname":"Ash Sha`bah",
    "gn:country_code":"YE",
    "gn:dem":2005,
    "gn:feature_class":"P",
    "gn:feature_code":"PPL",
    "gn:name":"Ash Sha\u2018bah",
    "gn:population":0,
    "gn:timezone":"Asia/Aden",
    "iso:country":"YE",
    "name:nno_x_preferred":[
        "Ash Sha`bah"
    ],
    "name:und_x_variant":[
        "Ash Sha\u2018bah"
    ],
    "wof:name":"Ash Sha`bah",
    "wof:placetype":"locality"
},
  "geometry": {"coordinates":[45.39401,14.37241],"type":"Point"}
}