{
  "type": "Feature",
  "properties": {
    "gn:admin1_code":"18.0",
    "gn:admin2_code":"3002.0",
    "gn:asciiname":"Rukhamah",
    "gn:country_code":"YE",
    "gn:dem":1990,
    "gn:feature_class":"P",
    "gn:feature_code":"PPL",
    "gn:name":"Rukhamah",
    "gn:population":0,
    "gn:timezone":"Asia/Aden",
    "iso:country":"YE",
    "wof:name":"Rukhamah",
    "wof:placetype":"locality"
},
  "geometry": {"coordinates":[44.6095,14.08461],"type":"Point"}
}