{
  "type": "Feature",
  "properties": {
    "gn:admin1_code":"19.0",
    "gn:admin2_code":"2918.0",
    "gn:asciiname":"Mi`azib Qaradah",
    "gn:country_code":"YE",
    "gn:dem":2222,
    "gn:feature_class":"P",
    "gn:feature_code":"PPL",
    "gn:name":"Mi\u2018\u0101z\u012bb Qara\u1e11ah",
    "gn:population":0,
    "gn:timezone":"Asia/Aden",
    "iso:country":"YE",
    "name:und_x_variant":[
        "Mi\u2018\u0101z\u012bb Qara\u1e11ah"
    ],
    "wof:name":"Mi`azib Qaradah",
    "wof:placetype":"locality"
},
  "geometry": {"coordinates":[43.86119,15.90561],"type":"Point"}
}