{
  "type": "Feature",
  "properties": {
    "gn:country":"YE",
    "gn:fcode":"PPL",
    "gn:population":53,
    "iso:country":"YE",
    "name:ara_x_preferred":[
        "\u0639\u0634\u0631"
    ],
    "qs:name":"\u2018Ashar",
    "qs:photos_9r":0,
    "qs:photos_sr":0,
    "qs:pop_sr":"1",
    "wof:name":"\u2018Ashar",
    "wof:placetype":"locality",
    "wof:population":53
},
  "geometry": {"coordinates":[44.18442,16.63026],"type":"Point"}
}