{
  "type": "Feature",
  "properties": {
    "gn:admin1_code":"16.0",
    "gn:admin2_code":"2303.0",
    "gn:asciiname":"Bayt al Mu`afa",
    "gn:country_code":"YE",
    "gn:dem":2031,
    "gn:feature_class":"P",
    "gn:feature_code":"PPL",
    "gn:name":"Bayt al Mu\u2018\u0101f\u0101",
    "gn:population":0,
    "gn:timezone":"Asia/Aden",
    "iso:country":"YE",
    "name:und_x_variant":[
        "Bayt al Mu\u2018\u0101f\u0101"
    ],
    "wof:name":"Bayt al Mu`afa",
    "wof:placetype":"locality"
},
  "geometry": {"coordinates":[44.44319,15.66546],"type":"Point"}
}