{
  "type": "Feature",
  "properties": {
    "gn:admin1_code":"15.0",
    "gn:admin2_code":"2210.0",
    "gn:asciiname":"Al Qabdah",
    "gn:country_code":"YE",
    "gn:dem":2474,
    "gn:feature_class":"P",
    "gn:feature_code":"PPL",
    "gn:name":"Al Qab\u1e11ah",
    "gn:population":0,
    "gn:timezone":"Asia/Aden",
    "iso:country":"YE",
    "name:ara_x_preferred":[
        "\u0627\u0644\u0642\u0628\u0636\u0629"
    ],
    "name:und_x_variant":[
        "Al Qab\u1e11ah"
    ],
    "wof:name":"Al Qabdah",
    "wof:placetype":"locality"
},
  "geometry": {"coordinates":[43.53046,17.02326],"type":"Point"}
}