{
  "type": "Feature",
  "properties": {
    "gn:admin1_code":"24.0",
    "gn:admin2_code":"2513.0",
    "gn:asciiname":"`Ukaysah",
    "gn:country_code":"YE",
    "gn:dem":412,
    "gn:feature_class":"P",
    "gn:feature_code":"PPL",
    "gn:name":"\u2018Ukaysah",
    "gn:population":0,
    "gn:timezone":"Asia/Aden",
    "iso:country":"YE",
    "name:und_x_variant":[
        "\u2018Ukayshah",
        "\u2018Ukaysah"
    ],
    "wof:name":"`Ukaysah",
    "wof:placetype":"locality"
},
  "geometry": {"coordinates":[43.92083,13.02278],"type":"Point"}
}