{
  "type": "Feature",
  "properties": {
    "gn:country":"YE",
    "gn:fcode":"PPL",
    "gn:pop":5,
    "iso:country":"YE",
    "name:ara_x_preferred":[
        "\u0623\u0645 \u0627\u0644\u0632\u0628\u0627\u0631"
    ],
    "name:eng_x_preferred":[
        "Umm Az Zubar"
    ],
    "qs:name":"Umm az Zub\u0101r",
    "qs:photos_9r":0,
    "qs:photos_sr":0,
    "qs:pop_sr":"1",
    "wof:name":"Umm az Zub\u0101r",
    "wof:placetype":"locality",
    "wof:population":5
},
  "geometry": {"coordinates":[44.79907,16.1417],"type":"Point"}
}