{
  "type": "Feature",
  "properties": {
    "gn:country":"YE",
    "gn:fcode":"PPL",
    "gn:pop":2,
    "iso:country":"YE",
    "name:ara_x_preferred":[
        "\u063a\u0627\u0631\u0628 \u0627\u0644\u062d\u0645\u0644\u064a"
    ],
    "name:eng_x_preferred":[
        "Gharib Al Hamiliyah"
    ],
    "qs:name":"Gh\u0101rib al \u1e28amil\u012byah",
    "qs:photos_9r":0,
    "qs:photos_sr":0,
    "qs:pop_sr":"1",
    "wof:name":"Gh\u0101rib al \u1e28amil\u012byah",
    "wof:placetype":"locality",
    "wof:population":2
},
  "geometry": {"coordinates":[43.41462,16.13839],"type":"Point"}
}