{
  "type": "Feature",
  "properties": {
    "gn:admin1_code":"25.0",
    "gn:admin2_code":"1505.0",
    "gn:asciiname":"Wadi Bahsus",
    "gn:country_code":"YE",
    "gn:dem":750,
    "gn:feature_class":"P",
    "gn:feature_code":"PPL",
    "gn:name":"W\u0101d\u012b Bahs\u016bs",
    "gn:population":0,
    "gn:timezone":"Asia/Aden",
    "iso:country":"YE",
    "name:und_x_variant":[
        "W\u0101d\u012b Bahs\u016bs"
    ],
    "wof:name":"Wadi Bahsus",
    "wof:placetype":"locality"
},
  "geometry": {"coordinates":[43.77028,13.59361],"type":"Point"}
}