{
  "type": "Feature",
  "properties": {
    "gn:admin1_code":"4.0",
    "gn:admin2_code":"1919.0",
    "gn:asciiname":"Qar`an",
    "gn:country_code":"YE",
    "gn:dem":734,
    "gn:feature_class":"P",
    "gn:feature_code":"PPL",
    "gn:name":"Qar\u2018\u0101n",
    "gn:population":0,
    "gn:timezone":"Asia/Aden",
    "iso:country":"YE",
    "name:nno_x_preferred":[
        "Qar`an"
    ],
    "name:und_x_variant":[
        "Kar\u2018\u0101n",
        "Qar\u2018\u0101n"
    ],
    "wof:name":"Qar`an",
    "wof:placetype":"locality"
},
  "geometry": {"coordinates":[48.29861,15.67361],"type":"Point"}
}