{
  "type": "Feature",
  "properties": {
    "gn:admin1_code":"8.0",
    "gn:admin2_code":"1801.0",
    "gn:asciiname":"Dayr `Ali al Makki",
    "gn:country_code":"YE",
    "gn:dem":132,
    "gn:feature_class":"P",
    "gn:feature_code":"PPL",
    "gn:name":"Dayr \u2018Al\u012b al Makk\u012b",
    "gn:population":0,
    "gn:timezone":"Asia/Aden",
    "iso:country":"YE",
    "name:und_x_variant":[
        "Dayr \u2018Al\u012b al Makk\u012b"
    ],
    "wof:name":"Dayr `Ali al Makki",
    "wof:placetype":"locality"
},
  "geometry": {"coordinates":[43.13902,15.83941],"type":"Point"}
}