{
  "type": "Feature",
  "properties": {
    "gn:admin1_code":"11.0",
    "gn:admin2_code":"2006.0",
    "gn:asciiname":"As Sabal",
    "gn:country_code":"YE",
    "gn:dem":1578,
    "gn:feature_class":"P",
    "gn:feature_code":"PPL",
    "gn:name":"As Sabal",
    "gn:population":0,
    "gn:timezone":"Asia/Aden",
    "iso:country":"YE",
    "wof:name":"As Sabal",
    "wof:placetype":"locality"
},
  "geometry": {"coordinates":[43.91325,14.36903],"type":"Point"}
}