{
  "type": "Feature",
  "properties": {
    "gn:admin1_code":"8.0",
    "gn:admin2_code":"1818.0",
    "gn:asciiname":"Shatt al Jubn",
    "gn:country_code":"YE",
    "gn:dem":666,
    "gn:feature_class":"P",
    "gn:feature_code":"PPL",
    "gn:name":"Sha\u0163\u0163 al Jubn",
    "gn:population":0,
    "gn:timezone":"Asia/Aden",
    "iso:country":"YE",
    "name:und_x_variant":[
        "Sha\u0163\u0163 al Jubn"
    ],
    "wof:name":"Shatt al Jubn",
    "wof:placetype":"locality"
},
  "geometry": {"coordinates":[43.77266,14.05754],"type":"Point"}
}