{
  "type": "Feature",
  "properties": {
    "gn:admin1_code":"8.0",
    "gn:admin2_code":"1824.0",
    "gn:asciiname":"Bayt al Bazaz",
    "gn:country_code":"YE",
    "gn:dem":152,
    "gn:feature_class":"P",
    "gn:feature_code":"PPL",
    "gn:name":"Bayt al Baz\u0101z",
    "gn:population":0,
    "gn:timezone":"Asia/Aden",
    "iso:country":"YE",
    "name:und_x_variant":[
        "Al Baz\u0101zah",
        "El Bazaze",
        "Bazey",
        "Bayt al Baz\u0101z"
    ],
    "wof:name":"Bayt al Bazaz",
    "wof:placetype":"locality"
},
  "geometry": {"coordinates":[43.45174,13.99933],"type":"Point"}
}