{
  "type": "Feature",
  "properties": {
    "gn:admin1_code":"16.0",
    "gn:admin2_code":"2303.0",
    "gn:asciiname":"Ar Razzaqi",
    "gn:country_code":"YE",
    "gn:dem":2158,
    "gn:feature_class":"P",
    "gn:feature_code":"PPL",
    "gn:name":"Ar Razz\u0101q\u012b",
    "gn:population":0,
    "gn:timezone":"Asia/Aden",
    "iso:country":"YE",
    "name:ara_x_preferred":[
        "\u0627\u0644\u0631\u0632\u0627\u0642\u064a"
    ],
    "name:und_x_variant":[
        "Ar Razz\u0101q\u012b"
    ],
    "wof:name":"Ar Razzaqi",
    "wof:placetype":"locality"
},
  "geometry": {"coordinates":[44.52693,15.74931],"type":"Point"}
}