{
  "type": "Feature",
  "properties": {
    "gn:admin1_code":"10.0",
    "gn:admin2_code":"2703.0",
    "gn:asciiname":"Bayt Humaydah",
    "gn:country_code":"YE",
    "gn:dem":2173,
    "gn:feature_class":"P",
    "gn:feature_code":"PPL",
    "gn:name":"Bayt \u1e28umay\u1e11ah",
    "gn:population":0,
    "gn:timezone":"Asia/Aden",
    "iso:country":"YE",
    "name:und_x_variant":[
        "Bayt \u1e28umay\u1e11ah"
    ],
    "wof:name":"Bayt Humaydah",
    "wof:placetype":"locality"
},
  "geometry": {"coordinates":[43.6873,15.47286],"type":"Point"}
}