{
  "type": "Feature",
  "properties": {
    "gn:admin1_code":"19.0",
    "gn:admin2_code":"2906.0",
    "gn:asciiname":"Al Jimlul",
    "gn:country_code":"YE",
    "gn:dem":2375,
    "gn:feature_class":"P",
    "gn:feature_code":"PPL",
    "gn:name":"Al Jiml\u016bl",
    "gn:population":0,
    "gn:timezone":"Asia/Aden",
    "iso:country":"YE",
    "name:ara_x_preferred":[
        "Al Jiml\u016bl"
    ],
    "wof:name":"Al Jimlul",
    "wof:placetype":"locality"
},
  "geometry": {"coordinates":[43.64953,16.21279],"type":"Point"}
}