{
  "type": "Feature",
  "properties": {
    "gn:admin1_code":"25.0",
    "gn:admin2_code":"1505.0",
    "gn:asciiname":"Wahijah",
    "gn:country_code":"YE",
    "gn:dem":484,
    "gn:feature_class":"P",
    "gn:feature_code":"PPL",
    "gn:name":"W\u0101\u1e29ijah",
    "gn:population":0,
    "gn:timezone":"Asia/Aden",
    "iso:country":"YE",
    "name:ara_x_preferred":[
        "\u0648\u0627\u062d\u062c\u0629"
    ],
    "name:und_x_variant":[
        "Qaryat W\u0101\u1e29ijah",
        "W\u0101\u1e29ijah"
    ],
    "wof:name":"Wahijah",
    "wof:placetype":"locality"
},
  "geometry": {"coordinates":[43.66992,13.47228],"type":"Point"}
}