{
  "type": "Feature",
  "properties": {
    "gn:admin1_code":"3.0",
    "gn:admin2_code":"2807.0",
    "gn:asciiname":"Liban",
    "gn:country_code":"YE",
    "gn:dem":5,
    "gn:feature_class":"P",
    "gn:feature_code":"PPL",
    "gn:name":"L\u012bb\u0101n",
    "gn:population":0,
    "gn:timezone":"Asia/Aden",
    "iso:country":"YE",
    "name:ara_x_preferred":[
        "L\u012bb\u0101n"
    ],
    "wof:name":"Liban",
    "wof:placetype":"locality"
},
  "geometry": {"coordinates":[51.64022,15.39014],"type":"Point"}
}