{
  "type": "Feature",
  "properties": {
    "gn:admin1_code":"16.0",
    "gn:admin2_code":"2313.0",
    "gn:asciiname":"Az Zawariqah",
    "gn:country_code":"YE",
    "gn:dem":2573,
    "gn:feature_class":"P",
    "gn:feature_code":"PPL",
    "gn:name":"Az Zaw\u0101riqah",
    "gn:population":0,
    "gn:timezone":"Asia/Aden",
    "iso:country":"YE",
    "name:und_x_variant":[
        "Az Zaw\u0101riqah"
    ],
    "wof:name":"Az Zawariqah",
    "wof:placetype":"locality"
},
  "geometry": {"coordinates":[44.63022,15.36366],"type":"Point"}
}