{
  "type": "Feature",
  "properties": {
    "gn:country":"YE",
    "gn:fcode":"PPL",
    "gn:population":9,
    "iso:country":"YE",
    "name:ara_x_preferred":[
        "Al \u1e28iy\u0101f"
    ],
    "name:ara_x_variant":[
        "\u0627\u0644\u062d\u064a\u0640\u0627\u0641"
    ],
    "qs:name":"Al \u1e28iy\u0101f",
    "qs:photos_9r":0,
    "qs:photos_sr":0,
    "qs:pop_sr":"1",
    "wof:name":"Al \u1e28iy\u0101f",
    "wof:placetype":"locality",
    "wof:population":9
},
  "geometry": {"coordinates":[43.66958,16.19895],"type":"Point"}
}