{
  "type": "Feature",
  "properties": {
    "gn:country":"YE",
    "gn:fcode":"PPL",
    "gn:pop":16,
    "iso:country":"YE",
    "name:ara_x_preferred":[
        "\u0627\u0644\u0646\u062e\u064a\u0644\u0629"
    ],
    "name:eng_x_preferred":[
        "An Nakhilah"
    ],
    "qs:name":"An Nakh\u012blah",
    "qs:photos_9r":0,
    "qs:photos_sr":0,
    "qs:pop_sr":"1",
    "wof:name":"An Nakh\u012blah",
    "wof:placetype":"locality",
    "wof:population":16
},
  "geometry": {"coordinates":[43.61993,13.1097],"type":"Point"}
}