{
  "type": "Feature",
  "properties": {
    "gn:admin1_code":"4.0",
    "gn:admin2_code":"1916.0",
    "gn:asciiname":"Husun al Qa`",
    "gn:country_code":"YE",
    "gn:dem":993,
    "gn:feature_class":"P",
    "gn:feature_code":"PPL",
    "gn:name":"\u1e28u\u015f\u016bn al Q\u0101\u2018",
    "gn:population":0,
    "gn:timezone":"Asia/Aden",
    "iso:country":"YE",
    "name:und_x_variant":[
        "\u1e28u\u015f\u016bn al Q\u0101\u2018"
    ],
    "wof:name":"Husun al Qa`",
    "wof:placetype":"locality"
},
  "geometry": {"coordinates":[48.95,15.25],"type":"Point"}
}