{
  "type": "Feature",
  "properties": {
    "gn:admin1_code":"21.0",
    "gn:admin2_code":"1611.0",
    "gn:asciiname":"Ma`abil",
    "gn:country_code":"YE",
    "gn:dem":2079,
    "gn:feature_class":"P",
    "gn:feature_code":"PPL",
    "gn:name":"Ma\u2018\u0101bil",
    "gn:population":0,
    "gn:timezone":"Asia/Aden",
    "iso:country":"YE",
    "name:ara_x_preferred":[
        "\u0645\u0639\u0627\u0628\u0644"
    ],
    "name:und_x_variant":[
        "Ma\u2018\u0101bil"
    ],
    "wof:name":"Ma`abil",
    "wof:placetype":"locality"
},
  "geometry": {"coordinates":[44.40967,16.70032999999999],"type":"Point"}
}