{
  "type": "Feature",
  "properties": {
    "gn:admin1_code":"20.0",
    "gn:admin2_code":"1410.0",
    "gn:asciiname":"Am Dijarah",
    "gn:country_code":"YE",
    "gn:dem":2118,
    "gn:feature_class":"P",
    "gn:feature_code":"PPL",
    "gn:name":"Am Dijarah",
    "gn:population":0,
    "gn:timezone":"Asia/Aden",
    "iso:country":"YE",
    "name:und_x_variant":[
        "Umm Dijarah",
        "Am Dijarah",
        "Ad Dijarah"
    ],
    "wof:name":"Am Dijarah",
    "wof:placetype":"locality"
},
  "geometry": {"coordinates":[45.59582,13.94144],"type":"Point"}
}