{
  "type": "Feature",
  "properties": {
    "gn:admin1_code":"15.0",
    "gn:admin2_code":"2205.0",
    "gn:asciiname":"As Sadaqah",
    "gn:country_code":"YE",
    "gn:dem":1425,
    "gn:feature_class":"P",
    "gn:feature_code":"PPL",
    "gn:name":"A\u015f \u015eadaqah",
    "gn:population":0,
    "gn:timezone":"Asia/Aden",
    "iso:country":"YE",
    "name:ara_x_preferred":[
        "\u0627\u0644\u0635\u062f\u0642\u0629"
    ],
    "name:und_x_variant":[
        "A\u015f \u015eadaqah"
    ],
    "wof:name":"As Sadaqah",
    "wof:placetype":"locality"
},
  "geometry": {"coordinates":[43.24276,16.90595],"type":"Point"}
}