{
  "type": "Feature",
  "properties": {
    "gn:admin1_code":"21.0",
    "gn:admin2_code":"1610.0",
    "gn:asciiname":"Rahban",
    "gn:country_code":"YE",
    "gn:dem":1733,
    "gn:feature_class":"P",
    "gn:feature_code":"PPL",
    "gn:name":"Ra\u1e29b\u0101n",
    "gn:population":0,
    "gn:timezone":"Asia/Aden",
    "iso:country":"YE",
    "name:ara_x_preferred":[
        "\u0631\u062d\u0628\u0627\u0646"
    ],
    "name:und_x_variant":[
        "Ra\u1e29b\u0101n"
    ],
    "wof:name":"Rahban",
    "wof:placetype":"locality"
},
  "geometry": {"coordinates":[44.52328,16.91636],"type":"Point"}
}