{
  "type": "Feature",
  "properties": {
    "gn:admin1_code":"8.0",
    "gn:admin2_code":"1824.0",
    "gn:asciiname":"Bayt al Wahsh",
    "gn:country_code":"YE",
    "gn:dem":172,
    "gn:feature_class":"P",
    "gn:feature_code":"PPL",
    "gn:name":"Bayt al Wa\u1e29sh",
    "gn:population":0,
    "gn:timezone":"Asia/Aden",
    "iso:country":"YE",
    "name:und_x_variant":[
        "Bayt al Wa\u1e29sh"
    ],
    "wof:name":"Bayt al Wahsh",
    "wof:placetype":"locality"
},
  "geometry": {"coordinates":[43.42104000000001,14.28324],"type":"Point"}
}