{
  "type": "Feature",
  "properties": {
    "gn:admin1_code":"22.0",
    "gn:admin2_code":"1724.0",
    "gn:asciiname":"Al Qutu`",
    "gn:country_code":"YE",
    "gn:dem":243,
    "gn:feature_class":"P",
    "gn:feature_code":"PPL",
    "gn:name":"Al Qu\u0163\u016b\u2018",
    "gn:population":0,
    "gn:timezone":"Asia/Aden",
    "iso:country":"YE",
    "name:ara_x_preferred":[
        "Al Qu\u0163\u016b\u2018"
    ],
    "wof:name":"Al Qutu`",
    "wof:placetype":"locality"
},
  "geometry": {"coordinates":[43.29694,15.63922],"type":"Point"}
}