{
  "type": "Feature",
  "properties": {
    "gn:gn_country":"YE",
    "gn:gn_fcode":"PPL",
    "gn:gn_pop":7,
    "gn:population":7,
    "iso:country":"YE",
    "name:ara_x_preferred":[
        "\u0634\u0639\u0628 \u0627\u0644\u062d\u0635\u0627\u0631"
    ],
    "name:eng_x_preferred":[
        "Shi'b Al Hisar"
    ],
    "name:eng_x_variant":[
        "Sh\u0101\u0163\u012b \u2018Umar"
    ],
    "name:unk_x_variant":[
        "\u0634\u0639\u0628 \u0627\u0644\u062d\u0635\u0627\u0631"
    ],
    "qs_pg:aaroncc":"YE",
    "qs_pg:gn_country":"YE",
    "qs_pg:gn_fcode":"PPL",
    "qs_pg:gn_pop":7,
    "qs_pg:name":"Shi\u2018b al \u1e28i\u015f\u0101r",
    "qs_pg:photos_9r":0,
    "qs_pg:photos_sr":0,
    "qs_pg:pop_sr":1,
    "qs_pg:qs_pg_placetype":"locality",
    "wof:name":"Shi\u2018b al \u1e28i\u015f\u0101r",
    "wof:placetype":"locality",
    "wof:population":7
},
  "geometry": {"coordinates":[43.17514,16.2289],"type":"Point"}
}