{
  "type": "Feature",
  "properties": {
    "gn:admin1_code":"8.0",
    "gn:admin2_code":"1814.0",
    "gn:asciiname":"Bayt as Sayyid `Umar Yusuf",
    "gn:country_code":"YE",
    "gn:dem":90,
    "gn:feature_class":"P",
    "gn:feature_code":"PPL",
    "gn:name":"Bayt as Sayyid \u2018Umar Y\u016bsuf",
    "gn:population":0,
    "gn:timezone":"Asia/Aden",
    "iso:country":"YE",
    "name:und_x_variant":[
        "Bayt as Sayyid \u2018Umar Y\u016bsuf"
    ],
    "wof:name":"Bayt as Sayyid `Umar Yusuf",
    "wof:placetype":"locality"
},
  "geometry": {"coordinates":[43.22556,14.57695],"type":"Point"}
}