{
  "type": "Feature",
  "properties": {
    "gn:country":"YE",
    "gn:fcode":"PPL",
    "gn:pop":15,
    "iso:country":"YE",
    "name:ara_x_preferred":[
        "\u0627\u0644\u0632\u0639\u0644\u0627"
    ],
    "name:eng_x_preferred":[
        "Az Za'la"
    ],
    "qs:name":"Az Za\u2018l\u0101",
    "qs:photos_9r":0,
    "qs:photos_sr":0,
    "qs:pop_sr":"1",
    "wof:name":"Az Za\u2018l\u0101",
    "wof:placetype":"locality",
    "wof:population":15
},
  "geometry": {"coordinates":[43.67599,16.2864],"type":"Point"}
}