{
  "type": "Feature",
  "properties": {
    "gn:admin1_code":"25.0",
    "gn:admin2_code":"1509.0",
    "gn:asciiname":"Manajid ad Dabab",
    "gn:country_code":"YE",
    "gn:dem":1334,
    "gn:feature_class":"P",
    "gn:feature_code":"PPL",
    "gn:name":"Man\u0101jid a\u1e11 \u1e10ab\u0101b",
    "gn:population":0,
    "gn:timezone":"Asia/Aden",
    "iso:country":"YE",
    "name:und_x_variant":[
        "Man\u0101jid a\u1e11 \u1e10ab\u0101b"
    ],
    "wof:name":"Manajid ad Dabab",
    "wof:placetype":"locality"
},
  "geometry": {"coordinates":[43.93333,13.51667],"type":"Point"}
}