{
  "type": "Feature",
  "properties": {
    "gn:admin1_code":"21.0",
    "gn:admin2_code":"1602.0",
    "gn:asciiname":"Buraybir",
    "gn:country_code":"YE",
    "gn:dem":1324,
    "gn:feature_class":"P",
    "gn:feature_code":"PPLL",
    "gn:name":"Buraybir",
    "gn:population":0,
    "gn:timezone":"Asia/Aden",
    "iso:country":"YE",
    "name:ara_x_preferred":[
        "\u0628\u0631\u064a\u0628\u0631"
    ],
    "wof:name":"Buraybir",
    "wof:placetype":"locality"
},
  "geometry": {"coordinates":[44.41584,16.40986],"type":"Point"}
}