{
  "type": "Feature",
  "properties": {
    "gn:country":"YE",
    "gn:fcode":"PPL",
    "gn:pop":2,
    "iso:country":"YE",
    "name:ara_x_preferred":[
        "\u0627\u0644\u0639\u0627\u0642\u0644\u064a\u0629 \u0627\u0644\u0639\u0644\u064a\u0627"
    ],
    "name:eng_x_preferred":[
        "Al 'Aqiliyah Al 'Ulya"
    ],
    "qs:name":"Al \u2018\u0100qil\u012byah al \u2018Uly\u0101",
    "qs:photos_9r":0,
    "qs:photos_sr":0,
    "qs:pop_sr":"1",
    "wof:name":"Al \u2018\u0100qil\u012byah al \u2018Uly\u0101",
    "wof:placetype":"locality",
    "wof:population":2
},
  "geometry": {"coordinates":[43.62431,16.25014],"type":"Point"}
}