{
  "type": "Feature",
  "properties": {
    "gn:admin1_code":"21.0",
    "gn:admin2_code":"1603.0",
    "gn:asciiname":"Qurayh",
    "gn:country_code":"YE",
    "gn:dem":1234,
    "gn:feature_class":"P",
    "gn:feature_code":"PPLL",
    "gn:name":"Quray\u1e29",
    "gn:population":0,
    "gn:timezone":"Asia/Aden",
    "iso:country":"YE",
    "name:ara_x_preferred":[
        "\u0642\u0631\u064a\u062d"
    ],
    "name:und_x_variant":[
        "Quray\u1e29"
    ],
    "wof:name":"Qurayh",
    "wof:placetype":"locality"
},
  "geometry": {"coordinates":[44.35978,16.13604],"type":"Point"}
}