{
  "type": "Feature",
  "properties": {
    "gn:admin1_code":"20.0",
    "gn:admin2_code":"1404.0",
    "gn:asciiname":"Al Gharra'",
    "gn:country_code":"YE",
    "gn:dem":2059,
    "gn:feature_class":"P",
    "gn:feature_code":"PPL",
    "gn:name":"Al Gharr\u0101\u2019",
    "gn:population":0,
    "gn:timezone":"Asia/Aden",
    "iso:country":"YE",
    "name:und_x_variant":[
        "Al Gharr\u0101\u2019"
    ],
    "wof:name":"Al Gharra'",
    "wof:placetype":"locality"
},
  "geometry": {"coordinates":[45.78555,14.05182],"type":"Point"}
}