{
  "type": "Feature",
  "properties": {
    "gn:country":"YE",
    "gn:fcode":"PPL",
    "gn:pop":6,
    "iso:country":"YE",
    "name:ara_x_preferred":[
        "\u0627\u0644\u0631\u0634\u0646\u0629"
    ],
    "name:eng_x_preferred":[
        "Ar Rushnah"
    ],
    "name:eng_x_variant":[
        "Bi\u2019r al Jad\u012bdah"
    ],
    "qs:name":"Ar Rushnah",
    "qs:photos_9r":0,
    "qs:photos_sr":0,
    "qs:pop_sr":"1",
    "wof:name":"Ar Rushnah",
    "wof:placetype":"locality",
    "wof:population":6
},
  "geometry": {"coordinates":[43.43592,16.27599],"type":"Point"}
}