{
  "type": "Feature",
  "properties": {
    "gn:admin1_code":"19.0",
    "gn:admin2_code":"2914.0",
    "gn:asciiname":"Mahallat Bayt Shamlan",
    "gn:country_code":"YE",
    "gn:dem":1189,
    "gn:feature_class":"P",
    "gn:feature_code":"PPL",
    "gn:name":"Ma\u1e29all\u0101t Bayt Shaml\u0101n",
    "gn:population":0,
    "gn:timezone":"Asia/Aden",
    "iso:country":"YE",
    "name:und_x_variant":[
        "Ma\u1e29all\u0101t Bayt Shaml\u0101n"
    ],
    "wof:name":"Mahallat Bayt Shamlan",
    "wof:placetype":"locality"
},
  "geometry": {"coordinates":[43.73548,15.83348],"type":"Point"}
}