{
  "type": "Feature",
  "properties": {
    "gn:admin1_code":"15.0",
    "gn:admin2_code":"2203.0",
    "gn:asciiname":"Al Mahfid",
    "gn:country_code":"YE",
    "gn:dem":2402,
    "gn:feature_class":"P",
    "gn:feature_code":"PPL",
    "gn:name":"Al Ma\u1e29fid",
    "gn:population":0,
    "gn:timezone":"Asia/Aden",
    "iso:country":"YE",
    "name:ara_x_preferred":[
        "\u0627\u0644\u0645\u062d\u0641\u062f"
    ],
    "name:und_x_variant":[
        "Al Ma\u1e29fid"
    ],
    "wof:name":"Al Mahfid",
    "wof:placetype":"locality"
},
  "geometry": {"coordinates":[43.39019,17.24012999999999],"type":"Point"}
}