{
  "type": "Feature",
  "properties": {
    "gn:admin1_code":"25.0",
    "gn:admin2_code":"1515.0",
    "gn:asciiname":"Al Barunah",
    "gn:country_code":"YE",
    "gn:dem":876,
    "gn:feature_class":"P",
    "gn:feature_code":"PPL",
    "gn:name":"Al Bar\u016bnah",
    "gn:population":0,
    "gn:timezone":"Asia/Aden",
    "iso:country":"YE",
    "name:ara_x_preferred":[
        "\u0627\u0644\u0628\u0631\u0648\u0646\u0629"
    ],
    "name:und_x_variant":[
        "Al Bar\u016bnah"
    ],
    "wof:name":"Al Barunah",
    "wof:placetype":"locality"
},
  "geometry": {"coordinates":[43.97757,13.08575],"type":"Point"}
}