{
  "type": "Feature",
  "properties": {
    "gn:admin1_code":"20.0",
    "gn:admin2_code":"1408.0",
    "gn:asciiname":"Bilas",
    "gn:country_code":"YE",
    "gn:dem":2259,
    "gn:feature_class":"P",
    "gn:feature_code":"PPL",
    "gn:name":"Bil\u0101s",
    "gn:population":0,
    "gn:timezone":"Asia/Aden",
    "iso:country":"YE",
    "name:ara_x_preferred":[
        "Bil\u0101s"
    ],
    "name:ukr_x_preferred":[
        "\u0411\u0456\u043b\u0430\u0441"
    ],
    "name:und_x_variant":[
        "Bal\u0101s"
    ],
    "wof:name":"Bilas",
    "wof:placetype":"locality"
},
  "geometry": {"coordinates":[45.74419,13.91945],"type":"Point"}
}