{
  "type": "Feature",
  "properties": {
    "gn:admin1_code":"22.0",
    "gn:admin2_code":"1708.0",
    "gn:asciiname":"Bani Humran",
    "gn:country_code":"YE",
    "gn:dem":979,
    "gn:feature_class":"P",
    "gn:feature_code":"PPL",
    "gn:name":"Ban\u012b \u1e28umr\u0101n",
    "gn:population":0,
    "gn:timezone":"Asia/Aden",
    "iso:country":"YE",
    "name:und_x_variant":[
        "Ban\u012b \u1e28umr\u0101n"
    ],
    "wof:name":"Bani Humran",
    "wof:placetype":"locality"
},
  "geometry": {"coordinates":[43.58864000000001,16.03879],"type":"Point"}
}