{
  "type": "Feature",
  "properties": {
    "gn:admin1_code":"24.0",
    "gn:admin2_code":"2512.0",
    "gn:asciiname":"Al Kabbah",
    "gn:country_code":"YE",
    "gn:dem":1066,
    "gn:feature_class":"P",
    "gn:feature_code":"PPL",
    "gn:name":"Al Kabbah",
    "gn:population":0,
    "gn:timezone":"Asia/Aden",
    "iso:country":"YE",
    "name:ara_x_preferred":[
        "\u0627\u0644\u0643\u0628\u0629"
    ],
    "wof:name":"Al Kabbah",
    "wof:placetype":"locality"
},
  "geometry": {"coordinates":[44.23137,13.21169],"type":"Point"}
}