{
  "type": "Feature",
  "properties": {
    "gn:admin1_code":"25.0",
    "gn:admin2_code":"1517.0",
    "gn:asciiname":"Ja'fat al Jabal",
    "gn:country_code":"YE",
    "gn:dem":1065,
    "gn:feature_class":"P",
    "gn:feature_code":"PPL",
    "gn:name":"Ja\u2018fat al Jabal",
    "gn:population":0,
    "gn:timezone":"Asia/Aden",
    "iso:country":"YE",
    "name:ara_x_preferred":[
        "\u062c\u0639\u0641\u0629 \u0627\u0644\u062c\u0628\u0644"
    ],
    "name:und_x_variant":[
        "Ja\u2018fat al Jabal"
    ],
    "wof:name":"Ja'fat al Jabal",
    "wof:placetype":"locality"
},
  "geometry": {"coordinates":[44.24502,13.24084],"type":"Point"}
}