{
  "type": "Feature",
  "properties": {
    "gn:admin1_code":"19.0",
    "gn:admin2_code":"2917.0",
    "gn:asciiname":"Ad Darb",
    "gn:country_code":"YE",
    "gn:dem":2901,
    "gn:feature_class":"P",
    "gn:feature_code":"PPL",
    "gn:name":"Ad Darb",
    "gn:population":0,
    "gn:timezone":"Asia/Aden",
    "iso:country":"YE",
    "wof:name":"Ad Darb",
    "wof:placetype":"locality"
},
  "geometry": {"coordinates":[43.87085,15.60181],"type":"Point"}
}