{
  "type": "Feature",
  "properties": {
    "gn:gn_country":"YE",
    "gn:gn_fcode":"PPL",
    "gn:gn_pop":8,
    "gn:population":8,
    "iso:country":"YE",
    "name:ara_x_preferred":[
        "\u0627\u0644\u0645\u062c\u0639\u062f\u0644\u0629"
    ],
    "name:eng_x_preferred":[
        "Al Maj'adilah"
    ],
    "qs_pg:aaroncc":"YE",
    "qs_pg:gn_country":"YE",
    "qs_pg:gn_fcode":"PPL",
    "qs_pg:gn_pop":8,
    "qs_pg:name":"Al Maj\u2018adilah",
    "qs_pg:photos_9r":0,
    "qs_pg:photos_sr":0,
    "qs_pg:pop_sr":1,
    "qs_pg:qs_pg_placetype":"locality",
    "wof:name":"Al Maj\u2018adilah",
    "wof:placetype":"locality",
    "wof:population":8
},
  "geometry": {"coordinates":[43.36864,16.30476],"type":"Point"}
}