{
  "type": "Feature",
  "properties": {
    "gn:admin1_code":"22.0",
    "gn:admin2_code":"1722.0",
    "gn:asciiname":"Hanadiwah",
    "gn:country_code":"YE",
    "gn:dem":575,
    "gn:feature_class":"P",
    "gn:feature_code":"PPL",
    "gn:name":"Han\u0101diwah",
    "gn:population":0,
    "gn:timezone":"Asia/Aden",
    "iso:country":"YE",
    "name:und_x_variant":[
        "Han\u0101diwah"
    ],
    "wof:name":"Hanadiwah",
    "wof:placetype":"locality"
},
  "geometry": {"coordinates":[43.31363,15.80619],"type":"Point"}
}