{
  "type": "Feature",
  "properties": {
    "gn:admin1_code":"19.0",
    "gn:admin2_code":"2904.0",
    "gn:asciiname":"Kharab at Tabishi",
    "gn:country_code":"YE",
    "gn:dem":1116,
    "gn:feature_class":"P",
    "gn:feature_code":"PPL",
    "gn:name":"Khar\u0101b a\u0163 \u0162abish\u012b",
    "gn:population":0,
    "gn:timezone":"Asia/Aden",
    "iso:country":"YE",
    "name:und_x_variant":[
        "Khar\u0101b a\u0163 \u0162abish\u012b"
    ],
    "wof:name":"Kharab at Tabishi",
    "wof:placetype":"locality"
},
  "geometry": {"coordinates":[43.79529,16.15141],"type":"Point"}
}