{
  "type": "Feature",
  "properties": {
    "gn:country":"YE",
    "gn:fcode":"PPLL",
    "gn:population":11,
    "iso:country":"YE",
    "name:ara_x_preferred":[
        "\u0628\u0637\u062d"
    ],
    "name:eng_x_preferred":[
        "Batih"
    ],
    "name:eng_x_variant":[
        "Al \u2018Irf\u0101\u2019"
    ],
    "qs:name":"Ba\u0163i\u1e29",
    "qs:photos_9r":0,
    "qs:photos_sr":0,
    "qs:pop_sr":"1",
    "wof:name":"Ba\u0163i\u1e29",
    "wof:placetype":"locality",
    "wof:population":11
},
  "geometry": {"coordinates":[44.05865,17.30713],"type":"Point"}
}