{
  "type": "Feature",
  "properties": {
    "gn:admin1_code":"8.0",
    "gn:admin2_code":"1825.0",
    "gn:asciiname":"Bayt az Zayn",
    "gn:country_code":"YE",
    "gn:dem":163,
    "gn:feature_class":"P",
    "gn:feature_code":"PPL",
    "gn:name":"Bayt az Zayn",
    "gn:population":0,
    "gn:timezone":"Asia/Aden",
    "iso:country":"YE",
    "wof:name":"Bayt az Zayn",
    "wof:placetype":"locality"
},
  "geometry": {"coordinates":[43.44445,14.03472],"type":"Point"}
}