{
  "type": "Feature",
  "properties": {
    "gn:admin1_code":"16.0",
    "gn:admin2_code":"2313.0",
    "gn:asciiname":"Bayt ash Shami",
    "gn:country_code":"YE",
    "gn:dem":2620,
    "gn:feature_class":"P",
    "gn:feature_code":"PPL",
    "gn:name":"Bayt ash Sh\u0101m\u012b",
    "gn:population":0,
    "gn:timezone":"Asia/Aden",
    "iso:country":"YE",
    "name:ara_x_preferred":[
        "\u0628\u064a\u062a \u0627\u0644\u0634\u0627\u0645\u064a"
    ],
    "name:und_x_variant":[
        "Bayt ash Sh\u0101m\u012b"
    ],
    "wof:name":"Bayt ash Shami",
    "wof:placetype":"locality"
},
  "geometry": {"coordinates":[44.65119,15.40037],"type":"Point"}
}