{
  "type": "Feature",
  "properties": {
    "gn:admin1_code":"23.0",
    "gn:admin2_code":"1105.0",
    "gn:asciiname":"Manzil ash Sharaf",
    "gn:country_code":"YE",
    "gn:dem":2144,
    "gn:feature_class":"P",
    "gn:feature_code":"PPL",
    "gn:name":"Manzil ash Sharaf",
    "gn:population":0,
    "gn:timezone":"Asia/Aden",
    "iso:country":"YE",
    "wof:name":"Manzil ash Sharaf",
    "wof:placetype":"locality"
},
  "geometry": {"coordinates":[44.42394,13.99065],"type":"Point"}
}