{
  "type": "Feature",
  "properties": {
    "gn:country":"YE",
    "gn:fcode":"PPL",
    "gn:population":1,
    "iso:country":"YE",
    "name:ara_x_preferred":[
        "\u062c\u0627\u0648\u0641"
    ],
    "name:eng_x_preferred":[
        "Jawaf"
    ],
    "name:eng_x_variant":[
        "Al Khar\u0101bah"
    ],
    "qs:name":"J\u0101waf",
    "qs:photos_9r":0,
    "qs:photos_sr":0,
    "qs:pop_sr":"1",
    "wof:name":"J\u0101waf",
    "wof:placetype":"locality",
    "wof:population":1
},
  "geometry": {"coordinates":[43.67717,16.08339],"type":"Point"}
}