{
  "type": "Feature",
  "properties": {
    "gn:admin1_code":"23.0",
    "gn:admin2_code":"1103.0",
    "gn:asciiname":"Maswarah",
    "gn:country_code":"YE",
    "gn:dem":2432,
    "gn:feature_class":"P",
    "gn:feature_code":"PPL",
    "gn:name":"Maswarah",
    "gn:population":0,
    "gn:timezone":"Asia/Aden",
    "iso:country":"YE",
    "wof:name":"Maswarah",
    "wof:placetype":"locality"
},
  "geometry": {"coordinates":[44.52844,14.21608],"type":"Point"}
}