{
  "type": "Feature",
  "properties": {
    "gn:admin1_code":"16.0",
    "gn:admin2_code":"2302.0",
    "gn:asciiname":"Bayt Abu Dajjanah",
    "gn:country_code":"YE",
    "gn:dem":2441,
    "gn:feature_class":"P",
    "gn:feature_code":"PPL",
    "gn:name":"Bayt Ab\u016b Dajj\u0101nah",
    "gn:population":0,
    "gn:timezone":"Asia/Aden",
    "iso:country":"YE",
    "name:ara_x_preferred":[
        "\u0628\u064a\u062a \u0623\u0628\u0648 \u062f\u062c\u0627\u0646\u0629"
    ],
    "name:und_x_variant":[
        "Bayt Ab\u016b Dajj\u0101nah"
    ],
    "wof:name":"Bayt Abu Dajjanah",
    "wof:placetype":"locality"
},
  "geometry": {"coordinates":[44.24578,15.80279],"type":"Point"}
}