{
  "type": "Feature",
  "properties": {
    "gn:country":"YE",
    "gn:fcode":"PPL",
    "gn:population":1,
    "iso:country":"YE",
    "name:ara_x_preferred":[
        "Z\u0327\u0101hir Qu\u015f\u0101d\u012b"
    ],
    "name:ara_x_variant":[
        "\u0638\u0627\u0647\u0631 \u0642\u0635\u0627\u062f\u064a"
    ],
    "name:eng_x_preferred":[
        "Zahir Qusadi"
    ],
    "name:eng_x_variant":[
        "Al \u1e28\u0101zah"
    ],
    "qs:name":"Z\u0327\u0101hir Qu\u015f\u0101d\u012b",
    "qs:photos_9r":0,
    "qs:photos_sr":0,
    "qs:pop_sr":"1",
    "wof:name":"Z\u0327\u0101hir Qu\u015f\u0101d\u012b",
    "wof:placetype":"locality",
    "wof:population":1
},
  "geometry": {"coordinates":[43.35316,16.6698],"type":"Point"}
}