{
  "type": "Feature",
  "properties": {
    "gn:admin1_code":"5.0",
    "gn:asciiname":"Al Bahhar",
    "gn:country_code":"YE",
    "gn:dem":1166,
    "gn:feature_class":"P",
    "gn:feature_code":"PPL",
    "gn:name":"Al Ba\u1e29\u1e29\u0101r",
    "gn:population":0,
    "gn:timezone":"Asia/Aden",
    "iso:country":"YE",
    "name:ara_x_preferred":[
        "\u0627\u0644\u0628\u062d\u0627\u0631"
    ],
    "name:und_x_variant":[
        "Al Ba\u1e29\u1e29\u0101r"
    ],
    "wof:name":"Al Bahhar",
    "wof:placetype":"locality"
},
  "geometry": {"coordinates":[45.98476,14.56436],"type":"Point"}
}