{
  "type": "Feature",
  "properties": {
    "gn:admin1_code":"10.0",
    "gn:admin2_code":"2701.0",
    "gn:asciiname":"Al Wa`r",
    "gn:country_code":"YE",
    "gn:dem":1827,
    "gn:feature_class":"P",
    "gn:feature_code":"PPL",
    "gn:name":"Al Wa\u2018r",
    "gn:population":0,
    "gn:timezone":"Asia/Aden",
    "iso:country":"YE",
    "name:und_x_variant":[
        "Al Wa\u2018r"
    ],
    "wof:name":"Al Wa`r",
    "wof:placetype":"locality"
},
  "geometry": {"coordinates":[43.89324000000001,15.42119],"type":"Point"}
}