{
  "type": "Feature",
  "properties": {
    "gn:admin1_code":"22.0",
    "gn:admin2_code":"1712.0",
    "gn:asciiname":"Wadi al Hadi",
    "gn:country_code":"YE",
    "gn:dem":257,
    "gn:feature_class":"P",
    "gn:feature_code":"PPLL",
    "gn:name":"W\u0101d\u012b al Had\u012b",
    "gn:population":0,
    "gn:timezone":"Asia/Aden",
    "iso:country":"YE",
    "name:ara_x_preferred":[
        "\u0648\u0627\u062f\u064a \u0627\u0644\u0647\u062f\u064a"
    ],
    "name:und_x_variant":[
        "Ma\u1e29all W\u0101d\u012b al Had\u012b",
        "W\u0101d\u012b al Had\u012b"
    ],
    "wof:name":"Wadi al Hadi",
    "wof:placetype":"locality"
},
  "geometry": {"coordinates":[43.24191,16.17407],"type":"Point"}
}