{
  "type": "Feature",
  "properties": {
    "gn:country":"YE",
    "gn:fcode":"PPL",
    "gn:pop":15,
    "iso:country":"YE",
    "name:ara_x_preferred":[
        "\u0627\u0644\u062a \u0642\u0644\u064a\u0644\u064a"
    ],
    "name:eng_x_preferred":[
        "Alt Qulayli"
    ],
    "name:eng_x_variant":[
        "Qa\u015fabat Khaz\u0101\u2018"
    ],
    "qs:name":"Alt Qulayl\u012b",
    "qs:photos_9r":0,
    "qs:photos_sr":0,
    "qs:pop_sr":"1",
    "wof:name":"Alt Qulayl\u012b",
    "wof:placetype":"locality",
    "wof:population":15
},
  "geometry": {"coordinates":[43.28477,16.94214],"type":"Point"}
}