{
  "type": "Feature",
  "properties": {
    "gn:country":"YE",
    "gn:fcode":"PPLX",
    "gn:pop":29,
    "iso:country":"YE",
    "name:ara_x_preferred":[
        "\u0639\u0645\u062f"
    ],
    "qs:name":"\u2018Amad",
    "qs:photos_9r":0,
    "qs:photos_sr":0,
    "qs:pop_sr":"1",
    "wd:wordcount":42,
    "wof:name":"\u2018Amad",
    "wof:placetype":"neighbourhood",
    "wof:population":29
},
  "geometry": {"coordinates":[43.43209,16.78006],"type":"Point"}
}