{
  "type": "Feature",
  "properties": {
    "gn:admin1_code":"22.0",
    "gn:admin2_code":"1718.0",
    "gn:asciiname":"Bayt al Hajar",
    "gn:country_code":"YE",
    "gn:dem":2075,
    "gn:feature_class":"P",
    "gn:feature_code":"PPL",
    "gn:name":"Bayt al \u1e28ajar",
    "gn:population":0,
    "gn:timezone":"Asia/Aden",
    "iso:country":"YE",
    "name:und_x_variant":[
        "Bayt al \u1e28ajar"
    ],
    "wof:name":"Bayt al Hajar",
    "wof:placetype":"locality"
},
  "geometry": {"coordinates":[43.68322,15.75519],"type":"Point"}
}