{
  "type": "Feature",
  "properties": {
    "gn:admin1_code":"21.0",
    "gn:admin2_code":"1605.0",
    "gn:asciiname":"Al `Asalat",
    "gn:country_code":"YE",
    "gn:dem":1119,
    "gn:feature_class":"P",
    "gn:feature_code":"PPL",
    "gn:name":"Al \u2018A\u015fal\u0101t",
    "gn:population":0,
    "gn:timezone":"Asia/Aden",
    "iso:country":"YE",
    "name:ara_x_preferred":[
        "\u0627\u0644\u0639\u0635\u0644\u0627\u062a"
    ],
    "name:und_x_variant":[
        "Al \u2018A\u015fal\u0101t"
    ],
    "wof:name":"Al `Asalat",
    "wof:placetype":"locality"
},
  "geometry": {"coordinates":[44.75534,16.17529],"type":"Point"}
}