{
  "type": "Feature",
  "properties": {
    "gn:country":"YE",
    "gn:fcode":"PPL",
    "gn:pop":6,
    "iso:country":"YE",
    "name:ara_x_preferred":[
        "\u0627\u0644\u0645\u0648\u0632\u064a\u0627\u062a"
    ],
    "name:eng_x_preferred":[
        "Al Mawziyat"
    ],
    "name:eng_x_variant":[
        "Ban\u012b Ja\u2018far"
    ],
    "qs:name":"Al Mawz\u012by\u0101t",
    "qs:photos_9r":0,
    "qs:photos_sr":0,
    "qs:pop_sr":"1",
    "wof:name":"Al Mawz\u012by\u0101t",
    "wof:placetype":"locality",
    "wof:population":6
},
  "geometry": {"coordinates":[43.36759,16.13312],"type":"Point"}
}