{
  "type": "Feature",
  "properties": {
    "gn:country":"YE",
    "gn:fcode":"PPL",
    "gn:population":18,
    "iso:country":"YE",
    "name:ara_x_preferred":[
        "\u0100l S\u0101mir"
    ],
    "name:ara_x_variant":[
        "\u0627\u0644 \u0633\u0627\u0645\u0631"
    ],
    "name:eng_x_preferred":[
        "Al Samir"
    ],
    "name:eng_x_variant":[
        "Gh\u0101rib Qumr"
    ],
    "qs:name":"\u0100l S\u0101mir",
    "qs:photos_9r":0,
    "qs:photos_sr":0,
    "qs:pop_sr":"1",
    "wof:name":"\u0100l S\u0101mir",
    "wof:placetype":"locality",
    "wof:population":18
},
  "geometry": {"coordinates":[43.82198,17.03066],"type":"Point"}
}