{
  "type": "Feature",
  "properties": {
    "gn:country":"YE",
    "gn:fcode":"PPL",
    "gn:population":3,
    "iso:country":"YE",
    "name:ara_x_preferred":[
        "\u063a\u0627\u0631\u0628 \u0627\u0644\u0633\u0647\u0648"
    ],
    "name:eng_x_preferred":[
        "Gharib As Sahw"
    ],
    "name:nno_x_preferred":[
        "Al Hanakah"
    ],
    "qs:name":"Gh\u0101rib as Sahw",
    "qs:photos_9r":0,
    "qs:photos_sr":0,
    "qs:pop_sr":"1",
    "wof:name":"Gh\u0101rib as Sahw",
    "wof:placetype":"locality",
    "wof:population":3
},
  "geometry": {"coordinates":[43.3306,16.65398],"type":"Point"}
}