{
  "type": "Feature",
  "properties": {
    "gn:admin1_code":"20.0",
    "gn:admin2_code":"1404.0",
    "gn:asciiname":"Dammaj",
    "gn:country_code":"YE",
    "gn:dem":1955,
    "gn:feature_class":"P",
    "gn:feature_code":"PPL",
    "gn:name":"Damm\u0101j",
    "gn:population":0,
    "gn:timezone":"Asia/Aden",
    "iso:country":"YE",
    "name:ara_x_preferred":[
        "\u062f\u0645\u0627\u062c"
    ],
    "name:und_x_variant":[
        "Damm\u0101j"
    ],
    "wof:name":"Dammaj",
    "wof:placetype":"locality"
},
  "geometry": {"coordinates":[45.83724,14.23814],"type":"Point"}
}