{
  "type": "Feature",
  "properties": {
    "gn:admin1_code":"8.0",
    "gn:admin2_code":"1802.0",
    "gn:asciiname":"Bani Qutb",
    "gn:country_code":"YE",
    "gn:dem":56,
    "gn:feature_class":"P",
    "gn:feature_code":"PPL",
    "gn:name":"Ban\u012b Qu\u0163b",
    "gn:population":0,
    "gn:timezone":"Asia/Aden",
    "iso:country":"YE",
    "name:ara_x_preferred":[
        "\u0628\u0646\u064a \u0642\u0637\u0628"
    ],
    "name:und_x_variant":[
        "Ban\u012b Qu\u0163b"
    ],
    "wof:name":"Bani Qutb",
    "wof:placetype":"locality"
},
  "geometry": {"coordinates":[42.93329,15.6876],"type":"Point"}
}