{
  "type": "Feature",
  "properties": {
    "gn:admin1_code":"16.0",
    "gn:admin2_code":"2314.0",
    "gn:asciiname":"Ad Duwayli`",
    "gn:country_code":"YE",
    "gn:dem":2127,
    "gn:feature_class":"P",
    "gn:feature_code":"PPL",
    "gn:name":"A\u1e11 \u1e10uwayli\u2018",
    "gn:population":0,
    "gn:timezone":"Asia/Aden",
    "iso:country":"YE",
    "name:und_x_variant":[
        "A\u1e11 \u1e10uwayli\u2018"
    ],
    "wof:name":"Ad Duwayli`",
    "wof:placetype":"locality"
},
  "geometry": {"coordinates":[44.80032,15.1585],"type":"Point"}
}