{
  "type": "Feature",
  "properties": {
    "gn:admin1_code":"8.0",
    "gn:admin2_code":"1813.0",
    "gn:asciiname":"Al Jurwah",
    "gn:country_code":"YE",
    "gn:dem":150,
    "gn:feature_class":"P",
    "gn:feature_code":"PPL",
    "gn:name":"Al Jurwah",
    "gn:population":0,
    "gn:timezone":"Asia/Aden",
    "iso:country":"YE",
    "name:ara_x_preferred":[
        "\u0627\u0644\u062c\u0631\u0648\u0629"
    ],
    "name:und_x_variant":[
        "Ma\u1e29all al Jurwah",
        "Al Jurwah"
    ],
    "wof:name":"Al Jurwah",
    "wof:placetype":"locality"
},
  "geometry": {"coordinates":[43.33675,14.89484],"type":"Point"}
}