{
  "type": "Feature",
  "properties": {
    "gn:country":"YE",
    "gn:fcode":"PPL",
    "gn:pop":4,
    "iso:country":"YE",
    "name:ara_x_preferred":[
        "\u0627\u0644\u062e\u064a\u0627\u0637\u064a"
    ],
    "name:eng_x_preferred":[
        "Al Khayati"
    ],
    "name:eng_x_variant":[
        "Al Qu\u015fayr"
    ],
    "qs:name":"Al Khay\u0101\u0163\u012b",
    "qs:photos_9r":0,
    "qs:photos_sr":0,
    "qs:pop_sr":"1",
    "wof:name":"Al Khay\u0101\u0163\u012b",
    "wof:placetype":"locality",
    "wof:population":4
},
  "geometry": {"coordinates":[43.33991,16.73805],"type":"Point"}
}