{
  "type": "Feature",
  "properties": {
    "gn:admin1_code":"22.0",
    "gn:admin2_code":"1703.0",
    "gn:asciiname":"Az Zayla`iyah",
    "gn:country_code":"YE",
    "gn:dem":40,
    "gn:feature_class":"P",
    "gn:feature_code":"PPL",
    "gn:name":"Az Zayla\u2018\u012byah",
    "gn:population":0,
    "gn:timezone":"Asia/Aden",
    "iso:country":"YE",
    "name:und_x_variant":[
        "Az Zayla\u2018\u012bah",
        "Az Zayla\u2018\u012byah"
    ],
    "wof:name":"Az Zayla`iyah",
    "wof:placetype":"locality"
},
  "geometry": {"coordinates":[42.93333,16.05],"type":"Point"}
}