{
  "type": "Feature",
  "properties": {
    "gn:country":"YE",
    "gn:fcode":"PPL",
    "gn:pop":8,
    "iso:country":"YE",
    "name:ara_x_preferred":[
        "\u0648\u0637\u0646 \u062e\u064a\u0631\u0627\u0646"
    ],
    "name:eng_x_preferred":[
        "Watan Khayran"
    ],
    "qs:name":"Wa\u0163an Khayr\u0101n",
    "qs:photos_9r":0,
    "qs:photos_sr":0,
    "qs:pop_sr":"1",
    "wof:name":"Wa\u0163an Khayr\u0101n",
    "wof:placetype":"locality",
    "wof:population":8
},
  "geometry": {"coordinates":[43.53572,16.80745],"type":"Point"}
}