{
  "type": "Feature",
  "properties": {
    "gn:admin1_code":"22.0",
    "gn:admin2_code":"1704.0",
    "gn:asciiname":"Az Zahar",
    "gn:country_code":"YE",
    "gn:dem":111,
    "gn:feature_class":"P",
    "gn:feature_code":"PPL",
    "gn:name":"Az\u0327 Z\u0327ah\u0101r",
    "gn:population":0,
    "gn:timezone":"Asia/Aden",
    "iso:country":"YE",
    "name:und_x_variant":[
        "Az\u0327 Z\u0327ah\u0101r"
    ],
    "wof:name":"Az Zahar",
    "wof:placetype":"locality"
},
  "geometry": {"coordinates":[43.11374,16.15259],"type":"Point"}
}