{
  "type": "Feature",
  "properties": {
    "gn:admin1_code":"16.0",
    "gn:admin2_code":"2303.0",
    "gn:asciiname":"Bayt Qal'am",
    "gn:country_code":"YE",
    "gn:dem":2348,
    "gn:feature_class":"P",
    "gn:feature_code":"PPL",
    "gn:name":"Bayt Qal\u2018am",
    "gn:population":0,
    "gn:timezone":"Asia/Aden",
    "iso:country":"YE",
    "name:ara_x_preferred":[
        "\u0628\u064a\u062a \u0642\u0644\u0639\u0645"
    ],
    "name:und_x_variant":[
        "Bayt Qal\u2018am"
    ],
    "wof:name":"Bayt Qal'am",
    "wof:placetype":"locality"
},
  "geometry": {"coordinates":[44.54273,15.6238],"type":"Point"}
}