{
  "type": "Feature",
  "properties": {
    "gn:admin1_code":"20.0",
    "gn:asciiname":"Ad Dur",
    "gn:country_code":"YE",
    "gn:dem":2542,
    "gn:feature_class":"P",
    "gn:feature_code":"PPL",
    "gn:name":"Ad D\u016br",
    "gn:population":0,
    "gn:timezone":"Asia/Aden",
    "iso:country":"YE",
    "name:ara_x_preferred":[
        "\u0627\u0644\u062f\u0648\u0631"
    ],
    "name:ell_x_preferred":[
        "\u0391\u03bd\u03c4 \u039d\u03c4\u03bf\u03c5\u03c1"
    ],
    "name:fas_x_preferred":[
        "\u0627\u0644\u062f\u0648\u0631"
    ],
    "name:ind_x_preferred":[
        "Ad Dur"
    ],
    "name:nno_x_preferred":[
        "Ad Dur"
    ],
    "name:und_x_variant":[
        "Ad D\u016br"
    ],
    "wof:name":"Ad Dur",
    "wof:placetype":"locality"
},
  "geometry": {"coordinates":[44.46148,14.47652],"type":"Point"}
}