{
  "type": "Feature",
  "properties": {
    "gn:admin1_code":"22.0",
    "gn:admin2_code":"1725.0",
    "gn:asciiname":"Al Qal`ah Qat`at as Sarabi",
    "gn:country_code":"YE",
    "gn:dem":1503,
    "gn:feature_class":"P",
    "gn:feature_code":"PPL",
    "gn:name":"Al Qal\u2018ah Qa\u0163\u2018at a\u015f \u015ear\u0101b\u012b",
    "gn:population":0,
    "gn:timezone":"Asia/Aden",
    "iso:country":"YE",
    "name:und_x_variant":[
        "Al Qal\u2018ah Qa\u0163\u2018at a\u015f \u015ear\u0101b\u012b"
    ],
    "wof:name":"Al Qal`ah Qat`at as Sarabi",
    "wof:placetype":"locality"
},
  "geometry": {"coordinates":[43.56308,15.58135],"type":"Point"}
}