{
  "type": "Feature",
  "properties": {
    "gn:admin1_code":"23.0",
    "gn:admin2_code":"1101.0",
    "gn:asciiname":"Al Makdum",
    "gn:country_code":"YE",
    "gn:dem":1233,
    "gn:feature_class":"P",
    "gn:feature_code":"PPL",
    "gn:name":"Al Makd\u016bm",
    "gn:population":0,
    "gn:timezone":"Asia/Aden",
    "iso:country":"YE",
    "name:und_x_variant":[
        "Al Makd\u016bm"
    ],
    "wof:name":"Al Makdum",
    "wof:placetype":"locality"
},
  "geometry": {"coordinates":[43.95381,14.33135],"type":"Point"}
}