{
  "type": "Feature",
  "properties": {
    "gn:country":"YE",
    "gn:fcode":"PPLX",
    "gn:pop":4,
    "iso:country":"YE",
    "name:ara_x_preferred":[
        "\u2018\u0100jir"
    ],
    "name:ara_x_variant":[
        "\u0639\u0627\u062c\u0631"
    ],
    "qs:name":"\u2018\u0100jir",
    "qs:photos_9r":0,
    "qs:photos_sr":0,
    "qs:pop_sr":"1",
    "wof:name":"\u2018\u0100jir",
    "wof:placetype":"neighbourhood",
    "wof:population":4
},
  "geometry": {"coordinates":[43.68579,16.15353],"type":"Point"}
}