{
  "type": "Feature",
  "properties": {
    "gn:country":"YE",
    "gn:fcode":"PPLX",
    "gn:pop":27,
    "iso:country":"YE",
    "name:ara_x_preferred":[
        "\u0627\u0644 \u062c\u0639\u0627\u0645\u0644"
    ],
    "qs:name":"\u0100l Ja\u2018\u0101mil",
    "qs:photos_9r":0,
    "qs:photos_sr":0,
    "qs:pop_sr":"1",
    "wof:name":"\u0100l Ja\u2018\u0101mil",
    "wof:placetype":"neighbourhood",
    "wof:population":27
},
  "geometry": {"coordinates":[43.81395,17.04029],"type":"Point"}
}