{
  "type": "Feature",
  "properties": {
    "gn:admin1_code":"19.0",
    "gn:admin2_code":"2905.0",
    "gn:asciiname":"Hajla",
    "gn:country_code":"YE",
    "gn:dem":1280,
    "gn:feature_class":"P",
    "gn:feature_code":"PPL",
    "gn:name":"\u1e28ajl\u0101",
    "gn:population":0,
    "gn:timezone":"Asia/Aden",
    "iso:country":"YE",
    "name:ara_x_preferred":[
        "\u062d\u062c\u0644\u0627"
    ],
    "name:bul_x_preferred":[
        "\u0425\u0430\u043b\u0430"
    ],
    "name:ceb_x_preferred":[
        "Hajla"
    ],
    "name:ces_x_preferred":[
        "Hajla"
    ],
    "name:deu_x_preferred":[
        "Hajla"
    ],
    "name:nld_x_preferred":[
        "Hajla"
    ],
    "name:nno_x_preferred":[
        "Hajla"
    ],
    "name:pol_x_preferred":[
        "Hajla"
    ],
    "name:sqi_x_preferred":[
        "Hajla"
    ],
    "name:srp_x_preferred":[
        "\u0425\u0430\u0458\u043b\u0430"
    ],
    "name:swe_x_preferred":[
        "Hajla"
    ],
    "name:und_x_variant":[
        "\u1e28ajl\u0101"
    ],
    "wof:name":"Hajla",
    "wof:placetype":"locality"
},
  "geometry": {"coordinates":[43.75001,16.20385],"type":"Point"}
}