{
  "type": "Feature",
  "properties": {
    "gn:admin1_code":"18.0",
    "gn:admin2_code":"3005.0",
    "gn:asciiname":"`Arshi",
    "gn:country_code":"YE",
    "gn:dem":2019,
    "gn:feature_class":"P",
    "gn:feature_code":"PPL",
    "gn:name":"\u2018Arsh\u012b",
    "gn:population":0,
    "gn:timezone":"Asia/Aden",
    "iso:country":"YE",
    "name:ara_x_preferred":[
        "\u2018Arsh\u012b"
    ],
    "name:und_x_variant":[
        "\u2018Ursh\u012b"
    ],
    "wof:name":"`Arshi",
    "wof:placetype":"locality"
},
  "geometry": {"coordinates":[44.88333,13.76667],"type":"Point"}
}