{
  "type": "Feature",
  "properties": {
    "gn:admin1_code":"18.0",
    "gn:admin2_code":"3006.0",
    "gn:asciiname":"Habil as Salamah",
    "gn:country_code":"YE",
    "gn:dem":1291,
    "gn:feature_class":"P",
    "gn:feature_code":"PPL",
    "gn:name":"\u1e28ab\u012bl as Sal\u0101mah",
    "gn:population":0,
    "gn:timezone":"Asia/Aden",
    "iso:country":"YE",
    "name:und_x_variant":[
        "Habil-as-Salami",
        "\u1e28ab\u012bl as Sal\u0101mah"
    ],
    "wof:name":"Habil as Salamah",
    "wof:placetype":"locality"
},
  "geometry": {"coordinates":[44.71021,13.83232],"type":"Point"}
}