{
  "type": "Feature",
  "properties": {
    "gn:admin1_code":"5.0",
    "gn:admin2_code":"2108.0",
    "gn:asciiname":"An Naqqaq",
    "gn:country_code":"YE",
    "gn:dem":1205,
    "gn:elevation":"2.0",
    "gn:feature_class":"P",
    "gn:feature_code":"PPL",
    "gn:name":"An Naqq\u0101q",
    "gn:population":0,
    "gn:timezone":"Asia/Aden",
    "iso:country":"YE",
    "name:ara_x_preferred":[
        "An Nuq\u0101q"
    ],
    "name:und_x_variant":[
        "Umm Nuq\u0101q",
        "Am-Nuqaq",
        "Nuq\u0101q",
        "An Naqq\u0101q"
    ],
    "wof:name":"An Naqqaq",
    "wof:placetype":"locality"
},
  "geometry": {"coordinates":[45.99897,14.52039],"type":"Point"}
}