{
  "type": "Feature",
  "properties": {
    "gn:admin1_code":"16.0",
    "gn:admin2_code":"2314.0",
    "gn:asciiname":"Al Qahir",
    "gn:country_code":"YE",
    "gn:dem":2093,
    "gn:feature_class":"P",
    "gn:feature_code":"PPL",
    "gn:name":"Al Q\u0101hir",
    "gn:population":0,
    "gn:timezone":"Asia/Aden",
    "iso:country":"YE",
    "name:ara_x_preferred":[
        "Al Q\u0101hir"
    ],
    "wof:name":"Al Qahir",
    "wof:placetype":"locality"
},
  "geometry": {"coordinates":[44.84813,15.10095],"type":"Point"}
}