{
  "type": "Feature",
  "properties": {
    "gn:admin1_code":"22.0",
    "gn:admin2_code":"1710.0",
    "gn:asciiname":"Al Marjalah",
    "gn:country_code":"YE",
    "gn:dem":704,
    "gn:feature_class":"P",
    "gn:feature_code":"PPL",
    "gn:name":"Al Marjalah",
    "gn:population":0,
    "gn:timezone":"Asia/Aden",
    "iso:country":"YE",
    "name:ara_x_preferred":[
        "\u0627\u0644\u0645\u0631\u062c\u0644\u0629"
    ],
    "wof:name":"Al Marjalah",
    "wof:placetype":"locality"
},
  "geometry": {"coordinates":[43.39419,16.02617],"type":"Point"}
}