{
  "type": "Feature",
  "properties": {
    "gn:country":"YE",
    "gn:fcode":"PPL",
    "gn:population":2,
    "iso:country":"YE",
    "name:ara_x_preferred":[
        "Al Mishb\u0101b"
    ],
    "name:ara_x_variant":[
        "\u0627\u0644\u0645\u0634\u0628\u0627\u0628"
    ],
    "qs:name":"Al Mishb\u0101b",
    "qs:photos_9r":0,
    "qs:photos_sr":0,
    "qs:pop_sr":"1",
    "wof:name":"Al Mishb\u0101b",
    "wof:placetype":"locality",
    "wof:population":2
},
  "geometry": {"coordinates":[43.32637,16.64315],"type":"Point"}
}