{
  "type": "Feature",
  "properties": {
    "gn:admin1_code":"8.0",
    "gn:admin2_code":"1801.0",
    "gn:asciiname":"As Saqayif",
    "gn:country_code":"YE",
    "gn:dem":46,
    "gn:feature_class":"P",
    "gn:feature_code":"PPL",
    "gn:name":"As Saq\u0101yif",
    "gn:population":0,
    "gn:timezone":"Asia/Aden",
    "iso:country":"YE",
    "name:ara_x_preferred":[
        "\u0627\u0644\u0633\u0642\u0627\u064a\u0641"
    ],
    "name:und_x_variant":[
        "As Saq\u0101\u2019if",
        "As Saq\u0101yif"
    ],
    "wof:name":"As Saqayif",
    "wof:placetype":"locality"
},
  "geometry": {"coordinates":[42.93975,15.75188],"type":"Point"}
}