{
  "type": "Feature",
  "properties": {
    "gn:admin1_code":"21.0",
    "gn:admin2_code":"1603.0",
    "gn:asciiname":"As Safiyah",
    "gn:country_code":"YE",
    "gn:dem":1270,
    "gn:feature_class":"P",
    "gn:feature_code":"PPL",
    "gn:name":"A\u015f S\u0101fiyah",
    "gn:population":0,
    "gn:timezone":"Asia/Aden",
    "iso:country":"YE",
    "name:ara_x_preferred":[
        "\u0627\u0644\u0635\u0627\u0641\u064a\u0629"
    ],
    "name:und_x_variant":[
        "A\u015f S\u0101fiyah"
    ],
    "wof:name":"As Safiyah",
    "wof:placetype":"locality"
},
  "geometry": {"coordinates":[44.40565,16.08621],"type":"Point"}
}