{
  "type": "Feature",
  "properties": {
    "gn:admin1_code":"22.0",
    "gn:admin2_code":"1725.0",
    "gn:asciiname":"Bayt Mahmud",
    "gn:country_code":"YE",
    "gn:dem":1167,
    "gn:feature_class":"P",
    "gn:feature_code":"PPL",
    "gn:name":"Bayt Ma\u1e29m\u016bd",
    "gn:population":0,
    "gn:timezone":"Asia/Aden",
    "iso:country":"YE",
    "name:ara_x_preferred":[
        "\u0628\u064a\u062a \u0645\u062d\u0645\u0648\u062f"
    ],
    "name:und_x_variant":[
        "Bayt Ma\u1e29m\u016bd"
    ],
    "wof:name":"Bayt Mahmud",
    "wof:placetype":"locality"
},
  "geometry": {"coordinates":[43.5616,15.59228],"type":"Point"}
}