{
  "type": "Feature",
  "properties": {
    "gn:admin1_code":"16.0",
    "gn:admin2_code":"2315.0",
    "gn:asciiname":"Al Hanakah as Sufla",
    "gn:country_code":"YE",
    "gn:dem":2489,
    "gn:feature_class":"P",
    "gn:feature_code":"PPL",
    "gn:name":"Al \u1e28anakah as Sufl\u00e1",
    "gn:population":0,
    "gn:timezone":"Asia/Aden",
    "iso:country":"YE",
    "name:und_x_variant":[
        "Al \u1e28anakah as Sufl\u00e1"
    ],
    "wof:name":"Al Hanakah as Sufla",
    "wof:placetype":"locality"
},
  "geometry": {"coordinates":[44.44728,14.9536],"type":"Point"}
}