{
  "type": "Feature",
  "properties": {
    "gn:admin1_code":"15.0",
    "gn:admin2_code":"2207.0",
    "gn:asciiname":"Ar Radhah",
    "gn:country_code":"YE",
    "gn:dem":279,
    "gn:feature_class":"P",
    "gn:feature_code":"PPL",
    "gn:name":"Ar Rad\u1e29ah",
    "gn:population":0,
    "gn:timezone":"Asia/Aden",
    "iso:country":"YE",
    "name:ara_x_preferred":[
        "\u0627\u0644\u0631\u062f\u062d\u0629"
    ],
    "name:und_x_variant":[
        "Ar Rad\u1e29ah"
    ],
    "wof:name":"Ar Radhah",
    "wof:placetype":"locality"
},
  "geometry": {"coordinates":[43.22975,16.70611],"type":"Point"}
}