{
  "type": "Feature",
  "properties": {
    "gn:admin1_code":"8.0",
    "gn:admin2_code":"1805.0",
    "gn:asciiname":"Mahall Salim 'Aqil",
    "gn:country_code":"YE",
    "gn:dem":29,
    "gn:feature_class":"P",
    "gn:feature_code":"PPL",
    "gn:name":"Ma\u1e29all S\u0101lim \u2018Aq\u012bl",
    "gn:population":0,
    "gn:timezone":"Asia/Aden",
    "iso:country":"YE",
    "name:ara_x_preferred":[
        "\u0645\u062d\u0644 \u0633\u0627\u0644\u0645 \u0639\u0642\u064a\u0644"
    ],
    "name:und_x_variant":[
        "Ma\u1e29all S\u0101lim \u2018Aq\u012bl"
    ],
    "wof:name":"Mahall Salim 'Aqil",
    "wof:placetype":"locality"
},
  "geometry": {"coordinates":[42.90653,15.35188],"type":"Point"}
}