{
  "type": "Feature",
  "properties": {
    "gn:admin1_code":"15.0",
    "gn:admin2_code":"2210.0",
    "gn:asciiname":"Majz",
    "gn:country_code":"YE",
    "gn:dem":2494,
    "gn:feature_class":"P",
    "gn:feature_code":"PPL",
    "gn:name":"Majz",
    "gn:population":0,
    "gn:timezone":"Asia/Aden",
    "iso:country":"YE",
    "wof:name":"Majz",
    "wof:placetype":"locality"
},
  "geometry": {"coordinates":[43.46667,17.13332999999999],"type":"Point"}
}