{
  "type": "Feature",
  "properties": {
    "gn:admin1_code":"20.0",
    "gn:admin2_code":"1406.0",
    "gn:asciiname":"Dhi Na`im",
    "gn:country_code":"YE",
    "gn:dem":1956,
    "gn:feature_class":"P",
    "gn:feature_code":"PPLA2",
    "gn:name":"Dh\u012b N\u0101\u2018im",
    "gn:population":0,
    "gn:timezone":"Asia/Aden",
    "iso:country":"YE",
    "name:ara_x_preferred":[
        "Dh\u012b N\u0101\u2018im"
    ],
    "name:ara_x_variant":[
        "\u0630\u064a \u0646\u0627\u0639\u0645"
    ],
    "wof:name":"Dhi Na`im",
    "wof:placetype":"locality"
},
  "geometry": {"coordinates":[45.44807,14.10574],"type":"Point"}
}