{
  "type": "Feature",
  "properties": {
    "gn:admin1_code":"8.0",
    "gn:admin2_code":"1809.0",
    "gn:asciiname":"Al Majalil",
    "gn:country_code":"YE",
    "gn:dem":99,
    "gn:feature_class":"P",
    "gn:feature_code":"PPL",
    "gn:name":"Al Maj\u0101l\u012bl",
    "gn:population":0,
    "gn:timezone":"Asia/Aden",
    "iso:country":"YE",
    "name:ara_x_preferred":[
        "\u0627\u0644\u0645\u062c\u0627\u0644\u064a\u0644"
    ],
    "name:und_x_variant":[
        "Al Maj\u0101l\u012bl"
    ],
    "wof:name":"Al Majalil",
    "wof:placetype":"locality"
},
  "geometry": {"coordinates":[43.12349,15.2316],"type":"Point"}
}