{
  "type": "Feature",
  "properties": {
    "gn:admin1_code":"15.0",
    "gn:admin2_code":"2210.0",
    "gn:asciiname":"Al Qasr",
    "gn:country_code":"YE",
    "gn:dem":1891,
    "gn:feature_class":"P",
    "gn:feature_code":"PPL",
    "gn:name":"Al Qa\u015fr",
    "gn:population":0,
    "gn:timezone":"Asia/Aden",
    "iso:country":"YE",
    "name:ara_x_preferred":[
        "\u0627\u0644\u0642\u0635\u0631"
    ],
    "name:und_x_variant":[
        "Al Qa\u015fr"
    ],
    "wof:name":"Al Qasr",
    "wof:placetype":"locality"
},
  "geometry": {"coordinates":[43.40558,17.02108],"type":"Point"}
}