{
  "type": "Feature",
  "properties": {
    "gn:country":"YE",
    "gn:fcode":"PPL",
    "gn:population":10,
    "iso:country":"YE",
    "name:ara_x_preferred":[
        "\u0627\u0644\u062c\u064a\u0628\u0629"
    ],
    "qs:name":"Al Jab\u012byah",
    "qs:photos_9r":0,
    "qs:photos_sr":0,
    "qs:pop_sr":"1",
    "wof:name":"Al Jab\u012byah",
    "wof:placetype":"locality",
    "wof:population":10
},
  "geometry": {"coordinates":[43.20368,17.1082],"type":"Point"}
}