{
  "type": "Feature",
  "properties": {
    "gn:country":"YE",
    "gn:fcode":"PPL",
    "gn:pop":6,
    "iso:country":"YE",
    "name:ara_x_preferred":[
        "\u0627\u0644\u0628\u0648\u0631\u062d\u0629"
    ],
    "name:eng_x_preferred":[
        "Al BUrhah"
    ],
    "name:eng_x_variant":[
        "\u1e28alaq\u012bn"
    ],
    "qs:name":"Al B\u016br\u1e29ah",
    "qs:photos_9r":0,
    "qs:photos_sr":0,
    "qs:pop_sr":"1",
    "wof:name":"Al B\u016br\u1e29ah",
    "wof:placetype":"locality",
    "wof:population":6
},
  "geometry": {"coordinates":[43.80868,13.46218],"type":"Point"}
}