{
  "type": "Feature",
  "properties": {
    "gn:admin1_code":"25.0",
    "gn:admin2_code":"1515.0",
    "gn:asciiname":"Al Maqalihah",
    "gn:country_code":"YE",
    "gn:dem":2107,
    "gn:feature_class":"P",
    "gn:feature_code":"PPL",
    "gn:name":"Al Maq\u0101li\u1e29ah",
    "gn:population":0,
    "gn:timezone":"Asia/Aden",
    "iso:country":"YE",
    "name:ara_x_preferred":[
        "\u0627\u0644\u0645\u0642\u0627\u0644\u062d\u0629"
    ],
    "name:und_x_variant":[
        "Al Maq\u0101li\u1e29ah"
    ],
    "wof:name":"Al Maqalihah",
    "wof:placetype":"locality"
},
  "geometry": {"coordinates":[44.16904,13.20614],"type":"Point"}
}