{
  "type": "Feature",
  "properties": {
    "gn:country":"YE",
    "gn:fcode":"PPL",
    "gn:pop":1,
    "iso:country":"YE",
    "name:ara_x_preferred":[
        "\u062b\u0628\u064a\u0646"
    ],
    "name:eng_x_preferred":[
        "Thubayn"
    ],
    "name:eng_x_variant":[
        "Al \u1e28\u0101fah"
    ],
    "qs:name":"Thubayn",
    "qs:photos_9r":0,
    "qs:photos_sr":0,
    "qs:pop_sr":"1",
    "wof:name":"Thubayn",
    "wof:placetype":"locality",
    "wof:population":1
},
  "geometry": {"coordinates":[45.39362,14.83842],"type":"Point"}
}