{
  "type": "Feature",
  "properties": {
    "gn:admin1_code":"22.0",
    "gn:admin2_code":"1722.0",
    "gn:asciiname":"`Ayyid",
    "gn:country_code":"YE",
    "gn:dem":484,
    "gn:feature_class":"P",
    "gn:feature_code":"PPL",
    "gn:name":"\u2018Ayyid",
    "gn:population":0,
    "gn:timezone":"Asia/Aden",
    "iso:country":"YE",
    "name:ara_x_preferred":[
        "\u2018Ayyid"
    ],
    "wof:name":"`Ayyid",
    "wof:placetype":"locality"
},
  "geometry": {"coordinates":[43.3226,15.75256],"type":"Point"}
}