{
  "type": "Feature",
  "properties": {
    "gn:admin1_code":"24.0",
    "gn:admin2_code":"2513.0",
    "gn:asciiname":"Al `Ashush",
    "gn:country_code":"YE",
    "gn:dem":427,
    "gn:feature_class":"P",
    "gn:feature_code":"PPL",
    "gn:name":"Al \u2018Ash\u016bsh",
    "gn:population":0,
    "gn:timezone":"Asia/Aden",
    "iso:country":"YE",
    "name:ara_x_preferred":[
        "Al \u2018Ash\u016bsh"
    ],
    "wof:name":"Al `Ashush",
    "wof:placetype":"locality"
},
  "geometry": {"coordinates":[43.87513,12.96638],"type":"Point"}
}