{
  "type": "Feature",
  "properties": {
    "gn:admin1_code":"25.0",
    "gn:admin2_code":"1515.0",
    "gn:asciiname":"Al Mu'aynah",
    "gn:country_code":"YE",
    "gn:dem":1933,
    "gn:feature_class":"P",
    "gn:feature_code":"PPL",
    "gn:name":"Al Mu\u2018aynah",
    "gn:population":0,
    "gn:timezone":"Asia/Aden",
    "iso:country":"YE",
    "name:ara_x_preferred":[
        "\u0627\u0644\u0645\u0639\u064a\u0646\u0629"
    ],
    "name:und_x_variant":[
        "Al Mu\u2018aynah"
    ],
    "wof:name":"Al Mu'aynah",
    "wof:placetype":"locality"
},
  "geometry": {"coordinates":[44.13475,13.23322],"type":"Point"}
}