{
  "type": "Feature",
  "properties": {
    "gn:admin1_code":"22.0",
    "gn:admin2_code":"1731.0",
    "gn:asciiname":"Qaryat ar Ra's",
    "gn:country_code":"YE",
    "gn:dem":1712,
    "gn:feature_class":"P",
    "gn:feature_code":"PPL",
    "gn:name":"Qaryat ar Ra\u2019s",
    "gn:population":0,
    "gn:timezone":"Asia/Aden",
    "iso:country":"YE",
    "name:ara_x_preferred":[
        "\u0642\u0631\u064a\u0629 \u0627\u0644\u0631\u0623\u0633"
    ],
    "name:und_x_variant":[
        "Qaryat ar Ra\u2019s"
    ],
    "wof:name":"Qaryat ar Ra's",
    "wof:placetype":"locality"
},
  "geometry": {"coordinates":[43.43968,16.33274],"type":"Point"}
}