{
  "type": "Feature",
  "properties": {
    "gn:country":"YE",
    "gn:fcode":"PPL",
    "gn:population":13,
    "iso:country":"YE",
    "name:ara_x_preferred":[
        "\u0627\u0644\u062d\u0636\u0648\u064a"
    ],
    "name:eng_x_preferred":[
        "Al Hauawi"
    ],
    "name:eng_x_variant":[
        "Ban\u012b \u2018Aq\u012bl"
    ],
    "qs_pg:aaroncc":"YE",
    "qs_pg:gn_country":"YE",
    "qs_pg:gn_fcode":"PPL",
    "qs_pg:gn_pop":13,
    "qs_pg:name":"Al \u1e28a\u1e11aw\u012b",
    "qs_pg:photos_9r":0,
    "qs_pg:photos_sr":0,
    "qs_pg:pop_sr":1,
    "qs_pg:qs_pg_placetype":"locality",
    "wof:name":"Al \u1e28a\u1e11aw\u012b",
    "wof:placetype":"locality",
    "wof:population":13
},
  "geometry": {"coordinates":[45.30352,14.55927],"type":"Point"}
}