{
  "type": "Feature",
  "properties": {
    "gn:admin1_code":"19.0",
    "gn:admin2_code":"2920.0",
    "gn:asciiname":"Bayt Ja'shan",
    "gn:country_code":"YE",
    "gn:dem":2222,
    "gn:feature_class":"P",
    "gn:feature_code":"PPL",
    "gn:name":"Bayt Ja\u2018sh\u0101n",
    "gn:population":0,
    "gn:timezone":"Asia/Aden",
    "iso:country":"YE",
    "name:ara_x_preferred":[
        "\u0628\u064a\u062a \u062c\u0639\u0634\u0627\u0646"
    ],
    "name:und_x_variant":[
        "Bayt Ja\u2018sh\u0101n"
    ],
    "wof:name":"Bayt Ja'shan",
    "wof:placetype":"locality"
},
  "geometry": {"coordinates":[43.97344,16.16684],"type":"Point"}
}