{
  "type": "Feature",
  "properties": {
    "gn:admin1_code":"16.0",
    "gn:admin2_code":"2302.0",
    "gn:asciiname":"Bayt Jawdar",
    "gn:country_code":"YE",
    "gn:dem":2445,
    "gn:feature_class":"P",
    "gn:feature_code":"PPL",
    "gn:name":"Bayt Jawdar",
    "gn:population":0,
    "gn:timezone":"Asia/Aden",
    "iso:country":"YE",
    "name:ara_x_preferred":[
        "\u0628\u064a\u062a \u062c\u0648\u062f\u0631"
    ],
    "wof:name":"Bayt Jawdar",
    "wof:placetype":"locality"
},
  "geometry": {"coordinates":[44.20861,15.69058],"type":"Point"}
}