{
  "type": "Feature",
  "properties": {
    "gn:admin1_code":"11.0",
    "gn:admin2_code":"2005.0",
    "gn:asciiname":"Al Markaz",
    "gn:country_code":"YE",
    "gn:dem":1837,
    "gn:feature_class":"P",
    "gn:feature_code":"PPL",
    "gn:name":"Al Markaz",
    "gn:population":0,
    "gn:timezone":"Asia/Aden",
    "iso:country":"YE",
    "wof:name":"Al Markaz",
    "wof:placetype":"locality"
},
  "geometry": {"coordinates":[43.9061,14.41945],"type":"Point"}
}