{
  "type": "Feature",
  "properties": {
    "gn:admin1_code":"16.0",
    "gn:admin2_code":"2312.0",
    "gn:asciiname":"Al Haddadah",
    "gn:country_code":"YE",
    "gn:dem":2106,
    "gn:feature_class":"P",
    "gn:feature_code":"PPL",
    "gn:name":"Al \u1e28add\u0101dah",
    "gn:population":0,
    "gn:timezone":"Asia/Aden",
    "iso:country":"YE",
    "name:ara_x_preferred":[
        "\u0627\u0644\u062d\u062f\u0627\u062f\u0629"
    ],
    "name:und_x_variant":[
        "Al \u1e28add\u0101dah"
    ],
    "wof:name":"Al Haddadah",
    "wof:placetype":"locality"
},
  "geometry": {"coordinates":[44.72828,15.28911],"type":"Point"}
}