{
  "type": "Feature",
  "properties": {
    "gn:admin1_code":"22.0",
    "gn:admin2_code":"1724.0",
    "gn:asciiname":"Mahall al `Ara'is",
    "gn:country_code":"YE",
    "gn:dem":376,
    "gn:feature_class":"P",
    "gn:feature_code":"PPL",
    "gn:name":"Ma\u1e29all al \u2018Ar\u0101\u2019is",
    "gn:population":0,
    "gn:timezone":"Asia/Aden",
    "iso:country":"YE",
    "name:und_x_variant":[
        "Ma\u1e29all al \u2018Ar\u0101\u2019is"
    ],
    "wof:name":"Mahall al `Ara'is",
    "wof:placetype":"locality"
},
  "geometry": {"coordinates":[43.39039,15.58057],"type":"Point"}
}