{
  "type": "Feature",
  "properties": {
    "gn:country":"YE",
    "gn:fcode":"PPL",
    "gn:pop":17,
    "iso:country":"YE",
    "name:ara_x_preferred":[
        "\u0637\u0648\u0631 \u0628\u0635\u064a\u0631"
    ],
    "name:eng_x_preferred":[
        "Tawr Basir"
    ],
    "name:eng_x_variant":[
        "Al Kurayf"
    ],
    "qs:name":"\u0162awr Ba\u015f\u012br",
    "qs:photos_9r":0,
    "qs:photos_sr":0,
    "qs:pop_sr":"1",
    "wof:name":"\u0162awr Ba\u015f\u012br",
    "wof:placetype":"locality",
    "wof:population":17
},
  "geometry": {"coordinates":[43.80009,13.16621],"type":"Point"}
}