{
  "type": "Feature",
  "properties": {
    "gn:admin1_code":"19.0",
    "gn:admin2_code":"2904.0",
    "gn:asciiname":"As Safi'",
    "gn:country_code":"YE",
    "gn:dem":1179,
    "gn:feature_class":"P",
    "gn:feature_code":"PPL",
    "gn:name":"A\u015f \u015e\u0101fi\u2018",
    "gn:population":0,
    "gn:timezone":"Asia/Aden",
    "iso:country":"YE",
    "name:ara_x_preferred":[
        "A\u015f \u015e\u0101fi\u2018"
    ],
    "name:ara_x_variant":[
        "\u0627\u0644\u0635\u0627\u0641\u0639"
    ],
    "wof:name":"As Safi'",
    "wof:placetype":"locality"
},
  "geometry": {"coordinates":[43.78901,16.18634],"type":"Point"}
}