{
  "type": "Feature",
  "properties": {
    "gn:admin1_code":"10.0",
    "gn:admin2_code":"2709.0",
    "gn:asciiname":"Al Manif",
    "gn:country_code":"YE",
    "gn:dem":1400,
    "gn:feature_class":"P",
    "gn:feature_code":"PPL",
    "gn:name":"Al Man\u012bf",
    "gn:population":0,
    "gn:timezone":"Asia/Aden",
    "iso:country":"YE",
    "name:und_x_variant":[
        "Al Man\u012bf"
    ],
    "wof:name":"Al Manif",
    "wof:placetype":"locality"
},
  "geometry": {"coordinates":[43.48084,15.46613],"type":"Point"}
}