{
  "type": "Feature",
  "properties": {
    "gn:admin1_code":"20.0",
    "gn:admin2_code":"1411.0",
    "gn:asciiname":"Nafasan",
    "gn:country_code":"YE",
    "gn:dem":1968,
    "gn:feature_class":"P",
    "gn:feature_code":"PPL",
    "gn:name":"Nafas\u0101n",
    "gn:population":0,
    "gn:timezone":"Asia/Aden",
    "iso:country":"YE",
    "name:und_x_variant":[
        "Nafas\u0101n"
    ],
    "wof:name":"Nafasan",
    "wof:placetype":"locality"
},
  "geometry": {"coordinates":[45.22395,14.32439],"type":"Point"}
}