{
  "type": "Feature",
  "properties": {
    "gn:country":"YE",
    "gn:fcode":"PPL",
    "gn:pop":4,
    "iso:country":"YE",
    "name:ara_x_preferred":[
        "Al \u2018Ariq"
    ],
    "name:ara_x_variant":[
        "\u0627\u0644\u0639\u0631\u0642"
    ],
    "qs:name":"Al \u2018Ariq",
    "qs:photos_9r":0,
    "qs:photos_sr":0,
    "qs:pop_sr":"1",
    "wof:name":"Al \u2018Ariq",
    "wof:placetype":"locality",
    "wof:population":4
},
  "geometry": {"coordinates":[43.28011,16.04184],"type":"Point"}
}