{
  "type": "Feature",
  "properties": {
    "gn:admin1_code":"25.0",
    "gn:admin2_code":"1513.0",
    "gn:asciiname":"Shi`b an Nakhlah",
    "gn:country_code":"YE",
    "gn:dem":1149,
    "gn:feature_class":"P",
    "gn:feature_code":"PPL",
    "gn:name":"Shi\u2018b an Nakhlah",
    "gn:population":0,
    "gn:timezone":"Asia/Aden",
    "iso:country":"YE",
    "name:und_x_variant":[
        "Shi\u2018b an Nakhlah"
    ],
    "wof:name":"Shi`b an Nakhlah",
    "wof:placetype":"locality"
},
  "geometry": {"coordinates":[44.20251,13.5254],"type":"Point"}
}