{
  "type": "Feature",
  "properties": {
    "gn:country":"YE",
    "gn:fcode":"PPL",
    "gn:pop":5,
    "iso:country":"YE",
    "name:ara_x_preferred":[
        "\u0627\u0644\u0645\u0639\u0631\u0627\u0636\u0629"
    ],
    "name:eng_x_preferred":[
        "Al Mi'rauah"
    ],
    "name:eng_x_variant":[
        "\u0100l Ma\u1e29f\u016bz\u0327"
    ],
    "qs:name":"Al Mi\u2018r\u0101\u1e11ah",
    "qs:photos_9r":0,
    "qs:photos_sr":0,
    "qs:pop_sr":"1",
    "wof:name":"Al Mi\u2018r\u0101\u1e11ah",
    "wof:placetype":"locality",
    "wof:population":5
},
  "geometry": {"coordinates":[43.73106,16.0299],"type":"Point"}
}