{
  "type": "Feature",
  "properties": {
    "gn:country":"YE",
    "gn:fcode":"PPLF",
    "gn:population":10,
    "iso:country":"YE",
    "name:ara_x_preferred":[
        "\u0645\u0635\u0644\u0628\u0648 \u0627\u0644\u0623\u0633\u0641\u0644"
    ],
    "name:eng_x_preferred":[
        "MaslibU Al Asfal"
    ],
    "name:eng_x_variant":[
        "Qih\u0101h"
    ],
    "qs:name":"Ma\u015flib\u016b al Asfal",
    "qs:photos_9r":0,
    "qs:photos_sr":0,
    "qs:pop_sr":"1",
    "wof:name":"Ma\u015flib\u016b al Asfal",
    "wof:placetype":"locality",
    "wof:population":10
},
  "geometry": {"coordinates":[43.43535,16.3851],"type":"Point"}
}