{
  "type": "Feature",
  "properties": {
    "gn:country":"YE",
    "gn:fcode":"PPL",
    "gn:pop":1,
    "iso:country":"YE",
    "name:ara_x_preferred":[
        "Al \u2018Irq"
    ],
    "name:ara_x_variant":[
        "\u0627\u0644\u0639\u0631\u0642"
    ],
    "name:eng_x_preferred":[
        "Al 'Irq"
    ],
    "name:eng_x_variant":[
        "At Taw\u0101m"
    ],
    "qs:name":"Al \u2018Irq",
    "qs:photos_9r":0,
    "qs:photos_sr":0,
    "qs:pop_sr":"1",
    "wof:name":"Al \u2018Irq",
    "wof:placetype":"locality",
    "wof:population":1
},
  "geometry": {"coordinates":[43.25014,17.16105],"type":"Point"}
}