{
  "type": "Feature",
  "properties": {
    "gn:country":"YE",
    "gn:fcode":"PPL",
    "gn:pop":19,
    "iso:country":"YE",
    "name:ara_x_preferred":[
        "\u0639\u062c\u0627\u062c\u0629"
    ],
    "name:eng_x_preferred":[
        "Ajajah"
    ],
    "name:eng_x_variant":[
        "Al Bu\u1e29ay\u1e29",
        "'Ajajah"
    ],
    "qs:name":"\u2018Aj\u0101jah",
    "qs:photos_9r":0,
    "qs:photos_sr":0,
    "qs:pop_sr":"1",
    "wof:name":"\u2018Aj\u0101jah",
    "wof:placetype":"locality",
    "wof:population":19
},
  "geometry": {"coordinates":[46.28826,16.65156],"type":"Point"}
}