{
  "type": "Feature",
  "properties": {
    "gn:admin1_code":"27.0",
    "gn:admin2_code":"3102.0",
    "gn:asciiname":"Al Mahadilah",
    "gn:country_code":"YE",
    "gn:dem":287,
    "gn:feature_class":"P",
    "gn:feature_code":"PPL",
    "gn:name":"Al Mah\u0101dilah",
    "gn:population":0,
    "gn:timezone":"Asia/Aden",
    "iso:country":"YE",
    "name:ara_x_preferred":[
        "\u0627\u0644\u0645\u0647\u0627\u062f\u0644\u0629"
    ],
    "name:und_x_variant":[
        "Al Mah\u0101dilah"
    ],
    "wof:name":"Al Mahadilah",
    "wof:placetype":"locality"
},
  "geometry": {"coordinates":[43.49723,14.62744],"type":"Point"}
}