{
  "type": "Feature",
  "properties": {
    "gn:admin1_code":"8.0",
    "gn:admin2_code":"1820.0",
    "gn:asciiname":"Bayt Furtut",
    "gn:country_code":"YE",
    "gn:dem":117,
    "gn:feature_class":"P",
    "gn:feature_code":"PPL",
    "gn:name":"Bayt Furt\u016bt",
    "gn:population":0,
    "gn:timezone":"Asia/Aden",
    "iso:country":"YE",
    "name:und_x_variant":[
        "Bayt Furt\u016bt"
    ],
    "wof:name":"Bayt Furtut",
    "wof:placetype":"locality"
},
  "geometry": {"coordinates":[43.37967,13.92894],"type":"Point"}
}