{
  "type": "Feature",
  "properties": {
    "gn:country":"YE",
    "gn:fcode":"PPL",
    "gn:population":7,
    "iso:country":"YE",
    "name:ara_x_preferred":[
        "\u0627\u0644\u0645\u0631\u064a\u0634"
    ],
    "name:eng_x_preferred":[
        "Al Muraysh"
    ],
    "name:eng_x_variant":[
        "D\u0101r al Man\u015f\u016brah"
    ],
    "qs_pg:aaroncc":"YE",
    "qs_pg:gn_country":"YE",
    "qs_pg:gn_fcode":"PPL",
    "qs_pg:gn_pop":7,
    "qs_pg:name":"Al Muraysh",
    "qs_pg:photos_9r":0,
    "qs_pg:photos_sr":0,
    "qs_pg:pop_sr":1,
    "qs_pg:qs_pg_placetype":"locality",
    "wof:name":"Al Muraysh",
    "wof:placetype":"locality",
    "wof:population":7
},
  "geometry": {"coordinates":[43.35188,16.99287],"type":"Point"}
}