{
  "type": "Feature",
  "properties": {
    "gn:country":"YE",
    "gn:fcode":"PPL",
    "gn:population":77,
    "iso:country":"YE",
    "name:ara_x_preferred":[
        "\u062d\u0635\u064a\u0628 \u0627\u0644\u0642\u0631\u064a\u0645\u0627\u0621"
    ],
    "name:eng_x_preferred":[
        "Husayb Al Qurayma"
    ],
    "name:eng_x_variant":[
        "Ar Ruwayn"
    ],
    "qs:name":"\u1e28usayb al Quraym\u0101\u2019",
    "qs:photos_9r":0,
    "qs:photos_sr":0,
    "qs:pop_sr":"1",
    "wof:name":"\u1e28usayb al Quraym\u0101\u2019",
    "wof:placetype":"locality",
    "wof:population":77
},
  "geometry": {"coordinates":[43.53548,13.26922],"type":"Point"}
}