{
  "type": "Feature",
  "properties": {
    "gn:admin1_code":"23.0",
    "gn:admin2_code":"1101.0",
    "gn:asciiname":"Ad Diyarah",
    "gn:country_code":"YE",
    "gn:dem":1224,
    "gn:feature_class":"P",
    "gn:feature_code":"PPL",
    "gn:name":"Ad Diy\u0101rah",
    "gn:population":0,
    "gn:timezone":"Asia/Aden",
    "iso:country":"YE",
    "name:ara_x_preferred":[
        "\u0627\u0644\u062f\u064a\u0627\u0631\u0629"
    ],
    "name:und_x_variant":[
        "Ad Diy\u0101rah"
    ],
    "wof:name":"Ad Diyarah",
    "wof:placetype":"locality"
},
  "geometry": {"coordinates":[44.01154,14.3483],"type":"Point"}
}