{
  "type": "Feature",
  "properties": {
    "gn:country":"YE",
    "gn:fcode":"PPL",
    "gn:population":17,
    "iso:country":"YE",
    "name:ara_x_preferred":[
        "\u0100l Sumn\u0101n"
    ],
    "name:ara_x_variant":[
        "\u0627\u0644 \u0633\u0645\u0646\u0627\u0646"
    ],
    "name:eng_x_preferred":[
        "Al Sumnan"
    ],
    "name:eng_x_variant":[
        "Bayt Madhk\u016br"
    ],
    "qs:name":"\u0100l Sumn\u0101n",
    "qs:photos_9r":0,
    "qs:photos_sr":0,
    "qs:pop_sr":"1",
    "wof:name":"\u0100l Sumn\u0101n",
    "wof:placetype":"locality",
    "wof:population":17
},
  "geometry": {"coordinates":[44.83599,16.07248],"type":"Point"}
}