{
  "type": "Feature",
  "properties": {
    "gn:admin1_code":"22.0",
    "gn:admin2_code":"1707.0",
    "gn:asciiname":"Al Qitrah",
    "gn:country_code":"YE",
    "gn:dem":949,
    "gn:feature_class":"P",
    "gn:feature_code":"PPL",
    "gn:name":"Al Qitrah",
    "gn:population":0,
    "gn:timezone":"Asia/Aden",
    "iso:country":"YE",
    "name:ara_x_preferred":[
        "\u0627\u0644\u0642\u062a\u0631\u0629"
    ],
    "wof:name":"Al Qitrah",
    "wof:placetype":"locality"
},
  "geometry": {"coordinates":[43.43883,16.26016],"type":"Point"}
}