{
  "type": "Feature",
  "properties": {
    "gn:admin1_code":"14.0",
    "gn:admin2_code":"2609.0",
    "gn:asciiname":"Jiba'",
    "gn:country_code":"YE",
    "gn:dem":1212,
    "gn:feature_class":"P",
    "gn:feature_code":"PPL",
    "gn:name":"Jib\u0101\u2019",
    "gn:population":0,
    "gn:timezone":"Asia/Aden",
    "iso:country":"YE",
    "name:ara_x_preferred":[
        "Jib\u0101\u2019"
    ],
    "name:ara_x_variant":[
        "\u062c\u0628\u0627\u0621"
    ],
    "wof:name":"Jiba'",
    "wof:placetype":"locality"
},
  "geometry": {"coordinates":[45.43043,14.89144],"type":"Point"}
}