{
  "type": "Feature",
  "properties": {
    "gn:admin1_code":"23.0",
    "gn:admin2_code":"1111.0",
    "gn:asciiname":"`Adan Nuran",
    "gn:country_code":"YE",
    "gn:dem":1642,
    "gn:feature_class":"P",
    "gn:feature_code":"PPL",
    "gn:name":"\u2018Adan N\u016br\u0101n",
    "gn:population":0,
    "gn:timezone":"Asia/Aden",
    "iso:country":"YE",
    "name:und_x_variant":[
        "\u2018Adan N\u016br\u0101n"
    ],
    "wof:name":"`Adan Nuran",
    "wof:placetype":"locality"
},
  "geometry": {"coordinates":[43.95233,13.90875],"type":"Point"}
}