{
  "type": "Feature",
  "properties": {
    "gn:admin1_code":"25.0",
    "gn:admin2_code":"1505.0",
    "gn:asciiname":"Al Maghaynarib",
    "gn:country_code":"YE",
    "gn:dem":591,
    "gn:feature_class":"P",
    "gn:feature_code":"PPL",
    "gn:name":"Al Maghayn\u0101rib",
    "gn:population":0,
    "gn:timezone":"Asia/Aden",
    "iso:country":"YE",
    "name:und_x_variant":[
        "Al Maghayn\u0101rib"
    ],
    "wof:name":"Al Maghaynarib",
    "wof:placetype":"locality"
},
  "geometry": {"coordinates":[43.67227000000001,13.54411],"type":"Point"}
}