{
  "type": "Feature",
  "properties": {
    "gn:country":"YE",
    "gn:fcode":"PPLL",
    "gn:population":8,
    "iso:country":"YE",
    "name:ara_x_preferred":[
        "\u0642\u0644\u0639\u0629 \u0642\u0645\u0631\u064a"
    ],
    "name:eng_x_preferred":[
        "Qila'at Qamri"
    ],
    "name:eng_x_variant":[
        "Bi\u2019r Fara\u1e29"
    ],
    "name:und_x_variant":[
        "Qal\u2018at Qamar\u012b"
    ],
    "qs:name":"Qila\u2018at Qamr\u012b",
    "qs:photos_9r":0,
    "qs:photos_sr":0,
    "qs:pop_sr":"1",
    "wof:name":"Qila\u2018at Qamr\u012b",
    "wof:placetype":"locality",
    "wof:population":8
},
  "geometry": {"coordinates":[43.35795,16.19873],"type":"Point"}
}