{
  "type": "Feature",
  "properties": {
    "gn:country":"YE",
    "gn:fcode":"PPLX",
    "gn:population":18,
    "iso:country":"YE",
    "name:ara_x_preferred":[
        "\u0630\u0648 \u0634\u064a\u0628\u0629"
    ],
    "qs:name":"Dh\u016b Sh\u012bbah",
    "qs:photos_9r":0,
    "qs:photos_sr":0,
    "qs:pop_sr":"1",
    "wof:name":"Dh\u016b Sh\u012bbah",
    "wof:placetype":"neighbourhood",
    "wof:population":18
},
  "geometry": {"coordinates":[43.89928,16.57351],"type":"Point"}
}