{
  "type": "Feature",
  "properties": {
    "gn:admin1_code":"19.0",
    "gn:admin2_code":"2916.0",
    "gn:asciiname":"Ar Rumayh",
    "gn:country_code":"YE",
    "gn:dem":2903,
    "gn:feature_class":"P",
    "gn:feature_code":"PPL",
    "gn:name":"Ar Rumay\u1e29",
    "gn:population":0,
    "gn:timezone":"Asia/Aden",
    "iso:country":"YE",
    "name:und_x_variant":[
        "Ar Rumay\u1e29"
    ],
    "wof:name":"Ar Rumayh",
    "wof:placetype":"locality"
},
  "geometry": {"coordinates":[43.69554,15.60345],"type":"Point"}
}