{
  "type": "Feature",
  "properties": {
    "gn:admin1_code":"23.0",
    "gn:admin2_code":"1117.0",
    "gn:asciiname":"Al Ahqaq",
    "gn:country_code":"YE",
    "gn:dem":2017,
    "gn:feature_class":"P",
    "gn:feature_code":"PPL",
    "gn:name":"Al A\u1e29q\u0101q",
    "gn:population":0,
    "gn:timezone":"Asia/Aden",
    "iso:country":"YE",
    "name:ara_x_preferred":[
        "Al A\u1e29q\u0101q"
    ],
    "wof:name":"Al Ahqaq",
    "wof:placetype":"locality"
},
  "geometry": {"coordinates":[43.95807,13.87886],"type":"Point"}
}