{
  "type": "Feature",
  "properties": {
    "gn:admin1_code":"3.0",
    "gn:admin2_code":"2806.0",
    "gn:asciiname":"Akhl Burayqah",
    "gn:cc2":"YE",
    "gn:country_code":"YE",
    "gn:dem":210,
    "gn:feature_class":"P",
    "gn:feature_code":"PPL",
    "gn:name":"Akhl Burayqah",
    "gn:population":0,
    "gn:timezone":"Asia/Aden",
    "iso:country":"YE",
    "name:und_x_variant":[
        "Akhl Breigha",
        "Akhl Burayqah"
    ],
    "wof:name":"Akhl Burayqah",
    "wof:placetype":"locality"
},
  "geometry": {"coordinates":[50.92194,15.59083],"type":"Point"}
}