{
  "type": "Feature",
  "properties": {
    "gn:country":"YE",
    "gn:fcode":"PPL",
    "gn:population":3,
    "iso:country":"YE",
    "name:ara_x_preferred":[
        "\u0643\u0631\u0633\u0649 \u0627\u0644\u0646\u0648\u0628"
    ],
    "name:eng_x_preferred":[
        "Kursa An Nawab"
    ],
    "name:eng_x_variant":[
        "Al Qayyimah"
    ],
    "qs:name":"Kurs\u00e1 an Nawab",
    "qs:photos_9r":0,
    "qs:photos_sr":0,
    "qs:pop_sr":"1",
    "wof:name":"Kurs\u00e1 an Nawab",
    "wof:placetype":"locality",
    "wof:population":3
},
  "geometry": {"coordinates":[43.2858,16.53574],"type":"Point"}
}