{
  "type": "Feature",
  "properties": {
    "gn:country":"YE",
    "gn:fcode":"PPL",
    "gn:pop":3,
    "iso:country":"YE",
    "name:ara_x_preferred":[
        "\u0627\u0644\u062e\u0632\u064a\u0631\u0629"
    ],
    "name:eng_x_preferred":[
        "Al Khazirah"
    ],
    "name:unk_x_variant":[
        "\u0627\u0644\u062e\u0632\u064a\u0631\u0629"
    ],
    "qs:name":"Al Khaz\u012brah",
    "qs:photos_9r":0,
    "qs:photos_sr":0,
    "qs:pop_sr":"1",
    "wof:name":"Al Khaz\u012brah",
    "wof:placetype":"locality",
    "wof:population":3
},
  "geometry": {"coordinates":[43.25403,16.22399],"type":"Point"}
}