{
  "type": "Feature",
  "properties": {
    "gn:admin1_code":"5.0",
    "gn:admin2_code":"2110.0",
    "gn:asciiname":"Am Sharfa'",
    "gn:country_code":"YE",
    "gn:dem":1104,
    "gn:feature_class":"P",
    "gn:feature_code":"PPL",
    "gn:name":"Am Sharf\u0101\u2019",
    "gn:population":0,
    "gn:timezone":"Asia/Aden",
    "iso:country":"YE",
    "name:und_x_variant":[
        "Am Sharf\u0101\u2019",
        "Ash Sharf\u0101\u2019"
    ],
    "wof:name":"Am Sharfa'",
    "wof:placetype":"locality"
},
  "geometry": {"coordinates":[46.43652,14.49736],"type":"Point"}
}