{
  "type": "Feature",
  "properties": {
    "gn:country":"YE",
    "gn:fcode":"PPL",
    "gn:population":10,
    "iso:country":"YE",
    "name:ara_x_preferred":[
        "\u0627\u0644\u062f\u0631\u0628"
    ],
    "qs:name":"Ad Darb",
    "qs:photos_9r":0,
    "qs:photos_sr":0,
    "qs:pop_sr":"1",
    "wof:name":"Ad Darb",
    "wof:placetype":"locality",
    "wof:population":10
},
  "geometry": {"coordinates":[43.44309,16.14923],"type":"Point"}
}