{
  "type": "Feature",
  "properties": {
    "gn:admin1_code":"20.0",
    "gn:admin2_code":"1415.0",
    "gn:asciiname":"Laqah",
    "gn:country_code":"YE",
    "gn:dem":2111,
    "gn:feature_class":"P",
    "gn:feature_code":"PPL",
    "gn:name":"Laq\u0101\u1e29",
    "gn:population":0,
    "gn:timezone":"Asia/Aden",
    "iso:country":"YE",
    "name:ara_x_preferred":[
        "\u0644\u0642\u0627\u062d"
    ],
    "name:und_x_variant":[
        "Laq\u0101\u1e29"
    ],
    "wof:name":"Laqah",
    "wof:placetype":"locality"
},
  "geometry": {"coordinates":[44.83214,14.54],"type":"Point"}
}