{
  "type": "Feature",
  "properties": {
    "gn:admin1_code":"23.0",
    "gn:admin2_code":"1109.0",
    "gn:asciiname":"Al Madraj",
    "gn:country_code":"YE",
    "gn:dem":1224,
    "gn:feature_class":"P",
    "gn:feature_code":"PPL",
    "gn:name":"Al Madraj",
    "gn:population":0,
    "gn:timezone":"Asia/Aden",
    "iso:country":"YE",
    "name:ara_x_preferred":[
        "\u0627\u0644\u0645\u062f\u0631\u062c"
    ],
    "name:und_x_variant":[
        "Al Mudarraj",
        "Al Madraj"
    ],
    "wof:name":"Al Madraj",
    "wof:placetype":"locality"
},
  "geometry": {"coordinates":[43.98154,14.15153],"type":"Point"}
}