{
  "type": "Feature",
  "properties": {
    "gn:country":"YE",
    "gn:fcode":"PPL",
    "gn:population":1,
    "iso:country":"YE",
    "name:ara_x_preferred":[
        "\u0627\u0644\u0634\u0631\u0639"
    ],
    "qs:name":"Ash Shar\u2018",
    "qs:photos_9r":0,
    "qs:photos_sr":0,
    "qs:pop_sr":"1",
    "wof:name":"Ash Shar\u2018",
    "wof:placetype":"locality",
    "wof:population":1
},
  "geometry": {"coordinates":[43.721,16.17273],"type":"Point"}
}