{
  "type": "Feature",
  "properties": {
    "gn:country":"YE",
    "gn:fcode":"PPL",
    "gn:pop":8,
    "iso:country":"YE",
    "name:ara_x_preferred":[
        "\u0627\u0644\u0646\u064a\u0627\u0628\u0629"
    ],
    "name:eng_x_preferred":[
        "An Niyabah"
    ],
    "qs:name":"An Niy\u0101bah",
    "qs:photos_9r":0,
    "qs:photos_sr":0,
    "qs:pop_sr":"1",
    "wof:name":"An Niy\u0101bah",
    "wof:placetype":"locality",
    "wof:population":8
},
  "geometry": {"coordinates":[43.37235,16.07502],"type":"Point"}
}