{
  "type": "Feature",
  "properties": {
    "gn:admin1_code":"8.0",
    "gn:admin2_code":"1814.0",
    "gn:asciiname":"Bayt Zayn",
    "gn:country_code":"YE",
    "gn:dem":30,
    "gn:feature_class":"P",
    "gn:feature_code":"PPL",
    "gn:name":"Bayt Zayn",
    "gn:population":0,
    "gn:timezone":"Asia/Aden",
    "iso:country":"YE",
    "name:ara_x_preferred":[
        "\u0628\u064a\u062a \u0632\u064a\u0646"
    ],
    "wof:name":"Bayt Zayn",
    "wof:placetype":"locality"
},
  "geometry": {"coordinates":[43.07354,14.7343],"type":"Point"}
}