{
  "type": "Feature",
  "properties": {
    "gn:country":"YE",
    "gn:fcode":"PPL",
    "gn:pop":44,
    "iso:country":"YE",
    "name:ara_x_preferred":[
        "\u0627\u0644\u062c\u0631\u064a\u0628\u0629"
    ],
    "name:eng_x_preferred":[
        "Al Juraybah"
    ],
    "qs:name":"Al Juraybah",
    "qs:photos_9r":0,
    "qs:photos_sr":0,
    "qs:pop_sr":"1",
    "wof:name":"Al Juraybah",
    "wof:placetype":"locality",
    "wof:population":44
},
  "geometry": {"coordinates":[43.70747,13.32539],"type":"Point"}
}