{
  "type": "Feature",
  "properties": {
    "gn:country":"YE",
    "gn:fcode":"PPL",
    "gn:population":4,
    "iso:country":"YE",
    "name:ara_x_preferred":[
        "\u0627\u0644\u062d\u0644\u0629"
    ],
    "qs:name":"Al \u1e28alah",
    "qs:photos_9r":0,
    "qs:photos_sr":0,
    "qs:pop_sr":"1",
    "wof:name":"Al \u1e28alah",
    "wof:placetype":"locality",
    "wof:population":4
},
  "geometry": {"coordinates":[44.38174,17.23188],"type":"Point"}
}