{
  "type": "Feature",
  "properties": {
    "gn:admin1_code":"4.0",
    "gn:admin2_code":"1918.0",
    "gn:asciiname":"Ruhab",
    "gn:country_code":"YE",
    "gn:dem":1057,
    "gn:feature_class":"P",
    "gn:feature_code":"PPL",
    "gn:name":"Ru\u1e29\u0101b",
    "gn:population":0,
    "gn:timezone":"Asia/Aden",
    "iso:country":"YE",
    "name:ara_x_preferred":[
        "Ru\u1e29\u0101b"
    ],
    "wof:name":"Ruhab",
    "wof:placetype":"locality"
},
  "geometry": {"coordinates":[48.33889,15.14917],"type":"Point"}
}