{
  "type": "Feature",
  "properties": {
    "gn:admin1_code":"16.0",
    "gn:admin2_code":"2316.0",
    "gn:asciiname":"Bayt ar Ruwayshat",
    "gn:cc2":"YE",
    "gn:country_code":"YE",
    "gn:dem":2137,
    "gn:feature_class":"P",
    "gn:feature_code":"PPL",
    "gn:name":"Bayt ar Ruwaysh\u0101t",
    "gn:population":0,
    "gn:timezone":"Asia/Aden",
    "iso:country":"YE",
    "name:und_x_variant":[
        "Bayt al Ruwayshan",
        "Bayt ar Ruwaysh\u0101t"
    ],
    "wof:name":"Bayt ar Ruwayshat",
    "wof:placetype":"locality"
},
  "geometry": {"coordinates":[44.56667,15.18333],"type":"Point"}
}