{
  "type": "Feature",
  "properties": {
    "gn:country":"YE",
    "gn:fcode":"PPL",
    "gn:population":10,
    "iso:country":"YE",
    "name:ara_x_preferred":[
        "\u0627\u0644\u0645\u0641\u0644\u064a\u0629 \u0627\u0644\u062d\u0645\u0631\u0627\u0621"
    ],
    "name:eng_x_preferred":[
        "Al Mafliyah Al Hamra"
    ],
    "name:eng_x_variant":[
        "At Tawbah"
    ],
    "qs_pg:aaroncc":"YE",
    "qs_pg:gn_country":"YE",
    "qs_pg:gn_fcode":"PPL",
    "qs_pg:gn_pop":10,
    "qs_pg:name":"Al Mafl\u012byah al \u1e28amr\u0101\u2019",
    "qs_pg:photos_9r":0,
    "qs_pg:photos_sr":0,
    "qs_pg:pop_sr":1,
    "qs_pg:qs_pg_placetype":"locality",
    "wof:name":"Al Mafl\u012byah al \u1e28amr\u0101\u2019",
    "wof:placetype":"locality",
    "wof:population":10
},
  "geometry": {"coordinates":[43.21744,16.64189],"type":"Point"}
}