{
  "type": "Feature",
  "properties": {
    "gn:admin1_code":"15.0",
    "gn:admin2_code":"2206.0",
    "gn:asciiname":"Al 'Amrah",
    "gn:country_code":"YE",
    "gn:dem":1135,
    "gn:feature_class":"P",
    "gn:feature_code":"PPL",
    "gn:name":"Al \u2018Amrah",
    "gn:population":0,
    "gn:timezone":"Asia/Aden",
    "iso:country":"YE",
    "name:ara_x_preferred":[
        "\u0627\u0644\u0639\u0645\u0631\u0629"
    ],
    "name:und_x_variant":[
        "Al \u2018Amrah",
        "Al \u2018Umrah"
    ],
    "wof:name":"Al 'Amrah",
    "wof:placetype":"locality"
},
  "geometry": {"coordinates":[43.17973,16.91174],"type":"Point"}
}