{
  "type": "Feature",
  "properties": {
    "gn:admin1_code":"15.0",
    "gn:admin2_code":"2210.0",
    "gn:asciiname":"Al Mahjil",
    "gn:country_code":"YE",
    "gn:dem":1860,
    "gn:feature_class":"P",
    "gn:feature_code":"PPL",
    "gn:name":"Al Ma\u1e29jil",
    "gn:population":0,
    "gn:timezone":"Asia/Aden",
    "iso:country":"YE",
    "name:ara_x_preferred":[
        "\u0627\u0644\u0645\u062d\u062c\u0644"
    ],
    "name:und_x_variant":[
        "Al Ma\u1e29jil"
    ],
    "wof:name":"Al Mahjil",
    "wof:placetype":"locality"
},
  "geometry": {"coordinates":[43.40286,17.01326],"type":"Point"}
}