{
  "type": "Feature",
  "properties": {
    "gn:admin1_code":"4.0",
    "gn:admin2_code":"1913.0",
    "gn:asciiname":"Hasana",
    "gn:country_code":"YE",
    "gn:dem":5,
    "gn:feature_class":"P",
    "gn:feature_code":"PPL",
    "gn:name":"Hasana",
    "gn:population":0,
    "gn:timezone":"Asia/Aden",
    "iso:country":"YE",
    "name:und_x_variant":[
        "\u1e28a\u015f\u0101nah"
    ],
    "wof:name":"Hasana",
    "wof:placetype":"locality"
},
  "geometry": {"coordinates":[50.50667,15.04167],"type":"Point"}
}