{
  "type": "Feature",
  "properties": {
    "gn:admin1_code":"8.0",
    "gn:admin2_code":"1807.0",
    "gn:asciiname":"Abkar Ghanam",
    "gn:country_code":"YE",
    "gn:dem":64,
    "gn:feature_class":"P",
    "gn:feature_code":"PPL",
    "gn:name":"Abkar Ghanam",
    "gn:population":0,
    "gn:timezone":"Asia/Aden",
    "iso:country":"YE",
    "name:ara_x_preferred":[
        "\u0623\u0628\u0643\u0631 \u063a\u0646\u0645"
    ],
    "name:und_x_variant":[
        "Dayr Om\u00e1r",
        "Dayr \u2018Umar",
        "Abkar Ghanam"
    ],
    "wof:name":"Abkar Ghanam",
    "wof:placetype":"locality"
},
  "geometry": {"coordinates":[43.02966,15.24155],"type":"Point"}
}