{
  "type": "Feature",
  "properties": {
    "gn:admin1_code":"23.0",
    "gn:admin2_code":"1110.0",
    "gn:asciiname":"Al Barra'",
    "gn:country_code":"YE",
    "gn:dem":694,
    "gn:feature_class":"P",
    "gn:feature_code":"PPL",
    "gn:name":"Al Barr\u0101\u2019",
    "gn:population":0,
    "gn:timezone":"Asia/Aden",
    "iso:country":"YE",
    "name:und_x_variant":[
        "Al Barr\u0101\u2019"
    ],
    "wof:name":"Al Barra'",
    "wof:placetype":"locality"
},
  "geometry": {"coordinates":[43.72556,13.8752],"type":"Point"}
}