{
  "type": "Feature",
  "properties": {
    "gn:admin1_code":"25.0",
    "gn:admin2_code":"1515.0",
    "gn:asciiname":"An Nuzayhah",
    "gn:country_code":"YE",
    "gn:dem":737,
    "gn:feature_class":"P",
    "gn:feature_code":"PPL",
    "gn:name":"An Nuzayhah",
    "gn:population":0,
    "gn:timezone":"Asia/Aden",
    "iso:country":"YE",
    "name:ara_x_preferred":[
        "\u0627\u0644\u0646\u0632\u064a\u0647\u0629"
    ],
    "wof:name":"An Nuzayhah",
    "wof:placetype":"locality"
},
  "geometry": {"coordinates":[43.87275,13.24002],"type":"Point"}
}