{
  "type": "Feature",
  "properties": {
    "gn:admin1_code":"23.0",
    "gn:admin2_code":"1101.0",
    "gn:asciiname":"Al Qahabi",
    "gn:country_code":"YE",
    "gn:dem":1371,
    "gn:feature_class":"P",
    "gn:feature_code":"PPL",
    "gn:name":"Al Qah\u0101b\u012b",
    "gn:population":0,
    "gn:timezone":"Asia/Aden",
    "iso:country":"YE",
    "name:ara_x_preferred":[
        "\u0627\u0644\u0642\u0647\u0627\u0628\u064a"
    ],
    "name:und_x_variant":[
        "Al Qah\u0101b\u012b"
    ],
    "wof:name":"Al Qahabi",
    "wof:placetype":"locality"
},
  "geometry": {"coordinates":[44.10886,14.2866],"type":"Point"}
}