{
  "type": "Feature",
  "properties": {
    "gn:admin1_code":"5.0",
    "gn:admin2_code":"2109.0",
    "gn:asciiname":"Wasi`an",
    "gn:country_code":"YE",
    "gn:dem":1071,
    "gn:feature_class":"P",
    "gn:feature_code":"PPL",
    "gn:name":"Was\u012b\u2018\u0101n",
    "gn:population":0,
    "gn:timezone":"Asia/Aden",
    "iso:country":"YE",
    "name:und_x_variant":[
        "Was\u012b\u2018\u0101n"
    ],
    "wof:name":"Wasi`an",
    "wof:placetype":"locality"
},
  "geometry": {"coordinates":[46.20792,14.61056],"type":"Point"}
}