{
  "type": "Feature",
  "properties": {
    "gn:admin1_code":"22.0",
    "gn:admin2_code":"1720.0",
    "gn:asciiname":"Al Jamimah",
    "gn:country_code":"YE",
    "gn:dem":1515,
    "gn:feature_class":"P",
    "gn:feature_code":"PPL",
    "gn:name":"Al Jam\u012bmah",
    "gn:population":0,
    "gn:timezone":"Asia/Aden",
    "iso:country":"YE",
    "name:und_x_variant":[
        "Al Jam\u012bmah"
    ],
    "wof:name":"Al Jamimah",
    "wof:placetype":"locality"
},
  "geometry": {"coordinates":[43.55403,15.76474],"type":"Point"}
}