{
  "type": "Feature",
  "properties": {
    "gn:gn_country":"YE",
    "gn:gn_fcode":"PPL",
    "gn:gn_pop":4,
    "gn:population":4,
    "iso:country":"YE",
    "name:ara_x_preferred":[
        "Al \u2018Adh\u012br"
    ],
    "name:ara_x_variant":[
        "\u0627\u0644\u0639\u0630\u064a\u0631"
    ],
    "name:eng_x_preferred":[
        "Al 'Adhir"
    ],
    "qs_pg:aaroncc":"YE",
    "qs_pg:gn_country":"YE",
    "qs_pg:gn_fcode":"PPL",
    "qs_pg:gn_pop":4,
    "qs_pg:name":"Al \u2018Adh\u012br",
    "qs_pg:photos_9r":0,
    "qs_pg:photos_sr":0,
    "qs_pg:pop_sr":1,
    "qs_pg:qs_pg_placetype":"locality",
    "wof:name":"Al \u2018Adh\u012br",
    "wof:placetype":"locality",
    "wof:population":4
},
  "geometry": {"coordinates":[43.15001,16.33295],"type":"Point"}
}