{
  "type": "Feature",
  "properties": {
    "gn:country":"YE",
    "gn:fcode":"PPL",
    "gn:population":13,
    "iso:country":"YE",
    "name:ara_x_preferred":[
        "\u062d\u064a\u062f \u0646\u0627\u0635\u0631"
    ],
    "name:eng_x_preferred":[
        "Hayd Nasir"
    ],
    "name:eng_x_variant":[
        "Al Kar\u0101nah"
    ],
    "qs:name":"\u1e28ayd N\u0101\u015fir",
    "qs:photos_9r":0,
    "qs:photos_sr":0,
    "qs:pop_sr":"1",
    "wof:name":"\u1e28ayd N\u0101\u015fir",
    "wof:placetype":"locality",
    "wof:population":13
},
  "geometry": {"coordinates":[45.07723,14.33654],"type":"Point"}
}