{
  "type": "Feature",
  "properties": {
    "gn:admin1_code":"16.0",
    "gn:admin2_code":"2307.0",
    "gn:asciiname":"Al Qadhaf",
    "gn:country_code":"YE",
    "gn:dem":2913,
    "gn:feature_class":"P",
    "gn:feature_code":"PPL",
    "gn:name":"Al Qadhaf",
    "gn:population":0,
    "gn:timezone":"Asia/Aden",
    "iso:country":"YE",
    "wof:name":"Al Qadhaf",
    "wof:placetype":"locality"
},
  "geometry": {"coordinates":[44.01834,15.25753],"type":"Point"}
}