{
  "type": "Feature",
  "properties": {
    "gn:admin1_code":"18.0",
    "gn:admin2_code":"3009.0",
    "gn:asciiname":"Qaryat al Ghalil",
    "gn:country_code":"YE",
    "gn:dem":1433,
    "gn:feature_class":"P",
    "gn:feature_code":"PPL",
    "gn:name":"Qaryat al Ghal\u012bl",
    "gn:population":0,
    "gn:timezone":"Asia/Aden",
    "iso:country":"YE",
    "name:und_x_variant":[
        "Qaryat al Ghal\u012bl"
    ],
    "wof:name":"Qaryat al Ghalil",
    "wof:placetype":"locality"
},
  "geometry": {"coordinates":[44.41384,13.72341],"type":"Point"}
}