{
  "type": "Feature",
  "properties": {
    "gn:admin1_code":"8.0",
    "gn:admin2_code":"1810.0",
    "gn:asciiname":"Mahall Bani Yusuf",
    "gn:country_code":"YE",
    "gn:dem":126,
    "gn:feature_class":"P",
    "gn:feature_code":"PPL",
    "gn:name":"Ma\u1e29all Ban\u012b Y\u016bsuf",
    "gn:population":0,
    "gn:timezone":"Asia/Aden",
    "iso:country":"YE",
    "name:und_x_variant":[
        "Ma\u1e29all Ban\u012b Y\u016bsuf"
    ],
    "wof:name":"Mahall Bani Yusuf",
    "wof:placetype":"locality"
},
  "geometry": {"coordinates":[43.17999,15.0968],"type":"Point"}
}