{
  "type": "Feature",
  "properties": {
    "gn:admin1_code":"23.0",
    "gn:admin2_code":"1104.0",
    "gn:asciiname":"Bayt Mashra`",
    "gn:country_code":"YE",
    "gn:dem":2847,
    "gn:feature_class":"P",
    "gn:feature_code":"PPL",
    "gn:name":"Bayt Mashra\u2018",
    "gn:population":0,
    "gn:timezone":"Asia/Aden",
    "iso:country":"YE",
    "name:und_x_variant":[
        "Bayt Mashra\u2018"
    ],
    "wof:name":"Bayt Mashra`",
    "wof:placetype":"locality"
},
  "geometry": {"coordinates":[44.48653,14.14068],"type":"Point"}
}