{
  "type": "Feature",
  "properties": {
    "gn:admin1_code":"15.0",
    "gn:admin2_code":"2203.0",
    "gn:asciiname":"Al Qahabah",
    "gn:country_code":"YE",
    "gn:dem":1821,
    "gn:feature_class":"P",
    "gn:feature_code":"PPL",
    "gn:name":"Al Qahabah",
    "gn:population":0,
    "gn:timezone":"Asia/Aden",
    "iso:country":"YE",
    "wof:name":"Al Qahabah",
    "wof:placetype":"locality"
},
  "geometry": {"coordinates":[43.28729000000001,17.21454],"type":"Point"}
}