{
  "type": "Feature",
  "properties": {
    "gn:admin1_code":"20.0",
    "gn:asciiname":"Dhira` al Hamad",
    "gn:country_code":"YE",
    "gn:dem":-9999,
    "gn:feature_class":"P",
    "gn:feature_code":"PPL",
    "gn:name":"Dhir\u0101\u2018 al \u1e28ama\u1e11",
    "gn:population":0,
    "gn:timezone":"Asia/Aden",
    "iso:country":"YE",
    "name:ara_x_preferred":[
        "\u0630\u0631\u0627\u0639 \u0627\u0644\u062d\u0645\u0636"
    ],
    "name:und_x_variant":[
        "Dhir\u0101\u2018 al \u1e28ama\u1e11"
    ],
    "wof:name":"Dhira` al Hamad",
    "wof:placetype":"locality"
},
  "geometry": {"coordinates":[0.7853,0.25168],"type":"Point"}
}