{
  "type": "Feature",
  "properties": {
    "gn:admin1_code":"22.0",
    "gn:admin2_code":"1709.0",
    "gn:asciiname":"Wadi al Qiyas",
    "gn:country_code":"YE",
    "gn:dem":1508,
    "gn:feature_class":"P",
    "gn:feature_code":"PPL",
    "gn:name":"W\u0101d\u012b al Qiy\u0101s",
    "gn:population":0,
    "gn:timezone":"Asia/Aden",
    "iso:country":"YE",
    "name:ara_x_preferred":[
        "\u0648\u0627\u062f\u064a \u0627\u0644\u0642\u064a\u0627\u0633"
    ],
    "name:und_x_variant":[
        "W\u0101d\u012b al Qiy\u0101s"
    ],
    "wof:name":"Wadi al Qiyas",
    "wof:placetype":"locality"
},
  "geometry": {"coordinates":[43.48984,16.00427],"type":"Point"}
}