{
  "type": "Feature",
  "properties": {
    "gn:admin1_code":"14.0",
    "gn:admin2_code":"2608.0",
    "gn:asciiname":"Al Wadih",
    "gn:country_code":"YE",
    "gn:dem":1545,
    "gn:feature_class":"P",
    "gn:feature_code":"PPL",
    "gn:name":"Al W\u0101\u1e11i\u1e29",
    "gn:population":4,
    "gn:timezone":"Asia/Aden",
    "iso:country":"YE",
    "name:ara_x_preferred":[
        "Al W\u0101\u1e11i\u1e29"
    ],
    "name:ara_x_variant":[
        "\u0627\u0644\u0648\u0627\u0636\u062d"
    ],
    "wof:name":"Al Wadih",
    "wof:placetype":"locality",
    "wof:population":4
},
  "geometry": {"coordinates":[45.10249,14.96413],"type":"Point"}
}