{
  "type": "Feature",
  "properties": {
    "gn:admin1_code":"1.0",
    "gn:admin2_code":"1211.0",
    "gn:asciiname":"Ar Rawdah",
    "gn:country_code":"YE",
    "gn:dem":449,
    "gn:feature_class":"P",
    "gn:feature_code":"PPL",
    "gn:name":"Ar Raw\u1e11ah",
    "gn:population":0,
    "gn:timezone":"Asia/Aden",
    "iso:country":"YE",
    "name:und_x_variant":[
        "Raudah",
        "Al Raudah",
        "Rauda",
        "Ar Raw\u1e11ah"
    ],
    "wof:name":"Ar Rawdah",
    "wof:placetype":"locality"
},
  "geometry": {"coordinates":[45.6006,13.48447],"type":"Point"}
}