{
  "type": "Feature",
  "properties": {
    "gn:admin1_code":"8.0",
    "gn:admin2_code":"1824.0",
    "gn:asciiname":"Al Buratah",
    "gn:country_code":"YE",
    "gn:dem":156,
    "gn:feature_class":"P",
    "gn:feature_code":"PPL",
    "gn:name":"Al Bur\u0101tah",
    "gn:population":0,
    "gn:timezone":"Asia/Aden",
    "iso:country":"YE",
    "name:und_x_variant":[
        "Al Bur\u0101tah"
    ],
    "wof:name":"Al Buratah",
    "wof:placetype":"locality"
},
  "geometry": {"coordinates":[43.40443,14.26911],"type":"Point"}
}