{
  "type": "Feature",
  "properties": {
    "gn:admin1_code":"26.0",
    "gn:admin2_code":"1310.0",
    "gn:asciiname":"Al Hanaq",
    "gn:country_code":"YE",
    "gn:dem":2153,
    "gn:feature_class":"P",
    "gn:feature_code":"PPL",
    "gn:name":"Al \u1e28anaq",
    "gn:population":0,
    "gn:timezone":"Asia/Aden",
    "iso:country":"YE",
    "name:ara_x_preferred":[
        "\u0627\u0644\u062d\u0646\u0642"
    ],
    "name:und_x_variant":[
        "Al \u1e28anaq"
    ],
    "wof:name":"Al Hanaq",
    "wof:placetype":"locality"
},
  "geometry": {"coordinates":[44.25701,15.56694],"type":"Point"}
}