{
  "type": "Feature",
  "properties": {
    "gn:admin1_code":"25.0",
    "gn:admin2_code":"1517.0",
    "gn:asciiname":"Qarad",
    "gn:country_code":"YE",
    "gn:dem":1994,
    "gn:feature_class":"P",
    "gn:feature_code":"PPL",
    "gn:name":"Qara\u1e11",
    "gn:population":0,
    "gn:timezone":"Asia/Aden",
    "iso:country":"YE",
    "name:und_x_variant":[
        "Qara\u1e11"
    ],
    "wof:name":"Qarad",
    "wof:placetype":"locality"
},
  "geometry": {"coordinates":[44.25556,13.32574],"type":"Point"}
}