{
  "type": "Feature",
  "properties": {
    "gn:country":"YE",
    "gn:fcode":"PPL",
    "gn:population":2,
    "iso:country":"YE",
    "name:ara_x_preferred":[
        "\u0627\u0644\u062d\u062c\u0628"
    ],
    "name:eng_x_preferred":[
        "Al Hajab"
    ],
    "name:eng_x_variant":[
        "\u2018Aqabat ath Thawr"
    ],
    "qs:name":"Al \u1e28ajab",
    "qs:photos_9r":0,
    "qs:photos_sr":0,
    "qs:pop_sr":"1",
    "wof:name":"Al \u1e28ajab",
    "wof:placetype":"locality",
    "wof:population":2
},
  "geometry": {"coordinates":[43.81476,13.36531],"type":"Point"}
}