{
  "type": "Feature",
  "properties": {
    "gn:admin1_code":"23.0",
    "gn:admin2_code":"1101.0",
    "gn:asciiname":"Dar al Karabah",
    "gn:country_code":"YE",
    "gn:dem":1841,
    "gn:feature_class":"P",
    "gn:feature_code":"PPL",
    "gn:name":"D\u0101r al Kar\u0101bah",
    "gn:population":0,
    "gn:timezone":"Asia/Aden",
    "iso:country":"YE",
    "name:ara_x_preferred":[
        "\u062f\u0627\u0631 \u0627\u0644\u0643\u0631\u0627\u0628\u0629"
    ],
    "name:und_x_variant":[
        "D\u0101r al Kar\u0101bah"
    ],
    "wof:name":"Dar al Karabah",
    "wof:placetype":"locality"
},
  "geometry": {"coordinates":[44.22721,14.2511],"type":"Point"}
}