{
  "type": "Feature",
  "properties": {
    "gn:admin1_code":"5.0",
    "gn:admin2_code":"2111.0",
    "gn:asciiname":"Sa`adah",
    "gn:country_code":"YE",
    "gn:dem":1509,
    "gn:feature_class":"P",
    "gn:feature_code":"PPL",
    "gn:name":"Sa\u2018\u0101dah",
    "gn:population":0,
    "gn:timezone":"Asia/Aden",
    "iso:country":"YE",
    "name:und_x_variant":[
        "Sa\u2019ada",
        "Sa\u2018\u0101dah",
        "Am Sa\u2019ada"
    ],
    "wof:name":"Sa`adah",
    "wof:placetype":"locality"
},
  "geometry": {"coordinates":[46.40505,14.21915],"type":"Point"}
}