{
  "type": "Feature",
  "properties": {
    "gn:admin1_code":"16.0",
    "gn:admin2_code":"2304.0",
    "gn:asciiname":"Ar Rawnah",
    "gn:country_code":"YE",
    "gn:dem":2451,
    "gn:feature_class":"P",
    "gn:feature_code":"PPL",
    "gn:name":"Ar Rawnah",
    "gn:population":0,
    "gn:timezone":"Asia/Aden",
    "iso:country":"YE",
    "wof:name":"Ar Rawnah",
    "wof:placetype":"locality"
},
  "geometry": {"coordinates":[44.34645,15.41854],"type":"Point"}
}