{
  "type": "Feature",
  "properties": {
    "gn:admin1_code":"21.0",
    "gn:admin2_code":"1602.0",
    "gn:asciiname":"Zakhmirah",
    "gn:country_code":"YE",
    "gn:dem":1293,
    "gn:feature_class":"P",
    "gn:feature_code":"PPL",
    "gn:name":"Zakhmirah",
    "gn:population":0,
    "gn:timezone":"Asia/Aden",
    "iso:country":"YE",
    "name:ara_x_preferred":[
        "\u0632\u062e\u0645\u0631\u0629"
    ],
    "wof:name":"Zakhmirah",
    "wof:placetype":"locality"
},
  "geometry": {"coordinates":[44.43055,16.47274],"type":"Point"}
}