{
  "type": "Feature",
  "properties": {
    "gn:admin1_code":"24.0",
    "gn:admin2_code":"2510.0",
    "gn:asciiname":"Lakamat al `Aydi",
    "gn:country_code":"YE",
    "gn:dem":1061,
    "gn:feature_class":"P",
    "gn:feature_code":"PPL",
    "gn:name":"Lakamat al \u2018Ayd\u012b",
    "gn:population":0,
    "gn:timezone":"Asia/Aden",
    "iso:country":"YE",
    "name:und_x_variant":[
        "Lakamat al \u2018Ayd\u012b"
    ],
    "wof:name":"Lakamat al `Aydi",
    "wof:placetype":"locality"
},
  "geometry": {"coordinates":[44.30473,13.36497],"type":"Point"}
}