{
  "type": "Feature",
  "properties": {
    "gn:admin1_code":"14.0",
    "gn:admin2_code":"2607.0",
    "gn:asciiname":"Kasa'",
    "gn:country_code":"YE",
    "gn:dem":2222,
    "gn:feature_class":"P",
    "gn:feature_code":"PPLL",
    "gn:name":"Kas\u0101\u2018",
    "gn:population":0,
    "gn:timezone":"Asia/Aden",
    "iso:country":"YE",
    "name:ara_x_preferred":[
        "\u0643\u0633\u0627\u0639"
    ],
    "name:und_x_variant":[
        "Kas\u0101\u2018"
    ],
    "wof:name":"Kasa'",
    "wof:placetype":"locality"
},
  "geometry": {"coordinates":[45.18624000000001,15.11666],"type":"Point"}
}