{
  "type": "Feature",
  "properties": {
    "gn:admin1_code":"11.0",
    "gn:admin2_code":"2001.0",
    "gn:asciiname":"Al Farghah",
    "gn:country_code":"YE",
    "gn:dem":2089,
    "gn:feature_class":"P",
    "gn:feature_code":"PPL",
    "gn:name":"Al Farghah",
    "gn:population":0,
    "gn:timezone":"Asia/Aden",
    "iso:country":"YE",
    "name:ara_x_preferred":[
        "\u0627\u0644\u0641\u0631\u063a\u0629"
    ],
    "name:und_x_variant":[
        "Al Faraghah",
        "Al Farghah"
    ],
    "wof:name":"Al Farghah",
    "wof:placetype":"locality"
},
  "geometry": {"coordinates":[44.75529,14.75356],"type":"Point"}
}