{
  "type": "Feature",
  "properties": {
    "gn:admin1_code":"23.0",
    "gn:admin2_code":"1114.0",
    "gn:asciiname":"Jidabah",
    "gn:country_code":"YE",
    "gn:dem":2492,
    "gn:feature_class":"P",
    "gn:feature_code":"PPL",
    "gn:name":"Jid\u0101bah",
    "gn:population":0,
    "gn:timezone":"Asia/Aden",
    "iso:country":"YE",
    "name:und_x_variant":[
        "Jid\u0101bah"
    ],
    "wof:name":"Jidabah",
    "wof:placetype":"locality"
},
  "geometry": {"coordinates":[44.27854,13.95313],"type":"Point"}
}