{
  "type": "Feature",
  "properties": {
    "gn:admin1_code":"11.0",
    "gn:admin2_code":"2012.0",
    "gn:asciiname":"Bani Mihan",
    "gn:country_code":"YE",
    "gn:dem":2010,
    "gn:feature_class":"P",
    "gn:feature_code":"PPL",
    "gn:name":"Ban\u012b Mi\u1e29an",
    "gn:population":0,
    "gn:timezone":"Asia/Aden",
    "iso:country":"YE",
    "name:und_x_variant":[
        "Ban\u012b Mi\u1e29an"
    ],
    "wof:name":"Bani Mihan",
    "wof:placetype":"locality"
},
  "geometry": {"coordinates":[44.12027,14.70036],"type":"Point"}
}