{
  "type": "Feature",
  "properties": {
    "gn:admin1_code":"8.0",
    "gn:admin2_code":"1810.0",
    "gn:asciiname":"Mahall Faris",
    "gn:country_code":"YE",
    "gn:dem":108,
    "gn:feature_class":"P",
    "gn:feature_code":"PPL",
    "gn:name":"Ma\u1e29all F\u0101ris",
    "gn:population":0,
    "gn:timezone":"Asia/Aden",
    "iso:country":"YE",
    "name:ara_x_preferred":[
        "\u0645\u062d\u0644 \u0641\u0627\u0631\u0633"
    ],
    "name:und_x_variant":[
        "Ma\u1e29all Jab\u0101\u2019",
        "Ma\u1e29all F\u0101ris"
    ],
    "wof:name":"Mahall Faris",
    "wof:placetype":"locality"
},
  "geometry": {"coordinates":[43.14763,15.13991],"type":"Point"}
}