{
  "type": "Feature",
  "properties": {
    "gn:admin1_code":"16.0",
    "gn:admin2_code":"2316.0",
    "gn:asciiname":"Bani Sha'i`",
    "gn:country_code":"YE",
    "gn:dem":2345,
    "gn:feature_class":"P",
    "gn:feature_code":"PPL",
    "gn:name":"Ban\u012b Sh\u0101\u2019i\u2018",
    "gn:population":0,
    "gn:timezone":"Asia/Aden",
    "iso:country":"YE",
    "name:und_x_variant":[
        "Ban\u012b Sh\u0101\u2019i\u2018"
    ],
    "wof:name":"Bani Sha'i`",
    "wof:placetype":"locality"
},
  "geometry": {"coordinates":[44.42074,15.12927],"type":"Point"}
}