{
  "type": "Feature",
  "properties": {
    "gn:country":"YE",
    "gn:fcode":"PPL",
    "gn:pop":3,
    "iso:country":"YE",
    "name:ara_x_preferred":[
        "\u0642\u0644\u0639\u0629 \u0627\u0644\u062c\u0646\u0629"
    ],
    "name:eng_x_preferred":[
        "Qal'at Al Jinnah"
    ],
    "name:unk_x_variant":[
        "Qal\u2018at al Jannah"
    ],
    "qs:name":"Qal\u2018at al Jinnah",
    "qs:photos_9r":0,
    "qs:photos_sr":0,
    "qs:pop_sr":"1",
    "wof:name":"Qal\u2018at al Jinnah",
    "wof:placetype":"locality",
    "wof:population":3
},
  "geometry": {"coordinates":[43.39566,16.25211],"type":"Point"}
}