{
  "type": "Feature",
  "properties": {
    "gn:admin1_code":"22.0",
    "gn:admin2_code":"1727.0",
    "gn:asciiname":"Sha'b Ghazal",
    "gn:country_code":"YE",
    "gn:dem":896,
    "gn:feature_class":"P",
    "gn:feature_code":"PPL",
    "gn:name":"Sha\u2018b Ghaz\u0101l",
    "gn:population":0,
    "gn:timezone":"Asia/Aden",
    "iso:country":"YE",
    "name:ara_x_preferred":[
        "\u0634\u0639\u0628 \u063a\u0632\u0627\u0644"
    ],
    "name:und_x_variant":[
        "Sha\u2018b Ghaz\u0101l"
    ],
    "wof:name":"Sha'b Ghazal",
    "wof:placetype":"locality"
},
  "geometry": {"coordinates":[43.55488,15.56115],"type":"Point"}
}