{
  "type": "Feature",
  "properties": {
    "gn:country":"YE",
    "gn:fcode":"PPL",
    "gn:pop":2,
    "iso:country":"YE",
    "name:ara_x_preferred":[
        "\u0627\u0644\u062c\u0631\u0641 \u0627\u0644\u0634\u0631\u0642\u064a\u0629"
    ],
    "name:eng_x_preferred":[
        "Al Jarf Ash Sharqi"
    ],
    "name:eng_x_variant":[
        "\u0100l \u1e28asan"
    ],
    "qs:name":"Al Jarf ash Sharq\u012b",
    "qs:photos_9r":0,
    "qs:photos_sr":0,
    "qs:pop_sr":"1",
    "wof:name":"Al Jarf ash Sharq\u012b",
    "wof:placetype":"locality",
    "wof:population":2
},
  "geometry": {"coordinates":[43.32014,16.34702],"type":"Point"}
}