{
  "type": "Feature",
  "properties": {
    "gn:admin1_code":"19.0",
    "gn:admin2_code":"2908.0",
    "gn:asciiname":"Ash Sharqi al A'la",
    "gn:country_code":"YE",
    "gn:dem":1677,
    "gn:feature_class":"P",
    "gn:feature_code":"PPL",
    "gn:name":"Ash Sharq\u012b al A\u2018l\u00e1",
    "gn:population":0,
    "gn:timezone":"Asia/Aden",
    "iso:country":"YE",
    "name:ara_x_preferred":[
        "\u0627\u0644\u0634\u0631\u0642\u064a \u0627\u0644\u0623\u0639\u0644\u0649"
    ],
    "name:und_x_variant":[
        "Ash Sharq\u012b al A\u2018l\u00e1"
    ],
    "wof:name":"Ash Sharqi al A'la",
    "wof:placetype":"locality"
},
  "geometry": {"coordinates":[43.72735,16.0775],"type":"Point"}
}