{
  "type": "Feature",
  "properties": {
    "gn:admin1_code":"11.0",
    "gn:admin2_code":"2004.0",
    "gn:asciiname":"Talibayn",
    "gn:country_code":"YE",
    "gn:dem":2612,
    "gn:feature_class":"P",
    "gn:feature_code":"PPL",
    "gn:name":"T\u0101libayn",
    "gn:population":0,
    "gn:timezone":"Asia/Aden",
    "iso:country":"YE",
    "name:und_x_variant":[
        "T\u0101libayn"
    ],
    "wof:name":"Talibayn",
    "wof:placetype":"locality"
},
  "geometry": {"coordinates":[44.10311,14.51394],"type":"Point"}
}