{
  "type": "Feature",
  "properties": {
    "gn:admin1_code":"23.0",
    "gn:admin2_code":"1104.0",
    "gn:asciiname":"Bayt az Zubaydi",
    "gn:country_code":"YE",
    "gn:dem":2484,
    "gn:feature_class":"P",
    "gn:feature_code":"PPL",
    "gn:name":"Bayt az Zubayd\u012b",
    "gn:population":0,
    "gn:timezone":"Asia/Aden",
    "iso:country":"YE",
    "name:ara_x_preferred":[
        "\u0628\u064a\u062a \u0627\u0644\u0632\u0628\u064a\u062f\u064a"
    ],
    "name:und_x_variant":[
        "Bayt az Zubayd\u012b"
    ],
    "wof:name":"Bayt az Zubaydi",
    "wof:placetype":"locality"
},
  "geometry": {"coordinates":[44.58165,14.11372],"type":"Point"}
}