{
  "type": "Feature",
  "properties": {
    "gn:admin1_code":"23.0",
    "gn:admin2_code":"1109.0",
    "gn:asciiname":"Sha`bah",
    "gn:country_code":"YE",
    "gn:dem":1822,
    "gn:feature_class":"P",
    "gn:feature_code":"PPL",
    "gn:name":"Sha\u2018bah",
    "gn:population":0,
    "gn:timezone":"Asia/Aden",
    "iso:country":"YE",
    "name:ara_x_preferred":[
        "\u0634\u0639\u0628\u0629"
    ],
    "name:und_x_variant":[
        "Sha\u2018bah",
        "Shu\u2018bah"
    ],
    "wof:name":"Sha`bah",
    "wof:placetype":"locality"
},
  "geometry": {"coordinates":[44.02175,14.05883],"type":"Point"}
}