{
  "type": "Feature",
  "properties": {
    "gn:admin1_code":"25.0",
    "gn:admin2_code":"1516.0",
    "gn:asciiname":"Al Hajjaj",
    "gn:country_code":"YE",
    "gn:dem":678,
    "gn:feature_class":"P",
    "gn:feature_code":"PPL",
    "gn:name":"Al \u1e28ajjaj",
    "gn:population":0,
    "gn:timezone":"Asia/Aden",
    "iso:country":"YE",
    "name:ara_x_preferred":[
        "\u0627\u0644\u062d\u062c\u062c"
    ],
    "name:und_x_variant":[
        "Al \u1e28ajjaj"
    ],
    "wof:name":"Al Hajjaj",
    "wof:placetype":"locality"
},
  "geometry": {"coordinates":[43.86061,13.14468],"type":"Point"}
}