{
  "type": "Feature",
  "properties": {
    "gn:country":"YE",
    "gn:fcode":"PPL",
    "gn:population":2,
    "iso:country":"YE",
    "name:ara_x_preferred":[
        "\u0627\u0644\u0645\u0633\u0631\u062d"
    ],
    "qs:name":"Al Misra\u1e29",
    "qs:photos_9r":0,
    "qs:photos_sr":0,
    "qs:pop_sr":"1",
    "wof:name":"Al Misra\u1e29",
    "wof:placetype":"locality",
    "wof:population":2
},
  "geometry": {"coordinates":[44.11179,16.96414],"type":"Point"}
}