{
  "type": "Feature",
  "properties": {
    "gn:admin1_code":"22.0",
    "gn:admin2_code":"1725.0",
    "gn:asciiname":"Bayt Muhammad 'Ali",
    "gn:country_code":"YE",
    "gn:dem":1499,
    "gn:feature_class":"P",
    "gn:feature_code":"PPL",
    "gn:name":"Bayt Mu\u1e29ammad \u2018Al\u012b",
    "gn:population":0,
    "gn:timezone":"Asia/Aden",
    "iso:country":"YE",
    "name:ara_x_preferred":[
        "\u0628\u064a\u062a \u0645\u062d\u0645\u062f \u0639\u0644\u064a"
    ],
    "name:und_x_variant":[
        "Bayt Mu\u1e29ammad \u2018Al\u012b"
    ],
    "wof:name":"Bayt Muhammad 'Ali",
    "wof:placetype":"locality"
},
  "geometry": {"coordinates":[43.56196,15.58239],"type":"Point"}
}