{
  "type": "Feature",
  "properties": {
    "gn:admin1_code":"23.0",
    "gn:admin2_code":"1108.0",
    "gn:asciiname":"Az Zawahi",
    "gn:country_code":"YE",
    "gn:dem":1834,
    "gn:feature_class":"P",
    "gn:feature_code":"PPL",
    "gn:name":"Az Zaw\u0101\u1e29\u012b",
    "gn:population":0,
    "gn:timezone":"Asia/Aden",
    "iso:country":"YE",
    "name:ara_x_preferred":[
        "\u0627\u0644\u0632\u0648\u0627\u062d\u064a"
    ],
    "name:und_x_variant":[
        "Az Zaw\u0101\u1e29\u012b"
    ],
    "wof:name":"Az Zawahi",
    "wof:placetype":"locality"
},
  "geometry": {"coordinates":[44.08904,14.11305],"type":"Point"}
}