{
  "type": "Feature",
  "properties": {
    "gn:admin1_code":"8.0",
    "gn:admin2_code":"1820.0",
    "gn:asciiname":"Al Jashshah",
    "gn:country_code":"YE",
    "gn:dem":6,
    "gn:feature_class":"P",
    "gn:feature_code":"PPL",
    "gn:name":"Al Jashshah",
    "gn:population":0,
    "gn:timezone":"Asia/Aden",
    "iso:country":"YE",
    "wof:name":"Al Jashshah",
    "wof:placetype":"locality"
},
  "geometry": {"coordinates":[43.23947,13.816],"type":"Point"}
}