{
  "type": "Feature",
  "properties": {
    "gn:admin1_code":"25.0",
    "gn:admin2_code":"1522.0",
    "gn:asciiname":"Anif",
    "gn:country_code":"YE",
    "gn:dem":1591,
    "gn:feature_class":"P",
    "gn:feature_code":"PPL",
    "gn:name":"An\u012bf",
    "gn:population":0,
    "gn:timezone":"Asia/Aden",
    "iso:country":"YE",
    "name:ara_x_preferred":[
        "An\u012bf"
    ],
    "name:bar_x_preferred":[
        "Anif"
    ],
    "name:bul_x_preferred":[
        "\u0410\u043d\u0438\u0444"
    ],
    "name:ceb_x_preferred":[
        "Anif"
    ],
    "name:ces_x_preferred":[
        "Anif"
    ],
    "name:deu_x_preferred":[
        "Anif"
    ],
    "name:epo_x_preferred":[
        "Anif"
    ],
    "name:fas_x_preferred":[
        "\u0622\u0646\u06cc\u0641"
    ],
    "name:fra_x_preferred":[
        "Anif"
    ],
    "name:hun_x_preferred":[
        "Anif"
    ],
    "name:ita_x_preferred":[
        "Anif"
    ],
    "name:kaz_x_preferred":[
        "\u0410\u043d\u0438\u0444"
    ],
    "name:nld_x_preferred":[
        "Anif"
    ],
    "name:nno_x_preferred":[
        "Anif"
    ],
    "name:pnb_x_preferred":[
        "\u0622\u0646\u0641"
    ],
    "name:pol_x_preferred":[
        "Anif"
    ],
    "name:ron_x_preferred":[
        "Anif"
    ],
    "name:rus_x_preferred":[
        "\u0410\u043d\u0438\u0444"
    ],
    "name:slk_x_preferred":[
        "Anif"
    ],
    "name:spa_x_preferred":[
        "Anif"
    ],
    "name:swe_x_preferred":[
        "Anif"
    ],
    "name:ukr_x_preferred":[
        "\u0410\u043d\u0456\u0444"
    ],
    "name:uzb_x_preferred":[
        "Anif"
    ],
    "name:vol_x_preferred":[
        "Anif"
    ],
    "name:war_x_preferred":[
        "Anif"
    ],
    "name:zho_x_preferred":[
        "\u963f\u5c3c\u592b"
    ],
    "wof:name":"Anif",
    "wof:placetype":"locality"
},
  "geometry": {"coordinates":[44.18333,13.26667],"type":"Point"}
}