{
  "type": "Feature",
  "properties": {
    "gn:admin1_code":"25.0",
    "gn:admin2_code":"1522.0",
    "gn:asciiname":"Anif",
    "gn:country_code":"YE",
    "gn:dem":1591,
    "gn:feature_class":"P",
    "gn:feature_code":"PPL",
    "gn:name":"An\u012bf",
    "gn:population":0,
    "gn:timezone":"Asia/Aden",
    "iso:country":"YE",
    "name:ara_x_preferred":[
        "An\u012bf"
    ],
    "wof:name":"Anif",
    "wof:placetype":"locality"
},
  "geometry": {"coordinates":[44.18333,13.26667],"type":"Point"}
}