{
  "type": "Feature",
  "properties": {
    "gn:admin1_code":"19.0",
    "gn:admin2_code":"2901.0",
    "gn:asciiname":"Bayt as Sayyid",
    "gn:country_code":"YE",
    "gn:dem":1594,
    "gn:feature_class":"P",
    "gn:feature_code":"PPL",
    "gn:name":"Bayt as Sayyid",
    "gn:population":0,
    "gn:timezone":"Asia/Aden",
    "iso:country":"YE",
    "name:ara_x_preferred":[
        "\u0628\u064a\u062a \u0627\u0644\u0633\u064a\u062f"
    ],
    "wof:name":"Bayt as Sayyid",
    "wof:placetype":"locality"
},
  "geometry": {"coordinates":[44.07406,16.40993],"type":"Point"}
}