{
  "type": "Feature",
  "properties": {
    "gn:admin1_code":"23.0",
    "gn:admin2_code":"1106.0",
    "gn:asciiname":"Al Hajar",
    "gn:country_code":"YE",
    "gn:dem":2463,
    "gn:feature_class":"P",
    "gn:feature_code":"PPL",
    "gn:name":"Al Hajar",
    "gn:population":0,
    "gn:timezone":"Asia/Aden",
    "iso:country":"YE",
    "name:ara_x_preferred":[
        "\u0627\u0644\u0647\u062c\u0631"
    ],
    "name:ceb_x_preferred":[
        "Al Hajar"
    ],
    "wof:name":"Al Hajar",
    "wof:placetype":"locality"
},
  "geometry": {"coordinates":[44.35261,14.13866],"type":"Point"}
}