{
  "type": "Feature",
  "properties": {
    "gn:admin1_code":"15.0",
    "gn:admin2_code":"2206.0",
    "gn:asciiname":"Shughathi",
    "gn:country_code":"YE",
    "gn:dem":879,
    "gn:feature_class":"P",
    "gn:feature_code":"PPL",
    "gn:name":"Shugh\u0101th\u012b",
    "gn:population":0,
    "gn:timezone":"Asia/Aden",
    "iso:country":"YE",
    "name:ara_x_preferred":[
        "Shugh\u0101th\u012b"
    ],
    "name:ara_x_variant":[
        "\u0634\u063a\u0627\u062b\u064a"
    ],
    "wof:name":"Shughathi",
    "wof:placetype":"locality"
},
  "geometry": {"coordinates":[43.17423,16.91432],"type":"Point"}
}