{
  "type": "Feature",
  "properties": {
    "gn:admin1_code":"19.0",
    "gn:admin2_code":"2901.0",
    "gn:asciiname":"Gha'ibah",
    "gn:country_code":"YE",
    "gn:dem":1638,
    "gn:feature_class":"P",
    "gn:feature_code":"PPL",
    "gn:name":"Gh\u0101\u2019ibah",
    "gn:population":0,
    "gn:timezone":"Asia/Aden",
    "iso:country":"YE",
    "name:ara_x_preferred":[
        "\u063a\u0627\u0626\u0628\u0629"
    ],
    "name:und_x_variant":[
        "Gh\u0101\u2019ibah"
    ],
    "wof:name":"Gha'ibah",
    "wof:placetype":"locality"
},
  "geometry": {"coordinates":[44.03309,16.43633],"type":"Point"}
}