{
  "type": "Feature",
  "properties": {
    "gn:admin1_code":"8.0",
    "gn:admin2_code":"1810.0",
    "gn:asciiname":"Al `Asalah",
    "gn:country_code":"YE",
    "gn:dem":87,
    "gn:feature_class":"P",
    "gn:feature_code":"PPL",
    "gn:name":"Al \u2018Asalah",
    "gn:population":0,
    "gn:timezone":"Asia/Aden",
    "iso:country":"YE",
    "name:und_x_variant":[
        "Al \u2018Asalah"
    ],
    "wof:name":"Al `Asalah",
    "wof:placetype":"locality"
},
  "geometry": {"coordinates":[43.10655,15.16189],"type":"Point"}
}