{
  "type": "Feature",
  "properties": {
    "gn:admin1_code":"23.0",
    "gn:admin2_code":"1102.0",
    "gn:asciiname":"Al 'Adanah",
    "gn:country_code":"YE",
    "gn:dem":1914,
    "gn:feature_class":"P",
    "gn:feature_code":"PPL",
    "gn:name":"Al \u2018Adanah",
    "gn:population":0,
    "gn:timezone":"Asia/Aden",
    "iso:country":"YE",
    "name:ara_x_preferred":[
        "\u0627\u0644\u0639\u062f\u0646\u0629"
    ],
    "name:und_x_variant":[
        "Al \u2018Adanah"
    ],
    "wof:name":"Al 'Adanah",
    "wof:placetype":"locality"
},
  "geometry": {"coordinates":[44.22832,14.31691],"type":"Point"}
}