{
  "type": "Feature",
  "properties": {
    "gn:admin1_code":"8.0",
    "gn:admin2_code":"1812.0",
    "gn:asciiname":"Az Zahrah",
    "gn:country_code":"YE",
    "gn:dem":1279,
    "gn:feature_class":"P",
    "gn:feature_code":"PPLL",
    "gn:name":"Az\u0327 Z\u0327ahrah",
    "gn:population":0,
    "gn:timezone":"Asia/Aden",
    "iso:country":"YE",
    "name:ara_x_preferred":[
        "\u0627\u0644\u0638\u0647\u0631\u0629"
    ],
    "name:ara_x_variant":[
        "\u0638\u0647\u0631\u0629 \u062f\u0648\u0628\u0639"
    ],
    "name:und_x_variant":[
        "Az\u0327 Z\u0327ahrah",
        "Z\u0327ahrat Duway\u2018"
    ],
    "wof:name":"Az Zahrah",
    "wof:placetype":"locality"
},
  "geometry": {"coordinates":[43.47819000000001,14.91089],"type":"Point"}
}