{
  "type": "Feature",
  "properties": {
    "gn:admin1_code":"25.0",
    "gn:admin2_code":"1511.0",
    "gn:asciiname":"Al Marzuh",
    "gn:country_code":"YE",
    "gn:dem":1968,
    "gn:feature_class":"P",
    "gn:feature_code":"PPL",
    "gn:name":"Al Marz\u016b\u1e29",
    "gn:population":0,
    "gn:timezone":"Asia/Aden",
    "iso:country":"YE",
    "name:und_x_variant":[
        "Al Marz\u016b\u1e29"
    ],
    "wof:name":"Al Marzuh",
    "wof:placetype":"locality"
},
  "geometry": {"coordinates":[44.02984,13.55056],"type":"Point"}
}