{
  "type": "Feature",
  "properties": {
    "gn:admin1_code":"22.0",
    "gn:admin2_code":"1713.0",
    "gn:asciiname":"Daymat al Kadhi",
    "gn:country_code":"YE",
    "gn:dem":432,
    "gn:feature_class":"P",
    "gn:feature_code":"PPL",
    "gn:name":"Daymat al K\u0101dh\u012b",
    "gn:population":0,
    "gn:timezone":"Asia/Aden",
    "iso:country":"YE",
    "name:und_x_variant":[
        "Daymat al K\u0101dh\u012b"
    ],
    "wof:name":"Daymat al Kadhi",
    "wof:placetype":"locality"
},
  "geometry": {"coordinates":[43.33375,15.90181],"type":"Point"}
}