{
  "type": "Feature",
  "properties": {
    "gn:country":"YE",
    "gn:fcode":"PPL",
    "gn:pop":8,
    "iso:country":"YE",
    "name:ara_x_preferred":[
        "\u0630\u0631\u0627\u0639 \u0627\u0644\u0628\u0627\u0635\u0645"
    ],
    "name:eng_x_preferred":[
        "Dhira' Al Basim"
    ],
    "name:eng_x_variant":[
        "Khar\u0101b al \u1e28aj\u012b"
    ],
    "qs:name":"Dhir\u0101\u2018 al B\u0101\u015fim",
    "qs:photos_9r":0,
    "qs:photos_sr":0,
    "qs:pop_sr":"1",
    "wof:name":"Dhir\u0101\u2018 al B\u0101\u015fim",
    "wof:placetype":"locality",
    "wof:population":8
},
  "geometry": {"coordinates":[43.21148,17.17118],"type":"Point"}
}