{
  "type": "Feature",
  "properties": {
    "gn:admin1_code":"16.0",
    "gn:admin2_code":"2313.0",
    "gn:asciiname":"Adh Dhira`",
    "gn:country_code":"YE",
    "gn:dem":2641,
    "gn:feature_class":"P",
    "gn:feature_code":"PPL",
    "gn:name":"Adh Dhir\u0101\u2018",
    "gn:population":0,
    "gn:timezone":"Asia/Aden",
    "iso:country":"YE",
    "name:ara_x_preferred":[
        "Adh Dhir\u0101\u2018"
    ],
    "name:ara_x_variant":[
        "\u0627\u0644\u0630\u0631\u0627\u0639"
    ],
    "wof:name":"Adh Dhira`",
    "wof:placetype":"locality"
},
  "geometry": {"coordinates":[44.52194,15.34844],"type":"Point"}
}