{
  "type": "Feature",
  "properties": {
    "gn:admin1_code":"22.0",
    "gn:admin2_code":"1718.0",
    "gn:asciiname":"Mahall `Awad",
    "gn:country_code":"YE",
    "gn:dem":1429,
    "gn:feature_class":"P",
    "gn:feature_code":"PPL",
    "gn:name":"Ma\u1e29all \u2018Aw\u0101\u1e11",
    "gn:population":0,
    "gn:timezone":"Asia/Aden",
    "iso:country":"YE",
    "name:und_x_variant":[
        "Ma\u1e29all \u2018Aw\u0101\u1e11"
    ],
    "wof:name":"Mahall `Awad",
    "wof:placetype":"locality"
},
  "geometry": {"coordinates":[43.65359,15.79464],"type":"Point"}
}