{
  "type": "Feature",
  "properties": {
    "gn:admin1_code":"8.0",
    "gn:admin2_code":"1817.0",
    "gn:asciiname":"Al 'Alawiyah",
    "gn:country_code":"YE",
    "gn:dem":136,
    "gn:feature_class":"P",
    "gn:feature_code":"PPL",
    "gn:name":"Al \u2018Al\u0101w\u012byah",
    "gn:population":0,
    "gn:timezone":"Asia/Aden",
    "iso:country":"YE",
    "name:ara_x_preferred":[
        "\u0627\u0644\u0639\u0644\u0627\u0648\u064a\u0629"
    ],
    "name:und_x_variant":[
        "Al \u2018Al\u0101w\u012byah"
    ],
    "wof:name":"Al 'Alawiyah",
    "wof:placetype":"locality"
},
  "geometry": {"coordinates":[43.3334,14.52265],"type":"Point"}
}