{
  "type": "Feature",
  "properties": {
    "gn:admin1_code":"8.0",
    "gn:admin2_code":"1812.0",
    "gn:asciiname":"Khasib",
    "gn:country_code":"YE",
    "gn:dem":1332,
    "gn:feature_class":"P",
    "gn:feature_code":"PPL",
    "gn:name":"Kha\u015f\u012bb",
    "gn:population":0,
    "gn:timezone":"Asia/Aden",
    "iso:country":"YE",
    "name:ara_x_preferred":[
        "\u062e\u0635\u064a\u0628"
    ],
    "name:und_x_variant":[
        "Kha\u015f\u012bb"
    ],
    "wof:name":"Khasib",
    "wof:placetype":"locality"
},
  "geometry": {"coordinates":[43.43754000000001,14.90273],"type":"Point"}
}