{
  "type": "Feature",
  "properties": {
    "gn:admin1_code":"19.0",
    "gn:admin2_code":"2912.0",
    "gn:asciiname":"Al Lumi",
    "gn:country_code":"YE",
    "gn:dem":2578,
    "gn:feature_class":"P",
    "gn:feature_code":"PPL",
    "gn:name":"Al L\u016bm\u012b",
    "gn:population":0,
    "gn:timezone":"Asia/Aden",
    "iso:country":"YE",
    "name:ara_x_preferred":[
        "Al L\u016bm\u012b"
    ],
    "name:und_x_variant":[
        "L\u016bm\u012b"
    ],
    "wof:name":"Al Lumi",
    "wof:placetype":"locality"
},
  "geometry": {"coordinates":[43.89894,15.837],"type":"Point"}
}