{
  "type": "Feature",
  "properties": {
    "gn:country":"YE",
    "gn:fcode":"PPL",
    "gn:pop":5,
    "iso:country":"YE",
    "name:ara_x_preferred":[
        "Al Min\u0101ki\u2018"
    ],
    "name:ara_x_variant":[
        "\u0627\u0644\u0645\u0646\u0627\u0643\u0639"
    ],
    "name:eng_x_preferred":[
        "Al Minaki'"
    ],
    "name:eng_x_variant":[
        "\u0100l A\u1e29mad"
    ],
    "qs:name":"Al Min\u0101ki\u2018",
    "qs:photos_9r":0,
    "qs:photos_sr":0,
    "qs:pop_sr":"1",
    "wof:name":"Al Min\u0101ki\u2018",
    "wof:placetype":"locality",
    "wof:population":5
},
  "geometry": {"coordinates":[43.61544,16.01277],"type":"Point"}
}