{
  "type": "Feature",
  "properties": {
    "gn:country":"YE",
    "gn:fcode":"PPL",
    "gn:pop":8,
    "iso:country":"YE",
    "name:ara_x_preferred":[
        "\u0627\u0644\u0645\u062c\u0631\u0628"
    ],
    "qs:name":"Al Majrib",
    "qs:photos_9r":0,
    "qs:photos_sr":0,
    "qs:pop_sr":"1",
    "wof:name":"Al Majrib",
    "wof:placetype":"locality",
    "wof:population":8
},
  "geometry": {"coordinates":[43.34883,16.15483],"type":"Point"}
}