{
  "type": "Feature",
  "properties": {
    "gn:admin1_code":"14.0",
    "gn:admin2_code":"2606.0",
    "gn:asciiname":"Al Mihramah",
    "gn:country_code":"YE",
    "gn:dem":1532,
    "gn:feature_class":"P",
    "gn:feature_code":"PPL",
    "gn:name":"Al Mihr\u0101mah",
    "gn:population":0,
    "gn:timezone":"Asia/Aden",
    "iso:country":"YE",
    "name:ara_x_preferred":[
        "\u0627\u0644\u0645\u0647\u0631\u0627\u0645\u0629"
    ],
    "name:und_x_variant":[
        "Al Mihr\u0101mah"
    ],
    "wof:name":"Al Mihramah",
    "wof:placetype":"locality"
},
  "geometry": {"coordinates":[44.76958,15.50626],"type":"Point"}
}