{
  "type": "Feature",
  "properties": {
    "gn:admin1_code":"18.0",
    "gn:admin2_code":"3002.0",
    "gn:asciiname":"Qidah",
    "gn:country_code":"YE",
    "gn:dem":2482,
    "gn:feature_class":"P",
    "gn:feature_code":"PPL",
    "gn:name":"Qi\u1e11ah",
    "gn:population":0,
    "gn:timezone":"Asia/Aden",
    "iso:country":"YE",
    "name:und_x_variant":[
        "Qi\u1e11ah"
    ],
    "wof:name":"Qidah",
    "wof:placetype":"locality"
},
  "geometry": {"coordinates":[44.63789000000001,14.0374],"type":"Point"}
}