{
  "type": "Feature",
  "properties": {
    "gn:country":"YE",
    "gn:fcode":"PPL",
    "gn:population":3,
    "iso:country":"YE",
    "name:ara_x_preferred":[
        "\u0639\u0628\u062f\u0627\u0646\u0629"
    ],
    "name:eng_x_preferred":[
        "Abdanah"
    ],
    "name:eng_x_variant":[
        "\u2018Ash\u0101n",
        "'Abdanah"
    ],
    "qs:name":"\u2018Abd\u0101nah",
    "qs:photos_9r":0,
    "qs:photos_sr":0,
    "qs:pop_sr":"1",
    "wof:name":"\u2018Abd\u0101nah",
    "wof:placetype":"locality",
    "wof:population":3
},
  "geometry": {"coordinates":[44.29214,16.50217],"type":"Point"}
}