{
  "type": "Feature",
  "properties": {
    "gn:admin1_code":"16.0",
    "gn:admin2_code":"2313.0",
    "gn:asciiname":"Al Ghumalah",
    "gn:country_code":"YE",
    "gn:dem":2676,
    "gn:feature_class":"P",
    "gn:feature_code":"PPL",
    "gn:name":"Al Ghum\u0101lah",
    "gn:population":0,
    "gn:timezone":"Asia/Aden",
    "iso:country":"YE",
    "name:und_x_variant":[
        "Al Ghum\u0101lah"
    ],
    "wof:name":"Al Ghumalah",
    "wof:placetype":"locality"
},
  "geometry": {"coordinates":[44.65836,15.36233],"type":"Point"}
}