{
  "type": "Feature",
  "properties": {
    "gn:country":"YE",
    "gn:fcode":"PPL",
    "gn:pop":1,
    "iso:country":"YE",
    "name:ara_x_preferred":[
        "Al Juw\u0101r"
    ],
    "name:ara_x_variant":[
        "\u0627\u0644\u062c\u0648\u0627\u0631"
    ],
    "name:eng_x_preferred":[
        "Al Juwar"
    ],
    "qs:name":"Al Juw\u0101r",
    "qs:photos_9r":0,
    "qs:photos_sr":0,
    "qs:pop_sr":"1",
    "wof:name":"Al Juw\u0101r",
    "wof:placetype":"locality",
    "wof:population":1
},
  "geometry": {"coordinates":[45.14759,14.67548],"type":"Point"}
}