{
  "type": "Feature",
  "properties": {
    "gn:country":"YE",
    "gn:fcode":"PPL",
    "gn:population":26,
    "iso:country":"YE",
    "name:ara_x_preferred":[
        "\u0627\u0644\u0645\u0632\u062d\u0627\u062c\u0629"
    ],
    "name:eng_x_preferred":[
        "Al Mazhajah"
    ],
    "name:eng_x_variant":[
        "Al Qarn\u012b"
    ],
    "qs:name":"Al Maz\u1e29\u0101jah",
    "qs:photos_9r":0,
    "qs:photos_sr":0,
    "qs:pop_sr":"1",
    "wof:name":"Al Maz\u1e29\u0101jah",
    "wof:placetype":"locality",
    "wof:population":26
},
  "geometry": {"coordinates":[43.76057,13.30066],"type":"Point"}
}