{
  "type": "Feature",
  "properties": {
    "gn:country":"YE",
    "gn:fcode":"PPL",
    "gn:population":2,
    "iso:country":"YE",
    "name:ara_x_preferred":[
        "\u0627\u0644\u0645\u062c\u0627\u0631\u064a\u0646"
    ],
    "qs:name":"Al Maj\u0101r\u012bn",
    "qs:photos_9r":0,
    "qs:photos_sr":0,
    "qs:pop_sr":"1",
    "wof:name":"Al Maj\u0101r\u012bn",
    "wof:placetype":"locality",
    "wof:population":2
},
  "geometry": {"coordinates":[43.4708,16.12895],"type":"Point"}
}