{
  "type": "Feature",
  "properties": {
    "gn:admin1_code":"14.0",
    "gn:admin2_code":"2610.0",
    "gn:asciiname":"Al `Arsh",
    "gn:country_code":"YE",
    "gn:dem":1872,
    "gn:feature_class":"P",
    "gn:feature_code":"PPL",
    "gn:name":"Al \u2018Arsh",
    "gn:population":0,
    "gn:timezone":"Asia/Aden",
    "iso:country":"YE",
    "name:ara_x_preferred":[
        "Al \u2018Ursh"
    ],
    "name:ara_x_variant":[
        "\u0627\u0644\u0639\u0631\u0634"
    ],
    "name:und_x_variant":[
        "Al \u2018Arsh"
    ],
    "wof:name":"Al `Arsh",
    "wof:placetype":"locality"
},
  "geometry": {"coordinates":[45.18361,14.59571],"type":"Point"}
}