{
  "type": "Feature",
  "properties": {
    "gn:admin1_code":"8.0",
    "gn:admin2_code":"1810.0",
    "gn:asciiname":"Quzayh",
    "gn:country_code":"YE",
    "gn:dem":93,
    "gn:feature_class":"P",
    "gn:feature_code":"PPL",
    "gn:name":"Quzay\u1e29",
    "gn:population":0,
    "gn:timezone":"Asia/Aden",
    "iso:country":"YE",
    "name:ara_x_preferred":[
        "\u0642\u0632\u064a\u062d"
    ],
    "name:und_x_variant":[
        "Quzay\u1e29"
    ],
    "wof:name":"Quzayh",
    "wof:placetype":"locality"
},
  "geometry": {"coordinates":[43.11736,15.14781],"type":"Point"}
}