{
  "type": "Feature",
  "properties": {
    "gn:admin1_code":"8.0",
    "gn:admin2_code":"1801.0",
    "gn:asciiname":"Al Qal`ah as Saghirah",
    "gn:country_code":"YE",
    "gn:dem":195,
    "gn:feature_class":"P",
    "gn:feature_code":"PPL",
    "gn:name":"Al Qal\u2018ah a\u015f \u015eagh\u012brah",
    "gn:population":0,
    "gn:timezone":"Asia/Aden",
    "iso:country":"YE",
    "name:und_x_variant":[
        "Al Qal\u2018ah a\u015f \u015eagh\u012brah"
    ],
    "wof:name":"Al Qal`ah as Saghirah",
    "wof:placetype":"locality"
},
  "geometry": {"coordinates":[43.227,15.77885],"type":"Point"}
}