{
  "type": "Feature",
  "properties": {
    "gn:admin1_code":"19.0",
    "gn:admin2_code":"2906.0",
    "gn:asciiname":"As Sayah",
    "gn:country_code":"YE",
    "gn:dem":1343,
    "gn:feature_class":"P",
    "gn:feature_code":"PPL",
    "gn:name":"A\u015f \u015e\u0101yah",
    "gn:population":0,
    "gn:timezone":"Asia/Aden",
    "iso:country":"YE",
    "name:ara_x_preferred":[
        "\u0627\u0644\u0635\u0627\u064a\u0629"
    ],
    "name:und_x_variant":[
        "A\u015f \u015e\u0101yah"
    ],
    "wof:name":"As Sayah",
    "wof:placetype":"locality"
},
  "geometry": {"coordinates":[43.61771,16.20644],"type":"Point"}
}