{
  "type": "Feature",
  "properties": {
    "gn:admin1_code":"22.0",
    "gn:admin2_code":"1711.0",
    "gn:asciiname":"Mahall al Karif",
    "gn:country_code":"YE",
    "gn:dem":390,
    "gn:feature_class":"P",
    "gn:feature_code":"PPL",
    "gn:name":"Ma\u1e29all al Kar\u012bf",
    "gn:population":0,
    "gn:timezone":"Asia/Aden",
    "iso:country":"YE",
    "name:und_x_variant":[
        "Ma\u1e29all al Kar\u012bf"
    ],
    "wof:name":"Mahall al Karif",
    "wof:placetype":"locality"
},
  "geometry": {"coordinates":[43.35513,15.96914],"type":"Point"}
}