{
  "type": "Feature",
  "properties": {
    "gn:admin1_code":"22.0",
    "gn:admin2_code":"1725.0",
    "gn:asciiname":"Al Hijrah",
    "gn:country_code":"YE",
    "gn:dem":677,
    "gn:feature_class":"P",
    "gn:feature_code":"PPL",
    "gn:name":"Al Hijrah",
    "gn:population":0,
    "gn:timezone":"Asia/Aden",
    "iso:country":"YE",
    "name:ara_x_preferred":[
        "\u0627\u0644\u0647\u062c\u0631\u0629"
    ],
    "wof:name":"Al Hijrah",
    "wof:placetype":"locality"
},
  "geometry": {"coordinates":[43.50063,15.56841],"type":"Point"}
}