{
  "type": "Feature",
  "properties": {
    "gn:admin1_code":"16.0",
    "gn:admin2_code":"2302.0",
    "gn:asciiname":"Qaryat al Bayda'",
    "gn:country_code":"YE",
    "gn:dem":2704,
    "gn:feature_class":"P",
    "gn:feature_code":"PPL",
    "gn:name":"Qaryat al Bay\u1e11\u0101\u2019",
    "gn:population":0,
    "gn:timezone":"Asia/Aden",
    "iso:country":"YE",
    "name:ara_x_preferred":[
        "\u0642\u0631\u064a\u0629 \u0627\u0644\u0628\u064a\u0636\u0627\u0621"
    ],
    "name:und_x_variant":[
        "Qaryat al Bay\u1e11\u0101\u2019"
    ],
    "wof:name":"Qaryat al Bayda'",
    "wof:placetype":"locality"
},
  "geometry": {"coordinates":[44.18599,15.76952],"type":"Point"}
}