{
  "type": "Feature",
  "properties": {
    "gn:admin1_code":"25.0",
    "gn:admin2_code":"1515.0",
    "gn:asciiname":"Al Mi'saqah",
    "gn:country_code":"YE",
    "gn:dem":2113,
    "gn:feature_class":"P",
    "gn:feature_code":"PPL",
    "gn:name":"Al Mi\u2018s\u0101qah",
    "gn:population":0,
    "gn:timezone":"Asia/Aden",
    "iso:country":"YE",
    "name:ara_x_preferred":[
        "\u0627\u0644\u0645\u0639\u0633\u0627\u0642\u0629"
    ],
    "name:und_x_variant":[
        "Al Mi\u2018s\u0101qah"
    ],
    "wof:name":"Al Mi'saqah",
    "wof:placetype":"locality"
},
  "geometry": {"coordinates":[44.16606,13.22629],"type":"Point"}
}