{
  "type": "Feature",
  "properties": {
    "gn:admin1_code":"8.0",
    "gn:admin2_code":"1816.0",
    "gn:asciiname":"Al Asfal",
    "gn:country_code":"YE",
    "gn:dem":167,
    "gn:feature_class":"P",
    "gn:feature_code":"PPL",
    "gn:name":"Al Asfal",
    "gn:population":0,
    "gn:timezone":"Asia/Aden",
    "iso:country":"YE",
    "name:ara_x_preferred":[
        "\u0627\u0644\u0627\u0633\u0641\u0644"
    ],
    "name:und_x_variant":[
        "Al Ma\u1e29j\u016br",
        "Al Asfal"
    ],
    "wof:name":"Al Asfal",
    "wof:placetype":"locality"
},
  "geometry": {"coordinates":[43.3929,14.69914],"type":"Point"}
}