{
  "type": "Feature",
  "properties": {
    "gn:admin1_code":"5.0",
    "gn:admin2_code":"2107.0",
    "gn:asciiname":"As Salil",
    "gn:country_code":"YE",
    "gn:dem":1164,
    "gn:elevation":"2.0",
    "gn:feature_class":"P",
    "gn:feature_code":"PPL",
    "gn:name":"As Sal\u012bl",
    "gn:population":0,
    "gn:timezone":"Asia/Aden",
    "iso:country":"YE",
    "name:und_x_variant":[
        "Al Sal\u012bl",
        "As Sal\u012bl"
    ],
    "wof:name":"As Salil",
    "wof:placetype":"locality"
},
  "geometry": {"coordinates":[45.68035,14.7814],"type":"Point"}
}