{
  "type": "Feature",
  "properties": {
    "gn:admin1_code":"23.0",
    "gn:admin2_code":"1101.0",
    "gn:asciiname":"Ash Shahz",
    "gn:country_code":"YE",
    "gn:dem":1448,
    "gn:feature_class":"P",
    "gn:feature_code":"PPL",
    "gn:name":"Ash Shahz",
    "gn:population":0,
    "gn:timezone":"Asia/Aden",
    "iso:country":"YE",
    "name:ara_x_preferred":[
        "\u0627\u0644\u0634\u0647\u0632"
    ],
    "wof:name":"Ash Shahz",
    "wof:placetype":"locality"
},
  "geometry": {"coordinates":[44.14443,14.29683],"type":"Point"}
}