{
  "type": "Feature",
  "properties": {
    "gn:admin1_code":"11.0",
    "gn:admin2_code":"2004.0",
    "gn:asciiname":"Dhanaban",
    "gn:country_code":"YE",
    "gn:dem":2537,
    "gn:feature_class":"P",
    "gn:feature_code":"PPL",
    "gn:name":"Dhanab\u0101n",
    "gn:population":0,
    "gn:timezone":"Asia/Aden",
    "iso:country":"YE",
    "name:und_x_variant":[
        "Dhanab\u0101n"
    ],
    "wof:name":"Dhanaban",
    "wof:placetype":"locality"
},
  "geometry": {"coordinates":[44.1343,14.51632],"type":"Point"}
}