{
  "type": "Feature",
  "properties": {
    "gn:country":"YE",
    "gn:fcode":"PPL",
    "gn:pop":17,
    "iso:country":"YE",
    "name:ara_x_preferred":[
        "Al Bir\u0101n"
    ],
    "name:ara_x_variant":[
        "\u0627\u0644\u0628\u0631\u0627\u0646"
    ],
    "name:eng_x_preferred":[
        "Al Biran"
    ],
    "name:eng_x_variant":[
        "Dh\u016b M\u0101\u0163ir"
    ],
    "qs:name":"Al Bir\u0101n",
    "qs:photos_9r":0,
    "qs:photos_sr":0,
    "qs:pop_sr":"1",
    "wof:name":"Al Bir\u0101n",
    "wof:placetype":"locality",
    "wof:population":17
},
  "geometry": {"coordinates":[43.5732,16.37875],"type":"Point"}
}