{
  "type": "Feature",
  "properties": {
    "gn:admin1_code":"25.0",
    "gn:admin2_code":"1501.0",
    "gn:asciiname":"Habil az Zubay`ah",
    "gn:country_code":"YE",
    "gn:dem":1353,
    "gn:feature_class":"P",
    "gn:feature_code":"PPL",
    "gn:name":"\u1e28ab\u012bl az\u0327 Z\u0327ubay\u2018ah",
    "gn:population":0,
    "gn:timezone":"Asia/Aden",
    "iso:country":"YE",
    "name:und_x_variant":[
        "\u1e28ab\u012bl az\u0327 Z\u0327ubay\u2018ah",
        "D\u0101r al \u1e28\u012bl"
    ],
    "wof:name":"Habil az Zubay`ah",
    "wof:placetype":"locality"
},
  "geometry": {"coordinates":[44.33515,13.61839],"type":"Point"}
}