{
  "type": "Feature",
  "properties": {
    "gn:admin1_code":"25.0",
    "gn:admin2_code":"1511.0",
    "gn:asciiname":"Adud",
    "gn:country_code":"YE",
    "gn:dem":1912,
    "gn:feature_class":"P",
    "gn:feature_code":"PPL",
    "gn:name":"Ad\u016bd",
    "gn:population":0,
    "gn:timezone":"Asia/Aden",
    "iso:country":"YE",
    "name:ara_x_preferred":[
        "Ad\u016bd"
    ],
    "wof:name":"Adud",
    "wof:placetype":"locality"
},
  "geometry": {"coordinates":[43.98087,13.54762],"type":"Point"}
}