{
  "type": "Feature",
  "properties": {
    "gn:admin1_code":"11.0",
    "gn:admin2_code":"2005.0",
    "gn:asciiname":"Al Matamir",
    "gn:country_code":"YE",
    "gn:dem":1714,
    "gn:feature_class":"P",
    "gn:feature_code":"PPL",
    "gn:name":"Al Ma\u0163\u0101mir",
    "gn:population":0,
    "gn:timezone":"Asia/Aden",
    "iso:country":"YE",
    "name:und_x_variant":[
        "Al Ma\u0163\u0101mir"
    ],
    "wof:name":"Al Matamir",
    "wof:placetype":"locality"
},
  "geometry": {"coordinates":[44.00569,14.45309],"type":"Point"}
}