{
  "type": "Feature",
  "properties": {
    "gn:admin1_code":"5.0",
    "gn:admin2_code":"2112.0",
    "gn:asciiname":"Al Kawrah",
    "gn:country_code":"YE",
    "gn:dem":1205,
    "gn:feature_class":"P",
    "gn:feature_code":"PPL",
    "gn:name":"Al Kawrah",
    "gn:population":0,
    "gn:timezone":"Asia/Aden",
    "iso:country":"YE",
    "name:und_x_variant":[
        "Kaula",
        "Al Kaura",
        "Al Kawrah"
    ],
    "wof:name":"Al Kawrah",
    "wof:placetype":"locality"
},
  "geometry": {"coordinates":[46.9343,14.30352],"type":"Point"}
}