{
  "type": "Feature",
  "properties": {
    "gn:admin1_code":"20.0",
    "gn:admin2_code":"1408.0",
    "gn:asciiname":"Karish",
    "gn:country_code":"YE",
    "gn:dem":2249,
    "gn:feature_class":"P",
    "gn:feature_code":"PPL",
    "gn:name":"Kar\u012bsh",
    "gn:population":0,
    "gn:timezone":"Asia/Aden",
    "iso:country":"YE",
    "name:und_x_variant":[
        "Kar\u012bsh"
    ],
    "wof:name":"Karish",
    "wof:placetype":"locality"
},
  "geometry": {"coordinates":[45.76301,13.98083],"type":"Point"}
}