{
  "type": "Feature",
  "properties": {
    "gn:admin1_code":"5.0",
    "gn:admin2_code":"2112.0",
    "gn:asciiname":"Wadi mama",
    "gn:country_code":"YE",
    "gn:dem":1343,
    "gn:elevation":"1300.0",
    "gn:feature_class":"P",
    "gn:feature_code":"PPL",
    "gn:name":"Wadi m\u0101m\u0101",
    "gn:population":0,
    "gn:timezone":"Asia/Aden",
    "iso:country":"YE",
    "name:ara_x_colloquial":[
        "\u0648\u0627\u062f\u064a \u0645\u0639\u0645\u0639"
    ],
    "name:ara_x_historical":[
        "\u0648\u0627\u062f\u064a \u0645\u0639\u0645\u0639"
    ],
    "name:ara_x_preferred":[
        "\u0648\u0627\u062f\u064a \u0645\u0639\u0645\u0639"
    ],
    "wof:name":"Wadi mama",
    "wof:placetype":"locality"
},
  "geometry": {"coordinates":[46.73811,14.31616],"type":"Point"}
}