{
  "type": "Feature",
  "properties": {
    "gn:admin1_code":"16.0",
    "gn:admin2_code":"2302.0",
    "gn:asciiname":"Sirwan",
    "gn:country_code":"YE",
    "gn:dem":2161,
    "gn:feature_class":"P",
    "gn:feature_code":"PPL",
    "gn:name":"\u015eirw\u0101n",
    "gn:population":0,
    "gn:timezone":"Asia/Aden",
    "iso:country":"YE",
    "name:ara_x_preferred":[
        "\u015eirw\u0101n"
    ],
    "wof:name":"Sirwan",
    "wof:placetype":"locality"
},
  "geometry": {"coordinates":[44.35,15.88333],"type":"Point"}
}