{
  "type": "Feature",
  "properties": {
    "gn:admin1_code":"22.0",
    "gn:admin2_code":"1725.0",
    "gn:asciiname":"Tarab Zahir",
    "gn:country_code":"YE",
    "gn:dem":726,
    "gn:feature_class":"P",
    "gn:feature_code":"PPL",
    "gn:name":"\u0162ar\u0101b Z\u0101hir",
    "gn:population":0,
    "gn:timezone":"Asia/Aden",
    "iso:country":"YE",
    "name:ara_x_preferred":[
        "\u0637\u0631\u0627\u0628 \u0632\u0627\u0647\u0640\u0631"
    ],
    "name:und_x_variant":[
        "\u0162ar\u0101b Z\u0101hir"
    ],
    "wof:name":"Tarab Zahir",
    "wof:placetype":"locality"
},
  "geometry": {"coordinates":[43.52732,15.56463],"type":"Point"}
}