{
  "type": "Feature",
  "properties": {
    "gn:admin1_code":"8.0",
    "gn:admin2_code":"1808.0",
    "gn:asciiname":"Mahsin al Baydani",
    "gn:country_code":"YE",
    "gn:dem":164,
    "gn:feature_class":"P",
    "gn:feature_code":"PPL",
    "gn:name":"Ma\u1e29sin al Bay\u1e11\u0101n\u012b",
    "gn:population":0,
    "gn:timezone":"Asia/Aden",
    "iso:country":"YE",
    "name:ara_x_preferred":[
        "\u0645\u062d\u0633\u0646 \u0627\u0644\u0628\u064a\u0636\u0627\u0646\u064a"
    ],
    "name:und_x_variant":[
        "Ma\u1e29sin al Bay\u1e11\u0101n\u012b"
    ],
    "wof:name":"Mahsin al Baydani",
    "wof:placetype":"locality"
},
  "geometry": {"coordinates":[43.2469,15.28155],"type":"Point"}
}