{
  "type": "Feature",
  "properties": {
    "gn:admin1_code":"10.0",
    "gn:admin2_code":"2707.0",
    "gn:asciiname":"Malihah",
    "gn:country_code":"YE",
    "gn:dem":1056,
    "gn:feature_class":"P",
    "gn:feature_code":"PPL",
    "gn:name":"M\u0101li\u1e29ah",
    "gn:population":0,
    "gn:timezone":"Asia/Aden",
    "iso:country":"YE",
    "name:und_x_variant":[
        "M\u0101li\u1e29ah"
    ],
    "wof:name":"Malihah",
    "wof:placetype":"locality"
},
  "geometry": {"coordinates":[43.52443,15.35946],"type":"Point"}
}