{
  "type": "Feature",
  "properties": {
    "gn:admin1_code":"23.0",
    "gn:admin2_code":"1102.0",
    "gn:asciiname":"Salami",
    "gn:cc2":"YE",
    "gn:country_code":"YE",
    "gn:dem":2924,
    "gn:feature_class":"P",
    "gn:feature_code":"PPL",
    "gn:name":"Sal\u0101m\u012b",
    "gn:population":0,
    "gn:timezone":"Asia/Aden",
    "iso:country":"YE",
    "name:afr_x_preferred":[
        "Salami"
    ],
    "name:ara_x_preferred":[
        "\u0633\u0644\u0627\u0645\u064a"
    ],
    "name:bar_x_preferred":[
        "Edlwuascht"
    ],
    "name:bel_x_preferred":[
        "\u0421\u0430\u043b\u044f\u043c\u0456"
    ],
    "name:bre_x_preferred":[
        "Salami"
    ],
    "name:bul_x_preferred":[
        "\u0421\u0430\u043b\u0430\u043c"
    ],
    "name:cat_x_preferred":[
        "Salami"
    ],
    "name:ces_x_preferred":[
        "Sal\u00e1m"
    ],
    "name:cos_x_preferred":[
        "Salamu"
    ],
    "name:dan_x_preferred":[
        "Salami"
    ],
    "name:deu_x_preferred":[
        "Salami"
    ],
    "name:ell_x_preferred":[
        "\u03a3\u03b1\u03bb\u03ac\u03bc\u03b9"
    ],
    "name:epo_x_preferred":[
        "Salamo"
    ],
    "name:est_x_preferred":[
        "Salaami"
    ],
    "name:eus_x_preferred":[
        "Salami"
    ],
    "name:fas_x_preferred":[
        "\u0633\u0627\u0644\u0627\u0645\u06cc"
    ],
    "name:fin_x_preferred":[
        "Salami"
    ],
    "name:fra_x_preferred":[
        "Salami"
    ],
    "name:glg_x_preferred":[
        "Salame"
    ],
    "name:heb_x_preferred":[
        "\u05e1\u05dc\u05de\u05d9"
    ],
    "name:hrv_x_preferred":[
        "Salama"
    ],
    "name:hun_x_preferred":[
        "Szal\u00e1mi"
    ],
    "name:hye_x_preferred":[
        "\u054d\u0561\u056c\u0575\u0561\u0574\u056b"
    ],
    "name:ind_x_preferred":[
        "Salami"
    ],
    "name:ita_x_preferred":[
        "Salame"
    ],
    "name:jpn_x_preferred":[
        "\u30b5\u30e9\u30df"
    ],
    "name:kat_x_preferred":[
        "\u10e1\u10d0\u10da\u10d8\u10d0\u10db\u10d8"
    ],
    "name:kaz_x_preferred":[
        "\u0421\u0430\u043b\u044f\u043c\u0438"
    ],
    "name:kor_x_preferred":[
        "\uc0b4\ub77c\ubbf8"
    ],
    "name:ltz_x_preferred":[
        "Salami"
    ],
    "name:mkd_x_preferred":[
        "\u0421\u0430\u043b\u0430\u043c\u0430"
    ],
    "name:msa_x_preferred":[
        "Salami"
    ],
    "name:nld_x_preferred":[
        "Salami"
    ],
    "name:nno_x_preferred":[
        "Salami"
    ],
    "name:nor_x_preferred":[
        "Salami"
    ],
    "name:pol_x_preferred":[
        "Salami"
    ],
    "name:por_x_preferred":[
        "Salame"
    ],
    "name:ron_x_preferred":[
        "Salam"
    ],
    "name:rus_x_preferred":[
        "\u0421\u0430\u043b\u044f\u043c\u0438"
    ],
    "name:sco_x_preferred":[
        "Salami"
    ],
    "name:spa_x_preferred":[
        "Salami"
    ],
    "name:srp_x_preferred":[
        "\u0421\u0430\u043b\u0430\u043c\u0430"
    ],
    "name:swe_x_preferred":[
        "Salami"
    ],
    "name:tgl_x_preferred":[
        "Salami"
    ],
    "name:tur_x_preferred":[
        "Salam"
    ],
    "name:ukr_x_preferred":[
        "\u0421\u0430\u043b\u044f\u043c\u0456"
    ],
    "name:und_x_variant":[
        "Selami",
        "Sal\u0101m\u012b"
    ],
    "name:urd_x_preferred":[
        "\u0633\u0627\u0644\u0627\u0645\u06cc"
    ],
    "name:vie_x_preferred":[
        "Salami"
    ],
    "name:zho_x_preferred":[
        "\u838e\u6a02\u7f8e\u8178"
    ],
    "wof:name":"Salami",
    "wof:placetype":"locality"
},
  "geometry": {"coordinates":[44.28333,14.16667],"type":"Point"}
}