{
  "type": "Feature",
  "properties": {
    "gn:admin1_code":"23.0",
    "gn:admin2_code":"1102.0",
    "gn:asciiname":"Salami",
    "gn:cc2":"YE",
    "gn:country_code":"YE",
    "gn:dem":2924,
    "gn:feature_class":"P",
    "gn:feature_code":"PPL",
    "gn:name":"Sal\u0101m\u012b",
    "gn:population":0,
    "gn:timezone":"Asia/Aden",
    "iso:country":"YE",
    "name:und_x_variant":[
        "Selami",
        "Sal\u0101m\u012b"
    ],
    "wof:name":"Salami",
    "wof:placetype":"locality"
},
  "geometry": {"coordinates":[44.28333,14.16667],"type":"Point"}
}