{
  "type": "Feature",
  "properties": {
    "gn:country":"YE",
    "gn:fcode":"PPL",
    "gn:population":4,
    "iso:country":"YE",
    "name:ara_x_preferred":[
        "\u0628\u064a\u062a \u0627\u0644\u0631\u062c\u0645"
    ],
    "name:eng_x_preferred":[
        "Bayt Ar Rujm"
    ],
    "name:eng_x_variant":[
        "A\u0163 \u0162arf"
    ],
    "qs:name":"Bayt ar Rujm",
    "qs:photos_9r":0,
    "qs:photos_sr":0,
    "qs:pop_sr":"1",
    "wof:name":"Bayt ar Rujm",
    "wof:placetype":"locality",
    "wof:population":4
},
  "geometry": {"coordinates":[43.31362,16.12905],"type":"Point"}
}