{
  "type": "Feature",
  "properties": {
    "gn:country":"YE",
    "gn:fcode":"PPL",
    "gn:population":6,
    "iso:country":"YE",
    "name:ara_x_preferred":[
        "\u062d\u0631\u0645\u0627\u0644\u0629 \u0627\u0644 \u0637\u0627\u0644\u0628"
    ],
    "name:eng_x_preferred":[
        "Harmalat Al Talib"
    ],
    "name:eng_x_variant":[
        "Shun\u012b\u2018ah"
    ],
    "qs:name":"\u1e28arm\u0101lat \u0100l \u0162\u0101lib",
    "qs:photos_9r":0,
    "qs:photos_sr":0,
    "qs:pop_sr":"1",
    "wof:name":"\u1e28arm\u0101lat \u0100l \u0162\u0101lib",
    "wof:placetype":"locality",
    "wof:population":6
},
  "geometry": {"coordinates":[45.37194,15.47305],"type":"Point"}
}