{
  "type": "Feature",
  "properties": {
    "gn:admin1_code":"19.0",
    "gn:admin2_code":"2918.0",
    "gn:asciiname":"Quhal",
    "gn:country_code":"YE",
    "gn:dem":2298,
    "gn:feature_class":"P",
    "gn:feature_code":"PPL",
    "gn:name":"Quh\u0101l",
    "gn:population":0,
    "gn:timezone":"Asia/Aden",
    "iso:country":"YE",
    "name:ara_x_preferred":[
        "Quh\u0101l"
    ],
    "wof:name":"Quhal",
    "wof:placetype":"locality"
},
  "geometry": {"coordinates":[44.01538,15.66318],"type":"Point"}
}