{
  "type": "Feature",
  "properties": {
    "gn:admin1_code":"14.0",
    "gn:admin2_code":"2604.0",
    "gn:asciiname":"Shahiq",
    "gn:cc2":"YE",
    "gn:country_code":"YE",
    "gn:dem":1935,
    "gn:feature_class":"P",
    "gn:feature_code":"PPL",
    "gn:name":"Sh\u0101hiq",
    "gn:population":0,
    "gn:timezone":"Asia/Aden",
    "iso:country":"YE",
    "name:ara_x_preferred":[
        "Sh\u0101hiq"
    ],
    "name:und_x_variant":[
        "Shahik"
    ],
    "wof:name":"Shahiq",
    "wof:placetype":"locality"
},
  "geometry": {"coordinates":[44.63333,15.43333],"type":"Point"}
}