{
  "type": "Feature",
  "properties": {
    "gn:admin1_code":"8.0",
    "gn:admin2_code":"1812.0",
    "gn:asciiname":"Ad Dawla'",
    "gn:country_code":"YE",
    "gn:dem":1617,
    "gn:feature_class":"P",
    "gn:feature_code":"PPL",
    "gn:name":"A\u1e11 \u1e10awla\u2018",
    "gn:population":0,
    "gn:timezone":"Asia/Aden",
    "iso:country":"YE",
    "name:ara_x_preferred":[
        "\u0627\u0644\u0636\u0648\u0644\u0639"
    ],
    "name:und_x_variant":[
        "A\u1e11 \u1e10awla\u2018"
    ],
    "wof:name":"Ad Dawla'",
    "wof:placetype":"locality"
},
  "geometry": {"coordinates":[43.49954,14.88378],"type":"Point"}
}