{
  "type": "Feature",
  "properties": {
    "gn:country":"YE",
    "gn:fcode":"PPL",
    "gn:population":4,
    "iso:country":"YE",
    "name:ara_x_preferred":[
        "\u0627\u0644\u0642\u0634\u0628"
    ],
    "name:und_x_variant":[
        "Al Qashab"
    ],
    "qs:name":"Al Qushab",
    "qs:photos_9r":0,
    "qs:photos_sr":0,
    "qs:pop_sr":"1",
    "wof:name":"Al Qushab",
    "wof:placetype":"locality",
    "wof:population":4
},
  "geometry": {"coordinates":[43.46044,16.3131],"type":"Point"}
}