{
  "type": "Feature",
  "properties": {
    "gn:admin1_code":"11.0",
    "gn:admin2_code":"2004.0",
    "gn:asciiname":"Hawrah",
    "gn:country_code":"YE",
    "gn:dem":2319,
    "gn:feature_class":"P",
    "gn:feature_code":"PPL",
    "gn:name":"\u1e28awrah",
    "gn:population":0,
    "gn:timezone":"Asia/Aden",
    "iso:country":"YE",
    "name:und_x_variant":[
        "\u1e28awrah"
    ],
    "wof:name":"Hawrah",
    "wof:placetype":"locality"
},
  "geometry": {"coordinates":[44.08519,14.52123],"type":"Point"}
}