{
  "type": "Feature",
  "properties": {
    "gn:admin1_code":"23.0",
    "gn:admin2_code":"1102.0",
    "gn:asciiname":"Al 'Arr",
    "gn:country_code":"YE",
    "gn:dem":1793,
    "gn:feature_class":"P",
    "gn:feature_code":"PPL",
    "gn:name":"Al \u2018Arr",
    "gn:population":0,
    "gn:timezone":"Asia/Aden",
    "iso:country":"YE",
    "name:ara_x_preferred":[
        "\u0627\u0644\u0639\u0631"
    ],
    "name:und_x_variant":[
        "Al \u2018Arr"
    ],
    "wof:name":"Al 'Arr",
    "wof:placetype":"locality"
},
  "geometry": {"coordinates":[44.22594,14.3082],"type":"Point"}
}