{
  "type": "Feature",
  "properties": {
    "gn:admin1_code":"19.0",
    "gn:admin2_code":"2912.0",
    "gn:asciiname":"Bayt Zahir",
    "gn:country_code":"YE",
    "gn:dem":2409,
    "gn:feature_class":"P",
    "gn:feature_code":"PPL",
    "gn:name":"Bayt Z\u0101hir",
    "gn:population":0,
    "gn:timezone":"Asia/Aden",
    "iso:country":"YE",
    "name:und_x_variant":[
        "Bayt Z\u0101hir"
    ],
    "wof:name":"Bayt Zahir",
    "wof:placetype":"locality"
},
  "geometry": {"coordinates":[43.8368,15.68897],"type":"Point"}
}