{
  "type": "Feature",
  "properties": {
    "gn:admin1_code":"8.0",
    "gn:admin2_code":"1812.0",
    "gn:asciiname":"Al Kibar",
    "gn:country_code":"YE",
    "gn:dem":1230,
    "gn:feature_class":"P",
    "gn:feature_code":"PPL",
    "gn:name":"Al Kib\u0101r",
    "gn:population":0,
    "gn:timezone":"Asia/Aden",
    "iso:country":"YE",
    "name:ara_x_preferred":[
        "\u0627\u0644\u0643\u0628\u0627\u0631"
    ],
    "name:und_x_variant":[
        "Al Kib\u0101r"
    ],
    "wof:name":"Al Kibar",
    "wof:placetype":"locality"
},
  "geometry": {"coordinates":[43.49606,14.93814],"type":"Point"}
}