{
  "type": "Feature",
  "properties": {
    "gn:country":"YE",
    "gn:fcode":"PPL",
    "gn:population":2,
    "iso:country":"YE",
    "name:ara_x_preferred":[
        "\u0627\u0644\u0634\u0642\u0631\u0629"
    ],
    "qs:name":"Ash Shuqrah",
    "qs:photos_9r":0,
    "qs:photos_sr":0,
    "qs:pop_sr":"1",
    "wof:name":"Ash Shuqrah",
    "wof:placetype":"locality",
    "wof:population":2
},
  "geometry": {"coordinates":[43.24705,17.23839],"type":"Point"}
}