{
  "type": "Feature",
  "properties": {
    "gn:admin1_code":"22.0",
    "gn:admin2_code":"1707.0",
    "gn:asciiname":"Al Lu'ti",
    "gn:country_code":"YE",
    "gn:dem":1555,
    "gn:feature_class":"P",
    "gn:feature_code":"PPL",
    "gn:name":"Al Lu\u2019t\u012b",
    "gn:population":0,
    "gn:timezone":"Asia/Aden",
    "iso:country":"YE",
    "name:ara_x_preferred":[
        "Al Lu\u2019t\u012b"
    ],
    "name:ara_x_variant":[
        "\u0627\u0644\u0644\u0624\u062a\u064a"
    ],
    "wof:name":"Al Lu'ti",
    "wof:placetype":"locality"
},
  "geometry": {"coordinates":[43.45616,16.21899],"type":"Point"}
}