{
  "type": "Feature",
  "properties": {
    "gn:admin1_code":"19.0",
    "gn:admin2_code":"2920.0",
    "gn:asciiname":"Al Hawarith",
    "gn:country_code":"YE",
    "gn:dem":2215,
    "gn:feature_class":"P",
    "gn:feature_code":"PPL",
    "gn:name":"Al \u1e28aw\u0101rith",
    "gn:population":0,
    "gn:timezone":"Asia/Aden",
    "iso:country":"YE",
    "name:und_x_variant":[
        "Al \u1e28aw\u0101rith"
    ],
    "wof:name":"Al Hawarith",
    "wof:placetype":"locality"
},
  "geometry": {"coordinates":[43.9338,16.09929],"type":"Point"}
}