{
  "type": "Feature",
  "properties": {
    "gn:admin1_code":"19.0",
    "gn:admin2_code":"2913.0",
    "gn:asciiname":"Bani Jaysh",
    "gn:country_code":"YE",
    "gn:dem":1806,
    "gn:feature_class":"P",
    "gn:feature_code":"PPL",
    "gn:name":"Ban\u012b Jaysh",
    "gn:population":0,
    "gn:timezone":"Asia/Aden",
    "iso:country":"YE",
    "name:und_x_variant":[
        "Ban\u012b Jaysh"
    ],
    "wof:name":"Bani Jaysh",
    "wof:placetype":"locality"
},
  "geometry": {"coordinates":[43.7749,15.94666],"type":"Point"}
}