{
  "type": "Feature",
  "properties": {
    "gn:admin1_code":"23.0",
    "gn:admin2_code":"1106.0",
    "gn:asciiname":"Dhi Hubur",
    "gn:country_code":"YE",
    "gn:dem":2919,
    "gn:feature_class":"P",
    "gn:feature_code":"PPL",
    "gn:name":"Dh\u012b Hub\u016br",
    "gn:population":0,
    "gn:timezone":"Asia/Aden",
    "iso:country":"YE",
    "name:ara_x_preferred":[
        "Dh\u012b Ahb\u016br"
    ],
    "name:ara_x_variant":[
        "\u0630\u064a \u0647\u0628\u0648\u0631"
    ],
    "name:und_x_variant":[
        "Dh\u012b Hub\u016br"
    ],
    "wof:name":"Dhi Hubur",
    "wof:placetype":"locality"
},
  "geometry": {"coordinates":[44.36444,14.10491],"type":"Point"}
}