{
  "type": "Feature",
  "properties": {
    "gn:admin1_code":"5.0",
    "gn:admin2_code":"2112.0",
    "gn:asciiname":"Hisn Al Jazi`",
    "gn:country_code":"YE",
    "gn:dem":1263,
    "gn:feature_class":"P",
    "gn:feature_code":"PPL",
    "gn:name":"\u1e28i\u015fn \u0100l J\u0101zi\u2018",
    "gn:population":0,
    "gn:timezone":"Asia/Aden",
    "iso:country":"YE",
    "name:ara_x_preferred":[
        "\u1e28i\u015fn \u0100l J\u0101zi\u2018"
    ],
    "wof:name":"Hisn Al Jazi`",
    "wof:placetype":"locality"
},
  "geometry": {"coordinates":[46.88829000000001,14.32456],"type":"Point"}
}