{
  "type": "Feature",
  "properties": {
    "gn:admin1_code":"24.0",
    "gn:admin2_code":"2507.0",
    "gn:asciiname":"Jalam",
    "gn:country_code":"YE",
    "gn:dem":1038,
    "gn:feature_class":"P",
    "gn:feature_code":"PPL",
    "gn:name":"Jalam",
    "gn:population":0,
    "gn:timezone":"Asia/Aden",
    "iso:country":"YE",
    "wof:name":"Jalam",
    "wof:placetype":"locality"
},
  "geometry": {"coordinates":[44.955,13.48667],"type":"Point"}
}