{
  "type": "Feature",
  "properties": {
    "gn:admin1_code":"22.0",
    "gn:admin2_code":"1702.0",
    "gn:asciiname":"Al Maghbar",
    "gn:country_code":"YE",
    "gn:dem":99,
    "gn:feature_class":"P",
    "gn:feature_code":"PPL",
    "gn:name":"Al Maghbar",
    "gn:population":0,
    "gn:timezone":"Asia/Aden",
    "iso:country":"YE",
    "wof:name":"Al Maghbar",
    "wof:placetype":"locality"
},
  "geometry": {"coordinates":[43.02804,16.47041],"type":"Point"}
}