{
  "type": "Feature",
  "properties": {
    "gn:country":"YE",
    "gn:fcode":"PPL",
    "gn:population":2,
    "iso:country":"YE",
    "name:ara_x_preferred":[
        "\u0627\u0644\u062e\u0634\u0628\u0629"
    ],
    "name:eng_x_preferred":[
        "Al Khashabah"
    ],
    "name:eng_x_variant":[
        "\u2018Aj\u0101jah"
    ],
    "qs:name":"Al Khashabah",
    "qs:photos_9r":0,
    "qs:photos_sr":0,
    "qs:pop_sr":"1",
    "wof:name":"Al Khashabah",
    "wof:placetype":"locality",
    "wof:population":2
},
  "geometry": {"coordinates":[45.46227,14.9414],"type":"Point"}
}