{
  "type": "Feature",
  "properties": {
    "gn:admin1_code":"22.0",
    "gn:admin2_code":"1729.0",
    "gn:asciiname":"Al Halhali",
    "gn:country_code":"YE",
    "gn:dem":2010,
    "gn:feature_class":"P",
    "gn:feature_code":"PPL",
    "gn:name":"Al \u1e28al\u1e29al\u012b",
    "gn:population":0,
    "gn:timezone":"Asia/Aden",
    "iso:country":"YE",
    "name:und_x_variant":[
        "Al \u1e28al\u1e29al\u012b"
    ],
    "wof:name":"Al Halhali",
    "wof:placetype":"locality"
},
  "geometry": {"coordinates":[43.62207,15.62741],"type":"Point"}
}