{
  "type": "Feature",
  "properties": {
    "gn:admin1_code":"16.0",
    "gn:admin2_code":"2309.0",
    "gn:asciiname":"Al Ma`iniyah",
    "gn:country_code":"YE",
    "gn:dem":1355,
    "gn:feature_class":"P",
    "gn:feature_code":"PPL",
    "gn:name":"Al Ma\u2018\u012bn\u012byah",
    "gn:population":0,
    "gn:timezone":"Asia/Aden",
    "iso:country":"YE",
    "name:und_x_variant":[
        "Al Ma\u2018\u012bn\u012byah",
        "Al Mu\u2018ayn\u012byah"
    ],
    "wof:name":"Al Ma`iniyah",
    "wof:placetype":"locality"
},
  "geometry": {"coordinates":[43.85114,14.96144],"type":"Point"}
}