{
  "type": "Feature",
  "properties": {
    "gn:admin1_code":"8.0",
    "gn:admin2_code":"1819.0",
    "gn:asciiname":"Kaydah",
    "gn:country_code":"YE",
    "gn:dem":269,
    "gn:feature_class":"P",
    "gn:feature_code":"PPL",
    "gn:name":"Kaydah",
    "gn:population":0,
    "gn:timezone":"Asia/Aden",
    "iso:country":"YE",
    "wof:name":"Kaydah",
    "wof:placetype":"locality"
},
  "geometry": {"coordinates":[43.52776,14.00449],"type":"Point"}
}