{
  "type": "Feature",
  "properties": {
    "gn:admin1_code":"23.0",
    "gn:admin2_code":"1113.0",
    "gn:asciiname":"Al Uzhur",
    "gn:country_code":"YE",
    "gn:dem":2138,
    "gn:feature_class":"P",
    "gn:feature_code":"PPL",
    "gn:name":"Al Uz\u0327hur",
    "gn:population":0,
    "gn:timezone":"Asia/Aden",
    "iso:country":"YE",
    "name:ara_x_preferred":[
        "Al Uz\u0327hur"
    ],
    "wof:name":"Al Uzhur",
    "wof:placetype":"locality"
},
  "geometry": {"coordinates":[44.35033,13.97001],"type":"Point"}
}