{
  "type": "Feature",
  "properties": {
    "gn:country":"YE",
    "gn:fcode":"PPL",
    "gn:pop":3,
    "iso:country":"YE",
    "name:ara_x_preferred":[
        "\u062e\u0644\u064a\u0644\u0629 \u0627\u0644\u0639\u064a\u0627"
    ],
    "name:eng_x_preferred":[
        "Khalilah Al 'Ulya"
    ],
    "qs:name":"Khal\u012blah al \u2018Uly\u0101",
    "qs:photos_9r":0,
    "qs:photos_sr":0,
    "qs:pop_sr":"1",
    "wof:name":"Khal\u012blah al \u2018Uly\u0101",
    "wof:placetype":"locality",
    "wof:population":3
},
  "geometry": {"coordinates":[45.31528,14.70556],"type":"Point"}
}