{
  "type": "Feature",
  "properties": {
    "gn:admin1_code":"11.0",
    "gn:admin2_code":"1102.0",
    "gn:asciiname":"Al `Ashshah",
    "gn:country_code":"YE",
    "gn:dem":2652,
    "gn:feature_class":"P",
    "gn:feature_code":"PPL",
    "gn:name":"Al \u2018Ashshah",
    "gn:population":0,
    "gn:timezone":"Asia/Aden",
    "iso:country":"YE",
    "name:ara_x_preferred":[
        "\u0627\u0644\u0639\u0634\u0629"
    ],
    "name:und_x_variant":[
        "Al \u2018Ashshah"
    ],
    "wof:name":"Al `Ashshah",
    "wof:placetype":"locality"
},
  "geometry": {"coordinates":[44.27916,14.3292],"type":"Point"}
}