{
  "type": "Feature",
  "properties": {
    "gn:country":"YE",
    "gn:fcode":"PPL",
    "gn:pop":2,
    "iso:country":"YE",
    "name:ara_x_preferred":[
        "\u0628\u064a\u062a \u0647\u0631\u0627\u0648\u0629"
    ],
    "name:eng_x_preferred":[
        "Bayt Harawah"
    ],
    "name:eng_x_variant":[
        "A\u015f \u015eulay\u1e29\u012b"
    ],
    "qs:name":"Bayt Har\u0101wah",
    "qs:photos_9r":0,
    "qs:photos_sr":0,
    "qs:pop_sr":"1",
    "wof:name":"Bayt Har\u0101wah",
    "wof:placetype":"locality",
    "wof:population":2
},
  "geometry": {"coordinates":[43.70675,16.17726],"type":"Point"}
}