{
  "type": "Feature",
  "properties": {
    "gn:admin1_code":"21.0",
    "gn:admin2_code":"1611.0",
    "gn:asciiname":"Rihaymat",
    "gn:country_code":"YE",
    "gn:dem":2095,
    "gn:feature_class":"P",
    "gn:feature_code":"PPL",
    "gn:name":"Rihaym\u0101t",
    "gn:population":0,
    "gn:timezone":"Asia/Aden",
    "iso:country":"YE",
    "name:und_x_variant":[
        "Rihaym\u0101t"
    ],
    "wof:name":"Rihaymat",
    "wof:placetype":"locality"
},
  "geometry": {"coordinates":[44.38898,16.71045],"type":"Point"}
}