{
  "type": "Feature",
  "properties": {
    "gn:admin1_code":"22.0",
    "gn:admin2_code":"1715.0",
    "gn:asciiname":"Shamsan",
    "gn:country_code":"YE",
    "gn:dem":1560,
    "gn:feature_class":"P",
    "gn:feature_code":"PPL",
    "gn:name":"Shams\u0101n",
    "gn:population":0,
    "gn:timezone":"Asia/Aden",
    "iso:country":"YE",
    "name:und_x_variant":[
        "Shams\u0101n"
    ],
    "wof:name":"Shamsan",
    "wof:placetype":"locality"
},
  "geometry": {"coordinates":[43.43479,15.94979],"type":"Point"}
}