{
  "type": "Feature",
  "properties": {
    "gn:country":"YE",
    "gn:fcode":"PPL",
    "gn:pop":7,
    "iso:country":"YE",
    "name:ara_x_preferred":[
        "\u0639\u0636\u064a\u0628"
    ],
    "name:eng_x_preferred":[
        "Uuayb"
    ],
    "qs:name":"\u2018U\u1e11ayb",
    "qs:photos_9r":0,
    "qs:photos_sr":0,
    "qs:pop_sr":"1",
    "wof:name":"\u2018U\u1e11ayb",
    "wof:placetype":"locality",
    "wof:population":7
},
  "geometry": {"coordinates":[44.11074,16.91097],"type":"Point"}
}