{
  "type": "Feature",
  "properties": {
    "gn:admin1_code":"25.0",
    "gn:admin2_code":"1501.0",
    "gn:asciiname":"Al Hawabinah",
    "gn:country_code":"YE",
    "gn:dem":1262,
    "gn:feature_class":"P",
    "gn:feature_code":"PPL",
    "gn:name":"Al \u1e28aw\u0101binah",
    "gn:population":0,
    "gn:timezone":"Asia/Aden",
    "iso:country":"YE",
    "name:und_x_variant":[
        "Al \u1e28aw\u0101binah",
        "Al \u1e28ak\u012bm"
    ],
    "wof:name":"Al Hawabinah",
    "wof:placetype":"locality"
},
  "geometry": {"coordinates":[44.36939,13.55349],"type":"Point"}
}