{
  "type": "Feature",
  "properties": {
    "gn:admin1_code":"11.0",
    "gn:admin2_code":"2009.0",
    "gn:asciiname":"Khirbat as Sayyid",
    "gn:country_code":"YE",
    "gn:dem":2374,
    "gn:feature_class":"P",
    "gn:feature_code":"PPL",
    "gn:name":"Khirbat as Sayyid",
    "gn:population":0,
    "gn:timezone":"Asia/Aden",
    "iso:country":"YE",
    "wof:name":"Khirbat as Sayyid",
    "wof:placetype":"locality"
},
  "geometry": {"coordinates":[44.64217,14.4177],"type":"Point"}
}