{
  "type": "Feature",
  "properties": {
    "gn:admin1_code":"23.0",
    "gn:admin2_code":"1101.0",
    "gn:asciiname":"Al Mi'laf",
    "gn:country_code":"YE",
    "gn:dem":2494,
    "gn:feature_class":"P",
    "gn:feature_code":"PPL",
    "gn:name":"Al Mi\u2018l\u0101f",
    "gn:population":0,
    "gn:timezone":"Asia/Aden",
    "iso:country":"YE",
    "name:ara_x_preferred":[
        "\u0627\u0644\u0645\u0639\u0644\u0627\u0641"
    ],
    "name:und_x_variant":[
        "Al Mi\u2018l\u0101f"
    ],
    "wof:name":"Al Mi'laf",
    "wof:placetype":"locality"
},
  "geometry": {"coordinates":[44.23506,14.28498],"type":"Point"}
}