{
  "type": "Feature",
  "properties": {
    "gn:admin1_code":"23.0",
    "gn:admin2_code":"1103.0",
    "gn:asciiname":"Qarn `Ambari",
    "gn:country_code":"YE",
    "gn:dem":2079,
    "gn:feature_class":"P",
    "gn:feature_code":"PPL",
    "gn:name":"Qarn \u2018Ambar\u012b",
    "gn:population":0,
    "gn:timezone":"Asia/Aden",
    "iso:country":"YE",
    "name:und_x_variant":[
        "Qarn \u2018Ambar\u012b"
    ],
    "wof:name":"Qarn `Ambari",
    "wof:placetype":"locality"
},
  "geometry": {"coordinates":[44.62393,14.19396],"type":"Point"}
}