{
  "type": "Feature",
  "properties": {
    "gn:country":"YE",
    "gn:fcode":"PPL",
    "gn:pop":2,
    "iso:country":"YE",
    "name:ara_x_preferred":[
        "\u062e\u0637\u0648\u0629 \u0627\u0644\u0634\u0642\u0631\u0629"
    ],
    "name:eng_x_preferred":[
        "Khatwat Ash Shuqrah"
    ],
    "name:eng_x_variant":[
        "Al \u2018\u0100ri\u1e11ah"
    ],
    "qs:name":"Kha\u0163wat ash Shuqrah",
    "qs:photos_9r":0,
    "qs:photos_sr":0,
    "qs:pop_sr":"1",
    "wof:name":"Kha\u0163wat ash Shuqrah",
    "wof:placetype":"locality",
    "wof:population":2
},
  "geometry": {"coordinates":[43.20699,17.13878],"type":"Point"}
}