{
  "type": "Feature",
  "properties": {
    "gn:admin1_code":"8.0",
    "gn:admin2_code":"1806.0",
    "gn:asciiname":"Dayr az Zahir",
    "gn:country_code":"YE",
    "gn:dem":78,
    "gn:feature_class":"P",
    "gn:feature_code":"PPL",
    "gn:name":"Dayr az Z\u0101hir",
    "gn:population":0,
    "gn:timezone":"Asia/Aden",
    "iso:country":"YE",
    "name:und_x_variant":[
        "Dayr az Z\u0101hir",
        "Dayr Saher"
    ],
    "wof:name":"Dayr az Zahir",
    "wof:placetype":"locality"
},
  "geometry": {"coordinates":[43.0928,15.38116],"type":"Point"}
}