{
  "type": "Feature",
  "properties": {
    "gn:country":"YE",
    "gn:fcode":"PPLX",
    "gn:population":30,
    "iso:country":"YE",
    "name:ara_x_preferred":[
        "\u0627\u0644\u0623\u0639\u0631\u062c"
    ],
    "qs:name":"Al A\u2018raj",
    "qs:photos_9r":0,
    "qs:photos_sr":0,
    "qs:pop_sr":"1",
    "wof:name":"Al A\u2018raj",
    "wof:placetype":"neighbourhood",
    "wof:population":30
},
  "geometry": {"coordinates":[43.8102,16.89412],"type":"Point"}
}