{
  "type": "Feature",
  "properties": {
    "gn:admin1_code":"14.0",
    "gn:admin2_code":"2609.0",
    "gn:asciiname":"Sharq",
    "gn:country_code":"YE",
    "gn:dem":1211,
    "gn:feature_class":"P",
    "gn:feature_code":"PPL",
    "gn:name":"Sharq",
    "gn:population":0,
    "gn:timezone":"Asia/Aden",
    "iso:country":"YE",
    "name:ara_x_preferred":[
        "\u0634\u0631\u0642"
    ],
    "wof:name":"Sharq",
    "wof:placetype":"locality"
},
  "geometry": {"coordinates":[45.42133,14.90845],"type":"Point"}
}