{
  "type": "Feature",
  "properties": {
    "gn:admin1_code":"11.0",
    "gn:admin2_code":"2006.0",
    "gn:asciiname":"Bani al Haddad",
    "gn:country_code":"YE",
    "gn:dem":2282,
    "gn:feature_class":"P",
    "gn:feature_code":"PPL",
    "gn:name":"Ban\u012b al \u1e28add\u0101d",
    "gn:population":0,
    "gn:timezone":"Asia/Aden",
    "iso:country":"YE",
    "name:und_x_variant":[
        "Ban\u012b al \u1e28add\u0101d"
    ],
    "wof:name":"Bani al Haddad",
    "wof:placetype":"locality"
},
  "geometry": {"coordinates":[43.85602,14.35705],"type":"Point"}
}