{
  "type": "Feature",
  "properties": {
    "gn:admin1_code":"20.0",
    "gn:admin2_code":"1405.0",
    "gn:asciiname":"Hamhamah",
    "gn:country_code":"YE",
    "gn:dem":1996,
    "gn:feature_class":"P",
    "gn:feature_code":"PPL",
    "gn:name":"\u1e28am\u1e29amah",
    "gn:population":0,
    "gn:timezone":"Asia/Aden",
    "iso:country":"YE",
    "name:ara_x_preferred":[
        "\u062d\u0645\u062d\u0645\u0629"
    ],
    "name:und_x_variant":[
        "\u1e28am\u1e29amah"
    ],
    "wof:name":"Hamhamah",
    "wof:placetype":"locality"
},
  "geometry": {"coordinates":[45.40002,14.04117],"type":"Point"}
}