{
  "type": "Feature",
  "properties": {
    "gn:country":"YE",
    "gn:fcode":"PPL",
    "gn:pop":2,
    "iso:country":"YE",
    "name:ara_x_preferred":[
        "\u0648\u0627\u062f\u0639\u0640\u0640\u0629"
    ],
    "name:eng_x_preferred":[
        "Wad'ah"
    ],
    "qs:name":"W\u0101d\u2018ah",
    "qs:photos_9r":0,
    "qs:photos_sr":0,
    "qs:pop_sr":"1",
    "wof:name":"W\u0101d\u2018ah",
    "wof:placetype":"locality",
    "wof:population":2
},
  "geometry": {"coordinates":[43.42523,16.42243],"type":"Point"}
}