{
  "type": "Feature",
  "properties": {
    "gn:admin1_code":"18.0",
    "gn:admin2_code":"3006.0",
    "gn:asciiname":"Al Kurb",
    "gn:country_code":"YE",
    "gn:dem":1429,
    "gn:feature_class":"P",
    "gn:feature_code":"PPL",
    "gn:name":"Al Kurb",
    "gn:population":0,
    "gn:timezone":"Asia/Aden",
    "iso:country":"YE",
    "name:und_x_variant":[
        "El Kurb",
        "Al Kurb"
    ],
    "wof:name":"Al Kurb",
    "wof:placetype":"locality"
},
  "geometry": {"coordinates":[44.74758,13.67072],"type":"Point"}
}