{
  "type": "Feature",
  "properties": {
    "gn:admin1_code":"24.0",
    "gn:admin2_code":"2512.0",
    "gn:asciiname":"Barh al Ma'",
    "gn:country_code":"YE",
    "gn:dem":1412,
    "gn:feature_class":"P",
    "gn:feature_code":"PPL",
    "gn:name":"Bar\u1e29 al M\u0101\u2019",
    "gn:population":0,
    "gn:timezone":"Asia/Aden",
    "iso:country":"YE",
    "name:und_x_variant":[
        "Bar\u1e29 al M\u0101\u2019"
    ],
    "wof:name":"Barh al Ma'",
    "wof:placetype":"locality"
},
  "geometry": {"coordinates":[44.19704,13.17045],"type":"Point"}
}