{
  "type": "Feature",
  "properties": {
    "gn:admin1_code":"8.0",
    "gn:admin2_code":"1810.0",
    "gn:asciiname":"Bani Samin",
    "gn:country_code":"YE",
    "gn:dem":184,
    "gn:feature_class":"P",
    "gn:feature_code":"PPL",
    "gn:name":"Ban\u012b Sam\u012bn",
    "gn:population":0,
    "gn:timezone":"Asia/Aden",
    "iso:country":"YE",
    "name:ara_x_preferred":[
        "\u0628\u0646\u064a \u0633\u0645\u064a\u0646"
    ],
    "name:und_x_variant":[
        "Ban\u012b Sam\u012bn"
    ],
    "wof:name":"Bani Samin",
    "wof:placetype":"locality"
},
  "geometry": {"coordinates":[43.26588,15.09334],"type":"Point"}
}