{
  "type": "Feature",
  "properties": {
    "gn:admin1_code":"22.0",
    "gn:admin2_code":"1709.0",
    "gn:asciiname":"Dhira' al Jamimah",
    "gn:country_code":"YE",
    "gn:dem":1707,
    "gn:feature_class":"P",
    "gn:feature_code":"PPL",
    "gn:name":"Dhir\u0101\u2018 al Jam\u012bmah",
    "gn:population":0,
    "gn:timezone":"Asia/Aden",
    "iso:country":"YE",
    "name:ara_x_preferred":[
        "\u0630\u0631\u0627\u0639 \u0627\u0644\u062c\u0645\u064a\u0645\u0629"
    ],
    "name:und_x_variant":[
        "Dhir\u0101\u2018 al Jam\u012bmah"
    ],
    "wof:name":"Dhira' al Jamimah",
    "wof:placetype":"locality"
},
  "geometry": {"coordinates":[43.46277,16.01639],"type":"Point"}
}