{
  "type": "Feature",
  "properties": {
    "gn:admin1_code":"23.0",
    "gn:admin2_code":"1102.0",
    "gn:asciiname":"Dha Khawlan",
    "gn:country_code":"YE",
    "gn:dem":2953,
    "gn:feature_class":"P",
    "gn:feature_code":"PPL",
    "gn:name":"Dh\u00e1 Khawl\u0101n",
    "gn:population":0,
    "gn:timezone":"Asia/Aden",
    "iso:country":"YE",
    "name:ara_x_preferred":[
        "\u0630\u0649 \u062e\u0648\u0644\u0627\u0646"
    ],
    "name:und_x_variant":[
        "Dh\u012b Khawl\u0101n",
        "Dh\u00e1 Khawl\u0101n"
    ],
    "wof:name":"Dha Khawlan",
    "wof:placetype":"locality"
},
  "geometry": {"coordinates":[44.29001,14.17503],"type":"Point"}
}