{
  "type": "Feature",
  "properties": {
    "gn:admin1_code":"22.0",
    "gn:admin2_code":"1702.0",
    "gn:asciiname":"Al `Atnah",
    "gn:country_code":"YE",
    "gn:dem":82,
    "gn:feature_class":"P",
    "gn:feature_code":"PPL",
    "gn:name":"Al \u2018Atnah",
    "gn:population":0,
    "gn:timezone":"Asia/Aden",
    "iso:country":"YE",
    "name:und_x_variant":[
        "Al \u2018Atnah"
    ],
    "wof:name":"Al `Atnah",
    "wof:placetype":"locality"
},
  "geometry": {"coordinates":[43.03333,16.36667000000001],"type":"Point"}
}