{
  "type": "Feature",
  "properties": {
    "gn:admin1_code":"10.0",
    "gn:admin2_code":"2709.0",
    "gn:asciiname":"As Sahlah",
    "gn:country_code":"YE",
    "gn:dem":1139,
    "gn:feature_class":"P",
    "gn:feature_code":"PPL",
    "gn:name":"As Sahlah",
    "gn:population":0,
    "gn:timezone":"Asia/Aden",
    "iso:country":"YE",
    "wof:name":"As Sahlah",
    "wof:placetype":"locality"
},
  "geometry": {"coordinates":[43.62428,15.33271],"type":"Point"}
}