{
  "type": "Feature",
  "properties": {
    "gn:admin1_code":"23.0",
    "gn:admin2_code":"1120.0",
    "gn:asciiname":"Al Mandam",
    "gn:country_code":"YE",
    "gn:dem":1962,
    "gn:feature_class":"P",
    "gn:feature_code":"PPL",
    "gn:name":"Al Mandam",
    "gn:population":0,
    "gn:timezone":"Asia/Aden",
    "iso:country":"YE",
    "wof:name":"Al Mandam",
    "wof:placetype":"locality"
},
  "geometry": {"coordinates":[44.21484,13.93593],"type":"Point"}
}