{
  "type": "Feature",
  "properties": {
    "gn:country":"YE",
    "gn:fcode":"PPL",
    "gn:pop":11,
    "iso:country":"YE",
    "name:ara_x_preferred":[
        "\u0627\u0644\u0633\u0631\u0648 \u0627\u0644\u0623\u0633\u0641\u0644"
    ],
    "name:eng_x_preferred":[
        "As Sarw Al Asfal"
    ],
    "name:eng_x_variant":[
        "Al Jur\u016bbah"
    ],
    "qs:name":"As Sarw al Asfal",
    "qs:photos_9r":0,
    "qs:photos_sr":0,
    "qs:pop_sr":"1",
    "wof:name":"As Sarw al Asfal",
    "wof:placetype":"locality",
    "wof:population":11
},
  "geometry": {"coordinates":[43.25179,16.94821],"type":"Point"}
}