{
  "type": "Feature",
  "properties": {
    "gn:admin1_code":"25.0",
    "gn:admin2_code":"1502.0",
    "gn:asciiname":"`Ukaysh",
    "gn:country_code":"YE",
    "gn:dem":917,
    "gn:feature_class":"P",
    "gn:feature_code":"PPL",
    "gn:name":"\u2018Ukaysh",
    "gn:population":0,
    "gn:timezone":"Asia/Aden",
    "iso:country":"YE",
    "name:ara_x_preferred":[
        "\u0639\u0643\u064a\u0634"
    ],
    "name:und_x_variant":[
        "Okeish",
        "\u2018Ukaysh"
    ],
    "wof:name":"`Ukaysh",
    "wof:placetype":"locality"
},
  "geometry": {"coordinates":[43.87676,13.65334],"type":"Point"}
}