{
  "type": "Feature",
  "properties": {
    "gn:admin1_code":"16.0",
    "gn:admin2_code":"2316.0",
    "gn:asciiname":"Al Birbirah",
    "gn:country_code":"YE",
    "gn:dem":2135,
    "gn:feature_class":"P",
    "gn:feature_code":"PPL",
    "gn:name":"Al Birbirah",
    "gn:population":0,
    "gn:timezone":"Asia/Aden",
    "iso:country":"YE",
    "wof:name":"Al Birbirah",
    "wof:placetype":"locality"
},
  "geometry": {"coordinates":[44.54361,15.14419],"type":"Point"}
}