{
  "type": "Feature",
  "properties": {
    "gn:admin1_code":"15.0",
    "gn:admin2_code":"2202.0",
    "gn:asciiname":"Mahadinah",
    "gn:country_code":"YE",
    "gn:dem":1957,
    "gn:feature_class":"P",
    "gn:feature_code":"PPL",
    "gn:name":"Ma\u1e29\u0101\u1e11inah",
    "gn:population":0,
    "gn:timezone":"Asia/Aden",
    "iso:country":"YE",
    "name:und_x_variant":[
        "Ma\u1e29\u0101\u1e11inah"
    ],
    "wof:name":"Mahadinah",
    "wof:placetype":"locality"
},
  "geometry": {"coordinates":[43.35073,17.32432],"type":"Point"}
}