{
  "type": "Feature",
  "properties": {
    "gn:admin1_code":"23.0",
    "gn:admin2_code":"1103.0",
    "gn:asciiname":"Al Qawfa`ah",
    "gn:country_code":"YE",
    "gn:dem":2264,
    "gn:feature_class":"P",
    "gn:feature_code":"PPL",
    "gn:name":"Al Qawfa\u2018ah",
    "gn:population":0,
    "gn:timezone":"Asia/Aden",
    "iso:country":"YE",
    "name:ara_x_preferred":[
        "\u0627\u0644\u0642\u0648\u0641\u0639\u0629"
    ],
    "name:und_x_variant":[
        "Al Q\u016bfa\u2018ah",
        "Al Qawfa\u2018ah"
    ],
    "wof:name":"Al Qawfa`ah",
    "wof:placetype":"locality"
},
  "geometry": {"coordinates":[44.54468,14.25955],"type":"Point"}
}