{
  "type": "Feature",
  "properties": {
    "gn:admin1_code":"4.0",
    "gn:admin2_code":"1916.0",
    "gn:asciiname":"Al Quzah",
    "gn:cc2":"YE",
    "gn:country_code":"YE",
    "gn:dem":1118,
    "gn:feature_class":"P",
    "gn:feature_code":"PPL",
    "gn:name":"Al Quzah",
    "gn:population":0,
    "gn:timezone":"Asia/Aden",
    "iso:country":"YE",
    "name:und_x_variant":[
        "Qazau",
        "Qazaw",
        "Al Quzah"
    ],
    "wof:name":"Al Quzah",
    "wof:placetype":"locality"
},
  "geometry": {"coordinates":[49.12389,15.10611],"type":"Point"}
}