{
  "type": "Feature",
  "properties": {
    "gn:admin1_code":"10.0",
    "gn:admin2_code":"2709.0",
    "gn:asciiname":"Bayt as Sarawi",
    "gn:country_code":"YE",
    "gn:dem":1202,
    "gn:feature_class":"P",
    "gn:feature_code":"PPL",
    "gn:name":"Bayt as Saraw\u012b",
    "gn:population":0,
    "gn:timezone":"Asia/Aden",
    "iso:country":"YE",
    "name:und_x_variant":[
        "Bayt as Saraw\u012b"
    ],
    "wof:name":"Bayt as Sarawi",
    "wof:placetype":"locality"
},
  "geometry": {"coordinates":[43.51367,15.50678],"type":"Point"}
}