{
  "type": "Feature",
  "properties": {
    "gn:admin1_code":"16.0",
    "gn:admin2_code":"2302.0",
    "gn:asciiname":"Al Mahall",
    "gn:country_code":"YE",
    "gn:dem":2396,
    "gn:feature_class":"P",
    "gn:feature_code":"PPL",
    "gn:name":"Al Ma\u1e29all",
    "gn:population":0,
    "gn:timezone":"Asia/Aden",
    "iso:country":"YE",
    "name:und_x_variant":[
        "Al Ma\u1e29all"
    ],
    "wof:name":"Al Mahall",
    "wof:placetype":"locality"
},
  "geometry": {"coordinates":[44.30988,15.7788],"type":"Point"}
}