{
  "type": "Feature",
  "properties": {
    "gn:country":"YE",
    "gn:fcode":"PPL",
    "gn:pop":12,
    "iso:country":"YE",
    "name:ara_x_preferred":[
        "\u0635\u062d\u0637 \u0627\u0644\u0639\u062f\u0646"
    ],
    "name:eng_x_preferred":[
        "Sahat Al 'Adan"
    ],
    "qs:name":"\u015ea\u1e29a\u0163 al \u2018Adan",
    "qs:photos_9r":0,
    "qs:photos_sr":0,
    "qs:pop_sr":"1",
    "wof:name":"\u015ea\u1e29a\u0163 al \u2018Adan",
    "wof:placetype":"locality",
    "wof:population":12
},
  "geometry": {"coordinates":[43.28808,17.00687],"type":"Point"}
}