{
  "type": "Feature",
  "properties": {
    "gn:country":"YE",
    "gn:fcode":"PPLX",
    "gn:population":2,
    "iso:country":"YE",
    "name:ara_x_preferred":[
        "\u0645\u0648\u0641 \u0627\u0644\u0645\u064a\u062f\u0627\u0646"
    ],
    "qs:name":"Mawf al Mayd\u0101n",
    "qs:photos_9r":0,
    "qs:photos_sr":0,
    "qs:pop_sr":"1",
    "wof:name":"Mawf al Mayd\u0101n",
    "wof:placetype":"neighbourhood",
    "wof:population":2
},
  "geometry": {"coordinates":[43.703,16.18409],"type":"Point"}
}