{
  "type": "Feature",
  "properties": {
    "gn:admin1_code":"14.0",
    "gn:admin2_code":"2606.0",
    "gn:asciiname":"Nasib al Bir",
    "gn:country_code":"YE",
    "gn:dem":1316,
    "gn:feature_class":"P",
    "gn:feature_code":"PPL",
    "gn:name":"Na\u015f\u012bb al B\u012br",
    "gn:population":0,
    "gn:timezone":"Asia/Aden",
    "iso:country":"YE",
    "name:ara_x_preferred":[
        "\u0646\u0635\u064a\u0628 \u0627\u0644\u0628\u064a\u0631"
    ],
    "name:und_x_variant":[
        "Na\u015f\u012bb al B\u012br"
    ],
    "wof:name":"Nasib al Bir",
    "wof:placetype":"locality"
},
  "geometry": {"coordinates":[45.18566,15.41509],"type":"Point"}
}