{
  "type": "Feature",
  "properties": {
    "gn:admin1_code":"11.0",
    "gn:admin2_code":"2001.0",
    "gn:asciiname":"Bayt al Ma`tuf",
    "gn:country_code":"YE",
    "gn:dem":2476,
    "gn:feature_class":"P",
    "gn:feature_code":"PPL",
    "gn:name":"Bayt al Ma\u2018\u0163\u016bf",
    "gn:population":0,
    "gn:timezone":"Asia/Aden",
    "iso:country":"YE",
    "name:und_x_variant":[
        "Bayt al Ma\u2018\u0163\u016bf"
    ],
    "wof:name":"Bayt al Ma`tuf",
    "wof:placetype":"locality"
},
  "geometry": {"coordinates":[44.3573,14.83087],"type":"Point"}
}