{
  "type": "Feature",
  "properties": {
    "gn:admin1_code":"23.0",
    "gn:admin2_code":"1101.0",
    "gn:asciiname":"Kawlat Ranin",
    "gn:country_code":"YE",
    "gn:dem":1662,
    "gn:feature_class":"P",
    "gn:feature_code":"PPL",
    "gn:name":"Kawlat Ran\u012bn",
    "gn:population":0,
    "gn:timezone":"Asia/Aden",
    "iso:country":"YE",
    "name:ara_x_preferred":[
        "\u0643\u0648\u0644\u0629 \u0631\u0646\u064a\u0646"
    ],
    "name:und_x_variant":[
        "Kawlat Ran\u012bn"
    ],
    "wof:name":"Kawlat Ranin",
    "wof:placetype":"locality"
},
  "geometry": {"coordinates":[44.14382,14.31557],"type":"Point"}
}