{
  "type": "Feature",
  "properties": {
    "gn:admin1_code":"25.0",
    "gn:admin2_code":"1509.0",
    "gn:asciiname":"Shi`b Subayt",
    "gn:country_code":"YE",
    "gn:dem":883,
    "gn:feature_class":"P",
    "gn:feature_code":"PPL",
    "gn:name":"Shi\u2018b Subayt",
    "gn:population":0,
    "gn:timezone":"Asia/Aden",
    "iso:country":"YE",
    "name:ara_x_preferred":[
        "\u0634\u0639\u0628 \u0633\u0628\u064a\u062a"
    ],
    "name:und_x_variant":[
        "Shi\u2018b Subayt"
    ],
    "wof:name":"Shi`b Subayt",
    "wof:placetype":"locality"
},
  "geometry": {"coordinates":[43.81667,13.51667],"type":"Point"}
}