{
  "type": "Feature",
  "properties": {
    "gn:admin1_code":"19.0",
    "gn:admin2_code":"2910.0",
    "gn:asciiname":"Mahall al Asiyah",
    "gn:country_code":"YE",
    "gn:dem":2369,
    "gn:feature_class":"P",
    "gn:feature_code":"PPL",
    "gn:name":"Mah\u0101ll al A\u015fiy\u0101\u1e29",
    "gn:population":0,
    "gn:timezone":"Asia/Aden",
    "iso:country":"YE",
    "name:und_x_variant":[
        "Mah\u0101ll al A\u015fiy\u0101\u1e29"
    ],
    "wof:name":"Mahall al Asiyah",
    "wof:placetype":"locality"
},
  "geometry": {"coordinates":[44.05544,15.91275],"type":"Point"}
}