{
  "type": "Feature",
  "properties": {
    "gn:country":"YE",
    "gn:fcode":"PPL",
    "gn:population":6,
    "iso:country":"YE",
    "name:ara_x_preferred":[
        "Al I\u1e29\u015f\u0101m"
    ],
    "name:ara_x_variant":[
        "\u0627\u0644\u0625\u062d\u0635\u0627\u0645"
    ],
    "name:eng_x_preferred":[
        "Al Ihsam"
    ],
    "name:eng_x_variant":[
        "Al \u1e28ulq\u016bm"
    ],
    "qs:name":"Al I\u1e29\u015f\u0101m",
    "qs:photos_9r":0,
    "qs:photos_sr":0,
    "qs:pop_sr":"1",
    "wof:name":"Al I\u1e29\u015f\u0101m",
    "wof:placetype":"locality",
    "wof:population":6
},
  "geometry": {"coordinates":[45.34948,14.26127],"type":"Point"}
}