{
  "type": "Feature",
  "properties": {
    "gn:admin1_code":"25.0",
    "gn:admin2_code":"1509.0",
    "gn:asciiname":"`Aya' al Janad",
    "gn:country_code":"YE",
    "gn:dem":971,
    "gn:feature_class":"P",
    "gn:feature_code":"PPL",
    "gn:name":"\u2018Ay\u0101\u2019 al Janad",
    "gn:population":0,
    "gn:timezone":"Asia/Aden",
    "iso:country":"YE",
    "name:und_x_variant":[
        "\u2018Ay\u0101\u2019 al Janad"
    ],
    "wof:name":"`Aya' al Janad",
    "wof:placetype":"locality"
},
  "geometry": {"coordinates":[43.81637,13.48485],"type":"Point"}
}