{
  "type": "Feature",
  "properties": {
    "gn:admin1_code":"15.0",
    "gn:admin2_code":"2203.0",
    "gn:asciiname":"Ash Shatba'",
    "gn:country_code":"YE",
    "gn:dem":1883,
    "gn:feature_class":"P",
    "gn:feature_code":"PPL",
    "gn:name":"Ash Sha\u0163b\u0101\u2019",
    "gn:population":0,
    "gn:timezone":"Asia/Aden",
    "iso:country":"YE",
    "name:ara_x_preferred":[
        "\u0627\u0644\u0634\u0637\u0628\u0627\u0621"
    ],
    "name:und_x_variant":[
        "Ash Sha\u0163b\u0101\u2019"
    ],
    "wof:name":"Ash Shatba'",
    "wof:placetype":"locality"
},
  "geometry": {"coordinates":[43.24426,17.17762999999999],"type":"Point"}
}