{
  "type": "Feature",
  "properties": {
    "gn:admin1_code":"25.0",
    "gn:admin2_code":"1508.0",
    "gn:asciiname":"Al Wahiz",
    "gn:country_code":"YE",
    "gn:dem":278,
    "gn:feature_class":"P",
    "gn:feature_code":"PPL",
    "gn:name":"Al Wa\u1e29iz",
    "gn:population":0,
    "gn:timezone":"Asia/Aden",
    "iso:country":"YE",
    "name:und_x_variant":[
        "Al Wa\u1e29iz"
    ],
    "wof:name":"Al Wahiz",
    "wof:placetype":"locality"
},
  "geometry": {"coordinates":[43.58624,13.46248],"type":"Point"}
}