{
  "type": "Feature",
  "properties": {
    "gn:admin1_code":"25.0",
    "gn:admin2_code":"1502.0",
    "gn:asciiname":"Ghurab A`la",
    "gn:country_code":"YE",
    "gn:dem":1099,
    "gn:feature_class":"P",
    "gn:feature_code":"PPL",
    "gn:name":"Ghur\u0101b A\u2018l\u00e1",
    "gn:population":0,
    "gn:timezone":"Asia/Aden",
    "iso:country":"YE",
    "name:ara_x_preferred":[
        "Ghur\u0101b A\u2018l\u00e1"
    ],
    "name:ara_x_variant":[
        "\u063a\u0631\u0627\u0628 \u0623\u0639\u0644\u0649"
    ],
    "wof:name":"Ghurab A`la",
    "wof:placetype":"locality"
},
  "geometry": {"coordinates":[43.9593,13.61096],"type":"Point"}
}