{
  "type": "Feature",
  "properties": {
    "gn:admin1_code":"15.0",
    "gn:admin2_code":"2206.0",
    "gn:asciiname":"Al Musayni`ah",
    "gn:country_code":"YE",
    "gn:dem":725,
    "gn:feature_class":"P",
    "gn:feature_code":"PPL",
    "gn:name":"Al Mu\u015fayni\u2018ah",
    "gn:population":0,
    "gn:timezone":"Asia/Aden",
    "iso:country":"YE",
    "name:und_x_variant":[
        "Al Mu\u015fayni\u2018ah"
    ],
    "wof:name":"Al Musayni`ah",
    "wof:placetype":"locality"
},
  "geometry": {"coordinates":[43.17535,16.88161],"type":"Point"}
}