{
  "type": "Feature",
  "properties": {
    "gn:country":"YE",
    "gn:fcode":"PPL",
    "gn:pop":2,
    "iso:country":"YE",
    "name:ara_x_preferred":[
        "\u0627\u0644 \u0637\u0641\u0632\u0648\u0632"
    ],
    "name:eng_x_preferred":[
        "Al TafzUz"
    ],
    "qs:name":"\u0100l \u0162afz\u016bz",
    "qs:photos_9r":0,
    "qs:photos_sr":0,
    "qs:pop_sr":"1",
    "wof:name":"\u0100l \u0162afz\u016bz",
    "wof:placetype":"locality",
    "wof:population":2
},
  "geometry": {"coordinates":[45.44615,14.91708],"type":"Point"}
}