{
  "type": "Feature",
  "properties": {
    "gn:admin1_code":"16.0",
    "gn:admin2_code":"2305.0",
    "gn:asciiname":"Sukhalit",
    "gn:country_code":"YE",
    "gn:dem":2428,
    "gn:feature_class":"P",
    "gn:feature_code":"PPL",
    "gn:name":"Sukh\u0101l\u012bt",
    "gn:population":0,
    "gn:timezone":"Asia/Aden",
    "iso:country":"YE",
    "name:ara_x_preferred":[
        "Sukh\u0101l\u012bt"
    ],
    "wof:name":"Sukhalit",
    "wof:placetype":"locality"
},
  "geometry": {"coordinates":[44.36393,15.26348],"type":"Point"}
}