{
  "type": "Feature",
  "properties": {
    "gn:country":"YE",
    "gn:fcode":"PPL",
    "gn:population":1,
    "iso:country":"YE",
    "name:ara_x_preferred":[
        "\u0627\u0644\u0646\u0645\u0631\u064a\u0646"
    ],
    "name:eng_x_preferred":[
        "An Namrayn"
    ],
    "name:eng_x_variant":[
        "Al Marh\u016bb"
    ],
    "qs:name":"An Namrayn",
    "qs:photos_9r":0,
    "qs:photos_sr":0,
    "qs:pop_sr":"1",
    "wof:name":"An Namrayn",
    "wof:placetype":"locality",
    "wof:population":1
},
  "geometry": {"coordinates":[45.12426,14.79116],"type":"Point"}
}