{
  "type": "Feature",
  "properties": {
    "gn:country":"YE",
    "gn:fcode":"PPL",
    "gn:pop":6,
    "iso:country":"YE",
    "name:ara_x_preferred":[
        "\u0645\u0631\u0634\u062f\u0629"
    ],
    "name:eng_x_preferred":[
        "Murshadah"
    ],
    "qs:name":"Murshadah",
    "qs:photos_9r":0,
    "qs:photos_sr":0,
    "qs:pop_sr":"1",
    "wof:name":"Murshadah",
    "wof:placetype":"locality",
    "wof:population":6
},
  "geometry": {"coordinates":[44.33071,17.03719],"type":"Point"}
}