{
  "type": "Feature",
  "properties": {
    "gn:admin1_code":"25.0",
    "gn:admin2_code":"1509.0",
    "gn:asciiname":"Al Mihsha'",
    "gn:country_code":"YE",
    "gn:dem":2094,
    "gn:feature_class":"P",
    "gn:feature_code":"PPL",
    "gn:name":"Al Mi\u1e29sh\u0101\u2019",
    "gn:population":0,
    "gn:timezone":"Asia/Aden",
    "iso:country":"YE",
    "name:ara_x_preferred":[
        "Al Mi\u1e29sh\u0101\u2019"
    ],
    "wof:name":"Al Mihsha'",
    "wof:placetype":"locality"
},
  "geometry": {"coordinates":[43.87531,13.50147],"type":"Point"}
}