{
  "type": "Feature",
  "properties": {
    "gn:admin1_code":"25.0",
    "gn:admin2_code":"1515.0",
    "gn:asciiname":"'Awd",
    "gn:country_code":"YE",
    "gn:dem":1896,
    "gn:feature_class":"P",
    "gn:feature_code":"PPL",
    "gn:name":"\u2018Awd",
    "gn:population":0,
    "gn:timezone":"Asia/Aden",
    "iso:country":"YE",
    "name:ara_x_preferred":[
        "\u0639\u0648\u062f"
    ],
    "name:und_x_variant":[
        "\u2018Awd"
    ],
    "wof:name":"'Awd",
    "wof:placetype":"locality"
},
  "geometry": {"coordinates":[44.13529000000001,13.21558],"type":"Point"}
}