{
  "type": "Feature",
  "properties": {
    "gn:admin1_code":"20.0",
    "gn:admin2_code":"1412.0",
    "gn:asciiname":"Al Khilaw ash Shurayzah",
    "gn:country_code":"YE",
    "gn:dem":2063,
    "gn:feature_class":"P",
    "gn:feature_code":"PPL",
    "gn:name":"Al Khil\u0101w ash Shurayzah",
    "gn:population":0,
    "gn:timezone":"Asia/Aden",
    "iso:country":"YE",
    "name:und_x_variant":[
        "Al Khil\u0101w ash Shurayzah"
    ],
    "wof:name":"Al Khilaw ash Shurayzah",
    "wof:placetype":"locality"
},
  "geometry": {"coordinates":[45.27084,14.53086],"type":"Point"}
}