{
  "type": "Feature",
  "properties": {
    "gn:country":"YE",
    "gn:fcode":"PPL",
    "gn:population":10,
    "iso:country":"YE",
    "name:ara_x_preferred":[
        "\u062c\u0627\u0631\u0648\u062f"
    ],
    "name:eng_x_preferred":[
        "Jarwad"
    ],
    "name:eng_x_variant":[
        "Ash Shaw\u0101ji\u2018"
    ],
    "qs:name":"J\u0101rwad",
    "qs:photos_9r":0,
    "qs:photos_sr":0,
    "qs:pop_sr":"1",
    "wof:name":"J\u0101rwad",
    "wof:placetype":"locality",
    "wof:population":10
},
  "geometry": {"coordinates":[43.32691,16.29592],"type":"Point"}
}