{
  "type": "Feature",
  "properties": {
    "gn:admin1_code":"19.0",
    "gn:admin2_code":"2903.0",
    "gn:asciiname":"Al 'Uqbah al Gharbiyah",
    "gn:country_code":"YE",
    "gn:dem":1312,
    "gn:feature_class":"P",
    "gn:feature_code":"PPL",
    "gn:name":"Al \u2018Uqbah al Gharb\u012byah",
    "gn:population":0,
    "gn:timezone":"Asia/Aden",
    "iso:country":"YE",
    "name:ara_x_preferred":[
        "\u0627\u0644\u0639\u0642\u0628\u0629 \u0627\u0644\u063a\u0631\u0628\u064a\u0629"
    ],
    "name:und_x_variant":[
        "Al \u2018Uqbah al Gharb\u012byah"
    ],
    "wof:name":"Al 'Uqbah al Gharbiyah",
    "wof:placetype":"locality"
},
  "geometry": {"coordinates":[43.82042,16.12577000000001],"type":"Point"}
}