{
  "type": "Feature",
  "properties": {
    "gn:country":"YE",
    "gn:fcode":"PPL",
    "gn:pop":8,
    "iso:country":"YE",
    "name:ara_x_preferred":[
        "\u0100l Mu\u1e29sin \u2018Al\u012b"
    ],
    "name:ara_x_variant":[
        "\u0627\u0644 \u0645\u062d\u0633\u0646 \u0639\u0644\u064a"
    ],
    "name:eng_x_preferred":[
        "Al Muhsin 'Ali"
    ],
    "name:eng_x_variant":[
        "Suhaylah"
    ],
    "qs:name":"\u0100l Mu\u1e29sin \u2018Al\u012b",
    "qs:photos_9r":0,
    "qs:photos_sr":0,
    "qs:pop_sr":"1",
    "wof:name":"\u0100l Mu\u1e29sin \u2018Al\u012b",
    "wof:placetype":"locality",
    "wof:population":8
},
  "geometry": {"coordinates":[45.32261,14.06446],"type":"Point"}
}