{
  "type": "Feature",
  "properties": {
    "gn:country":"YE",
    "gn:fcode":"PPL",
    "gn:population":17,
    "iso:country":"YE",
    "name:ara_x_preferred":[
        "\u0627\u0644\u0634\u0628\u0627\u0643\u064a\u0629"
    ],
    "name:eng_x_preferred":[
        "Ash Shabakiyah"
    ],
    "name:eng_x_variant":[
        "Al Mu\u2018ayram"
    ],
    "qs:name":"Ash Shab\u0101k\u012byah",
    "qs:photos_9r":0,
    "qs:photos_sr":0,
    "qs:pop_sr":"1",
    "wof:name":"Ash Shab\u0101k\u012byah",
    "wof:placetype":"locality",
    "wof:population":17
},
  "geometry": {"coordinates":[43.0453,16.26283],"type":"Point"}
}