{
  "type": "Feature",
  "properties": {
    "gn:admin1_code":"24.0",
    "gn:admin2_code":"2512.0",
    "gn:asciiname":"Ash Shuhuj",
    "gn:country_code":"YE",
    "gn:dem":862,
    "gn:feature_class":"P",
    "gn:feature_code":"PPL",
    "gn:name":"Ash Shu\u1e29\u016bj",
    "gn:population":0,
    "gn:timezone":"Asia/Aden",
    "iso:country":"YE",
    "name:ara_x_preferred":[
        "\u0627\u0644\u0634\u062d\u0648\u062c"
    ],
    "name:und_x_variant":[
        "Ash Shu\u1e29\u016bj"
    ],
    "wof:name":"Ash Shuhuj",
    "wof:placetype":"locality"
},
  "geometry": {"coordinates":[44.24572,13.17491],"type":"Point"}
}