{
  "type": "Feature",
  "properties": {
    "gn:country":"YE",
    "gn:fcode":"PPL",
    "gn:pop":1,
    "iso:country":"YE",
    "name:ara_x_preferred":[
        "\u0627\u0644\u0646\u0648\u0628\u0629"
    ],
    "name:eng_x_preferred":[
        "An Nawbah"
    ],
    "name:eng_x_variant":[
        "Ash Sha\u2018bayn"
    ],
    "qs:name":"An Nawbah",
    "qs:photos_9r":0,
    "qs:photos_sr":0,
    "qs:pop_sr":"1",
    "wof:name":"An Nawbah",
    "wof:placetype":"locality",
    "wof:population":1
},
  "geometry": {"coordinates":[43.92035,13.21203],"type":"Point"}
}