{
  "type": "Feature",
  "properties": {
    "gn:country":"YE",
    "gn:fcode":"PPL",
    "gn:population":4,
    "iso:country":"YE",
    "name:ara_x_preferred":[
        "\u0627\u0644\u0623\u0628\u062a\u0631"
    ],
    "name:eng_x_preferred":[
        "Al Abtar"
    ],
    "name:eng_x_variant":[
        "Ban\u012b Sham\u012blah"
    ],
    "qs_pg:aaroncc":"YE",
    "qs_pg:gn_country":"YE",
    "qs_pg:gn_fcode":"PPL",
    "qs_pg:gn_pop":4,
    "qs_pg:name":"Al Abtar",
    "qs_pg:photos_9r":0,
    "qs_pg:photos_sr":0,
    "qs_pg:pop_sr":1,
    "qs_pg:qs_pg_placetype":"locality",
    "wof:name":"Al Abtar",
    "wof:placetype":"locality",
    "wof:population":4
},
  "geometry": {"coordinates":[45.23323,14.76017],"type":"Point"}
}