{
  "type": "Feature",
  "properties": {
    "gn:country":"YE",
    "gn:fcode":"PPL",
    "gn:pop":4,
    "iso:country":"YE",
    "name:ara_x_preferred":[
        "\u0634\u0639\u0628 \u0627\u0644\u0639\u0648\u062c\u0627\u0621"
    ],
    "name:eng_x_preferred":[
        "Sha'b Al 'Awja"
    ],
    "name:eng_x_variant":[
        "Waridah"
    ],
    "qs:name":"Sha\u2018b al \u2018Awj\u0101\u2019",
    "qs:photos_9r":0,
    "qs:photos_sr":0,
    "qs:pop_sr":"1",
    "wof:name":"Sha\u2018b al \u2018Awj\u0101\u2019",
    "wof:placetype":"locality",
    "wof:population":4
},
  "geometry": {"coordinates":[43.30032,16.17699],"type":"Point"}
}