{
  "type": "Feature",
  "properties": {
    "gn:admin1_code":"18.0",
    "gn:admin2_code":"3002.0",
    "gn:asciiname":"Al `Irfaf",
    "gn:country_code":"YE",
    "gn:dem":2121,
    "gn:feature_class":"P",
    "gn:feature_code":"PPL",
    "gn:name":"Al \u2018Irf\u0101f",
    "gn:population":0,
    "gn:timezone":"Asia/Aden",
    "iso:country":"YE",
    "name:ara_x_preferred":[
        "Al \u2018Irf\u0101f"
    ],
    "wof:name":"Al `Irfaf",
    "wof:placetype":"locality"
},
  "geometry": {"coordinates":[44.66734,14.01234],"type":"Point"}
}