{
  "type": "Feature",
  "properties": {
    "gn:country":"YE",
    "gn:fcode":"PPL",
    "gn:pop":5,
    "iso:country":"YE",
    "name:ara_x_preferred":[
        "\u0645\u063a\u0631\u0628\u0629 \u0627\u0644\u0633\u0644\u0639\u0629"
    ],
    "name:eng_x_preferred":[
        "Maghribat As Sil'ah"
    ],
    "name:eng_x_variant":[
        "Al Mardah"
    ],
    "qs:name":"Maghribat as Sil\u2018ah",
    "qs:photos_9r":0,
    "qs:photos_sr":0,
    "qs:pop_sr":"1",
    "wof:name":"Maghribat as Sil\u2018ah",
    "wof:placetype":"locality",
    "wof:population":5
},
  "geometry": {"coordinates":[43.45389,16.24062],"type":"Point"}
}