{
  "type": "Feature",
  "properties": {
    "gn:admin1_code":"25.0",
    "gn:admin2_code":"1514.0",
    "gn:asciiname":"Ad Da`ah",
    "gn:country_code":"YE",
    "gn:dem":1683,
    "gn:feature_class":"P",
    "gn:feature_code":"PPL",
    "gn:name":"A\u1e11 \u1e10a\u2018ah",
    "gn:population":0,
    "gn:timezone":"Asia/Aden",
    "iso:country":"YE",
    "name:und_x_variant":[
        "A\u1e11 \u1e10a\u2018ah"
    ],
    "wof:name":"Ad Da`ah",
    "wof:placetype":"locality"
},
  "geometry": {"coordinates":[44.16848,13.35496],"type":"Point"}
}