{
  "type": "Feature",
  "properties": {
    "gn:admin1_code":"23.0",
    "gn:admin2_code":"1112.0",
    "gn:asciiname":"Al Khuzayjah",
    "gn:country_code":"YE",
    "gn:dem":2749,
    "gn:feature_class":"P",
    "gn:feature_code":"PPL",
    "gn:name":"Al Khuzayjah",
    "gn:population":0,
    "gn:timezone":"Asia/Aden",
    "iso:country":"YE",
    "wof:name":"Al Khuzayjah",
    "wof:placetype":"locality"
},
  "geometry": {"coordinates":[44.08031,13.87384],"type":"Point"}
}