{
  "type": "Feature",
  "properties": {
    "gn:country":"YE",
    "gn:fcode":"PPL",
    "gn:pop":8,
    "iso:country":"YE",
    "name:ara_x_preferred":[
        "\u062c\u0647\u0648\u0629 \u062b\u0645\u064a\u0631\u0629"
    ],
    "name:eng_x_preferred":[
        "Jahwat Thamirah"
    ],
    "qs:name":"Jahwat Tham\u012brah",
    "qs:photos_9r":0,
    "qs:photos_sr":0,
    "qs:pop_sr":"1",
    "wof:name":"Jahwat Tham\u012brah",
    "wof:placetype":"locality",
    "wof:population":8
},
  "geometry": {"coordinates":[43.28592,16.88767],"type":"Point"}
}