{
  "type": "Feature",
  "properties": {
    "gn:admin1_code":"25.0",
    "gn:admin2_code":"1508.0",
    "gn:asciiname":"Bayt az Zumaykir",
    "gn:country_code":"YE",
    "gn:dem":177,
    "gn:feature_class":"P",
    "gn:feature_code":"PPL",
    "gn:name":"Bayt az Zumayk\u012br",
    "gn:population":0,
    "gn:timezone":"Asia/Aden",
    "iso:country":"YE",
    "name:und_x_variant":[
        "Bayt az Zumayk\u012br"
    ],
    "wof:name":"Bayt az Zumaykir",
    "wof:placetype":"locality"
},
  "geometry": {"coordinates":[43.48981,13.26043],"type":"Point"}
}