{
  "type": "Feature",
  "properties": {
    "gn:country":"YE",
    "gn:fcode":"PPL",
    "gn:population":22,
    "iso:country":"YE",
    "name:ara_x_preferred":[
        "\u0622\u0644 \u0648\u0636\u0627\u0646"
    ],
    "qs:name":"\u0100l Wa\u1e11\u0101n",
    "qs:photos_9r":0,
    "qs:photos_sr":0,
    "qs:pop_sr":"1",
    "wof:name":"\u0100l Wa\u1e11\u0101n",
    "wof:placetype":"locality",
    "wof:population":22
},
  "geometry": {"coordinates":[43.77656,16.90704],"type":"Point"}
}