{
  "type": "Feature",
  "properties": {
    "gn:country":"YE",
    "gn:fcode":"PPL",
    "gn:pop":14,
    "iso:country":"YE",
    "name:ara_x_preferred":[
        "\u0627\u0644\u0646\u0642\u0648\u0639"
    ],
    "qs:name":"An Naq\u016b\u2018",
    "qs:photos_9r":0,
    "qs:photos_sr":0,
    "qs:pop_sr":"1",
    "wof:name":"An Naq\u016b\u2018",
    "wof:placetype":"locality",
    "wof:population":14
},
  "geometry": {"coordinates":[43.80729,16.90128],"type":"Point"}
}