{
  "type": "Feature",
  "properties": {
    "gn:admin1_code":"15.0",
    "gn:admin2_code":"2206.0",
    "gn:asciiname":"Al Ghuriyah",
    "gn:country_code":"YE",
    "gn:dem":1311,
    "gn:feature_class":"P",
    "gn:feature_code":"PPL",
    "gn:name":"Al Gh\u016br\u012byah",
    "gn:population":0,
    "gn:timezone":"Asia/Aden",
    "iso:country":"YE",
    "name:ara_x_preferred":[
        "\u0627\u0644\u063a\u0648\u0631\u064a\u0629"
    ],
    "name:und_x_variant":[
        "Al Gh\u016br\u012byah"
    ],
    "wof:name":"Al Ghuriyah",
    "wof:placetype":"locality"
},
  "geometry": {"coordinates":[43.18669000000001,16.91049],"type":"Point"}
}