{
  "type": "Feature",
  "properties": {
    "gn:admin1_code":"19.0",
    "gn:admin2_code":"2908.0",
    "gn:asciiname":"Al Mashwaqi",
    "gn:country_code":"YE",
    "gn:dem":1148,
    "gn:feature_class":"P",
    "gn:feature_code":"PPLL",
    "gn:name":"Al Mashw\u0101q\u012b",
    "gn:population":0,
    "gn:timezone":"Asia/Aden",
    "iso:country":"YE",
    "name:ara_x_preferred":[
        "\u0627\u0644\u0645\u0634\u0648\u0627\u0642\u064a"
    ],
    "name:und_x_variant":[
        "Al Mashw\u0101q\u012b"
    ],
    "wof:name":"Al Mashwaqi",
    "wof:placetype":"locality"
},
  "geometry": {"coordinates":[43.80703,16.09318],"type":"Point"}
}