{
  "type": "Feature",
  "properties": {
    "gn:admin1_code":"18.0",
    "gn:admin2_code":"3004.0",
    "gn:asciiname":"Thawwan",
    "gn:country_code":"YE",
    "gn:dem":2101,
    "gn:feature_class":"P",
    "gn:feature_code":"PPL",
    "gn:name":"Thaww\u0101n",
    "gn:population":0,
    "gn:timezone":"Asia/Aden",
    "iso:country":"YE",
    "name:und_x_variant":[
        "Thawan",
        "Thaww\u0101n"
    ],
    "wof:name":"Thawwan",
    "wof:placetype":"locality"
},
  "geometry": {"coordinates":[44.87215,13.89224],"type":"Point"}
}