{
  "type": "Feature",
  "properties": {
    "gn:country":"YE",
    "gn:fcode":"PPL",
    "gn:population":1,
    "iso:country":"YE",
    "name:ara_x_preferred":[
        "\u0627\u0644\u062d\u0636\u064a\u0646"
    ],
    "qs:name":"Al \u1e28u\u1e11ayn",
    "qs:photos_9r":0,
    "qs:photos_sr":0,
    "qs:pop_sr":"1",
    "wof:name":"Al \u1e28u\u1e11ayn",
    "wof:placetype":"locality",
    "wof:population":1
},
  "geometry": {"coordinates":[43.81062,13.40766],"type":"Point"}
}