{
  "type": "Feature",
  "properties": {
    "gn:admin1_code":"14.0",
    "gn:admin2_code":"2611.0",
    "gn:asciiname":"Al Mitrash",
    "gn:country_code":"YE",
    "gn:dem":2157,
    "gn:feature_class":"P",
    "gn:feature_code":"PPL",
    "gn:name":"Al Mi\u0163r\u0101sh",
    "gn:population":9,
    "gn:timezone":"Asia/Aden",
    "iso:country":"YE",
    "name:ara_x_preferred":[
        "Al Mi\u0163r\u0101sh"
    ],
    "name:ara_x_variant":[
        "\u0627\u0644\u0645\u0637\u0631\u0627\u0634"
    ],
    "wof:name":"Al Mitrash",
    "wof:placetype":"locality",
    "wof:population":9
},
  "geometry": {"coordinates":[45.3904,14.69919],"type":"Point"}
}