{
  "type": "Feature",
  "properties": {
    "gn:country":"YE",
    "gn:fcode":"PPL",
    "gn:population":3,
    "iso:country":"YE",
    "name:ara_x_preferred":[
        "\u0636\u0631\u0628 \u0642\u062d\u0645\u0640\u0627\u0646"
    ],
    "name:eng_x_preferred":[
        "Darb Qahman"
    ],
    "name:eng_x_variant":[
        "Al Bi\u0163\u0101\u1e29"
    ],
    "qs_pg:aaroncc":"YE",
    "qs_pg:gn_country":"YE",
    "qs_pg:gn_fcode":"PPL",
    "qs_pg:gn_pop":3,
    "qs_pg:name":"\u1e10arb Qa\u1e29m\u0101n",
    "qs_pg:photos_9r":0,
    "qs_pg:photos_sr":0,
    "qs_pg:pop_sr":1,
    "qs_pg:qs_pg_placetype":"locality",
    "wof:name":"\u1e10arb Qa\u1e29m\u0101n",
    "wof:placetype":"locality",
    "wof:population":3
},
  "geometry": {"coordinates":[43.59944,16.14417],"type":"Point"}
}