{
  "type": "Feature",
  "properties": {
    "gn:admin1_code":"20.0",
    "gn:admin2_code":"1412.0",
    "gn:asciiname":"Hammat Hayran",
    "gn:country_code":"YE",
    "gn:dem":2070,
    "gn:feature_class":"P",
    "gn:feature_code":"PPL",
    "gn:name":"\u1e28ammat \u1e28ayr\u0101n",
    "gn:population":0,
    "gn:timezone":"Asia/Aden",
    "iso:country":"YE",
    "name:und_x_variant":[
        "\u1e28ammat \u1e28ayr\u0101n"
    ],
    "wof:name":"Hammat Hayran",
    "wof:placetype":"locality"
},
  "geometry": {"coordinates":[45.26674000000001,14.52244],"type":"Point"}
}