{
  "type": "Feature",
  "properties": {
    "gn:admin1_code":"23.0",
    "gn:admin2_code":"1109.0",
    "gn:asciiname":"As Salabah",
    "gn:country_code":"YE",
    "gn:dem":1383,
    "gn:feature_class":"P",
    "gn:feature_code":"PPL",
    "gn:name":"A\u015f \u015ealabah",
    "gn:population":0,
    "gn:timezone":"Asia/Aden",
    "iso:country":"YE",
    "name:und_x_variant":[
        "A\u015f \u015ealabah"
    ],
    "wof:name":"As Salabah",
    "wof:placetype":"locality"
},
  "geometry": {"coordinates":[43.982,14.08992],"type":"Point"}
}