{
  "type": "Feature",
  "properties": {
    "gn:admin1_code":"1.0",
    "gn:admin2_code":"1204.0",
    "gn:asciiname":"Sakin Ahl `Ubayd",
    "gn:country_code":"YE",
    "gn:dem":851,
    "gn:feature_class":"P",
    "gn:feature_code":"PPL",
    "gn:name":"S\u0101kin Ahl \u2018Ubayd",
    "gn:population":0,
    "gn:timezone":"Asia/Aden",
    "iso:country":"YE",
    "name:und_x_variant":[
        "S\u0101kin",
        "S\u0101kin Ahl \u2018Ubayd"
    ],
    "wof:name":"Sakin Ahl `Ubayd",
    "wof:placetype":"locality"
},
  "geometry": {"coordinates":[45.89774,13.78397],"type":"Point"}
}