{
  "type": "Feature",
  "properties": {
    "gn:country":"YE",
    "gn:fcode":"PPL",
    "gn:population":31,
    "iso:country":"YE",
    "name:ara_x_preferred":[
        "\u0627\u0644 \u0627\u0644\u0648\u063a\u0628\u064a"
    ],
    "name:eng_x_preferred":[
        "Al Al Waghbi"
    ],
    "name:eng_x_variant":[
        "Bayt al Jall\u0101l"
    ],
    "qs:name":"\u0100l al Waghb\u012b",
    "qs:photos_9r":0,
    "qs:photos_sr":0,
    "qs:pop_sr":"1",
    "wof:name":"\u0100l al Waghb\u012b",
    "wof:placetype":"locality",
    "wof:population":31
},
  "geometry": {"coordinates":[43.44743,17.40142],"type":"Point"}
}