{
  "type": "Feature",
  "properties": {
    "gn:admin1_code":"16.0",
    "gn:admin2_code":"2302.0",
    "gn:asciiname":"Ad Dawa`ir",
    "gn:country_code":"YE",
    "gn:dem":2605,
    "gn:feature_class":"P",
    "gn:feature_code":"PPL",
    "gn:name":"Ad Daw\u0101\u2018ir",
    "gn:population":0,
    "gn:timezone":"Asia/Aden",
    "iso:country":"YE",
    "name:und_x_variant":[
        "Ad Daw\u0101\u2018ir"
    ],
    "wof:name":"Ad Dawa`ir",
    "wof:placetype":"locality"
},
  "geometry": {"coordinates":[44.19281,15.90741],"type":"Point"}
}