{
  "type": "Feature",
  "properties": {
    "gn:country":"YE",
    "gn:fcode":"PPL",
    "gn:pop":34,
    "iso:country":"YE",
    "name:ara_x_preferred":[
        "S\u016bq Hint"
    ],
    "name:ara_x_variant":[
        "\u0633\u0648\u0642 \u0647\u0646\u062a"
    ],
    "name:eng_x_preferred":[
        "SUq Hint"
    ],
    "name:eng_x_variant":[
        "Ar Rakabah"
    ],
    "qs:name":"S\u016bq Hint",
    "qs:photos_9r":0,
    "qs:photos_sr":0,
    "qs:pop_sr":"1",
    "wof:name":"S\u016bq Hint",
    "wof:placetype":"locality",
    "wof:population":34
},
  "geometry": {"coordinates":[45.32352,15.4618],"type":"Point"}
}