{
  "type": "Feature",
  "properties": {
    "gn:admin1_code":"15.0",
    "gn:admin2_code":"2215.0",
    "gn:asciiname":"Ar Raq'ah",
    "gn:country_code":"YE",
    "gn:dem":1963,
    "gn:feature_class":"P",
    "gn:feature_code":"PPL",
    "gn:name":"Ar Raq\u2018ah",
    "gn:population":14,
    "gn:timezone":"Asia/Aden",
    "iso:country":"YE",
    "name:ara_x_preferred":[
        "\u0627\u0644\u0631\u0642\u0639\u0629"
    ],
    "name:und_x_variant":[
        "Ar Raq\u2018ah"
    ],
    "wof:name":"Ar Raq'ah",
    "wof:placetype":"locality",
    "wof:population":14
},
  "geometry": {"coordinates":[43.77929,16.89674],"type":"Point"}
}