{
  "type": "Feature",
  "properties": {
    "gn:admin1_code":"18.0",
    "gn:admin2_code":"3001.0",
    "gn:asciiname":"Al Jaburiyah",
    "gn:country_code":"YE",
    "gn:dem":2014,
    "gn:feature_class":"P",
    "gn:feature_code":"PPL",
    "gn:name":"Al Jab\u016br\u012byah",
    "gn:population":0,
    "gn:timezone":"Asia/Aden",
    "iso:country":"YE",
    "name:und_x_variant":[
        "Al Jab\u016br\u012byah"
    ],
    "wof:name":"Al Jaburiyah",
    "wof:placetype":"locality"
},
  "geometry": {"coordinates":[44.87633,14.14854],"type":"Point"}
}