{
  "type": "Feature",
  "properties": {
    "gn:admin1_code":"19.0",
    "gn:admin2_code":"2916.0",
    "gn:asciiname":"Bayt Thamir",
    "gn:country_code":"YE",
    "gn:dem":1784,
    "gn:feature_class":"P",
    "gn:feature_code":"PPL",
    "gn:name":"Bayt Th\u0101mir",
    "gn:population":0,
    "gn:timezone":"Asia/Aden",
    "iso:country":"YE",
    "name:und_x_variant":[
        "Bayt Th\u0101mir"
    ],
    "wof:name":"Bayt Thamir",
    "wof:placetype":"locality"
},
  "geometry": {"coordinates":[43.72731,15.53922],"type":"Point"}
}