{
  "type": "Feature",
  "properties": {
    "gn:admin1_code":"23.0",
    "gn:admin2_code":"1109.0",
    "gn:asciiname":"Al Habil",
    "gn:country_code":"YE",
    "gn:dem":630,
    "gn:feature_class":"P",
    "gn:feature_code":"PPL",
    "gn:name":"Al \u1e28ab\u012bl",
    "gn:population":0,
    "gn:timezone":"Asia/Aden",
    "iso:country":"YE",
    "name:fas_x_preferred":[
        "\u0627\u0644\u0647\u0628\u06cc\u0644"
    ],
    "name:nno_x_preferred":[
        "Al Habil"
    ],
    "name:und_x_variant":[
        "Al \u1e28ab\u012bl"
    ],
    "wof:name":"Al Habil",
    "wof:placetype":"locality"
},
  "geometry": {"coordinates":[43.75453,14.0996],"type":"Point"}
}