{
  "type": "Feature",
  "properties": {
    "gn:admin1_code":"26.0",
    "gn:admin2_code":"1310.0",
    "gn:asciiname":"Bayt Harun",
    "gn:country_code":"YE",
    "gn:dem":2168,
    "gn:feature_class":"P",
    "gn:feature_code":"PPL",
    "gn:name":"Bayt H\u0101r\u016bn",
    "gn:population":0,
    "gn:timezone":"Asia/Aden",
    "iso:country":"YE",
    "name:ara_x_preferred":[
        "\u0628\u064a\u062a \u0647\u0627\u0631\u0648\u0646"
    ],
    "name:und_x_variant":[
        "Bayt H\u0101r\u016bn"
    ],
    "wof:name":"Bayt Harun",
    "wof:placetype":"locality"
},
  "geometry": {"coordinates":[44.21735,15.54317],"type":"Point"}
}