{
  "type": "Feature",
  "properties": {
    "gn:admin1_code":"8.0",
    "gn:admin2_code":"1810.0",
    "gn:asciiname":"Mahall as Sumayn",
    "gn:country_code":"YE",
    "gn:dem":357,
    "gn:feature_class":"P",
    "gn:feature_code":"PPL",
    "gn:name":"Ma\u1e29all as Sumayn",
    "gn:population":0,
    "gn:timezone":"Asia/Aden",
    "iso:country":"YE",
    "name:und_x_variant":[
        "Ma\u1e29all as Sumayn"
    ],
    "wof:name":"Mahall as Sumayn",
    "wof:placetype":"locality"
},
  "geometry": {"coordinates":[43.42722,15.1086],"type":"Point"}
}