{
  "type": "Feature",
  "properties": {
    "gn:admin1_code":"22.0",
    "gn:admin2_code":"1726.0",
    "gn:asciiname":"Bayt az Zayn",
    "gn:country_code":"YE",
    "gn:dem":1193,
    "gn:feature_class":"P",
    "gn:feature_code":"PPL",
    "gn:name":"Bayt az Zayn",
    "gn:population":0,
    "gn:timezone":"Asia/Aden",
    "iso:country":"YE",
    "wof:name":"Bayt az Zayn",
    "wof:placetype":"locality"
},
  "geometry": {"coordinates":[43.53559,15.61191],"type":"Point"}
}