{
  "type": "Feature",
  "properties": {
    "gn:gn_country":"YE",
    "gn:gn_fcode":"PPL",
    "gn:gn_pop":11,
    "gn:population":11,
    "iso:country":"YE",
    "name:ara_x_preferred":[
        "\u0627\u0644\u0643\u0648\u0627\u0644"
    ],
    "qs_pg:aaroncc":"YE",
    "qs_pg:gn_country":"YE",
    "qs_pg:gn_fcode":"PPL",
    "qs_pg:gn_pop":11,
    "qs_pg:name":"Al Kaw\u0101l",
    "qs_pg:photos_9r":0,
    "qs_pg:photos_sr":0,
    "qs_pg:pop_sr":1,
    "qs_pg:qs_pg_placetype":"locality",
    "wof:name":"Al Kaw\u0101l",
    "wof:placetype":"locality",
    "wof:population":11
},
  "geometry": {"coordinates":[43.43294,16.14233],"type":"Point"}
}