{
  "type": "Feature",
  "properties": {
    "gn:admin1_code":"15.0",
    "gn:admin2_code":"2211.0",
    "gn:asciiname":"Al Mihtawiyah",
    "gn:country_code":"YE",
    "gn:dem":1900,
    "gn:feature_class":"P",
    "gn:feature_code":"PPL",
    "gn:name":"Al Mi\u1e29taw\u012byah",
    "gn:population":0,
    "gn:timezone":"Asia/Aden",
    "iso:country":"YE",
    "name:ara_x_preferred":[
        "\u0627\u0644\u0645\u062d\u062a\u0648\u064a\u0629"
    ],
    "name:und_x_variant":[
        "Al Mi\u1e29taw\u012byah"
    ],
    "wof:name":"Al Mihtawiyah",
    "wof:placetype":"locality"
},
  "geometry": {"coordinates":[43.71908,17.0629],"type":"Point"}
}