{
  "type": "Feature",
  "properties": {
    "gn:admin1_code":"24.0",
    "gn:admin2_code":"2507.0",
    "gn:asciiname":"Al `Uqlah",
    "gn:country_code":"YE",
    "gn:dem":1199,
    "gn:feature_class":"P",
    "gn:feature_code":"PPL",
    "gn:name":"Al \u2018Uqlah",
    "gn:population":0,
    "gn:timezone":"Asia/Aden",
    "iso:country":"YE",
    "name:und_x_variant":[
        "Al Uglah",
        "Al \u2018Uqlah"
    ],
    "wof:name":"Al `Uqlah",
    "wof:placetype":"locality"
},
  "geometry": {"coordinates":[44.97222,13.45611],"type":"Point"}
}