{
  "type": "Feature",
  "properties": {
    "gn:admin1_code":"8.0",
    "gn:admin2_code":"1817.0",
    "gn:asciiname":"Al Khayi'",
    "gn:country_code":"YE",
    "gn:dem":298,
    "gn:feature_class":"P",
    "gn:feature_code":"PPL",
    "gn:name":"Al Kh\u0101yi\u2018",
    "gn:population":0,
    "gn:timezone":"Asia/Aden",
    "iso:country":"YE",
    "name:ara_x_preferred":[
        "Al Kh\u0101yi\u2018"
    ],
    "wof:name":"Al Khayi'",
    "wof:placetype":"locality"
},
  "geometry": {"coordinates":[43.48616,14.60617],"type":"Point"}
}