{
  "type": "Feature",
  "properties": {
    "gn:admin1_code":"16.0",
    "gn:admin2_code":"2302.0",
    "gn:asciiname":"Bayt Rabih",
    "gn:country_code":"YE",
    "gn:dem":2614,
    "gn:feature_class":"P",
    "gn:feature_code":"PPL",
    "gn:name":"Bayt R\u0101bi\u1e29",
    "gn:population":0,
    "gn:timezone":"Asia/Aden",
    "iso:country":"YE",
    "name:ara_x_preferred":[
        "\u0628\u064a\u062a \u0631\u0627\u0628\u062d"
    ],
    "name:und_x_variant":[
        "Bayt R\u0101bi\u1e29"
    ],
    "wof:name":"Bayt Rabih",
    "wof:placetype":"locality"
},
  "geometry": {"coordinates":[44.17637,15.86705],"type":"Point"}
}