{
  "type": "Feature",
  "properties": {
    "gn:admin1_code":"10.0",
    "gn:admin2_code":"2707.0",
    "gn:asciiname":"Al Hajarah",
    "gn:country_code":"YE",
    "gn:dem":549,
    "gn:feature_class":"P",
    "gn:feature_code":"PPL",
    "gn:name":"Al Hajarah",
    "gn:population":0,
    "gn:timezone":"Asia/Aden",
    "iso:country":"YE",
    "wof:name":"Al Hajarah",
    "wof:placetype":"locality"
},
  "geometry": {"coordinates":[43.51888,15.20675],"type":"Point"}
}