{
  "type": "Feature",
  "properties": {
    "gn:admin1_code":"11.0",
    "gn:admin2_code":"2004.0",
    "gn:asciiname":"Al Qurun",
    "gn:cc2":"YE",
    "gn:country_code":"YE",
    "gn:dem":1945,
    "gn:feature_class":"P",
    "gn:feature_code":"PPL",
    "gn:name":"Al Qur\u016bn",
    "gn:population":0,
    "gn:timezone":"Asia/Aden",
    "iso:country":"YE",
    "name:ara_x_preferred":[
        "Al Qur\u016bn"
    ],
    "name:und_x_variant":[
        "El Gerun",
        "Qur\u016bn",
        "Quram",
        "Qurum"
    ],
    "wof:name":"Al Qurun",
    "wof:placetype":"locality"
},
  "geometry": {"coordinates":[44.18333,14.46667],"type":"Point"}
}