{
  "type": "Feature",
  "properties": {
    "gn:country":"YE",
    "gn:fcode":"PPL",
    "gn:pop":4,
    "iso:country":"YE",
    "name:ara_x_preferred":[
        "Ath Thiry\u0101"
    ],
    "name:ara_x_variant":[
        "\u0627\u0644\u062b\u0631\u064a\u0627"
    ],
    "name:eng_x_preferred":[
        "Ath Thirya"
    ],
    "qs:name":"Ath Thiry\u0101",
    "qs:photos_9r":0,
    "qs:photos_sr":0,
    "qs:pop_sr":"1",
    "wof:name":"Ath Thiry\u0101",
    "wof:placetype":"locality",
    "wof:population":4
},
  "geometry": {"coordinates":[45.80921,14.1469],"type":"Point"}
}