{
  "type": "Feature",
  "properties": {
    "gn:country":"YE",
    "gn:fcode":"PPL",
    "gn:pop":4,
    "iso:country":"YE",
    "name:ara_x_preferred":[
        "\u0628\u064a\u062a \u0627\u0644\u062c\u0627\u062f\u0639\u064a"
    ],
    "name:eng_x_preferred":[
        "Bayt Al Jad'i"
    ],
    "name:eng_x_variant":[
        "Al Bad\u2018\u012b"
    ],
    "qs:name":"Bayt al J\u0101d\u2018\u012b",
    "qs:photos_9r":0,
    "qs:photos_sr":0,
    "qs:pop_sr":"1",
    "wof:name":"Bayt al J\u0101d\u2018\u012b",
    "wof:placetype":"locality",
    "wof:population":4
},
  "geometry": {"coordinates":[43.3788,16.33393],"type":"Point"}
}