{
  "type": "Feature",
  "properties": {
    "gn:admin1_code":"20.0",
    "gn:admin2_code":"1407.0",
    "gn:asciiname":"Al Barraq",
    "gn:country_code":"YE",
    "gn:dem":1969,
    "gn:feature_class":"P",
    "gn:feature_code":"PPL",
    "gn:name":"Al Barr\u0101q",
    "gn:population":0,
    "gn:timezone":"Asia/Aden",
    "iso:country":"YE",
    "name:und_x_variant":[
        "Al Barr\u0101q"
    ],
    "wof:name":"Al Barraq",
    "wof:placetype":"locality"
},
  "geometry": {"coordinates":[45.42948,14.21577],"type":"Point"}
}