{
  "type": "Feature",
  "properties": {
    "gn:country":"YE",
    "gn:fcode":"PPL",
    "gn:population":36,
    "iso:country":"YE",
    "name:ara_x_preferred":[
        "\u0627\u0644\u062d\u0630\u0627\u064a\u0629"
    ],
    "qs_pg:aaroncc":"YE",
    "qs_pg:gn_country":"YE",
    "qs_pg:gn_fcode":"PPL",
    "qs_pg:gn_pop":36,
    "qs_pg:name":"Al \u1e28idh\u0101yah",
    "qs_pg:photos_9r":0,
    "qs_pg:photos_sr":0,
    "qs_pg:pop_sr":1,
    "qs_pg:qs_pg_placetype":"locality",
    "wof:name":"Al \u1e28idh\u0101yah",
    "wof:placetype":"locality",
    "wof:population":36
},
  "geometry": {"coordinates":[43.39275,16.83714],"type":"Point"}
}