{
  "type": "Feature",
  "properties": {
    "gn:country":"YE",
    "gn:fcode":"PPL",
    "gn:pop":5,
    "iso:country":"YE",
    "name:ara_x_preferred":[
        "\u0627\u0644\u0639\u0634\u0629"
    ],
    "qs:name":"Al \u2018Ashshah",
    "qs:photos_9r":0,
    "qs:photos_sr":0,
    "qs:pop_sr":"1",
    "wof:name":"Al \u2018Ashshah",
    "wof:placetype":"locality",
    "wof:population":5
},
  "geometry": {"coordinates":[44.01868,16.54508],"type":"Point"}
}