{
  "type": "Feature",
  "properties": {
    "gn:admin1_code":"16.0",
    "gn:admin2_code":"2312.0",
    "gn:asciiname":"Wadi Mamar",
    "gn:country_code":"YE",
    "gn:dem":2111,
    "gn:feature_class":"P",
    "gn:feature_code":"PPL",
    "gn:name":"W\u0101d\u012b M\u0101mar",
    "gn:population":0,
    "gn:timezone":"Asia/Aden",
    "iso:country":"YE",
    "name:und_x_variant":[
        "W\u0101d\u012b M\u0101mar"
    ],
    "wof:name":"Wadi Mamar",
    "wof:placetype":"locality"
},
  "geometry": {"coordinates":[44.73897,15.29037],"type":"Point"}
}