{
  "type": "Feature",
  "properties": {
    "gn:admin1_code":"19.0",
    "gn:admin2_code":"2903.0",
    "gn:asciiname":"Ash Shati",
    "gn:country_code":"YE",
    "gn:dem":1198,
    "gn:feature_class":"P",
    "gn:feature_code":"PPL",
    "gn:name":"Ash Sh\u0101\u0163\u012b",
    "gn:population":0,
    "gn:timezone":"Asia/Aden",
    "iso:country":"YE",
    "name:ara_x_preferred":[
        "Ash Sh\u0101\u0163\u012b"
    ],
    "name:ara_x_variant":[
        "\u0627\u0644\u0634\u0627\u0637\u064a"
    ],
    "wof:name":"Ash Shati",
    "wof:placetype":"locality"
},
  "geometry": {"coordinates":[43.85364000000001,16.25167],"type":"Point"}
}