{
  "type": "Feature",
  "properties": {
    "gn:admin1_code":"19.0",
    "gn:admin2_code":"2916.0",
    "gn:asciiname":"Al Afqur",
    "gn:country_code":"YE",
    "gn:dem":1750,
    "gn:feature_class":"P",
    "gn:feature_code":"PPL",
    "gn:name":"Al Afq\u016br",
    "gn:population":0,
    "gn:timezone":"Asia/Aden",
    "iso:country":"YE",
    "name:ara_x_preferred":[
        "Al Afq\u016br"
    ],
    "wof:name":"Al Afqur",
    "wof:placetype":"locality"
},
  "geometry": {"coordinates":[43.69592,15.56159],"type":"Point"}
}