{
  "type": "Feature",
  "properties": {
    "gn:admin1_code":"22.0",
    "gn:admin2_code":"1722.0",
    "gn:asciiname":"Birayqit",
    "gn:country_code":"YE",
    "gn:dem":323,
    "gn:feature_class":"P",
    "gn:feature_code":"PPL",
    "gn:name":"Birayqi\u0163",
    "gn:population":0,
    "gn:timezone":"Asia/Aden",
    "iso:country":"YE",
    "name:und_x_variant":[
        "Birayqi\u0163"
    ],
    "wof:name":"Birayqit",
    "wof:placetype":"locality"
},
  "geometry": {"coordinates":[43.2657,15.81972],"type":"Point"}
}