{
  "type": "Feature",
  "properties": {
    "gn:admin1_code":"11.0",
    "gn:admin2_code":"2007.0",
    "gn:asciiname":"Bani Salamah",
    "gn:country_code":"YE",
    "gn:dem":987,
    "gn:feature_class":"P",
    "gn:feature_code":"PPL",
    "gn:name":"Ban\u012b Salamah",
    "gn:population":0,
    "gn:timezone":"Asia/Aden",
    "iso:country":"YE",
    "name:und_x_variant":[
        "Ban\u012b Salamah"
    ],
    "wof:name":"Bani Salamah",
    "wof:placetype":"locality"
},
  "geometry": {"coordinates":[43.56603,14.25599],"type":"Point"}
}