{
  "type": "Feature",
  "properties": {
    "gn:admin1_code":"23.0",
    "gn:admin2_code":"1113.0",
    "gn:asciiname":"As Sanahi",
    "gn:country_code":"YE",
    "gn:dem":2181,
    "gn:feature_class":"P",
    "gn:feature_code":"PPL",
    "gn:name":"As San\u0101\u1e29\u012b",
    "gn:population":0,
    "gn:timezone":"Asia/Aden",
    "iso:country":"YE",
    "name:ara_x_preferred":[
        "\u0627\u0644\u0633\u0646\u0627\u062d\u064a"
    ],
    "name:und_x_variant":[
        "As San\u0101\u1e29\u012b",
        "Sanahi"
    ],
    "wof:name":"As Sanahi",
    "wof:placetype":"locality"
},
  "geometry": {"coordinates":[44.38664,14.00187],"type":"Point"}
}