{
  "type": "Feature",
  "properties": {
    "gn:admin1_code":"24.0",
    "gn:admin2_code":"2512.0",
    "gn:asciiname":"Shararah",
    "gn:country_code":"YE",
    "gn:dem":1010,
    "gn:feature_class":"P",
    "gn:feature_code":"PPL",
    "gn:name":"Shar\u0101rah",
    "gn:population":0,
    "gn:timezone":"Asia/Aden",
    "iso:country":"YE",
    "name:ara_x_preferred":[
        "\u0634\u0631\u0627\u0631\u0629"
    ],
    "name:nno_x_preferred":[
        "Shararah"
    ],
    "name:und_x_variant":[
        "Shar\u0101rah"
    ],
    "wof:name":"Shararah",
    "wof:placetype":"locality"
},
  "geometry": {"coordinates":[44.16334000000001,13.16149],"type":"Point"}
}