{
  "type": "Feature",
  "properties": {
    "gn:country":"YE",
    "gn:fcode":"PPL",
    "gn:population":2,
    "iso:country":"YE",
    "name:ara_x_preferred":[
        "\u0627\u0644\u0623\u0646\u0635\u0628"
    ],
    "name:eng_x_preferred":[
        "Al Ansab"
    ],
    "name:eng_x_variant":[
        "Al Muw\u0101simah"
    ],
    "qs:name":"Al An\u015fab",
    "qs:photos_9r":0,
    "qs:photos_sr":0,
    "qs:pop_sr":"1",
    "wof:name":"Al An\u015fab",
    "wof:placetype":"locality",
    "wof:population":2
},
  "geometry": {"coordinates":[45.21026,14.85922],"type":"Point"}
}