{
  "type": "Feature",
  "properties": {
    "gn:admin1_code":"16.0",
    "gn:admin2_code":"2306.0",
    "gn:asciiname":"Wadi al Jar",
    "gn:country_code":"YE",
    "gn:dem":1618,
    "gn:feature_class":"P",
    "gn:feature_code":"PPL",
    "gn:name":"W\u0101d\u012b al J\u0101r",
    "gn:population":0,
    "gn:timezone":"Asia/Aden",
    "iso:country":"YE",
    "name:und_x_variant":[
        "W\u0101d\u012b al J\u0101r"
    ],
    "wof:name":"Wadi al Jar",
    "wof:placetype":"locality"
},
  "geometry": {"coordinates":[44.19167,14.995],"type":"Point"}
}