{
  "type": "Feature",
  "properties": {
    "gn:country":"YE",
    "gn:fcode":"PPL",
    "gn:population":7,
    "iso:country":"YE",
    "name:ara_x_preferred":[
        "\u2018\u0100dhir \u1e28idh\u0101\u2019"
    ],
    "name:ara_x_variant":[
        "\u0639\u0627\u0630\u0631 \u062d\u0630\u0627\u0621"
    ],
    "name:eng_x_preferred":[
        "Adhir Hidha"
    ],
    "name:eng_x_variant":[
        "\u2018Arw\u0101n",
        "'Adhir Hidha"
    ],
    "qs:name":"\u2018\u0100dhir \u1e28idh\u0101\u2019",
    "qs:photos_9r":0,
    "qs:photos_sr":0,
    "qs:pop_sr":"1",
    "wof:name":"\u2018\u0100dhir \u1e28idh\u0101\u2019",
    "wof:placetype":"locality",
    "wof:population":7
},
  "geometry": {"coordinates":[43.72138,16.05457],"type":"Point"}
}