{
  "type": "Feature",
  "properties": {
    "gn:admin1_code":"21.0",
    "gn:admin2_code":"1610.0",
    "gn:asciiname":"Ash Sharj",
    "gn:country_code":"YE",
    "gn:dem":2157,
    "gn:feature_class":"P",
    "gn:feature_code":"PPL",
    "gn:name":"Ash Sharj",
    "gn:population":0,
    "gn:timezone":"Asia/Aden",
    "iso:country":"YE",
    "name:ara_x_preferred":[
        "\u0627\u0644\u0634\u0631\u062c"
    ],
    "wof:name":"Ash Sharj",
    "wof:placetype":"locality"
},
  "geometry": {"coordinates":[44.27885,16.7792],"type":"Point"}
}