{
  "type": "Feature",
  "properties": {
    "gn:admin1_code":"8.0",
    "gn:admin2_code":"1809.0",
    "gn:asciiname":"Al Jammal",
    "gn:country_code":"YE",
    "gn:dem":57,
    "gn:feature_class":"P",
    "gn:feature_code":"PPL",
    "gn:name":"Al Jamm\u0101l",
    "gn:population":0,
    "gn:timezone":"Asia/Aden",
    "iso:country":"YE",
    "name:ara_x_preferred":[
        "\u0627\u0644\u062c\u0645\u0627\u0644"
    ],
    "name:und_x_variant":[
        "Al Jamm\u0101l"
    ],
    "wof:name":"Al Jammal",
    "wof:placetype":"locality"
},
  "geometry": {"coordinates":[43.02111,15.16985],"type":"Point"}
}