{
  "type": "Feature",
  "properties": {
    "gn:admin1_code":"8.0",
    "gn:admin2_code":"1810.0",
    "gn:asciiname":"Al Malwah",
    "gn:country_code":"YE",
    "gn:dem":245,
    "gn:feature_class":"P",
    "gn:feature_code":"PPL",
    "gn:name":"Al Malwah",
    "gn:population":0,
    "gn:timezone":"Asia/Aden",
    "iso:country":"YE",
    "name:und_x_variant":[
        "El M\u00e9lwe",
        "Al Malua",
        "El Malua",
        "Al Malwah"
    ],
    "wof:name":"Al Malwah",
    "wof:placetype":"locality"
},
  "geometry": {"coordinates":[43.3338,15.11596],"type":"Point"}
}