{
  "type": "Feature",
  "properties": {
    "gn:admin1_code":"11.0",
    "gn:admin2_code":"2011.0",
    "gn:asciiname":"Al Hudra",
    "gn:cc2":"YE",
    "gn:country_code":"YE",
    "gn:dem":1597,
    "gn:feature_class":"P",
    "gn:feature_code":"PPL",
    "gn:name":"Al Hudra",
    "gn:population":0,
    "gn:timezone":"Asia/Aden",
    "iso:country":"YE",
    "name:und_x_variant":[
        "El Hudra",
        "Al Hudra"
    ],
    "wof:name":"Al Hudra",
    "wof:placetype":"locality"
},
  "geometry": {"coordinates":[44.11667,14.91667],"type":"Point"}
}