{
  "type": "Feature",
  "properties": {
    "gn:admin1_code":"14.0",
    "gn:admin2_code":"2603.0",
    "gn:asciiname":"Suq al Harmal",
    "gn:country_code":"YE",
    "gn:dem":1202,
    "gn:feature_class":"P",
    "gn:feature_code":"PPL",
    "gn:name":"S\u016bq al \u1e28armal",
    "gn:population":0,
    "gn:timezone":"Asia/Aden",
    "iso:country":"YE",
    "name:und_x_variant":[
        "S\u016bq al \u1e28armal"
    ],
    "wof:name":"Suq al Harmal",
    "wof:placetype":"locality"
},
  "geometry": {"coordinates":[45.02783,15.59501],"type":"Point"}
}