{
  "type": "Feature",
  "properties": {
    "gn:country":"YE",
    "gn:fcode":"PPL",
    "gn:pop":5,
    "iso:country":"YE",
    "name:ara_x_preferred":[
        "\u0642\u0631\u0646 \u0628\u0646 \u0633\u0648\u0642\u0629"
    ],
    "name:eng_x_preferred":[
        "Qarn Bin SUqah"
    ],
    "qs:name":"Qarn Bin S\u016bqah",
    "qs:photos_9r":0,
    "qs:photos_sr":0,
    "qs:pop_sr":"1",
    "wof:name":"Qarn Bin S\u016bqah",
    "wof:placetype":"locality",
    "wof:population":5
},
  "geometry": {"coordinates":[43.28296,16.52181],"type":"Point"}
}