{
  "type": "Feature",
  "properties": {
    "gn:admin1_code":"23.0",
    "gn:admin2_code":"1102.0",
    "gn:asciiname":"Yalalah",
    "gn:country_code":"YE",
    "gn:dem":2292,
    "gn:feature_class":"P",
    "gn:feature_code":"PPL",
    "gn:name":"Yal\u0101lah",
    "gn:population":0,
    "gn:timezone":"Asia/Aden",
    "iso:country":"YE",
    "name:ara_x_preferred":[
        "\u064a\u0644\u0627\u0644\u0629"
    ],
    "name:und_x_variant":[
        "Yal\u0101lah"
    ],
    "wof:name":"Yalalah",
    "wof:placetype":"locality"
},
  "geometry": {"coordinates":[44.18,14.34769],"type":"Point"}
}