{
  "type": "Feature",
  "properties": {
    "gn:country":"YE",
    "gn:fcode":"PPL",
    "gn:pop":2,
    "iso:country":"YE",
    "name:ara_x_preferred":[
        "\u0634\u0639\u0628 \u0627\u0644\u062f\u0645\u064a"
    ],
    "name:eng_x_preferred":[
        "Sha'b Ad Dammi"
    ],
    "name:eng_x_variant":[
        "Al Ma\u015f\u0101b\u012b\u1e29 al \u2018Uly\u0101"
    ],
    "qs:name":"Sha\u2018b ad Damm\u012b",
    "qs:photos_9r":0,
    "qs:photos_sr":0,
    "qs:pop_sr":"1",
    "wof:name":"Sha\u2018b ad Damm\u012b",
    "wof:placetype":"locality",
    "wof:population":2
},
  "geometry": {"coordinates":[43.70618,16.08691],"type":"Point"}
}