{
  "type": "Feature",
  "properties": {
    "gn:admin1_code":"8.0",
    "gn:admin2_code":"1814.0",
    "gn:asciiname":"Mazra'at Yahya Muhammad",
    "gn:country_code":"YE",
    "gn:dem":33,
    "gn:feature_class":"P",
    "gn:feature_code":"PPL",
    "gn:name":"Mazra\u2018at Ya\u1e29y\u00e1 Mu\u1e29ammad",
    "gn:population":0,
    "gn:timezone":"Asia/Aden",
    "iso:country":"YE",
    "name:ara_x_preferred":[
        "\u0645\u0632\u0631\u0639\u0629 \u064a\u062d\u064a\u0649 \u0645\u062d\u0645\u062f"
    ],
    "name:und_x_variant":[
        "Mazra\u2018at Ya\u1e29y\u00e1 Mu\u1e29ammad"
    ],
    "wof:name":"Mazra'at Yahya Muhammad",
    "wof:placetype":"locality"
},
  "geometry": {"coordinates":[43.09031,14.72651],"type":"Point"}
}