{
  "type": "Feature",
  "properties": {
    "gn:country":"YE",
    "gn:fcode":"PPL",
    "gn:population":5,
    "iso:country":"YE",
    "name:ara_x_preferred":[
        "\u0631\u062d\u0627\u0628 \u0627\u0644\u0642\u0648\u0627\u0646\u0639"
    ],
    "name:eng_x_preferred":[
        "Rahab Al Qawani'"
    ],
    "name:vie_x_preferred":[
        "Al \u1e28aydirah"
    ],
    "qs:name":"Ra\u1e29\u0101b al Qaw\u0101ni\u2018",
    "qs:photos_9r":0,
    "qs:photos_sr":0,
    "qs:pop_sr":"1",
    "wof:name":"Ra\u1e29\u0101b al Qaw\u0101ni\u2018",
    "wof:placetype":"locality",
    "wof:population":5
},
  "geometry": {"coordinates":[45.32612,14.06832],"type":"Point"}
}