{
  "type": "Feature",
  "properties": {
    "gn:country":"YE",
    "gn:fcode":"PPL",
    "gn:population":1,
    "iso:country":"YE",
    "name:ara_x_preferred":[
        "\u0627\u0644\u0644\u062c\u0639\u0629"
    ],
    "name:eng_x_preferred":[
        "Al Laj'ah"
    ],
    "name:eng_x_variant":[
        "W\u0101d\u012b Bak\u012br"
    ],
    "qs:name":"Al Laj\u2018ah",
    "qs:photos_9r":0,
    "qs:photos_sr":0,
    "qs:pop_sr":"1",
    "wof:name":"Al Laj\u2018ah",
    "wof:placetype":"locality",
    "wof:population":1
},
  "geometry": {"coordinates":[43.9631,13.19864],"type":"Point"}
}