{
  "type": "Feature",
  "properties": {
    "gn:admin1_code":"11.0",
    "gn:admin2_code":"2007.0",
    "gn:asciiname":"Al Jum`ah",
    "gn:country_code":"YE",
    "gn:dem":315,
    "gn:feature_class":"P",
    "gn:feature_code":"PPL",
    "gn:name":"Al Jum\u2018ah",
    "gn:population":0,
    "gn:timezone":"Asia/Aden",
    "iso:country":"YE",
    "name:und_x_variant":[
        "Al Jum\u2018ah"
    ],
    "wof:name":"Al Jum`ah",
    "wof:placetype":"locality"
},
  "geometry": {"coordinates":[43.52798,14.27899],"type":"Point"}
}