{
  "type": "Feature",
  "properties": {
    "gn:country":"YE",
    "gn:fcode":"PPL",
    "gn:population":1,
    "iso:country":"YE",
    "name:ara_x_preferred":[
        "\u0645\u063a\u0631\u0628\u0629 \u0627\u0644\u0647\u0627\u062f\u0649"
    ],
    "name:eng_x_preferred":[
        "Maghrabat Al Hadi"
    ],
    "name:eng_x_variant":[
        "Al Buw\u0101rah"
    ],
    "qs:name":"Maghrabat al H\u0101d\u012b",
    "qs:photos_9r":0,
    "qs:photos_sr":0,
    "qs:pop_sr":"1",
    "wof:name":"Maghrabat al H\u0101d\u012b",
    "wof:placetype":"locality",
    "wof:population":1
},
  "geometry": {"coordinates":[43.69701,16.04734],"type":"Point"}
}