{
  "type": "Feature",
  "properties": {
    "gn:admin1_code":"25.0",
    "gn:admin2_code":"1505.0",
    "gn:asciiname":"Al Mu`aysir",
    "gn:country_code":"YE",
    "gn:dem":280,
    "gn:feature_class":"P",
    "gn:feature_code":"PPL",
    "gn:name":"Al Mu\u2018ay\u015fir",
    "gn:population":0,
    "gn:timezone":"Asia/Aden",
    "iso:country":"YE",
    "name:ara_x_preferred":[
        "\u0627\u0644\u0645\u0639\u064a\u0635\u0631"
    ],
    "name:und_x_variant":[
        "Al Mu\u2018ay\u015fir"
    ],
    "wof:name":"Al Mu`aysir",
    "wof:placetype":"locality"
},
  "geometry": {"coordinates":[43.49538,13.82946],"type":"Point"}
}