{
  "type": "Feature",
  "properties": {
    "gn:country":"YE",
    "gn:fcode":"PPL",
    "gn:population":1,
    "iso:country":"YE",
    "name:ara_x_preferred":[
        "\u0642\u0637\u0627\u0639 \u0627\u0644\u0635\u0631\u062d\u0629"
    ],
    "name:eng_x_preferred":[
        "Qita' As Sarhah"
    ],
    "name:eng_x_variant":[
        "Mil\u1e29aqat Khayr"
    ],
    "qs:name":"Qi\u0163\u0101\u2018 a\u015f \u015ear\u1e29ah",
    "qs:photos_9r":0,
    "qs:photos_sr":0,
    "qs:pop_sr":"1",
    "wof:name":"Qi\u0163\u0101\u2018 a\u015f \u015ear\u1e29ah",
    "wof:placetype":"locality",
    "wof:population":1
},
  "geometry": {"coordinates":[43.30486,16.18272],"type":"Point"}
}