{
  "type": "Feature",
  "properties": {
    "gn:admin1_code":"11.0",
    "gn:admin2_code":"2012.0",
    "gn:asciiname":"Maj`arah",
    "gn:country_code":"YE",
    "gn:dem":2198,
    "gn:feature_class":"P",
    "gn:feature_code":"PPL",
    "gn:name":"Maj\u2018arah",
    "gn:population":0,
    "gn:timezone":"Asia/Aden",
    "iso:country":"YE",
    "name:und_x_variant":[
        "Maj\u2018arah"
    ],
    "wof:name":"Maj`arah",
    "wof:placetype":"locality"
},
  "geometry": {"coordinates":[44.08685,14.68295],"type":"Point"}
}