{
  "type": "Feature",
  "properties": {
    "gn:country":"YE",
    "gn:fcode":"PPL",
    "gn:pop":1,
    "iso:country":"YE",
    "name:ara_x_preferred":[
        "\u0627\u0644\u0645\u0634\u0627\u064a\u0645\u0629"
    ],
    "name:eng_x_preferred":[
        "Al Mishayimah"
    ],
    "name:eng_x_variant":[
        "\u2018U\u015f\u016br"
    ],
    "qs:name":"Al Mish\u0101yimah",
    "qs:photos_9r":0,
    "qs:photos_sr":0,
    "qs:pop_sr":"1",
    "wof:name":"Al Mish\u0101yimah",
    "wof:placetype":"locality",
    "wof:population":1
},
  "geometry": {"coordinates":[43.30107,16.6694],"type":"Point"}
}