{
  "type": "Feature",
  "properties": {
    "gn:admin1_code":"25.0",
    "gn:admin2_code":"1503.0",
    "gn:asciiname":"Az Zawhah",
    "gn:country_code":"YE",
    "gn:dem":1397,
    "gn:feature_class":"P",
    "gn:feature_code":"PPL",
    "gn:name":"Az Zaw\u1e29ah",
    "gn:population":0,
    "gn:timezone":"Asia/Aden",
    "iso:country":"YE",
    "name:und_x_variant":[
        "Az Zaw\u1e29ah"
    ],
    "wof:name":"Az Zawhah",
    "wof:placetype":"locality"
},
  "geometry": {"coordinates":[43.84456,13.76084],"type":"Point"}
}