{
  "type": "Feature",
  "properties": {
    "gn:admin1_code":"21.0",
    "gn:admin2_code":"1603.0",
    "gn:asciiname":"Bani Shurayh",
    "gn:country_code":"YE",
    "gn:dem":1187,
    "gn:feature_class":"P",
    "gn:feature_code":"PPL",
    "gn:name":"Ban\u012b Shuray\u1e29",
    "gn:population":0,
    "gn:timezone":"Asia/Aden",
    "iso:country":"YE",
    "name:ara_x_preferred":[
        "\u0628\u0646\u064a \u0634\u0631\u064a\u062d"
    ],
    "name:und_x_variant":[
        "Ban\u012b Shuray\u1e29"
    ],
    "wof:name":"Bani Shurayh",
    "wof:placetype":"locality"
},
  "geometry": {"coordinates":[44.49848,16.26973],"type":"Point"}
}