{
  "type": "Feature",
  "properties": {
    "gn:admin1_code":"21.0",
    "gn:admin2_code":"1612.0",
    "gn:asciiname":"Al Malahat",
    "gn:country_code":"YE",
    "gn:dem":1359,
    "gn:feature_class":"P",
    "gn:feature_code":"PPL",
    "gn:name":"Al Mala\u1e29\u0101t",
    "gn:population":0,
    "gn:timezone":"Asia/Aden",
    "iso:country":"YE",
    "name:ara_x_preferred":[
        "\u0627\u0644\u0645\u0644\u062d\u0627\u062a"
    ],
    "name:und_x_variant":[
        "Al Mala\u1e29\u0101t"
    ],
    "wof:name":"Al Malahat",
    "wof:placetype":"locality"
},
  "geometry": {"coordinates":[44.27301,16.53023],"type":"Point"}
}