{
  "type": "Feature",
  "properties": {
    "gn:country":"YE",
    "gn:fcode":"PPL",
    "gn:pop":24,
    "iso:country":"YE",
    "name:ara_x_preferred":[
        "\u0627\u0644\u0645\u0636\u0644\u0639"
    ],
    "name:eng_x_preferred":[
        "Al Maula'"
    ],
    "qs:name":"Al Ma\u1e11la\u2018",
    "qs:photos_9r":0,
    "qs:photos_sr":0,
    "qs:pop_sr":"1",
    "wof:name":"Al Ma\u1e11la\u2018",
    "wof:placetype":"locality",
    "wof:population":24
},
  "geometry": {"coordinates":[43.73494,13.29138],"type":"Point"}
}