{
  "type": "Feature",
  "properties": {
    "gn:admin1_code":"1.0",
    "gn:admin2_code":"1211.0",
    "gn:asciiname":"Al Ma`ar",
    "gn:country_code":"YE",
    "gn:dem":260,
    "gn:feature_class":"P",
    "gn:feature_code":"PPL",
    "gn:name":"Al Ma\u2018ar",
    "gn:population":0,
    "gn:timezone":"Asia/Aden",
    "iso:country":"YE",
    "name:ara_x_preferred":[
        "\u0627\u0644\u0645\u0639\u0631"
    ],
    "name:fas_x_preferred":[
        "\u0627\u0644\u0645\u0639\u0631"
    ],
    "name:nno_x_preferred":[
        "Al Ma`ar"
    ],
    "name:und_x_variant":[
        "M\u0101yirah",
        "Al Ma\u2018irr",
        "Ma\u2018ir",
        "Al Ma\u2018ar"
    ],
    "wof:name":"Al Ma`ar",
    "wof:placetype":"locality"
},
  "geometry": {"coordinates":[45.44339,13.39298],"type":"Point"}
}