{
  "type": "Feature",
  "properties": {
    "gn:admin1_code":"25.0",
    "gn:admin2_code":"1501.0",
    "gn:asciiname":"Al Mabadir",
    "gn:country_code":"YE",
    "gn:dem":1326,
    "gn:feature_class":"P",
    "gn:feature_code":"PPL",
    "gn:name":"Al Mab\u0101dir",
    "gn:population":0,
    "gn:timezone":"Asia/Aden",
    "iso:country":"YE",
    "name:und_x_variant":[
        "Al Mab\u0101dir"
    ],
    "wof:name":"Al Mabadir",
    "wof:placetype":"locality"
},
  "geometry": {"coordinates":[44.30052,13.66071],"type":"Point"}
}