{
  "type": "Feature",
  "properties": {
    "gn:admin1_code":"16.0",
    "gn:admin2_code":"2312.0",
    "gn:asciiname":"Al Hadan al Wasi'",
    "gn:country_code":"YE",
    "gn:dem":1628,
    "gn:feature_class":"P",
    "gn:feature_code":"PPL",
    "gn:name":"Al \u1e28a\u1e11an al Was\u012b\u2018",
    "gn:population":0,
    "gn:timezone":"Asia/Aden",
    "iso:country":"YE",
    "name:ara_x_preferred":[
        "\u0627\u0644\u062d\u0636\u0646 \u0627\u0644\u0648\u0633\u064a\u0639"
    ],
    "name:und_x_variant":[
        "Al \u1e28a\u1e11an al Was\u012b\u2018"
    ],
    "wof:name":"Al Hadan al Wasi'",
    "wof:placetype":"locality"
},
  "geometry": {"coordinates":[44.82516,15.38257],"type":"Point"}
}