{
  "type": "Feature",
  "properties": {
    "gn:admin1_code":"22.0",
    "gn:admin2_code":"1722.0",
    "gn:asciiname":"Adh Dhira`",
    "gn:country_code":"YE",
    "gn:dem":696,
    "gn:feature_class":"P",
    "gn:feature_code":"PPL",
    "gn:name":"Adh Dhir\u0101\u2018",
    "gn:population":0,
    "gn:timezone":"Asia/Aden",
    "iso:country":"YE",
    "name:ara_x_preferred":[
        "Adh Dhir\u0101\u2018"
    ],
    "wof:name":"Adh Dhira`",
    "wof:placetype":"locality"
},
  "geometry": {"coordinates":[43.3203,15.83656],"type":"Point"}
}