{
  "type": "Feature",
  "properties": {
    "gn:admin1_code":"4.0",
    "gn:admin2_code":"1916.0",
    "gn:asciiname":"Kut ash Shaykh Junayd",
    "gn:cc2":"YE",
    "gn:country_code":"YE",
    "gn:dem":1078,
    "gn:feature_class":"P",
    "gn:feature_code":"PPL",
    "gn:name":"K\u016bt ash Shaykh Junayd",
    "gn:population":0,
    "gn:timezone":"Asia/Aden",
    "iso:country":"YE",
    "name:und_x_variant":[
        "K\u016bt al-Shaikh Junaid",
        "K\u016bt ash Shaykh Junayd"
    ],
    "wof:name":"Kut ash Shaykh Junayd",
    "wof:placetype":"locality"
},
  "geometry": {"coordinates":[48.93333,15.28333],"type":"Point"}
}