{
  "type": "Feature",
  "properties": {
    "gn:admin1_code":"11.0",
    "gn:admin2_code":"2001.0",
    "gn:asciiname":"Rahah",
    "gn:country_code":"YE",
    "gn:dem":2408,
    "gn:feature_class":"P",
    "gn:feature_code":"PPL",
    "gn:name":"R\u0101\u1e29ah",
    "gn:population":0,
    "gn:timezone":"Asia/Aden",
    "iso:country":"YE",
    "name:und_x_variant":[
        "R\u0101\u1e29ah"
    ],
    "wof:name":"Rahah",
    "wof:placetype":"locality"
},
  "geometry": {"coordinates":[44.36667,14.95],"type":"Point"}
}