{
  "type": "Feature",
  "properties": {
    "gn:admin1_code":"23.0",
    "gn:admin2_code":"1111.0",
    "gn:asciiname":"Al `Udayn",
    "gn:country_code":"YE",
    "gn:dem":1282,
    "gn:feature_class":"P",
    "gn:feature_code":"PPLA2",
    "gn:name":"Al \u2018Udayn",
    "gn:population":0,
    "gn:timezone":"Asia/Aden",
    "iso:country":"YE",
    "name:ara_x_preferred":[
        "\u0627\u0644\u0639\u062f\u064a\u0646"
    ],
    "name:und_x_variant":[
        "Udain",
        "Al \u2018Udain",
        "\u2018Udayn",
        "El-\u2018Udein",
        "Al \u2018Udayn"
    ],
    "wof:name":"Al `Udayn",
    "wof:placetype":"locality"
},
  "geometry": {"coordinates":[43.99673,13.96918],"type":"Point"}
}