{
  "type": "Feature",
  "properties": {
    "gn:admin1_code":"8.0",
    "gn:admin2_code":"1801.0",
    "gn:asciiname":"Dayr Ranif",
    "gn:country_code":"YE",
    "gn:dem":168,
    "gn:feature_class":"P",
    "gn:feature_code":"PPL",
    "gn:name":"Dayr R\u0101nif",
    "gn:population":0,
    "gn:timezone":"Asia/Aden",
    "iso:country":"YE",
    "name:und_x_variant":[
        "Dayr R\u0101nif"
    ],
    "wof:name":"Dayr Ranif",
    "wof:placetype":"locality"
},
  "geometry": {"coordinates":[43.20966,15.74448],"type":"Point"}
}