{
  "type": "Feature",
  "properties": {
    "gn:admin1_code":"23.0",
    "gn:admin2_code":"1101.0",
    "gn:asciiname":"Zahrat al Humri",
    "gn:country_code":"YE",
    "gn:dem":1351,
    "gn:feature_class":"P",
    "gn:feature_code":"PPL",
    "gn:name":"Z\u0327ahrat al \u1e28umr\u012b",
    "gn:population":0,
    "gn:timezone":"Asia/Aden",
    "iso:country":"YE",
    "name:ara_x_preferred":[
        "\u0638\u0647\u0631\u0629 \u0627\u0644\u062d\u0645\u0631\u064a"
    ],
    "name:und_x_variant":[
        "Z\u0327ahrat al \u1e28umr\u012b"
    ],
    "wof:name":"Zahrat al Humri",
    "wof:placetype":"locality"
},
  "geometry": {"coordinates":[44.12785,14.27224],"type":"Point"}
}