{
  "type": "Feature",
  "properties": {
    "gn:admin1_code":"1.0",
    "gn:admin2_code":"1204.0",
    "gn:asciiname":"Sakin Ahl 'Abbad",
    "gn:country_code":"YE",
    "gn:dem":1050,
    "gn:feature_class":"P",
    "gn:feature_code":"PPL",
    "gn:name":"S\u0101kin Ahl \u2018Abb\u0101d",
    "gn:population":0,
    "gn:timezone":"Asia/Aden",
    "iso:country":"YE",
    "name:ara_x_preferred":[
        "S\u0101kin Ahl \u2018Abb\u0101d"
    ],
    "wof:name":"Sakin Ahl 'Abbad",
    "wof:placetype":"locality"
},
  "geometry": {"coordinates":[45.86829,13.9287],"type":"Point"}
}