{
  "type": "Feature",
  "properties": {
    "gn:admin1_code":"23.0",
    "gn:admin2_code":"1101.0",
    "gn:asciiname":"Hayjat at Tayyar",
    "gn:country_code":"YE",
    "gn:dem":1069,
    "gn:feature_class":"P",
    "gn:feature_code":"PPL",
    "gn:name":"Hayjat a\u0163 \u0162ayy\u0101r",
    "gn:population":0,
    "gn:timezone":"Asia/Aden",
    "iso:country":"YE",
    "name:ara_x_preferred":[
        "\u0647\u064a\u062c\u0629 \u0627\u0644\u0637\u064a\u0627\u0631"
    ],
    "name:und_x_variant":[
        "Hayjat a\u0163 \u0162ayy\u0101r"
    ],
    "wof:name":"Hayjat at Tayyar",
    "wof:placetype":"locality"
},
  "geometry": {"coordinates":[44.02582,14.27444],"type":"Point"}
}