{
  "type": "Feature",
  "properties": {
    "gn:country":"YE",
    "gn:fcode":"PPL",
    "gn:pop":15,
    "iso:country":"YE",
    "name:ara_x_preferred":[
        "Az\u0327 Z\u0327ih\u0101r\u012b"
    ],
    "name:ara_x_variant":[
        "\u0627\u0644\u0638\u0647\u0627\u0631\u064a"
    ],
    "name:eng_x_preferred":[
        "Az Zihari"
    ],
    "qs:name":"Az\u0327 Z\u0327ih\u0101r\u012b",
    "qs:photos_9r":0,
    "qs:photos_sr":0,
    "qs:pop_sr":"1",
    "wof:name":"Az\u0327 Z\u0327ih\u0101r\u012b",
    "wof:placetype":"locality",
    "wof:population":15
},
  "geometry": {"coordinates":[44.18417,15.49406],"type":"Point"}
}