{
  "type": "Feature",
  "properties": {
    "gn:admin1_code":"25.0",
    "gn:admin2_code":"1515.0",
    "gn:asciiname":"Al Ha'it",
    "gn:country_code":"YE",
    "gn:dem":1385,
    "gn:feature_class":"P",
    "gn:feature_code":"PPL",
    "gn:name":"Al \u1e28\u0101\u2019i\u0163",
    "gn:population":0,
    "gn:timezone":"Asia/Aden",
    "iso:country":"YE",
    "name:ara_x_preferred":[
        "\u0627\u0644\u062d\u0627\u0626\u0637"
    ],
    "name:und_x_variant":[
        "Al \u1e28\u0101\u2019i\u0163"
    ],
    "wof:name":"Al Ha'it",
    "wof:placetype":"locality"
},
  "geometry": {"coordinates":[44.14079,13.2065],"type":"Point"}
}