{
  "type": "Feature",
  "properties": {
    "gn:admin1_code":"19.0",
    "gn:admin2_code":"2903.0",
    "gn:asciiname":"Sha'b Sulayman",
    "gn:country_code":"YE",
    "gn:dem":1393,
    "gn:feature_class":"P",
    "gn:feature_code":"PPL",
    "gn:name":"Sha\u2018b Sulaym\u0101n",
    "gn:population":0,
    "gn:timezone":"Asia/Aden",
    "iso:country":"YE",
    "name:ara_x_preferred":[
        "\u0634\u0639\u0628 \u0633\u0644\u064a\u0645\u0627\u0646"
    ],
    "name:und_x_variant":[
        "Sha\u2018b Sulaym\u0101n"
    ],
    "wof:name":"Sha'b Sulayman",
    "wof:placetype":"locality"
},
  "geometry": {"coordinates":[43.7742,16.4207],"type":"Point"}
}