{
  "type": "Feature",
  "properties": {
    "gn:country":"YE",
    "gn:fcode":"PPL",
    "gn:population":12,
    "iso:country":"YE",
    "name:ara_x_preferred":[
        "\u0627\u0644\u062d\u0645\u0629"
    ],
    "qs:name":"Al \u1e28ammah",
    "qs:photos_9r":0,
    "qs:photos_sr":0,
    "qs:pop_sr":"1",
    "wof:name":"Al \u1e28ammah",
    "wof:placetype":"locality",
    "wof:population":12
},
  "geometry": {"coordinates":[45.17955,14.40145],"type":"Point"}
}