{
  "type": "Feature",
  "properties": {
    "gn:admin1_code":"22.0",
    "gn:admin2_code":"1718.0",
    "gn:asciiname":"Al Hima'",
    "gn:country_code":"YE",
    "gn:dem":2113,
    "gn:feature_class":"P",
    "gn:feature_code":"PPL",
    "gn:name":"Al \u1e28im\u0101\u2019",
    "gn:population":0,
    "gn:timezone":"Asia/Aden",
    "iso:country":"YE",
    "name:ara_x_preferred":[
        "Al \u1e28im\u0101\u2019"
    ],
    "wof:name":"Al Hima'",
    "wof:placetype":"locality"
},
  "geometry": {"coordinates":[43.70225,15.75619],"type":"Point"}
}