{
  "type": "Feature",
  "properties": {
    "gn:admin1_code":"16.0",
    "gn:admin2_code":"2310.0",
    "gn:asciiname":"As Salul",
    "gn:country_code":"YE",
    "gn:dem":2112,
    "gn:feature_class":"P",
    "gn:feature_code":"PPL",
    "gn:name":"A\u015f \u015eal\u016bl",
    "gn:population":0,
    "gn:timezone":"Asia/Aden",
    "iso:country":"YE",
    "name:und_x_variant":[
        "A\u015f \u015eal\u016bl"
    ],
    "wof:name":"As Salul",
    "wof:placetype":"locality"
},
  "geometry": {"coordinates":[43.7698,15.054],"type":"Point"}
}