{
  "type": "Feature",
  "properties": {
    "gn:country":"YE",
    "gn:fcode":"PPL",
    "gn:population":1,
    "iso:country":"YE",
    "name:ara_x_preferred":[
        "\u0648\u0627\u062f\u064a \u0641\u0644\u0627\u062d"
    ],
    "name:eng_x_preferred":[
        "Wadi Falah"
    ],
    "name:eng_x_variant":[
        "A\u015f \u015eaf\u0101r\u012b"
    ],
    "qs:name":"W\u0101d\u012b Fal\u0101\u1e29",
    "qs:photos_9r":0,
    "qs:photos_sr":0,
    "qs:pop_sr":"1",
    "wof:name":"W\u0101d\u012b Fal\u0101\u1e29",
    "wof:placetype":"locality",
    "wof:population":1
},
  "geometry": {"coordinates":[43.44304,16.25396],"type":"Point"}
}