{
  "type": "Feature",
  "properties": {
    "gn:country":"YE",
    "gn:fcode":"PPLX",
    "gn:population":16,
    "iso:country":"YE",
    "name:ara_x_preferred":[
        "Gh\u016bl Dh\u016b Jibr\u0101n"
    ],
    "name:ara_x_variant":[
        "\u063a\u0648\u0644 \u0630\u0648 \u062c\u0628\u0631\u0627\u0646"
    ],
    "qs:name":"Gh\u016bl Dh\u016b Jibr\u0101n",
    "qs:photos_9r":0,
    "qs:photos_sr":0,
    "qs:pop_sr":"1",
    "wof:name":"Gh\u016bl Dh\u016b Jibr\u0101n",
    "wof:placetype":"neighbourhood",
    "wof:population":16
},
  "geometry": {"coordinates":[43.89732,16.57801],"type":"Point"}
}