{
  "type": "Feature",
  "properties": {
    "gn:country":"YE",
    "gn:fcode":"PPL",
    "gn:pop":4,
    "iso:country":"YE",
    "name:ara_x_preferred":[
        "\u0645\u0642\u0627\u0645 \u0630\u0648 \u0641\u0627\u0635\u0644"
    ],
    "name:eng_x_preferred":[
        "Maqam DhU Fasil"
    ],
    "name:urd_x_preferred":[
        "\u0645\u062f\u06cc\u0631\u06cc\u06c1"
    ],
    "qs:name":"Maq\u0101m Dh\u016b F\u0101\u015fil",
    "qs:photos_9r":0,
    "qs:photos_sr":0,
    "qs:pop_sr":"1",
    "wof:name":"Maq\u0101m Dh\u016b F\u0101\u015fil",
    "wof:placetype":"locality",
    "wof:population":4
},
  "geometry": {"coordinates":[44.21118,16.6625],"type":"Point"}
}