{
  "type": "Feature",
  "properties": {
    "gn:admin1_code":"14.0",
    "gn:admin2_code":"2613.0",
    "gn:asciiname":"Al `Iwash",
    "gn:country_code":"YE",
    "gn:dem":1045,
    "gn:feature_class":"P",
    "gn:feature_code":"PPL",
    "gn:name":"Al \u2018Iw\u0101sh",
    "gn:population":0,
    "gn:timezone":"Asia/Aden",
    "iso:country":"YE",
    "name:ara_x_preferred":[
        "Al \u2018Iw\u0101sh"
    ],
    "name:ara_x_variant":[
        "\u0627\u0644\u0639\u0648\u0627\u0634"
    ],
    "wof:name":"Al `Iwash",
    "wof:placetype":"locality"
},
  "geometry": {"coordinates":[45.40645,15.57627],"type":"Point"}
}