{
  "type": "Feature",
  "properties": {
    "gn:country":"YE",
    "gn:fcode":"PPL",
    "gn:pop":2,
    "iso:country":"YE",
    "name:ara_x_preferred":[
        "\u063a\u0648\u0644 \u062d\u0628\u0627\u0646"
    ],
    "name:eng_x_preferred":[
        "Ghawl Hiban"
    ],
    "name:eng_x_variant":[
        "A\u0163 \u0162ayyib"
    ],
    "qs:name":"Ghawl \u1e28ib\u0101n",
    "qs:photos_9r":0,
    "qs:photos_sr":0,
    "qs:pop_sr":"1",
    "wof:name":"Ghawl \u1e28ib\u0101n",
    "wof:placetype":"locality",
    "wof:population":2
},
  "geometry": {"coordinates":[43.52367,16.30811],"type":"Point"}
}