{
  "type": "Feature",
  "properties": {
    "gn:admin1_code":"14.0",
    "gn:admin2_code":"2604.0",
    "gn:asciiname":"Al `Amud",
    "gn:country_code":"YE",
    "gn:dem":1677,
    "gn:feature_class":"P",
    "gn:feature_code":"PPL",
    "gn:name":"Al \u2018Am\u016bd",
    "gn:population":0,
    "gn:timezone":"Asia/Aden",
    "iso:country":"YE",
    "name:ara_x_preferred":[
        "Al \u2018Am\u016bd"
    ],
    "name:ara_x_variant":[
        "\u0627\u0644\u0639\u0645\u0648\u062f"
    ],
    "wof:name":"Al `Amud",
    "wof:placetype":"locality"
},
  "geometry": {"coordinates":[44.68517,15.49462],"type":"Point"}
}