{
  "type": "Feature",
  "properties": {
    "gn:admin1_code":"14.0",
    "gn:admin2_code":"2606.0",
    "gn:asciiname":"As Sirhah",
    "gn:country_code":"YE",
    "gn:dem":1542,
    "gn:feature_class":"P",
    "gn:feature_code":"PPL",
    "gn:name":"As Sir\u1e29ah",
    "gn:population":0,
    "gn:timezone":"Asia/Aden",
    "iso:country":"YE",
    "name:ara_x_preferred":[
        "\u0627\u0644\u0633\u0631\u062d\u0629"
    ],
    "name:und_x_variant":[
        "As Sir\u1e29ah"
    ],
    "wof:name":"As Sirhah",
    "wof:placetype":"locality"
},
  "geometry": {"coordinates":[44.76383,15.54264],"type":"Point"}
}