{
  "type": "Feature",
  "properties": {
    "gn:admin1_code":"15.0",
    "gn:admin2_code":"2207.0",
    "gn:asciiname":"Sha'b as Sa'id",
    "gn:country_code":"YE",
    "gn:dem":684,
    "gn:feature_class":"P",
    "gn:feature_code":"PPL",
    "gn:name":"Sha\u2018b as Sa\u2018\u012bd",
    "gn:population":0,
    "gn:timezone":"Asia/Aden",
    "iso:country":"YE",
    "name:ara_x_preferred":[
        "\u0634\u0639\u0628 \u0627\u0644\u0633\u0639\u064a\u062f"
    ],
    "name:und_x_variant":[
        "Sha\u2018b as Sa\u2018\u012bd"
    ],
    "wof:name":"Sha'b as Sa'id",
    "wof:placetype":"locality"
},
  "geometry": {"coordinates":[43.31388,16.66603],"type":"Point"}
}