{
  "type": "Feature",
  "properties": {
    "gn:admin1_code":"14.0",
    "gn:admin2_code":"2601.0",
    "gn:asciiname":"As Sahari",
    "gn:country_code":"YE",
    "gn:dem":1184,
    "gn:feature_class":"P",
    "gn:feature_code":"PPL",
    "gn:name":"As Sa\u1e29\u0101r\u012b",
    "gn:population":0,
    "gn:timezone":"Asia/Aden",
    "iso:country":"YE",
    "name:ara_x_preferred":[
        "\u0627\u0644\u0633\u062d\u0627\u0631\u064a"
    ],
    "name:und_x_variant":[
        "As Sa\u1e29\u0101r\u012b",
        "Qaryat as Sa\u1e29\u0101r\u012b"
    ],
    "wof:name":"As Sahari",
    "wof:placetype":"locality"
},
  "geometry": {"coordinates":[44.74712,15.88192],"type":"Point"}
}