{
  "type": "Feature",
  "properties": {
    "gn:country":"YE",
    "gn:fcode":"PPL",
    "gn:pop":7,
    "iso:country":"YE",
    "name:ara_x_preferred":[
        "\u0100l S\u0101tir"
    ],
    "name:ara_x_variant":[
        "\u0627\u0644 \u0633\u0627\u062a\u0631"
    ],
    "name:eng_x_preferred":[
        "Al Satir"
    ],
    "qs:name":"\u0100l S\u0101tir",
    "qs:photos_9r":0,
    "qs:photos_sr":0,
    "qs:pop_sr":"1",
    "wof:name":"\u0100l S\u0101tir",
    "wof:placetype":"locality",
    "wof:population":7
},
  "geometry": {"coordinates":[43.36458,16.80253],"type":"Point"}
}