{
  "type": "Feature",
  "properties": {
    "gn:admin1_code":"10.0",
    "gn:admin2_code":"2702.0",
    "gn:asciiname":"Bayt Buraz",
    "gn:country_code":"YE",
    "gn:dem":2228,
    "gn:feature_class":"P",
    "gn:feature_code":"PPL",
    "gn:name":"Bayt Bur\u0101z",
    "gn:population":0,
    "gn:timezone":"Asia/Aden",
    "iso:country":"YE",
    "name:und_x_variant":[
        "Bayt Bur\u0101z"
    ],
    "wof:name":"Bayt Buraz",
    "wof:placetype":"locality"
},
  "geometry": {"coordinates":[43.69463,15.4965],"type":"Point"}
}