{
  "type": "Feature",
  "properties": {
    "gn:admin1_code":"18.0",
    "gn:admin2_code":"3004.0",
    "gn:asciiname":"As Surraha",
    "gn:country_code":"YE",
    "gn:dem":2004,
    "gn:feature_class":"P",
    "gn:feature_code":"PPL",
    "gn:name":"As Surraha",
    "gn:population":0,
    "gn:timezone":"Asia/Aden",
    "iso:country":"YE",
    "name:und_x_variant":[
        "Al Suraha",
        "As Surraha"
    ],
    "wof:name":"As Surraha",
    "wof:placetype":"locality"
},
  "geometry": {"coordinates":[44.89331,13.83587],"type":"Point"}
}