{
  "type": "Feature",
  "properties": {
    "gn:admin1_code":"10.0",
    "gn:admin2_code":"2704.0",
    "gn:asciiname":"Al `Azib",
    "gn:country_code":"YE",
    "gn:dem":1050,
    "gn:feature_class":"P",
    "gn:feature_code":"PPL",
    "gn:name":"Al \u2018Az\u012bb",
    "gn:population":0,
    "gn:timezone":"Asia/Aden",
    "iso:country":"YE",
    "name:ara_x_preferred":[
        "Al \u2018Az\u012bb"
    ],
    "wof:name":"Al `Azib",
    "wof:placetype":"locality"
},
  "geometry": {"coordinates":[43.32331,15.47307],"type":"Point"}
}