{
  "type": "Feature",
  "properties": {
    "gn:country":"YE",
    "gn:fcode":"AREA",
    "gn:population":15,
    "iso:country":"YE",
    "name:ara_x_preferred":[
        "\u064a\u062d\u0627\u0645\u0631"
    ],
    "qs:name":"Ya\u1e29\u0101mir",
    "qs:photos_9r":0,
    "qs:photos_sr":0,
    "qs:pop_sr":"1",
    "wof:name":"Ya\u1e29\u0101mir",
    "wof:placetype":"locality",
    "wof:population":15
},
  "geometry": {"coordinates":[46.30765,16.54373],"type":"Point"}
}