{
  "type": "Feature",
  "properties": {
    "gn:country":"YE",
    "gn:fcode":"PPL",
    "gn:pop":16,
    "iso:country":"YE",
    "name:ara_x_preferred":[
        "\u0628\u064a\u062a \u0627\u0644\u0642\u0644\u0639\u0629"
    ],
    "name:eng_x_preferred":[
        "Bayt Al Qal'ah"
    ],
    "qs:name":"Bayt al Qal\u2018ah",
    "qs:photos_9r":0,
    "qs:photos_sr":0,
    "qs:pop_sr":"1",
    "wof:name":"Bayt al Qal\u2018ah",
    "wof:placetype":"locality",
    "wof:population":16
},
  "geometry": {"coordinates":[43.42442,16.24025],"type":"Point"}
}