{
  "type": "Feature",
  "properties": {
    "gn:admin1_code":"11.0",
    "gn:admin2_code":"2007.0",
    "gn:asciiname":"`Uwayd al Yamani",
    "gn:country_code":"YE",
    "gn:dem":412,
    "gn:feature_class":"P",
    "gn:feature_code":"PPL",
    "gn:name":"\u2018Uwayd al Yam\u0101n\u012b",
    "gn:population":0,
    "gn:timezone":"Asia/Aden",
    "iso:country":"YE",
    "name:und_x_variant":[
        "\u2018Uwayd al Yam\u0101n\u012b"
    ],
    "wof:name":"`Uwayd al Yamani",
    "wof:placetype":"locality"
},
  "geometry": {"coordinates":[43.50237,14.34707],"type":"Point"}
}