{
  "type": "Feature",
  "properties": {
    "gn:gn_country":"YE",
    "gn:gn_fcode":"PPL",
    "gn:gn_pop":22,
    "gn:population":22,
    "iso:country":"YE",
    "name:ara_x_preferred":[
        "\u0627\u0644\u063a\u0631\u064a\u0642\u0629"
    ],
    "name:eng_x_preferred":[
        "Al Ghurayqah"
    ],
    "name:eng_x_variant":[
        "Al Ma\u2018z\u016bb"
    ],
    "qs_pg:aaroncc":"YE",
    "qs_pg:gn_country":"YE",
    "qs_pg:gn_fcode":"PPL",
    "qs_pg:gn_pop":22,
    "qs_pg:name":"Al Ghurayqah",
    "qs_pg:photos_9r":0,
    "qs_pg:photos_sr":0,
    "qs_pg:pop_sr":1,
    "qs_pg:qs_pg_placetype":"locality",
    "wof:name":"Al Ghurayqah",
    "wof:placetype":"locality",
    "wof:population":22
},
  "geometry": {"coordinates":[45.56617,14.00504],"type":"Point"}
}