{
  "type": "Feature",
  "properties": {
    "gn:country":"YE",
    "gn:fcode":"PPL",
    "gn:population":1,
    "iso:country":"YE",
    "name:ara_x_preferred":[
        "\u0627\u0644\u0643\u0631\u0627\u0646\u0629"
    ],
    "name:eng_x_preferred":[
        "Al Karanah"
    ],
    "name:vie_x_preferred":[
        "Kuhlan Affar"
    ],
    "qs:name":"Al Kar\u0101nah",
    "qs:photos_9r":0,
    "qs:photos_sr":0,
    "qs:pop_sr":"1",
    "wof:name":"Al Kar\u0101nah",
    "wof:placetype":"locality",
    "wof:population":1
},
  "geometry": {"coordinates":[43.29829,17.51232],"type":"Point"}
}