{
  "type": "Feature",
  "properties": {
    "gn:admin1_code":"8.0",
    "gn:admin2_code":"1807.0",
    "gn:asciiname":"Mahall Shaw'i Qasim Aqzal",
    "gn:country_code":"YE",
    "gn:dem":71,
    "gn:feature_class":"P",
    "gn:feature_code":"PPL",
    "gn:name":"Ma\u1e29all Shaw\u2018\u012b Q\u0101sim Aqzal",
    "gn:population":0,
    "gn:timezone":"Asia/Aden",
    "iso:country":"YE",
    "name:ara_x_preferred":[
        "\u0645\u062d\u0644 \u0634\u0648\u0639\u064a \u0642\u0627\u0633\u0645 \u0623\u0642\u0632\u0644"
    ],
    "name:und_x_variant":[
        "Ma\u1e29all Shaw\u2018\u012b Q\u0101sim Aqzal"
    ],
    "wof:name":"Mahall Shaw'i Qasim Aqzal",
    "wof:placetype":"locality"
},
  "geometry": {"coordinates":[43.06275,15.32237],"type":"Point"}
}