{
  "type": "Feature",
  "properties": {
    "gn:admin1_code":"15.0",
    "gn:admin2_code":"2203.0",
    "gn:asciiname":"'Abbas al Gharin",
    "gn:country_code":"YE",
    "gn:dem":877,
    "gn:feature_class":"P",
    "gn:feature_code":"PPL",
    "gn:name":"\u2018Abb\u0101s al Ghar\u012bn",
    "gn:population":0,
    "gn:timezone":"Asia/Aden",
    "iso:country":"YE",
    "name:ara_x_preferred":[
        "\u0639\u0628\u0627\u0633 \u0627\u0644\u063a\u0631\u064a\u0646"
    ],
    "name:und_x_variant":[
        "\u2018Abb\u0101s al Ghar\u012bn"
    ],
    "wof:name":"'Abbas al Gharin",
    "wof:placetype":"locality"
},
  "geometry": {"coordinates":[43.25075,17.23476],"type":"Point"}
}