{
  "type": "Feature",
  "properties": {
    "gn:country":"YE",
    "gn:fcode":"PPLX",
    "gn:population":8,
    "iso:country":"YE",
    "name:ara_x_preferred":[
        "Al M\u012br\u0101d"
    ],
    "name:ara_x_variant":[
        "\u0627\u0644\u0645\u064a\u0631\u0627\u062f"
    ],
    "qs:name":"Al M\u012br\u0101d",
    "qs:photos_9r":0,
    "qs:photos_sr":0,
    "qs:pop_sr":"1",
    "wof:name":"Al M\u012br\u0101d",
    "wof:placetype":"neighbourhood",
    "wof:population":8
},
  "geometry": {"coordinates":[44.47494,16.65576],"type":"Point"}
}