{
  "type": "Feature",
  "properties": {
    "gn:admin1_code":"8.0",
    "gn:admin2_code":"1817.0",
    "gn:asciiname":"Al Minjarah",
    "gn:country_code":"YE",
    "gn:dem":136,
    "gn:feature_class":"P",
    "gn:feature_code":"PPL",
    "gn:name":"Al Minj\u0101rah",
    "gn:population":0,
    "gn:timezone":"Asia/Aden",
    "iso:country":"YE",
    "name:und_x_variant":[
        "Al Minj\u0101rah"
    ],
    "wof:name":"Al Minjarah",
    "wof:placetype":"locality"
},
  "geometry": {"coordinates":[43.396,14.52857],"type":"Point"}
}