{
  "type": "Feature",
  "properties": {
    "gn:country":"YE",
    "gn:fcode":"PPL",
    "gn:pop":6,
    "iso:country":"YE",
    "name:ara_x_preferred":[
        "\u0628\u064a\u062a \u0627\u0644\u0645\u063a\u0627\u0631\u0628"
    ],
    "name:eng_x_preferred":[
        "Bayt Al Mugharib"
    ],
    "name:eng_x_variant":[
        "A\u1e11 \u1e10abr"
    ],
    "qs:name":"Bayt al Mugh\u0101rib",
    "qs:photos_9r":0,
    "qs:photos_sr":0,
    "qs:pop_sr":"1",
    "wof:name":"Bayt al Mugh\u0101rib",
    "wof:placetype":"locality",
    "wof:population":6
},
  "geometry": {"coordinates":[43.42362,16.07544],"type":"Point"}
}