{
  "type": "Feature",
  "properties": {
    "gn:admin1_code":"16.0",
    "gn:admin2_code":"2303.0",
    "gn:asciiname":"Ghawl Sahib",
    "gn:country_code":"YE",
    "gn:dem":1851,
    "gn:feature_class":"P",
    "gn:feature_code":"PPLL",
    "gn:name":"Ghawl S\u0101\u1e29ib",
    "gn:population":0,
    "gn:timezone":"Asia/Aden",
    "iso:country":"YE",
    "name:ara_x_preferred":[
        "\u063a\u0648\u0644 \u0633\u0627\u062d\u0628"
    ],
    "name:und_x_variant":[
        "Ghawl S\u0101\u1e29ib"
    ],
    "wof:name":"Ghawl Sahib",
    "wof:placetype":"locality"
},
  "geometry": {"coordinates":[44.47638,15.84859],"type":"Point"}
}