{
  "type": "Feature",
  "properties": {
    "gn:admin1_code":"10.0",
    "gn:admin2_code":"2707.0",
    "gn:asciiname":"Al Masjid",
    "gn:country_code":"YE",
    "gn:dem":1319,
    "gn:feature_class":"P",
    "gn:feature_code":"PPL",
    "gn:name":"Al Masjid",
    "gn:population":0,
    "gn:timezone":"Asia/Aden",
    "iso:country":"YE",
    "wof:name":"Al Masjid",
    "wof:placetype":"locality"
},
  "geometry": {"coordinates":[43.56288,15.2957],"type":"Point"}
}