{
  "type": "Feature",
  "properties": {
    "gn:country":"YE",
    "gn:fcode":"PPL",
    "gn:pop":1,
    "iso:country":"YE",
    "name:ara_x_preferred":[
        "\u0627\u0644\u0642\u0637\u0639"
    ],
    "qs:name":"Al Qa\u0163i\u2018",
    "qs:photos_9r":0,
    "qs:photos_sr":0,
    "qs:pop_sr":"1",
    "wof:name":"Al Qa\u0163i\u2018",
    "wof:placetype":"locality",
    "wof:population":1
},
  "geometry": {"coordinates":[43.41894,16.03234],"type":"Point"}
}