{
  "type": "Feature",
  "properties": {
    "gn:admin1_code":"15.0",
    "gn:admin2_code":"2203.0",
    "gn:asciiname":"Al `Awmiyah",
    "gn:country_code":"YE",
    "gn:dem":2601,
    "gn:feature_class":"P",
    "gn:feature_code":"PPL",
    "gn:name":"Al \u2018Awm\u012byah",
    "gn:population":0,
    "gn:timezone":"Asia/Aden",
    "iso:country":"YE",
    "name:ara_x_preferred":[
        "\u0627\u0644\u0639\u0648\u0645\u064a\u0629"
    ],
    "name:und_x_variant":[
        "Al \u2018Awm\u012byah"
    ],
    "wof:name":"Al `Awmiyah",
    "wof:placetype":"locality"
},
  "geometry": {"coordinates":[43.36424,17.24181],"type":"Point"}
}