{
  "type": "Feature",
  "properties": {
    "gn:admin1_code":"20.0",
    "gn:admin2_code":"1404.0",
    "gn:asciiname":"As Samakhiyah",
    "gn:country_code":"YE",
    "gn:dem":2035,
    "gn:feature_class":"P",
    "gn:feature_code":"PPL",
    "gn:name":"As Samakh\u012byah",
    "gn:population":0,
    "gn:timezone":"Asia/Aden",
    "iso:country":"YE",
    "name:und_x_variant":[
        "As Samakh\u012byah"
    ],
    "wof:name":"As Samakhiyah",
    "wof:placetype":"locality"
},
  "geometry": {"coordinates":[45.75435,14.09765],"type":"Point"}
}