{
  "type": "Feature",
  "properties": {
    "gn:admin1_code":"25.0",
    "gn:admin2_code":"1517.0",
    "gn:asciiname":"Najd al Kudayshah",
    "gn:country_code":"YE",
    "gn:dem":1414,
    "gn:feature_class":"P",
    "gn:feature_code":"PPL",
    "gn:name":"Najd al Kudayshah",
    "gn:population":0,
    "gn:timezone":"Asia/Aden",
    "iso:country":"YE",
    "name:ara_x_preferred":[
        "\u0646\u062c\u062f \u0627\u0644\u0643\u062f\u064a\u0634\u0629"
    ],
    "wof:name":"Najd al Kudayshah",
    "wof:placetype":"locality"
},
  "geometry": {"coordinates":[44.19124,13.24864],"type":"Point"}
}