{
  "type": "Feature",
  "properties": {
    "gn:admin1_code":"14.0",
    "gn:admin2_code":"2614.0",
    "gn:asciiname":"Al Wadam Al Ka'dan",
    "gn:country_code":"YE",
    "gn:dem":2050,
    "gn:feature_class":"P",
    "gn:feature_code":"PPL",
    "gn:name":"Al Wa\u1e11am \u0100l Ka\u2018d\u0101n",
    "gn:population":0,
    "gn:timezone":"Asia/Aden",
    "iso:country":"YE",
    "name:ara_x_preferred":[
        "\u0627\u0644\u0648\u0636\u0645 \u0622\u0644 \u0643\u0639\u062f\u0627\u0646"
    ],
    "name:und_x_variant":[
        "Al Wa\u1e11am \u0100l Ka\u2018d\u0101n"
    ],
    "wof:name":"Al Wadam Al Ka'dan",
    "wof:placetype":"locality"
},
  "geometry": {"coordinates":[45.18377,15.04342],"type":"Point"}
}