{
  "type": "Feature",
  "properties": {
    "gn:admin1_code":"20.0",
    "gn:admin2_code":"1408.0",
    "gn:asciiname":"Bathan",
    "gn:country_code":"YE",
    "gn:dem":1920,
    "gn:feature_class":"P",
    "gn:feature_code":"PPL",
    "gn:name":"Ba\u0163\u1e29\u0101n",
    "gn:population":0,
    "gn:timezone":"Asia/Aden",
    "iso:country":"YE",
    "name:nno_x_preferred":[
        "Bathan"
    ],
    "name:tam_x_preferred":[
        "\u0baa\u0ba4\u0ba9\u0bcd"
    ],
    "name:und_x_variant":[
        "Qaryat Ba\u0163\u1e29\u0101n",
        "Ba\u0163\u1e29\u0101n"
    ],
    "wof:name":"Bathan",
    "wof:placetype":"locality"
},
  "geometry": {"coordinates":[45.91083,14.08722],"type":"Point"}
}