{
  "type": "Feature",
  "properties": {
    "gn:country":"YE",
    "gn:fcode":"PPL",
    "gn:population":15,
    "iso:country":"YE",
    "name:ara_x_preferred":[
        "\u0634\u0639\u0628 \u0627\u0644\u0645\u0639\u0632\u0628\u0629"
    ],
    "name:eng_x_preferred":[
        "Sha'b Al Ma'zibah"
    ],
    "name:eng_x_variant":[
        "Dayr \u2018Abadah"
    ],
    "name:und_x_variant":[
        "Sha\u2018b al Ma\u2018zabah"
    ],
    "qs_pg:aaroncc":"YE",
    "qs_pg:gn_country":"YE",
    "qs_pg:gn_fcode":"PPL",
    "qs_pg:gn_pop":15,
    "qs_pg:name":"Sha\u2018b al Ma\u2018zibah",
    "qs_pg:photos_9r":0,
    "qs_pg:photos_sr":0,
    "qs_pg:pop_sr":1,
    "qs_pg:qs_pg_placetype":"locality",
    "wof:name":"Sha\u2018b al Ma\u2018zibah",
    "wof:placetype":"locality",
    "wof:population":15
},
  "geometry": {"coordinates":[43.40079,16.15872],"type":"Point"}
}