{
  "type": "Feature",
  "properties": {
    "gn:country":"YE",
    "gn:fcode":"PPL",
    "gn:pop":1,
    "iso:country":"YE",
    "name:ara_x_preferred":[
        "\u0628\u064a\u062a \u0627\u0644\u0637\u0628\u0631"
    ],
    "name:eng_x_preferred":[
        "Bayt At Tabar"
    ],
    "qs:name":"Bayt a\u0163 \u0162abar",
    "qs:photos_9r":0,
    "qs:photos_sr":0,
    "qs:pop_sr":"1",
    "wof:name":"Bayt a\u0163 \u0162abar",
    "wof:placetype":"locality",
    "wof:population":1
},
  "geometry": {"coordinates":[43.39465,16.07803],"type":"Point"}
}