{
  "type": "Feature",
  "properties": {
    "gn:admin1_code":"22.0",
    "gn:admin2_code":"1720.0",
    "gn:asciiname":"Al Mawhabah",
    "gn:country_code":"YE",
    "gn:dem":1565,
    "gn:feature_class":"P",
    "gn:feature_code":"PPL",
    "gn:name":"Al Mawhabah",
    "gn:population":0,
    "gn:timezone":"Asia/Aden",
    "iso:country":"YE",
    "wof:name":"Al Mawhabah",
    "wof:placetype":"locality"
},
  "geometry": {"coordinates":[43.55127,15.76154],"type":"Point"}
}