{
  "type": "Feature",
  "properties": {
    "gn:country":"YE",
    "gn:fcode":"PPLX",
    "gn:population":1,
    "iso:country":"YE",
    "name:ara_x_preferred":[
        "\u0627\u0644\u0628\u0631\u064a\u0643\u0629"
    ],
    "name:fas_x_preferred":[
        "\u0627\u0644\u0628\u0648\u0631\u06cc\u06a9\u0647"
    ],
    "name:nno_x_preferred":[
        "Al Buraykah"
    ],
    "qs:name":"Al Buraykah",
    "qs:photos_9r":0,
    "qs:photos_sr":0,
    "qs:pop_sr":"1",
    "wd:wordcount":24,
    "wof:name":"Al Buraykah",
    "wof:placetype":"neighbourhood",
    "wof:population":1
},
  "geometry": {"coordinates":[43.67235,16.01949],"type":"Point"}
}