{
  "type": "Feature",
  "properties": {
    "gn:admin1_code":"25.0",
    "gn:admin2_code":"1513.0",
    "gn:asciiname":"Qaryat Husmah",
    "gn:country_code":"YE",
    "gn:dem":1469,
    "gn:feature_class":"P",
    "gn:feature_code":"PPL",
    "gn:name":"Qaryat \u1e28u\u015fm\u0101h",
    "gn:population":0,
    "gn:timezone":"Asia/Aden",
    "iso:country":"YE",
    "name:und_x_variant":[
        "Qaryat \u1e28u\u015fm\u0101h"
    ],
    "wof:name":"Qaryat Husmah",
    "wof:placetype":"locality"
},
  "geometry": {"coordinates":[44.2959,13.31666],"type":"Point"}
}