{
  "type": "Feature",
  "properties": {
    "gn:country":"YE",
    "gn:fcode":"PPLX",
    "gn:pop":15,
    "iso:country":"YE",
    "name:ara_x_preferred":[
        "Al Mirb\u0101\u1e29"
    ],
    "name:ara_x_variant":[
        "\u0627\u0644\u0645\u0631\u0628\u0627\u062d"
    ],
    "qs:name":"Al Mirb\u0101\u1e29",
    "qs:photos_9r":0,
    "qs:photos_sr":0,
    "qs:pop_sr":"1",
    "wof:name":"Al Mirb\u0101\u1e29",
    "wof:placetype":"neighbourhood",
    "wof:population":15
},
  "geometry": {"coordinates":[44.39222,16.64149],"type":"Point"}
}