{
  "type": "Feature",
  "properties": {
    "gn:admin1_code":"4.0",
    "gn:asciiname":"Hisn Julaydan",
    "gn:country_code":"YE",
    "gn:dem":1257,
    "gn:feature_class":"P",
    "gn:feature_code":"PPL",
    "gn:name":"\u1e28i\u015fn Julayd\u0101n",
    "gn:population":0,
    "gn:timezone":"Asia/Aden",
    "iso:country":"YE",
    "name:ara_x_preferred":[
        "\u062d\u0635\u0646 \u062c\u0644\u064a\u062f\u0627\u0646"
    ],
    "name:und_x_variant":[
        "\u1e28i\u015fn Julayd\u0101n"
    ],
    "wof:name":"Hisn Julaydan",
    "wof:placetype":"locality"
},
  "geometry": {"coordinates":[47.71175,16.14442],"type":"Point"}
}