{
  "type": "Feature",
  "properties": {
    "gn:admin1_code":"8.0",
    "gn:admin2_code":"1825.0",
    "gn:asciiname":"Qaryat az Zurq",
    "gn:country_code":"YE",
    "gn:dem":207,
    "gn:feature_class":"P",
    "gn:feature_code":"PPL",
    "gn:name":"Qaryat az Zurq",
    "gn:population":0,
    "gn:timezone":"Asia/Aden",
    "iso:country":"YE",
    "wof:name":"Qaryat az Zurq",
    "wof:placetype":"locality"
},
  "geometry": {"coordinates":[43.45906,14.06952],"type":"Point"}
}