{
  "type": "Feature",
  "properties": {
    "gn:admin1_code":"22.0",
    "gn:admin2_code":"1716.0",
    "gn:asciiname":"Bani `Umar",
    "gn:country_code":"YE",
    "gn:dem":1768,
    "gn:feature_class":"P",
    "gn:feature_code":"PPL",
    "gn:name":"Ban\u012b \u2018Umar",
    "gn:population":0,
    "gn:timezone":"Asia/Aden",
    "iso:country":"YE",
    "name:und_x_variant":[
        "Ban\u012b \u2018Umar"
    ],
    "wof:name":"Bani `Umar",
    "wof:placetype":"locality"
},
  "geometry": {"coordinates":[43.50114,15.96212],"type":"Point"}
}