{
  "type": "Feature",
  "properties": {
    "gn:admin1_code":"22.0",
    "gn:admin2_code":"1725.0",
    "gn:asciiname":"Al Hajaf",
    "gn:country_code":"YE",
    "gn:dem":1363,
    "gn:feature_class":"P",
    "gn:feature_code":"PPL",
    "gn:name":"Al \u1e28ajaf",
    "gn:population":0,
    "gn:timezone":"Asia/Aden",
    "iso:country":"YE",
    "name:ara_x_preferred":[
        "\u0627\u0644\u062d\u062c\u0641"
    ],
    "name:und_x_variant":[
        "Al \u1e28ajaf"
    ],
    "wof:name":"Al Hajaf",
    "wof:placetype":"locality"
},
  "geometry": {"coordinates":[43.55751,15.58844],"type":"Point"}
}