{
  "type": "Feature",
  "properties": {
    "gn:country":"YE",
    "gn:fcode":"PPL",
    "gn:pop":5,
    "iso:country":"YE",
    "name:ara_x_preferred":[
        "Al \u2018Akm"
    ],
    "name:ara_x_variant":[
        "\u0627\u0644\u0639\u0643\u0645"
    ],
    "name:eng_x_preferred":[
        "Al 'Akm"
    ],
    "name:eng_x_variant":[
        "An Nawbah"
    ],
    "qs:name":"Al \u2018Akm",
    "qs:photos_9r":0,
    "qs:photos_sr":0,
    "qs:pop_sr":"1",
    "wof:name":"Al \u2018Akm",
    "wof:placetype":"locality",
    "wof:population":5
},
  "geometry": {"coordinates":[43.81182,13.48362],"type":"Point"}
}