{
  "type": "Feature",
  "properties": {
    "gn:admin1_code":"25.0",
    "gn:admin2_code":"1516.0",
    "gn:asciiname":"Al Ku'ub al A'la",
    "gn:country_code":"YE",
    "gn:dem":647,
    "gn:feature_class":"P",
    "gn:feature_code":"PPL",
    "gn:name":"Al Ku\u2018\u016bb al A\u2018l\u00e1",
    "gn:population":0,
    "gn:timezone":"Asia/Aden",
    "iso:country":"YE",
    "name:ara_x_preferred":[
        "\u0627\u0644\u0643\u0639\u0648\u0628 \u0627\u0644\u0623\u0639\u0644\u0649"
    ],
    "name:und_x_variant":[
        "Al Ku\u2018\u016bb al A\u2018l\u00e1"
    ],
    "wof:name":"Al Ku'ub al A'la",
    "wof:placetype":"locality"
},
  "geometry": {"coordinates":[43.78917,13.13885],"type":"Point"}
}