{
  "type": "Feature",
  "properties": {
    "gn:admin1_code":"24.0",
    "gn:admin2_code":"2510.0",
    "gn:asciiname":"Dar al Batsk",
    "gn:country_code":"YE",
    "gn:dem":759,
    "gn:feature_class":"P",
    "gn:feature_code":"PPL",
    "gn:name":"D\u0101r al Batsk",
    "gn:population":0,
    "gn:timezone":"Asia/Aden",
    "iso:country":"YE",
    "name:und_x_variant":[
        "D\u0101r al Batsk"
    ],
    "wof:name":"Dar al Batsk",
    "wof:placetype":"locality"
},
  "geometry": {"coordinates":[44.46667,13.23333],"type":"Point"}
}