{
  "type": "Feature",
  "properties": {
    "gn:admin1_code":"15.0",
    "gn:admin2_code":"2210.0",
    "gn:asciiname":"Al Maththah",
    "gn:country_code":"YE",
    "gn:dem":1989,
    "gn:feature_class":"P",
    "gn:feature_code":"PPL",
    "gn:name":"Al Maththah",
    "gn:population":0,
    "gn:timezone":"Asia/Aden",
    "iso:country":"YE",
    "name:ara_x_preferred":[
        "\u0627\u0644\u0645\u062b\u0629"
    ],
    "wof:name":"Al Maththah",
    "wof:placetype":"locality"
},
  "geometry": {"coordinates":[43.49424000000001,17.17794],"type":"Point"}
}