{
  "type": "Feature",
  "properties": {
    "gn:country":"YE",
    "gn:fcode":"PPLL",
    "gn:pop":6,
    "iso:country":"YE",
    "name:ara_x_preferred":[
        "\u0627\u0644 \u0645\u0637\u0631\u064a"
    ],
    "name:eng_x_preferred":[
        "Al Matri"
    ],
    "qs:name":"\u0100l Ma\u0163r\u012b",
    "qs:photos_9r":0,
    "qs:photos_sr":0,
    "qs:pop_sr":"1",
    "wof:name":"\u0100l Ma\u0163r\u012b",
    "wof:placetype":"locality",
    "wof:population":6
},
  "geometry": {"coordinates":[43.39965,16.77846],"type":"Point"}
}