{
  "type": "Feature",
  "properties": {
    "gn:country":"YE",
    "gn:fcode":"PPL",
    "gn:population":1,
    "iso:country":"YE",
    "name:ara_x_preferred":[
        "\u0627\u0644\u0643\u062f\u062d\u0640\u0629"
    ],
    "name:eng_x_preferred":[
        "Al Kadhah"
    ],
    "name:eng_x_variant":[
        "Al Ash\u2018ar"
    ],
    "qs:name":"Al Kad\u1e29ah",
    "qs:photos_9r":0,
    "qs:photos_sr":0,
    "qs:pop_sr":"1",
    "wof:name":"Al Kad\u1e29ah",
    "wof:placetype":"locality",
    "wof:population":1
},
  "geometry": {"coordinates":[43.67694,16.14065],"type":"Point"}
}