{
  "type": "Feature",
  "properties": {
    "gn:country":"YE",
    "gn:fcode":"PPL",
    "gn:pop":7,
    "iso:country":"YE",
    "name:ara_x_preferred":[
        "\u2018Athr\u0101n"
    ],
    "name:ara_x_variant":[
        "\u0639\u062b\u0631\u0627\u0646"
    ],
    "name:eng_x_preferred":[
        "Athran"
    ],
    "qs:name":"\u2018Athr\u0101n",
    "qs:photos_9r":0,
    "qs:photos_sr":0,
    "qs:pop_sr":"1",
    "wof:name":"\u2018Athr\u0101n",
    "wof:placetype":"locality",
    "wof:population":7
},
  "geometry": {"coordinates":[43.40132,16.88971],"type":"Point"}
}