{
  "type": "Feature",
  "properties": {
    "gn:admin1_code":"14.0",
    "gn:admin2_code":"2602.0",
    "gn:asciiname":"Qawz Qari'",
    "gn:country_code":"YE",
    "gn:dem":1112,
    "gn:feature_class":"P",
    "gn:feature_code":"PPL",
    "gn:name":"Qawz Qar\u012b\u2018",
    "gn:population":0,
    "gn:timezone":"Asia/Aden",
    "iso:country":"YE",
    "name:ara_x_preferred":[
        "\u0642\u0648\u0632 \u0642\u0631\u064a\u0639"
    ],
    "name:und_x_variant":[
        "Qawz Qar\u012b\u2018"
    ],
    "wof:name":"Qawz Qari'",
    "wof:placetype":"locality"
},
  "geometry": {"coordinates":[45.06337,15.72745],"type":"Point"}
}