{
  "type": "Feature",
  "properties": {
    "gn:admin1_code":"20.0",
    "gn:admin2_code":"1406.0",
    "gn:asciiname":"Ad Dayghash",
    "gn:country_code":"YE",
    "gn:dem":1951,
    "gn:feature_class":"P",
    "gn:feature_code":"PPL",
    "gn:name":"Ad Daygh\u0101sh",
    "gn:population":0,
    "gn:timezone":"Asia/Aden",
    "iso:country":"YE",
    "name:ara_x_preferred":[
        "\u0633\u0641\u062f\u0629"
    ],
    "name:und_x_variant":[
        "Ad Daygh\u0101sh",
        "Safadah"
    ],
    "wof:name":"Ad Dayghash",
    "wof:placetype":"locality"
},
  "geometry": {"coordinates":[45.4926,14.11812],"type":"Point"}
}