{
  "type": "Feature",
  "properties": {
    "gn:admin1_code":"16.0",
    "gn:admin2_code":"2304.0",
    "gn:asciiname":"Sura'",
    "gn:country_code":"YE",
    "gn:dem":2462,
    "gn:feature_class":"P",
    "gn:feature_code":"PPL",
    "gn:name":"\u015eura\u2018",
    "gn:population":0,
    "gn:timezone":"Asia/Aden",
    "iso:country":"YE",
    "name:ara_x_preferred":[
        "\u0635\u0631\u0639"
    ],
    "name:und_x_variant":[
        "\u015eura\u2018"
    ],
    "wof:name":"Sura'",
    "wof:placetype":"locality"
},
  "geometry": {"coordinates":[44.51636,15.49488],"type":"Point"}
}