{
  "type": "Feature",
  "properties": {
    "gn:admin1_code":"19.0",
    "gn:admin2_code":"2903.0",
    "gn:asciiname":"'Ajajah",
    "gn:country_code":"YE",
    "gn:dem":1385,
    "gn:feature_class":"P",
    "gn:feature_code":"PPLL",
    "gn:name":"\u2018Aj\u0101jah",
    "gn:population":0,
    "gn:timezone":"Asia/Aden",
    "iso:country":"YE",
    "name:ara_x_preferred":[
        "\u0639\u062c\u0627\u062c\u0629"
    ],
    "name:und_x_variant":[
        "\u2018Aj\u0101jah"
    ],
    "wof:name":"'Ajajah",
    "wof:placetype":"locality"
},
  "geometry": {"coordinates":[43.83634,16.1399],"type":"Point"}
}