{
  "type": "Feature",
  "properties": {
    "gn:admin1_code":"25.0",
    "gn:admin2_code":"1521.0",
    "gn:asciiname":"Dahiyah",
    "gn:country_code":"YE",
    "gn:dem":1206,
    "gn:feature_class":"P",
    "gn:feature_code":"PPL",
    "gn:name":"D\u0101\u1e29iyah",
    "gn:population":0,
    "gn:timezone":"Asia/Aden",
    "iso:country":"YE",
    "name:und_x_variant":[
        "D\u0101\u1e29iyah"
    ],
    "wof:name":"Dahiyah",
    "wof:placetype":"locality"
},
  "geometry": {"coordinates":[43.97879,13.46623],"type":"Point"}
}