{
  "type": "Feature",
  "properties": {
    "gn:admin1_code":"23.0",
    "gn:admin2_code":"1120.0",
    "gn:asciiname":"Haqlah",
    "gn:country_code":"YE",
    "gn:dem":2309,
    "gn:feature_class":"P",
    "gn:feature_code":"PPL",
    "gn:name":"\u1e28aqlah",
    "gn:population":0,
    "gn:timezone":"Asia/Aden",
    "iso:country":"YE",
    "name:und_x_variant":[
        "\u1e28aqlah"
    ],
    "wof:name":"Haqlah",
    "wof:placetype":"locality"
},
  "geometry": {"coordinates":[44.21879000000001,13.95416],"type":"Point"}
}