{
  "type": "Feature",
  "properties": {
    "gn:country":"YE",
    "gn:fcode":"PPL",
    "gn:pop":2,
    "iso:country":"YE",
    "name:ara_x_preferred":[
        "\u0100l Qur\u015f\u0101n"
    ],
    "name:ara_x_variant":[
        "\u0627\u0644 \u0642\u0631\u0635\u0627\u0646"
    ],
    "name:eng_x_preferred":[
        "Al Qursan"
    ],
    "name:eng_x_variant":[
        "\u1e28adaq\u012b"
    ],
    "qs:name":"\u0100l Qur\u015f\u0101n",
    "qs:photos_9r":0,
    "qs:photos_sr":0,
    "qs:pop_sr":"1",
    "wof:name":"\u0100l Qur\u015f\u0101n",
    "wof:placetype":"locality",
    "wof:population":2
},
  "geometry": {"coordinates":[44.77931,16.1322],"type":"Point"}
}