{
  "type": "Feature",
  "properties": {
    "gn:admin1_code":"15.0",
    "gn:admin2_code":"2213.0",
    "gn:asciiname":"Al Malfaj",
    "gn:country_code":"YE",
    "gn:dem":1841,
    "gn:feature_class":"P",
    "gn:feature_code":"PPL",
    "gn:name":"Al Malfaj",
    "gn:population":0,
    "gn:timezone":"Asia/Aden",
    "iso:country":"YE",
    "name:ara_x_preferred":[
        "\u0627\u0644\u0645\u0644\u0641\u062c"
    ],
    "wof:name":"Al Malfaj",
    "wof:placetype":"locality"
},
  "geometry": {"coordinates":[44.20084,16.88261],"type":"Point"}
}