{
  "type": "Feature",
  "properties": {
    "gn:admin1_code":"14.0",
    "gn:asciiname":"Furta'",
    "gn:country_code":"YE",
    "gn:dem":1747,
    "gn:feature_class":"P",
    "gn:feature_code":"PPL",
    "gn:name":"Furt\u0101\u2019",
    "gn:population":0,
    "gn:timezone":"Asia/Aden",
    "iso:country":"YE",
    "name:ara_x_preferred":[
        "\u0641\u0631\u062a\u0627\u0621"
    ],
    "name:und_x_variant":[
        "Furt\u0101\u2019"
    ],
    "wof:name":"Furta'",
    "wof:placetype":"locality"
},
  "geometry": {"coordinates":[44.72767,16.44083],"type":"Point"}
}