{
  "type": "Feature",
  "properties": {
    "gn:country":"YE",
    "gn:fcode":"PPL",
    "gn:pop":2,
    "iso:country":"YE",
    "name:ara_x_preferred":[
        "\u0627\u0644\u0642\u0631\u0649"
    ],
    "qs:name":"Al Qar\u00e1",
    "qs:photos_9r":0,
    "qs:photos_sr":0,
    "qs:pop_sr":"1",
    "wof:name":"Al Qar\u00e1",
    "wof:placetype":"locality",
    "wof:population":2
},
  "geometry": {"coordinates":[44.22951,16.69067],"type":"Point"}
}