{
  "type": "Feature",
  "properties": {
    "gn:admin1_code":"25.0",
    "gn:admin2_code":"1517.0",
    "gn:asciiname":"Al Hadarim",
    "gn:country_code":"YE",
    "gn:dem":1093,
    "gn:feature_class":"P",
    "gn:feature_code":"PPL",
    "gn:name":"Al \u1e28a\u1e11\u0101rim",
    "gn:population":0,
    "gn:timezone":"Asia/Aden",
    "iso:country":"YE",
    "name:ara_x_preferred":[
        "\u0627\u0644\u062d\u0636\u0627\u0631\u0645"
    ],
    "name:und_x_variant":[
        "Al \u1e28a\u1e11\u0101rim"
    ],
    "wof:name":"Al Hadarim",
    "wof:placetype":"locality"
},
  "geometry": {"coordinates":[44.23177,13.24488],"type":"Point"}
}