{
  "type": "Feature",
  "properties": {
    "gn:admin1_code":"22.0",
    "gn:admin2_code":"1725.0",
    "gn:asciiname":"Bayt al `Adlani",
    "gn:country_code":"YE",
    "gn:dem":1136,
    "gn:feature_class":"P",
    "gn:feature_code":"PPL",
    "gn:name":"Bayt al \u2018Adl\u0101n\u012b",
    "gn:population":0,
    "gn:timezone":"Asia/Aden",
    "iso:country":"YE",
    "name:und_x_variant":[
        "Bayt al \u2018Adl\u0101n\u012b"
    ],
    "wof:name":"Bayt al `Adlani",
    "wof:placetype":"locality"
},
  "geometry": {"coordinates":[43.54227,15.57406],"type":"Point"}
}