{
  "type": "Feature",
  "properties": {
    "gn:admin1_code":"19.0",
    "gn:admin2_code":"2901.0",
    "gn:asciiname":"Birkat as Sudan",
    "gn:cc2":"YE",
    "gn:country_code":"YE",
    "gn:dem":1980,
    "gn:feature_class":"P",
    "gn:feature_code":"PPL",
    "gn:name":"Birkat as S\u016bd\u0101n",
    "gn:population":0,
    "gn:timezone":"Asia/Aden",
    "iso:country":"YE",
    "name:und_x_variant":[
        "Birket-es-Sudan",
        "Birkat as S\u016bd\u0101n"
    ],
    "wof:name":"Birkat as Sudan",
    "wof:placetype":"locality"
},
  "geometry": {"coordinates":[43.73333,16.66667],"type":"Point"}
}