{
  "type": "Feature",
  "properties": {
    "gn:admin1_code":"5.0",
    "gn:admin2_code":"2115.0",
    "gn:asciiname":"Sarr al Hajri",
    "gn:country_code":"YE",
    "gn:dem":815,
    "gn:feature_class":"P",
    "gn:feature_code":"PPL",
    "gn:name":"Sarr al \u1e28ajr\u012b",
    "gn:population":0,
    "gn:timezone":"Asia/Aden",
    "iso:country":"YE",
    "name:und_x_variant":[
        "Sarr al \u1e28ajr\u012b"
    ],
    "wof:name":"Sarr al Hajri",
    "wof:placetype":"locality"
},
  "geometry": {"coordinates":[47.29037,14.46931],"type":"Point"}
}