{
  "type": "Feature",
  "properties": {
    "gn:admin1_code":"8.0",
    "gn:admin2_code":"1801.0",
    "gn:asciiname":"Muslaybat al Gharbiyah",
    "gn:country_code":"YE",
    "gn:dem":79,
    "gn:feature_class":"P",
    "gn:feature_code":"PPL",
    "gn:name":"Mu\u015flaybat al Gharb\u012byah",
    "gn:population":0,
    "gn:timezone":"Asia/Aden",
    "iso:country":"YE",
    "name:ara_x_preferred":[
        "\u0645\u0635\u0644\u064a\u0628\u0629 \u0627\u0644\u063a\u0631\u0628\u064a\u0629"
    ],
    "name:und_x_variant":[
        "Al Mu\u015flaybah",
        "Mu\u015flaybat al Gharb\u012byah"
    ],
    "wof:name":"Muslaybat al Gharbiyah",
    "wof:placetype":"locality"
},
  "geometry": {"coordinates":[42.99902,15.68686],"type":"Point"}
}