{
  "type": "Feature",
  "properties": {
    "gn:admin1_code":"19.0",
    "gn:admin2_code":"2902.0",
    "gn:asciiname":"Dha `Uwayd",
    "gn:country_code":"YE",
    "gn:dem":1858,
    "gn:feature_class":"P",
    "gn:feature_code":"PPL",
    "gn:name":"Dh\u0101 \u2018Uwayd",
    "gn:population":0,
    "gn:timezone":"Asia/Aden",
    "iso:country":"YE",
    "name:und_x_variant":[
        "Dh\u0101 \u2018Uwayd"
    ],
    "wof:name":"Dha `Uwayd",
    "wof:placetype":"locality"
},
  "geometry": {"coordinates":[43.96721,16.27817000000001],"type":"Point"}
}