{
  "type": "Feature",
  "properties": {
    "gn:admin1_code":"22.0",
    "gn:admin2_code":"1719.0",
    "gn:asciiname":"Shiras",
    "gn:country_code":"YE",
    "gn:dem":956,
    "gn:feature_class":"P",
    "gn:feature_code":"PPL",
    "gn:name":"Shiras",
    "gn:population":0,
    "gn:timezone":"Asia/Aden",
    "iso:country":"YE",
    "wof:name":"Shiras",
    "wof:placetype":"locality"
},
  "geometry": {"coordinates":[43.63524,15.73653],"type":"Point"}
}