{
  "type": "Feature",
  "properties": {
    "gn:admin1_code":"25.0",
    "gn:admin2_code":"1502.0",
    "gn:asciiname":"`Urakid",
    "gn:country_code":"YE",
    "gn:dem":1604,
    "gn:feature_class":"P",
    "gn:feature_code":"PPL",
    "gn:name":"\u2018Ur\u0101ki\u1e11",
    "gn:population":0,
    "gn:timezone":"Asia/Aden",
    "iso:country":"YE",
    "name:ara_x_preferred":[
        "\u2018Ur\u0101ki\u1e11"
    ],
    "wof:name":"`Urakid",
    "wof:placetype":"locality"
},
  "geometry": {"coordinates":[44.11346,13.75037],"type":"Point"}
}