{
  "type": "Feature",
  "properties": {
    "gn:admin1_code":"24.0",
    "gn:admin2_code":"2508.0",
    "gn:asciiname":"Ad Danabah",
    "gn:country_code":"YE",
    "gn:dem":568,
    "gn:feature_class":"P",
    "gn:feature_code":"PPL",
    "gn:name":"Ad Danabah",
    "gn:population":0,
    "gn:timezone":"Asia/Aden",
    "iso:country":"YE",
    "wof:name":"Ad Danabah",
    "wof:placetype":"locality"
},
  "geometry": {"coordinates":[44.80778,13.44472],"type":"Point"}
}