{
  "type": "Feature",
  "properties": {
    "gn:country":"YE",
    "gn:fcode":"PPL",
    "gn:pop":6,
    "iso:country":"YE",
    "name:ara_x_preferred":[
        "Al \u1e28ulq\u016bm"
    ],
    "name:ara_x_variant":[
        "\u0627\u0644\u062d\u0644\u0642\u0648\u0645"
    ],
    "name:eng_x_preferred":[
        "Al HulqUm"
    ],
    "name:eng_x_variant":[
        "M\u0101ni\u2018"
    ],
    "qs:name":"Al \u1e28ulq\u016bm",
    "qs:photos_9r":0,
    "qs:photos_sr":0,
    "qs:pop_sr":"1",
    "wof:name":"Al \u1e28ulq\u016bm",
    "wof:placetype":"locality",
    "wof:population":6
},
  "geometry": {"coordinates":[43.64422,13.11695],"type":"Point"}
}