{
  "type": "Feature",
  "properties": {
    "gn:admin1_code":"16.0",
    "gn:admin2_code":"2307.0",
    "gn:asciiname":"Shi`abat",
    "gn:country_code":"YE",
    "gn:dem":2859,
    "gn:feature_class":"P",
    "gn:feature_code":"PPL",
    "gn:name":"Shi\u2018\u0101b\u0101t",
    "gn:population":0,
    "gn:timezone":"Asia/Aden",
    "iso:country":"YE",
    "name:ara_x_preferred":[
        "Shi\u2018\u0101b\u0101t"
    ],
    "wof:name":"Shi`abat",
    "wof:placetype":"locality"
},
  "geometry": {"coordinates":[43.99489000000001,15.19045],"type":"Point"}
}