{
  "type": "Feature",
  "properties": {
    "gn:admin1_code":"22.0",
    "gn:admin2_code":"1724.0",
    "gn:asciiname":"Al Abtah",
    "gn:country_code":"YE",
    "gn:dem":408,
    "gn:feature_class":"P",
    "gn:feature_code":"PPL",
    "gn:name":"Al Ab\u0163a\u1e29",
    "gn:population":0,
    "gn:timezone":"Asia/Aden",
    "iso:country":"YE",
    "name:und_x_variant":[
        "Al Ab\u0163a\u1e29"
    ],
    "wof:name":"Al Abtah",
    "wof:placetype":"locality"
},
  "geometry": {"coordinates":[43.35768,15.55331],"type":"Point"}
}