{
  "type": "Feature",
  "properties": {
    "gn:country":"YE",
    "gn:fcode":"PPL",
    "gn:population":7,
    "iso:country":"YE",
    "name:ara_x_preferred":[
        "\u0648\u0627\u062f\u064a \u0639\u062c\u064a\u0645\u0627\u0646"
    ],
    "name:eng_x_preferred":[
        "Wadi 'Ujayman"
    ],
    "name:eng_x_variant":[
        "Al W\u0101\u1e11aj"
    ],
    "qs_pg:aaroncc":"YE",
    "qs_pg:gn_country":"YE",
    "qs_pg:gn_fcode":"PPL",
    "qs_pg:gn_pop":7,
    "qs_pg:name":"W\u0101d\u012b \u2018Ujaym\u0101n",
    "qs_pg:photos_9r":0,
    "qs_pg:photos_sr":0,
    "qs_pg:pop_sr":1,
    "qs_pg:qs_pg_placetype":"locality",
    "wof:name":"W\u0101d\u012b \u2018Ujaym\u0101n",
    "wof:placetype":"locality",
    "wof:population":7
},
  "geometry": {"coordinates":[43.40145,16.31388],"type":"Point"}
}