{
  "type": "Feature",
  "properties": {
    "gn:admin1_code":"23.0",
    "gn:admin2_code":"1106.0",
    "gn:asciiname":"Al Jadni",
    "gn:country_code":"YE",
    "gn:dem":2731,
    "gn:feature_class":"P",
    "gn:feature_code":"PPL",
    "gn:name":"Al Jadn\u012b",
    "gn:population":0,
    "gn:timezone":"Asia/Aden",
    "iso:country":"YE",
    "name:ara_x_preferred":[
        "\u0627\u0644\u062c\u062f\u0646\u064a"
    ],
    "name:und_x_variant":[
        "Al Judan\u012b",
        "Al Jadn\u012b"
    ],
    "wof:name":"Al Jadni",
    "wof:placetype":"locality"
},
  "geometry": {"coordinates":[44.39307,14.18783],"type":"Point"}
}