{
  "type": "Feature",
  "properties": {
    "gn:country":"YE",
    "gn:fcode":"PPL",
    "gn:population":5,
    "iso:country":"YE",
    "name:ara_x_preferred":[
        "\u0627\u0644\u062a \u0645\u0639\u0634\u064a\u0629"
    ],
    "name:eng_x_preferred":[
        "Alt Ma'shiyah"
    ],
    "name:eng_x_variant":[
        "\u0100l Gh\u0101nim"
    ],
    "qs:name":"Alt Ma\u2018sh\u012byah",
    "qs:photos_9r":0,
    "qs:photos_sr":0,
    "qs:pop_sr":"1",
    "wof:name":"Alt Ma\u2018sh\u012byah",
    "wof:placetype":"locality",
    "wof:population":5
},
  "geometry": {"coordinates":[43.26279,16.92084],"type":"Point"}
}