{
  "type": "Feature",
  "properties": {
    "gn:admin1_code":"22.0",
    "gn:admin2_code":"1726.0",
    "gn:asciiname":"Niswi",
    "gn:country_code":"YE",
    "gn:dem":914,
    "gn:feature_class":"P",
    "gn:feature_code":"PPL",
    "gn:name":"Nisw\u012b",
    "gn:population":0,
    "gn:timezone":"Asia/Aden",
    "iso:country":"YE",
    "name:ara_x_preferred":[
        "Nisw\u012b"
    ],
    "wof:name":"Niswi",
    "wof:placetype":"locality"
},
  "geometry": {"coordinates":[43.52953,15.64937],"type":"Point"}
}