{
  "type": "Feature",
  "properties": {
    "gn:admin1_code":"22.0",
    "gn:admin2_code":"1723.0",
    "gn:asciiname":"Bayt al `Umaysi al Milhah",
    "gn:country_code":"YE",
    "gn:dem":1070,
    "gn:feature_class":"P",
    "gn:feature_code":"PPL",
    "gn:name":"Bayt al \u2018Umays\u012b al Mil\u1e29ah",
    "gn:population":0,
    "gn:timezone":"Asia/Aden",
    "iso:country":"YE",
    "name:und_x_variant":[
        "Bayt al \u2018Umays\u012b al Mil\u1e29ah"
    ],
    "wof:name":"Bayt al `Umaysi al Milhah",
    "wof:placetype":"locality"
},
  "geometry": {"coordinates":[43.46692,15.71947],"type":"Point"}
}