{
  "type": "Feature",
  "properties": {
    "gn:admin1_code":"24.0",
    "gn:admin2_code":"2515.0",
    "gn:asciiname":"Za'idah",
    "gn:country_code":"YE",
    "gn:dem":261,
    "gn:feature_class":"P",
    "gn:feature_code":"PPL",
    "gn:name":"Z\u0101\u2019idah",
    "gn:population":0,
    "gn:timezone":"Asia/Aden",
    "iso:country":"YE",
    "name:und_x_variant":[
        "Zaida",
        "Z\u0101\u2019idah"
    ],
    "wof:name":"Za'idah",
    "wof:placetype":"locality"
},
  "geometry": {"coordinates":[44.80667,13.16722],"type":"Point"}
}