{
  "type": "Feature",
  "properties": {
    "gn:admin1_code":"19.0",
    "gn:admin2_code":"2912.0",
    "gn:asciiname":"Al Malahah",
    "gn:country_code":"YE",
    "gn:dem":2475,
    "gn:feature_class":"P",
    "gn:feature_code":"PPL",
    "gn:name":"Al Mala\u1e29ah",
    "gn:population":0,
    "gn:timezone":"Asia/Aden",
    "iso:country":"YE",
    "name:und_x_variant":[
        "Al Mala\u1e29ah"
    ],
    "wof:name":"Al Malahah",
    "wof:placetype":"locality"
},
  "geometry": {"coordinates":[43.89818,15.73671],"type":"Point"}
}