{
  "type": "Feature",
  "properties": {
    "gn:admin1_code":"25.0",
    "gn:admin2_code":"1504.0",
    "gn:asciiname":"Ar Rawnah",
    "gn:country_code":"YE",
    "gn:dem":1410,
    "gn:feature_class":"P",
    "gn:feature_code":"PPLA2",
    "gn:name":"Ar Rawnah",
    "gn:population":0,
    "gn:timezone":"Asia/Aden",
    "iso:country":"YE",
    "name:ara_x_preferred":[
        "\u0627\u0644\u0631\u0648\u0646\u0629"
    ],
    "wof:name":"Ar Rawnah",
    "wof:placetype":"locality"
},
  "geometry": {"coordinates":[43.80286,13.75638],"type":"Point"}
}