{
  "type": "Feature",
  "properties": {
    "gn:country":"YE",
    "gn:fcode":"PPL",
    "gn:pop":4,
    "iso:country":"YE",
    "name:ara_x_preferred":[
        "\u0627\u0644\u062c\u0644\u0627\u064a\u0645"
    ],
    "name:eng_x_preferred":[
        "Al Jalayam"
    ],
    "qs:name":"Al Jal\u0101yam",
    "qs:photos_9r":0,
    "qs:photos_sr":0,
    "qs:pop_sr":"1",
    "wof:name":"Al Jal\u0101yam",
    "wof:placetype":"locality",
    "wof:population":4
},
  "geometry": {"coordinates":[43.42313,16.03771],"type":"Point"}
}