{
  "type": "Feature",
  "properties": {
    "gn:admin1_code":"22.0",
    "gn:admin2_code":"1718.0",
    "gn:asciiname":"Bayt Khayrah",
    "gn:country_code":"YE",
    "gn:dem":1881,
    "gn:feature_class":"P",
    "gn:feature_code":"PPL",
    "gn:name":"Bayt Khayrah",
    "gn:population":0,
    "gn:timezone":"Asia/Aden",
    "iso:country":"YE",
    "wof:name":"Bayt Khayrah",
    "wof:placetype":"locality"
},
  "geometry": {"coordinates":[43.74011,15.72936],"type":"Point"}
}