{
  "type": "Feature",
  "properties": {
    "gn:admin1_code":"18.0",
    "gn:admin2_code":"3008.0",
    "gn:asciiname":"Usharah",
    "gn:country_code":"YE",
    "gn:dem":1211,
    "gn:feature_class":"P",
    "gn:feature_code":"PPL",
    "gn:name":"Usharah",
    "gn:population":0,
    "gn:timezone":"Asia/Aden",
    "iso:country":"YE",
    "name:und_x_variant":[
        "Ashara",
        "Usharah"
    ],
    "wof:name":"Usharah",
    "wof:placetype":"locality"
},
  "geometry": {"coordinates":[44.60463,13.67491],"type":"Point"}
}