{
  "type": "Feature",
  "properties": {
    "gn:admin1_code":"2.0",
    "gn:admin2_code":"2403.0",
    "gn:asciiname":"Bi'r Fadl",
    "gn:country_code":"YE",
    "gn:dem":14,
    "gn:feature_class":"P",
    "gn:feature_code":"PPL",
    "gn:name":"Bi\u2019r Fa\u1e11l",
    "gn:population":0,
    "gn:timezone":"Asia/Aden",
    "iso:country":"YE",
    "name:und_x_variant":[
        "Bir Fadhl",
        "Bi\u2019r Fa\u1e11l"
    ],
    "wof:name":"Bi'r Fadl",
    "wof:placetype":"locality"
},
  "geometry": {"coordinates":[44.9625,12.865],"type":"Point"}
}