{
  "type": "Feature",
  "properties": {
    "gn:country":"YE",
    "gn:fcode":"PPLX",
    "gn:pop":4,
    "iso:country":"YE",
    "name:ara_x_preferred":[
        "Al Muw\u0101jil"
    ],
    "name:ara_x_variant":[
        "\u0627\u0644\u0645\u0648\u0627\u062c\u0644"
    ],
    "qs:name":"Al Muw\u0101jil",
    "qs:photos_9r":0,
    "qs:photos_sr":0,
    "qs:pop_sr":"1",
    "wof:name":"Al Muw\u0101jil",
    "wof:placetype":"neighbourhood",
    "wof:population":4
},
  "geometry": {"coordinates":[43.66972,16.01952],"type":"Point"}
}