{
  "type": "Feature",
  "properties": {
    "gn:admin1_code":"25.0",
    "gn:admin2_code":"1515.0",
    "gn:asciiname":"Jabal Sabran",
    "gn:country_code":"YE",
    "gn:dem":2097,
    "gn:feature_class":"P",
    "gn:feature_code":"PPL",
    "gn:name":"Jabal \u015eabr\u0101n",
    "gn:population":0,
    "gn:timezone":"Asia/Aden",
    "iso:country":"YE",
    "name:ara_x_preferred":[
        "\u062c\u0628\u0644 \u0635\u0628\u0631\u0627\u0646"
    ],
    "name:und_x_variant":[
        "\u2018Ily\u0101fah",
        "Jabal \u015eabr\u0101n",
        "Jabal \u015eabar\u0101n"
    ],
    "wof:name":"Jabal Sabran",
    "wof:placetype":"locality"
},
  "geometry": {"coordinates":[44.15162,13.23272],"type":"Point"}
}