{
  "type": "Feature",
  "properties": {
    "gn:admin1_code":"22.0",
    "gn:admin2_code":"1702.0",
    "gn:asciiname":"Hasamah",
    "gn:country_code":"YE",
    "gn:dem":96,
    "gn:feature_class":"P",
    "gn:feature_code":"PPL",
    "gn:name":"\u1e28a\u015famah",
    "gn:population":0,
    "gn:timezone":"Asia/Aden",
    "iso:country":"YE",
    "name:und_x_variant":[
        "\u1e28a\u015famah"
    ],
    "wof:name":"Hasamah",
    "wof:placetype":"locality"
},
  "geometry": {"coordinates":[43.08113,16.3669],"type":"Point"}
}