{
  "type": "Feature",
  "properties": {
    "gn:admin1_code":"22.0",
    "gn:admin2_code":"1731.0",
    "gn:asciiname":"Jiyu al Akharah",
    "gn:country_code":"YE",
    "gn:dem":1129,
    "gn:feature_class":"P",
    "gn:feature_code":"PPL",
    "gn:name":"Jiy\u016b al Akharah",
    "gn:population":0,
    "gn:timezone":"Asia/Aden",
    "iso:country":"YE",
    "name:und_x_variant":[
        "Jiy\u016b al Akharah"
    ],
    "wof:name":"Jiyu al Akharah",
    "wof:placetype":"locality"
},
  "geometry": {"coordinates":[43.51447,16.2725],"type":"Point"}
}