{
  "type": "Feature",
  "properties": {
    "gn:admin1_code":"25.0",
    "gn:admin2_code":"1517.0",
    "gn:asciiname":"Al Kubaybah",
    "gn:country_code":"YE",
    "gn:dem":1095,
    "gn:feature_class":"P",
    "gn:feature_code":"PPL",
    "gn:name":"Al Kubaybah",
    "gn:population":0,
    "gn:timezone":"Asia/Aden",
    "iso:country":"YE",
    "name:ara_x_preferred":[
        "\u0627\u0644\u0643\u0628\u064a\u0628\u0629"
    ],
    "wof:name":"Al Kubaybah",
    "wof:placetype":"locality"
},
  "geometry": {"coordinates":[44.23825,13.24656],"type":"Point"}
}