{
  "type": "Feature",
  "properties": {
    "gn:admin1_code":"19.0",
    "gn:admin2_code":"2913.0",
    "gn:asciiname":"Ruhayqah",
    "gn:country_code":"YE",
    "gn:dem":1753,
    "gn:feature_class":"P",
    "gn:feature_code":"PPL",
    "gn:name":"Ruhayqah",
    "gn:population":0,
    "gn:timezone":"Asia/Aden",
    "iso:country":"YE",
    "wof:name":"Ruhayqah",
    "wof:placetype":"locality"
},
  "geometry": {"coordinates":[43.79329,15.9299],"type":"Point"}
}