{
  "type": "Feature",
  "properties": {
    "gn:admin1_code":"4.0",
    "gn:admin2_code":"1907.0",
    "gn:asciiname":"Hayd Talib ar Rizq",
    "gn:cc2":"YE",
    "gn:country_code":"YE",
    "gn:dem":673,
    "gn:feature_class":"P",
    "gn:feature_code":"PPL",
    "gn:name":"\u1e28ayd \u0162\u0101lib ar Rizq",
    "gn:population":0,
    "gn:timezone":"Asia/Aden",
    "iso:country":"YE",
    "name:und_x_variant":[
        "\u1e24aid \u1e6c\u0101lib al-Rizq",
        "Hajd T\u0101lib al-Rizq",
        "\u1e28ayd \u0162\u0101lib ar Rizq"
    ],
    "wof:name":"Hayd Talib ar Rizq",
    "wof:placetype":"locality"
},
  "geometry": {"coordinates":[48.48333,15.86667],"type":"Point"}
}