{
  "type": "Feature",
  "properties": {
    "gn:country":"YE",
    "gn:fcode":"PPL",
    "gn:pop":21,
    "iso:country":"YE",
    "name:ara_x_preferred":[
        "\u0627\u0644\u0631\u0648\u0636\u0629"
    ],
    "name:eng_x_preferred":[
        "Ar Rawuah"
    ],
    "qs:name":"Ar Raw\u1e11ah",
    "qs:photos_9r":0,
    "qs:photos_sr":0,
    "qs:pop_sr":"1",
    "wof:name":"Ar Raw\u1e11ah",
    "wof:placetype":"locality",
    "wof:population":21
},
  "geometry": {"coordinates":[45.53771,15.03706],"type":"Point"}
}