{
  "type": "Feature",
  "properties": {
    "gn:admin1_code":"8.0",
    "gn:admin2_code":"1814.0",
    "gn:asciiname":"Al Kabaziyah",
    "gn:country_code":"YE",
    "gn:dem":59,
    "gn:feature_class":"P",
    "gn:feature_code":"PPL",
    "gn:name":"Al Kab\u0101z\u012byah",
    "gn:population":0,
    "gn:timezone":"Asia/Aden",
    "iso:country":"YE",
    "name:ara_x_preferred":[
        "\u0627\u0644\u0643\u0628\u0627\u0632\u064a\u0629"
    ],
    "name:und_x_variant":[
        "Al Kab\u0101z\u012byah"
    ],
    "wof:name":"Al Kabaziyah",
    "wof:placetype":"locality"
},
  "geometry": {"coordinates":[43.21935,14.60622],"type":"Point"}
}