{
  "type": "Feature",
  "properties": {
    "gn:admin1_code":"25.0",
    "gn:admin2_code":"1513.0",
    "gn:asciiname":"Hudhiyah",
    "gn:country_code":"YE",
    "gn:dem":1693,
    "gn:feature_class":"P",
    "gn:feature_code":"PPL",
    "gn:name":"\u1e28udhiyah",
    "gn:population":0,
    "gn:timezone":"Asia/Aden",
    "iso:country":"YE",
    "name:und_x_variant":[
        "\u1e28udhiyah"
    ],
    "wof:name":"Hudhiyah",
    "wof:placetype":"locality"
},
  "geometry": {"coordinates":[44.08736,13.41332],"type":"Point"}
}