{
  "type": "Feature",
  "properties": {
    "gn:admin1_code":"23.0",
    "gn:admin2_code":"1103.0",
    "gn:asciiname":"Al Marazim",
    "gn:country_code":"YE",
    "gn:dem":2546,
    "gn:feature_class":"P",
    "gn:feature_code":"PPL",
    "gn:name":"Al Mar\u0101zim",
    "gn:population":0,
    "gn:timezone":"Asia/Aden",
    "iso:country":"YE",
    "name:und_x_variant":[
        "Al Mar\u0101zim"
    ],
    "wof:name":"Al Marazim",
    "wof:placetype":"locality"
},
  "geometry": {"coordinates":[44.499,14.26193],"type":"Point"}
}