{
  "type": "Feature",
  "properties": {
    "gn:country":"YE",
    "gn:fcode":"PPL",
    "gn:pop":5,
    "iso:country":"YE",
    "name:ara_x_preferred":[
        "\u0627\u0644\u0648\u0639\u0631\u0629"
    ],
    "qs:name":"Al Wa\u2018irah",
    "qs:photos_9r":0,
    "qs:photos_sr":0,
    "qs:pop_sr":"1",
    "wof:name":"Al Wa\u2018irah",
    "wof:placetype":"locality",
    "wof:population":5
},
  "geometry": {"coordinates":[43.45545,16.20304],"type":"Point"}
}