{
  "type": "Feature",
  "properties": {
    "gn:country":"YE",
    "gn:fcode":"PPL",
    "gn:pop":29,
    "iso:country":"YE",
    "name:ara_x_preferred":[
        "Dhub\u0101n"
    ],
    "name:ara_x_variant":[
        "\u0630\u0628\u0627\u0646"
    ],
    "name:eng_x_preferred":[
        "Dhuban"
    ],
    "name:eng_x_variant":[
        "Al Jithwah"
    ],
    "qs:name":"Dhub\u0101n",
    "qs:photos_9r":0,
    "qs:photos_sr":0,
    "qs:pop_sr":"1",
    "wof:name":"Dhub\u0101n",
    "wof:placetype":"locality",
    "wof:population":29
},
  "geometry": {"coordinates":[45.14778,14.38007],"type":"Point"}
}