{
  "type": "Feature",
  "properties": {
    "gn:admin1_code":"5.0",
    "gn:admin2_code":"2107.0",
    "gn:asciiname":"Al Jabih",
    "gn:country_code":"YE",
    "gn:dem":1147,
    "gn:elevation":"2.0",
    "gn:feature_class":"P",
    "gn:feature_code":"PPL",
    "gn:name":"Al J\u0101bih",
    "gn:population":0,
    "gn:timezone":"Asia/Aden",
    "iso:country":"YE",
    "name:ara_x_preferred":[
        "Al J\u0101bih"
    ],
    "wof:name":"Al Jabih",
    "wof:placetype":"locality"
},
  "geometry": {"coordinates":[45.68652,14.79708],"type":"Point"}
}