{
  "type": "Feature",
  "properties": {
    "gn:admin1_code":"4.0",
    "gn:admin2_code":"1917.0",
    "gn:asciiname":"Ghayl Ba Wazir",
    "gn:country_code":"YE",
    "gn:dem":87,
    "gn:feature_class":"P",
    "gn:feature_code":"PPLA2",
    "gn:name":"Ghayl B\u0101 Waz\u012br",
    "gn:population":0,
    "gn:timezone":"Asia/Aden",
    "iso:country":"YE",
    "name:ara_x_preferred":[
        "\u063a\u064a\u0644 \u0628\u0627 \u0648\u0632\u064a\u0631"
    ],
    "name:ara_x_variant":[
        "\u063a\u064a\u0644 \u0628\u0627\u0648\u0632\u064a\u0631"
    ],
    "name:fas_x_preferred":[
        "\u063a\u06cc\u0644 \u0628\u0627\u0648\u0632\u06cc\u0631"
    ],
    "name:nno_x_preferred":[
        "Ghayl Ba Wazir"
    ],
    "name:und_x_variant":[
        "Ghail B\u0101 Waz\u012br",
        "Gheil B\u0101 Wazir",
        "Ghayl B\u0101 Waz\u012br"
    ],
    "wof:name":"Ghayl Ba Wazir",
    "wof:placetype":"locality"
},
  "geometry": {"coordinates":[49.36611,14.77611],"type":"Point"}
}