{
  "type": "Feature",
  "properties": {
    "gn:admin1_code":"15.0",
    "gn:admin2_code":"2208.0",
    "gn:asciiname":"Al Qashbah",
    "gn:country_code":"YE",
    "gn:dem":1776,
    "gn:feature_class":"P",
    "gn:feature_code":"PPL",
    "gn:name":"Al Qashbah",
    "gn:population":0,
    "gn:timezone":"Asia/Aden",
    "iso:country":"YE",
    "name:ara_x_preferred":[
        "\u0627\u0644\u0642\u0634\u0628\u0629"
    ],
    "name:und_x_variant":[
        "Al Qishbah"
    ],
    "wof:name":"Al Qashbah",
    "wof:placetype":"locality"
},
  "geometry": {"coordinates":[43.38216,16.84235],"type":"Point"}
}