{
  "type": "Feature",
  "properties": {
    "gn:country":"YE",
    "gn:fcode":"PPL",
    "gn:pop":22,
    "iso:country":"YE",
    "name:ara_x_preferred":[
        "\u0627\u0644\u0647\u064a\u062c\u0629"
    ],
    "qs:name":"Al Hayjah",
    "qs:photos_9r":0,
    "qs:photos_sr":0,
    "qs:pop_sr":"1",
    "wof:name":"Al Hayjah",
    "wof:placetype":"locality",
    "wof:population":22
},
  "geometry": {"coordinates":[43.67536,16.34136],"type":"Point"}
}