{
  "type": "Feature",
  "properties": {
    "gn:admin1_code":"20.0",
    "gn:admin2_code":"1411.0",
    "gn:asciiname":"Dammaj Bayt al Khadir",
    "gn:country_code":"YE",
    "gn:dem":2003,
    "gn:feature_class":"P",
    "gn:feature_code":"PPL",
    "gn:name":"Dammaj Bayt al Kha\u1e11ir",
    "gn:population":0,
    "gn:timezone":"Asia/Aden",
    "iso:country":"YE",
    "name:ara_x_preferred":[
        "Dim\u0101j"
    ],
    "name:und_x_variant":[
        "Dammaj Bayt al Kha\u1e11ir"
    ],
    "wof:name":"Dammaj Bayt al Khadir",
    "wof:placetype":"locality"
},
  "geometry": {"coordinates":[45.25654,14.27036],"type":"Point"}
}