{
  "type": "Feature",
  "properties": {
    "gn:admin1_code":"22.0",
    "gn:admin2_code":"1724.0",
    "gn:asciiname":"Az Zuhur",
    "gn:country_code":"YE",
    "gn:dem":438,
    "gn:feature_class":"P",
    "gn:feature_code":"PPL",
    "gn:name":"Az\u0327 Z\u0327uh\u016br",
    "gn:population":0,
    "gn:timezone":"Asia/Aden",
    "iso:country":"YE",
    "name:ara_x_preferred":[
        "Az\u0327 Z\u0327uh\u016br"
    ],
    "wof:name":"Az Zuhur",
    "wof:placetype":"locality"
},
  "geometry": {"coordinates":[43.41053,15.6384],"type":"Point"}
}