{
  "type": "Feature",
  "properties": {
    "gn:country":"YE",
    "gn:fcode":"PPL",
    "gn:pop":2,
    "iso:country":"YE",
    "name:ara_x_preferred":[
        "\u062d\u064a\u0627\u0641 \u0627\u0644\u062d\u062c\u064a\u0644"
    ],
    "name:eng_x_preferred":[
        "Hiyaf Al Hujayl"
    ],
    "name:eng_x_variant":[
        "\u0100l H\u0101shil"
    ],
    "qs:name":"\u1e28iy\u0101f al \u1e28ujayl",
    "qs:photos_9r":0,
    "qs:photos_sr":0,
    "qs:pop_sr":"1",
    "wof:name":"\u1e28iy\u0101f al \u1e28ujayl",
    "wof:placetype":"locality",
    "wof:population":2
},
  "geometry": {"coordinates":[43.25988,17.10773],"type":"Point"}
}