{
  "type": "Feature",
  "properties": {
    "gn:admin1_code":"20.0",
    "gn:admin2_code":"1417.0",
    "gn:asciiname":"Shihab",
    "gn:country_code":"YE",
    "gn:dem":2612,
    "gn:feature_class":"P",
    "gn:feature_code":"PPL",
    "gn:name":"Shih\u0101b",
    "gn:population":0,
    "gn:timezone":"Asia/Aden",
    "iso:country":"YE",
    "name:ara_x_preferred":[
        "Shih\u0101b"
    ],
    "wof:name":"Shihab",
    "wof:placetype":"locality"
},
  "geometry": {"coordinates":[44.73917,14.30223],"type":"Point"}
}