{
  "type": "Feature",
  "properties": {
    "gn:admin1_code":"1.0",
    "gn:admin2_code":"1211.0",
    "gn:asciiname":"Ja`ar",
    "gn:country_code":"YE",
    "gn:dem":71,
    "gn:feature_class":"P",
    "gn:feature_code":"PPLA2",
    "gn:name":"Ja\u2018\u0101r",
    "gn:population":0,
    "gn:timezone":"Asia/Aden",
    "iso:country":"YE",
    "name:ara_x_preferred":[
        "\u062c\u0639\u0627\u0631"
    ],
    "name:und_x_variant":[
        "Gia\u2018ar",
        "Ji\u2018\u0101r",
        "Khanfar",
        "Ja\u2018\u0101r"
    ],
    "wof:name":"Ja`ar",
    "wof:placetype":"locality"
},
  "geometry": {"coordinates":[45.30559,13.223],"type":"Point"}
}