{
  "type": "Feature",
  "properties": {
    "gn:admin1_code":"23.0",
    "gn:admin2_code":"1115.0",
    "gn:asciiname":"As Sarih",
    "gn:country_code":"YE",
    "gn:dem":2022,
    "gn:feature_class":"P",
    "gn:feature_code":"PPL",
    "gn:name":"As Sar\u012b\u1e29",
    "gn:population":0,
    "gn:timezone":"Asia/Aden",
    "iso:country":"YE",
    "name:und_x_variant":[
        "As Sar\u012b\u1e29"
    ],
    "wof:name":"As Sarih",
    "wof:placetype":"locality"
},
  "geometry": {"coordinates":[44.23344,13.8866],"type":"Point"}
}