{
  "type": "Feature",
  "properties": {
    "gn:admin1_code":"5.0",
    "gn:admin2_code":"2110.0",
    "gn:asciiname":"Hiswan",
    "gn:country_code":"YE",
    "gn:dem":1142,
    "gn:feature_class":"P",
    "gn:feature_code":"PPL",
    "gn:name":"Hisw\u0101n",
    "gn:population":0,
    "gn:timezone":"Asia/Aden",
    "iso:country":"YE",
    "name:ara_x_preferred":[
        "Hisw\u0101n"
    ],
    "wof:name":"Hiswan",
    "wof:placetype":"locality"
},
  "geometry": {"coordinates":[46.40037,14.45393],"type":"Point"}
}