{
  "type": "Feature",
  "properties": {
    "gn:country":"YE",
    "gn:fcode":"PPL",
    "gn:population":3,
    "iso:country":"YE",
    "name:ara_x_preferred":[
        "Mi\u0163r\u0101sh"
    ],
    "name:ara_x_variant":[
        "\u0645\u0637\u0631\u0627\u0634"
    ],
    "name:eng_x_preferred":[
        "Mitrash"
    ],
    "name:nno_x_preferred":[
        "Sinwan"
    ],
    "qs:name":"Mi\u0163r\u0101sh",
    "qs:photos_9r":0,
    "qs:photos_sr":0,
    "qs:pop_sr":"1",
    "wof:name":"Mi\u0163r\u0101sh",
    "wof:placetype":"locality",
    "wof:population":3
},
  "geometry": {"coordinates":[43.61123,16.27081],"type":"Point"}
}