{
  "type": "Feature",
  "properties": {
    "gn:admin1_code":"23.0",
    "gn:admin2_code":"1105.0",
    "gn:asciiname":"Naqil ash Shawhati",
    "gn:country_code":"YE",
    "gn:dem":2592,
    "gn:feature_class":"P",
    "gn:feature_code":"PPL",
    "gn:name":"Naq\u012bl ash Shaw\u1e29a\u0163\u012b",
    "gn:population":0,
    "gn:timezone":"Asia/Aden",
    "iso:country":"YE",
    "name:ara_x_preferred":[
        "\u0646\u0642\u064a\u0644 \u0627\u0644\u0634\u0648\u062d\u0637\u064a"
    ],
    "name:und_x_variant":[
        "Naq\u012bl ash Shaw\u1e29a\u0163\u012b"
    ],
    "wof:name":"Naqil ash Shawhati",
    "wof:placetype":"locality"
},
  "geometry": {"coordinates":[44.42635,14.04702],"type":"Point"}
}