{
  "type": "Feature",
  "properties": {
    "gn:admin1_code":"15.0",
    "gn:admin2_code":"2211.0",
    "gn:asciiname":"Al Khabt",
    "gn:country_code":"YE",
    "gn:dem":1904,
    "gn:feature_class":"P",
    "gn:feature_code":"PPL",
    "gn:name":"Al Khabt",
    "gn:population":0,
    "gn:timezone":"Asia/Aden",
    "iso:country":"YE",
    "name:ara_x_preferred":[
        "\u0627\u0644\u062e\u0628\u062a"
    ],
    "wof:name":"Al Khabt",
    "wof:placetype":"locality"
},
  "geometry": {"coordinates":[43.70274000000001,17.00569],"type":"Point"}
}