{
  "type": "Feature",
  "properties": {
    "gn:admin1_code":"25.0",
    "gn:admin2_code":"1508.0",
    "gn:asciiname":"Dar Da`sayn",
    "gn:country_code":"YE",
    "gn:dem":231,
    "gn:feature_class":"P",
    "gn:feature_code":"PPL",
    "gn:name":"D\u0101r Da\u2018sayn",
    "gn:population":0,
    "gn:timezone":"Asia/Aden",
    "iso:country":"YE",
    "name:ara_x_preferred":[
        "\u062f\u0627\u0631 \u062f\u0639\u0633\u064a\u0646"
    ],
    "name:und_x_variant":[
        "D\u0101r Da\u2018sayn"
    ],
    "wof:name":"Dar Da`sayn",
    "wof:placetype":"locality"
},
  "geometry": {"coordinates":[43.52746,13.28526],"type":"Point"}
}