{
  "type": "Feature",
  "properties": {
    "gn:admin1_code":"20.0",
    "gn:admin2_code":"1416.0",
    "gn:asciiname":"Qarn al Asad",
    "gn:country_code":"YE",
    "gn:dem":2172,
    "gn:feature_class":"P",
    "gn:feature_code":"PPL",
    "gn:name":"Qarn al Asad",
    "gn:population":0,
    "gn:timezone":"Asia/Aden",
    "iso:country":"YE",
    "name:und_x_variant":[
        "Qamal Asad",
        "Qarn al Asad"
    ],
    "wof:name":"Qarn al Asad",
    "wof:placetype":"locality"
},
  "geometry": {"coordinates":[44.82382,14.3559],"type":"Point"}
}