{
  "type": "Feature",
  "properties": {
    "gn:admin1_code":"5.0",
    "gn:admin2_code":"2117.0",
    "gn:asciiname":"Qana'",
    "gn:country_code":"YE",
    "gn:dem":-3,
    "gn:feature_class":"P",
    "gn:feature_code":"PPL",
    "gn:name":"Qana\u2018",
    "gn:population":0,
    "gn:timezone":"Asia/Aden",
    "iso:country":"YE",
    "name:und_x_variant":[
        "Qana\u2018"
    ],
    "wof:name":"Qana'",
    "wof:placetype":"locality"
},
  "geometry": {"coordinates":[48.32113,14.00622],"type":"Point"}
}