{
  "type": "Feature",
  "properties": {
    "gn:admin1_code":"15.0",
    "gn:admin2_code":"2203.0",
    "gn:asciiname":"Khulayq",
    "gn:country_code":"YE",
    "gn:dem":1973,
    "gn:feature_class":"P",
    "gn:feature_code":"PPL",
    "gn:name":"Khulayq",
    "gn:population":0,
    "gn:timezone":"Asia/Aden",
    "iso:country":"YE",
    "name:ara_x_preferred":[
        "\u062e\u0644\u064a\u0642"
    ],
    "wof:name":"Khulayq",
    "wof:placetype":"locality"
},
  "geometry": {"coordinates":[43.25265,17.15596],"type":"Point"}
}