{
  "type": "Feature",
  "properties": {
    "gn:admin1_code":"5.0",
    "gn:admin2_code":"2107.0",
    "gn:asciiname":"Habban",
    "gn:country_code":"YE",
    "gn:dem":1182,
    "gn:elevation":"2.0",
    "gn:feature_class":"P",
    "gn:feature_code":"PPL",
    "gn:name":"\u1e28abb\u0101n",
    "gn:population":0,
    "gn:timezone":"Asia/Aden",
    "iso:country":"YE",
    "name:fra_x_preferred":[
        "Habban"
    ],
    "name:und_x_variant":[
        "\u1e28abb\u0101n"
    ],
    "wof:name":"Habban",
    "wof:placetype":"locality"
},
  "geometry": {"coordinates":[45.73795,14.70783],"type":"Point"}
}