{
  "type": "Feature",
  "properties": {
    "gn:admin1_code":"14.0",
    "gn:admin2_code":"2613.0",
    "gn:asciiname":"Wahshan",
    "gn:country_code":"YE",
    "gn:dem":1066,
    "gn:feature_class":"P",
    "gn:feature_code":"PPL",
    "gn:name":"Wa\u1e29sh\u0101n",
    "gn:population":0,
    "gn:timezone":"Asia/Aden",
    "iso:country":"YE",
    "name:ara_x_preferred":[
        "\u0648\u062d\u0634\u0627\u0646"
    ],
    "name:und_x_variant":[
        "Wa\u1e29sh\u0101n"
    ],
    "wof:name":"Wahshan",
    "wof:placetype":"locality"
},
  "geometry": {"coordinates":[45.43076,15.47339],"type":"Point"}
}