{
  "type": "Feature",
  "properties": {
    "gn:admin1_code":"8.0",
    "gn:admin2_code":"1806.0",
    "gn:asciiname":"Dayr `Uwidan",
    "gn:country_code":"YE",
    "gn:dem":122,
    "gn:feature_class":"P",
    "gn:feature_code":"PPL",
    "gn:name":"Dayr \u2018Uw\u012bd\u0101n",
    "gn:population":0,
    "gn:timezone":"Asia/Aden",
    "iso:country":"YE",
    "name:und_x_variant":[
        "Dayr \u2018Uw\u012bd\u0101n"
    ],
    "wof:name":"Dayr `Uwidan",
    "wof:placetype":"locality"
},
  "geometry": {"coordinates":[43.19392,15.48482],"type":"Point"}
}