{
  "type": "Feature",
  "properties": {
    "gn:country":"YE",
    "gn:fcode":"PPL",
    "gn:population":12,
    "iso:country":"YE",
    "name:ara_x_preferred":[
        "\u2018Irq"
    ],
    "name:ara_x_variant":[
        "\u0639\u0631\u0642"
    ],
    "name:eng_x_preferred":[
        "Irq"
    ],
    "name:eng_x_variant":[
        "Dhir\u0101\u2018 Sa\u2018\u016bd",
        "'Irq"
    ],
    "qs:name":"\u2018Irq",
    "qs:photos_9r":0,
    "qs:photos_sr":0,
    "qs:pop_sr":"1",
    "wof:name":"\u2018Irq",
    "wof:placetype":"locality",
    "wof:population":12
},
  "geometry": {"coordinates":[43.36321,16.98332],"type":"Point"}
}