{
  "type": "Feature",
  "properties": {
    "gn:country":"YE",
    "gn:fcode":"PPL",
    "gn:population":5,
    "iso:country":"YE",
    "name:ara_x_preferred":[
        "Al Q\u0101fi\u2018"
    ],
    "name:ara_x_variant":[
        "\u0627\u0644\u0642\u0627\u0641\u0639"
    ],
    "qs:name":"Al Q\u0101fi\u2018",
    "qs:photos_9r":0,
    "qs:photos_sr":0,
    "qs:pop_sr":"1",
    "wof:name":"Al Q\u0101fi\u2018",
    "wof:placetype":"locality",
    "wof:population":5
},
  "geometry": {"coordinates":[43.68885,16.04327],"type":"Point"}
}