{
  "type": "Feature",
  "properties": {
    "gn:admin1_code":"15.0",
    "gn:admin2_code":"2204.0",
    "gn:asciiname":"Al Lujayj",
    "gn:country_code":"YE",
    "gn:dem":1682,
    "gn:feature_class":"P",
    "gn:feature_code":"PPL",
    "gn:name":"Al Lujayj",
    "gn:population":0,
    "gn:timezone":"Asia/Aden",
    "iso:country":"YE",
    "name:ara_x_preferred":[
        "Al \u2018\u0100d\u012b"
    ],
    "name:ara_x_variant":[
        "\u0627\u0644\u0644\u062c\u064a\u062c"
    ],
    "wof:name":"Al Lujayj",
    "wof:placetype":"locality"
},
  "geometry": {"coordinates":[43.35961,16.98761],"type":"Point"}
}