{
  "type": "Feature",
  "properties": {
    "gn:admin1_code":"8.0",
    "gn:admin2_code":"1816.0",
    "gn:asciiname":"Bani al Wayt",
    "gn:country_code":"YE",
    "gn:dem":125,
    "gn:feature_class":"P",
    "gn:feature_code":"PPL",
    "gn:name":"Ban\u012b al Way\u0163",
    "gn:population":0,
    "gn:timezone":"Asia/Aden",
    "iso:country":"YE",
    "name:und_x_variant":[
        "Ban\u012b al Way\u0163"
    ],
    "wof:name":"Bani al Wayt",
    "wof:placetype":"locality"
},
  "geometry": {"coordinates":[43.2843,14.68335],"type":"Point"}
}