{
  "type": "Feature",
  "properties": {
    "gn:admin1_code":"8.0",
    "gn:admin2_code":"1818.0",
    "gn:asciiname":"Al Mazawih",
    "gn:country_code":"YE",
    "gn:dem":288,
    "gn:feature_class":"P",
    "gn:feature_code":"PPL",
    "gn:name":"Al Maz\u0327\u0101w\u012b\u1e29",
    "gn:population":0,
    "gn:timezone":"Asia/Aden",
    "iso:country":"YE",
    "name:und_x_variant":[
        "Al Maz\u0327\u0101w\u012b\u1e29"
    ],
    "wof:name":"Al Mazawih",
    "wof:placetype":"locality"
},
  "geometry": {"coordinates":[43.55132,14.01677],"type":"Point"}
}