{
  "type": "Feature",
  "properties": {
    "gn:admin1_code":"23.0",
    "gn:admin2_code":"1105.0",
    "gn:asciiname":"Qablan",
    "gn:country_code":"YE",
    "gn:dem":3171,
    "gn:feature_class":"P",
    "gn:feature_code":"PPL",
    "gn:name":"Qabl\u0101n",
    "gn:population":0,
    "gn:timezone":"Asia/Aden",
    "iso:country":"YE",
    "name:ara_x_preferred":[
        "\u0642\u0628\u0644\u0627\u0646"
    ],
    "name:und_x_variant":[
        "Qabl\u0101n"
    ],
    "wof:name":"Qablan",
    "wof:placetype":"locality"
},
  "geometry": {"coordinates":[44.33426,14.04552],"type":"Point"}
}