{
  "type": "Feature",
  "properties": {
    "gn:admin1_code":"16.0",
    "gn:admin2_code":"2315.0",
    "gn:asciiname":"Bayt Mahdad",
    "gn:country_code":"YE",
    "gn:dem":2477,
    "gn:feature_class":"P",
    "gn:feature_code":"PPL",
    "gn:name":"Bayt Ma\u1e29dad",
    "gn:population":0,
    "gn:timezone":"Asia/Aden",
    "iso:country":"YE",
    "name:und_x_variant":[
        "Bayt Ma\u1e29dad"
    ],
    "wof:name":"Bayt Mahdad",
    "wof:placetype":"locality"
},
  "geometry": {"coordinates":[44.4228,14.96623],"type":"Point"}
}