{
  "type": "Feature",
  "properties": {
    "gn:admin1_code":"11.0",
    "gn:admin2_code":"2002.0",
    "gn:asciiname":"Qubbat Hathith",
    "gn:country_code":"YE",
    "gn:dem":2418,
    "gn:feature_class":"P",
    "gn:feature_code":"PPL",
    "gn:name":"Qubbat \u1e28ath\u012bth",
    "gn:population":0,
    "gn:timezone":"Asia/Aden",
    "iso:country":"YE",
    "name:und_x_variant":[
        "Qubbat \u1e28ath\u012bth"
    ],
    "wof:name":"Qubbat Hathith",
    "wof:placetype":"locality"
},
  "geometry": {"coordinates":[44.27239,14.64959],"type":"Point"}
}