{
  "type": "Feature",
  "properties": {
    "gn:admin1_code":"16.0",
    "gn:admin2_code":"2303.0",
    "gn:asciiname":"Bayt Shayban",
    "gn:country_code":"YE",
    "gn:dem":2168,
    "gn:feature_class":"P",
    "gn:feature_code":"PPL",
    "gn:name":"Bayt Shayb\u0101n",
    "gn:population":0,
    "gn:timezone":"Asia/Aden",
    "iso:country":"YE",
    "name:und_x_variant":[
        "Bayt Shayb\u0101n"
    ],
    "wof:name":"Bayt Shayban",
    "wof:placetype":"locality"
},
  "geometry": {"coordinates":[44.49386,15.60036],"type":"Point"}
}