{
  "type": "Feature",
  "properties": {
    "gn:admin1_code":"16.0",
    "gn:admin2_code":"2310.0",
    "gn:asciiname":"Al Jirmah",
    "gn:country_code":"YE",
    "gn:dem":2200,
    "gn:feature_class":"P",
    "gn:feature_code":"PPL",
    "gn:name":"Al Jirmah",
    "gn:population":0,
    "gn:timezone":"Asia/Aden",
    "iso:country":"YE",
    "name:fas_x_preferred":[
        "\u0627\u0644\u062c\u06cc\u0631\u0645\u0627\u0647"
    ],
    "name:nno_x_preferred":[
        "Al-Jirmah"
    ],
    "wof:name":"Al Jirmah",
    "wof:placetype":"locality"
},
  "geometry": {"coordinates":[43.77975,15.04693],"type":"Point"}
}