{
  "type": "Feature",
  "properties": {
    "gn:admin1_code":"25.0",
    "gn:admin2_code":"1515.0",
    "gn:asciiname":"Duba` ad Dakhil Ma'ilah",
    "gn:country_code":"YE",
    "gn:dem":1185,
    "gn:feature_class":"P",
    "gn:feature_code":"PPL",
    "gn:name":"Duba\u2018 ad D\u0101khil M\u0101\u2019ilah",
    "gn:population":0,
    "gn:timezone":"Asia/Aden",
    "iso:country":"YE",
    "name:und_x_variant":[
        "Duba\u2018 ad D\u0101khil M\u0101\u2019ilah",
        "Duba\u2018 ad D\u0101khil M\u0101\u2018ilah"
    ],
    "wof:name":"Duba` ad Dakhil Ma'ilah",
    "wof:placetype":"locality"
},
  "geometry": {"coordinates":[43.98215,13.21527],"type":"Point"}
}