{
  "type": "Feature",
  "properties": {
    "gn:admin1_code":"1.0",
    "gn:admin2_code":"1202.0",
    "gn:asciiname":"Al Qawz",
    "gn:country_code":"YE",
    "gn:dem":778,
    "gn:feature_class":"P",
    "gn:feature_code":"PPL",
    "gn:name":"Al Qawz",
    "gn:population":0,
    "gn:timezone":"Asia/Aden",
    "iso:country":"YE",
    "name:ara_x_preferred":[
        "\u0627\u0644\u0642\u0648\u0632"
    ],
    "name:und_x_variant":[
        "Am Qaws",
        "Al Qaws",
        "Am-Qaus",
        "Umm Qaws",
        "Al Qawz"
    ],
    "wof:name":"Al Qawz",
    "wof:placetype":"locality"
},
  "geometry": {"coordinates":[46.14929,13.88921],"type":"Point"}
}