{
  "type": "Feature",
  "properties": {
    "gn:admin1_code":"11.0",
    "gn:admin2_code":"2006.0",
    "gn:asciiname":"Makhlaf Ghaythan",
    "gn:country_code":"YE",
    "gn:dem":1247,
    "gn:feature_class":"P",
    "gn:feature_code":"PPL",
    "gn:name":"Makhlaf Ghayth\u0101n",
    "gn:population":0,
    "gn:timezone":"Asia/Aden",
    "iso:country":"YE",
    "name:und_x_variant":[
        "Makhlaf Ghayth\u0101n"
    ],
    "wof:name":"Makhlaf Ghaythan",
    "wof:placetype":"locality"
},
  "geometry": {"coordinates":[43.80744,14.30316],"type":"Point"}
}