{
  "type": "Feature",
  "properties": {
    "gn:admin1_code":"11.0",
    "gn:admin2_code":"2007.0",
    "gn:asciiname":"Bayt `Awn",
    "gn:country_code":"YE",
    "gn:dem":459,
    "gn:feature_class":"P",
    "gn:feature_code":"PPL",
    "gn:name":"Bayt \u2018Awn",
    "gn:population":0,
    "gn:timezone":"Asia/Aden",
    "iso:country":"YE",
    "name:und_x_variant":[
        "Bayt \u2018Awn"
    ],
    "wof:name":"Bayt `Awn",
    "wof:placetype":"locality"
},
  "geometry": {"coordinates":[43.54892,14.2991],"type":"Point"}
}