{
  "type": "Feature",
  "properties": {
    "gn:country":"YE",
    "gn:fcode":"PPL",
    "gn:pop":12,
    "iso:country":"YE",
    "name:ara_x_preferred":[
        "\u0648\u0627\u062f\u064a \u0627\u0644\u0639\u0628\u064a\u062f"
    ],
    "name:eng_x_preferred":[
        "Wadi Al 'Ubayd"
    ],
    "name:eng_x_variant":[
        "Al Maqradah"
    ],
    "qs:name":"W\u0101d\u012b al \u2018Ubayd",
    "qs:photos_9r":0,
    "qs:photos_sr":0,
    "qs:pop_sr":"1",
    "wof:name":"W\u0101d\u012b al \u2018Ubayd",
    "wof:placetype":"locality",
    "wof:population":12
},
  "geometry": {"coordinates":[43.45606,16.14612],"type":"Point"}
}