{
  "type": "Feature",
  "properties": {
    "gn:admin1_code":"16.0",
    "gn:admin2_code":"2312.0",
    "gn:asciiname":"Bani al Qadi",
    "gn:country_code":"YE",
    "gn:dem":2478,
    "gn:feature_class":"P",
    "gn:feature_code":"PPL",
    "gn:name":"Ban\u012b al Q\u0101\u1e11\u012b",
    "gn:population":0,
    "gn:timezone":"Asia/Aden",
    "iso:country":"YE",
    "name:ara_x_preferred":[
        "\u0628\u0646\u064a \u0627\u0644\u0642\u0627\u0636\u064a"
    ],
    "name:und_x_variant":[
        "Ban\u012b al Q\u0101\u1e11\u012b"
    ],
    "wof:name":"Bani al Qadi",
    "wof:placetype":"locality"
},
  "geometry": {"coordinates":[44.61666,15.34683],"type":"Point"}
}