{
  "type": "Feature",
  "properties": {
    "gn:country":"YE",
    "gn:fcode":"PPL",
    "gn:pop":12,
    "iso:country":"YE",
    "name:ara_x_preferred":[
        "Al Mu\u1e29\u0101nidh"
    ],
    "name:ara_x_variant":[
        "\u0627\u0644\u0645\u062d\u0627\u0646\u0630"
    ],
    "name:eng_x_preferred":[
        "Al Muhanidh"
    ],
    "name:eng_x_variant":[
        "A\u1e11 \u1e10ijrah"
    ],
    "qs:name":"Al Mu\u1e29\u0101nidh",
    "qs:photos_9r":0,
    "qs:photos_sr":0,
    "qs:pop_sr":"1",
    "wof:name":"Al Mu\u1e29\u0101nidh",
    "wof:placetype":"locality",
    "wof:population":12
},
  "geometry": {"coordinates":[43.61078,16.01372],"type":"Point"}
}