{
  "type": "Feature",
  "properties": {
    "gn:country":"YE",
    "gn:fcode":"PPL",
    "gn:population":4,
    "iso:country":"YE",
    "name:ara_x_preferred":[
        "Al Muj\u0101nib"
    ],
    "name:ara_x_variant":[
        "\u0627\u0644\u0645\u062c\u0627\u0646\u0628"
    ],
    "name:eng_x_preferred":[
        "Al Mujanib"
    ],
    "name:eng_x_variant":[
        "Al \u1e28ar\u0101\u2019iq"
    ],
    "qs:name":"Al Muj\u0101nib",
    "qs:photos_9r":0,
    "qs:photos_sr":0,
    "qs:pop_sr":"1",
    "wof:name":"Al Muj\u0101nib",
    "wof:placetype":"locality",
    "wof:population":4
},
  "geometry": {"coordinates":[43.24103,17.25927],"type":"Point"}
}