{
  "type": "Feature",
  "properties": {
    "gn:country":"YE",
    "gn:fcode":"PPL",
    "gn:population":19,
    "iso:country":"YE",
    "name:ara_x_preferred":[
        "Al Mishr\u0101q"
    ],
    "name:ara_x_variant":[
        "\u0627\u0644\u0645\u0634\u0631\u0627\u0642"
    ],
    "name:deu_x_preferred":[
        "Al-Mishraq"
    ],
    "name:eng_x_preferred":[
        "Al Qan\u0101birah"
    ],
    "name:eng_x_variant":[
        "Al-Mishraq"
    ],
    "name:fra_x_preferred":[
        "Al-Mishraq"
    ],
    "name:ita_x_preferred":[
        "Al-Mishraq"
    ],
    "name:jpn_x_preferred":[
        "\u30a2\u30eb\uff1d\u30df\u30b7\u30e5\u30e9\u30af"
    ],
    "name:nob_x_preferred":[
        "Al-Mishraq"
    ],
    "name:slv_x_preferred":[
        "Al-Mishraq"
    ],
    "qs:name":"Al Mishr\u0101q",
    "qs:photos_9r":0,
    "qs:photos_sr":0,
    "qs:pop_sr":"1",
    "wd:wordcount":123,
    "wof:name":"Al Mishr\u0101q",
    "wof:placetype":"locality",
    "wof:population":19
},
  "geometry": {"coordinates":[43.50277,16.96444],"type":"Point"}
}