{
  "type": "Feature",
  "properties": {
    "gn:country":"YE",
    "gn:fcode":"PPL",
    "gn:pop":19,
    "iso:country":"YE",
    "name:ara_x_preferred":[
        "Al Mishr\u0101q"
    ],
    "name:ara_x_variant":[
        "\u0627\u0644\u0645\u0634\u0631\u0627\u0642"
    ],
    "qs:name":"Al Mishr\u0101q",
    "qs:photos_9r":0,
    "qs:photos_sr":0,
    "qs:pop_sr":"1",
    "wd:wordcount":123,
    "wof:name":"Al Mishr\u0101q",
    "wof:placetype":"locality",
    "wof:population":19
},
  "geometry": {"coordinates":[43.50277,16.96444],"type":"Point"}
}