{
  "type": "Feature",
  "properties": {
    "gn:admin1_code":"15.0",
    "gn:admin2_code":"2211.0",
    "gn:asciiname":"Al Shafi`ah",
    "gn:country_code":"YE",
    "gn:dem":1959,
    "gn:feature_class":"P",
    "gn:feature_code":"PPL",
    "gn:name":"\u0100l Sh\u0101fi\u2018ah",
    "gn:population":0,
    "gn:timezone":"Asia/Aden",
    "iso:country":"YE",
    "name:und_x_variant":[
        "\u0100l Sh\u0101fi\u2018ah"
    ],
    "wof:name":"Al Shafi`ah",
    "wof:placetype":"locality"
},
  "geometry": {"coordinates":[43.75,17.03333],"type":"Point"}
}