{
  "type": "Feature",
  "properties": {
    "gn:admin1_code":"28.0",
    "gn:admin2_code":"1926.0",
    "gn:asciiname":"Bayt Hajfinuh",
    "gn:country_code":"YE",
    "gn:dem":533,
    "gn:feature_class":"P",
    "gn:feature_code":"PPL",
    "gn:name":"Bayt \u1e28ajf\u012bn\u016bh",
    "gn:population":0,
    "gn:timezone":"Asia/Aden",
    "iso:country":"YE",
    "wof:name":"Bayt Hajfinuh",
    "wof:placetype":"locality"
},
  "geometry": {"coordinates":[54.37457,12.55807],"type":"Point"}
}