{
  "type": "Feature",
  "properties": {
    "gn:admin1_code":"25.0",
    "gn:admin2_code":"1505.0",
    "gn:asciiname":"Mulhim",
    "gn:country_code":"YE",
    "gn:dem":721,
    "gn:feature_class":"P",
    "gn:feature_code":"PPL",
    "gn:name":"Mul\u1e29im",
    "gn:population":0,
    "gn:timezone":"Asia/Aden",
    "iso:country":"YE",
    "name:ara_x_preferred":[
        "Mul\u1e29im"
    ],
    "name:ara_x_variant":[
        "\u0645\u0644\u062d\u0645"
    ],
    "wof:name":"Mulhim",
    "wof:placetype":"locality"
},
  "geometry": {"coordinates":[43.75461,13.55663],"type":"Point"}
}