{
  "type": "Feature",
  "properties": {
    "gn:country":"YE",
    "gn:fcode":"PPL",
    "gn:pop":12,
    "iso:country":"YE",
    "name:ara_x_preferred":[
        "\u0627\u0644\u0645\u0635\u0628\u062d"
    ],
    "qs:name":"Al Ma\u015fna\u2018",
    "qs:photos_9r":0,
    "qs:photos_sr":0,
    "qs:pop_sr":"1",
    "wof:name":"Al Ma\u015fna\u2018",
    "wof:placetype":"locality",
    "wof:population":12
},
  "geometry": {"coordinates":[43.291,16.87019],"type":"Point"}
}