{
  "type": "Feature",
  "properties": {
    "gn:admin1_code":"8.0",
    "gn:admin2_code":"1814.0",
    "gn:asciiname":"At Ta'if",
    "gn:country_code":"YE",
    "gn:dem":13,
    "gn:feature_class":"P",
    "gn:feature_code":"PPL",
    "gn:name":"A\u0163 \u0162\u0101\u2019if",
    "gn:population":0,
    "gn:timezone":"Asia/Aden",
    "iso:country":"YE",
    "name:ara_x_preferred":[
        "A\u0163 \u0162\u0101\u2019if"
    ],
    "wof:name":"At Ta'if",
    "wof:placetype":"locality"
},
  "geometry": {"coordinates":[43.01051,14.56589],"type":"Point"}
}