{
  "type": "Feature",
  "properties": {
    "gn:admin1_code":"4.0",
    "gn:admin2_code":"1921.0",
    "gn:asciiname":"Turumil",
    "gn:country_code":"YE",
    "gn:dem":1144,
    "gn:feature_class":"P",
    "gn:feature_code":"PPL",
    "gn:name":"Turumil",
    "gn:population":0,
    "gn:timezone":"Asia/Aden",
    "iso:country":"YE",
    "wof:name":"Turumil",
    "wof:placetype":"locality"
},
  "geometry": {"coordinates":[47.86667,15.21667],"type":"Point"}
}