{
  "type": "Feature",
  "properties": {
    "gn:country":"YE",
    "gn:fcode":"PPLL",
    "gn:population":25,
    "iso:country":"YE",
    "name:ara_x_preferred":[
        "\u0627\u0644\u062a\u0648\u064a\u0644\u0642\u0629"
    ],
    "name:eng_x_preferred":[
        "At Tuwayliqah"
    ],
    "name:eng_x_variant":[
        "Al \u2018Abil"
    ],
    "qs:name":"At Tuwayliqah",
    "qs:photos_9r":0,
    "qs:photos_sr":0,
    "qs:pop_sr":"1",
    "wof:name":"At Tuwayliqah",
    "wof:placetype":"locality",
    "wof:population":25
},
  "geometry": {"coordinates":[44.39403,16.60482],"type":"Point"}
}