{
  "type": "Feature",
  "properties": {
    "gn:country":"YE",
    "gn:fcode":"PPL",
    "gn:pop":18,
    "iso:country":"YE",
    "name:ara_x_preferred":[
        "\u0627\u0644\u062d\u0631\u0627\u062a"
    ],
    "name:eng_x_preferred":[
        "Al Harat"
    ],
    "qs:name":"Al \u1e28ar\u0101t",
    "qs:photos_9r":0,
    "qs:photos_sr":0,
    "qs:pop_sr":"1",
    "wof:name":"Al \u1e28ar\u0101t",
    "wof:placetype":"locality",
    "wof:population":18
},
  "geometry": {"coordinates":[45.28803,14.33949],"type":"Point"}
}