{
  "type": "Feature",
  "properties": {
    "gn:admin1_code":"8.0",
    "gn:admin2_code":"1819.0",
    "gn:asciiname":"Qaryat at Tulayli",
    "gn:country_code":"YE",
    "gn:dem":250,
    "gn:feature_class":"P",
    "gn:feature_code":"PPL",
    "gn:name":"Qaryat a\u0163 \u0162ulayl\u012b",
    "gn:population":0,
    "gn:timezone":"Asia/Aden",
    "iso:country":"YE",
    "name:und_x_variant":[
        "Qaryat a\u0163 \u0162ulayl\u012b"
    ],
    "wof:name":"Qaryat at Tulayli",
    "wof:placetype":"locality"
},
  "geometry": {"coordinates":[43.53854000000001,13.95951],"type":"Point"}
}