{
  "type": "Feature",
  "properties": {
    "gn:admin1_code":"11.0",
    "gn:admin2_code":"2007.0",
    "gn:asciiname":"Al Qillah",
    "gn:country_code":"YE",
    "gn:dem":1260,
    "gn:feature_class":"P",
    "gn:feature_code":"PPL",
    "gn:name":"Al Qillah",
    "gn:population":0,
    "gn:timezone":"Asia/Aden",
    "iso:country":"YE",
    "wof:name":"Al Qillah",
    "wof:placetype":"locality"
},
  "geometry": {"coordinates":[43.68073,14.3014],"type":"Point"}
}