{
  "type": "Feature",
  "properties": {
    "gn:admin1_code":"14.0",
    "gn:admin2_code":"2609.0",
    "gn:asciiname":"Al Mahfuz",
    "gn:country_code":"YE",
    "gn:dem":1199,
    "gn:feature_class":"P",
    "gn:feature_code":"PPL",
    "gn:name":"\u0100l Ma\u1e29f\u016bz\u0327",
    "gn:population":3,
    "gn:timezone":"Asia/Aden",
    "iso:country":"YE",
    "name:ara_x_preferred":[
        "\u0627\u0644 \u0645\u062d\u0641\u0648\u0638"
    ],
    "name:und_x_variant":[
        "\u0100l Ma\u1e29f\u016bz\u0327"
    ],
    "wof:name":"Al Mahfuz",
    "wof:placetype":"locality",
    "wof:population":3
},
  "geometry": {"coordinates":[45.451,14.9247],"type":"Point"}
}