{
  "type": "Feature",
  "properties": {
    "gn:admin1_code":"8.0",
    "gn:admin2_code":"1802.0",
    "gn:asciiname":"Bani Qadri",
    "gn:country_code":"YE",
    "gn:dem":65,
    "gn:feature_class":"P",
    "gn:feature_code":"PPL",
    "gn:name":"Ban\u012b Qadr\u012b",
    "gn:population":0,
    "gn:timezone":"Asia/Aden",
    "iso:country":"YE",
    "name:ara_x_preferred":[
        "\u0628\u0646\u064a \u0642\u062f\u0631\u064a"
    ],
    "name:und_x_variant":[
        "Ban\u012b Qadr\u012b"
    ],
    "wof:name":"Bani Qadri",
    "wof:placetype":"locality"
},
  "geometry": {"coordinates":[42.94772,15.68662],"type":"Point"}
}