{
  "type": "Feature",
  "properties": {
    "gn:admin1_code":"25.0",
    "gn:admin2_code":"1511.0",
    "gn:asciiname":"Qaryat ar Rukn",
    "gn:country_code":"YE",
    "gn:dem":1214,
    "gn:feature_class":"P",
    "gn:feature_code":"PPL",
    "gn:name":"Qaryat ar Rukn",
    "gn:population":0,
    "gn:timezone":"Asia/Aden",
    "iso:country":"YE",
    "name:ara_x_preferred":[
        "\u0627\u0644\u0631\u0643\u0646"
    ],
    "name:und_x_variant":[
        "Ar Rukn"
    ],
    "wof:name":"Qaryat ar Rukn",
    "wof:placetype":"locality"
},
  "geometry": {"coordinates":[43.95331,13.53935],"type":"Point"}
}