{
  "type": "Feature",
  "properties": {
    "gn:country":"YE",
    "gn:fcode":"PPL",
    "gn:population":11,
    "iso:country":"YE",
    "name:ara_x_preferred":[
        "\u0646\u0642\u064a\u0644 \u0639\u0645\u0631"
    ],
    "name:eng_x_preferred":[
        "Naqil 'Umar"
    ],
    "name:eng_x_variant":[
        "\u1e28awd al Qaw\u0101\u2018id"
    ],
    "qs:name":"Naq\u012bl \u2018Umar",
    "qs:photos_9r":0,
    "qs:photos_sr":0,
    "qs:pop_sr":"1",
    "wof:name":"Naq\u012bl \u2018Umar",
    "wof:placetype":"locality",
    "wof:population":11
},
  "geometry": {"coordinates":[43.45634,16.247],"type":"Point"}
}