{
  "type": "Feature",
  "properties": {
    "gn:admin1_code":"19.0",
    "gn:admin2_code":"2903.0",
    "gn:asciiname":"Al Washah",
    "gn:country_code":"YE",
    "gn:dem":1212,
    "gn:feature_class":"P",
    "gn:feature_code":"PPL",
    "gn:name":"Al Wash\u0101\u1e29",
    "gn:population":0,
    "gn:timezone":"Asia/Aden",
    "iso:country":"YE",
    "name:ara_x_preferred":[
        "\u0627\u0644\u0648\u0634\u0627\u062d"
    ],
    "name:und_x_variant":[
        "Al Wash\u0101\u1e29"
    ],
    "wof:name":"Al Washah",
    "wof:placetype":"locality"
},
  "geometry": {"coordinates":[43.86106,16.2616],"type":"Point"}
}