{
  "type": "Feature",
  "properties": {
    "gn:admin1_code":"1.0",
    "gn:admin2_code":"1203.0",
    "gn:asciiname":"Jayshan",
    "gn:country_code":"YE",
    "gn:dem":1562,
    "gn:feature_class":"P",
    "gn:feature_code":"PPLA2",
    "gn:name":"Jaysh\u0101n",
    "gn:population":0,
    "gn:timezone":"Asia/Aden",
    "iso:country":"YE",
    "name:ara_x_preferred":[
        "\u062c\u064a\u0634\u0627\u0646"
    ],
    "name:und_x_variant":[
        "Jaysh\u0101n"
    ],
    "wof:name":"Jayshan",
    "wof:placetype":"locality"
},
  "geometry": {"coordinates":[46.17905,14.25204],"type":"Point"}
}