{
  "type": "Feature",
  "properties": {
    "gn:admin1_code":"19.0",
    "gn:admin2_code":"2905.0",
    "gn:asciiname":"Bayt al `Awsh",
    "gn:country_code":"YE",
    "gn:dem":1300,
    "gn:feature_class":"P",
    "gn:feature_code":"PPL",
    "gn:name":"Bayt al \u2018Awsh",
    "gn:population":0,
    "gn:timezone":"Asia/Aden",
    "iso:country":"YE",
    "name:ara_x_preferred":[
        "\u0628\u064a\u062a \u0627\u0644\u0639\u0648\u0634"
    ],
    "name:und_x_variant":[
        "Bayt al \u2018Awsh"
    ],
    "wof:name":"Bayt al `Awsh",
    "wof:placetype":"locality"
},
  "geometry": {"coordinates":[43.72654,16.1636],"type":"Point"}
}