{
  "type": "Feature",
  "properties": {
    "gn:admin1_code":"24.0",
    "gn:admin2_code":"2510.0",
    "gn:asciiname":"Shanin",
    "gn:country_code":"YE",
    "gn:dem":1041,
    "gn:feature_class":"P",
    "gn:feature_code":"PPL",
    "gn:name":"Shan\u012bn",
    "gn:population":0,
    "gn:timezone":"Asia/Aden",
    "iso:country":"YE",
    "name:und_x_variant":[
        "Shani",
        "Shan\u012bn"
    ],
    "wof:name":"Shanin",
    "wof:placetype":"locality"
},
  "geometry": {"coordinates":[44.44537,13.29573],"type":"Point"}
}