{
  "type": "Feature",
  "properties": {
    "gn:admin1_code":"16.0",
    "gn:admin2_code":"2312.0",
    "gn:asciiname":"An Naharah",
    "gn:country_code":"YE",
    "gn:dem":1592,
    "gn:feature_class":"P",
    "gn:feature_code":"PPL",
    "gn:name":"An Na\u1e29\u0101rah",
    "gn:population":0,
    "gn:timezone":"Asia/Aden",
    "iso:country":"YE",
    "name:ara_x_preferred":[
        "\u0627\u0644\u0646\u062d\u0627\u0631\u0629"
    ],
    "name:und_x_variant":[
        "An Na\u1e29\u0101rah"
    ],
    "wof:name":"An Naharah",
    "wof:placetype":"locality"
},
  "geometry": {"coordinates":[44.84193,15.40188],"type":"Point"}
}