{
  "type": "Feature",
  "properties": {
    "gn:country":"YE",
    "gn:fcode":"PPL",
    "gn:population":10,
    "iso:country":"YE",
    "name:ara_x_preferred":[
        "\u0627\u0644\u063a\u0648\u0644"
    ],
    "name:eng_x_preferred":[
        "Al Ghawl"
    ],
    "name:nno_x_preferred":[
        "Ash Shamiyah"
    ],
    "qs:name":"Al Ghawl",
    "qs:photos_9r":0,
    "qs:photos_sr":0,
    "qs:pop_sr":"1",
    "wof:name":"Al Ghawl",
    "wof:placetype":"locality",
    "wof:population":10
},
  "geometry": {"coordinates":[45.50493,14.02972],"type":"Point"}
}