{
  "type": "Feature",
  "properties": {
    "gn:country":"YE",
    "gn:fcode":"PPL",
    "gn:population":2,
    "iso:country":"YE",
    "name:ara_x_preferred":[
        "\u0627\u0644\u062d\u062b\u064a\u0631\u0629"
    ],
    "name:eng_x_preferred":[
        "Al Hathirah"
    ],
    "name:eng_x_variant":[
        "\u1e28\u0101zat al Ghurfah"
    ],
    "qs:name":"Al \u1e28ath\u012brah",
    "qs:photos_9r":0,
    "qs:photos_sr":0,
    "qs:pop_sr":"1",
    "wof:name":"Al \u1e28ath\u012brah",
    "wof:placetype":"locality",
    "wof:population":2
},
  "geometry": {"coordinates":[43.32378,17.46699],"type":"Point"}
}