{
  "type": "Feature",
  "properties": {
    "gn:country":"YE",
    "gn:fcode":"PPL",
    "gn:population":5,
    "iso:country":"YE",
    "name:ara_x_preferred":[
        "\u0648\u0627\u062f\u064a \u0627\u0644\u062d\u062f\u0627\u062f"
    ],
    "name:eng_x_preferred":[
        "Wadi Al Hidad"
    ],
    "name:eng_x_variant":[
        "\u2018Almarqibah"
    ],
    "qs:name":"W\u0101d\u012b al \u1e28id\u0101d",
    "qs:photos_9r":0,
    "qs:photos_sr":0,
    "qs:pop_sr":"1",
    "wof:name":"W\u0101d\u012b al \u1e28id\u0101d",
    "wof:placetype":"locality",
    "wof:population":5
},
  "geometry": {"coordinates":[43.41347,16.06509],"type":"Point"}
}