{
  "type": "Feature",
  "properties": {
    "gn:admin1_code":"25.0",
    "gn:admin2_code":"1515.0",
    "gn:asciiname":"As Sadad",
    "gn:country_code":"YE",
    "gn:dem":2153,
    "gn:feature_class":"P",
    "gn:feature_code":"PPL",
    "gn:name":"As Sad\u0101d",
    "gn:population":0,
    "gn:timezone":"Asia/Aden",
    "iso:country":"YE",
    "name:ara_x_preferred":[
        "\u0627\u0644\u0633\u062f\u0627\u062f"
    ],
    "name:und_x_variant":[
        "As Sad\u0101d"
    ],
    "wof:name":"As Sadad",
    "wof:placetype":"locality"
},
  "geometry": {"coordinates":[44.17043,13.23371],"type":"Point"}
}