{
  "type": "Feature",
  "properties": {
    "gn:admin1_code":"24.0",
    "gn:admin2_code":"2515.0",
    "gn:asciiname":"Ash Shuzayf",
    "gn:country_code":"YE",
    "gn:dem":132,
    "gn:feature_class":"P",
    "gn:feature_code":"PPL",
    "gn:name":"Ash Shuz\u0327ayf",
    "gn:population":0,
    "gn:timezone":"Asia/Aden",
    "iso:country":"YE",
    "name:und_x_variant":[
        "Ash Shuz\u0327ayf"
    ],
    "wof:name":"Ash Shuzayf",
    "wof:placetype":"locality"
},
  "geometry": {"coordinates":[44.85861,13.05056],"type":"Point"}
}