{
  "type": "Feature",
  "properties": {
    "gn:country":"YE",
    "gn:fcode":"PPL",
    "gn:pop":21,
    "iso:country":"YE",
    "name:ara_x_preferred":[
        "\u0623\u0628\u0631\u0642 \u0627\u0644\u0645\u062c\u0632\u0639"
    ],
    "name:eng_x_preferred":[
        "Abraq Al Majza'"
    ],
    "name:eng_x_variant":[
        "Al Khadimah"
    ],
    "qs:name":"Abraq al Majza\u2018",
    "qs:photos_9r":0,
    "qs:photos_sr":0,
    "qs:pop_sr":"1",
    "wof:name":"Abraq al Majza\u2018",
    "wof:placetype":"locality",
    "wof:population":21
},
  "geometry": {"coordinates":[44.56242,17.20175],"type":"Point"}
}