{
  "type": "Feature",
  "properties": {
    "gn:admin1_code":"16.0",
    "gn:admin2_code":"2309.0",
    "gn:asciiname":"An Najd",
    "gn:country_code":"YE",
    "gn:dem":1563,
    "gn:feature_class":"P",
    "gn:feature_code":"PPL",
    "gn:name":"An Najd",
    "gn:population":0,
    "gn:timezone":"Asia/Aden",
    "iso:country":"YE",
    "name:fas_x_preferred":[
        "\u0627\u0646 \u0646\u062c\u062f"
    ],
    "name:nno_x_preferred":[
        "An Najd"
    ],
    "wof:name":"An Najd",
    "wof:placetype":"locality"
},
  "geometry": {"coordinates":[43.83133,15.03087],"type":"Point"}
}