{
  "type": "Feature",
  "properties": {
    "gn:country":"YE",
    "gn:fcode":"PPLX",
    "gn:pop":2,
    "iso:country":"YE",
    "name:ara_x_preferred":[
        "\u0627\u0644\u0645\u0646\u0635\u0648\u0631\u0629 \u0627\u0644\u0633\u0641\u0644\u0649"
    ],
    "qs:name":"Al Man\u015f\u016brah as Sufl\u00e1",
    "qs:photos_9r":0,
    "qs:photos_sr":0,
    "qs:pop_sr":"1",
    "wof:name":"Al Man\u015f\u016brah as Sufl\u00e1",
    "wof:placetype":"neighbourhood",
    "wof:population":2
},
  "geometry": {"coordinates":[43.30648,16.66461],"type":"Point"}
}