{
  "type": "Feature",
  "properties": {
    "gn:admin1_code":"24.0",
    "gn:admin2_code":"2515.0",
    "gn:asciiname":"Al Qurayshi",
    "gn:country_code":"YE",
    "gn:dem":162,
    "gn:feature_class":"P",
    "gn:feature_code":"PPL",
    "gn:name":"Al Quraysh\u012b",
    "gn:population":0,
    "gn:timezone":"Asia/Aden",
    "iso:country":"YE",
    "name:und_x_variant":[
        "Al Kureshi",
        "Al Quraysh\u012b"
    ],
    "wof:name":"Al Qurayshi",
    "wof:placetype":"locality"
},
  "geometry": {"coordinates":[44.87167,13.08083],"type":"Point"}
}