{
  "type": "Feature",
  "properties": {
    "gn:admin1_code":"24.0",
    "gn:admin2_code":"2512.0",
    "gn:asciiname":"Ad Dawn",
    "gn:country_code":"YE",
    "gn:dem":879,
    "gn:feature_class":"P",
    "gn:feature_code":"PPL",
    "gn:name":"A\u1e11 \u1e10awn",
    "gn:population":0,
    "gn:timezone":"Asia/Aden",
    "iso:country":"YE",
    "name:ara_x_preferred":[
        "\u0627\u0644\u0636\u0648\u0646"
    ],
    "name:und_x_variant":[
        "A\u1e11 \u1e10awn"
    ],
    "wof:name":"Ad Dawn",
    "wof:placetype":"locality"
},
  "geometry": {"coordinates":[44.20006,13.13763],"type":"Point"}
}