{
  "type": "Feature",
  "properties": {
    "gn:admin1_code":"25.0",
    "gn:admin2_code":"1521.0",
    "gn:asciiname":"Al A`rud",
    "gn:country_code":"YE",
    "gn:dem":985,
    "gn:feature_class":"P",
    "gn:feature_code":"PPL",
    "gn:name":"Al A\u2018r\u016bd",
    "gn:population":0,
    "gn:timezone":"Asia/Aden",
    "iso:country":"YE",
    "name:ara_x_preferred":[
        "Al A\u2018r\u016bd"
    ],
    "wof:name":"Al A`rud",
    "wof:placetype":"locality"
},
  "geometry": {"coordinates":[43.92603,13.39213],"type":"Point"}
}