{
  "type": "Feature",
  "properties": {
    "gn:country":"YE",
    "gn:fcode":"PPLF",
    "gn:pop":14,
    "iso:country":"YE",
    "name:ara_x_preferred":[
        "Dh\u016b Dhiy\u0101b"
    ],
    "name:ara_x_variant":[
        "\u0630\u0648 \u0630\u064a\u0627\u0628"
    ],
    "name:eng_x_preferred":[
        "DhU Dhiyab"
    ],
    "name:eng_x_variant":[
        "Gh\u0101rib Si\u2018\u0101r\u012b"
    ],
    "qs:name":"Dh\u016b Dhiy\u0101b",
    "qs:photos_9r":0,
    "qs:photos_sr":0,
    "qs:pop_sr":"1",
    "wof:name":"Dh\u016b Dhiy\u0101b",
    "wof:placetype":"locality",
    "wof:population":14
},
  "geometry": {"coordinates":[44.0292,16.89995],"type":"Point"}
}