{
  "type": "Feature",
  "properties": {
    "gn:admin1_code":"23.0",
    "gn:admin2_code":"1101.0",
    "gn:asciiname":"Hajr Mashrafah",
    "gn:country_code":"YE",
    "gn:dem":2100,
    "gn:feature_class":"P",
    "gn:feature_code":"PPL",
    "gn:name":"\u1e28ajr Mashrafah",
    "gn:population":0,
    "gn:timezone":"Asia/Aden",
    "iso:country":"YE",
    "name:ara_x_preferred":[
        "\u062d\u062c\u0631 \u0645\u0634\u0631\u0641\u0629"
    ],
    "name:und_x_variant":[
        "\u1e28ajar Mashrafah",
        "\u1e28ajr Mashrafah"
    ],
    "wof:name":"Hajr Mashrafah",
    "wof:placetype":"locality"
},
  "geometry": {"coordinates":[44.23724,14.26081],"type":"Point"}
}