{
  "type": "Feature",
  "properties": {
    "gn:admin1_code":"19.0",
    "gn:admin2_code":"2918.0",
    "gn:asciiname":"Ad Diqrari",
    "gn:country_code":"YE",
    "gn:dem":2471,
    "gn:feature_class":"P",
    "gn:feature_code":"PPL",
    "gn:name":"Ad Diqr\u0101r\u012b",
    "gn:population":0,
    "gn:timezone":"Asia/Aden",
    "iso:country":"YE",
    "name:ara_x_preferred":[
        "Ad Diqr\u0101r\u012b"
    ],
    "wof:name":"Ad Diqrari",
    "wof:placetype":"locality"
},
  "geometry": {"coordinates":[43.99505,15.61088],"type":"Point"}
}