{
  "type": "Feature",
  "properties": {
    "gn:admin1_code":"23.0",
    "gn:admin2_code":"1101.0",
    "gn:asciiname":"Al 'Asaqah",
    "gn:country_code":"YE",
    "gn:dem":1153,
    "gn:feature_class":"P",
    "gn:feature_code":"PPL",
    "gn:name":"Al \u2018Asaqah",
    "gn:population":0,
    "gn:timezone":"Asia/Aden",
    "iso:country":"YE",
    "name:ara_x_preferred":[
        "\u0627\u0644\u0639\u0633\u0642\u0629"
    ],
    "name:und_x_variant":[
        "Al \u2018Asaqah"
    ],
    "wof:name":"Al 'Asaqah",
    "wof:placetype":"locality"
},
  "geometry": {"coordinates":[44.04015,14.3198],"type":"Point"}
}