{
  "type": "Feature",
  "properties": {
    "gn:country":"YE",
    "gn:fcode":"PPL",
    "gn:population":33,
    "iso:country":"YE",
    "name:ara_x_preferred":[
        "Al \u1e28im\u0101\u2019"
    ],
    "name:ara_x_variant":[
        "\u0627\u0644\u062d\u0645\u0627\u0621"
    ],
    "name:eng_x_preferred":[
        "Al Hima"
    ],
    "name:eng_x_variant":[
        "Ar Raffah"
    ],
    "qs_pg:aaroncc":"YE",
    "qs_pg:gn_country":"YE",
    "qs_pg:gn_fcode":"PPL",
    "qs_pg:gn_pop":33,
    "qs_pg:name":"Al \u1e28im\u0101\u2019",
    "qs_pg:photos_9r":0,
    "qs_pg:photos_sr":0,
    "qs_pg:pop_sr":1,
    "qs_pg:qs_pg_placetype":"locality",
    "wof:name":"Al \u1e28im\u0101\u2019",
    "wof:placetype":"locality",
    "wof:population":33
},
  "geometry": {"coordinates":[43.32835,17.19135],"type":"Point"}
}