{
  "type": "Feature",
  "properties": {
    "gn:country":"YE",
    "gn:fcode":"PPLX",
    "gn:pop":30,
    "iso:country":"YE",
    "name:ara_x_preferred":[
        "\u0627\u0644\u0643\u0648\u0644\u0629 \u0627\u0644\u0639\u0644\u064a\u0627"
    ],
    "qs:name":"Al Kawlah al \u2018Uly\u0101",
    "qs:photos_9r":0,
    "qs:photos_sr":0,
    "qs:pop_sr":"1",
    "wof:name":"Al Kawlah al \u2018Uly\u0101",
    "wof:placetype":"neighbourhood",
    "wof:population":30
},
  "geometry": {"coordinates":[43.47395,16.34566],"type":"Point"}
}