{
  "type": "Feature",
  "properties": {
    "gn:admin1_code":"25.0",
    "gn:admin2_code":"1522.0",
    "gn:asciiname":"Al Jahili",
    "gn:country_code":"YE",
    "gn:dem":1343,
    "gn:feature_class":"P",
    "gn:feature_code":"PPL",
    "gn:name":"Al J\u0101hil\u012b",
    "gn:population":0,
    "gn:timezone":"Asia/Aden",
    "iso:country":"YE",
    "name:ara_x_preferred":[
        "Al J\u0101hil\u012b"
    ],
    "wof:name":"Al Jahili",
    "wof:placetype":"locality"
},
  "geometry": {"coordinates":[44.10302,13.25191],"type":"Point"}
}