{
  "type": "Feature",
  "properties": {
    "gn:admin1_code":"24.0",
    "gn:admin2_code":"2511.0",
    "gn:asciiname":"Tafih",
    "gn:country_code":"YE",
    "gn:dem":615,
    "gn:feature_class":"P",
    "gn:feature_code":"PPL",
    "gn:name":"Taf\u012b\u1e29",
    "gn:population":0,
    "gn:timezone":"Asia/Aden",
    "iso:country":"YE",
    "name:und_x_variant":[
        "Taf\u012b\u1e29",
        "Tafih"
    ],
    "wof:name":"Tafih",
    "wof:placetype":"locality"
},
  "geometry": {"coordinates":[44.32278,13.17079],"type":"Point"}
}