{
  "type": "Feature",
  "properties": {
    "gn:admin1_code":"8.0",
    "gn:admin2_code":"1802.0",
    "gn:asciiname":"Al Humasiyah",
    "gn:country_code":"YE",
    "gn:dem":38,
    "gn:feature_class":"P",
    "gn:feature_code":"PPL",
    "gn:name":"Al \u1e28um\u0101s\u012byah",
    "gn:population":0,
    "gn:timezone":"Asia/Aden",
    "iso:country":"YE",
    "wof:name":"Al Humasiyah",
    "wof:placetype":"locality"
},
  "geometry": {"coordinates":[42.89682,15.75076],"type":"Point"}
}