{
  "type": "Feature",
  "properties": {
    "gn:admin1_code":"25.0",
    "gn:admin2_code":"1513.0",
    "gn:asciiname":"Ash Shuqaq",
    "gn:country_code":"YE",
    "gn:dem":1049,
    "gn:feature_class":"P",
    "gn:feature_code":"PPL",
    "gn:name":"Ash Shuq\u0101q",
    "gn:population":0,
    "gn:timezone":"Asia/Aden",
    "iso:country":"YE",
    "name:ara_x_preferred":[
        "Ash Shuq\u0101q"
    ],
    "wof:name":"Ash Shuqaq",
    "wof:placetype":"locality"
},
  "geometry": {"coordinates":[44.2638,13.44708],"type":"Point"}
}