{
  "type": "Feature",
  "properties": {
    "gn:admin1_code":"8.0",
    "gn:admin2_code":"1815.0",
    "gn:asciiname":"Buyut al Manamah",
    "gn:country_code":"YE",
    "gn:dem":189,
    "gn:feature_class":"P",
    "gn:feature_code":"PPL",
    "gn:name":"Buy\u016bt al Man\u0101mah",
    "gn:population":0,
    "gn:timezone":"Asia/Aden",
    "iso:country":"YE",
    "name:ara_x_preferred":[
        "\u0628\u064a\u0648\u062a \u0627\u0644\u0645\u0646\u0627\u0645\u0629"
    ],
    "name:und_x_variant":[
        "Bayt al Man\u0101mah",
        "Buy\u016bt al Man\u0101mah"
    ],
    "wof:name":"Buyut al Manamah",
    "wof:placetype":"locality"
},
  "geometry": {"coordinates":[43.40595,14.73861],"type":"Point"}
}