{
  "type": "Feature",
  "properties": {
    "gn:country":"YE",
    "gn:fcode":"PPL",
    "gn:pop":57,
    "iso:country":"YE",
    "name:ara_x_preferred":[
        "\u0100l \u2018Al\u012b"
    ],
    "name:ara_x_variant":[
        "\u0627\u0644 \u0639\u0644\u064a"
    ],
    "name:eng_x_preferred":[
        "Al 'Ali"
    ],
    "qs:name":"\u0100l \u2018Al\u012b",
    "qs:photos_9r":0,
    "qs:photos_sr":0,
    "qs:pop_sr":"1",
    "wof:name":"\u0100l \u2018Al\u012b",
    "wof:placetype":"locality",
    "wof:population":57
},
  "geometry": {"coordinates":[43.45326,17.21821],"type":"Point"}
}