{
  "type": "Feature",
  "properties": {
    "gn:country":"YE",
    "gn:fcode":"PPL",
    "gn:population":3,
    "iso:country":"YE",
    "name:ara_x_preferred":[
        "\u062f\u0628\u0639\u0627\u0646"
    ],
    "name:eng_x_preferred":[
        "Dab'an"
    ],
    "qs:name":"Dab\u2018\u0101n",
    "qs:photos_9r":0,
    "qs:photos_sr":0,
    "qs:pop_sr":"1",
    "wof:name":"Dab\u2018\u0101n",
    "wof:placetype":"locality",
    "wof:population":3
},
  "geometry": {"coordinates":[43.34752,16.68024],"type":"Point"}
}