{
  "type": "Feature",
  "properties": {
    "gn:country":"YE",
    "gn:fcode":"PPL",
    "gn:population":4,
    "iso:country":"YE",
    "name:ara_x_preferred":[
        "\u0636\u0627\u0631\u0628\u0629 \u0627\u0644\u062d\u0635\u0628"
    ],
    "name:eng_x_preferred":[
        "Daribat Al Hasib"
    ],
    "name:eng_x_variant":[
        "Al Ha\u1e11bah"
    ],
    "qs:name":"\u1e10\u0101ribat al \u1e28a\u015fib",
    "qs:photos_9r":0,
    "qs:photos_sr":0,
    "qs:pop_sr":"1",
    "wof:name":"\u1e10\u0101ribat al \u1e28a\u015fib",
    "wof:placetype":"locality",
    "wof:population":4
},
  "geometry": {"coordinates":[43.80689,13.47961],"type":"Point"}
}