{
  "type": "Feature",
  "properties": {
    "gn:country":"YE",
    "gn:fcode":"PPL",
    "gn:pop":6,
    "iso:country":"YE",
    "name:ara_x_preferred":[
        "Ar Ri\u1e11\u016bm"
    ],
    "name:ara_x_variant":[
        "\u0627\u0644\u0631\u0636\u0648\u0645"
    ],
    "name:eng_x_preferred":[
        "Ar RiuUm"
    ],
    "qs:name":"Ar Ri\u1e11\u016bm",
    "qs:photos_9r":0,
    "qs:photos_sr":0,
    "qs:pop_sr":"1",
    "wof:name":"Ar Ri\u1e11\u016bm",
    "wof:placetype":"locality",
    "wof:population":6
},
  "geometry": {"coordinates":[44.2333,17.07331],"type":"Point"}
}