{
  "type": "Feature",
  "properties": {
    "gn:admin1_code":"11.0",
    "gn:admin2_code":"2007.0",
    "gn:asciiname":"Al Hawf",
    "gn:country_code":"YE",
    "gn:dem":422,
    "gn:feature_class":"P",
    "gn:feature_code":"PPL",
    "gn:name":"Al \u1e28awf",
    "gn:population":0,
    "gn:timezone":"Asia/Aden",
    "iso:country":"YE",
    "name:und_x_variant":[
        "Al \u1e28awf"
    ],
    "wof:name":"Al Hawf",
    "wof:placetype":"locality"
},
  "geometry": {"coordinates":[43.53256,14.34387],"type":"Point"}
}