{
  "type": "Feature",
  "properties": {
    "gn:admin1_code":"8.0",
    "gn:admin2_code":"1809.0",
    "gn:asciiname":"Al Majawinah",
    "gn:country_code":"YE",
    "gn:dem":62,
    "gn:feature_class":"P",
    "gn:feature_code":"PPL",
    "gn:name":"Al Maj\u0101winah",
    "gn:population":0,
    "gn:timezone":"Asia/Aden",
    "iso:country":"YE",
    "name:ara_x_preferred":[
        "\u0627\u0644\u0645\u062c\u0627\u0648\u0646\u0629"
    ],
    "name:und_x_variant":[
        "Ma\u1e29all al Maj\u0101winah",
        "Al Maj\u0101winah"
    ],
    "wof:name":"Al Majawinah",
    "wof:placetype":"locality"
},
  "geometry": {"coordinates":[43.02983,15.18552],"type":"Point"}
}