{
  "type": "Feature",
  "properties": {
    "gn:admin1_code":"25.0",
    "gn:admin2_code":"1509.0",
    "gn:asciiname":"Qaryat Wahir",
    "gn:country_code":"YE",
    "gn:dem":1277,
    "gn:feature_class":"P",
    "gn:feature_code":"PPL",
    "gn:name":"Qaryat Wahir",
    "gn:population":0,
    "gn:timezone":"Asia/Aden",
    "iso:country":"YE",
    "wof:name":"Qaryat Wahir",
    "wof:placetype":"locality"
},
  "geometry": {"coordinates":[43.87778,13.54521],"type":"Point"}
}