{
  "type": "Feature",
  "properties": {
    "gn:country":"YE",
    "gn:fcode":"PPL",
    "gn:pop":2,
    "iso:country":"YE",
    "name:ara_x_preferred":[
        "\u0642\u0644\u0629 \u0627\u0644\u0641\u0631\u0648\u0634"
    ],
    "name:eng_x_preferred":[
        "Qullat Al FirUsh"
    ],
    "qs:name":"Qullat al Fir\u016bsh",
    "qs:photos_9r":0,
    "qs:photos_sr":0,
    "qs:pop_sr":"1",
    "wof:name":"Qullat al Fir\u016bsh",
    "wof:placetype":"locality",
    "wof:population":2
},
  "geometry": {"coordinates":[43.24243,17.24798],"type":"Point"}
}