{
  "type": "Feature",
  "properties": {
    "gn:admin1_code":"8.0",
    "gn:admin2_code":"1806.0",
    "gn:asciiname":"Al Murayqi",
    "gn:country_code":"YE",
    "gn:dem":51,
    "gn:feature_class":"P",
    "gn:feature_code":"PPL",
    "gn:name":"Al Murayq\u012b",
    "gn:population":0,
    "gn:timezone":"Asia/Aden",
    "iso:country":"YE",
    "name:und_x_variant":[
        "Al Murayq\u012b"
    ],
    "wof:name":"Al Murayqi",
    "wof:placetype":"locality"
},
  "geometry": {"coordinates":[42.99314,15.3937],"type":"Point"}
}