{
  "type": "Feature",
  "properties": {
    "gn:admin1_code":"23.0",
    "gn:admin2_code":"1108.0",
    "gn:asciiname":"An Nakhlah",
    "gn:country_code":"YE",
    "gn:dem":1413,
    "gn:feature_class":"P",
    "gn:feature_code":"PPL",
    "gn:name":"An Nakhlah",
    "gn:population":0,
    "gn:timezone":"Asia/Aden",
    "iso:country":"YE",
    "name:ara_x_preferred":[
        "\u0627\u0644\u0646\u062e\u0644\u0629"
    ],
    "wof:name":"An Nakhlah",
    "wof:placetype":"locality"
},
  "geometry": {"coordinates":[44.07824,14.16844],"type":"Point"}
}