{
  "type": "Feature",
  "properties": {
    "gn:admin1_code":"24.0",
    "gn:admin2_code":"2512.0",
    "gn:asciiname":"Ad Darb",
    "gn:country_code":"YE",
    "gn:dem":1198,
    "gn:feature_class":"P",
    "gn:feature_code":"PPL",
    "gn:name":"Ad Darb",
    "gn:population":0,
    "gn:timezone":"Asia/Aden",
    "iso:country":"YE",
    "name:ara_x_preferred":[
        "\u0627\u0644\u062f\u0631\u0628"
    ],
    "wof:name":"Ad Darb",
    "wof:placetype":"locality"
},
  "geometry": {"coordinates":[44.2038,13.21399],"type":"Point"}
}