{
  "type": "Feature",
  "properties": {
    "gn:admin1_code":"8.0",
    "gn:admin2_code":"1809.0",
    "gn:asciiname":"Hasan Saghir",
    "gn:country_code":"YE",
    "gn:dem":64,
    "gn:feature_class":"P",
    "gn:feature_code":"PPL",
    "gn:name":"\u1e28asan \u015eagh\u012br",
    "gn:population":0,
    "gn:timezone":"Asia/Aden",
    "iso:country":"YE",
    "name:ara_x_preferred":[
        "\u062d\u0633\u0646 \u0635\u063a\u064a\u0631"
    ],
    "name:und_x_variant":[
        "\u1e28asan \u015eagh\u012br"
    ],
    "wof:name":"Hasan Saghir",
    "wof:placetype":"locality"
},
  "geometry": {"coordinates":[43.03100000000001,15.20784],"type":"Point"}
}