{
  "type": "Feature",
  "properties": {
    "gn:admin1_code":"22.0",
    "gn:admin2_code":"1727.0",
    "gn:asciiname":"Bayt 'Ali Qutli",
    "gn:country_code":"YE",
    "gn:dem":1219,
    "gn:feature_class":"P",
    "gn:feature_code":"PPL",
    "gn:name":"Bayt \u2018Al\u012b Qu\u0163l\u012b",
    "gn:population":0,
    "gn:timezone":"Asia/Aden",
    "iso:country":"YE",
    "name:ara_x_preferred":[
        "\u0628\u064a\u062a \u0639\u0644\u064a \u0642\u0637\u0644\u064a"
    ],
    "name:und_x_variant":[
        "Bayt \u2018Al\u012b Qu\u0163l\u012b"
    ],
    "wof:name":"Bayt 'Ali Qutli",
    "wof:placetype":"locality"
},
  "geometry": {"coordinates":[43.57285,15.58037],"type":"Point"}
}