{
  "type": "Feature",
  "properties": {
    "gn:country":"YE",
    "gn:fcode":"PPL",
    "gn:pop":3,
    "iso:country":"YE",
    "name:ara_x_preferred":[
        "\u0628\u064a\u062a \u064a\u062d\u064a \u062d\u0633\u064a\u0646 \u0627\u0644\u0639\u0628\u062f\u0644\u064a"
    ],
    "name:eng_x_preferred":[
        "Bayt Yahya Husayn Al 'Abdali"
    ],
    "qs:name":"Bayt Ya\u1e29ya \u1e28usayn al \u2018Abdal\u012b",
    "qs:photos_9r":0,
    "qs:photos_sr":0,
    "qs:pop_sr":"1",
    "wof:name":"Bayt Ya\u1e29ya \u1e28usayn al \u2018Abdal\u012b",
    "wof:placetype":"locality",
    "wof:population":3
},
  "geometry": {"coordinates":[43.17044,16.65871],"type":"Point"}
}