{
  "type": "Feature",
  "properties": {
    "gn:admin1_code":"25.0",
    "gn:admin2_code":"1503.0",
    "gn:asciiname":"Ahjur",
    "gn:country_code":"YE",
    "gn:dem":1380,
    "gn:feature_class":"P",
    "gn:feature_code":"PPL",
    "gn:name":"A\u1e29j\u016br",
    "gn:population":0,
    "gn:timezone":"Asia/Aden",
    "iso:country":"YE",
    "name:ara_x_preferred":[
        "A\u1e29j\u016br"
    ],
    "wof:name":"Ahjur",
    "wof:placetype":"locality"
},
  "geometry": {"coordinates":[43.95207,13.74629],"type":"Point"}
}