{
  "type": "Feature",
  "properties": {
    "gn:admin1_code":"11.0",
    "gn:admin2_code":"2005.0",
    "gn:asciiname":"Hisn Huwayz",
    "gn:country_code":"YE",
    "gn:dem":1846,
    "gn:feature_class":"P",
    "gn:feature_code":"PPL",
    "gn:name":"\u1e28i\u015fn \u1e28uwayz",
    "gn:population":0,
    "gn:timezone":"Asia/Aden",
    "iso:country":"YE",
    "name:und_x_variant":[
        "\u1e28i\u015fn \u1e28uwayz"
    ],
    "wof:name":"Hisn Huwayz",
    "wof:placetype":"locality"
},
  "geometry": {"coordinates":[43.98628,14.47854],"type":"Point"}
}