{
  "type": "Feature",
  "properties": {
    "gn:admin1_code":"8.0",
    "gn:admin2_code":"1816.0",
    "gn:asciiname":"Bayt al Karimi",
    "gn:country_code":"YE",
    "gn:dem":140,
    "gn:feature_class":"P",
    "gn:feature_code":"PPL",
    "gn:name":"Bayt al Kar\u012bm\u012b",
    "gn:population":0,
    "gn:timezone":"Asia/Aden",
    "iso:country":"YE",
    "name:ara_x_preferred":[
        "\u0628\u064a\u062a \u0627\u0644\u0643\u0631\u064a\u0645\u064a"
    ],
    "name:und_x_variant":[
        "Bayt al Kar\u012bm\u012b"
    ],
    "wof:name":"Bayt al Karimi",
    "wof:placetype":"locality"
},
  "geometry": {"coordinates":[43.36026,14.70829],"type":"Point"}
}