{
  "type": "Feature",
  "properties": {
    "gn:country":"YE",
    "gn:fcode":"PPL",
    "gn:pop":2,
    "iso:country":"YE",
    "name:ara_x_preferred":[
        "\u0627\u0644\u0639\u0644\u0628 \u0627\u0644\u0623\u0641\u062c\u062d"
    ],
    "name:eng_x_preferred":[
        "Al 'Alb Al Afjah"
    ],
    "qs:name":"Al \u2018Alb al Afja\u1e29",
    "qs:photos_9r":0,
    "qs:photos_sr":0,
    "qs:pop_sr":"1",
    "wof:name":"Al \u2018Alb al Afja\u1e29",
    "wof:placetype":"locality",
    "wof:population":2
},
  "geometry": {"coordinates":[44.04749,17.27231],"type":"Point"}
}