{
  "type": "Feature",
  "properties": {
    "gn:admin1_code":"4.0",
    "gn:admin2_code":"1908.0",
    "gn:asciiname":"Ash Shahi",
    "gn:cc2":"YE",
    "gn:country_code":"YE",
    "gn:dem":687,
    "gn:feature_class":"P",
    "gn:feature_code":"PPL",
    "gn:name":"Ash Sh\u0101h\u012b",
    "gn:population":0,
    "gn:timezone":"Asia/Aden",
    "iso:country":"YE",
    "name:ara_x_preferred":[
        "Ash Sh\u0101h\u012b"
    ],
    "name:und_x_variant":[
        "Aish Shahi",
        "Al-Sh\u0101h\u012b"
    ],
    "wof:name":"Ash Shahi",
    "wof:placetype":"locality"
},
  "geometry": {"coordinates":[48.66667,15.81667],"type":"Point"}
}