{
  "type": "Feature",
  "properties": {
    "gn:country":"YE",
    "gn:fcode":"PPL",
    "gn:pop":3,
    "iso:country":"YE",
    "name:ara_x_preferred":[
        "\u0639\u0648\u0636"
    ],
    "name:eng_x_preferred":[
        "Awau"
    ],
    "name:unk_x_variant":[
        "\u2018Iwa\u1e11"
    ],
    "qs:name":"\u2018Awa\u1e11",
    "qs:photos_9r":0,
    "qs:photos_sr":0,
    "qs:pop_sr":"1",
    "wof:name":"\u2018Awa\u1e11",
    "wof:placetype":"locality",
    "wof:population":3
},
  "geometry": {"coordinates":[44.11585,17.33202],"type":"Point"}
}