{
  "type": "Feature",
  "properties": {
    "gn:admin1_code":"18.0",
    "gn:admin2_code":"3005.0",
    "gn:asciiname":"Al Husayn",
    "gn:country_code":"YE",
    "gn:dem":1386,
    "gn:feature_class":"P",
    "gn:feature_code":"PPLA2",
    "gn:name":"Al \u1e28usayn",
    "gn:population":0,
    "gn:timezone":"Asia/Aden",
    "iso:country":"YE",
    "name:ara_x_preferred":[
        "\u0627\u0644\u062d\u0635\u064a\u0646"
    ],
    "name:und_x_variant":[
        "Al Husen",
        "Al Husain",
        "Al \u1e28usayn"
    ],
    "wof:name":"Al Husayn",
    "wof:placetype":"locality"
},
  "geometry": {"coordinates":[44.76886,13.79199],"type":"Point"}
}