{
  "type": "Feature",
  "properties": {
    "gn:admin1_code":"14.0",
    "gn:admin2_code":"2610.0",
    "gn:asciiname":"Al Ghurr",
    "gn:country_code":"YE",
    "gn:dem":1852,
    "gn:feature_class":"P",
    "gn:feature_code":"PPL",
    "gn:name":"Al Ghurr",
    "gn:population":0,
    "gn:timezone":"Asia/Aden",
    "iso:country":"YE",
    "name:ara_x_preferred":[
        "\u0627\u0644\u063a\u0631"
    ],
    "wof:name":"Al Ghurr",
    "wof:placetype":"locality"
},
  "geometry": {"coordinates":[45.16035,14.65093],"type":"Point"}
}