{
  "type": "Feature",
  "properties": {
    "gn:country":"YE",
    "gn:fcode":"PPL",
    "gn:pop":43,
    "iso:country":"YE",
    "name:ara_x_preferred":[
        "\u0627\u0644\u062d\u0636\u0646"
    ],
    "qs:name":"Al \u1e28a\u1e11n",
    "qs:photos_9r":0,
    "qs:photos_sr":0,
    "qs:pop_sr":"1",
    "wof:name":"Al \u1e28a\u1e11n",
    "wof:placetype":"locality",
    "wof:population":43
},
  "geometry": {"coordinates":[44.16058,15.45957],"type":"Point"}
}