{
  "type": "Feature",
  "properties": {
    "gn:country":"YE",
    "gn:fcode":"PPL",
    "gn:population":3,
    "iso:country":"YE",
    "name:ara_x_preferred":[
        "\u0627\u0644\u062c\u0628\u064a\u0628\u0629"
    ],
    "name:eng_x_preferred":[
        "Al Jubaybah"
    ],
    "name:eng_x_variant":[
        "Shahr al Mardaf"
    ],
    "qs:name":"Al Jubaybah",
    "qs:photos_9r":0,
    "qs:photos_sr":0,
    "qs:pop_sr":"1",
    "wof:name":"Al Jubaybah",
    "wof:placetype":"locality",
    "wof:population":3
},
  "geometry": {"coordinates":[43.25965,16.50165],"type":"Point"}
}