{
  "type": "Feature",
  "properties": {
    "gn:admin1_code":"28.0",
    "gn:admin2_code":"1926.0",
    "gn:asciiname":"Samhon",
    "gn:country_code":"YE",
    "gn:dem":487,
    "gn:feature_class":"P",
    "gn:feature_code":"PPL",
    "gn:name":"Samhon",
    "gn:population":0,
    "gn:timezone":"Asia/Aden",
    "iso:country":"YE",
    "name:und_x_variant":[
        "Samhun",
        "Samhon"
    ],
    "wof:name":"Samhon",
    "wof:placetype":"locality"
},
  "geometry": {"coordinates":[54.45,12.55],"type":"Point"}
}