{
  "type": "Feature",
  "properties": {
    "gn:country":"YE",
    "gn:fcode":"PPLX",
    "gn:population":2,
    "iso:country":"YE",
    "name:ara_x_preferred":[
        "\u0645\u0648\u0641 \u0627\u0644\u0623\u062d\u064a\u0646\u0649"
    ],
    "qs:name":"Mawf al U\u1e29ayn\u00e1",
    "qs:photos_9r":0,
    "qs:photos_sr":0,
    "qs:pop_sr":"1",
    "wof:name":"Mawf al U\u1e29ayn\u00e1",
    "wof:placetype":"neighbourhood",
    "wof:population":2
},
  "geometry": {"coordinates":[43.70311,16.18468],"type":"Point"}
}