{
  "type": "Feature",
  "properties": {
    "gn:admin1_code":"22.0",
    "gn:admin2_code":"1727.0",
    "gn:asciiname":"Bayt Ahmad 'Ali al Warad",
    "gn:country_code":"YE",
    "gn:dem":1245,
    "gn:feature_class":"P",
    "gn:feature_code":"PPL",
    "gn:name":"Bayt A\u1e29mad \u2018Al\u012b al Warad",
    "gn:population":0,
    "gn:timezone":"Asia/Aden",
    "iso:country":"YE",
    "name:ara_x_preferred":[
        "\u0628\u064a\u062a \u0627\u062d\u0645\u062f \u0639\u0644\u064a \u0627\u0644\u0648\u0631\u062f"
    ],
    "name:und_x_variant":[
        "Bayt A\u1e29mad \u2018Al\u012b al Warad"
    ],
    "wof:name":"Bayt Ahmad 'Ali al Warad",
    "wof:placetype":"locality"
},
  "geometry": {"coordinates":[43.57308,15.56176],"type":"Point"}
}