{
  "type": "Feature",
  "properties": {
    "gn:country":"YE",
    "gn:fcode":"PPL",
    "gn:pop":9,
    "iso:country":"YE",
    "name:ara_x_preferred":[
        "\u0627\u0644\u0637\u0627\u0626\u0631\u0629"
    ],
    "name:eng_x_preferred":[
        "At Tairah"
    ],
    "name:swe_x_preferred":[
        "Maksar"
    ],
    "qs:name":"A\u0163 \u0162\u0101\u2019irah",
    "qs:photos_9r":0,
    "qs:photos_sr":0,
    "qs:pop_sr":"1",
    "wof:name":"A\u0163 \u0162\u0101\u2019irah",
    "wof:placetype":"locality",
    "wof:population":9
},
  "geometry": {"coordinates":[43.83686,16.87779],"type":"Point"}
}