{
  "type": "Feature",
  "properties": {
    "gn:admin1_code":"8.0",
    "gn:admin2_code":"1806.0",
    "gn:asciiname":"Dayr al Humadiyah",
    "gn:country_code":"YE",
    "gn:dem":57,
    "gn:feature_class":"P",
    "gn:feature_code":"PPL",
    "gn:name":"Dayr al \u1e28um\u0101d\u012byah",
    "gn:population":0,
    "gn:timezone":"Asia/Aden",
    "iso:country":"YE",
    "name:und_x_variant":[
        "Dayr al \u1e28um\u0101d\u012byah",
        "Dayr al \u1e28amm\u0101d\u012byah"
    ],
    "wof:name":"Dayr al Humadiyah",
    "wof:placetype":"locality"
},
  "geometry": {"coordinates":[43.01391,15.43558],"type":"Point"}
}