{
  "type": "Feature",
  "properties": {
    "gn:admin1_code":"8.0",
    "gn:admin2_code":"1809.0",
    "gn:asciiname":"Al Jaw'i",
    "gn:country_code":"YE",
    "gn:dem":213,
    "gn:feature_class":"P",
    "gn:feature_code":"PPL",
    "gn:name":"Al Jaw\u2018\u012b",
    "gn:population":0,
    "gn:timezone":"Asia/Aden",
    "iso:country":"YE",
    "name:ara_x_preferred":[
        "\u0627\u0644\u062c\u0648\u0639\u064a"
    ],
    "name:und_x_variant":[
        "Al Jaw\u2018\u012b"
    ],
    "wof:name":"Al Jaw'i",
    "wof:placetype":"locality"
},
  "geometry": {"coordinates":[43.27736,15.23386],"type":"Point"}
}