{
  "type": "Feature",
  "properties": {
    "gn:admin1_code":"11.0",
    "gn:admin2_code":"2011.0",
    "gn:asciiname":"Bani Sanad",
    "gn:country_code":"YE",
    "gn:dem":2210,
    "gn:feature_class":"P",
    "gn:feature_code":"PPL",
    "gn:name":"Ban\u012b Sanad",
    "gn:population":0,
    "gn:timezone":"Asia/Aden",
    "iso:country":"YE",
    "name:und_x_variant":[
        "Ban\u012b Sanad"
    ],
    "wof:name":"Bani Sanad",
    "wof:placetype":"locality"
},
  "geometry": {"coordinates":[44.20818,14.81678],"type":"Point"}
}