{
  "type": "Feature",
  "properties": {
    "gn:country":"YE",
    "gn:fcode":"PPL",
    "gn:pop":35,
    "iso:country":"YE",
    "name:ara_x_preferred":[
        "\u0627\u0644\u0645\u0633\u064a\u0644 \u0628\u062f\u064a\u0639"
    ],
    "name:eng_x_preferred":[
        "Al Musayl Badi'"
    ],
    "qs:name":"Al Musayl Bad\u012b\u2018",
    "qs:photos_9r":0,
    "qs:photos_sr":0,
    "qs:pop_sr":"1",
    "wof:name":"Al Musayl Bad\u012b\u2018",
    "wof:placetype":"locality",
    "wof:population":35
},
  "geometry": {"coordinates":[43.68085,16.96888],"type":"Point"}
}