{
  "type": "Feature",
  "properties": {
    "gn:country":"YE",
    "gn:fcode":"PPL",
    "gn:population":4,
    "iso:country":"YE",
    "name:ara_x_preferred":[
        "Al Mu\u1e11\u0101rib"
    ],
    "name:ara_x_variant":[
        "\u0627\u0644\u0645\u0636\u0627\u0631\u0628"
    ],
    "name:eng_x_preferred":[
        "Al Muuarib"
    ],
    "name:eng_x_variant":[
        "Ash Shajn"
    ],
    "qs:name":"Al Mu\u1e11\u0101rib",
    "qs:photos_9r":0,
    "qs:photos_sr":0,
    "qs:pop_sr":"1",
    "wof:name":"Al Mu\u1e11\u0101rib",
    "wof:placetype":"locality",
    "wof:population":4
},
  "geometry": {"coordinates":[43.37138,16.76115],"type":"Point"}
}