{
  "type": "Feature",
  "properties": {
    "gn:admin1_code":"11.0",
    "gn:admin2_code":"2005.0",
    "gn:asciiname":"Al Qarn",
    "gn:country_code":"YE",
    "gn:dem":1749,
    "gn:feature_class":"P",
    "gn:feature_code":"PPL",
    "gn:name":"Al Qarn",
    "gn:population":0,
    "gn:timezone":"Asia/Aden",
    "iso:country":"YE",
    "name:ara_x_preferred":[
        "\u0627\u0644\u0642\u0631\u0646"
    ],
    "name:und_x_variant":[
        "Al Qayn",
        "Al Qarn"
    ],
    "wof:name":"Al Qarn",
    "wof:placetype":"locality"
},
  "geometry": {"coordinates":[43.87612,14.45387],"type":"Point"}
}