{
  "type": "Feature",
  "properties": {
    "gn:admin1_code":"10.0",
    "gn:admin2_code":"2705.0",
    "gn:asciiname":"`Ukaybir",
    "gn:country_code":"YE",
    "gn:dem":1563,
    "gn:feature_class":"P",
    "gn:feature_code":"PPL",
    "gn:name":"\u2018Ukaybir",
    "gn:population":0,
    "gn:timezone":"Asia/Aden",
    "iso:country":"YE",
    "name:ara_x_preferred":[
        "\u0639\u0643\u064a\u0628\u0631"
    ],
    "name:und_x_variant":[
        "\u2018Ukaybir",
        "\u2018Ukayb\u012br"
    ],
    "wof:name":"`Ukaybir",
    "wof:placetype":"locality"
},
  "geometry": {"coordinates":[43.34077,15.33634],"type":"Point"}
}