{
  "type": "Feature",
  "properties": {
    "gn:admin1_code":"19.0",
    "gn:admin2_code":"2901.0",
    "gn:asciiname":"Az Zurayfah",
    "gn:country_code":"YE",
    "gn:dem":1948,
    "gn:feature_class":"P",
    "gn:feature_code":"PPLL",
    "gn:name":"Az\u0327 Z\u0327urayfah",
    "gn:population":0,
    "gn:timezone":"Asia/Aden",
    "iso:country":"YE",
    "name:ara_x_preferred":[
        "\u0627\u0644\u0638\u0631\u064a\u0641\u0629"
    ],
    "name:und_x_variant":[
        "Az\u0327 Z\u0327urayfah"
    ],
    "wof:name":"Az Zurayfah",
    "wof:placetype":"locality"
},
  "geometry": {"coordinates":[43.88396,16.4894],"type":"Point"}
}