{
  "type": "Feature",
  "properties": {
    "gn:admin1_code":"10.0",
    "gn:admin2_code":"2709.0",
    "gn:asciiname":"Hijrat Bani Sawd",
    "gn:country_code":"YE",
    "gn:dem":605,
    "gn:feature_class":"P",
    "gn:feature_code":"PPL",
    "gn:name":"Hijrat Ban\u012b Sawd",
    "gn:population":0,
    "gn:timezone":"Asia/Aden",
    "iso:country":"YE",
    "name:und_x_variant":[
        "Hijrat Ban\u012b Sawd"
    ],
    "wof:name":"Hijrat Bani Sawd",
    "wof:placetype":"locality"
},
  "geometry": {"coordinates":[43.5057,15.54073],"type":"Point"}
}