{
  "type": "Feature",
  "properties": {
    "gn:admin1_code":"24.0",
    "gn:admin2_code":"2502.0",
    "gn:asciiname":"Khalid",
    "gn:country_code":"YE",
    "gn:dem":2270,
    "gn:feature_class":"P",
    "gn:feature_code":"PPL",
    "gn:name":"Kh\u0101lid",
    "gn:population":0,
    "gn:timezone":"Asia/Aden",
    "iso:country":"YE",
    "name:ara_x_preferred":[
        "Kh\u0101lid"
    ],
    "wof:name":"Khalid",
    "wof:placetype":"locality"
},
  "geometry": {"coordinates":[45.2525,13.8673],"type":"Point"}
}