{
  "type": "Feature",
  "properties": {
    "gn:gn_country":"YE",
    "gn:gn_fcode":"PPL",
    "gn:gn_pop":20,
    "gn:population":20,
    "iso:country":"YE",
    "name:ara_x_preferred":[
        "\u0635\u0631\u0648 \u062c\u0647\u064a\u0644"
    ],
    "name:eng_x_preferred":[
        "Sirw Juhayl"
    ],
    "name:eng_x_variant":[
        "Al Jadibah"
    ],
    "qs_pg:aaroncc":"YE",
    "qs_pg:gn_country":"YE",
    "qs_pg:gn_fcode":"PPL",
    "qs_pg:gn_pop":20,
    "qs_pg:name":"\u015eirw Juhayl",
    "qs_pg:photos_9r":0,
    "qs_pg:photos_sr":0,
    "qs_pg:pop_sr":1,
    "qs_pg:qs_pg_placetype":"locality",
    "wof:name":"\u015eirw Juhayl",
    "wof:placetype":"locality",
    "wof:population":20
},
  "geometry": {"coordinates":[43.27003,16.96113],"type":"Point"}
}