{
  "type": "Feature",
  "properties": {
    "gn:admin1_code":"22.0",
    "gn:admin2_code":"1721.0",
    "gn:asciiname":"Dakhin",
    "gn:country_code":"YE",
    "gn:dem":1244,
    "gn:feature_class":"P",
    "gn:feature_code":"PPL",
    "gn:name":"D\u0101khin",
    "gn:population":0,
    "gn:timezone":"Asia/Aden",
    "iso:country":"YE",
    "name:ara_x_preferred":[
        "D\u0101khin"
    ],
    "wof:name":"Dakhin",
    "wof:placetype":"locality"
},
  "geometry": {"coordinates":[43.47768,15.85861],"type":"Point"}
}