{
  "type": "Feature",
  "properties": {
    "gn:admin1_code":"20.0",
    "gn:admin2_code":"1419.0",
    "gn:asciiname":"Al Ashru`",
    "gn:country_code":"YE",
    "gn:dem":1973,
    "gn:feature_class":"P",
    "gn:feature_code":"PPL",
    "gn:name":"Al Ashru\u2018",
    "gn:population":0,
    "gn:timezone":"Asia/Aden",
    "iso:country":"YE",
    "name:ara_x_preferred":[
        "Al Ashru\u2018"
    ],
    "wof:name":"Al Ashru`",
    "wof:placetype":"locality"
},
  "geometry": {"coordinates":[45.0603,14.33238],"type":"Point"}
}