{
  "type": "Feature",
  "properties": {
    "gn:country":"YE",
    "gn:fcode":"PPL",
    "gn:pop":5,
    "iso:country":"YE",
    "name:ara_x_preferred":[
        "\u0627\u0644\u0645\u0639\u064a\u0646\u0629"
    ],
    "name:unk_x_variant":[
        "Al Mu\u2018aynah"
    ],
    "qs:name":"Al Mu\u2018\u012bnah",
    "qs:photos_9r":0,
    "qs:photos_sr":0,
    "qs:pop_sr":"1",
    "wof:name":"Al Mu\u2018\u012bnah",
    "wof:placetype":"locality",
    "wof:population":5
},
  "geometry": {"coordinates":[43.4267,16.09005],"type":"Point"}
}