{
  "type": "Feature",
  "properties": {
    "gn:country":"YE",
    "gn:fcode":"PPL",
    "gn:pop":10,
    "iso:country":"YE",
    "name:ara_x_preferred":[
        "\u0627\u0644\u0631\u0643\u0628\u0629"
    ],
    "qs:name":"Ar Rukbah",
    "qs:photos_9r":0,
    "qs:photos_sr":0,
    "qs:pop_sr":"1",
    "wof:name":"Ar Rukbah",
    "wof:placetype":"locality",
    "wof:population":10
},
  "geometry": {"coordinates":[43.26191,16.88586],"type":"Point"}
}