{
  "type": "Feature",
  "properties": {
    "gn:admin1_code":"19.0",
    "gn:admin2_code":"2901.0",
    "gn:asciiname":"Hadabat Husaynah",
    "gn:country_code":"YE",
    "gn:dem":1594,
    "gn:feature_class":"P",
    "gn:feature_code":"PPL",
    "gn:name":"\u1e28adabat \u1e28usaynah",
    "gn:population":0,
    "gn:timezone":"Asia/Aden",
    "iso:country":"YE",
    "name:ara_x_preferred":[
        "\u062d\u062f\u0628\u0629 \u062d\u0633\u064a\u0646\u0629"
    ],
    "name:und_x_variant":[
        "\u1e28adabat \u1e28usaynah"
    ],
    "wof:name":"Hadabat Husaynah",
    "wof:placetype":"locality"
},
  "geometry": {"coordinates":[44.07155,16.41047],"type":"Point"}
}