{
  "type": "Feature",
  "properties": {
    "gn:admin1_code":"8.0",
    "gn:admin2_code":"1816.0",
    "gn:asciiname":"Al Qusariyah",
    "gn:country_code":"YE",
    "gn:dem":129,
    "gn:feature_class":"P",
    "gn:feature_code":"PPL",
    "gn:name":"Al Qu\u015f\u0101r\u012byah",
    "gn:population":0,
    "gn:timezone":"Asia/Aden",
    "iso:country":"YE",
    "name:und_x_variant":[
        "Al Qu\u015f\u0101r\u012byah"
    ],
    "wof:name":"Al Qusariyah",
    "wof:placetype":"locality"
},
  "geometry": {"coordinates":[43.27991,14.71534],"type":"Point"}
}