{
  "type": "Feature",
  "properties": {
    "gn:admin1_code":"19.0",
    "gn:admin2_code":"2913.0",
    "gn:asciiname":"Bani Shaddad",
    "gn:country_code":"YE",
    "gn:dem":1033,
    "gn:feature_class":"P",
    "gn:feature_code":"PPL",
    "gn:name":"Ban\u012b Shadd\u0101d",
    "gn:population":0,
    "gn:timezone":"Asia/Aden",
    "iso:country":"YE",
    "name:ara_x_preferred":[
        "\u0639\u0632\u0644\u0629 \u0628\u0646\u064a \u0634\u062f\u0627\u062f"
    ],
    "name:ceb_x_preferred":[
        "Ban\u012b Shad\u0101d"
    ],
    "name:nno_x_preferred":[
        "Bani Shaddad"
    ],
    "name:und_x_variant":[
        "Ban\u012b Shadd\u0101d"
    ],
    "wof:name":"Bani Shaddad",
    "wof:placetype":"locality"
},
  "geometry": {"coordinates":[43.71991,15.90905],"type":"Point"}
}