{
  "type": "Feature",
  "properties": {
    "gn:admin1_code":"23.0",
    "gn:admin2_code":"1110.0",
    "gn:asciiname":"An Nudaym",
    "gn:country_code":"YE",
    "gn:dem":719,
    "gn:feature_class":"P",
    "gn:feature_code":"PPL",
    "gn:name":"An Nudaym",
    "gn:population":0,
    "gn:timezone":"Asia/Aden",
    "iso:country":"YE",
    "name:ara_x_preferred":[
        "\u0627\u0644\u0646\u062f\u064a\u0645"
    ],
    "name:und_x_variant":[
        "An Nad\u012bm"
    ],
    "wof:name":"An Nudaym",
    "wof:placetype":"locality"
},
  "geometry": {"coordinates":[43.7428,13.96812],"type":"Point"}
}