{
  "type": "Feature",
  "properties": {
    "gn:country":"YE",
    "gn:fcode":"PPLX",
    "gn:population":7,
    "iso:country":"YE",
    "name:ara_x_preferred":[
        "\u0627\u0644\u062d\u0645\u0627\u062f"
    ],
    "name:und_x_variant":[
        "Al \u1e28amm\u0101d"
    ],
    "qs:name":"Al \u1e28am\u0101d",
    "qs:photos_9r":0,
    "qs:photos_sr":0,
    "qs:pop_sr":"1",
    "wof:name":"Al \u1e28am\u0101d",
    "wof:placetype":"neighbourhood",
    "wof:population":7
},
  "geometry": {"coordinates":[44.26143,16.57532],"type":"Point"}
}