{
  "type": "Feature",
  "properties": {
    "gn:admin1_code":"18.0",
    "gn:admin2_code":"3005.0",
    "gn:asciiname":"Sulayb",
    "gn:country_code":"YE",
    "gn:dem":1608,
    "gn:feature_class":"P",
    "gn:feature_code":"PPL",
    "gn:name":"Sulayb",
    "gn:population":0,
    "gn:timezone":"Asia/Aden",
    "iso:country":"YE",
    "name:und_x_variant":[
        "Suleb",
        "Sulayb"
    ],
    "wof:name":"Sulayb",
    "wof:placetype":"locality"
},
  "geometry": {"coordinates":[44.84317,13.74728],"type":"Point"}
}