{
  "type": "Feature",
  "properties": {
    "gn:admin1_code":"15.0",
    "gn:admin2_code":"2205.0",
    "gn:asciiname":"Buq`at Bani Safwan",
    "gn:country_code":"YE",
    "gn:dem":1645,
    "gn:feature_class":"P",
    "gn:feature_code":"PPL",
    "gn:name":"Buq\u2018at Ban\u012b \u015eafw\u0101n",
    "gn:population":0,
    "gn:timezone":"Asia/Aden",
    "iso:country":"YE",
    "name:und_x_variant":[
        "Buq\u2018at Ban\u012b \u015eafw\u0101n"
    ],
    "wof:name":"Buq`at Bani Safwan",
    "wof:placetype":"locality"
},
  "geometry": {"coordinates":[43.22569,16.96286],"type":"Point"}
}