{
  "type": "Feature",
  "properties": {
    "gn:admin1_code":"16.0",
    "gn:admin2_code":"2308.0",
    "gn:asciiname":"Bani Sulayman",
    "gn:country_code":"YE",
    "gn:dem":1488,
    "gn:feature_class":"P",
    "gn:feature_code":"PPL",
    "gn:name":"Ban\u012b Sulaym\u0101n",
    "gn:population":0,
    "gn:timezone":"Asia/Aden",
    "iso:country":"YE",
    "name:nno_x_preferred":[
        "Bani Sulayman"
    ],
    "name:spa_x_preferred":[
        "Bani Sulayman"
    ],
    "name:und_x_variant":[
        "Ban\u012b Sulaym\u0101n"
    ],
    "wof:name":"Bani Sulayman",
    "wof:placetype":"locality"
},
  "geometry": {"coordinates":[43.85,15.21667],"type":"Point"}
}