{
  "type": "Feature",
  "properties": {
    "gn:admin1_code":"10.0",
    "gn:admin2_code":"2703.0",
    "gn:asciiname":"Bayt al Jubari",
    "gn:country_code":"YE",
    "gn:dem":1715,
    "gn:feature_class":"P",
    "gn:feature_code":"PPL",
    "gn:name":"Bayt al Jubar\u012b",
    "gn:population":0,
    "gn:timezone":"Asia/Aden",
    "iso:country":"YE",
    "name:und_x_variant":[
        "Bayt al Jubar\u012b"
    ],
    "wof:name":"Bayt al Jubari",
    "wof:placetype":"locality"
},
  "geometry": {"coordinates":[43.67306,15.3935],"type":"Point"}
}