{
  "type": "Feature",
  "properties": {
    "gn:admin1_code":"14.0",
    "gn:admin2_code":"2606.0",
    "gn:asciiname":"Al Harjah",
    "gn:country_code":"YE",
    "gn:dem":1554,
    "gn:feature_class":"P",
    "gn:feature_code":"PPL",
    "gn:name":"Al \u1e28arjah",
    "gn:population":0,
    "gn:timezone":"Asia/Aden",
    "iso:country":"YE",
    "name:ara_x_preferred":[
        "\u0627\u0644\u062d\u0631\u062c\u0629"
    ],
    "name:und_x_variant":[
        "Al \u1e28arajah",
        "Al \u1e28arjah"
    ],
    "wof:name":"Al Harjah",
    "wof:placetype":"locality"
},
  "geometry": {"coordinates":[44.86683,15.41303],"type":"Point"}
}