{
  "type": "Feature",
  "properties": {
    "gn:admin1_code":"19.0",
    "gn:admin2_code":"2901.0",
    "gn:asciiname":"Al Wali",
    "gn:country_code":"YE",
    "gn:dem":1546,
    "gn:feature_class":"P",
    "gn:feature_code":"PPL",
    "gn:name":"Al W\u0101l\u012b",
    "gn:population":0,
    "gn:timezone":"Asia/Aden",
    "iso:country":"YE",
    "name:ara_x_preferred":[
        "\u0627\u0644\u0648\u0627\u0644\u064a"
    ],
    "name:und_x_variant":[
        "Al W\u0101l\u012b"
    ],
    "wof:name":"Al Wali",
    "wof:placetype":"locality"
},
  "geometry": {"coordinates":[44.25506,16.03598],"type":"Point"}
}