{
  "type": "Feature",
  "properties": {
    "gn:admin1_code":"23.0",
    "gn:admin2_code":"1101.0",
    "gn:asciiname":"Basar",
    "gn:country_code":"YE",
    "gn:dem":2237,
    "gn:feature_class":"P",
    "gn:feature_code":"PPL",
    "gn:name":"Basar",
    "gn:population":0,
    "gn:timezone":"Asia/Aden",
    "iso:country":"YE",
    "name:ceb_x_preferred":[
        "Basar"
    ],
    "name:deu_x_preferred":[
        "Basar"
    ],
    "name:pol_x_preferred":[
        "Bazar"
    ],
    "name:swe_x_preferred":[
        "Basar"
    ],
    "name:ukr_x_preferred":[
        "\u0411\u0430\u0437\u0430\u0440"
    ],
    "wof:name":"Basar",
    "wof:placetype":"locality"
},
  "geometry": {"coordinates":[44.18262,14.3683],"type":"Point"}
}