{
  "type": "Feature",
  "properties": {
    "gn:admin1_code":"23.0",
    "gn:admin2_code":"1108.0",
    "gn:asciiname":"Damid",
    "gn:country_code":"YE",
    "gn:dem":1384,
    "gn:feature_class":"P",
    "gn:feature_code":"PPL",
    "gn:name":"\u1e10amid",
    "gn:population":0,
    "gn:timezone":"Asia/Aden",
    "iso:country":"YE",
    "name:und_x_variant":[
        "\u1e10amid"
    ],
    "wof:name":"Damid",
    "wof:placetype":"locality"
},
  "geometry": {"coordinates":[44.13189000000001,14.1685],"type":"Point"}
}