{
  "type": "Feature",
  "properties": {
    "gn:admin1_code":"21.0",
    "gn:admin2_code":"1609.0",
    "gn:asciiname":"Al Khalaq",
    "gn:country_code":"YE",
    "gn:dem":1100,
    "gn:feature_class":"P",
    "gn:feature_code":"PPL",
    "gn:name":"Al Khalaq",
    "gn:population":0,
    "gn:timezone":"Asia/Aden",
    "iso:country":"YE",
    "name:ara_x_preferred":[
        "\u0627\u0644\u062e\u0644\u0642"
    ],
    "wof:name":"Al Khalaq",
    "wof:placetype":"locality"
},
  "geometry": {"coordinates":[44.82767,16.07215],"type":"Point"}
}