{
  "type": "Feature",
  "properties": {
    "gn:admin1_code":"8.0",
    "gn:admin2_code":"1810.0",
    "gn:asciiname":"Mahall 'Ali 'Arjah",
    "gn:country_code":"YE",
    "gn:dem":104,
    "gn:feature_class":"P",
    "gn:feature_code":"PPL",
    "gn:name":"Ma\u1e29all \u2018Al\u012b \u2018Arjah",
    "gn:population":0,
    "gn:timezone":"Asia/Aden",
    "iso:country":"YE",
    "name:ara_x_preferred":[
        "\u0645\u062d\u0644 \u0639\u0644\u064a \u0639\u0631\u062c\u0629"
    ],
    "name:und_x_variant":[
        "Ma\u1e29all \u2018Al\u012b \u2018Arjah"
    ],
    "wof:name":"Mahall 'Ali 'Arjah",
    "wof:placetype":"locality"
},
  "geometry": {"coordinates":[43.1362,15.12971],"type":"Point"}
}