{
  "type": "Feature",
  "properties": {
    "gn:admin1_code":"20.0",
    "gn:admin2_code":"1406.0",
    "gn:asciiname":"Duray`a'",
    "gn:country_code":"YE",
    "gn:dem":2012,
    "gn:feature_class":"P",
    "gn:feature_code":"PPL",
    "gn:name":"Duray\u2018\u0101\u2019",
    "gn:population":0,
    "gn:timezone":"Asia/Aden",
    "iso:country":"YE",
    "name:und_x_variant":[
        "Duray\u2018\u0101\u2019"
    ],
    "wof:name":"Duray`a'",
    "wof:placetype":"locality"
},
  "geometry": {"coordinates":[45.43277,14.0539],"type":"Point"}
}