{
  "type": "Feature",
  "properties": {
    "gn:country":"YE",
    "gn:fcode":"PPL",
    "gn:population":1,
    "iso:country":"YE",
    "name:ara_x_preferred":[
        "\u0639\u0631\u0628\u064a\u0646"
    ],
    "name:eng_x_preferred":[
        "Arbayn"
    ],
    "name:eng_x_variant":[
        "'Arbayn"
    ],
    "qs:name":"\u2018Arbayn",
    "qs:photos_9r":0,
    "qs:photos_sr":0,
    "qs:pop_sr":"1",
    "wof:name":"\u2018Arbayn",
    "wof:placetype":"locality",
    "wof:population":1
},
  "geometry": {"coordinates":[43.42872,16.68088],"type":"Point"}
}