{
  "type": "Feature",
  "properties": {
    "gn:admin1_code":"23.0",
    "gn:admin2_code":"1101.0",
    "gn:asciiname":"Al Haljum",
    "gn:country_code":"YE",
    "gn:dem":1246,
    "gn:feature_class":"P",
    "gn:feature_code":"PPL",
    "gn:name":"Al \u1e28alj\u016bm",
    "gn:population":0,
    "gn:timezone":"Asia/Aden",
    "iso:country":"YE",
    "name:ara_x_preferred":[
        "\u0627\u0644\u062d\u0644\u062c\u0648\u0645"
    ],
    "name:und_x_variant":[
        "Al \u1e28alj\u016bm"
    ],
    "wof:name":"Al Haljum",
    "wof:placetype":"locality"
},
  "geometry": {"coordinates":[44.05488,14.34936],"type":"Point"}
}