{
  "type": "Feature",
  "properties": {
    "gn:admin1_code":"22.0",
    "gn:admin2_code":"1708.0",
    "gn:asciiname":"Mahall Bayt ad Dil`ah",
    "gn:country_code":"YE",
    "gn:dem":845,
    "gn:feature_class":"P",
    "gn:feature_code":"PPL",
    "gn:name":"Ma\u1e29all Bayt a\u1e11 \u1e10il\u2018ah",
    "gn:population":0,
    "gn:timezone":"Asia/Aden",
    "iso:country":"YE",
    "name:und_x_variant":[
        "Ma\u1e29all Bayt a\u1e11 \u1e10il\u2018ah"
    ],
    "wof:name":"Mahall Bayt ad Dil`ah",
    "wof:placetype":"locality"
},
  "geometry": {"coordinates":[43.56132,15.99664],"type":"Point"}
}