{
  "type": "Feature",
  "properties": {
    "gn:admin1_code":"24.0",
    "gn:admin2_code":"2515.0",
    "gn:asciiname":"Ash Sharj",
    "gn:country_code":"YE",
    "gn:dem":65,
    "gn:feature_class":"P",
    "gn:feature_code":"PPL",
    "gn:name":"Ash Sharj",
    "gn:population":0,
    "gn:timezone":"Asia/Aden",
    "iso:country":"YE",
    "wof:name":"Ash Sharj",
    "wof:placetype":"locality"
},
  "geometry": {"coordinates":[44.91306,12.96972],"type":"Point"}
}