{
  "type": "Feature",
  "properties": {
    "gn:country":"YE",
    "gn:fcode":"PPL",
    "gn:pop":9,
    "iso:country":"YE",
    "name:ara_x_preferred":[
        "\u0627\u0644\u0636\u0647\u0627\u0631"
    ],
    "qs:name":"A\u1e11 \u1e10ah\u0101r",
    "qs:photos_9r":0,
    "qs:photos_sr":0,
    "qs:pop_sr":"1",
    "wd:wordcount":18,
    "wof:name":"A\u1e11 \u1e10ah\u0101r",
    "wof:placetype":"locality",
    "wof:population":9
},
  "geometry": {"coordinates":[43.29869,16.19872],"type":"Point"}
}