{
  "type": "Feature",
  "properties": {
    "gn:admin1_code":"11.0",
    "gn:admin2_code":"2007.0",
    "gn:asciiname":"Al Hajar",
    "gn:country_code":"YE",
    "gn:dem":1302,
    "gn:feature_class":"P",
    "gn:feature_code":"PPL",
    "gn:name":"Al Hajar",
    "gn:population":0,
    "gn:timezone":"Asia/Aden",
    "iso:country":"YE",
    "name:ceb_x_preferred":[
        "Al Hajar"
    ],
    "wof:name":"Al Hajar",
    "wof:placetype":"locality"
},
  "geometry": {"coordinates":[43.67154,14.30931],"type":"Point"}
}