{
  "type": "Feature",
  "properties": {
    "gn:admin1_code":"11.0",
    "gn:admin2_code":"2005.0",
    "gn:asciiname":"Al Ja`war",
    "gn:country_code":"YE",
    "gn:dem":2301,
    "gn:feature_class":"P",
    "gn:feature_code":"PPL",
    "gn:name":"Al Ja\u2018war",
    "gn:population":0,
    "gn:timezone":"Asia/Aden",
    "iso:country":"YE",
    "name:und_x_variant":[
        "Al Ja\u2018war"
    ],
    "wof:name":"Al Ja`war",
    "wof:placetype":"locality"
},
  "geometry": {"coordinates":[44.07182,14.50243],"type":"Point"}
}