{
  "type": "Feature",
  "properties": {
    "gn:admin1_code":"15.0",
    "gn:admin2_code":"2209.0",
    "gn:asciiname":"Ibn al Makir",
    "gn:country_code":"YE",
    "gn:dem":2445,
    "gn:feature_class":"P",
    "gn:feature_code":"PPL",
    "gn:name":"Ibn al Mak\u012br",
    "gn:population":0,
    "gn:timezone":"Asia/Aden",
    "iso:country":"YE",
    "name:und_x_variant":[
        "Ibn al Mak\u012br"
    ],
    "wof:name":"Ibn al Makir",
    "wof:placetype":"locality"
},
  "geometry": {"coordinates":[43.37214,16.91968],"type":"Point"}
}