{
  "type": "Feature",
  "properties": {
    "gn:country":"YE",
    "gn:fcode":"PPL",
    "gn:population":91,
    "iso:country":"YE",
    "name:ara_x_preferred":[
        "\u0622\u0644 \u0633\u0631\u0628\u064a"
    ],
    "name:eng_x_preferred":[
        "Al Surabi"
    ],
    "name:eng_x_variant":[
        "S\u016bq al Khayr"
    ],
    "name:und_x_variant":[
        "\u0100l a\u015f \u015eurab\u012b"
    ],
    "qs:name":"\u0100l Surab\u012b",
    "qs:photos_9r":0,
    "qs:photos_sr":0,
    "qs:pop_sr":"1",
    "wof:name":"\u0100l Surab\u012b",
    "wof:placetype":"locality",
    "wof:population":91
},
  "geometry": {"coordinates":[43.68169,16.91934],"type":"Point"}
}