{
  "type": "Feature",
  "properties": {
    "gn:admin1_code":"11.0",
    "gn:admin2_code":"2008.0",
    "gn:asciiname":"Al Mawahib",
    "gn:country_code":"YE",
    "gn:dem":2408,
    "gn:feature_class":"P",
    "gn:feature_code":"PPL",
    "gn:name":"Al Maw\u0101hib",
    "gn:population":0,
    "gn:timezone":"Asia/Aden",
    "iso:country":"YE",
    "name:und_x_variant":[
        "Moayib",
        "Al Maw\u0101hib"
    ],
    "wof:name":"Al Mawahib",
    "wof:placetype":"locality"
},
  "geometry": {"coordinates":[44.42568,14.58886],"type":"Point"}
}