{
  "type": "Feature",
  "properties": {
    "gn:admin1_code":"19.0",
    "gn:admin2_code":"2919.0",
    "gn:asciiname":"Ar Ras'ah",
    "gn:country_code":"YE",
    "gn:dem":1590,
    "gn:feature_class":"P",
    "gn:feature_code":"PPLL",
    "gn:name":"Ar Ra\u015f\u2018ah",
    "gn:population":0,
    "gn:timezone":"Asia/Aden",
    "iso:country":"YE",
    "name:ara_x_preferred":[
        "\u0627\u0644\u0631\u0635\u0639\u0629"
    ],
    "name:und_x_variant":[
        "Ar Ra\u015f\u2018ah"
    ],
    "wof:name":"Ar Ras'ah",
    "wof:placetype":"locality"
},
  "geometry": {"coordinates":[43.80964,16.03002],"type":"Point"}
}