{
  "type": "Feature",
  "properties": {
    "gn:admin1_code":"16.0",
    "gn:admin2_code":"2915.0",
    "gn:asciiname":"Bayt al Huwayt",
    "gn:country_code":"YE",
    "gn:dem":2828,
    "gn:feature_class":"P",
    "gn:feature_code":"PPL",
    "gn:name":"Bayt al \u1e28uwayt",
    "gn:population":0,
    "gn:timezone":"Asia/Aden",
    "iso:country":"YE",
    "name:nno_x_preferred":[
        "Bayt al-Huwayt"
    ],
    "wof:name":"Bayt al Huwayt",
    "wof:placetype":"locality"
},
  "geometry": {"coordinates":[43.76667,15.71667],"type":"Point"}
}