{
  "type": "Feature",
  "properties": {
    "gn:admin1_code":"23.0",
    "gn:admin2_code":"1115.0",
    "gn:asciiname":"Al Mihla'i",
    "gn:country_code":"YE",
    "gn:dem":1956,
    "gn:feature_class":"P",
    "gn:feature_code":"PPL",
    "gn:name":"Al Mi\u1e29l\u0101\u2019\u012b",
    "gn:population":0,
    "gn:timezone":"Asia/Aden",
    "iso:country":"YE",
    "name:ara_x_preferred":[
        "Al Mi\u1e29l\u0101\u2019\u012b"
    ],
    "wof:name":"Al Mihla'i",
    "wof:placetype":"locality"
},
  "geometry": {"coordinates":[44.24077,13.86336],"type":"Point"}
}