{
  "type": "Feature",
  "properties": {
    "gn:admin1_code":"14.0",
    "gn:admin2_code":"2609.0",
    "gn:asciiname":"Ilah",
    "gn:country_code":"YE",
    "gn:dem":1215,
    "gn:feature_class":"P",
    "gn:feature_code":"PPL",
    "gn:name":"\u012alah",
    "gn:population":0,
    "gn:timezone":"Asia/Aden",
    "iso:country":"YE",
    "name:ara_x_preferred":[
        "\u0625\u064a\u0644\u0629"
    ],
    "name:und_x_variant":[
        "\u012alah"
    ],
    "wof:name":"Ilah",
    "wof:placetype":"locality"
},
  "geometry": {"coordinates":[45.41283,14.90679],"type":"Point"}
}