{
  "type": "Feature",
  "properties": {
    "gn:admin1_code":"23.0",
    "gn:admin2_code":"1103.0",
    "gn:asciiname":"Dhi Sha`bah",
    "gn:country_code":"YE",
    "gn:dem":2586,
    "gn:feature_class":"P",
    "gn:feature_code":"PPL",
    "gn:name":"Dh\u012b Sha\u2018bah",
    "gn:population":0,
    "gn:timezone":"Asia/Aden",
    "iso:country":"YE",
    "name:und_x_variant":[
        "Dh\u012b Sha\u2018bah"
    ],
    "wof:name":"Dhi Sha`bah",
    "wof:placetype":"locality"
},
  "geometry": {"coordinates":[44.50494000000001,14.21518],"type":"Point"}
}