{
  "type": "Feature",
  "properties": {
    "gn:admin1_code":"8.0",
    "gn:admin2_code":"1801.0",
    "gn:asciiname":"Dayr al `Izabi",
    "gn:country_code":"YE",
    "gn:dem":114,
    "gn:feature_class":"P",
    "gn:feature_code":"PPL",
    "gn:name":"Dayr al \u2018Iz\u0327\u0101b\u012b",
    "gn:population":0,
    "gn:timezone":"Asia/Aden",
    "iso:country":"YE",
    "name:und_x_variant":[
        "Dayr al \u2018Iz\u0327\u0101b\u012b"
    ],
    "wof:name":"Dayr al `Izabi",
    "wof:placetype":"locality"
},
  "geometry": {"coordinates":[43.12104,15.76492],"type":"Point"}
}