{
  "type": "Feature",
  "properties": {
    "gn:admin1_code":"25.0",
    "gn:admin2_code":"1507.0",
    "gn:asciiname":"Al 'Arjush",
    "gn:country_code":"YE",
    "gn:dem":189,
    "gn:feature_class":"P",
    "gn:feature_code":"PPL",
    "gn:name":"Al \u2018Arj\u016bsh",
    "gn:population":0,
    "gn:timezone":"Asia/Aden",
    "iso:country":"YE",
    "name:ara_x_preferred":[
        "Al \u2018Arj\u016bsh"
    ],
    "name:ara_x_variant":[
        "\u0627\u0644\u0639\u0631\u062c\u0648\u0634"
    ],
    "wof:name":"Al 'Arjush",
    "wof:placetype":"locality"
},
  "geometry": {"coordinates":[43.5148,13.23442],"type":"Point"}
}