{
  "type": "Feature",
  "properties": {
    "gn:country":"YE",
    "gn:fcode":"MKT",
    "gn:population":7,
    "iso:country":"YE",
    "name:ara_x_preferred":[
        "\u0645\u062d\u0644 \u0623\u0633\u0644\u0645"
    ],
    "name:und_x_variant":[
        "Ma\u1e29all Aslam"
    ],
    "qs:name":"Ma\u1e29al Aslam",
    "qs:photos_9r":0,
    "qs:photos_sr":0,
    "qs:pop_sr":"1",
    "wof:name":"Ma\u1e29al Aslam",
    "wof:placetype":"locality",
    "wof:population":7
},
  "geometry": {"coordinates":[43.18498,16.23232],"type":"Point"}
}