{
  "type": "Feature",
  "properties": {
    "gn:admin1_code":"10.0",
    "gn:admin2_code":"2701.0",
    "gn:asciiname":"Hajarat az Zaqar",
    "gn:country_code":"YE",
    "gn:dem":3069,
    "gn:feature_class":"P",
    "gn:feature_code":"PPL",
    "gn:name":"\u1e28ajarat az Zaqar",
    "gn:population":0,
    "gn:timezone":"Asia/Aden",
    "iso:country":"YE",
    "name:und_x_variant":[
        "\u1e28ajarat az Zaqar"
    ],
    "wof:name":"Hajarat az Zaqar",
    "wof:placetype":"locality"
},
  "geometry": {"coordinates":[43.84508,15.5404],"type":"Point"}
}