{
  "type": "Feature",
  "properties": {
    "gn:admin1_code":"20.0",
    "gn:admin2_code":"1406.0",
    "gn:asciiname":"Dhamjayr",
    "gn:country_code":"YE",
    "gn:dem":1965,
    "gn:feature_class":"P",
    "gn:feature_code":"PPL",
    "gn:name":"Dhamjayr",
    "gn:population":0,
    "gn:timezone":"Asia/Aden",
    "iso:country":"YE",
    "name:und_x_variant":[
        "Damjar",
        "Dh\u012b Mujayr",
        "Dh\u012b am J\u012br"
    ],
    "wof:name":"Dhamjayr",
    "wof:placetype":"locality"
},
  "geometry": {"coordinates":[45.42642,14.08589],"type":"Point"}
}