{
  "type": "Feature",
  "properties": {
    "gn:admin1_code":"14.0",
    "gn:admin2_code":"2613.0",
    "gn:asciiname":"Al Faraj",
    "gn:country_code":"YE",
    "gn:dem":1070,
    "gn:feature_class":"P",
    "gn:feature_code":"PPL",
    "gn:name":"\u0100l Faraj",
    "gn:population":0,
    "gn:timezone":"Asia/Aden",
    "iso:country":"YE",
    "name:ara_x_preferred":[
        "\u0627\u0644\u0641\u0631\u062c"
    ],
    "name:ara_x_variant":[
        "\u0627\u0644 \u0641\u0631\u062c"
    ],
    "name:und_x_variant":[
        "\u0100l Faraj",
        "Al Faraj"
    ],
    "wof:name":"Al Faraj",
    "wof:placetype":"locality"
},
  "geometry": {"coordinates":[45.42076,15.42811],"type":"Point"}
}