{
  "type": "Feature",
  "properties": {
    "gn:admin1_code":"25.0",
    "gn:admin2_code":"1515.0",
    "gn:asciiname":"Yadim al Barh",
    "gn:country_code":"YE",
    "gn:dem":864,
    "gn:feature_class":"P",
    "gn:feature_code":"PPL",
    "gn:name":"Y\u0101dim al Bar\u1e29",
    "gn:population":0,
    "gn:timezone":"Asia/Aden",
    "iso:country":"YE",
    "name:ara_x_preferred":[
        "Y\u0101dim"
    ],
    "name:ara_x_variant":[
        "\u064a\u0627\u062f\u0645 \u0627\u0644\u0628\u0631\u062d"
    ],
    "name:und_x_variant":[
        "Y\u0101dim al Bar\u1e29"
    ],
    "wof:name":"Yadim al Barh",
    "wof:placetype":"locality"
},
  "geometry": {"coordinates":[43.92583,13.23078],"type":"Point"}
}