{
  "type": "Feature",
  "properties": {
    "gn:admin1_code":"19.0",
    "gn:admin2_code":"2918.0",
    "gn:asciiname":"Bayt `Umar",
    "gn:country_code":"YE",
    "gn:dem":2657,
    "gn:feature_class":"P",
    "gn:feature_code":"PPL",
    "gn:name":"Bayt \u2018Umar",
    "gn:population":0,
    "gn:timezone":"Asia/Aden",
    "iso:country":"YE",
    "name:und_x_variant":[
        "Bayt \u2018Umar"
    ],
    "wof:name":"Bayt `Umar",
    "wof:placetype":"locality"
},
  "geometry": {"coordinates":[43.90456,15.60476],"type":"Point"}
}