{
  "type": "Feature",
  "properties": {
    "gn:admin1_code":"11.0",
    "gn:admin2_code":"2001.0",
    "gn:asciiname":"Ja'ish",
    "gn:country_code":"YE",
    "gn:dem":2296,
    "gn:feature_class":"P",
    "gn:feature_code":"PPL",
    "gn:name":"J\u0101\u2019\u012bsh",
    "gn:population":0,
    "gn:timezone":"Asia/Aden",
    "iso:country":"YE",
    "name:ara_x_preferred":[
        "J\u0101\u2019\u012bsh"
    ],
    "wof:name":"Ja'ish",
    "wof:placetype":"locality"
},
  "geometry": {"coordinates":[44.4428,14.9071],"type":"Point"}
}