{
  "type": "Feature",
  "properties": {
    "gn:admin1_code":"8.0",
    "gn:admin2_code":"1806.0",
    "gn:asciiname":"Dayr al Qiham Sharqi",
    "gn:country_code":"YE",
    "gn:dem":72,
    "gn:feature_class":"P",
    "gn:feature_code":"PPL",
    "gn:name":"Dayr al Qi\u1e29\u0101m Sharq\u012b",
    "gn:population":0,
    "gn:timezone":"Asia/Aden",
    "iso:country":"YE",
    "name:und_x_variant":[
        "Dayr al Qi\u1e29\u0101m Sharq\u012b"
    ],
    "wof:name":"Dayr al Qiham Sharqi",
    "wof:placetype":"locality"
},
  "geometry": {"coordinates":[43.04537,15.49186],"type":"Point"}
}