{
  "type": "Feature",
  "properties": {
    "gn:admin1_code":"25.0",
    "gn:admin2_code":"1521.0",
    "gn:asciiname":"Suq al Ahad",
    "gn:country_code":"YE",
    "gn:dem":1331,
    "gn:feature_class":"P",
    "gn:feature_code":"PPL",
    "gn:name":"S\u016bq al A\u1e29ad",
    "gn:population":0,
    "gn:timezone":"Asia/Aden",
    "iso:country":"YE",
    "name:und_x_variant":[
        "S\u016bq al A\u1e29ad"
    ],
    "wof:name":"Suq al Ahad",
    "wof:placetype":"locality"
},
  "geometry": {"coordinates":[44.05877,13.34677],"type":"Point"}
}