{
  "type": "Feature",
  "properties": {
    "gn:admin1_code":"20.0",
    "gn:admin2_code":"1414.0",
    "gn:asciiname":"Al Matar",
    "gn:country_code":"YE",
    "gn:dem":2090,
    "gn:feature_class":"P",
    "gn:feature_code":"PPL",
    "gn:name":"Al Mat\u0101r",
    "gn:population":0,
    "gn:timezone":"Asia/Aden",
    "iso:country":"YE",
    "name:und_x_variant":[
        "Al Mat\u0101r"
    ],
    "wof:name":"Al Matar",
    "wof:placetype":"locality"
},
  "geometry": {"coordinates":[44.90174,14.47581],"type":"Point"}
}