{
  "type": "Feature",
  "properties": {
    "gn:country":"YE",
    "gn:fcode":"PPL",
    "gn:pop":5,
    "iso:country":"YE",
    "name:ara_x_preferred":[
        "\u0627\u0644\u0645\u0643\u062d\u064a\u0644\u0629"
    ],
    "name:eng_x_preferred":[
        "Al Makhaylah"
    ],
    "qs:name":"Al Mak\u1e29aylah",
    "qs:photos_9r":0,
    "qs:photos_sr":0,
    "qs:pop_sr":"1",
    "wof:name":"Al Mak\u1e29aylah",
    "wof:placetype":"locality",
    "wof:population":5
},
  "geometry": {"coordinates":[43.27733,16.14893],"type":"Point"}
}