{
  "type": "Feature",
  "properties": {
    "gn:country":"YE",
    "gn:fcode":"PPLX",
    "gn:population":45,
    "iso:country":"YE",
    "name:ara_x_preferred":[
        "\u0627\u0644\u0645\u0642\u0639"
    ],
    "qs:name":"Al Maq\u2018",
    "qs:photos_9r":0,
    "qs:photos_sr":0,
    "qs:pop_sr":"1",
    "wof:name":"Al Maq\u2018",
    "wof:placetype":"neighbourhood",
    "wof:population":45
},
  "geometry": {"coordinates":[43.70688,16.05135],"type":"Point"}
}