{
  "type": "Feature",
  "properties": {
    "gn:country":"YE",
    "gn:fcode":"PPL",
    "gn:population":4,
    "iso:country":"YE",
    "name:ara_x_preferred":[
        "\u0627\u0644\u062c\u0631\u0641"
    ],
    "qs:name":"Al Jurf",
    "qs:photos_9r":0,
    "qs:photos_sr":0,
    "qs:pop_sr":"1",
    "wof:name":"Al Jurf",
    "wof:placetype":"locality",
    "wof:population":4
},
  "geometry": {"coordinates":[43.37031,16.07538],"type":"Point"}
}