{
  "type": "Feature",
  "properties": {
    "gn:admin1_code":"23.0",
    "gn:admin2_code":"1109.0",
    "gn:asciiname":"Al Hazm",
    "gn:country_code":"YE",
    "gn:dem":1945,
    "gn:feature_class":"P",
    "gn:feature_code":"PPL",
    "gn:name":"Al \u1e28azm",
    "gn:population":0,
    "gn:timezone":"Asia/Aden",
    "iso:country":"YE",
    "name:und_x_variant":[
        "Al \u1e28azm"
    ],
    "wof:name":"Al Hazm",
    "wof:placetype":"locality"
},
  "geometry": {"coordinates":[43.99309,14.02709],"type":"Point"}
}