{
  "type": "Feature",
  "properties": {
    "gn:admin1_code":"23.0",
    "gn:admin2_code":"1101.0",
    "gn:asciiname":"Ad Dar Qibal al `Ulya",
    "gn:country_code":"YE",
    "gn:dem":2151,
    "gn:feature_class":"P",
    "gn:feature_code":"PPL",
    "gn:name":"Ad D\u0101r Qib\u0101l al \u2018Uly\u0101",
    "gn:population":0,
    "gn:timezone":"Asia/Aden",
    "iso:country":"YE",
    "name:ara_x_preferred":[
        "\u0627\u0644\u062f\u0627\u0631 \u0642\u0628\u0627\u0644 \u0627\u0644\u0639\u0644\u064a\u0627"
    ],
    "name:und_x_variant":[
        "Qib\u0101l al \u2018Uly\u0101",
        "Ad D\u0101r Qib\u0101l al \u2018Uly\u0101"
    ],
    "wof:name":"Ad Dar Qibal al `Ulya",
    "wof:placetype":"locality"
},
  "geometry": {"coordinates":[44.25795,14.26006],"type":"Point"}
}