{
  "type": "Feature",
  "properties": {
    "gn:admin1_code":"8.0",
    "gn:admin2_code":"1810.0",
    "gn:asciiname":"Al Hisn",
    "gn:country_code":"YE",
    "gn:dem":821,
    "gn:feature_class":"P",
    "gn:feature_code":"PPL",
    "gn:name":"Al \u1e28i\u015fn",
    "gn:population":0,
    "gn:timezone":"Asia/Aden",
    "iso:country":"YE",
    "name:ara_x_preferred":[
        "Al \u1e28i\u015fn"
    ],
    "wof:name":"Al Hisn",
    "wof:placetype":"locality"
},
  "geometry": {"coordinates":[43.37651,15.03286],"type":"Point"}
}