{
  "type": "Feature",
  "properties": {
    "gn:country":"YE",
    "gn:fcode":"PPL",
    "gn:pop":3,
    "iso:country":"YE",
    "name:ara_x_preferred":[
        "\u0628\u064a\u062a \u0627\u0644\u0647\u0645\u064a\u0633\u064a"
    ],
    "name:eng_x_preferred":[
        "Bayt Al Humaysi"
    ],
    "name:eng_x_variant":[
        "\u0162iddah"
    ],
    "qs:name":"Bayt al Humays\u012b",
    "qs:photos_9r":0,
    "qs:photos_sr":0,
    "qs:pop_sr":"1",
    "wof:name":"Bayt al Humays\u012b",
    "wof:placetype":"locality",
    "wof:population":3
},
  "geometry": {"coordinates":[45.15352,13.77737],"type":"Point"}
}