{
  "type": "Feature",
  "properties": {
    "gn:admin1_code":"8.0",
    "gn:admin2_code":"1824.0",
    "gn:asciiname":"Bayt al Qissi",
    "gn:country_code":"YE",
    "gn:dem":175,
    "gn:feature_class":"P",
    "gn:feature_code":"PPL",
    "gn:name":"Bayt al Qiss\u012b",
    "gn:population":0,
    "gn:timezone":"Asia/Aden",
    "iso:country":"YE",
    "name:und_x_variant":[
        "Bayt al Qiss\u012b"
    ],
    "wof:name":"Bayt al Qissi",
    "wof:placetype":"locality"
},
  "geometry": {"coordinates":[43.40785,14.30401],"type":"Point"}
}