{
  "type": "Feature",
  "properties": {
    "gn:admin1_code":"23.0",
    "gn:admin2_code":"1101.0",
    "gn:asciiname":"Al `Arishah",
    "gn:country_code":"YE",
    "gn:dem":1284,
    "gn:feature_class":"P",
    "gn:feature_code":"PPL",
    "gn:name":"Al \u2018Arishah",
    "gn:population":0,
    "gn:timezone":"Asia/Aden",
    "iso:country":"YE",
    "name:ara_x_preferred":[
        "\u0627\u0644\u0639\u0631\u0634\u0629"
    ],
    "name:und_x_variant":[
        "Al \u2018Arishah",
        "Al \u2018Arshah"
    ],
    "wof:name":"Al `Arishah",
    "wof:placetype":"locality"
},
  "geometry": {"coordinates":[44.11159,14.20164],"type":"Point"}
}