{
  "type": "Feature",
  "properties": {
    "gn:admin1_code":"11.0",
    "gn:admin2_code":"2011.0",
    "gn:asciiname":"Al `Aridah",
    "gn:country_code":"YE",
    "gn:dem":1713,
    "gn:feature_class":"P",
    "gn:feature_code":"PPL",
    "gn:name":"Al \u2018\u0100ri\u1e11ah",
    "gn:population":0,
    "gn:timezone":"Asia/Aden",
    "iso:country":"YE",
    "name:und_x_variant":[
        "Al \u2018\u0100ri\u1e11ah"
    ],
    "wof:name":"Al `Aridah",
    "wof:placetype":"locality"
},
  "geometry": {"coordinates":[44.14664000000001,14.88883],"type":"Point"}
}