{
  "type": "Feature",
  "properties": {
    "gn:admin1_code":"16.0",
    "gn:admin2_code":"2306.0",
    "gn:asciiname":"Bayt az Ziyadi",
    "gn:country_code":"YE",
    "gn:dem":2652,
    "gn:feature_class":"P",
    "gn:feature_code":"PPL",
    "gn:name":"Bayt az Ziy\u0101d\u012b",
    "gn:population":0,
    "gn:timezone":"Asia/Aden",
    "iso:country":"YE",
    "name:und_x_variant":[
        "Bayt az Ziy\u0101r\u012b",
        "Bayt az Ziy\u0101d\u012b",
        "Bayt az Zaydah"
    ],
    "wof:name":"Bayt az Ziyadi",
    "wof:placetype":"locality"
},
  "geometry": {"coordinates":[44.27218,14.96953],"type":"Point"}
}