{
  "type": "Feature",
  "properties": {
    "gn:admin1_code":"11.0",
    "gn:admin2_code":"2006.0",
    "gn:asciiname":"Al `Anin",
    "gn:country_code":"YE",
    "gn:dem":1432,
    "gn:feature_class":"P",
    "gn:feature_code":"PPL",
    "gn:name":"Al \u2018An\u012bn",
    "gn:population":0,
    "gn:timezone":"Asia/Aden",
    "iso:country":"YE",
    "name:ara_x_preferred":[
        "Al \u2018An\u012bn"
    ],
    "wof:name":"Al `Anin",
    "wof:placetype":"locality"
},
  "geometry": {"coordinates":[43.72144,14.37413],"type":"Point"}
}