{
  "type": "Feature",
  "properties": {
    "gn:admin1_code":"8.0",
    "gn:admin2_code":"1824.0",
    "gn:asciiname":"Hajji ash Shamiri",
    "gn:country_code":"YE",
    "gn:dem":110,
    "gn:feature_class":"P",
    "gn:feature_code":"PPL",
    "gn:name":"\u1e28\u0101jj\u012b ash Sham\u012br\u012b",
    "gn:population":0,
    "gn:timezone":"Asia/Aden",
    "iso:country":"YE",
    "name:und_x_variant":[
        "\u1e28\u0101jj\u012b ash Sham\u012br\u012b"
    ],
    "wof:name":"Hajji ash Shamiri",
    "wof:placetype":"locality"
},
  "geometry": {"coordinates":[43.31232,14.17592],"type":"Point"}
}