{
  "type": "Feature",
  "properties": {
    "gn:country":"YE",
    "gn:fcode":"PPL",
    "gn:pop":1,
    "iso:country":"YE",
    "name:ara_x_preferred":[
        "\u0627\u0644\u062f\u0645\u0633"
    ],
    "name:eng_x_preferred":[
        "Ad Dams"
    ],
    "name:eng_x_variant":[
        "Adh Dhir\u0101\u2018 ash Sharq\u012b"
    ],
    "qs:name":"Ad Dams",
    "qs:photos_9r":0,
    "qs:photos_sr":0,
    "qs:pop_sr":"1",
    "wof:name":"Ad Dams",
    "wof:placetype":"locality",
    "wof:population":1
},
  "geometry": {"coordinates":[43.80617,13.46154],"type":"Point"}
}