{
  "type": "Feature",
  "properties": {
    "gn:admin1_code":"23.0",
    "gn:admin2_code":"1115.0",
    "gn:asciiname":"Yihar",
    "gn:country_code":"YE",
    "gn:dem":1752,
    "gn:feature_class":"P",
    "gn:feature_code":"PPL",
    "gn:name":"Yih\u0101r",
    "gn:population":0,
    "gn:timezone":"Asia/Aden",
    "iso:country":"YE",
    "name:ara_x_preferred":[
        "Yih\u0101r"
    ],
    "wof:name":"Yihar",
    "wof:placetype":"locality"
},
  "geometry": {"coordinates":[44.18533,13.79197],"type":"Point"}
}