{
  "type": "Feature",
  "properties": {
    "gn:admin1_code":"24.0",
    "gn:admin2_code":"2505.0",
    "gn:asciiname":"Jidrah",
    "gn:country_code":"YE",
    "gn:dem":761,
    "gn:feature_class":"P",
    "gn:feature_code":"PPL",
    "gn:name":"Jidrah",
    "gn:population":0,
    "gn:timezone":"Asia/Aden",
    "iso:country":"YE",
    "name:und_x_variant":[
        "Jidra",
        "Jidrah"
    ],
    "wof:name":"Jidrah",
    "wof:placetype":"locality"
},
  "geometry": {"coordinates":[44.90068,13.59507],"type":"Point"}
}