{
  "type": "Feature",
  "properties": {
    "gn:country":"YE",
    "gn:fcode":"PPL",
    "gn:pop":4,
    "iso:country":"YE",
    "name:ara_x_preferred":[
        "\u0627\u0644\u0645\u0636\u0645\u0648\u0646"
    ],
    "name:eng_x_preferred":[
        "Al MaumUn"
    ],
    "qs:name":"Al Ma\u1e11m\u016bn",
    "qs:photos_9r":0,
    "qs:photos_sr":0,
    "qs:pop_sr":"1",
    "wof:name":"Al Ma\u1e11m\u016bn",
    "wof:placetype":"locality",
    "wof:population":4
},
  "geometry": {"coordinates":[44.46491,16.91815],"type":"Point"}
}