{
  "type": "Feature",
  "properties": {
    "gn:country":"YE",
    "gn:fcode":"PPL",
    "gn:population":2,
    "iso:country":"YE",
    "name:ara_x_preferred":[
        "\u0628\u064a\u062a \u0627\u0644\u062e\u0631\u0627\u0628\u0629"
    ],
    "name:eng_x_preferred":[
        "Bayt Al Khirabah"
    ],
    "name:eng_x_variant":[
        "Qash\u2018 Dh\u016b \u1e28\u0101jib"
    ],
    "qs:name":"Bayt al Khir\u0101bah",
    "qs:photos_9r":0,
    "qs:photos_sr":0,
    "qs:pop_sr":"1",
    "wof:name":"Bayt al Khir\u0101bah",
    "wof:placetype":"locality",
    "wof:population":2
},
  "geometry": {"coordinates":[43.39944,16.02497],"type":"Point"}
}