{
  "type": "Feature",
  "properties": {
    "gn:admin1_code":"21.0",
    "gn:admin2_code":"1602.0",
    "gn:asciiname":"Al Mihzam",
    "gn:country_code":"YE",
    "gn:dem":1301,
    "gn:feature_class":"P",
    "gn:feature_code":"PPL",
    "gn:name":"Al Mi\u1e29z\u0101m",
    "gn:population":0,
    "gn:timezone":"Asia/Aden",
    "iso:country":"YE",
    "name:ara_x_preferred":[
        "\u0627\u0644\u0645\u062d\u0632\u0627\u0645"
    ],
    "name:und_x_variant":[
        "Al Mi\u1e29z\u0101m"
    ],
    "wof:name":"Al Mihzam",
    "wof:placetype":"locality"
},
  "geometry": {"coordinates":[44.43184,16.48306],"type":"Point"}
}