{
  "type": "Feature",
  "properties": {
    "gn:country":"YE",
    "gn:fcode":"PPL",
    "gn:population":3,
    "iso:country":"YE",
    "name:ara_x_preferred":[
        "\u0627\u0644\u0633\u064a\u0628"
    ],
    "name:eng_x_preferred":[
        "As Sayb"
    ],
    "name:eng_x_variant":[
        "Al Mazkh\u0101\u0163"
    ],
    "qs:name":"As Sayb",
    "qs:photos_9r":0,
    "qs:photos_sr":0,
    "qs:pop_sr":"1",
    "wof:name":"As Sayb",
    "wof:placetype":"locality",
    "wof:population":3
},
  "geometry": {"coordinates":[43.29855,17.392],"type":"Point"}
}