{
  "type": "Feature",
  "properties": {
    "gn:admin1_code":"8.0",
    "gn:admin2_code":"1817.0",
    "gn:asciiname":"Sha`ra",
    "gn:country_code":"YE",
    "gn:dem":94,
    "gn:feature_class":"P",
    "gn:feature_code":"PPL",
    "gn:name":"Sha\u2018r\u00e1",
    "gn:population":0,
    "gn:timezone":"Asia/Aden",
    "iso:country":"YE",
    "name:und_x_variant":[
        "Sha\u2018r\u00e1"
    ],
    "wof:name":"Sha`ra",
    "wof:placetype":"locality"
},
  "geometry": {"coordinates":[43.32534,14.63568],"type":"Point"}
}