{
  "type": "Feature",
  "properties": {
    "gn:admin1_code":"8.0",
    "gn:admin2_code":"1810.0",
    "gn:asciiname":"Al Balah",
    "gn:country_code":"YE",
    "gn:dem":123,
    "gn:feature_class":"P",
    "gn:feature_code":"PPL",
    "gn:name":"Al Bala\u1e29",
    "gn:population":0,
    "gn:timezone":"Asia/Aden",
    "iso:country":"YE",
    "name:ara_x_preferred":[
        "\u0627\u0644\u0628\u0644\u062d"
    ],
    "name:und_x_variant":[
        "Al Bala\u1e29"
    ],
    "wof:name":"Al Balah",
    "wof:placetype":"locality"
},
  "geometry": {"coordinates":[43.18117,15.0773],"type":"Point"}
}