{
  "type": "Feature",
  "properties": {
    "gn:admin1_code":"22.0",
    "gn:admin2_code":"1730.0",
    "gn:asciiname":"Al Khadra'",
    "gn:country_code":"YE",
    "gn:dem":584,
    "gn:feature_class":"P",
    "gn:feature_code":"PPL",
    "gn:name":"Al Khadr\u0101\u2019",
    "gn:population":8,
    "gn:timezone":"Asia/Aden",
    "iso:country":"YE",
    "name:ara_x_preferred":[
        "\u0627\u0644\u062e\u062f\u0631\u0627\u0621"
    ],
    "name:und_x_variant":[
        "Al Khadr\u0101\u2019"
    ],
    "wof:name":"Al Khadra'",
    "wof:placetype":"locality",
    "wof:population":8
},
  "geometry": {"coordinates":[43.3891,16.40235],"type":"Point"}
}