{
  "type": "Feature",
  "properties": {
    "gn:admin1_code":"11.0",
    "gn:admin2_code":"2004.0",
    "gn:asciiname":"Al Kharabah",
    "gn:country_code":"YE",
    "gn:dem":1744,
    "gn:feature_class":"P",
    "gn:feature_code":"PPLF",
    "gn:name":"Al Khar\u0101bah",
    "gn:population":0,
    "gn:timezone":"Asia/Aden",
    "iso:country":"YE",
    "name:ara_x_preferred":[
        "\u0627\u0644\u062e\u0631\u0627\u0628\u0629"
    ],
    "name:und_x_variant":[
        "Al Khar\u0101bah"
    ],
    "wof:name":"Al Kharabah",
    "wof:placetype":"locality"
},
  "geometry": {"coordinates":[44.14752,14.46428],"type":"Point"}
}