{
  "type": "Feature",
  "properties": {
    "gn:admin1_code":"24.0",
    "gn:admin2_code":"2501.0",
    "gn:asciiname":"Khulaqah",
    "gn:country_code":"YE",
    "gn:dem":2218,
    "gn:feature_class":"P",
    "gn:feature_code":"PPL",
    "gn:name":"Khul\u0101qah",
    "gn:population":0,
    "gn:timezone":"Asia/Aden",
    "iso:country":"YE",
    "name:und_x_variant":[
        "Khul\u0101qah"
    ],
    "wof:name":"Khulaqah",
    "wof:placetype":"locality"
},
  "geometry": {"coordinates":[45.23333,13.93333],"type":"Point"}
}