{
  "type": "Feature",
  "properties": {
    "gn:country":"YE",
    "gn:fcode":"PPL",
    "gn:pop":4,
    "iso:country":"YE",
    "name:ara_x_preferred":[
        "\u0627\u0644\u0633\u0631"
    ],
    "qs:name":"As Sirr",
    "qs:photos_9r":0,
    "qs:photos_sr":0,
    "qs:pop_sr":"1",
    "wd:wordcount":12,
    "wof:name":"As Sirr",
    "wof:placetype":"locality",
    "wof:population":4
},
  "geometry": {"coordinates":[43.34524,16.3333],"type":"Point"}
}