{
  "type": "Feature",
  "properties": {
    "gn:country":"YE",
    "gn:fcode":"PPL",
    "gn:pop":11,
    "iso:country":"YE",
    "name:ara_x_preferred":[
        "\u0622\u0644 \u0627\u0644\u0623\u062f\u0648\u0644"
    ],
    "name:eng_x_preferred":[
        "Al Al Adawal"
    ],
    "name:eng_x_variant":[
        "Al \u2018Aniqah"
    ],
    "qs:name":"\u0100l al Adawal",
    "qs:photos_9r":0,
    "qs:photos_sr":0,
    "qs:pop_sr":"1",
    "wof:name":"\u0100l al Adawal",
    "wof:placetype":"locality",
    "wof:population":11
},
  "geometry": {"coordinates":[44.16409,16.92274],"type":"Point"}
}