{
  "type": "Feature",
  "properties": {
    "gn:admin1_code":"5.0",
    "gn:admin2_code":"2107.0",
    "gn:asciiname":"Al Hawabit",
    "gn:country_code":"YE",
    "gn:dem":1117,
    "gn:elevation":"2.0",
    "gn:feature_class":"P",
    "gn:feature_code":"PPL",
    "gn:name":"Al Haw\u0101bi\u0163",
    "gn:population":0,
    "gn:timezone":"Asia/Aden",
    "iso:country":"YE",
    "name:und_x_variant":[
        "Al Haw\u0101bi\u0163"
    ],
    "wof:name":"Al Hawabit",
    "wof:placetype":"locality"
},
  "geometry": {"coordinates":[45.72477,14.81801],"type":"Point"}
}