{
  "type": "Feature",
  "properties": {
    "gn:admin1_code":"19.0",
    "gn:admin2_code":"2912.0",
    "gn:asciiname":"Bani `Ala",
    "gn:country_code":"YE",
    "gn:dem":2090,
    "gn:feature_class":"P",
    "gn:feature_code":"PPL",
    "gn:name":"Ban\u012b \u2018Al\u00e1",
    "gn:population":0,
    "gn:timezone":"Asia/Aden",
    "iso:country":"YE",
    "name:und_x_variant":[
        "Ban\u012b \u2018Al\u00e1"
    ],
    "wof:name":"Bani `Ala",
    "wof:placetype":"locality"
},
  "geometry": {"coordinates":[43.82638,15.89118],"type":"Point"}
}