{
  "type": "Feature",
  "properties": {
    "gn:admin1_code":"10.0",
    "gn:admin2_code":"2705.0",
    "gn:asciiname":"Dibyan",
    "gn:country_code":"YE",
    "gn:dem":253,
    "gn:feature_class":"P",
    "gn:feature_code":"PPL",
    "gn:name":"\u1e10iby\u0101n",
    "gn:population":0,
    "gn:timezone":"Asia/Aden",
    "iso:country":"YE",
    "name:ara_x_preferred":[
        "\u1e10iby\u0101n"
    ],
    "wof:name":"Dibyan",
    "wof:placetype":"locality"
},
  "geometry": {"coordinates":[43.26218,15.43482],"type":"Point"}
}