{
  "type": "Feature",
  "properties": {
    "gn:country":"YE",
    "gn:fcode":"PPLX",
    "gn:pop":5,
    "iso:country":"YE",
    "name:ara_x_preferred":[
        "\u062d\u064a\u0641\u0629 \u062f\u064a\u0628\u0627\u0646"
    ],
    "qs:name":"\u1e28ayfat Daby\u0101n",
    "qs:photos_9r":0,
    "qs:photos_sr":0,
    "qs:pop_sr":"1",
    "wof:name":"\u1e28ayfat Daby\u0101n",
    "wof:placetype":"neighbourhood",
    "wof:population":5
},
  "geometry": {"coordinates":[43.4174,16.04121],"type":"Point"}
}