{
  "type": "Feature",
  "properties": {
    "gn:admin1_code":"14.0",
    "gn:admin2_code":"2601.0",
    "gn:asciiname":"Al Bush",
    "gn:country_code":"YE",
    "gn:dem":1280,
    "gn:feature_class":"P",
    "gn:feature_code":"PPL",
    "gn:name":"Al B\u016bsh",
    "gn:population":0,
    "gn:timezone":"Asia/Aden",
    "iso:country":"YE",
    "name:ara_x_preferred":[
        "\u0627\u0644\u0628\u0648\u0634"
    ],
    "name:und_x_variant":[
        "Al B\u016bsh"
    ],
    "wof:name":"Al Bush",
    "wof:placetype":"locality"
},
  "geometry": {"coordinates":[44.74908,15.7922],"type":"Point"}
}