{
  "type": "Feature",
  "properties": {
    "gn:admin1_code":"16.0",
    "gn:admin2_code":"2309.0",
    "gn:asciiname":"Bayt al `Ali",
    "gn:country_code":"YE",
    "gn:dem":1659,
    "gn:feature_class":"P",
    "gn:feature_code":"PPL",
    "gn:name":"Bayt al \u2018Al\u012b",
    "gn:population":0,
    "gn:timezone":"Asia/Aden",
    "iso:country":"YE",
    "name:und_x_variant":[
        "Bayt al \u2018Al\u012b"
    ],
    "wof:name":"Bayt al `Ali",
    "wof:placetype":"locality"
},
  "geometry": {"coordinates":[43.90036,15.06198],"type":"Point"}
}