{
  "type": "Feature",
  "properties": {
    "gn:country":"YE",
    "gn:fcode":"PPL",
    "gn:pop":2,
    "iso:country":"YE",
    "name:ara_x_preferred":[
        "\u0627\u0644\u062d\u0630\u064a\u0629 \u0627\u0644\u0633\u0641\u0644\u0649"
    ],
    "name:eng_x_preferred":[
        "Al Hadhiyah As Sufla"
    ],
    "name:eng_x_variant":[
        "Gharr\u0101\u2019 al Qawz"
    ],
    "qs:name":"Al \u1e28adh\u012byah as Sufl\u00e1",
    "qs:photos_9r":0,
    "qs:photos_sr":0,
    "qs:pop_sr":"1",
    "wof:name":"Al \u1e28adh\u012byah as Sufl\u00e1",
    "wof:placetype":"locality",
    "wof:population":2
},
  "geometry": {"coordinates":[44.83153,16.86346],"type":"Point"}
}