{
  "type": "Feature",
  "properties": {
    "gn:admin1_code":"8.0",
    "gn:admin2_code":"1810.0",
    "gn:asciiname":"Al Khansa'",
    "gn:country_code":"YE",
    "gn:dem":172,
    "gn:feature_class":"P",
    "gn:feature_code":"PPL",
    "gn:name":"Al Khans\u0101\u2019",
    "gn:population":0,
    "gn:timezone":"Asia/Aden",
    "iso:country":"YE",
    "name:ara_x_preferred":[
        "\u0627\u0644\u062e\u0646\u0633\u0627\u0621"
    ],
    "name:und_x_variant":[
        "Al Khans\u0101\u2019"
    ],
    "wof:name":"Al Khansa'",
    "wof:placetype":"locality"
},
  "geometry": {"coordinates":[43.26344,15.06032],"type":"Point"}
}