{
  "type": "Feature",
  "properties": {
    "gn:admin1_code":"14.0",
    "gn:admin2_code":"2604.0",
    "gn:asciiname":"Khalif al Mid'a'",
    "gn:country_code":"YE",
    "gn:dem":1893,
    "gn:feature_class":"P",
    "gn:feature_code":"PPL",
    "gn:name":"Khal\u012bf al Mid\u2018\u0101\u2019",
    "gn:population":0,
    "gn:timezone":"Asia/Aden",
    "iso:country":"YE",
    "name:ara_x_preferred":[
        "\u062e\u0644\u064a\u0641 \u0627\u0644\u0645\u062f\u0639\u0627\u0621"
    ],
    "name:und_x_variant":[
        "Khal\u012bf al Mid\u2018\u0101\u2019"
    ],
    "wof:name":"Khalif al Mid'a'",
    "wof:placetype":"locality"
},
  "geometry": {"coordinates":[44.5951,15.45252],"type":"Point"}
}