{
  "type": "Feature",
  "properties": {
    "gn:admin1_code":"16.0",
    "gn:admin2_code":"2308.0",
    "gn:asciiname":"Kudafah",
    "gn:country_code":"YE",
    "gn:dem":1657,
    "gn:feature_class":"P",
    "gn:feature_code":"PPL",
    "gn:name":"Kud\u0101fah",
    "gn:population":0,
    "gn:timezone":"Asia/Aden",
    "iso:country":"YE",
    "name:und_x_variant":[
        "Kud\u0101fah"
    ],
    "wof:name":"Kudafah",
    "wof:placetype":"locality"
},
  "geometry": {"coordinates":[43.88942,15.23398],"type":"Point"}
}