{
  "type": "Feature",
  "properties": {
    "gn:admin1_code":"18.0",
    "gn:admin2_code":"3009.0",
    "gn:asciiname":"Thawkab",
    "gn:cc2":"YE",
    "gn:country_code":"YE",
    "gn:dem":1423,
    "gn:feature_class":"P",
    "gn:feature_code":"PPL",
    "gn:name":"Thawkab",
    "gn:population":0,
    "gn:timezone":"Asia/Aden",
    "iso:country":"YE",
    "name:und_x_variant":[
        "Thaukab",
        "Thawkab"
    ],
    "wof:name":"Thawkab",
    "wof:placetype":"locality"
},
  "geometry": {"coordinates":[44.55,13.76667],"type":"Point"}
}