{
  "type": "Feature",
  "properties": {
    "gn:admin1_code":"14.0",
    "gn:asciiname":"Al `Ibr al Qadad",
    "gn:country_code":"YE",
    "gn:dem":1573,
    "gn:feature_class":"P",
    "gn:feature_code":"PPL",
    "gn:name":"Al \u2018Ibr al Qa\u1e11\u0101\u1e11",
    "gn:population":0,
    "gn:timezone":"Asia/Aden",
    "iso:country":"YE",
    "name:ara_x_preferred":[
        "\u0627\u0644\u0639\u0628\u0631 \u0627\u0644\u0642\u0636\u0627\u0636"
    ],
    "name:und_x_variant":[
        "Al \u2018Ibr al Qa\u1e11\u0101\u1e11"
    ],
    "wof:name":"Al `Ibr al Qadad",
    "wof:placetype":"locality"
},
  "geometry": {"coordinates":[44.91588,16.4485],"type":"Point"}
}