{
  "type": "Feature",
  "properties": {
    "gn:admin1_code":"14.0",
    "gn:admin2_code":"2613.0",
    "gn:asciiname":"Al Hazmah",
    "gn:cc2":"YE",
    "gn:country_code":"YE",
    "gn:dem":1053,
    "gn:feature_class":"P",
    "gn:feature_code":"PPL",
    "gn:name":"Al \u1e28azmah",
    "gn:population":0,
    "gn:timezone":"Asia/Aden",
    "iso:country":"YE",
    "name:und_x_variant":[
        "Al Huzmah",
        "Al \u1e28azmah"
    ],
    "wof:name":"Al Hazmah",
    "wof:placetype":"locality"
},
  "geometry": {"coordinates":[45.38333,15.56667],"type":"Point"}
}