{
  "type": "Feature",
  "properties": {
    "gn:admin1_code":"21.0",
    "gn:admin2_code":"1611.0",
    "gn:asciiname":"Shawl ar Rashid",
    "gn:country_code":"YE",
    "gn:dem":2038,
    "gn:feature_class":"P",
    "gn:feature_code":"PPL",
    "gn:name":"Shawl ar R\u0101shid",
    "gn:population":0,
    "gn:timezone":"Asia/Aden",
    "iso:country":"YE",
    "name:und_x_variant":[
        "Shawl ar R\u0101shid"
    ],
    "wof:name":"Shawl ar Rashid",
    "wof:placetype":"locality"
},
  "geometry": {"coordinates":[44.43466,16.7582],"type":"Point"}
}