{
  "type": "Feature",
  "properties": {
    "gn:admin1_code":"19.0",
    "gn:admin2_code":"2909.0",
    "gn:asciiname":"Mahall Yanur",
    "gn:country_code":"YE",
    "gn:dem":1997,
    "gn:feature_class":"P",
    "gn:feature_code":"PPL",
    "gn:name":"Ma\u1e29all Yan\u016br",
    "gn:population":0,
    "gn:timezone":"Asia/Aden",
    "iso:country":"YE",
    "name:und_x_variant":[
        "Ma\u1e29all Yan\u016br"
    ],
    "wof:name":"Mahall Yanur",
    "wof:placetype":"locality"
},
  "geometry": {"coordinates":[44.14468,15.92418],"type":"Point"}
}