{
  "type": "Feature",
  "properties": {
    "gn:admin1_code":"19.0",
    "gn:admin2_code":"2919.0",
    "gn:asciiname":"Al Musayjid",
    "gn:country_code":"YE",
    "gn:dem":2292,
    "gn:feature_class":"P",
    "gn:feature_code":"PPL",
    "gn:name":"Al Musayjid",
    "gn:population":0,
    "gn:timezone":"Asia/Aden",
    "iso:country":"YE",
    "name:ara_x_preferred":[
        "\u0627\u0644\u0645\u0633\u064a\u062c\u064a\u062f"
    ],
    "name:fas_x_preferred":[
        "\u0627\u0644\u0645\u0633\u06cc\u062c\u06cc\u062f"
    ],
    "name:nno_x_preferred":[
        "Al Musayjid"
    ],
    "name:urd_x_preferred":[
        "\u0627\u0644\u0645\u0633\u06cc\u062c\u06cc\u062f"
    ],
    "wof:name":"Al Musayjid",
    "wof:placetype":"locality"
},
  "geometry": {"coordinates":[43.91211,16.0453],"type":"Point"}
}