{
  "type": "Feature",
  "properties": {
    "gn:country":"YE",
    "gn:fcode":"PPL",
    "gn:pop":1,
    "iso:country":"YE",
    "name:ara_x_preferred":[
        "\u0631\u0632\u0645 \u0627\u0644\u0646\u0647\u0645\u064a"
    ],
    "name:eng_x_preferred":[
        "Razm An Nahmi"
    ],
    "qs:name":"Razm an Nahm\u012b",
    "qs:photos_9r":0,
    "qs:photos_sr":0,
    "qs:pop_sr":"1",
    "wof:name":"Razm an Nahm\u012b",
    "wof:placetype":"locality",
    "wof:population":1
},
  "geometry": {"coordinates":[43.36214,16.359],"type":"Point"}
}