{
  "type": "Feature",
  "properties": {
    "gn:admin1_code":"25.0",
    "gn:admin2_code":"1522.0",
    "gn:asciiname":"Al Miqtar",
    "gn:country_code":"YE",
    "gn:dem":1327,
    "gn:feature_class":"P",
    "gn:feature_code":"PPL",
    "gn:name":"Al Miq\u0163\u0101r",
    "gn:population":0,
    "gn:timezone":"Asia/Aden",
    "iso:country":"YE",
    "name:ara_x_preferred":[
        "Al Miq\u0163\u0101r"
    ],
    "wof:name":"Al Miqtar",
    "wof:placetype":"locality"
},
  "geometry": {"coordinates":[44.06332,13.26914],"type":"Point"}
}