{
  "type": "Feature",
  "properties": {
    "gn:admin1_code":"16.0",
    "gn:admin2_code":"2911.0",
    "gn:asciiname":"Dhayfan",
    "gn:country_code":"YE",
    "gn:dem":2588,
    "gn:feature_class":"P",
    "gn:feature_code":"PPL",
    "gn:name":"Dhayfan",
    "gn:population":0,
    "gn:timezone":"Asia/Aden",
    "iso:country":"YE",
    "wof:name":"Dhayfan",
    "wof:placetype":"locality"
},
  "geometry": {"coordinates":[44.08917,15.70528],"type":"Point"}
}