{
  "type": "Feature",
  "properties": {
    "gn:admin1_code":"15.0",
    "gn:admin2_code":"2209.0",
    "gn:asciiname":"Al Bazih",
    "gn:country_code":"YE",
    "gn:dem":1984,
    "gn:feature_class":"P",
    "gn:feature_code":"PPL",
    "gn:name":"Al B\u0101zi\u1e29",
    "gn:population":0,
    "gn:timezone":"Asia/Aden",
    "iso:country":"YE",
    "name:ara_x_preferred":[
        "Al B\u0101zikh"
    ],
    "name:ara_x_variant":[
        "Al B\u0101zi\u1e29",
        "\u0627\u0644\u0628\u0627\u0632\u062d"
    ],
    "wof:name":"Al Bazih",
    "wof:placetype":"locality"
},
  "geometry": {"coordinates":[43.38658,16.85926],"type":"Point"}
}