{
  "type": "Feature",
  "properties": {
    "gn:gn_country":"YE",
    "gn:gn_fcode":"PPL",
    "gn:gn_pop":2,
    "gn:population":2,
    "iso:country":"YE",
    "name:ara_x_preferred":[
        "\u0648\u0627\u062f\u064a \u0627\u0644\u0645\u0634\u0627\u0648\u0644\u0629"
    ],
    "name:eng_x_preferred":[
        "Wadi Al Mashawilah"
    ],
    "qs_pg:aaroncc":"YE",
    "qs_pg:gn_country":"YE",
    "qs_pg:gn_fcode":"PPL",
    "qs_pg:gn_pop":2,
    "qs_pg:name":"W\u0101d\u012b al Mash\u0101wilah",
    "qs_pg:photos_9r":0,
    "qs_pg:photos_sr":0,
    "qs_pg:pop_sr":1,
    "qs_pg:qs_pg_placetype":"locality",
    "wof:name":"W\u0101d\u012b al Mash\u0101wilah",
    "wof:placetype":"locality",
    "wof:population":2
},
  "geometry": {"coordinates":[45.14168,13.78735],"type":"Point"}
}