{
  "type": "Feature",
  "properties": {
    "gn:admin1_code":"16.0",
    "gn:admin2_code":"2305.0",
    "gn:asciiname":"Al Jahshi",
    "gn:country_code":"YE",
    "gn:dem":2451,
    "gn:feature_class":"P",
    "gn:feature_code":"PPL",
    "gn:name":"Al Ja\u1e29sh\u012b",
    "gn:population":0,
    "gn:timezone":"Asia/Aden",
    "iso:country":"YE",
    "name:und_x_variant":[
        "Al Ja\u1e29sh\u012b"
    ],
    "wof:name":"Al Jahshi",
    "wof:placetype":"locality"
},
  "geometry": {"coordinates":[44.31003,15.12539],"type":"Point"}
}