{
  "type": "Feature",
  "properties": {
    "gn:admin1_code":"15.0",
    "gn:admin2_code":"2210.0",
    "gn:asciiname":"Alt az Zubrah",
    "gn:country_code":"YE",
    "gn:dem":1757,
    "gn:feature_class":"P",
    "gn:feature_code":"PPL",
    "gn:name":"Alt az Zubrah",
    "gn:population":0,
    "gn:timezone":"Asia/Aden",
    "iso:country":"YE",
    "name:ara_x_preferred":[
        "\u0627\u0644\u062a \u0627\u0644\u0632\u0628\u0631\u0629"
    ],
    "name:und_x_variant":[
        "Dhir\u0101\u2018 lbn az Zubrah",
        "Alt az Zubrah"
    ],
    "wof:name":"Alt az Zubrah",
    "wof:placetype":"locality"
},
  "geometry": {"coordinates":[43.40703,17.05453],"type":"Point"}
}