{
  "type": "Feature",
  "properties": {
    "gn:country":"YE",
    "gn:fcode":"PPL",
    "gn:pop":2,
    "iso:country":"YE",
    "name:ara_x_preferred":[
        "\u062d\u0628\u064a\u0644 \u0627\u0644\u0645\u0636\u0629"
    ],
    "name:eng_x_preferred":[
        "Habil Al Mauah"
    ],
    "name:eng_x_variant":[
        "\u2018A\u0163r\u0101n"
    ],
    "qs:name":"\u1e28ab\u012bl al Ma\u1e11ah",
    "qs:photos_9r":0,
    "qs:photos_sr":0,
    "qs:pop_sr":"1",
    "wof:name":"\u1e28ab\u012bl al Ma\u1e11ah",
    "wof:placetype":"locality",
    "wof:population":2
},
  "geometry": {"coordinates":[43.24451,17.10212],"type":"Point"}
}