{
  "type": "Feature",
  "properties": {
    "gn:country":"YE",
    "gn:fcode":"PPL",
    "gn:pop":21,
    "iso:country":"YE",
    "name:ara_x_preferred":[
        "\u0627\u0644\u0637\u0627\u0631\u0641\u0640\u0629"
    ],
    "name:eng_x_preferred":[
        "At Tarifah"
    ],
    "name:eng_x_variant":[
        "Ath Tharibah"
    ],
    "qs:name":"A\u0163 \u0162\u0101rifah",
    "qs:photos_9r":0,
    "qs:photos_sr":0,
    "qs:pop_sr":"1",
    "wof:name":"A\u0163 \u0162\u0101rifah",
    "wof:placetype":"locality",
    "wof:population":21
},
  "geometry": {"coordinates":[43.60874,16.01125],"type":"Point"}
}