{
  "type": "Feature",
  "properties": {
    "gn:admin1_code":"11.0",
    "gn:admin2_code":"2005.0",
    "gn:asciiname":"Ad Dar",
    "gn:country_code":"YE",
    "gn:dem":1992,
    "gn:feature_class":"P",
    "gn:feature_code":"PPL",
    "gn:name":"Ad D\u0101r",
    "gn:population":0,
    "gn:timezone":"Asia/Aden",
    "iso:country":"YE",
    "name:ara_x_preferred":[
        "Ad D\u0101r"
    ],
    "wof:name":"Ad Dar",
    "wof:placetype":"locality"
},
  "geometry": {"coordinates":[43.94731,14.45485],"type":"Point"}
}