{
  "type": "Feature",
  "properties": {
    "gn:country":"YE",
    "gn:fcode":"PPL",
    "gn:pop":35,
    "iso:country":"YE",
    "name:ara_x_preferred":[
        "\u0627\u0644\u0648\u0627\u062f\u064a"
    ],
    "name:eng_x_preferred":[
        "Al Wadi"
    ],
    "name:eng_x_variant":[
        "Al Jabal al A\u2018l\u00e1"
    ],
    "name:unk_x_variant":[
        "\u0627\u0644\u0648\u0627\u062f\u064a"
    ],
    "qs:name":"Al W\u0101d\u012b",
    "qs:photos_9r":0,
    "qs:photos_sr":0,
    "qs:pop_sr":"1",
    "wof:name":"Al W\u0101d\u012b",
    "wof:placetype":"locality",
    "wof:population":35
},
  "geometry": {"coordinates":[42.99966,16.26917],"type":"Point"}
}