{
  "type": "Feature",
  "properties": {
    "gn:country":"YE",
    "gn:fcode":"PPL",
    "gn:pop":1,
    "iso:country":"YE",
    "name:ara_x_preferred":[
        "\u0627\u0644\u0633\u0627\u062f\u0629"
    ],
    "qs:name":"As S\u0101ddah",
    "qs:photos_9r":0,
    "qs:photos_sr":0,
    "qs:pop_sr":"1",
    "wd:wordcount":57,
    "wof:name":"As S\u0101ddah",
    "wof:placetype":"locality",
    "wof:population":1
},
  "geometry": {"coordinates":[44.21523,16.53886],"type":"Point"}
}