{
  "type": "Feature",
  "properties": {
    "gn:admin1_code":"11.0",
    "gn:admin2_code":"2012.0",
    "gn:asciiname":"Qihlan",
    "gn:country_code":"YE",
    "gn:dem":2283,
    "gn:feature_class":"P",
    "gn:feature_code":"PPL",
    "gn:name":"Qihl\u0101n",
    "gn:population":0,
    "gn:timezone":"Asia/Aden",
    "iso:country":"YE",
    "name:ara_x_preferred":[
        "Qihl\u0101n"
    ],
    "wof:name":"Qihlan",
    "wof:placetype":"locality"
},
  "geometry": {"coordinates":[44.10406,14.61543],"type":"Point"}
}