{
  "type": "Feature",
  "properties": {
    "gn:admin1_code":"20.0",
    "gn:admin2_code":"1414.0",
    "gn:asciiname":"As Sidd",
    "gn:country_code":"YE",
    "gn:dem":2115,
    "gn:feature_class":"P",
    "gn:feature_code":"PPL",
    "gn:name":"As Sidd",
    "gn:population":0,
    "gn:timezone":"Asia/Aden",
    "iso:country":"YE",
    "wof:name":"As Sidd",
    "wof:placetype":"locality"
},
  "geometry": {"coordinates":[44.85925,14.42587],"type":"Point"}
}