{
  "type": "Feature",
  "properties": {
    "gn:country":"YE",
    "gn:fcode":"PPL",
    "gn:population":2,
    "iso:country":"YE",
    "name:ara_x_preferred":[
        "Shi\u2018\u0101th"
    ],
    "name:ara_x_variant":[
        "\u0634\u0639\u0640\u0640\u0627\u062b",
        "\u0634\u0639\u0627\u062b"
    ],
    "name:eng_x_preferred":[
        "Shi'ath"
    ],
    "name:eng_x_variant":[
        "Bi\u2019r \u015e\u0101li\u1e29"
    ],
    "qs:name":"Shi\u2018\u0101th",
    "qs:photos_9r":0,
    "qs:photos_sr":0,
    "qs:pop_sr":"1",
    "wof:name":"Shi\u2018\u0101th",
    "wof:placetype":"locality",
    "wof:population":2
},
  "geometry": {"coordinates":[43.41755,16.30796],"type":"Point"}
}