{
  "type": "Feature",
  "properties": {
    "gn:admin1_code":"19.0",
    "gn:admin2_code":"2920.0",
    "gn:asciiname":"Bayt al Bashah",
    "gn:country_code":"YE",
    "gn:dem":2179,
    "gn:feature_class":"P",
    "gn:feature_code":"PPL",
    "gn:name":"Bayt al B\u0101shah",
    "gn:population":0,
    "gn:timezone":"Asia/Aden",
    "iso:country":"YE",
    "name:und_x_variant":[
        "Bayt al B\u0101shah"
    ],
    "wof:name":"Bayt al Bashah",
    "wof:placetype":"locality"
},
  "geometry": {"coordinates":[44.00269,16.11523],"type":"Point"}
}