{
  "type": "Feature",
  "properties": {
    "gn:country":"YE",
    "gn:fcode":"PPL",
    "gn:pop":3,
    "iso:country":"YE",
    "name:ara_x_preferred":[
        "\u0642\u0631\u0646 \u0627\u0644\u0628\u062f\u064a\u0639"
    ],
    "name:ara_x_variant":[
        "\u0627\u0644\u0628\u062f\u064a\u0639"
    ],
    "name:eng_x_preferred":[
        "Qarn Al Badi'"
    ],
    "name:eng_x_variant":[
        "Al Q\u0101\u2019im"
    ],
    "name:unk_x_variant":[
        "Al Bad\u012b\u2018"
    ],
    "qs:name":"Qarn al Bad\u012b\u2018",
    "qs:photos_9r":0,
    "qs:photos_sr":0,
    "qs:pop_sr":"1",
    "wof:name":"Qarn al Bad\u012b\u2018",
    "wof:placetype":"locality",
    "wof:population":3
},
  "geometry": {"coordinates":[43.4283,16.43808],"type":"Point"}
}