{
  "type": "Feature",
  "properties": {
    "gn:admin1_code":"8.0",
    "gn:admin2_code":"1801.0",
    "gn:asciiname":"Dayr Mida",
    "gn:country_code":"YE",
    "gn:dem":99,
    "gn:feature_class":"P",
    "gn:feature_code":"PPL",
    "gn:name":"Dayr Mida",
    "gn:population":0,
    "gn:timezone":"Asia/Aden",
    "iso:country":"YE",
    "wof:name":"Dayr Mida",
    "wof:placetype":"locality"
},
  "geometry": {"coordinates":[43.06667,15.68333],"type":"Point"}
}