{
  "type": "Feature",
  "properties": {
    "gn:admin1_code":"4.0",
    "gn:admin2_code":"1922.0",
    "gn:asciiname":"Shamariyah",
    "gn:country_code":"YE",
    "gn:dem":1475,
    "gn:feature_class":"P",
    "gn:feature_code":"PPL",
    "gn:name":"Shamar\u012byah",
    "gn:population":0,
    "gn:timezone":"Asia/Aden",
    "iso:country":"YE",
    "name:und_x_variant":[
        "Shamar\u012byah"
    ],
    "wof:name":"Shamariyah",
    "wof:placetype":"locality"
},
  "geometry": {"coordinates":[47.65,15.15],"type":"Point"}
}