{
  "type": "Feature",
  "properties": {
    "gn:country":"YE",
    "gn:fcode":"PPL",
    "gn:population":10,
    "iso:country":"YE",
    "name:ara_x_preferred":[
        "Z\u0101jir"
    ],
    "name:ara_x_variant":[
        "\u0632\u0627\u062c\u0631"
    ],
    "name:eng_x_preferred":[
        "Zajir"
    ],
    "name:eng_x_variant":[
        "Al Ma\u1e11m\u0101r"
    ],
    "qs:name":"Z\u0101jir",
    "qs:photos_9r":0,
    "qs:photos_sr":0,
    "qs:pop_sr":"1",
    "wof:name":"Z\u0101jir",
    "wof:placetype":"locality",
    "wof:population":10
},
  "geometry": {"coordinates":[43.45283,16.31704],"type":"Point"}
}