{
  "type": "Feature",
  "properties": {
    "gn:admin1_code":"21.0",
    "gn:admin2_code":"1610.0",
    "gn:asciiname":"Bin Qumri",
    "gn:country_code":"YE",
    "gn:dem":2146,
    "gn:feature_class":"P",
    "gn:feature_code":"PPL",
    "gn:name":"Bin Qumr\u012b",
    "gn:population":0,
    "gn:timezone":"Asia/Aden",
    "iso:country":"YE",
    "name:ara_x_preferred":[
        "Bin Qumr\u012b"
    ],
    "name:ara_x_variant":[
        "\u0628\u0646 \u0642\u0645\u0631\u064a"
    ],
    "name:und_x_variant":[
        "Ma\u1e29all Bin Qumr\u012b"
    ],
    "wof:name":"Bin Qumri",
    "wof:placetype":"locality"
},
  "geometry": {"coordinates":[44.29303,16.77972],"type":"Point"}
}