{
  "type": "Feature",
  "properties": {
    "gn:admin1_code":"25.0",
    "gn:admin2_code":"1505.0",
    "gn:asciiname":"Al Mar`amah",
    "gn:country_code":"YE",
    "gn:dem":888,
    "gn:feature_class":"P",
    "gn:feature_code":"PPL",
    "gn:name":"Al Mar\u2018\u0101mah",
    "gn:population":0,
    "gn:timezone":"Asia/Aden",
    "iso:country":"YE",
    "name:und_x_variant":[
        "Al Mar\u2018\u0101mah"
    ],
    "wof:name":"Al Mar`amah",
    "wof:placetype":"locality"
},
  "geometry": {"coordinates":[43.71667,13.71667],"type":"Point"}
}