{
  "type": "Feature",
  "properties": {
    "gn:admin1_code":"25.0",
    "gn:admin2_code":"1504.0",
    "gn:asciiname":"Tawahin",
    "gn:country_code":"YE",
    "gn:dem":736,
    "gn:feature_class":"P",
    "gn:feature_code":"PPL",
    "gn:name":"\u0162aw\u0101\u1e29\u012bn",
    "gn:population":0,
    "gn:timezone":"Asia/Aden",
    "iso:country":"YE",
    "name:ara_x_preferred":[
        "\u0627\u0644\u0637\u0648\u0627\u062d\u064a\u0646"
    ],
    "name:und_x_variant":[
        "\u0162aw\u0101\u1e29\u012bn",
        "A\u0163 \u0162aw\u0101\u1e29\u012bn"
    ],
    "wof:name":"Tawahin",
    "wof:placetype":"locality"
},
  "geometry": {"coordinates":[43.77449,13.82616],"type":"Point"}
}