{
  "type": "Feature",
  "properties": {
    "gn:admin1_code":"22.0",
    "gn:admin2_code":"1730.0",
    "gn:asciiname":"Al Majnah",
    "gn:country_code":"YE",
    "gn:dem":731,
    "gn:feature_class":"P",
    "gn:feature_code":"PPL",
    "gn:name":"Al Majnah",
    "gn:population":0,
    "gn:timezone":"Asia/Aden",
    "iso:country":"YE",
    "name:ara_x_preferred":[
        "\u0627\u0644\u0645\u062c\u0646\u0629"
    ],
    "wof:name":"Al Majnah",
    "wof:placetype":"locality"
},
  "geometry": {"coordinates":[43.37675,16.33961],"type":"Point"}
}