{
  "type": "Feature",
  "properties": {
    "gn:admin1_code":"15.0",
    "gn:admin2_code":"2209.0",
    "gn:asciiname":"Jidayrah",
    "gn:country_code":"YE",
    "gn:dem":2120,
    "gn:feature_class":"P",
    "gn:feature_code":"PPL",
    "gn:name":"Jidayrah",
    "gn:population":0,
    "gn:timezone":"Asia/Aden",
    "iso:country":"YE",
    "name:ara_x_preferred":[
        "\u062c\u062f\u064a\u0631\u0629"
    ],
    "wof:name":"Jidayrah",
    "wof:placetype":"locality"
},
  "geometry": {"coordinates":[43.49268,16.78681],"type":"Point"}
}