{
  "type": "Feature",
  "properties": {
    "gn:country":"YE",
    "gn:fcode":"PPL",
    "gn:population":5,
    "iso:country":"YE",
    "name:ara_x_preferred":[
        "\u0642\u0631\u064a\u0629 \u0627\u0644\u0634\u0627\u0645\u0640\u064a"
    ],
    "name:eng_x_preferred":[
        "Qaryat Ash Shami"
    ],
    "name:eng_x_variant":[
        "Al Mansifah"
    ],
    "qs:name":"Qaryat ash Sh\u0101m\u012b",
    "qs:photos_9r":0,
    "qs:photos_sr":0,
    "qs:pop_sr":"1",
    "wof:name":"Qaryat ash Sh\u0101m\u012b",
    "wof:placetype":"locality",
    "wof:population":5
},
  "geometry": {"coordinates":[43.67975,16.19358],"type":"Point"}
}