{
  "type": "Feature",
  "properties": {
    "gn:country":"YE",
    "gn:fcode":"PPL",
    "gn:population":1,
    "iso:country":"YE",
    "name:ara_x_preferred":[
        "\u0627\u0644\u0645\u0644\u0627\u0642\u064a"
    ],
    "name:eng_x_preferred":[
        "Al Malaqi"
    ],
    "name:eng_x_variant":[
        "Al Minz\u0101f"
    ],
    "qs:name":"Al Mal\u0101q\u012b",
    "qs:photos_9r":0,
    "qs:photos_sr":0,
    "qs:pop_sr":"1",
    "wof:name":"Al Mal\u0101q\u012b",
    "wof:placetype":"locality",
    "wof:population":1
},
  "geometry": {"coordinates":[43.84251,13.25495],"type":"Point"}
}