{
  "type": "Feature",
  "properties": {
    "gn:admin1_code":"22.0",
    "gn:admin2_code":"1702.0",
    "gn:asciiname":"Bani al Juma`i",
    "gn:country_code":"YE",
    "gn:dem":144,
    "gn:feature_class":"P",
    "gn:feature_code":"PPL",
    "gn:name":"Ban\u012b al Jum\u0101\u2018\u012b",
    "gn:population":0,
    "gn:timezone":"Asia/Aden",
    "iso:country":"YE",
    "name:und_x_variant":[
        "Ban\u012b al Jum\u0101\u2018\u012b"
    ],
    "wof:name":"Bani al Juma`i",
    "wof:placetype":"locality"
},
  "geometry": {"coordinates":[43.17583,16.33527999999999],"type":"Point"}
}