{
  "type": "Feature",
  "properties": {
    "gn:admin1_code":"22.0",
    "gn:admin2_code":"1725.0",
    "gn:asciiname":"`Izzan",
    "gn:country_code":"YE",
    "gn:dem":891,
    "gn:feature_class":"P",
    "gn:feature_code":"PPL",
    "gn:name":"\u2018Izz\u0101n",
    "gn:population":0,
    "gn:timezone":"Asia/Aden",
    "iso:country":"YE",
    "name:ara_x_preferred":[
        "\u2018Izz\u0101n"
    ],
    "wof:name":"`Izzan",
    "wof:placetype":"locality"
},
  "geometry": {"coordinates":[43.5299,15.57807],"type":"Point"}
}