{
  "type": "Feature",
  "properties": {
    "gn:admin1_code":"11.0",
    "gn:admin2_code":"2007.0",
    "gn:asciiname":"Al Harf",
    "gn:country_code":"YE",
    "gn:dem":1261,
    "gn:feature_class":"P",
    "gn:feature_code":"PPL",
    "gn:name":"Al \u1e28arf",
    "gn:population":0,
    "gn:timezone":"Asia/Aden",
    "iso:country":"YE",
    "name:ara_x_preferred":[
        "\u0627\u0644\u062d\u0631\u0641"
    ],
    "name:und_x_variant":[
        "Al \u1e28arf"
    ],
    "wof:name":"Al Harf",
    "wof:placetype":"locality"
},
  "geometry": {"coordinates":[43.61307,14.2641],"type":"Point"}
}