{
  "type": "Feature",
  "properties": {
    "gn:admin1_code":"1.0",
    "gn:admin2_code":"1204.0",
    "gn:asciiname":"Am Qarn",
    "gn:country_code":"YE",
    "gn:dem":1070,
    "gn:feature_class":"P",
    "gn:feature_code":"PPL",
    "gn:name":"Am Qarn",
    "gn:population":0,
    "gn:timezone":"Asia/Aden",
    "iso:country":"YE",
    "wof:name":"Am Qarn",
    "wof:placetype":"locality"
},
  "geometry": {"coordinates":[45.79054,13.85995],"type":"Point"}
}