{
  "type": "Feature",
  "properties": {
    "gn:country":"YE",
    "gn:fcode":"PPL",
    "gn:pop":2,
    "iso:country":"YE",
    "name:ara_x_preferred":[
        "\u0633\u0646\u0627\u0645\u0629"
    ],
    "qs:name":"Sun\u0101mah",
    "qs:photos_9r":0,
    "qs:photos_sr":0,
    "qs:pop_sr":"1",
    "wof:name":"Sun\u0101mah",
    "wof:placetype":"locality",
    "wof:population":2
},
  "geometry": {"coordinates":[43.27195,17.4937],"type":"Point"}
}