{
  "type": "Feature",
  "properties": {
    "gn:admin1_code":"23.0",
    "gn:admin2_code":"1114.0",
    "gn:asciiname":"Khurat Bani `Atif",
    "gn:country_code":"YE",
    "gn:dem":1791,
    "gn:feature_class":"P",
    "gn:feature_code":"PPL",
    "gn:name":"Kh\u016brat Ban\u012b \u2018\u0100\u0163if",
    "gn:population":0,
    "gn:timezone":"Asia/Aden",
    "iso:country":"YE",
    "name:und_x_variant":[
        "Kh\u016brat Ban\u012b \u2018\u0100\u0163if"
    ],
    "wof:name":"Khurat Bani `Atif",
    "wof:placetype":"locality"
},
  "geometry": {"coordinates":[44.31418,13.78875],"type":"Point"}
}