{
  "type": "Feature",
  "properties": {
    "gn:admin1_code":"8.0",
    "gn:admin2_code":"1824.0",
    "gn:asciiname":"Dar Ghalib",
    "gn:country_code":"YE",
    "gn:dem":300,
    "gn:feature_class":"P",
    "gn:feature_code":"PPL",
    "gn:name":"D\u0101r Gh\u0101lib",
    "gn:population":0,
    "gn:timezone":"Asia/Aden",
    "iso:country":"YE",
    "name:ara_x_preferred":[
        "D\u0101r Gh\u0101lib"
    ],
    "wof:name":"Dar Ghalib",
    "wof:placetype":"locality"
},
  "geometry": {"coordinates":[43.4742,14.37181],"type":"Point"}
}