{
  "type": "Feature",
  "properties": {
    "gn:admin1_code":"14.0",
    "gn:admin2_code":"2607.0",
    "gn:asciiname":"Ar Ruq'",
    "gn:country_code":"YE",
    "gn:dem":1257,
    "gn:feature_class":"P",
    "gn:feature_code":"PPL",
    "gn:name":"Ar Ruq\u2018",
    "gn:population":0,
    "gn:timezone":"Asia/Aden",
    "iso:country":"YE",
    "name:ara_x_preferred":[
        "\u0627\u0644\u0631\u0642\u0639"
    ],
    "name:und_x_variant":[
        "Ar Ruq\u2018"
    ],
    "wof:name":"Ar Ruq'",
    "wof:placetype":"locality"
},
  "geometry": {"coordinates":[45.18337,15.19218],"type":"Point"}
}