{
  "type": "Feature",
  "properties": {
    "gn:admin1_code":"16.0",
    "gn:admin2_code":"2302.0",
    "gn:asciiname":"Bayt al Hajam",
    "gn:country_code":"YE",
    "gn:dem":2412,
    "gn:feature_class":"P",
    "gn:feature_code":"PPL",
    "gn:name":"Bayt al Haj\u0101m",
    "gn:population":0,
    "gn:timezone":"Asia/Aden",
    "iso:country":"YE",
    "name:und_x_variant":[
        "Bayt al Haj\u0101m"
    ],
    "wof:name":"Bayt al Hajam",
    "wof:placetype":"locality"
},
  "geometry": {"coordinates":[44.26382,15.74595],"type":"Point"}
}