{
  "type": "Feature",
  "properties": {
    "gn:country":"YE",
    "gn:fcode":"PPL",
    "gn:population":7,
    "iso:country":"YE",
    "name:ara_x_preferred":[
        "\u0627\u0644\u062d\u0646\u064a\u0629"
    ],
    "qs:name":"Al \u1e28unayyah",
    "qs:photos_9r":0,
    "qs:photos_sr":0,
    "qs:pop_sr":"1",
    "wof:name":"Al \u1e28unayyah",
    "wof:placetype":"locality",
    "wof:population":7
},
  "geometry": {"coordinates":[43.45181,16.31579],"type":"Point"}
}