{
  "type": "Feature",
  "properties": {
    "gn:admin1_code":"25.0",
    "gn:admin2_code":"1515.0",
    "gn:asciiname":"Al Qaryah al 'Ulya",
    "gn:country_code":"YE",
    "gn:dem":1354,
    "gn:feature_class":"P",
    "gn:feature_code":"PPL",
    "gn:name":"Al Qaryah al \u2018Uly\u0101",
    "gn:population":0,
    "gn:timezone":"Asia/Aden",
    "iso:country":"YE",
    "name:ara_x_preferred":[
        "\u0627\u0644\u0642\u0631\u064a\u0629 \u0627\u0644\u0639\u0644\u064a\u0627"
    ],
    "name:und_x_variant":[
        "Al Qaryah al \u2018Uly\u0101"
    ],
    "wof:name":"Al Qaryah al 'Ulya",
    "wof:placetype":"locality"
},
  "geometry": {"coordinates":[43.96422000000001,13.13163],"type":"Point"}
}