{
  "type": "Feature",
  "properties": {
    "gn:admin1_code":"18.0",
    "gn:admin2_code":"3007.0",
    "gn:asciiname":"Al `Asdaf",
    "gn:country_code":"YE",
    "gn:dem":1863,
    "gn:feature_class":"P",
    "gn:feature_code":"PPL",
    "gn:name":"Al \u2018Asdaf",
    "gn:population":0,
    "gn:timezone":"Asia/Aden",
    "iso:country":"YE",
    "name:und_x_variant":[
        "A\u015fd\u0101f",
        "Al \u2018Asdaf"
    ],
    "wof:name":"Al `Asdaf",
    "wof:placetype":"locality"
},
  "geometry": {"coordinates":[44.68333,13.71667],"type":"Point"}
}