{
  "type": "Feature",
  "properties": {
    "gn:admin1_code":"8.0",
    "gn:admin2_code":"1813.0",
    "gn:asciiname":"Kurzum",
    "gn:country_code":"YE",
    "gn:dem":126,
    "gn:feature_class":"P",
    "gn:feature_code":"PPL",
    "gn:name":"Kurzum",
    "gn:population":0,
    "gn:timezone":"Asia/Aden",
    "iso:country":"YE",
    "wof:name":"Kurzum",
    "wof:placetype":"locality"
},
  "geometry": {"coordinates":[43.33266,14.85228],"type":"Point"}
}