{
  "type": "Feature",
  "properties": {
    "gn:admin1_code":"23.0",
    "gn:admin2_code":"1114.0",
    "gn:asciiname":"Dhi `Asal",
    "gn:country_code":"YE",
    "gn:dem":1861,
    "gn:feature_class":"P",
    "gn:feature_code":"PPL",
    "gn:name":"Dh\u012b \u2018Asal",
    "gn:population":0,
    "gn:timezone":"Asia/Aden",
    "iso:country":"YE",
    "name:und_x_variant":[
        "Dh\u012b \u2018Asal"
    ],
    "wof:name":"Dhi `Asal",
    "wof:placetype":"locality"
},
  "geometry": {"coordinates":[44.28605,13.8405],"type":"Point"}
}