{
  "type": "Feature",
  "properties": {
    "gn:admin1_code":"14.0",
    "gn:admin2_code":"2603.0",
    "gn:asciiname":"Al Madid",
    "gn:country_code":"YE",
    "gn:dem":1212,
    "gn:feature_class":"P",
    "gn:feature_code":"PPL",
    "gn:name":"Al Mad\u012bd",
    "gn:population":0,
    "gn:timezone":"Asia/Aden",
    "iso:country":"YE",
    "wof:name":"Al Madid",
    "wof:placetype":"locality"
},
  "geometry": {"coordinates":[44.9625,15.65],"type":"Point"}
}