{
  "type": "Feature",
  "properties": {
    "gn:country":"YE",
    "gn:fcode":"PPL",
    "gn:pop":2,
    "iso:country":"YE",
    "name:ara_x_preferred":[
        "\u062f\u0631\u0628 \u0635\u0642\u0631"
    ],
    "name:eng_x_preferred":[
        "Darb Saqr"
    ],
    "name:eng_x_variant":[
        "D\u0101rat \u015eal\u0101\u1e29"
    ],
    "qs:name":"Darb \u015eaqr",
    "qs:photos_9r":0,
    "qs:photos_sr":0,
    "qs:pop_sr":"1",
    "wof:name":"Darb \u015eaqr",
    "wof:placetype":"locality",
    "wof:population":2
},
  "geometry": {"coordinates":[43.73212,16.09209],"type":"Point"}
}