{
  "type": "Feature",
  "properties": {
    "gn:admin1_code":"22.0",
    "gn:admin2_code":"1703.0",
    "gn:asciiname":"Al Mashayibah",
    "gn:country_code":"YE",
    "gn:dem":20,
    "gn:feature_class":"P",
    "gn:feature_code":"PPL",
    "gn:name":"Al Mash\u0101yibah",
    "gn:population":0,
    "gn:timezone":"Asia/Aden",
    "iso:country":"YE",
    "name:und_x_variant":[
        "Al Mash\u0101yibah"
    ],
    "wof:name":"Al Mashayibah",
    "wof:placetype":"locality"
},
  "geometry": {"coordinates":[42.86667,16.31667],"type":"Point"}
}