{
  "type": "Feature",
  "properties": {
    "gn:admin1_code":"18.0",
    "gn:admin2_code":"3002.0",
    "gn:asciiname":"Al Jidlah",
    "gn:country_code":"YE",
    "gn:dem":2242,
    "gn:feature_class":"P",
    "gn:feature_code":"PPL",
    "gn:name":"Al Jidlah",
    "gn:population":0,
    "gn:timezone":"Asia/Aden",
    "iso:country":"YE",
    "wof:name":"Al Jidlah",
    "wof:placetype":"locality"
},
  "geometry": {"coordinates":[44.77462,14.16848],"type":"Point"}
}