{
  "type": "Feature",
  "properties": {
    "gn:country":"YE",
    "gn:fcode":"PPL",
    "gn:pop":3,
    "iso:country":"YE",
    "name:ara_x_preferred":[
        "\u0632\u0628\u064a\u0628"
    ],
    "name:eng_x_preferred":[
        "Zabib"
    ],
    "name:eng_x_variant":[
        "N\u0101mah"
    ],
    "qs:name":"Zab\u012bb",
    "qs:photos_9r":0,
    "qs:photos_sr":0,
    "qs:pop_sr":"1",
    "wof:name":"Zab\u012bb",
    "wof:placetype":"locality",
    "wof:population":3
},
  "geometry": {"coordinates":[45.1635,14.90103],"type":"Point"}
}