{
  "type": "Feature",
  "properties": {
    "gn:admin1_code":"10.0",
    "gn:admin2_code":"2708.0",
    "gn:asciiname":"Bayt Hufayz",
    "gn:country_code":"YE",
    "gn:dem":1879,
    "gn:feature_class":"P",
    "gn:feature_code":"PPL",
    "gn:name":"Bayt \u1e28ufayz\u0327",
    "gn:population":0,
    "gn:timezone":"Asia/Aden",
    "iso:country":"YE",
    "name:und_x_variant":[
        "Bayt \u1e28ufayz\u0327"
    ],
    "wof:name":"Bayt Hufayz",
    "wof:placetype":"locality"
},
  "geometry": {"coordinates":[43.54178,15.45764],"type":"Point"}
}