{
  "type": "Feature",
  "properties": {
    "gn:admin1_code":"8.0",
    "gn:asciiname":"Qaryat `Isa",
    "gn:country_code":"YE",
    "gn:dem":5,
    "gn:feature_class":"P",
    "gn:feature_code":"PPL",
    "gn:name":"Qaryat \u2018\u012as\u00e1",
    "gn:population":0,
    "gn:timezone":"Asia/Aden",
    "iso:country":"YE",
    "name:und_x_variant":[
        "Ras Isa",
        "Qaryat \u2018\u012as\u00e1",
        "\u2018Is\u00e1"
    ],
    "wof:name":"Qaryat `Isa",
    "wof:placetype":"locality"
},
  "geometry": {"coordinates":[42.66246,15.18854],"type":"Point"}
}