{
  "type": "Feature",
  "properties": {
    "gn:admin1_code":"16.0",
    "gn:admin2_code":"2304.0",
    "gn:asciiname":"Hisn as Sa'id",
    "gn:country_code":"YE",
    "gn:dem":2379,
    "gn:feature_class":"P",
    "gn:feature_code":"PPL",
    "gn:name":"\u1e28i\u015fn as Sa\u2018\u012bd",
    "gn:population":0,
    "gn:timezone":"Asia/Aden",
    "iso:country":"YE",
    "name:ara_x_preferred":[
        "\u062d\u0635\u0646 \u0627\u0644\u0633\u0639\u064a\u062f"
    ],
    "name:und_x_variant":[
        "\u1e28i\u015fn as Sa\u2018\u012bd"
    ],
    "wof:name":"Hisn as Sa'id",
    "wof:placetype":"locality"
},
  "geometry": {"coordinates":[44.43074,15.52065],"type":"Point"}
}