{
  "type": "Feature",
  "properties": {
    "gn:admin1_code":"23.0",
    "gn:admin2_code":"1104.0",
    "gn:asciiname":"Bayt al Bana'",
    "gn:country_code":"YE",
    "gn:dem":2440,
    "gn:feature_class":"P",
    "gn:feature_code":"PPL",
    "gn:name":"Bayt al Ban\u0101\u2019",
    "gn:population":0,
    "gn:timezone":"Asia/Aden",
    "iso:country":"YE",
    "name:ara_x_preferred":[
        "\u0628\u064a\u062a \u0627\u0644\u0628\u0646\u0627\u0621"
    ],
    "name:und_x_variant":[
        "Bayt al Ban\u0101\u2019",
        "Bayt al Bana\u2019"
    ],
    "wof:name":"Bayt al Bana'",
    "wof:placetype":"locality"
},
  "geometry": {"coordinates":[44.41374,14.08884],"type":"Point"}
}