{
  "type": "Feature",
  "properties": {
    "gn:admin1_code":"24.0",
    "gn:admin2_code":"2513.0",
    "gn:asciiname":"Harahirah",
    "gn:country_code":"YE",
    "gn:dem":304,
    "gn:feature_class":"P",
    "gn:feature_code":"PPL",
    "gn:name":"Har\u0101hirah",
    "gn:population":0,
    "gn:timezone":"Asia/Aden",
    "iso:country":"YE",
    "name:und_x_variant":[
        "Har\u0101hirah"
    ],
    "wof:name":"Harahirah",
    "wof:placetype":"locality"
},
  "geometry": {"coordinates":[43.98891,12.95539],"type":"Point"}
}