{
  "type": "Feature",
  "properties": {
    "gn:admin1_code":"18.0",
    "gn:admin2_code":"3006.0",
    "gn:asciiname":"Shaghadir",
    "gn:country_code":"YE",
    "gn:dem":1271,
    "gn:feature_class":"P",
    "gn:feature_code":"PPL",
    "gn:name":"Shagh\u0101dir",
    "gn:population":0,
    "gn:timezone":"Asia/Aden",
    "iso:country":"YE",
    "name:und_x_variant":[
        "Shagadir",
        "Shagh\u0101dir",
        "Shegadi"
    ],
    "wof:name":"Shaghadir",
    "wof:placetype":"locality"
},
  "geometry": {"coordinates":[44.655,13.80317],"type":"Point"}
}