{
  "type": "Feature",
  "properties": {
    "gn:admin1_code":"18.0",
    "gn:admin2_code":"3008.0",
    "gn:asciiname":"Wajam",
    "gn:country_code":"YE",
    "gn:dem":1454,
    "gn:feature_class":"P",
    "gn:feature_code":"PPL",
    "gn:name":"Wajam",
    "gn:population":0,
    "gn:timezone":"Asia/Aden",
    "iso:country":"YE",
    "wof:name":"Wajam",
    "wof:placetype":"locality"
},
  "geometry": {"coordinates":[44.66,13.67806],"type":"Point"}
}