{
  "type": "Feature",
  "properties": {
    "gn:country":"YE",
    "gn:fcode":"PPL",
    "gn:population":5,
    "iso:country":"YE",
    "name:ara_x_preferred":[
        "\u0627\u0644 \u0645\u0628\u0627\u0631\u0643"
    ],
    "qs:name":"\u0100l Mub\u0101rrak",
    "qs:photos_9r":0,
    "qs:photos_sr":0,
    "qs:pop_sr":"1",
    "wof:name":"\u0100l Mub\u0101rrak",
    "wof:placetype":"locality",
    "wof:population":5
},
  "geometry": {"coordinates":[44.33426,17.03717],"type":"Point"}
}