{
  "type": "Feature",
  "properties": {
    "gn:admin1_code":"23.0",
    "gn:admin2_code":"1103.0",
    "gn:asciiname":"Al Ajlab",
    "gn:country_code":"YE",
    "gn:dem":2071,
    "gn:feature_class":"P",
    "gn:feature_code":"PPL",
    "gn:name":"Al Ajlab",
    "gn:population":0,
    "gn:timezone":"Asia/Aden",
    "iso:country":"YE",
    "name:ara_x_preferred":[
        "\u0627\u0644\u0623\u062c\u0644\u0628"
    ],
    "name:und_x_variant":[
        "Al Ajlub",
        "Ajlub",
        "Al Ajl\u016bb",
        "Al Ajlab"
    ],
    "wof:name":"Al Ajlab",
    "wof:placetype":"locality"
},
  "geometry": {"coordinates":[44.59591,14.20281],"type":"Point"}
}