{
  "type": "Feature",
  "properties": {
    "gn:admin1_code":"25.0",
    "gn:admin2_code":"1509.0",
    "gn:asciiname":"Qaryat Humarah",
    "gn:country_code":"YE",
    "gn:dem":846,
    "gn:feature_class":"P",
    "gn:feature_code":"PPL",
    "gn:name":"Qaryat \u1e28umarah",
    "gn:population":0,
    "gn:timezone":"Asia/Aden",
    "iso:country":"YE",
    "name:und_x_variant":[
        "Qaryat \u1e28umarah"
    ],
    "wof:name":"Qaryat Humarah",
    "wof:placetype":"locality"
},
  "geometry": {"coordinates":[43.83928,13.39781],"type":"Point"}
}