{
  "type": "Feature",
  "properties": {
    "gn:country":"YE",
    "gn:fcode":"PPL",
    "gn:pop":65,
    "iso:country":"YE",
    "name:ara_x_preferred":[
        "\u0628\u0646\u064a \u0639\u0631\u062c\u0627\u0646"
    ],
    "name:eng_x_preferred":[
        "Bani 'Urjan"
    ],
    "name:unk_x_variant":[
        "\u0628\u0646\u064a \u0639\u0631\u062c\u0627\u0646"
    ],
    "qs:name":"Ban\u012b \u2018Urj\u0101n",
    "qs:photos_9r":0,
    "qs:photos_sr":0,
    "qs:pop_sr":"1",
    "wof:name":"Ban\u012b \u2018Urj\u0101n",
    "wof:placetype":"locality",
    "wof:population":65
},
  "geometry": {"coordinates":[43.138,16.00132],"type":"Point"}
}