{
  "type": "Feature",
  "properties": {
    "gn:admin1_code":"15.0",
    "gn:admin2_code":"2212.0",
    "gn:asciiname":"Al Khandaqah",
    "gn:country_code":"YE",
    "gn:dem":1625,
    "gn:feature_class":"P",
    "gn:feature_code":"PPL",
    "gn:name":"Al Khandaqah",
    "gn:population":0,
    "gn:timezone":"Asia/Aden",
    "iso:country":"YE",
    "name:ara_x_preferred":[
        "\u0627\u0644\u062e\u0646\u062f\u0642\u0629"
    ],
    "wof:name":"Al Khandaqah",
    "wof:placetype":"locality"
},
  "geometry": {"coordinates":[43.96643,16.7044],"type":"Point"}
}