{
  "type": "Feature",
  "properties": {
    "gn:admin1_code":"19.0",
    "gn:admin2_code":"2901.0",
    "gn:asciiname":"Dawran",
    "gn:country_code":"YE",
    "gn:dem":1581,
    "gn:feature_class":"P",
    "gn:feature_code":"PPL",
    "gn:name":"Dawr\u0101n",
    "gn:population":0,
    "gn:timezone":"Asia/Aden",
    "iso:country":"YE",
    "name:ara_x_preferred":[
        "\u062f\u0648\u0631\u0627\u0646"
    ],
    "name:und_x_variant":[
        "Dawr\u0101n"
    ],
    "wof:name":"Dawran",
    "wof:placetype":"locality"
},
  "geometry": {"coordinates":[44.1088,16.25011],"type":"Point"}
}