{
  "type": "Feature",
  "properties": {
    "gn:country":"YE",
    "gn:fcode":"PPLF",
    "gn:pop":15,
    "iso:country":"YE",
    "name:ara_x_preferred":[
        "\u0645\u0633\u062d\u0648\u0628\u0629"
    ],
    "name:eng_x_preferred":[
        "MashUbah"
    ],
    "name:nno_x_preferred":[
        "Al Jillah"
    ],
    "qs:name":"Mas\u1e29\u016bbah",
    "qs:photos_9r":0,
    "qs:photos_sr":0,
    "qs:pop_sr":"1",
    "wof:name":"Mas\u1e29\u016bbah",
    "wof:placetype":"locality",
    "wof:population":15
},
  "geometry": {"coordinates":[43.44198,16.37383],"type":"Point"}
}