{
  "type": "Feature",
  "properties": {
    "gn:admin1_code":"23.0",
    "gn:admin2_code":"1102.0",
    "gn:asciiname":"Al Jabjab",
    "gn:country_code":"YE",
    "gn:dem":1620,
    "gn:feature_class":"P",
    "gn:feature_code":"PPL",
    "gn:name":"Al Jabjab",
    "gn:population":0,
    "gn:timezone":"Asia/Aden",
    "iso:country":"YE",
    "name:ara_x_preferred":[
        "\u0627\u0644\u062c\u0628\u062c\u0628"
    ],
    "wof:name":"Al Jabjab",
    "wof:placetype":"locality"
},
  "geometry": {"coordinates":[44.17067,14.28763],"type":"Point"}
}