{
  "type": "Feature",
  "properties": {
    "gn:admin1_code":"22.0",
    "gn:admin2_code":"1725.0",
    "gn:asciiname":"Al 'Aksh",
    "gn:country_code":"YE",
    "gn:dem":898,
    "gn:feature_class":"P",
    "gn:feature_code":"PPL",
    "gn:name":"Al \u2018Aksh",
    "gn:population":0,
    "gn:timezone":"Asia/Aden",
    "iso:country":"YE",
    "name:ara_x_preferred":[
        "\u0627\u0644\u0639\u0643\u0634"
    ],
    "name:und_x_variant":[
        "Al \u2018Aksh"
    ],
    "wof:name":"Al 'Aksh",
    "wof:placetype":"locality"
},
  "geometry": {"coordinates":[43.5398,15.58841],"type":"Point"}
}