{
  "type": "Feature",
  "properties": {
    "gn:admin1_code":"16.0",
    "gn:admin2_code":"2309.0",
    "gn:asciiname":"Al Malawi",
    "gn:country_code":"YE",
    "gn:dem":1425,
    "gn:feature_class":"P",
    "gn:feature_code":"PPL",
    "gn:name":"Al Mal\u0101w\u012b",
    "gn:population":0,
    "gn:timezone":"Asia/Aden",
    "iso:country":"YE",
    "name:und_x_variant":[
        "Al Mal\u0101w\u012b"
    ],
    "wof:name":"Al Malawi",
    "wof:placetype":"locality"
},
  "geometry": {"coordinates":[43.82873,15.12204],"type":"Point"}
}