{
  "type": "Feature",
  "properties": {
    "gn:admin1_code":"22.0",
    "gn:admin2_code":"1702.0",
    "gn:asciiname":"Al Hadid",
    "gn:country_code":"YE",
    "gn:dem":217,
    "gn:feature_class":"P",
    "gn:feature_code":"PPL",
    "gn:name":"Al \u1e28ad\u012bd",
    "gn:population":0,
    "gn:timezone":"Asia/Aden",
    "iso:country":"YE",
    "name:ara_x_preferred":[
        "\u0627\u0644\u062d\u062f\u064a\u062f"
    ],
    "name:und_x_variant":[
        "Al \u1e28ad\u012bd"
    ],
    "wof:name":"Al Hadid",
    "wof:placetype":"locality"
},
  "geometry": {"coordinates":[43.20023,16.60232],"type":"Point"}
}