{
  "type": "Feature",
  "properties": {
    "gn:country":"YE",
    "gn:fcode":"PPL",
    "gn:pop":23,
    "iso:country":"YE",
    "name:ara_x_preferred":[
        "\u062d\u0628\u0631"
    ],
    "name:eng_x_preferred":[
        "Habr"
    ],
    "qs:name":"\u1e28abr",
    "qs:photos_9r":0,
    "qs:photos_sr":0,
    "qs:pop_sr":"1",
    "wof:name":"\u1e28abr",
    "wof:placetype":"locality",
    "wof:population":23
},
  "geometry": {"coordinates":[43.50225,16.89588],"type":"Point"}
}