{
  "type": "Feature",
  "properties": {
    "gn:admin1_code":"26.0",
    "gn:admin2_code":"1308.0",
    "gn:asciiname":"Madhbah",
    "gn:country_code":"YE",
    "gn:dem":2301,
    "gn:feature_class":"P",
    "gn:feature_code":"PPL",
    "gn:name":"Madhba\u1e29",
    "gn:population":0,
    "gn:timezone":"Asia/Aden",
    "iso:country":"YE",
    "name:ara_x_preferred":[
        "\u0645\u0630\u0628\u062d"
    ],
    "name:und_x_variant":[
        "Madba\u1e29",
        "Madhba\u1e29"
    ],
    "wof:name":"Madhbah",
    "wof:placetype":"locality"
},
  "geometry": {"coordinates":[44.16559,15.37517],"type":"Point"}
}