{
  "type": "Feature",
  "properties": {
    "gn:gn_country":"YE",
    "gn:gn_fcode":"PPL",
    "gn:gn_pop":2,
    "gn:population":2,
    "iso:country":"YE",
    "name:ara_x_preferred":[
        "\u0642\u062f\u062d"
    ],
    "name:eng_x_preferred":[
        "Qadih"
    ],
    "qs_pg:aaroncc":"YE",
    "qs_pg:gn_country":"YE",
    "qs_pg:gn_fcode":"PPL",
    "qs_pg:gn_pop":2,
    "qs_pg:name":"Qadi\u1e29",
    "qs_pg:photos_9r":0,
    "qs_pg:photos_sr":0,
    "qs_pg:pop_sr":1,
    "qs_pg:qs_pg_placetype":"locality",
    "wof:name":"Qadi\u1e29",
    "wof:placetype":"locality",
    "wof:population":2
},
  "geometry": {"coordinates":[43.71675,16.09059],"type":"Point"}
}