{
  "type": "Feature",
  "properties": {
    "gn:admin1_code":"11.0",
    "gn:asciiname":"Rakhmat al `Ummal",
    "gn:country_code":"YE",
    "gn:dem":2121,
    "gn:feature_class":"P",
    "gn:feature_code":"PPL",
    "gn:name":"Rakhmat al \u2018Umm\u0101l",
    "gn:population":0,
    "gn:timezone":"Asia/Aden",
    "iso:country":"YE",
    "name:ara_x_preferred":[
        "\u0631\u062e\u0645\u0629 \u0627\u0644\u0639\u0645\u0627\u0644"
    ],
    "name:und_x_variant":[
        "Rakhmat al \u2018Umm\u0101l"
    ],
    "wof:name":"Rakhmat al `Ummal",
    "wof:placetype":"locality"
},
  "geometry": {"coordinates":[44.25712,14.36432],"type":"Point"}
}