{
  "type": "Feature",
  "properties": {
    "gn:admin1_code":"22.0",
    "gn:admin2_code":"1724.0",
    "gn:asciiname":"Al Mihwal",
    "gn:country_code":"YE",
    "gn:dem":299,
    "gn:feature_class":"P",
    "gn:feature_code":"PPL",
    "gn:name":"Al Mi\u1e29w\u0101l",
    "gn:population":0,
    "gn:timezone":"Asia/Aden",
    "iso:country":"YE",
    "name:ara_x_preferred":[
        "Al Mi\u1e29w\u0101l"
    ],
    "wof:name":"Al Mihwal",
    "wof:placetype":"locality"
},
  "geometry": {"coordinates":[43.2907,15.56455],"type":"Point"}
}