{
  "type": "Feature",
  "properties": {
    "gn:admin1_code":"8.0",
    "gn:admin2_code":"1814.0",
    "gn:asciiname":"Al 'Armah",
    "gn:country_code":"YE",
    "gn:dem":20,
    "gn:feature_class":"P",
    "gn:feature_code":"PPL",
    "gn:name":"Al \u2018Armah",
    "gn:population":0,
    "gn:timezone":"Asia/Aden",
    "iso:country":"YE",
    "name:ara_x_preferred":[
        "\u0627\u0644\u0639\u0631\u0645\u0629"
    ],
    "name:und_x_variant":[
        "Al \u2018Armah"
    ],
    "wof:name":"Al 'Armah",
    "wof:placetype":"locality"
},
  "geometry": {"coordinates":[43.06561,14.6239],"type":"Point"}
}