{
  "type": "Feature",
  "properties": {
    "gn:admin1_code":"11.0",
    "gn:admin2_code":"2007.0",
    "gn:asciiname":"Al Buhayriyah",
    "gn:country_code":"YE",
    "gn:dem":746,
    "gn:feature_class":"P",
    "gn:feature_code":"PPL",
    "gn:name":"Al Bu\u1e29ayr\u012byah",
    "gn:population":0,
    "gn:timezone":"Asia/Aden",
    "iso:country":"YE",
    "name:und_x_variant":[
        "Al Bu\u1e29ayr\u012byah"
    ],
    "wof:name":"Al Buhayriyah",
    "wof:placetype":"locality"
},
  "geometry": {"coordinates":[43.75384,14.14285],"type":"Point"}
}