{
  "type": "Feature",
  "properties": {
    "gn:admin1_code":"4.0",
    "gn:admin2_code":"1911.0",
    "gn:asciiname":"Khubayah",
    "gn:country_code":"YE",
    "gn:dem":608,
    "gn:feature_class":"P",
    "gn:feature_code":"PPL",
    "gn:name":"Khub\u0101yah",
    "gn:population":0,
    "gn:timezone":"Asia/Aden",
    "iso:country":"YE",
    "name:und_x_variant":[
        "Khub\u0101yah"
    ],
    "wof:name":"Khubayah",
    "wof:placetype":"locality"
},
  "geometry": {"coordinates":[49.04028,16.04111],"type":"Point"}
}