{
  "type": "Feature",
  "properties": {
    "gn:country":"YE",
    "gn:fcode":"PPL",
    "gn:population":2,
    "iso:country":"YE",
    "name:ara_x_preferred":[
        "\u0634\u0637 \u0645\u0639\u0648\u0636\u0629"
    ],
    "name:eng_x_preferred":[
        "Shatt Ma'wiuah"
    ],
    "name:eng_x_variant":[
        "W\u0101d\u012b al Mu\u2018ayn"
    ],
    "qs:name":"Sha\u0163\u0163 Ma\u2018wi\u1e11ah",
    "qs:photos_9r":0,
    "qs:photos_sr":0,
    "qs:pop_sr":"1",
    "wof:name":"Sha\u0163\u0163 Ma\u2018wi\u1e11ah",
    "wof:placetype":"locality",
    "wof:population":2
},
  "geometry": {"coordinates":[43.68019,13.12704],"type":"Point"}
}