{
  "type": "Feature",
  "properties": {
    "gn:country":"YE",
    "gn:fcode":"PPL",
    "gn:pop":1,
    "iso:country":"YE",
    "name:ara_x_preferred":[
        "\u0627\u0644\u0645\u0634\u0631\u062d\u0629"
    ],
    "name:eng_x_preferred":[
        "Al Mashrihah"
    ],
    "name:eng_x_variant":[
        "Alt Qulayl\u012b"
    ],
    "qs:name":"Al Mashri\u1e29ah",
    "qs:photos_9r":0,
    "qs:photos_sr":0,
    "qs:pop_sr":"1",
    "wof:name":"Al Mashri\u1e29ah",
    "wof:placetype":"locality",
    "wof:population":1
},
  "geometry": {"coordinates":[43.357,16.6713],"type":"Point"}
}