{
  "type": "Feature",
  "properties": {
    "gn:country":"YE",
    "gn:fcode":"PPL",
    "gn:population":7,
    "iso:country":"YE",
    "name:ara_x_preferred":[
        "\u0634\u0639\u0628 \u0627\u0644\u0628\u0646\u062f\u0642"
    ],
    "name:eng_x_preferred":[
        "Sha'b Al Bandaq"
    ],
    "name:eng_x_variant":[
        "\u0100l al Baqm\u0101\u2019"
    ],
    "qs:name":"Sha\u2018b al Bandaq",
    "qs:photos_9r":0,
    "qs:photos_sr":0,
    "qs:pop_sr":"1",
    "wof:name":"Sha\u2018b al Bandaq",
    "wof:placetype":"locality",
    "wof:population":7
},
  "geometry": {"coordinates":[43.3654,16.68323],"type":"Point"}
}