{
  "type": "Feature",
  "properties": {
    "gn:admin1_code":"19.0",
    "gn:admin2_code":"2901.0",
    "gn:asciiname":"Khashat Abu 'Alamah",
    "gn:country_code":"YE",
    "gn:dem":1667,
    "gn:feature_class":"P",
    "gn:feature_code":"PPL",
    "gn:name":"Khashat Ab\u016b \u2018Al\u0101mah",
    "gn:population":0,
    "gn:timezone":"Asia/Aden",
    "iso:country":"YE",
    "name:ara_x_preferred":[
        "\u062e\u0634\u0629 \u0623\u0628\u0648 \u0639\u0644\u0627\u0645\u0629"
    ],
    "name:und_x_variant":[
        "Khashat Ab\u016b \u2018Al\u0101mah"
    ],
    "wof:name":"Khashat Abu 'Alamah",
    "wof:placetype":"locality"
},
  "geometry": {"coordinates":[44.04736,16.50024],"type":"Point"}
}