{
  "type": "Feature",
  "properties": {
    "gn:admin1_code":"19.0",
    "gn:admin2_code":"2904.0",
    "gn:asciiname":"Qarn al Kharaf",
    "gn:country":"YE",
    "gn:country_code":"YE",
    "gn:dem":1298,
    "gn:fcode":"PPL",
    "gn:feature_class":"P",
    "gn:feature_code":"PPL",
    "gn:name":"Qarn al Kharaf",
    "gn:population":9,
    "gn:timezone":"Asia/Aden",
    "iso:country":"YE",
    "name:ara_x_preferred":[
        "\u0642\u0631\u0646 \u0627\u0644\u062e\u0631\u0641"
    ],
    "name:ara_x_variant":[
        "\u0627\u0644\u062e\u0631\u0641"
    ],
    "name:eng_x_preferred":[
        "Qarn Al Kharaf"
    ],
    "name:eng_x_variant":[
        "\u1e28ab\u012bl al \u1e28arash"
    ],
    "name:und_x_variant":[
        "Al Kharaf"
    ],
    "qs:name":"Qarn al Kharaf",
    "qs:photos_9r":0,
    "qs:photos_sr":0,
    "qs:pop_sr":"1",
    "wof:name":"Qarn al Kharaf",
    "wof:placetype":"locality",
    "wof:population":9
},
  "geometry": {"coordinates":[43.67325,16.343],"type":"Point"}
}