{
  "type": "Feature",
  "properties": {
    "gn:country":"YE",
    "gn:fcode":"PPL",
    "gn:pop":9,
    "iso:country":"YE",
    "name:ara_x_preferred":[
        "\u0642\u0631\u0646 \u0627\u0644\u062e\u0631\u0641"
    ],
    "name:ara_x_variant":[
        "\u0627\u0644\u062e\u0631\u0641"
    ],
    "name:eng_x_preferred":[
        "Qarn Al Kharaf"
    ],
    "name:unk_x_variant":[
        "Al Kharaf"
    ],
    "qs:name":"Qarn al Kharaf",
    "qs:photos_9r":0,
    "qs:photos_sr":0,
    "qs:pop_sr":"1",
    "wof:name":"Qarn al Kharaf",
    "wof:placetype":"locality",
    "wof:population":9
},
  "geometry": {"coordinates":[43.67325,16.343],"type":"Point"}
}