{
  "type": "Feature",
  "properties": {
    "gn:country":"YE",
    "gn:fcode":"PPL",
    "gn:pop":4,
    "iso:country":"YE",
    "name:ara_x_preferred":[
        "Ash Shir\u0101k"
    ],
    "name:ara_x_variant":[
        "\u0627\u0644\u0634\u0631\u0627\u0643"
    ],
    "name:eng_x_preferred":[
        "Ash Shirak"
    ],
    "name:eng_x_variant":[
        "Maghrabat al H\u0101d\u012b"
    ],
    "qs:name":"Ash Shir\u0101k",
    "qs:photos_9r":0,
    "qs:photos_sr":0,
    "qs:pop_sr":"1",
    "wof:name":"Ash Shir\u0101k",
    "wof:placetype":"locality",
    "wof:population":4
},
  "geometry": {"coordinates":[43.35441,16.29561],"type":"Point"}
}