{
  "type": "Feature",
  "properties": {
    "gn:admin1_code":"20.0",
    "gn:admin2_code":"1420.0",
    "gn:asciiname":"Ash Sharyah",
    "gn:country_code":"YE",
    "gn:dem":2038,
    "gn:feature_class":"P",
    "gn:feature_code":"PPL",
    "gn:name":"Ash Sharyah",
    "gn:population":0,
    "gn:timezone":"Asia/Aden",
    "iso:country":"YE",
    "name:ara_x_preferred":[
        "\u0627\u0644\u0634\u0631\u064a\u0629"
    ],
    "wof:name":"Ash Sharyah",
    "wof:placetype":"locality"
},
  "geometry": {"coordinates":[45.36698,14.37354],"type":"Point"}
}