{
  "type": "Feature",
  "properties": {
    "gn:country":"YE",
    "gn:fcode":"PPL",
    "gn:population":9,
    "iso:country":"YE",
    "name:ara_x_preferred":[
        "\u0648\u0627\u062f\u064a \u0627\u0644\u062d\u0645\u0640\u0631 \u0648 \u0627\u0644\u0645\u0631\u0648\u0629"
    ],
    "name:ara_x_variant":[
        "\u0648\u0627\u062f\u064a \u0627\u0644\u062d\u0645\u0631 \u0648 \u0627\u0644\u0645\u0631\u0648\u0629"
    ],
    "name:eng_x_preferred":[
        "Wadi Al Hamir Wa Al"
    ],
    "qs:name":"W\u0101d\u012b al \u1e28amir wa Al Marwah",
    "qs:photos_9r":0,
    "qs:photos_sr":0,
    "qs:pop_sr":"1",
    "wof:name":"W\u0101d\u012b al \u1e28amir wa Al Marwah",
    "wof:placetype":"locality",
    "wof:population":9
},
  "geometry": {"coordinates":[43.39599,16.18191],"type":"Point"}
}