{
  "type": "Feature",
  "properties": {
    "gn:country":"YE",
    "gn:fcode":"PPL",
    "gn:population":2,
    "iso:country":"YE",
    "name:ara_x_preferred":[
        "Rid\u0101\u1e29"
    ],
    "name:ara_x_variant":[
        "\u0631\u062f\u0627\u062d"
    ],
    "name:eng_x_preferred":[
        "Ridah"
    ],
    "name:eng_x_variant":[
        "Ar Ra\u015f\u012bd"
    ],
    "qs:name":"Rid\u0101\u1e29",
    "qs:photos_9r":0,
    "qs:photos_sr":0,
    "qs:pop_sr":"1",
    "wof:name":"Rid\u0101\u1e29",
    "wof:placetype":"locality",
    "wof:population":2
},
  "geometry": {"coordinates":[43.28969,16.77342],"type":"Point"}
}