{
  "type": "Feature",
  "properties": {
    "gn:admin1_code":"23.0",
    "gn:admin2_code":"1104.0",
    "gn:asciiname":"Dhawdan",
    "gn:country_code":"YE",
    "gn:dem":2879,
    "gn:feature_class":"P",
    "gn:feature_code":"PPL",
    "gn:name":"Dhawd\u0101n",
    "gn:population":0,
    "gn:timezone":"Asia/Aden",
    "iso:country":"YE",
    "name:ara_x_preferred":[
        "\u0630\u0648\u062f\u0627\u0646"
    ],
    "name:und_x_variant":[
        "Dhawd\u0101n"
    ],
    "wof:name":"Dhawdan",
    "wof:placetype":"locality"
},
  "geometry": {"coordinates":[44.47835,14.03787],"type":"Point"}
}