{
  "type": "Feature",
  "properties": {
    "gn:country":"YE",
    "gn:fcode":"PPL",
    "gn:pop":10,
    "iso:country":"YE",
    "name:ara_x_preferred":[
        "\u0627\u0644\u0633\u0628\u0627\u0639"
    ],
    "name:eng_x_preferred":[
        "As Saba'"
    ],
    "qs:name":"As Sab\u0101\u2018",
    "qs:photos_9r":0,
    "qs:photos_sr":0,
    "qs:pop_sr":"1",
    "wof:name":"As Sab\u0101\u2018",
    "wof:placetype":"locality",
    "wof:population":10
},
  "geometry": {"coordinates":[43.44021,16.19056],"type":"Point"}
}