{
  "type": "Feature",
  "properties": {
    "gn:admin1_code":"25.0",
    "gn:admin2_code":"1509.0",
    "gn:asciiname":"Midhafah",
    "gn:country_code":"YE",
    "gn:dem":1053,
    "gn:feature_class":"P",
    "gn:feature_code":"PPL",
    "gn:name":"Midh\u0101fah",
    "gn:population":0,
    "gn:timezone":"Asia/Aden",
    "iso:country":"YE",
    "name:und_x_variant":[
        "Midh\u0101fah"
    ],
    "wof:name":"Midhafah",
    "wof:placetype":"locality"
},
  "geometry": {"coordinates":[43.85391,13.4364],"type":"Point"}
}