{
  "type": "Feature",
  "properties": {
    "gn:admin1_code":"19.0",
    "gn:admin2_code":"2905.0",
    "gn:asciiname":"Al Jawar",
    "gn:country_code":"YE",
    "gn:dem":1866,
    "gn:feature_class":"P",
    "gn:feature_code":"PPL",
    "gn:name":"Al Jaw\u0101r",
    "gn:population":0,
    "gn:timezone":"Asia/Aden",
    "iso:country":"YE",
    "name:und_x_variant":[
        "Al Jaw\u0101r"
    ],
    "wof:name":"Al Jawar",
    "wof:placetype":"locality"
},
  "geometry": {"coordinates":[43.70505,16.23919],"type":"Point"}
}