{
  "type": "Feature",
  "properties": {
    "gn:admin1_code":"15.0",
    "gn:admin2_code":"2208.0",
    "gn:asciiname":"Hajar an Nub",
    "gn:country_code":"YE",
    "gn:dem":1937,
    "gn:feature_class":"P",
    "gn:feature_code":"PPL",
    "gn:name":"\u1e28ajar an N\u016bb",
    "gn:population":0,
    "gn:timezone":"Asia/Aden",
    "iso:country":"YE",
    "name:ara_x_preferred":[
        "\u062d\u062c\u0631 \u0627\u0644\u0646\u0648\u0628"
    ],
    "name:und_x_variant":[
        "\u1e28ajar an N\u016bb"
    ],
    "wof:name":"Hajar an Nub",
    "wof:placetype":"locality"
},
  "geometry": {"coordinates":[43.40099,16.79743],"type":"Point"}
}