{
  "type": "Feature",
  "properties": {
    "gn:admin1_code":"5.0",
    "gn:admin2_code":"2103.0",
    "gn:asciiname":"Al Mabda`ah",
    "gn:country_code":"YE",
    "gn:dem":1177,
    "gn:feature_class":"P",
    "gn:feature_code":"PPL",
    "gn:name":"Al Mabda\u2018ah",
    "gn:population":0,
    "gn:timezone":"Asia/Aden",
    "iso:country":"YE",
    "name:und_x_variant":[
        "Al Mabda\u2018ah"
    ],
    "wof:name":"Al Mabda`ah",
    "wof:placetype":"locality"
},
  "geometry": {"coordinates":[47.1176,14.95475],"type":"Point"}
}