{
  "type": "Feature",
  "properties": {
    "gn:admin1_code":"23.0",
    "gn:admin2_code":"1113.0",
    "gn:asciiname":"Al Hamadi",
    "gn:country_code":"YE",
    "gn:dem":3063,
    "gn:feature_class":"P",
    "gn:feature_code":"PPL",
    "gn:name":"Al \u1e28am\u0101d\u012b",
    "gn:population":0,
    "gn:timezone":"Asia/Aden",
    "iso:country":"YE",
    "name:ara_x_preferred":[
        "\u0627\u0644\u062d\u0645\u0627\u062f\u064a"
    ],
    "name:und_x_variant":[
        "Al \u1e28am\u0101d\u012b",
        "Al \u1e28amm\u0101d\u012b"
    ],
    "wof:name":"Al Hamadi",
    "wof:placetype":"locality"
},
  "geometry": {"coordinates":[44.2827,14.05844],"type":"Point"}
}