{
  "type": "Feature",
  "properties": {
    "gn:admin1_code":"11.0",
    "gn:admin2_code":"2012.0",
    "gn:asciiname":"Bayt ash Shi`b",
    "gn:country_code":"YE",
    "gn:dem":2088,
    "gn:feature_class":"P",
    "gn:feature_code":"PPL",
    "gn:name":"Bayt ash Shi\u2018b",
    "gn:population":0,
    "gn:timezone":"Asia/Aden",
    "iso:country":"YE",
    "name:und_x_variant":[
        "Bayt ash Shi\u2018b"
    ],
    "wof:name":"Bayt ash Shi`b",
    "wof:placetype":"locality"
},
  "geometry": {"coordinates":[44.11778,14.71147],"type":"Point"}
}