{
  "type": "Feature",
  "properties": {
    "gn:admin1_code":"19.0",
    "gn:admin2_code":"2920.0",
    "gn:asciiname":"Bayt Sa'ful",
    "gn:country_code":"YE",
    "gn:dem":2385,
    "gn:feature_class":"P",
    "gn:feature_code":"PPL",
    "gn:name":"Bayt Sa\u2018f\u016bl",
    "gn:population":0,
    "gn:timezone":"Asia/Aden",
    "iso:country":"YE",
    "name:ara_x_preferred":[
        "\u0628\u064a\u062a \u0633\u0639\u0641\u0648\u0644"
    ],
    "name:und_x_variant":[
        "Bayt Sa\u2018f\u016bl"
    ],
    "wof:name":"Bayt Sa'ful",
    "wof:placetype":"locality"
},
  "geometry": {"coordinates":[43.99006,16.08495],"type":"Point"}
}