{
  "type": "Feature",
  "properties": {
    "gn:admin1_code":"25.0",
    "gn:admin2_code":"1501.0",
    "gn:asciiname":"Hutrush",
    "gn:country_code":"YE",
    "gn:dem":1319,
    "gn:feature_class":"P",
    "gn:feature_code":"PPL",
    "gn:name":"\u1e28utr\u016bsh",
    "gn:population":0,
    "gn:timezone":"Asia/Aden",
    "iso:country":"YE",
    "name:ara_x_preferred":[
        "\u1e28utr\u016bsh"
    ],
    "wof:name":"Hutrush",
    "wof:placetype":"locality"
},
  "geometry": {"coordinates":[44.21467,13.66946],"type":"Point"}
}