{
  "type": "Feature",
  "properties": {
    "gn:country":"YE",
    "gn:fcode":"TRB",
    "gn:population":3,
    "iso:country":"YE",
    "name:ara_x_preferred":[
        "\u0628\u062f\u0648 \u0630\u064a \u0643\u062d\u0644"
    ],
    "qs:name":"Badw Dh\u012b Ka\u1e29al",
    "qs:photos_9r":0,
    "qs:photos_sr":0,
    "qs:pop_sr":"1",
    "wof:name":"Badw Dh\u012b Ka\u1e29al",
    "wof:placetype":"locality",
    "wof:population":3
},
  "geometry": {"coordinates":[43.80367,17.06544],"type":"Point"}
}