{
  "type": "Feature",
  "properties": {
    "gn:admin1_code":"8.0",
    "gn:admin2_code":"1801.0",
    "gn:asciiname":"Ar Rusfah",
    "gn:country_code":"YE",
    "gn:dem":113,
    "gn:feature_class":"P",
    "gn:feature_code":"PPL",
    "gn:name":"Ar Ru\u015ffah",
    "gn:population":0,
    "gn:timezone":"Asia/Aden",
    "iso:country":"YE",
    "name:und_x_variant":[
        "Rosfah",
        "Ar Ru\u015ffah",
        "Ra\u015ffah"
    ],
    "wof:name":"Ar Rusfah",
    "wof:placetype":"locality"
},
  "geometry": {"coordinates":[43.10775,15.69632],"type":"Point"}
}