{
  "type": "Feature",
  "properties": {
    "gn:admin1_code":"19.0",
    "gn:admin2_code":"2919.0",
    "gn:asciiname":"Al Jiraf al A'la",
    "gn:country_code":"YE",
    "gn:dem":2478,
    "gn:feature_class":"P",
    "gn:feature_code":"PPL",
    "gn:name":"Al Jir\u0101f al A\u2018l\u00e1",
    "gn:population":0,
    "gn:timezone":"Asia/Aden",
    "iso:country":"YE",
    "name:und_x_variant":[
        "Al Jir\u0101f al A\u2018l\u00e1",
        "Ahle Belluzein"
    ],
    "wof:name":"Al Jiraf al A'la",
    "wof:placetype":"locality"
},
  "geometry": {"coordinates":[43.9938,16.02422],"type":"Point"}
}