{
  "type": "Feature",
  "properties": {
    "gn:admin1_code":"10.0",
    "gn:admin2_code":"2707.0",
    "gn:asciiname":"Mahall ash Shaykh Isma`il",
    "gn:country_code":"YE",
    "gn:dem":409,
    "gn:feature_class":"P",
    "gn:feature_code":"PPL",
    "gn:name":"Ma\u1e29all ash Shaykh Ism\u0101\u2018\u012bl",
    "gn:population":0,
    "gn:timezone":"Asia/Aden",
    "iso:country":"YE",
    "name:und_x_variant":[
        "Ma\u1e29all ash Shaykh Ism\u0101\u2018\u012bl"
    ],
    "wof:name":"Mahall ash Shaykh Isma`il",
    "wof:placetype":"locality"
},
  "geometry": {"coordinates":[43.43129,15.14442],"type":"Point"}
}