{
  "type": "Feature",
  "properties": {
    "gn:country":"YE",
    "gn:fcode":"PPL",
    "gn:pop":37,
    "iso:country":"YE",
    "name:ara_x_preferred":[
        "\u0100l \u1e28urb\u0101n"
    ],
    "name:ara_x_variant":[
        "\u0627\u0644 \u062d\u0631\u0628\u0627\u0646"
    ],
    "name:eng_x_preferred":[
        "Al Hurban"
    ],
    "name:eng_x_variant":[
        "Kawlat \u015eal\u0101\u1e29"
    ],
    "qs:name":"\u0100l \u1e28urb\u0101n",
    "qs:photos_9r":0,
    "qs:photos_sr":0,
    "qs:pop_sr":"1",
    "wof:name":"\u0100l \u1e28urb\u0101n",
    "wof:placetype":"locality",
    "wof:population":37
},
  "geometry": {"coordinates":[43.77878,17.00552],"type":"Point"}
}