{
  "type": "Feature",
  "properties": {
    "gn:admin1_code":"25.0",
    "gn:admin2_code":"1517.0",
    "gn:asciiname":"Ar Ram al A`la",
    "gn:country_code":"YE",
    "gn:dem":1229,
    "gn:feature_class":"P",
    "gn:feature_code":"PPL",
    "gn:name":"Ar R\u0101m al A\u2018l\u00e1",
    "gn:population":0,
    "gn:timezone":"Asia/Aden",
    "iso:country":"YE",
    "name:und_x_variant":[
        "Ar R\u0101m al A\u2018l\u00e1"
    ],
    "wof:name":"Ar Ram al A`la",
    "wof:placetype":"locality"
},
  "geometry": {"coordinates":[44.27452,13.27055],"type":"Point"}
}