{
  "type": "Feature",
  "properties": {
    "gn:admin1_code":"23.0",
    "gn:admin2_code":"1115.0",
    "gn:asciiname":"Manzil `Ayqari",
    "gn:country_code":"YE",
    "gn:dem":2201,
    "gn:feature_class":"P",
    "gn:feature_code":"PPL",
    "gn:name":"Manzil \u2018Ayqar\u012b",
    "gn:population":0,
    "gn:timezone":"Asia/Aden",
    "iso:country":"YE",
    "name:und_x_variant":[
        "Manzil \u2018Ayqar\u012b"
    ],
    "wof:name":"Manzil `Ayqari",
    "wof:placetype":"locality"
},
  "geometry": {"coordinates":[44.21398,13.87945],"type":"Point"}
}