{
  "type": "Feature",
  "properties": {
    "gn:admin1_code":"25.0",
    "gn:admin2_code":"1508.0",
    "gn:asciiname":"Al Maqsab",
    "gn:country_code":"YE",
    "gn:dem":482,
    "gn:feature_class":"P",
    "gn:feature_code":"PPL",
    "gn:name":"Al Maq\u015f\u0101b",
    "gn:population":0,
    "gn:timezone":"Asia/Aden",
    "iso:country":"YE",
    "name:ara_x_preferred":[
        "\u0627\u0644\u0645\u0642\u0635\u0627\u0628"
    ],
    "name:und_x_variant":[
        "Al Maq\u015fab",
        "Al Maq\u015f\u0101b"
    ],
    "wof:name":"Al Maqsab",
    "wof:placetype":"locality"
},
  "geometry": {"coordinates":[43.7261,13.33233],"type":"Point"}
}