{
  "type": "Feature",
  "properties": {
    "gn:country":"YE",
    "gn:fcode":"PPL",
    "gn:pop":1,
    "iso:country":"YE",
    "name:ara_x_preferred":[
        "\u0632\u0648\u0631 \u062c\u0627\u0628\u0631"
    ],
    "name:eng_x_preferred":[
        "Zawr Jabir"
    ],
    "qs:name":"Zawr J\u0101bir",
    "qs:photos_9r":0,
    "qs:photos_sr":0,
    "qs:pop_sr":"1",
    "wof:name":"Zawr J\u0101bir",
    "wof:placetype":"locality",
    "wof:population":1
},
  "geometry": {"coordinates":[44.82208,16.84414],"type":"Point"}
}