{
  "type": "Feature",
  "properties": {
    "gn:admin1_code":"8.0",
    "gn:admin2_code":"1806.0",
    "gn:asciiname":"Dayr al Jubayli",
    "gn:country_code":"YE",
    "gn:dem":64,
    "gn:feature_class":"P",
    "gn:feature_code":"PPL",
    "gn:name":"Dayr al Jubayl\u012b",
    "gn:population":0,
    "gn:timezone":"Asia/Aden",
    "iso:country":"YE",
    "name:und_x_variant":[
        "Dayr al Jubayl\u012b"
    ],
    "wof:name":"Dayr al Jubayli",
    "wof:placetype":"locality"
},
  "geometry": {"coordinates":[43.03534000000001,15.3949],"type":"Point"}
}