{
  "type": "Feature",
  "properties": {
    "gn:admin1_code":"16.0",
    "gn:admin2_code":"2302.0",
    "gn:asciiname":"`Iyal Kithir",
    "gn:country_code":"YE",
    "gn:dem":2302,
    "gn:feature_class":"P",
    "gn:feature_code":"PPL",
    "gn:name":"\u2018Iy\u0101l Kith\u012br",
    "gn:population":0,
    "gn:timezone":"Asia/Aden",
    "iso:country":"YE",
    "name:ara_x_preferred":[
        "\u2018Iy\u0101l Kith\u012br"
    ],
    "wof:name":"`Iyal Kithir",
    "wof:placetype":"locality"
},
  "geometry": {"coordinates":[44.3412,15.83901],"type":"Point"}
}