{
  "type": "Feature",
  "properties": {
    "gn:admin1_code":"20.0",
    "gn:admin2_code":"1419.0",
    "gn:asciiname":"An Najd",
    "gn:country_code":"YE",
    "gn:dem":1878,
    "gn:feature_class":"P",
    "gn:feature_code":"PPL",
    "gn:name":"An Najd",
    "gn:population":0,
    "gn:timezone":"Asia/Aden",
    "iso:country":"YE",
    "name:ara_x_preferred":[
        "\u0639\u0646\u0627\u0642\u0629"
    ],
    "name:fas_x_preferred":[
        "\u0627\u0646 \u0646\u062c\u062f"
    ],
    "name:nno_x_preferred":[
        "An Najd"
    ],
    "name:und_x_variant":[
        "\u2018In\u0101fah"
    ],
    "wof:name":"An Najd",
    "wof:placetype":"locality"
},
  "geometry": {"coordinates":[45.10116,14.23103],"type":"Point"}
}