{
  "type": "Feature",
  "properties": {
    "gn:admin1_code":"14.0",
    "gn:admin2_code":"2606.0",
    "gn:asciiname":"Ad Dir'i",
    "gn:country_code":"YE",
    "gn:dem":1496,
    "gn:feature_class":"P",
    "gn:feature_code":"PPL",
    "gn:name":"Ad Dir\u2018\u012b",
    "gn:population":0,
    "gn:timezone":"Asia/Aden",
    "iso:country":"YE",
    "name:ara_x_preferred":[
        "\u0627\u0644\u062f\u0631\u0639\u064a"
    ],
    "name:und_x_variant":[
        "Ad Dir\u2018\u012b"
    ],
    "wof:name":"Ad Dir'i",
    "wof:placetype":"locality"
},
  "geometry": {"coordinates":[44.97684,15.47402],"type":"Point"}
}