{
  "type": "Feature",
  "properties": {
    "gn:admin1_code":"16.0",
    "gn:admin2_code":"2309.0",
    "gn:asciiname":"Al Husayn",
    "gn:country_code":"YE",
    "gn:dem":1513,
    "gn:feature_class":"P",
    "gn:feature_code":"PPL",
    "gn:name":"Al \u1e28u\u015fayn",
    "gn:population":0,
    "gn:timezone":"Asia/Aden",
    "iso:country":"YE",
    "name:und_x_variant":[
        "Al \u1e28u\u015fayn"
    ],
    "wof:name":"Al Husayn",
    "wof:placetype":"locality"
},
  "geometry": {"coordinates":[43.9182,15.01419],"type":"Point"}
}