{
  "type": "Feature",
  "properties": {
    "gn:admin1_code":"25.0",
    "gn:admin2_code":"1506.0",
    "gn:asciiname":"Al Bilayli",
    "gn:country_code":"YE",
    "gn:dem":13,
    "gn:feature_class":"P",
    "gn:feature_code":"PPL",
    "gn:name":"Al Bilayl\u012b",
    "gn:population":0,
    "gn:timezone":"Asia/Aden",
    "iso:country":"YE",
    "name:und_x_variant":[
        "Al Bilayl\u012b"
    ],
    "wof:name":"Al Bilayli",
    "wof:placetype":"locality"
},
  "geometry": {"coordinates":[43.27501,13.29622],"type":"Point"}
}