{
  "type": "Feature",
  "properties": {
    "gn:admin1_code":"16.0",
    "gn:admin2_code":"2308.0",
    "gn:asciiname":"Amrash",
    "gn:country_code":"YE",
    "gn:dem":2022,
    "gn:feature_class":"P",
    "gn:feature_code":"PPL",
    "gn:name":"Amrash",
    "gn:population":0,
    "gn:timezone":"Asia/Aden",
    "iso:country":"YE",
    "name:fas_x_preferred":[
        "\u0627\u0645\u0631\u0627\u0634"
    ],
    "name:nno_x_preferred":[
        "Amrash"
    ],
    "wof:name":"Amrash",
    "wof:placetype":"locality"
},
  "geometry": {"coordinates":[43.90622000000001,15.24567],"type":"Point"}
}