{
  "type": "Feature",
  "properties": {
    "gn:admin1_code":"8.0",
    "gn:admin2_code":"1812.0",
    "gn:asciiname":"Al Jumjumah",
    "gn:country_code":"YE",
    "gn:dem":1914,
    "gn:feature_class":"P",
    "gn:feature_code":"PPL",
    "gn:name":"Al Jumjumah",
    "gn:population":0,
    "gn:timezone":"Asia/Aden",
    "iso:country":"YE",
    "name:ara_x_preferred":[
        "\u0627\u0644\u062c\u0645\u062c\u0645\u0629"
    ],
    "wof:name":"Al Jumjumah",
    "wof:placetype":"locality"
},
  "geometry": {"coordinates":[43.49236,14.89331],"type":"Point"}
}