{
  "type": "Feature",
  "properties": {
    "gn:admin1_code":"20.0",
    "gn:admin2_code":"1407.0",
    "gn:asciiname":"Diban",
    "gn:country_code":"YE",
    "gn:dem":1933,
    "gn:feature_class":"P",
    "gn:feature_code":"PPL",
    "gn:name":"Dib\u0101n",
    "gn:population":0,
    "gn:timezone":"Asia/Aden",
    "iso:country":"YE",
    "name:ara_x_preferred":[
        "Dib\u0101n"
    ],
    "wof:name":"Diban",
    "wof:placetype":"locality"
},
  "geometry": {"coordinates":[45.33219,14.12158],"type":"Point"}
}