{
  "type": "Feature",
  "properties": {
    "gn:admin1_code":"25.0",
    "gn:admin2_code":"1521.0",
    "gn:asciiname":"Al Qurf",
    "gn:country_code":"YE",
    "gn:dem":1747,
    "gn:feature_class":"P",
    "gn:feature_code":"PPL",
    "gn:name":"Al Qurf",
    "gn:population":0,
    "gn:timezone":"Asia/Aden",
    "iso:country":"YE",
    "name:und_x_variant":[
        "Al Qirf"
    ],
    "wof:name":"Al Qurf",
    "wof:placetype":"locality"
},
  "geometry": {"coordinates":[44.0742,13.38135],"type":"Point"}
}