{
  "type": "Feature",
  "properties": {
    "gn:admin1_code":"15.0",
    "gn:admin2_code":"2201.0",
    "gn:asciiname":"Hijrat ar Rawabi",
    "gn:country_code":"YE",
    "gn:dem":2063,
    "gn:feature_class":"P",
    "gn:feature_code":"PPL",
    "gn:name":"Hijrat ar Raw\u0101b\u012b",
    "gn:population":0,
    "gn:timezone":"Asia/Aden",
    "iso:country":"YE",
    "name:und_x_variant":[
        "Hijrat ar Raw\u0101b\u012b"
    ],
    "wof:name":"Hijrat ar Rawabi",
    "wof:placetype":"locality"
},
  "geometry": {"coordinates":[43.45494,17.30742],"type":"Point"}
}