{
  "type": "Feature",
  "properties": {
    "gn:country":"YE",
    "gn:fcode":"PPL",
    "gn:pop":13,
    "iso:country":"YE",
    "name:ara_x_preferred":[
        "\u0648\u0627\u062f\u064a \u0627\u0644\u063a\u0645\u064a\u0631"
    ],
    "name:eng_x_preferred":[
        "Wadi Al Ghamir"
    ],
    "name:eng_x_variant":[
        "Bayt Qalam"
    ],
    "qs:name":"W\u0101d\u012b al Gham\u012br",
    "qs:photos_9r":0,
    "qs:photos_sr":0,
    "qs:pop_sr":"1",
    "wof:name":"W\u0101d\u012b al Gham\u012br",
    "wof:placetype":"locality",
    "wof:population":13
},
  "geometry": {"coordinates":[43.36068,16.80062],"type":"Point"}
}