{
  "type": "Feature",
  "properties": {
    "gn:admin1_code":"20.0",
    "gn:admin2_code":"1414.0",
    "gn:asciiname":"Al Milh",
    "gn:country_code":"YE",
    "gn:dem":1937,
    "gn:feature_class":"P",
    "gn:feature_code":"PPL",
    "gn:name":"Al Mil\u1e29",
    "gn:population":0,
    "gn:timezone":"Asia/Aden",
    "iso:country":"YE",
    "name:ara_x_preferred":[
        "\u0627\u0644\u0645\u0644\u062d"
    ],
    "name:und_x_variant":[
        "Al Mala\u1e29",
        "Al Mil\u1e29"
    ],
    "wof:name":"Al Milh",
    "wof:placetype":"locality"
},
  "geometry": {"coordinates":[44.88611,14.61069],"type":"Point"}
}