{
  "type": "Feature",
  "properties": {
    "gn:country":"YE",
    "gn:fcode":"PPL",
    "gn:pop":4,
    "iso:country":"YE",
    "name:ara_x_preferred":[
        "W\u0101si\u0163"
    ],
    "name:ara_x_variant":[
        "\u0648\u0627\u0633\u0637"
    ],
    "qs:name":"W\u0101si\u0163",
    "qs:photos_9r":0,
    "qs:photos_sr":0,
    "qs:pop_sr":"1",
    "wof:name":"W\u0101si\u0163",
    "wof:placetype":"locality",
    "wof:population":4
},
  "geometry": {"coordinates":[45.38698,14.21394],"type":"Point"}
}