{
  "type": "Feature",
  "properties": {
    "gn:admin1_code":"23.0",
    "gn:admin2_code":"1106.0",
    "gn:asciiname":"`Adanah",
    "gn:country_code":"YE",
    "gn:dem":2184,
    "gn:feature_class":"P",
    "gn:feature_code":"PPL",
    "gn:name":"\u2018Adanah",
    "gn:population":0,
    "gn:timezone":"Asia/Aden",
    "iso:country":"YE",
    "name:ara_x_preferred":[
        "\u0639\u062f\u0646\u0629"
    ],
    "name:und_x_variant":[
        "\u2018Adanah"
    ],
    "wof:name":"`Adanah",
    "wof:placetype":"locality"
},
  "geometry": {"coordinates":[44.43545,14.12256],"type":"Point"}
}