{
  "type": "Feature",
  "properties": {
    "gn:country":"YE",
    "gn:fcode":"PPL",
    "gn:population":1,
    "iso:country":"YE",
    "name:ara_x_preferred":[
        "\u0646\u064a\u062f \u0627\u0644\u0628\u064a\u0639\u0629"
    ],
    "name:eng_x_preferred":[
        "Nayd Al Bay'ah"
    ],
    "name:eng_x_variant":[
        "Al \u1e28u\u015fayr"
    ],
    "qs:name":"Nayd al Bay\u2018ah",
    "qs:photos_9r":0,
    "qs:photos_sr":0,
    "qs:pop_sr":"1",
    "wof:name":"Nayd al Bay\u2018ah",
    "wof:placetype":"locality",
    "wof:population":1
},
  "geometry": {"coordinates":[43.25462,17.11277],"type":"Point"}
}