{
  "type": "Feature",
  "properties": {
    "gn:country":"YE",
    "gn:fcode":"PPL",
    "gn:population":15,
    "iso:country":"YE",
    "name:ara_x_preferred":[
        "\u0622\u0644 \u0627\u0644\u0632\u0628\u064a\u0631\u064a"
    ],
    "name:eng_x_preferred":[
        "Al Zubayri"
    ],
    "name:eng_x_variant":[
        "Az Zarb al Jan\u016bb\u012b"
    ],
    "qs:name":"\u0100l Zubayr\u012b",
    "qs:photos_9r":0,
    "qs:photos_sr":0,
    "qs:pop_sr":"1",
    "wof:name":"\u0100l Zubayr\u012b",
    "wof:placetype":"locality",
    "wof:population":15
},
  "geometry": {"coordinates":[43.74958,16.75967],"type":"Point"}
}