{
  "type": "Feature",
  "properties": {
    "gn:admin1_code":"19.0",
    "gn:admin2_code":"2905.0",
    "gn:asciiname":"Bani `Awad",
    "gn:country_code":"YE",
    "gn:dem":1464,
    "gn:feature_class":"P",
    "gn:feature_code":"PPL",
    "gn:name":"Ban\u012b \u2018Aw\u0101\u1e11",
    "gn:population":0,
    "gn:timezone":"Asia/Aden",
    "iso:country":"YE",
    "name:und_x_variant":[
        "Ban\u012b \u2018Aw\u0101\u1e11"
    ],
    "wof:name":"Bani `Awad",
    "wof:placetype":"locality"
},
  "geometry": {"coordinates":[43.65039,16.11407],"type":"Point"}
}