{
  "type": "Feature",
  "properties": {
    "gn:admin1_code":"25.0",
    "gn:admin2_code":"1504.0",
    "gn:asciiname":"Muqaylid",
    "gn:country_code":"YE",
    "gn:dem":1364,
    "gn:feature_class":"P",
    "gn:feature_code":"PPL",
    "gn:name":"Muqaylid",
    "gn:population":0,
    "gn:timezone":"Asia/Aden",
    "iso:country":"YE",
    "name:ara_x_preferred":[
        "\u0627\u0644\u0645\u0642\u064a\u0644\u062f"
    ],
    "name:und_x_variant":[
        "Al Muqaylid"
    ],
    "wof:name":"Muqaylid",
    "wof:placetype":"locality"
},
  "geometry": {"coordinates":[43.80793,13.749],"type":"Point"}
}