{
  "type": "Feature",
  "properties": {
    "gn:admin1_code":"22.0",
    "gn:admin2_code":"1724.0",
    "gn:asciiname":"Al Hadabah",
    "gn:country_code":"YE",
    "gn:dem":253,
    "gn:feature_class":"P",
    "gn:feature_code":"PPL",
    "gn:name":"Al \u1e28adabah",
    "gn:population":0,
    "gn:timezone":"Asia/Aden",
    "iso:country":"YE",
    "name:und_x_variant":[
        "Al \u1e28adabah"
    ],
    "wof:name":"Al Hadabah",
    "wof:placetype":"locality"
},
  "geometry": {"coordinates":[43.31248,15.62517],"type":"Point"}
}