{
  "type": "Feature",
  "properties": {
    "gn:admin1_code":"8.0",
    "gn:admin2_code":"1809.0",
    "gn:asciiname":"Muhammad Hashim",
    "gn:country_code":"YE",
    "gn:dem":82,
    "gn:feature_class":"P",
    "gn:feature_code":"PPL",
    "gn:name":"Mu\u1e29ammad H\u0101shim",
    "gn:population":0,
    "gn:timezone":"Asia/Aden",
    "iso:country":"YE",
    "name:ara_x_preferred":[
        "\u0645\u062d\u0645\u062f \u0647\u0627\u0634\u0645"
    ],
    "name:und_x_variant":[
        "Mu\u1e29ammad H\u0101shim"
    ],
    "wof:name":"Muhammad Hashim",
    "wof:placetype":"locality"
},
  "geometry": {"coordinates":[43.09417,15.19706],"type":"Point"}
}