{
  "type": "Feature",
  "properties": {
    "gn:admin1_code":"24.0",
    "gn:admin2_code":"2510.0",
    "gn:asciiname":"Al Qayfi",
    "gn:country_code":"YE",
    "gn:dem":520,
    "gn:feature_class":"P",
    "gn:feature_code":"PPL",
    "gn:name":"Al Qayf\u012b",
    "gn:population":0,
    "gn:timezone":"Asia/Aden",
    "iso:country":"YE",
    "name:und_x_variant":[
        "Al Qayf\u012b"
    ],
    "wof:name":"Al Qayfi",
    "wof:placetype":"locality"
},
  "geometry": {"coordinates":[44.58333,13.28472],"type":"Point"}
}