{
  "type": "Feature",
  "properties": {
    "gn:country":"YE",
    "gn:fcode":"PPLX",
    "gn:population":10,
    "iso:country":"YE",
    "name:ara_x_preferred":[
        "\u0627\u0644\u0642\u0632\u0639\u0629"
    ],
    "qs:name":"Al Qaz\u2018ah",
    "qs:photos_9r":0,
    "qs:photos_sr":0,
    "qs:pop_sr":"1",
    "wof:name":"Al Qaz\u2018ah",
    "wof:placetype":"neighbourhood",
    "wof:population":10
},
  "geometry": {"coordinates":[43.67965,16.13926],"type":"Point"}
}