{
  "type": "Feature",
  "properties": {
    "gn:admin1_code":"16.0",
    "gn:admin2_code":"2304.0",
    "gn:asciiname":"Bayt as Siraji",
    "gn:country_code":"YE",
    "gn:dem":2288,
    "gn:feature_class":"P",
    "gn:feature_code":"PPL",
    "gn:name":"Bayt as Sir\u0101j\u012b",
    "gn:population":0,
    "gn:timezone":"Asia/Aden",
    "iso:country":"YE",
    "name:und_x_variant":[
        "Bayt as Sir\u0101j\u012b"
    ],
    "wof:name":"Bayt as Siraji",
    "wof:placetype":"locality"
},
  "geometry": {"coordinates":[44.39545,15.49857],"type":"Point"}
}