{
  "type": "Feature",
  "properties": {
    "gn:admin1_code":"20.0",
    "gn:admin2_code":"1418.0",
    "gn:asciiname":"An Nawbah",
    "gn:country_code":"YE",
    "gn:dem":2745,
    "gn:feature_class":"P",
    "gn:feature_code":"PPL",
    "gn:name":"An Nawbah",
    "gn:population":0,
    "gn:timezone":"Asia/Aden",
    "iso:country":"YE",
    "wof:name":"An Nawbah",
    "wof:placetype":"locality"
},
  "geometry": {"coordinates":[44.7781,14.23763],"type":"Point"}
}