{
  "type": "Feature",
  "properties": {
    "gn:country":"YE",
    "gn:fcode":"PPL",
    "gn:population":1,
    "iso:country":"YE",
    "name:ara_x_preferred":[
        "\u0627\u0644\u0637\u0648\u0627\u0644"
    ],
    "name:eng_x_preferred":[
        "At Tawal"
    ],
    "name:eng_x_variant":[
        "Al Qu\u0163ayf"
    ],
    "qs:name":"A\u0163 \u0162aw\u0101l",
    "qs:photos_9r":0,
    "qs:photos_sr":0,
    "qs:pop_sr":"1",
    "wof:name":"A\u0163 \u0162aw\u0101l",
    "wof:placetype":"locality",
    "wof:population":1
},
  "geometry": {"coordinates":[43.85232,13.40316],"type":"Point"}
}