{
  "type": "Feature",
  "properties": {
    "gn:country":"YE",
    "gn:fcode":"PPL",
    "gn:population":20,
    "iso:country":"YE",
    "name:ara_x_preferred":[
        "\u0627\u0644\u0646\u0645\u0634\u0649"
    ],
    "name:eng_x_preferred":[
        "An Namsha"
    ],
    "name:vie_x_preferred":[
        "Kuhlan Affar"
    ],
    "qs:name":"An Namsh\u00e1",
    "qs:photos_9r":0,
    "qs:photos_sr":0,
    "qs:pop_sr":"1",
    "wof:name":"An Namsh\u00e1",
    "wof:placetype":"locality",
    "wof:population":20
},
  "geometry": {"coordinates":[45.24699,14.26809],"type":"Point"}
}