{
  "type": "Feature",
  "properties": {
    "gn:admin1_code":"19.0",
    "gn:admin2_code":"2910.0",
    "gn:asciiname":"Bayt al Jirbah",
    "gn:country_code":"YE",
    "gn:dem":2235,
    "gn:feature_class":"P",
    "gn:feature_code":"PPL",
    "gn:name":"Bayt al Jirbah",
    "gn:population":0,
    "gn:timezone":"Asia/Aden",
    "iso:country":"YE",
    "wof:name":"Bayt al Jirbah",
    "wof:placetype":"locality"
},
  "geometry": {"coordinates":[44.08719,15.81759],"type":"Point"}
}