{
  "type": "Feature",
  "properties": {
    "gn:admin1_code":"18.0",
    "gn:admin2_code":"3006.0",
    "gn:asciiname":"Ash Shi`b",
    "gn:country_code":"YE",
    "gn:dem":1594,
    "gn:feature_class":"P",
    "gn:feature_code":"PPL",
    "gn:name":"Ash Shi\u2018b",
    "gn:population":0,
    "gn:timezone":"Asia/Aden",
    "iso:country":"YE",
    "name:ara_x_preferred":[
        "Ash Shi\u2018b"
    ],
    "name:nno_x_preferred":[
        "Ash Shi`b"
    ],
    "name:und_x_variant":[
        "Sha\u2019ab"
    ],
    "wof:name":"Ash Shi`b",
    "wof:placetype":"locality"
},
  "geometry": {"coordinates":[44.71001,13.76365],"type":"Point"}
}