{
  "type": "Feature",
  "properties": {
    "gn:country":"YE",
    "gn:fcode":"OCH",
    "gn:population":6,
    "iso:country":"YE",
    "name:ara_x_preferred":[
        "\u0622\u0644 \u0648\u0647\u0627\u0633"
    ],
    "qs:name":"\u0100l Wah\u0101s",
    "qs:photos_9r":0,
    "qs:photos_sr":0,
    "qs:pop_sr":"1",
    "wof:name":"\u0100l Wah\u0101s",
    "wof:placetype":"locality",
    "wof:population":6
},
  "geometry": {"coordinates":[45.01695,16.98114],"type":"Point"}
}