{
  "type": "Feature",
  "properties": {
    "gn:admin1_code":"4.0",
    "gn:asciiname":"Al Jawal",
    "gn:country_code":"YE",
    "gn:dem":1250,
    "gn:feature_class":"P",
    "gn:feature_code":"PPL",
    "gn:name":"Al Jawal",
    "gn:population":0,
    "gn:timezone":"Asia/Aden",
    "iso:country":"YE",
    "name:ara_x_preferred":[
        "\u0627\u0644\u062c\u0648\u0644"
    ],
    "wof:name":"Al Jawal",
    "wof:placetype":"locality"
},
  "geometry": {"coordinates":[47.77327,16.08266],"type":"Point"}
}