{
  "type": "Feature",
  "properties": {
    "gn:admin1_code":"4.0",
    "gn:admin2_code":"1911.0",
    "gn:asciiname":"Rudayh",
    "gn:cc2":"YE",
    "gn:country_code":"YE",
    "gn:dem":647,
    "gn:feature_class":"P",
    "gn:feature_code":"PPL",
    "gn:name":"Ru\u1e11ay\u1e29",
    "gn:population":0,
    "gn:timezone":"Asia/Aden",
    "iso:country":"YE",
    "name:und_x_variant":[
        "Rudaih",
        "Ru\u1e11ay\u1e29"
    ],
    "wof:name":"Rudayh",
    "wof:placetype":"locality"
},
  "geometry": {"coordinates":[49.00333,15.89139],"type":"Point"}
}