{
  "type": "Feature",
  "properties": {
    "gn:admin1_code":"22.0",
    "gn:admin2_code":"1727.0",
    "gn:asciiname":"Adh Dhunub",
    "gn:country_code":"YE",
    "gn:dem":936,
    "gn:feature_class":"P",
    "gn:feature_code":"PPL",
    "gn:name":"Adh Dhun\u016bb",
    "gn:population":0,
    "gn:timezone":"Asia/Aden",
    "iso:country":"YE",
    "name:ara_x_preferred":[
        "\u0627\u0644\u0630\u0646\u0648\u0628"
    ],
    "name:und_x_variant":[
        "Adh Dhun\u016bb"
    ],
    "wof:name":"Adh Dhunub",
    "wof:placetype":"locality"
},
  "geometry": {"coordinates":[43.61825,15.54005],"type":"Point"}
}