{
  "type": "Feature",
  "properties": {
    "gn:country":"YE",
    "gn:fcode":"PPL",
    "gn:pop":11,
    "iso:country":"YE",
    "name:ara_x_preferred":[
        "\u062d\u062f\u0628\u0629 \u0636\u062e\u0627\u0631"
    ],
    "name:eng_x_preferred":[
        "Hadibat Dukhar"
    ],
    "qs:name":"\u1e28adibat \u1e10ukh\u0101r",
    "qs:photos_9r":0,
    "qs:photos_sr":0,
    "qs:pop_sr":"1",
    "wof:name":"\u1e28adibat \u1e10ukh\u0101r",
    "wof:placetype":"locality",
    "wof:population":11
},
  "geometry": {"coordinates":[43.74274,16.30384],"type":"Point"}
}