{
  "type": "Feature",
  "properties": {
    "gn:admin1_code":"23.0",
    "gn:admin2_code":"1101.0",
    "gn:asciiname":"Sha'b at Tamari",
    "gn:country_code":"YE",
    "gn:dem":1184,
    "gn:feature_class":"P",
    "gn:feature_code":"PPL",
    "gn:name":"Sha\u2018b at Tam\u0101r\u012b",
    "gn:population":0,
    "gn:timezone":"Asia/Aden",
    "iso:country":"YE",
    "name:ara_x_preferred":[
        "\u0634\u0639\u0628 \u0627\u0644\u062a\u0645\u0627\u0631\u064a"
    ],
    "name:und_x_variant":[
        "Sha\u2018b at Tam\u0101r\u012b"
    ],
    "wof:name":"Sha'b at Tamari",
    "wof:placetype":"locality"
},
  "geometry": {"coordinates":[44.04621,14.25036],"type":"Point"}
}