{
  "type": "Feature",
  "properties": {
    "gn:admin1_code":"24.0",
    "gn:admin2_code":"2513.0",
    "gn:asciiname":"Wali Jaylan",
    "gn:country_code":"YE",
    "gn:dem":232,
    "gn:feature_class":"P",
    "gn:feature_code":"PPL",
    "gn:name":"W\u0101l\u012b Jayl\u0101n",
    "gn:population":0,
    "gn:timezone":"Asia/Aden",
    "iso:country":"YE",
    "name:und_x_variant":[
        "Wali Jelan",
        "W\u0101l\u012b Jayl\u0101n"
    ],
    "wof:name":"Wali Jaylan",
    "wof:placetype":"locality"
},
  "geometry": {"coordinates":[44.06667,12.86667],"type":"Point"}
}