{
  "type": "Feature",
  "properties": {
    "gn:admin1_code":"18.0",
    "gn:admin2_code":"3009.0",
    "gn:asciiname":"Sardud",
    "gn:country_code":"YE",
    "gn:dem":1884,
    "gn:feature_class":"P",
    "gn:feature_code":"PPL",
    "gn:name":"Sard\u016bd",
    "gn:population":0,
    "gn:timezone":"Asia/Aden",
    "iso:country":"YE",
    "name:und_x_variant":[
        "Sard\u016bd"
    ],
    "wof:name":"Sardud",
    "wof:placetype":"locality"
},
  "geometry": {"coordinates":[44.41557,13.78642],"type":"Point"}
}