{
  "type": "Feature",
  "properties": {
    "gn:country":"YE",
    "gn:fcode":"PPL",
    "gn:pop":3,
    "iso:country":"YE",
    "name:ara_x_preferred":[
        "\u0630\u0631\u0627\u0639 \u0645\u0631\u0648\u0627\u0646"
    ],
    "name:eng_x_preferred":[
        "Dhira Marwan"
    ],
    "qs:name":"Dhir\u0101\u2019 Marw\u0101n",
    "qs:photos_9r":0,
    "qs:photos_sr":0,
    "qs:pop_sr":"1",
    "wof:name":"Dhir\u0101\u2019 Marw\u0101n",
    "wof:placetype":"locality",
    "wof:population":3
},
  "geometry": {"coordinates":[45.37038,14.62779],"type":"Point"}
}