{
  "type": "Feature",
  "properties": {
    "gn:admin1_code":"20.0",
    "gn:admin2_code":"1416.0",
    "gn:asciiname":"Al Maghrabah",
    "gn:country_code":"YE",
    "gn:dem":2190,
    "gn:feature_class":"P",
    "gn:feature_code":"PPL",
    "gn:name":"Al Maghrabah",
    "gn:population":0,
    "gn:timezone":"Asia/Aden",
    "iso:country":"YE",
    "name:ara_x_preferred":[
        "\u0627\u0644\u0645\u063a\u0631\u0628\u0629"
    ],
    "wof:name":"Al Maghrabah",
    "wof:placetype":"locality"
},
  "geometry": {"coordinates":[44.78751,14.39541],"type":"Point"}
}