{
  "type": "Feature",
  "properties": {
    "gn:country":"YE",
    "gn:fcode":"PPL",
    "gn:population":2,
    "iso:country":"YE",
    "name:ara_x_preferred":[
        "\u062d\u0628\u064a\u0644 \u0627\u0644\u0648\u0627\u0633\u0637"
    ],
    "name:eng_x_preferred":[
        "Habil Al Wasit"
    ],
    "name:eng_x_variant":[
        "Sha\u2018b M\u0101\u0163ir"
    ],
    "qs_pg:aaroncc":"YE",
    "qs_pg:gn_country":"YE",
    "qs_pg:gn_fcode":"PPL",
    "qs_pg:gn_pop":2,
    "qs_pg:name":"\u1e28ab\u012bl al W\u0101si\u0163",
    "qs_pg:photos_9r":0,
    "qs_pg:photos_sr":0,
    "qs_pg:pop_sr":1,
    "qs_pg:qs_pg_placetype":"locality",
    "wof:name":"\u1e28ab\u012bl al W\u0101si\u0163",
    "wof:placetype":"locality",
    "wof:population":2
},
  "geometry": {"coordinates":[43.26522,17.10862],"type":"Point"}
}