{
  "type": "Feature",
  "properties": {
    "gn:country":"YE",
    "gn:fcode":"PPL",
    "gn:population":3,
    "iso:country":"YE",
    "name:ara_x_preferred":[
        "\u0639\u0643\u0627\u0648\u0644"
    ],
    "name:eng_x_preferred":[
        "Akawal"
    ],
    "name:eng_x_variant":[
        "Al \u2018Aw\u0101j\u012b",
        "'Akawal"
    ],
    "qs:name":"\u2018Ak\u0101wal",
    "qs:photos_9r":0,
    "qs:photos_sr":0,
    "qs:pop_sr":"1",
    "wof:name":"\u2018Ak\u0101wal",
    "wof:placetype":"locality",
    "wof:population":3
},
  "geometry": {"coordinates":[43.2524,17.12264],"type":"Point"}
}