{
  "type": "Feature",
  "properties": {
    "gn:admin1_code":"15.0",
    "gn:admin2_code":"2210.0",
    "gn:asciiname":"Nayd al Wila`",
    "gn:country_code":"YE",
    "gn:dem":1561,
    "gn:feature_class":"P",
    "gn:feature_code":"PPL",
    "gn:name":"Nayd al Wil\u0101\u2018",
    "gn:population":0,
    "gn:timezone":"Asia/Aden",
    "iso:country":"YE",
    "name:ara_x_preferred":[
        "\u0646\u064a\u062f \u0627\u0644\u0648\u0644\u0627\u0639"
    ],
    "name:und_x_variant":[
        "Nayd al Wil\u0101\u2018"
    ],
    "wof:name":"Nayd al Wila`",
    "wof:placetype":"locality"
},
  "geometry": {"coordinates":[43.33166,17.19349],"type":"Point"}
}