{
  "type": "Feature",
  "properties": {
    "gn:admin1_code":"11.0",
    "gn:admin2_code":"2007.0",
    "gn:asciiname":"As Subayh",
    "gn:country_code":"YE",
    "gn:dem":1360,
    "gn:feature_class":"P",
    "gn:feature_code":"PPL",
    "gn:name":"A\u015f \u015eubay\u1e29",
    "gn:population":0,
    "gn:timezone":"Asia/Aden",
    "iso:country":"YE",
    "name:ara_x_preferred":[
        "\u0627\u0644\u0635\u0628\u064a\u062d"
    ],
    "name:und_x_variant":[
        "A\u015f \u015eab\u012b\u1e29",
        "A\u015f \u015eubay\u1e29"
    ],
    "wof:name":"As Subayh",
    "wof:placetype":"locality"
},
  "geometry": {"coordinates":[43.57948,14.27302],"type":"Point"}
}