{
  "type": "Feature",
  "properties": {
    "gn:admin1_code":"14.0",
    "gn:admin2_code":"2606.0",
    "gn:asciiname":"Al an Nawasirah",
    "gn:country_code":"YE",
    "gn:dem":1906,
    "gn:feature_class":"P",
    "gn:feature_code":"PPL",
    "gn:name":"\u0100l an Naw\u0101\u015firah",
    "gn:population":0,
    "gn:timezone":"Asia/Aden",
    "iso:country":"YE",
    "name:ara_x_preferred":[
        "\u0622\u0644 \u0627\u0644\u0646\u0648\u0627\u0635\u0631\u0629"
    ],
    "name:und_x_variant":[
        "\u0100l an Naw\u0101\u015firah"
    ],
    "wof:name":"Al an Nawasirah",
    "wof:placetype":"locality"
},
  "geometry": {"coordinates":[45.06757,15.51282],"type":"Point"}
}