{
  "type": "Feature",
  "properties": {
    "gn:admin1_code":"23.0",
    "gn:admin2_code":"1115.0",
    "gn:asciiname":"Al Afaj",
    "gn:country_code":"YE",
    "gn:dem":1734,
    "gn:feature_class":"P",
    "gn:feature_code":"PPL",
    "gn:name":"Al Afaj",
    "gn:population":0,
    "gn:timezone":"Asia/Aden",
    "iso:country":"YE",
    "wof:name":"Al Afaj",
    "wof:placetype":"locality"
},
  "geometry": {"coordinates":[44.21228,13.78561],"type":"Point"}
}