{
  "type": "Feature",
  "properties": {
    "gn:country":"YE",
    "gn:fcode":"PPL",
    "gn:pop":14,
    "iso:country":"YE",
    "name:ara_x_preferred":[
        "\u0639\u0637\u0641\u0629 \u0627\u0644 \u062c\u0645\u064a\u0644"
    ],
    "name:eng_x_preferred":[
        "Itfat Al Jamil"
    ],
    "qs:name":"\u2018I\u0163fat \u0100l Jam\u012bl",
    "qs:photos_9r":0,
    "qs:photos_sr":0,
    "qs:pop_sr":"1",
    "wof:name":"\u2018I\u0163fat \u0100l Jam\u012bl",
    "wof:placetype":"locality",
    "wof:population":14
},
  "geometry": {"coordinates":[44.37854,16.77511],"type":"Point"}
}