{
  "type": "Feature",
  "properties": {
    "gn:admin1_code":"11.0",
    "gn:asciiname":"Al Qansa`i",
    "gn:country_code":"YE",
    "gn:dem":2589,
    "gn:feature_class":"P",
    "gn:feature_code":"PPL",
    "gn:name":"Al Qan\u015fa\u2018\u012b",
    "gn:population":0,
    "gn:timezone":"Asia/Aden",
    "iso:country":"YE",
    "name:ara_x_preferred":[
        "\u0627\u0644\u0642\u0646\u0635\u0639\u064a"
    ],
    "name:und_x_variant":[
        "Al Qan\u015fa\u2018\u012b"
    ],
    "wof:name":"Al Qansa`i",
    "wof:placetype":"locality"
},
  "geometry": {"coordinates":[44.32935,14.34575],"type":"Point"}
}