{
  "type": "Feature",
  "properties": {
    "gn:country":"YE",
    "gn:fcode":"PPL",
    "gn:pop":6,
    "iso:country":"YE",
    "name:ara_x_preferred":[
        "\u0627\u0644\u062f\u0643\u0627\u0646"
    ],
    "name:eng_x_preferred":[
        "Ad Dakkan"
    ],
    "qs:name":"Ad Dakk\u0101n",
    "qs:photos_9r":0,
    "qs:photos_sr":0,
    "qs:pop_sr":"1",
    "wof:name":"Ad Dakk\u0101n",
    "wof:placetype":"locality",
    "wof:population":6
},
  "geometry": {"coordinates":[43.8226,13.33627],"type":"Point"}
}