{
  "type": "Feature",
  "properties": {
    "gn:admin1_code":"16.0",
    "gn:admin2_code":"2302.0",
    "gn:asciiname":"Bayt Abu Hadi",
    "gn:country_code":"YE",
    "gn:dem":2472,
    "gn:feature_class":"P",
    "gn:feature_code":"PPL",
    "gn:name":"Bayt Ab\u016b H\u0101d\u012b",
    "gn:population":0,
    "gn:timezone":"Asia/Aden",
    "iso:country":"YE",
    "name:ara_x_preferred":[
        "\u0628\u064a\u062a \u0623\u0628\u0648 \u0647\u0627\u062f\u064a"
    ],
    "name:und_x_variant":[
        "Bayt Ab\u016b H\u0101d\u012b"
    ],
    "wof:name":"Bayt Abu Hadi",
    "wof:placetype":"locality"
},
  "geometry": {"coordinates":[44.20824,15.6965],"type":"Point"}
}