{
  "type": "Feature",
  "properties": {
    "gn:admin1_code":"19.0",
    "gn:admin2_code":"2911.0",
    "gn:asciiname":"Sumayn",
    "gn:country_code":"YE",
    "gn:dem":2617,
    "gn:feature_class":"P",
    "gn:feature_code":"PPL",
    "gn:name":"Sumayn",
    "gn:population":0,
    "gn:timezone":"Asia/Aden",
    "iso:country":"YE",
    "wof:name":"Sumayn",
    "wof:placetype":"locality"
},
  "geometry": {"coordinates":[44.10291,15.64913],"type":"Point"}
}