{
  "type": "Feature",
  "properties": {
    "gn:country":"YE",
    "gn:fcode":"PPL",
    "gn:pop":2,
    "iso:country":"YE",
    "name:ara_x_preferred":[
        "\u0645\u0637\u0631"
    ],
    "name:eng_x_preferred":[
        "Matar"
    ],
    "qs:name":"Ma\u0163ar",
    "qs:photos_9r":0,
    "qs:photos_sr":0,
    "qs:pop_sr":"1",
    "wd:wordcount":55,
    "wof:name":"Ma\u0163ar",
    "wof:placetype":"locality",
    "wof:population":2
},
  "geometry": {"coordinates":[44.31633,16.69324],"type":"Point"}
}