{
  "type": "Feature",
  "properties": {
    "gn:admin1_code":"19.0",
    "gn:admin2_code":"2901.0",
    "gn:asciiname":"Ad Daq`ah",
    "gn:country_code":"YE",
    "gn:dem":1663,
    "gn:feature_class":"P",
    "gn:feature_code":"PPL",
    "gn:name":"Ad Daq\u2018ah",
    "gn:population":0,
    "gn:timezone":"Asia/Aden",
    "iso:country":"YE",
    "name:ara_x_preferred":[
        "\u0627\u0644\u0630\u0642\u0639\u0629"
    ],
    "name:und_x_variant":[
        "Ad Daq\u2018ah"
    ],
    "wof:name":"Ad Daq`ah",
    "wof:placetype":"locality"
},
  "geometry": {"coordinates":[44.06363,16.49406],"type":"Point"}
}