{
  "type": "Feature",
  "properties": {
    "gn:gn_country":"YE",
    "gn:gn_fcode":"FRMS",
    "gn:gn_pop":40,
    "gn:population":40,
    "iso:country":"YE",
    "name:ara_x_preferred":[
        "\u0627\u0644\u062d\u0631\u062c"
    ],
    "qs_pg:aaroncc":"YE",
    "qs_pg:gn_country":"YE",
    "qs_pg:gn_fcode":"FRMS",
    "qs_pg:gn_pop":40,
    "qs_pg:name":"Al \u1e28araj",
    "qs_pg:photos_9r":0,
    "qs_pg:photos_sr":0,
    "qs_pg:pop_sr":1,
    "qs_pg:qs_pg_placetype":"locality",
    "wof:name":"Al \u1e28araj",
    "wof:placetype":"locality",
    "wof:population":40
},
  "geometry": {"coordinates":[45.34996,15.38807],"type":"Point"}
}