{
  "type": "Feature",
  "properties": {
    "gn:country":"YE",
    "gn:fcode":"PPL",
    "gn:pop":2,
    "iso:country":"YE",
    "name:ara_x_preferred":[
        "\u0639\u0644\u0649 \u0635\u062d\u064a\u0641"
    ],
    "name:eng_x_preferred":[
        "Ala Suhayf"
    ],
    "name:eng_x_variant":[
        "\u1e28usayb al Quraym\u0101\u2019",
        "'Ala Suhayf"
    ],
    "qs:name":"\u2018Al\u00e1 \u015eu\u1e29ayf",
    "qs:photos_9r":0,
    "qs:photos_sr":0,
    "qs:pop_sr":"1",
    "wof:name":"\u2018Al\u00e1 \u015eu\u1e29ayf",
    "wof:placetype":"locality",
    "wof:population":2
},
  "geometry": {"coordinates":[43.22365,17.16325],"type":"Point"}
}