{
  "type": "Feature",
  "properties": {
    "gn:admin1_code":"15.0",
    "gn:admin2_code":"2206.0",
    "gn:asciiname":"Al Aghwal",
    "gn:country_code":"YE",
    "gn:dem":732,
    "gn:feature_class":"P",
    "gn:feature_code":"PPL",
    "gn:name":"Al Aghw\u0101l",
    "gn:population":0,
    "gn:timezone":"Asia/Aden",
    "iso:country":"YE",
    "name:ara_x_preferred":[
        "Al Aghw\u0101l"
    ],
    "name:ara_x_variant":[
        "\u0627\u0644\u0623\u063a\u0648\u0627\u0644"
    ],
    "wof:name":"Al Aghwal",
    "wof:placetype":"locality"
},
  "geometry": {"coordinates":[43.17586,16.88965],"type":"Point"}
}