{
  "type": "Feature",
  "properties": {
    "gn:admin1_code":"18.0",
    "gn:admin2_code":"3009.0",
    "gn:asciiname":"Al Mihamidah",
    "gn:country_code":"YE",
    "gn:dem":2111,
    "gn:feature_class":"P",
    "gn:feature_code":"PPL",
    "gn:name":"Al Mi\u1e29\u0101midah",
    "gn:population":0,
    "gn:timezone":"Asia/Aden",
    "iso:country":"YE",
    "name:und_x_variant":[
        "Al Mi\u1e29\u0101midah"
    ],
    "wof:name":"Al Mihamidah",
    "wof:placetype":"locality"
},
  "geometry": {"coordinates":[44.48222,13.707],"type":"Point"}
}