{
  "type": "Feature",
  "properties": {
    "gn:admin1_code":"8.0",
    "gn:admin2_code":"1817.0",
    "gn:asciiname":"Bani Misha`fil",
    "gn:country_code":"YE",
    "gn:dem":109,
    "gn:feature_class":"P",
    "gn:feature_code":"PPL",
    "gn:name":"Ban\u012b Misha\u2018fil",
    "gn:population":0,
    "gn:timezone":"Asia/Aden",
    "iso:country":"YE",
    "name:und_x_variant":[
        "Ban\u012b Misha\u2018fil"
    ],
    "wof:name":"Bani Misha`fil",
    "wof:placetype":"locality"
},
  "geometry": {"coordinates":[43.2989,14.3547],"type":"Point"}
}