{
  "type": "Feature",
  "properties": {
    "gn:country":"YE",
    "gn:fcode":"PPL",
    "gn:pop":13,
    "iso:country":"YE",
    "name:ara_x_preferred":[
        "\u0634\u0639\u0628 \u0627\u0644\u0646\u062c\u062f"
    ],
    "name:eng_x_preferred":[
        "Sha'b An Najd"
    ],
    "name:eng_x_variant":[
        "D\u0101r Jayhl\u0101n"
    ],
    "qs:name":"Sha\u2018b an Najd",
    "qs:photos_9r":0,
    "qs:photos_sr":0,
    "qs:pop_sr":"1",
    "wof:name":"Sha\u2018b an Najd",
    "wof:placetype":"locality",
    "wof:population":13
},
  "geometry": {"coordinates":[43.71486,16.06454],"type":"Point"}
}