{
  "type": "Feature",
  "properties": {
    "gn:country":"YE",
    "gn:fcode":"PPL",
    "gn:pop":3,
    "iso:country":"YE",
    "name:ara_x_preferred":[
        "\u063a\u0627\u0631\u0628 \u0627\u0644\u0642\u064a\u0641"
    ],
    "name:eng_x_preferred":[
        "Gharib Al Qayf"
    ],
    "qs:name":"Gh\u0101rib al Qayf",
    "qs:photos_9r":0,
    "qs:photos_sr":0,
    "qs:pop_sr":"1",
    "wof:name":"Gh\u0101rib al Qayf",
    "wof:placetype":"locality",
    "wof:population":3
},
  "geometry": {"coordinates":[43.32137,16.73589],"type":"Point"}
}