{
  "type": "Feature",
  "properties": {
    "gn:country":"YE",
    "gn:fcode":"PPL",
    "gn:pop":1,
    "iso:country":"YE",
    "name:ara_x_preferred":[
        "\u0627\u0644\u063a\u0645\u0631\u0629"
    ],
    "qs:name":"Al Ghumrah",
    "qs:photos_9r":0,
    "qs:photos_sr":0,
    "qs:pop_sr":"1",
    "wof:name":"Al Ghumrah",
    "wof:placetype":"locality",
    "wof:population":1
},
  "geometry": {"coordinates":[43.415,16.29734],"type":"Point"}
}