{
  "type": "Feature",
  "properties": {
    "gn:admin1_code":"25.0",
    "gn:admin2_code":"1517.0",
    "gn:asciiname":"Al Habil",
    "gn:country_code":"YE",
    "gn:dem":1096,
    "gn:feature_class":"P",
    "gn:feature_code":"PPL",
    "gn:name":"Al \u1e28ab\u012bl",
    "gn:population":0,
    "gn:timezone":"Asia/Aden",
    "iso:country":"YE",
    "name:und_x_variant":[
        "Al \u1e28ab\u012bl"
    ],
    "wof:name":"Al Habil",
    "wof:placetype":"locality"
},
  "geometry": {"coordinates":[44.26652,13.2816],"type":"Point"}
}