{
  "type": "Feature",
  "properties": {
    "gn:admin1_code":"23.0",
    "gn:admin2_code":"1104.0",
    "gn:asciiname":"Bayt al Mas",
    "gn:country_code":"YE",
    "gn:dem":2454,
    "gn:feature_class":"P",
    "gn:feature_code":"PPL",
    "gn:name":"Bayt al M\u0101s",
    "gn:population":0,
    "gn:timezone":"Asia/Aden",
    "iso:country":"YE",
    "name:ara_x_preferred":[
        "\u0628\u064a\u062a \u0627\u0644\u0645\u0627\u0633"
    ],
    "name:und_x_variant":[
        "Bayt al M\u0101s"
    ],
    "wof:name":"Bayt al Mas",
    "wof:placetype":"locality"
},
  "geometry": {"coordinates":[44.42711,14.08752],"type":"Point"}
}