{
  "type": "Feature",
  "properties": {
    "gn:admin1_code":"23.0",
    "gn:admin2_code":"1104.0",
    "gn:asciiname":"Dar al Yafi`i",
    "gn:country_code":"YE",
    "gn:dem":2235,
    "gn:feature_class":"P",
    "gn:feature_code":"PPL",
    "gn:name":"D\u0101r al Y\u0101fi\u2018\u012b",
    "gn:population":0,
    "gn:timezone":"Asia/Aden",
    "iso:country":"YE",
    "name:ara_x_preferred":[
        "\u062f\u0627\u0631 \u0627\u0644\u064a\u0627\u0641\u0639\u064a"
    ],
    "name:und_x_variant":[
        "Duwayr al \u2018Awd",
        "D\u0101r al Y\u0101fi\u2018\u012b"
    ],
    "wof:name":"Dar al Yafi`i",
    "wof:placetype":"locality"
},
  "geometry": {"coordinates":[44.52517,14.04873],"type":"Point"}
}