{
  "type": "Feature",
  "properties": {
    "gn:admin1_code":"20.0",
    "gn:admin2_code":"2010.0",
    "gn:asciiname":"Al Qaryah",
    "gn:country_code":"YE",
    "gn:dem":2423,
    "gn:feature_class":"P",
    "gn:feature_code":"PPL",
    "gn:name":"Al Qaryah",
    "gn:population":0,
    "gn:timezone":"Asia/Aden",
    "iso:country":"YE",
    "name:ara_x_preferred":[
        "\u0627\u0644\u0642\u0631\u064a\u0629"
    ],
    "name:ara_x_variant":[
        "\u0627\u0644\u062f\u0627\u062e\u0644\u064a\u0629"
    ],
    "name:und_x_variant":[
        "Ad D\u0101khil\u012byah"
    ],
    "wof:name":"Al Qaryah",
    "wof:placetype":"locality"
},
  "geometry": {"coordinates":[44.47196,14.31762],"type":"Point"}
}