{
  "type": "Feature",
  "properties": {
    "gn:admin1_code":"15.0",
    "gn:admin2_code":"2210.0",
    "gn:asciiname":"Al Sariyah",
    "gn:country_code":"YE",
    "gn:dem":1987,
    "gn:feature_class":"P",
    "gn:feature_code":"PPL",
    "gn:name":"\u0100l Sar\u012byah",
    "gn:population":0,
    "gn:timezone":"Asia/Aden",
    "iso:country":"YE",
    "name:ara_x_preferred":[
        "\u0627\u0644 \u0633\u0631\u064a\u0629"
    ],
    "name:und_x_variant":[
        "\u0100l Sar\u012byah"
    ],
    "wof:name":"Al Sariyah",
    "wof:placetype":"locality"
},
  "geometry": {"coordinates":[43.59361,17.03484],"type":"Point"}
}