{
  "type": "Feature",
  "properties": {
    "gn:admin1_code":"19.0",
    "gn:admin2_code":"2901.0",
    "gn:asciiname":"Ad Daribah",
    "gn:country_code":"YE",
    "gn:dem":1588,
    "gn:feature_class":"P",
    "gn:feature_code":"PPL",
    "gn:name":"A\u1e11 \u1e10\u0101ribah",
    "gn:population":0,
    "gn:timezone":"Asia/Aden",
    "iso:country":"YE",
    "name:ara_x_preferred":[
        "\u0627\u0644\u0636\u0627\u0631\u0628\u0629"
    ],
    "name:und_x_variant":[
        "A\u1e11 \u1e10\u0101ribah"
    ],
    "wof:name":"Ad Daribah",
    "wof:placetype":"locality"
},
  "geometry": {"coordinates":[44.08236,16.43543],"type":"Point"}
}