{
  "type": "Feature",
  "properties": {
    "gn:admin1_code":"27.0",
    "gn:admin2_code":"3102.0",
    "gn:asciiname":"Al Jabi",
    "gn:country_code":"YE",
    "gn:dem":1789,
    "gn:feature_class":"P",
    "gn:feature_code":"PPL",
    "gn:name":"Al Jab\u012b",
    "gn:population":0,
    "gn:timezone":"Asia/Aden",
    "iso:country":"YE",
    "name:und_x_variant":[
        "Al Jab\u012b"
    ],
    "wof:name":"Al Jabi",
    "wof:placetype":"locality"
},
  "geometry": {"coordinates":[43.75,14.68333],"type":"Point"}
}