{
  "type": "Feature",
  "properties": {
    "gn:admin1_code":"25.0",
    "gn:admin2_code":"1515.0",
    "gn:asciiname":"Dar al Khuttaf",
    "gn:country_code":"YE",
    "gn:dem":938,
    "gn:feature_class":"P",
    "gn:feature_code":"PPL",
    "gn:name":"D\u0101r al Khu\u0163\u0163\u0101f",
    "gn:population":0,
    "gn:timezone":"Asia/Aden",
    "iso:country":"YE",
    "name:und_x_variant":[
        "D\u0101r al Khu\u0163\u0163\u0101f"
    ],
    "wof:name":"Dar al Khuttaf",
    "wof:placetype":"locality"
},
  "geometry": {"coordinates":[43.94804,13.26241],"type":"Point"}
}