{
  "type": "Feature",
  "properties": {
    "gn:country":"YE",
    "gn:fcode":"PPL",
    "gn:population":16,
    "iso:country":"YE",
    "name:ara_x_preferred":[
        "Al \u2018Irf\u0101\u2019"
    ],
    "name:ara_x_variant":[
        "\u0627\u0644\u0639\u0631\u0641\u0627\u0621"
    ],
    "name:eng_x_preferred":[
        "Al 'Irfa"
    ],
    "qs:name":"Al \u2018Irf\u0101\u2019",
    "qs:photos_9r":0,
    "qs:photos_sr":0,
    "qs:pop_sr":"1",
    "wof:name":"Al \u2018Irf\u0101\u2019",
    "wof:placetype":"locality",
    "wof:population":16
},
  "geometry": {"coordinates":[45.20524,14.99729],"type":"Point"}
}