{
  "type": "Feature",
  "properties": {
    "gn:admin1_code":"11.0",
    "gn:admin2_code":"1102.0",
    "gn:asciiname":"Ribat ash Sha`ri",
    "gn:country_code":"YE",
    "gn:dem":2635,
    "gn:feature_class":"P",
    "gn:feature_code":"PPL",
    "gn:name":"Rib\u0101\u0163 ash Sha\u2018r\u012b",
    "gn:population":0,
    "gn:timezone":"Asia/Aden",
    "iso:country":"YE",
    "name:ara_x_preferred":[
        "\u0631\u0628\u0627\u0637 \u0627\u0644\u0634\u0639\u0631\u064a"
    ],
    "name:und_x_variant":[
        "Rib\u0101\u0163 ash Sha\u2018r\u012b"
    ],
    "wof:name":"Ribat ash Sha`ri",
    "wof:placetype":"locality"
},
  "geometry": {"coordinates":[44.28931,14.25463],"type":"Point"}
}