{
  "type": "Feature",
  "properties": {
    "gn:admin1_code":"20.0",
    "gn:asciiname":"Dhira` al Birak",
    "gn:country_code":"YE",
    "gn:dem":2199,
    "gn:feature_class":"P",
    "gn:feature_code":"PPL",
    "gn:name":"Dhir\u0101\u2018 al Birak",
    "gn:population":0,
    "gn:timezone":"Asia/Aden",
    "iso:country":"YE",
    "name:ara_x_preferred":[
        "\u0630\u0631\u0627\u0639 \u0627\u0644\u0628\u0631\u0643"
    ],
    "name:und_x_variant":[
        "Dhir\u0101\u2018 al Birak"
    ],
    "wof:name":"Dhira` al Birak",
    "wof:placetype":"locality"
},
  "geometry": {"coordinates":[44.36667,14.39339],"type":"Point"}
}