{
  "type": "Feature",
  "properties": {
    "gn:country":"YE",
    "gn:fcode":"PPL",
    "gn:pop":14,
    "iso:country":"YE",
    "name:ara_x_preferred":[
        "\u0645\u062c\u0644\u064a\u0644"
    ],
    "name:eng_x_preferred":[
        "Majlil"
    ],
    "name:eng_x_variant":[
        "Mirm\u0101d"
    ],
    "qs:name":"Majl\u012bl",
    "qs:photos_9r":0,
    "qs:photos_sr":0,
    "qs:pop_sr":"1",
    "wof:name":"Majl\u012bl",
    "wof:placetype":"locality",
    "wof:population":14
},
  "geometry": {"coordinates":[43.66038,16.48578],"type":"Point"}
}