{
  "type": "Feature",
  "properties": {
    "gn:admin1_code":"11.0",
    "gn:admin2_code":"2003.0",
    "gn:asciiname":"Al Ma`atin",
    "gn:country_code":"YE",
    "gn:dem":1976,
    "gn:feature_class":"P",
    "gn:feature_code":"PPL",
    "gn:name":"Al Ma\u2018\u0101\u0163\u012bn",
    "gn:population":0,
    "gn:timezone":"Asia/Aden",
    "iso:country":"YE",
    "name:und_x_variant":[
        "Al Ma\u2018\u0101\u0163\u012bn"
    ],
    "wof:name":"Al Ma`atin",
    "wof:placetype":"locality"
},
  "geometry": {"coordinates":[43.90313,14.80015],"type":"Point"}
}