{
  "type": "Feature",
  "properties": {
    "gn:admin1_code":"4.0",
    "gn:admin2_code":"1921.0",
    "gn:asciiname":"Ar Rahm",
    "gn:cc2":"YE",
    "gn:country_code":"YE",
    "gn:dem":822,
    "gn:feature_class":"P",
    "gn:feature_code":"PPL",
    "gn:name":"Ar Ra\u1e29m",
    "gn:population":0,
    "gn:timezone":"Asia/Aden",
    "iso:country":"YE",
    "name:und_x_variant":[
        "Al-Ra\u1e25m",
        "Ar Ra\u1e29m"
    ],
    "wof:name":"Ar Rahm",
    "wof:placetype":"locality"
},
  "geometry": {"coordinates":[48.06667,15.46667],"type":"Point"}
}