{
  "type": "Feature",
  "properties": {
    "gn:admin1_code":"23.0",
    "gn:admin2_code":"1110.0",
    "gn:asciiname":"Ad Dayah",
    "gn:country_code":"YE",
    "gn:dem":656,
    "gn:feature_class":"P",
    "gn:feature_code":"PPL",
    "gn:name":"A\u1e11 \u1e10ay\u0101\u1e29",
    "gn:population":0,
    "gn:timezone":"Asia/Aden",
    "iso:country":"YE",
    "name:und_x_variant":[
        "A\u1e11 \u1e10ay\u0101\u1e29"
    ],
    "wof:name":"Ad Dayah",
    "wof:placetype":"locality"
},
  "geometry": {"coordinates":[43.70732,13.85566],"type":"Point"}
}