{
  "type": "Feature",
  "properties": {
    "gn:admin1_code":"22.0",
    "gn:admin2_code":"1724.0",
    "gn:asciiname":"Mahall Abd Allah `Awas",
    "gn:country_code":"YE",
    "gn:dem":439,
    "gn:feature_class":"P",
    "gn:feature_code":"PPL",
    "gn:name":"Ma\u1e29all Abd All\u0101h \u2018Awas",
    "gn:population":0,
    "gn:timezone":"Asia/Aden",
    "iso:country":"YE",
    "name:und_x_variant":[
        "Ma\u1e29all Abd All\u0101h \u2018Awas"
    ],
    "wof:name":"Mahall Abd Allah `Awas",
    "wof:placetype":"locality"
},
  "geometry": {"coordinates":[43.43247,15.57223],"type":"Point"}
}