{
  "type": "Feature",
  "properties": {
    "gn:admin1_code":"8.0",
    "gn:admin2_code":"1815.0",
    "gn:asciiname":"Muraqqidah",
    "gn:country_code":"YE",
    "gn:dem":286,
    "gn:feature_class":"P",
    "gn:feature_code":"PPL",
    "gn:name":"Muraqqidah",
    "gn:population":0,
    "gn:timezone":"Asia/Aden",
    "iso:country":"YE",
    "wof:name":"Muraqqidah",
    "wof:placetype":"locality"
},
  "geometry": {"coordinates":[43.46571,14.76684],"type":"Point"}
}