{
  "type": "Feature",
  "properties": {
    "gn:admin1_code":"23.0",
    "gn:admin2_code":"1102.0",
    "gn:asciiname":"Dar az Zubayri",
    "gn:country_code":"YE",
    "gn:dem":2420,
    "gn:feature_class":"P",
    "gn:feature_code":"PPL",
    "gn:name":"D\u0101r az Zubayr\u012b",
    "gn:population":0,
    "gn:timezone":"Asia/Aden",
    "iso:country":"YE",
    "name:und_x_variant":[
        "D\u0101r az Zubayr\u012b"
    ],
    "wof:name":"Dar az Zubayri",
    "wof:placetype":"locality"
},
  "geometry": {"coordinates":[44.46977,14.28524],"type":"Point"}
}