{
  "type": "Feature",
  "properties": {
    "gn:admin1_code":"22.0",
    "gn:admin2_code":"1712.0",
    "gn:asciiname":"Habil",
    "gn:country_code":"YE",
    "gn:dem":430,
    "gn:feature_class":"P",
    "gn:feature_code":"PPL",
    "gn:name":"\u1e28abil",
    "gn:population":0,
    "gn:timezone":"Asia/Aden",
    "iso:country":"YE",
    "name:und_x_variant":[
        "\u1e28abil"
    ],
    "wof:name":"Habil",
    "wof:placetype":"locality"
},
  "geometry": {"coordinates":[43.28856,16.10756],"type":"Point"}
}