{
  "type": "Feature",
  "properties": {
    "gn:country":"YE",
    "gn:fcode":"PPL",
    "gn:population":15,
    "iso:country":"YE",
    "name:ara_x_preferred":[
        "\u0627\u0644\u0645\u0633\u0648\u062f\u064a\u0629"
    ],
    "name:eng_x_preferred":[
        "Al MasUdiyah"
    ],
    "name:eng_x_variant":[
        "Al \u2018A\u015fimah"
    ],
    "name:und_x_variant":[
        "Al Musawwad\u012byah"
    ],
    "qs_pg:aaroncc":"YE",
    "qs_pg:gn_country":"YE",
    "qs_pg:gn_fcode":"PPL",
    "qs_pg:gn_pop":15,
    "qs_pg:name":"Al Mas\u016bd\u012byah",
    "qs_pg:photos_9r":0,
    "qs_pg:photos_sr":0,
    "qs_pg:pop_sr":1,
    "qs_pg:qs_pg_placetype":"locality",
    "wof:name":"Al Mas\u016bd\u012byah",
    "wof:placetype":"locality",
    "wof:population":15
},
  "geometry": {"coordinates":[43.00175,16.42867],"type":"Point"}
}