{
  "type": "Feature",
  "properties": {
    "gn:country":"YE",
    "gn:fcode":"PPL",
    "gn:pop":8,
    "iso:country":"YE",
    "name:ara_x_preferred":[
        "\u0627\u0644\u0635\u062d\u0646"
    ],
    "name:eng_x_preferred":[
        "As Sahn"
    ],
    "name:eng_x_variant":[
        "Al \u1e28\u0101li\u0163\u012b"
    ],
    "qs:name":"A\u015f \u015ea\u1e29n",
    "qs:photos_9r":0,
    "qs:photos_sr":0,
    "qs:pop_sr":"1",
    "wof:name":"A\u015f \u015ea\u1e29n",
    "wof:placetype":"locality",
    "wof:population":8
},
  "geometry": {"coordinates":[44.17991,17.30953],"type":"Point"}
}