{
  "type": "Feature",
  "properties": {
    "gn:admin1_code":"22.0",
    "gn:admin2_code":"1720.0",
    "gn:asciiname":"Mahall Sahl al Qara`i",
    "gn:country_code":"YE",
    "gn:dem":859,
    "gn:feature_class":"P",
    "gn:feature_code":"PPL",
    "gn:name":"Ma\u1e29all Sahl al Qar\u0101\u2018\u012b",
    "gn:population":0,
    "gn:timezone":"Asia/Aden",
    "iso:country":"YE",
    "name:und_x_variant":[
        "Ma\u1e29all Sahl al Qar\u0101\u2018\u012b"
    ],
    "wof:name":"Mahall Sahl al Qara`i",
    "wof:placetype":"locality"
},
  "geometry": {"coordinates":[43.53023,15.69716],"type":"Point"}
}