{
  "type": "Feature",
  "properties": {
    "gn:country":"YE",
    "gn:fcode":"PPL",
    "gn:pop":14,
    "iso:country":"YE",
    "name:ara_x_preferred":[
        "\u0627\u0644 \u063a\u0648\u062c\u0627\u0646"
    ],
    "name:eng_x_preferred":[
        "Al Ghawjan"
    ],
    "qs:name":"\u0100l Ghawj\u0101n",
    "qs:photos_9r":0,
    "qs:photos_sr":0,
    "qs:pop_sr":"1",
    "wof:name":"\u0100l Ghawj\u0101n",
    "wof:placetype":"locality",
    "wof:population":14
},
  "geometry": {"coordinates":[44.49813,16.67732],"type":"Point"}
}