{
  "type": "Feature",
  "properties": {
    "gn:admin1_code":"15.0",
    "gn:admin2_code":"2201.0",
    "gn:asciiname":"Al Musahif",
    "gn:country_code":"YE",
    "gn:dem":2117,
    "gn:feature_class":"P",
    "gn:feature_code":"PPL",
    "gn:name":"Al Mu\u015f\u0101\u1e29if",
    "gn:population":0,
    "gn:timezone":"Asia/Aden",
    "iso:country":"YE",
    "name:ara_x_preferred":[
        "Al Mu\u015f\u0101\u1e29if"
    ],
    "wof:name":"Al Musahif",
    "wof:placetype":"locality"
},
  "geometry": {"coordinates":[43.46446,17.39523],"type":"Point"}
}