{
  "type": "Feature",
  "properties": {
    "gn:admin1_code":"14.0",
    "gn:admin2_code":"2603.0",
    "gn:asciiname":"Al Hinzub",
    "gn:country_code":"YE",
    "gn:dem":1188,
    "gn:feature_class":"P",
    "gn:feature_code":"PPL",
    "gn:name":"Al \u1e28inz\u016bb",
    "gn:population":0,
    "gn:timezone":"Asia/Aden",
    "iso:country":"YE",
    "name:ara_x_preferred":[
        "Al \u1e28inz\u016bb"
    ],
    "name:ara_x_variant":[
        "\u0627\u0644\u062d\u0646\u0632\u0648\u0628"
    ],
    "wof:name":"Al Hinzub",
    "wof:placetype":"locality"
},
  "geometry": {"coordinates":[45.02513,15.62361],"type":"Point"}
}