{
  "type": "Feature",
  "properties": {
    "gn:admin1_code":"20.0",
    "gn:admin2_code":"1401.0",
    "gn:asciiname":"As Sadr",
    "gn:country_code":"YE",
    "gn:dem":1785,
    "gn:feature_class":"P",
    "gn:feature_code":"PPL",
    "gn:name":"As Sadr",
    "gn:population":0,
    "gn:timezone":"Asia/Aden",
    "iso:country":"YE",
    "name:nno_x_preferred":[
        "As Sadr"
    ],
    "wof:name":"As Sadr",
    "wof:placetype":"locality"
},
  "geometry": {"coordinates":[45.49814,14.56226],"type":"Point"}
}