{
  "type": "Feature",
  "properties": {
    "gn:country":"YE",
    "gn:fcode":"PPL",
    "gn:pop":1,
    "iso:country":"YE",
    "name:ara_x_preferred":[
        "\u0627\u0644\u062d\u064a\u0641\u0629 \u0627\u0644\u0639\u0644\u064a\u0627"
    ],
    "name:eng_x_preferred":[
        "Al Hayfah Al 'Ulya"
    ],
    "qs:name":"Al \u1e28ayfah al \u2018Uly\u0101",
    "qs:photos_9r":0,
    "qs:photos_sr":0,
    "qs:pop_sr":"1",
    "wof:name":"Al \u1e28ayfah al \u2018Uly\u0101",
    "wof:placetype":"locality",
    "wof:population":1
},
  "geometry": {"coordinates":[43.71053,16.06693],"type":"Point"}
}