{
  "type": "Feature",
  "properties": {
    "gn:admin1_code":"15.0",
    "gn:admin2_code":"2206.0",
    "gn:asciiname":"Al Fujur",
    "gn:country_code":"YE",
    "gn:dem":592,
    "gn:feature_class":"P",
    "gn:feature_code":"PPL",
    "gn:name":"Al Fuj\u016br",
    "gn:population":0,
    "gn:timezone":"Asia/Aden",
    "iso:country":"YE",
    "name:ara_x_preferred":[
        "Al Fuj\u016br"
    ],
    "name:ara_x_variant":[
        "\u0627\u0644\u0641\u062c\u0648\u0631"
    ],
    "wof:name":"Al Fujur",
    "wof:placetype":"locality"
},
  "geometry": {"coordinates":[43.20142,16.89768],"type":"Point"}
}