{
  "type": "Feature",
  "properties": {
    "gn:admin1_code":"19.0",
    "gn:admin2_code":"2919.0",
    "gn:asciiname":"Bayt Qaryah",
    "gn:country_code":"YE",
    "gn:dem":2378,
    "gn:feature_class":"P",
    "gn:feature_code":"PPL",
    "gn:name":"Bayt Qaryah",
    "gn:population":0,
    "gn:timezone":"Asia/Aden",
    "iso:country":"YE",
    "name:ara_x_preferred":[
        "\u0628\u064a\u062a \u0627\u0644\u0642\u0631\u064a\u0629"
    ],
    "wof:name":"Bayt Qaryah",
    "wof:placetype":"locality"
},
  "geometry": {"coordinates":[44.03449000000001,16.04646],"type":"Point"}
}