{
  "type": "Feature",
  "properties": {
    "gn:admin1_code":"8.0",
    "gn:admin2_code":"1812.0",
    "gn:asciiname":"Al Jalhah",
    "gn:country_code":"YE",
    "gn:dem":834,
    "gn:feature_class":"P",
    "gn:feature_code":"PPL",
    "gn:name":"Al Jal\u1e29ah",
    "gn:population":0,
    "gn:timezone":"Asia/Aden",
    "iso:country":"YE",
    "name:ara_x_preferred":[
        "\u0627\u0644\u062c\u0644\u062d\u0629"
    ],
    "name:und_x_variant":[
        "Al \u2018\u0100ri\u1e11ah",
        "Al Jal\u1e29ah"
    ],
    "wof:name":"Al Jalhah",
    "wof:placetype":"locality"
},
  "geometry": {"coordinates":[43.42457,14.92735],"type":"Point"}
}