{
  "type": "Feature",
  "properties": {
    "gn:country":"YE",
    "gn:fcode":"PPLX",
    "gn:population":23,
    "iso:country":"YE",
    "name:ara_x_preferred":[
        "\u062d\u0627\u0631\u0629 \u0627\u0644\u0639\u0646\u0633\u0642"
    ],
    "qs:name":"\u1e28\u0101rat al \u2018Ansiq",
    "qs:photos_9r":0,
    "qs:photos_sr":0,
    "qs:pop_sr":"1",
    "wof:name":"\u1e28\u0101rat al \u2018Ansiq",
    "wof:placetype":"neighbourhood",
    "wof:population":23
},
  "geometry": {"coordinates":[44.28754,16.54989],"type":"Point"}
}