{
  "type": "Feature",
  "properties": {
    "gn:admin1_code":"8.0",
    "gn:admin2_code":"1811.0",
    "gn:asciiname":"Dayr al Hayy",
    "gn:country_code":"YE",
    "gn:dem":546,
    "gn:feature_class":"P",
    "gn:feature_code":"PPL",
    "gn:name":"Dayr al \u1e28ayy",
    "gn:population":0,
    "gn:timezone":"Asia/Aden",
    "iso:country":"YE",
    "name:und_x_variant":[
        "Dayr al \u1e28ayy",
        "Dayr al Hayy"
    ],
    "wof:name":"Dayr al Hayy",
    "wof:placetype":"locality"
},
  "geometry": {"coordinates":[43.58086,14.98553],"type":"Point"}
}