{
  "type": "Feature",
  "properties": {
    "gn:admin1_code":"10.0",
    "gn:admin2_code":"2705.0",
    "gn:asciiname":"Yanhuq",
    "gn:country_code":"YE",
    "gn:dem":483,
    "gn:feature_class":"P",
    "gn:feature_code":"PPL",
    "gn:name":"Yanhuq",
    "gn:population":0,
    "gn:timezone":"Asia/Aden",
    "iso:country":"YE",
    "wof:name":"Yanhuq",
    "wof:placetype":"locality"
},
  "geometry": {"coordinates":[43.39914,15.26924],"type":"Point"}
}