{
  "type": "Feature",
  "properties": {
    "gn:admin1_code":"22.0",
    "gn:admin2_code":"1721.0",
    "gn:asciiname":"Kubayban",
    "gn:country_code":"YE",
    "gn:dem":1330,
    "gn:feature_class":"P",
    "gn:feature_code":"PPL",
    "gn:name":"Kubayb\u0101n",
    "gn:population":0,
    "gn:timezone":"Asia/Aden",
    "iso:country":"YE",
    "name:und_x_variant":[
        "Kubayb\u0101n"
    ],
    "wof:name":"Kubayban",
    "wof:placetype":"locality"
},
  "geometry": {"coordinates":[43.42493,15.85722],"type":"Point"}
}