{
  "type": "Feature",
  "properties": {
    "gn:country":"YE",
    "gn:fcode":"PPL",
    "gn:pop":13,
    "iso:country":"YE",
    "name:ara_x_preferred":[
        "\u062d\u062c\u0641\u0627\u0631"
    ],
    "name:eng_x_preferred":[
        "Hajfar"
    ],
    "qs:name":"\u1e28ajf\u0101r",
    "qs:photos_9r":0,
    "qs:photos_sr":0,
    "qs:pop_sr":"1",
    "wof:name":"\u1e28ajf\u0101r",
    "wof:placetype":"locality",
    "wof:population":13
},
  "geometry": {"coordinates":[43.77663,13.16453],"type":"Point"}
}