{
  "type": "Feature",
  "properties": {
    "gn:country":"YE",
    "gn:fcode":"PPL",
    "gn:pop":7,
    "iso:country":"YE",
    "name:ara_x_preferred":[
        "\u0627\u0644 \u062d\u0633\u0646"
    ],
    "name:eng_x_preferred":[
        "Al Hassan"
    ],
    "qs:name":"\u0100l \u1e28assan",
    "qs:photos_9r":0,
    "qs:photos_sr":0,
    "qs:pop_sr":"1",
    "wof:name":"\u0100l \u1e28assan",
    "wof:placetype":"locality",
    "wof:population":7
},
  "geometry": {"coordinates":[45.42337,14.0651],"type":"Point"}
}