{
  "type": "Feature",
  "properties": {
    "gn:admin1_code":"8.0",
    "gn:admin2_code":"1807.0",
    "gn:asciiname":"Hamian",
    "gn:country_code":"YE",
    "gn:dem":60,
    "gn:feature_class":"P",
    "gn:feature_code":"PPL",
    "gn:name":"Hamian",
    "gn:population":0,
    "gn:timezone":"Asia/Aden",
    "iso:country":"YE",
    "wof:name":"Hamian",
    "wof:placetype":"locality"
},
  "geometry": {"coordinates":[43.01254,15.29174],"type":"Point"}
}