{
  "type": "Feature",
  "properties": {
    "gn:admin1_code":"5.0",
    "gn:admin2_code":"2107.0",
    "gn:asciiname":"Bayhan",
    "gn:country_code":"YE",
    "gn:dem":1127,
    "gn:elevation":"2.0",
    "gn:feature_class":"P",
    "gn:feature_code":"PPLA2",
    "gn:name":"Bay\u1e29\u0101n",
    "gn:population":0,
    "gn:timezone":"Asia/Aden",
    "iso:country":"YE",
    "name:ara_x_preferred":[
        "\u0628\u064a\u062d\u0627\u0646"
    ],
    "name:cat_x_preferred":[
        "Beihan"
    ],
    "name:ceb_x_preferred":[
        "Bayhan"
    ],
    "name:deu_x_preferred":[
        "Baihan al-Kisab"
    ],
    "name:fas_x_preferred":[
        "\u0628\u06cc\u062d\u0627\u0646"
    ],
    "name:fra_x_preferred":[
        "Beihan"
    ],
    "name:hrv_x_preferred":[
        "Beihan"
    ],
    "name:ita_x_preferred":[
        "Beihan"
    ],
    "name:nno_x_preferred":[
        "Beihan"
    ],
    "name:pol_x_preferred":[
        "Bajhan"
    ],
    "name:por_x_preferred":[
        "Beihan"
    ],
    "name:spa_x_preferred":[
        "Beihan"
    ],
    "name:und_x_variant":[
        "S\u016bq \u2018Abd All\u0101b",
        "\u1e24i\u1e63n \u2018Abd All\u0101h",
        "Al-Ka\u1e63\u0101b",
        "Bai\u1e25\u0101n al-Qa\u1e63\u0101b",
        "Bayhan al Quisab",
        "Bay\u1e29\u0101n al Qa\u015f\u0101b",
        "Bay\u1e29\u0101n",
        "Beihan Qasab",
        "Beuhan",
        "Beih\u0101 al Qas\u0101b",
        "Bayhan Qasab",
        "Bay\u1e29\u0101n al Qi\u015f\u0101b"
    ],
    "wof:name":"Bayhan",
    "wof:placetype":"locality"
},
  "geometry": {"coordinates":[45.71889,14.80067],"type":"Point"}
}