{
  "type": "Feature",
  "properties": {
    "gn:admin1_code":"23.0",
    "gn:admin2_code":"1111.0",
    "gn:asciiname":"Dar `Umayr",
    "gn:country_code":"YE",
    "gn:dem":1336,
    "gn:feature_class":"P",
    "gn:feature_code":"PPL",
    "gn:name":"D\u0101r \u2018Umayr",
    "gn:population":0,
    "gn:timezone":"Asia/Aden",
    "iso:country":"YE",
    "name:und_x_variant":[
        "D\u0101r \u2018Umayr"
    ],
    "wof:name":"Dar `Umayr",
    "wof:placetype":"locality"
},
  "geometry": {"coordinates":[43.96498,13.93936],"type":"Point"}
}