{
  "type": "Feature",
  "properties": {
    "gn:admin1_code":"16.0",
    "gn:admin2_code":"2312.0",
    "gn:asciiname":"Bani Sulayh",
    "gn:country_code":"YE",
    "gn:dem":2008,
    "gn:feature_class":"P",
    "gn:feature_code":"PPL",
    "gn:name":"Ban\u012b \u015eulay\u1e29",
    "gn:population":0,
    "gn:timezone":"Asia/Aden",
    "iso:country":"YE",
    "name:nno_x_preferred":[
        "Bani Sulih"
    ],
    "name:und_x_variant":[
        "Ban\u012b \u015eulay\u1e29",
        "Ban\u012b Suli\u1e29"
    ],
    "wof:name":"Bani Sulayh",
    "wof:placetype":"locality"
},
  "geometry": {"coordinates":[44.72842,15.22475],"type":"Point"}
}