{
  "type": "Feature",
  "properties": {
    "gn:admin1_code":"23.0",
    "gn:admin2_code":"1120.0",
    "gn:asciiname":"Ad Dakhlah",
    "gn:country_code":"YE",
    "gn:dem":1688,
    "gn:feature_class":"P",
    "gn:feature_code":"PPL",
    "gn:name":"Ad Dakhlah",
    "gn:population":0,
    "gn:timezone":"Asia/Aden",
    "iso:country":"YE",
    "name:ara_x_preferred":[
        "\u0627\u0644\u062f\u062e\u0644\u0629"
    ],
    "wof:name":"Ad Dakhlah",
    "wof:placetype":"locality"
},
  "geometry": {"coordinates":[44.14027,14.0579],"type":"Point"}
}