{
  "type": "Feature",
  "properties": {
    "gn:admin1_code":"5.0",
    "gn:admin2_code":"2112.0",
    "gn:asciiname":"Al Mahzarah",
    "gn:country_code":"YE",
    "gn:dem":1232,
    "gn:feature_class":"P",
    "gn:feature_code":"PPL",
    "gn:name":"Al Ma\u1e29z\u0327arah",
    "gn:population":0,
    "gn:timezone":"Asia/Aden",
    "iso:country":"YE",
    "name:ara_x_preferred":[
        "\u0627\u0644\u0645\u062d\u0638\u0631\u0629"
    ],
    "name:und_x_variant":[
        "Al Ma\u1e29\u1e11arah",
        "Al Ma\u1e29z\u0327arah"
    ],
    "wof:name":"Al Mahzarah",
    "wof:placetype":"locality"
},
  "geometry": {"coordinates":[46.84274,14.42543],"type":"Point"}
}