{
  "type": "Feature",
  "properties": {
    "gn:admin1_code":"19.0",
    "gn:admin2_code":"2901.0",
    "gn:asciiname":"Fayyahah",
    "gn:country_code":"YE",
    "gn:dem":1653,
    "gn:feature_class":"P",
    "gn:feature_code":"PPLL",
    "gn:name":"Fayy\u0101\u1e29ah",
    "gn:population":0,
    "gn:timezone":"Asia/Aden",
    "iso:country":"YE",
    "name:ara_x_preferred":[
        "\u0641\u064a\u0627\u062d\u0629"
    ],
    "name:und_x_variant":[
        "Fayy\u0101\u1e29ah"
    ],
    "wof:name":"Fayyahah",
    "wof:placetype":"locality"
},
  "geometry": {"coordinates":[44.10642,16.20987],"type":"Point"}
}