{
  "type": "Feature",
  "properties": {
    "gn:admin1_code":"23.0",
    "gn:admin2_code":"1103.0",
    "gn:asciiname":"Shi`b as Sanaf",
    "gn:country_code":"YE",
    "gn:dem":2405,
    "gn:feature_class":"P",
    "gn:feature_code":"PPL",
    "gn:name":"Shi\u2018b as Sanaf",
    "gn:population":0,
    "gn:timezone":"Asia/Aden",
    "iso:country":"YE",
    "name:und_x_variant":[
        "Shi\u2018b as Sanaf"
    ],
    "wof:name":"Shi`b as Sanaf",
    "wof:placetype":"locality"
},
  "geometry": {"coordinates":[44.53166,14.23021],"type":"Point"}
}