{
  "type": "Feature",
  "properties": {
    "gn:admin1_code":"24.0",
    "gn:admin2_code":"2510.0",
    "gn:asciiname":"Al Harrayshah",
    "gn:country_code":"YE",
    "gn:dem":1371,
    "gn:feature_class":"P",
    "gn:feature_code":"PPL",
    "gn:name":"Al Harrayshah",
    "gn:population":0,
    "gn:timezone":"Asia/Aden",
    "iso:country":"YE",
    "wof:name":"Al Harrayshah",
    "wof:placetype":"locality"
},
  "geometry": {"coordinates":[44.40866,13.31666],"type":"Point"}
}