{
  "type": "Feature",
  "properties": {
    "gn:admin1_code":"23.0",
    "gn:admin2_code":"1115.0",
    "gn:asciiname":"Al Quray`a'",
    "gn:country_code":"YE",
    "gn:dem":1729,
    "gn:feature_class":"P",
    "gn:feature_code":"PPL",
    "gn:name":"Al Quray\u2018\u0101\u2019",
    "gn:population":0,
    "gn:timezone":"Asia/Aden",
    "iso:country":"YE",
    "name:und_x_variant":[
        "Al Quray\u2018\u0101\u2019"
    ],
    "wof:name":"Al Quray`a'",
    "wof:placetype":"locality"
},
  "geometry": {"coordinates":[44.19552,13.79585],"type":"Point"}
}