{
  "type": "Feature",
  "properties": {
    "gn:admin1_code":"23.0",
    "gn:admin2_code":"1120.0",
    "gn:asciiname":"As Sawafi",
    "gn:country_code":"YE",
    "gn:dem":2007,
    "gn:feature_class":"P",
    "gn:feature_code":"PPL",
    "gn:name":"A\u015f \u015eaw\u0101f\u012b",
    "gn:population":0,
    "gn:timezone":"Asia/Aden",
    "iso:country":"YE",
    "name:und_x_variant":[
        "A\u015f \u015eaw\u0101f\u012b"
    ],
    "wof:name":"As Sawafi",
    "wof:placetype":"locality"
},
  "geometry": {"coordinates":[44.15151,14.01091],"type":"Point"}
}