{
  "type": "Feature",
  "properties": {
    "gn:admin1_code":"10.0",
    "gn:admin2_code":"2704.0",
    "gn:asciiname":"Al Hinnayah",
    "gn:country_code":"YE",
    "gn:dem":439,
    "gn:feature_class":"P",
    "gn:feature_code":"PPL",
    "gn:name":"Al Hinn\u0101yah",
    "gn:population":0,
    "gn:timezone":"Asia/Aden",
    "iso:country":"YE",
    "name:und_x_variant":[
        "Al Hinn\u0101yah"
    ],
    "wof:name":"Al Hinnayah",
    "wof:placetype":"locality"
},
  "geometry": {"coordinates":[43.35358,15.49763],"type":"Point"}
}