{
  "type": "Feature",
  "properties": {
    "gn:admin1_code":"8.0",
    "gn:admin2_code":"1812.0",
    "gn:asciiname":"Al Wati'",
    "gn:country_code":"YE",
    "gn:dem":1443,
    "gn:feature_class":"P",
    "gn:feature_code":"PPL",
    "gn:name":"Al W\u0101\u0163i\u2019",
    "gn:population":0,
    "gn:timezone":"Asia/Aden",
    "iso:country":"YE",
    "name:ara_x_preferred":[
        "\u0627\u0644\u0648\u0627\u0637\u0626"
    ],
    "name:und_x_variant":[
        "Al W\u0101\u0163i\u2019"
    ],
    "wof:name":"Al Wati'",
    "wof:placetype":"locality"
},
  "geometry": {"coordinates":[43.44822,14.88838],"type":"Point"}
}