{
  "type": "Feature",
  "properties": {
    "gn:admin1_code":"24.0",
    "gn:admin2_code":"2512.0",
    "gn:asciiname":"Al 'Awarid",
    "gn:country_code":"YE",
    "gn:dem":1185,
    "gn:feature_class":"P",
    "gn:feature_code":"PPL",
    "gn:name":"Al \u2018Aw\u0101ri\u1e11",
    "gn:population":0,
    "gn:timezone":"Asia/Aden",
    "iso:country":"YE",
    "name:ara_x_preferred":[
        "\u0627\u0644\u0639\u0648\u0627\u0631\u0636"
    ],
    "name:und_x_variant":[
        "Al \u2018Aw\u0101ri\u1e11"
    ],
    "wof:name":"Al 'Awarid",
    "wof:placetype":"locality"
},
  "geometry": {"coordinates":[44.14342,13.18291],"type":"Point"}
}