{
  "type": "Feature",
  "properties": {
    "gn:admin1_code":"24.0",
    "gn:admin2_code":"2512.0",
    "gn:asciiname":"Al Mu'aydhirah",
    "gn:country_code":"YE",
    "gn:dem":1079,
    "gn:feature_class":"P",
    "gn:feature_code":"PPL",
    "gn:name":"Al Mu\u2018aydhirah",
    "gn:population":0,
    "gn:timezone":"Asia/Aden",
    "iso:country":"YE",
    "name:ara_x_preferred":[
        "\u0627\u0644\u0645\u0639\u064a\u0630\u0631\u0629"
    ],
    "name:und_x_variant":[
        "Al Mu\u2018aydhirah"
    ],
    "wof:name":"Al Mu'aydhirah",
    "wof:placetype":"locality"
},
  "geometry": {"coordinates":[44.17334,13.16381],"type":"Point"}
}