{
  "type": "Feature",
  "properties": {
    "gn:admin1_code":"23.0",
    "gn:admin2_code":"1106.0",
    "gn:asciiname":"Suq ath Thuluth",
    "gn:country_code":"YE",
    "gn:dem":2227,
    "gn:feature_class":"P",
    "gn:feature_code":"PPL",
    "gn:name":"S\u016bq ath Thul\u016bth",
    "gn:population":0,
    "gn:timezone":"Asia/Aden",
    "iso:country":"YE",
    "name:ara_x_preferred":[
        "\u0633\u0648\u0642 \u0627\u0644\u062b\u0644\u0648\u062b"
    ],
    "name:und_x_variant":[
        "S\u016bq ath Thul\u016bth"
    ],
    "wof:name":"Suq ath Thuluth",
    "wof:placetype":"locality"
},
  "geometry": {"coordinates":[44.41739000000001,14.12994],"type":"Point"}
}