{
  "type": "Feature",
  "properties": {
    "gn:admin1_code":"20.0",
    "gn:admin2_code":"1405.0",
    "gn:asciiname":"Al Ahmad 'Abd Allah",
    "gn:country_code":"YE",
    "gn:dem":1994,
    "gn:feature_class":"P",
    "gn:feature_code":"PPL",
    "gn:name":"\u0100l A\u1e29mad \u2018Abd All\u0101h",
    "gn:population":0,
    "gn:timezone":"Asia/Aden",
    "iso:country":"YE",
    "name:ara_x_preferred":[
        "\u0627\u0644 \u0623\u062d\u0645\u062f \u0639\u0628\u062f \u0627\u0644\u0644\u0647"
    ],
    "name:und_x_variant":[
        "\u0100l A\u1e29mad \u2018Abd All\u0101h"
    ],
    "wof:name":"Al Ahmad 'Abd Allah",
    "wof:placetype":"locality"
},
  "geometry": {"coordinates":[45.38178,14.03069],"type":"Point"}
}