{
  "type": "Feature",
  "properties": {
    "gn:admin1_code":"14.0",
    "gn:admin2_code":"2612.0",
    "gn:asciiname":"Al Haymid",
    "gn:country_code":"YE",
    "gn:dem":1103,
    "gn:feature_class":"P",
    "gn:feature_code":"PPL",
    "gn:name":"\u0100l \u1e28aymid",
    "gn:population":0,
    "gn:timezone":"Asia/Aden",
    "iso:country":"YE",
    "name:ara_x_preferred":[
        "\u0622\u0644 \u062d\u064a\u0645\u062f"
    ],
    "name:und_x_variant":[
        "\u0100l \u1e28aymid"
    ],
    "wof:name":"Al Haymid",
    "wof:placetype":"locality"
},
  "geometry": {"coordinates":[45.32127,15.40444],"type":"Point"}
}