{
  "type": "Feature",
  "properties": {
    "gn:admin1_code":"23.0",
    "gn:admin2_code":"1115.0",
    "gn:asciiname":"Ash Shi`ab",
    "gn:country_code":"YE",
    "gn:dem":1980,
    "gn:feature_class":"P",
    "gn:feature_code":"PPL",
    "gn:name":"Ash Shi\u2018\u0101b",
    "gn:population":0,
    "gn:timezone":"Asia/Aden",
    "iso:country":"YE",
    "name:ara_x_preferred":[
        "Ash Shi\u2018\u0101b"
    ],
    "wof:name":"Ash Shi`ab",
    "wof:placetype":"locality"
},
  "geometry": {"coordinates":[44.23456,13.85559],"type":"Point"}
}