{
  "type": "Feature",
  "properties": {
    "gn:country":"YE",
    "gn:fcode":"PPL",
    "gn:pop":15,
    "iso:country":"YE",
    "name:ara_x_preferred":[
        "Al Khiy\u0101l"
    ],
    "name:ara_x_variant":[
        "\u0627\u0644\u062e\u064a\u0627\u0644"
    ],
    "name:eng_x_preferred":[
        "Al Khiyal"
    ],
    "name:eng_x_variant":[
        "Al Luj\u0101f"
    ],
    "qs:name":"Al Khiy\u0101l",
    "qs:photos_9r":0,
    "qs:photos_sr":0,
    "qs:pop_sr":"1",
    "wof:name":"Al Khiy\u0101l",
    "wof:placetype":"locality",
    "wof:population":15
},
  "geometry": {"coordinates":[45.80583,14.28115],"type":"Point"}
}