{
  "type": "Feature",
  "properties": {
    "gn:admin1_code":"8.0",
    "gn:admin2_code":"1818.0",
    "gn:asciiname":"Al Kubbah",
    "gn:country_code":"YE",
    "gn:dem":548,
    "gn:feature_class":"P",
    "gn:feature_code":"PPL",
    "gn:name":"Al Kubbah",
    "gn:population":0,
    "gn:timezone":"Asia/Aden",
    "iso:country":"YE",
    "name:ara_x_preferred":[
        "\u0627\u0644\u0643\u0628\u0629"
    ],
    "name:und_x_variant":[
        "Al Kabbah",
        "Al Kubbah"
    ],
    "wof:name":"Al Kubbah",
    "wof:placetype":"locality"
},
  "geometry": {"coordinates":[43.69995,14.03057],"type":"Point"}
}