{
  "type": "Feature",
  "properties": {
    "gn:admin1_code":"23.0",
    "gn:admin2_code":"1109.0",
    "gn:asciiname":"Al Ma`adhir",
    "gn:country_code":"YE",
    "gn:dem":884,
    "gn:feature_class":"P",
    "gn:feature_code":"PPL",
    "gn:name":"Al Ma\u2018\u0101dhir",
    "gn:population":0,
    "gn:timezone":"Asia/Aden",
    "iso:country":"YE",
    "name:ara_x_preferred":[
        "\u0627\u0644\u0645\u0639\u0627\u0630\u0631"
    ],
    "name:und_x_variant":[
        "Al Ma\u2018\u0101dir",
        "Al Ma\u2018\u0101dhir"
    ],
    "wof:name":"Al Ma`adhir",
    "wof:placetype":"locality"
},
  "geometry": {"coordinates":[43.84103,14.06952],"type":"Point"}
}