{
  "type": "Feature",
  "properties": {
    "gn:country":"YE",
    "gn:fcode":"PPL",
    "gn:pop":1,
    "iso:country":"YE",
    "name:ara_x_preferred":[
        "\u0627\u0644\u0645\u0631\u062f\u0629"
    ],
    "name:eng_x_preferred":[
        "Al Maradah"
    ],
    "name:eng_x_variant":[
        "Al A\u1e29mar"
    ],
    "qs:name":"Al Maradah",
    "qs:photos_9r":0,
    "qs:photos_sr":0,
    "qs:pop_sr":"1",
    "wof:name":"Al Maradah",
    "wof:placetype":"locality",
    "wof:population":1
},
  "geometry": {"coordinates":[43.95569,13.1312],"type":"Point"}
}