{
  "type": "Feature",
  "properties": {
    "gn:admin1_code":"8.0",
    "gn:admin2_code":"1810.0",
    "gn:asciiname":"Dahamiyah",
    "gn:country_code":"YE",
    "gn:dem":66,
    "gn:feature_class":"P",
    "gn:feature_code":"PPL",
    "gn:name":"Dah\u0101m\u012byah",
    "gn:population":0,
    "gn:timezone":"Asia/Aden",
    "iso:country":"YE",
    "name:und_x_variant":[
        "Dah\u0101m\u012byah"
    ],
    "wof:name":"Dahamiyah",
    "wof:placetype":"locality"
},
  "geometry": {"coordinates":[43.05654000000001,15.09757],"type":"Point"}
}