{
  "type": "Feature",
  "properties": {
    "gn:admin1_code":"20.0",
    "gn:admin2_code":"1411.0",
    "gn:asciiname":"Ma`alla'",
    "gn:country_code":"YE",
    "gn:dem":1985,
    "gn:feature_class":"P",
    "gn:feature_code":"PPL",
    "gn:name":"Ma\u2018all\u0101\u2019",
    "gn:population":0,
    "gn:timezone":"Asia/Aden",
    "iso:country":"YE",
    "name:und_x_variant":[
        "Ma\u2018all\u0101\u2019"
    ],
    "wof:name":"Ma`alla'",
    "wof:placetype":"locality"
},
  "geometry": {"coordinates":[45.22819000000001,14.28677],"type":"Point"}
}