{
  "type": "Feature",
  "properties": {
    "gn:country":"YE",
    "gn:fcode":"PPL",
    "gn:pop":8,
    "iso:country":"YE",
    "name:ara_x_preferred":[
        "\u0627\u0644\u0634\u062f\u0646\u0629"
    ],
    "name:eng_x_preferred":[
        "Ash Shadnah"
    ],
    "name:vie_x_preferred":[
        "Kuhlan Affar"
    ],
    "qs:name":"Ash Shadnah",
    "qs:photos_9r":0,
    "qs:photos_sr":0,
    "qs:pop_sr":"1",
    "wof:name":"Ash Shadnah",
    "wof:placetype":"locality",
    "wof:population":8
},
  "geometry": {"coordinates":[43.46336,16.32789],"type":"Point"}
}