{
  "type": "Feature",
  "properties": {
    "gn:admin1_code":"22.0",
    "gn:admin2_code":"1709.0",
    "gn:asciiname":"Bayt al Mawqir",
    "gn:country_code":"YE",
    "gn:dem":1778,
    "gn:feature_class":"P",
    "gn:feature_code":"PPL",
    "gn:name":"Bayt al Mawqir",
    "gn:population":0,
    "gn:timezone":"Asia/Aden",
    "iso:country":"YE",
    "name:ara_x_preferred":[
        "\u0628\u064a\u062a \u0627\u0644\u0645\u0648\u0642\u0631"
    ],
    "wof:name":"Bayt al Mawqir",
    "wof:placetype":"locality"
},
  "geometry": {"coordinates":[43.45248,16.0516],"type":"Point"}
}