{
  "type": "Feature",
  "properties": {
    "gn:admin1_code":"21.0",
    "gn:admin2_code":"1601.0",
    "gn:asciiname":"Mahdah",
    "gn:country_code":"YE",
    "gn:dem":1436,
    "gn:feature_class":"P",
    "gn:feature_code":"PPL",
    "gn:name":"Ma\u1e29\u1e11ah",
    "gn:population":0,
    "gn:timezone":"Asia/Aden",
    "iso:country":"YE",
    "name:ara_x_preferred":[
        "\u0648\u0644\u0627\u064a\u0629 \u0645\u062d\u0636\u0629"
    ],
    "name:ces_x_preferred":[
        "Mahz\u00e1"
    ],
    "name:deu_x_preferred":[
        "Mahda"
    ],
    "name:fas_x_preferred":[
        "\u0645\u062d\u0636\u0647"
    ],
    "name:nno_x_preferred":[
        "Mahdha"
    ],
    "name:und_x_variant":[
        "Ma\u1e29\u1e11ah"
    ],
    "wof:name":"Mahdah",
    "wof:placetype":"locality"
},
  "geometry": {"coordinates":[44.85212,16.69483],"type":"Point"}
}