{
  "type": "Feature",
  "properties": {
    "gn:admin1_code":"21.0",
    "gn:admin2_code":"1601.0",
    "gn:asciiname":"Mahdah",
    "gn:country_code":"YE",
    "gn:dem":1436,
    "gn:feature_class":"P",
    "gn:feature_code":"PPL",
    "gn:name":"Ma\u1e29\u1e11ah",
    "gn:population":0,
    "gn:timezone":"Asia/Aden",
    "iso:country":"YE",
    "name:und_x_variant":[
        "Ma\u1e29\u1e11ah"
    ],
    "wof:name":"Mahdah",
    "wof:placetype":"locality"
},
  "geometry": {"coordinates":[44.85212,16.69483],"type":"Point"}
}