{
  "type": "Feature",
  "properties": {
    "gn:admin1_code":"18.0",
    "gn:admin2_code":"3004.0",
    "gn:asciiname":"Al Ajil",
    "gn:country_code":"YE",
    "gn:dem":1873,
    "gn:feature_class":"P",
    "gn:feature_code":"PPL",
    "gn:name":"Al Ajil",
    "gn:population":0,
    "gn:timezone":"Asia/Aden",
    "iso:country":"YE",
    "wof:name":"Al Ajil",
    "wof:placetype":"locality"
},
  "geometry": {"coordinates":[44.90851,13.81816],"type":"Point"}
}