{
  "type": "Feature",
  "properties": {
    "gn:admin1_code":"25.0",
    "gn:admin2_code":"1508.0",
    "gn:asciiname":"Ar Rujim",
    "gn:country_code":"YE",
    "gn:dem":368,
    "gn:feature_class":"P",
    "gn:feature_code":"PPL",
    "gn:name":"Ar Ruj\u012bm",
    "gn:population":0,
    "gn:timezone":"Asia/Aden",
    "iso:country":"YE",
    "name:ara_x_preferred":[
        "Ar Ruj\u012bm"
    ],
    "wof:name":"Ar Rujim",
    "wof:placetype":"locality"
},
  "geometry": {"coordinates":[43.60492,13.53395],"type":"Point"}
}