{
  "type": "Feature",
  "properties": {
    "gn:admin1_code":"8.0",
    "gn:admin2_code":"1809.0",
    "gn:asciiname":"Al Makin",
    "gn:country_code":"YE",
    "gn:dem":63,
    "gn:feature_class":"P",
    "gn:feature_code":"PPL",
    "gn:name":"Al Mak\u012bn",
    "gn:population":0,
    "gn:timezone":"Asia/Aden",
    "iso:country":"YE",
    "name:ara_x_preferred":[
        "\u0627\u0644\u0645\u0643\u064a\u0646"
    ],
    "name:und_x_variant":[
        "Ma\u1e29all al Mak\u012bn",
        "Al Mak\u012bn"
    ],
    "wof:name":"Al Makin",
    "wof:placetype":"locality"
},
  "geometry": {"coordinates":[43.03222,15.20963],"type":"Point"}
}