{
  "type": "Feature",
  "properties": {
    "gn:country":"YE",
    "gn:fcode":"PPL",
    "gn:pop":9,
    "iso:country":"YE",
    "name:ara_x_preferred":[
        "\u0627\u0644\u0639\u0645\u0631\u0629"
    ],
    "name:eng_x_preferred":[
        "Al 'Amirah"
    ],
    "name:eng_x_variant":[
        "Al Jurayb"
    ],
    "name:unk_x_variant":[
        "Al \u2018Amrah"
    ],
    "qs:name":"Al \u2018Amirah",
    "qs:photos_9r":0,
    "qs:photos_sr":0,
    "qs:pop_sr":"1",
    "wof:name":"Al \u2018Amirah",
    "wof:placetype":"locality",
    "wof:population":9
},
  "geometry": {"coordinates":[43.31794,16.73742],"type":"Point"}
}