{
  "type": "Feature",
  "properties": {
    "gn:country":"YE",
    "gn:fcode":"PPL",
    "gn:pop":31,
    "iso:country":"YE",
    "name:ara_x_preferred":[
        "Al B\u0101h\u012b"
    ],
    "name:ara_x_variant":[
        "\u0627\u0644\u0628\u0627\u0647\u064a"
    ],
    "name:eng_x_preferred":[
        "Al Bahi"
    ],
    "name:eng_x_variant":[
        "\u0100l Mashiq\u012b"
    ],
    "qs:name":"Al B\u0101h\u012b",
    "qs:photos_9r":0,
    "qs:photos_sr":0,
    "qs:pop_sr":"1",
    "wof:name":"Al B\u0101h\u012b",
    "wof:placetype":"locality",
    "wof:population":31
},
  "geometry": {"coordinates":[45.36725,15.46624],"type":"Point"}
}