{
  "type": "Feature",
  "properties": {
    "gn:admin1_code":"23.0",
    "gn:admin2_code":"1120.0",
    "gn:asciiname":"Al Mahaqir",
    "gn:country_code":"YE",
    "gn:dem":2481,
    "gn:feature_class":"P",
    "gn:feature_code":"PPL",
    "gn:name":"Al Ma\u1e29\u0101qir",
    "gn:population":0,
    "gn:timezone":"Asia/Aden",
    "iso:country":"YE",
    "name:und_x_variant":[
        "Al Ma\u1e29\u0101qir"
    ],
    "wof:name":"Al Mahaqir",
    "wof:placetype":"locality"
},
  "geometry": {"coordinates":[44.22122,13.98725],"type":"Point"}
}