{
  "type": "Feature",
  "properties": {
    "gn:admin1_code":"24.0",
    "gn:admin2_code":"2512.0",
    "gn:asciiname":"Nakab as Suq",
    "gn:country_code":"YE",
    "gn:dem":1132,
    "gn:feature_class":"P",
    "gn:feature_code":"PPL",
    "gn:name":"Nakab as S\u016bq",
    "gn:population":0,
    "gn:timezone":"Asia/Aden",
    "iso:country":"YE",
    "name:ara_x_preferred":[
        "\u0646\u0643\u0628 \u0627\u0644\u0633\u0648\u0642"
    ],
    "name:und_x_variant":[
        "Nakab as S\u016bq"
    ],
    "wof:name":"Nakab as Suq",
    "wof:placetype":"locality"
},
  "geometry": {"coordinates":[44.21024,13.19525],"type":"Point"}
}