{
  "type": "Feature",
  "properties": {
    "gn:admin1_code":"4.0",
    "gn:admin2_code":"1918.0",
    "gn:asciiname":"Fayl",
    "gn:cc2":"YE",
    "gn:country_code":"YE",
    "gn:dem":1103,
    "gn:feature_class":"P",
    "gn:feature_code":"PPL",
    "gn:name":"Fayl",
    "gn:population":0,
    "gn:timezone":"Asia/Aden",
    "iso:country":"YE",
    "name:nno_x_preferred":[
        "Fayl"
    ],
    "name:und_x_variant":[
        "Fail"
    ],
    "wof:name":"Fayl",
    "wof:placetype":"locality"
},
  "geometry": {"coordinates":[48.35944,15.29583],"type":"Point"}
}