{
  "type": "Feature",
  "properties": {
    "gn:admin1_code":"4.0",
    "gn:admin2_code":"1919.0",
    "gn:asciiname":"Sharj ash Sharif",
    "gn:cc2":"YE",
    "gn:country_code":"YE",
    "gn:dem":1045,
    "gn:feature_class":"P",
    "gn:feature_code":"PPL",
    "gn:name":"Sharj ash Shar\u012bf",
    "gn:population":0,
    "gn:timezone":"Asia/Aden",
    "iso:country":"YE",
    "name:und_x_variant":[
        "Sharj al-Shar\u012bf",
        "Sharj ash Shar\u012bf"
    ],
    "wof:name":"Sharj ash Sharif",
    "wof:placetype":"locality"
},
  "geometry": {"coordinates":[48.48333,15.38333],"type":"Point"}
}