{
  "type": "Feature",
  "properties": {
    "gn:admin1_code":"11.0",
    "gn:admin2_code":"2009.0",
    "gn:asciiname":"Al `Allanah",
    "gn:country_code":"YE",
    "gn:dem":2465,
    "gn:feature_class":"P",
    "gn:feature_code":"PPL",
    "gn:name":"Al \u2018All\u0101nah",
    "gn:population":0,
    "gn:timezone":"Asia/Aden",
    "iso:country":"YE",
    "name:und_x_variant":[
        "Al \u2018All\u0101nah"
    ],
    "wof:name":"Al `Allanah",
    "wof:placetype":"locality"
},
  "geometry": {"coordinates":[44.49842,14.56481],"type":"Point"}
}