{
  "type": "Feature",
  "properties": {
    "gn:admin1_code":"1.0",
    "gn:admin2_code":"1211.0",
    "gn:asciiname":"Masadi`ah",
    "gn:country_code":"YE",
    "gn:dem":58,
    "gn:feature_class":"P",
    "gn:feature_code":"PPL",
    "gn:name":"Ma\u015f\u0101d\u012b\u2018ah",
    "gn:population":0,
    "gn:timezone":"Asia/Aden",
    "iso:country":"YE",
    "name:nno_x_preferred":[
        "Masadi`ah"
    ],
    "name:und_x_variant":[
        "Ma\u015f\u0101d\u012b\u2018ah"
    ],
    "wof:name":"Masadi`ah",
    "wof:placetype":"locality"
},
  "geometry": {"coordinates":[45.27472,13.20889],"type":"Point"}
}