{
  "type": "Feature",
  "properties": {
    "gn:country":"YE",
    "gn:fcode":"PPL",
    "gn:pop":6,
    "iso:country":"YE",
    "name:ara_x_preferred":[
        "\u0627\u0644\u0634\u062c\u064a\u0639"
    ],
    "name:eng_x_preferred":[
        "Ash Shujay'"
    ],
    "name:eng_x_variant":[
        "Ash Shuwa\u1e29i\u0163\u012b"
    ],
    "qs:name":"Ash Shujay\u2018",
    "qs:photos_9r":0,
    "qs:photos_sr":0,
    "qs:pop_sr":"1",
    "wof:name":"Ash Shujay\u2018",
    "wof:placetype":"locality",
    "wof:population":6
},
  "geometry": {"coordinates":[43.83831,13.44816],"type":"Point"}
}