{
  "type": "Feature",
  "properties": {
    "gn:admin1_code":"22.0",
    "gn:admin2_code":"1724.0",
    "gn:asciiname":"Mahall al Mi`raj",
    "gn:country_code":"YE",
    "gn:dem":314,
    "gn:feature_class":"P",
    "gn:feature_code":"PPL",
    "gn:name":"Ma\u1e29all al Mi\u2018r\u0101j",
    "gn:population":0,
    "gn:timezone":"Asia/Aden",
    "iso:country":"YE",
    "name:und_x_variant":[
        "Ma\u1e29all al Mi\u2018r\u0101j"
    ],
    "wof:name":"Mahall al Mi`raj",
    "wof:placetype":"locality"
},
  "geometry": {"coordinates":[43.32244,15.55972],"type":"Point"}
}