{
  "type": "Feature",
  "properties": {
    "gn:admin1_code":"23.0",
    "gn:admin2_code":"1105.0",
    "gn:asciiname":"Dogara",
    "gn:country_code":"YE",
    "gn:dem":3017,
    "gn:feature_class":"P",
    "gn:feature_code":"PPL",
    "gn:name":"Dogara",
    "gn:population":0,
    "gn:timezone":"Asia/Aden",
    "iso:country":"YE",
    "wof:name":"Dogara",
    "wof:placetype":"locality"
},
  "geometry": {"coordinates":[44.33333,14.06667],"type":"Point"}
}