{
  "type": "Feature",
  "properties": {
    "gn:admin1_code":"19.0",
    "gn:admin2_code":"2909.0",
    "gn:asciiname":"Mahall an Najar",
    "gn:country_code":"YE",
    "gn:dem":2149,
    "gn:feature_class":"P",
    "gn:feature_code":"PPL",
    "gn:name":"Ma\u1e29all an Najar",
    "gn:population":0,
    "gn:timezone":"Asia/Aden",
    "iso:country":"YE",
    "name:und_x_variant":[
        "Ma\u1e29all an Najar"
    ],
    "wof:name":"Mahall an Najar",
    "wof:placetype":"locality"
},
  "geometry": {"coordinates":[44.07683,16.05868],"type":"Point"}
}