{
  "type": "Feature",
  "properties": {
    "gn:country":"YE",
    "gn:fcode":"PPL",
    "gn:population":5,
    "iso:country":"YE",
    "name:ara_x_preferred":[
        "Al Mi\u2018z\u0101n"
    ],
    "name:ara_x_variant":[
        "\u0627\u0644\u0645\u0639\u0632\u0627\u0628"
    ],
    "qs_pg:aaroncc":"YE",
    "qs_pg:gn_country":"YE",
    "qs_pg:gn_fcode":"PPL",
    "qs_pg:gn_pop":5,
    "qs_pg:name":"Al Mi\u2018z\u0101n",
    "qs_pg:photos_9r":0,
    "qs_pg:photos_sr":0,
    "qs_pg:pop_sr":1,
    "qs_pg:qs_pg_placetype":"locality",
    "wof:name":"Al Mi\u2018z\u0101n",
    "wof:placetype":"locality",
    "wof:population":5
},
  "geometry": {"coordinates":[43.3254,16.06049],"type":"Point"}
}