{
  "type": "Feature",
  "properties": {
    "gn:admin1_code":"8.0",
    "gn:admin2_code":"1807.0",
    "gn:asciiname":"Mahall 'Abd Allah Shaw'i",
    "gn:country_code":"YE",
    "gn:dem":35,
    "gn:feature_class":"P",
    "gn:feature_code":"PPL",
    "gn:name":"Ma\u1e29all \u2018Abd All\u0101h Shaw\u2018\u012b",
    "gn:population":0,
    "gn:timezone":"Asia/Aden",
    "iso:country":"YE",
    "name:ara_x_preferred":[
        "\u0645\u062d\u0644 \u0639\u0628\u062f \u0627\u0644\u0644\u0647 \u0634\u0648\u0639\u064a"
    ],
    "name:und_x_variant":[
        "Ma\u1e29all \u2018Abd All\u0101h Shaw\u2018\u012b"
    ],
    "wof:name":"Mahall 'Abd Allah Shaw'i",
    "wof:placetype":"locality"
},
  "geometry": {"coordinates":[42.94076,15.21702],"type":"Point"}
}