{
  "type": "Feature",
  "properties": {
    "gn:country":"YE",
    "gn:fcode":"PPL",
    "gn:pop":3,
    "iso:country":"YE",
    "name:ara_x_preferred":[
        "\u0648\u0639\u0631 \u0627\u0644\u0645\u0639\u064a\u0646"
    ],
    "name:eng_x_preferred":[
        "Wa'r Al Ma'in"
    ],
    "name:eng_x_variant":[
        "Al Gharb\u012b"
    ],
    "qs:name":"Wa\u2018r al Ma\u2018\u012bn",
    "qs:photos_9r":0,
    "qs:photos_sr":0,
    "qs:pop_sr":"1",
    "wof:name":"Wa\u2018r al Ma\u2018\u012bn",
    "wof:placetype":"locality",
    "wof:population":3
},
  "geometry": {"coordinates":[43.37843,16.88602],"type":"Point"}
}