{
  "type": "Feature",
  "properties": {
    "gn:admin1_code":"23.0",
    "gn:admin2_code":"1101.0",
    "gn:asciiname":"Az Zahrah",
    "gn:country_code":"YE",
    "gn:dem":1573,
    "gn:feature_class":"P",
    "gn:feature_code":"PPL",
    "gn:name":"Az\u0327 Z\u0327ahrah",
    "gn:population":0,
    "gn:timezone":"Asia/Aden",
    "iso:country":"YE",
    "name:ara_x_preferred":[
        "\u0627\u0644\u0638\u0647\u0631\u0629"
    ],
    "name:nno_x_preferred":[
        "Az Zahrah"
    ],
    "name:und_x_variant":[
        "Az\u0327 Z\u0327ahrah"
    ],
    "wof:name":"Az Zahrah",
    "wof:placetype":"locality"
},
  "geometry": {"coordinates":[44.1355,14.2527],"type":"Point"}
}