{
  "type": "Feature",
  "properties": {
    "gn:admin1_code":"18.0",
    "gn:admin2_code":"3006.0",
    "gn:asciiname":"Al Hazzah",
    "gn:country_code":"YE",
    "gn:dem":1276,
    "gn:feature_class":"P",
    "gn:feature_code":"PPL",
    "gn:name":"Al H\u0101zzah",
    "gn:population":0,
    "gn:timezone":"Asia/Aden",
    "iso:country":"YE",
    "name:und_x_variant":[
        "Haza",
        "Al H\u0101zzah",
        "Al \u1e28\u0101zzah"
    ],
    "wof:name":"Al Hazzah",
    "wof:placetype":"locality"
},
  "geometry": {"coordinates":[44.7028,13.8097],"type":"Point"}
}