{
  "type": "Feature",
  "properties": {
    "gn:admin1_code":"25.0",
    "gn:admin2_code":"1511.0",
    "gn:asciiname":"As Sufaylah",
    "gn:country_code":"YE",
    "gn:dem":1546,
    "gn:feature_class":"P",
    "gn:feature_code":"PPL",
    "gn:name":"As Sufaylah",
    "gn:population":0,
    "gn:timezone":"Asia/Aden",
    "iso:country":"YE",
    "wof:name":"As Sufaylah",
    "wof:placetype":"locality"
},
  "geometry": {"coordinates":[44.08165,13.57505],"type":"Point"}
}