{
  "type": "Feature",
  "properties": {
    "gn:country":"YE",
    "gn:fcode":"PPLX",
    "gn:pop":5,
    "iso:country":"YE",
    "name:ara_x_preferred":[
        "\u0627\u0644\u0635\u0648\u0628\u0640\u0629"
    ],
    "qs:name":"A\u015f \u015eawbah",
    "qs:photos_9r":0,
    "qs:photos_sr":0,
    "qs:pop_sr":"1",
    "wof:name":"A\u015f \u015eawbah",
    "wof:placetype":"neighbourhood",
    "wof:population":5
},
  "geometry": {"coordinates":[43.68988,16.18781],"type":"Point"}
}