{
  "type": "Feature",
  "properties": {
    "gn:admin1_code":"19.0",
    "gn:admin2_code":"2901.0",
    "gn:asciiname":"Al Khublan",
    "gn:country_code":"YE",
    "gn:dem":1592,
    "gn:feature_class":"P",
    "gn:feature_code":"PPL",
    "gn:name":"Al Khubl\u0101n",
    "gn:population":0,
    "gn:timezone":"Asia/Aden",
    "iso:country":"YE",
    "name:ara_x_preferred":[
        "Al Khubl\u0101n"
    ],
    "name:ara_x_variant":[
        "\u0627\u0644\u062e\u0628\u0644\u0627\u0646"
    ],
    "wof:name":"Al Khublan",
    "wof:placetype":"locality"
},
  "geometry": {"coordinates":[44.08434000000001,16.29631],"type":"Point"}
}