{
  "type": "Feature",
  "properties": {
    "gn:admin1_code":"19.0",
    "gn:admin2_code":"2912.0",
    "gn:asciiname":"Bayt Na`im",
    "gn:country_code":"YE",
    "gn:dem":1709,
    "gn:feature_class":"P",
    "gn:feature_code":"PPL",
    "gn:name":"Bayt N\u0101\u2018im",
    "gn:population":0,
    "gn:timezone":"Asia/Aden",
    "iso:country":"YE",
    "name:nno_x_preferred":[
        "Bayt Na`Im"
    ],
    "name:und_x_variant":[
        "Bayt N\u0101\u2018im"
    ],
    "wof:name":"Bayt Na`im",
    "wof:placetype":"locality"
},
  "geometry": {"coordinates":[43.78333,15.75],"type":"Point"}
}