{
  "type": "Feature",
  "properties": {
    "gn:admin1_code":"22.0",
    "gn:admin2_code":"1712.0",
    "gn:asciiname":"Zar as Saqifah",
    "gn:country_code":"YE",
    "gn:dem":309,
    "gn:feature_class":"P",
    "gn:feature_code":"PPL",
    "gn:name":"Z\u0101r as Saq\u012bfah",
    "gn:population":0,
    "gn:timezone":"Asia/Aden",
    "iso:country":"YE",
    "name:und_x_variant":[
        "Z\u0101r as Saq\u012bfah"
    ],
    "wof:name":"Zar as Saqifah",
    "wof:placetype":"locality"
},
  "geometry": {"coordinates":[43.30339,15.98245],"type":"Point"}
}