{
  "type": "Feature",
  "properties": {
    "gn:admin1_code":"8.0",
    "gn:admin2_code":"1802.0",
    "gn:asciiname":"An Nashiriyah",
    "gn:country_code":"YE",
    "gn:dem":28,
    "gn:feature_class":"P",
    "gn:feature_code":"PPL",
    "gn:name":"An N\u0101shir\u012byah",
    "gn:population":0,
    "gn:timezone":"Asia/Aden",
    "iso:country":"YE",
    "name:und_x_variant":[
        "An N\u0101shir\u012byah"
    ],
    "wof:name":"An Nashiriyah",
    "wof:placetype":"locality"
},
  "geometry": {"coordinates":[42.84796,15.73957],"type":"Point"}
}