{
  "type": "Feature",
  "properties": {
    "gn:country":"YE",
    "gn:fcode":"PPLX",
    "gn:pop":11,
    "iso:country":"YE",
    "name:ara_x_preferred":[
        "\u0627\u0644\u0642\u0627\u0641\u064a\u0629"
    ],
    "qs:name":"Al Q\u0101f\u012byah",
    "qs:photos_9r":0,
    "qs:photos_sr":0,
    "qs:pop_sr":"1",
    "wof:name":"Al Q\u0101f\u012byah",
    "wof:placetype":"neighbourhood",
    "wof:population":11
},
  "geometry": {"coordinates":[43.35548,16.32203],"type":"Point"}
}