{
  "type": "Feature",
  "properties": {
    "gn:country":"YE",
    "gn:fcode":"PPL",
    "gn:pop":10,
    "iso:country":"YE",
    "name:ara_x_preferred":[
        "\u0627\u0644\u0631\u062c\u0628\u064a\u0629"
    ],
    "name:eng_x_preferred":[
        "Ar Rajbiyah"
    ],
    "name:eng_x_variant":[
        "Al \u1e28adibah al Wis\u0163\u00e1"
    ],
    "qs:name":"Ar Rajb\u012byah",
    "qs:photos_9r":0,
    "qs:photos_sr":0,
    "qs:pop_sr":"1",
    "wof:name":"Ar Rajb\u012byah",
    "wof:placetype":"locality",
    "wof:population":10
},
  "geometry": {"coordinates":[43.83668,13.33712],"type":"Point"}
}