{
  "type": "Feature",
  "properties": {
    "gn:country":"YE",
    "gn:fcode":"PPL",
    "gn:pop":2,
    "iso:country":"YE",
    "name:ara_x_preferred":[
        "Al Liw\u0101l\u00e1"
    ],
    "name:ara_x_variant":[
        "\u0627\u0644\u0644\u0648\u0627\u0644\u0649"
    ],
    "name:eng_x_preferred":[
        "Al Liwala"
    ],
    "qs:name":"Al Liw\u0101l\u00e1",
    "qs:photos_9r":0,
    "qs:photos_sr":0,
    "qs:pop_sr":"1",
    "wof:name":"Al Liw\u0101l\u00e1",
    "wof:placetype":"locality",
    "wof:population":2
},
  "geometry": {"coordinates":[43.37733,16.34543],"type":"Point"}
}