{
  "type": "Feature",
  "properties": {
    "gn:admin1_code":"8.0",
    "gn:admin2_code":"1807.0",
    "gn:asciiname":"Al Jarab ash Sharqi Bani Ghazi",
    "gn:country_code":"YE",
    "gn:dem":152,
    "gn:feature_class":"P",
    "gn:feature_code":"PPL",
    "gn:name":"Al Jarab ash Sharq\u012b Ban\u012b Gh\u0101z\u012b",
    "gn:population":0,
    "gn:timezone":"Asia/Aden",
    "iso:country":"YE",
    "name:ara_x_preferred":[
        "\u0627\u0644\u062c\u0631\u0628 \u0627\u0644\u0634\u0631\u0642\u064a \u0628\u0646\u064a \u063a\u0627\u0632\u064a"
    ],
    "name:und_x_variant":[
        "Al Jarab ash Sharq\u012b Ban\u012b Gh\u0101z\u012b"
    ],
    "wof:name":"Al Jarab ash Sharqi Bani Ghazi",
    "wof:placetype":"locality"
},
  "geometry": {"coordinates":[43.21722000000001,15.42907],"type":"Point"}
}