{
  "type": "Feature",
  "properties": {
    "gn:country":"YE",
    "gn:fcode":"PPL",
    "gn:population":2,
    "iso:country":"YE",
    "name:ara_x_preferred":[
        "\u0627\u0644\u0645\u062f\u0629"
    ],
    "name:eng_x_preferred":[
        "Al Maddah"
    ],
    "name:eng_x_variant":[
        "\u1e28ab\u012bl I\u1e29s\u0101n"
    ],
    "qs:name":"Al Maddah",
    "qs:photos_9r":0,
    "qs:photos_sr":0,
    "qs:pop_sr":"1",
    "wof:name":"Al Maddah",
    "wof:placetype":"locality",
    "wof:population":2
},
  "geometry": {"coordinates":[43.28652,16.77248],"type":"Point"}
}