{
  "type": "Feature",
  "properties": {
    "gn:admin1_code":"19.0",
    "gn:admin2_code":"2912.0",
    "gn:asciiname":"Qatwan",
    "gn:country_code":"YE",
    "gn:dem":2199,
    "gn:feature_class":"P",
    "gn:feature_code":"PPL",
    "gn:name":"Qa\u0163w\u0101n",
    "gn:population":0,
    "gn:timezone":"Asia/Aden",
    "iso:country":"YE",
    "name:ara_x_preferred":[
        "\u0642\u0637\u0648\u0627\u0646"
    ],
    "name:und_x_variant":[
        "Qa\u0163w\u0101n"
    ],
    "wof:name":"Qatwan",
    "wof:placetype":"locality"
},
  "geometry": {"coordinates":[44.00989000000001,15.75728],"type":"Point"}
}