{
  "type": "Feature",
  "properties": {
    "gn:admin1_code":"23.0",
    "gn:admin2_code":"1108.0",
    "gn:asciiname":"Zahir",
    "gn:country_code":"YE",
    "gn:dem":1275,
    "gn:feature_class":"P",
    "gn:feature_code":"PPL",
    "gn:name":"Z\u0101\u1e29ir",
    "gn:population":0,
    "gn:timezone":"Asia/Aden",
    "iso:country":"YE",
    "name:ara_x_preferred":[
        "Z\u0101\u1e29ir"
    ],
    "name:deu_x_preferred":[
        "Zahir"
    ],
    "name:ita_x_preferred":[
        "Zahir"
    ],
    "name:pol_x_preferred":[
        "Zahir"
    ],
    "name:tur_x_preferred":[
        "Zahir"
    ],
    "wof:name":"Zahir",
    "wof:placetype":"locality"
},
  "geometry": {"coordinates":[44.06652,14.20493],"type":"Point"}
}