{
  "type": "Feature",
  "properties": {
    "gn:admin1_code":"8.0",
    "gn:admin2_code":"1802.0",
    "gn:asciiname":"Ad Dimnah",
    "gn:country_code":"YE",
    "gn:dem":57,
    "gn:feature_class":"P",
    "gn:feature_code":"PPL",
    "gn:name":"Ad Dimnah",
    "gn:population":0,
    "gn:timezone":"Asia/Aden",
    "iso:country":"YE",
    "name:und_x_variant":[
        "Dayr ad Dimnah"
    ],
    "wof:name":"Ad Dimnah",
    "wof:placetype":"locality"
},
  "geometry": {"coordinates":[42.964,15.58661],"type":"Point"}
}