{
  "type": "Feature",
  "properties": {
    "gn:admin1_code":"20.0",
    "gn:admin2_code":"1410.0",
    "gn:asciiname":"Madhwaqin",
    "gn:cc2":"YE",
    "gn:country_code":"YE",
    "gn:dem":2094,
    "gn:feature_class":"P",
    "gn:feature_code":"PPL",
    "gn:name":"Madhwaq\u012bn",
    "gn:population":0,
    "gn:timezone":"Asia/Aden",
    "iso:country":"YE",
    "name:ara_x_preferred":[
        "\u0645\u0630\u0648\u0642\u064a\u0646"
    ],
    "name:und_x_variant":[
        "Madhwaqayn",
        "Madhwagain",
        "Madhwaq\u012bn"
    ],
    "wof:name":"Madhwaqin",
    "wof:placetype":"locality"
},
  "geometry": {"coordinates":[45.62528,13.98583],"type":"Point"}
}