{
  "type": "Feature",
  "properties": {
    "gn:admin1_code":"19.0",
    "gn:admin2_code":"2913.0",
    "gn:asciiname":"Lahaf al 'Araf",
    "gn:country_code":"YE",
    "gn:dem":1110,
    "gn:feature_class":"P",
    "gn:feature_code":"PPL",
    "gn:name":"La\u1e29af al \u2018Araf",
    "gn:population":0,
    "gn:timezone":"Asia/Aden",
    "iso:country":"YE",
    "name:ara_x_preferred":[
        "\u0644\u062d\u0641 \u0627\u0644\u0639\u0631\u0641"
    ],
    "name:und_x_variant":[
        "La\u1e29af al \u2018Araf"
    ],
    "wof:name":"Lahaf al 'Araf",
    "wof:placetype":"locality"
},
  "geometry": {"coordinates":[43.79007,16.0281],"type":"Point"}
}