{
  "type": "Feature",
  "properties": {
    "gn:admin1_code":"8.0",
    "gn:admin2_code":"1807.0",
    "gn:asciiname":"Dayr `Ayyash",
    "gn:country_code":"YE",
    "gn:dem":67,
    "gn:feature_class":"P",
    "gn:feature_code":"PPL",
    "gn:name":"Dayr \u2018Ayy\u0101sh",
    "gn:population":0,
    "gn:timezone":"Asia/Aden",
    "iso:country":"YE",
    "name:und_x_variant":[
        "Dayr \u2018Ayy\u0101sh"
    ],
    "wof:name":"Dayr `Ayyash",
    "wof:placetype":"locality"
},
  "geometry": {"coordinates":[43.03247,15.2769],"type":"Point"}
}