{
  "type": "Feature",
  "properties": {
    "gn:admin1_code":"15.0",
    "gn:admin2_code":"2210.0",
    "gn:asciiname":"Athijrah",
    "gn:country_code":"YE",
    "gn:dem":2346,
    "gn:feature_class":"P",
    "gn:feature_code":"PPL",
    "gn:name":"Athijrah",
    "gn:population":0,
    "gn:timezone":"Asia/Aden",
    "iso:country":"YE",
    "wof:name":"Athijrah",
    "wof:placetype":"locality"
},
  "geometry": {"coordinates":[43.55,17.01667],"type":"Point"}
}