{
  "type": "Feature",
  "properties": {
    "gn:admin1_code":"22.0",
    "gn:admin2_code":"1706.0",
    "gn:asciiname":"Al Makhafi",
    "gn:country_code":"YE",
    "gn:dem":201,
    "gn:feature_class":"P",
    "gn:feature_code":"PPL",
    "gn:name":"Al Makh\u0101f\u012b",
    "gn:population":0,
    "gn:timezone":"Asia/Aden",
    "iso:country":"YE",
    "name:ara_x_preferred":[
        "\u0627\u0644\u0645\u062e\u0627\u0641\u064a"
    ],
    "name:und_x_variant":[
        "Al Makh\u0101f\u012b",
        "Al Makh\u0101b\u012b"
    ],
    "wof:name":"Al Makhafi",
    "wof:placetype":"locality"
},
  "geometry": {"coordinates":[43.20231,16.24302999999999],"type":"Point"}
}