{
  "type": "Feature",
  "properties": {
    "gn:admin1_code":"21.0",
    "gn:admin2_code":"1601.0",
    "gn:asciiname":"Al Mishaqah",
    "gn:country_code":"YE",
    "gn:dem":1458,
    "gn:feature_class":"P",
    "gn:feature_code":"PPL",
    "gn:name":"Al Mish\u0101qah",
    "gn:population":0,
    "gn:timezone":"Asia/Aden",
    "iso:country":"YE",
    "name:und_x_variant":[
        "Al Mish\u0101qah"
    ],
    "wof:name":"Al Mishaqah",
    "wof:placetype":"locality"
},
  "geometry": {"coordinates":[44.82975,16.72289],"type":"Point"}
}