{
  "type": "Feature",
  "properties": {
    "gn:admin1_code":"8.0",
    "gn:admin2_code":"1806.0",
    "gn:asciiname":"Mahall al Hulayli",
    "gn:country_code":"YE",
    "gn:dem":106,
    "gn:feature_class":"P",
    "gn:feature_code":"PPL",
    "gn:name":"Ma\u1e29all al Hulayl\u012b",
    "gn:population":0,
    "gn:timezone":"Asia/Aden",
    "iso:country":"YE",
    "name:und_x_variant":[
        "Ma\u1e29all al Hulayl\u012b",
        "Dayr al \u1e28ulayl"
    ],
    "wof:name":"Mahall al Hulayli",
    "wof:placetype":"locality"
},
  "geometry": {"coordinates":[43.1671,15.45567],"type":"Point"}
}