{
  "type": "Feature",
  "properties": {
    "gn:admin1_code":"22.0",
    "gn:admin2_code":"1728.0",
    "gn:asciiname":"Mahall ash Shayabi",
    "gn:country_code":"YE",
    "gn:dem":940,
    "gn:feature_class":"P",
    "gn:feature_code":"PPL",
    "gn:name":"Ma\u1e29all ash Shay\u0101b\u012b",
    "gn:population":0,
    "gn:timezone":"Asia/Aden",
    "iso:country":"YE",
    "name:und_x_variant":[
        "Ma\u1e29all ash Shay\u0101b\u012b"
    ],
    "wof:name":"Mahall ash Shayabi",
    "wof:placetype":"locality"
},
  "geometry": {"coordinates":[43.55607,15.68119],"type":"Point"}
}