{
  "type": "Feature",
  "properties": {
    "gn:admin1_code":"23.0",
    "gn:admin2_code":"1105.0",
    "gn:asciiname":"Hadar",
    "gn:country_code":"YE",
    "gn:dem":1944,
    "gn:feature_class":"P",
    "gn:feature_code":"PPL",
    "gn:name":"\u1e28a\u1e11ar",
    "gn:population":0,
    "gn:timezone":"Asia/Aden",
    "iso:country":"YE",
    "name:fra_x_preferred":[
        "Hadar"
    ],
    "name:heb_x_preferred":[
        "\u05d4\u05d3\u05e8"
    ],
    "name:ita_x_preferred":[
        "Hadar"
    ],
    "name:nld_x_preferred":[
        "Hadar"
    ],
    "name:pol_x_preferred":[
        "Hadar"
    ],
    "name:por_x_preferred":[
        "Hadar"
    ],
    "name:slk_x_preferred":[
        "Hadar"
    ],
    "name:slv_x_preferred":[
        "Hadar"
    ],
    "name:spa_x_preferred":[
        "Hadar"
    ],
    "name:swe_x_preferred":[
        "Hadar"
    ],
    "name:und_x_variant":[
        "\u1e28a\u1e11ar"
    ],
    "wof:name":"Hadar",
    "wof:placetype":"locality"
},
  "geometry": {"coordinates":[44.42913,14.03264],"type":"Point"}
}