{
  "type": "Feature",
  "properties": {
    "gn:country":"YE",
    "gn:fcode":"PPL",
    "gn:pop":4,
    "iso:country":"YE",
    "name:ara_x_preferred":[
        "\u062b\u0628\u0631"
    ],
    "name:eng_x_preferred":[
        "Thabir"
    ],
    "qs:name":"Thabir",
    "qs:photos_9r":0,
    "qs:photos_sr":0,
    "qs:pop_sr":"1",
    "wof:name":"Thabir",
    "wof:placetype":"locality",
    "wof:population":4
},
  "geometry": {"coordinates":[43.43201,16.139],"type":"Point"}
}