{
  "type": "Feature",
  "properties": {
    "gn:admin1_code":"25.0",
    "gn:admin2_code":"1505.0",
    "gn:asciiname":"Adh Dhinab",
    "gn:country_code":"YE",
    "gn:dem":657,
    "gn:feature_class":"P",
    "gn:feature_code":"PPL",
    "gn:name":"Adh Dhinab",
    "gn:population":0,
    "gn:timezone":"Asia/Aden",
    "iso:country":"YE",
    "wof:name":"Adh Dhinab",
    "wof:placetype":"locality"
},
  "geometry": {"coordinates":[43.74881,13.47932],"type":"Point"}
}