{
  "type": "Feature",
  "properties": {
    "gn:admin1_code":"23.0",
    "gn:admin2_code":"1116.0",
    "gn:asciiname":"Dhil Banwah",
    "gn:country_code":"YE",
    "gn:dem":2002,
    "gn:feature_class":"P",
    "gn:feature_code":"PPL",
    "gn:name":"Dhil Banwah",
    "gn:population":0,
    "gn:timezone":"Asia/Aden",
    "iso:country":"YE",
    "wof:name":"Dhil Banwah",
    "wof:placetype":"locality"
},
  "geometry": {"coordinates":[44.03417,13.83383],"type":"Point"}
}