{
  "type": "Feature",
  "properties": {
    "gn:admin1_code":"5.0",
    "gn:admin2_code":"2114.0",
    "gn:asciiname":"As Samadiyah",
    "gn:country_code":"YE",
    "gn:dem":1171,
    "gn:feature_class":"P",
    "gn:feature_code":"PPL",
    "gn:name":"A\u015f \u015eamad\u012byah",
    "gn:population":0,
    "gn:timezone":"Asia/Aden",
    "iso:country":"YE",
    "name:und_x_variant":[
        "Al-\u1e62amad\u012byah",
        "A\u015f \u015eamad\u012byah"
    ],
    "wof:name":"As Samadiyah",
    "wof:placetype":"locality"
},
  "geometry": {"coordinates":[47.18317,14.49749],"type":"Point"}
}