{
  "type": "Feature",
  "properties": {
    "gn:admin1_code":"8.0",
    "gn:admin2_code":"1814.0",
    "gn:asciiname":"Al Maghalisah",
    "gn:country_code":"YE",
    "gn:dem":48,
    "gn:feature_class":"P",
    "gn:feature_code":"PPL",
    "gn:name":"Al Magh\u0101lisah",
    "gn:population":0,
    "gn:timezone":"Asia/Aden",
    "iso:country":"YE",
    "name:ara_x_preferred":[
        "\u0627\u0644\u0645\u063a\u0627\u0644\u0633\u0629"
    ],
    "name:und_x_variant":[
        "Al Magh\u0101lisah"
    ],
    "wof:name":"Al Maghalisah",
    "wof:placetype":"locality"
},
  "geometry": {"coordinates":[43.13691,14.61454],"type":"Point"}
}