{
  "type": "Feature",
  "properties": {
    "gn:admin1_code":"2.0",
    "gn:admin2_code":"2406.0",
    "gn:asciiname":"Mayyun",
    "gn:country_code":"YE",
    "gn:dem":7,
    "gn:feature_class":"P",
    "gn:feature_code":"PPL",
    "gn:name":"Mayy\u016bn",
    "gn:population":0,
    "gn:timezone":"Asia/Aden",
    "iso:country":"YE",
    "name:ara_x_preferred":[
        "\u0645\u064a\u0648\u0646"
    ],
    "name:und_x_variant":[
        "Jazirat al Barim",
        "Neyun",
        "May\u016bn",
        "Meyun",
        "Mayy\u016bn"
    ],
    "wof:name":"Mayyun",
    "wof:placetype":"locality"
},
  "geometry": {"coordinates":[43.42331,12.65443],"type":"Point"}
}