{
  "type": "Feature",
  "properties": {
    "gn:country":"YE",
    "gn:fcode":"PPL",
    "gn:population":2,
    "iso:country":"YE",
    "name:ara_x_preferred":[
        "\u063a\u0648\u0644 \u0627\u0644\u0639\u0631\u062c\u0627\u062a"
    ],
    "name:eng_x_preferred":[
        "Ghawl Al 'Arjat"
    ],
    "name:eng_x_variant":[
        "Gh\u0101rib al Juhayr"
    ],
    "qs:name":"Ghawl al \u2018Arj\u0101t",
    "qs:photos_9r":0,
    "qs:photos_sr":0,
    "qs:pop_sr":"1",
    "wof:name":"Ghawl al \u2018Arj\u0101t",
    "wof:placetype":"locality",
    "wof:population":2
},
  "geometry": {"coordinates":[43.3178,16.52346],"type":"Point"}
}