{
  "type": "Feature",
  "properties": {
    "gn:country":"YE",
    "gn:fcode":"PPL",
    "gn:pop":10,
    "iso:country":"YE",
    "name:ara_x_preferred":[
        "\u0645\u062f\u0644\u064a\u0629"
    ],
    "name:eng_x_preferred":[
        "Madliyah"
    ],
    "qs:name":"Madl\u012byah",
    "qs:photos_9r":0,
    "qs:photos_sr":0,
    "qs:pop_sr":"1",
    "wof:name":"Madl\u012byah",
    "wof:placetype":"locality",
    "wof:population":10
},
  "geometry": {"coordinates":[43.48273,16.36951],"type":"Point"}
}