{
  "type": "Feature",
  "properties": {
    "gn:admin1_code":"8.0",
    "gn:admin2_code":"1817.0",
    "gn:asciiname":"'Ubayd Abkar",
    "gn:country_code":"YE",
    "gn:dem":134,
    "gn:feature_class":"P",
    "gn:feature_code":"PPL",
    "gn:name":"\u2018Ubayd Abkar",
    "gn:population":0,
    "gn:timezone":"Asia/Aden",
    "iso:country":"YE",
    "name:ara_x_preferred":[
        "\u0639\u0628\u064a\u062f \u0623\u0628\u0643\u0631"
    ],
    "name:und_x_variant":[
        "\u2018Ubayd Abkar"
    ],
    "wof:name":"'Ubayd Abkar",
    "wof:placetype":"locality"
},
  "geometry": {"coordinates":[43.30947000000001,14.53813],"type":"Point"}
}