{
  "type": "Feature",
  "properties": {
    "gn:admin1_code":"19.0",
    "gn:admin2_code":"2920.0",
    "gn:asciiname":"Bayt Ghabiq",
    "gn:country_code":"YE",
    "gn:dem":2242,
    "gn:feature_class":"P",
    "gn:feature_code":"PPL",
    "gn:name":"Bayt Gh\u0101biq",
    "gn:population":0,
    "gn:timezone":"Asia/Aden",
    "iso:country":"YE",
    "name:ara_x_preferred":[
        "\u0628\u064a\u062a \u063a\u0627\u0628\u0642"
    ],
    "name:und_x_variant":[
        "Bayt Gh\u0101biq"
    ],
    "wof:name":"Bayt Ghabiq",
    "wof:placetype":"locality"
},
  "geometry": {"coordinates":[43.96934,16.16774],"type":"Point"}
}