{
  "type": "Feature",
  "properties": {
    "gn:admin1_code":"11.0",
    "gn:admin2_code":"2012.0",
    "gn:asciiname":"As Sirm",
    "gn:country_code":"YE",
    "gn:dem":1454,
    "gn:feature_class":"P",
    "gn:feature_code":"PPL",
    "gn:name":"A\u015f \u015eirm",
    "gn:population":0,
    "gn:timezone":"Asia/Aden",
    "iso:country":"YE",
    "name:ara_x_preferred":[
        "A\u015f \u015eirm"
    ],
    "wof:name":"As Sirm",
    "wof:placetype":"locality"
},
  "geometry": {"coordinates":[44.0299,14.56762],"type":"Point"}
}