{
  "type": "Feature",
  "properties": {
    "gn:country":"YE",
    "gn:fcode":"PPL",
    "gn:population":3,
    "iso:country":"YE",
    "name:ara_x_preferred":[
        "\u062d\u0635\u0628 \u0627\u0644\u0633\u064a\u0627\u0631\u064a"
    ],
    "name:eng_x_preferred":[
        "Hasab As Siyari"
    ],
    "name:eng_x_variant":[
        "Al \u1e28illah al \u2018Uly\u0101"
    ],
    "qs:name":"\u1e28a\u015fab as Siy\u0101r\u012b",
    "qs:photos_9r":0,
    "qs:photos_sr":0,
    "qs:pop_sr":"1",
    "wof:name":"\u1e28a\u015fab as Siy\u0101r\u012b",
    "wof:placetype":"locality",
    "wof:population":3
},
  "geometry": {"coordinates":[43.82223,13.40856],"type":"Point"}
}