{
  "type": "Feature",
  "properties": {
    "gn:country":"YE",
    "gn:fcode":"PPL",
    "gn:pop":2,
    "iso:country":"YE",
    "name:ara_x_preferred":[
        "Al Ab\u0101yi\u1e11"
    ],
    "name:ara_x_variant":[
        "\u0627\u0644\u0623\u0628\u0627\u064a\u0636"
    ],
    "name:eng_x_preferred":[
        "Al Abayiu"
    ],
    "name:eng_x_variant":[
        "Al Hashamah"
    ],
    "qs:name":"Al Ab\u0101yi\u1e11",
    "qs:photos_9r":0,
    "qs:photos_sr":0,
    "qs:pop_sr":"1",
    "wof:name":"Al Ab\u0101yi\u1e11",
    "wof:placetype":"locality",
    "wof:population":2
},
  "geometry": {"coordinates":[45.06488,14.91567],"type":"Point"}
}