{
  "type": "Feature",
  "properties": {
    "gn:admin1_code":"4.0",
    "gn:admin2_code":"1917.0",
    "gn:asciiname":"An Naq`ah",
    "gn:country_code":"YE",
    "gn:dem":106,
    "gn:feature_class":"P",
    "gn:feature_code":"PPL",
    "gn:name":"An Naq\u2018ah",
    "gn:population":0,
    "gn:timezone":"Asia/Aden",
    "iso:country":"YE",
    "name:und_x_variant":[
        "An Naqa\u2018ah",
        "Al-Naqa\u2018ah",
        "An Naq\u2018ah"
    ],
    "wof:name":"An Naq`ah",
    "wof:placetype":"locality"
},
  "geometry": {"coordinates":[49.33333,14.79889],"type":"Point"}
}