{
  "type": "Feature",
  "properties": {
    "gn:admin1_code":"22.0",
    "gn:admin2_code":"1728.0",
    "gn:asciiname":"Sa`sa`ah",
    "gn:country_code":"YE",
    "gn:dem":1659,
    "gn:feature_class":"P",
    "gn:feature_code":"PPL",
    "gn:name":"\u015ea\u2018\u015fa\u2018ah",
    "gn:population":0,
    "gn:timezone":"Asia/Aden",
    "iso:country":"YE",
    "name:und_x_variant":[
        "\u015ea\u2018\u015fa\u2018ah"
    ],
    "wof:name":"Sa`sa`ah",
    "wof:placetype":"locality"
},
  "geometry": {"coordinates":[43.59977,15.68612],"type":"Point"}
}