{
  "type": "Feature",
  "properties": {
    "gn:admin1_code":"8.0",
    "gn:admin2_code":"1824.0",
    "gn:asciiname":"Al Arba`in",
    "gn:country_code":"YE",
    "gn:dem":190,
    "gn:feature_class":"P",
    "gn:feature_code":"PPL",
    "gn:name":"Al Arba\u2018\u012bn",
    "gn:population":0,
    "gn:timezone":"Asia/Aden",
    "iso:country":"YE",
    "name:und_x_variant":[
        "Al Arba\u2018\u012bn"
    ],
    "wof:name":"Al Arba`in",
    "wof:placetype":"locality"
},
  "geometry": {"coordinates":[43.38784,14.36438],"type":"Point"}
}