{
  "type": "Feature",
  "properties": {
    "gn:admin1_code":"19.0",
    "gn:admin2_code":"2901.0",
    "gn:asciiname":"Mahjar Dunih",
    "gn:country_code":"YE",
    "gn:dem":1588,
    "gn:feature_class":"P",
    "gn:feature_code":"PPL",
    "gn:name":"Ma\u1e29jar D\u016bni\u1e29",
    "gn:population":0,
    "gn:timezone":"Asia/Aden",
    "iso:country":"YE",
    "name:ara_x_preferred":[
        "\u0645\u062d\u062c\u0631 \u062f\u0648\u0646\u062d"
    ],
    "name:und_x_variant":[
        "Ma\u1e29jar D\u016bni\u1e29"
    ],
    "wof:name":"Mahjar Dunih",
    "wof:placetype":"locality"
},
  "geometry": {"coordinates":[44.09481,16.42882],"type":"Point"}
}