{
  "type": "Feature",
  "properties": {
    "gn:admin1_code":"22.0",
    "gn:admin2_code":"1728.0",
    "gn:asciiname":"Al Qutub",
    "gn:country_code":"YE",
    "gn:dem":1620,
    "gn:feature_class":"P",
    "gn:feature_code":"PPL",
    "gn:name":"Al Qu\u0163ub",
    "gn:population":0,
    "gn:timezone":"Asia/Aden",
    "iso:country":"YE",
    "name:ara_x_preferred":[
        "Al Qu\u0163ub"
    ],
    "wof:name":"Al Qutub",
    "wof:placetype":"locality"
},
  "geometry": {"coordinates":[43.61102,15.68029],"type":"Point"}
}