{
  "type": "Feature",
  "properties": {
    "gn:admin1_code":"22.0",
    "gn:admin2_code":"1710.0",
    "gn:asciiname":"Al 'Isabah",
    "gn:country_code":"YE",
    "gn:dem":1311,
    "gn:feature_class":"P",
    "gn:feature_code":"PPL",
    "gn:name":"Al \u2018I\u015f\u0101bah",
    "gn:population":8,
    "gn:timezone":"Asia/Aden",
    "iso:country":"YE",
    "name:ara_x_preferred":[
        "\u0627\u0644\u0639\u0635\u0627\u0628\u0629"
    ],
    "name:und_x_variant":[
        "Al \u2018I\u015f\u0101bah"
    ],
    "wof:name":"Al 'Isabah",
    "wof:placetype":"locality",
    "wof:population":8
},
  "geometry": {"coordinates":[43.42726,16.06427],"type":"Point"}
}