{
  "type": "Feature",
  "properties": {
    "gn:admin1_code":"19.0",
    "gn:admin2_code":"2903.0",
    "gn:asciiname":"Al Hawbaj",
    "gn:country_code":"YE",
    "gn:dem":1114,
    "gn:feature_class":"P",
    "gn:feature_code":"PPLL",
    "gn:name":"Al Hawbaj",
    "gn:population":0,
    "gn:timezone":"Asia/Aden",
    "iso:country":"YE",
    "name:ara_x_preferred":[
        "\u0627\u0644\u0647\u0648\u0628\u062c"
    ],
    "wof:name":"Al Hawbaj",
    "wof:placetype":"locality"
},
  "geometry": {"coordinates":[43.80965,16.12126],"type":"Point"}
}