{
  "type": "Feature",
  "properties": {
    "gn:admin1_code":"28.0",
    "gn:admin2_code":"1926.0",
    "gn:asciiname":"Kodih",
    "gn:country_code":"YE",
    "gn:dem":14,
    "gn:feature_class":"P",
    "gn:feature_code":"PPL",
    "gn:name":"K\u014ddih",
    "gn:population":0,
    "gn:timezone":"Asia/Aden",
    "iso:country":"YE",
    "name:und_x_variant":[
        "K\u016bdah",
        "Kodih",
        "K\u014ddih",
        "Kud\u1e29ah"
    ],
    "wof:name":"Kodih",
    "wof:placetype":"locality"
},
  "geometry": {"coordinates":[54.04142,12.64135],"type":"Point"}
}