{
  "type": "Feature",
  "properties": {
    "gn:admin1_code":"25.0",
    "gn:admin2_code":"1515.0",
    "gn:asciiname":"As Silwah",
    "gn:country_code":"YE",
    "gn:dem":1945,
    "gn:feature_class":"P",
    "gn:feature_code":"PPL",
    "gn:name":"A\u015f \u015eilw\u0101\u1e29",
    "gn:population":0,
    "gn:timezone":"Asia/Aden",
    "iso:country":"YE",
    "name:ara_x_preferred":[
        "\u0627\u0644\u0635\u0644\u0648\u0627\u062d"
    ],
    "name:und_x_variant":[
        "A\u015f \u015eilw\u0101\u1e29"
    ],
    "wof:name":"As Silwah",
    "wof:placetype":"locality"
},
  "geometry": {"coordinates":[44.13622,13.23376],"type":"Point"}
}