{
  "type": "Feature",
  "properties": {
    "gn:admin1_code":"8.0",
    "gn:admin2_code":"1819.0",
    "gn:asciiname":"Dar al Quhaym",
    "gn:country_code":"YE",
    "gn:dem":186,
    "gn:feature_class":"P",
    "gn:feature_code":"PPL",
    "gn:name":"D\u0101r al Qu\u1e29aym",
    "gn:population":0,
    "gn:timezone":"Asia/Aden",
    "iso:country":"YE",
    "name:ara_x_preferred":[
        "\u062f\u0627\u0631 \u0627\u0644\u0642\u062d\u064a\u0645"
    ],
    "name:und_x_variant":[
        "D\u0101r al Qu\u1e29aym",
        "D\u0101r al Quhaym"
    ],
    "wof:name":"Dar al Quhaym",
    "wof:placetype":"locality"
},
  "geometry": {"coordinates":[43.47122,13.88171],"type":"Point"}
}