{
  "type": "Feature",
  "properties": {
    "gn:admin1_code":"14.0",
    "gn:admin2_code":"2606.0",
    "gn:asciiname":"Al 'Alib",
    "gn:country_code":"YE",
    "gn:dem":1457,
    "gn:feature_class":"P",
    "gn:feature_code":"PPL",
    "gn:name":"Al \u2018Al\u012bb",
    "gn:population":0,
    "gn:timezone":"Asia/Aden",
    "iso:country":"YE",
    "name:ara_x_preferred":[
        "\u0627\u0644\u0639\u0644\u064a\u0628"
    ],
    "name:und_x_variant":[
        "Al \u2018Al\u012bb"
    ],
    "wof:name":"Al 'Alib",
    "wof:placetype":"locality"
},
  "geometry": {"coordinates":[45.05145,15.41592],"type":"Point"}
}