{
  "type": "Feature",
  "properties": {
    "gn:admin1_code":"8.0",
    "gn:admin2_code":"1813.0",
    "gn:asciiname":"Mahall Mutri",
    "gn:country_code":"YE",
    "gn:dem":179,
    "gn:feature_class":"P",
    "gn:feature_code":"PPL",
    "gn:name":"Ma\u1e29all Mu\u0163r\u012b",
    "gn:population":0,
    "gn:timezone":"Asia/Aden",
    "iso:country":"YE",
    "name:ara_x_preferred":[
        "\u0645\u062d\u0644 \u0645\u0637\u0631\u064a"
    ],
    "name:und_x_variant":[
        "A\u0163 \u0162\u0101yah",
        "Ma\u1e29all Mu\u0163r\u012b"
    ],
    "wof:name":"Mahall Mutri",
    "wof:placetype":"locality"
},
  "geometry": {"coordinates":[43.38252,14.88959],"type":"Point"}
}