{
  "type": "Feature",
  "properties": {
    "gn:country":"YE",
    "gn:fcode":"PPL",
    "gn:population":8,
    "iso:country":"YE",
    "name:ara_x_preferred":[
        "\u0627\u0644\u0642\u0644\u062a\u064a\u0646"
    ],
    "name:eng_x_preferred":[
        "Al Qullatayn"
    ],
    "name:eng_x_variant":[
        "Al \u1e28azm"
    ],
    "qs:name":"Al Qullatayn",
    "qs:photos_9r":0,
    "qs:photos_sr":0,
    "qs:pop_sr":"1",
    "wof:name":"Al Qullatayn",
    "wof:placetype":"locality",
    "wof:population":8
},
  "geometry": {"coordinates":[45.0189,14.05602],"type":"Point"}
}