{
  "type": "Feature",
  "properties": {
    "gn:admin1_code":"16.0",
    "gn:admin2_code":"2316.0",
    "gn:asciiname":"Bayt Abu Sab`ah",
    "gn:country_code":"YE",
    "gn:dem":2249,
    "gn:feature_class":"P",
    "gn:feature_code":"PPL",
    "gn:name":"Bayt Ab\u016b Sab\u2018ah",
    "gn:population":0,
    "gn:timezone":"Asia/Aden",
    "iso:country":"YE",
    "name:und_x_variant":[
        "Bayt Ab\u016b Sab\u2018ah"
    ],
    "wof:name":"Bayt Abu Sab`ah",
    "wof:placetype":"locality"
},
  "geometry": {"coordinates":[44.57652,15.26292],"type":"Point"}
}