{
  "type": "Feature",
  "properties": {
    "gn:admin1_code":"11.0",
    "gn:admin2_code":"2006.0",
    "gn:asciiname":"Dhi Salih",
    "gn:country_code":"YE",
    "gn:dem":1498,
    "gn:feature_class":"P",
    "gn:feature_code":"PPL",
    "gn:name":"Dh\u012b \u015e\u0101li\u1e29",
    "gn:population":0,
    "gn:timezone":"Asia/Aden",
    "iso:country":"YE",
    "name:ara_x_preferred":[
        "Dh\u012b \u015e\u0101li\u1e29"
    ],
    "wof:name":"Dhi Salih",
    "wof:placetype":"locality"
},
  "geometry": {"coordinates":[43.82781,14.27822],"type":"Point"}
}