{
  "type": "Feature",
  "properties": {
    "gn:admin1_code":"21.0",
    "gn:admin2_code":"1605.0",
    "gn:asciiname":"Umm as Sitn",
    "gn:country_code":"YE",
    "gn:dem":1064,
    "gn:feature_class":"P",
    "gn:feature_code":"PPL",
    "gn:name":"Umm as Sitn",
    "gn:population":0,
    "gn:timezone":"Asia/Aden",
    "iso:country":"YE",
    "name:ara_x_preferred":[
        "\u0623\u0645 \u0627\u0644\u0633\u062a\u0646"
    ],
    "name:und_x_variant":[
        "Umm as Sitit",
        "Umm as Sitn"
    ],
    "wof:name":"Umm as Sitn",
    "wof:placetype":"locality"
},
  "geometry": {"coordinates":[44.98631,16.00875],"type":"Point"}
}