{
  "type": "Feature",
  "properties": {
    "gn:admin1_code":"8.0",
    "gn:admin2_code":"1810.0",
    "gn:asciiname":"As Suqayya'",
    "gn:country_code":"YE",
    "gn:dem":101,
    "gn:feature_class":"P",
    "gn:feature_code":"PPL",
    "gn:name":"As Suqayy\u0101\u2019",
    "gn:population":0,
    "gn:timezone":"Asia/Aden",
    "iso:country":"YE",
    "name:und_x_variant":[
        "As Suqayy\u0101\u2019"
    ],
    "wof:name":"As Suqayya'",
    "wof:placetype":"locality"
},
  "geometry": {"coordinates":[43.13329,15.10339],"type":"Point"}
}