{
  "type": "Feature",
  "properties": {
    "gn:admin1_code":"5.0",
    "gn:admin2_code":"2107.0",
    "gn:asciiname":"Mawqis",
    "gn:country_code":"YE",
    "gn:dem":1172,
    "gn:elevation":"2.0",
    "gn:feature_class":"P",
    "gn:feature_code":"PPL",
    "gn:name":"Mawqis",
    "gn:population":0,
    "gn:timezone":"Asia/Aden",
    "iso:country":"YE",
    "name:ara_x_preferred":[
        "\u0645\u0648\u0642\u0633"
    ],
    "name:und_x_variant":[
        "M\u016bqis",
        "Mawqi\u015f",
        "Mawqis"
    ],
    "wof:name":"Mawqis",
    "wof:placetype":"locality"
},
  "geometry": {"coordinates":[45.67579,14.77664],"type":"Point"}
}