{
  "type": "Feature",
  "properties": {
    "gn:admin1_code":"11.0",
    "gn:admin2_code":"2005.0",
    "gn:asciiname":"As Sabir",
    "gn:country_code":"YE",
    "gn:dem":2238,
    "gn:feature_class":"P",
    "gn:feature_code":"PPL",
    "gn:name":"As Sab\u012br",
    "gn:population":0,
    "gn:timezone":"Asia/Aden",
    "iso:country":"YE",
    "name:und_x_variant":[
        "As Sab\u012br"
    ],
    "wof:name":"As Sabir",
    "wof:placetype":"locality"
},
  "geometry": {"coordinates":[44.06351,14.52092],"type":"Point"}
}