{
  "type": "Feature",
  "properties": {
    "gn:country":"YE",
    "gn:fcode":"PPL",
    "gn:population":25,
    "iso:country":"YE",
    "name:ara_x_preferred":[
        "\u0627\u0644\u0641\u0631\u0639"
    ],
    "qs:name":"Al Fari\u2018",
    "qs:photos_9r":0,
    "qs:photos_sr":0,
    "qs:pop_sr":"1",
    "wof:name":"Al Fari\u2018",
    "wof:placetype":"locality",
    "wof:population":25
},
  "geometry": {"coordinates":[44.17335,17.28783],"type":"Point"}
}