{
  "type": "Feature",
  "properties": {
    "gn:country":"YE",
    "gn:fcode":"PPL",
    "gn:population":3,
    "iso:country":"YE",
    "name:ara_x_preferred":[
        "\u0642\u0627\u0626\u0645 \u0646\u0639\u0645\u0627\u0646"
    ],
    "name:eng_x_preferred":[
        "Qaim Na'man"
    ],
    "name:eng_x_variant":[
        "Nakhl\u0101n"
    ],
    "name:und_x_variant":[
        "Q\u0101\u2019im Nu\u2018m\u0101n"
    ],
    "qs:name":"Q\u0101\u2019im Na\u2018m\u0101n",
    "qs:photos_9r":0,
    "qs:photos_sr":0,
    "qs:pop_sr":"1",
    "wof:name":"Q\u0101\u2019im Na\u2018m\u0101n",
    "wof:placetype":"locality",
    "wof:population":3
},
  "geometry": {"coordinates":[43.31269,16.77281],"type":"Point"}
}