{
  "type": "Feature",
  "properties": {
    "gn:admin1_code":"22.0",
    "gn:admin2_code":"1711.0",
    "gn:asciiname":"Al 'Alaya",
    "gn:country_code":"YE",
    "gn:dem":456,
    "gn:feature_class":"P",
    "gn:feature_code":"PPL",
    "gn:name":"Al \u2018Al\u0101y\u0101",
    "gn:population":5,
    "gn:timezone":"Asia/Aden",
    "iso:country":"YE",
    "name:ara_x_preferred":[
        "Al \u2018Al\u0101y\u0101"
    ],
    "name:ara_x_variant":[
        "\u0627\u0644\u0639\u0644\u0627\u064a\u0627"
    ],
    "wof:name":"Al 'Alaya",
    "wof:placetype":"locality",
    "wof:population":5
},
  "geometry": {"coordinates":[43.36477,16.03872],"type":"Point"}
}