{
  "type": "Feature",
  "properties": {
    "gn:admin1_code":"23.0",
    "gn:admin2_code":"1114.0",
    "gn:asciiname":"Ash Shawqat",
    "gn:country_code":"YE",
    "gn:dem":1525,
    "gn:feature_class":"P",
    "gn:feature_code":"PPL",
    "gn:name":"Ash Shawq\u0101t",
    "gn:population":0,
    "gn:timezone":"Asia/Aden",
    "iso:country":"YE",
    "name:und_x_variant":[
        "Ash Shawq\u0101t"
    ],
    "wof:name":"Ash Shawqat",
    "wof:placetype":"locality"
},
  "geometry": {"coordinates":[44.35,13.81667],"type":"Point"}
}