{
  "type": "Feature",
  "properties": {
    "gn:admin1_code":"19.0",
    "gn:admin2_code":"2912.0",
    "gn:asciiname":"Bayt ar Rajwi",
    "gn:country_code":"YE",
    "gn:dem":2191,
    "gn:feature_class":"P",
    "gn:feature_code":"PPL",
    "gn:name":"Bayt ar Rajw\u012b",
    "gn:population":0,
    "gn:timezone":"Asia/Aden",
    "iso:country":"YE",
    "name:ara_x_preferred":[
        "\u0628\u064a\u062a \u0627\u0644\u0631\u062c\u0648\u064a"
    ],
    "name:und_x_variant":[
        "Bayt ar Rajw\u012b"
    ],
    "wof:name":"Bayt ar Rajwi",
    "wof:placetype":"locality"
},
  "geometry": {"coordinates":[44.02474,15.79097],"type":"Point"}
}