{
  "type": "Feature",
  "properties": {
    "gn:admin1_code":"19.0",
    "gn:admin2_code":"2919.0",
    "gn:asciiname":"Bayt Salih 'Abd Allah",
    "gn:country_code":"YE",
    "gn:dem":2372,
    "gn:feature_class":"P",
    "gn:feature_code":"PPL",
    "gn:name":"Bayt \u015e\u0101li\u1e29 \u2018Abd All\u0101h",
    "gn:population":0,
    "gn:timezone":"Asia/Aden",
    "iso:country":"YE",
    "name:ara_x_preferred":[
        "\u0628\u064a\u062a \u0635\u0627\u0644\u062d \u0639\u0628\u062f \u0627\u0644\u0644\u0647"
    ],
    "name:und_x_variant":[
        "Bayt \u015e\u0101li\u1e29 \u2018Abd All\u0101h"
    ],
    "wof:name":"Bayt Salih 'Abd Allah",
    "wof:placetype":"locality"
},
  "geometry": {"coordinates":[43.97543,16.05112],"type":"Point"}
}