{
  "type": "Feature",
  "properties": {
    "gn:admin1_code":"14.0",
    "gn:admin2_code":"2607.0",
    "gn:asciiname":"An Nazilah",
    "gn:country_code":"YE",
    "gn:dem":1261,
    "gn:feature_class":"P",
    "gn:feature_code":"PPL",
    "gn:name":"An Naz\u012blah",
    "gn:population":0,
    "gn:timezone":"Asia/Aden",
    "iso:country":"YE",
    "name:ara_x_preferred":[
        "\u0627\u0644\u0646\u0632\u064a\u0644\u0629"
    ],
    "name:und_x_variant":[
        "An Naz\u012blah"
    ],
    "wof:name":"An Nazilah",
    "wof:placetype":"locality"
},
  "geometry": {"coordinates":[45.31286,15.07238],"type":"Point"}
}