{
  "type": "Feature",
  "properties": {
    "gn:admin1_code":"22.0",
    "gn:admin2_code":"1716.0",
    "gn:asciiname":"Ash Sha`ariyah",
    "gn:country_code":"YE",
    "gn:dem":1963,
    "gn:feature_class":"P",
    "gn:feature_code":"PPL",
    "gn:name":"Ash Sha\u2018\u0101r\u012byah",
    "gn:population":0,
    "gn:timezone":"Asia/Aden",
    "iso:country":"YE",
    "name:und_x_variant":[
        "Ash Sha\u2018\u0101r\u012byah"
    ],
    "wof:name":"Ash Sha`ariyah",
    "wof:placetype":"locality"
},
  "geometry": {"coordinates":[43.47888,15.98296],"type":"Point"}
}