{
  "type": "Feature",
  "properties": {
    "gn:admin1_code":"14.0",
    "gn:asciiname":"Al Muharraq",
    "gn:country_code":"YE",
    "gn:dem":1170,
    "gn:feature_class":"P",
    "gn:feature_code":"PPL",
    "gn:name":"Al Mu\u1e29arraq",
    "gn:population":0,
    "gn:timezone":"Asia/Aden",
    "iso:country":"YE",
    "name:ara_x_preferred":[
        "\u0627\u0644\u0645\u062d\u0631\u0642"
    ],
    "name:und_x_variant":[
        "Al Mu\u1e29arraq"
    ],
    "wof:name":"Al Muharraq",
    "wof:placetype":"locality"
},
  "geometry": {"coordinates":[44.54914,16.2264],"type":"Point"}
}