{
  "type": "Feature",
  "properties": {
    "gn:admin1_code":"18.0",
    "gn:admin2_code":"3008.0",
    "gn:asciiname":"Burat",
    "gn:country_code":"YE",
    "gn:dem":1335,
    "gn:feature_class":"P",
    "gn:feature_code":"PPL",
    "gn:name":"Bur\u0101t",
    "gn:population":0,
    "gn:timezone":"Asia/Aden",
    "iso:country":"YE",
    "name:ara_x_preferred":[
        "Bur\u0101t"
    ],
    "name:und_x_variant":[
        "Borat"
    ],
    "wof:name":"Burat",
    "wof:placetype":"locality"
},
  "geometry": {"coordinates":[44.61226,13.67102],"type":"Point"}
}