{
  "type": "Feature",
  "properties": {
    "gn:admin1_code":"22.0",
    "gn:admin2_code":"1717.0",
    "gn:asciiname":"Al `Adinah",
    "gn:country_code":"YE",
    "gn:dem":669,
    "gn:feature_class":"P",
    "gn:feature_code":"PPL",
    "gn:name":"Al \u2018Ad\u012bnah",
    "gn:population":0,
    "gn:timezone":"Asia/Aden",
    "iso:country":"YE",
    "name:und_x_variant":[
        "Al \u2018Ad\u012bnah"
    ],
    "wof:name":"Al `Adinah",
    "wof:placetype":"locality"
},
  "geometry": {"coordinates":[43.58103,15.85127],"type":"Point"}
}