{
  "type": "Feature",
  "properties": {
    "gn:admin1_code":"14.0",
    "gn:admin2_code":"2605.0",
    "gn:asciiname":"Dar al 'Abl",
    "gn:country_code":"YE",
    "gn:dem":2074,
    "gn:feature_class":"P",
    "gn:feature_code":"PPL",
    "gn:name":"D\u0101r al \u2018Abl",
    "gn:population":0,
    "gn:timezone":"Asia/Aden",
    "iso:country":"YE",
    "name:ara_x_preferred":[
        "\u062f\u0627\u0631 \u0627\u0644\u0639\u0628\u0644"
    ],
    "name:und_x_variant":[
        "D\u0101r al \u2018Abl"
    ],
    "wof:name":"Dar al 'Abl",
    "wof:placetype":"locality"
},
  "geometry": {"coordinates":[44.70682,15.43694],"type":"Point"}
}