{
  "type": "Feature",
  "properties": {
    "gn:admin1_code":"14.0",
    "gn:admin2_code":"2606.0",
    "gn:asciiname":"Al Mus'ad",
    "gn:country_code":"YE",
    "gn:dem":1482,
    "gn:feature_class":"P",
    "gn:feature_code":"PPL",
    "gn:name":"\u0100l Mus\u2018ad",
    "gn:population":0,
    "gn:timezone":"Asia/Aden",
    "iso:country":"YE",
    "name:ara_x_preferred":[
        "\u0622\u0644 \u0645\u0633\u0639\u062f"
    ],
    "name:und_x_variant":[
        "\u0100l Mus\u2018ad"
    ],
    "wof:name":"Al Mus'ad",
    "wof:placetype":"locality"
},
  "geometry": {"coordinates":[44.96074,15.45603],"type":"Point"}
}