{
  "type": "Feature",
  "properties": {
    "gn:admin1_code":"24.0",
    "gn:admin2_code":"2512.0",
    "gn:asciiname":"Sharaf Sharjab",
    "gn:country_code":"YE",
    "gn:dem":1866,
    "gn:feature_class":"P",
    "gn:feature_code":"PPL",
    "gn:name":"Sharaf Sharjab",
    "gn:population":0,
    "gn:timezone":"Asia/Aden",
    "iso:country":"YE",
    "name:und_x_variant":[
        "Sharjab",
        "Sharaf Sharjab"
    ],
    "wof:name":"Sharaf Sharjab",
    "wof:placetype":"locality"
},
  "geometry": {"coordinates":[44.18281,13.18393],"type":"Point"}
}