{
  "type": "Feature",
  "properties": {
    "gn:admin1_code":"15.0",
    "gn:admin2_code":"2209.0",
    "gn:asciiname":"Al Mabsal",
    "gn:country_code":"YE",
    "gn:dem":2605,
    "gn:feature_class":"P",
    "gn:feature_code":"PPL",
    "gn:name":"Al Mabsal",
    "gn:population":0,
    "gn:timezone":"Asia/Aden",
    "iso:country":"YE",
    "name:ara_x_preferred":[
        "\u0627\u0644\u0645\u0628\u0633\u0644"
    ],
    "wof:name":"Al Mabsal",
    "wof:placetype":"locality"
},
  "geometry": {"coordinates":[43.45482,16.80777],"type":"Point"}
}