{
  "type": "Feature",
  "properties": {
    "gn:admin1_code":"22.0",
    "gn:admin2_code":"1722.0",
    "gn:asciiname":"Mahall al Mawatirah",
    "gn:country_code":"YE",
    "gn:dem":230,
    "gn:feature_class":"P",
    "gn:feature_code":"PPL",
    "gn:name":"Ma\u1e29all al Maw\u0101\u0163irah",
    "gn:population":0,
    "gn:timezone":"Asia/Aden",
    "iso:country":"YE",
    "name:und_x_variant":[
        "Ma\u1e29all al Maw\u0101\u0163irah"
    ],
    "wof:name":"Mahall al Mawatirah",
    "wof:placetype":"locality"
},
  "geometry": {"coordinates":[43.26355,15.70699],"type":"Point"}
}