{
  "type": "Feature",
  "properties": {
    "gn:admin1_code":"11.0",
    "gn:admin2_code":"2011.0",
    "gn:asciiname":"Bayt an Nushayri",
    "gn:country_code":"YE",
    "gn:dem":2243,
    "gn:feature_class":"P",
    "gn:feature_code":"PPL",
    "gn:name":"Bayt an Nushayr\u012b",
    "gn:population":0,
    "gn:timezone":"Asia/Aden",
    "iso:country":"YE",
    "name:und_x_variant":[
        "Bayt an Nushayr\u012b"
    ],
    "wof:name":"Bayt an Nushayri",
    "wof:placetype":"locality"
},
  "geometry": {"coordinates":[44.23095,14.75612],"type":"Point"}
}