{
  "type": "Feature",
  "properties": {
    "gn:admin1_code":"28.0",
    "gn:admin2_code":"1926.0",
    "gn:asciiname":"Dayqaf",
    "gn:country_code":"YE",
    "gn:dem":112,
    "gn:feature_class":"P",
    "gn:feature_code":"PPL",
    "gn:name":"Dayqaf",
    "gn:population":0,
    "gn:timezone":"Asia/Aden",
    "iso:country":"YE",
    "wof:name":"Dayqaf",
    "wof:placetype":"locality"
},
  "geometry": {"coordinates":[54.2035,12.57623],"type":"Point"}
}