{
  "type": "Feature",
  "properties": {
    "gn:admin1_code":"21.0",
    "gn:admin2_code":"1602.0",
    "gn:asciiname":"As Sirar",
    "gn:country_code":"YE",
    "gn:dem":1251,
    "gn:feature_class":"P",
    "gn:feature_code":"PPL",
    "gn:name":"As Sir\u0101r",
    "gn:population":0,
    "gn:timezone":"Asia/Aden",
    "iso:country":"YE",
    "name:ara_x_preferred":[
        "Sir\u0101r"
    ],
    "name:ara_x_variant":[
        "\u0627\u0644\u0633\u0631\u0627\u0631"
    ],
    "name:und_x_variant":[
        "As Sir\u0101r"
    ],
    "wof:name":"As Sirar",
    "wof:placetype":"locality"
},
  "geometry": {"coordinates":[44.45511,16.42263],"type":"Point"}
}