{
  "type": "Feature",
  "properties": {
    "gn:admin1_code":"8.0",
    "gn:admin2_code":"1801.0",
    "gn:asciiname":"Mirdaf al `Abid",
    "gn:country_code":"YE",
    "gn:dem":110,
    "gn:feature_class":"P",
    "gn:feature_code":"PPL",
    "gn:name":"Mird\u0101f al \u2018Ab\u012bd",
    "gn:population":0,
    "gn:timezone":"Asia/Aden",
    "iso:country":"YE",
    "name:und_x_variant":[
        "Mird\u0101f al \u2018Ab\u012bd"
    ],
    "wof:name":"Mirdaf al `Abid",
    "wof:placetype":"locality"
},
  "geometry": {"coordinates":[43.10299000000001,15.66059],"type":"Point"}
}