{
  "type": "Feature",
  "properties": {
    "gn:country":"YE",
    "gn:fcode":"PPL",
    "gn:pop":7,
    "iso:country":"YE",
    "name:ara_x_preferred":[
        "\u0628\u064a\u0648\u062a \u0627\u0644\u0648\u0627\u062f\u064a"
    ],
    "name:eng_x_preferred":[
        "BuyUt Al Wadi"
    ],
    "qs:name":"Buy\u016bt al W\u0101d\u012b",
    "qs:photos_9r":0,
    "qs:photos_sr":0,
    "qs:pop_sr":"1",
    "wof:name":"Buy\u016bt al W\u0101d\u012b",
    "wof:placetype":"locality",
    "wof:population":7
},
  "geometry": {"coordinates":[43.4647,16.79955],"type":"Point"}
}