{
  "type": "Feature",
  "properties": {
    "gn:country":"YE",
    "gn:fcode":"PPL",
    "gn:population":1,
    "iso:country":"YE",
    "name:ara_x_preferred":[
        "Al \u2018Ar\u015f\u016bm"
    ],
    "name:ara_x_variant":[
        "\u0627\u0644\u0639\u0631\u0635\u0648\u0645"
    ],
    "name:eng_x_preferred":[
        "Al 'ArsUm"
    ],
    "name:eng_x_variant":[
        "Al Qiy\u0101f\u012bn"
    ],
    "qs:name":"Al \u2018Ar\u015f\u016bm",
    "qs:photos_9r":0,
    "qs:photos_sr":0,
    "qs:pop_sr":"1",
    "wof:name":"Al \u2018Ar\u015f\u016bm",
    "wof:placetype":"locality",
    "wof:population":1
},
  "geometry": {"coordinates":[43.83624,13.36514],"type":"Point"}
}