{
  "type": "Feature",
  "properties": {
    "gn:country":"YE",
    "gn:fcode":"PPL",
    "gn:pop":5,
    "iso:country":"YE",
    "name:ara_x_preferred":[
        "\u062c\u0646\u0628\u064a\u0631\u0629 \u0627\u0644\u0645\u0631\u0648\u0649"
    ],
    "name:eng_x_preferred":[
        "Janabirat Al Marwa"
    ],
    "qs:name":"Janab\u012brat al Marw\u00e1",
    "qs:photos_9r":0,
    "qs:photos_sr":0,
    "qs:pop_sr":"1",
    "wof:name":"Janab\u012brat al Marw\u00e1",
    "wof:placetype":"locality",
    "wof:population":5
},
  "geometry": {"coordinates":[43.23354,16.69923],"type":"Point"}
}