{
  "type": "Feature",
  "properties": {
    "gn:admin1_code":"16.0",
    "gn:admin2_code":"2310.0",
    "gn:asciiname":"Lakamat Qidrah",
    "gn:country_code":"YE",
    "gn:dem":2176,
    "gn:feature_class":"P",
    "gn:feature_code":"PPL",
    "gn:name":"Lakamat Qidrah",
    "gn:population":0,
    "gn:timezone":"Asia/Aden",
    "iso:country":"YE",
    "wof:name":"Lakamat Qidrah",
    "wof:placetype":"locality"
},
  "geometry": {"coordinates":[43.75334,15.01422],"type":"Point"}
}