{
  "type": "Feature",
  "properties": {
    "gn:country":"YE",
    "gn:fcode":"PPLX",
    "gn:pop":3,
    "iso:country":"YE",
    "name:ara_x_preferred":[
        "\u0627\u0644\u0645\u0642\u0627\u0645 \u0627\u0644\u0648\u0627\u0633\u0637"
    ],
    "qs:name":"Al Maq\u0101m al W\u0101si\u0163",
    "qs:photos_9r":0,
    "qs:photos_sr":0,
    "qs:pop_sr":"1",
    "wof:name":"Al Maq\u0101m al W\u0101si\u0163",
    "wof:placetype":"neighbourhood",
    "wof:population":3
},
  "geometry": {"coordinates":[44.50114,16.88781],"type":"Point"}
}