{
  "type": "Feature",
  "properties": {
    "gn:admin1_code":"16.0",
    "gn:admin2_code":"2310.0",
    "gn:asciiname":"Bartan",
    "gn:country_code":"YE",
    "gn:dem":1705,
    "gn:feature_class":"P",
    "gn:feature_code":"PPL",
    "gn:name":"Bart\u0101n",
    "gn:population":0,
    "gn:timezone":"Asia/Aden",
    "iso:country":"YE",
    "name:und_x_variant":[
        "Bart\u0101n"
    ],
    "wof:name":"Bartan",
    "wof:placetype":"locality"
},
  "geometry": {"coordinates":[43.75397,15.0899],"type":"Point"}
}