{
  "type": "Feature",
  "properties": {
    "gn:country":"YE",
    "gn:fcode":"PPL",
    "gn:pop":2,
    "iso:country":"YE",
    "name:ara_x_preferred":[
        "\u0627\u0644\u0639\u062a\u0645\u0629"
    ],
    "name:eng_x_preferred":[
        "Al 'Atamah"
    ],
    "name:fra_x_preferred":[
        "Al Madfan"
    ],
    "qs:name":"Al \u2018Atamah",
    "qs:photos_9r":0,
    "qs:photos_sr":0,
    "qs:pop_sr":"1",
    "wof:name":"Al \u2018Atamah",
    "wof:placetype":"locality",
    "wof:population":2
},
  "geometry": {"coordinates":[43.34977,16.16346],"type":"Point"}
}