{
  "type": "Feature",
  "properties": {
    "gn:country":"YE",
    "gn:fcode":"PPL",
    "gn:population":4,
    "iso:country":"YE",
    "name:ara_x_preferred":[
        "\u0627\u0644\u0634\u0639\u0627\u0628"
    ],
    "name:und_x_variant":[
        "Ash Shi\u2018\u0101b"
    ],
    "qs:name":"Ash Shu\u2018\u0101b",
    "qs:photos_9r":0,
    "qs:photos_sr":0,
    "qs:pop_sr":"1",
    "wof:name":"Ash Shu\u2018\u0101b",
    "wof:placetype":"locality",
    "wof:population":4
},
  "geometry": {"coordinates":[43.7141,16.0591],"type":"Point"}
}