{
  "type": "Feature",
  "properties": {
    "gn:admin1_code":"8.0",
    "gn:admin2_code":"1815.0",
    "gn:asciiname":"Ya`uth al Azyab al Ahmad",
    "gn:country_code":"YE",
    "gn:dem":106,
    "gn:feature_class":"P",
    "gn:feature_code":"PPL",
    "gn:name":"Ya\u2018\u016bth al Azyab al A\u1e29mad",
    "gn:population":0,
    "gn:timezone":"Asia/Aden",
    "iso:country":"YE",
    "name:ara_x_preferred":[
        "\u064a\u0639\u0648\u062b \u0627\u0644\u0627\u0632\u064a\u0628 \u0623\u062d\u0645\u062f"
    ],
    "name:und_x_variant":[
        "Bayt al Azyab",
        "Ya\u2018\u016bth al Azyab al A\u1e29mad"
    ],
    "wof:name":"Ya`uth al Azyab al Ahmad",
    "wof:placetype":"locality"
},
  "geometry": {"coordinates":[43.23093,14.72446],"type":"Point"}
}