{
  "type": "Feature",
  "properties": {
    "gn:country":"YE",
    "gn:fcode":"PPL",
    "gn:population":14,
    "iso:country":"YE",
    "name:ara_x_preferred":[
        "\u0628\u064a\u062a \u0633\u0648\u0627\u062f\u064a"
    ],
    "name:eng_x_preferred":[
        "Bayt Sawadi"
    ],
    "name:eng_x_variant":[
        "Qullat Ja\u2018\u0101r"
    ],
    "qs:name":"Bayt Saw\u0101d\u012b",
    "qs:photos_9r":0,
    "qs:photos_sr":0,
    "qs:pop_sr":"1",
    "wof:name":"Bayt Saw\u0101d\u012b",
    "wof:placetype":"locality",
    "wof:population":14
},
  "geometry": {"coordinates":[43.27299,16.92351],"type":"Point"}
}