{
  "type": "Feature",
  "properties": {
    "gn:country":"YE",
    "gn:fcode":"PPL",
    "gn:population":5,
    "iso:country":"YE",
    "name:ara_x_preferred":[
        "\u0634\u0639\u0628 \u062d\u0645\u0631"
    ],
    "name:eng_x_preferred":[
        "Sha'b Hamr"
    ],
    "name:eng_x_variant":[
        "Al \u2018A\u015f\u0101yir"
    ],
    "qs:name":"Sha\u2018b \u1e28amr",
    "qs:photos_9r":0,
    "qs:photos_sr":0,
    "qs:pop_sr":"1",
    "wof:name":"Sha\u2018b \u1e28amr",
    "wof:placetype":"locality",
    "wof:population":5
},
  "geometry": {"coordinates":[43.80394,13.4203],"type":"Point"}
}