{
  "type": "Feature",
  "properties": {
    "gn:admin1_code":"19.0",
    "gn:admin2_code":"2908.0",
    "gn:asciiname":"Al Ma`ali",
    "gn:country_code":"YE",
    "gn:dem":1598,
    "gn:feature_class":"P",
    "gn:feature_code":"PPL",
    "gn:name":"Al Ma\u2018\u0101l\u012b",
    "gn:population":0,
    "gn:timezone":"Asia/Aden",
    "iso:country":"YE",
    "name:ara_x_preferred":[
        "\u0627\u0644\u0645\u0639\u0627\u0644\u064a"
    ],
    "name:und_x_variant":[
        "Al Ma\u2018\u0101l\u012b"
    ],
    "wof:name":"Al Ma`ali",
    "wof:placetype":"locality"
},
  "geometry": {"coordinates":[43.72137,16.06883],"type":"Point"}
}