{
  "type": "Feature",
  "properties": {
    "gn:admin1_code":"25.0",
    "gn:admin2_code":"1513.0",
    "gn:asciiname":"Ar Ruzmah",
    "gn:country_code":"YE",
    "gn:dem":891,
    "gn:feature_class":"P",
    "gn:feature_code":"PPL",
    "gn:name":"Ar Ruzmah",
    "gn:population":0,
    "gn:timezone":"Asia/Aden",
    "iso:country":"YE",
    "wof:name":"Ar Ruzmah",
    "wof:placetype":"locality"
},
  "geometry": {"coordinates":[44.41523,13.40192],"type":"Point"}
}