{
  "type": "Feature",
  "properties": {
    "gn:admin1_code":"8.0",
    "gn:admin2_code":"1810.0",
    "gn:asciiname":"Al Bawsiyah",
    "gn:country_code":"YE",
    "gn:dem":61,
    "gn:feature_class":"P",
    "gn:feature_code":"PPL",
    "gn:name":"Al Baw\u015f\u012byah",
    "gn:population":0,
    "gn:timezone":"Asia/Aden",
    "iso:country":"YE",
    "name:und_x_variant":[
        "Al Baw\u015f\u012byah"
    ],
    "wof:name":"Al Bawsiyah",
    "wof:placetype":"locality"
},
  "geometry": {"coordinates":[43.05065,15.07736],"type":"Point"}
}