{
  "type": "Feature",
  "properties": {
    "gn:admin1_code":"24.0",
    "gn:admin2_code":"2508.0",
    "gn:asciiname":"Bayt Saywad",
    "gn:country_code":"YE",
    "gn:dem":542,
    "gn:feature_class":"P",
    "gn:feature_code":"PPL",
    "gn:name":"Bayt Saywad",
    "gn:population":0,
    "gn:timezone":"Asia/Aden",
    "iso:country":"YE",
    "wof:name":"Bayt Saywad",
    "wof:placetype":"locality"
},
  "geometry": {"coordinates":[44.85139,13.4525],"type":"Point"}
}