{
  "type": "Feature",
  "properties": {
    "gn:country":"YE",
    "gn:fcode":"PPL",
    "gn:pop":3,
    "iso:country":"YE",
    "name:ara_x_preferred":[
        "\u0627\u0644\u062e\u0631\u0627\u0628\u0629"
    ],
    "qs:name":"Al Khar\u0101bah",
    "qs:photos_9r":0,
    "qs:photos_sr":0,
    "qs:pop_sr":"1",
    "wof:name":"Al Khar\u0101bah",
    "wof:placetype":"locality",
    "wof:population":3
},
  "geometry": {"coordinates":[45.3846,14.672],"type":"Point"}
}