{
  "type": "Feature",
  "properties": {
    "gn:admin1_code":"25.0",
    "gn:admin2_code":"1522.0",
    "gn:asciiname":"Adh Dhunayb",
    "gn:country_code":"YE",
    "gn:dem":1159,
    "gn:feature_class":"P",
    "gn:feature_code":"PPL",
    "gn:name":"Adh Dhunayb",
    "gn:population":0,
    "gn:timezone":"Asia/Aden",
    "iso:country":"YE",
    "wof:name":"Adh Dhunayb",
    "wof:placetype":"locality"
},
  "geometry": {"coordinates":[44.21416,13.27736],"type":"Point"}
}