{
  "type": "Feature",
  "properties": {
    "gn:country":"YE",
    "gn:fcode":"PPL",
    "gn:pop":15,
    "iso:country":"YE",
    "name:ara_x_preferred":[
        "\u0627\u0644\u0645\u062e\u0631\u0648\u0645"
    ],
    "name:eng_x_preferred":[
        "Al MakhrUm"
    ],
    "qs:name":"Al Makhr\u016bm",
    "qs:photos_9r":0,
    "qs:photos_sr":0,
    "qs:pop_sr":"1",
    "wof:name":"Al Makhr\u016bm",
    "wof:placetype":"locality",
    "wof:population":15
},
  "geometry": {"coordinates":[44.45854,16.67534],"type":"Point"}
}