{
  "type": "Feature",
  "properties": {
    "gn:admin1_code":"21.0",
    "gn:admin2_code":"1608.0",
    "gn:asciiname":"Al `Adbah",
    "gn:country_code":"YE",
    "gn:dem":1155,
    "gn:feature_class":"P",
    "gn:feature_code":"PPL",
    "gn:name":"Al \u2018A\u1e11bah",
    "gn:population":0,
    "gn:timezone":"Asia/Aden",
    "iso:country":"YE",
    "name:und_x_variant":[
        "Al \u2018A\u1e11bah"
    ],
    "wof:name":"Al `Adbah",
    "wof:placetype":"locality"
},
  "geometry": {"coordinates":[44.66184000000001,16.09141],"type":"Point"}
}