{
  "type": "Feature",
  "properties": {
    "gn:gn_country":"YE",
    "gn:gn_fcode":"PPL",
    "gn:gn_pop":12,
    "gn:population":12,
    "iso:country":"YE",
    "name:ara_x_preferred":[
        "\u0627\u0644\u0645\u0634\u064a\u062d\u064a\u0629"
    ],
    "name:eng_x_preferred":[
        "Al Mushayhiyah"
    ],
    "name:unk_x_variant":[
        "\u0627\u0644\u0645\u0634\u064a\u062d\u064a\u0629"
    ],
    "qs_pg:aaroncc":"YE",
    "qs_pg:gn_country":"YE",
    "qs_pg:gn_fcode":"PPL",
    "qs_pg:gn_pop":12,
    "qs_pg:name":"Al Mushay\u1e29\u012byah",
    "qs_pg:photos_9r":0,
    "qs_pg:photos_sr":0,
    "qs_pg:pop_sr":1,
    "qs_pg:qs_pg_placetype":"locality",
    "wof:name":"Al Mushay\u1e29\u012byah",
    "wof:placetype":"locality",
    "wof:population":12
},
  "geometry": {"coordinates":[43.18763,16.2368],"type":"Point"}
}