{
  "type": "Feature",
  "properties": {
    "gn:admin1_code":"19.0",
    "gn:admin2_code":"2915.0",
    "gn:asciiname":"Bayt al Mahyaf",
    "gn:country_code":"YE",
    "gn:dem":2121,
    "gn:feature_class":"P",
    "gn:feature_code":"PPL",
    "gn:name":"Bayt al Mahyaf",
    "gn:population":0,
    "gn:timezone":"Asia/Aden",
    "iso:country":"YE",
    "wof:name":"Bayt al Mahyaf",
    "wof:placetype":"locality"
},
  "geometry": {"coordinates":[43.74341,15.71664],"type":"Point"}
}