{
  "type": "Feature",
  "properties": {
    "gn:admin1_code":"23.0",
    "gn:admin2_code":"1115.0",
    "gn:asciiname":"Ad Dahanah",
    "gn:country_code":"YE",
    "gn:dem":2285,
    "gn:feature_class":"P",
    "gn:feature_code":"PPL",
    "gn:name":"Ad Dahanah",
    "gn:population":0,
    "gn:timezone":"Asia/Aden",
    "iso:country":"YE",
    "name:und_x_variant":[
        "Ad Dahana",
        "\u1e28az\u0327\u0101rah",
        "Ad Dahanah",
        "Ad Dahama"
    ],
    "wof:name":"Ad Dahanah",
    "wof:placetype":"locality"
},
  "geometry": {"coordinates":[44.18379,13.8922],"type":"Point"}
}