{
  "type": "Feature",
  "properties": {
    "gn:admin1_code":"8.0",
    "gn:admin2_code":"1812.0",
    "gn:asciiname":"Zahran",
    "gn:country_code":"YE",
    "gn:dem":877,
    "gn:feature_class":"P",
    "gn:feature_code":"PPL",
    "gn:name":"Z\u0327ahr\u0101n",
    "gn:population":0,
    "gn:timezone":"Asia/Aden",
    "iso:country":"YE",
    "name:ara_x_preferred":[
        "\u0638\u0647\u0631\u0627\u0646"
    ],
    "name:ceb_x_preferred":[
        "Zahran"
    ],
    "name:und_x_variant":[
        "Z\u0327ahr\u0101n"
    ],
    "wof:name":"Zahran",
    "wof:placetype":"locality"
},
  "geometry": {"coordinates":[43.43093,14.92921],"type":"Point"}
}