{
  "type": "Feature",
  "properties": {
    "gn:admin1_code":"10.0",
    "gn:admin2_code":"2707.0",
    "gn:asciiname":"Mahall al Ghabr",
    "gn:country_code":"YE",
    "gn:dem":424,
    "gn:feature_class":"P",
    "gn:feature_code":"PPL",
    "gn:name":"Ma\u1e29all al Ghabr",
    "gn:population":0,
    "gn:timezone":"Asia/Aden",
    "iso:country":"YE",
    "name:und_x_variant":[
        "Ma\u1e29all al Ghabr"
    ],
    "wof:name":"Mahall al Ghabr",
    "wof:placetype":"locality"
},
  "geometry": {"coordinates":[43.45256,15.13501],"type":"Point"}
}