{
  "type": "Feature",
  "properties": {
    "gn:admin1_code":"14.0",
    "gn:asciiname":"Az Zabarah as Sufla",
    "gn:country_code":"YE",
    "gn:dem":1181,
    "gn:feature_class":"P",
    "gn:feature_code":"PPL",
    "gn:name":"Az Zab\u0101rah as Sufl\u00e1",
    "gn:population":0,
    "gn:timezone":"Asia/Aden",
    "iso:country":"YE",
    "name:ara_x_preferred":[
        "\u0627\u0644\u0632\u0628\u0627\u0631\u0629 \u0627\u0644\u0633\u0641\u0644\u0649"
    ],
    "name:und_x_variant":[
        "Az Zab\u0101rah as Sufl\u00e1"
    ],
    "wof:name":"Az Zabarah as Sufla",
    "wof:placetype":"locality"
},
  "geometry": {"coordinates":[44.52516,16.25082],"type":"Point"}
}