{
  "type": "Feature",
  "properties": {
    "gn:admin1_code":"23.0",
    "gn:admin2_code":"1101.0",
    "gn:asciiname":"Al Mashawif",
    "gn:country_code":"YE",
    "gn:dem":1275,
    "gn:feature_class":"P",
    "gn:feature_code":"PPL",
    "gn:name":"Al Mash\u0101w\u012bf",
    "gn:population":0,
    "gn:timezone":"Asia/Aden",
    "iso:country":"YE",
    "name:ara_x_preferred":[
        "\u0627\u0644\u0645\u0634\u0627\u0648\u064a\u0641"
    ],
    "name:und_x_variant":[
        "Al Mash\u0101w\u012bf"
    ],
    "wof:name":"Al Mashawif",
    "wof:placetype":"locality"
},
  "geometry": {"coordinates":[44.08661,14.28624],"type":"Point"}
}