{
  "type": "Feature",
  "properties": {
    "gn:admin1_code":"19.0",
    "gn:admin2_code":"2920.0",
    "gn:asciiname":"Far` Bani Malik",
    "gn:country_code":"YE",
    "gn:dem":2035,
    "gn:feature_class":"P",
    "gn:feature_code":"PPL",
    "gn:name":"Far\u2018 Ban\u012b M\u0101lik",
    "gn:population":0,
    "gn:timezone":"Asia/Aden",
    "iso:country":"YE",
    "name:und_x_variant":[
        "Far\u2018 Ban\u012b M\u0101lik"
    ],
    "wof:name":"Far` Bani Malik",
    "wof:placetype":"locality"
},
  "geometry": {"coordinates":[43.91357,16.09658],"type":"Point"}
}