{
  "type": "Feature",
  "properties": {
    "gn:admin1_code":"19.0",
    "gn:admin2_code":"2912.0",
    "gn:asciiname":"Bayt al Madan",
    "gn:country_code":"YE",
    "gn:dem":2243,
    "gn:feature_class":"P",
    "gn:feature_code":"PPL",
    "gn:name":"Bayt al Madan",
    "gn:population":0,
    "gn:timezone":"Asia/Aden",
    "iso:country":"YE",
    "wof:name":"Bayt al Madan",
    "wof:placetype":"locality"
},
  "geometry": {"coordinates":[43.94167,15.81168],"type":"Point"}
}