{
  "type": "Feature",
  "properties": {
    "gn:admin1_code":"25.0",
    "gn:admin2_code":"1504.0",
    "gn:asciiname":"As Sahhah",
    "gn:country_code":"YE",
    "gn:dem":1068,
    "gn:feature_class":"P",
    "gn:feature_code":"PPL",
    "gn:name":"As Sa\u1e29\u1e29ah",
    "gn:population":0,
    "gn:timezone":"Asia/Aden",
    "iso:country":"YE",
    "name:ara_x_preferred":[
        "\u0627\u0644\u0633\u062d\u0629"
    ],
    "name:und_x_variant":[
        "As Sa\u1e29\u1e29ah",
        "As Su\u1e29\u1e29ah"
    ],
    "wof:name":"As Sahhah",
    "wof:placetype":"locality"
},
  "geometry": {"coordinates":[43.80208,13.70301],"type":"Point"}
}