{
  "type": "Feature",
  "properties": {
    "gn:admin1_code":"15.0",
    "gn:admin2_code":"2211.0",
    "gn:asciiname":"Tubashi`ah",
    "gn:country_code":"YE",
    "gn:dem":1968,
    "gn:feature_class":"P",
    "gn:feature_code":"PPL",
    "gn:name":"Tub\u0101shi\u2018ah",
    "gn:population":0,
    "gn:timezone":"Asia/Aden",
    "iso:country":"YE",
    "name:ara_x_preferred":[
        "\u062a\u0628\u0627\u0634\u0639\u0629"
    ],
    "name:und_x_variant":[
        "Tub\u0101shi\u2018ah"
    ],
    "wof:name":"Tubashi`ah",
    "wof:placetype":"locality"
},
  "geometry": {"coordinates":[43.6112,17.04284],"type":"Point"}
}