{
  "type": "Feature",
  "properties": {
    "gn:admin1_code":"25.0",
    "gn:admin2_code":"1515.0",
    "gn:asciiname":"Dar al Athabah",
    "gn:country_code":"YE",
    "gn:dem":2098,
    "gn:feature_class":"P",
    "gn:feature_code":"PPL",
    "gn:name":"D\u0101r al Ath\u0101bah",
    "gn:population":0,
    "gn:timezone":"Asia/Aden",
    "iso:country":"YE",
    "name:ara_x_preferred":[
        "\u062f\u0627\u0631 \u0627\u0644\u0627\u062b\u0627\u0628\u0629"
    ],
    "name:und_x_variant":[
        "D\u0101r al Ath\u0101bah"
    ],
    "wof:name":"Dar al Athabah",
    "wof:placetype":"locality"
},
  "geometry": {"coordinates":[44.15359,13.23157],"type":"Point"}
}