{
  "type": "Feature",
  "properties": {
    "gn:admin1_code":"11.0",
    "gn:admin2_code":"1102.0",
    "gn:asciiname":"Al `Urr",
    "gn:country_code":"YE",
    "gn:dem":2688,
    "gn:feature_class":"P",
    "gn:feature_code":"PPL",
    "gn:name":"Al \u2018Urr",
    "gn:population":0,
    "gn:timezone":"Asia/Aden",
    "iso:country":"YE",
    "name:ara_x_preferred":[
        "Al \u2018Urr"
    ],
    "name:ara_x_variant":[
        "\u0627\u0644\u0639\u0631"
    ],
    "name:und_x_variant":[
        "Al \u2018Arr"
    ],
    "wof:name":"Al `Urr",
    "wof:placetype":"locality"
},
  "geometry": {"coordinates":[44.34756,14.35975],"type":"Point"}
}