{
  "type": "Feature",
  "properties": {
    "gn:admin1_code":"16.0",
    "gn:admin2_code":"2302.0",
    "gn:asciiname":"Bayt Shayi'",
    "gn:country_code":"YE",
    "gn:dem":2448,
    "gn:feature_class":"P",
    "gn:feature_code":"PPL",
    "gn:name":"Bayt Sh\u0101yi\u2018",
    "gn:population":0,
    "gn:timezone":"Asia/Aden",
    "iso:country":"YE",
    "name:ara_x_preferred":[
        "\u0628\u064a\u062a \u0634\u0627\u064a\u0639"
    ],
    "name:und_x_variant":[
        "Bayt Sh\u0101yi\u2018"
    ],
    "wof:name":"Bayt Shayi'",
    "wof:placetype":"locality"
},
  "geometry": {"coordinates":[44.24639000000001,15.80032],"type":"Point"}
}