{
  "type": "Feature",
  "properties": {
    "gn:admin1_code":"11.0",
    "gn:admin2_code":"2010.0",
    "gn:asciiname":"Al Qa`idah",
    "gn:country_code":"YE",
    "gn:dem":2459,
    "gn:feature_class":"P",
    "gn:feature_code":"PPL",
    "gn:name":"Al Q\u0101\u2018idah",
    "gn:population":0,
    "gn:timezone":"Asia/Aden",
    "iso:country":"YE",
    "name:und_x_variant":[
        "Al Q\u0101\u2018idah"
    ],
    "wof:name":"Al Qa`idah",
    "wof:placetype":"locality"
},
  "geometry": {"coordinates":[44.31927,14.48695],"type":"Point"}
}