{
  "type": "Feature",
  "properties": {
    "gn:admin1_code":"22.0",
    "gn:admin2_code":"1707.0",
    "gn:asciiname":"As San'ah",
    "gn:country_code":"YE",
    "gn:dem":1380,
    "gn:feature_class":"P",
    "gn:feature_code":"PPL",
    "gn:name":"A\u015f \u015e\u0101n\u2018ah",
    "gn:population":0,
    "gn:timezone":"Asia/Aden",
    "iso:country":"YE",
    "name:ara_x_preferred":[
        "\u0627\u0644\u0635\u0627\u0646\u0639\u0629"
    ],
    "name:und_x_variant":[
        "A\u015f \u015e\u0101n\u2018ah"
    ],
    "wof:name":"As San'ah",
    "wof:placetype":"locality"
},
  "geometry": {"coordinates":[43.40943,16.1268],"type":"Point"}
}