{
  "type": "Feature",
  "properties": {
    "gn:admin1_code":"23.0",
    "gn:admin2_code":"1106.0",
    "gn:asciiname":"Ma`wad",
    "gn:country_code":"YE",
    "gn:dem":3030,
    "gn:feature_class":"P",
    "gn:feature_code":"PPL",
    "gn:name":"Ma\u2018wad",
    "gn:population":0,
    "gn:timezone":"Asia/Aden",
    "iso:country":"YE",
    "name:und_x_variant":[
        "Ma\u2018wad"
    ],
    "wof:name":"Ma`wad",
    "wof:placetype":"locality"
},
  "geometry": {"coordinates":[44.25673,14.12367],"type":"Point"}
}