{
  "type": "Feature",
  "properties": {
    "gn:admin1_code":"8.0",
    "gn:admin2_code":"1817.0",
    "gn:asciiname":"Al Qasimiyah",
    "gn:country_code":"YE",
    "gn:dem":82,
    "gn:feature_class":"P",
    "gn:feature_code":"PPL",
    "gn:name":"Al Q\u0101sim\u012byah",
    "gn:population":0,
    "gn:timezone":"Asia/Aden",
    "iso:country":"YE",
    "name:und_x_variant":[
        "Al Q\u0101sim\u012byah"
    ],
    "wof:name":"Al Qasimiyah",
    "wof:placetype":"locality"
},
  "geometry": {"coordinates":[43.24196,14.31955],"type":"Point"}
}