{
  "type": "Feature",
  "properties": {
    "gn:admin1_code":"18.0",
    "gn:admin2_code":"3008.0",
    "gn:asciiname":"Sawwadah",
    "gn:cc2":"YE",
    "gn:country_code":"YE",
    "gn:dem":1398,
    "gn:feature_class":"P",
    "gn:feature_code":"PPL",
    "gn:name":"Saww\u0101dah",
    "gn:population":0,
    "gn:timezone":"Asia/Aden",
    "iso:country":"YE",
    "name:und_x_variant":[
        "Suwada",
        "Saww\u0101dah"
    ],
    "wof:name":"Sawwadah",
    "wof:placetype":"locality"
},
  "geometry": {"coordinates":[44.65,13.65],"type":"Point"}
}