{
  "type": "Feature",
  "properties": {
    "gn:country":"YE",
    "gn:fcode":"PPL",
    "gn:population":21,
    "iso:country":"YE",
    "name:ara_x_preferred":[
        "\u062d\u0628\u064a\u0644 \u0627\u0644\u0631\u0643\u0628 \u0627\u0644\u0634\u0631\u0642\u064a"
    ],
    "name:eng_x_preferred":[
        "Habil Ar Rakkib Ash Sharqi"
    ],
    "qs_pg:aaroncc":"YE",
    "qs_pg:gn_country":"YE",
    "qs_pg:gn_fcode":"PPL",
    "qs_pg:gn_pop":21,
    "qs_pg:name":"\u1e28ab\u012bl ar Rakkib ash Sharq\u012b",
    "qs_pg:photos_9r":0,
    "qs_pg:photos_sr":0,
    "qs_pg:pop_sr":1,
    "qs_pg:qs_pg_placetype":"locality",
    "wof:name":"\u1e28ab\u012bl ar Rakkib ash Sharq\u012b",
    "wof:placetype":"locality",
    "wof:population":21
},
  "geometry": {"coordinates":[43.37212,16.16351],"type":"Point"}
}