{
  "type": "Feature",
  "properties": {
    "gn:admin1_code":"22.0",
    "gn:admin2_code":"1718.0",
    "gn:asciiname":"Al Hawwan",
    "gn:country_code":"YE",
    "gn:dem":1928,
    "gn:feature_class":"P",
    "gn:feature_code":"PPL",
    "gn:name":"Al Haww\u0101n",
    "gn:population":0,
    "gn:timezone":"Asia/Aden",
    "iso:country":"YE",
    "name:und_x_variant":[
        "Al Haww\u0101n"
    ],
    "wof:name":"Al Hawwan",
    "wof:placetype":"locality"
},
  "geometry": {"coordinates":[43.71319,15.65724],"type":"Point"}
}