{
  "type": "Feature",
  "properties": {
    "gn:admin1_code":"8.0",
    "gn:admin2_code":"1810.0",
    "gn:asciiname":"Ad Duyur",
    "gn:country_code":"YE",
    "gn:dem":373,
    "gn:feature_class":"P",
    "gn:feature_code":"PPL",
    "gn:name":"Ad Duy\u016br",
    "gn:population":0,
    "gn:timezone":"Asia/Aden",
    "iso:country":"YE",
    "name:ara_x_preferred":[
        "Ad Duy\u016br"
    ],
    "name:und_x_variant":[
        "Ban\u012b Zayd"
    ],
    "wof:name":"Ad Duyur",
    "wof:placetype":"locality"
},
  "geometry": {"coordinates":[43.44092,15.03603],"type":"Point"}
}