{
  "type": "Feature",
  "properties": {
    "gn:admin1_code":"16.0",
    "gn:admin2_code":"2313.0",
    "gn:asciiname":"Bani Sha'i'",
    "gn:country_code":"YE",
    "gn:dem":2432,
    "gn:feature_class":"P",
    "gn:feature_code":"PPL",
    "gn:name":"Ban\u012b Sh\u0101\u2019i\u2018",
    "gn:population":0,
    "gn:timezone":"Asia/Aden",
    "iso:country":"YE",
    "name:ara_x_preferred":[
        "\u0628\u0646\u064a \u0634\u0627\u0626\u0639"
    ],
    "name:und_x_variant":[
        "Ban\u012b Sh\u0101\u2019i\u2018"
    ],
    "wof:name":"Bani Sha'i'",
    "wof:placetype":"locality"
},
  "geometry": {"coordinates":[44.59091,15.35295],"type":"Point"}
}