{
  "type": "Feature",
  "properties": {
    "gn:country":"YE",
    "gn:fcode":"PPL",
    "gn:pop":15,
    "iso:country":"YE",
    "name:ara_x_preferred":[
        "\u0623\u0643\u0628\u0631"
    ],
    "name:eng_x_preferred":[
        "Akbar"
    ],
    "name:eng_x_variant":[
        "Al Mirbakh"
    ],
    "qs:name":"Akbar",
    "qs:photos_9r":0,
    "qs:photos_sr":0,
    "qs:pop_sr":"1",
    "wd:wordcount":15176,
    "wof:name":"Akbar",
    "wof:placetype":"locality",
    "wof:population":15
},
  "geometry": {"coordinates":[43.565,17.21902],"type":"Point"}
}