{
  "type": "Feature",
  "properties": {
    "gn:country":"YE",
    "gn:fcode":"PPL",
    "gn:pop":3,
    "iso:country":"YE",
    "name:ara_x_preferred":[
        "\u0627\u0644\u0645\u062d\u062c\u0646"
    ],
    "name:eng_x_preferred":[
        "Al Mahjan"
    ],
    "name:eng_x_variant":[
        "Al Mawq\u2018\u012b"
    ],
    "qs:name":"Al Ma\u1e29jan",
    "qs:photos_9r":0,
    "qs:photos_sr":0,
    "qs:pop_sr":"1",
    "wof:name":"Al Ma\u1e29jan",
    "wof:placetype":"locality",
    "wof:population":3
},
  "geometry": {"coordinates":[45.34675,14.22395],"type":"Point"}
}