{
  "type": "Feature",
  "properties": {
    "gn:admin1_code":"10.0",
    "gn:admin2_code":"2707.0",
    "gn:asciiname":"Al Ma`mur",
    "gn:country_code":"YE",
    "gn:dem":1223,
    "gn:feature_class":"P",
    "gn:feature_code":"PPL",
    "gn:name":"Al Ma\u2018m\u016br",
    "gn:population":0,
    "gn:timezone":"Asia/Aden",
    "iso:country":"YE",
    "name:und_x_variant":[
        "Al Ma\u2018m\u016br"
    ],
    "wof:name":"Al Ma`mur",
    "wof:placetype":"locality"
},
  "geometry": {"coordinates":[43.60379,15.26705],"type":"Point"}
}