{
  "type": "Feature",
  "properties": {
    "gn:admin1_code":"8.0",
    "gn:admin2_code":"1802.0",
    "gn:asciiname":"Sha`b `Ubayd",
    "gn:country_code":"YE",
    "gn:dem":65,
    "gn:feature_class":"P",
    "gn:feature_code":"PPL",
    "gn:name":"Sha\u2018b \u2018Ubayd",
    "gn:population":0,
    "gn:timezone":"Asia/Aden",
    "iso:country":"YE",
    "name:ara_x_preferred":[
        "\u0634\u0639\u0628 \u0639\u0628\u064a\u062f"
    ],
    "name:und_x_variant":[
        "Shi\u2018b \u2018Ubayd",
        "Sha\u2018b \u2018Ubayd"
    ],
    "wof:name":"Sha`b `Ubayd",
    "wof:placetype":"locality"
},
  "geometry": {"coordinates":[42.97304000000001,15.69481],"type":"Point"}
}