{
  "type": "Feature",
  "properties": {
    "gn:admin1_code":"11.0",
    "gn:admin2_code":"2007.0",
    "gn:asciiname":"Al Haznah",
    "gn:country_code":"YE",
    "gn:dem":523,
    "gn:feature_class":"P",
    "gn:feature_code":"PPL",
    "gn:name":"Al \u1e28aznah",
    "gn:population":0,
    "gn:timezone":"Asia/Aden",
    "iso:country":"YE",
    "name:und_x_variant":[
        "Al \u1e28aznah"
    ],
    "wof:name":"Al Haznah",
    "wof:placetype":"locality"
},
  "geometry": {"coordinates":[43.65194,14.15122],"type":"Point"}
}