{
  "type": "Feature",
  "properties": {
    "gn:country":"YE",
    "gn:fcode":"PPL",
    "gn:pop":38,
    "iso:country":"YE",
    "name:ara_x_preferred":[
        "\u062d\u0635\u0628 \u0627\u0644\u0645\u0627\u0633"
    ],
    "name:eng_x_preferred":[
        "Hasab Al Mas"
    ],
    "name:eng_x_variant":[
        "Al Qurth\u012byah"
    ],
    "qs:name":"\u1e28a\u015fab al M\u0101s",
    "qs:photos_9r":0,
    "qs:photos_sr":0,
    "qs:pop_sr":"1",
    "wof:name":"\u1e28a\u015fab al M\u0101s",
    "wof:placetype":"locality",
    "wof:population":38
},
  "geometry": {"coordinates":[43.74425,13.07144],"type":"Point"}
}