{
  "type": "Feature",
  "properties": {
    "gn:country":"YE",
    "gn:fcode":"PPL",
    "gn:population":10,
    "iso:country":"YE",
    "name:ara_x_preferred":[
        "\u062c\u0648\u0627\u0631"
    ],
    "name:eng_x_preferred":[
        "Jawar"
    ],
    "name:eng_x_variant":[
        "Al Maql\u0101\u2018"
    ],
    "qs:name":"Jaw\u0101r",
    "qs:photos_9r":0,
    "qs:photos_sr":0,
    "qs:pop_sr":"1",
    "wd:wordcount":142,
    "wof:name":"Jaw\u0101r",
    "wof:placetype":"locality",
    "wof:population":10
},
  "geometry": {"coordinates":[44.45585,16.63525],"type":"Point"}
}