{
  "type": "Feature",
  "properties": {
    "gn:admin1_code":"16.0",
    "gn:admin2_code":"2312.0",
    "gn:asciiname":"Zalama",
    "gn:country_code":"YE",
    "gn:dem":1646,
    "gn:feature_class":"P",
    "gn:feature_code":"PPL",
    "gn:name":"Z\u0327al\u0101m\u0101",
    "gn:population":0,
    "gn:timezone":"Asia/Aden",
    "iso:country":"YE",
    "name:ara_x_preferred":[
        "\u0638\u0644\u0627\u0645\u0627"
    ],
    "name:und_x_variant":[
        "Z\u0327al\u0101m\u0101"
    ],
    "wof:name":"Zalama",
    "wof:placetype":"locality"
},
  "geometry": {"coordinates":[44.81101,15.35193],"type":"Point"}
}