{
  "type": "Feature",
  "properties": {
    "gn:admin1_code":"16.0",
    "gn:admin2_code":"2310.0",
    "gn:asciiname":"Bani `Atiyah",
    "gn:country_code":"YE",
    "gn:dem":1852,
    "gn:feature_class":"P",
    "gn:feature_code":"PPL",
    "gn:name":"Ban\u012b \u2018A\u0163\u012byah",
    "gn:population":0,
    "gn:timezone":"Asia/Aden",
    "iso:country":"YE",
    "name:und_x_variant":[
        "Ban\u012b \u2018A\u0163\u012byah"
    ],
    "wof:name":"Bani `Atiyah",
    "wof:placetype":"locality"
},
  "geometry": {"coordinates":[43.6284,15.19116],"type":"Point"}
}