{
  "type": "Feature",
  "properties": {
    "gn:admin1_code":"11.0",
    "gn:admin2_code":"2004.0",
    "gn:asciiname":"Ash Sharaf",
    "gn:country_code":"YE",
    "gn:dem":2325,
    "gn:feature_class":"P",
    "gn:feature_code":"PPL",
    "gn:name":"Ash Sharaf",
    "gn:population":0,
    "gn:timezone":"Asia/Aden",
    "iso:country":"YE",
    "wof:name":"Ash Sharaf",
    "wof:placetype":"locality"
},
  "geometry": {"coordinates":[44.14005,14.52559],"type":"Point"}
}