{
  "type": "Feature",
  "properties": {
    "gn:admin1_code":"1.0",
    "gn:admin2_code":"1211.0",
    "gn:asciiname":"Khanfar",
    "gn:country_code":"YE",
    "gn:dem":64,
    "gn:feature_class":"P",
    "gn:feature_code":"PPL",
    "gn:name":"Khanfar",
    "gn:population":0,
    "gn:timezone":"Asia/Aden",
    "iso:country":"YE",
    "name:heb_x_preferred":[
        "\u05d7'\u05e0\u05e4\u05e8"
    ],
    "wof:name":"Khanfar",
    "wof:placetype":"locality"
},
  "geometry": {"coordinates":[45.30556,13.21194],"type":"Point"}
}