{
  "type": "Feature",
  "properties": {
    "gn:admin1_code":"20.0",
    "gn:admin2_code":"1404.0",
    "gn:asciiname":"Hayd Al Shalil",
    "gn:country_code":"YE",
    "gn:dem":2015,
    "gn:feature_class":"P",
    "gn:feature_code":"PPL",
    "gn:name":"\u1e28ayd \u0100l Shal\u012bl",
    "gn:population":0,
    "gn:timezone":"Asia/Aden",
    "iso:country":"YE",
    "name:ara_x_preferred":[
        "\u062d\u064a\u062f \u0627\u0644 \u0634\u0644\u064a\u0644"
    ],
    "name:und_x_variant":[
        "\u0100l Shal\u012bl",
        "\u1e28ayd \u0100l Shal\u012bl"
    ],
    "wof:name":"Hayd Al Shalil",
    "wof:placetype":"locality"
},
  "geometry": {"coordinates":[45.77694,14.13807],"type":"Point"}
}