{
  "type": "Feature",
  "properties": {
    "gn:admin1_code":"8.0",
    "gn:admin2_code":"1816.0",
    "gn:asciiname":"Al Hajjamah",
    "gn:country_code":"YE",
    "gn:dem":148,
    "gn:feature_class":"P",
    "gn:feature_code":"PPL",
    "gn:name":"Al \u1e28ajj\u0101mah",
    "gn:population":0,
    "gn:timezone":"Asia/Aden",
    "iso:country":"YE",
    "name:und_x_variant":[
        "Al \u1e28ajj\u0101mah"
    ],
    "wof:name":"Al Hajjamah",
    "wof:placetype":"locality"
},
  "geometry": {"coordinates":[43.36428,14.71326],"type":"Point"}
}