{
  "type": "Feature",
  "properties": {
    "gn:country":"YE",
    "gn:fcode":"PPL",
    "gn:pop":11,
    "iso:country":"YE",
    "name:ara_x_preferred":[
        "\u0627\u0644\u0645\u0637\u0627\u064a\u0627"
    ],
    "name:eng_x_preferred":[
        "Al Mataya"
    ],
    "name:eng_x_variant":[
        "A\u015f \u015eif\u1e29\u0101\u2019"
    ],
    "qs:name":"Al Ma\u0163\u0101y\u0101",
    "qs:photos_9r":0,
    "qs:photos_sr":0,
    "qs:pop_sr":"1",
    "wof:name":"Al Ma\u0163\u0101y\u0101",
    "wof:placetype":"locality",
    "wof:population":11
},
  "geometry": {"coordinates":[43.73634,13.27556],"type":"Point"}
}