{
  "type": "Feature",
  "properties": {
    "gn:gn_country":"YE",
    "gn:gn_fcode":"PPL",
    "gn:gn_pop":3,
    "gn:population":3,
    "iso:country":"YE",
    "name:ara_x_preferred":[
        "\u0634\u0639\u0628 \u062c\u0627\u0628\u0631"
    ],
    "name:eng_x_preferred":[
        "Sha'b Jabir"
    ],
    "name:eng_x_variant":[
        "Ad Diy\u0101m"
    ],
    "qs_pg:aaroncc":"YE",
    "qs_pg:gn_country":"YE",
    "qs_pg:gn_fcode":"PPL",
    "qs_pg:gn_pop":3,
    "qs_pg:name":"Sha\u2018b J\u0101bir",
    "qs_pg:photos_9r":0,
    "qs_pg:photos_sr":0,
    "qs_pg:pop_sr":1,
    "qs_pg:qs_pg_placetype":"locality",
    "wof:name":"Sha\u2018b J\u0101bir",
    "wof:placetype":"locality",
    "wof:population":3
},
  "geometry": {"coordinates":[43.29289,16.08715],"type":"Point"}
}