{
  "type": "Feature",
  "properties": {
    "gn:admin1_code":"8.0",
    "gn:admin2_code":"1802.0",
    "gn:asciiname":"Bani Faris",
    "gn:country_code":"YE",
    "gn:dem":26,
    "gn:feature_class":"P",
    "gn:feature_code":"PPL",
    "gn:name":"Ban\u012b F\u0101ris",
    "gn:population":0,
    "gn:timezone":"Asia/Aden",
    "iso:country":"YE",
    "name:ara_x_preferred":[
        "\u0628\u0646\u064a \u0641\u0627\u0631\u0633"
    ],
    "name:und_x_variant":[
        "Ban\u012b F\u0101ris"
    ],
    "wof:name":"Bani Faris",
    "wof:placetype":"locality"
},
  "geometry": {"coordinates":[42.82052,15.67695],"type":"Point"}
}