{
  "type": "Feature",
  "properties": {
    "gn:admin1_code":"15.0",
    "gn:admin2_code":"2206.0",
    "gn:asciiname":"Ar Rawnaqi",
    "gn:country_code":"YE",
    "gn:dem":327,
    "gn:feature_class":"P",
    "gn:feature_code":"PPL",
    "gn:name":"Ar Rawnaq\u012b",
    "gn:population":0,
    "gn:timezone":"Asia/Aden",
    "iso:country":"YE",
    "name:ara_x_preferred":[
        "\u0627\u0644\u0631\u0648\u0646\u0642\u064a"
    ],
    "name:und_x_variant":[
        "Ar Rawnaq\u012b"
    ],
    "wof:name":"Ar Rawnaqi",
    "wof:placetype":"locality"
},
  "geometry": {"coordinates":[43.15797,16.92844],"type":"Point"}
}