{
  "type": "Feature",
  "properties": {
    "gn:country":"YE",
    "gn:fcode":"PPL",
    "gn:population":2,
    "iso:country":"YE",
    "name:ara_x_preferred":[
        "\u0627\u0644 \u0639\u0637\u064a\u0629"
    ],
    "name:eng_x_preferred":[
        "Al 'Attiyah"
    ],
    "name:eng_x_variant":[
        "\u0100l Zayd"
    ],
    "qs:name":"\u0100l \u2018A\u0163\u0163\u012byah",
    "qs:photos_9r":0,
    "qs:photos_sr":0,
    "qs:pop_sr":"1",
    "wof:name":"\u0100l \u2018A\u0163\u0163\u012byah",
    "wof:placetype":"locality",
    "wof:population":2
},
  "geometry": {"coordinates":[44.9945,15.99284],"type":"Point"}
}