{
  "type": "Feature",
  "properties": {
    "gn:gn_country":"YE",
    "gn:gn_fcode":"PPL",
    "gn:gn_pop":1,
    "gn:population":1,
    "iso:country":"YE",
    "name:ara_x_preferred":[
        "\u0627\u0644\u062c\u062f\u0628\u0629"
    ],
    "name:eng_x_preferred":[
        "Al Jadibah"
    ],
    "name:eng_x_variant":[
        "Bayt al Ma\u1e29ras"
    ],
    "qs_pg:aaroncc":"YE",
    "qs_pg:gn_country":"YE",
    "qs_pg:gn_fcode":"PPL",
    "qs_pg:gn_pop":1,
    "qs_pg:name":"Al Jadibah",
    "qs_pg:photos_9r":0,
    "qs_pg:photos_sr":0,
    "qs_pg:pop_sr":1,
    "qs_pg:qs_pg_placetype":"locality",
    "wof:name":"Al Jadibah",
    "wof:placetype":"locality",
    "wof:population":1
},
  "geometry": {"coordinates":[43.2407,17.16361],"type":"Point"}
}