{
  "type": "Feature",
  "properties": {
    "gn:admin1_code":"8.0",
    "gn:admin2_code":"1812.0",
    "gn:asciiname":"Mahall al Faqih",
    "gn:country_code":"YE",
    "gn:dem":194,
    "gn:feature_class":"P",
    "gn:feature_code":"PPL",
    "gn:name":"Ma\u1e29all al Faq\u012bh",
    "gn:population":0,
    "gn:timezone":"Asia/Aden",
    "iso:country":"YE",
    "name:ara_x_preferred":[
        "\u0645\u062d\u0644 \u0627\u0644\u0641\u0642\u064a\u0647"
    ],
    "name:und_x_variant":[
        "Ma\u1e29all al Faq\u012bh"
    ],
    "wof:name":"Mahall al Faqih",
    "wof:placetype":"locality"
},
  "geometry": {"coordinates":[43.41553,14.84917],"type":"Point"}
}