{
  "type": "Feature",
  "properties": {
    "gn:admin1_code":"24.0",
    "gn:admin2_code":"2511.0",
    "gn:asciiname":"Daymat Rajih",
    "gn:country_code":"YE",
    "gn:dem":371,
    "gn:feature_class":"P",
    "gn:feature_code":"PPL",
    "gn:name":"Daymat R\u0101jih",
    "gn:population":0,
    "gn:timezone":"Asia/Aden",
    "iso:country":"YE",
    "name:und_x_variant":[
        "Daymat R\u0101jih"
    ],
    "wof:name":"Daymat Rajih",
    "wof:placetype":"locality"
},
  "geometry": {"coordinates":[44.3421,13.0281],"type":"Point"}
}