{
  "type": "Feature",
  "properties": {
    "gn:admin1_code":"19.0",
    "gn:admin2_code":"2903.0",
    "gn:asciiname":"Al Jawwah",
    "gn:country_code":"YE",
    "gn:dem":1140,
    "gn:feature_class":"P",
    "gn:feature_code":"PPLL",
    "gn:name":"Al Jawwah",
    "gn:population":0,
    "gn:timezone":"Asia/Aden",
    "iso:country":"YE",
    "name:ara_x_preferred":[
        "\u0627\u0644\u062c\u0648\u0629"
    ],
    "wof:name":"Al Jawwah",
    "wof:placetype":"locality"
},
  "geometry": {"coordinates":[43.82053,16.20814],"type":"Point"}
}