{
  "type": "Feature",
  "properties": {
    "gn:country":"YE",
    "gn:fcode":"PPLX",
    "gn:pop":18,
    "iso:country":"YE",
    "name:ara_x_preferred":[
        "\u062d\u0627\u0631\u0629 \u0627\u0644\u0623\u0645\u0646 \u0627\u0644\u0633\u064a\u0627\u0633\u064a"
    ],
    "name:unk_x_variant":[
        "\u1e28\u0101rat al Amn as Siy\u0101s\u012b"
    ],
    "qs:name":"\u1e28\u0101rat al Aman as Siy\u0101s\u012b",
    "qs:photos_9r":0,
    "qs:photos_sr":0,
    "qs:pop_sr":"1",
    "wof:name":"\u1e28\u0101rat al Aman as Siy\u0101s\u012b",
    "wof:placetype":"neighbourhood",
    "wof:population":18
},
  "geometry": {"coordinates":[45.3196,15.46568],"type":"Point"}
}