{
  "type": "Feature",
  "properties": {
    "gn:admin1_code":"21.0",
    "gn:admin2_code":"1607.0",
    "gn:asciiname":"Al Murtafa'",
    "gn:country_code":"YE",
    "gn:dem":1178,
    "gn:feature_class":"P",
    "gn:feature_code":"PPLL",
    "gn:name":"Al Murtafa\u2018",
    "gn:population":0,
    "gn:timezone":"Asia/Aden",
    "iso:country":"YE",
    "name:ara_x_preferred":[
        "\u0627\u0644\u0645\u0631\u062a\u0641\u0639"
    ],
    "name:und_x_variant":[
        "Al Murtafa\u2018"
    ],
    "wof:name":"Al Murtafa'",
    "wof:placetype":"locality"
},
  "geometry": {"coordinates":[44.48552,16.17456],"type":"Point"}
}