{
  "type": "Feature",
  "properties": {
    "gn:admin1_code":"18.0",
    "gn:admin2_code":"3002.0",
    "gn:asciiname":"Al Athari",
    "gn:country_code":"YE",
    "gn:dem":1977,
    "gn:feature_class":"P",
    "gn:feature_code":"PPL",
    "gn:name":"Al Athar\u012b",
    "gn:population":0,
    "gn:timezone":"Asia/Aden",
    "iso:country":"YE",
    "name:ara_x_preferred":[
        "Al Ithr\u012b"
    ],
    "name:ara_x_variant":[
        "\u0627\u0644\u0623\u062b\u0631\u064a"
    ],
    "name:und_x_variant":[
        "Al Athar\u012b"
    ],
    "wof:name":"Al Athari",
    "wof:placetype":"locality"
},
  "geometry": {"coordinates":[44.71567,14.10626],"type":"Point"}
}