{
  "type": "Feature",
  "properties": {
    "gn:country":"YE",
    "gn:fcode":"PPL",
    "gn:pop":7,
    "iso:country":"YE",
    "name:ara_x_preferred":[
        "\u062c\u0639\u0645\u0629 \u0627\u0644 \u0645\u0646\u0635\u0631"
    ],
    "name:eng_x_preferred":[
        "Ji'mat Al Mansar"
    ],
    "qs:name":"Ji\u2018mat \u0100l Man\u015far",
    "qs:photos_9r":0,
    "qs:photos_sr":0,
    "qs:pop_sr":"1",
    "wof:name":"Ji\u2018mat \u0100l Man\u015far",
    "wof:placetype":"locality",
    "wof:population":7
},
  "geometry": {"coordinates":[45.39772,14.0346],"type":"Point"}
}