{
  "type": "Feature",
  "properties": {
    "gn:country":"YE",
    "gn:fcode":"PPL",
    "gn:population":25,
    "iso:country":"YE",
    "name:ara_x_preferred":[
        "\u0627\u0644 \u062d\u0631\u0628\u064a"
    ],
    "name:eng_x_preferred":[
        "Al Harabi"
    ],
    "name:eng_x_variant":[
        "Al Jarn"
    ],
    "qs_pg:aaroncc":"YE",
    "qs_pg:gn_country":"YE",
    "qs_pg:gn_fcode":"PPL",
    "qs_pg:gn_pop":25,
    "qs_pg:name":"\u0100l \u1e28arab\u012b",
    "qs_pg:photos_9r":0,
    "qs_pg:photos_sr":0,
    "qs_pg:pop_sr":1,
    "qs_pg:qs_pg_placetype":"locality",
    "wof:name":"\u0100l \u1e28arab\u012b",
    "wof:placetype":"locality",
    "wof:population":25
},
  "geometry": {"coordinates":[43.36339,16.80815],"type":"Point"}
}