{
  "type": "Feature",
  "properties": {
    "gn:admin1_code":"8.0",
    "gn:admin2_code":"1802.0",
    "gn:asciiname":"Al Faranishah",
    "gn:country_code":"YE",
    "gn:dem":64,
    "gn:feature_class":"P",
    "gn:feature_code":"PPL",
    "gn:name":"Al Far\u0101nishah",
    "gn:population":0,
    "gn:timezone":"Asia/Aden",
    "iso:country":"YE",
    "name:ara_x_preferred":[
        "\u0627\u0644\u0641\u0631\u0627\u0646\u0634\u0629"
    ],
    "name:und_x_variant":[
        "Al Far\u0101nishah"
    ],
    "wof:name":"Al Faranishah",
    "wof:placetype":"locality"
},
  "geometry": {"coordinates":[42.95273,15.68771],"type":"Point"}
}