{
  "type": "Feature",
  "properties": {
    "gn:admin1_code":"8.0",
    "gn:admin2_code":"1810.0",
    "gn:asciiname":"Al Mashhuriyah",
    "gn:country_code":"YE",
    "gn:dem":68,
    "gn:feature_class":"P",
    "gn:feature_code":"PPL",
    "gn:name":"Al Mashh\u016br\u012byah",
    "gn:population":0,
    "gn:timezone":"Asia/Aden",
    "iso:country":"YE",
    "name:ara_x_preferred":[
        "\u0627\u0644\u0645\u0634\u0647\u0648\u0631\u064a\u0629"
    ],
    "name:und_x_variant":[
        "Dayr al Mash\u0101hirab",
        "Mashh\u016br\u012byah",
        "Dayr al Mash\u0101\u1e29irah",
        "Al Mashh\u016br\u012byah"
    ],
    "wof:name":"Al Mashhuriyah",
    "wof:placetype":"locality"
},
  "geometry": {"coordinates":[43.07723,15.02296],"type":"Point"}
}