{
  "type": "Feature",
  "properties": {
    "gn:admin1_code":"10.0",
    "gn:admin2_code":"2709.0",
    "gn:asciiname":"Sid",
    "gn:country_code":"YE",
    "gn:dem":1870,
    "gn:feature_class":"P",
    "gn:feature_code":"PPL",
    "gn:name":"S\u012bd",
    "gn:population":0,
    "gn:timezone":"Asia/Aden",
    "iso:country":"YE",
    "name:ara_x_preferred":[
        "S\u012bd"
    ],
    "wof:name":"Sid",
    "wof:placetype":"locality"
},
  "geometry": {"coordinates":[43.58273,15.43842],"type":"Point"}
}