{
  "type": "Feature",
  "properties": {
    "gn:country":"YE",
    "gn:fcode":"PPL",
    "gn:population":13,
    "iso:country":"YE",
    "name:ara_x_preferred":[
        "\u0623\u0648\u0639\u0644"
    ],
    "name:eng_x_preferred":[
        "Aw'al"
    ],
    "name:eng_x_variant":[
        "Ibn \u1e28aydir"
    ],
    "qs:name":"Aw\u2018al",
    "qs:photos_9r":0,
    "qs:photos_sr":0,
    "qs:pop_sr":"1",
    "wof:name":"Aw\u2018al",
    "wof:placetype":"locality",
    "wof:population":13
},
  "geometry": {"coordinates":[43.38903,16.93784],"type":"Point"}
}