{
  "type": "Feature",
  "properties": {
    "gn:admin1_code":"16.0",
    "gn:admin2_code":"2316.0",
    "gn:asciiname":"Al Hanu",
    "gn:country_code":"YE",
    "gn:dem":2200,
    "gn:feature_class":"P",
    "gn:feature_code":"PPL",
    "gn:name":"Al \u1e28an\u016b",
    "gn:population":0,
    "gn:timezone":"Asia/Aden",
    "iso:country":"YE",
    "name:ara_x_preferred":[
        "\u0627\u0644\u062d\u0646\u0648"
    ],
    "name:und_x_variant":[
        "Al \u1e28an\u016b"
    ],
    "wof:name":"Al Hanu",
    "wof:placetype":"locality"
},
  "geometry": {"coordinates":[44.50026,15.21033],"type":"Point"}
}