{
  "type": "Feature",
  "properties": {
    "gn:admin1_code":"22.0",
    "gn:admin2_code":"1727.0",
    "gn:asciiname":"Ash Sharifah",
    "gn:country_code":"YE",
    "gn:dem":1968,
    "gn:feature_class":"P",
    "gn:feature_code":"PPL",
    "gn:name":"Ash Sharifah",
    "gn:population":0,
    "gn:timezone":"Asia/Aden",
    "iso:country":"YE",
    "wof:name":"Ash Sharifah",
    "wof:placetype":"locality"
},
  "geometry": {"coordinates":[43.58811,15.6259],"type":"Point"}
}