{
  "type": "Feature",
  "properties": {
    "gn:country":"YE",
    "gn:fcode":"PPL",
    "gn:pop":10,
    "iso:country":"YE",
    "name:ara_x_preferred":[
        "\u0627\u0644\u0639\u0634\u0629"
    ],
    "name:eng_x_preferred":[
        "Al 'Ashshah"
    ],
    "name:eng_x_variant":[
        "Ash Shaml\u012byah"
    ],
    "qs:name":"Al \u2018Ashshah",
    "qs:photos_9r":0,
    "qs:photos_sr":0,
    "qs:pop_sr":"1",
    "wof:name":"Al \u2018Ashshah",
    "wof:placetype":"locality",
    "wof:population":10
},
  "geometry": {"coordinates":[43.77299,13.24713],"type":"Point"}
}