{
  "type": "Feature",
  "properties": {
    "gn:admin1_code":"22.0",
    "gn:admin2_code":"1713.0",
    "gn:asciiname":"Al Qali`",
    "gn:country_code":"YE",
    "gn:dem":1185,
    "gn:feature_class":"P",
    "gn:feature_code":"PPL",
    "gn:name":"Al Qal\u012b\u2018",
    "gn:population":0,
    "gn:timezone":"Asia/Aden",
    "iso:country":"YE",
    "name:und_x_variant":[
        "Al Qal\u012b\u2018",
        "Ban\u012b Maj\u012b\u2018"
    ],
    "wof:name":"Al Qali`",
    "wof:placetype":"locality"
},
  "geometry": {"coordinates":[43.40385,15.91623],"type":"Point"}
}