{
  "type": "Feature",
  "properties": {
    "gn:gn_country":"YE",
    "gn:gn_fcode":"PPL",
    "gn:gn_pop":18,
    "gn:population":18,
    "iso:country":"YE",
    "name:ara_x_preferred":[
        "\u0627\u0644\u0631\u0642\u0648"
    ],
    "name:eng_x_preferred":[
        "Ar Raqw"
    ],
    "qs_pg:aaroncc":"YE",
    "qs_pg:gn_country":"YE",
    "qs_pg:gn_fcode":"PPL",
    "qs_pg:gn_pop":18,
    "qs_pg:name":"Ar Raqw",
    "qs_pg:photos_9r":0,
    "qs_pg:photos_sr":0,
    "qs_pg:pop_sr":1,
    "qs_pg:qs_pg_placetype":"locality",
    "wof:name":"Ar Raqw",
    "wof:placetype":"locality",
    "wof:population":18
},
  "geometry": {"coordinates":[43.20282,17.25526],"type":"Point"}
}