{
  "type": "Feature",
  "properties": {
    "gn:country":"YE",
    "gn:fcode":"PPL",
    "gn:pop":7,
    "iso:country":"YE",
    "name:ara_x_preferred":[
        "\u0627\u0644\u062d\u0646\u062f\u0648\u062f"
    ],
    "name:eng_x_preferred":[
        "Al HandUd"
    ],
    "name:eng_x_variant":[
        "Bayt al Aswad"
    ],
    "qs:name":"Al \u1e28and\u016bd",
    "qs:photos_9r":0,
    "qs:photos_sr":0,
    "qs:pop_sr":"1",
    "wof:name":"Al \u1e28and\u016bd",
    "wof:placetype":"locality",
    "wof:population":7
},
  "geometry": {"coordinates":[43.20053,17.11019],"type":"Point"}
}