{
  "type": "Feature",
  "properties": {
    "gn:admin1_code":"25.0",
    "gn:admin2_code":"1503.0",
    "gn:asciiname":"Qaryat Bani",
    "gn:country_code":"YE",
    "gn:dem":1313,
    "gn:feature_class":"P",
    "gn:feature_code":"PPL",
    "gn:name":"Qaryat Ban\u012b",
    "gn:population":0,
    "gn:timezone":"Asia/Aden",
    "iso:country":"YE",
    "name:ara_x_preferred":[
        "\u0628\u0646\u064a"
    ],
    "name:und_x_variant":[
        "Qaryat Ban\u012b",
        "Ban\u012b"
    ],
    "wof:name":"Qaryat Bani",
    "wof:placetype":"locality"
},
  "geometry": {"coordinates":[43.87032,13.82488],"type":"Point"}
}