{
  "type": "Feature",
  "properties": {
    "gn:admin1_code":"23.0",
    "gn:admin2_code":"1108.0",
    "gn:asciiname":"Qaryat ash Shi`b",
    "gn:country_code":"YE",
    "gn:dem":1647,
    "gn:feature_class":"P",
    "gn:feature_code":"PPL",
    "gn:name":"Qaryat ash Shi\u2018b",
    "gn:population":0,
    "gn:timezone":"Asia/Aden",
    "iso:country":"YE",
    "name:und_x_variant":[
        "Qaryat ash Shi\u2018b"
    ],
    "wof:name":"Qaryat ash Shi`b",
    "wof:placetype":"locality"
},
  "geometry": {"coordinates":[44.11713,14.15891],"type":"Point"}
}