{
  "type": "Feature",
  "properties": {
    "gn:gn_country":"YE",
    "gn:gn_fcode":"PPL",
    "gn:gn_pop":1,
    "gn:population":1,
    "iso:country":"YE",
    "name:ara_x_preferred":[
        "\u0627\u0644\u0635\u0641\u064a\u062d"
    ],
    "name:eng_x_preferred":[
        "As Sufayh"
    ],
    "qs_pg:aaroncc":"YE",
    "qs_pg:gn_country":"YE",
    "qs_pg:gn_fcode":"PPL",
    "qs_pg:gn_pop":1,
    "qs_pg:name":"A\u015f \u015eufay\u1e29",
    "qs_pg:photos_9r":0,
    "qs_pg:photos_sr":0,
    "qs_pg:pop_sr":1,
    "qs_pg:qs_pg_placetype":"locality",
    "wof:name":"A\u015f \u015eufay\u1e29",
    "wof:placetype":"locality",
    "wof:population":1
},
  "geometry": {"coordinates":[43.7111,16.09082],"type":"Point"}
}