{
  "type": "Feature",
  "properties": {
    "gn:country":"YE",
    "gn:fcode":"PPL",
    "gn:pop":3,
    "iso:country":"YE",
    "name:ara_x_preferred":[
        "\u0627\u0644\u0635\u0648\u063a\u0629"
    ],
    "name:eng_x_preferred":[
        "As Sawghah"
    ],
    "name:eng_x_variant":[
        "Al \u1e28aba\u0163"
    ],
    "qs:name":"A\u015f \u015eawghah",
    "qs:photos_9r":0,
    "qs:photos_sr":0,
    "qs:pop_sr":"1",
    "wof:name":"A\u015f \u015eawghah",
    "wof:placetype":"locality",
    "wof:population":3
},
  "geometry": {"coordinates":[43.39935,16.33873],"type":"Point"}
}