{
  "type": "Feature",
  "properties": {
    "gn:admin1_code":"14.0",
    "gn:admin2_code":"2605.0",
    "gn:asciiname":"Al Mazra`ah",
    "gn:country_code":"YE",
    "gn:dem":1698,
    "gn:feature_class":"P",
    "gn:feature_code":"PPL",
    "gn:name":"Al Mazra\u2018ah",
    "gn:population":0,
    "gn:timezone":"Asia/Aden",
    "iso:country":"YE",
    "name:ara_x_preferred":[
        "\u0627\u0644\u0645\u0632\u0631\u0639\u0629"
    ],
    "name:und_x_variant":[
        "Al Mazra\u2018ah"
    ],
    "wof:name":"Al Mazra`ah",
    "wof:placetype":"locality"
},
  "geometry": {"coordinates":[44.79287,15.34315],"type":"Point"}
}