{
  "type": "Feature",
  "properties": {
    "gn:admin1_code":"11.0",
    "gn:asciiname":"Bab al Mi`sarah",
    "gn:country_code":"YE",
    "gn:dem":2489,
    "gn:feature_class":"P",
    "gn:feature_code":"PPL",
    "gn:name":"B\u0101b al Mi\u2018\u015farah",
    "gn:population":0,
    "gn:timezone":"Asia/Aden",
    "iso:country":"YE",
    "name:ara_x_preferred":[
        "\u0628\u0627\u0628 \u0627\u0644\u0645\u0639\u0635\u0631\u0629"
    ],
    "name:und_x_variant":[
        "B\u0101b al Mi\u2018\u015farah"
    ],
    "wof:name":"Bab al Mi`sarah",
    "wof:placetype":"locality"
},
  "geometry": {"coordinates":[44.44512,14.28782],"type":"Point"}
}