{
  "type": "Feature",
  "properties": {
    "gn:admin1_code":"8.0",
    "gn:admin2_code":"1825.0",
    "gn:asciiname":"Al Mahdali",
    "gn:country_code":"YE",
    "gn:dem":102,
    "gn:feature_class":"P",
    "gn:feature_code":"PPL",
    "gn:name":"Al Mahdal\u012b",
    "gn:population":0,
    "gn:timezone":"Asia/Aden",
    "iso:country":"YE",
    "name:und_x_variant":[
        "Al Mahdal\u012b"
    ],
    "wof:name":"Al Mahdali",
    "wof:placetype":"locality"
},
  "geometry": {"coordinates":[43.2967,14.16251],"type":"Point"}
}