{
  "type": "Feature",
  "properties": {
    "gn:admin1_code":"4.0",
    "gn:admin2_code":"1916.0",
    "gn:asciiname":"Raydah",
    "gn:country_code":"YE",
    "gn:dem":870,
    "gn:feature_class":"P",
    "gn:feature_code":"PPL",
    "gn:name":"Raydah",
    "gn:population":0,
    "gn:timezone":"Asia/Aden",
    "iso:country":"YE",
    "wof:name":"Raydah",
    "wof:placetype":"locality"
},
  "geometry": {"coordinates":[49.23333,15.56667],"type":"Point"}
}