{
  "type": "Feature",
  "properties": {
    "gn:admin1_code":"8.0",
    "gn:admin2_code":"1817.0",
    "gn:asciiname":"Dimnat al Haddarah",
    "gn:country_code":"YE",
    "gn:dem":128,
    "gn:feature_class":"P",
    "gn:feature_code":"PPL",
    "gn:name":"Dimnat al Hadd\u0101rah",
    "gn:population":0,
    "gn:timezone":"Asia/Aden",
    "iso:country":"YE",
    "name:und_x_variant":[
        "Dimnat al Hadd\u0101rah"
    ],
    "wof:name":"Dimnat al Haddarah",
    "wof:placetype":"locality"
},
  "geometry": {"coordinates":[43.37839,14.60163],"type":"Point"}
}