{
  "type": "Feature",
  "properties": {
    "gn:admin1_code":"22.0",
    "gn:admin2_code":"1711.0",
    "gn:asciiname":"Al Qazaziyah",
    "gn:country_code":"YE",
    "gn:dem":431,
    "gn:feature_class":"P",
    "gn:feature_code":"PPL",
    "gn:name":"Al Qaz\u0101z\u012byah",
    "gn:population":0,
    "gn:timezone":"Asia/Aden",
    "iso:country":"YE",
    "name:und_x_variant":[
        "Al Qaz\u0101z\u012byah"
    ],
    "wof:name":"Al Qazaziyah",
    "wof:placetype":"locality"
},
  "geometry": {"coordinates":[43.36179,16.02836],"type":"Point"}
}