{
  "type": "Feature",
  "properties": {
    "gn:country":"YE",
    "gn:fcode":"PPL",
    "gn:population":17,
    "iso:country":"YE",
    "name:ara_x_preferred":[
        "Al \u2018Ar\u012bsh"
    ],
    "name:ara_x_variant":[
        "\u0627\u0644\u0639\u0631\u064a\u0634"
    ],
    "qs:name":"Al \u2018Ar\u012bsh",
    "qs:photos_9r":0,
    "qs:photos_sr":0,
    "qs:pop_sr":"1",
    "wof:name":"Al \u2018Ar\u012bsh",
    "wof:placetype":"locality",
    "wof:population":17
},
  "geometry": {"coordinates":[43.42387,16.09335],"type":"Point"}
}