{
  "type": "Feature",
  "properties": {
    "gn:country":"YE",
    "gn:fcode":"PPL",
    "gn:population":6,
    "iso:country":"YE",
    "name:ara_x_preferred":[
        "\u0648\u0647\u0627\u0628\u0629"
    ],
    "name:eng_x_preferred":[
        "Wahabah"
    ],
    "qs:name":"Wah\u0101bah",
    "qs:photos_9r":0,
    "qs:photos_sr":0,
    "qs:pop_sr":"1",
    "wof:name":"Wah\u0101bah",
    "wof:placetype":"locality",
    "wof:population":6
},
  "geometry": {"coordinates":[43.54615,16.82748],"type":"Point"}
}