{
  "type": "Feature",
  "properties": {
    "gn:gn_country":"YE",
    "gn:gn_fcode":"PPL",
    "gn:gn_pop":10,
    "gn:population":10,
    "iso:country":"YE",
    "name:ara_x_preferred":[
        "\u0632\u0641\u0642 \u062d\u0645\u062f"
    ],
    "name:eng_x_preferred":[
        "Zafq Hamad"
    ],
    "name:eng_x_variant":[
        "\u0100l Ab\u016b Nu\u2018ayr"
    ],
    "qs_pg:aaroncc":"YE",
    "qs_pg:gn_country":"YE",
    "qs_pg:gn_fcode":"PPL",
    "qs_pg:gn_pop":10,
    "qs_pg:name":"Zafq \u1e28amad",
    "qs_pg:photos_9r":0,
    "qs_pg:photos_sr":0,
    "qs_pg:pop_sr":1,
    "qs_pg:qs_pg_placetype":"locality",
    "wof:name":"Zafq \u1e28amad",
    "wof:placetype":"locality",
    "wof:population":10
},
  "geometry": {"coordinates":[44.39107,16.70098],"type":"Point"}
}