{
  "type": "Feature",
  "properties": {
    "gn:admin1_code":"14.0",
    "gn:admin2_code":"2606.0",
    "gn:asciiname":"Ash Shatt al A'la",
    "gn:country_code":"YE",
    "gn:dem":1491,
    "gn:feature_class":"P",
    "gn:feature_code":"PPL",
    "gn:name":"Ash Sha\u0163\u0163 al A\u2018l\u00e1",
    "gn:population":0,
    "gn:timezone":"Asia/Aden",
    "iso:country":"YE",
    "name:ara_x_preferred":[
        "\u0627\u0644\u0634\u0637 \u0627\u0644\u0627\u0639\u0644\u0649"
    ],
    "name:und_x_variant":[
        "Ash Sha\u0163\u0163 al A\u2018l\u00e1"
    ],
    "wof:name":"Ash Shatt al A'la",
    "wof:placetype":"locality"
},
  "geometry": {"coordinates":[44.97139,15.44513],"type":"Point"}
}