{
  "type": "Feature",
  "properties": {
    "gn:country":"YE",
    "gn:fcode":"PPL",
    "gn:pop":3,
    "iso:country":"YE",
    "name:ara_x_preferred":[
        "\u062d\u0628\u064a\u0644 \u0627\u0644\u0639\u0642\u0640\u0640\u0645"
    ],
    "name:ara_x_variant":[
        "\u062d\u0628\u064a\u0644 \u0627\u0644\u0639\u0642\u0645"
    ],
    "name:eng_x_preferred":[
        "Habil Al 'Aqqam"
    ],
    "name:eng_x_variant":[
        "Al \u2018Arf"
    ],
    "qs:name":"\u1e28ab\u012bl al \u2018Aqqam",
    "qs:photos_9r":0,
    "qs:photos_sr":0,
    "qs:pop_sr":"1",
    "wof:name":"\u1e28ab\u012bl al \u2018Aqqam",
    "wof:placetype":"locality",
    "wof:population":3
},
  "geometry": {"coordinates":[43.33561,16.11267],"type":"Point"}
}