{
  "type": "Feature",
  "properties": {
    "gn:country":"YE",
    "gn:fcode":"PPL",
    "gn:pop":12,
    "iso:country":"YE",
    "name:ara_x_preferred":[
        "\u063a\u0627\u0631\u0628 \u0627\u0644\u0633\u0648\u0627\u062f"
    ],
    "name:ara_x_variant":[
        "\u0627\u0644\u0633\u0648\u0627\u062f"
    ],
    "name:unk_x_variant":[
        "As Saw\u0101d"
    ],
    "qs:name":"Gh\u0101rib as Saw\u0101d",
    "qs:photos_9r":0,
    "qs:photos_sr":0,
    "qs:pop_sr":"1",
    "wof:name":"Gh\u0101rib as Saw\u0101d",
    "wof:placetype":"locality",
    "wof:population":12
},
  "geometry": {"coordinates":[43.61352,16.15357],"type":"Point"}
}