{
  "type": "Feature",
  "properties": {
    "gn:admin1_code":"18.0",
    "gn:admin2_code":"3001.0",
    "gn:asciiname":"Al Mahjar",
    "gn:country_code":"YE",
    "gn:dem":2232,
    "gn:feature_class":"P",
    "gn:feature_code":"PPL",
    "gn:name":"Al Ma\u1e29jar",
    "gn:population":0,
    "gn:timezone":"Asia/Aden",
    "iso:country":"YE",
    "name:ara_x_preferred":[
        "\u0627\u0644\u0645\u062d\u062c\u0631"
    ],
    "name:ara_x_variant":[
        "\u0627\u0644\u0645\u0647\u062c\u0631"
    ],
    "name:fas_x_preferred":[
        "\u0627\u0644\u0645\u0647\u062c\u0627\u0631"
    ],
    "name:nno_x_preferred":[
        "Al Mahjar"
    ],
    "name:und_x_variant":[
        "Al Ma\u1e29jar"
    ],
    "name:urd_x_preferred":[
        "\u0627\u0644\u0645\u06c1\u062c\u0631"
    ],
    "wof:name":"Al Mahjar",
    "wof:placetype":"locality"
},
  "geometry": {"coordinates":[44.81253,14.05285],"type":"Point"}
}