{
  "type": "Feature",
  "properties": {
    "gn:admin1_code":"16.0",
    "gn:admin2_code":"2305.0",
    "gn:asciiname":"Al Jayrif",
    "gn:country_code":"YE",
    "gn:dem":2470,
    "gn:feature_class":"P",
    "gn:feature_code":"PPL",
    "gn:name":"Al Jayrif",
    "gn:population":0,
    "gn:timezone":"Asia/Aden",
    "iso:country":"YE",
    "name:fas_x_preferred":[
        "\u0627\u0644\u062c\u0627\u06cc\u0631\u06cc\u0641"
    ],
    "name:nno_x_preferred":[
        "Al-Jayrif"
    ],
    "wof:name":"Al Jayrif",
    "wof:placetype":"locality"
},
  "geometry": {"coordinates":[44.29821,15.13523],"type":"Point"}
}