{
  "type": "Feature",
  "properties": {
    "gn:admin1_code":"25.0",
    "gn:admin2_code":"1502.0",
    "gn:asciiname":"Dabyah",
    "gn:country_code":"YE",
    "gn:dem":1533,
    "gn:feature_class":"P",
    "gn:feature_code":"PPL",
    "gn:name":"\u1e10abyah",
    "gn:population":0,
    "gn:timezone":"Asia/Aden",
    "iso:country":"YE",
    "name:nno_x_preferred":[
        "Dabyah"
    ],
    "name:und_x_variant":[
        "\u1e10abyah"
    ],
    "wof:name":"Dabyah",
    "wof:placetype":"locality"
},
  "geometry": {"coordinates":[44.08781,13.7694],"type":"Point"}
}