{
  "type": "Feature",
  "properties": {
    "gn:admin1_code":"25.0",
    "gn:admin2_code":"1515.0",
    "gn:asciiname":"Al Ghayl",
    "gn:country_code":"YE",
    "gn:dem":1885,
    "gn:feature_class":"P",
    "gn:feature_code":"PPL",
    "gn:name":"Al Ghayl",
    "gn:population":0,
    "gn:timezone":"Asia/Aden",
    "iso:country":"YE",
    "name:ara_x_preferred":[
        "\u0627\u0644\u063a\u064a\u0644"
    ],
    "wof:name":"Al Ghayl",
    "wof:placetype":"locality"
},
  "geometry": {"coordinates":[44.12974000000001,13.23254],"type":"Point"}
}