{
  "type": "Feature",
  "properties": {
    "gn:country":"YE",
    "gn:fcode":"PPL",
    "gn:population":3,
    "iso:country":"YE",
    "name:ara_x_preferred":[
        "\u0627\u0644\u0635\u0628\u064a\u062d\u0629"
    ],
    "name:eng_x_preferred":[
        "As Sabihah"
    ],
    "name:eng_x_variant":[
        "Al Mut\u0101ris"
    ],
    "qs:name":"A\u015f \u015eab\u012b\u1e29ah",
    "qs:photos_9r":0,
    "qs:photos_sr":0,
    "qs:pop_sr":"1",
    "wof:name":"A\u015f \u015eab\u012b\u1e29ah",
    "wof:placetype":"locality",
    "wof:population":3
},
  "geometry": {"coordinates":[43.3996,16.08795],"type":"Point"}
}