{
  "type": "Feature",
  "properties": {
    "gn:admin1_code":"10.0",
    "gn:admin2_code":"2707.0",
    "gn:asciiname":"At Tawil",
    "gn:country_code":"YE",
    "gn:dem":1782,
    "gn:feature_class":"P",
    "gn:feature_code":"PPL",
    "gn:name":"A\u0163 \u0162aw\u012bl",
    "gn:population":0,
    "gn:timezone":"Asia/Aden",
    "iso:country":"YE",
    "name:und_x_variant":[
        "A\u0163 \u0162aw\u012bl"
    ],
    "wof:name":"At Tawil",
    "wof:placetype":"locality"
},
  "geometry": {"coordinates":[43.4682,15.28198],"type":"Point"}
}