{
  "type": "Feature",
  "properties": {
    "gn:admin1_code":"24.0",
    "gn:admin2_code":"2512.0",
    "gn:asciiname":"Al Kadid",
    "gn:country_code":"YE",
    "gn:dem":994,
    "gn:feature_class":"P",
    "gn:feature_code":"PPL",
    "gn:name":"Al Kad\u012bd",
    "gn:population":0,
    "gn:timezone":"Asia/Aden",
    "iso:country":"YE",
    "name:ara_x_preferred":[
        "\u0627\u0644\u0643\u062f\u064a\u062f"
    ],
    "name:und_x_variant":[
        "Al Kad\u012bd"
    ],
    "wof:name":"Al Kadid",
    "wof:placetype":"locality"
},
  "geometry": {"coordinates":[44.17104000000001,13.15481],"type":"Point"}
}