{
  "type": "Feature",
  "properties": {
    "gn:admin1_code":"15.0",
    "gn:admin2_code":"2209.0",
    "gn:asciiname":"Thimamah",
    "gn:country_code":"YE",
    "gn:dem":2244,
    "gn:feature_class":"P",
    "gn:feature_code":"PPL",
    "gn:name":"Thim\u0101mah",
    "gn:population":0,
    "gn:timezone":"Asia/Aden",
    "iso:country":"YE",
    "name:ara_x_preferred":[
        "\u062b\u0645\u0627\u0645\u0629"
    ],
    "name:und_x_variant":[
        "Thim\u0101mah"
    ],
    "wof:name":"Thimamah",
    "wof:placetype":"locality"
},
  "geometry": {"coordinates":[43.44107,16.88679],"type":"Point"}
}