{
  "type": "Feature",
  "properties": {
    "gn:admin1_code":"19.0",
    "gn:admin2_code":"2908.0",
    "gn:asciiname":"Ad Dal'ah",
    "gn:country_code":"YE",
    "gn:dem":1630,
    "gn:feature_class":"P",
    "gn:feature_code":"PPL",
    "gn:name":"A\u1e11 \u1e10al\u2018ah",
    "gn:population":0,
    "gn:timezone":"Asia/Aden",
    "iso:country":"YE",
    "name:ara_x_preferred":[
        "\u0627\u0644\u0636\u0644\u0639\u0629"
    ],
    "name:und_x_variant":[
        "A\u1e11 \u1e10al\u2018ah"
    ],
    "wof:name":"Ad Dal'ah",
    "wof:placetype":"locality"
},
  "geometry": {"coordinates":[43.72281,16.10912],"type":"Point"}
}