{
  "type": "Feature",
  "properties": {
    "gn:admin1_code":"21.0",
    "gn:admin2_code":"1603.0",
    "gn:asciiname":"Nahd al Adaj",
    "gn:country_code":"YE",
    "gn:dem":1217,
    "gn:feature_class":"P",
    "gn:feature_code":"PPLL",
    "gn:name":"Na\u1e29d al A\u1e11aj",
    "gn:population":0,
    "gn:timezone":"Asia/Aden",
    "iso:country":"YE",
    "name:ara_x_preferred":[
        "\u0646\u062d\u062f \u0627\u0644\u0623\u0636\u062c"
    ],
    "name:und_x_variant":[
        "Na\u1e29d al A\u1e11aj"
    ],
    "wof:name":"Nahd al Adaj",
    "wof:placetype":"locality"
},
  "geometry": {"coordinates":[44.37166,16.16406],"type":"Point"}
}