{
  "type": "Feature",
  "properties": {
    "gn:admin1_code":"11.0",
    "gn:asciiname":"Al Ghawl",
    "gn:country_code":"YE",
    "gn:dem":2153,
    "gn:feature_class":"P",
    "gn:feature_code":"PPL",
    "gn:name":"Al Ghawl",
    "gn:population":0,
    "gn:timezone":"Asia/Aden",
    "iso:country":"YE",
    "name:ara_x_preferred":[
        "\u0627\u0644\u063a\u0648\u0644"
    ],
    "wof:name":"Al Ghawl",
    "wof:placetype":"locality"
},
  "geometry": {"coordinates":[44.25861,14.36362],"type":"Point"}
}