{
  "type": "Feature",
  "properties": {
    "gn:admin1_code":"14.0",
    "gn:admin2_code":"2602.0",
    "gn:asciiname":"Badw Sammar",
    "gn:country_code":"YE",
    "gn:dem":1112,
    "gn:feature_class":"P",
    "gn:feature_code":"PPL",
    "gn:name":"Badw Samm\u0101r",
    "gn:population":0,
    "gn:timezone":"Asia/Aden",
    "iso:country":"YE",
    "name:ara_x_preferred":[
        "\u0628\u062f\u0648 \u0633\u0645\u0627\u0631"
    ],
    "name:und_x_variant":[
        "Badw Samm\u0101r"
    ],
    "wof:name":"Badw Sammar",
    "wof:placetype":"locality"
},
  "geometry": {"coordinates":[45.05285,15.74598],"type":"Point"}
}