{
  "type": "Feature",
  "properties": {
    "gn:admin1_code":"19.0",
    "gn:admin2_code":"2905.0",
    "gn:asciiname":"Suq al Qasabah",
    "gn:country_code":"YE",
    "gn:dem":1479,
    "gn:feature_class":"P",
    "gn:feature_code":"PPL",
    "gn:name":"S\u016bq al Qa\u015fabah",
    "gn:population":0,
    "gn:timezone":"Asia/Aden",
    "iso:country":"YE",
    "name:ara_x_preferred":[
        "\u0633\u0648\u0642 \u0627\u0644\u0642\u0635\u0628\u0629"
    ],
    "name:und_x_variant":[
        "S\u016bq al Qa\u015fabah"
    ],
    "wof:name":"Suq al Qasabah",
    "wof:placetype":"locality"
},
  "geometry": {"coordinates":[43.70059000000001,16.14409],"type":"Point"}
}