{
  "type": "Feature",
  "properties": {
    "gn:admin1_code":"8.0",
    "gn:admin2_code":"1814.0",
    "gn:asciiname":"Ad Dahamah",
    "gn:country_code":"YE",
    "gn:dem":17,
    "gn:feature_class":"P",
    "gn:feature_code":"PPL",
    "gn:name":"Ad Dah\u0101mah",
    "gn:population":0,
    "gn:timezone":"Asia/Aden",
    "iso:country":"YE",
    "name:ara_x_preferred":[
        "\u0627\u0644\u062f\u0647\u0627\u0645\u0629"
    ],
    "name:und_x_variant":[
        "Ad Dah\u0101mah"
    ],
    "wof:name":"Ad Dahamah",
    "wof:placetype":"locality"
},
  "geometry": {"coordinates":[43.01569,14.68233],"type":"Point"}
}