{
  "type": "Feature",
  "properties": {
    "gn:admin1_code":"8.0",
    "gn:admin2_code":"1801.0",
    "gn:asciiname":"Kidf az Zughbi",
    "gn:country_code":"YE",
    "gn:dem":160,
    "gn:feature_class":"P",
    "gn:feature_code":"PPL",
    "gn:name":"Kidf az Zughb\u012b",
    "gn:population":0,
    "gn:timezone":"Asia/Aden",
    "iso:country":"YE",
    "name:und_x_variant":[
        "Kidf az Zughb\u012b"
    ],
    "wof:name":"Kidf az Zughbi",
    "wof:placetype":"locality"
},
  "geometry": {"coordinates":[43.19983,15.73061],"type":"Point"}
}