{
  "type": "Feature",
  "properties": {
    "gn:admin1_code":"15.0",
    "gn:admin2_code":"2206.0",
    "gn:asciiname":"Al Mashraqiyah",
    "gn:country_code":"YE",
    "gn:dem":320,
    "gn:feature_class":"P",
    "gn:feature_code":"PPL",
    "gn:name":"Al Mashraq\u012byah",
    "gn:population":0,
    "gn:timezone":"Asia/Aden",
    "iso:country":"YE",
    "name:ara_x_preferred":[
        "\u0627\u0644\u0645\u0634\u0631\u0642\u064a\u0629"
    ],
    "name:und_x_variant":[
        "Al Mashraq\u012byah"
    ],
    "wof:name":"Al Mashraqiyah",
    "wof:placetype":"locality"
},
  "geometry": {"coordinates":[43.15603,16.92847],"type":"Point"}
}