{
  "type": "Feature",
  "properties": {
    "gn:country":"YE",
    "gn:fcode":"PPL",
    "gn:population":3,
    "iso:country":"YE",
    "name:ara_x_preferred":[
        "Sh\u0101khir"
    ],
    "name:ara_x_variant":[
        "\u0634\u0627\u062c\u0631"
    ],
    "qs:name":"Sh\u0101khir",
    "qs:photos_9r":0,
    "qs:photos_sr":0,
    "qs:pop_sr":"1",
    "wof:name":"Sh\u0101khir",
    "wof:placetype":"locality",
    "wof:population":3
},
  "geometry": {"coordinates":[43.97083,16.70653],"type":"Point"}
}