{
  "type": "Feature",
  "properties": {
    "gn:country":"YE",
    "gn:fcode":"PPL",
    "gn:population":58,
    "iso:country":"YE",
    "name:ara_x_preferred":[
        "\u0627\u0644\u0639\u0628\u064a\u062f\u064a"
    ],
    "name:und_x_variant":[
        "Ma\u1e29all al \u2018Ubayd\u012b"
    ],
    "qs:name":"Al \u2018Ubayd\u012b",
    "qs:photos_9r":0,
    "qs:photos_sr":0,
    "qs:pop_sr":"1",
    "wof:name":"Al \u2018Ubayd\u012b",
    "wof:placetype":"locality",
    "wof:population":58
},
  "geometry": {"coordinates":[43.73532,16.81492],"type":"Point"}
}