{
  "type": "Feature",
  "properties": {
    "gn:admin1_code":"21.0",
    "gn:admin2_code":"1611.0",
    "gn:asciiname":"Ash Shirayy al A`la",
    "gn:country_code":"YE",
    "gn:dem":2055,
    "gn:feature_class":"P",
    "gn:feature_code":"PPL",
    "gn:name":"Ash Shirayy al A\u2018l\u00e1",
    "gn:population":0,
    "gn:timezone":"Asia/Aden",
    "iso:country":"YE",
    "name:und_x_variant":[
        "Ash Shirayy al A\u2018l\u00e1"
    ],
    "wof:name":"Ash Shirayy al A`la",
    "wof:placetype":"locality"
},
  "geometry": {"coordinates":[44.45656,16.67265],"type":"Point"}
}