{
  "type": "Feature",
  "properties": {
    "gn:country":"YE",
    "gn:fcode":"PPL",
    "gn:pop":8,
    "iso:country":"YE",
    "name:ara_x_preferred":[
        "\u0627\u0644\u062c\u0631\u0642"
    ],
    "name:eng_x_preferred":[
        "Al Jurriq"
    ],
    "qs:name":"Al Jurriq",
    "qs:photos_9r":0,
    "qs:photos_sr":0,
    "qs:pop_sr":"1",
    "wof:name":"Al Jurriq",
    "wof:placetype":"locality",
    "wof:population":8
},
  "geometry": {"coordinates":[43.36271,16.25424],"type":"Point"}
}