{
  "type": "Feature",
  "properties": {
    "gn:admin1_code":"5.0",
    "gn:admin2_code":"2111.0",
    "gn:asciiname":"Qa` Ba Musallam",
    "gn:country_code":"YE",
    "gn:dem":1411,
    "gn:feature_class":"P",
    "gn:feature_code":"PPL",
    "gn:name":"Q\u0101\u2018 B\u0101 Musallam",
    "gn:population":0,
    "gn:timezone":"Asia/Aden",
    "iso:country":"YE",
    "name:und_x_variant":[
        "Q\u0101\u2018 B\u0101 Musallam"
    ],
    "wof:name":"Qa` Ba Musallam",
    "wof:placetype":"locality"
},
  "geometry": {"coordinates":[46.4836,14.27144],"type":"Point"}
}