{
  "type": "Feature",
  "properties": {
    "gn:admin1_code":"11.0",
    "gn:admin2_code":"2003.0",
    "gn:asciiname":"Mahall Ghurab",
    "gn:country_code":"YE",
    "gn:dem":2225,
    "gn:feature_class":"P",
    "gn:feature_code":"PPL",
    "gn:name":"Ma\u1e29all Ghur\u0101b",
    "gn:population":0,
    "gn:timezone":"Asia/Aden",
    "iso:country":"YE",
    "name:und_x_variant":[
        "Ma\u1e29all Ghur\u0101b"
    ],
    "wof:name":"Mahall Ghurab",
    "wof:placetype":"locality"
},
  "geometry": {"coordinates":[44.02148,14.6855],"type":"Point"}
}