{
  "type": "Feature",
  "properties": {
    "gn:admin1_code":"23.0",
    "gn:admin2_code":"1110.0",
    "gn:asciiname":"Ash Sharaf Bani Yusuf",
    "gn:country_code":"YE",
    "gn:dem":1377,
    "gn:feature_class":"P",
    "gn:feature_code":"PPL",
    "gn:name":"Ash Sharaf Ban\u012b Y\u016bsuf",
    "gn:population":0,
    "gn:timezone":"Asia/Aden",
    "iso:country":"YE",
    "name:ara_x_preferred":[
        "\u0627\u0644\u0634\u0631\u0641"
    ],
    "name:und_x_variant":[
        "Ash Sharaf Ban\u012b Y\u016bsuf",
        "Ash Shurf"
    ],
    "wof:name":"Ash Sharaf Bani Yusuf",
    "wof:placetype":"locality"
},
  "geometry": {"coordinates":[43.80651,13.91077],"type":"Point"}
}