{
  "type": "Feature",
  "properties": {
    "gn:admin1_code":"22.0",
    "gn:admin2_code":"1725.0",
    "gn:asciiname":"At Tawrayn",
    "gn:country_code":"YE",
    "gn:dem":1305,
    "gn:feature_class":"P",
    "gn:feature_code":"PPL",
    "gn:name":"At Tawrayn",
    "gn:population":0,
    "gn:timezone":"Asia/Aden",
    "iso:country":"YE",
    "name:ara_x_preferred":[
        "\u0631\u062f\u0645\u0627\u0646"
    ],
    "wof:name":"At Tawrayn",
    "wof:placetype":"locality"
},
  "geometry": {"coordinates":[43.5552,15.58283],"type":"Point"}
}