{
  "type": "Feature",
  "properties": {
    "gn:admin1_code":"25.0",
    "gn:admin2_code":"1517.0",
    "gn:asciiname":"Hibal ad Daym",
    "gn:country_code":"YE",
    "gn:dem":1476,
    "gn:feature_class":"P",
    "gn:feature_code":"PPL",
    "gn:name":"\u1e28ib\u0101l ad Daym",
    "gn:population":0,
    "gn:timezone":"Asia/Aden",
    "iso:country":"YE",
    "name:ara_x_preferred":[
        "\u062d\u0628\u0627\u0644 \u0627\u0644\u062f\u064a\u0645"
    ],
    "name:und_x_variant":[
        "\u1e28ib\u0101l ad Daym"
    ],
    "wof:name":"Hibal ad Daym",
    "wof:placetype":"locality"
},
  "geometry": {"coordinates":[44.18675,13.22491],"type":"Point"}
}