{
  "type": "Feature",
  "properties": {
    "gn:admin1_code":"23.0",
    "gn:admin2_code":"1101.0",
    "gn:asciiname":"Al Mihja'",
    "gn:country_code":"YE",
    "gn:dem":876,
    "gn:feature_class":"P",
    "gn:feature_code":"PPL",
    "gn:name":"Al Mi\u1e29j\u0101\u2019",
    "gn:population":0,
    "gn:timezone":"Asia/Aden",
    "iso:country":"YE",
    "name:ara_x_preferred":[
        "\u0627\u0644\u0645\u062d\u062c\u0627\u0621"
    ],
    "name:und_x_variant":[
        "Al Ma\u1e29j\u0101\u2019",
        "Al Mi\u1e29j\u0101\u2019"
    ],
    "wof:name":"Al Mihja'",
    "wof:placetype":"locality"
},
  "geometry": {"coordinates":[43.94702,14.21355],"type":"Point"}
}