{
  "type": "Feature",
  "properties": {
    "gn:admin1_code":"25.0",
    "gn:admin2_code":"1501.0",
    "gn:asciiname":"Mi`kashah",
    "gn:country_code":"YE",
    "gn:dem":1407,
    "gn:feature_class":"P",
    "gn:feature_code":"PPL",
    "gn:name":"Mi\u2018k\u0101shah",
    "gn:population":0,
    "gn:timezone":"Asia/Aden",
    "iso:country":"YE",
    "name:und_x_variant":[
        "Mi\u2018k\u0101shah"
    ],
    "wof:name":"Mi`kashah",
    "wof:placetype":"locality"
},
  "geometry": {"coordinates":[44.19779000000001,13.63474],"type":"Point"}
}