{
  "type": "Feature",
  "properties": {
    "gn:country":"YE",
    "gn:fcode":"PPL",
    "gn:population":7,
    "iso:country":"YE",
    "name:ara_x_preferred":[
        "\u0627\u0644\u0645\u0642\u0646\u062f\u0631"
    ],
    "name:eng_x_preferred":[
        "Al Maqnadir"
    ],
    "name:eng_x_variant":[
        "Al Falakhah"
    ],
    "qs:name":"Al Maqnadir",
    "qs:photos_9r":0,
    "qs:photos_sr":0,
    "qs:pop_sr":"1",
    "wof:name":"Al Maqnadir",
    "wof:placetype":"locality",
    "wof:population":7
},
  "geometry": {"coordinates":[43.23556,17.17457],"type":"Point"}
}