{
  "type": "Feature",
  "properties": {
    "iso:country":"YE",
    "ne:ADM0CAP":0.0,
    "ne:ADM0NAME":"Yemen",
    "ne:ADM0_A3":"YEM",
    "ne:ADM1NAME":"Al Bayda'",
    "ne:ADMIN1_COD":0,
    "ne:CAPALT":0,
    "ne:CHANGED":0,
    "ne:CHECKME":0,
    "ne:COMPARE":0,
    "ne:DIFFASCII":0,
    "ne:ELEVATION":0.0,
    "ne:FEATURECLA":"Populated place",
    "ne:GEONAMEID":-1,
    "ne:GEONAMESNO":"No GeoNames match due to small population, not in GeoNames, or poor NEV placement.",
    "ne:GN_POP":0,
    "ne:GTOPO30":0.0,
    "ne:ISO_A2":"YE",
    "ne:LABELRANK":6,
    "ne:LATITUDE":14.429493,
    "ne:LONGITUDE":44.8341,
    "ne:LS_MATCH":1,
    "ne:LS_NAME":"Rida",
    "ne:MAX_AREAKM":23.0,
    "ne:MAX_AREAMI":9.0,
    "ne:MAX_BBXMAX":44.866667,
    "ne:MAX_BBXMIN":44.808333,
    "ne:MAX_BBYMAX":14.45,
    "ne:MAX_BBYMIN":14.4,
    "ne:MAX_NATSCA":20.0,
    "ne:MAX_PERKM":24.0,
    "ne:MAX_PERMI":15.0,
    "ne:MAX_POP10":45233,
    "ne:MAX_POP20":45233,
    "ne:MAX_POP300":0,
    "ne:MAX_POP310":0,
    "ne:MAX_POP50":0,
    "ne:MEAN_BBXC":44.84256,
    "ne:MEAN_BBYC":14.419048,
    "ne:MEGACITY":0,
    "ne:MIN_AREAKM":23.0,
    "ne:MIN_AREAMI":9.0,
    "ne:MIN_BBXMAX":44.866667,
    "ne:MIN_BBXMIN":44.808333,
    "ne:MIN_BBYMAX":14.45,
    "ne:MIN_BBYMIN":14.4,
    "ne:MIN_PERKM":24.0,
    "ne:MIN_PERMI":15.0,
    "ne:NAME":"Rida",
    "ne:NAMEASCII":"Rida",
    "ne:NAMEDIFF":0,
    "ne:NATSCALE":20,
    "ne:POP1950":0,
    "ne:POP1955":0,
    "ne:POP1960":0,
    "ne:POP1965":0,
    "ne:POP1970":0,
    "ne:POP1975":0,
    "ne:POP1980":0,
    "ne:POP1985":0,
    "ne:POP1990":0,
    "ne:POP1995":0,
    "ne:POP2000":0,
    "ne:POP2005":0,
    "ne:POP2010":0,
    "ne:POP2015":0,
    "ne:POP2020":0,
    "ne:POP2025":0,
    "ne:POP2050":0,
    "ne:POP_MAX":45233,
    "ne:POP_MIN":45233,
    "ne:POP_OTHER":45233,
    "ne:RANK_MAX":7,
    "ne:RANK_MIN":7,
    "ne:SCALERANK":7,
    "ne:SOV0NAME":"Yemen",
    "ne:SOV_A3":"YEM",
    "ne:UN_FID":0,
    "ne:UN_LAT":0.0,
    "ne:UN_LONG":0.0,
    "ne:WORLDCITY":0,
    "ne:min_zoom":6.7,
    "wof:name":"Rida",
    "wof:placetype":"locality"
},
  "geometry": {"coordinates":[44.83410029987147,14.42949261368096],"type":"Point"}
}