{
  "type": "Feature",
  "properties": {
    "gn:admin1_code":"22.0",
    "gn:admin2_code":"1727.0",
    "gn:asciiname":"Madhabah",
    "gn:country_code":"YE",
    "gn:dem":1253,
    "gn:feature_class":"P",
    "gn:feature_code":"PPL",
    "gn:name":"Madh\u0101bah",
    "gn:population":0,
    "gn:timezone":"Asia/Aden",
    "iso:country":"YE",
    "name:ara_x_preferred":[
        "\u0645\u0630\u0627\u0628\u0629"
    ],
    "name:und_x_variant":[
        "Madh\u0101bah"
    ],
    "wof:name":"Madhabah",
    "wof:placetype":"locality"
},
  "geometry": {"coordinates":[43.61545,15.55489],"type":"Point"}
}