{
  "type": "Feature",
  "properties": {
    "gn:country":"YE",
    "gn:fcode":"PPL",
    "gn:pop":3,
    "iso:country":"YE",
    "name:ara_x_preferred":[
        "\u0627\u0644\u0637\u062e\u0628\u0629"
    ],
    "name:eng_x_preferred":[
        "At Tujbah"
    ],
    "name:eng_x_variant":[
        "Gh\u0101rib al Khiy\u0101lah"
    ],
    "qs:name":"A\u0163 \u0162ujbah",
    "qs:photos_9r":0,
    "qs:photos_sr":0,
    "qs:pop_sr":"1",
    "wof:name":"A\u0163 \u0162ujbah",
    "wof:placetype":"locality",
    "wof:population":3
},
  "geometry": {"coordinates":[43.40825,16.29178],"type":"Point"}
}