{
  "type": "Feature",
  "properties": {
    "gn:admin1_code":"25.0",
    "gn:admin2_code":"1516.0",
    "gn:asciiname":"Ash Sharjayn",
    "gn:country_code":"YE",
    "gn:dem":672,
    "gn:feature_class":"P",
    "gn:feature_code":"PPL",
    "gn:name":"Ash Sharjayn",
    "gn:population":0,
    "gn:timezone":"Asia/Aden",
    "iso:country":"YE",
    "name:ara_x_preferred":[
        "\u0627\u0644\u0634\u0631\u062c\u064a\u0646"
    ],
    "name:und_x_variant":[
        "Ash Sharqayn",
        "Ash Sharjayn"
    ],
    "wof:name":"Ash Sharjayn",
    "wof:placetype":"locality"
},
  "geometry": {"coordinates":[43.7847,13.12501],"type":"Point"}
}