{
  "type": "Feature",
  "properties": {
    "gn:admin1_code":"15.0",
    "gn:admin2_code":"2201.0",
    "gn:asciiname":"Muraysifah",
    "gn:country_code":"YE",
    "gn:dem":1960,
    "gn:feature_class":"P",
    "gn:feature_code":"PPL",
    "gn:name":"Muray\u015fifah",
    "gn:population":0,
    "gn:timezone":"Asia/Aden",
    "iso:country":"YE",
    "name:ara_x_preferred":[
        "\u0645\u0631\u064a\u0635\u0641\u0629"
    ],
    "name:und_x_variant":[
        "Ar Ray\u015fighah",
        "\u2018Aqabat al \u2018Alb",
        "Muray\u015fifah"
    ],
    "wof:name":"Muraysifah",
    "wof:placetype":"locality"
},
  "geometry": {"coordinates":[43.42814,17.55307],"type":"Point"}
}