{
  "type": "Feature",
  "properties": {
    "gn:admin1_code":"15.0",
    "gn:admin2_code":"2209.0",
    "gn:asciiname":"Shihabah",
    "gn:country_code":"YE",
    "gn:dem":2539,
    "gn:feature_class":"P",
    "gn:feature_code":"PPL",
    "gn:name":"Shih\u0101b\u0101h",
    "gn:population":0,
    "gn:timezone":"Asia/Aden",
    "iso:country":"YE",
    "name:ara_x_preferred":[
        "Shih\u0101b\u0101h"
    ],
    "name:ara_x_variant":[
        "\u0634\u0647\u0627\u0628\u0627\u0647"
    ],
    "name:und_x_variant":[
        "Shih\u0101bah"
    ],
    "wof:name":"Shihabah",
    "wof:placetype":"locality"
},
  "geometry": {"coordinates":[43.44671,16.80767],"type":"Point"}
}