{
  "type": "Feature",
  "properties": {
    "gn:admin1_code":"22.0",
    "gn:admin2_code":"1722.0",
    "gn:asciiname":"Al Qal`ah al Bayda'",
    "gn:country_code":"YE",
    "gn:dem":202,
    "gn:feature_class":"P",
    "gn:feature_code":"PPL",
    "gn:name":"Al Qal\u2018ah al Bay\u1e11\u0101\u2019",
    "gn:population":0,
    "gn:timezone":"Asia/Aden",
    "iso:country":"YE",
    "name:und_x_variant":[
        "Al Qal\u2018ah al Bay\u1e11\u0101\u2019"
    ],
    "wof:name":"Al Qal`ah al Bayda'",
    "wof:placetype":"locality"
},
  "geometry": {"coordinates":[43.24355,15.70443],"type":"Point"}
}