{
  "type": "Feature",
  "properties": {
    "gn:country":"YE",
    "gn:fcode":"PPL",
    "gn:pop":4,
    "iso:country":"YE",
    "name:ara_x_preferred":[
        "\u0627\u0644\u0631\u0628\u064a\u0639\u064a"
    ],
    "name:eng_x_preferred":[
        "Ar Rubay'i"
    ],
    "qs:name":"Ar Rubay\u2018\u012b",
    "qs:photos_9r":0,
    "qs:photos_sr":0,
    "qs:pop_sr":"1",
    "wof:name":"Ar Rubay\u2018\u012b",
    "wof:placetype":"locality",
    "wof:population":4
},
  "geometry": {"coordinates":[43.75391,17.0141],"type":"Point"}
}