{
  "type": "Feature",
  "properties": {
    "gn:admin1_code":"21.0",
    "gn:admin2_code":"1611.0",
    "gn:asciiname":"Al Aqmar",
    "gn:country_code":"YE",
    "gn:dem":2080,
    "gn:feature_class":"P",
    "gn:feature_code":"PPL",
    "gn:name":"Al Aqmar",
    "gn:population":0,
    "gn:timezone":"Asia/Aden",
    "iso:country":"YE",
    "wof:name":"Al Aqmar",
    "wof:placetype":"locality"
},
  "geometry": {"coordinates":[44.47123,16.64258],"type":"Point"}
}