{
  "type": "Feature",
  "properties": {
    "gn:country":"YE",
    "gn:fcode":"PPL",
    "gn:population":6,
    "iso:country":"YE",
    "name:ara_x_preferred":[
        "Al \u1e28\u0101jib"
    ],
    "name:ara_x_variant":[
        "\u0627\u0644\u062d\u0627\u062c\u0628"
    ],
    "name:eng_x_preferred":[
        "Al Hajib"
    ],
    "name:eng_x_variant":[
        "Al Mir\u0101ji\u1e29"
    ],
    "qs:name":"Al \u1e28\u0101jib",
    "qs:photos_9r":0,
    "qs:photos_sr":0,
    "qs:pop_sr":"1",
    "wof:name":"Al \u1e28\u0101jib",
    "wof:placetype":"locality",
    "wof:population":6
},
  "geometry": {"coordinates":[43.89575,13.17613],"type":"Point"}
}