{
  "type": "Feature",
  "properties": {
    "gn:admin1_code":"25.0",
    "gn:admin2_code":"1509.0",
    "gn:asciiname":"Al Hujr",
    "gn:country_code":"YE",
    "gn:dem":1334,
    "gn:feature_class":"P",
    "gn:feature_code":"PPL",
    "gn:name":"Al \u1e28ujr",
    "gn:population":0,
    "gn:timezone":"Asia/Aden",
    "iso:country":"YE",
    "name:ara_x_preferred":[
        "Al \u1e28ujr"
    ],
    "wof:name":"Al Hujr",
    "wof:placetype":"locality"
},
  "geometry": {"coordinates":[43.86081,13.53755],"type":"Point"}
}