{
  "type": "Feature",
  "properties": {
    "gn:admin1_code":"25.0",
    "gn:admin2_code":"1517.0",
    "gn:asciiname":"Mirwah",
    "gn:country_code":"YE",
    "gn:dem":1473,
    "gn:feature_class":"P",
    "gn:feature_code":"PPL",
    "gn:name":"Mirwah",
    "gn:population":0,
    "gn:timezone":"Asia/Aden",
    "iso:country":"YE",
    "wof:name":"Mirwah",
    "wof:placetype":"locality"
},
  "geometry": {"coordinates":[44.32708,13.29211],"type":"Point"}
}