{
  "type": "Feature",
  "properties": {
    "gn:admin1_code":"11.0",
    "gn:admin2_code":"2009.0",
    "gn:asciiname":"Hammat ad Duhaymi",
    "gn:country_code":"YE",
    "gn:dem":2582,
    "gn:feature_class":"P",
    "gn:feature_code":"PPL",
    "gn:name":"\u1e28ammat ad Duhaym\u012b",
    "gn:population":0,
    "gn:timezone":"Asia/Aden",
    "iso:country":"YE",
    "name:und_x_variant":[
        "\u1e28ammat ad Duhaym\u012b"
    ],
    "wof:name":"Hammat ad Duhaymi",
    "wof:placetype":"locality"
},
  "geometry": {"coordinates":[44.58163,14.54256],"type":"Point"}
}