{
  "type": "Feature",
  "properties": {
    "gn:admin1_code":"8.0",
    "gn:admin2_code":"1817.0",
    "gn:asciiname":"Al Kudayrah",
    "gn:country_code":"YE",
    "gn:dem":121,
    "gn:feature_class":"P",
    "gn:feature_code":"PPL",
    "gn:name":"Al Kudayrah",
    "gn:population":0,
    "gn:timezone":"Asia/Aden",
    "iso:country":"YE",
    "wof:name":"Al Kudayrah",
    "wof:placetype":"locality"
},
  "geometry": {"coordinates":[43.3733,14.55816],"type":"Point"}
}