{
  "type": "Feature",
  "properties": {
    "gn:admin1_code":"15.0",
    "gn:admin2_code":"2209.0",
    "gn:asciiname":"Al Qadim",
    "gn:country_code":"YE",
    "gn:dem":1997,
    "gn:feature_class":"P",
    "gn:feature_code":"PPL",
    "gn:name":"Al Qad\u012bm",
    "gn:population":0,
    "gn:timezone":"Asia/Aden",
    "iso:country":"YE",
    "name:ara_x_preferred":[
        "\u0627\u0644\u0642\u062f\u064a\u0645"
    ],
    "name:und_x_variant":[
        "Al Qad\u012bm"
    ],
    "wof:name":"Al Qadim",
    "wof:placetype":"locality"
},
  "geometry": {"coordinates":[43.36946,16.90946],"type":"Point"}
}