{
  "type": "Feature",
  "properties": {
    "gn:admin1_code":"8.0",
    "gn:admin2_code":"1824.0",
    "gn:asciiname":"Mahwa al Hirrah",
    "gn:country_code":"YE",
    "gn:dem":161,
    "gn:feature_class":"P",
    "gn:feature_code":"PPL",
    "gn:name":"Ma\u1e29w\u00e1 al Hirrah",
    "gn:population":0,
    "gn:timezone":"Asia/Aden",
    "iso:country":"YE",
    "name:und_x_variant":[
        "Ma\u1e29w\u00e1 al Hirrah"
    ],
    "wof:name":"Mahwa al Hirrah",
    "wof:placetype":"locality"
},
  "geometry": {"coordinates":[43.37637,14.183],"type":"Point"}
}