{
  "type": "Feature",
  "properties": {
    "gn:admin1_code":"23.0",
    "gn:admin2_code":"1113.0",
    "gn:asciiname":"Al Jaba'ib",
    "gn:country_code":"YE",
    "gn:dem":2432,
    "gn:feature_class":"P",
    "gn:feature_code":"PPL",
    "gn:name":"Al Jab\u0101\u2019ib",
    "gn:population":0,
    "gn:timezone":"Asia/Aden",
    "iso:country":"YE",
    "name:ara_x_preferred":[
        "\u0627\u0644\u062c\u0628\u0627\u0626\u0628"
    ],
    "name:und_x_variant":[
        "Al Jab\u0101b",
        "Al Jab\u0101\u2019ib"
    ],
    "wof:name":"Al Jaba'ib",
    "wof:placetype":"locality"
},
  "geometry": {"coordinates":[44.27105,14.01928],"type":"Point"}
}