{
  "type": "Feature",
  "properties": {
    "gn:admin1_code":"25.0",
    "gn:admin2_code":"1518.0",
    "gn:asciiname":"Bi`rarah",
    "gn:country_code":"YE",
    "gn:dem":1235,
    "gn:feature_class":"P",
    "gn:feature_code":"PPL",
    "gn:name":"Bi\u2018r\u0101rah",
    "gn:population":0,
    "gn:timezone":"Asia/Aden",
    "iso:country":"YE",
    "name:und_x_variant":[
        "Bi\u2018r\u0101rah"
    ],
    "wof:name":"Bi`rarah",
    "wof:placetype":"locality"
},
  "geometry": {"coordinates":[43.99603,13.58591],"type":"Point"}
}