{
  "type": "Feature",
  "properties": {
    "gn:admin1_code":"22.0",
    "gn:admin2_code":"1710.0",
    "gn:asciiname":"Al Qaru",
    "gn:country_code":"YE",
    "gn:dem":1450,
    "gn:feature_class":"P",
    "gn:feature_code":"PPL",
    "gn:name":"Al Qar\u016b",
    "gn:population":0,
    "gn:timezone":"Asia/Aden",
    "iso:country":"YE",
    "name:ara_x_preferred":[
        "\u0627\u0644\u0642\u0631\u0648"
    ],
    "name:und_x_variant":[
        "Al Qar\u016b",
        "Al Qur\u016b\u2018"
    ],
    "wof:name":"Al Qaru",
    "wof:placetype":"locality"
},
  "geometry": {"coordinates":[43.4067,16.07834],"type":"Point"}
}