{
  "type": "Feature",
  "properties": {
    "gn:country":"YE",
    "gn:fcode":"PPL",
    "gn:population":21,
    "iso:country":"YE",
    "name:ara_x_preferred":[
        "\u0627\u0644\u0645\u0634\u0631\u0627\u0642"
    ],
    "name:eng_x_preferred":[
        "Al Mashraq"
    ],
    "name:eng_x_variant":[
        "Al \u2018Ar\u012bsh"
    ],
    "qs:name":"Al Mashr\u0101q",
    "qs:photos_9r":0,
    "qs:photos_sr":0,
    "qs:pop_sr":"1",
    "wof:name":"Al Mashr\u0101q",
    "wof:placetype":"locality",
    "wof:population":21
},
  "geometry": {"coordinates":[44.86312,16.9736],"type":"Point"}
}