{
  "type": "Feature",
  "properties": {
    "gn:country":"YE",
    "gn:fcode":"PPL",
    "gn:pop":11,
    "iso:country":"YE",
    "name:ara_x_preferred":[
        "\u0627\u0644 \u062d\u0646\u064a\u0634"
    ],
    "name:eng_x_preferred":[
        "Al Hunaysh"
    ],
    "qs:name":"\u0100l \u1e28unaysh",
    "qs:photos_9r":0,
    "qs:photos_sr":0,
    "qs:pop_sr":"1",
    "wof:name":"\u0100l \u1e28unaysh",
    "wof:placetype":"locality",
    "wof:population":11
},
  "geometry": {"coordinates":[45.57131,14.01387],"type":"Point"}
}