{
  "type": "Feature",
  "properties": {
    "gn:admin1_code":"22.0",
    "gn:admin2_code":"1722.0",
    "gn:asciiname":"Al Bashariyah",
    "gn:country_code":"YE",
    "gn:dem":755,
    "gn:feature_class":"P",
    "gn:feature_code":"PPL",
    "gn:name":"Al Bash\u0101r\u012byah",
    "gn:population":0,
    "gn:timezone":"Asia/Aden",
    "iso:country":"YE",
    "name:und_x_variant":[
        "Al Bash\u0101r\u012byah"
    ],
    "wof:name":"Al Bashariyah",
    "wof:placetype":"locality"
},
  "geometry": {"coordinates":[43.34679000000001,15.79687],"type":"Point"}
}