{
  "type": "Feature",
  "properties": {
    "gn:country":"YE",
    "gn:fcode":"PPL",
    "gn:population":1,
    "iso:country":"YE",
    "name:ara_x_preferred":[
        "\u0627\u0644\u0645\u062c\u062d\u0636"
    ],
    "name:eng_x_preferred":[
        "Al Majhau"
    ],
    "name:eng_x_variant":[
        "\u0100l Shamm\u0101n"
    ],
    "qs:name":"Al Maj\u1e29a\u1e11",
    "qs:photos_9r":0,
    "qs:photos_sr":0,
    "qs:pop_sr":"1",
    "wof:name":"Al Maj\u1e29a\u1e11",
    "wof:placetype":"locality",
    "wof:population":1
},
  "geometry": {"coordinates":[43.25634,17.22577],"type":"Point"}
}