{
  "type": "Feature",
  "properties": {
    "gn:admin1_code":"11.0",
    "gn:admin2_code":"2003.0",
    "gn:asciiname":"Athabah",
    "gn:country_code":"YE",
    "gn:dem":1952,
    "gn:feature_class":"P",
    "gn:feature_code":"PPL",
    "gn:name":"Athabah",
    "gn:population":0,
    "gn:timezone":"Asia/Aden",
    "iso:country":"YE",
    "wof:name":"Athabah",
    "wof:placetype":"locality"
},
  "geometry": {"coordinates":[43.90247,14.79414],"type":"Point"}
}