{
  "type": "Feature",
  "properties": {
    "gn:admin1_code":"8.0",
    "gn:admin2_code":"1811.0",
    "gn:asciiname":"Mahall al Qurun",
    "gn:country_code":"YE",
    "gn:dem":566,
    "gn:feature_class":"P",
    "gn:feature_code":"PPL",
    "gn:name":"Ma\u1e29all al Qur\u016bn",
    "gn:population":0,
    "gn:timezone":"Asia/Aden",
    "iso:country":"YE",
    "name:und_x_variant":[
        "Ma\u1e29all al Qur\u016bn"
    ],
    "wof:name":"Mahall al Qurun",
    "wof:placetype":"locality"
},
  "geometry": {"coordinates":[43.58882,14.96421],"type":"Point"}
}