{
  "type": "Feature",
  "properties": {
    "gn:country":"YE",
    "gn:fcode":"PPL",
    "gn:population":10,
    "iso:country":"YE",
    "name:ara_x_preferred":[
        "\u062d\u062c\u064a\u0646\u0629"
    ],
    "name:eng_x_preferred":[
        "Hujaynah"
    ],
    "name:eng_x_variant":[
        "\u0100l M\u016bs\u00e1"
    ],
    "qs:name":"\u1e28ujaynah",
    "qs:photos_9r":0,
    "qs:photos_sr":0,
    "qs:pop_sr":"1",
    "wof:name":"\u1e28ujaynah",
    "wof:placetype":"locality",
    "wof:population":10
},
  "geometry": {"coordinates":[43.78498,13.46552],"type":"Point"}
}