{
  "type": "Feature",
  "properties": {
    "gn:admin1_code":"25.0",
    "gn:admin2_code":"1505.0",
    "gn:asciiname":"Nawbat as Sawfiyah",
    "gn:country_code":"YE",
    "gn:dem":490,
    "gn:feature_class":"P",
    "gn:feature_code":"PPL",
    "gn:name":"Nawbat a\u015f \u015eawf\u012byah",
    "gn:population":0,
    "gn:timezone":"Asia/Aden",
    "iso:country":"YE",
    "name:ara_x_preferred":[
        "\u0646\u0648\u0628\u0629 \u0627\u0644\u0635\u0648\u0641\u064a\u0629"
    ],
    "name:und_x_variant":[
        "An Nawbah",
        "Nawbat a\u015f \u015eawf\u012byah"
    ],
    "wof:name":"Nawbat as Sawfiyah",
    "wof:placetype":"locality"
},
  "geometry": {"coordinates":[43.69569,13.43353],"type":"Point"}
}