{
  "type": "Feature",
  "properties": {
    "gn:admin1_code":"22.0",
    "gn:admin2_code":"1727.0",
    "gn:asciiname":"Qal`at Hatim",
    "gn:country_code":"YE",
    "gn:dem":1421,
    "gn:feature_class":"P",
    "gn:feature_code":"PPL",
    "gn:name":"Qal\u2018at \u1e28atim",
    "gn:population":0,
    "gn:timezone":"Asia/Aden",
    "iso:country":"YE",
    "name:und_x_variant":[
        "Qal\u2018at \u1e28atim"
    ],
    "wof:name":"Qal`at Hatim",
    "wof:placetype":"locality"
},
  "geometry": {"coordinates":[43.58015,15.56539],"type":"Point"}
}