{
  "type": "Feature",
  "properties": {
    "gn:country":"YE",
    "gn:fcode":"PPL",
    "gn:pop":8,
    "iso:country":"YE",
    "name:ara_x_preferred":[
        "\u0627\u0644\u0641\u0631\u0639\u064a\u0646"
    ],
    "name:eng_x_preferred":[
        "Al Gharayir"
    ],
    "name:unk_x_variant":[
        "Al Far\u2018\u012bn"
    ],
    "qs:name":"Al Ghar\u0101yir",
    "qs:photos_9r":0,
    "qs:photos_sr":0,
    "qs:pop_sr":"1",
    "wof:name":"Al Ghar\u0101yir",
    "wof:placetype":"locality",
    "wof:population":8
},
  "geometry": {"coordinates":[44.06661,17.07114],"type":"Point"}
}