{
  "type": "Feature",
  "properties": {
    "gn:admin1_code":"8.0",
    "gn:admin2_code":"1807.0",
    "gn:asciiname":"Mahall Abkar 'Ali Muhammad",
    "gn:country_code":"YE",
    "gn:dem":41,
    "gn:feature_class":"P",
    "gn:feature_code":"PPL",
    "gn:name":"Ma\u1e29all Abkar \u2018Al\u012b Mu\u1e29ammad",
    "gn:population":0,
    "gn:timezone":"Asia/Aden",
    "iso:country":"YE",
    "name:ara_x_preferred":[
        "\u0645\u062d\u0644 \u0623\u0628\u0643\u0631 \u0639\u0644\u064a \u0645\u062d\u0645\u062f"
    ],
    "name:und_x_variant":[
        "Ma\u1e29all Abkar \u2018Al\u012b Mu\u1e29ammad"
    ],
    "wof:name":"Mahall Abkar 'Ali Muhammad",
    "wof:placetype":"locality"
},
  "geometry": {"coordinates":[42.96113,15.23398],"type":"Point"}
}