{
  "type": "Feature",
  "properties": {
    "gn:admin1_code":"16.0",
    "gn:admin2_code":"2308.0",
    "gn:asciiname":"Al Halilah",
    "gn:country_code":"YE",
    "gn:dem":2644,
    "gn:feature_class":"P",
    "gn:feature_code":"PPL",
    "gn:name":"Al \u1e28al\u012blah",
    "gn:population":0,
    "gn:timezone":"Asia/Aden",
    "iso:country":"YE",
    "name:und_x_variant":[
        "Al \u1e28al\u012blah"
    ],
    "wof:name":"Al Halilah",
    "wof:placetype":"locality"
},
  "geometry": {"coordinates":[43.93264,15.25499],"type":"Point"}
}