{
  "type": "Feature",
  "properties": {
    "gn:admin1_code":"23.0",
    "gn:admin2_code":"1110.0",
    "gn:asciiname":"Al Majahish",
    "gn:country_code":"YE",
    "gn:dem":718,
    "gn:feature_class":"P",
    "gn:feature_code":"PPL",
    "gn:name":"Al Maj\u0101\u1e29\u012bsh",
    "gn:population":0,
    "gn:timezone":"Asia/Aden",
    "iso:country":"YE",
    "name:ara_x_preferred":[
        "\u0627\u0644\u0645\u062c\u0627\u062d\u064a\u0634"
    ],
    "name:und_x_variant":[
        "Al Maj\u0101\u1e29\u012bsh"
    ],
    "wof:name":"Al Majahish",
    "wof:placetype":"locality"
},
  "geometry": {"coordinates":[43.7448,13.95622],"type":"Point"}
}