{
  "type": "Feature",
  "properties": {
    "gn:country":"YE",
    "gn:fcode":"PPL",
    "gn:pop":2,
    "iso:country":"YE",
    "name:ara_x_preferred":[
        "\u0644\u0645\u0644\u0627\u0644"
    ],
    "name:eng_x_preferred":[
        "Lamlal"
    ],
    "qs:name":"Laml\u0101l",
    "qs:photos_9r":0,
    "qs:photos_sr":0,
    "qs:pop_sr":"1",
    "wof:name":"Laml\u0101l",
    "wof:placetype":"locality",
    "wof:population":2
},
  "geometry": {"coordinates":[45.01532,14.73832],"type":"Point"}
}