{
  "type": "Feature",
  "properties": {
    "gn:admin1_code":"18.0",
    "gn:admin2_code":"3004.0",
    "gn:asciiname":"`Ar`ar",
    "gn:country_code":"YE",
    "gn:dem":2236,
    "gn:feature_class":"P",
    "gn:feature_code":"PPL",
    "gn:name":"\u2018Ar\u2018ar",
    "gn:population":0,
    "gn:timezone":"Asia/Aden",
    "iso:country":"YE",
    "name:und_x_variant":[
        "Ara\u2019ar",
        "\u2018Ar\u2018ar"
    ],
    "wof:name":"`Ar`ar",
    "wof:placetype":"locality"
},
  "geometry": {"coordinates":[44.83333,13.88333],"type":"Point"}
}