{
  "type": "Feature",
  "properties": {
    "gn:admin1_code":"23.0",
    "gn:admin2_code":"1101.0",
    "gn:asciiname":"Suq al Ahad",
    "gn:country_code":"YE",
    "gn:dem":1473,
    "gn:feature_class":"P",
    "gn:feature_code":"PPL",
    "gn:name":"S\u016bq al A\u1e29ad",
    "gn:population":0,
    "gn:timezone":"Asia/Aden",
    "iso:country":"YE",
    "name:ara_x_preferred":[
        "\u0633\u0648\u0642 \u0627\u0644\u0623\u062d\u062f"
    ],
    "name:und_x_variant":[
        "S\u016bq al A\u1e29ad"
    ],
    "wof:name":"Suq al Ahad",
    "wof:placetype":"locality"
},
  "geometry": {"coordinates":[44.1284,14.35025],"type":"Point"}
}