{
  "type": "Feature",
  "properties": {
    "gn:admin1_code":"19.0",
    "gn:admin2_code":"2901.0",
    "gn:asciiname":"Sayfan",
    "gn:country_code":"YE",
    "gn:dem":1599,
    "gn:feature_class":"P",
    "gn:feature_code":"PPL",
    "gn:name":"\u015eayf\u0101n",
    "gn:population":0,
    "gn:timezone":"Asia/Aden",
    "iso:country":"YE",
    "name:und_x_variant":[
        "\u015eayf\u0101n"
    ],
    "wof:name":"Sayfan",
    "wof:placetype":"locality"
},
  "geometry": {"coordinates":[44.06295,16.41855],"type":"Point"}
}