{
  "type": "Feature",
  "properties": {
    "gn:admin1_code":"8.0",
    "gn:admin2_code":"1807.0",
    "gn:asciiname":"Dayr Muhammad",
    "gn:country_code":"YE",
    "gn:dem":51,
    "gn:feature_class":"P",
    "gn:feature_code":"PPL",
    "gn:name":"Dayr Mu\u1e29ammad",
    "gn:population":0,
    "gn:timezone":"Asia/Aden",
    "iso:country":"YE",
    "name:ara_x_preferred":[
        "\u062f\u064a\u0631 \u0645\u062d\u0645\u062f"
    ],
    "name:und_x_variant":[
        "Dayr Mu\u1e29ammad"
    ],
    "wof:name":"Dayr Muhammad",
    "wof:placetype":"locality"
},
  "geometry": {"coordinates":[42.98727,15.22171],"type":"Point"}
}