{
  "type": "Feature",
  "properties": {
    "gn:admin1_code":"23.0",
    "gn:admin2_code":"1101.0",
    "gn:asciiname":"Rababah",
    "gn:country_code":"YE",
    "gn:dem":1239,
    "gn:feature_class":"P",
    "gn:feature_code":"PPL",
    "gn:name":"Rab\u0101bah",
    "gn:population":0,
    "gn:timezone":"Asia/Aden",
    "iso:country":"YE",
    "name:ara_x_preferred":[
        "\u0631\u0628\u0627\u0628\u0629"
    ],
    "name:und_x_variant":[
        "Rab\u0101bah"
    ],
    "wof:name":"Rababah",
    "wof:placetype":"locality"
},
  "geometry": {"coordinates":[44.07551,14.30687],"type":"Point"}
}