{
  "type": "Feature",
  "properties": {
    "gn:country":"YE",
    "gn:fcode":"PPL",
    "gn:population":6,
    "iso:country":"YE",
    "name:ara_x_preferred":[
        "\u0627\u0644\u0644\u0643\u0628\u0629"
    ],
    "name:eng_x_preferred":[
        "Al Lakbah"
    ],
    "name:eng_x_variant":[
        "Shirqah"
    ],
    "qs:name":"Al Lakbah",
    "qs:photos_9r":0,
    "qs:photos_sr":0,
    "qs:pop_sr":"1",
    "wof:name":"Al Lakbah",
    "wof:placetype":"locality",
    "wof:population":6
},
  "geometry": {"coordinates":[43.315,16.24407],"type":"Point"}
}