{
  "type": "Feature",
  "properties": {
    "gn:admin1_code":"22.0",
    "gn:admin2_code":"1721.0",
    "gn:asciiname":"As Sahal",
    "gn:country_code":"YE",
    "gn:dem":1494,
    "gn:feature_class":"P",
    "gn:feature_code":"PPL",
    "gn:name":"As Sa\u1e29al",
    "gn:population":0,
    "gn:timezone":"Asia/Aden",
    "iso:country":"YE",
    "name:und_x_variant":[
        "As Sa\u1e29al"
    ],
    "wof:name":"As Sahal",
    "wof:placetype":"locality"
},
  "geometry": {"coordinates":[43.41959,15.84151],"type":"Point"}
}