{
  "type": "Feature",
  "properties": {
    "gn:admin1_code":"24.0",
    "gn:admin2_code":"2513.0",
    "gn:asciiname":"Makhabbah",
    "gn:country_code":"YE",
    "gn:dem":1,
    "gn:feature_class":"P",
    "gn:feature_code":"PPL",
    "gn:name":"Makhabbah",
    "gn:population":0,
    "gn:timezone":"Asia/Aden",
    "iso:country":"YE",
    "wof:name":"Makhabbah",
    "wof:placetype":"locality"
},
  "geometry": {"coordinates":[43.82403,12.6756],"type":"Point"}
}