{
  "type": "Feature",
  "properties": {
    "gn:admin1_code":"8.0",
    "gn:admin2_code":"1824.0",
    "gn:asciiname":"Al Bughayl",
    "gn:country_code":"YE",
    "gn:dem":176,
    "gn:feature_class":"P",
    "gn:feature_code":"PPL",
    "gn:name":"Al Bughayl",
    "gn:population":0,
    "gn:timezone":"Asia/Aden",
    "iso:country":"YE",
    "name:und_x_variant":[
        "El Bugheil",
        "Al Bughayl"
    ],
    "wof:name":"Al Bughayl",
    "wof:placetype":"locality"
},
  "geometry": {"coordinates":[43.46454,13.97903],"type":"Point"}
}