{
  "type": "Feature",
  "properties": {
    "gn:admin1_code":"23.0",
    "gn:admin2_code":"1101.0",
    "gn:asciiname":"'Aynan as Sufla",
    "gn:country_code":"YE",
    "gn:dem":1932,
    "gn:feature_class":"P",
    "gn:feature_code":"PPL",
    "gn:name":"\u2018Ayn\u0101n as Sufl\u00e1",
    "gn:population":0,
    "gn:timezone":"Asia/Aden",
    "iso:country":"YE",
    "name:ara_x_preferred":[
        "\u0639\u064a\u0646\u0627\u0646 \u0627\u0644\u0633\u0641\u0644\u0649"
    ],
    "name:und_x_variant":[
        "\u2018Ayn\u0101n as Sufl\u00e1"
    ],
    "wof:name":"'Aynan as Sufla",
    "wof:placetype":"locality"
},
  "geometry": {"coordinates":[44.20488,14.26184],"type":"Point"}
}