{
  "type": "Feature",
  "properties": {
    "gn:admin1_code":"22.0",
    "gn:admin2_code":"1716.0",
    "gn:asciiname":"Al Qal`ah",
    "gn:country_code":"YE",
    "gn:dem":1591,
    "gn:feature_class":"P",
    "gn:feature_code":"PPL",
    "gn:name":"Al Qal\u2018ah",
    "gn:population":0,
    "gn:timezone":"Asia/Aden",
    "iso:country":"YE",
    "name:und_x_variant":[
        "Al Qal\u2018ah"
    ],
    "wof:name":"Al Qal`ah",
    "wof:placetype":"locality"
},
  "geometry": {"coordinates":[43.52567,15.93784],"type":"Point"}
}