{
  "type": "Feature",
  "properties": {
    "gn:admin1_code":"24.0",
    "gn:admin2_code":"2512.0",
    "gn:asciiname":"Al Murayqib",
    "gn:country_code":"YE",
    "gn:dem":1291,
    "gn:feature_class":"P",
    "gn:feature_code":"PPL",
    "gn:name":"Al Murayqib",
    "gn:population":0,
    "gn:timezone":"Asia/Aden",
    "iso:country":"YE",
    "name:ara_x_preferred":[
        "\u0627\u0644\u0645\u0631\u064a\u0642\u0628"
    ],
    "wof:name":"Al Murayqib",
    "wof:placetype":"locality"
},
  "geometry": {"coordinates":[44.18512,13.16518],"type":"Point"}
}