{
  "type": "Feature",
  "properties": {
    "gn:admin1_code":"8.0",
    "gn:asciiname":"Al Ghanjah",
    "gn:country_code":"YE",
    "gn:dem":-9999,
    "gn:feature_class":"P",
    "gn:feature_code":"PPL",
    "gn:name":"Al Ghanjah",
    "gn:population":0,
    "gn:timezone":"Asia/Aden",
    "iso:country":"YE",
    "name:und_x_variant":[
        "El Ghenja",
        "El Ghanja",
        "Ghanja",
        "Al Ghanjah"
    ],
    "wof:name":"Al Ghanjah",
    "wof:placetype":"locality"
},
  "geometry": {"coordinates":[43.16667,13.93333],"type":"Point"}
}