{
  "type": "Feature",
  "properties": {
    "gn:country":"YE",
    "gn:fcode":"PPL",
    "gn:pop":13,
    "iso:country":"YE",
    "name:ara_x_preferred":[
        "\u0627\u0644\u062c\u0631\u0627\u062d\u064a\u0629"
    ],
    "name:ara_x_variant":[
        "\u0627\u0644\u0639\u0642\u062f\u0629",
        "\u0627\u0644\u062c\u0631\u0627\u0641\u064a\u0629"
    ],
    "name:unk_x_variant":[
        "Al \u2018Aqadah"
    ],
    "qs:name":"Al Jar\u0101\u1e29\u012byah",
    "qs:photos_9r":0,
    "qs:photos_sr":0,
    "qs:pop_sr":"1",
    "wof:name":"Al Jar\u0101\u1e29\u012byah",
    "wof:placetype":"locality",
    "wof:population":13
},
  "geometry": {"coordinates":[43.0436,16.22504],"type":"Point"}
}