{
  "type": "Feature",
  "properties": {
    "gn:admin1_code":"15.0",
    "gn:admin2_code":"2207.0",
    "gn:asciiname":"Ra'shah",
    "gn:country_code":"YE",
    "gn:dem":305,
    "gn:feature_class":"P",
    "gn:feature_code":"PPL",
    "gn:name":"Ra\u2018shah",
    "gn:population":0,
    "gn:timezone":"Asia/Aden",
    "iso:country":"YE",
    "name:ara_x_preferred":[
        "\u0631\u0639\u0634\u0629"
    ],
    "name:und_x_variant":[
        "Ra\u2018shah"
    ],
    "wof:name":"Ra'shah",
    "wof:placetype":"locality"
},
  "geometry": {"coordinates":[43.24567,16.80577000000001],"type":"Point"}
}