{
  "type": "Feature",
  "properties": {
    "gn:admin1_code":"11.0",
    "gn:admin2_code":"2012.0",
    "gn:asciiname":"Bayt al Qamadi",
    "gn:country_code":"YE",
    "gn:dem":1907,
    "gn:feature_class":"P",
    "gn:feature_code":"PPL",
    "gn:name":"Bayt al Qam\u0101d\u012b",
    "gn:population":0,
    "gn:timezone":"Asia/Aden",
    "iso:country":"YE",
    "name:und_x_variant":[
        "Bayt al Qam\u0101d\u012b"
    ],
    "wof:name":"Bayt al Qamadi",
    "wof:placetype":"locality"
},
  "geometry": {"coordinates":[44.09814,14.71338],"type":"Point"}
}