{
  "type": "Feature",
  "properties": {
    "gn:admin1_code":"22.0",
    "gn:admin2_code":"1712.0",
    "gn:asciiname":"Bani Muzim",
    "gn:country_code":"YE",
    "gn:dem":446,
    "gn:feature_class":"P",
    "gn:feature_code":"PPL",
    "gn:name":"Ban\u012b Muz\u0327\u012bm",
    "gn:population":0,
    "gn:timezone":"Asia/Aden",
    "iso:country":"YE",
    "name:und_x_variant":[
        "Ban\u012b Muz\u0327\u012bm"
    ],
    "wof:name":"Bani Muzim",
    "wof:placetype":"locality"
},
  "geometry": {"coordinates":[43.28915,16.13077],"type":"Point"}
}