{
  "type": "Feature",
  "properties": {
    "gn:admin1_code":"14.0",
    "gn:admin2_code":"2602.0",
    "gn:asciiname":"As Sahil",
    "gn:country_code":"YE",
    "gn:dem":1120,
    "gn:feature_class":"P",
    "gn:feature_code":"PPLL",
    "gn:name":"As S\u0101\u1e29il",
    "gn:population":0,
    "gn:timezone":"Asia/Aden",
    "iso:country":"YE",
    "name:ara_x_preferred":[
        "\u0627\u0644\u0633\u0627\u062d\u0644"
    ],
    "name:und_x_variant":[
        "As S\u0101\u1e29il"
    ],
    "wof:name":"As Sahil",
    "wof:placetype":"locality"
},
  "geometry": {"coordinates":[45.04671,15.71153],"type":"Point"}
}