{
  "type": "Feature",
  "properties": {
    "gn:admin1_code":"21.0",
    "gn:admin2_code":"1606.0",
    "gn:asciiname":"Bani Shihab",
    "gn:country_code":"YE",
    "gn:dem":1184,
    "gn:feature_class":"P",
    "gn:feature_code":"PPL",
    "gn:name":"Ban\u012b Shih\u0101b",
    "gn:population":0,
    "gn:timezone":"Asia/Aden",
    "iso:country":"YE",
    "name:ara_x_preferred":[
        "\u0628\u0646\u064a \u0634\u0647\u0627\u0628"
    ],
    "name:und_x_variant":[
        "Ban\u012b Shih\u0101b"
    ],
    "wof:name":"Bani Shihab",
    "wof:placetype":"locality"
},
  "geometry": {"coordinates":[44.53471,16.27107],"type":"Point"}
}