{
  "type": "Feature",
  "properties": {
    "gn:admin1_code":"10.0",
    "gn:admin2_code":"2709.0",
    "gn:asciiname":"Bi'r `Ali",
    "gn:country_code":"YE",
    "gn:dem":1248,
    "gn:feature_class":"P",
    "gn:feature_code":"PPL",
    "gn:name":"Bi\u2019r \u2018Al\u012b",
    "gn:population":0,
    "gn:timezone":"Asia/Aden",
    "iso:country":"YE",
    "name:ara_x_preferred":[
        "Bi\u2019r \u2018Al\u012b"
    ],
    "name:ara_x_variant":[
        "\u0628\u0626\u0631 \u0639\u0644\u064a"
    ],
    "name:fra_x_preferred":[
        "Bir Ali"
    ],
    "name:hrv_x_preferred":[
        "Bir Ali"
    ],
    "name:nno_x_preferred":[
        "Bi'r `Ali"
    ],
    "name:rus_x_preferred":[
        "\u0411\u0438\u0440-\u0410\u043b\u0438"
    ],
    "name:tur_x_preferred":[
        "Bir Ali"
    ],
    "wof:name":"Bi'r `Ali",
    "wof:placetype":"locality"
},
  "geometry": {"coordinates":[43.63985,15.35744],"type":"Point"}
}