{
  "type": "Feature",
  "properties": {
    "gn:admin1_code":"8.0",
    "gn:admin2_code":"1816.0",
    "gn:asciiname":"Makin",
    "gn:country_code":"YE",
    "gn:dem":139,
    "gn:feature_class":"P",
    "gn:feature_code":"PPL",
    "gn:name":"Mak\u012bn",
    "gn:population":0,
    "gn:timezone":"Asia/Aden",
    "iso:country":"YE",
    "name:ceb_x_preferred":[
        "Makin"
    ],
    "name:deu_x_preferred":[
        "Makin"
    ],
    "name:jpn_x_preferred":[
        "\u30de\u30ad\u30f3"
    ],
    "name:nds_x_preferred":[
        "Makin"
    ],
    "name:rus_x_preferred":[
        "\u041c\u0430\u043a\u0438\u043d"
    ],
    "name:swe_x_preferred":[
        "Makin"
    ],
    "name:und_x_variant":[
        "Makine",
        "Mak\u012bn"
    ],
    "wof:name":"Makin",
    "wof:placetype":"locality"
},
  "geometry": {"coordinates":[43.39775,14.64726],"type":"Point"}
}