{
  "type": "Feature",
  "properties": {
    "gn:admin1_code":"8.0",
    "gn:admin2_code":"1816.0",
    "gn:asciiname":"Makin",
    "gn:country_code":"YE",
    "gn:dem":139,
    "gn:feature_class":"P",
    "gn:feature_code":"PPL",
    "gn:name":"Mak\u012bn",
    "gn:population":0,
    "gn:timezone":"Asia/Aden",
    "iso:country":"YE",
    "name:und_x_variant":[
        "Makine",
        "Mak\u012bn"
    ],
    "wof:name":"Makin",
    "wof:placetype":"locality"
},
  "geometry": {"coordinates":[43.39775,14.64726],"type":"Point"}
}