{
  "type": "Feature",
  "properties": {
    "gn:country":"YE",
    "gn:fcode":"PPL",
    "gn:pop":9,
    "iso:country":"YE",
    "name:ara_x_preferred":[
        "Al J\u0101zi\u2018"
    ],
    "name:ara_x_variant":[
        "\u0627\u0644\u062c\u0627\u0632\u0639"
    ],
    "name:eng_x_preferred":[
        "Al Jazi'"
    ],
    "qs:name":"Al J\u0101zi\u2018",
    "qs:photos_9r":0,
    "qs:photos_sr":0,
    "qs:pop_sr":"1",
    "wof:name":"Al J\u0101zi\u2018",
    "wof:placetype":"locality",
    "wof:population":9
},
  "geometry": {"coordinates":[45.36008,14.64137],"type":"Point"}
}