{
  "type": "Feature",
  "properties": {
    "gn:country":"YE",
    "gn:fcode":"PPL",
    "gn:population":80,
    "iso:country":"YE",
    "name:ara_x_preferred":[
        "Al B\u0101\u0163il"
    ],
    "name:ara_x_variant":[
        "\u0627\u0644\u0628\u0627\u0637\u0644"
    ],
    "name:eng_x_preferred":[
        "Al Batil"
    ],
    "name:eng_x_variant":[
        "A\u015f \u015eadaqah"
    ],
    "name:und_x_variant":[
        "Dayr al B\u0101\u0163il"
    ],
    "qs:name":"Al B\u0101\u0163il",
    "qs:photos_9r":0,
    "qs:photos_sr":0,
    "qs:pop_sr":"1",
    "wof:name":"Al B\u0101\u0163il",
    "wof:placetype":"locality",
    "wof:population":80
},
  "geometry": {"coordinates":[43.19334,15.99329],"type":"Point"}
}