{
  "type": "Feature",
  "properties": {
    "gn:admin1_code":"22.0",
    "gn:admin2_code":"1709.0",
    "gn:asciiname":"At Tur al Asfal",
    "gn:country_code":"YE",
    "gn:dem":1339,
    "gn:feature_class":"P",
    "gn:feature_code":"PPL",
    "gn:name":"A\u0163 \u0162\u016br al Asfal",
    "gn:population":0,
    "gn:timezone":"Asia/Aden",
    "iso:country":"YE",
    "name:und_x_variant":[
        "A\u0163 \u0162\u016br al Asfal"
    ],
    "wof:name":"At Tur al Asfal",
    "wof:placetype":"locality"
},
  "geometry": {"coordinates":[43.53727,15.98573],"type":"Point"}
}