{
  "type": "Feature",
  "properties": {
    "gn:admin1_code":"5.0",
    "gn:admin2_code":"2101.0",
    "gn:asciiname":"Dar Muhaymud",
    "gn:country_code":"YE",
    "gn:dem":885,
    "gn:feature_class":"P",
    "gn:feature_code":"PPL",
    "gn:name":"D\u0101r Mu\u1e29aym\u016bd",
    "gn:population":0,
    "gn:timezone":"Asia/Aden",
    "iso:country":"YE",
    "name:und_x_variant":[
        "D\u0101r Muhaim\u016bd",
        "D\u0101r Mu\u1e29aym\u012bd",
        "D\u0101r Mu\u1e29aym\u016bd"
    ],
    "wof:name":"Dar Muhaymud",
    "wof:placetype":"locality"
},
  "geometry": {"coordinates":[47.58198,15.49543],"type":"Point"}
}