{
  "type": "Feature",
  "properties": {
    "gn:admin1_code":"23.0",
    "gn:admin2_code":"1101.0",
    "gn:asciiname":"Ka'abah",
    "gn:country_code":"YE",
    "gn:dem":1216,
    "gn:feature_class":"P",
    "gn:feature_code":"PPL",
    "gn:name":"Ka\u2018\u0101bah",
    "gn:population":0,
    "gn:timezone":"Asia/Aden",
    "iso:country":"YE",
    "name:ara_x_preferred":[
        "\u0643\u0639\u0627\u0628\u0629"
    ],
    "name:und_x_variant":[
        "Ka\u2018\u0101bah"
    ],
    "wof:name":"Ka'abah",
    "wof:placetype":"locality"
},
  "geometry": {"coordinates":[44.00211,14.31069],"type":"Point"}
}