{
  "type": "Feature",
  "properties": {
    "gn:admin1_code":"22.0",
    "gn:admin2_code":"1714.0",
    "gn:asciiname":"Bayt Ghaylan",
    "gn:country_code":"YE",
    "gn:dem":951,
    "gn:feature_class":"P",
    "gn:feature_code":"PPL",
    "gn:name":"Bayt Ghayl\u0101n",
    "gn:population":0,
    "gn:timezone":"Asia/Aden",
    "iso:country":"YE",
    "name:und_x_variant":[
        "Bayt Ghayl\u0101n"
    ],
    "wof:name":"Bayt Ghaylan",
    "wof:placetype":"locality"
},
  "geometry": {"coordinates":[43.42376,15.963],"type":"Point"}
}