{
  "type": "Feature",
  "properties": {
    "gn:admin1_code":"19.0",
    "gn:admin2_code":"2901.0",
    "gn:asciiname":"Shi'ab Sabarah",
    "gn:country_code":"YE",
    "gn:dem":1657,
    "gn:feature_class":"P",
    "gn:feature_code":"PPLL",
    "gn:name":"Shi\u2018\u0101b \u015eab\u0101rah",
    "gn:population":0,
    "gn:timezone":"Asia/Aden",
    "iso:country":"YE",
    "name:ara_x_preferred":[
        "\u0634\u0639\u0627\u0628 \u0635\u0628\u0627\u0631\u0629"
    ],
    "name:und_x_variant":[
        "Shi\u2018\u0101b \u015eab\u0101rah"
    ],
    "wof:name":"Shi'ab Sabarah",
    "wof:placetype":"locality"
},
  "geometry": {"coordinates":[44.18505,16.42985],"type":"Point"}
}