{
  "type": "Feature",
  "properties": {
    "gn:admin1_code":"25.0",
    "gn:admin2_code":"1521.0",
    "gn:asciiname":"Al Mihras",
    "gn:country_code":"YE",
    "gn:dem":1085,
    "gn:feature_class":"P",
    "gn:feature_code":"PPL",
    "gn:name":"Al Mi\u1e29r\u0101s",
    "gn:population":0,
    "gn:timezone":"Asia/Aden",
    "iso:country":"YE",
    "name:ara_x_preferred":[
        "Al Mi\u1e29r\u0101s"
    ],
    "wof:name":"Al Mihras",
    "wof:placetype":"locality"
},
  "geometry": {"coordinates":[43.95668,13.42631],"type":"Point"}
}