{
  "type": "Feature",
  "properties": {
    "gn:admin1_code":"4.0",
    "gn:asciiname":"Ahil Rumaydan",
    "gn:country_code":"YE",
    "gn:dem":901,
    "gn:feature_class":"P",
    "gn:feature_code":"PPL",
    "gn:name":"Ahil Rumayd\u0101n",
    "gn:population":0,
    "gn:timezone":"Asia/Aden",
    "iso:country":"YE",
    "name:ara_x_preferred":[
        "\u0623\u0647\u0644 \u0631\u0645\u064a\u062f\u0627\u0646"
    ],
    "name:und_x_variant":[
        "Ahil Rumayd\u0101n"
    ],
    "wof:name":"Ahil Rumaydan",
    "wof:placetype":"locality"
},
  "geometry": {"coordinates":[48.22692,16.6238],"type":"Point"}
}