{
  "type": "Feature",
  "properties": {
    "gn:admin1_code":"23.0",
    "gn:admin2_code":"1115.0",
    "gn:asciiname":"Bisherak",
    "gn:country_code":"YE",
    "gn:dem":2326,
    "gn:feature_class":"P",
    "gn:feature_code":"PPL",
    "gn:name":"Bisherak",
    "gn:population":0,
    "gn:timezone":"Asia/Aden",
    "iso:country":"YE",
    "wof:name":"Bisherak",
    "wof:placetype":"locality"
},
  "geometry": {"coordinates":[44.18333,13.86667],"type":"Point"}
}