{
  "type": "Feature",
  "properties": {
    "gn:country":"YE",
    "gn:fcode":"PPL",
    "gn:pop":16,
    "iso:country":"YE",
    "name:ara_x_preferred":[
        "\u0627\u0644\u0628\u0631\u0642\u0629"
    ],
    "name:eng_x_preferred":[
        "Al Bariqah"
    ],
    "qs:name":"Al Bariqah",
    "qs:photos_9r":0,
    "qs:photos_sr":0,
    "qs:pop_sr":"1",
    "wof:name":"Al Bariqah",
    "wof:placetype":"locality",
    "wof:population":16
},
  "geometry": {"coordinates":[44.41162,16.69989],"type":"Point"}
}