{
  "type": "Feature",
  "properties": {
    "gn:admin1_code":"19.0",
    "gn:admin2_code":"2909.0",
    "gn:asciiname":"Al Kulaybi",
    "gn:country_code":"YE",
    "gn:dem":1664,
    "gn:feature_class":"P",
    "gn:feature_code":"PPL",
    "gn:name":"Al Kulayb\u012b",
    "gn:population":0,
    "gn:timezone":"Asia/Aden",
    "iso:country":"YE",
    "name:ara_x_preferred":[
        "\u0627\u0644\u0643\u0644\u064a\u0628\u064a"
    ],
    "name:und_x_variant":[
        "Al Kulayb\u012b"
    ],
    "wof:name":"Al Kulaybi",
    "wof:placetype":"locality"
},
  "geometry": {"coordinates":[44.16293,16.00571],"type":"Point"}
}