{
  "type": "Feature",
  "properties": {
    "gn:country":"YE",
    "gn:fcode":"PPL",
    "gn:population":5,
    "iso:country":"YE",
    "name:ara_x_preferred":[
        "Al Mu\u015fb\u0101r"
    ],
    "name:ara_x_variant":[
        "\u0627\u0644\u0645\u0635\u0628\u0627\u0631"
    ],
    "qs:name":"Al Mu\u015fb\u0101r",
    "qs:photos_9r":0,
    "qs:photos_sr":0,
    "qs:pop_sr":"1",
    "wof:name":"Al Mu\u015fb\u0101r",
    "wof:placetype":"locality",
    "wof:population":5
},
  "geometry": {"coordinates":[43.36903,16.16075],"type":"Point"}
}