{
  "type": "Feature",
  "properties": {
    "gn:country":"YE",
    "gn:fcode":"PPL",
    "gn:pop":9,
    "iso:country":"YE",
    "name:ara_x_preferred":[
        "Al \u2018Id\u0101l"
    ],
    "name:ara_x_variant":[
        "\u0627\u0644\u0639\u062f\u0627\u0644"
    ],
    "name:eng_x_preferred":[
        "Al 'Idal"
    ],
    "qs:name":"Al \u2018Id\u0101l",
    "qs:photos_9r":0,
    "qs:photos_sr":0,
    "qs:pop_sr":"1",
    "wof:name":"Al \u2018Id\u0101l",
    "wof:placetype":"locality",
    "wof:population":9
},
  "geometry": {"coordinates":[43.97352,16.98921],"type":"Point"}
}