{
  "type": "Feature",
  "properties": {
    "gn:admin1_code":"5.0",
    "gn:asciiname":"Al Muhayyis",
    "gn:country_code":"YE",
    "gn:dem":1202,
    "gn:feature_class":"P",
    "gn:feature_code":"PPL",
    "gn:name":"Al Mu\u1e29ayyis",
    "gn:population":0,
    "gn:timezone":"Asia/Aden",
    "iso:country":"YE",
    "name:ara_x_preferred":[
        "\u0627\u0644\u0645\u062d\u064a\u064a\u0633"
    ],
    "name:und_x_variant":[
        "Al Mu\u1e29ayyis"
    ],
    "wof:name":"Al Muhayyis",
    "wof:placetype":"locality"
},
  "geometry": {"coordinates":[45.92078,14.5646],"type":"Point"}
}