{
  "type": "Feature",
  "properties": {
    "gn:country":"YE",
    "gn:fcode":"PPL",
    "gn:pop":1,
    "iso:country":"YE",
    "name:ara_x_preferred":[
        "\u062c\u0648\u0629 \u062d\u0648\u0627"
    ],
    "name:eng_x_preferred":[
        "Jawwat Huwa"
    ],
    "qs:name":"Jawwat \u1e28uw\u0101",
    "qs:photos_9r":0,
    "qs:photos_sr":0,
    "qs:pop_sr":"1",
    "wof:name":"Jawwat \u1e28uw\u0101",
    "wof:placetype":"locality",
    "wof:population":1
},
  "geometry": {"coordinates":[44.46247,16.87462],"type":"Point"}
}