{
  "type": "Feature",
  "properties": {
    "gn:country":"YE",
    "gn:fcode":"PPL",
    "gn:pop":1,
    "iso:country":"YE",
    "name:ara_x_preferred":[
        "\u0627\u0644\u0646\u062c\u062f"
    ],
    "name:eng_x_preferred":[
        "An Najd"
    ],
    "name:fas_x_preferred":[
        "\u0627\u0646 \u0646\u062c\u062f"
    ],
    "name:nno_x_preferred":[
        "An Najd"
    ],
    "qs:name":"An Najd",
    "qs:photos_9r":0,
    "qs:photos_sr":0,
    "qs:pop_sr":"1",
    "wd:wordcount":23,
    "wof:name":"An Najd",
    "wof:placetype":"locality",
    "wof:population":1
},
  "geometry": {"coordinates":[45.18777,14.91103],"type":"Point"}
}