{
  "type": "Feature",
  "properties": {
    "gn:country":"YE",
    "gn:fcode":"PPLX",
    "gn:population":9,
    "iso:country":"YE",
    "name:ara_x_preferred":[
        "Al \u2018Ab\u0101l"
    ],
    "name:ara_x_variant":[
        "\u0627\u0644\u0639\u0628\u0627\u0644"
    ],
    "qs:name":"Al \u2018Ab\u0101l",
    "qs:photos_9r":0,
    "qs:photos_sr":0,
    "qs:pop_sr":"1",
    "wof:name":"Al \u2018Ab\u0101l",
    "wof:placetype":"neighbourhood",
    "wof:population":9
},
  "geometry": {"coordinates":[50.31711,15.01843],"type":"Point"}
}