{
  "type": "Feature",
  "properties": {
    "gn:admin1_code":"8.0",
    "gn:admin2_code":"1814.0",
    "gn:asciiname":"Bayt al Ja`bali",
    "gn:country_code":"YE",
    "gn:dem":38,
    "gn:feature_class":"P",
    "gn:feature_code":"PPL",
    "gn:name":"Bayt al Ja\u2018bal\u012b",
    "gn:population":0,
    "gn:timezone":"Asia/Aden",
    "iso:country":"YE",
    "name:ara_x_preferred":[
        "\u0628\u064a\u062a \u0627\u0644\u062c\u0639\u0628\u0644\u064a"
    ],
    "name:und_x_variant":[
        "Bayt al Ja\u2018bal\u012b"
    ],
    "wof:name":"Bayt al Ja`bali",
    "wof:placetype":"locality"
},
  "geometry": {"coordinates":[43.08704,14.74623],"type":"Point"}
}