{
  "type": "Feature",
  "properties": {
    "gn:gn_country":"YE",
    "gn:gn_fcode":"PPL",
    "gn:gn_pop":8,
    "gn:population":8,
    "iso:country":"YE",
    "name:ara_x_preferred":[
        "\u0627\u0644\u062e\u0646\u0627\u064a\u0629"
    ],
    "name:eng_x_preferred":[
        "Al Khanayah"
    ],
    "qs_pg:aaroncc":"YE",
    "qs_pg:gn_country":"YE",
    "qs_pg:gn_fcode":"PPL",
    "qs_pg:gn_pop":8,
    "qs_pg:name":"Al Khan\u0101yah",
    "qs_pg:photos_9r":0,
    "qs_pg:photos_sr":0,
    "qs_pg:pop_sr":1,
    "qs_pg:qs_pg_placetype":"locality",
    "wof:name":"Al Khan\u0101yah",
    "wof:placetype":"locality",
    "wof:population":8
},
  "geometry": {"coordinates":[43.28763,16.19109],"type":"Point"}
}