{
  "type": "Feature",
  "properties": {
    "gn:admin1_code":"4.0",
    "gn:admin2_code":"1917.0",
    "gn:asciiname":"Husun Bin Humam",
    "gn:cc2":"YE",
    "gn:country_code":"YE",
    "gn:dem":100,
    "gn:feature_class":"P",
    "gn:feature_code":"PPL",
    "gn:name":"\u1e28u\u015f\u016bn Bin Hum\u0101m",
    "gn:population":0,
    "gn:timezone":"Asia/Aden",
    "iso:country":"YE",
    "name:ara_x_preferred":[
        "\u1e28u\u015f\u016bn Bin Hum\u0101m"
    ],
    "name:nno_x_preferred":[
        "Husun Bin Humam"
    ],
    "name:und_x_variant":[
        "Hus\u016bn B\u012bn Hum\u0101n",
        "\u1e28u\u015f\u016bn Bin Ham\u0101m"
    ],
    "wof:name":"Husun Bin Humam",
    "wof:placetype":"locality"
},
  "geometry": {"coordinates":[49.345,14.78611],"type":"Point"}
}