{
  "type": "Feature",
  "properties": {
    "gn:admin1_code":"8.0",
    "gn:admin2_code":"1814.0",
    "gn:asciiname":"Al Harashiyah",
    "gn:country_code":"YE",
    "gn:dem":50,
    "gn:feature_class":"P",
    "gn:feature_code":"PPL",
    "gn:name":"Al Har\u0101sh\u012byah",
    "gn:population":0,
    "gn:timezone":"Asia/Aden",
    "iso:country":"YE",
    "name:ara_x_preferred":[
        "\u0627\u0644\u0647\u0631\u0627\u0634\u064a\u0629"
    ],
    "name:und_x_variant":[
        "Al Har\u0101sh\u012byah"
    ],
    "wof:name":"Al Harashiyah",
    "wof:placetype":"locality"
},
  "geometry": {"coordinates":[43.1052,14.78657],"type":"Point"}
}