{
  "type": "Feature",
  "properties": {
    "gn:country":"YE",
    "gn:fcode":"PPLX",
    "gn:population":5,
    "iso:country":"YE",
    "name:ara_x_preferred":[
        "\u0627\u0644\u0645\u0648\u0642\u0639"
    ],
    "name:eng_x_preferred":[
        "Al-Mawqa`"
    ],
    "name:fas_x_preferred":[
        "\u0627\u0644-\u0645\u0627\u0648\u06a9\u0627\u0639"
    ],
    "name:nld_x_preferred":[
        "Al-Mawqa`"
    ],
    "name:nno_x_preferred":[
        "Al-Mawqa`"
    ],
    "qs:name":"Al Mawqa\u2018",
    "qs:photos_9r":0,
    "qs:photos_sr":0,
    "qs:pop_sr":"1",
    "wd:wordcount":23,
    "wof:name":"Al Mawqa\u2018",
    "wof:placetype":"neighbourhood",
    "wof:population":5
},
  "geometry": {"coordinates":[43.63605,16.18907],"type":"Point"}
}