{
  "type": "Feature",
  "properties": {
    "gn:admin1_code":"20.0",
    "gn:asciiname":"As Samh",
    "gn:country_code":"YE",
    "gn:dem":2548,
    "gn:feature_class":"P",
    "gn:feature_code":"PPL",
    "gn:name":"A\u015f \u015eam\u1e29",
    "gn:population":0,
    "gn:timezone":"Asia/Aden",
    "iso:country":"YE",
    "name:ara_x_preferred":[
        "\u0627\u0644\u0635\u0645\u062d"
    ],
    "name:und_x_variant":[
        "A\u015f \u015eam\u1e29"
    ],
    "wof:name":"As Samh",
    "wof:placetype":"locality"
},
  "geometry": {"coordinates":[44.42937,14.39087],"type":"Point"}
}