{
  "type": "Feature",
  "properties": {
    "gn:country":"YE",
    "gn:fcode":"PPL",
    "gn:pop":11,
    "iso:country":"YE",
    "name:ara_x_preferred":[
        "\u0627\u0644 \u062d\u0645\u0627\u0645\u0629"
    ],
    "name:eng_x_preferred":[
        "Al Hamamah"
    ],
    "qs:name":"\u0100l \u1e28am\u0101mah",
    "qs:photos_9r":0,
    "qs:photos_sr":0,
    "qs:pop_sr":"1",
    "wof:name":"\u0100l \u1e28am\u0101mah",
    "wof:placetype":"locality",
    "wof:population":11
},
  "geometry": {"coordinates":[44.78264,16.15554],"type":"Point"}
}