{
  "type": "Feature",
  "properties": {
    "gn:admin1_code":"5.0",
    "gn:admin2_code":"2107.0",
    "gn:asciiname":"Himan",
    "gn:country_code":"YE",
    "gn:dem":1210,
    "gn:elevation":"2.0",
    "gn:feature_class":"P",
    "gn:feature_code":"PPL",
    "gn:name":"\u1e28im\u0101n",
    "gn:population":0,
    "gn:timezone":"Asia/Aden",
    "iso:country":"YE",
    "name:ara_x_preferred":[
        "\u1e28im\u0101n"
    ],
    "name:und_x_variant":[
        "Him\u0101m"
    ],
    "wof:name":"Himan",
    "wof:placetype":"locality"
},
  "geometry": {"coordinates":[45.65423,14.73852],"type":"Point"}
}