{
  "type": "Feature",
  "properties": {
    "gn:admin1_code":"15.0",
    "gn:admin2_code":"2206.0",
    "gn:asciiname":"Na'man",
    "gn:country_code":"YE",
    "gn:dem":1209,
    "gn:feature_class":"P",
    "gn:feature_code":"PPL",
    "gn:name":"Na\u2018m\u0101n",
    "gn:population":0,
    "gn:timezone":"Asia/Aden",
    "iso:country":"YE",
    "name:ara_x_preferred":[
        "\u0646\u0639\u0645\u0627\u0646"
    ],
    "name:und_x_variant":[
        "Na\u2018m\u0101n"
    ],
    "wof:name":"Na'man",
    "wof:placetype":"locality"
},
  "geometry": {"coordinates":[43.18251,16.91104],"type":"Point"}
}