{
  "type": "Feature",
  "properties": {
    "gn:admin1_code":"8.0",
    "gn:admin2_code":"1816.0",
    "gn:asciiname":"Bayt an Na'im",
    "gn:country_code":"YE",
    "gn:dem":97,
    "gn:feature_class":"P",
    "gn:feature_code":"PPL",
    "gn:name":"Bayt an Na\u2018\u012bm",
    "gn:population":0,
    "gn:timezone":"Asia/Aden",
    "iso:country":"YE",
    "name:ara_x_preferred":[
        "\u0628\u064a\u062a \u0627\u0644\u0646\u0639\u064a\u0645"
    ],
    "name:und_x_variant":[
        "Bayt an Na\u2018\u012bm"
    ],
    "wof:name":"Bayt an Na'im",
    "wof:placetype":"locality"
},
  "geometry": {"coordinates":[43.31896,14.64971],"type":"Point"}
}