{
  "type": "Feature",
  "properties": {
    "gn:admin1_code":"24.0",
    "gn:admin2_code":"2507.0",
    "gn:asciiname":"Ad Daqqah",
    "gn:country_code":"YE",
    "gn:dem":694,
    "gn:feature_class":"P",
    "gn:feature_code":"PPL",
    "gn:name":"Ad Daqqah",
    "gn:population":0,
    "gn:timezone":"Asia/Aden",
    "iso:country":"YE",
    "name:und_x_variant":[
        "Dakka",
        "Daqqat Bijayr",
        "Daqqat Bujayr"
    ],
    "wof:name":"Ad Daqqah",
    "wof:placetype":"locality"
},
  "geometry": {"coordinates":[44.88815,13.52689],"type":"Point"}
}