{
  "type": "Feature",
  "properties": {
    "gn:country":"YE",
    "gn:fcode":"PPL",
    "gn:pop":3,
    "iso:country":"YE",
    "name:ara_x_preferred":[
        "Ash Shir\u0101n\u012b"
    ],
    "name:ara_x_variant":[
        "\u0627\u0644\u0634\u0631\u0627\u0646\u064a"
    ],
    "name:eng_x_preferred":[
        "Ash Shirani"
    ],
    "name:eng_x_variant":[
        "\u0162al\u1e29ah"
    ],
    "qs:name":"Ash Shir\u0101n\u012b",
    "qs:photos_9r":0,
    "qs:photos_sr":0,
    "qs:pop_sr":"1",
    "wd:wordcount":9938,
    "wof:name":"Ash Shir\u0101n\u012b",
    "wof:placetype":"locality",
    "wof:population":3
},
  "geometry": {"coordinates":[43.3271,16.64777],"type":"Point"}
}