{
  "type": "Feature",
  "properties": {
    "gn:admin1_code":"25.0",
    "gn:admin2_code":"1505.0",
    "gn:asciiname":"Dimnat Mirab",
    "gn:country_code":"YE",
    "gn:dem":1110,
    "gn:feature_class":"P",
    "gn:feature_code":"PPL",
    "gn:name":"Dimnat M\u012br\u0101b",
    "gn:population":0,
    "gn:timezone":"Asia/Aden",
    "iso:country":"YE",
    "name:und_x_variant":[
        "Dimnat M\u012br\u0101b"
    ],
    "wof:name":"Dimnat Mirab",
    "wof:placetype":"locality"
},
  "geometry": {"coordinates":[43.74896,13.70447],"type":"Point"}
}