{
  "type": "Feature",
  "properties": {
    "gn:admin1_code":"16.0",
    "gn:admin2_code":"2312.0",
    "gn:asciiname":"Al Qulayb",
    "gn:country_code":"YE",
    "gn:dem":1744,
    "gn:feature_class":"P",
    "gn:feature_code":"PPL",
    "gn:name":"Al Qulayb",
    "gn:population":0,
    "gn:timezone":"Asia/Aden",
    "iso:country":"YE",
    "name:ara_x_preferred":[
        "\u0627\u0644\u0642\u0644\u064a\u0628"
    ],
    "wof:name":"Al Qulayb",
    "wof:placetype":"locality"
},
  "geometry": {"coordinates":[44.79436,15.31846],"type":"Point"}
}