{
  "type": "Feature",
  "properties": {
    "gn:country":"YE",
    "gn:fcode":"PPL",
    "gn:population":11,
    "iso:country":"YE",
    "name:ara_x_preferred":[
        "\u0628\u0644\u0648"
    ],
    "name:eng_x_preferred":[
        "Balw"
    ],
    "name:eng_x_variant":[
        "Al Khu\u1e11r\u0101\u2019"
    ],
    "qs:name":"Balw",
    "qs:photos_9r":0,
    "qs:photos_sr":0,
    "qs:pop_sr":"1",
    "wof:name":"Balw",
    "wof:placetype":"locality",
    "wof:population":11
},
  "geometry": {"coordinates":[43.37077,16.93831],"type":"Point"}
}