{
  "type": "Feature",
  "properties": {
    "gn:country":"YE",
    "gn:fcode":"PPL",
    "gn:pop":11,
    "iso:country":"YE",
    "name:ara_x_preferred":[
        "\u063a\u0631\u0628 \u0627\u0644\u0645\u062f\u0643\u0644"
    ],
    "name:eng_x_preferred":[
        "Gharb Al Mudakkil"
    ],
    "name:eng_x_variant":[
        "Al Kawmah"
    ],
    "qs:name":"Gharb al Mudakkil",
    "qs:photos_9r":0,
    "qs:photos_sr":0,
    "qs:pop_sr":"1",
    "wof:name":"Gharb al Mudakkil",
    "wof:placetype":"locality",
    "wof:population":11
},
  "geometry": {"coordinates":[43.35061,16.20619],"type":"Point"}
}