{
  "type": "Feature",
  "properties": {
    "gn:admin1_code":"24.0",
    "gn:admin2_code":"2512.0",
    "gn:asciiname":"Za'ar'ari",
    "gn:country_code":"YE",
    "gn:dem":826,
    "gn:feature_class":"P",
    "gn:feature_code":"PPL",
    "gn:name":"Za\u2018ar\u2018ar\u012b",
    "gn:population":0,
    "gn:timezone":"Asia/Aden",
    "iso:country":"YE",
    "name:ara_x_preferred":[
        "\u0632\u0639\u0631\u0639\u0631\u064a"
    ],
    "name:und_x_variant":[
        "Za\u2018ar\u2018ar\u012b"
    ],
    "wof:name":"Za'ar'ari",
    "wof:placetype":"locality"
},
  "geometry": {"coordinates":[44.19946,13.13106],"type":"Point"}
}