{
  "type": "Feature",
  "properties": {
    "gn:country":"YE",
    "gn:fcode":"PPL",
    "gn:pop":18,
    "iso:country":"YE",
    "name:ara_x_preferred":[
        "\u0627\u0644 \u062d\u062f\u0631"
    ],
    "name:eng_x_preferred":[
        "Al Hadr"
    ],
    "name:eng_x_variant":[
        "Adba\u2018"
    ],
    "qs:name":"\u0100l \u1e28adr",
    "qs:photos_9r":0,
    "qs:photos_sr":0,
    "qs:pop_sr":"1",
    "wof:name":"\u0100l \u1e28adr",
    "wof:placetype":"locality",
    "wof:population":18
},
  "geometry": {"coordinates":[45.33486,15.442],"type":"Point"}
}