{
  "type": "Feature",
  "properties": {
    "gn:admin1_code":"20.0",
    "gn:admin2_code":"1414.0",
    "gn:asciiname":"Shamlat al `Ulya",
    "gn:country_code":"YE",
    "gn:dem":2028,
    "gn:feature_class":"P",
    "gn:feature_code":"PPL",
    "gn:name":"Shamlat al \u2018Uly\u0101",
    "gn:population":0,
    "gn:timezone":"Asia/Aden",
    "iso:country":"YE",
    "name:und_x_variant":[
        "Shamlat al \u2018Uly\u0101"
    ],
    "wof:name":"Shamlat al `Ulya",
    "wof:placetype":"locality"
},
  "geometry": {"coordinates":[44.97798,14.49621],"type":"Point"}
}