{
  "type": "Feature",
  "properties": {
    "gn:admin1_code":"8.0",
    "gn:admin2_code":"1807.0",
    "gn:asciiname":"Hasan Qasim",
    "gn:country_code":"YE",
    "gn:dem":26,
    "gn:feature_class":"P",
    "gn:feature_code":"PPL",
    "gn:name":"\u1e28asan Q\u0101sim",
    "gn:population":0,
    "gn:timezone":"Asia/Aden",
    "iso:country":"YE",
    "name:ara_x_preferred":[
        "\u062d\u0633\u0646 \u0642\u0627\u0633\u0645"
    ],
    "name:und_x_variant":[
        "\u1e28asan Q\u0101sim"
    ],
    "wof:name":"Hasan Qasim",
    "wof:placetype":"locality"
},
  "geometry": {"coordinates":[42.91292,15.23218],"type":"Point"}
}