{
  "type": "Feature",
  "properties": {
    "gn:country":"YE",
    "gn:fcode":"PPL",
    "gn:population":2,
    "iso:country":"YE",
    "name:ara_x_preferred":[
        "\u0627\u0644\u0628\u064a\u062c\u0631\u0627\u0621"
    ],
    "name:eng_x_preferred":[
        "Al Bayjara"
    ],
    "name:eng_x_variant":[
        "\u1e28ayfat al \u2018Anib"
    ],
    "qs:name":"Al Bayjar\u0101\u2019",
    "qs:photos_9r":0,
    "qs:photos_sr":0,
    "qs:pop_sr":"1",
    "wof:name":"Al Bayjar\u0101\u2019",
    "wof:placetype":"locality",
    "wof:population":2
},
  "geometry": {"coordinates":[43.3429,16.19385],"type":"Point"}
}