{
  "type": "Feature",
  "properties": {
    "gn:admin1_code":"11.0",
    "gn:admin2_code":"2011.0",
    "gn:asciiname":"Wadi Sayd",
    "gn:country_code":"YE",
    "gn:dem":1627,
    "gn:feature_class":"P",
    "gn:feature_code":"PPL",
    "gn:name":"W\u0101d\u012b \u015eayd",
    "gn:population":0,
    "gn:timezone":"Asia/Aden",
    "iso:country":"YE",
    "name:und_x_variant":[
        "W\u0101d\u012b \u015eayd"
    ],
    "wof:name":"Wadi Sayd",
    "wof:placetype":"locality"
},
  "geometry": {"coordinates":[43.97557000000001,14.79244],"type":"Point"}
}