{
  "type": "Feature",
  "properties": {
    "gn:admin1_code":"23.0",
    "gn:admin2_code":"1104.0",
    "gn:asciiname":"Bayt as Sabl",
    "gn:country_code":"YE",
    "gn:dem":1876,
    "gn:feature_class":"P",
    "gn:feature_code":"PPL",
    "gn:name":"Bayt a\u015f \u015eabl",
    "gn:population":0,
    "gn:timezone":"Asia/Aden",
    "iso:country":"YE",
    "name:ara_x_preferred":[
        "\u0628\u064a\u062a \u0627\u0644\u0635\u0628\u0644"
    ],
    "name:und_x_variant":[
        "Bayt a\u015f \u015eabl"
    ],
    "wof:name":"Bayt as Sabl",
    "wof:placetype":"locality"
},
  "geometry": {"coordinates":[44.45322,14.01719],"type":"Point"}
}