{
  "type": "Feature",
  "properties": {
    "gn:admin1_code":"8.0",
    "gn:admin2_code":"1819.0",
    "gn:asciiname":"Al Kadahah",
    "gn:country_code":"YE",
    "gn:dem":283,
    "gn:feature_class":"P",
    "gn:feature_code":"PPL",
    "gn:name":"Al Kada\u1e29ah",
    "gn:population":0,
    "gn:timezone":"Asia/Aden",
    "iso:country":"YE",
    "name:und_x_variant":[
        "Al Kada\u1e29ah"
    ],
    "wof:name":"Al Kadahah",
    "wof:placetype":"locality"
},
  "geometry": {"coordinates":[43.57733,13.96225],"type":"Point"}
}