{
  "type": "Feature",
  "properties": {
    "gn:admin1_code":"25.0",
    "gn:admin2_code":"1503.0",
    "gn:asciiname":"Al Miqdar",
    "gn:country_code":"YE",
    "gn:dem":1534,
    "gn:feature_class":"P",
    "gn:feature_code":"PPL",
    "gn:name":"Al Miqd\u0101r",
    "gn:population":0,
    "gn:timezone":"Asia/Aden",
    "iso:country":"YE",
    "name:ara_x_preferred":[
        "Al Miqd\u0101r"
    ],
    "name:ara_x_variant":[
        "\u0627\u0644\u0645\u0642\u062f\u0627\u0631"
    ],
    "wof:name":"Al Miqdar",
    "wof:placetype":"locality"
},
  "geometry": {"coordinates":[43.89877,13.82808],"type":"Point"}
}