{
  "type": "Feature",
  "properties": {
    "gn:admin1_code":"8.0",
    "gn:admin2_code":"1812.0",
    "gn:asciiname":"Tabih",
    "gn:country_code":"YE",
    "gn:dem":950,
    "gn:feature_class":"P",
    "gn:feature_code":"PPL",
    "gn:name":"\u0162ab\u012b\u1e29",
    "gn:population":0,
    "gn:timezone":"Asia/Aden",
    "iso:country":"YE",
    "name:ara_x_preferred":[
        "\u0637\u0628\u064a\u062d"
    ],
    "name:und_x_variant":[
        "\u0162ab\u012b\u1e29"
    ],
    "wof:name":"Tabih",
    "wof:placetype":"locality"
},
  "geometry": {"coordinates":[43.42666,14.88394],"type":"Point"}
}