{
  "type": "Feature",
  "properties": {
    "gn:country":"YE",
    "gn:fcode":"PPL",
    "gn:pop":2,
    "iso:country":"YE",
    "name:ara_x_preferred":[
        "\u0643\u0648\u0644\u0629 \u0627\u0644\u0639\u0634\u0629"
    ],
    "name:eng_x_preferred":[
        "Kawlat Al 'Ashshah"
    ],
    "qs:name":"Kawlat al \u2018Ashshah",
    "qs:photos_9r":0,
    "qs:photos_sr":0,
    "qs:pop_sr":"1",
    "wof:name":"Kawlat al \u2018Ashshah",
    "wof:placetype":"locality",
    "wof:population":2
},
  "geometry": {"coordinates":[45.20678,14.71088],"type":"Point"}
}