{
  "type": "Feature",
  "properties": {
    "gn:admin1_code":"4.0",
    "gn:admin2_code":"1907.0",
    "gn:asciiname":"Hisn al Mala",
    "gn:country_code":"YE",
    "gn:dem":1003,
    "gn:feature_class":"P",
    "gn:feature_code":"PPL",
    "gn:name":"\u1e28i\u015fn al Mal\u0101",
    "gn:population":0,
    "gn:timezone":"Asia/Aden",
    "iso:country":"YE",
    "name:und_x_variant":[
        "\u1e28i\u015fn al Mal\u0101"
    ],
    "wof:name":"Hisn al Mala",
    "wof:placetype":"locality"
},
  "geometry": {"coordinates":[48.53333,15.98333],"type":"Point"}
}