{
  "type": "Feature",
  "properties": {
    "gn:country":"YE",
    "gn:fcode":"PPL",
    "gn:population":6,
    "iso:country":"YE",
    "name:ara_x_preferred":[
        "\u0627\u0644\u062c\u0641\u0627\u0646\u0629"
    ],
    "name:eng_x_preferred":[
        "Al Jifanah"
    ],
    "name:eng_x_variant":[
        "Bi\u2019r al Jabal"
    ],
    "qs:name":"Al Jif\u0101nah",
    "qs:photos_9r":0,
    "qs:photos_sr":0,
    "qs:pop_sr":"1",
    "wof:name":"Al Jif\u0101nah",
    "wof:placetype":"locality",
    "wof:population":6
},
  "geometry": {"coordinates":[43.34661,16.2458],"type":"Point"}
}