{
  "type": "Feature",
  "properties": {
    "gn:admin1_code":"22.0",
    "gn:admin2_code":"1721.0",
    "gn:asciiname":"Samsar",
    "gn:cc2":"YE",
    "gn:country_code":"YE",
    "gn:dem":1069,
    "gn:feature_class":"P",
    "gn:feature_code":"PPL",
    "gn:name":"Samsar",
    "gn:population":0,
    "gn:timezone":"Asia/Aden",
    "iso:country":"YE",
    "name:und_x_variant":[
        "Semsar",
        "Semsan",
        "Samsar"
    ],
    "wof:name":"Samsar",
    "wof:placetype":"locality"
},
  "geometry": {"coordinates":[43.46667,15.88333],"type":"Point"}
}