{
  "type": "Feature",
  "properties": {
    "gn:admin1_code":"20.0",
    "gn:asciiname":"Az Za`zu`",
    "gn:country_code":"YE",
    "gn:dem":-9999,
    "gn:feature_class":"P",
    "gn:feature_code":"PPL",
    "gn:name":"Az Za\u2018z\u016b\u2018",
    "gn:population":0,
    "gn:timezone":"Asia/Aden",
    "iso:country":"YE",
    "name:ara_x_preferred":[
        "\u0627\u0644\u0632\u0639\u0632\u0648\u0639"
    ],
    "name:und_x_variant":[
        "Az Za\u2018z\u016b\u2018"
    ],
    "wof:name":"Az Za`zu`",
    "wof:placetype":"locality"
},
  "geometry": {"coordinates":[0.78226,0.25402],"type":"Point"}
}