{
  "type": "Feature",
  "properties": {
    "gn:country":"YE",
    "gn:fcode":"PPL",
    "gn:population":2,
    "iso:country":"YE",
    "name:ara_x_preferred":[
        "Khir\u0101b \u2018Ar\u0101j"
    ],
    "name:ara_x_variant":[
        "\u062e\u0631\u0627\u0628 \u0639\u0631\u0627\u062c"
    ],
    "name:eng_x_preferred":[
        "Khirab 'Araj"
    ],
    "name:eng_x_variant":[
        "Sha\u2018b al \u1e28aw\u0101rik"
    ],
    "qs:name":"Khir\u0101b \u2018Ar\u0101j",
    "qs:photos_9r":0,
    "qs:photos_sr":0,
    "qs:pop_sr":"1",
    "wof:name":"Khir\u0101b \u2018Ar\u0101j",
    "wof:placetype":"locality",
    "wof:population":2
},
  "geometry": {"coordinates":[43.40188,16.25704],"type":"Point"}
}