{
  "type": "Feature",
  "properties": {
    "gn:admin1_code":"8.0",
    "gn:admin2_code":"1802.0",
    "gn:asciiname":"Al Maqasiyah",
    "gn:country_code":"YE",
    "gn:dem":56,
    "gn:feature_class":"P",
    "gn:feature_code":"PPL",
    "gn:name":"Al Maqa\u015f\u012byah",
    "gn:population":0,
    "gn:timezone":"Asia/Aden",
    "iso:country":"YE",
    "name:und_x_variant":[
        "Al Maqa\u015f\u012byah",
        "Dayr Makassiya"
    ],
    "wof:name":"Al Maqasiyah",
    "wof:placetype":"locality"
},
  "geometry": {"coordinates":[42.97906,15.54882],"type":"Point"}
}