{
  "type": "Feature",
  "properties": {
    "gn:admin1_code":"25.0",
    "gn:admin2_code":"1504.0",
    "gn:asciiname":"`Urran",
    "gn:country_code":"YE",
    "gn:dem":1096,
    "gn:feature_class":"P",
    "gn:feature_code":"PPL",
    "gn:name":"\u2018Urr\u0101n",
    "gn:population":0,
    "gn:timezone":"Asia/Aden",
    "iso:country":"YE",
    "name:ara_x_preferred":[
        "\u2018Urr\u0101n"
    ],
    "name:ara_x_variant":[
        "\u0639\u0631\u0627\u0646"
    ],
    "name:und_x_variant":[
        "\u2018Ar\u0101n"
    ],
    "wof:name":"`Urran",
    "wof:placetype":"locality"
},
  "geometry": {"coordinates":[43.7847,13.80552],"type":"Point"}
}