{
  "type": "Feature",
  "properties": {
    "gn:admin1_code":"11.0",
    "gn:admin2_code":"2001.0",
    "gn:asciiname":"Bani Qatanah",
    "gn:country_code":"YE",
    "gn:dem":2169,
    "gn:feature_class":"P",
    "gn:feature_code":"PPL",
    "gn:name":"Ban\u012b Qa\u0163anah",
    "gn:population":0,
    "gn:timezone":"Asia/Aden",
    "iso:country":"YE",
    "name:ara_x_preferred":[
        "\u0628\u0646\u064a \u0642\u0637\u0646\u0629"
    ],
    "name:und_x_variant":[
        "Ban\u012b Qa\u0163anah"
    ],
    "wof:name":"Bani Qatanah",
    "wof:placetype":"locality"
},
  "geometry": {"coordinates":[44.63137,14.76412],"type":"Point"}
}