{
  "type": "Feature",
  "properties": {
    "gn:admin1_code":"8.0",
    "gn:admin2_code":"1813.0",
    "gn:asciiname":"Mahall at Tawahirah",
    "gn:country_code":"YE",
    "gn:dem":269,
    "gn:feature_class":"P",
    "gn:feature_code":"PPL",
    "gn:name":"Ma\u1e29all a\u0163 \u0162aw\u0101hirah",
    "gn:population":0,
    "gn:timezone":"Asia/Aden",
    "iso:country":"YE",
    "name:und_x_variant":[
        "Ma\u1e29all a\u0163 \u0162aw\u0101hirah"
    ],
    "wof:name":"Mahall at Tawahirah",
    "wof:placetype":"locality"
},
  "geometry": {"coordinates":[43.39497,14.94789],"type":"Point"}
}