{
  "type": "Feature",
  "properties": {
    "gn:admin1_code":"15.0",
    "gn:admin2_code":"2203.0",
    "gn:asciiname":"Jithimah",
    "gn:country_code":"YE",
    "gn:dem":1719,
    "gn:feature_class":"P",
    "gn:feature_code":"PPL",
    "gn:name":"Jithimah",
    "gn:population":0,
    "gn:timezone":"Asia/Aden",
    "iso:country":"YE",
    "name:ara_x_preferred":[
        "\u0627\u0644\u062c\u062b\u0645\u0629"
    ],
    "name:und_x_variant":[
        "Ji\u2018thimah",
        "Jithimah"
    ],
    "wof:name":"Jithimah",
    "wof:placetype":"locality"
},
  "geometry": {"coordinates":[43.30499,17.15846],"type":"Point"}
}