{
  "type": "Feature",
  "properties": {
    "gn:admin1_code":"25.0",
    "gn:admin2_code":"1513.0",
    "gn:asciiname":"Waqis",
    "gn:country_code":"YE",
    "gn:dem":1186,
    "gn:feature_class":"P",
    "gn:feature_code":"PPL",
    "gn:name":"W\u0101qi\u015f",
    "gn:population":0,
    "gn:timezone":"Asia/Aden",
    "iso:country":"YE",
    "name:ara_x_preferred":[
        "W\u0101qi\u015f"
    ],
    "wof:name":"Waqis",
    "wof:placetype":"locality"
},
  "geometry": {"coordinates":[44.18112,13.53008],"type":"Point"}
}