{
  "type": "Feature",
  "properties": {
    "gn:country":"YE",
    "gn:fcode":"PPL",
    "gn:pop":6,
    "iso:country":"YE",
    "name:ara_x_preferred":[
        "\u0627\u0644\u062d\u0642\u0648\u064a\u0629"
    ],
    "name:eng_x_preferred":[
        "Al Haqawiyah"
    ],
    "qs:name":"Al \u1e28aqaw\u012byah",
    "qs:photos_9r":0,
    "qs:photos_sr":0,
    "qs:pop_sr":"1",
    "wof:name":"Al \u1e28aqaw\u012byah",
    "wof:placetype":"locality",
    "wof:population":6
},
  "geometry": {"coordinates":[43.33734,16.22833],"type":"Point"}
}