{
  "type": "Feature",
  "properties": {
    "gn:admin1_code":"22.0",
    "gn:admin2_code":"1709.0",
    "gn:asciiname":"Al Jamimah wa as Safih",
    "gn:country_code":"YE",
    "gn:dem":1834,
    "gn:feature_class":"P",
    "gn:feature_code":"PPL",
    "gn:name":"Al Jam\u012bmah wa a\u015f \u015e\u0101fi\u1e29",
    "gn:population":0,
    "gn:timezone":"Asia/Aden",
    "iso:country":"YE",
    "name:ara_x_preferred":[
        "\u0627\u0644\u062c\u0645\u064a\u0645\u0629 \u0648 \u0627\u0644\u0635\u0627\u0641\u062d"
    ],
    "name:und_x_variant":[
        "Al Jam\u012bmah wa a\u015f \u015e\u0101fi\u1e29"
    ],
    "wof:name":"Al Jamimah wa as Safih",
    "wof:placetype":"locality"
},
  "geometry": {"coordinates":[43.45978,16.03014],"type":"Point"}
}