{
  "type": "Feature",
  "properties": {
    "gn:country":"YE",
    "gn:fcode":"PPL",
    "gn:population":3,
    "iso:country":"YE",
    "name:ara_x_preferred":[
        "\u0628\u064a\u062a \u0627\u0644\u0644\u063a\u0629"
    ],
    "name:eng_x_preferred":[
        "Bayt Al Lughah"
    ],
    "name:eng_x_variant":[
        "Al Mu\u2018\u0101rik"
    ],
    "qs:name":"Bayt al Lughah",
    "qs:photos_9r":0,
    "qs:photos_sr":0,
    "qs:pop_sr":"1",
    "wof:name":"Bayt al Lughah",
    "wof:placetype":"locality",
    "wof:population":3
},
  "geometry": {"coordinates":[43.3877,16.07991],"type":"Point"}
}