{
  "type": "Feature",
  "properties": {
    "gn:admin1_code":"14.0",
    "gn:admin2_code":"2609.0",
    "gn:asciiname":"Harib",
    "gn:country_code":"YE",
    "gn:dem":1161,
    "gn:feature_class":"P",
    "gn:feature_code":"PPLA2",
    "gn:name":"\u1e28ar\u012bb",
    "gn:population":0,
    "gn:timezone":"Asia/Aden",
    "iso:country":"YE",
    "name:ara_x_preferred":[
        "\u062d\u0631\u064a\u0628"
    ],
    "name:und_x_variant":[
        "Darb \u0100l \u2018Al\u012b",
        "Darb al \u2018Alt",
        "\u1e28ar\u012bb"
    ],
    "wof:name":"Harib",
    "wof:placetype":"locality"
},
  "geometry": {"coordinates":[45.50356,14.93156],"type":"Point"}
}