{
  "type": "Feature",
  "properties": {
    "gn:country":"YE",
    "gn:fcode":"PPLF",
    "gn:population":10,
    "iso:country":"YE",
    "name:ara_x_preferred":[
        "\u0622\u0644 \u0627\u0644\u0639\u0648\u0627\u062f\u064a"
    ],
    "name:eng_x_preferred":[
        "Al Al 'Awadi"
    ],
    "name:eng_x_variant":[
        "Al Ma\u2018ri\u1e11ah"
    ],
    "qs:name":"\u0100l al \u2018Aw\u0101d\u012b",
    "qs:photos_9r":0,
    "qs:photos_sr":0,
    "qs:pop_sr":"1",
    "wof:name":"\u0100l al \u2018Aw\u0101d\u012b",
    "wof:placetype":"locality",
    "wof:population":10
},
  "geometry": {"coordinates":[43.73583,16.92413],"type":"Point"}
}