{
  "type": "Feature",
  "properties": {
    "gn:admin1_code":"16.0",
    "gn:admin2_code":"2312.0",
    "gn:asciiname":"'Allub al Hadd",
    "gn:country_code":"YE",
    "gn:dem":1650,
    "gn:feature_class":"P",
    "gn:feature_code":"PPL",
    "gn:name":"\u2018All\u016bb al \u1e28add",
    "gn:population":0,
    "gn:timezone":"Asia/Aden",
    "iso:country":"YE",
    "name:ara_x_preferred":[
        "\u0639\u0644\u0648\u0628 \u0627\u0644\u062d\u062f"
    ],
    "name:und_x_variant":[
        "\u2018All\u016bb al \u1e28add"
    ],
    "wof:name":"'Allub al Hadd",
    "wof:placetype":"locality"
},
  "geometry": {"coordinates":[44.80547,15.34822],"type":"Point"}
}