{
  "type": "Feature",
  "properties": {
    "gn:admin1_code":"1.0",
    "gn:admin2_code":"1204.0",
    "gn:asciiname":"Sakin al Wadi",
    "gn:country_code":"YE",
    "gn:dem":1081,
    "gn:feature_class":"P",
    "gn:feature_code":"PPL",
    "gn:name":"S\u0101kin al W\u0101d\u012b",
    "gn:population":0,
    "gn:timezone":"Asia/Aden",
    "iso:country":"YE",
    "name:und_x_variant":[
        "S\u0101kin al W\u0101d\u012b"
    ],
    "wof:name":"Sakin al Wadi",
    "wof:placetype":"locality"
},
  "geometry": {"coordinates":[45.82324000000001,13.86523],"type":"Point"}
}