{
  "type": "Feature",
  "properties": {
    "gn:admin1_code":"24.0",
    "gn:admin2_code":"2511.0",
    "gn:asciiname":"Nawbat Khawdar",
    "gn:country_code":"YE",
    "gn:dem":728,
    "gn:feature_class":"P",
    "gn:feature_code":"PPL",
    "gn:name":"Nawbat Khaw\u1e11ar",
    "gn:population":0,
    "gn:timezone":"Asia/Aden",
    "iso:country":"YE",
    "name:und_x_variant":[
        "Nawbat Khaw\u1e11ar"
    ],
    "wof:name":"Nawbat Khawdar",
    "wof:placetype":"locality"
},
  "geometry": {"coordinates":[44.41561,13.20064],"type":"Point"}
}