{
  "type": "Feature",
  "properties": {
    "gn:admin1_code":"16.0",
    "gn:admin2_code":"2316.0",
    "gn:asciiname":"As Suwayda",
    "gn:country_code":"YE",
    "gn:dem":2339,
    "gn:feature_class":"P",
    "gn:feature_code":"PPL",
    "gn:name":"As Suwayd\u0101",
    "gn:population":0,
    "gn:timezone":"Asia/Aden",
    "iso:country":"YE",
    "name:ara_x_preferred":[
        "\u0627\u0644\u0633\u0648\u064a\u062f\u0627"
    ],
    "name:und_x_variant":[
        "As Suwayd\u0101"
    ],
    "wof:name":"As Suwayda",
    "wof:placetype":"locality"
},
  "geometry": {"coordinates":[44.53959,15.28656],"type":"Point"}
}