{
  "type": "Feature",
  "properties": {
    "gn:admin1_code":"25.0",
    "gn:admin2_code":"1505.0",
    "gn:asciiname":"Al Maharaqah",
    "gn:country_code":"YE",
    "gn:dem":642,
    "gn:feature_class":"P",
    "gn:feature_code":"PPL",
    "gn:name":"Al Ma\u1e29araqah",
    "gn:population":0,
    "gn:timezone":"Asia/Aden",
    "iso:country":"YE",
    "name:und_x_variant":[
        "Al Ma\u1e29araqah",
        "Al Mu\u1e29raqah"
    ],
    "wof:name":"Al Maharaqah",
    "wof:placetype":"locality"
},
  "geometry": {"coordinates":[43.72807,13.58635],"type":"Point"}
}