{
  "type": "Feature",
  "properties": {
    "gn:admin1_code":"8.0",
    "gn:admin2_code":"1805.0",
    "gn:asciiname":"Bayt ar Rubaydi",
    "gn:country_code":"YE",
    "gn:dem":46,
    "gn:feature_class":"P",
    "gn:feature_code":"PPL",
    "gn:name":"Bayt ar Rubayd\u012b",
    "gn:population":0,
    "gn:timezone":"Asia/Aden",
    "iso:country":"YE",
    "name:ara_x_preferred":[
        "\u0628\u064a\u062a \u0627\u0644\u0631\u0628\u064a\u062f\u064a"
    ],
    "name:und_x_variant":[
        "Bayt ar Rubayd\u012b"
    ],
    "wof:name":"Bayt ar Rubaydi",
    "wof:placetype":"locality"
},
  "geometry": {"coordinates":[42.97579,15.36999],"type":"Point"}
}