{
  "type": "Feature",
  "properties": {
    "gn:admin1_code":"25.0",
    "gn:admin2_code":"1515.0",
    "gn:asciiname":"Sanah",
    "gn:country_code":"YE",
    "gn:dem":1113,
    "gn:feature_class":"P",
    "gn:feature_code":"PPL",
    "gn:name":"\u015e\u0101nah",
    "gn:population":0,
    "gn:timezone":"Asia/Aden",
    "iso:country":"YE",
    "name:ara_x_preferred":[
        "\u0635\u0627\u0646\u0629"
    ],
    "name:und_x_variant":[
        "\u015e\u0101nah"
    ],
    "wof:name":"Sanah",
    "wof:placetype":"locality"
},
  "geometry": {"coordinates":[43.94003,13.20319],"type":"Point"}
}