{
  "type": "Feature",
  "properties": {
    "gn:country":"YE",
    "gn:fcode":"PPL",
    "gn:pop":2,
    "iso:country":"YE",
    "name:ara_x_preferred":[
        "\u0627\u0644\u0633\u0631\u0648"
    ],
    "qs:name":"As Sarw",
    "qs:photos_9r":0,
    "qs:photos_sr":0,
    "qs:pop_sr":"1",
    "wof:name":"As Sarw",
    "wof:placetype":"locality",
    "wof:population":2
},
  "geometry": {"coordinates":[43.37542,16.68705],"type":"Point"}
}