{
  "type": "Feature",
  "properties": {
    "gn:gn_country":"YE",
    "gn:gn_fcode":"PPL",
    "gn:gn_pop":3,
    "gn:population":3,
    "iso:country":"YE",
    "name:ara_x_preferred":[
        "\u0645\u0646\u0627\u062e \u0632\u0647\u064a\u0629"
    ],
    "name:eng_x_preferred":[
        "Manakh Zuhayyah"
    ],
    "qs_pg:aaroncc":"YE",
    "qs_pg:gn_country":"YE",
    "qs_pg:gn_fcode":"PPL",
    "qs_pg:gn_pop":3,
    "qs_pg:name":"Man\u0101kh Zuhayyah",
    "qs_pg:photos_9r":0,
    "qs_pg:photos_sr":0,
    "qs_pg:pop_sr":1,
    "qs_pg:qs_pg_placetype":"locality",
    "wof:name":"Man\u0101kh Zuhayyah",
    "wof:placetype":"locality",
    "wof:population":3
},
  "geometry": {"coordinates":[43.94566,13.24782],"type":"Point"}
}