{
  "type": "Feature",
  "properties": {
    "gn:admin1_code":"23.0",
    "gn:admin2_code":"1101.0",
    "gn:asciiname":"Al Mahraq al Asfal",
    "gn:country_code":"YE",
    "gn:dem":1208,
    "gn:feature_class":"P",
    "gn:feature_code":"PPL",
    "gn:name":"Al Ma\u1e29raq al Asfal",
    "gn:population":0,
    "gn:timezone":"Asia/Aden",
    "iso:country":"YE",
    "name:ara_x_preferred":[
        "\u0627\u0644\u0645\u062d\u0631\u0642 \u0627\u0644\u0623\u0633\u0641\u0644"
    ],
    "name:und_x_variant":[
        "Al Ma\u1e29raq al Asfal"
    ],
    "wof:name":"Al Mahraq al Asfal",
    "wof:placetype":"locality"
},
  "geometry": {"coordinates":[44.0531,14.33134],"type":"Point"}
}