{
  "type": "Feature",
  "properties": {
    "gn:admin1_code":"8.0",
    "gn:admin2_code":"1812.0",
    "gn:asciiname":"Al Milhaj",
    "gn:country_code":"YE",
    "gn:dem":1730,
    "gn:feature_class":"P",
    "gn:feature_code":"PPL",
    "gn:name":"Al Mil\u1e29\u0101j",
    "gn:population":0,
    "gn:timezone":"Asia/Aden",
    "iso:country":"YE",
    "name:ara_x_preferred":[
        "\u0627\u0644\u0645\u0644\u062d\u0627\u062c"
    ],
    "name:und_x_variant":[
        "Al Mil\u1e29\u0101j"
    ],
    "wof:name":"Al Milhaj",
    "wof:placetype":"locality"
},
  "geometry": {"coordinates":[43.49081,14.89173],"type":"Point"}
}