{
  "type": "Feature",
  "properties": {
    "gn:admin1_code":"20.0",
    "gn:admin2_code":"1416.0",
    "gn:asciiname":"Al Lahabi",
    "gn:country_code":"YE",
    "gn:dem":2211,
    "gn:feature_class":"P",
    "gn:feature_code":"PPL",
    "gn:name":"Al Lahab\u012b",
    "gn:population":0,
    "gn:timezone":"Asia/Aden",
    "iso:country":"YE",
    "name:ara_x_preferred":[
        "\u0627\u0644\u0644\u0647\u0628\u064a"
    ],
    "name:und_x_variant":[
        "Al Lahab\u012b"
    ],
    "wof:name":"Al Lahabi",
    "wof:placetype":"locality"
},
  "geometry": {"coordinates":[44.76514,14.44154],"type":"Point"}
}