{
  "type": "Feature",
  "properties": {
    "gn:country":"YE",
    "gn:fcode":"PPLX",
    "gn:population":44,
    "iso:country":"YE",
    "name:ara_x_preferred":[
        "\u062f\u0631\u0628 \u0627\u0644\u0645\u0627\u0645"
    ],
    "qs:name":"Darb al M\u0101m",
    "qs:photos_9r":0,
    "qs:photos_sr":0,
    "qs:pop_sr":"1",
    "wof:name":"Darb al M\u0101m",
    "wof:placetype":"neighbourhood",
    "wof:population":44
},
  "geometry": {"coordinates":[43.76665,16.94019],"type":"Point"}
}