{
  "type": "Feature",
  "properties": {
    "gn:admin1_code":"21.0",
    "gn:admin2_code":"1601.0",
    "gn:asciiname":"Hamayil",
    "gn:country_code":"YE",
    "gn:dem":1464,
    "gn:feature_class":"P",
    "gn:feature_code":"PPL",
    "gn:name":"\u1e28am\u0101yil",
    "gn:population":0,
    "gn:timezone":"Asia/Aden",
    "iso:country":"YE",
    "name:und_x_variant":[
        "\u1e28am\u0101yil"
    ],
    "wof:name":"Hamayil",
    "wof:placetype":"locality"
},
  "geometry": {"coordinates":[44.8322,16.67504],"type":"Point"}
}