{
  "type": "Feature",
  "properties": {
    "gn:admin1_code":"19.0",
    "gn:admin2_code":"2906.0",
    "gn:asciiname":"Bayt Sabrah",
    "gn:country_code":"YE",
    "gn:dem":2151,
    "gn:feature_class":"P",
    "gn:feature_code":"PPL",
    "gn:name":"Bayt \u015eabrah",
    "gn:population":0,
    "gn:timezone":"Asia/Aden",
    "iso:country":"YE",
    "name:und_x_variant":[
        "Bayt \u015eabrah"
    ],
    "wof:name":"Bayt Sabrah",
    "wof:placetype":"locality"
},
  "geometry": {"coordinates":[43.66264,16.22156],"type":"Point"}
}