{
  "type": "Feature",
  "properties": {
    "gn:admin1_code":"19.0",
    "gn:admin2_code":"2901.0",
    "gn:asciiname":"Al Hawshayn",
    "gn:country_code":"YE",
    "gn:dem":1641,
    "gn:feature_class":"P",
    "gn:feature_code":"PPL",
    "gn:name":"Al \u1e28awshayn",
    "gn:population":0,
    "gn:timezone":"Asia/Aden",
    "iso:country":"YE",
    "name:und_x_variant":[
        "Al \u1e28awshayn"
    ],
    "wof:name":"Al Hawshayn",
    "wof:placetype":"locality"
},
  "geometry": {"coordinates":[44.03212,16.43437],"type":"Point"}
}