{
  "type": "Feature",
  "properties": {
    "gn:country":"YE",
    "gn:fcode":"PPL",
    "gn:population":3,
    "iso:country":"YE",
    "name:ara_x_preferred":[
        "\u0627\u0644\u0642\u064a\u0645\u064a"
    ],
    "name:eng_x_preferred":[
        "Al Qaymi"
    ],
    "name:fas_x_preferred":[
        "\u0645\u06af\u062a\u0627\u0641"
    ],
    "qs:name":"Al Qaym\u012b",
    "qs:photos_9r":0,
    "qs:photos_sr":0,
    "qs:pop_sr":"1",
    "wof:name":"Al Qaym\u012b",
    "wof:placetype":"locality",
    "wof:population":3
},
  "geometry": {"coordinates":[43.44008,16.14948],"type":"Point"}
}