{
  "type": "Feature",
  "properties": {
    "gn:admin1_code":"25.0",
    "gn:admin2_code":"1506.0",
    "gn:asciiname":"Baqiriyah",
    "gn:country_code":"YE",
    "gn:dem":90,
    "gn:feature_class":"P",
    "gn:feature_code":"PPL",
    "gn:name":"B\u0101qir\u012byah",
    "gn:population":0,
    "gn:timezone":"Asia/Aden",
    "iso:country":"YE",
    "name:und_x_variant":[
        "B\u0101qir\u012byah"
    ],
    "wof:name":"Baqiriyah",
    "wof:placetype":"locality"
},
  "geometry": {"coordinates":[43.41331,13.49655],"type":"Point"}
}