{
  "type": "Feature",
  "properties": {
    "gn:country":"YE",
    "gn:fcode":"PPL",
    "gn:population":1,
    "iso:country":"YE",
    "name:ara_x_preferred":[
        "\u0627\u0644\u0639\u062a\u064a\u0642 \u0627\u0644\u0623\u0639\u0644\u0649"
    ],
    "name:eng_x_preferred":[
        "Al 'Atiq Al A'la"
    ],
    "name:eng_x_variant":[
        "Al Qumr"
    ],
    "qs:name":"Al \u2018At\u012bq al A\u2018l\u00e1",
    "qs:photos_9r":0,
    "qs:photos_sr":0,
    "qs:pop_sr":"1",
    "wof:name":"Al \u2018At\u012bq al A\u2018l\u00e1",
    "wof:placetype":"locality",
    "wof:population":1
},
  "geometry": {"coordinates":[43.30672,17.36462],"type":"Point"}
}