{
  "type": "Feature",
  "properties": {
    "gn:admin1_code":"8.0",
    "gn:admin2_code":"1817.0",
    "gn:asciiname":"Kuz",
    "gn:country_code":"YE",
    "gn:dem":278,
    "gn:feature_class":"P",
    "gn:feature_code":"PPL",
    "gn:name":"K\u016bz",
    "gn:population":0,
    "gn:timezone":"Asia/Aden",
    "iso:country":"YE",
    "name:ara_x_preferred":[
        "K\u016bz"
    ],
    "wof:name":"Kuz",
    "wof:placetype":"locality"
},
  "geometry": {"coordinates":[43.48556,14.57835],"type":"Point"}
}