{
  "type": "Feature",
  "properties": {
    "gn:admin1_code":"8.0",
    "gn:admin2_code":"1824.0",
    "gn:asciiname":"Bayt al Wali",
    "gn:country_code":"YE",
    "gn:dem":190,
    "gn:feature_class":"P",
    "gn:feature_code":"PPL",
    "gn:name":"Bayt al Wal\u012b",
    "gn:population":0,
    "gn:timezone":"Asia/Aden",
    "iso:country":"YE",
    "name:und_x_variant":[
        "Bayt al Wal\u012b"
    ],
    "wof:name":"Bayt al Wali",
    "wof:placetype":"locality"
},
  "geometry": {"coordinates":[43.42022,14.30725],"type":"Point"}
}