{
  "type": "Feature",
  "properties": {
    "gn:admin1_code":"27.0",
    "gn:admin2_code":"3102.0",
    "gn:asciiname":"Dayr al Masjid",
    "gn:country_code":"YE",
    "gn:dem":280,
    "gn:feature_class":"P",
    "gn:feature_code":"PPL",
    "gn:name":"Dayr al Masjid",
    "gn:population":0,
    "gn:timezone":"Asia/Aden",
    "iso:country":"YE",
    "name:ara_x_preferred":[
        "\u062f\u064a\u0631\u0627\u0644\u0645\u0633\u062c\u062f"
    ],
    "wof:name":"Dayr al Masjid",
    "wof:placetype":"locality"
},
  "geometry": {"coordinates":[43.48925,14.62363],"type":"Point"}
}