{
  "type": "Feature",
  "properties": {
    "gn:admin1_code":"15.0",
    "gn:admin2_code":"2210.0",
    "gn:asciiname":"Al Halah",
    "gn:country_code":"YE",
    "gn:dem":1907,
    "gn:feature_class":"P",
    "gn:feature_code":"PPL",
    "gn:name":"Al \u1e28al\u0101h",
    "gn:population":0,
    "gn:timezone":"Asia/Aden",
    "iso:country":"YE",
    "name:und_x_variant":[
        "Al \u1e28al\u0101h"
    ],
    "wof:name":"Al Halah",
    "wof:placetype":"locality"
},
  "geometry": {"coordinates":[43.57648,17.18004],"type":"Point"}
}