{
  "type": "Feature",
  "properties": {
    "gn:country":"YE",
    "gn:fcode":"PPL",
    "gn:pop":38,
    "iso:country":"YE",
    "name:ara_x_preferred":[
        "\u0627\u0644\u0645\u0639\u0631\u0641"
    ],
    "name:eng_x_preferred":[
        "Al Ma'rif"
    ],
    "name:eng_x_variant":[
        "Az\u0327 Z\u0327ih\u0101r al A\u2018l\u00e1"
    ],
    "qs:name":"Al Ma\u2018rif",
    "qs:photos_9r":0,
    "qs:photos_sr":0,
    "qs:pop_sr":"1",
    "wof:name":"Al Ma\u2018rif",
    "wof:placetype":"locality",
    "wof:population":38
},
  "geometry": {"coordinates":[45.37023,15.51783],"type":"Point"}
}