{
  "type": "Feature",
  "properties": {
    "gn:admin1_code":"22.0",
    "gn:admin2_code":"1701.0",
    "gn:asciiname":"Subran",
    "gn:country_code":"YE",
    "gn:dem":477,
    "gn:feature_class":"P",
    "gn:feature_code":"PPL",
    "gn:name":"\u015eubr\u0101n",
    "gn:population":0,
    "gn:timezone":"Asia/Aden",
    "iso:country":"YE",
    "name:ara_x_preferred":[
        "\u015eubr\u0101n"
    ],
    "wof:name":"Subran",
    "wof:placetype":"locality"
},
  "geometry": {"coordinates":[43.32262,16.51959],"type":"Point"}
}