{
  "type": "Feature",
  "properties": {
    "gn:admin1_code":"8.0",
    "gn:admin2_code":"1813.0",
    "gn:asciiname":"Al Jawniyah",
    "gn:country_code":"YE",
    "gn:dem":82,
    "gn:feature_class":"P",
    "gn:feature_code":"PPL",
    "gn:name":"Al Jawn\u012byah",
    "gn:population":0,
    "gn:timezone":"Asia/Aden",
    "iso:country":"YE",
    "name:und_x_variant":[
        "Al Jawn\u012byah"
    ],
    "wof:name":"Al Jawniyah",
    "wof:placetype":"locality"
},
  "geometry": {"coordinates":[43.17343,14.83043],"type":"Point"}
}