{
  "type": "Feature",
  "properties": {
    "gn:admin1_code":"10.0",
    "gn:admin2_code":"2709.0",
    "gn:asciiname":"Mahall al Hisn",
    "gn:country_code":"YE",
    "gn:dem":1246,
    "gn:feature_class":"P",
    "gn:feature_code":"PPL",
    "gn:name":"Ma\u1e29all al \u1e28i\u015fn",
    "gn:population":0,
    "gn:timezone":"Asia/Aden",
    "iso:country":"YE",
    "name:und_x_variant":[
        "Ma\u1e29all al \u1e28i\u015fn"
    ],
    "wof:name":"Mahall al Hisn",
    "wof:placetype":"locality"
},
  "geometry": {"coordinates":[43.46962,15.41067],"type":"Point"}
}