{
  "type": "Feature",
  "properties": {
    "gn:country":"YE",
    "gn:fcode":"PPL",
    "gn:pop":3,
    "iso:country":"YE",
    "name:ara_x_preferred":[
        "\u0642\u0627\u0626\u0645 \u0645\u0643\u0628\u062b"
    ],
    "name:eng_x_preferred":[
        "Qaim Mukabbath"
    ],
    "qs:name":"Q\u0101i\u2019m Mukabbath",
    "qs:photos_9r":0,
    "qs:photos_sr":0,
    "qs:pop_sr":"1",
    "wof:name":"Q\u0101i\u2019m Mukabbath",
    "wof:placetype":"locality",
    "wof:population":3
},
  "geometry": {"coordinates":[43.22013,16.42703],"type":"Point"}
}