{
  "type": "Feature",
  "properties": {
    "gn:country":"YE",
    "gn:fcode":"PPL",
    "gn:pop":1,
    "iso:country":"YE",
    "name:ara_x_preferred":[
        "\u0627\u0644\u0631\u0643\u064a\u0629"
    ],
    "name:eng_x_preferred":[
        "Ar Rakiyah"
    ],
    "qs:name":"Ar Rak\u012byah",
    "qs:photos_9r":0,
    "qs:photos_sr":0,
    "qs:pop_sr":"1",
    "wof:name":"Ar Rak\u012byah",
    "wof:placetype":"locality",
    "wof:population":1
},
  "geometry": {"coordinates":[43.34857,16.17035],"type":"Point"}
}