{
  "type": "Feature",
  "properties": {
    "gn:admin1_code":"14.0",
    "gn:admin2_code":"2613.0",
    "gn:asciiname":"Al Fidi",
    "gn:country_code":"YE",
    "gn:dem":1049,
    "gn:feature_class":"P",
    "gn:feature_code":"PPL",
    "gn:name":"Al Fi\u1e11\u012b",
    "gn:population":0,
    "gn:timezone":"Asia/Aden",
    "iso:country":"YE",
    "name:ara_x_preferred":[
        "Al Fi\u1e11\u012b"
    ],
    "name:ara_x_variant":[
        "\u0627\u0644\u0641\u0636\u064a"
    ],
    "wof:name":"Al Fidi",
    "wof:placetype":"locality"
},
  "geometry": {"coordinates":[45.39983,15.56412],"type":"Point"}
}