{
  "type": "Feature",
  "properties": {
    "gn:admin1_code":"23.0",
    "gn:admin2_code":"1109.0",
    "gn:asciiname":"Qihnat",
    "gn:country_code":"YE",
    "gn:dem":1730,
    "gn:feature_class":"P",
    "gn:feature_code":"PPL",
    "gn:name":"Qihn\u0101t",
    "gn:population":0,
    "gn:timezone":"Asia/Aden",
    "iso:country":"YE",
    "name:ara_x_preferred":[
        "Qihn\u0101t"
    ],
    "wof:name":"Qihnat",
    "wof:placetype":"locality"
},
  "geometry": {"coordinates":[43.99551,14.00859],"type":"Point"}
}