{
  "type": "Feature",
  "properties": {
    "gn:country":"YE",
    "gn:fcode":"PPL",
    "gn:population":6,
    "iso:country":"YE",
    "name:ara_x_preferred":[
        "\u0628\u0626\u0631 \u0631\u0647\u064a\u0634"
    ],
    "name:eng_x_preferred":[
        "Bir Ruhaysh"
    ],
    "name:eng_x_variant":[
        "\u2018Asiq"
    ],
    "qs:name":"Bi\u2019r Ruhaysh",
    "qs:photos_9r":0,
    "qs:photos_sr":0,
    "qs:pop_sr":"1",
    "wof:name":"Bi\u2019r Ruhaysh",
    "wof:placetype":"locality",
    "wof:population":6
},
  "geometry": {"coordinates":[45.3371,14.32274],"type":"Point"}
}