{
  "type": "Feature",
  "properties": {
    "gn:admin1_code":"23.0",
    "gn:admin2_code":"1113.0",
    "gn:asciiname":"Al Masha`ir",
    "gn:country_code":"YE",
    "gn:dem":2418,
    "gn:feature_class":"P",
    "gn:feature_code":"PPL",
    "gn:name":"Al Mash\u0101\u2018ir",
    "gn:population":0,
    "gn:timezone":"Asia/Aden",
    "iso:country":"YE",
    "name:und_x_variant":[
        "Al Mash\u0101\u2018ir"
    ],
    "wof:name":"Al Masha`ir",
    "wof:placetype":"locality"
},
  "geometry": {"coordinates":[44.27094,13.9507],"type":"Point"}
}