{
  "type": "Feature",
  "properties": {
    "gn:gn_country":"YE",
    "gn:gn_fcode":"PPL",
    "gn:gn_pop":1,
    "gn:population":1,
    "iso:country":"YE",
    "name:ara_x_preferred":[
        "\u0645\u063a\u0632\u0648\u0628\u0629"
    ],
    "name:eng_x_preferred":[
        "MaghzUbah"
    ],
    "qs_pg:aaroncc":"YE",
    "qs_pg:gn_country":"YE",
    "qs_pg:gn_fcode":"PPL",
    "qs_pg:gn_pop":1,
    "qs_pg:name":"Maghz\u016bbah",
    "qs_pg:photos_9r":0,
    "qs_pg:photos_sr":0,
    "qs_pg:pop_sr":1,
    "qs_pg:qs_pg_placetype":"locality",
    "wof:name":"Maghz\u016bbah",
    "wof:placetype":"locality",
    "wof:population":1
},
  "geometry": {"coordinates":[43.9784,13.12494],"type":"Point"}
}