{
  "type": "Feature",
  "properties": {
    "gn:country":"YE",
    "gn:fcode":"PPL",
    "gn:population":14,
    "iso:country":"YE",
    "name:ara_x_preferred":[
        "\u0647\u064a\u062c\u0629 \u0628\u0631\u0645"
    ],
    "name:eng_x_preferred":[
        "Hayjat Barrum"
    ],
    "name:eng_x_variant":[
        "Ash Shukhay\u1e11"
    ],
    "qs:name":"Hayjat Barrum",
    "qs:photos_9r":0,
    "qs:photos_sr":0,
    "qs:pop_sr":"1",
    "wof:name":"Hayjat Barrum",
    "wof:placetype":"locality",
    "wof:population":14
},
  "geometry": {"coordinates":[43.66704,16.48134],"type":"Point"}
}