{
  "type": "Feature",
  "properties": {
    "gn:admin1_code":"24.0",
    "gn:admin2_code":"2510.0",
    "gn:asciiname":"Shi`b as Suq",
    "gn:country_code":"YE",
    "gn:dem":968,
    "gn:feature_class":"P",
    "gn:feature_code":"PPL",
    "gn:name":"Shi\u2018b as S\u016bq",
    "gn:population":0,
    "gn:timezone":"Asia/Aden",
    "iso:country":"YE",
    "name:und_x_variant":[
        "Shi\u2018b as S\u016bq"
    ],
    "wof:name":"Shi`b as Suq",
    "wof:placetype":"locality"
},
  "geometry": {"coordinates":[44.39363,13.23833],"type":"Point"}
}