{
  "type": "Feature",
  "properties": {
    "gn:admin1_code":"8.0",
    "gn:admin2_code":"1824.0",
    "gn:asciiname":"Bayt Bul`ayd",
    "gn:country_code":"YE",
    "gn:dem":166,
    "gn:feature_class":"P",
    "gn:feature_code":"PPL",
    "gn:name":"Bayt Bul\u2018ayd",
    "gn:population":0,
    "gn:timezone":"Asia/Aden",
    "iso:country":"YE",
    "name:und_x_variant":[
        "Bayt Bul\u2018ayd"
    ],
    "wof:name":"Bayt Bul`ayd",
    "wof:placetype":"locality"
},
  "geometry": {"coordinates":[43.46263,14.02215],"type":"Point"}
}