{
  "type": "Feature",
  "properties": {
    "gn:admin1_code":"5.0",
    "gn:admin2_code":"2109.0",
    "gn:asciiname":"Bin Nata`",
    "gn:country_code":"YE",
    "gn:dem":1109,
    "gn:feature_class":"P",
    "gn:feature_code":"PPL",
    "gn:name":"Bin Na\u0163a\u2018",
    "gn:population":0,
    "gn:timezone":"Asia/Aden",
    "iso:country":"YE",
    "name:und_x_variant":[
        "Bannata",
        "Bin Na\u0163a\u2018"
    ],
    "wof:name":"Bin Nata`",
    "wof:placetype":"locality"
},
  "geometry": {"coordinates":[46.18686,14.5389],"type":"Point"}
}