{
  "type": "Feature",
  "properties": {
    "gn:country":"YE",
    "gn:fcode":"PPL",
    "gn:pop":12,
    "iso:country":"YE",
    "name:ara_x_preferred":[
        "\u0628\u0646\u064a \u0627\u0644\u0639\u0636\u0627\u0628\u064a"
    ],
    "name:eng_x_preferred":[
        "Bani Al 'Auabi"
    ],
    "name:eng_x_variant":[
        "Mawqar Sa\u2018\u012bd"
    ],
    "name:unk_x_variant":[
        "\u0628\u0646\u064a \u0627\u0644\u0639\u0636\u0627\u0628\u064a"
    ],
    "qs:name":"Ban\u012b al \u2018A\u1e11\u0101b\u012b",
    "qs:photos_9r":0,
    "qs:photos_sr":0,
    "qs:pop_sr":"1",
    "wof:name":"Ban\u012b al \u2018A\u1e11\u0101b\u012b",
    "wof:placetype":"locality",
    "wof:population":12
},
  "geometry": {"coordinates":[42.93314,16.09917],"type":"Point"}
}