{
  "type": "Feature",
  "properties": {
    "gn:admin1_code":"23.0",
    "gn:admin2_code":"1108.0",
    "gn:asciiname":"Nuqtat Bani Shihab",
    "gn:country_code":"YE",
    "gn:dem":1330,
    "gn:feature_class":"P",
    "gn:feature_code":"PPL",
    "gn:name":"Nuq\u0163at Ban\u012b Shih\u0101b",
    "gn:population":0,
    "gn:timezone":"Asia/Aden",
    "iso:country":"YE",
    "name:und_x_variant":[
        "Nuq\u0163at Ban\u012b Shih\u0101b"
    ],
    "wof:name":"Nuqtat Bani Shihab",
    "wof:placetype":"locality"
},
  "geometry": {"coordinates":[44.13223,14.17892],"type":"Point"}
}