{
  "type": "Feature",
  "properties": {
    "gn:admin1_code":"19.0",
    "gn:admin2_code":"2916.0",
    "gn:asciiname":"As Sammar",
    "gn:country_code":"YE",
    "gn:dem":1116,
    "gn:feature_class":"P",
    "gn:feature_code":"PPL",
    "gn:name":"A\u015f \u015eamm\u0101r",
    "gn:population":0,
    "gn:timezone":"Asia/Aden",
    "iso:country":"YE",
    "name:ara_x_preferred":[
        "\u0627\u0644\u0635\u0645\u0627\u0631"
    ],
    "name:und_x_variant":[
        "A\u015f \u015eamm\u0101r"
    ],
    "wof:name":"As Sammar",
    "wof:placetype":"locality"
},
  "geometry": {"coordinates":[43.64046,15.54012],"type":"Point"}
}