{
  "type": "Feature",
  "properties": {
    "gn:admin1_code":"19.0",
    "gn:admin2_code":"2911.0",
    "gn:asciiname":"Hamidah",
    "gn:country_code":"YE",
    "gn:dem":2213,
    "gn:feature_class":"P",
    "gn:feature_code":"PPL",
    "gn:name":"\u1e28amidah",
    "gn:population":0,
    "gn:timezone":"Asia/Aden",
    "iso:country":"YE",
    "name:nno_x_preferred":[
        "Hamidah"
    ],
    "name:und_x_variant":[
        "\u1e28amidah"
    ],
    "wof:name":"Hamidah",
    "wof:placetype":"locality"
},
  "geometry": {"coordinates":[43.96628,15.83267],"type":"Point"}
}