{
  "type": "Feature",
  "properties": {
    "gn:admin1_code":"23.0",
    "gn:admin2_code":"1105.0",
    "gn:asciiname":"Dikman",
    "gn:country_code":"YE",
    "gn:dem":2076,
    "gn:feature_class":"P",
    "gn:feature_code":"PPL",
    "gn:name":"Dikm\u0101n",
    "gn:population":0,
    "gn:timezone":"Asia/Aden",
    "iso:country":"YE",
    "name:ara_x_preferred":[
        "Dikm\u0101n"
    ],
    "wof:name":"Dikman",
    "wof:placetype":"locality"
},
  "geometry": {"coordinates":[44.40164,14.03345],"type":"Point"}
}