{
  "type": "Feature",
  "properties": {
    "gn:admin1_code":"22.0",
    "gn:admin2_code":"1725.0",
    "gn:asciiname":"'Abarat Darah",
    "gn:country_code":"YE",
    "gn:dem":705,
    "gn:feature_class":"P",
    "gn:feature_code":"PPL",
    "gn:name":"\u2018Ab\u0101rat D\u0101rah",
    "gn:population":0,
    "gn:timezone":"Asia/Aden",
    "iso:country":"YE",
    "name:ara_x_preferred":[
        "\u0639\u0628\u0627\u0631\u0629 \u062f\u0627\u0631\u0629"
    ],
    "name:und_x_variant":[
        "\u2018Ab\u0101rat D\u0101rah"
    ],
    "wof:name":"'Abarat Darah",
    "wof:placetype":"locality"
},
  "geometry": {"coordinates":[43.54241,15.54857],"type":"Point"}
}