{
  "type": "Feature",
  "properties": {
    "gn:admin1_code":"11.0",
    "gn:admin2_code":"2001.0",
    "gn:asciiname":"Bani Hayyan",
    "gn:country_code":"YE",
    "gn:dem":2256,
    "gn:feature_class":"P",
    "gn:feature_code":"PPL",
    "gn:name":"Ban\u012b \u1e28ayy\u0101n",
    "gn:population":0,
    "gn:timezone":"Asia/Aden",
    "iso:country":"YE",
    "name:und_x_variant":[
        "Ban\u012b \u1e28ayy\u0101n"
    ],
    "wof:name":"Bani Hayyan",
    "wof:placetype":"locality"
},
  "geometry": {"coordinates":[44.45732,14.82996],"type":"Point"}
}