{
  "type": "Feature",
  "properties": {
    "gn:country":"YE",
    "gn:fcode":"PPL",
    "gn:population":6,
    "iso:country":"YE",
    "name:ara_x_preferred":[
        "\u0628\u0642\u062b\u0629 \u0627\u0644\u0639\u0644\u064a\u0627"
    ],
    "name:eng_x_preferred":[
        "Baqthat Al 'Ulya"
    ],
    "name:eng_x_variant":[
        "Al \u2018Udhaynah"
    ],
    "qs:name":"Baqthat al \u2018Uly\u0101",
    "qs:photos_9r":0,
    "qs:photos_sr":0,
    "qs:pop_sr":"1",
    "wof:name":"Baqthat al \u2018Uly\u0101",
    "wof:placetype":"locality",
    "wof:population":6
},
  "geometry": {"coordinates":[45.1327,14.96534],"type":"Point"}
}