{
  "type": "Feature",
  "properties": {
    "gn:admin1_code":"22.0",
    "gn:admin2_code":"1701.0",
    "gn:asciiname":"Al 'Ishash",
    "gn:country_code":"YE",
    "gn:dem":516,
    "gn:feature_class":"P",
    "gn:feature_code":"PPL",
    "gn:name":"Al \u2018Ish\u0101sh",
    "gn:population":0,
    "gn:timezone":"Asia/Aden",
    "iso:country":"YE",
    "name:ara_x_preferred":[
        "Al \u2018Ish\u0101sh"
    ],
    "name:ara_x_variant":[
        "\u0627\u0644\u0639\u0634\u0627\u0634"
    ],
    "wof:name":"Al 'Ishash",
    "wof:placetype":"locality"
},
  "geometry": {"coordinates":[43.32446,16.56377],"type":"Point"}
}