{
  "type": "Feature",
  "properties": {
    "gn:admin1_code":"4.0",
    "gn:admin2_code":"1915.0",
    "gn:asciiname":"Dhabdhab",
    "gn:country_code":"YE",
    "gn:dem":73,
    "gn:feature_class":"P",
    "gn:feature_code":"PPL",
    "gn:name":"Dhabdhab",
    "gn:population":0,
    "gn:timezone":"Asia/Aden",
    "iso:country":"YE",
    "wof:name":"Dhabdhab",
    "wof:placetype":"locality"
},
  "geometry": {"coordinates":[49.55,14.83333],"type":"Point"}
}