{
  "type": "Feature",
  "properties": {
    "gn:country":"YE",
    "gn:fcode":"PPL",
    "gn:pop":1,
    "iso:country":"YE",
    "name:ara_x_preferred":[
        "\u0627\u0644\u0645\u0648\u0643\u0631"
    ],
    "name:eng_x_preferred":[
        "Al Mawkir"
    ],
    "qs:name":"Al Mawkir",
    "qs:photos_9r":0,
    "qs:photos_sr":0,
    "qs:pop_sr":"1",
    "wof:name":"Al Mawkir",
    "wof:placetype":"locality",
    "wof:population":1
},
  "geometry": {"coordinates":[43.43635,16.10517],"type":"Point"}
}