{
  "type": "Feature",
  "properties": {
    "gn:admin1_code":"23.0",
    "gn:admin2_code":"1107.0",
    "gn:asciiname":"Al Musayni`ah",
    "gn:country_code":"YE",
    "gn:dem":1510,
    "gn:feature_class":"P",
    "gn:feature_code":"PPL",
    "gn:name":"Al Mu\u015fayni\u2018ah",
    "gn:population":0,
    "gn:timezone":"Asia/Aden",
    "iso:country":"YE",
    "name:und_x_variant":[
        "Al Mu\u015fayni\u2018ah"
    ],
    "wof:name":"Al Musayni`ah",
    "wof:placetype":"locality"
},
  "geometry": {"coordinates":[44.17858,14.12706],"type":"Point"}
}