{
  "type": "Feature",
  "properties": {
    "gn:admin1_code":"18.0",
    "gn:admin2_code":"3002.0",
    "gn:asciiname":"Al `Ikrah",
    "gn:country_code":"YE",
    "gn:dem":1919,
    "gn:feature_class":"P",
    "gn:feature_code":"PPL",
    "gn:name":"Al \u2018Ikrah",
    "gn:population":0,
    "gn:timezone":"Asia/Aden",
    "iso:country":"YE",
    "name:und_x_variant":[
        "Al \u2018Ikrah"
    ],
    "wof:name":"Al `Ikrah",
    "wof:placetype":"locality"
},
  "geometry": {"coordinates":[44.63982,14.09977],"type":"Point"}
}