{
  "type": "Feature",
  "properties": {
    "gn:admin1_code":"20.0",
    "gn:admin2_code":"1415.0",
    "gn:asciiname":"Jaywirah",
    "gn:country_code":"YE",
    "gn:dem":2221,
    "gn:feature_class":"P",
    "gn:feature_code":"PPL",
    "gn:name":"Jaywirah",
    "gn:population":0,
    "gn:timezone":"Asia/Aden",
    "iso:country":"YE",
    "wof:name":"Jaywirah",
    "wof:placetype":"locality"
},
  "geometry": {"coordinates":[44.76742,14.68856],"type":"Point"}
}