{
  "type": "Feature",
  "properties": {
    "gn:admin1_code":"11.0",
    "gn:admin2_code":"2011.0",
    "gn:asciiname":"Samh",
    "gn:country_code":"YE",
    "gn:dem":2172,
    "gn:feature_class":"P",
    "gn:feature_code":"PPL",
    "gn:name":"Sam\u1e29",
    "gn:population":0,
    "gn:timezone":"Asia/Aden",
    "iso:country":"YE",
    "name:und_x_variant":[
        "Sam\u1e29"
    ],
    "wof:name":"Samh",
    "wof:placetype":"locality"
},
  "geometry": {"coordinates":[44.21411,14.78124],"type":"Point"}
}