{
  "type": "Feature",
  "properties": {
    "gn:admin1_code":"10.0",
    "gn:admin2_code":"2709.0",
    "gn:asciiname":"Bayt as Sufi",
    "gn:country_code":"YE",
    "gn:dem":1198,
    "gn:feature_class":"P",
    "gn:feature_code":"PPL",
    "gn:name":"Bayt a\u015f \u015e\u016bf\u012b",
    "gn:population":0,
    "gn:timezone":"Asia/Aden",
    "iso:country":"YE",
    "name:und_x_variant":[
        "Bayt a\u015f \u015e\u016bf\u012b"
    ],
    "wof:name":"Bayt as Sufi",
    "wof:placetype":"locality"
},
  "geometry": {"coordinates":[43.47379,15.46681],"type":"Point"}
}