{
  "type": "Feature",
  "properties": {
    "gn:admin1_code":"22.0",
    "gn:admin2_code":"1709.0",
    "gn:asciiname":"Al Kawmah",
    "gn:country_code":"YE",
    "gn:dem":1778,
    "gn:feature_class":"P",
    "gn:feature_code":"PPL",
    "gn:name":"Al Kawmah",
    "gn:population":0,
    "gn:timezone":"Asia/Aden",
    "iso:country":"YE",
    "name:ara_x_preferred":[
        "\u0627\u0644\u0643\u0648\u0645\u0629"
    ],
    "wof:name":"Al Kawmah",
    "wof:placetype":"locality"
},
  "geometry": {"coordinates":[43.45614000000001,16.03533],"type":"Point"}
}