{
  "type": "Feature",
  "properties": {
    "gn:admin1_code":"23.0",
    "gn:admin2_code":"1101.0",
    "gn:asciiname":"Qawbah",
    "gn:country_code":"YE",
    "gn:dem":1181,
    "gn:feature_class":"P",
    "gn:feature_code":"PPL",
    "gn:name":"Qawbah",
    "gn:population":0,
    "gn:timezone":"Asia/Aden",
    "iso:country":"YE",
    "name:ara_x_preferred":[
        "\u0642\u0648\u0628\u0629"
    ],
    "wof:name":"Qawbah",
    "wof:placetype":"locality"
},
  "geometry": {"coordinates":[44.02035,14.32424],"type":"Point"}
}