{
  "type": "Feature",
  "properties": {
    "gn:country":"YE",
    "gn:fcode":"PPL",
    "gn:population":6,
    "iso:country":"YE",
    "name:ara_x_preferred":[
        "\u0627\u0644\u0645\u0642\u0627\u0645 \u0627\u0644\u0634\u0631\u0642\u064a"
    ],
    "name:eng_x_preferred":[
        "Al Maqam Ash Sharqi"
    ],
    "name:eng_x_variant":[
        "Qaryat Mu\u2019\u0101nis"
    ],
    "qs:name":"Al Maq\u0101m ash Sharq\u012b",
    "qs:photos_9r":0,
    "qs:photos_sr":0,
    "qs:pop_sr":"1",
    "wof:name":"Al Maq\u0101m ash Sharq\u012b",
    "wof:placetype":"locality",
    "wof:population":6
},
  "geometry": {"coordinates":[44.56706,16.8832],"type":"Point"}
}