{
  "type": "Feature",
  "properties": {
    "gn:admin1_code":"24.0",
    "gn:admin2_code":"2512.0",
    "gn:asciiname":"Al Awdar",
    "gn:country_code":"YE",
    "gn:dem":1439,
    "gn:feature_class":"P",
    "gn:feature_code":"PPL",
    "gn:name":"Al Awd\u0101r",
    "gn:population":0,
    "gn:timezone":"Asia/Aden",
    "iso:country":"YE",
    "name:ara_x_preferred":[
        "\u0627\u0644\u0627\u0648\u062f\u0627\u0631"
    ],
    "name:und_x_variant":[
        "Al Awd\u0101r"
    ],
    "wof:name":"Al Awdar",
    "wof:placetype":"locality"
},
  "geometry": {"coordinates":[44.16518,13.19721],"type":"Point"}
}