{
  "type": "Feature",
  "properties": {
    "gn:admin1_code":"25.0",
    "gn:admin2_code":"1501.0",
    "gn:asciiname":"Al Khuwar",
    "gn:country_code":"YE",
    "gn:dem":1472,
    "gn:feature_class":"P",
    "gn:feature_code":"PPL",
    "gn:name":"Al Khuw\u0101r",
    "gn:population":0,
    "gn:timezone":"Asia/Aden",
    "iso:country":"YE",
    "name:ara_x_preferred":[
        "Al Khuw\u0101r"
    ],
    "wof:name":"Al Khuwar",
    "wof:placetype":"locality"
},
  "geometry": {"coordinates":[44.40078,13.72658],"type":"Point"}
}