{
  "type": "Feature",
  "properties": {
    "gn:admin1_code":"1.0",
    "gn:admin2_code":"1204.0",
    "gn:asciiname":"Am `Ayn",
    "gn:country_code":"YE",
    "gn:dem":867,
    "gn:feature_class":"P",
    "gn:feature_code":"PPL",
    "gn:name":"Am \u2018Ayn",
    "gn:population":0,
    "gn:timezone":"Asia/Aden",
    "iso:country":"YE",
    "name:ara_x_preferred":[
        "\u0623\u0645 \u0639\u064a\u0646"
    ],
    "name:ara_x_variant":[
        "Al \u2018Ayn",
        "Umm \u2018Ayn",
        "Am \u2018Ayn"
    ],
    "name:und_x_variant":[
        "An \u2018Ayn",
        "Al-\u2018Ain",
        "Am \u2018Ayn",
        "Al \u2018Ayn"
    ],
    "wof:name":"Am `Ayn",
    "wof:placetype":"locality"
},
  "geometry": {"coordinates":[45.88621,13.80041],"type":"Point"}
}